Workbook
Name Linking_1: #REF!
Name Linking_10: #REF!
Name Linking_11: #REF!
Name Linking_12: #REF!
Name Linking_13: 'Financial Summary'!$E$11:$W$63
Name Linking_14: #REF!
Name Linking_15: Assumptions!$N$515:$T$522
Name Linking_2: #REF!
Name Linking_3: 'Valuation - DCF'!$B$5:$AA$55
Name Linking_4: 'Financial Summary'!$E$11:$V$69
Name Linking_5: 'Financial Summary'!$E$11:$V$63
Name Linking_6: #REF!
Name Linking_7: #REF!
Name Linking_8: 'Financial Summary'!$E$11:$V$64
Name Linking_9: #REF!
Name ValidDateTable: #REF!

Sheet CircularReferenceAlert
B2: This workbook contains formulas which intentionally use circular reference calculation. These calculations can be resolved as intended by the originating analyst by applying the following settings in the File >> Options >> Formulas:
B5: 1) Select the Enable iterative calculation check box
B6: 2) Set Maximum Iterations = 100
B7: 3) Set Maximum Change = 0.001
B9: Failure to apply these settings can result in incorrect calculation or unexpected termination of your Microsoft Excel session.

Sheet ImportantDisclosures
A2: 1 Austin Road West
A3: Kowloon
A4: Hong Kong
A5: Tel: +852 2848 5200
A7: Authors: Melinda Baxter
A8: Date: 02 Feb 2026
A10: Ticker: GYG.AX
A11: Stock Rating: Overweight
A12: Industry: Australia Consumer
A13: Industry View: In-Line
A14: Price as of 02 Feb 2026: 22.18
A15: Target Price: 31.20
... A134: Equal-weight and Not-Rated to hold and Underweight to sell recommendations, respectively.
B136: Coverage Universe | D136: Investment Banking Clients (IBC) | G136: Other Material Investment Services Clients (MISC)
A137: Stock Rating Category | B137: Count | C137: % of Total | D137: Count | E137: % of Total IBC | F137: % of Rating Category | G137: Count | H137: % of Total Other MISC
A138: Overweight/Buy | B138: 1520 | C138: 0.41 | D138: 425 | E138: 0.48 | F138: 0.28 | G138: 685 | H138: 0.42
A139: Equal-weight/Hold | B139: 1579 | C139: 0.43 | D139: 375 | E139: 0.42 | F139: 0.24 | G139: 713 | H139: 0.44
A140: Not-Rated/Hold | B140: 4 | C140: 0 | D140: 1 | E140: 0 | F140: 0.25 | G140: 1 | H140: 0
A141: Underweight/Sell | B141: 592 | C141: 0.16 | D141: 89 | E141: 0.1 | F141: 0.15 | G141: 232 | H141: 0.14
A142: Total | B142: 3695 | D142: 890 | G142: 1631
A144: Data include common stock and ADRs currently assigned ratings. Investment Banking Clients are companies
A145: from whom Morgan Stanley received investment banking compensation in the last 12 months. Due to rounding
A146: off of decimals, the percentages provided in the "% of total" column may not add up to exactly 100
A147: percent.
A149: Analyst Stock Ratings
A151: Overweight (O). The stock's total return is expected to exceed the average total return of the analyst's
A152: industry (or industry team's) coverage universe, on a risk-adjusted basis, over the next 12-18 months.
A154: Equal-weight (E). The stock's total return is expected to be in line with the average total return of
A155: the analyst's industry (or industry team's) coverage universe, on a risk-adjusted basis, over the next
A156: 12-18 months.
A158: Not-Rated (NR). Currently the analyst does not have adequate conviction about the stock's total return
A159: relative to the average total return of the analyst's industry (or industry team's) coverage universe,
... A436: © Copyright 2026 Morgan Stanley

Sheet MENU
B3: Morgan Stanley
B5: Guzman y Gomez
A6: GYG-AU | B6: GYG.AX
B15: Contents
B16: Financial Summary
B17: Assumptions
B18: Financial Statements
B19: Valuation
B21: Last close | C21: =TODAY() -> 46055 | E21: 23.7
B23: Morgan Stanley Australian Consumer Team
B24: Melinda Baxter | D24: +612-9770 1176
B25: Mac Ross | D25: +612-9770 1579
B26: Julia de Sterke | D26: +612-9770 1658
B28: AUSTRALIAN CONSUMER RESEARCH
B29: Morgan Stanley Australia Ltd
B30: Level 39, Chifley Tower, 2 Chifley Square
B31: Sydney 2000 Australia

Sheet Financial Summary
E2: Guzman Y Gomez (GYG.AX)
E3: Financial Summary
E5: Year ended 30 June
A7: GYG-AU | E7: Share Price | F7: 23.5
E8: Mkt Cap | F8: =+F7*F9 -> 2381.7935
E9: SOI | F9: =+'Financial Statements'!L63 -> 101.35291
E11: Income Statement | O11: Balance Sheet
E12: Year ended 30 June | F12: Unit | G12: FY22 | H12: FY23 | I12: FY24 | J12: FY25 | K12: FY26e | L12: FY27e | M12: FY28e | O12: Year ended 30 June | P12: Unit | Q12: FY22 | R12: FY23 | S12: FY24 | T12: FY25 | U12: FY26e | V12: FY27e | W12: FY28e
E13: Revenue
A14: Revenue_Aust | E14: Australia | F14: A$m | G14: =VLOOKUP($A14,Assumptions!$1:$1048576,MATCH('Financial Summary'!G$12,Assumptions!$5:$5,0),FALSE) -> 168.027 | H14: =VLOOKUP($A14,Assumptions!$1:$1048576,MATCH('Financial Summary'!H$12,Assumptions!$5:$5,0),FALSE) -> 251.3815 | I14: =VLOOKUP($A14,Assumptions!$1:$1048576,MATCH('Financial Summary'!I$12,Assumptions!$5:$5,0),FALSE) -> 329.542 | J14: =VLOOKUP($A14,Assumptions!$1:$1048576,MATCH('Financial Summary'!J$12,Assumptions!$5:$5,0),FALSE) -> 424.5535 | K14: =VLOOKUP($A14,Assumptions!$1:$1048576,MATCH('Financial Summary'!K$12,Assumptions!$5:$5,0),FALSE) -> 550.06085 | L14: =VLOOKUP($A14,Assumptions!$1:$1048576,MATCH('Financial Summary'!L$12,Assumptions!$5:$5,0),FALSE) -> 665.2735 | M14: =VLOOKUP($A14,Assumptions!$1:$1048576,MATCH('Financial Summary'!M$12,Assumptions!$5:$5,0),FALSE) -> 804.50707 | O14: Cash & Cash Equivalents | P14: A$m | Q14: 0 | S14: =VLOOKUP($Y14,'Financial Statements'!$1:$1048576,MATCH('Financial Summary'!S$12,'Financial Statements'!$5:$5,0),FALSE) -> 294.48 | T14: =VLOOKUP($Y14,'Financial Statements'!$1:$1048576,MATCH('Financial Summary'!T$12,'Financial Statements'!$5:$5,0),FALSE) -> 281.743 | U14: =VLOOKUP($Y14,'Financial Statements'!$1:$1048576,MATCH('Financial Summary'!U$12,'Financial Statements'!$5:$5,0),FALSE) -> 269.57803 | V14: =VLOOKUP($Y14,'Financial Statements'!$1:$1048576,MATCH('Financial Summary'!V$12,'Financial Statements'!$5:$5,0),FALSE) -> 242.88346 | W14: =VLOOKUP($Y14,'Financial Statements'!$1:$1048576,MATCH('Financial Summary'!W$12,'Financial Statements'!$5:$5,0),FALSE) -> 233.92671 | Y14: CA_cash
A15: Revenue_SG | B15: Revenue_JP | C15: Revenue_US | E15: International | F15: A$m | G15: =VLOOKUP($A15,Assumptions!$1:$1048576,MATCH('Financial Summary'!G$12,Assumptions!$5:$5,0),FALSE)+VLOOKUP($B15,Assumptions!$1:$1048576,MATCH('Financial Summary'!G$12,Assumptions!$5:$5,0),FALSE)+VLOOKUP($C15,Assumptions!$1:$1048576,MATCH('Financial Summary'!G$12,Assumptions!$5:$5,0),FALSE) -> 3.773 | H15: =VLOOKUP($A15,Assumptions!$1:$1048576,MATCH('Financial Summary'!H$12,Assumptions!$5:$5,0),FALSE)+VLOOKUP($B15,Assumptions!$1:$1048576,MATCH('Financial Summary'!H$12,Assumptions!$5:$5,0),FALSE)+VLOOKUP($C15,Assumptions!$1:$1048576,MATCH('Financial Summary'!H$12,Assumptions!$5:$5,0),FALSE) -> 7.7185 | I15: =VLOOKUP($A15,Assumptions!$1:$1048576,MATCH('Financial Summary'!I$12,Assumptions!$5:$5,0),FALSE)+VLOOKUP($B15,Assumptions!$1:$1048576,MATCH('Financial Summary'!I$12,Assumptions!$5:$5,0),FALSE)+VLOOKUP($C15,Assumptions!$1:$1048576,MATCH('Financial Summary'!I$12,Assumptions!$5:$5,0),FALSE) -> 12.661 | J15: =VLOOKUP($A15,Assumptions!$1:$1048576,MATCH('Financial Summary'!J$12,Assumptions!$5:$5,0),FALSE)+VLOOKUP($B15,Assumptions!$1:$1048576,MATCH('Financial Summary'!J$12,Assumptions!$5:$5,0),FALSE)+VLOOKUP($C15,Assumptions!$1:$1048576,MATCH('Financial Summary'!J$12,Assumptions!$5:$5,0),FALSE) -> 11.7375 | K15: =VLOOKUP($A15,Assumptions!$1:$1048576,MATCH('Financial Summary'!K$12,Assumptions!$5:$5,0),FALSE)+VLOOKUP($B15,Assumptions!$1:$1048576,MATCH('Financial Summary'!K$12,Assumptions!$5:$5,0),FALSE)+VLOOKUP($C15,Assumptions!$1:$1048576,MATCH('Financial Summary'!K$12,Assumptions!$5:$5,0),FALSE) -> 15.667793 | L15: =VLOOKUP($A15,Assumptions!$1:$1048576,MATCH('Financial Summary'!L$12,Assumptions!$5:$5,0),FALSE)+VLOOKUP($B15,Assumptions!$1:$1048576,MATCH('Financial Summary'!L$12,Assumptions!$5:$5,0),FALSE)+VLOOKUP($C15,Assumptions!$1:$1048576,MATCH('Financial Summary'!L$12,Assumptions!$5:$5,0),FALSE) -> 21.68206 | M15: =VLOOKUP($A15,Assumptions!$1:$1048576,MATCH('Financial Summary'!M$12,Assumptions!$5:$5,0),FALSE)+VLOOKUP($B15,Assumptions!$1:$1048576,MATCH('Financial Summary'!M$12,Assumptions!$5:$5,0),FALSE)+VLOOKUP($C15,Assumptions!$1:$1048576,MATCH('Financial Summary'!M$12,Assumptions!$5:$5,0),FALSE) -> 29.174034 | O15: Current Receivables | P15: A$m | Q15: 0 | S15: =VLOOKUP($Y15,'Financial Statements'!$1:$1048576,MATCH('Financial Summary'!S$12,'Financial Statements'!$5:$5,0),FALSE) -> 26.02 | T15: =VLOOKUP($Y15,'Financial Statements'!$1:$1048576,MATCH('Financial Summary'!T$12,'Financial Statements'!$5:$5,0),FALSE) -> 24.703 | U15: =VLOOKUP($Y15,'Financial Statements'!$1:$1048576,MATCH('Financial Summary'!U$12,'Financial Statements'!$5:$5,0),FALSE) -> 32.031819 | V15: =VLOOKUP($Y15,'Financial Statements'!$1:$1048576,MATCH('Financial Summary'!V$12,'Financial Statements'!$5:$5,0),FALSE) -> 38.895744 | W15: =VLOOKUP($Y15,'Financial Statements'!$1:$1048576,MATCH('Financial Summary'!W$12,'Financial Statements'!$5:$5,0),FALSE) -> 47.203413 | Y15: CA_receivables
A16: Rev_other | E16: Other | F16: A$m | G16: =VLOOKUP($A16,Assumptions!$1:$1048576,MATCH('Financial Summary'!G$12,Assumptions!$5:$5,0),FALSE) -> 13.3 | H16: =VLOOKUP($A16,Assumptions!$1:$1048576,MATCH('Financial Summary'!H$12,Assumptions!$5:$5,0),FALSE) -> 17.7 | I16: =VLOOKUP($A16,Assumptions!$1:$1048576,MATCH('Financial Summary'!I$12,Assumptions!$5:$5,0),FALSE) -> 22.774 | J16: =VLOOKUP($A16,Assumptions!$1:$1048576,MATCH('Financial Summary'!J$12,Assumptions!$5:$5,0),FALSE) -> 32.024 | K16: =VLOOKUP($A16,Assumptions!$1:$1048576,MATCH('Financial Summary'!K$12,Assumptions!$5:$5,0),FALSE) -> 31.927277 | L16: =VLOOKUP($A16,Assumptions!$1:$1048576,MATCH('Financial Summary'!L$12,Assumptions!$5:$5,0),FALSE) -> 38.105297 | M16: =VLOOKUP($A16,Assumptions!$1:$1048576,MATCH('Financial Summary'!M$12,Assumptions!$5:$5,0),FALSE) -> 45.404292 | O16: Property, Plant, & Equipment | P16: A$m | Q16: 0 | S16: =VLOOKUP($Y16,'Financial Statements'!$1:$1048576,MATCH('Financial Summary'!S$12,'Financial Statements'!$5:$5,0),FALSE) -> 87.63 | T16: =VLOOKUP($Y16,'Financial Statements'!$1:$1048576,MATCH('Financial Summary'!T$12,'Financial Statements'!$5:$5,0),FALSE) -> 130.056 | U16: =VLOOKUP($Y16,'Financial Statements'!$1:$1048576,MATCH('Financial Summary'!U$12,'Financial Statements'!$5:$5,0),FALSE) -> 160.12529 | V16: =VLOOKUP($Y16,'Financial Statements'!$1:$1048576,MATCH('Financial Summary'!V$12,'Financial Statements'!$5:$5,0),FALSE) -> 203.13492 | W16: =VLOOKUP($Y16,'Financial Statements'!$1:$1048576,MATCH('Financial Summary'!W$12,'Financial Statements'!$5:$5,0),FALSE) -> 233.9555 | Y16: PPE
E17: Total Revenue | F17: A$m | G17: =SUM(G14:G16) -> 185.1 | H17: =SUM(H14:H16) -> 276.8 | I17: =SUM(I14:I16) -> 364.977 | J17: =SUM(J14:J16) -> 468.315 | K17: =SUM(K14:K16) -> 597.65592 | L17: =SUM(L14:L16) -> 725.06085 | M17: =SUM(M14:M16) -> 879.08539 | O17: Intangibles | P17: A$m | Q17: 0 | S17: =VLOOKUP($Y17,'Financial Statements'!$1:$1048576,MATCH('Financial Summary'!S$12,'Financial Statements'!$5:$5,0),FALSE) -> 10.586 | T17: =VLOOKUP($Y17,'Financial Statements'!$1:$1048576,MATCH('Financial Summary'!T$12,'Financial Statements'!$5:$5,0),FALSE) -> 18.305 | U17: =VLOOKUP($Y17,'Financial Statements'!$1:$1048576,MATCH('Financial Summary'!U$12,'Financial Statements'!$5:$5,0),FALSE) -> 16.571153 | V17: =VLOOKUP($Y17,'Financial Statements'!$1:$1048576,MATCH('Financial Summary'!V$12,'Financial Statements'!$5:$5,0),FALSE) -> 18.657356 | W17: =VLOOKUP($Y17,'Financial Statements'!$1:$1048576,MATCH('Financial Summary'!W$12,'Financial Statements'!$5:$5,0),FALSE) -> 21.950918 | Y17: Intangibles_BS
E18: % change | F18: % | H18: =H17/G17-1 -> 0.49540789 | I18: =I17/H17-1 -> 0.31855853 | J18: =J17/I17-1 -> 0.28313565 | K18: =K17/J17-1 -> 0.27618359 | L18: =L17/K17-1 -> 0.21317439 | M18: =M17/L17-1 -> 0.21242981 | O18: Other Assets | P18: A$m | Q18: 0 | S18: =S19-S14-S15-S16-S17 -> 243.081 | T18: =T19-T14-T15-T16-T17 -> 328.391 | U18: =U19-U14-U15-U16-U17 -> 367.16967 | V18: =V19-V14-V15-V16-V17 -> 424.43339 | W18: =W19-W14-W15-W16-W17 -> 480.2017
E19: 3yr CAGR | M19: =+(M17/J17)^(0.333333333333333)-1 -> 0.23357151 | O19: Total Assets | P19: A$m | Q19: 0 | S19: =VLOOKUP($Y19,'Financial Statements'!$1:$1048576,MATCH('Financial Summary'!S$12,'Financial Statements'!$5:$5,0),FALSE) -> 661.797 | T19: =VLOOKUP($Y19,'Financial Statements'!$1:$1048576,MATCH('Financial Summary'!T$12,'Financial Statements'!$5:$5,0),FALSE) -> 783.198 | U19: =VLOOKUP($Y19,'Financial Statements'!$1:$1048576,MATCH('Financial Summary'!U$12,'Financial Statements'!$5:$5,0),FALSE) -> 845.47597 | V19: =VLOOKUP($Y19,'Financial Statements'!$1:$1048576,MATCH('Financial Summary'!V$12,'Financial Statements'!$5:$5,0),FALSE) -> 928.00487 | W19: =VLOOKUP($Y19,'Financial Statements'!$1:$1048576,MATCH('Financial Summary'!W$12,'Financial Statements'!$5:$5,0),FALSE) -> 1017.2382 | Y19: Total_assets
A21: Group_Corp_restaurant_margin | E21: Corp restaurant margin | F21: A$m | G21: =VLOOKUP($A21,Assumptions!$1:$1048576,MATCH('Financial Summary'!G$12,Assumptions!$5:$5,0),FALSE) -> 19.2322 | H21: =VLOOKUP($A21,Assumptions!$1:$1048576,MATCH('Financial Summary'!H$12,Assumptions!$5:$5,0),FALSE) -> 29.76 | I21: =VLOOKUP($A21,Assumptions!$1:$1048576,MATCH('Financial Summary'!I$12,Assumptions!$5:$5,0),FALSE) -> 47.535 | J21: =VLOOKUP($A21,Assumptions!$1:$1048576,MATCH('Financial Summary'!J$12,Assumptions!$5:$5,0),FALSE) -> 59.2688 | K21: =VLOOKUP($A21,Assumptions!$1:$1048576,MATCH('Financial Summary'!K$12,Assumptions!$5:$5,0),FALSE) -> 81.905084 | L21: =VLOOKUP($A21,Assumptions!$1:$1048576,MATCH('Financial Summary'!L$12,Assumptions!$5:$5,0),FALSE) -> 107.60918 | M21: =VLOOKUP($A21,Assumptions!$1:$1048576,MATCH('Financial Summary'!M$12,Assumptions!$5:$5,0),FALSE) -> 136.27816 | O21: Current Payables | P21: A$m | Q21: 0 | S21: =VLOOKUP($Y21,'Financial Statements'!$1:$1048576,MATCH('Financial Summary'!S$12,'Financial Statements'!$5:$5,0),FALSE) -> 39.387 | T21: =VLOOKUP($Y21,'Financial Statements'!$1:$1048576,MATCH('Financial Summary'!T$12,'Financial Statements'!$5:$5,0),FALSE) -> 40.439 | U21: =VLOOKUP($Y21,'Financial Statements'!$1:$1048576,MATCH('Financial Summary'!U$12,'Financial Statements'!$5:$5,0),FALSE) -> 55.997827 | V21: =VLOOKUP($Y21,'Financial Statements'!$1:$1048576,MATCH('Financial Summary'!V$12,'Financial Statements'!$5:$5,0),FALSE) -> 68.097657 | W21: =VLOOKUP($Y21,'Financial Statements'!$1:$1048576,MATCH('Financial Summary'!W$12,'Financial Statements'!$5:$5,0),FALSE) -> 82.720269 | Y21: CL_payables
A22: Group_Franchise_rev | E22: Franchise revenue | F22: A$m | G22: =VLOOKUP($A22,Assumptions!$1:$1048576,MATCH('Financial Summary'!G$12,Assumptions!$5:$5,0),FALSE) -> 33.4 | H22: =VLOOKUP($A22,Assumptions!$1:$1048576,MATCH('Financial Summary'!H$12,Assumptions!$5:$5,0),FALSE) -> 46.8 | I22: =VLOOKUP($A22,Assumptions!$1:$1048576,MATCH('Financial Summary'!I$12,Assumptions!$5:$5,0),FALSE) -> 60.7 | J22: =VLOOKUP($A22,Assumptions!$1:$1048576,MATCH('Financial Summary'!J$12,Assumptions!$5:$5,0),FALSE) -> 78.924 | K22: =VLOOKUP($A22,Assumptions!$1:$1048576,MATCH('Financial Summary'!K$12,Assumptions!$5:$5,0),FALSE) -> 84.714638 | L22: =VLOOKUP($A22,Assumptions!$1:$1048576,MATCH('Financial Summary'!L$12,Assumptions!$5:$5,0),FALSE) -> 103.16223 | M22: =VLOOKUP($A22,Assumptions!$1:$1048576,MATCH('Financial Summary'!M$12,Assumptions!$5:$5,0),FALSE) -> 125.59537 | O22: Total Debt | P22: A$m | Q22: 0 | S22: =VLOOKUP($Y22,'Financial Statements'!$1:$1048576,MATCH('Financial Summary'!S$12,'Financial Statements'!$5:$5,0),FALSE) -> 0 | T22: =VLOOKUP($Y22,'Financial Statements'!$1:$1048576,MATCH('Financial Summary'!T$12,'Financial Statements'!$5:$5,0),FALSE) -> 0 | U22: =VLOOKUP($Y22,'Financial Statements'!$1:$1048576,MATCH('Financial Summary'!U$12,'Financial Statements'!$5:$5,0),FALSE) -> 0 | V22: =VLOOKUP($Y22,'Financial Statements'!$1:$1048576,MATCH('Financial Summary'!V$12,'Financial Statements'!$5:$5,0),FALSE) -> 0 | W22: =VLOOKUP($Y22,'Financial Statements'!$1:$1048576,MATCH('Financial Summary'!W$12,'Financial Statements'!$5:$5,0),FALSE) -> 0 | Y22: LT_borrowings
A23: Total_G&A_expense | E23: G&A expense | F23: A$m | G23: =VLOOKUP($A23,Assumptions!$1:$1048576,MATCH('Financial Summary'!G$12,Assumptions!$5:$5,0),FALSE) -> -37.2 | H23: =VLOOKUP($A23,Assumptions!$1:$1048576,MATCH('Financial Summary'!H$12,Assumptions!$5:$5,0),FALSE) -> -50.1 | I23: =VLOOKUP($A23,Assumptions!$1:$1048576,MATCH('Financial Summary'!I$12,Assumptions!$5:$5,0),FALSE) -> -69.2 | J23: =VLOOKUP($A23,Assumptions!$1:$1048576,MATCH('Financial Summary'!J$12,Assumptions!$5:$5,0),FALSE) -> -85.4 | K23: =VLOOKUP($A23,Assumptions!$1:$1048576,MATCH('Financial Summary'!K$12,Assumptions!$5:$5,0),FALSE) -> -95.042689 | L23: =VLOOKUP($A23,Assumptions!$1:$1048576,MATCH('Financial Summary'!L$12,Assumptions!$5:$5,0),FALSE) -> -104.3884 | M23: =VLOOKUP($A23,Assumptions!$1:$1048576,MATCH('Financial Summary'!M$12,Assumptions!$5:$5,0),FALSE) -> -114.7038 | O23: Other Liabilities | P23: A$m | Q23: 0 | S23: =+S24-S21-S22 -> 268.431 | T23: =+T24-T21-T22 -> 362.635 | U23: =+U24-U21-U22 -> 394.29721 | V23: =+V24-V21-V22 -> 443.82335 | W23: =+W24-W21-W22 -> 491.08215
A24: Segment_underlying_EBITDA | E24: EBITDA Segment Underlying | F24: A$m | G24: =VLOOKUP($A24,Assumptions!$1:$1048576,MATCH('Financial Summary'!G$12,Assumptions!$5:$5,0),FALSE) -> 15.4322 | H24: =VLOOKUP($A24,Assumptions!$1:$1048576,MATCH('Financial Summary'!H$12,Assumptions!$5:$5,0),FALSE) -> 26.46 | I24: =VLOOKUP($A24,Assumptions!$1:$1048576,MATCH('Financial Summary'!I$12,Assumptions!$5:$5,0),FALSE) -> 39.035 | J24: =VLOOKUP($A24,Assumptions!$1:$1048576,MATCH('Financial Summary'!J$12,Assumptions!$5:$5,0),FALSE) -> 52.7928 | K24: =VLOOKUP($A24,Assumptions!$1:$1048576,MATCH('Financial Summary'!K$12,Assumptions!$5:$5,0),FALSE) -> 71.577033 | L24: =VLOOKUP($A24,Assumptions!$1:$1048576,MATCH('Financial Summary'!L$12,Assumptions!$5:$5,0),FALSE) -> 106.38302 | M24: =VLOOKUP($A24,Assumptions!$1:$1048576,MATCH('Financial Summary'!M$12,Assumptions!$5:$5,0),FALSE) -> 147.16973 | O24: Total Liabilities | P24: A$m | Q24: 0 | S24: =VLOOKUP($Y24,'Financial Statements'!$1:$1048576,MATCH('Financial Summary'!S$12,'Financial Statements'!$5:$5,0),FALSE) -> 307.818 | T24: =VLOOKUP($Y24,'Financial Statements'!$1:$1048576,MATCH('Financial Summary'!T$12,'Financial Statements'!$5:$5,0),FALSE) -> 403.074 | U24: =VLOOKUP($Y24,'Financial Statements'!$1:$1048576,MATCH('Financial Summary'!U$12,'Financial Statements'!$5:$5,0),FALSE) -> 450.29504 | V24: =VLOOKUP($Y24,'Financial Statements'!$1:$1048576,MATCH('Financial Summary'!V$12,'Financial Statements'!$5:$5,0),FALSE) -> 511.92101 | W24: =VLOOKUP($Y24,'Financial Statements'!$1:$1048576,MATCH('Financial Summary'!W$12,'Financial Statements'!$5:$5,0),FALSE) -> 573.80242 | Y24: Total_liabilities | AC24: =_xlfn.RRI(2,K24,M24) -> 0.4339117
E25: % change | H25: =H24/G24-1 -> 0.71459675 | I25: =I24/H24-1 -> 0.47524565 | J25: =J24/I24-1 -> 0.3524478 | K25: =K24/J24-1 -> 0.35581051 | L25: =L24/K24-1 -> 0.48627307 | M25: =M24/L24-1 -> 0.38339501
E26: 3yr CAGR | M26: =+(M24/J24)^(0.333333333333333)-1 -> 0.40739046 | O26: Net Assets | P26: A$m | Q26: 0 | S26: =VLOOKUP($Y26,'Financial Statements'!$1:$1048576,MATCH('Financial Summary'!S$12,'Financial Statements'!$5:$5,0),FALSE) -> 353.979 | T26: =VLOOKUP($Y26,'Financial Statements'!$1:$1048576,MATCH('Financial Summary'!T$12,'Financial Statements'!$5:$5,0),FALSE) -> 380.124 | U26: =VLOOKUP($Y26,'Financial Statements'!$1:$1048576,MATCH('Financial Summary'!U$12,'Financial Statements'!$5:$5,0),FALSE) -> 395.18093 | V26: =VLOOKUP($Y26,'Financial Statements'!$1:$1048576,MATCH('Financial Summary'!V$12,'Financial Statements'!$5:$5,0),FALSE) -> 416.08387 | W26: =VLOOKUP($Y26,'Financial Statements'!$1:$1048576,MATCH('Financial Summary'!W$12,'Financial Statements'!$5:$5,0),FALSE) -> 443.43583 | Y26: Net_assets
O27: Net Debt (cash) | P27: A$m | Q27: 0 | S27: =VLOOKUP($Y27,Assumptions!$1:$1048576,MATCH('Financial Summary'!S$12,Assumptions!$5:$5,0),FALSE) -> -294.48 | T27: =VLOOKUP($Y27,Assumptions!$1:$1048576,MATCH('Financial Summary'!T$12,Assumptions!$5:$5,0),FALSE) -> -281.743 | U27: =VLOOKUP($Y27,Assumptions!$1:$1048576,MATCH('Financial Summary'!U$12,Assumptions!$5:$5,0),FALSE) -> -269.57803 | V27: =VLOOKUP($Y27,Assumptions!$1:$1048576,MATCH('Financial Summary'!V$12,Assumptions!$5:$5,0),FALSE) -> -242.88346 | W27: =VLOOKUP($Y27,Assumptions!$1:$1048576,MATCH('Financial Summary'!W$12,Assumptions!$5:$5,0),FALSE) -> -233.92671 | Y27: Net_Debt
A28: EBITDA_Normalised | E28: EBITDA Normalised | F28: A$m | G28: =VLOOKUP($A$28,'Financial Statements'!$1:$1048576,MATCH('Financial Summary'!G$12,'Financial Statements'!$5:$5,0),FALSE) -> 21.6 | H28: =VLOOKUP($A$28,'Financial Statements'!$1:$1048576,MATCH('Financial Summary'!H$12,'Financial Statements'!$5:$5,0),FALSE) -> 29.3 | I28: =VLOOKUP($A$28,'Financial Statements'!$1:$1048576,MATCH('Financial Summary'!I$12,'Financial Statements'!$5:$5,0),FALSE) -> 44.759 | J28: =VLOOKUP($A$28,'Financial Statements'!$1:$1048576,MATCH('Financial Summary'!J$12,'Financial Statements'!$5:$5,0),FALSE) -> 65.428 | K28: =VLOOKUP($A$28,'Financial Statements'!$1:$1048576,MATCH('Financial Summary'!K$12,'Financial Statements'!$5:$5,0),FALSE) -> 85.352441 | L28: =VLOOKUP($A$28,'Financial Statements'!$1:$1048576,MATCH('Financial Summary'!L$12,'Financial Statements'!$5:$5,0),FALSE) -> 125.68896 | M28: =VLOOKUP($A$28,'Financial Statements'!$1:$1048576,MATCH('Financial Summary'!M$12,'Financial Statements'!$5:$5,0),FALSE) -> 171.73704 | O28: Capital Employed | P28: A$m | Q28: 0 | S28: =+S26+S27 -> 59.499 | T28: =+T26+T27 -> 98.381 | U28: =+U26+U27 -> 125.6029 | V28: =+V26+V27 -> 173.20041 | W28: =+W26+W27 -> 209.50912
A30: Total_D&A | E30: Total D&A | F30: A$m | G30: =VLOOKUP($A30,'Financial Statements'!$1:$1048576,MATCH('Financial Summary'!G$12,'Financial Statements'!$5:$5,0),FALSE) -> -14.4 | H30: =VLOOKUP($A30,'Financial Statements'!$1:$1048576,MATCH('Financial Summary'!H$12,'Financial Statements'!$5:$5,0),FALSE) -> -25.5 | I30: =VLOOKUP($A30,'Financial Statements'!$1:$1048576,MATCH('Financial Summary'!I$12,'Financial Statements'!$5:$5,0),FALSE) -> -31.123 | J30: =VLOOKUP($A30,'Financial Statements'!$1:$1048576,MATCH('Financial Summary'!J$12,'Financial Statements'!$5:$5,0),FALSE) -> -39.681 | K30: =VLOOKUP($A30,'Financial Statements'!$1:$1048576,MATCH('Financial Summary'!K$12,'Financial Statements'!$5:$5,0),FALSE) -> -48.678845 | L30: =VLOOKUP($A30,'Financial Statements'!$1:$1048576,MATCH('Financial Summary'!L$12,'Financial Statements'!$5:$5,0),FALSE) -> -58.461202 | M30: =VLOOKUP($A30,'Financial Statements'!$1:$1048576,MATCH('Financial Summary'!M$12,'Financial Statements'!$5:$5,0),FALSE) -> -69.478955 | O30: Cash Flow Statement
E31: Total EBIT | F31: A$m | G31: =VLOOKUP($A32,'Financial Statements'!$1:$1048576,MATCH('Financial Summary'!G$12,'Financial Statements'!$5:$5,0),FALSE) -> 7.2 | H31: =VLOOKUP($A32,'Financial Statements'!$1:$1048576,MATCH('Financial Summary'!H$12,'Financial Statements'!$5:$5,0),FALSE) -> 3.8 | I31: =VLOOKUP($A32,'Financial Statements'!$1:$1048576,MATCH('Financial Summary'!I$12,'Financial Statements'!$5:$5,0),FALSE) -> 13.636 | J31: =VLOOKUP($A32,'Financial Statements'!$1:$1048576,MATCH('Financial Summary'!J$12,'Financial Statements'!$5:$5,0),FALSE) -> 25.747 | K31: =VLOOKUP($A32,'Financial Statements'!$1:$1048576,MATCH('Financial Summary'!K$12,'Financial Statements'!$5:$5,0),FALSE) -> 36.673596 | L31: =VLOOKUP($A32,'Financial Statements'!$1:$1048576,MATCH('Financial Summary'!L$12,'Financial Statements'!$5:$5,0),FALSE) -> 67.227753 | M31: =VLOOKUP($A32,'Financial Statements'!$1:$1048576,MATCH('Financial Summary'!M$12,'Financial Statements'!$5:$5,0),FALSE) -> 102.25809 | O31: Year ended 30 June | P31: Unit | Q31: FY22 | R31: FY23 | S31: FY24 | T31: FY25 | U31: FY26e | V31: FY27e | W31: FY28e
A32: Total_EBIT | E32: % change | F32: % | H32: =H31/G31-1 -> -0.47222222 | I32: =I31/H31-1 -> 2.5884211 | J32: =J31/I31-1 -> 0.88816368 | K32: =K31/J31-1 -> 0.42438327 | L32: =L31/K31-1 -> 0.83313775 | M32: =M31/L31-1 -> 0.52106956 | O32: EBIT | P32: A$m | Q32: =VLOOKUP($Y32,'Financial Statements'!$1:$1048576,MATCH('Financial Summary'!Q$31,'Financial Statements'!$5:$5,0),FALSE) -> 7.2 | S32: =VLOOKUP($Y32,'Financial Statements'!$1:$1048576,MATCH('Financial Summary'!S$31,'Financial Statements'!$5:$5,0),FALSE) -> 13.6 | T32: =VLOOKUP($Y32,'Financial Statements'!$1:$1048576,MATCH('Financial Summary'!T$31,'Financial Statements'!$5:$5,0),FALSE) -> 25.4 | U32: =VLOOKUP($Y32,'Financial Statements'!$1:$1048576,MATCH('Financial Summary'!U$31,'Financial Statements'!$5:$5,0),FALSE) -> 36.673596 | V32: =VLOOKUP($Y32,'Financial Statements'!$1:$1048576,MATCH('Financial Summary'!V$31,'Financial Statements'!$5:$5,0),FALSE) -> 67.227753 | W32: =VLOOKUP($Y32,'Financial Statements'!$1:$1048576,MATCH('Financial Summary'!W$31,'Financial Statements'!$5:$5,0),FALSE) -> 102.25809 | Y32: CF_EBIT
E33: 3yr CAGR | M33: =+(M31/J31)^(0.333333333333333)-1 -> 0.58364201 | O33: D&A | P33: A$m | Q33: =VLOOKUP($Y33,'Financial Statements'!$1:$1048576,MATCH('Financial Summary'!Q$31,'Financial Statements'!$5:$5,0),FALSE) -> 14.5 | S33: =VLOOKUP($Y33,'Financial Statements'!$1:$1048576,MATCH('Financial Summary'!S$31,'Financial Statements'!$5:$5,0),FALSE) -> 31.123 | T33: =VLOOKUP($Y33,'Financial Statements'!$1:$1048576,MATCH('Financial Summary'!T$31,'Financial Statements'!$5:$5,0),FALSE) -> 39.681 | U33: =VLOOKUP($Y33,'Financial Statements'!$1:$1048576,MATCH('Financial Summary'!U$31,'Financial Statements'!$5:$5,0),FALSE) -> 48.678845 | V33: =VLOOKUP($Y33,'Financial Statements'!$1:$1048576,MATCH('Financial Summary'!V$31,'Financial Statements'!$5:$5,0),FALSE) -> 58.461202 | W33: =VLOOKUP($Y33,'Financial Statements'!$1:$1048576,MATCH('Financial Summary'!W$31,'Financial Statements'!$5:$5,0),FALSE) -> 69.478955 | Y33: CF_D&A
O34: (Inc)/dec in working cap | P34: A$m | Q34: =VLOOKUP($Y34,'Financial Statements'!$1:$1048576,MATCH('Financial Summary'!Q$31,'Financial Statements'!$5:$5,0),FALSE) -> -1.1 | S34: =VLOOKUP($Y34,'Financial Statements'!$1:$1048576,MATCH('Financial Summary'!S$31,'Financial Statements'!$5:$5,0),FALSE) -> 10.541 | T34: =VLOOKUP($Y34,'Financial Statements'!$1:$1048576,MATCH('Financial Summary'!T$31,'Financial Statements'!$5:$5,0),FALSE) -> 10.734 | U34: =VLOOKUP($Y34,'Financial Statements'!$1:$1048576,MATCH('Financial Summary'!U$31,'Financial Statements'!$5:$5,0),FALSE) -> 6.7829699 | V34: =VLOOKUP($Y34,'Financial Statements'!$1:$1048576,MATCH('Financial Summary'!V$31,'Financial Statements'!$5:$5,0),FALSE) -> 4.1105691 | W34: =VLOOKUP($Y34,'Financial Statements'!$1:$1048576,MATCH('Financial Summary'!W$31,'Financial Statements'!$5:$5,0),FALSE) -> 4.9549784 | Y34: Chg_working_Cap
A35: Total_Net_Int | E35: Net Interest Expense | F35: A$m | G35: =VLOOKUP($A35,'Financial Statements'!$1:$1048576,MATCH('Financial Summary'!G$12,'Financial Statements'!$5:$5,0),FALSE) -> -1.6 | H35: =VLOOKUP($A35,'Financial Statements'!$1:$1048576,MATCH('Financial Summary'!H$12,'Financial Statements'!$5:$5,0),FALSE) -> 3.9 | I35: =VLOOKUP($A35,'Financial Statements'!$1:$1048576,MATCH('Financial Summary'!I$12,'Financial Statements'!$5:$5,0),FALSE) -> 2.617 | J35: =VLOOKUP($A35,'Financial Statements'!$1:$1048576,MATCH('Financial Summary'!J$12,'Financial Statements'!$5:$5,0),FALSE) -> 3.772 | K35: =VLOOKUP($A35,'Financial Statements'!$1:$1048576,MATCH('Financial Summary'!K$12,'Financial Statements'!$5:$5,0),FALSE) -> 2.2553574 | L35: =VLOOKUP($A35,'Financial Statements'!$1:$1048576,MATCH('Financial Summary'!L$12,'Financial Statements'!$5:$5,0),FALSE) -> -0.92870741 | M35: =VLOOKUP($A35,'Financial Statements'!$1:$1048576,MATCH('Financial Summary'!M$12,'Financial Statements'!$5:$5,0),FALSE) -> -4.8335596 | O35: Income Tax | P35: A$m | Q35: =VLOOKUP($Y35,'Financial Statements'!$1:$1048576,MATCH('Financial Summary'!Q$31,'Financial Statements'!$5:$5,0),FALSE) -> -0.1 | S35: =VLOOKUP($Y35,'Financial Statements'!$1:$1048576,MATCH('Financial Summary'!S$31,'Financial Statements'!$5:$5,0),FALSE) -> -6.502 | T35: =VLOOKUP($Y35,'Financial Statements'!$1:$1048576,MATCH('Financial Summary'!T$31,'Financial Statements'!$5:$5,0),FALSE) -> -19.389 | U35: =VLOOKUP($Y35,'Financial Statements'!$1:$1048576,MATCH('Financial Summary'!U$31,'Financial Statements'!$5:$5,0),FALSE) -> -17.447821 | V35: =VLOOKUP($Y35,'Financial Statements'!$1:$1048576,MATCH('Financial Summary'!V$31,'Financial Statements'!$5:$5,0),FALSE) -> -24.023059 | W35: =VLOOKUP($Y35,'Financial Statements'!$1:$1048576,MATCH('Financial Summary'!W$31,'Financial Statements'!$5:$5,0),FALSE) -> -32.20864 | Y35: CF_Income_tax
A36: PBT | E36: Profit Before Tax | F36: A$m | G36: =VLOOKUP($A36,'Financial Statements'!$1:$1048576,MATCH('Financial Summary'!G$12,'Financial Statements'!$5:$5,0),FALSE) -> 5.6 | H36: =VLOOKUP($A36,'Financial Statements'!$1:$1048576,MATCH('Financial Summary'!H$12,'Financial Statements'!$5:$5,0),FALSE) -> 7.7 | I36: =VLOOKUP($A36,'Financial Statements'!$1:$1048576,MATCH('Financial Summary'!I$12,'Financial Statements'!$5:$5,0),FALSE) -> 16.253 | J36: =VLOOKUP($A36,'Financial Statements'!$1:$1048576,MATCH('Financial Summary'!J$12,'Financial Statements'!$5:$5,0),FALSE) -> 29.519 | K36: =VLOOKUP($A36,'Financial Statements'!$1:$1048576,MATCH('Financial Summary'!K$12,'Financial Statements'!$5:$5,0),FALSE) -> 38.928953 | L36: =VLOOKUP($A36,'Financial Statements'!$1:$1048576,MATCH('Financial Summary'!L$12,'Financial Statements'!$5:$5,0),FALSE) -> 66.299046 | M36: =VLOOKUP($A36,'Financial Statements'!$1:$1048576,MATCH('Financial Summary'!M$12,'Financial Statements'!$5:$5,0),FALSE) -> 97.42453 | O36: Other | P36: A$m | Q36: =+Q37-Q32-Q33-Q34-Q35 -> -0.3 | S36: =+S37-S32-S33-S34-S35 -> 7.538 | T36: =+T37-T32-T33-T34-T35 -> 0.901 | U36: =+U37-U32-U33-U34-U35 -> 9.018 | V36: =+V37-V32-V33-V34-V35 -> 9.018 | W36: =+W37-W32-W33-W34-W35 -> 9.018
A37: Tax_expense | E37: Income Tax | F37: A$m | G37: =VLOOKUP($A37,'Financial Statements'!$1:$1048576,MATCH('Financial Summary'!G$12,'Financial Statements'!$5:$5,0),FALSE) -> -2.4 | H37: =VLOOKUP($A37,'Financial Statements'!$1:$1048576,MATCH('Financial Summary'!H$12,'Financial Statements'!$5:$5,0),FALSE) -> -4.7 | I37: =VLOOKUP($A37,'Financial Statements'!$1:$1048576,MATCH('Financial Summary'!I$12,'Financial Statements'!$5:$5,0),FALSE) -> -10.6 | J37: =VLOOKUP($A37,'Financial Statements'!$1:$1048576,MATCH('Financial Summary'!J$12,'Financial Statements'!$5:$5,0),FALSE) -> -14.7 | K37: =VLOOKUP($A37,'Financial Statements'!$1:$1048576,MATCH('Financial Summary'!K$12,'Financial Statements'!$5:$5,0),FALSE) -> -17.447821 | L37: =VLOOKUP($A37,'Financial Statements'!$1:$1048576,MATCH('Financial Summary'!L$12,'Financial Statements'!$5:$5,0),FALSE) -> -24.023059 | M37: =VLOOKUP($A37,'Financial Statements'!$1:$1048576,MATCH('Financial Summary'!M$12,'Financial Statements'!$5:$5,0),FALSE) -> -32.20864 | O37: Operating cash flow | P37: A$m | Q37: =VLOOKUP($Y37,'Financial Statements'!$1:$1048576,MATCH('Financial Summary'!Q$31,'Financial Statements'!$5:$5,0),FALSE) -> 20.2 | S37: =VLOOKUP($Y37,'Financial Statements'!$1:$1048576,MATCH('Financial Summary'!S$31,'Financial Statements'!$5:$5,0),FALSE) -> 56.3 | T37: =VLOOKUP($Y37,'Financial Statements'!$1:$1048576,MATCH('Financial Summary'!T$31,'Financial Statements'!$5:$5,0),FALSE) -> 57.327 | U37: =VLOOKUP($Y37,'Financial Statements'!$1:$1048576,MATCH('Financial Summary'!U$31,'Financial Statements'!$5:$5,0),FALSE) -> 83.70559 | V37: =VLOOKUP($Y37,'Financial Statements'!$1:$1048576,MATCH('Financial Summary'!V$31,'Financial Statements'!$5:$5,0),FALSE) -> 114.79447 | W37: =VLOOKUP($Y37,'Financial Statements'!$1:$1048576,MATCH('Financial Summary'!W$31,'Financial Statements'!$5:$5,0),FALSE) -> 153.50138 | Y37: OCF
A38: NPAT_underlying | E38: NPAT (Underlying) | F38: A$m | G38: =VLOOKUP($A38,'Financial Statements'!$1:$1048576,MATCH('Financial Summary'!G$12,'Financial Statements'!$5:$5,0),FALSE) -> 3.2 | H38: =VLOOKUP($A38,'Financial Statements'!$1:$1048576,MATCH('Financial Summary'!H$12,'Financial Statements'!$5:$5,0),FALSE) -> 3 | I38: =VLOOKUP($A38,'Financial Statements'!$1:$1048576,MATCH('Financial Summary'!I$12,'Financial Statements'!$5:$5,0),FALSE) -> 5.653 | J38: =VLOOKUP($A38,'Financial Statements'!$1:$1048576,MATCH('Financial Summary'!J$12,'Financial Statements'!$5:$5,0),FALSE) -> 14.819 | K38: =VLOOKUP($A38,'Financial Statements'!$1:$1048576,MATCH('Financial Summary'!K$12,'Financial Statements'!$5:$5,0),FALSE) -> 21.481133 | L38: =VLOOKUP($A38,'Financial Statements'!$1:$1048576,MATCH('Financial Summary'!L$12,'Financial Statements'!$5:$5,0),FALSE) -> 42.275987 | M38: =VLOOKUP($A38,'Financial Statements'!$1:$1048576,MATCH('Financial Summary'!M$12,'Financial Statements'!$5:$5,0),FALSE) -> 65.215889 | O38: Purchase of PPE | P38: A$m | Q38: =VLOOKUP($Y38,'Financial Statements'!$1:$1048576,MATCH('Financial Summary'!Q$31,'Financial Statements'!$5:$5,0),FALSE) -> -19.4 | S38: =VLOOKUP($Y38,'Financial Statements'!$1:$1048576,MATCH('Financial Summary'!S$31,'Financial Statements'!$5:$5,0),FALSE) -> -33.496 | T38: =VLOOKUP($Y38,'Financial Statements'!$1:$1048576,MATCH('Financial Summary'!T$31,'Financial Statements'!$5:$5,0),FALSE) -> -61.326 | U38: =VLOOKUP($Y38,'Financial Statements'!$1:$1048576,MATCH('Financial Summary'!U$31,'Financial Statements'!$5:$5,0),FALSE) -> -54.749065 | V38: =VLOOKUP($Y38,'Financial Statements'!$1:$1048576,MATCH('Financial Summary'!V$31,'Financial Statements'!$5:$5,0),FALSE) -> -73.021702 | W38: =VLOOKUP($Y38,'Financial Statements'!$1:$1048576,MATCH('Financial Summary'!W$31,'Financial Statements'!$5:$5,0),FALSE) -> -66.566951 | Y38: CF_PPE
E39: % change | H39: =H38/G38-1 -> -0.0625 | I39: =I38/H38-1 -> 0.88433333 | J39: =J38/I38-1 -> 1.6214399 | K39: =K38/J38-1 -> 0.44956694 | L39: =L38/K38-1 -> 0.96805205 | M39: =M38/L38-1 -> 0.54262252 | O39: Payments for Intangibles | P39: A$m | Q39: =VLOOKUP($Y39,'Financial Statements'!$1:$1048576,MATCH('Financial Summary'!Q$31,'Financial Statements'!$5:$5,0),FALSE) -> -7 | S39: =VLOOKUP($Y39,'Financial Statements'!$1:$1048576,MATCH('Financial Summary'!S$31,'Financial Statements'!$5:$5,0),FALSE) -> -0.063 | T39: =VLOOKUP($Y39,'Financial Statements'!$1:$1048576,MATCH('Financial Summary'!T$31,'Financial Statements'!$5:$5,0),FALSE) -> -0.037 | U39: =VLOOKUP($Y39,'Financial Statements'!$1:$1048576,MATCH('Financial Summary'!U$31,'Financial Statements'!$5:$5,0),FALSE) -> -5.6572864 | V39: =VLOOKUP($Y39,'Financial Statements'!$1:$1048576,MATCH('Financial Summary'!V$31,'Financial Statements'!$5:$5,0),FALSE) -> -10.304333 | W39: =VLOOKUP($Y39,'Financial Statements'!$1:$1048576,MATCH('Financial Summary'!W$31,'Financial Statements'!$5:$5,0),FALSE) -> -12.505216 | Y39: CF_Intangibles
E40: 3yr CAGR | M40: =+(M38/J38)^(0.333333333333333)-1 -> 0.63874548 | O40: Other investing | P40: A$m | Q40: =Q41-Q38-Q39 -> -5.3 | S40: =S41-S38-S39 -> -278.259 | T40: =T41-T38-T39 -> 26.812 | U40: =U41-U38-U39 -> 0 | V40: =V41-V38-V39 -> 0 | W40: =W41-W38-W39 -> 0
O41: Total Investing Cash Flows | P41: A$m | Q41: =VLOOKUP($Y41,'Financial Statements'!$1:$1048576,MATCH('Financial Summary'!Q$31,'Financial Statements'!$5:$5,0),FALSE) -> -31.7 | S41: =VLOOKUP($Y41,'Financial Statements'!$1:$1048576,MATCH('Financial Summary'!S$31,'Financial Statements'!$5:$5,0),FALSE) -> -311.818 | T41: =VLOOKUP($Y41,'Financial Statements'!$1:$1048576,MATCH('Financial Summary'!T$31,'Financial Statements'!$5:$5,0),FALSE) -> -34.551 | U41: =VLOOKUP($Y41,'Financial Statements'!$1:$1048576,MATCH('Financial Summary'!U$31,'Financial Statements'!$5:$5,0),FALSE) -> -60.406351 | V41: =VLOOKUP($Y41,'Financial Statements'!$1:$1048576,MATCH('Financial Summary'!V$31,'Financial Statements'!$5:$5,0),FALSE) -> -83.326036 | W41: =VLOOKUP($Y41,'Financial Statements'!$1:$1048576,MATCH('Financial Summary'!W$31,'Financial Statements'!$5:$5,0),FALSE) -> -79.072168 | Y41: Net_CF_Investing
E42: Significant Items | F42: A$m | G42: =+G43-G38 -> 0.7 | H42: =+H43-H38 -> -5.3 | I42: =+I43-I38 -> -19.401 | J42: =+J43-J38 -> -0.343 | K42: =+K43-K38 -> 0 | L42: =+L43-L38 -> -8.1712415e-13 | M42: =+M43-M38 -> -6.2527761e-12 | O42: Dividends paid | P42: A$m | Q42: =VLOOKUP($Y42,'Financial Statements'!$1:$1048576,MATCH('Financial Summary'!Q$31,'Financial Statements'!$5:$5,0),FALSE) -> 0 | S42: =VLOOKUP($Y42,'Financial Statements'!$1:$1048576,MATCH('Financial Summary'!S$31,'Financial Statements'!$5:$5,0),FALSE) -> 0 | T42: =VLOOKUP($Y42,'Financial Statements'!$1:$1048576,MATCH('Financial Summary'!T$31,'Financial Statements'!$5:$5,0),FALSE) -> 0 | U42: =VLOOKUP($Y42,'Financial Statements'!$1:$1048576,MATCH('Financial Summary'!U$31,'Financial Statements'!$5:$5,0),FALSE) -> -15.4422 | V42: =VLOOKUP($Y42,'Financial Statements'!$1:$1048576,MATCH('Financial Summary'!V$31,'Financial Statements'!$5:$5,0),FALSE) -> -30.391054 | W42: =VLOOKUP($Y42,'Financial Statements'!$1:$1048576,MATCH('Financial Summary'!W$31,'Financial Statements'!$5:$5,0),FALSE) -> -46.881924 | Y42: Div_paid
A43: NPAT_reported | E43: Reported NPAT | F43: A$m | G43: =VLOOKUP($A43,'Financial Statements'!$1:$1048576,MATCH('Financial Summary'!G$12,'Financial Statements'!$5:$5,0),FALSE) -> 3.9 | H43: =VLOOKUP($A43,'Financial Statements'!$1:$1048576,MATCH('Financial Summary'!H$12,'Financial Statements'!$5:$5,0),FALSE) -> -2.3 | I43: =VLOOKUP($A43,'Financial Statements'!$1:$1048576,MATCH('Financial Summary'!I$12,'Financial Statements'!$5:$5,0),FALSE) -> -13.748 | J43: =VLOOKUP($A43,'Financial Statements'!$1:$1048576,MATCH('Financial Summary'!J$12,'Financial Statements'!$5:$5,0),FALSE) -> 14.476 | K43: =VLOOKUP($A43,'Financial Statements'!$1:$1048576,MATCH('Financial Summary'!K$12,'Financial Statements'!$5:$5,0),FALSE) -> 21.481133 | L43: =VLOOKUP($A43,'Financial Statements'!$1:$1048576,MATCH('Financial Summary'!L$12,'Financial Statements'!$5:$5,0),FALSE) -> 42.275987 | M43: =VLOOKUP($A43,'Financial Statements'!$1:$1048576,MATCH('Financial Summary'!M$12,'Financial Statements'!$5:$5,0),FALSE) -> 65.215889 | O43: Net borrowings | P43: A$m | Q43: =VLOOKUP($Y43,'Financial Statements'!$1:$1048576,MATCH('Financial Summary'!Q$31,'Financial Statements'!$5:$5,0),FALSE)+VLOOKUP($Z$43,'Financial Statements'!$1:$1048576,MATCH('Financial Summary'!Q$12,'Financial Statements'!$5:$5,0),FALSE) -> 0 | S43: =VLOOKUP($Y43,'Financial Statements'!$1:$1048576,MATCH('Financial Summary'!S$31,'Financial Statements'!$5:$5,0),FALSE)+VLOOKUP($Z$43,'Financial Statements'!$1:$1048576,MATCH('Financial Summary'!S$12,'Financial Statements'!$5:$5,0),FALSE) -> -3 | T43: =VLOOKUP($Y43,'Financial Statements'!$1:$1048576,MATCH('Financial Summary'!T$31,'Financial Statements'!$5:$5,0),FALSE)+VLOOKUP($Z$43,'Financial Statements'!$1:$1048576,MATCH('Financial Summary'!T$12,'Financial Statements'!$5:$5,0),FALSE) -> 0 | U43: =VLOOKUP($Y43,'Financial Statements'!$1:$1048576,MATCH('Financial Summary'!U$31,'Financial Statements'!$5:$5,0),FALSE)+VLOOKUP($Z$43,'Financial Statements'!$1:$1048576,MATCH('Financial Summary'!U$12,'Financial Statements'!$5:$5,0),FALSE) -> 0 | V43: =VLOOKUP($Y43,'Financial Statements'!$1:$1048576,MATCH('Financial Summary'!V$31,'Financial Statements'!$5:$5,0),FALSE)+VLOOKUP($Z$43,'Financial Statements'!$1:$1048576,MATCH('Financial Summary'!V$12,'Financial Statements'!$5:$5,0),FALSE) -> 0 | W43: =VLOOKUP($Y43,'Financial Statements'!$1:$1048576,MATCH('Financial Summary'!W$31,'Financial Statements'!$5:$5,0),FALSE)+VLOOKUP($Z$43,'Financial Statements'!$1:$1048576,MATCH('Financial Summary'!W$12,'Financial Statements'!$5:$5,0),FALSE) -> 0 | Y43: Proceeds_borrowing | Z43: Repayment_borrowings
A44: EPS_underlying_diluted | E44: EPS (Underlying, Diluted) | F44: Cents | G44: =VLOOKUP($A44,'Financial Statements'!$1:$1048576,MATCH('Financial Summary'!G$12,'Financial Statements'!$5:$5,0),FALSE) -> 0 | H44: na | I44: =VLOOKUP($A44,'Financial Statements'!$1:$1048576,MATCH('Financial Summary'!I$12,'Financial Statements'!$5:$5,0),FALSE) -> 5.0682905 | J44: =VLOOKUP($A44,'Financial Statements'!$1:$1048576,MATCH('Financial Summary'!J$12,'Financial Statements'!$5:$5,0),FALSE) -> 13.992731 | K44: =VLOOKUP($A44,'Financial Statements'!$1:$1048576,MATCH('Financial Summary'!K$12,'Financial Statements'!$5:$5,0),FALSE) -> 20.283401 | L44: =VLOOKUP($A44,'Financial Statements'!$1:$1048576,MATCH('Financial Summary'!L$12,'Financial Statements'!$5:$5,0),FALSE) -> 39.918788 | M44: =VLOOKUP($A44,'Financial Statements'!$1:$1048576,MATCH('Financial Summary'!M$12,'Financial Statements'!$5:$5,0),FALSE) -> 61.579621 | O44: Other financing | P44: A$m | Q44: =+Q45-Q42-Q43 -> 1.8 | S44: =+S45-S42-S43 -> 257.934 | T44: =+T45-T42-T43 -> 0.679 | U44: =+U45-U42-U43 -> -20.022005 | V44: =+V45-V42-V43 -> -27.771951 | W44: =+W45-W42-W43 -> -36.504038
E45: % change | F45: % | G45: na | H45: =IFERROR(H44/G44-1,"na") -> na | I45: =IFERROR(I44/H44-1,"na") -> na | J45: =IFERROR(J44/I44-1,"na") -> 1.7608384 | K45: =IFERROR(K44/J44-1,"na") -> 0.44956694 | L45: =IFERROR(L44/K44-1,"na") -> 0.96805205 | M45: =IFERROR(M44/L44-1,"na") -> 0.54262252 | O45: Total Financing Cash Flows | P45: A$m | Q45: =VLOOKUP($Y45,'Financial Statements'!$1:$1048576,MATCH('Financial Summary'!Q$31,'Financial Statements'!$5:$5,0),FALSE) -> 1.8 | S45: =VLOOKUP($Y45,'Financial Statements'!$1:$1048576,MATCH('Financial Summary'!S$31,'Financial Statements'!$5:$5,0),FALSE) -> 254.934 | T45: =VLOOKUP($Y45,'Financial Statements'!$1:$1048576,MATCH('Financial Summary'!T$31,'Financial Statements'!$5:$5,0),FALSE) -> 0.679 | U45: =VLOOKUP($Y45,'Financial Statements'!$1:$1048576,MATCH('Financial Summary'!U$31,'Financial Statements'!$5:$5,0),FALSE) -> -35.464206 | V45: =VLOOKUP($Y45,'Financial Statements'!$1:$1048576,MATCH('Financial Summary'!V$31,'Financial Statements'!$5:$5,0),FALSE) -> -58.163005 | W45: =VLOOKUP($Y45,'Financial Statements'!$1:$1048576,MATCH('Financial Summary'!W$31,'Financial Statements'!$5:$5,0),FALSE) -> -83.385961 | Y45: Net_CF_Financing
E46: 3yr CAGR | M46: =+(M44/J44)^(0.333333333333333)-1 -> 0.63874548 | O46: Net change in cash | P46: A$m | Q46: =VLOOKUP($Y46,'Financial Statements'!$1:$1048576,MATCH('Financial Summary'!Q$31,'Financial Statements'!$5:$5,0),FALSE) -> -9.7 | S46: =VLOOKUP($Y46,'Financial Statements'!$1:$1048576,MATCH('Financial Summary'!S$31,'Financial Statements'!$5:$5,0),FALSE) -> -0.584 | T46: =VLOOKUP($Y46,'Financial Statements'!$1:$1048576,MATCH('Financial Summary'!T$31,'Financial Statements'!$5:$5,0),FALSE) -> 23.455 | U46: =VLOOKUP($Y46,'Financial Statements'!$1:$1048576,MATCH('Financial Summary'!U$31,'Financial Statements'!$5:$5,0),FALSE) -> -12.164966 | V46: =VLOOKUP($Y46,'Financial Statements'!$1:$1048576,MATCH('Financial Summary'!V$31,'Financial Statements'!$5:$5,0),FALSE) -> -26.694575 | W46: =VLOOKUP($Y46,'Financial Statements'!$1:$1048576,MATCH('Financial Summary'!W$31,'Financial Statements'!$5:$5,0),FALSE) -> -8.9567467 | Y46: Net_chg_Cash
E48: Network Sales | O48: Margins and returns
E49: Year ended 30 June | F49: Unit | G49: FY22 | H49: FY23 | I49: FY24 | J49: FY25 | K49: FY26e | L49: FY27e | M49: FY28e | O49: Year ended 30 June | P49: Unit | Q49: FY22 | R49: FY23 | S49: FY24e | T49: FY25 | U49: FY26e | V49: FY27e | W49: FY28e
A50: Aust_total_network _sales | E50: Aust Network Sales | F50: A$m | G50: =VLOOKUP($A50,Assumptions!$1:$1048576,MATCH('Financial Summary'!G$12,Assumptions!$5:$5,0),FALSE) -> 535.4 | H50: =VLOOKUP($A50,Assumptions!$1:$1048576,MATCH('Financial Summary'!H$12,Assumptions!$5:$5,0),FALSE) -> 702.9 | I50: =VLOOKUP($A50,Assumptions!$1:$1048576,MATCH('Financial Summary'!I$12,Assumptions!$5:$5,0),FALSE) -> 894.6 | J50: =VLOOKUP($A50,Assumptions!$1:$1048576,MATCH('Financial Summary'!J$12,Assumptions!$5:$5,0),FALSE) -> 1094.6 | K50: =VLOOKUP($A50,Assumptions!$1:$1048576,MATCH('Financial Summary'!K$12,Assumptions!$5:$5,0),FALSE) -> 1314.6094 | L50: =VLOOKUP($A50,Assumptions!$1:$1048576,MATCH('Financial Summary'!L$12,Assumptions!$5:$5,0),FALSE) -> 1573.8672 | M50: =VLOOKUP($A50,Assumptions!$1:$1048576,MATCH('Financial Summary'!M$12,Assumptions!$5:$5,0),FALSE) -> 1879.0226 | O50: EBITDA Segment Underlying Margin | P50: % | Q50: =+G24/G17 -> 0.083372231 | R50: =+H24/H17 -> 0.095592486 | S50: =+I24/I17 -> 0.10695194 | T50: =+J24/J17 -> 0.11272925 | U50: =+K24/K17 -> 0.11976295 | V50: =+L24/L17 -> 0.14672288 | W50: =+M24/M17 -> 0.16741233
A51: Aust_Network_sales_gth | E51: Aust Network Sales growth | F51: % | G51: =VLOOKUP($A51,Assumptions!$1:$1048576,MATCH('Financial Summary'!G$12,Assumptions!$5:$5,0),FALSE) -> 0 | H51: =VLOOKUP($A51,Assumptions!$1:$1048576,MATCH('Financial Summary'!H$12,Assumptions!$5:$5,0),FALSE) -> 0.31285021 | I51: =VLOOKUP($A51,Assumptions!$1:$1048576,MATCH('Financial Summary'!I$12,Assumptions!$5:$5,0),FALSE) -> 0.27272727 | J51: =VLOOKUP($A51,Assumptions!$1:$1048576,MATCH('Financial Summary'!J$12,Assumptions!$5:$5,0),FALSE) -> 0.2235636 | K51: =VLOOKUP($A51,Assumptions!$1:$1048576,MATCH('Financial Summary'!K$12,Assumptions!$5:$5,0),FALSE) -> 0.20099522 | L51: =VLOOKUP($A51,Assumptions!$1:$1048576,MATCH('Financial Summary'!L$12,Assumptions!$5:$5,0),FALSE) -> 0.19721284 | M51: =VLOOKUP($A51,Assumptions!$1:$1048576,MATCH('Financial Summary'!M$12,Assumptions!$5:$5,0),FALSE) -> 0.19388889 | O51: EBITDA Normalised Margin | P51: % | Q51: =G28/G17 -> 0.11669368 | R51: =H28/H17 -> 0.1058526 | S51: =I28/I17 -> 0.12263512 | T51: =J28/J17 -> 0.13970938 | U51: =K28/K17 -> 0.14281201 | V51: =L28/L17 -> 0.17334953 | W51: =M28/M17 -> 0.19535877
A52: SG_network_sales | E52: Singapore Network Sales | F52: A$m | G52: =VLOOKUP($A52,Assumptions!$1:$1048576,MATCH('Financial Summary'!G$12,Assumptions!$5:$5,0),FALSE) -> 31.4 | H52: =VLOOKUP($A52,Assumptions!$1:$1048576,MATCH('Financial Summary'!H$12,Assumptions!$5:$5,0),FALSE) -> 43.1 | I52: =VLOOKUP($A52,Assumptions!$1:$1048576,MATCH('Financial Summary'!I$12,Assumptions!$5:$5,0),FALSE) -> 46.4 | J52: =VLOOKUP($A52,Assumptions!$1:$1048576,MATCH('Financial Summary'!J$12,Assumptions!$5:$5,0),FALSE) -> 64.7 | K52: =VLOOKUP($A52,Assumptions!$1:$1048576,MATCH('Financial Summary'!K$12,Assumptions!$5:$5,0),FALSE) -> 74.745526 | L52: =VLOOKUP($A52,Assumptions!$1:$1048576,MATCH('Financial Summary'!L$12,Assumptions!$5:$5,0),FALSE) -> 83.357511 | M52: =VLOOKUP($A52,Assumptions!$1:$1048576,MATCH('Financial Summary'!M$12,Assumptions!$5:$5,0),FALSE) -> 89.064294 | O52: EBIT Margin | P52: % | Q52: =G31/G17 -> 0.038897893 | R52: =H31/H17 -> 0.013728324 | S52: =I31/I17 -> 0.037361258 | T52: =J31/J17 -> 0.054977953 | U52: =K31/K17 -> 0.061362391 | V52: =L31/L17 -> 0.092720153 | W52: =M31/M17 -> 0.11632327
A53: SG_network_sales % gth | E53: Singapore Network Sales growth | F53: % | G53: =VLOOKUP($A53,Assumptions!$1:$1048576,MATCH('Financial Summary'!G$12,Assumptions!$5:$5,0),FALSE) -> 0.42727273 | H53: =VLOOKUP($A53,Assumptions!$1:$1048576,MATCH('Financial Summary'!H$12,Assumptions!$5:$5,0),FALSE) -> 0.37261146 | I53: =VLOOKUP($A53,Assumptions!$1:$1048576,MATCH('Financial Summary'!I$12,Assumptions!$5:$5,0),FALSE) -> 0.076566125 | J53: =VLOOKUP($A53,Assumptions!$1:$1048576,MATCH('Financial Summary'!J$12,Assumptions!$5:$5,0),FALSE) -> 0.39439655 | K53: =VLOOKUP($A53,Assumptions!$1:$1048576,MATCH('Financial Summary'!K$12,Assumptions!$5:$5,0),FALSE) -> 0.15526316 | L53: =VLOOKUP($A53,Assumptions!$1:$1048576,MATCH('Financial Summary'!L$12,Assumptions!$5:$5,0),FALSE) -> 0.11521739 | M53: =VLOOKUP($A53,Assumptions!$1:$1048576,MATCH('Financial Summary'!M$12,Assumptions!$5:$5,0),FALSE) -> 0.068461538 | O53: NPAT Margin | P53: % | Q53: =G38/G17 -> 0.017287952 | R53: =H38/H17 -> 0.01083815 | S53: =I38/I17 -> 0.015488647 | T53: =J38/J17 -> 0.031643232 | U53: =K38/K17 -> 0.035942307 | V53: =L38/L17 -> 0.058306812 | W53: =M38/M17 -> 0.074186069
A54: JP_network_sales | E54: Japan Network Sales | F54: A$m | G54: =VLOOKUP($A54,Assumptions!$1:$1048576,MATCH('Financial Summary'!G$12,Assumptions!$5:$5,0),FALSE) -> 5.8 | H54: =VLOOKUP($A54,Assumptions!$1:$1048576,MATCH('Financial Summary'!H$12,Assumptions!$5:$5,0),FALSE) -> 7 | I54: =VLOOKUP($A54,Assumptions!$1:$1048576,MATCH('Financial Summary'!I$12,Assumptions!$5:$5,0),FALSE) -> 7.9 | J54: =VLOOKUP($A54,Assumptions!$1:$1048576,MATCH('Financial Summary'!J$12,Assumptions!$5:$5,0),FALSE) -> 9.1 | K54: =VLOOKUP($A54,Assumptions!$1:$1048576,MATCH('Financial Summary'!K$12,Assumptions!$5:$5,0),FALSE) -> 10.465 | L54: =VLOOKUP($A54,Assumptions!$1:$1048576,MATCH('Financial Summary'!L$12,Assumptions!$5:$5,0),FALSE) -> 12.732417 | M54: =VLOOKUP($A54,Assumptions!$1:$1048576,MATCH('Financial Summary'!M$12,Assumptions!$5:$5,0),FALSE) -> 14.705941 | O54: Group G&A (% of Revenue) | P54: % | Q54: =-VLOOKUP($Y$54,Assumptions!$1:$1048576,MATCH('Financial Summary'!G$12,Assumptions!$5:$5,0),FALSE)/VLOOKUP($Z$54,Assumptions!$1:$1048576,MATCH('Financial Summary'!G$12,Assumptions!$5:$5,0),FALSE) -> 0.064684403 | R54: =-VLOOKUP($Y$54,Assumptions!$1:$1048576,MATCH('Financial Summary'!H$12,Assumptions!$5:$5,0),FALSE)/VLOOKUP($Z$54,Assumptions!$1:$1048576,MATCH('Financial Summary'!H$12,Assumptions!$5:$5,0),FALSE) -> 0.066007905 | S54: =-VLOOKUP($Y$54,Assumptions!$1:$1048576,MATCH('Financial Summary'!I$12,Assumptions!$5:$5,0),FALSE)/VLOOKUP($Z$54,Assumptions!$1:$1048576,MATCH('Financial Summary'!I$12,Assumptions!$5:$5,0),FALSE) -> 0.072105866 | T54: =-VLOOKUP($Y$54,Assumptions!$1:$1048576,MATCH('Financial Summary'!J$12,Assumptions!$5:$5,0),FALSE)/VLOOKUP($Z$54,Assumptions!$1:$1048576,MATCH('Financial Summary'!J$12,Assumptions!$5:$5,0),FALSE) -> 0.0723361 | U54: =-VLOOKUP($Y$54,Assumptions!$1:$1048576,MATCH('Financial Summary'!K$12,Assumptions!$5:$5,0),FALSE)/VLOOKUP($Z$54,Assumptions!$1:$1048576,MATCH('Financial Summary'!K$12,Assumptions!$5:$5,0),FALSE) -> 0.067079358 | V54: =-VLOOKUP($Y$54,Assumptions!$1:$1048576,MATCH('Financial Summary'!L$12,Assumptions!$5:$5,0),FALSE)/VLOOKUP($Z$54,Assumptions!$1:$1048576,MATCH('Financial Summary'!L$12,Assumptions!$5:$5,0),FALSE) -> 0.06159536 | W54: =-VLOOKUP($Y$54,Assumptions!$1:$1048576,MATCH('Financial Summary'!M$12,Assumptions!$5:$5,0),FALSE)/VLOOKUP($Z$54,Assumptions!$1:$1048576,MATCH('Financial Summary'!M$12,Assumptions!$5:$5,0),FALSE) -> 0.056854564 | Y54: Total_G&A_expense | Z54: Total_network_sales
A55: JP_network_sales % gth | E55: Japan Network Sales growth | F55: % | G55: =VLOOKUP($A55,Assumptions!$1:$1048576,MATCH('Financial Summary'!G$12,Assumptions!$5:$5,0),FALSE) -> 0.16 | H55: =VLOOKUP($A55,Assumptions!$1:$1048576,MATCH('Financial Summary'!H$12,Assumptions!$5:$5,0),FALSE) -> 0.20689655 | I55: =VLOOKUP($A55,Assumptions!$1:$1048576,MATCH('Financial Summary'!I$12,Assumptions!$5:$5,0),FALSE) -> 0.12857143 | J55: =VLOOKUP($A55,Assumptions!$1:$1048576,MATCH('Financial Summary'!J$12,Assumptions!$5:$5,0),FALSE) -> 0.15189873 | K55: =VLOOKUP($A55,Assumptions!$1:$1048576,MATCH('Financial Summary'!K$12,Assumptions!$5:$5,0),FALSE) -> 0.15 | L55: =VLOOKUP($A55,Assumptions!$1:$1048576,MATCH('Financial Summary'!L$12,Assumptions!$5:$5,0),FALSE) -> 0.21666667 | M55: =VLOOKUP($A55,Assumptions!$1:$1048576,MATCH('Financial Summary'!M$12,Assumptions!$5:$5,0),FALSE) -> 0.155 | O55: ROA | P55: % | Q55: nm | R55: nm | S55: =I38/S19 -> 0.0085418943 | T55: =J38/AVERAGE(S19:T19) -> 0.020510798 | U55: =K38/AVERAGE(T19:U19) -> 0.026378677 | V55: =L38/AVERAGE(U19:V19) -> 0.047675719 | W55: =M38/AVERAGE(V19:W19) -> 0.067051659
A56: US_network_sales | E56: US Network Sales | F56: A$m | G56: =VLOOKUP($A56,Assumptions!$1:$1048576,MATCH('Financial Summary'!G$12,Assumptions!$5:$5,0),FALSE) -> 2.5 | H56: =VLOOKUP($A56,Assumptions!$1:$1048576,MATCH('Financial Summary'!H$12,Assumptions!$5:$5,0),FALSE) -> 6 | I56: =VLOOKUP($A56,Assumptions!$1:$1048576,MATCH('Financial Summary'!I$12,Assumptions!$5:$5,0),FALSE) -> 10.8 | J56: =VLOOKUP($A56,Assumptions!$1:$1048576,MATCH('Financial Summary'!J$12,Assumptions!$5:$5,0),FALSE) -> 12.2 | K56: =VLOOKUP($A56,Assumptions!$1:$1048576,MATCH('Financial Summary'!K$12,Assumptions!$5:$5,0),FALSE) -> 17.0495 | L56: =VLOOKUP($A56,Assumptions!$1:$1048576,MATCH('Financial Summary'!L$12,Assumptions!$5:$5,0),FALSE) -> 24.78735 | M56: =VLOOKUP($A56,Assumptions!$1:$1048576,MATCH('Financial Summary'!M$12,Assumptions!$5:$5,0),FALSE) -> 34.70229 | O56: ROE | P56: % | Q56: nm | R56: nm | S56: =I38/S26 -> 0.015969874 | T56: =J38/AVERAGE(S26:T26) -> 0.040373081 | U56: =K38/AVERAGE(T26:U26) -> 0.055413378 | V56: =L38/AVERAGE(U26:V26) -> 0.10422241 | W56: =M38/AVERAGE(V26:W26) -> 0.15174961
A57: US_Network_sales_gth | E57: US Network Sales growth | F57: % | G57: =VLOOKUP($A57,Assumptions!$1:$1048576,MATCH('Financial Summary'!G$12,Assumptions!$5:$5,0),FALSE) -> 0 | H57: =VLOOKUP($A57,Assumptions!$1:$1048576,MATCH('Financial Summary'!H$12,Assumptions!$5:$5,0),FALSE) -> 1.4 | I57: =VLOOKUP($A57,Assumptions!$1:$1048576,MATCH('Financial Summary'!I$12,Assumptions!$5:$5,0),FALSE) -> 0.8 | J57: =VLOOKUP($A57,Assumptions!$1:$1048576,MATCH('Financial Summary'!J$12,Assumptions!$5:$5,0),FALSE) -> 0.12962963 | K57: =VLOOKUP($A57,Assumptions!$1:$1048576,MATCH('Financial Summary'!K$12,Assumptions!$5:$5,0),FALSE) -> 0.3975 | L57: =VLOOKUP($A57,Assumptions!$1:$1048576,MATCH('Financial Summary'!L$12,Assumptions!$5:$5,0),FALSE) -> 0.45384615 | M57: =VLOOKUP($A57,Assumptions!$1:$1048576,MATCH('Financial Summary'!M$12,Assumptions!$5:$5,0),FALSE) -> 0.4
E59: Key Metrics | O59: Valuation
E60: Year ended 30 June | F60: Unit | G60: FY22 | H60: FY23 | I60: FY24 | J60: FY25 | K60: FY26e | L60: FY27e | M60: FY28e | O60: Year ended 30 June | P60: Unit | Q60: FY22 | R60: FY23 | S60: FY24 | T60: FY25 | U60: FY26e | V60: FY27e | W60: FY28e
A61: Aust_LFL | E61: Aust SSS growth | F61: % | G61: =VLOOKUP($A61,Assumptions!$1:$1048576,MATCH('Financial Summary'!G$12,Assumptions!$5:$5,0),FALSE) -> 0.182 | H61: =VLOOKUP($A61,Assumptions!$1:$1048576,MATCH('Financial Summary'!H$12,Assumptions!$5:$5,0),FALSE) -> 0.15 | I61: =VLOOKUP($A61,Assumptions!$1:$1048576,MATCH('Financial Summary'!I$12,Assumptions!$5:$5,0),FALSE) -> 0.081 | J61: =VLOOKUP($A61,Assumptions!$1:$1048576,MATCH('Financial Summary'!J$12,Assumptions!$5:$5,0),FALSE) -> 0.096 | K61: =VLOOKUP($A61,Assumptions!$1:$1048576,MATCH('Financial Summary'!K$12,Assumptions!$5:$5,0),FALSE) -> 0.06 | L61: =VLOOKUP($A61,Assumptions!$1:$1048576,MATCH('Financial Summary'!L$12,Assumptions!$5:$5,0),FALSE) -> 0.05 | M61: =VLOOKUP($A61,Assumptions!$1:$1048576,MATCH('Financial Summary'!M$12,Assumptions!$5:$5,0),FALSE) -> 0.05 | O61: P/E | P61: x | Q61: nm | R61: nm | S61: =$F$7/(I$44/100) -> 463.66719 | T61: =$F$7/(J$44/100) -> 167.94434 | U61: =$F$7/(K$44/100) -> 115.85828 | V61: =$F$7/(L$44/100) -> 58.869523 | W61: =$F$7/(M$44/100) -> 38.161976
A62: Aust_total_network_gth | E62: Aust Network growth (No. Stores) | F62: % | G62: =VLOOKUP($A62,Assumptions!$1:$1048576,MATCH('Financial Summary'!G$12,Assumptions!$5:$5,0),FALSE) -> 0 | H62: =VLOOKUP($A62,Assumptions!$1:$1048576,MATCH('Financial Summary'!H$12,Assumptions!$5:$5,0),FALSE) -> 0.14 | I62: =VLOOKUP($A62,Assumptions!$1:$1048576,MATCH('Financial Summary'!I$12,Assumptions!$5:$5,0),FALSE) -> 0.13450292 | J62: =VLOOKUP($A62,Assumptions!$1:$1048576,MATCH('Financial Summary'!J$12,Assumptions!$5:$5,0),FALSE) -> 0.15463918 | K62: =VLOOKUP($A62,Assumptions!$1:$1048576,MATCH('Financial Summary'!K$12,Assumptions!$5:$5,0),FALSE) -> 0.14285714 | L62: =VLOOKUP($A62,Assumptions!$1:$1048576,MATCH('Financial Summary'!L$12,Assumptions!$5:$5,0),FALSE) -> 0.13671875 | M62: =VLOOKUP($A62,Assumptions!$1:$1048576,MATCH('Financial Summary'!M$12,Assumptions!$5:$5,0),FALSE) -> 0.13745704 | O62: EV/EBITDA (Segment Underlying) | P62: x | Q62: nm | R62: nm | S62: =S68/I24 -> 53.47287 | T62: =T68/J24 -> 39.779108 | U62: =U68/K24 -> 29.509682 | V62: =V68/L24 -> 20.105747 | W62: =W68/M24 -> 14.594487
A63: Aust_Corp_EBITDA_margin | E63: Aust Corporate Restaurant EBITDA margin | F63: % | G63: =VLOOKUP($A63,Assumptions!$1:$1048576,MATCH('Financial Summary'!G$12,Assumptions!$5:$5,0),FALSE) -> 0.141 | H63: =VLOOKUP($A63,Assumptions!$1:$1048576,MATCH('Financial Summary'!H$12,Assumptions!$5:$5,0),FALSE) -> 0.144 | I63: =VLOOKUP($A63,Assumptions!$1:$1048576,MATCH('Financial Summary'!I$12,Assumptions!$5:$5,0),FALSE) -> 0.174 | J63: =VLOOKUP($A63,Assumptions!$1:$1048576,MATCH('Financial Summary'!J$12,Assumptions!$5:$5,0),FALSE) -> 0.179 | K63: =VLOOKUP($A63,Assumptions!$1:$1048576,MATCH('Financial Summary'!K$12,Assumptions!$5:$5,0),FALSE) -> 0.1835 | L63: =VLOOKUP($A63,Assumptions!$1:$1048576,MATCH('Financial Summary'!L$12,Assumptions!$5:$5,0),FALSE) -> 0.19022928 | M63: =VLOOKUP($A63,Assumptions!$1:$1048576,MATCH('Financial Summary'!M$12,Assumptions!$5:$5,0),FALSE) -> 0.19613578 | O63: EV/EBITDA (Normalised) | P63: x | Q63: nm | R63: nm | S63: =S68/I28 -> 46.634498 | T63: =T68/J28 -> 32.097122 | U63: =U68/K28 -> 24.746983 | V63: =V68/L28 -> 17.017486 | W63: =W68/M28 -> 12.506718
O68: Enterprise value | S68: =$F$8+S27 -> 2087.3135 | T68: =$F$8+T27 -> 2100.0505 | U68: =$F$8+U27 -> 2112.2154 | V68: =$F$8+V27 -> 2138.91 | W68: =$F$8+W27 -> 2147.8668

Sheet Financial Statements
B2: Guzman Y Gomez (GYG.AX)
B3: Financial statements
F4: Pro forma | G4: Pro forma | H4: Pro forma | I4: Pro forma | J4: Pro forma
B5: Year ended 30 June | C5: unit | D5: FY20 | E5: FY21 | F5: FY22 | G5: 1H23 | H5: 2H23 | I5: FY23 | J5: 1H24 | K5: 2H24 | L5: FY24 | M5: 1H25 | N5: 2H25 | O5: FY25 | P5: 1H26e | Q5: 2H26e | R5: FY26e | S5: 1H27e | T5: 2H27e | U5: FY27e | V5: 1H28e | W5: 2H28e | X5: FY28e | Y5: 1H29e | Z5: 2H29e | AA5: FY29e | AB5: =+Assumptions!AB5 -> 1H30e | AC5: =+Assumptions!AC5 -> 2H30e | AD5: =+Assumptions!AD5 -> FY30e | AE5: =+Assumptions!AE5 -> 1H31e | AF5: =+Assumptions!AF5 -> 2H31e | AG5: =+Assumptions!AG5 -> FY31e | AH5: =+Assumptions!AH5 -> 1H32e | AI5: =+Assumptions!AI5 -> 2H32e | ... AP5: =+Assumptions!AP5 -> FY34e | AQ5: 1H35e | AR5: 2H35e | AS5: FY35e | AT5: 1H36e | AU5: 2H36e | AV5: FY36e
A7: l | B7: Income Statement
B9: Revenue
B10: Australia | C10: A$m | F10: =+Assumptions!F18 -> 168.027 | G10: =+Assumptions!G18 -> 119.344 | H10: =+Assumptions!H18 -> 132.0375 | I10: =+Assumptions!I18 -> 251.3815 | J10: =+Assumptions!J18 -> 161.968 | K10: =+Assumptions!K18 -> 167.574 | L10: =+Assumptions!L18 -> 329.542 | M10: =+Assumptions!M18 -> 207.992 | ... AV10: =+Assumptions!AV18 -> 2216.8064
B11: Singapore | C11: A$m | F11: =+Assumptions!F19 -> 1.099 | G11: =+Assumptions!G19 -> 0.7525 | H11: =+Assumptions!H19 -> 0.756 | I11: =+Assumptions!I19 -> 1.5085 | J11: =+Assumptions!J19 -> 0.777 | K11: =+Assumptions!K19 -> 0.847 | L11: =+Assumptions!L19 -> 1.624 | M11: =+Assumptions!M19 -> 1.057 | ... AV11: =+Assumptions!AV19 -> 4.9336368
B12: Japan | C12: A$m | F12: =+Assumptions!F20 -> 0.174 | G12: =+Assumptions!G20 -> 0.096 | H12: =+Assumptions!H20 -> 0.114 | I12: =+Assumptions!I20 -> 0.21 | J12: =+Assumptions!J20 -> 0.126 | K12: =+Assumptions!K20 -> 0.111 | L12: =+Assumptions!L20 -> 0.237 | M12: =+Assumptions!M20 -> 0.138 | ... AV12: =+Assumptions!AV20 -> 0.90244992
B13: US | C13: A$m | F13: =+Assumptions!F21 -> 2.5 | G13: =+Assumptions!G21 -> 1.5 | H13: =+Assumptions!H21 -> 4.5 | I13: =+Assumptions!I21 -> 6 | J13: =+Assumptions!J21 -> 5.6 | K13: =+Assumptions!K21 -> 5.2 | L13: =+Assumptions!L21 -> 10.8 | M13: =+Assumptions!M21 -> 3.336 | ... AV13: =+Assumptions!AV21 -> 37.702678
A14: Other_revenue | B14: Other | C14: A$m | F14: =+Assumptions!F178 -> 13.3 | G14: =+Assumptions!G178 -> 8.7 | H14: =+Assumptions!H178 -> 9 | I14: =+Assumptions!I178 -> 17.7 | J14: =+Assumptions!J178 -> 11.7 | K14: =+Assumptions!K178 -> 11.074 | L14: =+Assumptions!L178 -> 22.774 | M14: =+Assumptions!M178 -> 14.711 | ... AV14: =+Assumptions!AV178 -> 122.41357
A15: Total_revenue | B15: Total revenue | C15: A$m | F15: =SUM(F10:F14) -> 185.1 | G15: =SUM(G10:G14) -> 130.3925 | H15: =SUM(H10:H14) -> 146.4075 | I15: =SUM(I10:I14) -> 276.8 | J15: =SUM(J10:J14) -> 180.171 | K15: =SUM(K10:K14) -> 184.806 | L15: =SUM(L10:L14) -> 364.977 | M15: =SUM(M10:M14) -> 227.234 | ... AV15: =SUM(AV10:AV14) -> 2382.7588
B16: % change | C16: % | I16: =I15/F15-1 -> 0.49540789 | J16: =J15/G15-1 -> 0.38175892 | K16: =K15/H15-1 -> 0.2622714 | L16: =L15/I15-1 -> 0.31855853 | M16: =M15/J15-1 -> 0.26121296 | N16: =N15/K15-1 -> 0.30450851 | O16: =O15/L15-1 -> 0.28313565 | P16: =P15/M15-1 -> 0.25576302 | ... AV16: =AV15/AS15-1 -> 0.087430324
A18: Total_COGS | B18: Cost of food and packaging | C18: A$m | F18: =Assumptions!F208 -> -44.2 | G18: =Assumptions!G208 -> -32.9 | H18: =Assumptions!H208 -> -37.5 | I18: =Assumptions!I208 -> -70.4 | J18: =Assumptions!J208 -> -43.2 | K18: =Assumptions!K208 -> -44.38 | L18: =Assumptions!L208 -> -87.58 | M18: =Assumptions!M208 -> -55.071 | N18: =Assumptions!N208 -> -58.877 | O18: =+M18+N18 -> -113.948 | P18: -74.560761 | Q18: -83.228511 | R18: =+P18+Q18 -> -157.78927 | S18: -90.509341 | T18: -101.37453 | U18: =+S18+T18 -> -191.88387 | V18: -110.54825 | W18: -122.53885 | X18: =+V18+W18 -> -233.0871 | Y18: -130.43738 | Z18: -143.82866 | AA18: =+Y18+Z18 -> -274.26604 | AB18: -151.42874 | AC18: -165.47742 | AD18: =+AB18+AC18 -> -316.90616 | AE18: -173.50019 | AF18: -189.09403 | AG18: =+AE18+AF18 -> -362.59422 | AH18: -197.40082 | AI18: -214.66039 | AJ18: =+AH18+AI18 -> -412.06122 | AK18: -223.25829 | AL18: -242.31212 | AM18: =+AK18+AL18 -> -465.5704 | AN18: -246.21344 | AO18: -265.79388 | AP18: =+AN18+AO18 -> -512.00732 | AQ18: -268.41787 | AR18: -289.43619 | AS18: =+AQ18+AR18 -> -557.85407 | AT18: -291.73876 | AU18: -314.26401 | AV18: =+AT18+AU18 -> -606.00277
B19: % change | C19: % | I19: =I18/F18-1 -> 0.59276018 | J19: =J18/G18-1 -> 0.31306991 | K19: =K18/H18-1 -> 0.18346667 | L19: =L18/I18-1 -> 0.24403409 | M19: =M18/J18-1 -> 0.27479167 | N19: =N18/K18-1 -> 0.32665615 | O19: =O18/L18-1 -> 0.3010733 | P19: =P18/M18-1 -> 0.35390243 | ... AV19: =AV18/AS18-1 -> 0.086310575
B21: Gross Profit | C21: A$m | F21: =F15+F18 -> 140.9 | G21: =G15+G18 -> 97.4925 | H21: =H15+H18 -> 108.9075 | I21: =I15+I18 -> 206.4 | J21: =J15+J18 -> 136.971 | K21: =K15+K18 -> 140.426 | L21: =L15+L18 -> 277.397 | M21: =M15+M18 -> 172.163 | ... AV21: =AV15+AV18 -> 1776.756
B22: % change | C22: % | I22: =I21/F21-1 -> 0.4648687 | J22: =J21/G21-1 -> 0.40493884 | K22: =K21/H21-1 -> 0.28940615 | L22: =L21/I21-1 -> 0.34397771 | M22: =M21/J21-1 -> 0.2569303 | N22: =N21/K21-1 -> 0.29750901 | O22: =O21/L21-1 -> 0.27747236 | P22: =P21/M21-1 -> 0.22437046 | ... AV22: =AV21/AS21-1 -> 0.087812768
B23: % margin | C23: % | I23: =+I21/I15 -> 0.74566474 | J23: =+J21/J15 -> 0.76022778 | K23: =+K21/K15 -> 0.75985628 | L23: =+L21/L15 -> 0.76003967 | M23: =+M21/M15 -> 0.7576463 | N23: =+N21/N15 -> 0.75577918 | O23: =+O21/O15 -> 0.75668514 | P23: =+P21/P15 -> 0.73870606 | ... AV23: =+AV21/AV15 -> 0.74567179
A25: Total_OpEx | B25: Total OPEX | C25: A$m | F25: =+Assumptions!F211+Assumptions!F214+Assumptions!F217+Assumptions!F220 -> -119.3 | G25: =+Assumptions!G211+Assumptions!G214+Assumptions!G217+Assumptions!G220 -> -82.9 | H25: =+Assumptions!H211+Assumptions!H214+Assumptions!H217+Assumptions!H220 -> -94.2 | I25: =+Assumptions!I211+Assumptions!I214+Assumptions!I217+Assumptions!I220 -> -177.1 | J25: =+Assumptions!J211+Assumptions!J214+Assumptions!J217+Assumptions!J220 -> -111.4 | K25: =+Assumptions!K211+Assumptions!K214+Assumptions!K217+Assumptions!K220 -> -121.238 | L25: =+Assumptions!L211+Assumptions!L214+Assumptions!L217+Assumptions!L220 -> -232.638 | M25: =+Assumptions!M211+Assumptions!M214+Assumptions!M217+Assumptions!M220 -> -140.481 | ... O25: =+Assumptions!O211+Assumptions!O214+Assumptions!O217+Assumptions!O220 -> -288.939 | P25: =+P29-P21 -> -170.2608 | Q25: =+Q29-Q21 -> -184.09856 | R25: =+R29-R21 -> -354.5142 | S25: =+S29-S21 -> -195.6952 | T25: =+T29-T21 -> -211.56317 | U25: =+U29-U21 -> -407.48803 | V25: =+V29-V21 -> -227.18235 | W25: =+W29-W21 -> -246.63372 | ... AV25: =+AV29-AV21 -> -1138.4828
B26: % change | I26: =I25/F25-1 -> 0.48449288 | J26: =J25/G25-1 -> 0.3437877 | K26: =K25/H25-1 -> 0.2870276 | L26: =L25/I25-1 -> 0.31359684 | M26: =M25/J25-1 -> 0.26105027 | N26: =N25/K25-1 -> 0.22451707 | O26: =O25/L25-1 -> 0.24201119 | P26: =P25/M25-1 -> 0.21198454 | ... AV26: =AV25/AS25-1 -> 0.083778392
A29: EBITDA_Normalised | B29: EBITDA (normalised) | C29: A$m | F29: =+F21+F25 -> 21.6 | G29: =+G21+G25 -> 14.5925 | H29: =+H21+H25 -> 14.7075 | I29: =+I21+I25 -> 29.3 | J29: =+J21+J25 -> 25.571 | K29: =+K21+K25 -> 19.188 | L29: =+L21+L25 -> 44.759 | M29: =+M21+M25 -> 31.682 | ... O29: =+O21+O25 -> 65.428 | P29: =+Assumptions!P285 -> 40.530492 | Q29: =+Assumptions!Q285 -> 44.821949 | R29: =+Assumptions!R285 -> 85.352441 | S29: =+Assumptions!S285 -> 57.927654 | T29: =+Assumptions!T285 -> 67.761302 | U29: =+Assumptions!U285 -> 125.68896 | V29: =+Assumptions!V285 -> 84.192956 | W29: =+Assumptions!W285 -> 87.544088 | ... AV29: =+Assumptions!AV285 -> 638.27316
B30: % change | I30: =I29/F29-1 -> 0.35648148 | J30: =J29/G29-1 -> 0.75233853 | K30: =K29/H29-1 -> 0.30464049 | L30: =L29/I29-1 -> 0.52761092 | M30: =M29/J29-1 -> 0.23898166 | N30: =N29/K29-1 -> 0.75870336 | O30: =O29/L29-1 -> 0.46178422 | P30: =P29/M29-1 -> 0.27929084 | ... AV30: =AV29/AS29-1 -> 0.095083918
B31: % margin | I31: =I29/I$15 -> 0.1058526 | J31: =J29/J$15 -> 0.14192628 | K31: =K29/K$15 -> 0.1038278 | L31: =L29/L$15 -> 0.12263512 | M31: =M29/M$15 -> 0.13942456 | N31: =N29/N$15 -> 0.13997785 | O31: =O29/O$15 -> 0.13970938 | P31: =P29/P$15 -> 0.1420368 | ... AV31: =AV29/AV$15 -> 0.2678715
B33: Depreciation | C33: A$m | F33: =-Assumptions!F341+Assumptions!F357 -> -12 | G33: =-Assumptions!G341+Assumptions!G357 -> -9.35 | H33: =-Assumptions!H341+Assumptions!H357 -> -9.35 | I33: =-Assumptions!I341+Assumptions!I357 -> -18.7 | J33: =-Assumptions!J341 -> -6.48 | K33: =-Assumptions!K341+Assumptions!K357 -> -12.1035 | L33: =-Assumptions!L341+Assumptions!L357 -> -24.207 | M33: =-Assumptions!M341+Assumptions!M357 -> -15.575 | N33: =-Assumptions!N341+Assumptions!N357 -> -17.595 | O33: =-Assumptions!O341+Assumptions!O357 -> -33.17 | P33: =-Assumptions!P341+Assumptions!P357 -> -20.026861 | Q33: =-Assumptions!Q341+Assumptions!Q357 -> -21.26085 | R33: =-Assumptions!R341+Assumptions!R357 -> -41.287711 | ... AV33: =-Assumptions!AV341+Assumptions!AV357 -> -145.39073
B34: Amortisation | C34: A$m | F34: =Assumptions!F371 -> -2.4 | G34: =Assumptions!G371 -> -3.2 | H34: =Assumptions!H371 -> -3.6 | I34: =Assumptions!I371 -> -6.8 | J34: =Assumptions!J371 -> -3.8 | K34: =Assumptions!K371 -> -3.116 | L34: =Assumptions!L371 -> -6.916 | M34: =Assumptions!M371 -> -3.505 | ... AV34: =Assumptions!AV371 -> -18.821343
A35: Total_D&A | B35: D&A | C35: A$m | F35: =+F33+F34 -> -14.4 | G35: =+G33+G34 -> -12.55 | H35: =+H33+H34 -> -12.95 | I35: =+I33+I34 -> -25.5 | J35: =+J33+J34 -> -10.28 | K35: =+K33+K34 -> -15.2195 | L35: =+L33+L34 -> -31.123 | M35: =+M33+M34 -> -19.08 | ... AV35: =+AV33+AV34 -> -164.21207
A38: Total_EBIT | B38: EBIT | C38: A$m | F38: =+F29+F35 -> 7.2 | G38: =+G29+G35 -> 2.0425 | H38: =+H29+H35 -> 1.7575 | I38: =+I29+I35 -> 3.8 | J38: =+J29+J35 -> 15.291 | K38: =+K29+K35 -> 3.9685 | L38: =+L29+L35 -> 13.636 | M38: =+M29+M35 -> 12.602 | ... AV38: =+AV29+AV35 -> 474.06108
B39: % change | I39: =I38/F38-1 -> -0.47222222 | J39: =J38/G38-1 -> 6.4864137 | K39: =K38/H38-1 -> 1.258037 | L39: =L38/I38-1 -> 2.5884211 | M39: =M38/J38-1 -> -0.17585508 | N39: =N38/K38-1 -> 2.3123346 | O39: =O38/L38-1 -> 0.88816368 | P39: =P38/M38-1 -> 0.3406151 | ... AV39: =AV38/AS38-1 -> 0.10324529
A40: Total_EBIT_margin | B40: % margin | I40: =I38/I$15 -> 0.013728324 | J40: =J38/J$15 -> 0.084869374 | K40: =K38/K$15 -> 0.02147387 | L40: =L38/L$15 -> 0.037361258 | M40: =M38/M$15 -> 0.05545825 | N40: =N38/N$15 -> 0.054525243 | O40: =O38/O$15 -> 0.054977953 | P40: =P38/P$15 -> 0.059205572 | ... AV40: =AV38/AV$15 -> 0.19895471
B42: Finance income | C42: A$m | F42: =+Assumptions!F472 -> 4.4 | G42: =+Assumptions!G472 -> 0 | H42: =+Assumptions!H472 -> 0 | I42: =+Assumptions!I472 -> 12.4 | J42: =+Assumptions!J472 -> 8.1705 | K42: =+Assumptions!K472 -> 8.1705 | L42: =+Assumptions!L472 -> 16.341 | M42: =+Assumptions!M472 -> 11.445 | ... AV42: =+Assumptions!AV472 -> 43.379628
B43: Finance costs | C43: A$m | F43: =+Assumptions!F473 -> -6 | G43: =+Assumptions!G473 -> 0 | H43: =+Assumptions!H473 -> 0 | I43: =+Assumptions!I473 -> -8.5 | J43: =+Assumptions!J473 -> -6.862 | K43: =+Assumptions!K473 -> -6.862 | L43: =+Assumptions!L473 -> -13.724 | M43: =+Assumptions!M473 -> -8.752 | ... AV43: =+Assumptions!AV473 -> -38.591694
A44: Total_Net_Int | B44: Net interest expense | C44: A$m | F44: =+F42+F43 -> -1.6 | G44: =+G42+G43 -> 0 | H44: =+H42+H43 -> 0 | I44: =+I42+I43 -> 3.9 | J44: =+J42+J43 -> 1.3085 | K44: =+K42+K43 -> 1.3085 | L44: =+L42+L43 -> 2.617 | M44: =+M42+M43 -> 2.693 | ... AV44: =+AV42+AV43 -> 4.7879344
A47: PBT | B47: Profit before tax | C47: A$m | F47: =F38+F44 -> 5.6 | G47: =G38+G44 -> 2.0425 | H47: =H38+H44 -> 1.7575 | I47: =I38+I44 -> 7.7 | J47: =J38+J44 -> 16.5995 | K47: =K38+K44 -> 5.277 | L47: =L38+L44 -> 16.253 | M47: =M38+M44 -> 15.295 | ... AV47: =AV38+AV44 -> 478.84902
A50: Tax_expense | B50: Income tax expense | C50: A$m | F50: =Assumptions!F307 -> -2.4 | G50: =Assumptions!G307 -> -2.3 | H50: =Assumptions!H307 -> -2.4 | I50: =Assumptions!I307 -> -4.7 | J50: =Assumptions!J307 -> -6.2 | K50: =Assumptions!K307 -> -4.4 | L50: =Assumptions!L307 -> -10.6 | M50: =Assumptions!M307 -> -7.9 | ... AV50: =Assumptions!AV307 -> -139.60805
A54: NPAT_underlying | B54: NPAT (underlying) | C54: A$m | F54: =F47+F50 -> 3.2 | G54: =G47+G50 -> -0.2575 | H54: =H47+H50 -> -0.6425 | I54: =I47+I50 -> 3 | J54: =J47+J50 -> 10.3995 | K54: =K47+K50 -> 0.877 | L54: =L47+L50 -> 5.653 | M54: =M47+M50 -> 7.395 | ... AV54: =AV47+AV50 -> 339.24097
A55: NRI_post_tax | B55: NRI (post tax) | C55: A$m | F55: =+F56-F54 -> 0.7 | G55: =+G56-G54 -> 1.1575 | H55: =+H56-H54 -> -2.5575 | I55: =+I56-I54 -> -5.3 | J55: =+J56-J54 -> -6.5995 | K55: =+K56-K54 -> -18.425 | L55: =+L56-L54 -> -19.401 | M55: =+M56-M54 -> -0.094 | ... O55: =+O56-O54 -> -0.343 | P55: 0 | Q55: =+P55 -> 0 | R55: =+Q55 -> 0 | S55: =+R55 -> 0 | T55: =+S55 -> 0 | U55: =+T55 -> 0 | V55: =+U55 -> 0 | W55: =+V55 -> 0 | X55: =+W55 -> 0 | ... AV55: =+AU55 -> 0
A56: NPAT_reported | B56: NPAT (reported) | C56: A$m | F56: 3.9 | G56: 0.9 | H56: =+I56-G56 -> -3.2 | I56: -2.3 | J56: 3.8 | K56: =+L56-J56 -> -17.548 | L56: -13.748 | M56: 7.301 | N56: =+O56-M56 -> 7.175 | O56: 14.476 | P56: =+P54+P55 -> 9.794725 | Q56: =+Q54+Q55 -> 11.686408 | R56: =+R54+R55 -> 21.481133 | S56: =+S54+S55 -> 18.267106 | T56: =+T54+T55 -> 24.008881 | U56: =+U54+U55 -> 42.275987 | V56: =+V54+V55 -> 32.066723 | W56: =+W54+W55 -> 33.149166 | ... AV56: =+AV54+AV55 -> 339.24097
B58: Underlying EPS (Basic) | C58: c | I58: =(I54/I63)*100 -> 2.9599544 | J58: =(J54/J63)*100 -> 10.260682 | K58: =+L58-J58 -> -4.6831411 | L58: =(L54/L63)*100 -> 5.5775407 | M58: =(M54/M63)*100 -> 7.2901496 | N58: =(N54/N63)*100 -> 6.9948893 | O58: =(O54/O63)*100 -> 14.598618 | P58: =(P54/P63)*100 -> 9.6490621 | Q58: =(Q54/Q63)*100 -> 11.512612 | R58: =(R54/R63)*100 -> 21.161674 | S58: =(S54/S63)*100 -> 17.995445 | ... AV58: =(AV54/AV63)*100 -> 334.19592
A59: EPS_underlying_diluted | B59: Underlying EPS (Diluted) (Modelware) | C59: c | I59: =(I54/I64)*100 -> 2.9599544 | J59: =(J54/J64)*100 -> 10.260682 | K59: =+L59-J59 -> -5.1923913 | L59: =(L54/L64)*100 -> 5.0682905 | M59: =(M54/M64)*100 -> 6.9675656 | N59: =(N54/N64)*100 -> 6.9948893 | O59: =(O54/O64)*100 -> 13.992731 | P59: =(P54/P64)*100 -> 9.2485967 | Q59: =(Q54/Q64)*100 -> 11.034804 | R59: =(R54/R64)*100 -> 20.283401 | S59: =(S54/S64)*100 -> 17.24858 | ... AV59: =(AV54/AV64)*100 -> 320.32578
B60: Reported EPS (Basic) | C60: c | I60: =(+I56/I63)*100 -> -2.2692983 | J60: =(+J56/J63)*100 -> 3.7492755 | K60: =+L60-J60 -> -17.31376 | L60: =(+L56/L63)*100 -> -13.564484 | M60: =(+M56/M63)*100 -> 7.1974824 | N60: =(+N56/N63)*100 -> 6.7602817 | O60: =(+O56/O63)*100 -> 14.260719 | P60: =(+P56/P63)*100 -> 9.6490621 | Q60: =(+Q56/Q63)*100 -> 11.512612 | R60: =(+R56/R63)*100 -> 21.161674 | S60: =(+S56/S63)*100 -> 17.995445 | ... AV60: =(+AV56/AV63)*100 -> 334.19592
A61: EPS_Reported_diluted | B61: Reported EPS (Diluted) | C61: c | I61: =(+I56/I64)*100 -> -2.2692983 | J61: =(+J56/J64)*100 -> 3.7492755 | K61: =+L61-J61 -> -16.075272 | L61: =(+L56/L64)*100 -> -12.325996 | M61: =(+M56/M64)*100 -> 6.8789988 | N61: =(+N56/N64)*100 -> 6.7602817 | O61: =(+O56/O64)*100 -> 13.668856 | P61: =(+P56/P64)*100 -> 9.2485967 | Q61: =(+Q56/Q64)*100 -> 11.034804 | R61: =(+R56/R64)*100 -> 20.283401 | S61: =(+S56/S64)*100 -> 17.24858 | ... AV61: =(+AV56/AV64)*100 -> 320.32578
K62: =+L62-J62 -> 0
B63: Weighted average shares (basic) | C63: m | F63: ND | G63: =+Assumptions!G322 -> 0 | H63: =+Assumptions!H322 -> 0 | I63: =+J63 -> 101.35291 | J63: =+Assumptions!J321 -> 101.35291 | K63: =+Assumptions!K321 -> 101.35291 | L63: =+Assumptions!L321 -> 101.35291 | M63: =+Assumptions!M321 -> 101.43825 | N63: =+Assumptions!N321 -> 106.13463 | O63: =+Assumptions!O321 -> 101.50961 | P63: =+Assumptions!P321 -> 101.50961 | Q63: =+Assumptions!Q321 -> 101.50961 | ... AV63: =+Assumptions!AV321 -> 101.50961
B64: Weighted average shares (diluted) | C64: m | F64: ND | G64: =+Assumptions!G323 -> 0 | H64: =+Assumptions!H323 -> 0 | I64: =+J64 -> 101.35291 | J64: =+Assumptions!J323 -> 101.35291 | K64: =+Assumptions!K323 -> 101.35291 | L64: =+Assumptions!L323 -> 111.53662 | M64: =+Assumptions!M323 -> 106.13463 | N64: =+Assumptions!N323 -> 106.13463 | O64: =+Assumptions!O323 -> 105.90499 | P64: =+Assumptions!P323 -> 105.90499 | Q64: =+Assumptions!Q323 -> 105.90499 | ... AV64: =+Assumptions!AV323 -> 105.90499
B66: Weighted average shares (basic) | C66: m | F66: =F63 -> ND | G66: =G63 -> 0 | H66: =H63 -> 0 | I66: =I63 -> 101.35291 | J66: =J63 -> 101.35291 | K66: =K63 -> 101.35291 | L66: =L63 -> 101.35291 | M66: =M63 -> 101.43825 | ... AV66: =AV63 -> 101.50961
A72: l | B72: Balance sheet
B74: Currents Assets
A75: CA_cash | B75: Cash & Cash Equivalents | C75: A$m | F75: 0 | I75: 36.504 | J75: 279.7 | K75: =+L75 -> 294.48 | L75: =16.385+278.095 -> 294.48 | M75: =16.882+257.611 -> 274.493 | N75: =+O75 -> 281.743 | O75: =39.675+242.068 -> 281.743 | P75: =+P156 -> 279.59941 | Q75: =+Q156 -> 269.57803 | R75: =Q75 -> 269.57803 | S75: =+S156 -> 257.02244 | T75: =+T156 -> 242.88346 | U75: =T75 -> 242.88346 | V75: =+V156 -> 238.02951 | W75: =+W156 -> 233.92671 | X75: =W75 -> 233.92671 | Y75: =+Y156 -> 230.70455 | Z75: =+Z156 -> 229.80971 | AA75: =Z75 -> 229.80971 | AB75: =+AB156 -> 231.74872 | AC75: =+AC156 -> 236.91066 | AD75: =AC75 -> 236.91066 | AE75: =+AE156 -> 242.57805 | AF75: =+AF156 -> 251.67311 | AG75: =AF75 -> 251.67311 | AH75: =+AH156 -> 261.31641 | AI75: =+AI156 -> 274.99607 | AJ75: =AI75 -> 274.99607 | AK75: =+AK156 -> 289.26917 | AL75: =+AL156 -> 308.23697 | AM75: =AL75 -> 308.23697 | AN75: =+AN156 -> 328.00907 | AO75: =+AO156 -> 353.64244 | AP75: =AO75 -> 353.64244 | AQ75: =+AQ156 -> 376.46619 | AR75: =+AR156 -> 406.02425 | AS75: =AR75 -> 406.02425 | AT75: =+AT156 -> 432.41553 | AU75: =+AU156 -> 466.06891 | AV75: =AU75 -> 466.06891
A76: CA_receivables | B76: Trade & Other Receivables | C76: A$m | F76: 0 | I76: 23.947 | J76: 21.2 | K76: =+L76 -> 26.02 | L76: 26.02 | M76: 18.852 | N76: =+O76 -> 24.703 | O76: 24.703 | P76: =+Assumptions!P415 -> 30.530917 | Q76: =+Assumptions!Q415 -> 32.031819 | R76: =Q76 -> 32.031819 | S76: =+Assumptions!S415 -> 36.883902 | T76: =+Assumptions!T415 -> 38.895744 | U76: =T76 -> 38.895744 | V76: =+Assumptions!V415 -> 45.294127 | W76: =+Assumptions!W415 -> 47.203413 | X76: =W76 -> 47.203413 | Y76: =+Assumptions!Y415 -> 54.11313 | Z76: =+Assumptions!Z415 -> 56.419977 | AA76: =Z76 -> 56.419977 | AB76: =+Assumptions!AB415 -> 63.22551 | AC76: =+Assumptions!AC415 -> 65.977473 | AD76: =AC76 -> 65.977473 | AE76: =+Assumptions!AE415 -> 72.765507 | AF76: =+Assumptions!AF415 -> 75.794037 | AG76: =AF76 -> 75.794037 | AH76: =+Assumptions!AH415 -> 83.11067 | AI76: =+Assumptions!AI415 -> 86.436875 | AJ76: =AI76 -> 86.436875 | AK76: =+Assumptions!AK415 -> 94.31734 | AL76: =+Assumptions!AL415 -> 97.963705 | AM76: =AL76 -> 97.963705 | AN76: =+Assumptions!AN415 -> 104.21261 | AO76: =+Assumptions!AO415 -> 107.91415 | AP76: =AO76 -> 107.91415 | AQ76: =+Assumptions!AQ415 -> 113.77844 | AR76: =+Assumptions!AR415 -> 117.73457 | AS76: =AR76 -> 117.73457 | AT76: =+Assumptions!AT415 -> 123.76111 | AU76: =+Assumptions!AU415 -> 127.9818 | AV76: =AU76 -> 127.9818
B77: Inventories | C77: A$m | F77: 0 | I77: 2.153 | J77: 3.2 | K77: =+L77 -> 2.825 | L77: 2.825 | M77: 4.249 | N77: =+O77 -> 3.761 | O77: 3.761 | P77: =+Assumptions!P416 -> 4.9219472 | Q77: =+Assumptions!Q416 -> 5.2080375 | R77: =Q77 -> 5.2080375 | S77: =+Assumptions!S416 -> 5.9747539 | T77: =+Assumptions!T416 -> 6.3333734 | U77: =T77 -> 6.3333734 | V77: =+Assumptions!V416 -> 7.2975735 | W77: =+Assumptions!W416 -> 7.6933389 | X77: =W77 -> 7.6933389 | Y77: =+Assumptions!Y416 -> 8.6105065 | Z77: =+Assumptions!Z416 -> 9.0525027 | AA77: =Z77 -> 9.0525027 | AB77: =+Assumptions!AB416 -> 9.9961998 | AC77: =+Assumptions!AC416 -> 10.459895 | AD77: =AC77 -> 10.459895 | AE77: =+Assumptions!AE416 -> 11.453193 | AF77: =+Assumptions!AF416 -> 11.967888 | AG77: =AF77 -> 11.967888 | AH77: =+Assumptions!AH416 -> 13.030935 | AI77: =+Assumptions!AI416 -> 13.600609 | AJ77: =AI77 -> 13.600609 | AK77: =+Assumptions!AK416 -> 14.737853 | AL77: =+Assumptions!AL416 -> 15.366749 | AM77: =AL77 -> 15.366749 | AN77: =+Assumptions!AN416 -> 16.253181 | AO77: =+Assumptions!AO416 -> 16.899459 | AP77: =AO77 -> 16.899459 | AQ77: =+Assumptions!AQ416 -> 17.718953 | AR77: =+Assumptions!AR416 -> 18.412689 | AS77: =AR77 -> 18.412689 | AT77: =+Assumptions!AT416 -> 19.258424 | AU77: =+Assumptions!AU416 -> 20.001899 | AV77: =AU77 -> 20.001899
B78: Finance Lease Receivables | C78: A$m | F78: 0 | I78: 10.772 | J78: 10.5 | K78: =+L78 -> 11.999 | L78: 11.999 | M78: 12.25 | N78: =+O78 -> 12.497 | O78: 12.497 | P78: =O78 -> 12.497 | Q78: =P78 -> 12.497 | R78: =Q78 -> 12.497 | S78: =R78 -> 12.497 | T78: =S78 -> 12.497 | U78: =T78 -> 12.497 | V78: =U78 -> 12.497 | W78: =V78 -> 12.497 | ... AV78: =AU78 -> 12.497
B79: Other Assets | C79: A$m | F79: 0 | I79: 3.56 | J79: 4.4 | K79: =+L79 -> 3.302 | L79: 3.302 | M79: 4.604 | N79: =+O79 -> 4.51 | O79: 4.51 | P79: =+O79 -> 4.51 | Q79: =+P79 -> 4.51 | R79: =Q79 -> 4.51 | S79: =+R79 -> 4.51 | T79: =+S79 -> 4.51 | U79: =T79 -> 4.51 | V79: =+U79 -> 4.51 | W79: =+V79 -> 4.51 | X79: =W79 -> 4.51 | Y79: =+X79 -> 4.51 | Z79: =+Y79 -> 4.51 | AA79: =Z79 -> 4.51 | AB79: =+AA79 -> 4.51 | AC79: =+AB79 -> 4.51 | AD79: =AC79 -> 4.51 | AE79: =+AD79 -> 4.51 | AF79: =+AE79 -> 4.51 | AG79: =AF79 -> 4.51 | AH79: =+AG79 -> 4.51 | AI79: =+AH79 -> 4.51 | AJ79: =AI79 -> 4.51 | AK79: =+AJ79 -> 4.51 | AL79: =+AK79 -> 4.51 | AM79: =AL79 -> 4.51 | AN79: =+AM79 -> 4.51 | AO79: =+AN79 -> 4.51 | AP79: =AO79 -> 4.51 | AQ79: =+AP79 -> 4.51 | AR79: =+AQ79 -> 4.51 | AS79: =AR79 -> 4.51 | AT79: =+AS79 -> 4.51 | AU79: =+AT79 -> 4.51 | AV79: =AU79 -> 4.51
B80: Total Current Assets | C80: A$m | I80: =SUM(I75:I79) -> 76.936 | J80: =SUM(J75:J79) -> 319 | K80: =+L80 -> 338.626 | L80: =SUM(L75:L79) -> 338.626 | M80: =SUM(M75:M79) -> 314.448 | N80: =+O80 -> 327.214 | O80: =SUM(O75:O79) -> 327.214 | P80: =SUM(P75:P79) -> 332.05928 | Q80: =SUM(Q75:Q79) -> 323.82489 | R80: =SUM(R75:R79) -> 323.82489 | S80: =SUM(S75:S79) -> 316.8881 | T80: =SUM(T75:T79) -> 305.11958 | U80: =SUM(U75:U79) -> 305.11958 | V80: =SUM(V75:V79) -> 307.62821 | ... AV80: =SUM(AV75:AV79) -> 631.05961
B82: Non-current Assets
B83: Trade & other Receivables | C83: A$m | F83: 0 | I83: 1.14 | J83: 1 | K83: =L83 -> 0.479 | L83: 0.479 | M83: 0.238 | N83: =O83 -> 0.137 | O83: 0.137 | P83: =+O83 -> 0.137 | Q83: =+P83 -> 0.137 | R83: =Q83 -> 0.137 | S83: =+R83 -> 0.137 | T83: =+S83 -> 0.137 | U83: =T83 -> 0.137 | V83: =+U83 -> 0.137 | W83: =+V83 -> 0.137 | X83: =W83 -> 0.137 | Y83: =+X83 -> 0.137 | Z83: =+Y83 -> 0.137 | AA83: =Z83 -> 0.137 | AB83: =+AA83 -> 0.137 | AC83: =+AB83 -> 0.137 | AD83: =AC83 -> 0.137 | AE83: =+AD83 -> 0.137 | AF83: =+AE83 -> 0.137 | AG83: =AF83 -> 0.137 | AH83: =+AG83 -> 0.137 | AI83: =+AH83 -> 0.137 | AJ83: =AI83 -> 0.137 | AK83: =+AJ83 -> 0.137 | AL83: =+AK83 -> 0.137 | AM83: =AL83 -> 0.137 | AN83: =+AM83 -> 0.137 | AO83: =+AN83 -> 0.137 | AP83: =AO83 -> 0.137 | AQ83: =+AP83 -> 0.137 | AR83: =+AQ83 -> 0.137 | AS83: =AR83 -> 0.137 | AT83: =+AS83 -> 0.137 | AU83: =+AT83 -> 0.137 | AV83: =AU83 -> 0.137
A84: PPE | B84: Property, Plant & Equipment | C84: A$m | F84: 0 | I84: 69.486 | J84: 78 | K84: =L84 -> 87.63 | L84: 87.63 | M84: 103.028 | N84: =O84 -> 130.056 | O84: 130.056 | P84: =Assumptions!P338 -> 145.70764 | Q84: =Assumptions!Q338 -> 160.12529 | R84: =Q84 -> 160.12529 | S84: =Assumptions!S338 -> 182.38041 | T84: =Assumptions!T338 -> 203.13492 | U84: =T84 -> 203.13492 | V84: =Assumptions!V338 -> 219.43887 | W84: =Assumptions!W338 -> 233.9555 | X84: =W84 -> 233.9555 | Y84: =Assumptions!Y338 -> 251.03992 | Z84: =Assumptions!Z338 -> 266.03939 | AA84: =Z84 -> 266.03939 | AB84: =Assumptions!AB338 -> 281.66276 | AC84: =Assumptions!AC338 -> 294.90187 | AD84: =AC84 -> 294.90187 | AE84: =Assumptions!AE338 -> 311.53574 | AF84: =Assumptions!AF338 -> 325.49135 | AG84: =AF84 -> 325.49135 | AH84: =Assumptions!AH338 -> 343.30319 | AI84: =Assumptions!AI338 -> 358.12974 | AJ84: =AI84 -> 358.12974 | AK84: =Assumptions!AK338 -> 377.30637 | AL84: =Assumptions!AL338 -> 393.17761 | AM84: =AL84 -> 393.17761 | AN84: =Assumptions!AN338 -> 411.21919 | AO84: =Assumptions!AO338 -> 425.70356 | AP84: =AO84 -> 425.70356 | AQ84: =Assumptions!AQ338 -> 445.31826 | AR84: =Assumptions!AR338 -> 461.1435 | AS84: =AR84 -> 461.1435 | AT84: =Assumptions!AT338 -> 482.50731 | AU84: =Assumptions!AU338 -> 499.84897 | AV84: =AU84 -> 499.84897
B85: Right-of-use Assets | C85: A$m | F85: 0 | I85: 98.939 | J85: 122.3 | K85: =L85 -> 93.796 | L85: 93.796 | M85: 104.149 | N85: =O85 -> 125.43 | O85: 125.43 | P85: =+Assumptions!P360 -> 129.16589 | Q85: =+Assumptions!Q360 -> 139.76084 | R85: =Q85 -> 139.76084 | S85: =+Assumptions!S360 -> 143.26882 | T85: =+Assumptions!T360 -> 161.52491 | U85: =T85 -> 161.52491 | V85: =+Assumptions!V360 -> 161.83642 | W85: =+Assumptions!W360 -> 177.09315 | X85: =W85 -> 177.09315 | Y85: =+Assumptions!Y360 -> 174.58513 | Z85: =+Assumptions!Z360 -> 187.66723 | AA85: =Z85 -> 187.66723 | AB85: =+Assumptions!AB360 -> 180.43965 | AC85: =+Assumptions!AC360 -> 188.07769 | AD85: =AC85 -> 188.07769 | AE85: =+Assumptions!AE360 -> 175.61789 | AF85: =+Assumptions!AF360 -> 178.41096 | AG85: =AF85 -> 178.41096 | AH85: =+Assumptions!AH360 -> 160.51216 | AI85: =+Assumptions!AI360 -> 158.64253 | AJ85: =AI85 -> 158.64253 | AK85: =+Assumptions!AK360 -> 134.63984 | AL85: =+Assumptions!AL360 -> 127.49618 | AM85: =AL85 -> 127.49618 | AN85: =+Assumptions!AN360 -> 107.06702 | AO85: =+Assumptions!AO360 -> 95.259205 | AP85: =AO85 -> 95.259205 | AQ85: =+Assumptions!AQ360 -> 72.390524 | AR85: =+Assumptions!AR360 -> 56.091957 | AS85: =AR85 -> 56.091957 | AT85: =+Assumptions!AT360 -> 29.092061 | AU85: =+Assumptions!AU360 -> 8.352787 | AV85: =AU85 -> 8.352787
B86: Finance Lease Receivable | C86: A$m | F86: 0 | I86: 58.561 | J86: 57.6 | K86: =L86 -> 114.404 | L86: 114.404 | M86: 137.32 | N86: =O86 -> 162.347 | O86: 162.347 | P86: =+Assumptions!P407 -> 180.34285 | Q86: =+Assumptions!Q407 -> 185.3478 | R86: =Q86 -> 185.3478 | S86: =+Assumptions!S407 -> 209.59638 | T86: =+Assumptions!T407 -> 219.72211 | U86: =T86 -> 219.72211 | V86: =+Assumptions!V407 -> 246.6353 | W86: =+Assumptions!W407 -> 258.56222 | X86: =W86 -> 258.56222 | Y86: =+Assumptions!Y407 -> 289.80256 | Z86: =+Assumptions!Z407 -> 302.98881 | AA86: =Z86 -> 302.98881 | AB86: =+Assumptions!AB407 -> 335.80152 | AC86: =+Assumptions!AC407 -> 349.52015 | AD86: =AC86 -> 349.52015 | AE86: =+Assumptions!AE407 -> 382.25331 | AF86: =+Assumptions!AF407 -> 397.29523 | AG86: =AF86 -> 397.29523 | AH86: =+Assumptions!AH407 -> 432.44614 | AI86: =+Assumptions!AI407 -> 448.90876 | AJ86: =AI86 -> 448.90876 | AK86: =+Assumptions!AK407 -> 486.64309 | AL86: =+Assumptions!AL407 -> 504.63012 | AM86: =AL86 -> 504.63012 | AN86: =+Assumptions!AN407 -> 534.35408 | AO86: =+Assumptions!AO407 -> 552.64834 | AP86: =AO86 -> 552.64834 | AQ86: =+Assumptions!AQ407 -> 580.54496 | AR86: =+Assumptions!AR407 -> 600.05345 | AS86: =AR86 -> 600.05345 | AT86: =+Assumptions!AT407 -> 628.99965 | AU86: =+Assumptions!AU407 -> 649.77839 | AV86: =AU86 -> 649.77839
A87: Intangibles_BS | B87: Intangibles | C87: A$m | F87: 0 | I87: 15.202 | J87: 11.7 | K87: =L87 -> 10.586 | L87: 10.586 | M87: 19.153 | N87: =O87 -> 18.305 | O87: 18.305 | P87: =+Assumptions!P374 -> 14.718665 | Q87: =+Assumptions!Q374 -> 16.571153 | R87: =Q87 -> 16.571153 | S87: =+Assumptions!S374 -> 15.834974 | T87: =+Assumptions!T374 -> 18.657356 | U87: =T87 -> 18.657356 | V87: =+Assumptions!V374 -> 20.161098 | W87: =+Assumptions!W374 -> 21.950918 | X87: =W87 -> 21.950918 | Y87: =+Assumptions!Y374 -> 24.096461 | Z87: =+Assumptions!Z374 -> 26.587649 | AA87: =Z87 -> 26.587649 | AB87: =+Assumptions!AB374 -> 29.396782 | AC87: =+Assumptions!AC374 -> 32.618255 | AD87: =AC87 -> 32.618255 | AE87: =+Assumptions!AE374 -> 36.122823 | AF87: =+Assumptions!AF374 -> 40.081171 | AG87: =AF87 -> 40.081171 | AH87: =+Assumptions!AH374 -> 44.341303 | AI87: =+Assumptions!AI374 -> 49.099816 | AJ87: =AI87 -> 49.099816 | AK87: =+Assumptions!AK374 -> 54.179859 | AL87: =+Assumptions!AL374 -> 59.806254 | AM87: =AL87 -> 59.806254 | AN87: =+Assumptions!AN374 -> 65.607764 | AO87: =+Assumptions!AO374 -> 71.963894 | AP87: =AO87 -> 71.963894 | AQ87: =+Assumptions!AQ374 -> 78.461992 | AR87: =+Assumptions!AR374 -> 85.552856 | AS87: =AR87 -> 85.552856 | AT87: =+Assumptions!AT374 -> 92.778571 | AU87: =+Assumptions!AU374 -> 100.63669 | AV87: =AU87 -> 100.63669
B88: Deferred Tax | C88: A$m | F88: 0 | I88: 4.243 | J88: 14.3 | K88: =L88 -> 16.276 | L88: 16.276 | M88: 16.633 | N88: =O88 -> 19.709 | O88: 19.709 | P88: =+O88 -> 19.709 | Q88: =+P88 -> 19.709 | R88: =Q88 -> 19.709 | S88: =+R88 -> 19.709 | T88: =+S88 -> 19.709 | U88: =T88 -> 19.709 | V88: =+U88 -> 19.709 | W88: =+V88 -> 19.709 | X88: =W88 -> 19.709 | Y88: =+X88 -> 19.709 | Z88: =+Y88 -> 19.709 | AA88: =Z88 -> 19.709 | AB88: =+AA88 -> 19.709 | AC88: =+AB88 -> 19.709 | AD88: =AC88 -> 19.709 | AE88: =+AD88 -> 19.709 | AF88: =+AE88 -> 19.709 | AG88: =AF88 -> 19.709 | AH88: =+AG88 -> 19.709 | AI88: =+AH88 -> 19.709 | AJ88: =AI88 -> 19.709 | AK88: =+AJ88 -> 19.709 | AL88: =+AK88 -> 19.709 | AM88: =AL88 -> 19.709 | AN88: =+AM88 -> 19.709 | AO88: =+AN88 -> 19.709 | AP88: =AO88 -> 19.709 | AQ88: =+AP88 -> 19.709 | AR88: =+AQ88 -> 19.709 | AS88: =AR88 -> 19.709 | AT88: =+AS88 -> 19.709 | AU88: =+AT88 -> 19.709 | AV88: =AU88 -> 19.709
B89: Total Non-Current Assets | C89: A$m | F89: =SUM(F83:F88) -> 0 | I89: =SUM(I83:I88) -> 247.571 | J89: =SUM(J83:J88) -> 284.9 | K89: =L89 -> 323.171 | L89: =SUM(L83:L88) -> 323.171 | M89: =SUM(M83:M88) -> 380.521 | N89: =O89 -> 455.984 | O89: =SUM(O83:O88) -> 455.984 | P89: =SUM(P83:P88) -> 489.78105 | Q89: =SUM(Q83:Q88) -> 521.65108 | R89: =SUM(R83:R88) -> 521.65108 | S89: =SUM(S83:S88) -> 570.92658 | T89: =SUM(T83:T88) -> 622.8853 | U89: =SUM(U83:U88) -> 622.8853 | V89: =SUM(V83:V88) -> 667.91769 | ... AV89: =SUM(AV83:AV88) -> 1278.4628
A90: Total_assets | B90: Total Assets | C90: A$m | F90: =+F89+F80 -> 0 | I90: =+I89+I80 -> 324.507 | J90: =+J89+J80 -> 603.9 | K90: =L90 -> 661.797 | L90: =+L89+L80 -> 661.797 | M90: =+M89+M80 -> 694.969 | N90: =O90 -> 783.198 | O90: =+O89+O80 -> 783.198 | P90: =+P89+P80 -> 821.84032 | Q90: =+Q89+Q80 -> 845.47597 | R90: =+R89+R80 -> 845.47597 | S90: =+S89+S80 -> 887.81468 | T90: =+T89+T80 -> 928.00487 | U90: =+U89+U80 -> 928.00487 | V90: =+V89+V80 -> 975.54589 | ... AV90: =+AV89+AV80 -> 1909.5224
R91: =+R89/Q89-1 -> 0 | U91: =+U89/T89-1 -> 0 | X91: =+X89/W89-1 -> 0 | AA91: =+AA89/Z89-1 -> 0 | AD91: =+AD89/AC89-1 -> 0 | AG91: =+AG89/AF89-1 -> 0 | AJ91: =+AJ89/AI89-1 -> 0 | AM91: =+AM89/AL89-1 -> 0 | AP91: =+AP89/AO89-1 -> 0 | AS91: =+AS89/AR89-1 -> 0 | AV91: =+AV89/AU89-1 -> 0
B92: Current Liabilities
A93: CL_payables | B93: Trade & Other Payables | C93: A$m | F93: 0 | I93: 32.635 | J93: 22 | K93: =L93 -> 39.387 | L93: 39.387 | M93: 30.198 | N93: =O93 -> 40.439 | O93: 40.439 | P93: =+Assumptions!P417 -> 52.921729 | Q93: =+Assumptions!Q417 -> 55.997827 | R93: =Q93 -> 55.997827 | S93: =+Assumptions!S417 -> 64.241711 | T93: =+Assumptions!T417 -> 68.097657 | U93: =T93 -> 68.097657 | V93: =+Assumptions!V417 -> 78.464922 | W93: =+Assumptions!W417 -> 82.720269 | X93: =W93 -> 82.720269 | Y93: =+Assumptions!Y417 -> 92.581833 | Z93: =+Assumptions!Z417 -> 97.334261 | AA93: =Z93 -> 97.334261 | AB93: =+Assumptions!AB417 -> 107.48108 | AC93: =+Assumptions!AC417 -> 112.46681 | AD93: =AC93 -> 112.46681 | AE93: =+Assumptions!AE417 -> 123.14694 | AF93: =+Assumptions!AF417 -> 128.68104 | AG93: =AF93 -> 128.68104 | AH93: =+Assumptions!AH417 -> 140.11114 | AI93: =+Assumptions!AI417 -> 146.23638 | AJ93: =AI93 -> 146.23638 | AK93: =+Assumptions!AK417 -> 158.46424 | AL93: =+Assumptions!AL417 -> 165.22626 | AM93: =AL93 -> 165.22626 | AN93: =+Assumptions!AN417 -> 174.75735 | AO93: =+Assumptions!AO417 -> 181.70625 | AP93: =AO93 -> 181.70625 | AQ93: =+Assumptions!AQ417 -> 190.51761 | AR93: =+Assumptions!AR417 -> 197.9768 | AS93: =AR93 -> 197.9768 | AT93: =+Assumptions!AT417 -> 207.07031 | AU93: =+Assumptions!AU417 -> 215.06429 | AV93: =AU93 -> 215.06429
B94: Contract Liabilities | C94: A$m | F94: 0 | I94: 1.681 | J94: 2.4 | K94: =L94 -> 2.054 | L94: 2.054 | M94: 1.397 | N94: =O94 -> 2.267 | O94: 2.267 | P94: =O94 -> 2.267 | Q94: =P94 -> 2.267 | R94: =Q94 -> 2.267 | S94: =R94 -> 2.267 | T94: =S94 -> 2.267 | U94: =T94 -> 2.267 | V94: =U94 -> 2.267 | W94: =V94 -> 2.267 | ... AV94: =AU94 -> 2.267
B95: Lease Liabilities | C95: A$m | F95: 0 | I95: 20.165 | J95: 20 | K95: =L95 -> 22.201 | L95: 22.201 | M95: 19.687 | N95: =O95 -> 23.652 | O95: 23.652 | P95: =O95 -> 23.652 | Q95: =P95 -> 23.652 | R95: =Q95 -> 23.652 | S95: =R95 -> 23.652 | T95: =S95 -> 23.652 | U95: =T95 -> 23.652 | V95: =U95 -> 23.652 | W95: =V95 -> 23.652 | ... AV95: =AU95 -> 23.652
B96: Income Tax | C96: A$m | F96: 0 | I96: 3.636 | J96: 9.7 | K96: =L96 -> 10.138 | L96: 10.138 | M96: 4.704 | N96: =O96 -> 8.916 | O96: 8.916 | P96: =+O96 -> 8.916 | Q96: =+P96 -> 8.916 | R96: =Q96 -> 8.916 | S96: =+R96 -> 8.916 | T96: =+S96 -> 8.916 | U96: =T96 -> 8.916 | V96: =+U96 -> 8.916 | W96: =+V96 -> 8.916 | X96: =W96 -> 8.916 | Y96: =+X96 -> 8.916 | Z96: =+Y96 -> 8.916 | AA96: =Z96 -> 8.916 | AB96: =+AA96 -> 8.916 | AC96: =+AB96 -> 8.916 | AD96: =AC96 -> 8.916 | AE96: =+AD96 -> 8.916 | AF96: =+AE96 -> 8.916 | AG96: =AF96 -> 8.916 | AH96: =+AG96 -> 8.916 | AI96: =+AH96 -> 8.916 | AJ96: =AI96 -> 8.916 | AK96: =+AJ96 -> 8.916 | AL96: =+AK96 -> 8.916 | AM96: =AL96 -> 8.916 | AN96: =+AM96 -> 8.916 | AO96: =+AN96 -> 8.916 | AP96: =AO96 -> 8.916 | AQ96: =+AP96 -> 8.916 | AR96: =+AQ96 -> 8.916 | AS96: =AR96 -> 8.916 | AT96: =+AS96 -> 8.916 | AU96: =+AT96 -> 8.916 | AV96: =AU96 -> 8.916
B97: Provisions | C97: A$m | F97: 0 | I97: 8.349 | J97: 5.4 | K97: =L97 -> 10.507 | L97: 10.507 | M97: 9.725 | N97: =O97 -> 10.766 | O97: 10.766 | P97: =+O97 -> 10.766 | Q97: =+P97 -> 10.766 | R97: =Q97 -> 10.766 | S97: =+R97 -> 10.766 | T97: =+S97 -> 10.766 | U97: =T97 -> 10.766 | V97: =+U97 -> 10.766 | W97: =+V97 -> 10.766 | X97: =W97 -> 10.766 | Y97: =+X97 -> 10.766 | Z97: =+Y97 -> 10.766 | AA97: =Z97 -> 10.766 | AB97: =+AA97 -> 10.766 | AC97: =+AB97 -> 10.766 | AD97: =AC97 -> 10.766 | AE97: =+AD97 -> 10.766 | AF97: =+AE97 -> 10.766 | AG97: =AF97 -> 10.766 | AH97: =+AG97 -> 10.766 | AI97: =+AH97 -> 10.766 | AJ97: =AI97 -> 10.766 | AK97: =+AJ97 -> 10.766 | AL97: =+AK97 -> 10.766 | AM97: =AL97 -> 10.766 | AN97: =+AM97 -> 10.766 | AO97: =+AN97 -> 10.766 | AP97: =AO97 -> 10.766 | AQ97: =+AP97 -> 10.766 | AR97: =+AQ97 -> 10.766 | AS97: =AR97 -> 10.766 | AT97: =+AS97 -> 10.766 | AU97: =+AT97 -> 10.766 | AV97: =AU97 -> 10.766
B98: Total Current Liabilities | C98: A$m | F98: =SUM(F93:F97) -> 0 | I98: =SUM(I93:I97) -> 66.466 | J98: =SUM(J93:J97) -> 59.5 | K98: =L98 -> 84.287 | L98: =SUM(L93:L97) -> 84.287 | M98: =SUM(M93:M97) -> 65.711 | N98: =O98 -> 86.04 | O98: =SUM(O93:O97) -> 86.04 | P98: =SUM(P93:P97) -> 98.522729 | Q98: =SUM(Q93:Q97) -> 101.59883 | R98: =SUM(R93:R97) -> 101.59883 | S98: =SUM(S93:S97) -> 109.84271 | T98: =SUM(T93:T97) -> 113.69866 | U98: =SUM(U93:U97) -> 113.69866 | V98: =SUM(V93:V97) -> 124.06592 | ... AV98: =SUM(AV93:AV97) -> 260.66529
B100: Total Non-Current Liabilities
B101: Contract Liabilities | C101: A$m | F101: 0 | I101: 2.177 | J101: 2.2 | K101: =L101 -> 2.429 | L101: 2.429 | M101: 2.519 | N101: =O101 -> 2.936 | O101: 2.936 | P101: =+O101 -> 2.936 | Q101: =+P101 -> 2.936 | R101: =Q101 -> 2.936 | S101: =+R101 -> 2.936 | T101: =+S101 -> 2.936 | U101: =T101 -> 2.936 | V101: =+U101 -> 2.936 | W101: =+V101 -> 2.936 | X101: =W101 -> 2.936 | Y101: =+X101 -> 2.936 | Z101: =+Y101 -> 2.936 | AA101: =Z101 -> 2.936 | AB101: =+AA101 -> 2.936 | AC101: =+AB101 -> 2.936 | AD101: =AC101 -> 2.936 | AE101: =+AD101 -> 2.936 | AF101: =+AE101 -> 2.936 | AG101: =AF101 -> 2.936 | AH101: =+AG101 -> 2.936 | AI101: =+AH101 -> 2.936 | AJ101: =AI101 -> 2.936 | AK101: =+AJ101 -> 2.936 | AL101: =+AK101 -> 2.936 | AM101: =AL101 -> 2.936 | AN101: =+AM101 -> 2.936 | AO101: =+AN101 -> 2.936 | AP101: =AO101 -> 2.936 | AQ101: =+AP101 -> 2.936 | AR101: =+AQ101 -> 2.936 | AS101: =AR101 -> 2.936 | AT101: =+AS101 -> 2.936 | AU101: =+AT101 -> 2.936 | AV101: =AU101 -> 2.936
A102: LT_borrowings | B102: Borrowings | C102: A$m | F102: 0 | I102: 3 | J102: 3 | K102: =L102 -> 0 | L102: 0 | M102: 0 | N102: =O102 -> 0 | O102: 0 | P102: =+Assumptions!P440 -> 0 | Q102: =+Assumptions!Q440 -> 0 | R102: =Q102 -> 0 | S102: =+Assumptions!S440 -> 0 | T102: =+Assumptions!T440 -> 0 | U102: =T102 -> 0 | V102: =+Assumptions!V440 -> 0 | W102: =+Assumptions!W440 -> 0 | X102: =W102 -> 0 | Y102: =+Assumptions!Y440 -> 0 | Z102: =+Assumptions!Z440 -> 0 | AA102: =Z102 -> 0 | AB102: =+Assumptions!AB440 -> 0 | AC102: =+Assumptions!AC440 -> 0 | AD102: =AC102 -> 0 | AE102: =+Assumptions!AE440 -> 0 | AF102: =+Assumptions!AF440 -> 0 | AG102: =AF102 -> 0 | AH102: =+Assumptions!AH440 -> 0 | AI102: =+Assumptions!AI440 -> 0 | AJ102: =AI102 -> 0 | AK102: =+Assumptions!AK440 -> 0 | AL102: =+Assumptions!AL440 -> 0 | AM102: =AL102 -> 0 | AN102: =+Assumptions!AN440 -> 0 | AO102: =+Assumptions!AO440 -> 0 | AP102: =AO102 -> 0 | AQ102: =+Assumptions!AQ440 -> 0 | AR102: =+Assumptions!AR440 -> 0 | AS102: =AR102 -> 0 | AT102: =+Assumptions!AT440 -> 0 | AU102: =+Assumptions!AU440 -> 0 | AV102: =AU102 -> 0
B103: Lease Liabilities | C103: A$m | F103: 0 | I103: 161.552 | J103: 188 | K103: =L103 -> 217.297 | L103: 217.297 | M103: 254.448 | N103: =O103 -> 307.659 | O103: 307.659 | P103: =+Assumptions!P401 -> 326.55603 | Q103: =+Assumptions!Q401 -> 339.32121 | R103: =Q103 -> 339.32121 | S103: =+Assumptions!S401 -> 363.77166 | T103: =+Assumptions!T401 -> 388.84735 | U103: =T103 -> 388.84735 | V103: =+Assumptions!V401 -> 412.49728 | W103: =+Assumptions!W401 -> 436.10615 | X103: =W103 -> 436.10615 | Y103: =+Assumptions!Y401 -> 461.15149 | Z103: =+Assumptions!Z401 -> 483.73286 | AA103: =Z103 -> 483.73286 | AB103: =+Assumptions!AB401 -> 505.81525 | AC103: =+Assumptions!AC401 -> 523.66918 | AD103: =AC103 -> 523.66918 | AE103: =+Assumptions!AE401 -> 540.90139 | AF103: =+Assumptions!AF401 -> 555.69521 | AG103: =AF103 -> 555.69521 | AH103: =+Assumptions!AH401 -> 570.62904 | AI103: =+Assumptions!AI401 -> 582.90376 | AJ103: =AI103 -> 582.90376 | AK103: =+Assumptions!AK401 -> 595.32279 | AL103: =+Assumptions!AL401 -> 604.85357 | AM103: =AL103 -> 604.85357 | AN103: =+Assumptions!AN401 -> 613.81756 | AO103: =+Assumptions!AO401 -> 619.97322 | AP103: =AO103 -> 619.97322 | AQ103: =+Assumptions!AQ401 -> 625.79445 | AR103: =+Assumptions!AR401 -> 629.79766 | AS103: =AR103 -> 629.79766 | AT103: =+Assumptions!AT401 -> 633.84147 | AU103: =+Assumptions!AU401 -> 635.97845 | AV103: =AU103 -> 635.97845
B104: Provisions | C104: A$m | F104: 0 | I104: 3.347 | J104: 3.83 | K104: =L104 -> 3.805 | L104: 3.805 | M104: 4.658 | N104: =O104 -> 6.439 | O104: 6.439 | P104: =+O104 -> 6.439 | Q104: =+P104 -> 6.439 | R104: =Q104 -> 6.439 | S104: =+R104 -> 6.439 | T104: =+S104 -> 6.439 | U104: =T104 -> 6.439 | V104: =+U104 -> 6.439 | W104: =+V104 -> 6.439 | X104: =W104 -> 6.439 | Y104: =+X104 -> 6.439 | Z104: =+Y104 -> 6.439 | AA104: =Z104 -> 6.439 | AB104: =+AA104 -> 6.439 | AC104: =+AB104 -> 6.439 | AD104: =AC104 -> 6.439 | AE104: =+AD104 -> 6.439 | AF104: =+AE104 -> 6.439 | AG104: =AF104 -> 6.439 | AH104: =+AG104 -> 6.439 | AI104: =+AH104 -> 6.439 | AJ104: =AI104 -> 6.439 | AK104: =+AJ104 -> 6.439 | AL104: =+AK104 -> 6.439 | AM104: =AL104 -> 6.439 | AN104: =+AM104 -> 6.439 | AO104: =+AN104 -> 6.439 | AP104: =AO104 -> 6.439 | AQ104: =+AP104 -> 6.439 | AR104: =+AQ104 -> 6.439 | AS104: =AR104 -> 6.439 | AT104: =+AS104 -> 6.439 | AU104: =+AT104 -> 6.439 | AV104: =AU104 -> 6.439
B105: Total Non-Current Liabilities | C105: A$m | F105: =SUM(F101:F104) -> 0 | I105: =SUM(I101:I104) -> 170.076 | J105: =SUM(J101:J104) -> 197.03 | K105: =L105 -> 223.531 | L105: =SUM(L101:L104) -> 223.531 | M105: =SUM(M101:M104) -> 261.625 | N105: =O105 -> 317.034 | O105: =SUM(O101:O104) -> 317.034 | P105: =SUM(P101:P104) -> 335.93103 | Q105: =SUM(Q101:Q104) -> 348.69621 | R105: =SUM(R101:R104) -> 348.69621 | S105: =SUM(S101:S104) -> 373.14666 | T105: =SUM(T101:T104) -> 398.22235 | U105: =SUM(U101:U104) -> 398.22235 | V105: =SUM(V101:V104) -> 421.87228 | ... AV105: =SUM(AV101:AV104) -> 645.35345
A106: Total_liabilities | B106: Total Liabilities | C106: A$m | F106: =+F98+F105 -> 0 | I106: =+I98+I105 -> 236.542 | J106: =+J98+J105 -> 256.53 | K106: =L106 -> 307.818 | L106: =+L98+L105 -> 307.818 | M106: =+M98+M105 -> 327.336 | N106: =O106 -> 403.074 | O106: =+O98+O105 -> 403.074 | P106: =+P98+P105 -> 434.45376 | Q106: =+Q98+Q105 -> 450.29504 | R106: =+R98+R105 -> 450.29504 | S106: =+S98+S105 -> 482.98937 | T106: =+T98+T105 -> 511.92101 | U106: =+U98+U105 -> 511.92101 | V106: =+V98+V105 -> 545.9382 | ... AV106: =+AV98+AV105 -> 906.01875
A108: Net_assets | B108: Net Assets | C108: A$m | F108: =+F90-F106 -> 0 | I108: =+I90-I106 -> 87.965 | J108: =+J90-J106 -> 347.37 | K108: =L108 -> 353.979 | L108: =+L90-L106 -> 353.979 | M108: =+M90-M106 -> 367.633 | N108: =O108 -> 380.124 | O108: =+O90-O106 -> 380.124 | P108: =+P90-P106 -> 387.38656 | Q108: =+Q90-Q106 -> 395.18093 | R108: =+R90-R106 -> 395.18093 | S108: =+S90-S106 -> 404.82531 | T108: =+T90-T106 -> 416.08387 | U108: =+U90-U106 -> 416.08387 | V108: =+V90-V106 -> 429.6077 | ... AV108: =+AV90-AV106 -> 1003.5037
B109: Issued Capital | C109: A$m | F109: =E109 -> 0 | I109: 104.046 | J109: 371.2 | K109: =L109 -> 372.708 | L109: 372.708 | M109: 373.593 | N109: =O109 -> 374.988 | O109: 374.988 | P109: =O109+P141 -> 374.988 | Q109: =P109+Q141 -> 374.988 | R109: =Q109 -> 374.988 | S109: =R109+S141 -> 374.988 | T109: =S109+T141 -> 374.988 | U109: =T109 -> 374.988 | V109: =U109+V141 -> 374.988 | W109: =V109+W141 -> 374.988 | X109: =W109 -> 374.988 | Y109: =X109+Y141 -> 374.988 | Z109: =Y109+Z141 -> 374.988 | AA109: =Z109 -> 374.988 | AB109: =AA109+AB141 -> 374.988 | AC109: =AB109+AC141 -> 374.988 | AD109: =AC109 -> 374.988 | AE109: =AD109+AE141 -> 374.988 | AF109: =AE109+AF141 -> 374.988 | AG109: =AF109 -> 374.988 | AH109: =AG109+AH141 -> 374.988 | AI109: =AH109+AI141 -> 374.988 | AJ109: =AI109 -> 374.988 | AK109: =AJ109+AK141 -> 374.988 | AL109: =AK109+AL141 -> 374.988 | AM109: =AL109 -> 374.988 | AN109: =AM109+AN141 -> 374.988 | AO109: =AN109+AO141 -> 374.988 | AP109: =AO109 -> 374.988 | AQ109: =AP109+AQ141 -> 374.988 | AR109: =AQ109+AR141 -> 374.988 | AS109: =AR109 -> 374.988 | AT109: =AS109+AT141 -> 374.988 | AU109: =AT109+AU141 -> 374.988 | AV109: =AU109 -> 374.988
B110: Reserves | C110: A$m | F110: =E110 -> 0 | I110: 10.776 | J110: =16.5+0.07 -> 16.57 | K110: =L110 -> 17.418 | L110: 17.418 | M110: =21.593+1.293 -> 22.886 | N110: =O110 -> 26.807 | O110: =26.737+0.07 -> 26.807 | P110: =+O110+P54 -> 36.601725 | Q110: =+P110+Q54 -> 48.288133 | R110: =Q110 -> 48.288133 | S110: =+R110+S54 -> 66.555238 | T110: =+S110+T54 -> 90.564119 | U110: =T110 -> 90.564119 | V110: =+U110+V54 -> 122.63084 | W110: =+V110+W54 -> 155.78001 | X110: =W110 -> 155.78001 | Y110: =+X110+Y54 -> 202.55993 | Z110: =+Y110+Z54 -> 251.54207 | AA110: =Z110 -> 251.54207 | AB110: =+AA110+AB54 -> 311.89787 | AC110: =+AB110+AC54 -> 378.93576 | AD110: =AC110 -> 378.93576 | AE110: =+AD110+AE54 -> 455.19724 | AF110: =+AE110+AF54 -> 538.96825 | AG110: =AF110 -> 538.96825 | AH110: =+AG110+AH54 -> 633.13957 | AI110: =+AH110+AI54 -> 735.74304 | AJ110: =AI110 -> 735.74304 | AK110: =+AJ110+AK54 -> 850.00879 | AL110: =+AK110+AL54 -> 973.7331 | AM110: =AL110 -> 973.7331 | AN110: =+AM110+AN54 -> 1105.4927 | AO110: =+AN110+AO54 -> 1246.6906 | AP110: =AO110 -> 1246.6906 | AQ110: =+AP110+AQ54 -> 1394.3344 | AR110: =+AQ110+AR54 -> 1552.1368 | AS110: =AR110 -> 1552.1368 | AT110: =+AS110+AT54 -> 1716.3082 | AU110: =+AT110+AU54 -> 1891.3778 | AV110: =AU110 -> 1891.3778
B111: Accumulated Gains/(Losses) | C111: A$m | F111: =E111 -> 0 | I111: -26.857 | J111: -40.4 | K111: =L111 -> -36.147 | L111: -36.147 | M111: -28.846 | N111: =O111 -> -21.671 | O111: -21.671 | P111: =+O111+P125+P147 -> -24.203161 | Q111: =+P111+Q125+Q147 -> -28.0952 | R111: =Q111 -> -28.0952 | S111: =+R111+S125+S147 -> -36.717924 | T111: =+S111+T125+T147 -> -49.468254 | U111: =T111 -> -49.468254 | V111: =+U111+V125+V147 -> -68.011146 | W111: =+V111+W125+W147 -> -87.332177 | X111: =W111 -> -87.332177 | Y111: =+X111+Y125+Y147 -> -116.45198 | Z111: =+Y111+Z125+Z147 -> -147.15491 | AA111: =Z111 -> -147.15491 | AB111: =+AA111+AB125+AB147 -> -186.03405 | AC111: =+AB111+AC125+AC147 -> -229.71676 | AD111: =AC111 -> -229.71676 | AE111: =+AD111+AE125+AE147 -> -280.03006 | AF111: =+AE111+AF125+AF147 -> -335.74175 | AG111: =AF111 -> -335.74175 | AH111: =+AG111+AH125+AH147 -> -398.92994 | AI111: =+AH111+AI125+AI147 -> -468.17978 | AJ111: =AI111 -> -468.17978 | AK111: =+AJ111+AK125+AK147 -> -545.81331 | AL111: =+AK111+AL125+AL147 -> -630.24634 | AM111: =AL111 -> -630.24634 | AN111: =+AM111+AN125+AN147 -> -720.45576 | AO111: =+AN111+AO125+AO147 -> -817.45008 | AP111: =AO111 -> -817.45008 | AQ111: =+AP111+AQ125+AQ147 -> -919.07812 | AR111: =+AQ111+AR125+AR147 -> -1028.009 | AS111: =AR111 -> -1028.009 | AT111: =+AS111+AT125+AT147 -> -1141.5183 | AU111: =+AT111+AU125+AU147 -> -1262.8621 | AV111: =AU111 -> -1262.8621
C113: A$m | F113: =+F109+F110+F111 -> 0 | I113: =+I109+I110+I111 -> 87.965 | J113: =+J109+J110+J111 -> 347.37 | K113: =+K109+K110+K111 -> 353.979 | L113: =+L109+L110+L111 -> 353.979 | M113: =+M109+M110+M111 -> 367.633 | N113: =+N109+N110+N111 -> 380.124 | O113: =+O109+O110+O111 -> 380.124 | P113: =+P109+P110+P111 -> 387.38656 | ... AV113: =+AV109+AV110+AV111 -> 1003.5037
B115: Test | F115: =IF(ABS(F90-(F106-F113)<0.1), "OK","ERR") -> OK | I115: =IF(ABS(I90-(I106-I113)<0.1), "OK","ERR") -> ERR | J115: =IF(ABS(J90-(J106-J113)<0.1), "OK","ERR") -> ERR | K115: =IF(ABS(K90-(K106-K113)<0.1), "OK","ERR") -> ERR | L115: =IF(ABS(L90-(L106-L113)<0.1), "OK","ERR") -> ERR | M115: =IF(ABS(M90-(M106-M113)<0.1), "OK","ERR") -> ERR | N115: =IF(ABS(N90-(N106-N113)<0.1), "OK","ERR") -> ERR | O115: =IF(ABS(O90-(O106-O113)<0.1), "OK","ERR") -> ERR | P115: =IF(ABS(P90-(P106-P113)<0.1), "OK","ERR") -> ERR | ... AV115: =IF(ABS(AV90-(AV106-AV113)<0.1), "OK","ERR") -> ERR
F116: =+F90-F106-F113 -> 0 | I116: =+I90-I106-I113 -> 0 | J116: =+J90-J106-J113 -> 0 | K116: =+K90-K106-K113 -> 0 | L116: =+L90-L106-L113 -> 0 | M116: =+M90-M106-M113 -> 0 | N116: =+N90-N106-N113 -> 0 | O116: =+O90-O106-O113 -> 0 | P116: =+P90-P106-P113 -> 0 | ... AV116: =+AV90-AV106-AV113 -> -2.3824418e-07
A118: l | B118: Cash Flow statement
B121: Operating activities
A123: CF_EBIT | B123: EBIT | C123: A$m | F123: 7.2 | G123: 1.6 | H123: =+I123-G123 -> 2.1 | I123: 3.7 | J123: 8.8 | K123: =+L123-J123 -> 4.8 | L123: 13.6 | M123: 12.5 | N123: =O123-M123 -> 12.9 | O123: 25.4 | P123: =+P38 -> 16.894431 | Q123: =+Q38 -> 19.779165 | R123: =P123+Q123 -> 36.673596 | S123: =+S38 -> 29.563124 | T123: =+T38 -> 37.66463 | U123: =S123+T123 -> 67.227753 | V123: =+V38 -> 50.457005 | W123: =+W38 -> 51.801084 | X123: =V123+W123 -> 102.25809 | Y123: =+Y38 -> 71.122725 | Z123: =+Z38 -> 74.537903 | AA123: =Y123+Z123 -> 145.66063 | AB123: =+AB38 -> 90.099437 | AC123: =+AC38 -> 99.716248 | AD123: =AB123+AC123 -> 189.81568 | AE123: =+AE38 -> 111.93056 | AF123: =+AF38 -> 122.67966 | AG123: =AE123+AF123 -> 234.61021 | AH123: =+AH38 -> 136.21821 | AI123: =+AI38 -> 148.22537 | AJ123: =AH123+AI123 -> 284.44359 | AK123: =+AK38 -> 163.17916 | AL123: =+AL38 -> 176.58148 | AM123: =AK123+AL123 -> 339.76064 | AN123: =+AN38 -> 186.69101 | AO123: =+AO38 -> 199.99931 | AP123: =AN123+AO123 -> 386.69032 | AQ123: =+AQ38 -> 207.70352 | AR123: =+AR38 -> 221.99338 | AS123: =AQ123+AR123 -> 429.6969 | AT123: =+AT38 -> 229.38211 | AU123: =+AU38 -> 244.67897 | AV123: =AT123+AU123 -> 474.06108
A124: CF_D&A | B124: Depreciation and amortisation | C124: A$m | F124: 14.5 | G124: 12.6 | H124: =+I124-G124 -> 13 | I124: 25.6 | J124: 15.9 | K124: =+L124-J124 -> 15.223 | L124: 31.123 | M124: 19.08 | N124: =O124-M124 -> 20.601 | O124: 39.681 | P124: =-P35 -> 23.636061 | Q124: =-Q35 -> 25.042784 | R124: =P124+Q124 -> 48.678845 | S124: =-S35 -> 28.364531 | T124: =-T35 -> 30.096672 | U124: =S124+T124 -> 58.461202 | V124: =-V35 -> 33.735951 | W124: =-W35 -> 35.743004 | X124: =V124+W124 -> 69.478955 | Y124: =-Y35 -> 39.386736 | Z124: =-Z35 -> 41.737179 | AA124: =Y124+Z124 -> 81.123915 | AB124: =-AB35 -> 45.137307 | AC124: =-AC35 -> 47.838298 | AD124: =AB124+AC124 -> 92.975605 | AE124: =-AE35 -> 50.969655 | AF124: =-AF35 -> 53.996458 | AG124: =AE124+AF124 -> 104.96611 | AH124: =-AH35 -> 57.177471 | AI124: =-AI35 -> 60.54556 | AJ124: =AH124+AI124 -> 117.72303 | AK124: =-AK35 -> 63.778715 | AL124: =-AL35 -> 67.503768 | AM124: =AK124+AL124 -> 131.28248 | AN124: =-AN35 -> 69.211537 | AO124: =-AO35 -> 73.194748 | AP124: =AN124+AO124 -> 142.40629 | AQ124: =-AQ35 -> 74.455764 | AR124: =-AR35 -> 78.700527 | AS124: =AQ124+AR124 -> 153.15629 | AT124: =-AT35 -> 79.852085 | AU124: =-AU35 -> 84.359988 | AV124: =AT124+AU124 -> 164.21207
B125: Equity settled share-based payments | C125: A$m | F125: 1.4 | G125: 2.7 | H125: =+I125-G125 -> 1 | I125: 3.7 | J125: 5.7 | K125: =+L125-J125 -> 5.442 | L125: 11.142 | M125: 4.587 | N125: =+O125-M125 -> 4.431 | O125: 9.018 | P125: =+R125*0.5 -> 4.509 | Q125: =+R125-P125 -> 4.509 | R125: =+O125 -> 9.018 | S125: =+U125*0.5 -> 4.509 | T125: =+U125-S125 -> 4.509 | U125: =+R125 -> 9.018 | V125: =+X125*0.5 -> 4.509 | W125: =+X125-V125 -> 4.509 | X125: =+U125 -> 9.018 | Y125: =+AA125*0.5 -> 4.509 | Z125: =+AA125-Y125 -> 4.509 | AA125: =+X125 -> 9.018 | AB125: =+AD125*0.5 -> 4.509 | AC125: =+AD125-AB125 -> 4.509 | AD125: =+AA125 -> 9.018 | AE125: =+AG125*0.5 -> 4.509 | AF125: =+AG125-AE125 -> 4.509 | AG125: =+AD125 -> 9.018 | AH125: =+AJ125*0.5 -> 4.509 | AI125: =+AJ125-AH125 -> 4.509 | AJ125: =+AG125 -> 9.018 | AK125: =+AM125*0.5 -> 4.509 | AL125: =+AM125-AK125 -> 4.509 | AM125: =+AJ125 -> 9.018 | AN125: =+AP125*0.5 -> 4.509 | AO125: =+AP125-AN125 -> 4.509 | AP125: =+AM125 -> 9.018 | AQ125: =+AS125*0.5 -> 4.509 | AR125: =+AS125-AQ125 -> 4.509 | AS125: =+AP125 -> 9.018 | AT125: =+AV125*0.5 -> 4.509 | AU125: =+AV125-AT125 -> 4.509 | AV125: =+AS125 -> 9.018
A126: Chg_working_Cap | B126: Change in operating assets and liabilities | C126: A$m | F126: -1.1 | G126: -2.7 | H126: =+I126-G126 -> 5.8 | I126: 3.1 | J126: -9.4 | K126: {=SUM(J76:J79,-K76:K79)+SUM(K93:K97,-J93:J97)} -> 19.941 | L126: =+J126+K126 -> 10.541 | M126: =7.353-1.424-1.506-7.496-0.72+0.071-0.357 -> -4.079 | N126: {=SUM(M76:M79,-N76:N79)+SUM(N93:N97,-M93:M97)} -> 14.813 | O126: =M126+N126 -> 10.734 | P126: {=SUM(O76:O79,-P76:P79)+SUM(P93:P97,-O93:O97)} -> 5.4938649 | Q126: {=SUM(P76:P79,-Q76:Q79)+SUM(Q93:Q97,-P93:P97)} -> 1.289105 | R126: =P126+Q126 -> 6.7829699 | S126: {=SUM(R76:R79,-S76:S79)+SUM(S93:S97,-R93:R97)} -> 2.6250848 | T126: {=SUM(S76:S79,-T76:T79)+SUM(T93:T97,-S93:S97)} -> 1.4854842 | U126: =S126+T126 -> 4.1105691 | V126: {=SUM(U76:U79,-V76:V79)+SUM(V93:V97,-U93:U97)} -> 3.0046833 | W126: {=SUM(V76:V79,-W76:W79)+SUM(W93:W97,-V93:V97)} -> 1.9502951 | X126: =V126+W126 -> 4.9549784 | Y126: {=SUM(X76:X79,-Y76:Y79)+SUM(Y93:Y97,-X93:X97)} -> 2.0346786 | Z126: {=SUM(Y76:Y79,-Z76:Z79)+SUM(Z93:Z97,-Y93:Y97)} -> 2.0035847 | AA126: =Y126+Z126 -> 4.0382633 | AB126: {=SUM(AA76:AA79,-AB76:AB79)+SUM(AB93:AB97,-AA93:AA97)} -> 2.3975852 | AC126: {=SUM(AB76:AB79,-AC76:AC79)+SUM(AC93:AC97,-AB93:AB97)} -> 1.7700777 | AD126: =AB126+AC126 -> 4.167663 | AE126: {=SUM(AD76:AD79,-AE76:AE79)+SUM(AE93:AE97,-AD93:AD97)} -> 2.8988016 | AF126: {=SUM(AE76:AE79,-AF76:AF79)+SUM(AF93:AF97,-AE93:AE97)} -> 1.9908748 | AG126: =AE126+AF126 -> 4.8896764 | AH126: {=SUM(AG76:AG79,-AH76:AH79)+SUM(AH93:AH97,-AG93:AG97)} -> 3.050412 | AI126: {=SUM(AH76:AH79,-AI76:AI79)+SUM(AI93:AI97,-AH93:AH97)} -> 2.2293673 | AJ126: =AH126+AI126 -> 5.2797793 | AK126: {=SUM(AJ76:AJ79,-AK76:AK79)+SUM(AK93:AK97,-AJ93:AJ97)} -> 3.2101514 | AL126: {=SUM(AK76:AK79,-AL76:AL79)+SUM(AL93:AL97,-AK93:AK97)} -> 2.4867517 | AM126: =AK126+AL126 -> 5.6969031 | AN126: {=SUM(AM76:AM79,-AN76:AN79)+SUM(AN93:AN97,-AM93:AM97)} -> 2.3957525 | AO126: {=SUM(AN76:AN79,-AO76:AO79)+SUM(AO93:AO97,-AN93:AN97)} -> 2.6010869 | AP126: =AN126+AO126 -> 4.9968393 | AQ126: {=SUM(AP76:AP79,-AQ76:AQ79)+SUM(AQ93:AQ97,-AP93:AP97)} -> 2.1275781 | AR126: {=SUM(AQ76:AQ79,-AR76:AR79)+SUM(AR93:AR97,-AQ93:AQ97)} -> 2.8093209 | AS126: =AQ126+AR126 -> 4.936899 | AT126: {=SUM(AS76:AS79,-AT76:AT79)+SUM(AT93:AT97,-AS93:AS97)} -> 2.221232 | AU126: {=SUM(AT76:AT79,-AU76:AU79)+SUM(AU93:AU97,-AT93:AT97)} -> 3.0298211 | AV126: =AT126+AU126 -> 5.2510531
B127: Other non-cash items | C127: A$m | F127: -0.1 | G127: 0.8 | H127: =+I127-G127 -> -0.3 | I127: 0.5 | J127: 0 | K127: =L127-J127 -> 1.795 | L127: =L130-L123-L124-L125-L126-L129-L128 -> 1.795 | M127: =M130-M123-M124-M125-M126-M129-M128 -> -7.454 | N127: =O127-M127 -> -0.416 | O127: =O130-O123-O124-O125-O126-O129-O128 -> -7.87 | P127: 0 | Q127: 0 | R127: =P127+Q127 -> 0 | S127: 0 | T127: 0 | U127: =S127+T127 -> 0 | V127: 0 | W127: 0 | X127: =V127+W127 -> 0 | Y127: 0 | Z127: 0 | AA127: =Y127+Z127 -> 0 | AB127: 0 | AC127: 0 | AD127: =AB127+AC127 -> 0 | AE127: 0 | AF127: 0 | AG127: =AE127+AF127 -> 0 | AH127: 0 | AI127: 0 | AJ127: =AH127+AI127 -> 0 | AK127: 0 | AL127: 0 | AM127: =AK127+AL127 -> 0 | AN127: 0 | AO127: 0 | AP127: =AN127+AO127 -> 0 | AQ127: 0 | AR127: 0 | AS127: =AQ127+AR127 -> 0 | AT127: 0 | AU127: 0 | AV127: =AT127+AU127 -> 0
B128: Change in franchisee receivables | C128: A$m | F128: -1.6 | G128: -2 | H128: =+I128-G128 -> 0.4 | I128: -1.6 | J128: -3.9 | K128: =J78-K78 -> -1.499 | L128: =+J128+K128 -> -5.399 | N128: =M78-N78 -> -0.247 | O128: =+M128+N128 -> -0.247 | P128: =O78-P78 -> 0 | Q128: =P78-Q78 -> 0 | R128: =P128+Q128 -> 0 | S128: =R78-S78 -> 0 | T128: =S78-T78 -> 0 | U128: =S128+T128 -> 0 | V128: =U78-V78 -> 0 | W128: =V78-W78 -> 0 | X128: =V128+W128 -> 0 | Y128: =X78-Y78 -> 0 | Z128: =Y78-Z78 -> 0 | AA128: =Y128+Z128 -> 0 | AB128: =AA78-AB78 -> 0 | AC128: =AB78-AC78 -> 0 | AD128: =AB128+AC128 -> 0 | AE128: =AD78-AE78 -> 0 | AF128: =AE78-AF78 -> 0 | AG128: =AE128+AF128 -> 0 | AH128: =AG78-AH78 -> 0 | AI128: =AH78-AI78 -> 0 | AJ128: =AH128+AI128 -> 0 | AK128: =AJ78-AK78 -> 0 | AL128: =AK78-AL78 -> 0 | AM128: =AK128+AL128 -> 0 | AN128: =AM78-AN78 -> 0 | AO128: =AN78-AO78 -> 0 | AP128: =AN128+AO128 -> 0 | AQ128: =AP78-AQ78 -> 0 | AR128: =AQ78-AR78 -> 0 | AS128: =AQ128+AR128 -> 0 | AT128: =AS78-AT78 -> 0 | AU128: =AT78-AU78 -> 0 | AV128: =AT128+AU128 -> 0
A129: CF_Income_tax | B129: Income Tax | C129: A$m | F129: -0.1 | G129: -1 | H129: =+I129-G129 -> -1.5 | I129: -2.5 | J129: -2.8 | K129: =+L129-J129 -> -3.702 | L129: -6.502 | M129: -5.434 | N129: =+O129-M129 -> -13.955 | O129: -19.389 | P129: =Assumptions!P307 -> -8.3973822 | Q129: =Assumptions!Q307 -> -9.0504388 | R129: =P129+Q129 -> -17.447821 | S129: =Assumptions!S307 -> -11.043712 | T129: =Assumptions!T307 -> -12.979347 | U129: =S129+T129 -> -24.023059 | V129: =Assumptions!V307 -> -16.067131 | W129: =Assumptions!W307 -> -16.141509 | X129: =V129+W129 -> -32.20864 | Y129: =Assumptions!Y307 -> -21.520626 | Z129: =Assumptions!Z307 -> -22.568117 | AA129: =Y129+Z129 -> -44.088743 | AB129: =Assumptions!AB307 -> -26.764626 | AC129: =Assumptions!AC307 -> -29.597355 | AD129: =AB129+AC129 -> -56.361981 | AE129: =Assumptions!AE307 -> -32.912806 | AF129: =Assumptions!AF307 -> -36.081402 | AG129: =AE129+AF129 -> -68.994208 | AH129: =Assumptions!AH307 -> -39.834242 | AI129: =Assumptions!AI307 -> -43.376861 | AJ129: =AH129+AI129 -> -83.211103 | AK129: =Assumptions!AK307 -> -47.598791 | AL129: =Assumptions!AL307 -> -51.557006 | AM129: =AK129+AL129 -> -99.155797 | AN129: =Assumptions!AN307 -> -54.583274 | AO129: =Assumptions!AO307 -> -58.539765 | AP129: =AN129+AO129 -> -113.12304 | AQ129: =Assumptions!AQ307 -> -60.928695 | AR129: =Assumptions!AR307 -> -65.177678 | AS129: =AQ129+AR129 -> -126.10637 | AT129: =Assumptions!AT307 -> -67.52942 | AU129: =Assumptions!AU307 -> -72.078628 | AV129: =AT129+AU129 -> -139.60805
A130: OCF | B130: Net cash from operating activities | C130: A$m | F130: =SUM(F123:F129) -> 20.2 | G130: =SUM(G123:G129) -> 12 | H130: =SUM(H123:H129) -> 20.5 | I130: =SUM(I123:I129) -> 32.5 | J130: =SUM(J123:J129) -> 14.3 | K130: =+L130-J130 -> 42 | L130: 56.3 | M130: 19.2 | N130: =+O130-M130 -> 38.127 | O130: 57.327 | P130: =SUM(P123:P129) -> 42.135975 | Q130: =SUM(Q123:Q129) -> 41.569615 | R130: =SUM(R123:R129) -> 83.70559 | S130: =SUM(S123:S129) -> 54.018027 | T130: =SUM(T123:T129) -> 60.776439 | U130: =SUM(U123:U129) -> 114.79447 | V130: =SUM(V123:V129) -> 75.639508 | W130: =SUM(W123:W129) -> 77.861874 | ... AV130: =SUM(AV123:AV129) -> 512.93416
B133: Investing activities
A134: CF_PPE | B134: Net payments for PP&E | C134: A$m | F134: -19.4 | G134: -14.7 | H134: =+I134-G134 -> -25 | I134: -39.7 | J134: -14.9 | K134: =+L134-J134 -> -18.596 | L134: -33.496 | M134: -21.855 | N134: =+O134-M134 -> -39.471 | O134: -61.326 | P134: =-Assumptions!P336 -> -27.374532 | Q134: =-Assumptions!Q336 -> -27.374532 | R134: =P134+Q134 -> -54.749065 | S134: =-Assumptions!S336 -> -36.510851 | T134: =-Assumptions!T336 -> -36.510851 | U134: =S134+T134 -> -73.021702 | V134: =-Assumptions!V336 -> -33.283476 | W134: =-Assumptions!W336 -> -33.283476 | X134: =V134+W134 -> -66.566951 | Y134: =-Assumptions!Y336 -> -36.891486 | Z134: =-Assumptions!Z336 -> -36.891486 | AA134: =Y134+Z134 -> -73.782972 | AB134: =-Assumptions!AB336 -> -38.273991 | AC134: =-Assumptions!AC336 -> -38.273991 | AD134: =AB134+AC134 -> -76.547982 | AE134: =-Assumptions!AE336 -> -42.077317 | AF134: =-Assumptions!AF336 -> -42.077317 | AG134: =AE134+AF134 -> -84.154634 | AH134: =-Assumptions!AH336 -> -46.17204 | AI134: =-Assumptions!AI336 -> -46.17204 | AJ134: =AH134+AI134 -> -92.34408 | AK134: =-Assumptions!AK336 -> -50.577958 | AL134: =-Assumptions!AL336 -> -50.577958 | AM134: =AK134+AL134 -> -101.15592 | AN134: =-Assumptions!AN336 -> -51.835084 | AO134: =-Assumptions!AO336 -> -51.835084 | AP134: =AN134+AO134 -> -103.67017 | AQ134: =-Assumptions!AQ336 -> -55.614599 | AR134: =-Assumptions!AR336 -> -55.614599 | AS134: =AQ134+AR134 -> -111.2292 | AT134: =-Assumptions!AT336 -> -59.57429 | AU134: =-Assumptions!AU336 -> -59.57429 | AV134: =AT134+AU134 -> -119.14858
A135: CF_Intangibles | B135: Net payments for Intangibles | C135: A$m | F135: -7 | G135: -1.4 | H135: =+I135-G135 -> -1.5 | I135: -2.9 | J135: 0 | K135: =+L135-J135 -> -0.063 | L135: -0.063 | M135: -0.008 | N135: =+O135-M135 -> -0.029 | O135: -0.037 | P135: =-Assumptions!P376 -> -0.022864509 | Q135: =-Assumptions!Q376 -> -5.6344219 | R135: =P135+Q135 -> -5.6572864 | S135: =-Assumptions!S376 -> -3.2571174 | T135: =-Assumptions!T376 -> -7.0472159 | U135: =S135+T135 -> -10.304333 | V135: =-Assumptions!V376 -> -5.9997024 | W135: =-Assumptions!W376 -> -6.5055141 | X135: =V135+W135 -> -12.505216 | Y135: =-Assumptions!Y376 -> -7.1678759 | Z135: =-Assumptions!Z376 -> -7.7790102 | AA135: =Y135+Z135 -> -14.946886 | AB135: =-Assumptions!AB376 -> -8.3749102 | AC135: =-Assumptions!AC376 -> -9.1039654 | AD135: =AB135+AC135 -> -17.478876 | AE135: =-Assumptions!AE376 -> -9.6385871 | AF135: =-Assumptions!AF376 -> -10.440911 | AG135: =AE135+AF135 -> -20.079498 | AH135: =-Assumptions!AH376 -> -11.008917 | AI135: =-Assumptions!AI376 -> -11.890102 | AJ135: =AH135+AI135 -> -22.899019 | AK135: =-Assumptions!AK376 -> -12.493363 | AL135: =-Assumptions!AL376 -> -13.459365 | AM135: =AK135+AL135 -> -25.952728 | AN135: =-Assumptions!AN376 -> -13.8041 | AO135: =-Assumptions!AO376 -> -14.784719 | AP135: =AN135+AO135 -> -28.588819 | AQ135: =-Assumptions!AQ376 -> -15.071198 | AR135: =-Assumptions!AR376 -> -16.119265 | AS135: =AQ135+AR135 -> -31.190463 | AT135: =-Assumptions!AT376 -> -16.393512 | AU135: =-Assumptions!AU376 -> -17.511666 | AV135: =AT135+AU135 -> -33.905178
B136: Net payments for purchases of business | C136: A$m | F136: -5.3 | G136: -5.4 | H136: =+I136-G136 -> -0.3 | I136: -5.7 | J136: 0 | K136: =L136-J136 -> -278.259 | L136: =L137-L134-L135 -> -278.259 | M136: =M137-M134-M135 -> 13.783 | N136: =O136-M136 -> 13.029 | O136: =O137-O134-O135 -> 26.812 | P136: 0 | Q136: 0 | R136: =P136+Q136 -> 0 | S136: 0 | T136: 0 | U136: =S136+T136 -> 0 | V136: 0 | W136: 0 | X136: =V136+W136 -> 0 | Y136: 0 | Z136: 0 | AA136: =Y136+Z136 -> 0 | AB136: 0 | AC136: 0 | AD136: =AB136+AC136 -> 0 | AE136: 0 | AF136: 0 | AG136: =AE136+AF136 -> 0 | AH136: 0 | AI136: 0 | AJ136: =AH136+AI136 -> 0 | AK136: 0 | AL136: 0 | AM136: =AK136+AL136 -> 0 | AN136: 0 | AO136: 0 | AP136: =AN136+AO136 -> 0 | AQ136: 0 | AR136: 0 | AS136: 0 | AT136: 0 | AU136: 0 | AV136: 0
A137: Net_CF_Investing | B137: Net cash from investing activities | C137: A$m | F137: =SUM(F134:F136) -> -31.7 | G137: =SUM(G134:G136) -> -21.5 | H137: =SUM(H134:H136) -> -26.8 | I137: =SUM(I134:I136) -> -48.3 | J137: =SUM(J134:J136) -> -14.9 | K137: =L137-J137 -> -296.918 | L137: -311.818 | M137: -8.08 | N137: =O137-M137 -> -26.471 | O137: -34.551 | P137: =SUM(P134:P136) -> -27.397397 | Q137: =SUM(Q134:Q136) -> -33.008954 | R137: =SUM(R134:R136) -> -60.406351 | S137: =SUM(S134:S136) -> -39.767969 | T137: =SUM(T134:T136) -> -43.558067 | U137: =SUM(U134:U136) -> -83.326036 | V137: =SUM(V134:V136) -> -39.283178 | W137: =SUM(W134:W136) -> -39.78899 | ... AV137: =SUM(AV134:AV136) -> -153.05376
B140: Financing activities
...

Sheet Assumptions
B2: Guzman Y Gomez (GYG.AX)
B3: Assumptions
F4: Pro forma | G4: Pro forma | H4: Pro forma | I4: Pro forma | J4: Pro forma
B5: Year ended 30 June | C5: unit | D5: FY20 | E5: FY21 | F5: FY22 | G5: 1H23 | H5: 2H23 | I5: FY23 | J5: 1H24 | K5: 2H24 | L5: FY24 | M5: 1H25 | N5: 2H25 | O5: FY25 | P5: 1H26e | Q5: 2H26e | R5: FY26e | S5: 1H27e | T5: 2H27e | U5: FY27e | V5: 1H28e | W5: 2H28e | X5: FY28e | Y5: 1H29e | Z5: 2H29e | AA5: FY29e | AB5: 1H30e | AC5: 2H30e | AD5: FY30e | AE5: 1H31e | AF5: 2H31e | AG5: FY31e | AH5: 1H32e | AI5: 2H32e | AJ5: FY32e | AK5: 1H33e | AL5: 2H33e | AM5: FY33e | AN5: 1H34e | AO5: 2H34e | AP5: FY34e | AQ5: 1H35e | AR5: 2H35e | AS5: FY35e | AT5: 1H36e | AU5: 2H36e | AV5: FY36e
A7: l | B7: Summary
B9: Network Sales
B10: Aust (Corp + Franchise) | C10: A$m | F10: 535.4 | G10: 334.9 | H10: =I10-G10 -> 368 | I10: 702.9 | J10: 438.6 | K10: =L10-J10 -> 456 | L10: 894.6 | M10: 538.2 | N10: =O10-M10 -> 556.4 | O10: 1094.6 | P10: =+P68+P89 -> 636.45455 | Q10: =+Q68+Q89 -> 678.15481 | R10: =+R68+R89 -> 1314.6094 | S10: =+S68+S89 -> 750.19698 | T10: =+T68+T89 -> 823.67023 | U10: =+U68+U89 -> 1573.8672 | V10: =+V68+V89 -> 895.52982 | W10: =+W68+W89 -> 983.49275 | ... AV10: =+AV68+AV89 -> 4976.458 | BF10: =(AD10/O10)^(1/5)-1 -> 0.18870886
B11: SG | C11: A$m | F11: 31.4 | G11: 21.5 | H11: =I11-G11 -> 21.6 | I11: 43.1 | J11: 22.2 | K11: =L11-J11 -> 24.2 | L11: 46.4 | M11: 30.2 | N11: =O11-M11 -> 34.5 | O11: 64.7 | P11: =+P104 -> 34.566757 | Q11: =+R11-P11 -> 40.17877 | R11: =+R104 -> 74.745526 | S11: =+S104 -> 39.044723 | T11: =+U11-S11 -> 44.312788 | U11: =+U104 -> 83.357511 | V11: =+V104 -> 41.74723 | W11: =+X11-V11 -> 47.317064 | X11: =+X104 -> 89.064294 | Y11: =+Y104 -> 44.517728 | Z11: =+AA11-Y11 -> 50.399363 | AA11: =+AA104 -> 94.917091 | AB11: =+AB104 -> 47.362336 | AC11: =+AD11-AB11 -> 53.566171 | AD11: =+AD104 -> 100.92851 | AE11: =+AE104 -> 50.286772 | AF11: =+AG11-AE11 -> 56.823606 | AG11: =+AG104 -> 107.11038 | AH11: =+AH104 -> 53.296473 | AI11: =+AJ11-AH11 -> 60.177521 | AJ11: =+AJ104 -> 113.47399 | AK11: =+AK104 -> 56.396676 | AL11: =+AM11-AK11 -> 63.633593 | AM11: =+AM104 -> 120.03027 | AN11: =+AN104 -> 59.592488 | AO11: =+AP11-AN11 -> 67.197381 | AP11: =+AP104 -> 126.78987 | AQ11: =+AQ104 -> 62.888933 | AR11: =+AS11-AQ11 -> 70.874379 | AS11: =+AS104 -> 133.76331 | AT11: =+AT104 -> 66.290997 | AU11: =+AV11-AT11 -> 74.670055 | AV11: =+AV104 -> 140.96105 | BH11: =K14-234.2 -> 254.9
B12: JP | C12: A$m | F12: 5.8 | G12: 3.2 | H12: =I12-G12 -> 3.8 | I12: 7 | J12: 4.2 | K12: =L12-J12 -> 3.7 | L12: 7.9 | M12: 4.6 | N12: =O12-M12 -> 4.5 | O12: 9.1 | P12: =+P128 -> 5.06 | Q12: =+R12-P12 -> 5.405 | R12: =+R128 -> 10.465 | S12: =+S128 -> 6.233 | T12: =+U12-S12 -> 6.4994167 | U12: =+U128 -> 12.732417 | V12: =+V128 -> 7.2510567 | W12: =+X12-V12 -> 7.4548846 | X12: =+X128 -> 14.705941 | Y12: =+Y128 -> 8.2318575 | Z12: =+AA12-Y12 -> 8.3858561 | AA12: =+AA128 -> 16.617714 | AB12: =+AB128 -> 9.1946269 | AC12: =+AD12-AB12 -> 9.3064276 | AD12: =+AD128 -> 18.501054 | AE12: =+AE128 -> 10.151549 | AF12: =+AG12-AE12 -> 10.226041 | AG12: =+AG128 -> 20.37759 | AH12: =+AH128 -> 11.111034 | AI12: =+AJ12-AH12 -> 11.151483 | AJ12: =+AJ128 -> 22.262517 | AK12: =+AK128 -> 12.079282 | AL12: =+AM12-AK12 -> 12.087918 | AM12: =+AM128 -> 24.167199 | AN12: =+AN128 -> 13.06111 | AO12: =+AP12-AN12 -> 13.039465 | AP12: =+AP128 -> 26.100575 | AQ12: =+AQ128 -> 14.060437 | AR12: =+AS12-AQ12 -> 14.009545 | AS12: =+AS128 -> 28.069982 | AT12: =+AT128 -> 15.080567 | AU12: =+AV12-AT12 -> 15.001097 | AV12: =+AV128 -> 30.081664
B13: US | C13: A$m | F13: 2.5 | G13: 1.5 | H13: =I13-G13 -> 4.5 | I13: 6 | J13: 5.6 | K13: =L13-J13 -> 5.2 | L13: 10.8 | M13: 4.9 | N13: =O13-M13 -> 7.3 | O13: 12.2 | P13: =+P165 -> 8.0596875 | Q13: =+R13-P13 -> 8.9898125 | R13: =+R165 -> 17.0495 | S13: =+S165 -> 11.753109 | T13: =+U13-S13 -> 13.034241 | U13: =+U165 -> 24.78735 | V13: =+V165 -> 17.422256 | W13: =+X13-V13 -> 17.280034 | X13: =+X165 -> 34.70229 | Y13: =+Y165 -> 18.293369 | Z13: =+AA13-Y13 -> 18.144035 | AA13: =+AA165 -> 36.437405 | AB13: =+AB165 -> 19.208038 | AC13: =+AD13-AB13 -> 19.051237 | AD13: =+AD165 -> 38.259275 | AE13: =+AE165 -> 20.168439 | AF13: =+AG13-AE13 -> 20.003799 | AG13: =+AG165 -> 40.172238 | AH13: =+AH165 -> 21.176861 | AI13: =+AJ13-AH13 -> 21.003989 | AJ13: =+AJ165 -> 42.18085 | AK13: =+AK165 -> 22.235704 | AL13: =+AM13-AK13 -> 22.054188 | AM13: =+AM165 -> 44.289893 | AN13: =+AN165 -> 23.34749 | AO13: =+AP13-AN13 -> 23.156898 | AP13: =+AP165 -> 46.504388 | AQ13: =+AQ165 -> 24.514864 | AR13: =+AS13-AQ13 -> 24.314743 | AS13: =+AS165 -> 48.829607 | AT13: =+AT165 -> 25.740607 | AU13: =+AV13-AT13 -> 25.53048 | AV13: =+AV165 -> 51.271087 | BH13: 289
A14: Total_network_sales | B14: Total Network Sales | C14: A$m | F14: =SUM(F10:F13) -> 575.1 | G14: =SUM(G10:G13) -> 361.1 | H14: =SUM(H10:H13) -> 397.9 | I14: =SUM(I10:I13) -> 759 | J14: =SUM(J10:J13) -> 470.6 | K14: =SUM(K10:K13) -> 489.1 | L14: =SUM(L10:L13) -> 959.7 | M14: =SUM(M10:M13) -> 577.9 | ... AV14: =SUM(AV10:AV13) -> 5198.7718 | BH14: =+N14-BH13 -> 313.7 | BI14: =+BH14/BH13-1 -> 0.085467128
B15: % change | C15: % | M15: =+M14/J14-1 -> 0.2280068 | N15: =+N14/K14-1 -> 0.23226334 | O15: =+O14/L14-1 -> 0.2301761 | BH15: =+BH14/BH11-1 -> 0.2306787
B17: Revenue
A18: Revenue_Aust | B18: Aust (Corp + Franchise) | C18: A$m | F18: =+F68+F92 -> 168.027 | G18: =+G68+G92 -> 119.344 | H18: =+H68+H92 -> 132.0375 | I18: =+I68+I92 -> 251.3815 | J18: =+J68+J92 -> 161.968 | K18: =+K68+K92 -> 167.574 | L18: =+L68+L92 -> 329.542 | M18: =+M68+M92 -> 207.992 | ... AV18: =+AV68+AV92 -> 2216.8064 | BF18: =(AA18/L18)^(1/5)-1 -> 0.2399136
A19: Revenue_SG | B19: SG | C19: A$m | F19: =+F116 -> 1.099 | G19: =+G116 -> 0.7525 | H19: =+H116 -> 0.756 | I19: =+I116 -> 1.5085 | J19: =+J116 -> 0.777 | K19: =+K116 -> 0.847 | L19: =+L116 -> 1.624 | M19: =+M116 -> 1.057 | ... AV19: =+AV116 -> 4.9336368
A20: Revenue_JP | B20: JP | C20: A$m | F20: =+F139 -> 0.174 | G20: =+G139 -> 0.096 | H20: =+H139 -> 0.114 | I20: =+I139 -> 0.21 | J20: =+J139 -> 0.126 | K20: =+K139 -> 0.111 | L20: =+L139 -> 0.237 | M20: =+M139 -> 0.138 | ... AV20: =+AV139 -> 0.90244992
A21: Revenue_US | B21: US | C21: A$m | F21: =+F165 -> 2.5 | G21: =+G165 -> 1.5 | H21: =+H165 -> 4.5 | I21: =+I165 -> 6 | J21: =+J165 -> 5.6 | K21: =+K165 -> 5.2 | L21: =+L165 -> 10.8 | M21: =+M167+M173 -> 3.336 | N21: =+N167+N173 -> 5.864 | O21: =+O167+O173 -> 9.2 | P21: =+P167+P173 -> 5.4134694 | Q21: =+Q167+Q173 -> 7.1694426 | R21: =+R167+R173 -> 12.73775 | S21: =+S167+S173 -> 7.8255 | T21: =+T167+T173 -> 10.327421 | ... AV21: =+AV167+AV173 -> 37.702678
A22: Revenue_total_ex_Other | B22: Total Revenue | C22: A$m | F22: =SUM(F18:F21) -> 171.8 | G22: =SUM(G18:G21) -> 121.6925 | H22: =SUM(H18:H21) -> 137.4075 | I22: =SUM(I18:I21) -> 259.1 | J22: =SUM(J18:J21) -> 168.471 | K22: =SUM(K18:K21) -> 173.732 | L22: =SUM(L18:L21) -> 342.203 | M22: =SUM(M18:M21) -> 212.523 | ... AV22: =SUM(AV18:AV21) -> 2260.3452
U23: =+(U18/L18)^(1/3)-1 -> 0.26385277
B24: Reported underlying revenue | C24: A$m | F24: 171.8 | G24: 121.2 | H24: =+I24-G24 -> 137.8 | I24: 259 | J24: 167.5 | K24: =+L24-J24 -> 174.7 | L24: 342.2 | M24: 212.4 | N24: =O24-M24 -> 223.582 | O24: 435.982
A27: l | B27: Australia / Singapore / Japan
B29: Aust
B30: Restaurants BOP (Corp + Franchised) | C30: # | G30: =+F33 -> 150 | H30: =+G33 -> 157 | I30: =+F33 -> 150 | J30: =+I33 -> 171 | K30: =+J33 -> 183 | L30: =+I33 -> 171 | M30: =+L33 -> 194 | N30: =+M33 -> 210 | O30: =+L33 -> 194 | P30: =+O33 -> 224 | Q30: =+P33 -> 236 | R30: =+O33 -> 224 | S30: =+R33 -> 256 | T30: =+S33 -> 273.5 | U30: =+R33 -> 256 | V30: =+U33 -> 291 | W30: =+V33 -> 311 | X30: =+U33 -> 291 | Y30: =+X33 -> 331 | Z30: =+Y33 -> 351 | AA30: =+X33 -> 331 | AB30: =+AA33 -> 371 | AC30: =+AB33 -> 388.5 | AD30: =+AA33 -> 371 | AE30: =+AD33 -> 406 | AF30: =+AE33 -> 423.5 | AG30: =+AD33 -> 406 | AH30: =+AG33 -> 441 | AI30: =+AH33 -> 458.5 | AJ30: =+AG33 -> 441 | AK30: =+AJ33 -> 476 | AL30: =+AK33 -> 493.5 | AM30: =+AJ33 -> 476 | AN30: =+AM33 -> 511 | AO30: =+AN33 -> 526 | AP30: =+AM33 -> 511 | AQ30: =+AP33 -> 541 | AR30: =+AQ33 -> 556 | AS30: =+AP33 -> 541 | AT30: =+AS33 -> 571 | AU30: =+AT33 -> 586 | AV30: =+AS33 -> 571
B31: Acquisitions / disposals | C31: # | G31: 0 | H31: 0 | I31: =+I61 -> 0 | J31: =+J61 -> 0 | K31: =+K61 -> 0 | L31: =+L61 -> 0 | M31: =+M61 -> 0 | N31: =+N61 -> 0 | O31: =+O61 -> 0 | P31: =+P61 -> 0 | ... AV31: =+AV61 -> 0
A32: Aust_net_openings | B32: Net openings | C32: # | G32: 7 | H32: 14 | I32: =+I62+I83 -> 21 | J32: =+J62+J83 -> 12 | K32: =+K62+K83 -> 11 | L32: =+L62+L83 -> 23 | M32: =+M62+M83 -> 16 | N32: =+N62+N83 -> 14 | O32: =+O62+O83 -> 30 | P32: =+P62+P83 -> 12 | ... AV32: =+AV62+AV83 -> 30
A33: Aust_Total_stores | B33: Restaurants EOP | C33: # | F33: =+F63+F84 -> 150 | G33: =+G63+G84 -> 157 | H33: =+H63+H84 -> 171 | I33: =+I63+I84 -> 171 | J33: =+J63+J84 -> 183 | K33: =+K30+K31+K32 -> 194 | L33: =+L30+L31+L32 -> 194 | M33: =+M30+M31+M32 -> 210 | N33: =+N30+N31+N32 -> 224 | O33: =+O30+O31+O32 -> 224 | P33: =+P30+P31+P32 -> 236 | Q33: =+Q30+Q31+Q32 -> 256 | R33: =+R30+R31+R32 -> 256 | ... AV33: =+AV30+AV31+AV32 -> 601 | BF33: =(AD33/O33)^(1/5)-1 -> 0.12630394 | BI33: =704/305-1 -> 1.3081967
A34: Aust_total_network_gth | B34: YoY % gth | C34: % | I34: =+I33/F33-1 -> 0.14 | J34: =+J33/G33-1 -> 0.1656051 | K34: =+K33/H33-1 -> 0.13450292 | L34: =+L33/I33-1 -> 0.13450292 | M34: =+M33/J33-1 -> 0.14754098 | N34: =+N33/K33-1 -> 0.15463918 | O34: =+O33/L33-1 -> 0.15463918 | P34: =+P33/M33-1 -> 0.12380952 | ... AV34: =+AV33/AS33-1 -> 0.052539405
B35: Average stores | C35: # | G35: =(G33+F33)/2 -> 153.5 | H35: =(H33+G33)/2 -> 164 | I35: =+(I33+F33)/2 -> 160.5 | J35: =(J33+I33)/2 -> 177 | K35: =(K33+J33)/2 -> 188.5 | L35: =+(L33+I33)/2 -> 182.5 | M35: =(M33+K33)/2 -> 202 | N35: =(N33+M33)/2 -> 217 | O35: =+(O33+L33)/2 -> 209 | P35: =(P33+N33)/2 -> 230 | Q35: =(Q33+P33)/2 -> 246 | R35: =+(R33+O33)/2 -> 240 | S35: =(S33+Q33)/2 -> 264.75 | T35: =(T33+S33)/2 -> 282.25 | U35: =+(U33+R33)/2 -> 273.5 | V35: =(V33+T33)/2 -> 301 | W35: =(W33+V33)/2 -> 321 | X35: =+(X33+U33)/2 -> 311 | Y35: =(Y33+W33)/2 -> 341 | Z35: =(Z33+Y33)/2 -> 361 | AA35: =+(AA33+X33)/2 -> 351 | AB35: =(AB33+Z33)/2 -> 379.75 | AC35: =(AC33+AB33)/2 -> 397.25 | AD35: =+(AD33+AA33)/2 -> 388.5 | AE35: =(AE33+AC33)/2 -> 414.75 | AF35: =(AF33+AE33)/2 -> 432.25 | AG35: =+(AG33+AD33)/2 -> 423.5 | AH35: =(AH33+AF33)/2 -> 449.75 | AI35: =(AI33+AH33)/2 -> 467.25 | AJ35: =+(AJ33+AG33)/2 -> 458.5 | AK35: =(AK33+AI33)/2 -> 484.75 | AL35: =(AL33+AK33)/2 -> 502.25 | AM35: =+(AM33+AJ33)/2 -> 493.5 | AN35: =(AN33+AL33)/2 -> 518.5 | AO35: =(AO33+AN33)/2 -> 533.5 | AP35: =+(AP33+AM33)/2 -> 526 | AQ35: =(AQ33+AO33)/2 -> 548.5 | AR35: =(AR33+AQ33)/2 -> 563.5 | AS35: =+(AS33+AP33)/2 -> 556 | AT35: =(AT33+AR33)/2 -> 578.5 | AU35: =(AU33+AT33)/2 -> 593.5 | AV35: =+(AV33+AS33)/2 -> 586
B36: Avg store % gth | C36: % | J36: =+J35/G35-1 -> 0.15309446 | K36: =+K35/H35-1 -> 0.14939024 | L36: =+L35/I35-1 -> 0.13707165 | M36: =+M35/L35-1 -> 0.10684932 | N36: =+N35/K35-1 -> 0.15119363 | O36: =+O35/L35-1 -> 0.14520548 | P36: =+P35/O35-1 -> 0.10047847 | Q36: =+Q35/P35-1 -> 0.069565217 | R36: =+R35/O35-1 -> 0.14832536 | S36: =+S35/R35-1 -> 0.103125 | T36: =+T35/S35-1 -> 0.066100094 | U36: =+U35/R35-1 -> 0.13958333 | V36: =+V35/U35-1 -> 0.10054845 | W36: =+W35/V35-1 -> 0.066445183 | X36: =+X35/U35-1 -> 0.13711152 | Y36: =+Y35/X35-1 -> 0.096463023 | Z36: =+Z35/Y35-1 -> 0.058651026 | AA36: =+AA35/X35-1 -> 0.12861736 | AB36: =+AB35/AA35-1 -> 0.081908832 | AC36: =+AC35/AB35-1 -> 0.046082949 | AD36: =+AD35/AA35-1 -> 0.10683761 | AE36: =+AE35/AD35-1 -> 0.067567568 | AF36: =+AF35/AE35-1 -> 0.042194093 | AG36: =+AG35/AD35-1 -> 0.09009009 | AH36: =+AH35/AG35-1 -> 0.061983471 | AI36: =+AI35/AH35-1 -> 0.038910506 | AJ36: =+AJ35/AG35-1 -> 0.082644628 | AK36: =+AK35/AJ35-1 -> 0.057251908 | AL36: =+AL35/AK35-1 -> 0.036101083 | AM36: =+AM35/AJ35-1 -> 0.076335878 | AN36: =+AN35/AM35-1 -> 0.050658561 | AO36: =+AO35/AN35-1 -> 0.028929605 | AP36: =+AP35/AM35-1 -> 0.06585613 | AQ36: =+AQ35/AP35-1 -> 0.042775665 | AR36: =+AR35/AQ35-1 -> 0.027347311 | AS36: =+AS35/AP35-1 -> 0.057034221 | AT36: =+AT35/AS35-1 -> 0.040467626 | AU36: =+AU35/AT35-1 -> 0.025929127 | AV36: =+AV35/AS35-1 -> 0.053956835
B38: Network Sales per Store | C38: A$m | F38: =+F46/F33 -> 3.5693333 | G38: =+G46/G33 -> 2.133121 | H38: =+H46/H33 -> 2.1520468 | I38: =+I46/I35 -> 4.3794393 | J38: =+J46/J33 -> 2.3967213 | K38: =+K46/K33 -> 2.3505155 | L38: =+L46/L35 -> 4.9019178 | M38: =+M46/M33 -> 2.5628571 | N38: =+N46/N33 -> 2.4839286 | O38: =+O46/O35 -> 5.2373206 | P38: =+M38*(1+P44) -> 2.7166286 | Q38: =+N38*(1+Q44) -> 2.6329643 | R38: =+O38*(1+R44) -> 5.5515598 | S38: =+P38*(1+S44) -> 2.85246 | T38: =+Q38*(1+T44) -> 2.7646125 | U38: =+R38*(1+U44) -> 5.8291378 | V38: =+S38*(1+V44) -> 2.995083 | W38: =+T38*(1+W44) -> 2.9028431 | ... AV38: =+AS38*(1+AV44) -> 8.5359486
B41: Network Sales per Store (New) | C41: A$m | F41: =+(F42*F38) -> 2.677 | G41: =+(G42*G38) -> 1.5998408 | H41: =+(H42*H38) -> 1.6140351 | I41: =+(I42*I38) -> 3.2845794 | J41: =+(J42*J38) -> 1.797541 | K41: =+(K42*K38) -> 1.7628866 | L41: =+(L42*L38) -> 3.6764384 | M41: =+(M42*M38) -> 1.4095714 | ... P41: =+(P42*P38) -> 1.4941457 | Q41: =R41-P41 -> 0.72647821 | R41: =+(R42*R38) -> 2.2206239 | S41: =+(S42*S38) -> 1.140984 | T41: =+(T42*T38) -> 1.105845 | U41: =+(U42*U38) -> 2.3316551 | V41: =+(V42*V38) -> 1.1980332 | W41: =+(W42*W38) -> 1.1611372 | X41: =+(X42*X38) -> 2.4482379 | Y41: =+(Y42*Y38) -> 1.2579349 | ... AV41: =+(AV42*AV38) -> 3.4143794
B42: % of mature store | C42: % | F42: 0.75 | G42: =+F42 -> 0.75 | H42: =+G42 -> 0.75 | I42: =+H42 -> 0.75 | J42: =+I42 -> 0.75 | K42: =+J42 -> 0.75 | L42: =+K42 -> 0.75 | M42: 0.55 | N42: 0.3 | O42: 0.425 | P42: 0.55 | Q42: =Q41/Q38 -> 0.27591647 | R42: 0.4 | S42: 0.4 | T42: =+S42 -> 0.4 | U42: =+T42 -> 0.4 | V42: =+U42 -> 0.4 | W42: =+V42 -> 0.4 | X42: =+W42 -> 0.4 | Y42: =+X42 -> 0.4 | Z42: =+Y42 -> 0.4 | AA42: =+Z42 -> 0.4 | ... AV42: =+AU42 -> 0.4
A44: Aust_LFL | B44: LFL gth | C44: % | F44: 0.182 | G44: 0.169 | H44: =(2*I44)-G44 -> 0.131 | I44: 0.15 | J44: 0.101 | K44: =(2*L44)-J44 -> 0.061 | L44: 0.081 | M44: 0.094 | N44: =+O44*2-M44 -> 0.098 | O44: 0.096 | P44: 0.06 | Q44: =+R44*2-P44 -> 0.06 | R44: 0.06 | S44: =+U44 -> 0.05 | T44: =+U44*2-S44 -> 0.05 | U44: 0.05 | V44: =+X44 -> 0.05 | W44: =+X44*2-V44 -> 0.05 | X44: 0.05 | Y44: =+AA44 -> 0.05 | Z44: =+AA44*2-Y44 -> 0.05 | AA44: 0.05 | AB44: 0.05 | AC44: =+AD44*2-AB44 -> 0.05 | AD44: 0.05 | AE44: 0.05 | AF44: =+AG44*2-AE44 -> 0.05 | AG44: 0.05 | AH44: 0.05 | AI44: =+AJ44*2-AH44 -> 0.05 | AJ44: 0.05 | AK44: 0.05 | AL44: =+AM44*2-AK44 -> 0.05 | AM44: 0.05 | AN44: =+AP44 -> 0.03 | AO44: =+AP44*2-AN44 -> 0.03 | AP44: 0.03 | AQ44: =+AS44 -> 0.03 | AR44: =+AS44*2-AQ44 -> 0.03 | AS44: 0.03 | AT44: =+AV44 -> 0.03 | AU44: =+AV44*2-AT44 -> 0.03 | AV44: 0.03
A46: Aust_total_network _sales | B46: Total Network Sales | C46: A$m | F46: =+F10 -> 535.4 | G46: =+G10 -> 334.9 | H46: =+H10 -> 368 | I46: =+I10 -> 702.9 | J46: =+J10 -> 438.6 | K46: =+K10 -> 456 | L46: =+L10 -> 894.6 | M46: =+M10 -> 538.2 | ... O46: =+O10 -> 1094.6 | P46: =+P38*P30+P32*P41+10 -> 636.45455 | Q46: =+R46-P46 -> 678.15481 | R46: =+R38*R30+R32*R41 -> 1314.6094 | S46: =+S38*S30+S32*S41 -> 750.19698 | T46: =+U46-S46 -> 823.67023 | U46: =+U38*U30+U32*U41 -> 1573.8672 | V46: =+V38*V30+V32*V41 -> 895.52982 | W46: =+X46-V46 -> 983.49275 | X46: =+X38*X30+X32*X41 -> 1879.0226 | Y46: =+Y38*Y30+Y32*Y41 -> 1066.0998 | Z46: =+AA46-Y46 -> 1163.9389 | AA46: =+AA38*AA30+AA32*AA41 -> 2230.0387 | AB46: =+AB38*AB30+AB32*AB41 -> 1248.1859 | AC46: =+AD46-AB46 -> 1349.7771 | AD46: =+AD38*AD30+AD32*AD41 -> 2597.9629 | AE46: =+AE38*AE30+AE32*AE41 -> 1431.9466 | AF46: =+AG46-AE46 -> 1543.9019 | AG46: =+AG38*AG30+AG32*AG41 -> 2975.8484 | AH46: =+AH38*AH30+AH32*AH41 -> 1630.9629 | AI46: =+AJ46-AH46 -> 1754.0647 | AJ46: =+AJ38*AJ30+AJ32*AJ41 -> 3385.0276 | AK46: =+AK38*AK30+AK32*AK41 -> 1846.3009 | AL46: =+AM46-AK46 -> 1981.3841 | AM46: =+AM38*AM30+AM32*AM41 -> 3827.6851 | AN46: =+AN38*AN30+AN32*AN41 -> 2035.5563 | AO46: =+AP46-AN46 -> 2172.4756 | AP46: =+AP38*AP30+AP32*AP41 -> 4208.032 | AQ46: =+AQ38*AQ30+AQ32*AQ41 -> 2218.2839 | AR46: =+AS46-AQ46 -> 2364.6089 | AS46: =+AS38*AS30+AS32*AS41 -> 4582.8928 | AT46: =+AT38*AT30+AT32*AT41 -> 2410.1432 | AU46: =+AV46-AT46 -> 2566.3148 | AV46: =+AV38*AV30+AV32*AV41 -> 4976.458
A47: Aust_Network_sales_gth | B47: % gth | I47: =+I46/F46-1 -> 0.31285021 | J47: =+J46/G46-1 -> 0.30964467 | K47: =+K46/H46-1 -> 0.23913043 | L47: =+L46/I46-1 -> 0.27272727 | M47: =+M46/J46-1 -> 0.22708618 | N47: =+N46/K46-1 -> 0.22017544 | O47: =+O46/L46-1 -> 0.2235636 | P47: =+P46/M46-1 -> 0.18256141 | ... AV47: =+AV46/AS46-1 -> 0.085877034
Y48: =+Y47-Y44-Y34 -> 0.011850864 | Z48: =+Z47-Z44-Z34 -> 0.012628871
A49: Aust_network_gth_# | B49: Network Growth | C49: # | J49: =+J62+J83 -> 12 | K49: =+K62+K83 -> 11 | L49: =+L62+L83 -> 23 | M49: =+M62+M83 -> 16 | N49: =+N62+N83 -> 14 | O49: =+O62+O83 -> 30 | P49: 12 | Q49: =+R49-P49 -> 20 | R49: =VLOOKUP($A$49,'GYG network model'!$B$1:$AI$32,MATCH(Assumptions!R$5,'GYG network model'!$B$1:$AM$1,0),FALSE) -> 32 | S49: =+U49*50% -> 17.5 | T49: =+U49-S49 -> 17.5 | U49: =VLOOKUP($A$49,'GYG network model'!$B$1:$AI$32,MATCH(Assumptions!U$5,'GYG network model'!$B$1:$AM$1,0),FALSE) -> 35 | V49: =+X49*50% -> 20 | W49: =+X49-V49 -> 20 | X49: =VLOOKUP($A$49,'GYG network model'!$B$1:$AI$32,MATCH(Assumptions!X$5,'GYG network model'!$B$1:$AM$1,0),FALSE) -> 40 | Y49: =+AA49*50% -> 20 | Z49: =+AA49-Y49 -> 20 | AA49: =VLOOKUP($A$49,'GYG network model'!$B$1:$AI$32,MATCH(Assumptions!AA$5,'GYG network model'!$B$1:$AM$1,0),FALSE) -> 40 | AB49: =+AD49*50% -> 17.5 | AC49: =+AD49-AB49 -> 17.5 | AD49: =VLOOKUP($A$49,'GYG network model'!$B$1:$AI$32,MATCH(Assumptions!AD$5,'GYG network model'!$B$1:$AM$1,0),FALSE) -> 35 | AE49: =+AG49*50% -> 17.5 | AF49: =+AG49-AE49 -> 17.5 | AG49: =VLOOKUP($A$49,'GYG network model'!$B$1:$AI$32,MATCH(Assumptions!AG$5,'GYG network model'!$B$1:$AM$1,0),FALSE) -> 35 | AH49: =+AJ49*50% -> 17.5 | AI49: =+AJ49-AH49 -> 17.5 | AJ49: =VLOOKUP($A$49,'GYG network model'!$B$1:$AI$32,MATCH(Assumptions!AJ$5,'GYG network model'!$B$1:$AM$1,0),FALSE) -> 35 | AK49: =+AM49*50% -> 17.5 | AL49: =+AM49-AK49 -> 17.5 | AM49: =VLOOKUP($A$49,'GYG network model'!$B$1:$AI$32,MATCH(Assumptions!AM$5,'GYG network model'!$B$1:$AM$1,0),FALSE) -> 35 | AN49: =+AP49*50% -> 15 | AO49: =+AP49-AN49 -> 15 | AP49: =VLOOKUP($A$49,'GYG network model'!$B$1:$AI$32,MATCH(Assumptions!AP$5,'GYG network model'!$B$1:$AM$1,0),FALSE) -> 30 | AQ49: =+AS49*50% -> 15 | AR49: =+AS49-AQ49 -> 15 | AS49: =VLOOKUP($A$49,'GYG network model'!$B$1:$AI$32,MATCH(Assumptions!AS$5,'GYG network model'!$B$1:$AM$1,0),FALSE) -> 30 | AT49: =+AV49*50% -> 15 | AU49: =+AV49-AT49 -> 15 | AV49: =VLOOKUP($A$49,'GYG network model'!$B$1:$AI$32,MATCH(Assumptions!AV$5,'GYG network model'!$B$1:$AM$1,0),FALSE) -> 30
B50: Aust Corp stores % Aust Corp + Franchisee | C50: % | F50: =F63/F33 -> 0.30666667 | G50: =G63/G33 -> 0.32484076 | H50: =H63/H33 -> 0.32163743 | I50: =I63/I33 -> 0.32163743 | J50: =J63/J33 -> 0.33879781 | K50: =K63/K33 -> 0.32989691 | L50: =L63/L33 -> 0.32989691 | M50: =M63/M33 -> 0.35238095 | ... AV50: =AV63/AV33 -> 0.3843594
B52: Group Franchise revenue
B53: Royalty revenue | C53: A$m | F53: =+F92+F116+F139 -> 30.1 | G53: =+G92+G116+G139 -> 19.5925 | H53: =+H92+H116+H139 -> 21.5075 | I53: =+I92+I116+I139 -> 41.1 | J53: =+J92+J116+J139 -> 26.271 | K53: =+K92+K116+K139 -> 26.232 | L53: =+L92+L116+L139 -> 52.503 | M53: =+M92+M116+M139 -> 33.136 | ... AV53: =+AV92+AV116+AV139 -> 311.88645
A54: Other_franchisee_rev | B54: Other | C54: A$m | F54: =+F55-F53 -> 3.3 | G54: =+G55-G53 -> 1.4075 | H54: =+I54-G54 -> 4.2925 | I54: =+I55-I53 -> 5.7 | J54: =+J55-J53 -> 3.229 | K54: =+L54-J54 -> 4.968 | L54: =+L55-L53 -> 8.197 | M54: =+M55-M53 -> 5.064 | N54: =+O54-M54 -> 6.469 | O54: =+O55-O53 -> 11.533 | P54: =+R54*50% -> 4.1348215 | Q54: =+R54-P54 -> 4.1348215 | R54: =+O54/O187*R187 -> 8.2696429 | S54: =+U54*50% -> 5.021718 | T54: =+U54-S54 -> 5.021718 | U54: =+R54/R187*U187 -> 10.043436 | V54: =+X54*50% -> 6.1726498 | W54: =+X54-V54 -> 6.1726498 | X54: =+U54/U187*X187 -> 12.3453 | Y54: =+AA54*50% -> 7.4041952 | Z54: =+AA54-Y54 -> 7.4041952 | AA54: =+X54/X187*AA187 -> 14.80839 | AB54: =+AD54*50% -> 8.6509571 | AC54: =+AD54-AB54 -> 8.6509571 | AD54: =+AA54/AA187*AD187 -> 17.301914 | AE54: =+AG54*50% -> 10.150406 | AF54: =+AG54-AE54 -> 10.150406 | AG54: =+AD54/AD187*AG187 -> 20.300813 | AH54: =+AJ54*50% -> 11.847551 | AI54: =+AJ54-AH54 -> 11.847551 | AJ54: =+AG54/AG187*AJ187 -> 23.695103 | AK54: =+AM54*50% -> 13.761776 | AL54: =+AM54-AK54 -> 13.761776 | AM54: =+AJ54/AJ187*AM187 -> 27.523552 | AN54: =+AP54*50% -> 15.447407 | AO54: =+AP54-AN54 -> 15.447407 | AP54: =+AM54/AM187*AP187 -> 30.894814 | AQ54: =+AS54*50% -> 17.339 | AR54: =+AS54-AQ54 -> 17.339 | AS54: =+AP54/AP187*AS187 -> 34.678001 | AT54: =+AV54*50% -> 19.396941 | AU54: =+AV54-AT54 -> 19.396941 | AV54: =+AS54/AS187*AV187 -> 38.793882
B55: Group Franchise Revenue (Aust /JP/SG) | C55: A$m | F55: 33.4 | G55: 21 | H55: =+I55-G55 -> 25.8 | I55: 46.8 | J55: 29.5 | K55: =+L55-J55 -> 31.2 | L55: 60.7 | M55: 38.2 | N55: =+O55-M55 -> 40.724 | O55: 78.924 | P55: =+P53+P54 -> 41.421728 | Q55: =+R55-P55 -> 43.29291 | R55: =+R53+R54 -> 84.714638 | S55: =+S53+S54 -> 49.46506 | T55: =+U55-S55 -> 53.697169 | U55: =+U53+U54 -> 103.16223 | V55: =+V53+V54 -> 64.379795 | W55: =+X55-V55 -> 61.215579 | X55: =+X53+X54 -> 125.59537 | Y55: =+Y53+Y54 -> 76.114068 | Z55: =+AA55-Y55 -> 75.97837 | AA55: =+AA53+AA54 -> 152.09244 | AB55: =+AB53+AB54 -> 85.906437 | AC55: =+AD55-AB55 -> 92.117562 | AD55: =+AD53+AD54 -> 178.024 | AE55: =+AE53+AE54 -> 99.077035 | AF55: =+AG55-AE55 -> 105.96353 | AG55: =+AG53+AG54 -> 205.04056 | AH55: =+AH53+AH54 -> 113.49837 | AI55: =+AJ55-AH55 -> 121.11427 | AJ55: =+AJ53+AJ54 -> 234.61264 | AK55: =+AK53+AK54 -> 129.26344 | AL55: =+AM55-AK55 -> 137.66642 | AM55: =+AM53+AM54 -> 266.92986 | AN55: =+AN53+AN54 -> 143.00392 | AO55: =+AP55-AN55 -> 151.5746 | AP55: =+AP53+AP54 -> 294.57852 | AQ55: =+AQ53+AQ54 -> 156.62845 | AR55: =+AS55-AQ55 -> 165.8156 | AS55: =+AS53+AS54 -> 322.44405 | AT55: =+AT53+AT54 -> 170.44251 | AU55: =+AV55-AT55 -> 180.23782 | AV55: =+AV53+AV54 -> 350.68033
B58: Australia - Corporate
B60: Restaurants BOP | C60: # | G60: =+F63 -> 46 | H60: =+G63 -> 51 | I60: =+F63 -> 46 | J60: =+I63 -> 55 | K60: =+J63 -> 62 | L60: =+I63 -> 55 | M60: =+L63 -> 64 | N60: =+M63 -> 74 | O60: =+L63 -> 64 | P60: =+O63 -> 81 | Q60: =+P63 -> 83 | R60: =+O63 -> 81 | S60: =+R63 -> 93 | T60: =+S63 -> 100 | U60: =+R63 -> 93 | V60: =+U63 -> 107 | W60: =+V63 -> 115 | X60: =+U63 -> 107 | Y60: =+X63 -> 123 | Z60: =+Y63 -> 131 | AA60: =+X63 -> 123 | AB60: =+AA63 -> 139 | AC60: =+AB63 -> 146 | AD60: =+AA63 -> 139 | AE60: =+AD63 -> 153 | AF60: =+AE63 -> 160 | AG60: =+AD63 -> 153 | AH60: =+AG63 -> 167 | AI60: =+AH63 -> 174 | AJ60: =+AG63 -> 167 | AK60: =+AJ63 -> 181 | AL60: =+AK63 -> 188 | AM60: =+AJ63 -> 181 | AN60: =+AM63 -> 195 | AO60: =+AN63 -> 201 | AP60: =+AM63 -> 195 | AQ60: =+AP63 -> 207 | AR60: =+AQ63 -> 213 | AS60: =+AP63 -> 207 | AT60: =+AS63 -> 219 | AU60: =+AT63 -> 225 | AV60: =+AS63 -> 219
B61: Acquisitions / disposals | C61: # | J61: 0 | L61: =+J61+K61 -> 0 | M61: 0 | O61: =+M61+N61 -> 0 | P61: 0 | Q61: 0 | R61: =+P61+Q61 -> 0 | S61: 0 | T61: 0 | U61: =+S61+T61 -> 0 | V61: 0 | W61: 0 | X61: =+V61+W61 -> 0 | Y61: 0 | Z61: 0 | AA61: =+Y61+Z61 -> 0 | AB61: 0 | AC61: 0 | AD61: =+AB61+AC61 -> 0 | AE61: 0 | AF61: 0 | AG61: =+AE61+AF61 -> 0 | AH61: 0 | AI61: 0 | AJ61: =+AH61+AI61 -> 0 | AK61: 0 | AL61: 0 | AM61: =+AK61+AL61 -> 0 | AN61: 0 | AO61: 0 | AP61: =+AN61+AO61 -> 0 | AQ61: 0 | AR61: 0 | AS61: =+AQ61+AR61 -> 0 | AT61: 0 | AU61: 0 | AV61: =+AT61+AU61 -> 0
B62: Net openings | C62: # | G62: =+G63-G60 -> 5 | H62: =+H63-H60 -> 4 | I62: =+I63-I60 -> 9 | J62: =+J63-J60 -> 7 | K62: =+K63-K60 -> 2 | L62: =+L63-L60 -> 9 | M62: =+M63-M60 -> 10 | N62: =+N63-N60 -> 7 | O62: =+O63-O60 -> 17 | P62: =+P49-P83 -> 2 | Q62: =+R62-P62 -> 10 | R62: =+R49-R83 -> 12 | S62: =+S49*40% -> 7 | T62: =+T49*40% -> 7 | U62: =+U49*40% -> 14 | V62: =+V49*40% -> 8 | W62: =+W49*40% -> 8 | X62: =+X49*40% -> 16 | Y62: =+Y49*40% -> 8 | Z62: =+Z49*40% -> 8 | ... AV62: =+AV49*40% -> 12
A63: Aust_corp_stores | B63: Restaurants EOP | C63: # | F63: 46 | G63: 51 | H63: =+I63 -> 55 | I63: 55 | J63: 62 | K63: =+L63 -> 64 | L63: 64 | M63: 74 | N63: =+O63 -> 81 | O63: 81 | P63: =+P60+P61+P62 -> 83 | Q63: =+Q60+Q61+Q62 -> 93 | R63: =+R60+R61+R62 -> 93 | S63: =+S60+S61+S62 -> 100 | T63: =+T60+T61+T62 -> 107 | U63: =+U60+U61+U62 -> 107 | V63: =+V60+V61+V62 -> 115 | W63: =+W60+W61+W62 -> 123 | ... AV63: =+AV60+AV61+AV62 -> 231
B64: Average stores | C64: # | G64: =+AVERAGE(F63:G63) -> 48.5 | H64: =+AVERAGE(G63:H63) -> 53 | I64: =+(I63+F63)/2 -> 50.5 | J64: =+AVERAGE(I63:J63) -> 58.5 | K64: =+AVERAGE(J63:K63) -> 63 | L64: =+(L63+I63)/2 -> 59.5 | M64: =+AVERAGE(L63:M63) -> 69 | N64: =+AVERAGE(M63:N63) -> 77.5 | O64: =+(O63+L63)/2 -> 72.5 | P64: =+AVERAGE(O63:P63) -> 82 | Q64: =+AVERAGE(P63:Q63) -> 88 | R64: =+(R63+O63)/2 -> 87 | S64: =+AVERAGE(R63:S63) -> 96.5 | T64: =+AVERAGE(S63:T63) -> 103.5 | U64: =+(U63+R63)/2 -> 100 | V64: =+AVERAGE(U63:V63) -> 111 | W64: =+AVERAGE(V63:W63) -> 119 | X64: =+(X63+U63)/2 -> 115 | Y64: =+AVERAGE(X63:Y63) -> 127 | Z64: =+AVERAGE(Y63:Z63) -> 135 | AA64: =+(AA63+X63)/2 -> 131 | AB64: =+AVERAGE(AA63:AB63) -> 142.5 | AC64: =+AVERAGE(AB63:AC63) -> 149.5 | AD64: =+(AD63+AA63)/2 -> 146 | AE64: =+AVERAGE(AD63:AE63) -> 156.5 | AF64: =+AVERAGE(AE63:AF63) -> 163.5 | AG64: =+(AG63+AD63)/2 -> 160 | AH64: =+AVERAGE(AG63:AH63) -> 170.5 | AI64: =+AVERAGE(AH63:AI63) -> 177.5 | AJ64: =+(AJ63+AG63)/2 -> 174 | AK64: =+AVERAGE(AJ63:AK63) -> 184.5 | AL64: =+AVERAGE(AK63:AL63) -> 191.5 | AM64: =+(AM63+AJ63)/2 -> 188 | AN64: =+AVERAGE(AM63:AN63) -> 198 | AO64: =+AVERAGE(AN63:AO63) -> 204 | AP64: =+(AP63+AM63)/2 -> 201 | AQ64: =+AVERAGE(AP63:AQ63) -> 210 | AR64: =+AVERAGE(AQ63:AR63) -> 216 | AS64: =+(AS63+AP63)/2 -> 213 | AT64: =+AVERAGE(AS63:AT63) -> 222 | AU64: =+AVERAGE(AT63:AU63) -> 228 | AV64: =+(AV63+AS63)/2 -> 225
B65: % gth | C65: % | J65: =+J64/G64-1 -> 0.20618557 | K65: =+K64/H64-1 -> 0.18867925 | L65: =+L64/I64-1 -> 0.17821782 | M65: =+M64/J64-1 -> 0.17948718 | N65: =+N64/K64-1 -> 0.23015873 | O65: =+O64/L64-1 -> 0.21848739 | P65: =+P64/M64-1 -> 0.1884058 | Q65: =+Q64/N64-1 -> 0.13548387 | ... AV65: =+AV64/AS64-1 -> 0.056338028
A68: Aust_Corp_network_sales | B68: Network sales | C68: A$m | F68: 139.2 | G68: 100.6 | H68: =+I68-G68 -> 111.4 | I68: 212 | J68: 136.6 | K68: =+L68-J68 -> 142.3 | L68: 278.9 | M68: 176.051 | N68: =+O68-M68 -> 183.649 | O68: 359.7 | P68: =(P46/P35*P64) -> 226.90988 | Q68: =+R68-P68 -> 249.63601 | R68: =(R46/R35*R64) -> 476.54589 | S68: =(S46/S35*S64) -> 273.4429 | T68: =+U68-S68 -> 302.01129 | U68: =(U46/U35*U64) -> 575.45419 | V68: =(V46/V35*V64) -> 330.24521 | W68: =+X68-V68 -> 364.5702 | X68: =(X46/X35*X64) -> 694.81542 | Y68: =(Y46/Y35*Y64) -> 397.05183 | Z68: =+AA68-Y68 -> 435.24181 | AA68: =(AA46/AA35*AA64) -> 832.29364 | AB68: =(AB46/AB35*AB64) -> 468.37784 | AC68: =+AD68-AB68 -> 507.94799 | AD68: =(AD46/AD35*AD64) -> 976.32583 | AE68: =(AE46/AE35*AE64) -> 540.32462 | AF68: =+AG68-AE68 -> 583.96286 | AG68: =(AG46/AG35*AG64) -> 1124.2875 | AH68: =(AH46/AH35*AH64) -> 618.29721 | AI68: =+AJ68-AH68 -> 666.31523 | AJ68: =(AJ46/AJ35*AJ64) -> 1284.6124 | AK68: =(AK46/AK35*AK64) -> 702.71794 | AL68: =+AM68-AK68 -> 755.4478 | AM68: =(AM46/AM35*AM64) -> 1458.1657 | AN68: =(AN46/AN35*AN64) -> 777.31949 | AO68: =+AP68-AN68 -> 830.69273 | AP68: =(AP46/AP35*AP64) -> 1608.0122 | AQ68: =(AQ46/AQ35*AQ64) -> 849.2974 | AR68: =+AS68-AQ68 -> 906.37915 | AS68: =(AS46/AS35*AS64) -> 1755.6766 | AT68: =(AT46/AT35*AT64) -> 924.89505 | AU68: =+AV68-AT68 -> 985.86102 | AV68: =(AV46/AV35*AV64) -> 1910.7561
A69: Aust_corp_network_sales_gth | B69: % gth | C69: % | I69: =+I68/F68-1 -> 0.52298851 | J69: =+J68/G68-1 -> 0.35785288 | K69: =+K68/H68-1 -> 0.27737882 | L69: =+L68/I68-1 -> 0.31556604 | M69: =+M68/J68-1 -> 0.28880673 | N69: =+N68/K68-1 -> 0.29057625 | O69: =+O68/L68-1 -> 0.28970957 | P69: =+P68/M68-1 -> 0.28888721 | ... AV69: =+AV68/AS68-1 -> 0.088330345
A72: Aust_corp_store_EBITDA | B72: Store operating profit | C72: A$m | F72: =+F74*F68 -> 19.6272 | G72: =+G74*G68 -> 13.7822 | H72: =+I72-G72 -> 16.7458 | I72: =+I74*I68 -> 30.528 | J72: =+J74*J68 -> 23.905 | K72: =+L72-J72 -> 24.6236 | L72: =+L74*L68 -> 48.5286 | M72: =+M74*M68 -> 31.68918 | N72: =+O72-M72 -> 32.69712 | O72: =+O74*O68 -> 64.3863 | P72: =+P74*P68 -> 42.205238 | Q72: =+R72-P72 -> 45.240933 | R72: =+R74*R68 -> 87.446172 | S72: =+S74*S68 -> 51.718307 | T72: =+U72-S72 -> 57.749929 | U72: =+U74*U68 -> 109.46824 | V72: =+V74*V68 -> 64.412348 | W72: =+X72-V72 -> 71.865816 | X72: =+X74*X68 -> 136.27816 | Y72: =+Y74*Y68 -> 79.826278 | Z72: =+AA72-Y72 -> 88.412959 | AA72: =+AA74*AA68 -> 168.23924 | AB72: =+AB74*AB68 -> 96.432909 | AC72: =+AD72-AB72 -> 105.64582 | AD72: =+AD74*AD68 -> 202.07873 | AE72: =+AE74*AE68 -> 112.80627 | AF72: =+AG72-AE72 -> 123.14432 | AG72: =+AG74*AG68 -> 235.95059 | AH72: =+AH74*AH68 -> 130.90063 | AI72: =+AJ72-AH72 -> 142.46911 | AJ72: =+AJ74*AJ68 -> 273.36974 | AK72: =+AK74*AK68 -> 150.87108 | AL72: =+AM72-AK72 -> 163.78399 | AM72: =+AM74*AM68 -> 314.65508 | AN72: =+AN74*AN68 -> 169.24577 | AO72: =+AP72-AN72 -> 182.62232 | AP72: =+AP74*AP68 -> 351.86809 | AQ72: =+AQ74*AQ68 -> 185.41181 | AR72: =+AS72-AQ72 -> 199.79026 | AS72: =+AS74*AS68 -> 385.20207 | AT72: =+AT74*AT68 -> 202.49883 | AU72: =+AV72-AT72 -> 217.933 | AV72: =+AV74*AV68 -> 420.43184
A73: Aust_corp_store_EBITDA_YoY_chg | B73: % gth | C73: % | I73: =+I72/F72-1 -> 0.55539252 | J73: =+J72/G72-1 -> 0.73448361 | K73: =+K72/H72-1 -> 0.47043438 | L73: =+L72/I72-1 -> 0.5896423 | M73: =+M72/J72-1 -> 0.32562978 | N73: =+N72/K72-1 -> 0.32787732 | O73: =+O72/L72-1 -> 0.32677019 | P73: =+P72/M72-1 -> 0.33185012 | ... AV73: =+AV72/AS72-1 -> 0.091457877
A74: Aust_Corp_EBITDA_margin | B74: Coporate restaurant EBITDA margin | C74: % | F74: 0.141 | G74: 0.137 | H74: =+H72/H68 -> 0.15032136 | I74: 0.144 | J74: 0.175 | K74: =+K72/K68 -> 0.17304006 | L74: 0.174 | M74: 0.18 | N74: =+N72/N68 -> 0.17804137 | O74: 0.179 | P74: 0.186 | Q74: =+Q72/Q68 -> 0.18122759 | R74: 0.1835 | S74: 0.1891375 | T74: =+T72/T68 -> 0.19121778 | U74: 0.19022928 | V74: 0.195044 | W74: =+W72/W68 -> 0.19712477 | X74: 0.19613578 | Y74: 0.2010475 | Z74: =+Z72/Z68 -> 0.20313526 | AA74: 0.20213928 | AB74: 0.205887 | AC74: =+AC72/AC68 -> 0.20798551 | AD74: 0.20697878 | AE74: 0.208775 | AF74: =+AF72/AF68 -> 0.21087697 | AG74: 0.20986678 | AH74: 0.2117115 | AI74: =+AI72/AI68 -> 0.21381638 | AJ74: 0.21280328 | AK74: 0.2146965 | AL74: =+AL72/AL68 -> 0.21680385 | AM74: 0.21578828 | AN74: 0.21773 | AO74: =+AO72/AO68 -> 0.21984341 | AP74: 0.21882178 | AQ74: 0.218312 | AR74: =+AR72/AR68 -> 0.2204268 | AS74: 0.21940378 | AT74: 0.2189425 | AU74: =+AU72/AU68 -> 0.22105854 | AV74: 0.22003428 | BF74: =+AD74-O74 -> 0.02797878
B75: % chg | C75: % | I75: =+I74-F74 -> 0.003 | J75: =+J74-G74 -> 0.038 | K75: =+K74-H74 -> 0.022718692 | L75: =+L74-I74 -> 0.03 | M75: =+M74-J74 -> 0.005 | N75: =+N74-K74 -> 0.0050013162 | O75: =+O74-L74 -> 0.005 | P75: =+P74-M74 -> 0.006 | ... AV75: =+AV74-AS74 -> 0.0006305
AA76: =+AA74-L74 -> 0.02813928
AA77: =+AA76/5 -> 0.005627856
B79: Australia - Franchised
B81: Restaurants BOP | C81: # | G81: =+F84 -> 104 | H81: =+G84 -> 106 | I81: =+F84 -> 104 | J81: =+I84 -> 116 | K81: =+J84 -> 121 | L81: =+I84 -> 116 | M81: =+L84 -> 130 | N81: =+M84 -> 136 | O81: =+L84 -> 130 | P81: =+O84 -> 143 | Q81: =+P84 -> 153 | R81: =+O84 -> 143 | S81: =+R84 -> 163 | T81: =+S84 -> 173.5 | U81: =+R84 -> 163 | V81: =+U84 -> 184 | W81: =+V84 -> 196 | X81: =+U84 -> 184 | Y81: =+X84 -> 208 | Z81: =+Y84 -> 220 | AA81: =+X84 -> 208 | AB81: =+AA84 -> 232 | AC81: =+AB84 -> 242.5 | AD81: =+AA84 -> 232 | AE81: =+AD84 -> 253 | AF81: =+AE84 -> 263.5 | AG81: =+AD84 -> 253 | AH81: =+AG84 -> 274 | AI81: =+AH84 -> 284.5 | AJ81: =+AG84 -> 274 | AK81: =+AJ84 -> 295 | AL81: =+AK84 -> 305.5 | AM81: =+AJ84 -> 295 | AN81: =+AM84 -> 316 | AO81: =+AN84 -> 325 | AP81: =+AM84 -> 316 | AQ81: =+AP84 -> 334 | AR81: =+AQ84 -> 343 | AS81: =+AP84 -> 334 | AT81: =+AS84 -> 352 | AU81: =+AT84 -> 361 | AV81: =+AS84 -> 352
B82: Acquisitions / disposals | C82: # | P82: 0 | Q82: 0 | R82: =+P82+Q82 -> 0 | S82: 0 | T82: 0 | U82: =+S82+T82 -> 0 | V82: 0 | W82: 0 | X82: =+V82+W82 -> 0 | Y82: 0 | Z82: 0 | AA82: =+Y82+Z82 -> 0 | AB82: 0 | AC82: 0 | AD82: =+AB82+AC82 -> 0 | AE82: 0 | AF82: 0 | AG82: =+AE82+AF82 -> 0 | AH82: 0 | AI82: 0 | AJ82: =+AH82+AI82 -> 0 | AK82: 0 | AL82: 0 | AM82: =+AK82+AL82 -> 0 | AN82: 0 | AO82: 0 | AP82: =+AN82+AO82 -> 0 | AQ82: 0 | AR82: 0 | AS82: =+AQ82+AR82 -> 0 | AT82: 0 | AU82: 0 | AV82: =+AT82+AU82 -> 0
B83: Net openings | C83: # | G83: =+G84-G81 -> 2 | H83: =+H84-H81 -> 10 | I83: =+I84-I81 -> 12 | J83: =+J84-J81 -> 5 | K83: =+K84-K81 -> 9 | L83: =+L84-L81 -> 14 | M83: =+M84-M81 -> 6 | N83: =+N84-N81 -> 7 | O83: =+O84-O81 -> 13 | P83: 10 | Q83: =+R83-P83 -> 10 | R83: =+'GYG network model'!Q35 -> 20 | S83: =+S49*60% -> 10.5 | T83: =+T49*60% -> 10.5 | U83: =+T83+S83 -> 21 | V83: =+V49*60% -> 12 | W83: =+W49*60% -> 12 | X83: =+W83+V83 -> 24 | Y83: =+Y49*60% -> 12 | Z83: =+Z49*60% -> 12 | AA83: =+Z83+Y83 -> 24 | AB83: =+AB49*60% -> 10.5 | AC83: =+AC49*60% -> 10.5 | AD83: =+AC83+AB83 -> 21 | AE83: =+AE49*60% -> 10.5 | AF83: =+AF49*60% -> 10.5 | AG83: =+AF83+AE83 -> 21 | AH83: =+AH49*60% -> 10.5 | AI83: =+AI49*60% -> 10.5 | AJ83: =+AI83+AH83 -> 21 | AK83: =+AK49*60% -> 10.5 | AL83: =+AL49*60% -> 10.5 | AM83: =+AL83+AK83 -> 21 | AN83: =+AN49*60% -> 9 | AO83: =+AO49*60% -> 9 | AP83: =+AO83+AN83 -> 18 | AQ83: =+AQ49*60% -> 9 | AR83: =+AR49*60% -> 9 | AS83: =+AR83+AQ83 -> 18 | AT83: =+AT49*60% -> 9 | AU83: =+AU49*60% -> 9 | AV83: =+AU83+AT83 -> 18
A84: Aust_Fran_stores | B84: Restaurants EOP | C84: # | F84: 104 | G84: 106 | H84: =+I84 -> 116 | I84: 116 | J84: 121 | K84: =+L84 -> 130 | L84: 130 | M84: 136 | N84: =+O84 -> 143 | O84: 143 | P84: =+P81+P82+P83 -> 153 | Q84: =+R84 -> 163 | R84: =+R81+R82+R83 -> 163 | S84: =+S81+S82+S83 -> 173.5 | T84: =+U84 -> 184 | U84: =+U81+U82+U83 -> 184 | V84: =+V81+V82+V83 -> 196 | W84: =+X84 -> 208 | X84: =+X81+X82+X83 -> 208 | Y84: =+Y81+Y82+Y83 -> 220 | Z84: =+AA84 -> 232 | AA84: =+AA81+AA82+AA83 -> 232 | AB84: =+AB81+AB82+AB83 -> 242.5 | AC84: =+AD84 -> 253 | AD84: =+AD81+AD82+AD83 -> 253 | AE84: =+AE81+AE82+AE83 -> 263.5 | AF84: =+AG84 -> 274 | AG84: =+AG81+AG82+AG83 -> 274 | AH84: =+AH81+AH82+AH83 -> 284.5 | AI84: =+AJ84 -> 295 | AJ84: =+AJ81+AJ82+AJ83 -> 295 | AK84: =+AK81+AK82+AK83 -> 305.5 | AL84: =+AM84 -> 316 | AM84: =+AM81+AM82+AM83 -> 316 | AN84: =+AN81+AN82+AN83 -> 325 | AO84: =+AP84 -> 334 | AP84: =+AP81+AP82+AP83 -> 334 | AQ84: =+AQ81+AQ82+AQ83 -> 343 | AR84: =+AS84 -> 352 | AS84: =+AS81+AS82+AS83 -> 352 | AT84: =+AT81+AT82+AT83 -> 361 | AU84: =+AV84 -> 370 | AV84: =+AV81+AV82+AV83 -> 370
B85: Average stores | C85: # | G85: =+AVERAGE(F84:G84) -> 105 | H85: =+AVERAGE(G84:H84) -> 111 | I85: =+(I84+F84)/2 -> 110 | J85: =+AVERAGE(I84:J84) -> 118.5 | K85: =+AVERAGE(J84:K84) -> 125.5 | L85: =+(L84+I84)/2 -> 123 | M85: =+AVERAGE(L84:M84) -> 133 | N85: =+AVERAGE(M84:N84) -> 139.5 | O85: =+(O84+L84)/2 -> 136.5 | P85: =+AVERAGE(O84:P84) -> 148 | Q85: =+AVERAGE(P84:Q84) -> 158 | R85: =+(R84+O84)/2 -> 153 | S85: =+AVERAGE(R84:S84) -> 168.25 | T85: =+AVERAGE(S84:T84) -> 178.75 | U85: =+(U84+R84)/2 -> 173.5 | V85: =+AVERAGE(U84:V84) -> 190 | W85: =+AVERAGE(V84:W84) -> 202 | X85: =+(X84+U84)/2 -> 196 | Y85: =+AVERAGE(X84:Y84) -> 214 | Z85: =+AVERAGE(Y84:Z84) -> 226 | AA85: =+(AA84+X84)/2 -> 220 | AB85: =+AVERAGE(AA84:AB84) -> 237.25 | AC85: =+AVERAGE(AB84:AC84) -> 247.75 | AD85: =+(AD84+AA84)/2 -> 242.5 | AE85: =+AVERAGE(AD84:AE84) -> 258.25 | AF85: =+AVERAGE(AE84:AF84) -> 268.75 | AG85: =+(AG84+AD84)/2 -> 263.5 | AH85: =+AVERAGE(AG84:AH84) -> 279.25 | AI85: =+AVERAGE(AH84:AI84) -> 289.75 | AJ85: =+(AJ84+AG84)/2 -> 284.5 | AK85: =+AVERAGE(AJ84:AK84) -> 300.25 | AL85: =+AVERAGE(AK84:AL84) -> 310.75 | AM85: =+(AM84+AJ84)/2 -> 305.5 | AN85: =+AVERAGE(AM84:AN84) -> 320.5 | AO85: =+AVERAGE(AN84:AO84) -> 329.5 | AP85: =+(AP84+AM84)/2 -> 325 | AQ85: =+AVERAGE(AP84:AQ84) -> 338.5 | AR85: =+AVERAGE(AQ84:AR84) -> 347.5 | AS85: =+(AS84+AP84)/2 -> 343 | AT85: =+AVERAGE(AS84:AT84) -> 356.5 | AU85: =+AVERAGE(AT84:AU84) -> 365.5 | AV85: =+(AV84+AS84)/2 -> 361
B86: % gth | C86: % | J86: =+J85/G85-1 -> 0.12857143 | K86: =+K85/H85-1 -> 0.13063063 | L86: =+L85/I85-1 -> 0.11818182 | M86: =+M85/J85-1 -> 0.12236287 | N86: =+N85/K85-1 -> 0.11155378 | O86: =+O85/L85-1 -> 0.1097561 | P86: =+P85/M85-1 -> 0.11278195 | Q86: =+Q85/N85-1 -> 0.13261649 | ... AV86: =+AV85/AS85-1 -> 0.052478134
A89: Aust_Fran_Network_sales | B89: Network sales | C89: A$m | F89: =+F10-F68 -> 396.2 | G89: =+G10-G68 -> 234.3 | H89: =+H10-H68 -> 256.6 | I89: =+I10-I68 -> 490.9 | J89: =+J10-J68 -> 302 | K89: =+K10-K68 -> 313.7 | L89: =+L10-L68 -> 615.7 | M89: =+M10-M68 -> 362.149 | ... O89: =+O10-O68 -> 734.9 | P89: =P46-P68 -> 409.54467 | Q89: =+R89-P89 -> 428.5188 | R89: =R46-R68 -> 838.06347 | S89: =S46-S68 -> 476.75408 | T89: =+U89-S89 -> 521.65894 | U89: =U46-U68 -> 998.41302 | V89: =V46-V68 -> 565.2846 | W89: =+X89-V89 -> 618.92255 | X89: =X46-X68 -> 1184.2071 | Y89: =Y46-Y68 -> 669.04796 | Z89: =+AA89-Y89 -> 728.69707 | AA89: =AA46-AA68 -> 1397.745 | AB89: =AB46-AB68 -> 779.80802 | AC89: =+AD89-AB89 -> 841.82907 | AD89: =AD46-AD68 -> 1621.6371 | AE89: =AE46-AE68 -> 891.62194 | AF89: =+AG89-AE89 -> 959.93901 | AG89: =AG46-AG68 -> 1851.561 | AH89: =AH46-AH68 -> 1012.6657 | AI89: =+AJ89-AH89 -> 1087.7495 | AJ89: =AJ46-AJ68 -> 2100.4152 | AK89: =AK46-AK68 -> 1143.583 | AL89: =+AM89-AK89 -> 1225.9363 | AM89: =AM46-AM68 -> 2369.5193 | AN89: =AN46-AN68 -> 1258.2368 | AO89: =+AP89-AN89 -> 1341.7829 | AP89: =AP46-AP68 -> 2600.0197 | AQ89: =AQ46-AQ68 -> 1368.9865 | AR89: =+AS89-AQ89 -> 1458.2297 | AS89: =AS46-AS68 -> 2827.2162 | AT89: =AT46-AT68 -> 1485.2481 | AU89: =+AV89-AT89 -> 1580.4538 | AV89: =AV46-AV68 -> 3065.702
A90: Aust_Franchisee_network_sales_gth | B90: % gth | C90: % | I90: =+I89/F89-1 -> 0.2390207 | J90: =+J89/G89-1 -> 0.2889458 | L90: =+L89/I89-1 -> 0.25422693 | M90: =+M89/J89-1 -> 0.19916887 | O90: =+O89/L89-1 -> 0.19360078 | P90: =+P89/M89-1 -> 0.13087339 | Q90: =+Q89/N89-1 -> 0.14961141 | R90: =+R89/O89-1 -> 0.14037756 | S90: =+S89/P89-1 -> 0.16410765 | T90: =+T89/Q89-1 -> 0.21735368 | U90: =+U89/R89-1 -> 0.19133342 | V90: =+V89/S89-1 -> 0.18569432 | ... AV90: =+AV89/AS89-1 -> 0.08435355
A92: Aust_Franchisee_Revenue | B92: Revenue | C92: A$m | F92: =30.1-F116-F139 -> 28.827 | G92: =+G93*G89 -> 18.744 | H92: =+I92-G92 -> 20.6375 | I92: =41.1-I116-I139 -> 39.3815 | J92: =+J93*J89 -> 25.368 | K92: =+L92-J92 -> 25.274 | L92: =51.858+0.645-L116-L139 -> 50.642 | M92: =32.187+0.949-M116-M139 -> 31.941 | N92: =+O92-M92 -> 32.9125 | O92: =66.761+0.63-O116-O139 -> 64.8535 | P92: =+P93*P89 -> 35.92527 | Q92: =+R92-P92 -> 37.589682 | R92: =+R93*R89 -> 73.514951 | S92: =+S93*S89 -> 42.889786 | T92: =+U92-S92 -> 46.929521 | U92: =+U93*U89 -> 89.819307 | V92: =+V93*V89 -> 56.52846 | W92: =+X92-V92 -> 53.163186 | X92: =+X93*X89 -> 109.69165 | Y92: =+Y93*Y89 -> 66.904796 | Z92: =+AA92-Y92 -> 66.558621 | AA92: =+AA93*AA89 -> 133.46342 | AB92: =+AB93*AB89 -> 75.321959 | AC92: =+AD92-AB92 -> 81.312596 | AD92: =+AD93*AD89 -> 156.63456 | AE92: =+AE93*AE89 -> 86.862045 | AF92: =+AG92-AE92 -> 93.517513 | AG92: =+AG93*AG89 -> 180.37956 | AH92: =+AH93*AH89 -> 99.452112 | AI92: =+AJ92-AH92 -> 106.82596 | AJ92: =+AJ93*AJ89 -> 206.27808 | AK92: =+AK93*AK89 -> 113.1654 | AL92: =+AM92-AK92 -> 121.31483 | AM92: =+AM93*AM89 -> 234.48023 | AN92: =+AN93*AN89 -> 125.07895 | AO92: =+AP92-AN92 -> 133.3841 | AP92: =+AP93*AP89 -> 258.46305 | AQ92: =+AQ93*AQ89 -> 136.66652 | AR92: =+AS92-AQ92 -> 145.57571 | AS92: =+AS93*AS89 -> 282.24223 | AT92: =+AT93*AT89 -> 148.27297 | AU92: =+AV92-AT92 -> 157.7774 | AV92: =+AV93*AV89 -> 306.05036
A93: Aust_Franchisee_royalty_fee | B93: % royalty | C93: % | F93: =F92/F89 -> 0.072758708 | G93: 0.08 | H93: =H92/H89 -> 0.080426734 | I93: =I92/I89 -> 0.08022306 | J93: 0.084 | K93: =K92/K89 -> 0.080567421 | L93: =L92/L89 -> 0.082251096 | M93: =M92/M89 -> 0.088198504 | N93: =N92/N89 -> 0.088296208 | O93: =O92/O89 -> 0.088248061 | P93: =+R93 -> 0.087720028 | Q93: =Q92/Q89 -> 0.087720028 | R93: 0.087720028 | S93: =+U93 -> 0.089962076 | T93: =T92/T89 -> 0.089962076 | U93: 0.089962076 | V93: 0.1 | W93: =W92/W89 -> 0.085896347 | X93: 0.092628765 | Y93: 0.1 | Z93: =Z92/Z89 -> 0.091339218 | AA93: 0.095484809 | AB93: =+AD93 -> 0.096590388 | AC93: =AC92/AC89 -> 0.096590388 | AD93: 0.096590388 | AE93: =+AG93 -> 0.097420265 | AF93: =AF92/AF89 -> 0.097420265 | AG93: 0.097420265 | AH93: =+AJ93 -> 0.09820824 | AI93: =AI92/AI89 -> 0.09820824 | AJ93: 0.09820824 | AK93: =+AM93 -> 0.098956876 | AL93: =AL92/AL89 -> 0.098956876 | AM93: 0.098956876 | AN93: =+AP93 -> 0.099408109 | AO93: =AO92/AO89 -> 0.099408109 | AP93: 0.099408109 | AQ93: =+AS93 -> 0.099830437 | AR93: =AR92/AR89 -> 0.099830437 | AS93: 0.099830437 | AT93: =AS93 -> 0.099830437 | AU93: =AU92/AU89 -> 0.099830437 | AV93: =AT93 -> 0.099830437
B94: % gth in rev | C94: % | I94: =+I92/F92-1 -> 0.36613245 | J94: =+J92/G92-1 -> 0.35339309 | K94: =+K92/H92-1 -> 0.22466384 | L94: =+L92/I92-1 -> 0.28593375 | M94: =+M92/J92-1 -> 0.25910596 | N94: =+N92/K92-1 -> 0.30222759 | O94: =+O92/L92-1 -> 0.28062675 | P94: =+P92/M92-1 -> 0.12473842 | ... AV94: =+AV92/AS92-1 -> 0.08435355
B97: SGP - Franchised
B99: Restaurants BOP | C99: # | I99: =+F101 -> 8 | J99: =+I101 -> 14 | K99: =+J101 -> 16 | L99: =+I101 -> 14 | M99: =+L101 -> 17 | N99: =+M101 -> 20 | O99: =+L101 -> 17 | P99: =+O101 -> 21 | Q99: =+P101 -> 23 | R99: =+O101 -> 21 | S99: =+R101 -> 25 | T99: =+S101 -> 26 | U99: =+R101 -> 25 | V99: =+U101 -> 27 | W99: =+V101 -> 28 | X99: =+U101 -> 27 | Y99: =+X101 -> 29 | Z99: =+Y101 -> 30 | AA99: =+X101 -> 29 | AB99: =+AA101 -> 31 | AC99: =+AB101 -> 32 | AD99: =+AA101 -> 31 | AE99: =+AD101 -> 33 | AF99: =+AE101 -> 34 | AG99: =+AD101 -> 33 | AH99: =+AG101 -> 35 | AI99: =+AH101 -> 36 | AJ99: =+AG101 -> 35 | AK99: =+AJ101 -> 37 | AL99: =+AK101 -> 38 | AM99: =+AJ101 -> 37 | AN99: =+AM101 -> 39 | AO99: =+AN101 -> 40 | AP99: =+AM101 -> 39 | AQ99: =+AP101 -> 41 | AR99: =+AQ101 -> 42 | AS99: =+AP101 -> 41 | AT99: =+AS101 -> 43 | AU99: =+AT101 -> 44 | AV99: =+AS101 -> 43
B100: Net openings | C100: # | I100: 6 | J100: 2 | K100: =+K101-K99 -> 1 | L100: =+J100+K100 -> 3 | M100: =+M101-M99 -> 3 | N100: =+N101-N99 -> 1 | O100: =+M100+N100 -> 4 | P100: 2 | Q100: 2 | R100: =+P100+Q100 -> 4 | S100: 1 | T100: 1 | U100: =+S100+T100 -> 2 | V100: 1 | W100: 1 | X100: =+V100+W100 -> 2 | Y100: 1 | Z100: 1 | AA100: =+Y100+Z100 -> 2 | AB100: 1 | AC100: 1 | AD100: =+AB100+AC100 -> 2 | AE100: 1 | AF100: 1 | AG100: =+AE100+AF100 -> 2 | AH100: 1 | AI100: 1 | AJ100: =+AH100+AI100 -> 2 | AK100: 1 | AL100: 1 | AM100: =+AK100+AL100 -> 2 | AN100: 1 | AO100: 1 | AP100: =+AN100+AO100 -> 2 | AQ100: 1 | AR100: 1 | AS100: =+AQ100+AR100 -> 2 | AT100: 1 | AU100: 1 | AV100: =+AT100+AU100 -> 2
B101: Restaurants EOP | C101: # | E101: =+F101-2 -> 6 | F101: 8 | G101: 10 | H101: 12 | I101: =+I99+I100 -> 14 | J101: =+J99+J100 -> 16 | K101: =+L101 -> 17 | L101: 17 | M101: 20 | N101: =+O101 -> 21 | O101: 21 | P101: =+P99+P100 -> 23 | Q101: =+Q99+Q100 -> 25 | R101: =+R99+R100 -> 25 | S101: =+S99+S100 -> 26 | T101: =+T99+T100 -> 27 | U101: =+U99+U100 -> 27 | V101: =+V99+V100 -> 28 | W101: =+W99+W100 -> 29 | ... AV101: =+AV99+AV100 -> 45
B102: Average stores | C102: # | G102: =+AVERAGE(F101:G101) -> 9 | H102: =+AVERAGE(G101:H101) -> 11 | I102: =+(I101+F101)/2 -> 11 | J102: =+AVERAGE(I101:J101) -> 15 | K102: =+AVERAGE(J101:K101) -> 16.5 | L102: =+(L101+I101)/2 -> 15.5 | M102: =+AVERAGE(L101:M101) -> 18.5 | N102: =+AVERAGE(M101:N101) -> 20.5 | O102: =+(O101+L101)/2 -> 19 | P102: =+AVERAGE(O101:P101) -> 22 | Q102: =+AVERAGE(P101:Q101) -> 24 | R102: =+(R101+O101)/2 -> 23 | S102: =+AVERAGE(R101:S101) -> 25.5 | T102: =+AVERAGE(S101:T101) -> 26.5 | U102: =+(U101+R101)/2 -> 26 | V102: =+AVERAGE(U101:V101) -> 27.5 | W102: =+AVERAGE(V101:W101) -> 28.5 | X102: =+(X101+U101)/2 -> 28 | Y102: =+AVERAGE(X101:Y101) -> 29.5 | Z102: =+AVERAGE(Y101:Z101) -> 30.5 | AA102: =+(AA101+X101)/2 -> 30 | AB102: =+AVERAGE(AA101:AB101) -> 31.5 | AC102: =+AVERAGE(AB101:AC101) -> 32.5 | AD102: =+(AD101+AA101)/2 -> 32 | AE102: =+AVERAGE(AD101:AE101) -> 33.5 | AF102: =+AVERAGE(AE101:AF101) -> 34.5 | AG102: =+(AG101+AD101)/2 -> 34 | AH102: =+AVERAGE(AG101:AH101) -> 35.5 | AI102: =+AVERAGE(AH101:AI101) -> 36.5 | AJ102: =+(AJ101+AG101)/2 -> 36 | AK102: =+AVERAGE(AJ101:AK101) -> 37.5 | AL102: =+AVERAGE(AK101:AL101) -> 38.5 | AM102: =+(AM101+AJ101)/2 -> 38 | AN102: =+AVERAGE(AM101:AN101) -> 39.5 | AO102: =+AVERAGE(AN101:AO101) -> 40.5 | AP102: =+(AP101+AM101)/2 -> 40 | AQ102: =+AVERAGE(AP101:AQ101) -> 41.5 | AR102: =+AVERAGE(AQ101:AR101) -> 42.5 | AS102: =+(AS101+AP101)/2 -> 42 | AT102: =+AVERAGE(AS101:AT101) -> 43.5 | AU102: =+AVERAGE(AT101:AU101) -> 44.5 | AV102: =+(AV101+AS101)/2 -> 44
A104: SG_network_sales | B104: Network Sales | C104: A$m | D104: 17 | E104: 22 | F104: 31.4 | G104: 21.5 | H104: =+I104-G104 -> 21.6 | I104: 43.1 | J104: 22.2 | K104: =+L104-J104 -> 24.2 | L104: 46.4 | M104: 30.2 | N104: =+O104-M104 -> 34.5 | O104: 64.7 | P104: =(1+P113)*M104 -> 34.566757 | Q104: =R104-P104 -> 40.17877 | R104: =(1+R113)*O104 -> 74.745526 | S104: =(1+S113)*P104 -> 39.044723 | T104: =U104-S104 -> 44.312788 | U104: =(1+U113)*R104 -> 83.357511 | V104: =(1+V113)*S104 -> 41.74723 | W104: =X104-V104 -> 47.317064 | X104: =(1+X113)*U104 -> 89.064294 | Y104: =(1+Y113)*V104 -> 44.517728 | Z104: =AA104-Y104 -> 50.399363 | AA104: =(1+AA113)*X104 -> 94.917091 | AB104: =(1+AB113)*Y104 -> 47.362336 | AC104: =AD104-AB104 -> 53.566171 | AD104: =(1+AD113)*AA104 -> 100.92851 | AE104: =(1+AE113)*AB104 -> 50.286772 | AF104: =AG104-AE104 -> 56.823606 | AG104: =(1+AG113)*AD104 -> 107.11038 | AH104: =(1+AH113)*AE104 -> 53.296473 | AI104: =AJ104-AH104 -> 60.177521 | AJ104: =(1+AJ113)*AG104 -> 113.47399 | AK104: =(1+AK113)*AH104 -> 56.396676 | AL104: =AM104-AK104 -> 63.633593 | AM104: =(1+AM113)*AJ104 -> 120.03027 | AN104: =(1+AN113)*AK104 -> 59.592488 | AO104: =AP104-AN104 -> 67.197381 | AP104: =(1+AP113)*AM104 -> 126.78987 | AQ104: =(1+AQ113)*AN104 -> 62.888933 | AR104: =AS104-AQ104 -> 70.874379 | AS104: =(1+AS113)*AP104 -> 133.76331 | AT104: =(1+AT113)*AQ104 -> 66.290997 | AU104: =AV104-AT104 -> 74.670055 | AV104: =(1+AV113)*AS104 -> 140.96105
A105: SG_network_sales % gth | B105: % gth | C105: % | E105: =+E104/D104-1 -> 0.29411765 | F105: =+F104/E104-1 -> 0.42727273 | I105: =+I104/F104-1 -> 0.37261146 | J105: =+J104/G104-1 -> 0.03255814 | K105: =+K104/H104-1 -> 0.12037037 | L105: =+L104/I104-1 -> 0.076566125 | M105: =+M104/J104-1 -> 0.36036036 | N105: =+N104/K104-1 -> 0.42561983 | O105: =+O104/L104-1 -> 0.39439655 | P105: =+P104/M104-1 -> 0.14459459 | ... AV105: =+AV104/AS104-1 -> 0.053809524
B107: Network sales per store | C107: A$m | E107: =E104/E101 -> 3.6666667 | F107: =F104/F101 -> 3.925 | G107: =G104/G102 -> 2.3888889 | H107: =H104/H102 -> 1.9636364 | I107: =I104/I102 -> 3.9181818 | J107: =J104/J102 -> 1.48 | K107: =K104/K102 -> 1.4666667 | L107: =L104/L102 -> 2.9935484 | M107: =M104/M102 -> 1.6324324 | N107: =N104/N102 -> 1.6829268 | ... AV107: =AV104/AV102 -> 3.2036603
B109: Network Sales
B110: LFL sales gth | C110: % | P110: 0.05 | Q110: =+(2*R110)-P110 -> 0.05 | R110: =+P110 -> 0.05 | S110: =+R110 -> 0.05 | T110: =+(2*U110)-S110 -> 0.05 | U110: =+S110 -> 0.05 | V110: 0.03 | W110: =+(2*X110)-V110 -> 0.03 | X110: =+V110 -> 0.03 | Y110: =+X110 -> 0.03 | Z110: =+(2*AA110)-Y110 -> 0.03 | AA110: =+Y110 -> 0.03 | AB110: =+AA110 -> 0.03 | AC110: =+(2*AD110)-AB110 -> 0.03 | AD110: =+AB110 -> 0.03 | AE110: =+AD110 -> 0.03 | AF110: =+(2*AG110)-AE110 -> 0.03 | AG110: =+AE110 -> 0.03 | AH110: =+AG110 -> 0.03 | AI110: =+(2*AJ110)-AH110 -> 0.03 | AJ110: =+AH110 -> 0.03 | AK110: =+AJ110 -> 0.03 | AL110: =+(2*AM110)-AK110 -> 0.03 | AM110: =+AK110 -> 0.03 | AN110: =+AM110 -> 0.03 | AO110: =+(2*AP110)-AN110 -> 0.03 | AP110: =+AN110 -> 0.03 | AQ110: =+AP110 -> 0.03 | AR110: =+(2*AS110)-AQ110 -> 0.03 | AS110: =+AQ110 -> 0.03 | AT110: =+AS110 -> 0.03 | AU110: =+(2*AV110)-AT110 -> 0.03 | AV110: =+AT110 -> 0.03
B111: Store growth | C111: % | K111: =K102/H102-1 -> 0.5 | L111: =L102/I102-1 -> 0.40909091 | M111: =M102/J102-1 -> 0.23333333 | N111: =N102/K102-1 -> 0.24242424 | O111: =O102/L102-1 -> 0.22580645 | P111: =P102/M102-1 -> 0.18918919 | Q111: =Q102/N102-1 -> 0.17073171 | R111: =R102/O102-1 -> 0.21052632 | ... AV111: =AV102/AS102-1 -> 0.047619048
B112: Implied cannibalisation / timing | C112: % | P112: =-50%*P111 -> -0.094594595 | Q112: =+Q113-Q110-Q111 -> -0.056129691 | R112: =-50%*R111 -> -0.10526316 | S112: =-50%*S111 -> -0.079545455 | T112: =+T113-T110-T111 -> -0.051276051 | U112: =-50%*U111 -> -0.065217391 | V112: =-50%*V111 -> -0.039215686 | W112: =+W113-W110-W111 -> -0.037674652 | X112: =-50%*X111 -> -0.038461538 | Y112: =-50%*Y111 -> -0.036363636 | Z112: =+Z113-Z110-Z111 -> -0.035034067 | AA112: =-50%*AA111 -> -0.035714286 | AB112: =-50%*AB111 -> -0.033898305 | AC112: =+AC113-AC110-AC111 -> -0.032739476 | AD112: =-50%*AD111 -> -0.033333333 | AE112: =-50%*AE111 -> -0.031746032 | AF112: =+AF113-AF110-AF111 -> -0.030727045 | AG112: =-50%*AG111 -> -0.03125 | AH112: =-50%*AH111 -> -0.029850746 | AI112: =+AI113-AI110-AI111 -> -0.028947732 | AJ112: =-50%*AJ111 -> -0.029411765 | AK112: =-50%*AK111 -> -0.028169014 | AL112: =+AL113-AL110-AL111 -> -0.027363243 | AM112: =-50%*AM111 -> -0.027777778 | AN112: =-50%*AN111 -> -0.026666667 | AO112: =+AO113-AO110-AO111 -> -0.025943235 | AP112: =-50%*AP111 -> -0.026315789 | AQ112: =-50%*AQ111 -> -0.025316456 | AR112: =+AR113-AR110-AR111 -> -0.024663358 | AS112: =-50%*AS111 -> -0.025 | AT112: =-50%*AT111 -> -0.024096386 | AU112: =+AU113-AU110-AU111 -> -0.023503841 | AV112: =-50%*AV111 -> -0.023809524
B113: Sales Growth | C113: % | P113: =+P110+P111+P112 -> 0.14459459 | Q113: =Q104/N104-1 -> 0.16460202 | R113: =+R110+R111+R112 -> 0.15526316 | S113: =+S110+S111+S112 -> 0.12954545 | T113: =T104/Q104-1 -> 0.10289062 | U113: =+U110+U111+U112 -> 0.11521739 | V113: =+V110+V111+V112 -> 0.069215686 | W113: =W104/T104-1 -> 0.067797046 | X113: =+X110+X111+X112 -> 0.068461538 | Y113: =+Y110+Y111+Y112 -> 0.066363636 | Z113: =Z104/W104-1 -> 0.065141372 | AA113: =+AA110+AA111+AA112 -> 0.065714286 | AB113: =+AB110+AB111+AB112 -> 0.063898305 | AC113: =AC104/Z104-1 -> 0.062834294 | AD113: =+AD110+AD111+AD112 -> 0.063333333 | AE113: =+AE110+AE111+AE112 -> 0.061746032 | AF113: =AF104/AC104-1 -> 0.060811417 | AG113: =+AG110+AG111+AG112 -> 0.06125 | AH113: =+AH110+AH111+AH112 -> 0.059850746 | AI113: =AI104/AF104-1 -> 0.059023282 | AJ113: =+AJ110+AJ111+AJ112 -> 0.059411765 | AK113: =+AK110+AK111+AK112 -> 0.058169014 | AL113: =AL104/AI104-1 -> 0.057431278 | AM113: =+AM110+AM111+AM112 -> 0.057777778 | AN113: =+AN110+AN111+AN112 -> 0.056666667 | AO113: =AO104/AL104-1 -> 0.056004817 | AP113: =+AP110+AP111+AP112 -> 0.056315789 | AQ113: =+AQ110+AQ111+AQ112 -> 0.055316456 | AR113: =AR104/AO104-1 -> 0.054719358 | AS113: =+AS110+AS111+AS112 -> 0.055 | AT113: =+AT110+AT111+AT112 -> 0.054096386 | AU113: =AU104/AR104-1 -> 0.053554983 | AV113: =+AV110+AV111+AV112 -> 0.053809524
B116: Revenue | C116: A$m | F116: =+F104*F118 -> 1.099 | G116: =+G104*G118 -> 0.7525 | H116: =+H104*H118 -> 0.756 | I116: =+I104*I118 -> 1.5085 | J116: =+J104*J118 -> 0.777 | K116: =+L116-J116 -> 0.847 | L116: =+L104*L118 -> 1.624 | M116: =+M104*M118 -> 1.057 | N116: =+O116-M116 -> 1.2075 | O116: =+O104*O118 -> 2.2645 | P116: =+P104*P118 -> 1.2098365 | Q116: =+R116-P116 -> 1.4062569 | R116: =+R104*R118 -> 2.6160934 | S116: =+S104*S118 -> 1.3665653 | T116: =+U116-S116 -> 1.5509476 | U116: =+U104*U118 -> 2.9175129 | V116: =+V104*V118 -> 1.4611531 | W116: =+X116-V116 -> 1.6560972 | X116: =+X104*X118 -> 3.1172503 | Y116: =+Y104*Y118 -> 1.5581205 | Z116: =+AA116-Y116 -> 1.7639777 | AA116: =+AA104*AA118 -> 3.3220982 | AB116: =+AB104*AB118 -> 1.6576817 | AC116: =+AD116-AB116 -> 1.874816 | AD116: =+AD104*AD118 -> 3.5324977 | AE116: =+AE104*AE118 -> 1.760037 | AF116: =+AG116-AE116 -> 1.9888262 | AG116: =+AG104*AG118 -> 3.7488632 | AH116: =+AH104*AH118 -> 1.8653765 | AI116: =+AJ116-AH116 -> 2.1062132 | AJ116: =+AJ104*AJ118 -> 3.9715898 | AK116: =+AK104*AK118 -> 1.9738837 | AL116: =+AM116-AK116 -> 2.2271758 | AM116: =+AM104*AM118 -> 4.2010594 | AN116: =+AN104*AN118 -> 2.0857371 | AO116: =+AP116-AN116 -> 2.3519083 | AP116: =+AP104*AP118 -> 4.4376454 | AQ116: =+AQ104*AQ118 -> 2.2011127 | AR116: =+AS116-AQ116 -> 2.4806033 | AS116: =+AS104*AS118 -> 4.6817159 | AT116: =+AT104*AT118 -> 2.3201849 | AU116: =+AV116-AT116 -> 2.6134519 | AV116: =+AV104*AV118 -> 4.9336368
B117: % gth | C117: % | I117: =+I116/F116-1 -> 0.37261146 | J117: =+J116/G116-1 -> 0.03255814 | K117: =+K116/H116-1 -> 0.12037037 | L117: =+L116/I116-1 -> 0.076566125 | M117: =+M116/J116-1 -> 0.36036036 | N117: =+N116/K116-1 -> 0.42561983 | O117: =+O116/L116-1 -> 0.39439655 | P117: =+P116/M116-1 -> 0.14459459 | ... AV117: =+AV116/AS116-1 -> 0.053809524
B118: Master Franchisee fee | C118: % | F118: 0.035 | G118: =+F118 -> 0.035 | H118: =+G118 -> 0.035 | I118: =+H118 -> 0.035 | J118: =+I118 -> 0.035 | K118: =K116/K104 -> 0.035 | L118: 0.035 | M118: =+L118 -> 0.035 | N118: =N116/N104 -> 0.035 | O118: 0.035 | P118: =+O118 -> 0.035 | Q118: =Q116/Q104 -> 0.035 | R118: =+P118 -> 0.035 | S118: =+R118 -> 0.035 | T118: =T116/T104 -> 0.035 | U118: =+S118 -> 0.035 | V118: =+U118 -> 0.035 | W118: =W116/W104 -> 0.035 | X118: =+V118 -> 0.035 | Y118: =+X118 -> 0.035 | Z118: =Z116/Z104 -> 0.035 | AA118: =+Y118 -> 0.035 | AB118: =+AA118 -> 0.035 | AC118: =AC116/AC104 -> 0.035 | AD118: =+AB118 -> 0.035 | AE118: =+AD118 -> 0.035 | AF118: =AF116/AF104 -> 0.035 | AG118: =+AE118 -> 0.035 | AH118: =+AG118 -> 0.035 | AI118: =AI116/AI104 -> 0.035 | AJ118: =+AH118 -> 0.035 | AK118: =+AJ118 -> 0.035 | AL118: =AL116/AL104 -> 0.035 | AM118: =+AK118 -> 0.035 | AN118: =+AM118 -> 0.035 | AO118: =AO116/AO104 -> 0.035 | AP118: =+AN118 -> 0.035 | AQ118: =+AP118 -> 0.035 | AR118: =AR116/AR104 -> 0.035 | AS118: =+AQ118 -> 0.035 | AT118: =+AS118 -> 0.035 | AU118: =AU116/AU104 -> 0.035 | AV118: =+AT118 -> 0.035
B121: JP - Franchised
B123: Restaurants BOP | C123: # | F123: =+E125 -> 2 | I123: =+F125 -> 2 | J123: =+I125 -> 4 | K123: =+J125 -> 4 | L123: =+I125 -> 4 | M123: =+L125 -> 5 | N123: =+M125 -> 5 | O123: =+L125 -> 5 | P123: =+O125 -> 5 | Q123: =+P125 -> 6 | R123: =+O125 -> 5 | S123: =+R125 -> 7 | T123: =+S125 -> 8 | U123: =+R125 -> 7 | V123: =+U125 -> 9 | W123: =+V125 -> 10 | X123: =+U125 -> 9 | Y123: =+X125 -> 11 | Z123: =+Y125 -> 12 | AA123: =+X125 -> 11 | AB123: =+AA125 -> 13 | AC123: =+AB125 -> 14 | AD123: =+AA125 -> 13 | AE123: =+AD125 -> 15 | AF123: =+AE125 -> 16 | AG123: =+AD125 -> 15 | AH123: =+AG125 -> 17 | AI123: =+AH125 -> 18 | AJ123: =+AG125 -> 17 | AK123: =+AJ125 -> 19 | AL123: =+AK125 -> 20 | AM123: =+AJ125 -> 19 | AN123: =+AM125 -> 21 | AO123: =+AN125 -> 22 | AP123: =+AM125 -> 21 | AQ123: =+AP125 -> 23 | AR123: =+AQ125 -> 24 | AS123: =+AP125 -> 23 | AT123: =+AS125 -> 25 | AU123: =+AT125 -> 26 | AV123: =+AS125 -> 25
B124: Net openings | C124: # | I124: 2 | J124: 0 | K124: =+K125-K123 -> 1 | L124: =+J124+K124 -> 1 | M124: =+M125-M123 -> 0 | N124: =+N125-N123 -> 0 | O124: =+M124+N124 -> 0 | P124: 1 | Q124: 1 | R124: =+P124+Q124 -> 2 | S124: 1 | T124: 1 | U124: =+S124+T124 -> 2 | V124: 1 | W124: 1 | X124: =+V124+W124 -> 2 | Y124: 1 | Z124: 1 | AA124: =+Y124+Z124 -> 2 | AB124: 1 | AC124: 1 | AD124: =+AB124+AC124 -> 2 | AE124: 1 | AF124: 1 | AG124: =+AE124+AF124 -> 2 | AH124: 1 | AI124: 1 | AJ124: =+AH124+AI124 -> 2 | AK124: 1 | AL124: 1 | AM124: =+AK124+AL124 -> 2 | AN124: 1 | AO124: 1 | AP124: =+AN124+AO124 -> 2 | AQ124: 1 | AR124: 1 | AS124: =+AQ124+AR124 -> 2 | AT124: 1 | AU124: 1 | AV124: =+AT124+AU124 -> 2
B125: Restaurants EOP | C125: # | E125: 2 | F125: 2 | G125: 3 | H125: 3 | I125: 4 | J125: =+J123+J124 -> 4 | K125: =+L125 -> 5 | L125: 5 | M125: 5 | N125: =+O125 -> 5 | O125: 5 | P125: =+P123+P124 -> 6 | Q125: =+Q123+Q124 -> 7 | R125: =+R123+R124 -> 7 | S125: =+S123+S124 -> 8 | T125: =+T123+T124 -> 9 | U125: =+U123+U124 -> 9 | V125: =+V123+V124 -> 10 | W125: =+W123+W124 -> 11 | ... AV125: =+AV123+AV124 -> 27
B126: Average stores | C126: # | G126: =+AVERAGE(F125:G125) -> 2.5 | H126: =+AVERAGE(G125:H125) -> 3 | I126: =+(I125+F125)/2 -> 3 | J126: =+AVERAGE(I125:J125) -> 4 | K126: =+AVERAGE(J125:K125) -> 4.5 | L126: =+(L125+I125)/2 -> 4.5 | M126: =+AVERAGE(L125:M125) -> 5 | N126: =+AVERAGE(M125:N125) -> 5 | O126: =+(O125+L125)/2 -> 5 | P126: =+AVERAGE(O125:P125) -> 5.5 | Q126: =+AVERAGE(P125:Q125) -> 6.5 | R126: =+(R125+O125)/2 -> 6 | S126: =+AVERAGE(R125:S125) -> 7.5 | T126: =+AVERAGE(S125:T125) -> 8.5 | U126: =+(U125+R125)/2 -> 8 | V126: =+AVERAGE(U125:V125) -> 9.5 | W126: =+AVERAGE(V125:W125) -> 10.5 | X126: =+(X125+U125)/2 -> 10 | Y126: =+AVERAGE(X125:Y125) -> 11.5 | Z126: =+AVERAGE(Y125:Z125) -> 12.5 | AA126: =+(AA125+X125)/2 -> 12 | AB126: =+AVERAGE(AA125:AB125) -> 13.5 | AC126: =+AVERAGE(AB125:AC125) -> 14.5 | AD126: =+(AD125+AA125)/2 -> 14 | AE126: =+AVERAGE(AD125:AE125) -> 15.5 | AF126: =+AVERAGE(AE125:AF125) -> 16.5 | AG126: =+(AG125+AD125)/2 -> 16 | AH126: =+AVERAGE(AG125:AH125) -> 17.5 | AI126: =+AVERAGE(AH125:AI125) -> 18.5 | AJ126: =+(AJ125+AG125)/2 -> 18 | AK126: =+AVERAGE(AJ125:AK125) -> 19.5 | AL126: =+AVERAGE(AK125:AL125) -> 20.5 | AM126: =+(AM125+AJ125)/2 -> 20 | AN126: =+AVERAGE(AM125:AN125) -> 21.5 | AO126: =+AVERAGE(AN125:AO125) -> 22.5 | AP126: =+(AP125+AM125)/2 -> 22 | AQ126: =+AVERAGE(AP125:AQ125) -> 23.5 | AR126: =+AVERAGE(AQ125:AR125) -> 24.5 | AS126: =+(AS125+AP125)/2 -> 24 | AT126: =+AVERAGE(AS125:AT125) -> 25.5 | AU126: =+AVERAGE(AT125:AU125) -> 26.5 | AV126: =+(AV125+AS125)/2 -> 26
A128: JP_network_sales | B128: Network Sales | C128: A$m | D128: 5 | E128: 5 | F128: 5.8 | G128: 3.2 | H128: =+I128-G128 -> 3.8 | I128: 7 | J128: 4.2 | K128: =L128-J128 -> 3.7 | L128: 7.9 | M128: 4.6 | N128: =O128-M128 -> 4.5 | O128: 9.1 | P128: =(1+P137)*M128 -> 5.06 | Q128: =+R128-P128 -> 5.405 | R128: =(1+R137)*O128 -> 10.465 | S128: =(1+S137)*P128 -> 6.233 | T128: =+U128-S128 -> 6.4994167 | U128: =(1+U137)*R128 -> 12.732417 | V128: =(1+V137)*S128 -> 7.2510567 | W128: =+X128-V128 -> 7.4548846 | X128: =(1+X137)*U128 -> 14.705941 | Y128: =(1+Y137)*V128 -> 8.2318575 | Z128: =+AA128-Y128 -> 8.3858561 | AA128: =(1+AA137)*X128 -> 16.617714 | AB128: =(1+AB137)*Y128 -> 9.1946269 | AC128: =+AD128-AB128 -> 9.3064276 | AD128: =(1+AD137)*AA128 -> 18.501054 | AE128: =(1+AE137)*AB128 -> 10.151549 | AF128: =+AG128-AE128 -> 10.226041 | AG128: =(1+AG137)*AD128 -> 20.37759 | AH128: =(1+AH137)*AE128 -> 11.111034 | AI128: =+AJ128-AH128 -> 11.151483 | AJ128: =(1+AJ137)*AG128 -> 22.262517 | AK128: =(1+AK137)*AH128 -> 12.079282 | AL128: =+AM128-AK128 -> 12.087918 | AM128: =(1+AM137)*AJ128 -> 24.167199 | AN128: =(1+AN137)*AK128 -> 13.06111 | AO128: =+AP128-AN128 -> 13.039465 | AP128: =(1+AP137)*AM128 -> 26.100575 | AQ128: =(1+AQ137)*AN128 -> 14.060437 | AR128: =+AS128-AQ128 -> 14.009545 | AS128: =(1+AS137)*AP128 -> 28.069982 | AT128: =(1+AT137)*AQ128 -> 15.080567 | AU128: =+AV128-AT128 -> 15.001097 | AV128: =(1+AV137)*AS128 -> 30.081664
A129: JP_network_sales % gth | B129: % gth | C129: % | E129: =+E128/D128-1 -> 0 | F129: =+F128/E128-1 -> 0.16 | I129: =+I128/F128-1 -> 0.20689655 | J129: =+J128/G128-1 -> 0.3125 | K129: =+K128/H128-1 -> -0.026315789 | L129: =+L128/I128-1 -> 0.12857143 | M129: =+M128/J128-1 -> 0.095238095 | N129: =+N128/K128-1 -> 0.21621622 | O129: =+O128/L128-1 -> 0.15189873 | P129: =+P128/M128-1 -> 0.1 | ... AV129: =+AV128/AS128-1 -> 0.071666667
B131: Network sales per store | C131: A$m | G131: =G128/G126 -> 1.28 | H131: =H128/H126 -> 1.2666667 | I131: =I128/I126 -> 2.3333333 | J131: =J128/J126 -> 1.05 | K131: =K128/K126 -> 0.82222222 | L131: =L128/L126 -> 1.7555556 | M131: =M128/M126 -> 0.92 | N131: =N128/N126 -> 0.9 | ... AV131: =AV128/AV126 -> 1.1569871
B133: Network Sales
B134: LFL sales gth | C134: % | P134: 0.05 | Q134: =+(2*R134)-P134 -> 0.05 | R134: =+P134 -> 0.05 | S134: =+R134 -> 0.05 | T134: =+(2*U134)-S134 -> 0.05 | U134: =+S134 -> 0.05 | V134: 0.03 | W134: =+(2*X134)-V134 -> 0.03 | X134: =+V134 -> 0.03 | Y134: =+X134 -> 0.03 | Z134: =+(2*AA134)-Y134 -> 0.03 | AA134: =+Y134 -> 0.03 | AB134: =+AA134 -> 0.03 | AC134: =+(2*AD134)-AB134 -> 0.03 | AD134: =+AB134 -> 0.03 | AE134: =+AD134 -> 0.03 | AF134: =+(2*AG134)-AE134 -> 0.03 | AG134: =+AE134 -> 0.03 | AH134: =+AG134 -> 0.03 | AI134: =+(2*AJ134)-AH134 -> 0.03 | AJ134: =+AH134 -> 0.03 | AK134: =+AJ134 -> 0.03 | AL134: =+(2*AM134)-AK134 -> 0.03 | AM134: =+AK134 -> 0.03 | AN134: =+AM134 -> 0.03 | AO134: =+(2*AP134)-AN134 -> 0.03 | AP134: =+AN134 -> 0.03 | AQ134: =+AP134 -> 0.03 | AR134: =+(2*AS134)-AQ134 -> 0.03 | AS134: =+AQ134 -> 0.03 | AT134: =+AS134 -> 0.03 | AU134: =+(2*AV134)-AT134 -> 0.03 | AV134: =+AT134 -> 0.03
B135: Store growth | C135: % | P135: =P126/M126-1 -> 0.1 | Q135: =Q126/N126-1 -> 0.3 | R135: =R126/O126-1 -> 0.2 | S135: =S126/P126-1 -> 0.36363636 | T135: =T126/Q126-1 -> 0.30769231 | U135: =U126/R126-1 -> 0.33333333 | V135: =V126/S126-1 -> 0.26666667 | W135: =W126/T126-1 -> 0.23529412 | ... AV135: =AV126/AS126-1 -> 0.083333333
B136: Implied cannibalisation / timing | C136: % | P136: =-50%*P135 -> -0.05 | Q136: =+Q137-Q134-Q135 -> -0.14888889 | R136: =-50%*R135 -> -0.1 | S136: =-50%*S135 -> -0.18181818 | T136: =+T137-T134-T135 -> -0.15521004 | U136: =-50%*U135 -> -0.16666667 | V136: =-50%*V135 -> -0.13333333 | W136: =+W137-W134-W135 -> -0.11828586 | X136: =-50%*X135 -> -0.125 | Y136: =-50%*Y135 -> -0.10526316 | Z136: =+Z137-Z134-Z135 -> -0.095595446 | AA136: =-50%*AA135 -> -0.1 | AB136: =-50%*AB135 -> -0.086956522 | AC136: =+AC137-AC134-AC135 -> -0.080223319 | AD136: =-50%*AD135 -> -0.083333333 | AE136: =-50%*AE135 -> -0.074074074 | AF136: =+AF137-AF134-AF135 -> -0.069116185 | AG136: =-50%*AG135 -> -0.071428571 | AH136: =-50%*AH135 -> -0.064516129 | AI136: =+AI137-AI134-AI135 -> -0.060713564 | AJ136: =-50%*AJ135 -> -0.0625 | AK136: =-50%*AK135 -> -0.057142857 | AL136: =+AL137-AL134-AL135 -> -0.054134097 | AM136: =-50%*AM135 -> -0.055555556 | AN136: =-50%*AN135 -> -0.051282051 | AO136: =+AO137-AO134-AO135 -> -0.048842111 | AP136: =-50%*AP135 -> -0.05 | AQ136: =-50%*AQ135 -> -0.046511628 | AR136: =+AR137-AR134-AR135 -> -0.044493181 | AS136: =-50%*AS135 -> -0.045454545 | AT136: =-50%*AT135 -> -0.042553191 | AU136: =+AU137-AU134-AU135 -> -0.040855732 | AV136: =-50%*AV135 -> -0.041666667
B137: Sales Growth | C137: % | P137: =+P134+P135+P136 -> 0.1 | Q137: =Q128/N128-1 -> 0.20111111 | R137: =+R134+R135+R136 -> 0.15 | S137: =+S134+S135+S136 -> 0.23181818 | T137: =T128/Q128-1 -> 0.20248227 | U137: =+U134+U135+U136 -> 0.21666667 | V137: =+V134+V135+V136 -> 0.16333333 | W137: =W128/T128-1 -> 0.14700826 | X137: =+X134+X135+X136 -> 0.155 | Y137: =+Y134+Y135+Y136 -> 0.13526316 | Z137: =Z128/W128-1 -> 0.12488074 | AA137: =+AA134+AA135+AA136 -> 0.13 | AB137: =+AB134+AB135+AB136 -> 0.11695652 | AC137: =AC128/Z128-1 -> 0.10977668 | AD137: =+AD134+AD135+AD136 -> 0.11333333 | AE137: =+AE134+AE135+AE136 -> 0.10407407 | AF137: =AF128/AC128-1 -> 0.09881485 | AG137: =+AG134+AG135+AG136 -> 0.10142857 | AH137: =+AH134+AH135+AH136 -> 0.094516129 | AI137: =AI128/AF128-1 -> 0.090498557 | AJ137: =+AJ134+AJ135+AJ136 -> 0.0925 | AK137: =+AK134+AK135+AK136 -> 0.087142857 | AL137: =AL128/AI128-1 -> 0.083974011 | AM137: =+AM134+AM135+AM136 -> 0.085555556 | AN137: =+AN134+AN135+AN136 -> 0.081282051 | AO137: =AO128/AL128-1 -> 0.078718865 | AP137: =+AP134+AP135+AP136 -> 0.08 | AQ137: =+AQ134+AQ135+AQ136 -> 0.076511628 | AR137: =AR128/AO128-1 -> 0.074395708 | AS137: =+AS134+AS135+AS136 -> 0.075454545 | AT137: =+AT134+AT135+AT136 -> 0.072553191 | AU137: =AU128/AR128-1 -> 0.070776921 | AV137: =+AV134+AV135+AV136 -> 0.071666667
B139: Revenue | C139: A$m | F139: =+F128*F141 -> 0.174 | G139: =+G128*G141 -> 0.096 | H139: =+H128*H141 -> 0.114 | I139: =+I128*I141 -> 0.21 | J139: =+J128*J141 -> 0.126 | K139: =+L139-J139 -> 0.111 | L139: =+L128*L141 -> 0.237 | M139: =+M128*M141 -> 0.138 | N139: =+O139-M139 -> 0.135 | O139: =+O128*O141 -> 0.273 | P139: =+P128*P141 -> 0.1518 | Q139: =+R139-P139 -> 0.16215 | R139: =+R128*R141 -> 0.31395 | S139: =+S128*S141 -> 0.18699 | T139: =+U139-S139 -> 0.1949825 | U139: =+U128*U141 -> 0.3819725 | V139: =+V128*V141 -> 0.2175317 | W139: =+X139-V139 -> 0.22364654 | X139: =+X128*X141 -> 0.44117824 | Y139: =+Y128*Y141 -> 0.24695572 | Z139: =+AA139-Y139 -> 0.25157568 | AA139: =+AA128*AA141 -> 0.49853141 | AB139: =+AB128*AB141 -> 0.27583881 | AC139: =+AD139-AB139 -> 0.27919283 | AD139: =+AD128*AD141 -> 0.55503163 | AE139: =+AE128*AE141 -> 0.30454648 | AF139: =+AG139-AE139 -> 0.30678122 | AG139: =+AG128*AG141 -> 0.6113277 | AH139: =+AH128*AH141 -> 0.33333103 | AI139: =+AJ139-AH139 -> 0.33454448 | AJ139: =+AJ128*AJ141 -> 0.66787551 | AK139: =+AK128*AK141 -> 0.36237845 | AL139: =+AM139-AK139 -> 0.36263753 | AM139: =+AM128*AM141 -> 0.72501597 | AN139: =+AN128*AN141 -> 0.39183331 | AO139: =+AP139-AN139 -> 0.39118394 | AP139: =+AP128*AP141 -> 0.78301725 | AQ139: =+AQ128*AQ141 -> 0.42181312 | AR139: =+AS139-AQ139 -> 0.42028635 | AS139: =+AS128*AS141 -> 0.84209946 | AT139: =+AT128*AT141 -> 0.452417 | AU139: =+AV139-AT139 -> 0.45003292 | AV139: =+AV128*AV141 -> 0.90244992
B140: % gth | C140: % | I140: =+I139/F139-1 -> 0.20689655 | J140: =+J139/G139-1 -> 0.3125 | K140: =+K139/H139-1 -> -0.026315789 | L140: =+L139/I139-1 -> 0.12857143 | M140: =+M139/J139-1 -> 0.095238095 | N140: =+N139/K139-1 -> 0.21621622 | O140: =+O139/L139-1 -> 0.15189873 | P140: =+P139/M139-1 -> 0.1 | ... AV140: =+AV139/AS139-1 -> 0.071666667
...

Sheet Valuation - DCF
B2: Guzman Y Gomez (GYG.AX)
B3: Assumptions
B5: Year ended 30 June | C5: unit
B7: DCF Valuation | F7: FY24e | G7: FY25e | H7: FY26e | I7: FY27e | J7: FY28e | K7: FY29e | L7: FY30e | M7: FY31e | N7: FY32e | O7: FY33e | P7: FY34e | Q7: FY35e | R7: FY36e | S7: FY37e | T7: FY38e | U7: FY39e | V7: FY40e | W7: FY41e | X7: FY42e | Y7: FY43e | Z7: FY44e | AA7: FY45e | AB7: FY46e
A8: Total_revenue | B8: Sales | C8: A$m | F8: =VLOOKUP($A8,'Financial Statements'!$1:$1048576,MATCH('Valuation - DCF'!F$7,'Financial Statements'!$5:$5,0),FALSE) -> #N/A | G8: =VLOOKUP($A8,'Financial Statements'!$1:$1048576,MATCH('Valuation - DCF'!G$7,'Financial Statements'!$5:$5,0),FALSE) -> #N/A | H8: =VLOOKUP($A8,'Financial Statements'!$1:$1048576,MATCH('Valuation - DCF'!H$7,'Financial Statements'!$5:$5,0),FALSE) -> 597.65592 | I8: =VLOOKUP($A8,'Financial Statements'!$1:$1048576,MATCH('Valuation - DCF'!I$7,'Financial Statements'!$5:$5,0),FALSE) -> 725.06085 | J8: =VLOOKUP($A8,'Financial Statements'!$1:$1048576,MATCH('Valuation - DCF'!J$7,'Financial Statements'!$5:$5,0),FALSE) -> 879.08539 | K8: =VLOOKUP($A8,'Financial Statements'!$1:$1048576,MATCH('Valuation - DCF'!K$7,'Financial Statements'!$5:$5,0),FALSE) -> 1050.0305 | L8: =VLOOKUP($A8,'Financial Statements'!$1:$1048576,MATCH('Valuation - DCF'!L$7,'Financial Statements'!$5:$5,0),FALSE) -> 1227.2916 | M8: =VLOOKUP($A8,'Financial Statements'!$1:$1048576,MATCH('Valuation - DCF'!M$7,'Financial Statements'!$5:$5,0),FALSE) -> 1409.8237 | ... R8: =VLOOKUP($A8,'Financial Statements'!$1:$1048576,MATCH('Valuation - DCF'!R$7,'Financial Statements'!$5:$5,0),FALSE) -> 2382.7588 | S8: =(1+S9)*R8 -> 2553.1933 | T8: =(1+T9)*S8 -> 2731.5911 | U8: =(1+U9)*T8 -> 2918.2777 | V8: =(1+V9)*U8 -> 3092.0381 | W8: =(1+W9)*V8 -> 3273.5234 | X8: =(1+X9)*W8 -> 3463.0408 | Y8: =(1+Y9)*X8 -> 3637.4146 | Z8: =(1+Z9)*Y8 -> 3819.0918 | ... AB8: =(1+AB9)*AA8 -> 4210.1221
B9: % growth | C9: % | G9: =+G8/F8-1 -> #N/A | H9: =+H8/G8-1 -> #N/A | I9: =+I8/H8-1 -> 0.21317439 | J9: =+J8/I8-1 -> 0.21242981 | K9: =+K8/J8-1 -> 0.19445792 | L9: =+L8/K8-1 -> 0.1688152 | M9: =+M8/L8-1 -> 0.14872757 | N9: =+N8/M8-1 -> 0.1404617 | ... R9: =+R8/Q8-1 -> 0.087430324 | S9: =+'GYG network model'!AB20+3% -> 0.071528239 | T9: =+'GYG network model'!AC20+3% -> 0.069872408 | U9: =+'GYG network model'!AD20+3% -> 0.068343558 | V9: =+'GYG network model'!AE20+3% -> 0.059542097 | W9: =+'GYG network model'!AF20+3% -> 0.058694405 | X9: =+'GYG network model'!AG20+3% -> 0.057894003 | Y9: =+'GYG network model'!AH20+3% -> 0.050352782 | Z9: =+'GYG network model'!AI20+3% -> 0.049946809 | AA9: =+Z9 -> 0.049946809 | AB9: =+AA9 -> 0.049946809
A10: EBIT_DCF | B10: EBIT | C10: A$m | F10: =VLOOKUP($A10,Assumptions!$1:$1048576,MATCH('Valuation - DCF'!F$7,Assumptions!$5:$5,0),FALSE) -> #N/A | G10: =VLOOKUP($A10,Assumptions!$1:$1048576,MATCH('Valuation - DCF'!G$7,Assumptions!$5:$5,0),FALSE) -> #N/A | H10: =VLOOKUP($A10,Assumptions!$1:$1048576,MATCH('Valuation - DCF'!H$7,Assumptions!$5:$5,0),FALSE) -> 36.673596 | I10: =VLOOKUP($A10,Assumptions!$1:$1048576,MATCH('Valuation - DCF'!I$7,Assumptions!$5:$5,0),FALSE) -> 67.227753 | J10: =VLOOKUP($A10,Assumptions!$1:$1048576,MATCH('Valuation - DCF'!J$7,Assumptions!$5:$5,0),FALSE) -> 102.25809 | K10: =VLOOKUP($A10,Assumptions!$1:$1048576,MATCH('Valuation - DCF'!K$7,Assumptions!$5:$5,0),FALSE) -> 145.66063 | L10: =VLOOKUP($A10,Assumptions!$1:$1048576,MATCH('Valuation - DCF'!L$7,Assumptions!$5:$5,0),FALSE) -> 189.81568 | M10: =VLOOKUP($A10,Assumptions!$1:$1048576,MATCH('Valuation - DCF'!M$7,Assumptions!$5:$5,0),FALSE) -> 234.61021 | ... R10: =VLOOKUP($A10,Assumptions!$1:$1048576,MATCH('Valuation - DCF'!R$7,Assumptions!$5:$5,0),FALSE) -> 474.06108 | S10: =S11*S8 -> 514.35282 | T10: =T11*T8 -> 557.12087 | U10: =U11*U8 -> 602.49218 | V10: =V11*V8 -> 646.09593 | W10: =W11*W8 -> 692.20195 | X10: =X11*X8 -> 740.9339 | Y10: =Y11*Y8 -> 787.33552 | Z10: =Z11*Z8 -> 836.20814 | ... AB10: =AB11*AB8 -> 932.35138
B11: % margin | C11: % | F11: =F10/F8 -> #N/A | G11: =G10/G8 -> #N/A | H11: =H10/H8 -> 0.061362391 | I11: =I10/I8 -> 0.092720153 | J11: =J10/J8 -> 0.11632327 | K11: =K10/K8 -> 0.13872038 | L11: =L10/L8 -> 0.15466225 | M11: =M10/M8 -> 0.16641103 | ... R11: =R10/R8 -> 0.19895471 | S11: =+R11+0.25% -> 0.20145471 | T11: =+S11+0.25% -> 0.20395471 | U11: =+T11+0.25% -> 0.20645471 | V11: =+U11+0.25% -> 0.20895471 | W11: =+V11+0.25% -> 0.21145471 | X11: =+W11+0.25% -> 0.21395471 | Y11: =+X11+0.25% -> 0.21645471 | Z11: =+Y11+0.25% -> 0.21895471 | AA11: =+Z11+0.25% -> 0.22145471 | AB11: =+AA11 -> 0.22145471
B12: % growth | C12: % | G12: =+G10/F10-1 -> #N/A | H12: =+H10/G10-1 -> #N/A | I12: =+I10/H10-1 -> 0.83313775 | J12: =+J10/I10-1 -> 0.52106956 | K12: =+K10/J10-1 -> 0.42444113 | L12: =+L10/K10-1 -> 0.30313653 | M12: =+M10/L10-1 -> 0.23598961 | N12: =+N10/M10-1 -> 0.21240922 | ... AB12: =+AB10/AA10-1 -> 0.049946809
A13: Tax_expense | B13: Less tax | C13: A$m | F13: =VLOOKUP($A13,'Financial Statements'!$1:$1048576,MATCH('Valuation - DCF'!F$7,'Financial Statements'!$5:$5,0),FALSE) -> #N/A | G13: =VLOOKUP($A13,'Financial Statements'!$1:$1048576,MATCH('Valuation - DCF'!G$7,'Financial Statements'!$5:$5,0),FALSE) -> #N/A | H13: =VLOOKUP($A13,'Financial Statements'!$1:$1048576,MATCH('Valuation - DCF'!H$7,'Financial Statements'!$5:$5,0),FALSE) -> -17.447821 | I13: =VLOOKUP($A13,'Financial Statements'!$1:$1048576,MATCH('Valuation - DCF'!I$7,'Financial Statements'!$5:$5,0),FALSE) -> -24.023059 | J13: =VLOOKUP($A13,'Financial Statements'!$1:$1048576,MATCH('Valuation - DCF'!J$7,'Financial Statements'!$5:$5,0),FALSE) -> -32.20864 | K13: =VLOOKUP($A13,'Financial Statements'!$1:$1048576,MATCH('Valuation - DCF'!K$7,'Financial Statements'!$5:$5,0),FALSE) -> -44.088743 | L13: =-$D$52*L$10 -> -56.944705 | M13: =-$D$52*M$10 -> -70.383064 | N13: =-$D$52*N$10 -> -85.333076 | O13: =-$D$52*O$10 -> -101.92819 | P13: =-$D$52*P$10 -> -116.0071 | Q13: =-$D$52*Q$10 -> -128.90907 | R13: =-$D$52*R$10 -> -142.21832 | S13: =-$D$52*S$10 -> -154.30585 | ... AB13: =-$D$52*AB$10 -> -279.70541
A14: AASB16_Net_int | B14: Less AASB16 Interest Expense | C14: A$m | F14: =VLOOKUP($A14,Assumptions!$1:$1048576,MATCH('Valuation - DCF'!F$7,Assumptions!$5:$5,0),FALSE) -> #N/A | G14: =VLOOKUP($A14,Assumptions!$1:$1048576,MATCH('Valuation - DCF'!G$7,Assumptions!$5:$5,0),FALSE) -> #N/A | H14: =VLOOKUP($A14,Assumptions!$1:$1048576,MATCH('Valuation - DCF'!H$7,Assumptions!$5:$5,0),FALSE) -> -9.4694211 | I14: =VLOOKUP($A14,Assumptions!$1:$1048576,MATCH('Valuation - DCF'!I$7,Assumptions!$5:$5,0),FALSE) -> -10.412249 | J14: =VLOOKUP($A14,Assumptions!$1:$1048576,MATCH('Valuation - DCF'!J$7,Assumptions!$5:$5,0),FALSE) -> -10.949545 | K14: =VLOOKUP($A14,Assumptions!$1:$1048576,MATCH('Valuation - DCF'!K$7,Assumptions!$5:$5,0),FALSE) -> -11.173977 | L14: =(1+L9)*K14 -> -13.060314 | M14: =(1+M9)*L14 -> -15.002743 | N14: =(1+N9)*M14 -> -17.110054 | O14: =(1+O9)*N14 -> -19.393892 | P14: =(1+P9)*O14 -> -21.366044 | Q14: =(1+Q9)*P14 -> -23.317634 | R14: =(1+R9)*Q14 -> -25.356303 | S14: =(1+S9)*R14 -> -27.169995 | ... AB14: =(1+AB9)*AA14 -> -44.802324
A15: Total_D&A_ExAASB16 | B15: Add D&A ex ROA | C15: A$m | F15: =-VLOOKUP($A15,Assumptions!$1:$1048576,MATCH('Valuation - DCF'!F$7,Assumptions!$5:$5,0),FALSE) -> #N/A | G15: =-VLOOKUP($A15,Assumptions!$1:$1048576,MATCH('Valuation - DCF'!G$7,Assumptions!$5:$5,0),FALSE) -> #N/A | H15: =-VLOOKUP($A15,Assumptions!$1:$1048576,MATCH('Valuation - DCF'!H$7,Assumptions!$5:$5,0),FALSE) -> 32.070903 | I15: =-VLOOKUP($A15,Assumptions!$1:$1048576,MATCH('Valuation - DCF'!I$7,Assumptions!$5:$5,0),FALSE) -> 38.230207 | J15: =-VLOOKUP($A15,Assumptions!$1:$1048576,MATCH('Valuation - DCF'!J$7,Assumptions!$5:$5,0),FALSE) -> 44.958022 | K15: =-VLOOKUP($A15,Assumptions!$1:$1048576,MATCH('Valuation - DCF'!K$7,Assumptions!$5:$5,0),FALSE) -> 52.009245 | L15: =-VLOOKUP($A15,Assumptions!$1:$1048576,MATCH('Valuation - DCF'!L$7,Assumptions!$5:$5,0),FALSE) -> 59.13377 | M15: =-VLOOKUP($A15,Assumptions!$1:$1048576,MATCH('Valuation - DCF'!M$7,Assumptions!$5:$5,0),FALSE) -> 66.181729 | ... R15: =-VLOOKUP($A15,Assumptions!$1:$1048576,MATCH('Valuation - DCF'!R$7,Assumptions!$5:$5,0),FALSE) -> 99.264457 | S15: =+R15*(1+S9) -> 106.36467 | T15: =+S15*(1+T9) -> 113.79662 | U15: =+T15*(1+U9) -> 121.57389 | V15: =+U15*(1+V9) -> 128.81265 | W15: =+V15*(1+W9) -> 136.37324 | X15: =+W15*(1+X9) -> 144.26843 | Y15: =+X15*(1+Y9) -> 151.53275 | Z15: =+Y15*(1+Z9) -> 159.10132 | ... AB15: =+AA15*(1+AB9) -> 175.39144
A16: Working_Cap_Chg | B16: Change in Working Capital | C16: A$m | F16: =-VLOOKUP($A16,Assumptions!$1:$1048576,MATCH('Valuation - DCF'!F$7,Assumptions!$5:$5,0),FALSE) -> #N/A | G16: =-VLOOKUP($A16,Assumptions!$1:$1048576,MATCH('Valuation - DCF'!G$7,Assumptions!$5:$5,0),FALSE) -> #N/A | H16: =-VLOOKUP($A16,Assumptions!$1:$1048576,MATCH('Valuation - DCF'!H$7,Assumptions!$5:$5,0),FALSE) -> -6.7829699 | I16: =-VLOOKUP($A16,Assumptions!$1:$1048576,MATCH('Valuation - DCF'!I$7,Assumptions!$5:$5,0),FALSE) -> -4.1105691 | J16: =-VLOOKUP($A16,Assumptions!$1:$1048576,MATCH('Valuation - DCF'!J$7,Assumptions!$5:$5,0),FALSE) -> -4.9549784 | K16: =-VLOOKUP($A16,Assumptions!$1:$1048576,MATCH('Valuation - DCF'!K$7,Assumptions!$5:$5,0),FALSE) -> -4.0382633 | L16: =-VLOOKUP($A16,Assumptions!$1:$1048576,MATCH('Valuation - DCF'!L$7,Assumptions!$5:$5,0),FALSE) -> -4.167663 | M16: =-VLOOKUP($A16,Assumptions!$1:$1048576,MATCH('Valuation - DCF'!M$7,Assumptions!$5:$5,0),FALSE) -> -4.8896764 | ... R16: =-VLOOKUP($A16,Assumptions!$1:$1048576,MATCH('Valuation - DCF'!R$7,Assumptions!$5:$5,0),FALSE) -> -5.2510531 | S16: =S17*S8 -> -5.6266517 | T16: =T17*T8 -> -6.0197994 | U16: =U17*U8 -> -6.4312139 | V16: =V17*V8 -> -6.8141418 | W16: =W17*W8 -> -7.2140938 | X16: =X17*X8 -> -7.6317466 | Y16: =Y17*Y8 -> -8.0160263 | Z16: =Z17*Z8 -> -8.4164012 | ... AB16: =AB17*AB8 -> -9.2781422
B17: Working Capital/Sales | C17: A$m | F17: =F16/F8 -> #N/A | G17: =G16/G8 -> #N/A | H17: =H16/H8 -> -0.011349289 | I17: =I16/I8 -> -0.0056692746 | J17: =J16/J8 -> -0.0056365155 | K17: =K16/K8 -> -0.0038458533 | L17: =L16/L8 -> -0.0033958212 | M17: =M16/M8 -> -0.0034682892 | ... R17: =R16/R8 -> -0.0022037703 | S17: =R17 -> -0.0022037703 | T17: =S17 -> -0.0022037703 | U17: =T17 -> -0.0022037703 | V17: =U17 -> -0.0022037703 | W17: =V17 -> -0.0022037703 | X17: =W17 -> -0.0022037703 | Y17: =X17 -> -0.0022037703 | Z17: =Y17 -> -0.0022037703 | ... AB17: =AA17 -> -0.0022037703
A18: Total_CapEx | B18: Less CapEx | C18: A$m | F18: =-VLOOKUP($A18,Assumptions!$1:$1048576,MATCH('Valuation - DCF'!F$7,Assumptions!$5:$5,0),FALSE) -> #N/A | G18: =-VLOOKUP($A18,Assumptions!$1:$1048576,MATCH('Valuation - DCF'!G$7,Assumptions!$5:$5,0),FALSE) -> #N/A | H18: =-VLOOKUP($A18,Assumptions!$1:$1048576,MATCH('Valuation - DCF'!H$7,Assumptions!$5:$5,0),FALSE) -> -60.406351 | I18: =-VLOOKUP($A18,Assumptions!$1:$1048576,MATCH('Valuation - DCF'!I$7,Assumptions!$5:$5,0),FALSE) -> -83.326036 | J18: =-VLOOKUP($A18,Assumptions!$1:$1048576,MATCH('Valuation - DCF'!J$7,Assumptions!$5:$5,0),FALSE) -> -79.072168 | K18: =-VLOOKUP($A18,Assumptions!$1:$1048576,MATCH('Valuation - DCF'!K$7,Assumptions!$5:$5,0),FALSE) -> -88.729858 | L18: =-VLOOKUP($A18,Assumptions!$1:$1048576,MATCH('Valuation - DCF'!L$7,Assumptions!$5:$5,0),FALSE) -> -94.026858 | M18: =-VLOOKUP($A18,Assumptions!$1:$1048576,MATCH('Valuation - DCF'!M$7,Assumptions!$5:$5,0),FALSE) -> -104.23413 | ... R18: =-VLOOKUP($A18,Assumptions!$1:$1048576,MATCH('Valuation - DCF'!R$7,Assumptions!$5:$5,0),FALSE) -> -153.05376 | S18: =-S19*S15 -> -159.547 | T18: =-T19*T15 -> -170.69494 | U18: =-U19*U15 -> -182.36084 | V18: =-V19*V15 -> -193.21898 | W18: =-W19*W15 -> -204.55985 | X18: =-X19*X15 -> -216.40264 | Y18: =-Y19*Y15 -> -227.29912 | Z18: =-Z19*Z15 -> -238.65198 | ... AB18: =-AB19*AB15 -> -263.08716
B19: CapEx/D&A | C19: A$m | F19: =-F18/F15 -> #N/A | G19: =-G18/G15 -> #N/A | H19: =-H18/H15 -> 1.8835251 | I19: =-I18/I15 -> 2.1795863 | J19: =-J18/J15 -> 1.7588 | K19: =-K18/K15 -> 1.7060401 | L19: =-L18/L15 -> 1.5900704 | M19: =-M18/M15 -> 1.5749684 | ... R19: =-R18/R15 -> 1.5418788 | S19: 1.5 | T19: =+S19 -> 1.5 | U19: =+T19 -> 1.5 | V19: =+U19 -> 1.5 | W19: =+V19 -> 1.5 | X19: =+W19 -> 1.5 | Y19: =+X19 -> 1.5 | Z19: =+Y19 -> 1.5 | AA19: =+Z19 -> 1.5 | AB19: =+AA19 -> 1.5
B20: CapEx/Sales | C20: A$m | F20: =-F18/F8 -> #N/A | G20: =-G18/G8 -> #N/A | H20: =-H18/H8 -> 0.10107212 | I20: =-I18/I8 -> 0.11492282 | J20: =-J18/J8 -> 0.089948222 | K20: =-K18/K8 -> 0.084502171 | L20: =-L18/L8 -> 0.076613297 | M20: =-M18/M8 -> 0.07393416 | ... AB20: =-AB18/AB8 -> 0.062489198
B22: Free cash flow | C22: A$m | F22: =F10+F13+F14+F15+F16+F18 -> #N/A | G22: =G10+G13+G14+G15+G16+G18 -> #N/A | H22: =H10+H13+H14+H15+H16+H18 -> -25.362064 | I22: =I10+I13+I14+I15+I16+I18 -> -16.413952 | J22: =J10+J13+J14+J15+J16+J18 -> 20.03078 | K22: =K10+K13+K14+K15+K16+K18 -> 49.639032 | L22: =L10+L13+L14+L15+L16+L18 -> 80.749914 | M22: =M10+M13+M14+M15+M16+M18 -> 106.28233 | ... AB22: =AB10+AB13+AB14+AB15+AB16+AB18 -> 510.86978
B23: % growth | C23: % | G23: =G22/F22-1 -> #N/A | H23: =H22/G22-1 -> #N/A | I23: =I22/H22-1 -> -0.35281481 | J23: =J22/I22-1 -> -2.2203508 | K23: =K22/J22-1 -> 1.4781378 | L23: =L22/K22-1 -> 0.62674233 | M23: =M22/L22-1 -> 0.31619122 | N23: =N22/M22-1 -> 0.27080064 | ... AB23: =AB22/AA22-1 -> 0.049946809
B26: Date | C26: 46254
B27: Year | C27: # | I27: 1 | J27: 2 | K27: 3 | L27: 4 | M27: 5 | N27: 6 | O27: 7 | P27: 8 | Q27: 9 | R27: 10 | S27: 11 | T27: 12 | U27: 13 | V27: 14 | W27: 15 | X27: 16 | Y27: 17 | Z27: 18 | AA27: 19 | AB27: 20
B28: Date at end of period | C28: Day | G28: 45838 | H28: 46203 | I28: 46568 | J28: 46934 | K28: 47299 | L28: 47664 | M28: 48029 | N28: 48395 | O28: 48760 | P28: 49125 | Q28: 49490 | R28: 49856 | S28: 50221 | T28: 50586 | U28: 50951 | V28: 51317 | W28: 51682 | X28: 52047 | Y28: 52412 | Z28: 52778 | AA28: 53143 | AB28: 53508
B29: Years between now & EOP | C29: # | G29: =IF(G$28>365,(G$28-$C$26)/365,0) -> -1.139726 | H29: =IF(H$28>365,(H$28-$C$26)/365,0) -> -0.13972603 | I29: =IF(I$28>365,(I$28-$C$26)/365,0) -> 0.86027397 | J29: =IF(J$28>365,(J$28-$C$26)/365,0) -> 1.8630137 | K29: =IF(K$28>365,(K$28-$C$26)/365,0) -> 2.8630137 | L29: =IF(L$28>365,(L$28-$C$26)/365,0) -> 3.8630137 | M29: =IF(M$28>365,(M$28-$C$26)/365,0) -> 4.8630137 | N29: =IF(N$28>365,(N$28-$C$26)/365,0) -> 5.8657534 | ... AB29: =IF(AB$28>365,(AB$28-$C$26)/365,0) -> 19.873973
B30: Discount factor | C30: # | G30: =IF(G29>0,(1/(1+$D$54)^G29),0) -> 0 | H30: =IF(H29>0,(1/(1+$D$54)^H29),0) -> 0 | I30: =IF(I29>0,(1/(1+$D$54)^I29),0) -> 0.92518709 | J30: =IF(J29>0,(1/(1+$D$54)^J29),0) -> 0.84501919 | K30: =IF(K29>0,(1/(1+$D$54)^K29),0) -> 0.77198903 | L30: =IF(L29>0,(1/(1+$D$54)^L29),0) -> 0.70527044 | M30: =IF(M29>0,(1/(1+$D$54)^M29),0) -> 0.64431796 | N30: =IF(N29>0,(1/(1+$D$54)^N29),0) -> 0.5884875 | ... AB30: =IF(AB29>0,(1/(1+$D$54)^AB29),0) -> 0.16589694
B31: Free cash flow | C31: A$m
B32: Discounted free cash flow | C32: A$m | H32: =H30*H22 -> 0 | I32: =I30*I22 -> -15.185976 | J32: =J30*J22 -> 16.926393 | K32: =K30*K22 -> 38.320788 | L32: =L30*L22 -> 56.950528 | M32: =M30*M22 -> 68.479613 | N32: =N30*N22 -> 79.483271 | O32: =O30*O22 -> 89.777058 | ... AB32: =AB30*AB22 -> 84.751735
B36: Total discounted free cash flow | C36: A$m | D36: =SUM(I32:AB32) -> 1590.0512
