Workbook

Sheet Value
B2: Valuation | C2: AFG.AX
I3: DDM | J3: Units
C4: Current Price = | D4: 2.35 | I4: Risk Free Rate | J4: % | K4: 0.04 | M4: 0.04
C5: Shares Outstanding = | D5: #VALUE! | I5: Beta | J5: x | K5: 1.2
C6: AS51 Index | I6: Market Premium | J6: % | K6: 0.06
C7: TARGET Relative Forward PE | I7: Ke | J7: % | K7: =K4+K5*K6 -> 0.112
C8: TARGET Forward PE | I8: ROE | J8: % p.a. | K8: 0.2
C9: PE Price Target = | E9: #VALUE! | I9: LT Payout Ratio | J9: % p.a. | K9: 0.7
I10: LT growth rate | J10: % p.a. | K10: =(1-K9)*K8 -> 0.06
J11: Dividend Discount Model | K11: =Annual!D308 -> 4.1462997 | L11: =K11/D4-1 -> 0.76438285 | N11: 4.1559
J12: SOTP | N12: =N11-K11 -> 0.0096002524
N13: =N12*E27 -> 2.5997483
B14: Notes | C14: Units | I14: Implied 12M PE Ratio | J14: x
B15: Actual Values | C15: 1000 | D15: (hard coded) | I15: Implied12M EV/EBITDA Ratio | J15: x
B16: Formula | C16: 1000 | I16: EV- market
B17: Manual entry (assumption) | C17: 1000 | D17: (usually from guidance given by management) | I17: ND/EV
C19: Actual ---> | E19: Forecast ----->
C20: 2024 | D20: 2025 | E20: 2026 | F20: 2027 | G20: 2028 | J20: Actual ---> | L20: Forecast -----> | Q20: Actual ---> | S20: Forecast ----->
B21: PE | J21: 2024 | K21: 2025 | L21: 2026 | M21: 2027 | N21: 2028 | Q21: 2024 | R21: 2025 | S21: 2026 | T21: 2027 | U21: 2028
B22: Consensus | D22: =$D$4/D28 -> 18.182286 | E22: =$D$4/E28 -> 14.110421 | F22: =$D$4/F28 -> 12.226321 | G22: =$D$4/G28 -> 11.048264 | I22: NPAT(AUDm) | P22: EBITDA (AUDm)
B23: Blackwattle | D23: =$D$4/D29 -> 18.518 | E23: =$D$4/E29 -> 13.262767 | F23: =$D$4/F29 -> 11.518222 | G23: =$D$4/G29 -> 10.187802 | I23: Consensus | K23: ='Vs cons'!E12 -> 35 | L23: ='Vs cons'!F12 -> 45.1 | M23: ='Vs cons'!G12 -> 52.05 | N23: ='Vs cons'!H12 -> 57.6 | P23: Consensus | R23: ='Vs cons'!E24 -> 55.25 | S23: ='Vs cons'!F24 -> 73.1 | T23: ='Vs cons'!G24 -> 83.7 | U23: ='Vs cons'!H24 -> 91.65
B24: Difference | E24: =E23/E22 -> 0.93992708 | H24: =Annual!A90 -> Statutory NPAT | I24: Blackwattle | J24: =INDEX(Annual!$A:$Y,MATCH(Value!$H24,Annual!$A:$A,0),MATCH(Value!J$21,Annual!$A$1:$Y$1,0)) -> 29 | K24: =INDEX(Annual!$A:$Y,MATCH(Value!$H24,Annual!$A:$A,0),MATCH(Value!K$21,Annual!$A$1:$Y$1,0)) -> 35 | L24: =INDEX(Annual!$A:$Y,MATCH(Value!$H24,Annual!$A:$A,0),MATCH(Value!L$21,Annual!$A$1:$Y$1,0)) -> 48.868385 | M24: =INDEX(Annual!$A:$Y,MATCH(Value!$H24,Annual!$A:$A,0),MATCH(Value!M$21,Annual!$A$1:$Y$1,0)) -> 56.269968 | N24: =INDEX(Annual!$A:$Y,MATCH(Value!$H24,Annual!$A:$A,0),MATCH(Value!N$21,Annual!$A$1:$Y$1,0)) -> 63.618239 | O24: EBITDA-Underlying EBITDA | P24: Blackwattle | Q24: =INDEX(Annual!$A:$Y,MATCH($O24,Annual!$A:$A,0),MATCH(Value!Q$21,Annual!$A$1:$Y$1,0)) -> 47.4 | R24: =INDEX(Annual!$A:$Y,MATCH($O24,Annual!$A:$A,0),MATCH(Value!R$21,Annual!$A$1:$Y$1,0)) -> 56.2 | S24: =INDEX(Annual!$A:$Y,MATCH($O24,Annual!$A:$A,0),MATCH(Value!S$21,Annual!$A$1:$Y$1,0)) -> 80.14594 | T24: =INDEX(Annual!$A:$Y,MATCH($O24,Annual!$A:$A,0),MATCH(Value!T$21,Annual!$A$1:$Y$1,0)) -> 93.116027 | U24: =INDEX(Annual!$A:$Y,MATCH($O24,Annual!$A:$A,0),MATCH(Value!U$21,Annual!$A$1:$Y$1,0)) -> 106.2139
I25: Difference | K25: =K24/K23-1 -> 0 | L25: =L24/L23-1 -> 0.083556201 | M25: =M24/M23-1 -> 0.081075265 | N25: =N24/N23-1 -> 0.10448331 | P25: Difference | R25: =R24/R23-1 -> 0.01719457 | S25: =S24/S23-1 -> 0.096387688 | T25: =T24/T23-1 -> 0.11249733 | U25: =U24/U23-1 -> 0.15890781
B26: EPS (Acps) | R26: =R23-R28 -> -64.75 | S26: =S23-S28 -> -63.3 | T26: =T23-T28 -> -67
A27: YE Basic Shares Outstanding | B27: Shares Outstanding | C27: =INDEX(Annual!$A:$Y,MATCH($A27,Annual!$A:$A,0),MATCH(C$20,Annual!$A$1:$Y$1,0)) -> 270.8 | D27: =INDEX(Annual!$A:$Y,MATCH($A27,Annual!$A:$A,0),MATCH(D$20,Annual!$A$1:$Y$1,0)) -> 270.8 | E27: =INDEX(Annual!$A:$Y,MATCH($A27,Annual!$A:$A,0),MATCH(E$20,Annual!$A$1:$Y$1,0)) -> 270.8 | F27: =INDEX(Annual!$A:$Y,MATCH($A27,Annual!$A:$A,0),MATCH(F$20,Annual!$A$1:$Y$1,0)) -> 270.8 | G27: =INDEX(Annual!$A:$Y,MATCH($A27,Annual!$A:$A,0),MATCH(G$20,Annual!$A$1:$Y$1,0)) -> 270.8 | I27: PBT (AUDm) | P27: GP (AUDm) | R27: =R24-R29 -> -63.8 | S27: =S24-S29 -> -65.287351 | T27: =T24-T29 -> -72.228102
B28: Consensus | D28: =K23/D27 -> 0.12924668 | E28: =L23/E27 -> 0.16654357 | F28: =M23/F27 -> 0.19220827 | G28: =N23/G27 -> 0.2127031 | I28: Consensus | P28: Consensus | R28: ='Vs cons'!E29 -> 120 | S28: ='Vs cons'!F29 -> 136.4 | T28: ='Vs cons'!G29 -> 150.7 | U28: ='Vs cons'!H29 -> 161.9
A29: EPS | B29: Blackwattle | C29: =INDEX(Annual!$A:$Y,MATCH($A29,Annual!$A:$A,0),MATCH(C$20,Annual!$A$1:$Y$1,0)) -> 0.1058008 | D29: =INDEX(Annual!$A:$Y,MATCH($A29,Annual!$A:$A,0),MATCH(D$20,Annual!$A$1:$Y$1,0)) -> 0.12690355 | E29: =INDEX(Annual!$A:$Y,MATCH($A29,Annual!$A:$A,0),MATCH(E$20,Annual!$A$1:$Y$1,0)) -> 0.17718776 | F29: =INDEX(Annual!$A:$Y,MATCH($A29,Annual!$A:$A,0),MATCH(F$20,Annual!$A$1:$Y$1,0)) -> 0.20402454 | G29: =INDEX(Annual!$A:$Y,MATCH($A29,Annual!$A:$A,0),MATCH(G$20,Annual!$A$1:$Y$1,0)) -> 0.23066802 | H29: PBT | I29: Blackwattle | J29: =INDEX(Annual!$A:$Y,MATCH(Value!$H29,Annual!$A:$A,0),MATCH(Value!J$21,Annual!$A$1:$Y$1,0)) -> 43.9 | K29: =INDEX(Annual!$A:$Y,MATCH(Value!$H29,Annual!$A:$A,0),MATCH(Value!K$21,Annual!$A$1:$Y$1,0)) -> 48.6 | L29: =INDEX(Annual!$A:$Y,MATCH(Value!$H29,Annual!$A:$A,0),MATCH(Value!L$21,Annual!$A$1:$Y$1,0)) -> 69.573249 | M29: =INDEX(Annual!$A:$Y,MATCH(Value!$H29,Annual!$A:$A,0),MATCH(Value!M$21,Annual!$A$1:$Y$1,0)) -> 80.11634 | N29: =INDEX(Annual!$A:$Y,MATCH(Value!$H29,Annual!$A:$A,0),MATCH(Value!N$21,Annual!$A$1:$Y$1,0)) -> 90.585207 | O29: =Annual!A19 -> GP-Gross Profit | P29: Blackwattle | Q29: =INDEX(Annual!$A:$Y,MATCH($O29,Annual!$A:$A,0),MATCH(Value!Q$21,Annual!$A$1:$Y$1,0)) -> 104.7 | R29: =INDEX(Annual!$A:$Y,MATCH($O29,Annual!$A:$A,0),MATCH(Value!R$21,Annual!$A$1:$Y$1,0)) -> 120 | S29: =INDEX(Annual!$A:$Y,MATCH($O29,Annual!$A:$A,0),MATCH(Value!S$21,Annual!$A$1:$Y$1,0)) -> 145.43329 | T29: =INDEX(Annual!$A:$Y,MATCH($O29,Annual!$A:$A,0),MATCH(Value!T$21,Annual!$A$1:$Y$1,0)) -> 165.34413 | U29: =INDEX(Annual!$A:$Y,MATCH($O29,Annual!$A:$A,0),MATCH(Value!U$21,Annual!$A$1:$Y$1,0)) -> 184.71041
B30: Difference | D30: =D29/D28-1 -> -0.018129079 | E30: =E29/E28-1 -> 0.063912325 | F30: =F29/F28-1 -> 0.061476366 | G30: =G29/G28-1 -> 0.084460046 | I30: Difference | P30: Difference | R30: =R29/R28-1 -> 0 | S30: =S29/S28-1 -> 0.066226476 | T30: =T29/T28-1 -> 0.097174044 | U30: =U29/U28-1 -> 0.14089199
B32: DPS (Acps) | I32: EBIT (AUDm) | P32: EV / EBITDA
B33: Consensus | I33: Consensus | K33: ='Vs cons'!E34 -> 44.75 | L33: ='Vs cons'!F34 -> 60.5 | M33: ='Vs cons'!G34 -> 71.1 | N33: ='Vs cons'!H34 -> 78.95 | P33: Consensus | Q33: =(INDEX(Annual!$A:$Y,MATCH($O34,Annual!$A:$A,0),MATCH(Value!Q$21,Annual!$A$1:$Y$1,0))+$D$4*C27)/Q23 -> #DIV/0! | R33: =(INDEX(Annual!$A:$Y,MATCH($O34,Annual!$A:$A,0),MATCH(Value!R$21,Annual!$A$1:$Y$1,0))+$D$4*D27)/R23 -> 11.300995 | S33: =(INDEX(Annual!$A:$Y,MATCH($O34,Annual!$A:$A,0),MATCH(Value!S$21,Annual!$A$1:$Y$1,0))+$D$4*E27)/S23 -> 8.611909 | T33: =(INDEX(Annual!$A:$Y,MATCH($O34,Annual!$A:$A,0),MATCH(Value!T$21,Annual!$A$1:$Y$1,0))+$D$4*F27)/T23 -> 7.7164297 | U33: =(INDEX(Annual!$A:$Y,MATCH($O34,Annual!$A:$A,0),MATCH(Value!U$21,Annual!$A$1:$Y$1,0))+$D$4*G27)/U23 -> 7.2280181
A34: Dividends | B34: Blackwattle | H34: EBIT | I34: Blackwattle | J34: =INDEX(Annual!$A:$Y,MATCH(Value!$H34,Annual!$A:$A,0),MATCH(Value!J$21,Annual!$A$1:$Y$1,0)) -> 40 | K34: =INDEX(Annual!$A:$Y,MATCH(Value!$H34,Annual!$A:$A,0),MATCH(Value!K$21,Annual!$A$1:$Y$1,0)) -> 45.7 | L34: =INDEX(Annual!$A:$Y,MATCH(Value!$H34,Annual!$A:$A,0),MATCH(Value!L$21,Annual!$A$1:$Y$1,0)) -> 65.879614 | M34: =INDEX(Annual!$A:$Y,MATCH(Value!$H34,Annual!$A:$A,0),MATCH(Value!M$21,Annual!$A$1:$Y$1,0)) -> 77.021133 | N34: =INDEX(Annual!$A:$Y,MATCH(Value!$H34,Annual!$A:$A,0),MATCH(Value!N$21,Annual!$A$1:$Y$1,0)) -> 88.406108 | O34: Net debt | P34: Blackwattle | Q34: =(INDEX(Annual!$A:$Y,MATCH($O34,Annual!$A:$A,0),MATCH(Value!Q$21,Annual!$A$1:$Y$1,0))+$D$4*C27)/Q24 -> 12.98903 | R34: =(INDEX(Annual!$A:$Y,MATCH($O34,Annual!$A:$A,0),MATCH(Value!R$21,Annual!$A$1:$Y$1,0))+$D$4*D27)/R24 -> 11.109964 | S34: =(INDEX(Annual!$A:$Y,MATCH($O34,Annual!$A:$A,0),MATCH(Value!S$21,Annual!$A$1:$Y$1,0))+$D$4*E27)/S24 -> 7.8548027 | T34: =(INDEX(Annual!$A:$Y,MATCH($O34,Annual!$A:$A,0),MATCH(Value!T$21,Annual!$A$1:$Y$1,0))+$D$4*F27)/T24 -> 6.9361332 | U34: =(INDEX(Annual!$A:$Y,MATCH($O34,Annual!$A:$A,0),MATCH(Value!U$21,Annual!$A$1:$Y$1,0))+$D$4*G27)/U24 -> 6.2369224
B35: Dividend Yield | I35: Difference | J35: =J34/J33-1 -> #DIV/0! | K35: =K34/K33-1 -> 0.02122905 | L35: =L34/L33-1 -> 0.088919247 | M35: =M34/M33-1 -> 0.083278946 | N35: =N34/N33-1 -> 0.11977337 | P35: Difference
B37: FY24 | C37: Consensus | D37: Blackwattle | E37: % Diff | F37: OLD | G37: % Diff
B38: EBITDA | C38: Please sign in | D38: 81 | E38: #VALUE! | G38: #DIV/0! | J38: PE | L38: EV/EBITDA | N38: EV/Sales | O38: EBITDA Growth | P38: EBITDA margin | Q38: Revenue Growth | R38: EBIT margin | S38: Rule of 40 | T38: Market Cap | U38: Dividend Yield | V38: Stock
B39: D&A | C39: #VALUE! | D39: 15 | E39: #VALUE! | G39: #DIV/0! | J39: FY1 | K39: FY2 | L39: FY1 | M39: FY2 | N39: NTM | O39: FY0-3 CAGR | P39: FY1 | Q39: 3yr CAGR | R39: FY3 | S39: FY3 | T39: AUDm | U39: NTM | V39: Code
B40: EBIT | C40: Please sign in | D40: 66 | E40: #VALUE! | G40: #DIV/0! | I40: #NAME? | J40: #NAME? | K40: #NAME? | L40: #NAME? | M40: #NAME? | N40: #NAME? | O40: #NAME? | P40: #VALUE! | Q40: #VALUE! | R40: #VALUE! | S40: #VALUE! | T40: #NAME? | U40: #NAME? | V40: AFG.AX
B41: Net Interest | C41: #VALUE! | D41: -2 | E41: #VALUE! | G41: #DIV/0!
B42: PBT | C42: Please sign in | D42: 69 | E42: #VALUE! | G42: #DIV/0! | I42: Global Cloud Services
B43: Tax | C43: #VALUE! | D43: 16 | E43: #VALUE! | G43: #DIV/0! | I43: #NAME? | J43: #NAME? | K43: #NAME? | L43: #NAME? | M43: #NAME? | N43: #NAME? | O43: #NAME? | P43: #VALUE! | Q43: #VALUE! | R43: #VALUE! | S43: #VALUE! | T43: #NAME? | U43: #NAME? | V43: PANW.O
B44: Tax Rate | C44: #VALUE! | D44: 0.24 | E44: #VALUE! | G44: #DIV/0! | I44: #NAME? | J44: #NAME? | K44: #NAME? | L44: #NAME? | M44: #NAME? | N44: #NAME? | O44: #NAME? | P44: #VALUE! | Q44: #VALUE! | R44: #VALUE! | S44: #VALUE! | T44: #NAME? | U44: #NAME? | V44: FTNT.O
B45: NPAT | C45: Please sign in | D45: 52 | E45: #VALUE! | G45: #DIV/0! | I45: #NAME? | J45: #NAME? | K45: #NAME? | L45: #NAME? | M45: #NAME? | N45: #NAME? | O45: #NAME? | P45: #VALUE! | Q45: #VALUE! | R45: #VALUE! | S45: #VALUE! | T45: #NAME? | U45: #NAME? | V45: CSCO.O
B47: FY25 | C47: Consensus | D47: Blackwattle | E47: % Diff | F47: OLD | G47: % Diff | I47: MEDIAN | J47: #NAME? | K47: #NAME? | L47: #NAME? | M47: #NAME? | N47: #NAME? | O47: #NAME? | P47: #VALUE! | Q47: #VALUE! | R47: #VALUE! | S47: #VALUE! | T47: #NAME? | U47: #NAME?
B48: EBITDA | C48: Please sign in | D48: 97 | E48: #VALUE! | G48: #DIV/0!
B49: D&A | C49: #VALUE! | D49: 17 | E49: #VALUE! | G49: #DIV/0! | I49: Aus Tech/SaaS
B50: EBIT | C50: Please sign in | D50: 80 | E50: #VALUE! | G50: #DIV/0! | I50: #NAME? | J50: #NAME? | K50: #NAME? | L50: #NAME? | M50: #NAME? | N50: #NAME? | O50: #NAME? | P50: #VALUE! | Q50: #VALUE! | R50: #VALUE! | S50: #VALUE! | T50: #NAME? | U50: #NAME? | V50: OCL.AX
B51: Net Interest | C51: #VALUE! | D51: #VALUE! | E51: #VALUE! | G51: #VALUE! | I51: #NAME? | J51: #NAME? | K51: #NAME? | L51: #NAME? | M51: #NAME? | N51: #NAME? | O51: #NAME? | P51: #VALUE! | Q51: #VALUE! | R51: #VALUE! | S51: #VALUE! | T51: #NAME? | U51: #NAME? | V51: MP1.AX
B52: PBT | C52: Please sign in | D52: #VALUE! | E52: #VALUE! | G52: #VALUE! | I52: #NAME? | J52: #NAME? | K52: #NAME? | L52: #NAME? | M52: #NAME? | N52: #NAME? | O52: #NAME? | P52: #VALUE! | Q52: #VALUE! | R52: #VALUE! | S52: #VALUE! | T52: #NAME? | U52: #NAME? | V52: TNE.AX
B53: Tax | C53: #VALUE! | D53: #VALUE! | E53: #VALUE! | G53: #VALUE! | I53: #NAME? | J53: #NAME? | K53: #NAME? | L53: #NAME? | M53: #NAME? | N53: #NAME? | O53: #NAME? | P53: #VALUE! | Q53: #VALUE! | R53: #VALUE! | S53: #VALUE! | T53: #NAME? | U53: #NAME? | V53: RDY.AX
B54: Tax Rate | C54: #VALUE! | D54: #VALUE! | E54: #VALUE! | G54: #VALUE! | I54: #NAME? | J54: #NAME? | K54: #NAME? | L54: #NAME? | M54: #NAME? | N54: #NAME? | O54: #NAME? | P54: #VALUE! | Q54: #VALUE! | R54: #VALUE! | S54: #VALUE! | T54: #NAME? | U54: #NAME? | V54: RUL.AX
B55: NPAT | C55: Please sign in | D55: #VALUE! | E55: #VALUE! | G55: #VALUE! | I55: #NAME? | J55: #NAME? | K55: #NAME? | L55: #NAME? | M55: #NAME? | N55: #NAME? | O55: #NAME? | P55: #VALUE! | Q55: #VALUE! | R55: #VALUE! | S55: #VALUE! | T55: #NAME? | U55: #NAME? | V55: WTC.AX
I56: #NAME? | J56: #NAME? | K56: #NAME? | L56: #NAME? | M56: #NAME? | N56: #NAME? | O56: #NAME? | P56: #VALUE! | Q56: #VALUE! | R56: #VALUE! | S56: #VALUE! | T56: #NAME? | U56: #NAME? | V56: XRO.AX
B57: FY26 | C57: Consensus | D57: Blackwattle | E57: % Diff | F57: OLD | G57: % Diff | I57: #NAME? | J57: #NAME? | K57: #NAME? | L57: #NAME? | M57: #NAME? | N57: #NAME? | O57: #NAME? | P57: #VALUE! | Q57: #VALUE! | R57: #VALUE! | S57: #VALUE! | T57: #NAME? | U57: #NAME? | V57: SDR.AX
B58: EBITDA | C58: Please sign in | D58: 116 | E58: #VALUE! | G58: #DIV/0! | I58: #NAME? | J58: #NAME? | K58: #NAME? | L58: #NAME? | M58: #NAME? | N58: #NAME? | O58: #NAME? | P58: #VALUE! | Q58: #VALUE! | R58: #VALUE! | S58: #VALUE! | T58: #NAME? | U58: #NAME? | V58: NXL.AX
B59: D&A | C59: #VALUE! | D59: 20 | E59: #VALUE! | G59: #DIV/0! | I59: #NAME? | J59: #NAME? | K59: #NAME? | L59: #NAME? | M59: #NAME? | N59: #NAME? | O59: #NAME? | P59: #VALUE! | Q59: #VALUE! | R59: #VALUE! | S59: #VALUE! | T59: #NAME? | U59: #NAME? | V59: HSN.AX
B60: EBIT | C60: Please sign in | D60: 97 | E60: #VALUE! | G60: #DIV/0! | I60: #NAME? | J60: #NAME? | K60: #NAME? | L60: #NAME? | M60: #NAME? | N60: #NAME? | O60: #NAME? | P60: #VALUE! | Q60: #VALUE! | R60: #VALUE! | S60: #VALUE! | T60: #NAME? | U60: #NAME? | V60: 360.AX
B61: Net Interest | C61: #VALUE! | D61: #VALUE! | E61: #VALUE! | G61: #VALUE! | I61: MEDIAN | J61: #NAME? | K61: #NAME? | L61: #NAME? | M61: #NAME? | N61: #NAME? | O61: #NAME? | P61: #VALUE! | Q61: #VALUE! | R61: #VALUE! | S61: #VALUE! | T61: #NAME?
B62: PBT | C62: Please sign in | D62: #VALUE! | E62: #VALUE! | G62: #VALUE!
B63: Tax | C63: #VALUE! | D63: #VALUE! | E63: #VALUE! | G63: #VALUE!
B64: Tax Rate | C64: #VALUE! | D64: #VALUE! | E64: #VALUE! | G64: #VALUE!
B65: NPAT | C65: Please sign in | D65: #VALUE! | E65: #VALUE! | G65: #VALUE!

Sheet Annual
B1: AFG Model Summary | D1: 2015 | E1: 2016 | F1: 2017 | G1: 2018 | H1: 2019 | I1: 2020 | J1: 2021 | K1: 2022 | L1: 2023 | M1: 2024 | N1: 2025 | O1: 2026 | P1: 2027 | Q1: 2028 | R1: 2029 | S1: 2030 | T1: 2031 | U1: 2032 | V1: 2033 | W1: 2034 | X1: 2035 | Z1: Earnings changes=> | AA1: 2025 | AC1: 2026 | AE1: 2027
E2: Actual ----------> | O2: Forecast -----> | AA2: Forecast -----> | AB2: Forecast -----> | AD2: Forecast -----> | AF2: Forecast ----->
C3: Units | D3: Source | E3: FY16A | F3: FY17A | G3: FY18A | H3: FY19A | I3: FY20A | J3: FY21A | K3: FY22A | L3: FY23A | M3: FY24A | N3: FY25A | O3: FY26E | P3: FY27E | Q3: FY28E | R3: FY29E | S3: FY30E | T3: FY31E | U3: FY32E | V3: FY33E | W3: FY34E | X3: FY35E | AA3: FY25E | AB3: FY24E | AC3: FY26E | AD3: FY24E | AE3: FY27E | AF3: FY24E
B4: P &L | D4: =DATE(D1,6,30) -> 42185 | E4: =DATE(E1,6,30) -> 42551 | F4: =DATE(F1,6,30) -> 42916 | G4: =DATE(G1,6,30) -> 43281 | H4: =DATE(H1,6,30) -> 43646 | I4: =DATE(I1,6,30) -> 44012 | J4: =DATE(J1,6,30) -> 44377 | K4: =DATE(K1,6,30) -> 44742 | ... X4: =DATE(X1,6,30) -> 49490
B6: Revenue | Q6: =Q9/Q7 -> 0.1056794 | R6: =R9/R7 -> 0.15990013 | S6: =S9/S7 -> 0.21711165 | T6: =T9/T7 -> 0.27829394 | U6: =U9/U7 -> 0.34259988 | V6: =V9/V7 -> 0.41024248 | W6: =W9/W7 -> 0.48144627 | X6: =X9/X7 -> 0.55644814
A7: Rev-Commission revenue and other income | B7: Commission revenue and other income | C7: AUDm | F7: 527 | G7: 551.1 | H7: 569.7 | I7: 589.3 | J7: 656.8 | K7: 820.1 | L7: 742.8 | M7: 799.2 | N7: 911.3 | O7: =INDEX(Segments!$A:$AJ,MATCH(Annual!$A7,Segments!$A:$A,0),MATCH("1H"&RIGHT(Annual!O$1,2),Segments!$A$3:$AJ$3,0))+INDEX(Segments!$A:$AJ,MATCH(Annual!$A7,Segments!$A:$A,0),MATCH("2H"&RIGHT(Annual!O$1,2),Segments!$A$3:$AJ$3,0)) -> 1066.3765 | P7: =INDEX(Segments!$A:$AJ,MATCH(Annual!$A7,Segments!$A:$A,0),MATCH("1H"&RIGHT(Annual!P$1,2),Segments!$A$3:$AJ$3,0))+INDEX(Segments!$A:$AJ,MATCH(Annual!$A7,Segments!$A:$A,0),MATCH("2H"&RIGHT(Annual!P$1,2),Segments!$A$3:$AJ$3,0)) -> 1176.6975 | Q7: =INDEX(Segments!$A:$AJ,MATCH(Annual!$A7,Segments!$A:$A,0),MATCH("1H"&RIGHT(Annual!Q$1,2),Segments!$A$3:$AJ$3,0))+INDEX(Segments!$A:$AJ,MATCH(Annual!$A7,Segments!$A:$A,0),MATCH("2H"&RIGHT(Annual!Q$1,2),Segments!$A$3:$AJ$3,0)) -> 1257.0466 | R7: =INDEX(Segments!$A:$AJ,MATCH(Annual!$A7,Segments!$A:$A,0),MATCH("1H"&RIGHT(Annual!R$1,2),Segments!$A$3:$AJ$3,0))+INDEX(Segments!$A:$AJ,MATCH(Annual!$A7,Segments!$A:$A,0),MATCH("2H"&RIGHT(Annual!R$1,2),Segments!$A$3:$AJ$3,0)) -> 1341.2374 | S7: =INDEX(Segments!$A:$AJ,MATCH(Annual!$A7,Segments!$A:$A,0),MATCH("1H"&RIGHT(Annual!S$1,2),Segments!$A$3:$AJ$3,0))+INDEX(Segments!$A:$AJ,MATCH(Annual!$A7,Segments!$A:$A,0),MATCH("2H"&RIGHT(Annual!S$1,2),Segments!$A$3:$AJ$3,0)) -> 1431.7949 | T7: =INDEX(Segments!$A:$AJ,MATCH(Annual!$A7,Segments!$A:$A,0),MATCH("1H"&RIGHT(Annual!T$1,2),Segments!$A$3:$AJ$3,0))+INDEX(Segments!$A:$AJ,MATCH(Annual!$A7,Segments!$A:$A,0),MATCH("2H"&RIGHT(Annual!T$1,2),Segments!$A$3:$AJ$3,0)) -> 1517.7026 | U7: =INDEX(Segments!$A:$AJ,MATCH(Annual!$A7,Segments!$A:$A,0),MATCH("1H"&RIGHT(Annual!U$1,2),Segments!$A$3:$AJ$3,0))+INDEX(Segments!$A:$AJ,MATCH(Annual!$A7,Segments!$A:$A,0),MATCH("2H"&RIGHT(Annual!U$1,2),Segments!$A$3:$AJ$3,0)) -> 1608.7648 | V7: =INDEX(Segments!$A:$AJ,MATCH(Annual!$A7,Segments!$A:$A,0),MATCH("1H"&RIGHT(Annual!V$1,2),Segments!$A$3:$AJ$3,0))+INDEX(Segments!$A:$AJ,MATCH(Annual!$A7,Segments!$A:$A,0),MATCH("2H"&RIGHT(Annual!V$1,2),Segments!$A$3:$AJ$3,0)) -> 1705.2907 | ... X7: =INDEX(Segments!$A:$AJ,MATCH(Annual!$A7,Segments!$A:$A,0),MATCH("1H"&RIGHT(Annual!X$1,2),Segments!$A$3:$AJ$3,0))+INDEX(Segments!$A:$AJ,MATCH(Annual!$A7,Segments!$A:$A,0),MATCH("2H"&RIGHT(Annual!X$1,2),Segments!$A$3:$AJ$3,0)) -> 1916.0646 | AA7: 90.2 | AB7: 821.1 | AC7: 127.4 | AD7: 958.6 | AE7: 155.1 | AF7: 1043.2
A8: Rev-Securitisation interest income | B8: Securitisation interest income | C8: AUDm | F8: 46.3 | G8: 52.3 | H8: 73.1 | I8: 85.7 | J8: 90.2 | K8: 108.8 | L8: 260 | M8: 278.6 | N8: 324.2 | O8: =INDEX(Segments!$A:$AJ,MATCH(Annual!$A8,Segments!$A:$A,0),MATCH("1H"&RIGHT(Annual!O$1,2),Segments!$A$3:$AJ$3,0))+INDEX(Segments!$A:$AJ,MATCH(Annual!$A8,Segments!$A:$A,0),MATCH("2H"&RIGHT(Annual!O$1,2),Segments!$A$3:$AJ$3,0)) -> 386.7516 | P8: =INDEX(Segments!$A:$AJ,MATCH(Annual!$A8,Segments!$A:$A,0),MATCH("1H"&RIGHT(Annual!P$1,2),Segments!$A$3:$AJ$3,0))+INDEX(Segments!$A:$AJ,MATCH(Annual!$A8,Segments!$A:$A,0),MATCH("2H"&RIGHT(Annual!P$1,2),Segments!$A$3:$AJ$3,0)) -> 425.42676 | Q8: =INDEX(Segments!$A:$AJ,MATCH(Annual!$A8,Segments!$A:$A,0),MATCH("1H"&RIGHT(Annual!Q$1,2),Segments!$A$3:$AJ$3,0))+INDEX(Segments!$A:$AJ,MATCH(Annual!$A8,Segments!$A:$A,0),MATCH("2H"&RIGHT(Annual!Q$1,2),Segments!$A$3:$AJ$3,0)) -> 450.95237 | R8: =INDEX(Segments!$A:$AJ,MATCH(Annual!$A8,Segments!$A:$A,0),MATCH("1H"&RIGHT(Annual!R$1,2),Segments!$A$3:$AJ$3,0))+INDEX(Segments!$A:$AJ,MATCH(Annual!$A8,Segments!$A:$A,0),MATCH("2H"&RIGHT(Annual!R$1,2),Segments!$A$3:$AJ$3,0)) -> 478.00951 | S8: =INDEX(Segments!$A:$AJ,MATCH(Annual!$A8,Segments!$A:$A,0),MATCH("1H"&RIGHT(Annual!S$1,2),Segments!$A$3:$AJ$3,0))+INDEX(Segments!$A:$AJ,MATCH(Annual!$A8,Segments!$A:$A,0),MATCH("2H"&RIGHT(Annual!S$1,2),Segments!$A$3:$AJ$3,0)) -> 506.69008 | T8: =INDEX(Segments!$A:$AJ,MATCH(Annual!$A8,Segments!$A:$A,0),MATCH("1H"&RIGHT(Annual!T$1,2),Segments!$A$3:$AJ$3,0))+INDEX(Segments!$A:$AJ,MATCH(Annual!$A8,Segments!$A:$A,0),MATCH("2H"&RIGHT(Annual!T$1,2),Segments!$A$3:$AJ$3,0)) -> 537.09148 | U8: =INDEX(Segments!$A:$AJ,MATCH(Annual!$A8,Segments!$A:$A,0),MATCH("1H"&RIGHT(Annual!U$1,2),Segments!$A$3:$AJ$3,0))+INDEX(Segments!$A:$AJ,MATCH(Annual!$A8,Segments!$A:$A,0),MATCH("2H"&RIGHT(Annual!U$1,2),Segments!$A$3:$AJ$3,0)) -> 569.31697 | V8: =INDEX(Segments!$A:$AJ,MATCH(Annual!$A8,Segments!$A:$A,0),MATCH("1H"&RIGHT(Annual!V$1,2),Segments!$A$3:$AJ$3,0))+INDEX(Segments!$A:$AJ,MATCH(Annual!$A8,Segments!$A:$A,0),MATCH("2H"&RIGHT(Annual!V$1,2),Segments!$A$3:$AJ$3,0)) -> 603.47599 | ... X8: =INDEX(Segments!$A:$AJ,MATCH(Annual!$A8,Segments!$A:$A,0),MATCH("1H"&RIGHT(Annual!X$1,2),Segments!$A$3:$AJ$3,0))+INDEX(Segments!$A:$AJ,MATCH(Annual!$A8,Segments!$A:$A,0),MATCH("2H"&RIGHT(Annual!X$1,2),Segments!$A$3:$AJ$3,0)) -> 678.06562 | AA8: 26.4 | AB8: 297.8 | AC8: 31.6 | AD8: 357.4 | AE8: 39.5 | AF8: 388.4
A9: Rev-Other | B9: Other | C9: AUDm | D9: AR | O9: =INDEX(Segments!$A:$AJ,MATCH(Annual!$A9,Segments!$A:$A,0),MATCH("1H"&RIGHT(Annual!O$1,2),Segments!$A$3:$AJ$3,0))+INDEX(Segments!$A:$AJ,MATCH(Annual!$A9,Segments!$A:$A,0),MATCH("2H"&RIGHT(Annual!O$1,2),Segments!$A$3:$AJ$3,0)) -> 21.623033 | P9: =INDEX(Segments!$A:$AJ,MATCH(Annual!$A9,Segments!$A:$A,0),MATCH("1H"&RIGHT(Annual!P$1,2),Segments!$A$3:$AJ$3,0))+INDEX(Segments!$A:$AJ,MATCH(Annual!$A9,Segments!$A:$A,0),MATCH("2H"&RIGHT(Annual!P$1,2),Segments!$A$3:$AJ$3,0)) -> 61.651305 | Q9: =INDEX(Segments!$A:$AJ,MATCH(Annual!$A9,Segments!$A:$A,0),MATCH("1H"&RIGHT(Annual!Q$1,2),Segments!$A$3:$AJ$3,0))+INDEX(Segments!$A:$AJ,MATCH(Annual!$A9,Segments!$A:$A,0),MATCH("2H"&RIGHT(Annual!Q$1,2),Segments!$A$3:$AJ$3,0)) -> 132.84393 | R9: =INDEX(Segments!$A:$AJ,MATCH(Annual!$A9,Segments!$A:$A,0),MATCH("1H"&RIGHT(Annual!R$1,2),Segments!$A$3:$AJ$3,0))+INDEX(Segments!$A:$AJ,MATCH(Annual!$A9,Segments!$A:$A,0),MATCH("2H"&RIGHT(Annual!R$1,2),Segments!$A$3:$AJ$3,0)) -> 214.46404 | S9: =INDEX(Segments!$A:$AJ,MATCH(Annual!$A9,Segments!$A:$A,0),MATCH("1H"&RIGHT(Annual!S$1,2),Segments!$A$3:$AJ$3,0))+INDEX(Segments!$A:$AJ,MATCH(Annual!$A9,Segments!$A:$A,0),MATCH("2H"&RIGHT(Annual!S$1,2),Segments!$A$3:$AJ$3,0)) -> 310.85937 | T9: =INDEX(Segments!$A:$AJ,MATCH(Annual!$A9,Segments!$A:$A,0),MATCH("1H"&RIGHT(Annual!T$1,2),Segments!$A$3:$AJ$3,0))+INDEX(Segments!$A:$AJ,MATCH(Annual!$A9,Segments!$A:$A,0),MATCH("2H"&RIGHT(Annual!T$1,2),Segments!$A$3:$AJ$3,0)) -> 422.36745 | U9: =INDEX(Segments!$A:$AJ,MATCH(Annual!$A9,Segments!$A:$A,0),MATCH("1H"&RIGHT(Annual!U$1,2),Segments!$A$3:$AJ$3,0))+INDEX(Segments!$A:$AJ,MATCH(Annual!$A9,Segments!$A:$A,0),MATCH("2H"&RIGHT(Annual!U$1,2),Segments!$A$3:$AJ$3,0)) -> 551.16262 | V9: =INDEX(Segments!$A:$AJ,MATCH(Annual!$A9,Segments!$A:$A,0),MATCH("1H"&RIGHT(Annual!V$1,2),Segments!$A$3:$AJ$3,0))+INDEX(Segments!$A:$AJ,MATCH(Annual!$A9,Segments!$A:$A,0),MATCH("2H"&RIGHT(Annual!V$1,2),Segments!$A$3:$AJ$3,0)) -> 699.58267 | ... X9: =INDEX(Segments!$A:$AJ,MATCH(Annual!$A9,Segments!$A:$A,0),MATCH("1H"&RIGHT(Annual!X$1,2),Segments!$A$3:$AJ$3,0))+INDEX(Segments!$A:$AJ,MATCH(Annual!$A9,Segments!$A:$A,0),MATCH("2H"&RIGHT(Annual!X$1,2),Segments!$A$3:$AJ$3,0)) -> 1066.1906 | AA9: 0.7 | AB9: -0.7 | AC9: 0.7 | AD9: 43.3 | AE9: 0.7 | AF9: 128.2
A10: Rev-Total Revenue | B10: Total Revenue | C10: AUDm | F10: =SUM(F7:F9) -> 573.3 | G10: =SUM(G7:G9) -> 603.4 | H10: =SUM(H7:H9) -> 642.8 | I10: =SUM(I7:I9) -> 675 | J10: =SUM(J7:J9) -> 747 | K10: =SUM(K7:K9) -> 928.9 | L10: =SUM(L7:L9) -> 1002.8 | M10: =SUM(M7:M9) -> 1077.8 | N10: =SUM(N7:N9) -> 1235.5 | O10: =INDEX(Segments!$A:$AJ,MATCH(Annual!$A10,Segments!$A:$A,0),MATCH("1H"&RIGHT(Annual!O$1,2),Segments!$A$3:$AJ$3,0))+INDEX(Segments!$A:$AJ,MATCH(Annual!$A10,Segments!$A:$A,0),MATCH("2H"&RIGHT(Annual!O$1,2),Segments!$A$3:$AJ$3,0)) -> 1474.7512 | P10: =INDEX(Segments!$A:$AJ,MATCH(Annual!$A10,Segments!$A:$A,0),MATCH("1H"&RIGHT(Annual!P$1,2),Segments!$A$3:$AJ$3,0))+INDEX(Segments!$A:$AJ,MATCH(Annual!$A10,Segments!$A:$A,0),MATCH("2H"&RIGHT(Annual!P$1,2),Segments!$A$3:$AJ$3,0)) -> 1663.7755 | Q10: =INDEX(Segments!$A:$AJ,MATCH(Annual!$A10,Segments!$A:$A,0),MATCH("1H"&RIGHT(Annual!Q$1,2),Segments!$A$3:$AJ$3,0))+INDEX(Segments!$A:$AJ,MATCH(Annual!$A10,Segments!$A:$A,0),MATCH("2H"&RIGHT(Annual!Q$1,2),Segments!$A$3:$AJ$3,0)) -> 1840.8429 | R10: =INDEX(Segments!$A:$AJ,MATCH(Annual!$A10,Segments!$A:$A,0),MATCH("1H"&RIGHT(Annual!R$1,2),Segments!$A$3:$AJ$3,0))+INDEX(Segments!$A:$AJ,MATCH(Annual!$A10,Segments!$A:$A,0),MATCH("2H"&RIGHT(Annual!R$1,2),Segments!$A$3:$AJ$3,0)) -> 2033.711 | S10: =INDEX(Segments!$A:$AJ,MATCH(Annual!$A10,Segments!$A:$A,0),MATCH("1H"&RIGHT(Annual!S$1,2),Segments!$A$3:$AJ$3,0))+INDEX(Segments!$A:$AJ,MATCH(Annual!$A10,Segments!$A:$A,0),MATCH("2H"&RIGHT(Annual!S$1,2),Segments!$A$3:$AJ$3,0)) -> 2249.3444 | T10: =INDEX(Segments!$A:$AJ,MATCH(Annual!$A10,Segments!$A:$A,0),MATCH("1H"&RIGHT(Annual!T$1,2),Segments!$A$3:$AJ$3,0))+INDEX(Segments!$A:$AJ,MATCH(Annual!$A10,Segments!$A:$A,0),MATCH("2H"&RIGHT(Annual!T$1,2),Segments!$A$3:$AJ$3,0)) -> 2477.1616 | U10: =INDEX(Segments!$A:$AJ,MATCH(Annual!$A10,Segments!$A:$A,0),MATCH("1H"&RIGHT(Annual!U$1,2),Segments!$A$3:$AJ$3,0))+INDEX(Segments!$A:$AJ,MATCH(Annual!$A10,Segments!$A:$A,0),MATCH("2H"&RIGHT(Annual!U$1,2),Segments!$A$3:$AJ$3,0)) -> 2729.2444 | V10: =INDEX(Segments!$A:$AJ,MATCH(Annual!$A10,Segments!$A:$A,0),MATCH("1H"&RIGHT(Annual!V$1,2),Segments!$A$3:$AJ$3,0))+INDEX(Segments!$A:$AJ,MATCH(Annual!$A10,Segments!$A:$A,0),MATCH("2H"&RIGHT(Annual!V$1,2),Segments!$A$3:$AJ$3,0)) -> 3008.3494 | ... X10: =INDEX(Segments!$A:$AJ,MATCH(Annual!$A10,Segments!$A:$A,0),MATCH("1H"&RIGHT(Annual!X$1,2),Segments!$A$3:$AJ$3,0))+INDEX(Segments!$A:$AJ,MATCH(Annual!$A10,Segments!$A:$A,0),MATCH("2H"&RIGHT(Annual!X$1,2),Segments!$A$3:$AJ$3,0)) -> 3660.3208 | AA10: 117.3 | AB10: 1118.2 | AC10: 159.7 | AD10: 1359.4 | AE10: 195.3 | AF10: 1559.9
B11: Growth | C11: % YoY | G11: =G10/F10-1 -> 0.052503053 | H11: =H10/G10-1 -> 0.065296652 | I11: =I10/H10-1 -> 0.050093342 | J11: =J10/I10-1 -> 0.10666667 | K11: =K10/J10-1 -> 0.24350736 | L11: =L10/K10-1 -> 0.079556465 | M11: =M10/L10-1 -> 0.074790586 | N11: =N10/M10-1 -> 0.14631657 | ... X11: =X10/W10-1 -> 0.10331752 | AA11: 0.15 | AB11: -0.01 | AC11: 0.36 | AD11: -0.13 | AE11: 0.22 | AF11: -0.07
B13: COGS
A14: DC-Commission and other cost of sales | B14: Commission and other cost of sales | C14: AUDm | D14: AR | F14: -474.6 | G14: -493.9 | H14: -514.1 | I14: -531.1 | J14: -598.1 | K14: -741 | L14: -679.1 | M14: -726.5 | N14: -832.6 | O14: =INDEX(Segments!$A:$AJ,MATCH(Annual!$A14,Segments!$A:$A,0),MATCH("1H"&RIGHT(Annual!O$1,2),Segments!$A$3:$AJ$3,0))+INDEX(Segments!$A:$AJ,MATCH(Annual!$A14,Segments!$A:$A,0),MATCH("2H"&RIGHT(Annual!O$1,2),Segments!$A$3:$AJ$3,0)) -> -960.57358 | P14: =INDEX(Segments!$A:$AJ,MATCH(Annual!$A14,Segments!$A:$A,0),MATCH("1H"&RIGHT(Annual!P$1,2),Segments!$A$3:$AJ$3,0))+INDEX(Segments!$A:$AJ,MATCH(Annual!$A14,Segments!$A:$A,0),MATCH("2H"&RIGHT(Annual!P$1,2),Segments!$A$3:$AJ$3,0)) -> -1059.9486 | Q14: =INDEX(Segments!$A:$AJ,MATCH(Annual!$A14,Segments!$A:$A,0),MATCH("1H"&RIGHT(Annual!Q$1,2),Segments!$A$3:$AJ$3,0))+INDEX(Segments!$A:$AJ,MATCH(Annual!$A14,Segments!$A:$A,0),MATCH("2H"&RIGHT(Annual!Q$1,2),Segments!$A$3:$AJ$3,0)) -> -1132.3253 | R14: =INDEX(Segments!$A:$AJ,MATCH(Annual!$A14,Segments!$A:$A,0),MATCH("1H"&RIGHT(Annual!R$1,2),Segments!$A$3:$AJ$3,0))+INDEX(Segments!$A:$AJ,MATCH(Annual!$A14,Segments!$A:$A,0),MATCH("2H"&RIGHT(Annual!R$1,2),Segments!$A$3:$AJ$3,0)) -> -1208.1626 | S14: =INDEX(Segments!$A:$AJ,MATCH(Annual!$A14,Segments!$A:$A,0),MATCH("1H"&RIGHT(Annual!S$1,2),Segments!$A$3:$AJ$3,0))+INDEX(Segments!$A:$AJ,MATCH(Annual!$A14,Segments!$A:$A,0),MATCH("2H"&RIGHT(Annual!S$1,2),Segments!$A$3:$AJ$3,0)) -> -1289.7347 | T14: =INDEX(Segments!$A:$AJ,MATCH(Annual!$A14,Segments!$A:$A,0),MATCH("1H"&RIGHT(Annual!T$1,2),Segments!$A$3:$AJ$3,0))+INDEX(Segments!$A:$AJ,MATCH(Annual!$A14,Segments!$A:$A,0),MATCH("2H"&RIGHT(Annual!T$1,2),Segments!$A$3:$AJ$3,0)) -> -1367.1188 | U14: =INDEX(Segments!$A:$AJ,MATCH(Annual!$A14,Segments!$A:$A,0),MATCH("1H"&RIGHT(Annual!U$1,2),Segments!$A$3:$AJ$3,0))+INDEX(Segments!$A:$AJ,MATCH(Annual!$A14,Segments!$A:$A,0),MATCH("2H"&RIGHT(Annual!U$1,2),Segments!$A$3:$AJ$3,0)) -> -1449.146 | V14: =INDEX(Segments!$A:$AJ,MATCH(Annual!$A14,Segments!$A:$A,0),MATCH("1H"&RIGHT(Annual!V$1,2),Segments!$A$3:$AJ$3,0))+INDEX(Segments!$A:$AJ,MATCH(Annual!$A14,Segments!$A:$A,0),MATCH("2H"&RIGHT(Annual!V$1,2),Segments!$A$3:$AJ$3,0)) -> -1536.0947 | ... X14: =INDEX(Segments!$A:$AJ,MATCH(Annual!$A14,Segments!$A:$A,0),MATCH("1H"&RIGHT(Annual!X$1,2),Segments!$A$3:$AJ$3,0))+INDEX(Segments!$A:$AJ,MATCH(Annual!$A14,Segments!$A:$A,0),MATCH("2H"&RIGHT(Annual!X$1,2),Segments!$A$3:$AJ$3,0)) -> -1725.956
A15: DC-Securitisation and interest expense | B15: Securitisation and interest expense | C15: AUDm | F15: -31.7 | G15: -36.9 | H15: -53.5 | I15: -53.3 | J15: -46.5 | K15: -57.7 | L15: -210.6 | M15: -246.6 | N15: -282.9 | O15: =INDEX(Segments!$A:$AJ,MATCH(Annual!$A15,Segments!$A:$A,0),MATCH("1H"&RIGHT(Annual!O$1,2),Segments!$A$3:$AJ$3,0))+INDEX(Segments!$A:$AJ,MATCH(Annual!$A15,Segments!$A:$A,0),MATCH("2H"&RIGHT(Annual!O$1,2),Segments!$A$3:$AJ$3,0)) -> -349.79161 | P15: =INDEX(Segments!$A:$AJ,MATCH(Annual!$A15,Segments!$A:$A,0),MATCH("1H"&RIGHT(Annual!P$1,2),Segments!$A$3:$AJ$3,0))+INDEX(Segments!$A:$AJ,MATCH(Annual!$A15,Segments!$A:$A,0),MATCH("2H"&RIGHT(Annual!P$1,2),Segments!$A$3:$AJ$3,0)) -> -384.37204 | Q15: =INDEX(Segments!$A:$AJ,MATCH(Annual!$A15,Segments!$A:$A,0),MATCH("1H"&RIGHT(Annual!Q$1,2),Segments!$A$3:$AJ$3,0))+INDEX(Segments!$A:$AJ,MATCH(Annual!$A15,Segments!$A:$A,0),MATCH("2H"&RIGHT(Annual!Q$1,2),Segments!$A$3:$AJ$3,0)) -> -407.06753 | R15: =INDEX(Segments!$A:$AJ,MATCH(Annual!$A15,Segments!$A:$A,0),MATCH("1H"&RIGHT(Annual!R$1,2),Segments!$A$3:$AJ$3,0))+INDEX(Segments!$A:$AJ,MATCH(Annual!$A15,Segments!$A:$A,0),MATCH("2H"&RIGHT(Annual!R$1,2),Segments!$A$3:$AJ$3,0)) -> -431.49158 | S15: =INDEX(Segments!$A:$AJ,MATCH(Annual!$A15,Segments!$A:$A,0),MATCH("1H"&RIGHT(Annual!S$1,2),Segments!$A$3:$AJ$3,0))+INDEX(Segments!$A:$AJ,MATCH(Annual!$A15,Segments!$A:$A,0),MATCH("2H"&RIGHT(Annual!S$1,2),Segments!$A$3:$AJ$3,0)) -> -457.38108 | T15: =INDEX(Segments!$A:$AJ,MATCH(Annual!$A15,Segments!$A:$A,0),MATCH("1H"&RIGHT(Annual!T$1,2),Segments!$A$3:$AJ$3,0))+INDEX(Segments!$A:$AJ,MATCH(Annual!$A15,Segments!$A:$A,0),MATCH("2H"&RIGHT(Annual!T$1,2),Segments!$A$3:$AJ$3,0)) -> -484.82394 | U15: =INDEX(Segments!$A:$AJ,MATCH(Annual!$A15,Segments!$A:$A,0),MATCH("1H"&RIGHT(Annual!U$1,2),Segments!$A$3:$AJ$3,0))+INDEX(Segments!$A:$AJ,MATCH(Annual!$A15,Segments!$A:$A,0),MATCH("2H"&RIGHT(Annual!U$1,2),Segments!$A$3:$AJ$3,0)) -> -513.91338 | V15: =INDEX(Segments!$A:$AJ,MATCH(Annual!$A15,Segments!$A:$A,0),MATCH("1H"&RIGHT(Annual!V$1,2),Segments!$A$3:$AJ$3,0))+INDEX(Segments!$A:$AJ,MATCH(Annual!$A15,Segments!$A:$A,0),MATCH("2H"&RIGHT(Annual!V$1,2),Segments!$A$3:$AJ$3,0)) -> -544.74818 | ... X15: =INDEX(Segments!$A:$AJ,MATCH(Annual!$A15,Segments!$A:$A,0),MATCH("1H"&RIGHT(Annual!X$1,2),Segments!$A$3:$AJ$3,0))+INDEX(Segments!$A:$AJ,MATCH(Annual!$A15,Segments!$A:$A,0),MATCH("2H"&RIGHT(Annual!X$1,2),Segments!$A$3:$AJ$3,0)) -> -612.07906
A16: DC-Other | B16: Other | C16: AUDm | O16: =INDEX(Segments!$A:$AJ,MATCH(Annual!$A16,Segments!$A:$A,0),MATCH("1H"&RIGHT(Annual!O$1,2),Segments!$A$3:$AJ$3,0))+INDEX(Segments!$A:$AJ,MATCH(Annual!$A16,Segments!$A:$A,0),MATCH("2H"&RIGHT(Annual!O$1,2),Segments!$A$3:$AJ$3,0)) -> -18.9527 | P16: =INDEX(Segments!$A:$AJ,MATCH(Annual!$A16,Segments!$A:$A,0),MATCH("1H"&RIGHT(Annual!P$1,2),Segments!$A$3:$AJ$3,0))+INDEX(Segments!$A:$AJ,MATCH(Annual!$A16,Segments!$A:$A,0),MATCH("2H"&RIGHT(Annual!P$1,2),Segments!$A$3:$AJ$3,0)) -> -54.110758 | Q16: =INDEX(Segments!$A:$AJ,MATCH(Annual!$A16,Segments!$A:$A,0),MATCH("1H"&RIGHT(Annual!Q$1,2),Segments!$A$3:$AJ$3,0))+INDEX(Segments!$A:$AJ,MATCH(Annual!$A16,Segments!$A:$A,0),MATCH("2H"&RIGHT(Annual!Q$1,2),Segments!$A$3:$AJ$3,0)) -> -116.73964 | R16: =INDEX(Segments!$A:$AJ,MATCH(Annual!$A16,Segments!$A:$A,0),MATCH("1H"&RIGHT(Annual!R$1,2),Segments!$A$3:$AJ$3,0))+INDEX(Segments!$A:$AJ,MATCH(Annual!$A16,Segments!$A:$A,0),MATCH("2H"&RIGHT(Annual!R$1,2),Segments!$A$3:$AJ$3,0)) -> -188.6191 | S16: =INDEX(Segments!$A:$AJ,MATCH(Annual!$A16,Segments!$A:$A,0),MATCH("1H"&RIGHT(Annual!S$1,2),Segments!$A$3:$AJ$3,0))+INDEX(Segments!$A:$AJ,MATCH(Annual!$A16,Segments!$A:$A,0),MATCH("2H"&RIGHT(Annual!S$1,2),Segments!$A$3:$AJ$3,0)) -> -273.59138 | T16: =INDEX(Segments!$A:$AJ,MATCH(Annual!$A16,Segments!$A:$A,0),MATCH("1H"&RIGHT(Annual!T$1,2),Segments!$A$3:$AJ$3,0))+INDEX(Segments!$A:$AJ,MATCH(Annual!$A16,Segments!$A:$A,0),MATCH("2H"&RIGHT(Annual!T$1,2),Segments!$A$3:$AJ$3,0)) -> -371.94953 | U16: =INDEX(Segments!$A:$AJ,MATCH(Annual!$A16,Segments!$A:$A,0),MATCH("1H"&RIGHT(Annual!U$1,2),Segments!$A$3:$AJ$3,0))+INDEX(Segments!$A:$AJ,MATCH(Annual!$A16,Segments!$A:$A,0),MATCH("2H"&RIGHT(Annual!U$1,2),Segments!$A$3:$AJ$3,0)) -> -485.63895 | V16: =INDEX(Segments!$A:$AJ,MATCH(Annual!$A16,Segments!$A:$A,0),MATCH("1H"&RIGHT(Annual!V$1,2),Segments!$A$3:$AJ$3,0))+INDEX(Segments!$A:$AJ,MATCH(Annual!$A16,Segments!$A:$A,0),MATCH("2H"&RIGHT(Annual!V$1,2),Segments!$A$3:$AJ$3,0)) -> -616.73956 | ... X16: =INDEX(Segments!$A:$AJ,MATCH(Annual!$A16,Segments!$A:$A,0),MATCH("1H"&RIGHT(Annual!X$1,2),Segments!$A$3:$AJ$3,0))+INDEX(Segments!$A:$AJ,MATCH(Annual!$A16,Segments!$A:$A,0),MATCH("2H"&RIGHT(Annual!X$1,2),Segments!$A$3:$AJ$3,0)) -> -940.86902
A17: DC-Total COGS | B17: Total COGS | C17: AUDm | F17: =SUM(F14:F16) -> -506.3 | G17: =SUM(G14:G16) -> -530.8 | H17: =SUM(H14:H16) -> -567.6 | I17: =SUM(I14:I16) -> -584.4 | J17: =SUM(J14:J16) -> -644.6 | K17: =SUM(K14:K16) -> -798.7 | L17: =SUM(L14:L16) -> -889.7 | M17: =SUM(M14:M16) -> -973.1 | N17: =SUM(N14:N16) -> -1115.5 | O17: =INDEX(Segments!$A:$AJ,MATCH(Annual!$A17,Segments!$A:$A,0),MATCH("1H"&RIGHT(Annual!O$1,2),Segments!$A$3:$AJ$3,0))+INDEX(Segments!$A:$AJ,MATCH(Annual!$A17,Segments!$A:$A,0),MATCH("2H"&RIGHT(Annual!O$1,2),Segments!$A$3:$AJ$3,0)) -> -1329.3179 | P17: =INDEX(Segments!$A:$AJ,MATCH(Annual!$A17,Segments!$A:$A,0),MATCH("1H"&RIGHT(Annual!P$1,2),Segments!$A$3:$AJ$3,0))+INDEX(Segments!$A:$AJ,MATCH(Annual!$A17,Segments!$A:$A,0),MATCH("2H"&RIGHT(Annual!P$1,2),Segments!$A$3:$AJ$3,0)) -> -1498.4314 | Q17: =INDEX(Segments!$A:$AJ,MATCH(Annual!$A17,Segments!$A:$A,0),MATCH("1H"&RIGHT(Annual!Q$1,2),Segments!$A$3:$AJ$3,0))+INDEX(Segments!$A:$AJ,MATCH(Annual!$A17,Segments!$A:$A,0),MATCH("2H"&RIGHT(Annual!Q$1,2),Segments!$A$3:$AJ$3,0)) -> -1656.1325 | R17: =INDEX(Segments!$A:$AJ,MATCH(Annual!$A17,Segments!$A:$A,0),MATCH("1H"&RIGHT(Annual!R$1,2),Segments!$A$3:$AJ$3,0))+INDEX(Segments!$A:$AJ,MATCH(Annual!$A17,Segments!$A:$A,0),MATCH("2H"&RIGHT(Annual!R$1,2),Segments!$A$3:$AJ$3,0)) -> -1828.2733 | S17: =INDEX(Segments!$A:$AJ,MATCH(Annual!$A17,Segments!$A:$A,0),MATCH("1H"&RIGHT(Annual!S$1,2),Segments!$A$3:$AJ$3,0))+INDEX(Segments!$A:$AJ,MATCH(Annual!$A17,Segments!$A:$A,0),MATCH("2H"&RIGHT(Annual!S$1,2),Segments!$A$3:$AJ$3,0)) -> -2020.7072 | T17: =INDEX(Segments!$A:$AJ,MATCH(Annual!$A17,Segments!$A:$A,0),MATCH("1H"&RIGHT(Annual!T$1,2),Segments!$A$3:$AJ$3,0))+INDEX(Segments!$A:$AJ,MATCH(Annual!$A17,Segments!$A:$A,0),MATCH("2H"&RIGHT(Annual!T$1,2),Segments!$A$3:$AJ$3,0)) -> -2223.8923 | U17: =INDEX(Segments!$A:$AJ,MATCH(Annual!$A17,Segments!$A:$A,0),MATCH("1H"&RIGHT(Annual!U$1,2),Segments!$A$3:$AJ$3,0))+INDEX(Segments!$A:$AJ,MATCH(Annual!$A17,Segments!$A:$A,0),MATCH("2H"&RIGHT(Annual!U$1,2),Segments!$A$3:$AJ$3,0)) -> -2448.6983 | V17: =INDEX(Segments!$A:$AJ,MATCH(Annual!$A17,Segments!$A:$A,0),MATCH("1H"&RIGHT(Annual!V$1,2),Segments!$A$3:$AJ$3,0))+INDEX(Segments!$A:$AJ,MATCH(Annual!$A17,Segments!$A:$A,0),MATCH("2H"&RIGHT(Annual!V$1,2),Segments!$A$3:$AJ$3,0)) -> -2697.5825 | ... X17: =INDEX(Segments!$A:$AJ,MATCH(Annual!$A17,Segments!$A:$A,0),MATCH("1H"&RIGHT(Annual!X$1,2),Segments!$A$3:$AJ$3,0))+INDEX(Segments!$A:$AJ,MATCH(Annual!$A17,Segments!$A:$A,0),MATCH("2H"&RIGHT(Annual!X$1,2),Segments!$A$3:$AJ$3,0)) -> -3278.9041 | AA17: -29.3 | AB17: -1086.2 | AC17: -39.9 | AD17: -1329 | AE17: -48.8 | AF17: -1529.9
A19: GP-Gross Profit | B19: Gross Profit | C19: AUDm | F19: =F10+F17 -> 67 | G19: =G10+G17 -> 72.6 | H19: =H10+H17 -> 75.2 | I19: =I10+I17 -> 90.6 | J19: =J10+J17 -> 102.4 | K19: =K10+K17 -> 130.2 | L19: =L10+L17 -> 113.1 | M19: =M10+M17 -> 104.7 | N19: =N10+N17 -> 120 | O19: =INDEX(Segments!$A:$AJ,MATCH(Annual!$A19,Segments!$A:$A,0),MATCH("1H"&RIGHT(Annual!O$1,2),Segments!$A$3:$AJ$3,0))+INDEX(Segments!$A:$AJ,MATCH(Annual!$A19,Segments!$A:$A,0),MATCH("2H"&RIGHT(Annual!O$1,2),Segments!$A$3:$AJ$3,0)) -> 145.43329 | P19: =INDEX(Segments!$A:$AJ,MATCH(Annual!$A19,Segments!$A:$A,0),MATCH("1H"&RIGHT(Annual!P$1,2),Segments!$A$3:$AJ$3,0))+INDEX(Segments!$A:$AJ,MATCH(Annual!$A19,Segments!$A:$A,0),MATCH("2H"&RIGHT(Annual!P$1,2),Segments!$A$3:$AJ$3,0)) -> 165.34413 | Q19: =INDEX(Segments!$A:$AJ,MATCH(Annual!$A19,Segments!$A:$A,0),MATCH("1H"&RIGHT(Annual!Q$1,2),Segments!$A$3:$AJ$3,0))+INDEX(Segments!$A:$AJ,MATCH(Annual!$A19,Segments!$A:$A,0),MATCH("2H"&RIGHT(Annual!Q$1,2),Segments!$A$3:$AJ$3,0)) -> 184.71041 | R19: =INDEX(Segments!$A:$AJ,MATCH(Annual!$A19,Segments!$A:$A,0),MATCH("1H"&RIGHT(Annual!R$1,2),Segments!$A$3:$AJ$3,0))+INDEX(Segments!$A:$AJ,MATCH(Annual!$A19,Segments!$A:$A,0),MATCH("2H"&RIGHT(Annual!R$1,2),Segments!$A$3:$AJ$3,0)) -> 205.43773 | S19: =INDEX(Segments!$A:$AJ,MATCH(Annual!$A19,Segments!$A:$A,0),MATCH("1H"&RIGHT(Annual!S$1,2),Segments!$A$3:$AJ$3,0))+INDEX(Segments!$A:$AJ,MATCH(Annual!$A19,Segments!$A:$A,0),MATCH("2H"&RIGHT(Annual!S$1,2),Segments!$A$3:$AJ$3,0)) -> 228.63719 | T19: =INDEX(Segments!$A:$AJ,MATCH(Annual!$A19,Segments!$A:$A,0),MATCH("1H"&RIGHT(Annual!T$1,2),Segments!$A$3:$AJ$3,0))+INDEX(Segments!$A:$AJ,MATCH(Annual!$A19,Segments!$A:$A,0),MATCH("2H"&RIGHT(Annual!T$1,2),Segments!$A$3:$AJ$3,0)) -> 253.26928 | U19: =INDEX(Segments!$A:$AJ,MATCH(Annual!$A19,Segments!$A:$A,0),MATCH("1H"&RIGHT(Annual!U$1,2),Segments!$A$3:$AJ$3,0))+INDEX(Segments!$A:$AJ,MATCH(Annual!$A19,Segments!$A:$A,0),MATCH("2H"&RIGHT(Annual!U$1,2),Segments!$A$3:$AJ$3,0)) -> 280.54611 | V19: =INDEX(Segments!$A:$AJ,MATCH(Annual!$A19,Segments!$A:$A,0),MATCH("1H"&RIGHT(Annual!V$1,2),Segments!$A$3:$AJ$3,0))+INDEX(Segments!$A:$AJ,MATCH(Annual!$A19,Segments!$A:$A,0),MATCH("2H"&RIGHT(Annual!V$1,2),Segments!$A$3:$AJ$3,0)) -> 310.7669 | ... X19: =INDEX(Segments!$A:$AJ,MATCH(Annual!$A19,Segments!$A:$A,0),MATCH("1H"&RIGHT(Annual!X$1,2),Segments!$A$3:$AJ$3,0))+INDEX(Segments!$A:$AJ,MATCH(Annual!$A19,Segments!$A:$A,0),MATCH("2H"&RIGHT(Annual!X$1,2),Segments!$A$3:$AJ$3,0)) -> 381.41673 | AA19: -29.3 | AB19: 149.3 | AC19: -39.9 | AD19: 190.1 | AE19: -48.8 | AF19: 225.2
A20: DC-Other income | B20: Other income | C20: AUDm | D20: AR | F20: 16.7 | G20: 13.4 | H20: 15.1 | I20: 14.5 | J20: 14.4 | K20: 20.4 | L20: 21.9 | M20: 17.3 | N20: 19.2 | O20: =INDEX(Segments!$A:$AJ,MATCH(Annual!$A20,Segments!$A:$A,0),MATCH("1H"&RIGHT(Annual!O$1,2),Segments!$A$3:$AJ$3,0))+INDEX(Segments!$A:$AJ,MATCH(Annual!$A20,Segments!$A:$A,0),MATCH("2H"&RIGHT(Annual!O$1,2),Segments!$A$3:$AJ$3,0)) -> 20.352 | P20: =INDEX(Segments!$A:$AJ,MATCH(Annual!$A20,Segments!$A:$A,0),MATCH("1H"&RIGHT(Annual!P$1,2),Segments!$A$3:$AJ$3,0))+INDEX(Segments!$A:$AJ,MATCH(Annual!$A20,Segments!$A:$A,0),MATCH("2H"&RIGHT(Annual!P$1,2),Segments!$A$3:$AJ$3,0)) -> 21.404718 | Q20: =INDEX(Segments!$A:$AJ,MATCH(Annual!$A20,Segments!$A:$A,0),MATCH("1H"&RIGHT(Annual!Q$1,2),Segments!$A$3:$AJ$3,0))+INDEX(Segments!$A:$AJ,MATCH(Annual!$A20,Segments!$A:$A,0),MATCH("2H"&RIGHT(Annual!Q$1,2),Segments!$A$3:$AJ$3,0)) -> 22.135438 | R20: =INDEX(Segments!$A:$AJ,MATCH(Annual!$A20,Segments!$A:$A,0),MATCH("1H"&RIGHT(Annual!R$1,2),Segments!$A$3:$AJ$3,0))+INDEX(Segments!$A:$AJ,MATCH(Annual!$A20,Segments!$A:$A,0),MATCH("2H"&RIGHT(Annual!R$1,2),Segments!$A$3:$AJ$3,0)) -> 22.876635 | S20: =INDEX(Segments!$A:$AJ,MATCH(Annual!$A20,Segments!$A:$A,0),MATCH("1H"&RIGHT(Annual!S$1,2),Segments!$A$3:$AJ$3,0))+INDEX(Segments!$A:$AJ,MATCH(Annual!$A20,Segments!$A:$A,0),MATCH("2H"&RIGHT(Annual!S$1,2),Segments!$A$3:$AJ$3,0)) -> 23.648855 | T20: =INDEX(Segments!$A:$AJ,MATCH(Annual!$A20,Segments!$A:$A,0),MATCH("1H"&RIGHT(Annual!T$1,2),Segments!$A$3:$AJ$3,0))+INDEX(Segments!$A:$AJ,MATCH(Annual!$A20,Segments!$A:$A,0),MATCH("2H"&RIGHT(Annual!T$1,2),Segments!$A$3:$AJ$3,0)) -> 24.35832 | U20: =INDEX(Segments!$A:$AJ,MATCH(Annual!$A20,Segments!$A:$A,0),MATCH("1H"&RIGHT(Annual!U$1,2),Segments!$A$3:$AJ$3,0))+INDEX(Segments!$A:$AJ,MATCH(Annual!$A20,Segments!$A:$A,0),MATCH("2H"&RIGHT(Annual!U$1,2),Segments!$A$3:$AJ$3,0)) -> 25.08907 | V20: =INDEX(Segments!$A:$AJ,MATCH(Annual!$A20,Segments!$A:$A,0),MATCH("1H"&RIGHT(Annual!V$1,2),Segments!$A$3:$AJ$3,0))+INDEX(Segments!$A:$AJ,MATCH(Annual!$A20,Segments!$A:$A,0),MATCH("2H"&RIGHT(Annual!V$1,2),Segments!$A$3:$AJ$3,0)) -> 25.841742 | ... X20: =INDEX(Segments!$A:$AJ,MATCH(Annual!$A20,Segments!$A:$A,0),MATCH("1H"&RIGHT(Annual!X$1,2),Segments!$A$3:$AJ$3,0))+INDEX(Segments!$A:$AJ,MATCH(Annual!$A20,Segments!$A:$A,0),MATCH("2H"&RIGHT(Annual!X$1,2),Segments!$A$3:$AJ$3,0)) -> 27.415504
A21: DC-Gross Profit inc Other income | B21: Gross Profit inc Other income | C21: AUDm | F21: =F19+F20 -> 83.7 | G21: =G19+G20 -> 86 | H21: =H19+H20 -> 90.3 | I21: =I19+I20 -> 105.1 | J21: =J19+J20 -> 116.8 | K21: =K19+K20 -> 150.6 | L21: =L19+L20 -> 135 | M21: =M19+M20 -> 122 | N21: =N19+N20 -> 139.2 | O21: =INDEX(Segments!$A:$AJ,MATCH(Annual!$A21,Segments!$A:$A,0),MATCH("1H"&RIGHT(Annual!O$1,2),Segments!$A$3:$AJ$3,0))+INDEX(Segments!$A:$AJ,MATCH(Annual!$A21,Segments!$A:$A,0),MATCH("2H"&RIGHT(Annual!O$1,2),Segments!$A$3:$AJ$3,0)) -> 165.78529 | P21: =INDEX(Segments!$A:$AJ,MATCH(Annual!$A21,Segments!$A:$A,0),MATCH("1H"&RIGHT(Annual!P$1,2),Segments!$A$3:$AJ$3,0))+INDEX(Segments!$A:$AJ,MATCH(Annual!$A21,Segments!$A:$A,0),MATCH("2H"&RIGHT(Annual!P$1,2),Segments!$A$3:$AJ$3,0)) -> 186.74885 | Q21: =INDEX(Segments!$A:$AJ,MATCH(Annual!$A21,Segments!$A:$A,0),MATCH("1H"&RIGHT(Annual!Q$1,2),Segments!$A$3:$AJ$3,0))+INDEX(Segments!$A:$AJ,MATCH(Annual!$A21,Segments!$A:$A,0),MATCH("2H"&RIGHT(Annual!Q$1,2),Segments!$A$3:$AJ$3,0)) -> 206.84585 | R21: =INDEX(Segments!$A:$AJ,MATCH(Annual!$A21,Segments!$A:$A,0),MATCH("1H"&RIGHT(Annual!R$1,2),Segments!$A$3:$AJ$3,0))+INDEX(Segments!$A:$AJ,MATCH(Annual!$A21,Segments!$A:$A,0),MATCH("2H"&RIGHT(Annual!R$1,2),Segments!$A$3:$AJ$3,0)) -> 228.31437 | S21: =INDEX(Segments!$A:$AJ,MATCH(Annual!$A21,Segments!$A:$A,0),MATCH("1H"&RIGHT(Annual!S$1,2),Segments!$A$3:$AJ$3,0))+INDEX(Segments!$A:$AJ,MATCH(Annual!$A21,Segments!$A:$A,0),MATCH("2H"&RIGHT(Annual!S$1,2),Segments!$A$3:$AJ$3,0)) -> 252.28604 | T21: =INDEX(Segments!$A:$AJ,MATCH(Annual!$A21,Segments!$A:$A,0),MATCH("1H"&RIGHT(Annual!T$1,2),Segments!$A$3:$AJ$3,0))+INDEX(Segments!$A:$AJ,MATCH(Annual!$A21,Segments!$A:$A,0),MATCH("2H"&RIGHT(Annual!T$1,2),Segments!$A$3:$AJ$3,0)) -> 277.6276 | U21: =INDEX(Segments!$A:$AJ,MATCH(Annual!$A21,Segments!$A:$A,0),MATCH("1H"&RIGHT(Annual!U$1,2),Segments!$A$3:$AJ$3,0))+INDEX(Segments!$A:$AJ,MATCH(Annual!$A21,Segments!$A:$A,0),MATCH("2H"&RIGHT(Annual!U$1,2),Segments!$A$3:$AJ$3,0)) -> 305.63518 | V21: =INDEX(Segments!$A:$AJ,MATCH(Annual!$A21,Segments!$A:$A,0),MATCH("1H"&RIGHT(Annual!V$1,2),Segments!$A$3:$AJ$3,0))+INDEX(Segments!$A:$AJ,MATCH(Annual!$A21,Segments!$A:$A,0),MATCH("2H"&RIGHT(Annual!V$1,2),Segments!$A$3:$AJ$3,0)) -> 336.60864 | ... X21: =INDEX(Segments!$A:$AJ,MATCH(Annual!$A21,Segments!$A:$A,0),MATCH("1H"&RIGHT(Annual!X$1,2),Segments!$A$3:$AJ$3,0))+INDEX(Segments!$A:$AJ,MATCH(Annual!$A21,Segments!$A:$A,0),MATCH("2H"&RIGHT(Annual!X$1,2),Segments!$A$3:$AJ$3,0)) -> 408.83223 | AA21: -29.3 | AB21: 168.5 | AC21: -39.9 | AD21: 212.9 | AE21: -48.8 | AF21: 250.5
A22: DC-Trail book adjustment | B22: Trail book adjustment | C22: AUDm | F22: =F29-F21 -> -19.9 | G22: =G29-G21 -> -7.5 | H22: =H29-H21 -> -6.3 | I22: =I29-I21 -> -2.6 | J22: =J29-J21 -> -2.4 | K22: =K29-K21 -> -8 | L22: =L29-L21 -> 9.2 | M22: =M29-M21 -> 5 | N22: =N29-N21 -> 3.6 | O22: =INDEX(Segments!$A:$AJ,MATCH(Annual!$A22,Segments!$A:$A,0),MATCH("1H"&RIGHT(Annual!O$1,2),Segments!$A$3:$AJ$3,0))+INDEX(Segments!$A:$AJ,MATCH(Annual!$A22,Segments!$A:$A,0),MATCH("2H"&RIGHT(Annual!O$1,2),Segments!$A$3:$AJ$3,0)) -> 4.1885885 | P22: =INDEX(Segments!$A:$AJ,MATCH(Annual!$A22,Segments!$A:$A,0),MATCH("1H"&RIGHT(Annual!P$1,2),Segments!$A$3:$AJ$3,0))+INDEX(Segments!$A:$AJ,MATCH(Annual!$A22,Segments!$A:$A,0),MATCH("2H"&RIGHT(Annual!P$1,2),Segments!$A$3:$AJ$3,0)) -> 4.6219517 | Q22: =INDEX(Segments!$A:$AJ,MATCH(Annual!$A22,Segments!$A:$A,0),MATCH("1H"&RIGHT(Annual!Q$1,2),Segments!$A$3:$AJ$3,0))+INDEX(Segments!$A:$AJ,MATCH(Annual!$A22,Segments!$A:$A,0),MATCH("2H"&RIGHT(Annual!Q$1,2),Segments!$A$3:$AJ$3,0)) -> 4.9376531 | R22: =INDEX(Segments!$A:$AJ,MATCH(Annual!$A22,Segments!$A:$A,0),MATCH("1H"&RIGHT(Annual!R$1,2),Segments!$A$3:$AJ$3,0))+INDEX(Segments!$A:$AJ,MATCH(Annual!$A22,Segments!$A:$A,0),MATCH("2H"&RIGHT(Annual!R$1,2),Segments!$A$3:$AJ$3,0)) -> 5.2684399 | S22: =INDEX(Segments!$A:$AJ,MATCH(Annual!$A22,Segments!$A:$A,0),MATCH("1H"&RIGHT(Annual!S$1,2),Segments!$A$3:$AJ$3,0))+INDEX(Segments!$A:$AJ,MATCH(Annual!$A22,Segments!$A:$A,0),MATCH("2H"&RIGHT(Annual!S$1,2),Segments!$A$3:$AJ$3,0)) -> 5.6242532 | T22: =INDEX(Segments!$A:$AJ,MATCH(Annual!$A22,Segments!$A:$A,0),MATCH("1H"&RIGHT(Annual!T$1,2),Segments!$A$3:$AJ$3,0))+INDEX(Segments!$A:$AJ,MATCH(Annual!$A22,Segments!$A:$A,0),MATCH("2H"&RIGHT(Annual!T$1,2),Segments!$A$3:$AJ$3,0)) -> 5.9617084 | U22: =INDEX(Segments!$A:$AJ,MATCH(Annual!$A22,Segments!$A:$A,0),MATCH("1H"&RIGHT(Annual!U$1,2),Segments!$A$3:$AJ$3,0))+INDEX(Segments!$A:$AJ,MATCH(Annual!$A22,Segments!$A:$A,0),MATCH("2H"&RIGHT(Annual!U$1,2),Segments!$A$3:$AJ$3,0)) -> 6.3194109 | V22: =INDEX(Segments!$A:$AJ,MATCH(Annual!$A22,Segments!$A:$A,0),MATCH("1H"&RIGHT(Annual!V$1,2),Segments!$A$3:$AJ$3,0))+INDEX(Segments!$A:$AJ,MATCH(Annual!$A22,Segments!$A:$A,0),MATCH("2H"&RIGHT(Annual!V$1,2),Segments!$A$3:$AJ$3,0)) -> 6.6985755 | ... X22: =INDEX(Segments!$A:$AJ,MATCH(Annual!$A22,Segments!$A:$A,0),MATCH("1H"&RIGHT(Annual!X$1,2),Segments!$A$3:$AJ$3,0))+INDEX(Segments!$A:$AJ,MATCH(Annual!$A22,Segments!$A:$A,0),MATCH("2H"&RIGHT(Annual!X$1,2),Segments!$A$3:$AJ$3,0)) -> 7.5265195
G23: =G20/F20-1 -> -0.19760479 | N23: =N19/M19-1 -> 0.14613181 | O23: =O19/N19-1 -> 0.21194409
B24: Gross Profit by segment | N24: =N25/N29 -> 0.79341737
A25: GP-Distribution | B25: Distribution | C25: AUDm | D25: Preso | J25: NR | K25: 101.8 | L25: 105.8 | M25: 104.4 | N25: 113.3 | O25: =INDEX(Segments!$A:$AJ,MATCH(Annual!$A25,Segments!$A:$A,0),MATCH("1H"&RIGHT(Annual!O$1,2),Segments!$A$3:$AJ$3,0))+INDEX(Segments!$A:$AJ,MATCH(Annual!$A25,Segments!$A:$A,0),MATCH("2H"&RIGHT(Annual!O$1,2),Segments!$A$3:$AJ$3,0)) -> 130.34356 | P25: =INDEX(Segments!$A:$AJ,MATCH(Annual!$A25,Segments!$A:$A,0),MATCH("1H"&RIGHT(Annual!P$1,2),Segments!$A$3:$AJ$3,0))+INDEX(Segments!$A:$AJ,MATCH(Annual!$A25,Segments!$A:$A,0),MATCH("2H"&RIGHT(Annual!P$1,2),Segments!$A$3:$AJ$3,0)) -> 142.77553 | Q25: =INDEX(Segments!$A:$AJ,MATCH(Annual!$A25,Segments!$A:$A,0),MATCH("1H"&RIGHT(Annual!Q$1,2),Segments!$A$3:$AJ$3,0))+INDEX(Segments!$A:$AJ,MATCH(Annual!$A25,Segments!$A:$A,0),MATCH("2H"&RIGHT(Annual!Q$1,2),Segments!$A$3:$AJ$3,0)) -> 151.79438 | R25: =INDEX(Segments!$A:$AJ,MATCH(Annual!$A25,Segments!$A:$A,0),MATCH("1H"&RIGHT(Annual!R$1,2),Segments!$A$3:$AJ$3,0))+INDEX(Segments!$A:$AJ,MATCH(Annual!$A25,Segments!$A:$A,0),MATCH("2H"&RIGHT(Annual!R$1,2),Segments!$A$3:$AJ$3,0)) -> 161.21994 | S25: =INDEX(Segments!$A:$AJ,MATCH(Annual!$A25,Segments!$A:$A,0),MATCH("1H"&RIGHT(Annual!S$1,2),Segments!$A$3:$AJ$3,0))+INDEX(Segments!$A:$AJ,MATCH(Annual!$A25,Segments!$A:$A,0),MATCH("2H"&RIGHT(Annual!S$1,2),Segments!$A$3:$AJ$3,0)) -> 171.33331 | T25: =INDEX(Segments!$A:$AJ,MATCH(Annual!$A25,Segments!$A:$A,0),MATCH("1H"&RIGHT(Annual!T$1,2),Segments!$A$3:$AJ$3,0))+INDEX(Segments!$A:$AJ,MATCH(Annual!$A25,Segments!$A:$A,0),MATCH("2H"&RIGHT(Annual!T$1,2),Segments!$A$3:$AJ$3,0)) -> 180.90384 | U25: =INDEX(Segments!$A:$AJ,MATCH(Annual!$A25,Segments!$A:$A,0),MATCH("1H"&RIGHT(Annual!U$1,2),Segments!$A$3:$AJ$3,0))+INDEX(Segments!$A:$AJ,MATCH(Annual!$A25,Segments!$A:$A,0),MATCH("2H"&RIGHT(Annual!U$1,2),Segments!$A$3:$AJ$3,0)) -> 191.02732 | V25: =INDEX(Segments!$A:$AJ,MATCH(Annual!$A25,Segments!$A:$A,0),MATCH("1H"&RIGHT(Annual!V$1,2),Segments!$A$3:$AJ$3,0))+INDEX(Segments!$A:$AJ,MATCH(Annual!$A25,Segments!$A:$A,0),MATCH("2H"&RIGHT(Annual!V$1,2),Segments!$A$3:$AJ$3,0)) -> 201.73629 | ... X25: =INDEX(Segments!$A:$AJ,MATCH(Annual!$A25,Segments!$A:$A,0),MATCH("1H"&RIGHT(Annual!X$1,2),Segments!$A$3:$AJ$3,0))+INDEX(Segments!$A:$AJ,MATCH(Annual!$A25,Segments!$A:$A,0),MATCH("2H"&RIGHT(Annual!X$1,2),Segments!$A$3:$AJ$3,0)) -> 225.05062 | AA25: -28.6 | AB25: 141.9 | AC25: 0 | AD25: 135 | AE25: 0 | AF25: 149
A26: GP-Manufacturing | B26: Manufacturing | C26: AUDm | J26: NR | K26: 40.8 | L26: 38.4 | M26: 22.6 | N26: 29.5 | O26: =INDEX(Segments!$A:$AJ,MATCH(Annual!$A26,Segments!$A:$A,0),MATCH("1H"&RIGHT(Annual!O$1,2),Segments!$A$3:$AJ$3,0))+INDEX(Segments!$A:$AJ,MATCH(Annual!$A26,Segments!$A:$A,0),MATCH("2H"&RIGHT(Annual!O$1,2),Segments!$A$3:$AJ$3,0)) -> 36.959988 | P26: =INDEX(Segments!$A:$AJ,MATCH(Annual!$A26,Segments!$A:$A,0),MATCH("1H"&RIGHT(Annual!P$1,2),Segments!$A$3:$AJ$3,0))+INDEX(Segments!$A:$AJ,MATCH(Annual!$A26,Segments!$A:$A,0),MATCH("2H"&RIGHT(Annual!P$1,2),Segments!$A$3:$AJ$3,0)) -> 41.054718 | Q26: =INDEX(Segments!$A:$AJ,MATCH(Annual!$A26,Segments!$A:$A,0),MATCH("1H"&RIGHT(Annual!Q$1,2),Segments!$A$3:$AJ$3,0))+INDEX(Segments!$A:$AJ,MATCH(Annual!$A26,Segments!$A:$A,0),MATCH("2H"&RIGHT(Annual!Q$1,2),Segments!$A$3:$AJ$3,0)) -> 43.884834 | R26: =INDEX(Segments!$A:$AJ,MATCH(Annual!$A26,Segments!$A:$A,0),MATCH("1H"&RIGHT(Annual!R$1,2),Segments!$A$3:$AJ$3,0))+INDEX(Segments!$A:$AJ,MATCH(Annual!$A26,Segments!$A:$A,0),MATCH("2H"&RIGHT(Annual!R$1,2),Segments!$A$3:$AJ$3,0)) -> 46.517924 | S26: =INDEX(Segments!$A:$AJ,MATCH(Annual!$A26,Segments!$A:$A,0),MATCH("1H"&RIGHT(Annual!S$1,2),Segments!$A$3:$AJ$3,0))+INDEX(Segments!$A:$AJ,MATCH(Annual!$A26,Segments!$A:$A,0),MATCH("2H"&RIGHT(Annual!S$1,2),Segments!$A$3:$AJ$3,0)) -> 49.308999 | T26: =INDEX(Segments!$A:$AJ,MATCH(Annual!$A26,Segments!$A:$A,0),MATCH("1H"&RIGHT(Annual!T$1,2),Segments!$A$3:$AJ$3,0))+INDEX(Segments!$A:$AJ,MATCH(Annual!$A26,Segments!$A:$A,0),MATCH("2H"&RIGHT(Annual!T$1,2),Segments!$A$3:$AJ$3,0)) -> 52.267539 | U26: =INDEX(Segments!$A:$AJ,MATCH(Annual!$A26,Segments!$A:$A,0),MATCH("1H"&RIGHT(Annual!U$1,2),Segments!$A$3:$AJ$3,0))+INDEX(Segments!$A:$AJ,MATCH(Annual!$A26,Segments!$A:$A,0),MATCH("2H"&RIGHT(Annual!U$1,2),Segments!$A$3:$AJ$3,0)) -> 55.403591 | V26: =INDEX(Segments!$A:$AJ,MATCH(Annual!$A26,Segments!$A:$A,0),MATCH("1H"&RIGHT(Annual!V$1,2),Segments!$A$3:$AJ$3,0))+INDEX(Segments!$A:$AJ,MATCH(Annual!$A26,Segments!$A:$A,0),MATCH("2H"&RIGHT(Annual!V$1,2),Segments!$A$3:$AJ$3,0)) -> 58.727807 | ... X26: =INDEX(Segments!$A:$AJ,MATCH(Annual!$A26,Segments!$A:$A,0),MATCH("1H"&RIGHT(Annual!X$1,2),Segments!$A$3:$AJ$3,0))+INDEX(Segments!$A:$AJ,MATCH(Annual!$A26,Segments!$A:$A,0),MATCH("2H"&RIGHT(Annual!X$1,2),Segments!$A$3:$AJ$3,0)) -> 65.986564 | AA26: -6.9 | AB26: 36.4 | AC26: 0 | AD26: 36.8 | AE26: 0 | AF26: 41.3
A27: GP-Central | B27: Central | C27: AUDm | O27: =INDEX(Segments!$A:$AJ,MATCH(Annual!$A27,Segments!$A:$A,0),MATCH("1H"&RIGHT(Annual!O$1,2),Segments!$A$3:$AJ$3,0))+INDEX(Segments!$A:$AJ,MATCH(Annual!$A27,Segments!$A:$A,0),MATCH("2H"&RIGHT(Annual!O$1,2),Segments!$A$3:$AJ$3,0)) -> 0 | P27: =INDEX(Segments!$A:$AJ,MATCH(Annual!$A27,Segments!$A:$A,0),MATCH("1H"&RIGHT(Annual!P$1,2),Segments!$A$3:$AJ$3,0))+INDEX(Segments!$A:$AJ,MATCH(Annual!$A27,Segments!$A:$A,0),MATCH("2H"&RIGHT(Annual!P$1,2),Segments!$A$3:$AJ$3,0)) -> 0 | Q27: =INDEX(Segments!$A:$AJ,MATCH(Annual!$A27,Segments!$A:$A,0),MATCH("1H"&RIGHT(Annual!Q$1,2),Segments!$A$3:$AJ$3,0))+INDEX(Segments!$A:$AJ,MATCH(Annual!$A27,Segments!$A:$A,0),MATCH("2H"&RIGHT(Annual!Q$1,2),Segments!$A$3:$AJ$3,0)) -> 0 | R27: =INDEX(Segments!$A:$AJ,MATCH(Annual!$A27,Segments!$A:$A,0),MATCH("1H"&RIGHT(Annual!R$1,2),Segments!$A$3:$AJ$3,0))+INDEX(Segments!$A:$AJ,MATCH(Annual!$A27,Segments!$A:$A,0),MATCH("2H"&RIGHT(Annual!R$1,2),Segments!$A$3:$AJ$3,0)) -> 0 | S27: =INDEX(Segments!$A:$AJ,MATCH(Annual!$A27,Segments!$A:$A,0),MATCH("1H"&RIGHT(Annual!S$1,2),Segments!$A$3:$AJ$3,0))+INDEX(Segments!$A:$AJ,MATCH(Annual!$A27,Segments!$A:$A,0),MATCH("2H"&RIGHT(Annual!S$1,2),Segments!$A$3:$AJ$3,0)) -> 0 | T27: =INDEX(Segments!$A:$AJ,MATCH(Annual!$A27,Segments!$A:$A,0),MATCH("1H"&RIGHT(Annual!T$1,2),Segments!$A$3:$AJ$3,0))+INDEX(Segments!$A:$AJ,MATCH(Annual!$A27,Segments!$A:$A,0),MATCH("2H"&RIGHT(Annual!T$1,2),Segments!$A$3:$AJ$3,0)) -> 0 | U27: =INDEX(Segments!$A:$AJ,MATCH(Annual!$A27,Segments!$A:$A,0),MATCH("1H"&RIGHT(Annual!U$1,2),Segments!$A$3:$AJ$3,0))+INDEX(Segments!$A:$AJ,MATCH(Annual!$A27,Segments!$A:$A,0),MATCH("2H"&RIGHT(Annual!U$1,2),Segments!$A$3:$AJ$3,0)) -> 0 | V27: =INDEX(Segments!$A:$AJ,MATCH(Annual!$A27,Segments!$A:$A,0),MATCH("1H"&RIGHT(Annual!V$1,2),Segments!$A$3:$AJ$3,0))+INDEX(Segments!$A:$AJ,MATCH(Annual!$A27,Segments!$A:$A,0),MATCH("2H"&RIGHT(Annual!V$1,2),Segments!$A$3:$AJ$3,0)) -> 0 | ... X27: =INDEX(Segments!$A:$AJ,MATCH(Annual!$A27,Segments!$A:$A,0),MATCH("1H"&RIGHT(Annual!X$1,2),Segments!$A$3:$AJ$3,0))+INDEX(Segments!$A:$AJ,MATCH(Annual!$A27,Segments!$A:$A,0),MATCH("2H"&RIGHT(Annual!X$1,2),Segments!$A$3:$AJ$3,0)) -> 0 | AA27: -6.9 | AB27: 6.9 | AC27: 0 | AD27: 0 | AE27: 0 | AF27: 0
A28: GP-Inorganic- forecast | B28: Inorganic- forecast | O28: =INDEX(Segments!$A:$AJ,MATCH(Annual!$A28,Segments!$A:$A,0),MATCH("1H"&RIGHT(Annual!O$1,2),Segments!$A$3:$AJ$3,0))+INDEX(Segments!$A:$AJ,MATCH(Annual!$A28,Segments!$A:$A,0),MATCH("2H"&RIGHT(Annual!O$1,2),Segments!$A$3:$AJ$3,0)) -> 2.6703328 | P28: =INDEX(Segments!$A:$AJ,MATCH(Annual!$A28,Segments!$A:$A,0),MATCH("1H"&RIGHT(Annual!P$1,2),Segments!$A$3:$AJ$3,0))+INDEX(Segments!$A:$AJ,MATCH(Annual!$A28,Segments!$A:$A,0),MATCH("2H"&RIGHT(Annual!P$1,2),Segments!$A$3:$AJ$3,0)) -> 7.5405477 | Q28: =INDEX(Segments!$A:$AJ,MATCH(Annual!$A28,Segments!$A:$A,0),MATCH("1H"&RIGHT(Annual!Q$1,2),Segments!$A$3:$AJ$3,0))+INDEX(Segments!$A:$AJ,MATCH(Annual!$A28,Segments!$A:$A,0),MATCH("2H"&RIGHT(Annual!Q$1,2),Segments!$A$3:$AJ$3,0)) -> 16.10429 | R28: =INDEX(Segments!$A:$AJ,MATCH(Annual!$A28,Segments!$A:$A,0),MATCH("1H"&RIGHT(Annual!R$1,2),Segments!$A$3:$AJ$3,0))+INDEX(Segments!$A:$AJ,MATCH(Annual!$A28,Segments!$A:$A,0),MATCH("2H"&RIGHT(Annual!R$1,2),Segments!$A$3:$AJ$3,0)) -> 25.844945 | S28: =INDEX(Segments!$A:$AJ,MATCH(Annual!$A28,Segments!$A:$A,0),MATCH("1H"&RIGHT(Annual!S$1,2),Segments!$A$3:$AJ$3,0))+INDEX(Segments!$A:$AJ,MATCH(Annual!$A28,Segments!$A:$A,0),MATCH("2H"&RIGHT(Annual!S$1,2),Segments!$A$3:$AJ$3,0)) -> 37.267985 | T28: =INDEX(Segments!$A:$AJ,MATCH(Annual!$A28,Segments!$A:$A,0),MATCH("1H"&RIGHT(Annual!T$1,2),Segments!$A$3:$AJ$3,0))+INDEX(Segments!$A:$AJ,MATCH(Annual!$A28,Segments!$A:$A,0),MATCH("2H"&RIGHT(Annual!T$1,2),Segments!$A$3:$AJ$3,0)) -> 50.417923 | U28: =INDEX(Segments!$A:$AJ,MATCH(Annual!$A28,Segments!$A:$A,0),MATCH("1H"&RIGHT(Annual!U$1,2),Segments!$A$3:$AJ$3,0))+INDEX(Segments!$A:$AJ,MATCH(Annual!$A28,Segments!$A:$A,0),MATCH("2H"&RIGHT(Annual!U$1,2),Segments!$A$3:$AJ$3,0)) -> 65.523674 | V28: =INDEX(Segments!$A:$AJ,MATCH(Annual!$A28,Segments!$A:$A,0),MATCH("1H"&RIGHT(Annual!V$1,2),Segments!$A$3:$AJ$3,0))+INDEX(Segments!$A:$AJ,MATCH(Annual!$A28,Segments!$A:$A,0),MATCH("2H"&RIGHT(Annual!V$1,2),Segments!$A$3:$AJ$3,0)) -> 82.843116 | ... X28: =INDEX(Segments!$A:$AJ,MATCH(Annual!$A28,Segments!$A:$A,0),MATCH("1H"&RIGHT(Annual!X$1,2),Segments!$A$3:$AJ$3,0))+INDEX(Segments!$A:$AJ,MATCH(Annual!$A28,Segments!$A:$A,0),MATCH("2H"&RIGHT(Annual!X$1,2),Segments!$A$3:$AJ$3,0)) -> 125.32157
A29: GP-Gross Profit and Other income excluding trail book adjustment | B29: Gross Profit and Other income excluding trail book adjustment | C29: AUDm | D29: Preso | F29: 63.8 | G29: 78.5 | H29: 84 | I29: 102.5 | J29: 114.4 | K29: =SUM(K25:K28) -> 142.6 | L29: =SUM(L25:L28) -> 144.2 | M29: =SUM(M25:M28) -> 127 | N29: =SUM(N25:N28) -> 142.8 | O29: =INDEX(Segments!$A:$AJ,MATCH(Annual!$A29,Segments!$A:$A,0),MATCH("1H"&RIGHT(Annual!O$1,2),Segments!$A$3:$AJ$3,0))+INDEX(Segments!$A:$AJ,MATCH(Annual!$A29,Segments!$A:$A,0),MATCH("2H"&RIGHT(Annual!O$1,2),Segments!$A$3:$AJ$3,0)) -> 169.97388 | P29: =INDEX(Segments!$A:$AJ,MATCH(Annual!$A29,Segments!$A:$A,0),MATCH("1H"&RIGHT(Annual!P$1,2),Segments!$A$3:$AJ$3,0))+INDEX(Segments!$A:$AJ,MATCH(Annual!$A29,Segments!$A:$A,0),MATCH("2H"&RIGHT(Annual!P$1,2),Segments!$A$3:$AJ$3,0)) -> 191.3708 | Q29: =INDEX(Segments!$A:$AJ,MATCH(Annual!$A29,Segments!$A:$A,0),MATCH("1H"&RIGHT(Annual!Q$1,2),Segments!$A$3:$AJ$3,0))+INDEX(Segments!$A:$AJ,MATCH(Annual!$A29,Segments!$A:$A,0),MATCH("2H"&RIGHT(Annual!Q$1,2),Segments!$A$3:$AJ$3,0)) -> 211.78351 | R29: =INDEX(Segments!$A:$AJ,MATCH(Annual!$A29,Segments!$A:$A,0),MATCH("1H"&RIGHT(Annual!R$1,2),Segments!$A$3:$AJ$3,0))+INDEX(Segments!$A:$AJ,MATCH(Annual!$A29,Segments!$A:$A,0),MATCH("2H"&RIGHT(Annual!R$1,2),Segments!$A$3:$AJ$3,0)) -> 233.58281 | S29: =INDEX(Segments!$A:$AJ,MATCH(Annual!$A29,Segments!$A:$A,0),MATCH("1H"&RIGHT(Annual!S$1,2),Segments!$A$3:$AJ$3,0))+INDEX(Segments!$A:$AJ,MATCH(Annual!$A29,Segments!$A:$A,0),MATCH("2H"&RIGHT(Annual!S$1,2),Segments!$A$3:$AJ$3,0)) -> 257.91029 | T29: =INDEX(Segments!$A:$AJ,MATCH(Annual!$A29,Segments!$A:$A,0),MATCH("1H"&RIGHT(Annual!T$1,2),Segments!$A$3:$AJ$3,0))+INDEX(Segments!$A:$AJ,MATCH(Annual!$A29,Segments!$A:$A,0),MATCH("2H"&RIGHT(Annual!T$1,2),Segments!$A$3:$AJ$3,0)) -> 283.5893 | U29: =INDEX(Segments!$A:$AJ,MATCH(Annual!$A29,Segments!$A:$A,0),MATCH("1H"&RIGHT(Annual!U$1,2),Segments!$A$3:$AJ$3,0))+INDEX(Segments!$A:$AJ,MATCH(Annual!$A29,Segments!$A:$A,0),MATCH("2H"&RIGHT(Annual!U$1,2),Segments!$A$3:$AJ$3,0)) -> 311.95459 | V29: =INDEX(Segments!$A:$AJ,MATCH(Annual!$A29,Segments!$A:$A,0),MATCH("1H"&RIGHT(Annual!V$1,2),Segments!$A$3:$AJ$3,0))+INDEX(Segments!$A:$AJ,MATCH(Annual!$A29,Segments!$A:$A,0),MATCH("2H"&RIGHT(Annual!V$1,2),Segments!$A$3:$AJ$3,0)) -> 343.30721 | ... X29: =INDEX(Segments!$A:$AJ,MATCH(Annual!$A29,Segments!$A:$A,0),MATCH("1H"&RIGHT(Annual!X$1,2),Segments!$A$3:$AJ$3,0))+INDEX(Segments!$A:$AJ,MATCH(Annual!$A29,Segments!$A:$A,0),MATCH("2H"&RIGHT(Annual!X$1,2),Segments!$A$3:$AJ$3,0)) -> 416.35875 | AA29: 18 | AB29: 124.8 | AC29: 46.3 | AD29: 131.1 | AE29: 61.9 | AF29: 144.5
B30: Growth | C30: % YoY | G30: =G29/F29-1 -> 0.23040752 | H30: =H29/G29-1 -> 0.070063694 | I30: =I29/H29-1 -> 0.2202381 | J30: =J29/I29-1 -> 0.11609756 | K30: =K29/J29-1 -> 0.2465035 | L30: =L29/K29-1 -> 0.011220196 | M30: =M29/L29-1 -> -0.11927878 | N30: =N29/M29-1 -> 0.12440945 | ... X30: =X29/W29-1 -> 0.10152655 | AA30: 0 | AC30: 0.1 | AE30: 0.2 | AF30: 0
A32: Number of acquired brokers | B32: Number of acquired brokers | C32: # | N32: 2 | O32: =INDEX(Segments!$A:$AJ,MATCH(Annual!$A32,Segments!$A:$A,0),MATCH("1H"&RIGHT(Annual!O$1,2),Segments!$A$3:$AJ$3,0))+INDEX(Segments!$A:$AJ,MATCH(Annual!$A32,Segments!$A:$A,0),MATCH("2H"&RIGHT(Annual!O$1,2),Segments!$A$3:$AJ$3,0)) -> 4 | P32: =INDEX(Segments!$A:$AJ,MATCH(Annual!$A32,Segments!$A:$A,0),MATCH("1H"&RIGHT(Annual!P$1,2),Segments!$A$3:$AJ$3,0))+INDEX(Segments!$A:$AJ,MATCH(Annual!$A32,Segments!$A:$A,0),MATCH("2H"&RIGHT(Annual!P$1,2),Segments!$A$3:$AJ$3,0)) -> 8 | Q32: =INDEX(Segments!$A:$AJ,MATCH(Annual!$A32,Segments!$A:$A,0),MATCH("1H"&RIGHT(Annual!Q$1,2),Segments!$A$3:$AJ$3,0))+INDEX(Segments!$A:$AJ,MATCH(Annual!$A32,Segments!$A:$A,0),MATCH("2H"&RIGHT(Annual!Q$1,2),Segments!$A$3:$AJ$3,0)) -> 8.56 | R32: =INDEX(Segments!$A:$AJ,MATCH(Annual!$A32,Segments!$A:$A,0),MATCH("1H"&RIGHT(Annual!R$1,2),Segments!$A$3:$AJ$3,0))+INDEX(Segments!$A:$AJ,MATCH(Annual!$A32,Segments!$A:$A,0),MATCH("2H"&RIGHT(Annual!R$1,2),Segments!$A$3:$AJ$3,0)) -> 9.1592 | S32: =INDEX(Segments!$A:$AJ,MATCH(Annual!$A32,Segments!$A:$A,0),MATCH("1H"&RIGHT(Annual!S$1,2),Segments!$A$3:$AJ$3,0))+INDEX(Segments!$A:$AJ,MATCH(Annual!$A32,Segments!$A:$A,0),MATCH("2H"&RIGHT(Annual!S$1,2),Segments!$A$3:$AJ$3,0)) -> 9.800344 | T32: =INDEX(Segments!$A:$AJ,MATCH(Annual!$A32,Segments!$A:$A,0),MATCH("1H"&RIGHT(Annual!T$1,2),Segments!$A$3:$AJ$3,0))+INDEX(Segments!$A:$AJ,MATCH(Annual!$A32,Segments!$A:$A,0),MATCH("2H"&RIGHT(Annual!T$1,2),Segments!$A$3:$AJ$3,0)) -> 10.486368 | U32: =INDEX(Segments!$A:$AJ,MATCH(Annual!$A32,Segments!$A:$A,0),MATCH("1H"&RIGHT(Annual!U$1,2),Segments!$A$3:$AJ$3,0))+INDEX(Segments!$A:$AJ,MATCH(Annual!$A32,Segments!$A:$A,0),MATCH("2H"&RIGHT(Annual!U$1,2),Segments!$A$3:$AJ$3,0)) -> 11.220414 | V32: =INDEX(Segments!$A:$AJ,MATCH(Annual!$A32,Segments!$A:$A,0),MATCH("1H"&RIGHT(Annual!V$1,2),Segments!$A$3:$AJ$3,0))+INDEX(Segments!$A:$AJ,MATCH(Annual!$A32,Segments!$A:$A,0),MATCH("2H"&RIGHT(Annual!V$1,2),Segments!$A$3:$AJ$3,0)) -> 12.005843 | ... X32: =INDEX(Segments!$A:$AJ,MATCH(Annual!$A32,Segments!$A:$A,0),MATCH("1H"&RIGHT(Annual!X$1,2),Segments!$A$3:$AJ$3,0))+INDEX(Segments!$A:$AJ,MATCH(Annual!$A32,Segments!$A:$A,0),MATCH("2H"&RIGHT(Annual!X$1,2),Segments!$A$3:$AJ$3,0)) -> 13.745489
A33: Number of acquired brokers cumulative | B33: Number of acquired brokers cumulative | C33: # | N33: =INDEX(Segments!$A:$AJ,MATCH(Annual!$A33,Segments!$A:$A,0),MATCH("2H"&RIGHT(Annual!N$1,2),Segments!$A$3:$AJ$3,0)) -> 2 | O33: =INDEX(Segments!$A:$AJ,MATCH(Annual!$A33,Segments!$A:$A,0),MATCH("2H"&RIGHT(Annual!O$1,2),Segments!$A$3:$AJ$3,0)) -> 6 | P33: =INDEX(Segments!$A:$AJ,MATCH(Annual!$A33,Segments!$A:$A,0),MATCH("2H"&RIGHT(Annual!P$1,2),Segments!$A$3:$AJ$3,0)) -> 14 | Q33: =INDEX(Segments!$A:$AJ,MATCH(Annual!$A33,Segments!$A:$A,0),MATCH("2H"&RIGHT(Annual!Q$1,2),Segments!$A$3:$AJ$3,0)) -> 22.56 | R33: =INDEX(Segments!$A:$AJ,MATCH(Annual!$A33,Segments!$A:$A,0),MATCH("2H"&RIGHT(Annual!R$1,2),Segments!$A$3:$AJ$3,0)) -> 31.7192 | S33: =INDEX(Segments!$A:$AJ,MATCH(Annual!$A33,Segments!$A:$A,0),MATCH("2H"&RIGHT(Annual!S$1,2),Segments!$A$3:$AJ$3,0)) -> 41.519544 | T33: =INDEX(Segments!$A:$AJ,MATCH(Annual!$A33,Segments!$A:$A,0),MATCH("2H"&RIGHT(Annual!T$1,2),Segments!$A$3:$AJ$3,0)) -> 52.005912 | U33: =INDEX(Segments!$A:$AJ,MATCH(Annual!$A33,Segments!$A:$A,0),MATCH("2H"&RIGHT(Annual!U$1,2),Segments!$A$3:$AJ$3,0)) -> 63.226326 | ... X33: =INDEX(Segments!$A:$AJ,MATCH(Annual!$A33,Segments!$A:$A,0),MATCH("2H"&RIGHT(Annual!X$1,2),Segments!$A$3:$AJ$3,0)) -> 101.82391
B34: FY29 Aspiration | R34: 35
A35: EBITDA per acquired broker | B35: EBITDA per acquired broker | C35: AUDm | N35: =0.85/2 -> 0.425 | O35: =INDEX(Segments!$A:$AJ,MATCH(Annual!$A35,Segments!$A:$A,0),MATCH("2H"&RIGHT(Annual!O$1,2),Segments!$A$3:$AJ$3,0)) -> 0.48875 | P35: =INDEX(Segments!$A:$AJ,MATCH(Annual!$A35,Segments!$A:$A,0),MATCH("2H"&RIGHT(Annual!P$1,2),Segments!$A$3:$AJ$3,0)) -> 0.537625 | Q35: =INDEX(Segments!$A:$AJ,MATCH(Annual!$A35,Segments!$A:$A,0),MATCH("2H"&RIGHT(Annual!Q$1,2),Segments!$A$3:$AJ$3,0)) -> 0.5698825 | R35: =INDEX(Segments!$A:$AJ,MATCH(Annual!$A35,Segments!$A:$A,0),MATCH("2H"&RIGHT(Annual!R$1,2),Segments!$A$3:$AJ$3,0)) -> 0.60407545 | S35: =INDEX(Segments!$A:$AJ,MATCH(Annual!$A35,Segments!$A:$A,0),MATCH("2H"&RIGHT(Annual!S$1,2),Segments!$A$3:$AJ$3,0)) -> 0.64031998 | T35: =INDEX(Segments!$A:$AJ,MATCH(Annual!$A35,Segments!$A:$A,0),MATCH("2H"&RIGHT(Annual!T$1,2),Segments!$A$3:$AJ$3,0)) -> 0.67873918 | U35: =INDEX(Segments!$A:$AJ,MATCH(Annual!$A35,Segments!$A:$A,0),MATCH("2H"&RIGHT(Annual!U$1,2),Segments!$A$3:$AJ$3,0)) -> 0.71946353 | V35: =INDEX(Segments!$A:$AJ,MATCH(Annual!$A35,Segments!$A:$A,0),MATCH("2H"&RIGHT(Annual!V$1,2),Segments!$A$3:$AJ$3,0)) -> 0.76263134 | ... X35: =INDEX(Segments!$A:$AJ,MATCH(Annual!$A35,Segments!$A:$A,0),MATCH("2H"&RIGHT(Annual!X$1,2),Segments!$A$3:$AJ$3,0)) -> 0.85689257
N36: =6/6.5/2 -> 0.46153846
B37: Operating Expenses
A38: Opex-Distribution | B38: Distribution | C38: AUDm | D38: AR | M38: =M47-M25 -> -42.8 | N38: =N47-N25 -> -45.4 | AA38: -28.6 | AB38: -16.8 | AC38: 0 | AD38: 0 | AE38: 0 | AF38: 0
A39: Opex-Manuracturing | B39: Manuracturing | C39: AUDm | M39: =M48-M26 -> -12.1 | N39: =N48-N26 -> -13.4 | AA39: -6.9 | AB39: -6.5 | AC39: 0 | AD39: 0 | AE39: 0 | AF39: 0
A40: Opex-Central | B40: Central | C40: AUDm | M40: =M49-M27 -> -24.7 | N40: =N49-N27 -> -27.8 | AA40: 0 | AB40: -27.8 | AC40: 0 | AD40: 0 | AE40: 0 | AF40: 0
A41: Opex-Total Operating Costs | B41: Total Operating Costs | C41: AUDm | F41: =F51-F29 -> -20.9 | G41: =G51-G29 -> -32.2 | H41: =H51-H29 -> -38.5 | I41: =I51-I29 -> -47.2 | J41: =J51-J29 -> -42.1 | K41: =K51-K29 -> -55.9 | L41: =L51-L29 -> -84.8 | M41: =M51-M29 -> -79.6 | N41: =N51-N29 -> -86.6 | O41: =INDEX(Segments!$A:$AJ,MATCH(Annual!$A41,Segments!$A:$A,0),MATCH("1H"&RIGHT(Annual!O$1,2),Segments!$A$3:$AJ$3,0))+INDEX(Segments!$A:$AJ,MATCH(Annual!$A41,Segments!$A:$A,0),MATCH("2H"&RIGHT(Annual!O$1,2),Segments!$A$3:$AJ$3,0)) -> -89.82794 | P41: =INDEX(Segments!$A:$AJ,MATCH(Annual!$A41,Segments!$A:$A,0),MATCH("1H"&RIGHT(Annual!P$1,2),Segments!$A$3:$AJ$3,0))+INDEX(Segments!$A:$AJ,MATCH(Annual!$A41,Segments!$A:$A,0),MATCH("2H"&RIGHT(Annual!P$1,2),Segments!$A$3:$AJ$3,0)) -> -98.254771 | Q41: =INDEX(Segments!$A:$AJ,MATCH(Annual!$A41,Segments!$A:$A,0),MATCH("1H"&RIGHT(Annual!Q$1,2),Segments!$A$3:$AJ$3,0))+INDEX(Segments!$A:$AJ,MATCH(Annual!$A41,Segments!$A:$A,0),MATCH("2H"&RIGHT(Annual!Q$1,2),Segments!$A$3:$AJ$3,0)) -> -105.5696 | R41: =INDEX(Segments!$A:$AJ,MATCH(Annual!$A41,Segments!$A:$A,0),MATCH("1H"&RIGHT(Annual!R$1,2),Segments!$A$3:$AJ$3,0))+INDEX(Segments!$A:$AJ,MATCH(Annual!$A41,Segments!$A:$A,0),MATCH("2H"&RIGHT(Annual!R$1,2),Segments!$A$3:$AJ$3,0)) -> -112.93496 | S41: =INDEX(Segments!$A:$AJ,MATCH(Annual!$A41,Segments!$A:$A,0),MATCH("1H"&RIGHT(Annual!S$1,2),Segments!$A$3:$AJ$3,0))+INDEX(Segments!$A:$AJ,MATCH(Annual!$A41,Segments!$A:$A,0),MATCH("2H"&RIGHT(Annual!S$1,2),Segments!$A$3:$AJ$3,0)) -> -122.12035 | T41: =INDEX(Segments!$A:$AJ,MATCH(Annual!$A41,Segments!$A:$A,0),MATCH("1H"&RIGHT(Annual!T$1,2),Segments!$A$3:$AJ$3,0))+INDEX(Segments!$A:$AJ,MATCH(Annual!$A41,Segments!$A:$A,0),MATCH("2H"&RIGHT(Annual!T$1,2),Segments!$A$3:$AJ$3,0)) -> -131.44577 | U41: =INDEX(Segments!$A:$AJ,MATCH(Annual!$A41,Segments!$A:$A,0),MATCH("1H"&RIGHT(Annual!U$1,2),Segments!$A$3:$AJ$3,0))+INDEX(Segments!$A:$AJ,MATCH(Annual!$A41,Segments!$A:$A,0),MATCH("2H"&RIGHT(Annual!U$1,2),Segments!$A$3:$AJ$3,0)) -> -141.47606 | V41: =INDEX(Segments!$A:$AJ,MATCH(Annual!$A41,Segments!$A:$A,0),MATCH("1H"&RIGHT(Annual!V$1,2),Segments!$A$3:$AJ$3,0))+INDEX(Segments!$A:$AJ,MATCH(Annual!$A41,Segments!$A:$A,0),MATCH("2H"&RIGHT(Annual!V$1,2),Segments!$A$3:$AJ$3,0)) -> -152.26417 | ... X41: =INDEX(Segments!$A:$AJ,MATCH(Annual!$A41,Segments!$A:$A,0),MATCH("1H"&RIGHT(Annual!X$1,2),Segments!$A$3:$AJ$3,0))+INDEX(Segments!$A:$AJ,MATCH(Annual!$A41,Segments!$A:$A,0),MATCH("2H"&RIGHT(Annual!X$1,2),Segments!$A$3:$AJ$3,0)) -> -176.34172 | AA41: -70 | AB41: -16.6 | AC41: -73.5 | AD41: -23 | AE41: -84.6 | AF41: -24.6
B42: Growth | C42: % YoY | L42: =L41/K41-1 -> 0.51699463 | M42: =M41/L41-1 -> -0.061320755 | N42: =N41/M41-1 -> 0.087939698 | O42: =O41/N41-1 -> 0.037274131 | P42: =P41/O41-1 -> 0.093810809 | Q42: =Q41/P41-1 -> 0.074447612 | R42: =R41/Q41-1 -> 0.069767776 | S42: =S41/R41-1 -> 0.081333422 | ... X42: =X41/W41-1 -> 0.07613196 | AA42: 0 | AC42: 0.1 | AE42: 0.2 | AF42: 0
B43: Cost to Income Ratio | C43: % | F43: =-F41/F29 -> 0.32758621 | G43: =-G41/G29 -> 0.41019108 | H43: =-H41/H29 -> 0.45833333 | I43: =-I41/I29 -> 0.4604878 | J43: =-J41/J29 -> 0.36800699 | K43: =-K41/K29 -> 0.39200561 | L43: =-L41/L29 -> 0.58807212 | M43: =-M41/M29 -> 0.62677165 | ... X43: =-X41/X29 -> 0.42353311 | AA43: 0.6 | AB43: 0 | AC43: 0.5 | AD43: 0.1 | AE43: 0.4 | AF43: 0.1
B44: FY29 Aspiration | R44: <50%
B46: EBITDA
A47: EBITDA-Distribution | B47: Distribution | C47: AUDm | D47: AR | L47: NR | M47: 61.6 | N47: 67.9 | AA47: -28.6 | AB47: 96.5 | AC47: 0 | AD47: 0 | AE47: 0 | AF47: 0
A48: EBITDA-Manuracturing | B48: Manuracturing | C48: AUDm | L48: NR | M48: 10.5 | N48: 16.1 | AA48: -6.9 | AB48: 23 | AC48: 0 | AD48: 0 | AE48: 0 | AF48: 0
A49: EBITDA-Central | B49: Central | C49: AUDm | M49: -24.7 | N49: -27.8 | AA49: -6.9 | AB49: -20.9 | AC49: 0 | AD49: 0 | AE49: 0 | AF49: 0
A50: EBITDA-Inorganic- forecast | B50: Inorganic- forecast | O50: =INDEX(Segments!$A:$AJ,MATCH(Annual!$A50,Segments!$A:$A,0),MATCH("1H"&RIGHT(Annual!O$1,2),Segments!$A$3:$AJ$3,0))+INDEX(Segments!$A:$AJ,MATCH(Annual!$A50,Segments!$A:$A,0),MATCH("2H"&RIGHT(Annual!O$1,2),Segments!$A$3:$AJ$3,0)) -> 1.275 | P50: =INDEX(Segments!$A:$AJ,MATCH(Annual!$A50,Segments!$A:$A,0),MATCH("1H"&RIGHT(Annual!P$1,2),Segments!$A$3:$AJ$3,0))+INDEX(Segments!$A:$AJ,MATCH(Annual!$A50,Segments!$A:$A,0),MATCH("2H"&RIGHT(Annual!P$1,2),Segments!$A$3:$AJ$3,0)) -> 3.70175 | Q50: =INDEX(Segments!$A:$AJ,MATCH(Annual!$A50,Segments!$A:$A,0),MATCH("1H"&RIGHT(Annual!Q$1,2),Segments!$A$3:$AJ$3,0))+INDEX(Segments!$A:$AJ,MATCH(Annual!$A50,Segments!$A:$A,0),MATCH("2H"&RIGHT(Annual!Q$1,2),Segments!$A$3:$AJ$3,0)) -> 8.1068495 | R50: =INDEX(Segments!$A:$AJ,MATCH(Annual!$A50,Segments!$A:$A,0),MATCH("1H"&RIGHT(Annual!R$1,2),Segments!$A$3:$AJ$3,0))+INDEX(Segments!$A:$AJ,MATCH(Annual!$A50,Segments!$A:$A,0),MATCH("2H"&RIGHT(Annual!R$1,2),Segments!$A$3:$AJ$3,0)) -> 13.376696 | S50: =INDEX(Segments!$A:$AJ,MATCH(Annual!$A50,Segments!$A:$A,0),MATCH("1H"&RIGHT(Annual!S$1,2),Segments!$A$3:$AJ$3,0))+INDEX(Segments!$A:$AJ,MATCH(Annual!$A50,Segments!$A:$A,0),MATCH("2H"&RIGHT(Annual!S$1,2),Segments!$A$3:$AJ$3,0)) -> 19.64649 | T50: =INDEX(Segments!$A:$AJ,MATCH(Annual!$A50,Segments!$A:$A,0),MATCH("1H"&RIGHT(Annual!T$1,2),Segments!$A$3:$AJ$3,0))+INDEX(Segments!$A:$AJ,MATCH(Annual!$A50,Segments!$A:$A,0),MATCH("2H"&RIGHT(Annual!T$1,2),Segments!$A$3:$AJ$3,0)) -> 27.070914 | U50: =INDEX(Segments!$A:$AJ,MATCH(Annual!$A50,Segments!$A:$A,0),MATCH("1H"&RIGHT(Annual!U$1,2),Segments!$A$3:$AJ$3,0))+INDEX(Segments!$A:$AJ,MATCH(Annual!$A50,Segments!$A:$A,0),MATCH("2H"&RIGHT(Annual!U$1,2),Segments!$A$3:$AJ$3,0)) -> 35.826847 | V50: =INDEX(Segments!$A:$AJ,MATCH(Annual!$A50,Segments!$A:$A,0),MATCH("1H"&RIGHT(Annual!V$1,2),Segments!$A$3:$AJ$3,0))+INDEX(Segments!$A:$AJ,MATCH(Annual!$A50,Segments!$A:$A,0),MATCH("2H"&RIGHT(Annual!V$1,2),Segments!$A$3:$AJ$3,0)) -> 46.116438 | ... X50: =INDEX(Segments!$A:$AJ,MATCH(Annual!$A50,Segments!$A:$A,0),MATCH("1H"&RIGHT(Annual!X$1,2),Segments!$A$3:$AJ$3,0))+INDEX(Segments!$A:$AJ,MATCH(Annual!$A50,Segments!$A:$A,0),MATCH("2H"&RIGHT(Annual!X$1,2),Segments!$A$3:$AJ$3,0)) -> 72.253016
A51: EBITDA-Underlying EBITDA | B51: Underlying EBITDA | C51: AUDm | D51: Preso | F51: 42.9 | G51: 46.3 | H51: 45.5 | I51: 55.3 | J51: 72.3 | K51: 86.7 | L51: 59.4 | M51: =SUM(M47:M50) -> 47.4 | N51: =SUM(N47:N50) -> 56.2 | O51: =INDEX(Segments!$A:$AJ,MATCH(Annual!$A51,Segments!$A:$A,0),MATCH("1H"&RIGHT(Annual!O$1,2),Segments!$A$3:$AJ$3,0))+INDEX(Segments!$A:$AJ,MATCH(Annual!$A51,Segments!$A:$A,0),MATCH("2H"&RIGHT(Annual!O$1,2),Segments!$A$3:$AJ$3,0)) -> 80.14594 | P51: =INDEX(Segments!$A:$AJ,MATCH(Annual!$A51,Segments!$A:$A,0),MATCH("1H"&RIGHT(Annual!P$1,2),Segments!$A$3:$AJ$3,0))+INDEX(Segments!$A:$AJ,MATCH(Annual!$A51,Segments!$A:$A,0),MATCH("2H"&RIGHT(Annual!P$1,2),Segments!$A$3:$AJ$3,0)) -> 93.116027 | Q51: =INDEX(Segments!$A:$AJ,MATCH(Annual!$A51,Segments!$A:$A,0),MATCH("1H"&RIGHT(Annual!Q$1,2),Segments!$A$3:$AJ$3,0))+INDEX(Segments!$A:$AJ,MATCH(Annual!$A51,Segments!$A:$A,0),MATCH("2H"&RIGHT(Annual!Q$1,2),Segments!$A$3:$AJ$3,0)) -> 106.2139 | R51: =INDEX(Segments!$A:$AJ,MATCH(Annual!$A51,Segments!$A:$A,0),MATCH("1H"&RIGHT(Annual!R$1,2),Segments!$A$3:$AJ$3,0))+INDEX(Segments!$A:$AJ,MATCH(Annual!$A51,Segments!$A:$A,0),MATCH("2H"&RIGHT(Annual!R$1,2),Segments!$A$3:$AJ$3,0)) -> 120.64785 | S51: =INDEX(Segments!$A:$AJ,MATCH(Annual!$A51,Segments!$A:$A,0),MATCH("1H"&RIGHT(Annual!S$1,2),Segments!$A$3:$AJ$3,0))+INDEX(Segments!$A:$AJ,MATCH(Annual!$A51,Segments!$A:$A,0),MATCH("2H"&RIGHT(Annual!S$1,2),Segments!$A$3:$AJ$3,0)) -> 135.78995 | T51: =INDEX(Segments!$A:$AJ,MATCH(Annual!$A51,Segments!$A:$A,0),MATCH("1H"&RIGHT(Annual!T$1,2),Segments!$A$3:$AJ$3,0))+INDEX(Segments!$A:$AJ,MATCH(Annual!$A51,Segments!$A:$A,0),MATCH("2H"&RIGHT(Annual!T$1,2),Segments!$A$3:$AJ$3,0)) -> 152.14353 | U51: =INDEX(Segments!$A:$AJ,MATCH(Annual!$A51,Segments!$A:$A,0),MATCH("1H"&RIGHT(Annual!U$1,2),Segments!$A$3:$AJ$3,0))+INDEX(Segments!$A:$AJ,MATCH(Annual!$A51,Segments!$A:$A,0),MATCH("2H"&RIGHT(Annual!U$1,2),Segments!$A$3:$AJ$3,0)) -> 170.47853 | V51: =INDEX(Segments!$A:$AJ,MATCH(Annual!$A51,Segments!$A:$A,0),MATCH("1H"&RIGHT(Annual!V$1,2),Segments!$A$3:$AJ$3,0))+INDEX(Segments!$A:$AJ,MATCH(Annual!$A51,Segments!$A:$A,0),MATCH("2H"&RIGHT(Annual!V$1,2),Segments!$A$3:$AJ$3,0)) -> 191.04305 | ... X51: =INDEX(Segments!$A:$AJ,MATCH(Annual!$A51,Segments!$A:$A,0),MATCH("1H"&RIGHT(Annual!X$1,2),Segments!$A$3:$AJ$3,0))+INDEX(Segments!$A:$AJ,MATCH(Annual!$A51,Segments!$A:$A,0),MATCH("2H"&RIGHT(Annual!X$1,2),Segments!$A$3:$AJ$3,0)) -> 240.01703 | AA51: 18 | AB51: 38.2 | AC51: 46.3 | AD51: 34.6 | AE51: 61.9 | AF51: 35.3
B52: Growth | C52: % YoY | L52: =L51/K51-1 -> -0.31487889 | M52: =M51/L51-1 -> -0.2020202 | N52: =N51/M51-1 -> 0.18565401 | O52: =O51/N51-1 -> 0.42608434 | P52: =P51/O51-1 -> 0.16183087 | Q52: =Q51/P51-1 -> 0.14066186 | R52: =R51/Q51-1 -> 0.1358951 | S52: =S51/R51-1 -> 0.12550656 | ... X52: =X51/W51-1 -> 0.12096132 | AA52: 8.18 | AB52: -8 | AC52: 1.57 | AD52: -1.13 | AE52: 0.34 | AF52: -0.14
B53: Margin | C53: % | K53: =K51/K$10 -> 0.093336204 | L53: =L51/L$10 -> 0.059234144 | M53: =M51/M$10 -> 0.043978475 | N53: =N51/N$10 -> 0.045487657 | O53: =O51/O$10 -> 0.054345398 | P53: =P51/P$10 -> 0.0559667 | Q53: =Q51/Q$10 -> 0.057698515 | R53: =R51/R$10 -> 0.059323989 | ... X53: =X51/X$10 -> 0.065572677 | AA53: 0.154 | AB53: -0.108 | AC53: 0.29 | AD53: -0.236 | AE53: 0.317 | AF53: -0.262
O54: 0.44393818 | P54: 0.18945382 | Q54: 0.15344959 | R54: 0.14061247 | S54: 0.12390163 | T54: 0.11363817 | U54: 0.10890116 | V54: 0.10480323 | W54: 0.10122965 | X54: 0.098091421
A55: Share-based payments (employees) | B55: Share-based payments (employees) | O55: =O52-O54 -> -0.017853838 | P55: =P52-P54 -> -0.027622955 | Q55: =Q52-Q54 -> -0.012787725 | R55: =R52-R54 -> -0.0047173717 | S55: =S52-S54 -> 0.0016049344 | T55: =T52-T54 -> 0.006794803 | U55: =U52-U54 -> 0.011610031 | V55: =V52-V54 -> 0.015824953 | ... X55: =X52-X54 -> 0.022869894 | AA55: -9.795 | AC55: -10.285 | AE55: -11.827 | AF55: 11.827
A56: EBITDA-EBITDA | B56: EBITDA | C56: AUDm | D56: Preso | F56: =F51+F55 -> 42.9 | G56: =G51+G55 -> 46.3 | H56: =H51+H55 -> 45.5 | I56: =I51+I55 -> 55.3 | J56: =J51+J55 -> 72.3 | K56: =K51+K55 -> 86.7 | L56: =L51+L55 -> 59.4 | M56: =M51+M55 -> 47.4 | N56: =N51+N55 -> 56.2 | O56: =INDEX(Segments!$A:$AJ,MATCH(Annual!$A56,Segments!$A:$A,0),MATCH("1H"&RIGHT(Annual!O$1,2),Segments!$A$3:$AJ$3,0))+INDEX(Segments!$A:$AJ,MATCH(Annual!$A56,Segments!$A:$A,0),MATCH("2H"&RIGHT(Annual!O$1,2),Segments!$A$3:$AJ$3,0)) -> 80.14594 | P56: =INDEX(Segments!$A:$AJ,MATCH(Annual!$A56,Segments!$A:$A,0),MATCH("1H"&RIGHT(Annual!P$1,2),Segments!$A$3:$AJ$3,0))+INDEX(Segments!$A:$AJ,MATCH(Annual!$A56,Segments!$A:$A,0),MATCH("2H"&RIGHT(Annual!P$1,2),Segments!$A$3:$AJ$3,0)) -> 93.116027 | Q56: =INDEX(Segments!$A:$AJ,MATCH(Annual!$A56,Segments!$A:$A,0),MATCH("1H"&RIGHT(Annual!Q$1,2),Segments!$A$3:$AJ$3,0))+INDEX(Segments!$A:$AJ,MATCH(Annual!$A56,Segments!$A:$A,0),MATCH("2H"&RIGHT(Annual!Q$1,2),Segments!$A$3:$AJ$3,0)) -> 106.2139 | R56: =INDEX(Segments!$A:$AJ,MATCH(Annual!$A56,Segments!$A:$A,0),MATCH("1H"&RIGHT(Annual!R$1,2),Segments!$A$3:$AJ$3,0))+INDEX(Segments!$A:$AJ,MATCH(Annual!$A56,Segments!$A:$A,0),MATCH("2H"&RIGHT(Annual!R$1,2),Segments!$A$3:$AJ$3,0)) -> 120.64785 | S56: =INDEX(Segments!$A:$AJ,MATCH(Annual!$A56,Segments!$A:$A,0),MATCH("1H"&RIGHT(Annual!S$1,2),Segments!$A$3:$AJ$3,0))+INDEX(Segments!$A:$AJ,MATCH(Annual!$A56,Segments!$A:$A,0),MATCH("2H"&RIGHT(Annual!S$1,2),Segments!$A$3:$AJ$3,0)) -> 135.78995 | T56: =INDEX(Segments!$A:$AJ,MATCH(Annual!$A56,Segments!$A:$A,0),MATCH("1H"&RIGHT(Annual!T$1,2),Segments!$A$3:$AJ$3,0))+INDEX(Segments!$A:$AJ,MATCH(Annual!$A56,Segments!$A:$A,0),MATCH("2H"&RIGHT(Annual!T$1,2),Segments!$A$3:$AJ$3,0)) -> 152.14353 | U56: =INDEX(Segments!$A:$AJ,MATCH(Annual!$A56,Segments!$A:$A,0),MATCH("1H"&RIGHT(Annual!U$1,2),Segments!$A$3:$AJ$3,0))+INDEX(Segments!$A:$AJ,MATCH(Annual!$A56,Segments!$A:$A,0),MATCH("2H"&RIGHT(Annual!U$1,2),Segments!$A$3:$AJ$3,0)) -> 170.47853 | V56: =INDEX(Segments!$A:$AJ,MATCH(Annual!$A56,Segments!$A:$A,0),MATCH("1H"&RIGHT(Annual!V$1,2),Segments!$A$3:$AJ$3,0))+INDEX(Segments!$A:$AJ,MATCH(Annual!$A56,Segments!$A:$A,0),MATCH("2H"&RIGHT(Annual!V$1,2),Segments!$A$3:$AJ$3,0)) -> 191.04305 | ... X56: =INDEX(Segments!$A:$AJ,MATCH(Annual!$A56,Segments!$A:$A,0),MATCH("1H"&RIGHT(Annual!X$1,2),Segments!$A$3:$AJ$3,0))+INDEX(Segments!$A:$AJ,MATCH(Annual!$A56,Segments!$A:$A,0),MATCH("2H"&RIGHT(Annual!X$1,2),Segments!$A$3:$AJ$3,0)) -> 240.01703 | AA56: 8.2 | AB56: 48 | AC56: 36 | AD56: 44.9 | AE56: 50.1 | AF56: 47.1
B57: Growth | C57: % YoY | L57: =L56/K56-1 -> -0.31487889 | M57: =M56/L56-1 -> -0.2020202 | N57: =N56/M56-1 -> 0.18565401 | O57: =O56/N56-1 -> 0.42608434 | P57: =P56/O56-1 -> 0.16183087 | Q57: =Q56/P56-1 -> 0.14066186 | R57: =R56/Q56-1 -> 0.1358951 | S57: =S56/R56-1 -> 0.12550656 | ... X57: =X56/W56-1 -> 0.12096132 | AA57: -1.87 | AB57: 2.05 | AC57: 3.38 | AD57: -2.94 | AE57: 0.39 | AF57: -0.19
B58: Margin | C58: % | K58: =K56/K$10 -> 0.093336204 | L58: =L56/L$10 -> 0.059234144 | M58: =M56/M$10 -> 0.043978475 | N58: =N56/N$10 -> 0.045487657 | O58: =O56/O$10 -> 0.054345398 | P58: =P56/P$10 -> 0.0559667 | Q58: =Q56/Q$10 -> 0.057698515 | R58: =R56/R$10 -> 0.059323989 | ... X58: =X56/X$10 -> 0.065572677 | AA58: 0.07 | AB58: -0.025 | AC58: 0.225 | AD58: -0.172 | AE58: 0.256 | AF58: -0.201
B60: D&A
A61: D&A-Depreciation | B61: Depreciation | C61: AUDm | D61: Pres | I61: =I64-I63-I62 -> -2.5 | J61: =J64-J63-J62 -> -2.1 | K61: =K64-K63-K62 -> -4.1 | L61: =L64-L63-L62 -> -7 | M61: =M64-M63-M62 -> -0.5 | N61: =N64-N63-N62 -> -0.9 | O61: =O$64/N$64*N61 -> -1.2228279 | P61: =P$64/O$64*O61 -> -1.3795623 | Q61: =Q$64/P$64*P61 -> -1.5263823 | R61: =R$64/Q$64*Q61 -> -1.6863038 | S61: =S$64/R$64*R61 -> -1.8651018 | T61: =T$64/S$64*S61 -> -2.0540023 | U61: =U$64/T$64*T61 -> -2.2630232 | V61: =V$64/U$64*U61 -> -2.4944503 | ... X61: =X$64/W$64*W61 -> -3.0350492 | AA61: -3.9 | AB61: 3 | AC61: -4 | AD61: 2.7 | AE61: -4.1 | AF61: 2.7
A62: D&A-Depreciation of right of use assets | B62: Depreciation of right of use assets | M62: -2.1 | N62: -1.7 | O62: =O$64/N$64*N62 -> -2.309786 | P62: =P$64/O$64*O62 -> -2.6058399 | Q62: =Q$64/P$64*P62 -> -2.8831665 | R62: =R$64/Q$64*Q62 -> -3.1852406 | S62: =S$64/R$64*R62 -> -3.5229701 | T62: =T$64/S$64*S62 -> -3.8797821 | U62: =U$64/T$64*T62 -> -4.2745995 | V62: =V$64/U$64*U62 -> -4.7117395 | ... X62: =X$64/W$64*W62 -> -5.7328708 | AA62: -1.7 | AB62: 0 | AC62: -1.8 | AD62: -0.6 | AE62: -1.8 | AF62: -0.9
A63: D&A-Amortisation | B63: Amortisation | C63: AUDm | D63: Preso | M63: -4.8 | N63: -7.9 | O63: =O$64/N$64*N63 -> -10.733712 | P63: =P$64/O$64*O63 -> -12.109492 | Q63: =Q$64/P$64*P63 -> -13.398244 | R63: =R$64/Q$64*Q63 -> -14.802 | S63: =S$64/R$64*R63 -> -16.371449 | T63: =T$64/S$64*S63 -> -18.029576 | U63: =U$64/T$64*T63 -> -19.864315 | V63: =V$64/U$64*U63 -> -21.895731 | ... X63: =X$64/W$64*W63 -> -26.640988 | AA63: -28.9 | AB63: 21 | AC63: -29.7 | AD63: 18.6 | AE63: -30.4 | AF63: 17.6
A64: D&A-D&A | B64: D&A | C64: AUDm | F64: -0.9 | G64: -1 | H64: -1 | I64: -2.5 | J64: -2.1 | K64: -4.1 | L64: -7 | M64: -7.4 | N64: -10.5 | O64: =INDEX(Segments!$A:$AJ,MATCH(Annual!$A64,Segments!$A:$A,0),MATCH("1H"&RIGHT(Annual!O$1,2),Segments!$A$3:$AJ$3,0))+INDEX(Segments!$A:$AJ,MATCH(Annual!$A64,Segments!$A:$A,0),MATCH("2H"&RIGHT(Annual!O$1,2),Segments!$A$3:$AJ$3,0)) -> -14.266326 | P64: =INDEX(Segments!$A:$AJ,MATCH(Annual!$A64,Segments!$A:$A,0),MATCH("1H"&RIGHT(Annual!P$1,2),Segments!$A$3:$AJ$3,0))+INDEX(Segments!$A:$AJ,MATCH(Annual!$A64,Segments!$A:$A,0),MATCH("2H"&RIGHT(Annual!P$1,2),Segments!$A$3:$AJ$3,0)) -> -16.094894 | Q64: =INDEX(Segments!$A:$AJ,MATCH(Annual!$A64,Segments!$A:$A,0),MATCH("1H"&RIGHT(Annual!Q$1,2),Segments!$A$3:$AJ$3,0))+INDEX(Segments!$A:$AJ,MATCH(Annual!$A64,Segments!$A:$A,0),MATCH("2H"&RIGHT(Annual!Q$1,2),Segments!$A$3:$AJ$3,0)) -> -17.807793 | R64: =INDEX(Segments!$A:$AJ,MATCH(Annual!$A64,Segments!$A:$A,0),MATCH("1H"&RIGHT(Annual!R$1,2),Segments!$A$3:$AJ$3,0))+INDEX(Segments!$A:$AJ,MATCH(Annual!$A64,Segments!$A:$A,0),MATCH("2H"&RIGHT(Annual!R$1,2),Segments!$A$3:$AJ$3,0)) -> -19.673545 | S64: =INDEX(Segments!$A:$AJ,MATCH(Annual!$A64,Segments!$A:$A,0),MATCH("1H"&RIGHT(Annual!S$1,2),Segments!$A$3:$AJ$3,0))+INDEX(Segments!$A:$AJ,MATCH(Annual!$A64,Segments!$A:$A,0),MATCH("2H"&RIGHT(Annual!S$1,2),Segments!$A$3:$AJ$3,0)) -> -21.759521 | T64: =INDEX(Segments!$A:$AJ,MATCH(Annual!$A64,Segments!$A:$A,0),MATCH("1H"&RIGHT(Annual!T$1,2),Segments!$A$3:$AJ$3,0))+INDEX(Segments!$A:$AJ,MATCH(Annual!$A64,Segments!$A:$A,0),MATCH("2H"&RIGHT(Annual!T$1,2),Segments!$A$3:$AJ$3,0)) -> -23.96336 | U64: =INDEX(Segments!$A:$AJ,MATCH(Annual!$A64,Segments!$A:$A,0),MATCH("1H"&RIGHT(Annual!U$1,2),Segments!$A$3:$AJ$3,0))+INDEX(Segments!$A:$AJ,MATCH(Annual!$A64,Segments!$A:$A,0),MATCH("2H"&RIGHT(Annual!U$1,2),Segments!$A$3:$AJ$3,0)) -> -26.401938 | V64: =INDEX(Segments!$A:$AJ,MATCH(Annual!$A64,Segments!$A:$A,0),MATCH("1H"&RIGHT(Annual!V$1,2),Segments!$A$3:$AJ$3,0))+INDEX(Segments!$A:$AJ,MATCH(Annual!$A64,Segments!$A:$A,0),MATCH("2H"&RIGHT(Annual!V$1,2),Segments!$A$3:$AJ$3,0)) -> -29.10192 | ... X64: =INDEX(Segments!$A:$AJ,MATCH(Annual!$A64,Segments!$A:$A,0),MATCH("1H"&RIGHT(Annual!X$1,2),Segments!$A$3:$AJ$3,0))+INDEX(Segments!$A:$AJ,MATCH(Annual!$A64,Segments!$A:$A,0),MATCH("2H"&RIGHT(Annual!X$1,2),Segments!$A$3:$AJ$3,0)) -> -35.408908 | AA64: -34.6 | AB64: 24.1 | AC64: -35.5 | AD64: 20.8 | AE64: -36.3 | AF64: 19.4
B65: D&A / Revenue | C65: % | I65: =I64/I$10 -> -0.0037037037 | J65: =J64/J$10 -> -0.002811245 | K65: =K64/K$10 -> -0.0044138228 | L65: =L64/L$10 -> -0.0069804547 | M65: =M64/M$10 -> -0.0068658378 | N65: =N64/N$10 -> -0.0084985836 | O65: =O64/O$10 -> -0.009673717 | P65: =P64/P$10 -> -0.009673717 | ... X65: =X64/X$10 -> -0.009673717 | AA65: -0.295 | AB65: 0.286 | AC65: -0.222 | AD65: 0.212 | AE65: -0.186 | AF65: 0.176
B67: EBIT
A68: EBIT | B68: EBIT | C68: AUDm | F68: =F56+F64 -> 42 | G68: =G56+G64 -> 45.3 | H68: =H56+H64 -> 44.5 | I68: =I56+I64 -> 52.8 | J68: =J56+J64 -> 70.2 | K68: =K56+K64 -> 82.6 | L68: =L56+L64 -> 52.4 | M68: =M56+M64 -> 40 | N68: =N56+N64 -> 45.7 | O68: =INDEX(Segments!$A:$AJ,MATCH(Annual!$A68,Segments!$A:$A,0),MATCH("1H"&RIGHT(Annual!O$1,2),Segments!$A$3:$AJ$3,0))+INDEX(Segments!$A:$AJ,MATCH(Annual!$A68,Segments!$A:$A,0),MATCH("2H"&RIGHT(Annual!O$1,2),Segments!$A$3:$AJ$3,0)) -> 65.879614 | P68: =INDEX(Segments!$A:$AJ,MATCH(Annual!$A68,Segments!$A:$A,0),MATCH("1H"&RIGHT(Annual!P$1,2),Segments!$A$3:$AJ$3,0))+INDEX(Segments!$A:$AJ,MATCH(Annual!$A68,Segments!$A:$A,0),MATCH("2H"&RIGHT(Annual!P$1,2),Segments!$A$3:$AJ$3,0)) -> 77.021133 | Q68: =INDEX(Segments!$A:$AJ,MATCH(Annual!$A68,Segments!$A:$A,0),MATCH("1H"&RIGHT(Annual!Q$1,2),Segments!$A$3:$AJ$3,0))+INDEX(Segments!$A:$AJ,MATCH(Annual!$A68,Segments!$A:$A,0),MATCH("2H"&RIGHT(Annual!Q$1,2),Segments!$A$3:$AJ$3,0)) -> 88.406108 | R68: =INDEX(Segments!$A:$AJ,MATCH(Annual!$A68,Segments!$A:$A,0),MATCH("1H"&RIGHT(Annual!R$1,2),Segments!$A$3:$AJ$3,0))+INDEX(Segments!$A:$AJ,MATCH(Annual!$A68,Segments!$A:$A,0),MATCH("2H"&RIGHT(Annual!R$1,2),Segments!$A$3:$AJ$3,0)) -> 100.9743 | S68: =INDEX(Segments!$A:$AJ,MATCH(Annual!$A68,Segments!$A:$A,0),MATCH("1H"&RIGHT(Annual!S$1,2),Segments!$A$3:$AJ$3,0))+INDEX(Segments!$A:$AJ,MATCH(Annual!$A68,Segments!$A:$A,0),MATCH("2H"&RIGHT(Annual!S$1,2),Segments!$A$3:$AJ$3,0)) -> 114.03042 | T68: =INDEX(Segments!$A:$AJ,MATCH(Annual!$A68,Segments!$A:$A,0),MATCH("1H"&RIGHT(Annual!T$1,2),Segments!$A$3:$AJ$3,0))+INDEX(Segments!$A:$AJ,MATCH(Annual!$A68,Segments!$A:$A,0),MATCH("2H"&RIGHT(Annual!T$1,2),Segments!$A$3:$AJ$3,0)) -> 128.18017 | U68: =INDEX(Segments!$A:$AJ,MATCH(Annual!$A68,Segments!$A:$A,0),MATCH("1H"&RIGHT(Annual!U$1,2),Segments!$A$3:$AJ$3,0))+INDEX(Segments!$A:$AJ,MATCH(Annual!$A68,Segments!$A:$A,0),MATCH("2H"&RIGHT(Annual!U$1,2),Segments!$A$3:$AJ$3,0)) -> 144.07659 | V68: =INDEX(Segments!$A:$AJ,MATCH(Annual!$A68,Segments!$A:$A,0),MATCH("1H"&RIGHT(Annual!V$1,2),Segments!$A$3:$AJ$3,0))+INDEX(Segments!$A:$AJ,MATCH(Annual!$A68,Segments!$A:$A,0),MATCH("2H"&RIGHT(Annual!V$1,2),Segments!$A$3:$AJ$3,0)) -> 161.94113 | ... X68: =INDEX(Segments!$A:$AJ,MATCH(Annual!$A68,Segments!$A:$A,0),MATCH("1H"&RIGHT(Annual!X$1,2),Segments!$A$3:$AJ$3,0))+INDEX(Segments!$A:$AJ,MATCH(Annual!$A68,Segments!$A:$A,0),MATCH("2H"&RIGHT(Annual!X$1,2),Segments!$A$3:$AJ$3,0)) -> 204.60813 | AA68: -26.4 | AB68: 72.1 | AC68: 0.5 | AD68: 65.6 | AE68: 13.7 | AF68: 66.5
B69: Underlying EBIT Growth | C69: % YoY | J69: =J68/I68-1 -> 0.32954545 | K69: =K68/J68-1 -> 0.17663818 | L69: =L68/K68-1 -> -0.36561743 | M69: =M68/L68-1 -> -0.23664122 | N69: =N68/M68-1 -> 0.1425 | O69: =O68/N68-1 -> 0.44156706 | P69: =P68/O68-1 -> 0.16911937 | Q69: =Q68/P68-1 -> 0.14781624 | ... X69: =X68/W68-1 -> 0.12407214 | AA69: -0.36 | AB69: 0.5 | AC69: -1.02 | AD69: 1.47 | AE69: 25.73 | AF69: -25.52
B70: EBIT Margin | C70: % | J70: =J68/J$10 -> 0.093975904 | K70: =K68/K$10 -> 0.088922381 | L70: =L68/L$10 -> 0.05225369 | M70: =M68/M$10 -> 0.037112637 | N70: =N68/N$10 -> 0.036989073 | O70: =O68/O$10 -> 0.044671681 | P70: =P68/P$10 -> 0.046292983 | Q70: =Q68/Q$10 -> 0.048024798 | ... X70: =X68/X$10 -> 0.05589896 | AA70: -0.225 | AB70: 0.262 | AC70: 0.003 | AD70: 0.04 | AE70: 0.07 | AF70: -0.024
B72: Interest
A73: Interest income | B73: Interest income | C73: AUDm | D73: AR | F73: 2.3 | G73: 2.5 | H73: 2 | I73: 0.9 | J73: 0.8 | K73: 0.3 | L73: 6.2 | M73: 7.6 | N73: 7 | O73: =O77*N197+6 -> 7.274 | P73: =P77*O197+6 -> 7.3307466 | Q73: =Q77*P197+6 -> 7.2606803 | R73: =R77*Q197+6 -> 7.2173189 | S73: =S77*R197+6 -> 7.1993093 | T73: =T77*S197+6 -> 7.2024315 | U73: =U77*T197+6 -> 7.2265936 | V73: =V77*U197+6 -> 7.2724554 | ... X73: =X77*W197+6 -> 7.435815 | AA73: 0 | AB73: 7 | AC73: 0 | AD73: 6.8 | AE73: 0 | AF73: #VALUE!
A74: Interest on lease liabilities | B74: Interest on lease liabilities | M74: -0.1 | N74: -0.2 | O74: =N74*O10/N10 -> -0.23872945 | P74: =O74*P10/O10 -> -0.2693283 | Q74: =P74*Q10/P10 -> -0.29799156 | R74: =Q74*R10/Q10 -> -0.32921263 | S74: =R74*S10/R10 -> -0.36411888 | T74: =S74*T10/S10 -> -0.40099742 | U74: =T74*U10/T10 -> -0.44180403 | V74: =U74*V10/U10 -> -0.48698492 | ... X74: =W74*X10/W10 -> -0.59252462 | AA74: -0.4 | AB74: 0.2 | AC74: -0.5 | AD74: 0.3 | AE74: -0.7 | AF74: 0.4
A75: Interest expense | B75: Interest expense | C75: AUDm | F75: =F76-F73-F74 -> 0 | G75: =G76-G73-G74 -> -0.1 | H75: =H76-H73-H74 -> 0 | I75: =I76-I73-I74 -> -0.1 | J75: =J76-J73-J74 -> -0.2 | K75: =K76-K73-K74 -> -1.1 | L75: =L76-L73-L74 -> -3.2 | M75: =M76-M73-M74 -> -3.6 | N75: =N76-N73-N74 -> -3.9 | O75: =O78*AVERAGE(N217:O217) -> -3.3416364 | P75: =P78*AVERAGE(O217:P217) -> -3.9662118 | Q75: =Q78*AVERAGE(P217:Q217) -> -4.7835897 | R75: =R78*AVERAGE(Q217:R217) -> -5.7016251 | S75: =S78*AVERAGE(R217:S217) -> -6.7328291 | T75: =T78*AVERAGE(S217:T217) -> -7.8906006 | U75: =U78*AVERAGE(T217:U217) -> -9.1898492 | V75: =V78*AVERAGE(U217:V217) -> -10.648381 | ... X75: =X78*AVERAGE(W217:X217) -> -14.126295 | AA75: -9.4 | AB75: 5.5 | AC75: -9.4 | AD75: 5.3 | AE75: -9.4 | AF75: 5.3
A76: Net Interest (underlying) | B76: Net Interest (underlying) | C76: AUDm | D76: AR | F76: 2.3 | G76: 2.4 | H76: 2 | I76: 0.8 | J76: 0.6 | K76: -0.8 | L76: 3 | M76: 3.9 | N76: 2.9 | O76: =SUM(O73:O75) -> 3.6936342 | P76: =SUM(P73:P75) -> 3.0952066 | Q76: =SUM(Q73:Q75) -> 2.1790991 | R76: =SUM(R73:R75) -> 1.1864812 | S76: =SUM(S73:S75) -> 0.1023613 | T76: =SUM(T73:T75) -> -1.0891665 | U76: =SUM(U73:U75) -> -2.4050597 | V76: =SUM(V73:V75) -> -3.8629105 | ... X76: =SUM(X73:X75) -> -7.2830047 | AA76: -9.8 | AB76: 12.7 | AC76: -9.9 | AD76: 12.4 | AE76: -10 | AF76: #VALUE!
B77: Interest income rate | L77: =L73/AVERAGE(K197:L197) -> 0.10333333 | M77: =M73/AVERAGE(L197:M197) -> 0.11930926 | N77: =N73/AVERAGE(M197:N197) -> 0.10678871 | O77: 0.02 | P77: =O77 -> 0.02 | Q77: =P77 -> 0.02 | R77: =Q77 -> 0.02 | S77: =R77 -> 0.02 | T77: =S77 -> 0.02 | U77: =T77 -> 0.02 | V77: =U77 -> 0.02 | W77: =V77 -> 0.02 | X77: =W77 -> 0.02 | AA77: 0 | AC77: 0 | AE77: 0 | AF77: 0.1
B78: Interest expense rate | L78: =L75/AVERAGE(K217:L217) -> -0.072234763 | M78: =M75/AVERAGE(L217:M217) -> -0.079120879 | N78: =N75/AVERAGE(M217:N217) -> -0.079268293 | O78: -0.06 | P78: -0.06 | Q78: -0.06 | R78: -0.06 | S78: -0.06 | T78: -0.06 | U78: -0.06 | V78: -0.06 | W78: -0.06 | X78: -0.06 | AA78: 0.13 | AB78: -0.21 | AC78: 0.13 | AD78: -0.21 | AE78: 0.13 | AF78: -0.21
B80: PBT
A81: PBT | B81: PBT | C81: AUDm | F81: =F68+F76 -> 44.3 | G81: =G68+G76 -> 47.7 | H81: =H68+H76 -> 46.5 | I81: =I68+I76 -> 53.6 | J81: =J68+J76 -> 70.8 | K81: =K68+K76 -> 81.8 | L81: =L68+L76 -> 55.4 | M81: =M68+M76 -> 43.9 | ... X81: =X68+X76 -> 197.32512 | AA81: -26.2 | AB81: 74.8 | AC81: -9.4 | AD81: 78 | AE81: 3.7 | AF81: #VALUE!
B83: Tax
A84: Tax expense | B84: Tax expense | C84: AUDm | D84: Preso | F84: =F88-F81 -> -14.1 | G84: =G88-G81 -> -14.4 | H84: =H88-H81 -> -13.5 | I84: =I88-I81 -> -15.5 | J84: =J88-J81 -> -19.5 | K84: =K88-K81 -> -42.1 | L84: =L88-L81 -> -16.3 | M84: =M88-M81 -> -13.4 | N84: =N88-N81 -> -13.2 | O84: =INDEX(Segments!$A:$AJ,MATCH(Annual!$A84,Segments!$A:$A,0),MATCH("1H"&RIGHT(Annual!O$1,2),Segments!$A$3:$AJ$3,0))+INDEX(Segments!$A:$AJ,MATCH(Annual!$A84,Segments!$A:$A,0),MATCH("2H"&RIGHT(Annual!O$1,2),Segments!$A$3:$AJ$3,0)) -> -20.943593 | P84: =INDEX(Segments!$A:$AJ,MATCH(Annual!$A84,Segments!$A:$A,0),MATCH("1H"&RIGHT(Annual!P$1,2),Segments!$A$3:$AJ$3,0))+INDEX(Segments!$A:$AJ,MATCH(Annual!$A84,Segments!$A:$A,0),MATCH("2H"&RIGHT(Annual!P$1,2),Segments!$A$3:$AJ$3,0)) -> -24.1157 | Q84: =INDEX(Segments!$A:$AJ,MATCH(Annual!$A84,Segments!$A:$A,0),MATCH("1H"&RIGHT(Annual!Q$1,2),Segments!$A$3:$AJ$3,0))+INDEX(Segments!$A:$AJ,MATCH(Annual!$A84,Segments!$A:$A,0),MATCH("2H"&RIGHT(Annual!Q$1,2),Segments!$A$3:$AJ$3,0)) -> -27.264959 | R84: =INDEX(Segments!$A:$AJ,MATCH(Annual!$A84,Segments!$A:$A,0),MATCH("1H"&RIGHT(Annual!R$1,2),Segments!$A$3:$AJ$3,0))+INDEX(Segments!$A:$AJ,MATCH(Annual!$A84,Segments!$A:$A,0),MATCH("2H"&RIGHT(Annual!R$1,2),Segments!$A$3:$AJ$3,0)) -> -30.746999 | S84: =INDEX(Segments!$A:$AJ,MATCH(Annual!$A84,Segments!$A:$A,0),MATCH("1H"&RIGHT(Annual!S$1,2),Segments!$A$3:$AJ$3,0))+INDEX(Segments!$A:$AJ,MATCH(Annual!$A84,Segments!$A:$A,0),MATCH("2H"&RIGHT(Annual!S$1,2),Segments!$A$3:$AJ$3,0)) -> -34.349071 | T84: =INDEX(Segments!$A:$AJ,MATCH(Annual!$A84,Segments!$A:$A,0),MATCH("1H"&RIGHT(Annual!T$1,2),Segments!$A$3:$AJ$3,0))+INDEX(Segments!$A:$AJ,MATCH(Annual!$A84,Segments!$A:$A,0),MATCH("2H"&RIGHT(Annual!T$1,2),Segments!$A$3:$AJ$3,0)) -> -38.247601 | U84: =INDEX(Segments!$A:$AJ,MATCH(Annual!$A84,Segments!$A:$A,0),MATCH("1H"&RIGHT(Annual!U$1,2),Segments!$A$3:$AJ$3,0))+INDEX(Segments!$A:$AJ,MATCH(Annual!$A84,Segments!$A:$A,0),MATCH("2H"&RIGHT(Annual!U$1,2),Segments!$A$3:$AJ$3,0)) -> -42.634001 | V84: =INDEX(Segments!$A:$AJ,MATCH(Annual!$A84,Segments!$A:$A,0),MATCH("1H"&RIGHT(Annual!V$1,2),Segments!$A$3:$AJ$3,0))+INDEX(Segments!$A:$AJ,MATCH(Annual!$A84,Segments!$A:$A,0),MATCH("2H"&RIGHT(Annual!V$1,2),Segments!$A$3:$AJ$3,0)) -> -47.56956 | ... X84: =INDEX(Segments!$A:$AJ,MATCH(Annual!$A84,Segments!$A:$A,0),MATCH("1H"&RIGHT(Annual!X$1,2),Segments!$A$3:$AJ$3,0))+INDEX(Segments!$A:$AJ,MATCH(Annual!$A84,Segments!$A:$A,0),MATCH("2H"&RIGHT(Annual!X$1,2),Segments!$A$3:$AJ$3,0)) -> -59.375294 | AA84: 5 | AB84: -18.2 | AC84: 1.9 | AD84: -22.5 | AE84: -0.7 | AF84: #VALUE!
A85: Underlying Tax rate | B85: Underlying Tax rate | C85: % | F85: =-F84/F81 -> 0.31828442 | G85: =-G84/G81 -> 0.30188679 | H85: =-H84/H81 -> 0.29032258 | I85: =-I84/I81 -> 0.2891791 | J85: =-J84/J81 -> 0.27542373 | K85: =-K84/K81 -> 0.51466993 | L85: =-L84/L81 -> 0.29422383 | M85: =-M84/M81 -> 0.30523918 | ... X85: =-X84/X81 -> 0.30090084 | AA85: 0.19 | AB85: 0.082 | AC85: 0.2 | AD85: 0.1 | AE85: 0.2 | AF85: #VALUE!
B87: NPAT | N87: =(N88/D88)^0.1-1 -> 0.087504802 | Y87: 273.7
A88: Statutory NPAT pre-NCI | B88: Statutory NPAT pre-NCI | C88: AUDm | D88: 15.3 | E88: 22.6 | F88: 30.2 | G88: 33.3 | H88: 33 | I88: 38.1 | J88: 51.3 | K88: 39.7 | L88: 39.1 | M88: 30.5 | N88: 35.4 | O88: =INDEX(Segments!$A:$AJ,MATCH(Annual!$A88,Segments!$A:$A,0),MATCH("1H"&RIGHT(Annual!O$1,2),Segments!$A$3:$AJ$3,0))+INDEX(Segments!$A:$AJ,MATCH(Annual!$A88,Segments!$A:$A,0),MATCH("2H"&RIGHT(Annual!O$1,2),Segments!$A$3:$AJ$3,0)) -> 48.868385 | P88: =INDEX(Segments!$A:$AJ,MATCH(Annual!$A88,Segments!$A:$A,0),MATCH("1H"&RIGHT(Annual!P$1,2),Segments!$A$3:$AJ$3,0))+INDEX(Segments!$A:$AJ,MATCH(Annual!$A88,Segments!$A:$A,0),MATCH("2H"&RIGHT(Annual!P$1,2),Segments!$A$3:$AJ$3,0)) -> 56.269968 | Q88: =INDEX(Segments!$A:$AJ,MATCH(Annual!$A88,Segments!$A:$A,0),MATCH("1H"&RIGHT(Annual!Q$1,2),Segments!$A$3:$AJ$3,0))+INDEX(Segments!$A:$AJ,MATCH(Annual!$A88,Segments!$A:$A,0),MATCH("2H"&RIGHT(Annual!Q$1,2),Segments!$A$3:$AJ$3,0)) -> 63.618239 | R88: =INDEX(Segments!$A:$AJ,MATCH(Annual!$A88,Segments!$A:$A,0),MATCH("1H"&RIGHT(Annual!R$1,2),Segments!$A$3:$AJ$3,0))+INDEX(Segments!$A:$AJ,MATCH(Annual!$A88,Segments!$A:$A,0),MATCH("2H"&RIGHT(Annual!R$1,2),Segments!$A$3:$AJ$3,0)) -> 71.742999 | S88: =INDEX(Segments!$A:$AJ,MATCH(Annual!$A88,Segments!$A:$A,0),MATCH("1H"&RIGHT(Annual!S$1,2),Segments!$A$3:$AJ$3,0))+INDEX(Segments!$A:$AJ,MATCH(Annual!$A88,Segments!$A:$A,0),MATCH("2H"&RIGHT(Annual!S$1,2),Segments!$A$3:$AJ$3,0)) -> 80.147833 | T88: =INDEX(Segments!$A:$AJ,MATCH(Annual!$A88,Segments!$A:$A,0),MATCH("1H"&RIGHT(Annual!T$1,2),Segments!$A$3:$AJ$3,0))+INDEX(Segments!$A:$AJ,MATCH(Annual!$A88,Segments!$A:$A,0),MATCH("2H"&RIGHT(Annual!T$1,2),Segments!$A$3:$AJ$3,0)) -> 89.244402 | U88: =INDEX(Segments!$A:$AJ,MATCH(Annual!$A88,Segments!$A:$A,0),MATCH("1H"&RIGHT(Annual!U$1,2),Segments!$A$3:$AJ$3,0))+INDEX(Segments!$A:$AJ,MATCH(Annual!$A88,Segments!$A:$A,0),MATCH("2H"&RIGHT(Annual!U$1,2),Segments!$A$3:$AJ$3,0)) -> 99.479336 | V88: =INDEX(Segments!$A:$AJ,MATCH(Annual!$A88,Segments!$A:$A,0),MATCH("1H"&RIGHT(Annual!V$1,2),Segments!$A$3:$AJ$3,0))+INDEX(Segments!$A:$AJ,MATCH(Annual!$A88,Segments!$A:$A,0),MATCH("2H"&RIGHT(Annual!V$1,2),Segments!$A$3:$AJ$3,0)) -> 110.99564 | ... X88: =INDEX(Segments!$A:$AJ,MATCH(Annual!$A88,Segments!$A:$A,0),MATCH("1H"&RIGHT(Annual!X$1,2),Segments!$A$3:$AJ$3,0))+INDEX(Segments!$A:$AJ,MATCH(Annual!$A88,Segments!$A:$A,0),MATCH("2H"&RIGHT(Annual!X$1,2),Segments!$A$3:$AJ$3,0)) -> 138.54235 | AA88: -21.7 | AB88: 57.1 | AC88: -7.5 | AD88: 55.5 | AE88: 2.9 | AF88: #VALUE!
A89: Non-controlling Interests | B89: Non-controlling Interests | F89: -0.1 | G89: 0 | H89: 0 | I89: 0 | J89: 0 | K89: -0.9 | L89: -1.8 | M89: -1.5 | N89: -0.4
A90: Statutory NPAT | B90: Statutory NPAT | C90: AUDm | F90: =F88+F89 -> 30.1 | G90: =G88+G89 -> 33.3 | H90: =H88+H89 -> 33 | I90: =I88+I89 -> 38.1 | J90: =J88+J89 -> 51.3 | K90: =K88+K89 -> 38.8 | L90: =L88+L89 -> 37.3 | M90: =M88+M89 -> 29 | N90: =N88+N89 -> 35 | O90: =INDEX(Segments!$A:$AJ,MATCH(Annual!$A90,Segments!$A:$A,0),MATCH("1H"&RIGHT(Annual!O$1,2),Segments!$A$3:$AJ$3,0))+INDEX(Segments!$A:$AJ,MATCH(Annual!$A90,Segments!$A:$A,0),MATCH("2H"&RIGHT(Annual!O$1,2),Segments!$A$3:$AJ$3,0)) -> 48.868385 | P90: =INDEX(Segments!$A:$AJ,MATCH(Annual!$A90,Segments!$A:$A,0),MATCH("1H"&RIGHT(Annual!P$1,2),Segments!$A$3:$AJ$3,0))+INDEX(Segments!$A:$AJ,MATCH(Annual!$A90,Segments!$A:$A,0),MATCH("2H"&RIGHT(Annual!P$1,2),Segments!$A$3:$AJ$3,0)) -> 56.269968 | Q90: =INDEX(Segments!$A:$AJ,MATCH(Annual!$A90,Segments!$A:$A,0),MATCH("1H"&RIGHT(Annual!Q$1,2),Segments!$A$3:$AJ$3,0))+INDEX(Segments!$A:$AJ,MATCH(Annual!$A90,Segments!$A:$A,0),MATCH("2H"&RIGHT(Annual!Q$1,2),Segments!$A$3:$AJ$3,0)) -> 63.618239 | R90: =INDEX(Segments!$A:$AJ,MATCH(Annual!$A90,Segments!$A:$A,0),MATCH("1H"&RIGHT(Annual!R$1,2),Segments!$A$3:$AJ$3,0))+INDEX(Segments!$A:$AJ,MATCH(Annual!$A90,Segments!$A:$A,0),MATCH("2H"&RIGHT(Annual!R$1,2),Segments!$A$3:$AJ$3,0)) -> 71.742999 | S90: =INDEX(Segments!$A:$AJ,MATCH(Annual!$A90,Segments!$A:$A,0),MATCH("1H"&RIGHT(Annual!S$1,2),Segments!$A$3:$AJ$3,0))+INDEX(Segments!$A:$AJ,MATCH(Annual!$A90,Segments!$A:$A,0),MATCH("2H"&RIGHT(Annual!S$1,2),Segments!$A$3:$AJ$3,0)) -> 80.147833 | T90: =INDEX(Segments!$A:$AJ,MATCH(Annual!$A90,Segments!$A:$A,0),MATCH("1H"&RIGHT(Annual!T$1,2),Segments!$A$3:$AJ$3,0))+INDEX(Segments!$A:$AJ,MATCH(Annual!$A90,Segments!$A:$A,0),MATCH("2H"&RIGHT(Annual!T$1,2),Segments!$A$3:$AJ$3,0)) -> 89.244402 | U90: =INDEX(Segments!$A:$AJ,MATCH(Annual!$A90,Segments!$A:$A,0),MATCH("1H"&RIGHT(Annual!U$1,2),Segments!$A$3:$AJ$3,0))+INDEX(Segments!$A:$AJ,MATCH(Annual!$A90,Segments!$A:$A,0),MATCH("2H"&RIGHT(Annual!U$1,2),Segments!$A$3:$AJ$3,0)) -> 99.479336 | V90: =INDEX(Segments!$A:$AJ,MATCH(Annual!$A90,Segments!$A:$A,0),MATCH("1H"&RIGHT(Annual!V$1,2),Segments!$A$3:$AJ$3,0))+INDEX(Segments!$A:$AJ,MATCH(Annual!$A90,Segments!$A:$A,0),MATCH("2H"&RIGHT(Annual!V$1,2),Segments!$A$3:$AJ$3,0)) -> 110.99564 | ... X90: =INDEX(Segments!$A:$AJ,MATCH(Annual!$A90,Segments!$A:$A,0),MATCH("1H"&RIGHT(Annual!X$1,2),Segments!$A$3:$AJ$3,0))+INDEX(Segments!$A:$AJ,MATCH(Annual!$A90,Segments!$A:$A,0),MATCH("2H"&RIGHT(Annual!X$1,2),Segments!$A$3:$AJ$3,0)) -> 138.54235 | AA90: -21.7 | AB90: 56.7 | AC90: -7.5 | AD90: 55.5 | AE90: 2.9 | AF90: #VALUE!
A91: Amortisation of intangibles | B91: Amortisation of intangibles | M91: 2.4 | N91: 2.4 | O91: =INDEX(Segments!$A:$AJ,MATCH(Annual!$A91,Segments!$A:$A,0),MATCH("1H"&RIGHT(Annual!O$1,2),Segments!$A$3:$AJ$3,0))+INDEX(Segments!$A:$AJ,MATCH(Annual!$A91,Segments!$A:$A,0),MATCH("2H"&RIGHT(Annual!O$1,2),Segments!$A$3:$AJ$3,0)) -> 3.3246544 | P91: =INDEX(Segments!$A:$AJ,MATCH(Annual!$A91,Segments!$A:$A,0),MATCH("1H"&RIGHT(Annual!P$1,2),Segments!$A$3:$AJ$3,0))+INDEX(Segments!$A:$AJ,MATCH(Annual!$A91,Segments!$A:$A,0),MATCH("2H"&RIGHT(Annual!P$1,2),Segments!$A$3:$AJ$3,0)) -> 3.7489975 | Q91: =INDEX(Segments!$A:$AJ,MATCH(Annual!$A91,Segments!$A:$A,0),MATCH("1H"&RIGHT(Annual!Q$1,2),Segments!$A$3:$AJ$3,0))+INDEX(Segments!$A:$AJ,MATCH(Annual!$A91,Segments!$A:$A,0),MATCH("2H"&RIGHT(Annual!Q$1,2),Segments!$A$3:$AJ$3,0)) -> 4.1484322 | R91: =INDEX(Segments!$A:$AJ,MATCH(Annual!$A91,Segments!$A:$A,0),MATCH("1H"&RIGHT(Annual!R$1,2),Segments!$A$3:$AJ$3,0))+INDEX(Segments!$A:$AJ,MATCH(Annual!$A91,Segments!$A:$A,0),MATCH("2H"&RIGHT(Annual!R$1,2),Segments!$A$3:$AJ$3,0)) -> 4.5835049 | S91: =INDEX(Segments!$A:$AJ,MATCH(Annual!$A91,Segments!$A:$A,0),MATCH("1H"&RIGHT(Annual!S$1,2),Segments!$A$3:$AJ$3,0))+INDEX(Segments!$A:$AJ,MATCH(Annual!$A91,Segments!$A:$A,0),MATCH("2H"&RIGHT(Annual!S$1,2),Segments!$A$3:$AJ$3,0)) -> 5.0699245 | T91: =INDEX(Segments!$A:$AJ,MATCH(Annual!$A91,Segments!$A:$A,0),MATCH("1H"&RIGHT(Annual!T$1,2),Segments!$A$3:$AJ$3,0))+INDEX(Segments!$A:$AJ,MATCH(Annual!$A91,Segments!$A:$A,0),MATCH("2H"&RIGHT(Annual!T$1,2),Segments!$A$3:$AJ$3,0)) -> 5.5838434 | U91: =INDEX(Segments!$A:$AJ,MATCH(Annual!$A91,Segments!$A:$A,0),MATCH("1H"&RIGHT(Annual!U$1,2),Segments!$A$3:$AJ$3,0))+INDEX(Segments!$A:$AJ,MATCH(Annual!$A91,Segments!$A:$A,0),MATCH("2H"&RIGHT(Annual!U$1,2),Segments!$A$3:$AJ$3,0)) -> 6.1525193 | V91: =INDEX(Segments!$A:$AJ,MATCH(Annual!$A91,Segments!$A:$A,0),MATCH("1H"&RIGHT(Annual!V$1,2),Segments!$A$3:$AJ$3,0))+INDEX(Segments!$A:$AJ,MATCH(Annual!$A91,Segments!$A:$A,0),MATCH("2H"&RIGHT(Annual!V$1,2),Segments!$A$3:$AJ$3,0)) -> 6.7821743 | ... X91: =INDEX(Segments!$A:$AJ,MATCH(Annual!$A91,Segments!$A:$A,0),MATCH("1H"&RIGHT(Annual!X$1,2),Segments!$A$3:$AJ$3,0))+INDEX(Segments!$A:$AJ,MATCH(Annual!$A91,Segments!$A:$A,0),MATCH("2H"&RIGHT(Annual!X$1,2),Segments!$A$3:$AJ$3,0)) -> 8.2530763 | AA91: 0 | AB91: 2.4 | AC91: 0 | AD91: 3 | AE91: 0 | AF91: 3.4
A92: Significant items after tax | B92: Significant items after tax | F92: =F93-F90-F91 -> -5 | G92: =G93-G90-G91 -> -5.2 | H92: =H93-H90-H91 -> -4.4 | I92: =I93-I90-I91 -> -1.8 | J92: =J93-J90-J91 -> -1.7 | K92: =K93-K90-K91 -> 17 | L92: =L93-L90-L91 -> 11 | M92: =M93-M90-M91 -> 4.7 | N92: =N93-N90-N91 -> 3.4 | O92: =INDEX(Segments!$A:$AJ,MATCH(Annual!$A92,Segments!$A:$A,0),MATCH("1H"&RIGHT(Annual!O$1,2),Segments!$A$3:$AJ$3,0))+INDEX(Segments!$A:$AJ,MATCH(Annual!$A92,Segments!$A:$A,0),MATCH("2H"&RIGHT(Annual!O$1,2),Segments!$A$3:$AJ$3,0)) -> 3.9983209 | P92: =INDEX(Segments!$A:$AJ,MATCH(Annual!$A92,Segments!$A:$A,0),MATCH("1H"&RIGHT(Annual!P$1,2),Segments!$A$3:$AJ$3,0))+INDEX(Segments!$A:$AJ,MATCH(Annual!$A92,Segments!$A:$A,0),MATCH("2H"&RIGHT(Annual!P$1,2),Segments!$A$3:$AJ$3,0)) -> 4.5245789 | Q92: =INDEX(Segments!$A:$AJ,MATCH(Annual!$A92,Segments!$A:$A,0),MATCH("1H"&RIGHT(Annual!Q$1,2),Segments!$A$3:$AJ$3,0))+INDEX(Segments!$A:$AJ,MATCH(Annual!$A92,Segments!$A:$A,0),MATCH("2H"&RIGHT(Annual!Q$1,2),Segments!$A$3:$AJ$3,0)) -> 5.0026625 | R92: =INDEX(Segments!$A:$AJ,MATCH(Annual!$A92,Segments!$A:$A,0),MATCH("1H"&RIGHT(Annual!R$1,2),Segments!$A$3:$AJ$3,0))+INDEX(Segments!$A:$AJ,MATCH(Annual!$A92,Segments!$A:$A,0),MATCH("2H"&RIGHT(Annual!R$1,2),Segments!$A$3:$AJ$3,0)) -> 5.5234541 | S92: =INDEX(Segments!$A:$AJ,MATCH(Annual!$A92,Segments!$A:$A,0),MATCH("1H"&RIGHT(Annual!S$1,2),Segments!$A$3:$AJ$3,0))+INDEX(Segments!$A:$AJ,MATCH(Annual!$A92,Segments!$A:$A,0),MATCH("2H"&RIGHT(Annual!S$1,2),Segments!$A$3:$AJ$3,0)) -> 6.1057727 | T92: =INDEX(Segments!$A:$AJ,MATCH(Annual!$A92,Segments!$A:$A,0),MATCH("1H"&RIGHT(Annual!T$1,2),Segments!$A$3:$AJ$3,0))+INDEX(Segments!$A:$AJ,MATCH(Annual!$A92,Segments!$A:$A,0),MATCH("2H"&RIGHT(Annual!T$1,2),Segments!$A$3:$AJ$3,0)) -> 6.7208744 | U92: =INDEX(Segments!$A:$AJ,MATCH(Annual!$A92,Segments!$A:$A,0),MATCH("1H"&RIGHT(Annual!U$1,2),Segments!$A$3:$AJ$3,0))+INDEX(Segments!$A:$AJ,MATCH(Annual!$A92,Segments!$A:$A,0),MATCH("2H"&RIGHT(Annual!U$1,2),Segments!$A$3:$AJ$3,0)) -> 7.4013565 | V92: =INDEX(Segments!$A:$AJ,MATCH(Annual!$A92,Segments!$A:$A,0),MATCH("1H"&RIGHT(Annual!V$1,2),Segments!$A$3:$AJ$3,0))+INDEX(Segments!$A:$AJ,MATCH(Annual!$A92,Segments!$A:$A,0),MATCH("2H"&RIGHT(Annual!V$1,2),Segments!$A$3:$AJ$3,0)) -> 8.1546336 | ... X92: =INDEX(Segments!$A:$AJ,MATCH(Annual!$A92,Segments!$A:$A,0),MATCH("1H"&RIGHT(Annual!X$1,2),Segments!$A$3:$AJ$3,0))+INDEX(Segments!$A:$AJ,MATCH(Annual!$A92,Segments!$A:$A,0),MATCH("2H"&RIGHT(Annual!X$1,2),Segments!$A$3:$AJ$3,0)) -> 9.9137166 | AA92: 0 | AB92: 3.4 | AC92: 0 | AD92: 4.2 | AE92: 0 | AF92: 4.9
A93: Underlying NPATA | B93: Underlying NPATA | C93: AUDm | F93: 25.1 | G93: 28.1 | H93: 28.6 | I93: 36.3 | J93: 49.6 | K93: 55.8 | L93: 48.3 | M93: 36.1 | N93: 40.8 | O93: =INDEX(Segments!$A:$AJ,MATCH(Annual!$A93,Segments!$A:$A,0),MATCH("1H"&RIGHT(Annual!O$1,2),Segments!$A$3:$AJ$3,0))+INDEX(Segments!$A:$AJ,MATCH(Annual!$A93,Segments!$A:$A,0),MATCH("2H"&RIGHT(Annual!O$1,2),Segments!$A$3:$AJ$3,0)) -> 56.19136 | P93: =INDEX(Segments!$A:$AJ,MATCH(Annual!$A93,Segments!$A:$A,0),MATCH("1H"&RIGHT(Annual!P$1,2),Segments!$A$3:$AJ$3,0))+INDEX(Segments!$A:$AJ,MATCH(Annual!$A93,Segments!$A:$A,0),MATCH("2H"&RIGHT(Annual!P$1,2),Segments!$A$3:$AJ$3,0)) -> 64.543544 | Q93: =INDEX(Segments!$A:$AJ,MATCH(Annual!$A93,Segments!$A:$A,0),MATCH("1H"&RIGHT(Annual!Q$1,2),Segments!$A$3:$AJ$3,0))+INDEX(Segments!$A:$AJ,MATCH(Annual!$A93,Segments!$A:$A,0),MATCH("2H"&RIGHT(Annual!Q$1,2),Segments!$A$3:$AJ$3,0)) -> 72.769334 | R93: =INDEX(Segments!$A:$AJ,MATCH(Annual!$A93,Segments!$A:$A,0),MATCH("1H"&RIGHT(Annual!R$1,2),Segments!$A$3:$AJ$3,0))+INDEX(Segments!$A:$AJ,MATCH(Annual!$A93,Segments!$A:$A,0),MATCH("2H"&RIGHT(Annual!R$1,2),Segments!$A$3:$AJ$3,0)) -> 81.849958 | S93: =INDEX(Segments!$A:$AJ,MATCH(Annual!$A93,Segments!$A:$A,0),MATCH("1H"&RIGHT(Annual!S$1,2),Segments!$A$3:$AJ$3,0))+INDEX(Segments!$A:$AJ,MATCH(Annual!$A93,Segments!$A:$A,0),MATCH("2H"&RIGHT(Annual!S$1,2),Segments!$A$3:$AJ$3,0)) -> 91.32353 | T93: =INDEX(Segments!$A:$AJ,MATCH(Annual!$A93,Segments!$A:$A,0),MATCH("1H"&RIGHT(Annual!T$1,2),Segments!$A$3:$AJ$3,0))+INDEX(Segments!$A:$AJ,MATCH(Annual!$A93,Segments!$A:$A,0),MATCH("2H"&RIGHT(Annual!T$1,2),Segments!$A$3:$AJ$3,0)) -> 101.54912 | U93: =INDEX(Segments!$A:$AJ,MATCH(Annual!$A93,Segments!$A:$A,0),MATCH("1H"&RIGHT(Annual!U$1,2),Segments!$A$3:$AJ$3,0))+INDEX(Segments!$A:$AJ,MATCH(Annual!$A93,Segments!$A:$A,0),MATCH("2H"&RIGHT(Annual!U$1,2),Segments!$A$3:$AJ$3,0)) -> 113.03321 | V93: =INDEX(Segments!$A:$AJ,MATCH(Annual!$A93,Segments!$A:$A,0),MATCH("1H"&RIGHT(Annual!V$1,2),Segments!$A$3:$AJ$3,0))+INDEX(Segments!$A:$AJ,MATCH(Annual!$A93,Segments!$A:$A,0),MATCH("2H"&RIGHT(Annual!V$1,2),Segments!$A$3:$AJ$3,0)) -> 125.93245 | ... X93: =INDEX(Segments!$A:$AJ,MATCH(Annual!$A93,Segments!$A:$A,0),MATCH("1H"&RIGHT(Annual!X$1,2),Segments!$A$3:$AJ$3,0))+INDEX(Segments!$A:$AJ,MATCH(Annual!$A93,Segments!$A:$A,0),MATCH("2H"&RIGHT(Annual!X$1,2),Segments!$A$3:$AJ$3,0)) -> 156.70915 | AA93: -21.7 | AB93: 62.5 | AC93: -7.5 | AD93: 59.7 | AE93: 2.9 | AF93: #VALUE!
B94: Underlying NPAT Growth | C94: % YoY | I94: =I93/H93-1 -> 0.26923077 | J94: =J93/I93-1 -> 0.36639118 | K94: =K93/J93-1 -> 0.125 | L94: =L93/K93-1 -> -0.1344086 | M94: =M93/L93-1 -> -0.25258799 | N94: =N93/M93-1 -> 0.13019391 | O94: =O93/N93-1 -> 0.37723921 | P94: =P93/O93-1 -> 0.14863823 | ... X94: =X93/W93-1 -> 0.11596889 | AA94: -0.603 | AB94: 0.733 | AC94: -0.654 | AD94: 0.933 | AE94: -1.39 | AF94: #VALUE!
B95: Underlying NPAT margin | C95: % | I95: =I93/I$10 -> 0.053777778 | J95: =J93/J$10 -> 0.066398929 | K95: =K93/K$10 -> 0.060071052 | L95: =L93/L$10 -> 0.048165138 | M95: =M93/M$10 -> 0.033494155 | N95: =N93/N$10 -> 0.033023068 | O95: =O93/O$10 -> 0.038102265 | P95: =P93/P$10 -> 0.03879342 | ... X95: =X93/X$10 -> 0.042812954 | AA95: -0.185 | AB95: 0.218 | AC95: -0.047 | AD95: 0.082 | AE95: 0.015 | AF95: #VALUE!
O96: 0.38566487 | P96: 0.14780889 | Q96: 0.12671245 | R96: 0.1240675 | S96: 0.11531972 | T96: 0.11148044 | U96: 0.11263001 | V96: 0.11369137 | W96: 0.11467963 | X96: 0.1156023
B97: EPS | O97: =O96-O94 -> 0.0084256592 | P97: =P96-P94 -> -0.0008293356 | Q97: =Q96-Q94 -> -0.00073312796 | R97: =R96-R94 -> -0.00071891819 | S97: =S96-S94 -> -0.00042343997 | T97: =T96-T94 -> -0.00049058601 | U97: =U96-U94 -> -0.00045901639 | V97: =V96-V94 -> -0.00042762434 | ... X97: =X96-X94 -> -0.00036658185
A98: YE Basic Shares Outstanding | B98: YE Basic Shares Outstanding | C98: #m | F98: 215.41 | G98: 216.1 | H98: 216.77 | I98: 267.74 | J98: 268.38 | K98: 269.13 | L98: 270.26 | M98: 270.8 | N98: 270.8 | O98: =N98+O268/Value!$D$4 -> 270.8 | P98: =O98+P268/Value!$D$4 -> 270.8 | Q98: =P98+Q268/Value!$D$4 -> 270.8 | R98: =Q98+R268/Value!$D$4 -> 270.8 | S98: =R98+S268/Value!$D$4 -> 270.8 | T98: =S98+T268/Value!$D$4 -> 270.8 | U98: =T98+U268/Value!$D$4 -> 270.8 | V98: =U98+V268/Value!$D$4 -> 270.8 | ... X98: =W98+X268/Value!$D$4 -> 270.8 | AA98: 1268.61 | AB98: -997.81 | AC98: 1268.61 | AD98: #VALUE! | AE98: 1268.61 | AF98: #VALUE!
B99: Weighted Average Basic Shares Outstanding | C99: #m | F99: 214.96 | G99: 216.1 | H99: 214.81 | I99: 220.15 | J99: 268.29 | K99: 269.02 | L99: 270.1 | M99: 270.3 | N99: 270.8 | O99: =AVERAGE(N98:O98) -> 270.8 | P99: =AVERAGE(O98:P98) -> 270.8 | Q99: =AVERAGE(P98:Q98) -> 270.8 | R99: =AVERAGE(Q98:R98) -> 270.8 | S99: =AVERAGE(R98:S98) -> 270.8 | T99: =AVERAGE(S98:T98) -> 270.8 | U99: =AVERAGE(T98:U98) -> 270.8 | V99: =AVERAGE(U98:V98) -> 270.8 | ... X99: =AVERAGE(W98:X98) -> 270.8 | AA99: 1208.13 | AB99: -937.33 | AC99: 1268.61 | AD99: #VALUE! | AE99: 1268.61 | AF99: #VALUE!
B100: Dilution | C100: #m | F100: 0 | G100: 0 | H100: 1.96 | I100: 2.68 | J100: 3.43 | K100: 3.69 | L100: 4.02 | M100: 3.8 | N100: 5 | O100: 5 | P100: 5 | Q100: 5 | R100: 5 | S100: 5 | T100: 5 | U100: 5 | V100: 5 | W100: 5 | X100: 5 | AA100: 0 | AB100: 5 | AC100: 0 | AD100: 5 | AE100: 0 | AF100: 5
A101: Weighted Average Diluted Shares Outstanding | B101: Weighted Average Diluted Shares Outstanding | C101: #m | F101: 214.96 | G101: 216.1 | H101: 216.77 | I101: 222.83 | J101: 271.71 | K101: 272.71 | L101: 274.12 | M101: 274.1 | N101: 275.8 | O101: =O99+O100 -> 275.8 | P101: =P99+P100 -> 275.8 | Q101: =Q99+Q100 -> 275.8 | R101: =R99+R100 -> 275.8 | S101: =S99+S100 -> 275.8 | T101: =T99+T100 -> 275.8 | U101: =U99+U100 -> 275.8 | V101: =V99+V100 -> 275.8 | ... X101: =X99+X100 -> 275.8 | AA101: 1208.13 | AB101: -932.33 | AC101: 1268.61 | AD101: #VALUE! | AE101: 1268.61 | AF101: #VALUE!
A103: EPSA | B103: Underlying EPSA | C103: AUDps | F103: =F93/F101 -> 0.11676591 | G103: =G93/G101 -> 0.13003239 | H103: =H93/H101 -> 0.13193708 | I103: =I93/I101 -> 0.16290446 | J103: =J93/J101 -> 0.18254757 | K103: =K93/K101 -> 0.20461296 | L103: =L93/L101 -> 0.1762002 | M103: =M93/M101 -> 0.13170376 | ... X103: =X93/X101 -> 0.5681985 | AA103: -0.018 | AB103: 0.166 | AC103: -0.006 | AD103: #VALUE! | AE103: 0.002 | AF103: #VALUE!
B104: EPSA Growth | C104: % YoY | G104: =G103/F103-1 -> 0.11361606 | H104: =H103/G103-1 -> 0.014647764 | I104: =I103/H103-1 -> 0.23471325 | J104: =J103/I103-1 -> 0.12058057 | K104: =K103/J103-1 -> 0.12087474 | L104: =L103/K103-1 -> -0.13886097 | M104: =M103/L103-1 -> -0.25253346 | N104: =N103/M103-1 -> 0.12322752 | ... X104: =X103/W103-1 -> 0.11596889 | AA104: -0.63 | AB104: 0.75 | AC104: -0.67 | AD104: #VALUE! | AE104: -1.39 | AF104: #VALUE!
A105: EPS | B105: Underlying EPS | C105: AUDps | F105: =F90/F101 -> 0.14002605 | G105: =G90/G101 -> 0.15409533 | H105: =H90/H101 -> 0.15223509 | I105: =I90/I101 -> 0.17098236 | J105: =J90/J101 -> 0.18880424 | K105: =K90/K101 -> 0.14227568 | L105: =L90/L101 -> 0.13607179 | M105: =M90/M101 -> 0.1058008 | ... X105: =X90/X101 -> 0.50232905 | AA105: -0.018 | AB105: 0.166 | AC105: -0.006 | AD105: #VALUE! | AE105: 0.002 | AF105: #VALUE!
B106: EPSA Growth | C106: % YoY | G106: =G105/F105-1 -> 0.10047612 | H106: =H105/G105-1 -> -0.012071997 | I106: =I105/H105-1 -> 0.12314688 | J106: =J105/I105-1 -> 0.10423225 | K106: =K105/J105-1 -> -0.24643812 | L106: =L105/K105-1 -> -0.043604671 | M106: =M105/L105-1 -> -0.22246338 | N106: =N105/M105-1 -> 0.19945738 | ... X106: =X105/W105-1 -> 0.11767783 | AA106: -0.63 | AB106: 0.75 | AC106: -0.67 | AD106: #VALUE! | AE106: -1.39 | AF106: #VALUE!
B107: Average Share Price | C107: AUDps | AA107: 0.67 | AB107: #VALUE! | AC107: 0.67 | AD107: #VALUE! | AE107: 0.67 | AF107: #VALUE!
B108: PE multiple | C108: x | AA108: -37.2 | AB108: #VALUE! | AC108: -112.9 | AD108: #VALUE! | AE108: 289.8 | AF108: #VALUE!
B110: Dividends
A111: Dividends | B111: Dividends | C111: AUDps | J111: 0.133 | K111: 0.166 | L111: 0.107 | M111: 0.08 | N111: 0.091 | O111: =O113*O103 -> 0.12532877 | P111: =P113*P103 -> 0.14395741 | Q111: =Q113*Q103 -> 0.16230415 | R111: =R113*R103 -> 0.1825575 | S111: =S113*S103 -> 0.20368729 | T111: =T113*T103 -> 0.22649436 | U111: =U113*U103 -> 0.25210839 | V111: =V113*V103 -> 0.28087874 | ... X111: =X113*X103 -> 0.39773895 | AA111: 0 | AB111: 0.091 | AC111: 0 | AD111: #VALUE! | AE111: 0 | AF111: #VALUE!
B112: Dividends | C112: AUDm | J112: =J111*J99 -> 35.68257 | K112: =K111*K99 -> 44.65732 | L112: =L111*L99 -> 28.9007 | M112: =M111*M99 -> 21.624 | N112: =N111*N99 -> 24.6428 | O112: =O111*O99 -> 33.93903 | P112: =P111*P99 -> 38.983668 | Q112: =Q111*Q99 -> 43.951964 | ... X112: =X111*X99 -> 107.70771 | AA112: 0 | AB112: 24.6 | AC112: 0 | AD112: #VALUE! | AE112: 0 | AF112: #VALUE!
B113: Payout Ratio | C113: % | J113: =J111/J103 -> 0.72857722 | K113: =K111/K103 -> 0.81128781 | L113: =L111/L103 -> 0.60726377 | M113: =M111/M103 -> 0.60742382 | N113: =N111/N103 -> 0.61514216 | O113: =N113 -> 0.61514216 | P113: =O113 -> 0.61514216 | Q113: =P113 -> 0.61514216 | R113: =Q113 -> 0.61514216 | S113: =R113 -> 0.61514216 | T113: =S113 -> 0.61514216 | U113: =T113 -> 0.61514216 | V113: =U113 -> 0.61514216 | W113: =V113 -> 0.61514216 | X113: =Value!$K$9 -> 0.7 | AA113: 0 | AB113: 0.62 | AC113: 0 | AD113: 0.61 | AE113: 0 | AF113: 0.61
...

Sheet Charts
E29: 14.5 | F29: 0.038
E30: 17.7 | F30: 0.053
E32: AFG | F32: Non-Equity brokers
E33: =SUMPRODUCT(E29:E30,F29:F30)/SUM(E29:E30) -> 0.046245342 | F33: =1-E33 -> 0.95375466
S71: Broker growth
U91: 1.31 | V91: =U91^(1/8)-1 -> 0.034329502
U93: FY15 | V93: FY23 | W93: =U93 -> FY15 | X93: =V93 -> FY23
T94: Broker services | U94: 4.42 | V94: 5.74 | W94: 100 | X94: 131 | Y94: =W94-W95 -> 11.312217 | Z94: =X94-X95 -> 23.506969 | AA94: =(Z94-Y94)/100 -> 0.12194751 | AB94: =(1+AA94)^(1/8)-1 -> 0.01448719 | AC94: =(1+AA94) -> 1.1219475
T95: Other | U95: 3.92 | V95: 4.71 | W95: =U95/U$94*100 -> 88.687783 | X95: =V95/V$94*X$94 -> 107.49303 | Y95: =W95-W96 -> 29.411765 | Z95: =X95-X96 -> 64.587108 | AA95: =(Z95-Y95)/100 -> 0.35175343 | AB95: =(1+AA95)^(1/8)-1 -> 0.038394036 | AC95: =(1+AA95) -> 1.3517534
T96: Resi | U96: 2.62 | V96: 1.88 | W96: =U96/U$94*100 -> 59.276018 | X96: =V96/V$94*X$94 -> 42.905923 | Y96: =W96-W97 -> 59.276018 | Z96: =X96-X97 -> 42.905923 | AA96: =(Z96-Y96)/100 -> -0.16370095 | AB96: =(1+AA96)^(1/8)-1 -> -0.022098301 | AC96: =(1+AA96) -> 0.83629905
AC97: =AC94*AC95*AC96 -> 1.2683281
AA100: =1.31^(1/8)-1 -> 0.034329502
V104: 3
V105: -2
V106: 1
V107: 4
V108: 5
V109: -2

Sheet Segments
B1: Segments | D1: 2020 | E1: 2020 | F1: 2021 | G1: 2021 | H1: 2022 | I1: 2022 | J1: 2023 | K1: 2023 | L1: 2024 | M1: 2024 | N1: 2025 | O1: 2025 | P1: 2026 | Q1: 2026 | R1: 2027 | S1: 2027 | T1: 2028 | U1: 2028 | V1: 2029 | W1: 2029 | X1: 2030 | Y1: 2030 | Z1: 2031 | AA1: 2031 | AB1: 2032 | AC1: 2032 | AD1: 2033 | AE1: 2033 | AF1: 2034 | AG1: 2034 | AH1: 2035 | AI1: 2035
D2: Actual ----------> | P2: Forecast -----> | AK2: Seasonality- 5yr averages
C3: Units | D3: 1H20 | E3: 2H20 | F3: 1H21 | G3: 2H21 | H3: 1H22 | I3: 2H22 | J3: 1H23 | K3: 2H23 | L3: 1H24 | M3: 2H24 | N3: 1H25 | O3: 2H25 | P3: 1H26 | Q3: 2H26 | R3: 1H27 | S3: 2H27 | T3: 1H28 | U3: 2H28 | V3: 1H29 | W3: 2H29 | X3: 1H30 | Y3: 2H30 | Z3: 1H31 | AA3: 2H31 | AB3: 1H32 | AC3: 2H32 | AD3: 1H33 | AE3: 2H33 | AF3: 1H34 | AG3: 2H34 | AH3: 1H35 | AI3: 2H35 | AK3: 1H | AL3: 2H
B4: P &L | D4: 43800 | E4: 43983 | F4: 44166 | G4: 44348 | H4: 44531 | I4: 44713 | J4: 44896 | K4: 45078 | L4: 45261 | M4: 45444 | N4: 45627 | O4: 45809
B6: Revenue
A7: Rev-Commission revenue and other income | B7: Commission revenue and other income | C7: AUDm | G7: =INDEX(Annual!$A:$Y,MATCH(Segments!$A7,Annual!$A:$A,0),MATCH(Segments!G$1,Annual!$A$1:$Y$1,0))-F7 -> 656.8 | H7: 419 | I7: =INDEX(Annual!$A:$Y,MATCH(Segments!$A7,Annual!$A:$A,0),MATCH(Segments!I$1,Annual!$A$1:$Y$1,0))-H7 -> 401.1 | J7: 405.4 | K7: =INDEX(Annual!$A:$Y,MATCH(Segments!$A7,Annual!$A:$A,0),MATCH(Segments!K$1,Annual!$A$1:$Y$1,0))-J7 -> 337.4 | L7: 423.2 | M7: =INDEX(Annual!$A:$Y,MATCH(Segments!$A7,Annual!$A:$A,0),MATCH(Segments!M$1,Annual!$A$1:$Y$1,0))-L7 -> 376 | N7: 467.4 | O7: =INDEX(Annual!$A:$Y,MATCH(Segments!$A7,Annual!$A:$A,0),MATCH(Segments!O$1,Annual!$A$1:$Y$1,0))-N7 -> 443.9 | P7: =N7*P114/N114 -> 556.9486 | Q7: =O7*Q114/O114 -> 509.42795 | R7: =P7*R114/P114 -> 614.55178 | S7: =Q7*S114/Q114 -> 562.1457 | T7: =R7*T114/R114 -> 656.47475 | U7: =S7*U114/S114 -> 600.57184 | V7: =T7*V114/T114 -> 700.40599 | W7: =U7*W114/U114 -> 640.83145 | ... AI7: =AG7*AI114/AG114 -> 915.53422 | AM7: 1H25 preso
A8: Rev-Securitisation interest income | B8: Securitisation interest income | C8: AUDm | G8: =INDEX(Annual!$A:$Y,MATCH(Segments!$A8,Annual!$A:$A,0),MATCH(Segments!G$1,Annual!$A$1:$Y$1,0))-F8 -> 90.2 | H8: 50.7 | I8: =INDEX(Annual!$A:$Y,MATCH(Segments!$A8,Annual!$A:$A,0),MATCH(Segments!I$1,Annual!$A$1:$Y$1,0))-H8 -> 58.1 | J8: 119.8 | K8: =INDEX(Annual!$A:$Y,MATCH(Segments!$A8,Annual!$A:$A,0),MATCH(Segments!K$1,Annual!$A$1:$Y$1,0))-J8 -> 140.2 | L8: 139.2 | M8: =INDEX(Annual!$A:$Y,MATCH(Segments!$A8,Annual!$A:$A,0),MATCH(Segments!M$1,Annual!$A$1:$Y$1,0))-L8 -> 139.4 | N8: 158.2 | O8: =INDEX(Annual!$A:$Y,MATCH(Segments!$A8,Annual!$A:$A,0),MATCH(Segments!O$1,Annual!$A$1:$Y$1,0))-N8 -> 166 | P8: =N8*(1+P192) -> 195.8516 | Q8: =O8*(1+Q192) -> 190.9 | R8: =P8*(1+R192) -> 215.43676 | S8: =Q8*(1+S192) -> 209.99 | T8: =R8*(1+T192) -> 228.36297 | U8: =S8*(1+U192) -> 222.5894 | V8: =T8*(1+V192) -> 242.06474 | W8: =U8*(1+W192) -> 235.94476 | ... AI8: =AG8*(1+AI192) -> 334.69216
A9: Rev-Other | B9: Other | C9: AUDm | D9: AR | P9: =P28*P7/P25 -> 7.9846486 | Q9: =Q28*Q7/Q25 -> 13.638384 | R9: =R28*R7/R25 -> 25.089313 | S9: =S28*S7/S25 -> 36.561992 | T9: =T28*T7/T25 -> 62.046749 | U9: =U28*U7/U25 -> 70.79718 | V9: =V28*V7/V25 -> 104.40213 | W9: =W28*W7/W25 -> 110.06191 | ... AI9: =AI28*AI7/AI25 -> 519.47598
A10: Rev-Total Revenue | B10: Total Revenue | C10: AUDm | G10: =INDEX(Annual!$A:$Y,MATCH(Segments!$A10,Annual!$A:$A,0),MATCH(Segments!G$1,Annual!$A$1:$Y$1,0))-F10 -> 747 | H10: =SUM(H7:H9) -> 469.7 | I10: =INDEX(Annual!$A:$Y,MATCH(Segments!$A10,Annual!$A:$A,0),MATCH(Segments!I$1,Annual!$A$1:$Y$1,0))-H10 -> 459.2 | J10: =SUM(J7:J9) -> 525.2 | K10: =INDEX(Annual!$A:$Y,MATCH(Segments!$A10,Annual!$A:$A,0),MATCH(Segments!K$1,Annual!$A$1:$Y$1,0))-J10 -> 477.6 | L10: =SUM(L7:L9) -> 562.4 | M10: =INDEX(Annual!$A:$Y,MATCH(Segments!$A10,Annual!$A:$A,0),MATCH(Segments!M$1,Annual!$A$1:$Y$1,0))-L10 -> 515.4 | N10: =SUM(N7:N9) -> 625.6 | O10: =INDEX(Annual!$A:$Y,MATCH(Segments!$A10,Annual!$A:$A,0),MATCH(Segments!O$1,Annual!$A$1:$Y$1,0))-N10 -> 609.9 | P10: =SUM(P7:P9) -> 760.78485 | Q10: =SUM(Q7:Q9) -> 713.96633 | R10: =SUM(R7:R9) -> 855.07785 | S10: =SUM(S7:S9) -> 808.6977 | T10: =SUM(T7:T9) -> 946.88446 | U10: =SUM(U7:U9) -> 893.95842 | V10: =SUM(V7:V9) -> 1046.8729 | W10: =SUM(W7:W9) -> 986.83813 | ... AI10: =SUM(AI7:AI9) -> 1769.7024
A11: 0 | B11: Growth | C11: % YoY | G11: =G10/E10-1 -> #DIV/0! | H11: =H10/F10-1 -> #DIV/0! | I11: =I10/G10-1 -> -0.38527443 | J11: =J10/H10-1 -> 0.11816053 | K11: =K10/I10-1 -> 0.040069686 | L11: =L10/J10-1 -> 0.07083016 | M11: =M10/K10-1 -> 0.079145729 | N11: =N10/L10-1 -> 0.11237553 | ... AI11: =AI10/AG10-1 -> 0.10273507
A12: 0
A13: 0 | B13: COGS
A14: DC-Commission and other cost of sales | B14: Commission and other cost of sales | C14: AUDm | D14: AR | G14: =INDEX(Annual!$A:$Y,MATCH(Segments!$A14,Annual!$A:$A,0),MATCH(Segments!G$1,Annual!$A$1:$Y$1,0))-F14 -> -598.1 | H14: -382.9 | I14: =INDEX(Annual!$A:$Y,MATCH(Segments!$A14,Annual!$A:$A,0),MATCH(Segments!I$1,Annual!$A$1:$Y$1,0))-H14 -> -358.1 | J14: -370.6 | K14: =INDEX(Annual!$A:$Y,MATCH(Segments!$A14,Annual!$A:$A,0),MATCH(Segments!K$1,Annual!$A$1:$Y$1,0))-J14 -> -308.5 | L14: -385.4 | M14: =INDEX(Annual!$A:$Y,MATCH(Segments!$A14,Annual!$A:$A,0),MATCH(Segments!M$1,Annual!$A$1:$Y$1,0))-L14 -> -341.1 | N14: -428.8 | O14: =INDEX(Annual!$A:$Y,MATCH(Segments!$A14,Annual!$A:$A,0),MATCH(Segments!O$1,Annual!$A$1:$Y$1,0))-N14 -> -403.8 | P14: =P25-P7-P22-P20 -> -504.28037 | Q14: =Q25-Q7-Q22-Q20 -> -456.2932 | R14: =R25-R7-R22-R20 -> -556.43627 | S14: =S25-S7-S22-S20 -> -503.51235 | T14: =T25-T7-T22-T20 -> -594.39477 | U14: =U25-U7-U22-U20 -> -537.93054 | V14: =V25-V7-V22-V20 -> -634.17162 | W14: =W25-W7-W22-W20 -> -573.99096 | ... AI14: =AI25-AI7-AI22-AI20 -> -820.04147
A15: DC-Securitisation and interest expense | B15: Securitisation and interest expense | C15: AUDm | G15: =INDEX(Annual!$A:$Y,MATCH(Segments!$A15,Annual!$A:$A,0),MATCH(Segments!G$1,Annual!$A$1:$Y$1,0))-F15 -> -46.5 | H15: -25.6 | I15: =INDEX(Annual!$A:$Y,MATCH(Segments!$A15,Annual!$A:$A,0),MATCH(Segments!I$1,Annual!$A$1:$Y$1,0))-H15 -> -32.1 | J15: -92.6 | K15: =INDEX(Annual!$A:$Y,MATCH(Segments!$A15,Annual!$A:$A,0),MATCH(Segments!K$1,Annual!$A$1:$Y$1,0))-J15 -> -118 | L15: -122.8 | M15: =INDEX(Annual!$A:$Y,MATCH(Segments!$A15,Annual!$A:$A,0),MATCH(Segments!M$1,Annual!$A$1:$Y$1,0))-L15 -> -123.8 | N15: -139.6 | O15: =INDEX(Annual!$A:$Y,MATCH(Segments!$A15,Annual!$A:$A,0),MATCH(Segments!O$1,Annual!$A$1:$Y$1,0))-N15 -> -143.3 | P15: =P26-P8 -> -178.76284 | Q15: =Q26-Q8 -> -171.02877 | R15: =R26-R8 -> -196.2404 | S15: =S26-S8 -> -188.13164 | T15: =T26-T8 -> -207.64799 | U15: =U26-U8 -> -199.41954 | V15: =V26-V8 -> -220.10687 | W15: =W26-W8 -> -211.38472 | ... AI15: =AI26-AI8 -> -299.85326
A16: DC-Other | B16: Other | C16: AUDm | P16: =P28-P9 -> -7.0402042 | Q16: =Q28-Q9 -> -11.912496 | R16: =R28-R9 -> -22.146303 | S16: =S28-S9 -> -31.964455 | T16: =T28-T9 -> -54.808113 | U16: =U28-U9 -> -61.931525 | V16: =V28-V9 -> -92.285386 | W16: =W28-W9 -> -96.333714 | ... AI16: =AI28-AI9 -> -455.95727
A17: DC-Total COGS | B17: Total COGS | C17: AUDm | G17: =INDEX(Annual!$A:$Y,MATCH(Segments!$A17,Annual!$A:$A,0),MATCH(Segments!G$1,Annual!$A$1:$Y$1,0))-F17 -> -644.6 | H17: =SUM(H14:H16) -> -408.5 | I17: =INDEX(Annual!$A:$Y,MATCH(Segments!$A17,Annual!$A:$A,0),MATCH(Segments!I$1,Annual!$A$1:$Y$1,0))-H17 -> -390.2 | J17: =SUM(J14:J16) -> -463.2 | K17: =INDEX(Annual!$A:$Y,MATCH(Segments!$A17,Annual!$A:$A,0),MATCH(Segments!K$1,Annual!$A$1:$Y$1,0))-J17 -> -426.5 | L17: =SUM(L14:L16) -> -508.2 | M17: =INDEX(Annual!$A:$Y,MATCH(Segments!$A17,Annual!$A:$A,0),MATCH(Segments!M$1,Annual!$A$1:$Y$1,0))-L17 -> -464.9 | N17: =SUM(N14:N16) -> -568.4 | O17: =INDEX(Annual!$A:$Y,MATCH(Segments!$A17,Annual!$A:$A,0),MATCH(Segments!O$1,Annual!$A$1:$Y$1,0))-N17 -> -547.1 | P17: =SUM(P14:P16) -> -690.08342 | Q17: =SUM(Q14:Q16) -> -639.23446 | R17: =SUM(R14:R16) -> -774.82297 | S17: =SUM(S14:S16) -> -723.60845 | T17: =SUM(T14:T16) -> -856.85087 | U17: =SUM(U14:U16) -> -799.2816 | V17: =SUM(V14:V16) -> -946.56387 | W17: =SUM(W14:W16) -> -881.70938 | ... AI17: =SUM(AI14:AI16) -> -1575.852
A18: 0
A19: GP-Gross Profit | B19: Gross Profit | C19: AUDm | G19: =INDEX(Annual!$A:$Y,MATCH(Segments!$A19,Annual!$A:$A,0),MATCH(Segments!G$1,Annual!$A$1:$Y$1,0))-F19 -> 102.4 | H19: =H10+H17 -> 61.2 | I19: =INDEX(Annual!$A:$Y,MATCH(Segments!$A19,Annual!$A:$A,0),MATCH(Segments!I$1,Annual!$A$1:$Y$1,0))-H19 -> 69 | J19: =J10+J17 -> 62 | K19: =INDEX(Annual!$A:$Y,MATCH(Segments!$A19,Annual!$A:$A,0),MATCH(Segments!K$1,Annual!$A$1:$Y$1,0))-J19 -> 51.1 | L19: =L10+L17 -> 54.2 | M19: =INDEX(Annual!$A:$Y,MATCH(Segments!$A19,Annual!$A:$A,0),MATCH(Segments!M$1,Annual!$A$1:$Y$1,0))-L19 -> 50.5 | N19: =N10+N17 -> 57.2 | O19: =INDEX(Annual!$A:$Y,MATCH(Segments!$A19,Annual!$A:$A,0),MATCH(Segments!O$1,Annual!$A$1:$Y$1,0))-N19 -> 62.8 | P19: =P10+P17 -> 70.701424 | Q19: =Q10+Q17 -> 74.731867 | R19: =R10+R17 -> 80.254881 | S19: =S10+S17 -> 85.089247 | T19: =T10+T17 -> 90.033595 | U19: =U10+U17 -> 94.676819 | V19: =V10+V17 -> 100.30899 | W19: =W10+W17 -> 105.12874 | ... AI19: =AI10+AI17 -> 193.85037
A20: DC-Other income | B20: Other income | C20: AUDm | D20: AR | G20: 14.4 | H20: 8.8 | I20: 11.6 | J20: 11.5 | K20: 10.3 | L20: 10.1 | M20: 7.2 | N20: 11 | O20: =INDEX(Annual!$A:$Y,MATCH(Segments!$A20,Annual!$A:$A,0),MATCH(Segments!O$1,Annual!$A$1:$Y$1,0))-N20 -> 8.2 | P20: =P117 -> 11.66 | Q20: =Q117 -> 8.692 | R20: =R117 -> 12.262976 | S20: =S117 -> 9.1417424 | T20: =T117 -> 12.681248 | U20: =U117 -> 9.4541898 | V20: =V117 -> 13.105563 | W20: =W117 -> 9.7710728 | ... AI20: =AI117 -> 11.710117
A21: DC-Gross Profit inc Other income | B21: Gross Profit inc Other income | C21: AUDm | G21: =INDEX(Annual!$A:$Y,MATCH(Segments!$A21,Annual!$A:$A,0),MATCH(Segments!G$1,Annual!$A$1:$Y$1,0))-F21 -> 116.8 | H21: =H19+H20 -> 70 | I21: =INDEX(Annual!$A:$Y,MATCH(Segments!$A21,Annual!$A:$A,0),MATCH(Segments!I$1,Annual!$A$1:$Y$1,0))-H21 -> 80.6 | J21: =J19+J20 -> 73.5 | K21: =INDEX(Annual!$A:$Y,MATCH(Segments!$A21,Annual!$A:$A,0),MATCH(Segments!K$1,Annual!$A$1:$Y$1,0))-J21 -> 61.5 | L21: =L19+L20 -> 64.3 | M21: =INDEX(Annual!$A:$Y,MATCH(Segments!$A21,Annual!$A:$A,0),MATCH(Segments!M$1,Annual!$A$1:$Y$1,0))-L21 -> 57.7 | N21: =N19+N20 -> 68.2 | O21: =INDEX(Annual!$A:$Y,MATCH(Segments!$A21,Annual!$A:$A,0),MATCH(Segments!O$1,Annual!$A$1:$Y$1,0))-N21 -> 71 | P21: =P19+P20 -> 82.361424 | Q21: =Q19+Q20 -> 83.423867 | R21: =R19+R20 -> 92.517857 | S21: =S19+S20 -> 94.23099 | T21: =T19+T20 -> 102.71484 | U21: =U19+U20 -> 104.13101 | V21: =V19+V20 -> 113.41455 | W21: =W19+W20 -> 114.89982 | ... AI21: =AI19+AI20 -> 205.56048
A22: DC-Trail book adjustment | B22: Trail book adjustment | C22: AUDm | D22: Preso | G22: =INDEX(Annual!$A:$Y,MATCH(Segments!$A22,Annual!$A:$A,0),MATCH(Segments!G$1,Annual!$A$1:$Y$1,0))-F22 -> -2.4 | H22: -4.1 | I22: =INDEX(Annual!$A:$Y,MATCH(Segments!$A22,Annual!$A:$A,0),MATCH(Segments!I$1,Annual!$A$1:$Y$1,0))-H22 -> -3.9 | J22: =J29-J21 -> 2.6 | K22: =INDEX(Annual!$A:$Y,MATCH(Segments!$A22,Annual!$A:$A,0),MATCH(Segments!K$1,Annual!$A$1:$Y$1,0))-J22 -> 6.6 | L22: =L29-L21 -> 1.5 | M22: =INDEX(Annual!$A:$Y,MATCH(Segments!$A22,Annual!$A:$A,0),MATCH(Segments!M$1,Annual!$A$1:$Y$1,0))-L22 -> 3.5 | N22: =N29-N21 -> 1.3 | O22: =INDEX(Annual!$A:$Y,MATCH(Segments!$A22,Annual!$A:$A,0),MATCH(Segments!O$1,Annual!$A$1:$Y$1,0))-N22 -> 2.3 | P22: =P118 -> 1.5490654 | Q22: =Q118 -> 2.639523 | R22: =R118 -> 1.7092797 | S22: =S118 -> 2.912672 | T22: =T118 -> 1.8258818 | U22: =U118 -> 3.1117712 | V22: =V118 -> 1.9480697 | W22: =W118 -> 3.3203702 | ... AI22: =AI118 -> 4.7437006
A23: 0
A24: 0 | B24: Gross Profit by segment | N24: =N19/L19-1 -> 0.055350554 | O24: =O19/M19-1 -> 0.24356436 | P24: =P19/N19-1 -> 0.23603888 | Q24: =Q19/O19-1 -> 0.18999789
A25: GP-Distribution | B25: Distribution | C25: AUDm | D25: Preso | H25: NR | J25: 54.5 | K25: 51.3 | L25: 53.9 | M25: 50.5 | N25: 56.5 | O25: =INDEX(Annual!$A:$Y,MATCH(Segments!$A25,Annual!$A:$A,0),MATCH(Segments!O$1,Annual!$A$1:$Y$1,0))-N25 -> 56.8 | P25: =P119 -> 65.87729 | Q25: =Q119 -> 64.46627 | R25: =R119 -> 72.087764 | S25: =S119 -> 70.687769 | T25: =T119 -> 76.587113 | U25: =U119 -> 75.207268 | V25: =V119 -> 81.288003 | W25: =W119 -> 79.931939 | ... AI25: =AI119 -> 111.94657
A26: GP-Manufacturing | B26: Manufacturing | C26: AUDm | J26: 21.6 | K26: 16.8 | L26: 11.9 | M26: 10.7 | N26: 13 | O26: =INDEX(Annual!$A:$Y,MATCH(Segments!$A26,Annual!$A:$A,0),MATCH(Segments!O$1,Annual!$A$1:$Y$1,0))-N26 -> 16.5 | P26: =P134 -> 17.088755 | Q26: =Q134 -> 19.871233 | R26: =R134 -> 19.196362 | S26: =S134 -> 21.858356 | T26: =T134 -> 20.714977 | U26: =U134 -> 23.169857 | V26: =V134 -> 21.957875 | W26: =W134 -> 24.560049 | ... AI26: =AI134 -> 34.838898
A27: GP-Central | B27: Central | C27: AUDm
A28: GP-Inorganic- forecast | B28: Inorganic- forecast | C28: AUDm | P28: =P50/(1-P44) -> 0.94444444 | Q28: =Q50/(1-Q44) -> 1.7258883 | R28: =R50/(1-R44) -> 2.9430108 | S28: =S50/(1-S44) -> 4.5975369 | T28: =T50/(1-T44) -> 7.2386354 | U28: =U50/(1-U44) -> 8.8656545 | V28: =V50/(1-V44) -> 12.116745 | W28: =W50/(1-W44) -> 13.7282 | ... AI28: =AI50/(1-AI44) -> 63.518714
A29: GP-Gross Profit and Other income excluding trail book adjustment | B29: Gross Profit and Other income excluding trail book adjustment | C29: AUDm | D29: Preso | G29: =INDEX(Annual!$A:$Y,MATCH(Segments!$A29,Annual!$A:$A,0),MATCH(Segments!G$1,Annual!$A$1:$Y$1,0))-F29 -> 114.4 | H29: =SUM(H25:H28) -> 0 | I29: =INDEX(Annual!$A:$Y,MATCH(Segments!$A29,Annual!$A:$A,0),MATCH(Segments!I$1,Annual!$A$1:$Y$1,0))-H29 -> 142.6 | J29: =SUM(J25:J28) -> 76.1 | K29: =INDEX(Annual!$A:$Y,MATCH(Segments!$A29,Annual!$A:$A,0),MATCH(Segments!K$1,Annual!$A$1:$Y$1,0))-J29 -> 68.1 | L29: =SUM(L25:L28) -> 65.8 | M29: =INDEX(Annual!$A:$Y,MATCH(Segments!$A29,Annual!$A:$A,0),MATCH(Segments!M$1,Annual!$A$1:$Y$1,0))-L29 -> 61.2 | N29: =SUM(N25:N28) -> 69.5 | O29: =INDEX(Annual!$A:$Y,MATCH(Segments!$A29,Annual!$A:$A,0),MATCH(Segments!O$1,Annual!$A$1:$Y$1,0))-N29 -> 73.3 | P29: =SUM(P25:P28) -> 83.910489 | Q29: =SUM(Q25:Q28) -> 86.06339 | R29: =SUM(R25:R28) -> 94.227136 | S29: =SUM(S25:S28) -> 97.143662 | T29: =SUM(T25:T28) -> 104.54073 | U29: =SUM(U25:U28) -> 107.24278 | V29: =SUM(V25:V28) -> 115.36262 | W29: =SUM(W25:W28) -> 118.22019 | ... AI29: =SUM(AI25:AI28) -> 210.30419
A30: 0 | B30: Growth | C30: % YoY | G30: =G29/E29-1 -> #DIV/0! | H30: =H29/F29-1 -> #DIV/0! | I30: =I29/G29-1 -> 0.2465035 | J30: =J29/H29-1 -> #DIV/0! | K30: =K29/I29-1 -> -0.52244039 | L30: =L29/J29-1 -> -0.13534823 | M30: =M29/K29-1 -> -0.10132159 | N30: =N29/L29-1 -> 0.056231003 | ... AI30: =AI29/AG29-1 -> 0.10124673
P31: 2 | Q31: 2 | R31: 4 | S31: 4 | T31: 4 | U31: 4 | V31: 4 | W31: 4 | X31: 4 | Y31: 4 | Z31: 4 | AA31: 4 | AB31: 4 | AC31: 4 | AD31: 4 | AE31: 4 | AF31: 4 | AG31: 4 | AH31: 4 | AI31: 4
A32: Number of acquired brokers | B32: Number of acquired brokers during period | C32: # | N32: 0 | O32: =INDEX(Annual!$A:$Y,MATCH(Segments!$A32,Annual!$A:$A,0),MATCH(Segments!O$1,Annual!$A$1:$Y$1,0))-N32 -> 2 | P32: 2 | Q32: 2 | R32: 4 | S32: 4 | T32: =R32*1.07 -> 4.28 | U32: =S32*1.07 -> 4.28 | V32: =T32*1.07 -> 4.5796 | W32: =U32*1.07 -> 4.5796 | X32: =V32*1.07 -> 4.900172 | Y32: =W32*1.07 -> 4.900172 | Z32: =X32*1.07 -> 5.243184 | AA32: =Y32*1.07 -> 5.243184 | ... AI32: =AG32*1.07 -> 6.8727447
A33: =Annual!A33 -> Number of acquired brokers cumulative | B33: Number of acquired brokers cumulative | C33: # | N33: 0 | O33: =SUM($N32:O32) -> 2 | P33: =SUM($N32:P32) -> 4 | Q33: =SUM($N32:Q32) -> 6 | R33: =SUM($N32:R32) -> 10 | S33: =SUM($N32:S32) -> 14 | T33: =SUM($N32:T32) -> 18.28 | U33: =SUM($N32:U32) -> 22.56 | V33: =SUM($N32:V32) -> 27.1396 | ... AI33: =SUM($N32:AI32) -> 101.82391
A34: EBITDA per acquired broker | B34: EBITDA per acquired broker- annualised | C34: AUDm | N34: 0 | O34: =INDEX(Annual!$A:$Y,MATCH(Segments!$A34,Annual!$A:$A,0),MATCH(Segments!O$1,Annual!$A$1:$Y$1,0))-N34 -> 0.425 | P34: =O34 -> 0.425 | Q34: =O34*(1+Q180) -> 0.48875 | R34: =P34*(1+R180) -> 0.4675 | S34: =Q34*(1+S180) -> 0.537625 | T34: =R34*(1+T180) -> 0.49555 | U34: =S34*(1+U180) -> 0.5698825 | V34: =T34*(1+V180) -> 0.525283 | W34: =U34*(1+W180) -> 0.60407545 | X34: =V34*(1+X180) -> 0.55679998 | ... AI34: =AG34*(1+AI180) -> 0.85689257
B35: EV/EBITDA multiple of acquired | C35: x | O35: 6.5 | P35: 6.5 | Q35: 6.5 | R35: 6.5 | S35: 6.5 | T35: 6.5 | U35: 6.5 | V35: 6.5 | W35: 6.5 | X35: 6.5 | Y35: 6.5 | Z35: 6.5 | AA35: 6.5 | AB35: 6.5 | AC35: 6.5 | AD35: 6.5 | AE35: 6.5 | AF35: 6.5 | AG35: 6.5 | AH35: 6.5 | AI35: 6.5
A36: =Annual!A277 -> Cash for acquisitions- broker equity | B36: Cash for acquisitions | C36: AUDm | O36: =O32*O35*O34 -> 5.525 | P36: =P32*P35*P34 -> 5.525 | Q36: =Q32*Q35*Q34 -> 6.35375 | R36: =R32*R35*R34 -> 12.155 | S36: =S32*S35*S34 -> 13.97825 | T36: =T32*T35*T34 -> 13.786201 | U36: =U32*U35*U34 -> 15.854131 | V36: =V32*V35*V34 -> 15.636309 | ... AI36: =AI32*AI35*AI34 -> 38.279825
A37: 0
A38: 0 | B38: Operating Expenses
B39: Distribution | L39: =L47-L25 -> -25.8 | M39: =M47-M25 -> -17 | N39: =N47-N25 -> -25.3 | O39: =O47-O25 -> -20.1
B40: Manufacturing | L40: =L48-L26 -> -6.3 | M40: =M48-M26 -> -5.8 | N40: =N48-N26 -> -7.3 | O40: =O48-O26 -> -6.1
B41: Central | L41: =L49-L27 -> -9.7 | M41: =M49-M27 -> -15 | N41: =N49-N27 -> -11.9 | O41: =O49-O27 -> -15.9
A42: Opex-Total Operating Costs | B42: Total Operating Costs | C42: AUDm | G42: =G51-G29 -> -42.1 | H42: =H51-H29 -> 42.5 | I42: =I51-I29 -> -98.4 | J42: =J51-J29 -> -42.3 | K42: =K51-K29 -> -42.5 | L42: =L51-L29 -> -41.8 | M42: =M51-M29 -> -37.8 | N42: =N51-N29 -> -44.5 | O42: =O51-O29 -> -42.1 | P42: =-P29*P44 -> -46.150769 | Q42: =-Q29*Q44 -> -43.677171 | R42: =-R29*R44 -> -50.411518 | S42: =-S29*S44 -> -47.843253 | T42: =-T29*T44 -> -54.361177 | U42: =-U29*U44 -> -51.208428 | V42: =-V29*V44 -> -58.258124 | W42: =-W29*W44 -> -54.676837 | ... AI42: =-AI29*AI44 -> -84.647435
A43: 0 | B43: Growth | C43: % YoY | G43: =G42/E42-1 -> #DIV/0! | H43: =H42/F42-1 -> #DIV/0! | I43: =I42/G42-1 -> 1.3372922 | J43: =J42/H42-1 -> -1.9952941 | K43: =K42/I42-1 -> -0.56808943 | L43: =L42/J42-1 -> -0.011820331 | M43: =M42/K42-1 -> -0.11058824 | N43: =N42/L42-1 -> 0.064593301 | ... AI43: =AI42/AG42-1 -> 0.074549839
A44: 0 | B44: Cost to Income Ratio | C44: % | G44: =-G42/G29 -> 0.36800699 | H44: =-H42/H29 -> #DIV/0! | I44: =-I42/I29 -> 0.69004208 | J44: =-J42/J29 -> 0.55584757 | K44: =-K42/K29 -> 0.62408223 | L44: =-L42/L29 -> 0.63525836 | M44: =-M42/M29 -> 0.61764706 | N44: =-N42/N29 -> 0.64028777 | O44: =-O42/O29 -> 0.57435198 | P44: 0.55 | Q44: 0.5075 | R44: =P44-1.5% -> 0.535 | S44: =Q44-1.5% -> 0.4925 | T44: =R44-1.5% -> 0.52 | U44: =S44-1.5% -> 0.4775 | V44: =T44-1.5% -> 0.505 | W44: =U44-1.5% -> 0.4625 | X44: =V44-1% -> 0.495 | Y44: =W44-1% -> 0.4525 | Z44: =X44-1% -> 0.485 | AA44: =Y44-1% -> 0.4425 | AB44: =Z44-1% -> 0.475 | AC44: =AA44-1% -> 0.4325 | AD44: =AB44-1% -> 0.465 | AE44: =AC44-1% -> 0.4225 | ... AI44: =AG44-1% -> 0.4025
A45: 0
A46: 0 | B46: EBITDA | L46: NR | N46: NR
A47: EBITDA-Distribution | B47: Distribution | C47: AUDm | D47: Preso | H47: NR | J47: NR | L47: =L79+2.5-1.1 -> 28.1 | M47: =INDEX(Annual!$A:$Y,MATCH(Segments!$A47,Annual!$A:$A,0),MATCH(Segments!M$1,Annual!$A$1:$Y$1,0))-L47 -> 33.5 | N47: =N79+3.5-1.2 -> 31.2 | O47: =INDEX(Annual!$A:$Y,MATCH(Segments!$A47,Annual!$A:$A,0),MATCH(Segments!O$1,Annual!$A$1:$Y$1,0))-N47 -> 36.7
A48: EBITDA-Manuracturing | B48: Manufacturing | C48: AUDm | L48: =L80-3 -> 5.6 | M48: =INDEX(Annual!$A:$Y,MATCH(Segments!$A48,Annual!$A:$A,0),MATCH(Segments!M$1,Annual!$A$1:$Y$1,0))-L48 -> 4.9 | N48: =N80-2.7 -> 5.7 | O48: =INDEX(Annual!$A:$Y,MATCH(Segments!$A48,Annual!$A:$A,0),MATCH(Segments!O$1,Annual!$A$1:$Y$1,0))-N48 -> 10.4
A49: EBITDA-Central | B49: Central | C49: AUDm | L49: =L81-L75+1.1 -> -9.7 | M49: =INDEX(Annual!$A:$Y,MATCH(Segments!$A49,Annual!$A:$A,0),MATCH(Segments!M$1,Annual!$A$1:$Y$1,0))-L49 -> -15 | N49: =N81-N75+1.1 -> -11.9 | O49: =INDEX(Annual!$A:$Y,MATCH(Segments!$A49,Annual!$A:$A,0),MATCH(Segments!O$1,Annual!$A$1:$Y$1,0))-N49 -> -15.9
A50: EBITDA-Inorganic- forecast | B50: Inorganic- forecast | P50: =N50*1.07+(N32*N34+O32*O34)/2 -> 0.425 | Q50: =O50*1.07+(O32*O34+P32*P34)/2 -> 0.85 | R50: =P50*1.07+(P32*P34+Q32*Q34)/2 -> 1.3685 | S50: =Q50*1.07+(Q32*Q34+R32*R34)/2 -> 2.33325 | T50: =R50*1.07+(R32*R34+S32*S34)/2 -> 3.474545 | U50: =S50*1.07+(S32*S34+T32*T34)/2 -> 4.6323045 | V50: =T50*1.07+(T32*T34+U32*U34)/2 -> 5.9977887 | W50: =U50*1.07+(U32*U34+V32*V34)/2 -> 7.3789074 | ... AI50: =AG50*1.07+(AG32*AG34+AH32*AH34)/2 -> 37.952432
A51: EBITDA-Underlying EBITDA | B51: Underlying EBITDA | C51: AUDm | D51: Preso | G51: =INDEX(Annual!$A:$Y,MATCH(Segments!$A51,Annual!$A:$A,0),MATCH(Segments!G$1,Annual!$A$1:$Y$1,0))-F51 -> 72.3 | H51: =H68-H64 -> 42.5 | I51: =INDEX(Annual!$A:$Y,MATCH(Segments!$A51,Annual!$A:$A,0),MATCH(Segments!I$1,Annual!$A$1:$Y$1,0))-H51 -> 44.2 | J51: =J68-J64 -> 33.8 | K51: =INDEX(Annual!$A:$Y,MATCH(Segments!$A51,Annual!$A:$A,0),MATCH(Segments!K$1,Annual!$A$1:$Y$1,0))-J51 -> 25.6 | L51: =L68-L64 -> 24 | M51: =INDEX(Annual!$A:$Y,MATCH(Segments!$A51,Annual!$A:$A,0),MATCH(Segments!M$1,Annual!$A$1:$Y$1,0))-L51 -> 23.4 | N51: =N68-N64 -> 25 | O51: =INDEX(Annual!$A:$Y,MATCH(Segments!$A51,Annual!$A:$A,0),MATCH(Segments!O$1,Annual!$A$1:$Y$1,0))-N51 -> 31.2 | P51: =P29+P42 -> 37.75972 | Q51: =Q29+Q42 -> 42.38622 | R51: =R29+R42 -> 43.815618 | S51: =S29+S42 -> 49.300408 | T51: =T29+T42 -> 50.179548 | U51: =U29+U42 -> 56.034353 | V51: =V29+V42 -> 57.104498 | W51: =W29+W42 -> 63.543351 | ... AI51: =AI29+AI42 -> 125.65675
A52: 0 | B52: Growth | C52: % YoY | G52: =G51/E51-1 -> #DIV/0! | H52: =H51/F51-1 -> #DIV/0! | I52: =I51/G51-1 -> -0.38865837 | J52: =J51/H51-1 -> -0.20470588 | K52: =K51/I51-1 -> -0.42081448 | L52: =L51/J51-1 -> -0.28994083 | M52: =M51/K51-1 -> -0.0859375 | N52: =N51/L51-1 -> 0.041666667 | ... AI52: =AI51/AG51-1 -> 0.11999135
A53: 0 | B53: Margin | C53: % | G53: =G51/G$10 -> 0.096787149 | H53: =H51/H$10 -> 0.090483287 | I53: =I51/I$10 -> 0.096254355 | J53: =J51/J$10 -> 0.064356436 | K53: =K51/K$10 -> 0.05360134 | L53: =L51/L$10 -> 0.042674253 | M53: =M51/M$10 -> 0.04540163 | N53: =N51/N$10 -> 0.039961637 | ... AI53: =AI51/AI$10 -> 0.071004455
A54: 0
A55: Share-based payments (employees) | B55: Share-based payments (employees)
A56: EBITDA-EBITDA | B56: EBITDA | C56: AUDm | D56: Preso | H56: =H51 -> 42.5 | I56: =INDEX(Annual!$A:$Y,MATCH(Segments!$A56,Annual!$A:$A,0),MATCH(Segments!I$1,Annual!$A$1:$Y$1,0))-H56 -> 44.2 | J56: =J51 -> 33.8 | K56: =INDEX(Annual!$A:$Y,MATCH(Segments!$A56,Annual!$A:$A,0),MATCH(Segments!K$1,Annual!$A$1:$Y$1,0))-J56 -> 25.6 | L56: =L51 -> 24 | M56: =INDEX(Annual!$A:$Y,MATCH(Segments!$A56,Annual!$A:$A,0),MATCH(Segments!M$1,Annual!$A$1:$Y$1,0))-L56 -> 23.4 | N56: =N51+N55 -> 25 | O56: =INDEX(Annual!$A:$Y,MATCH(Segments!$A56,Annual!$A:$A,0),MATCH(Segments!O$1,Annual!$A$1:$Y$1,0))-N56 -> 31.2 | P56: =P51+P55 -> 37.75972 | Q56: =Q51+Q55 -> 42.38622 | R56: =R51+R55 -> 43.815618 | S56: =S51+S55 -> 49.300408 | T56: =T51+T55 -> 50.179548 | U56: =U51+U55 -> 56.034353 | V56: =V51+V55 -> 57.104498 | W56: =W51+W55 -> 63.543351 | ... AI56: =AI51+AI55 -> 125.65675
A57: 0 | B57: Growth | C57: % YoY | H57: =H56/F56-1 -> #DIV/0! | I57: =I56/G56-1 -> #DIV/0! | J57: =J56/H56-1 -> -0.20470588 | K57: =K56/I56-1 -> -0.42081448 | L57: =L56/J56-1 -> -0.28994083 | M57: =M56/K56-1 -> -0.0859375 | N57: =N56/L56-1 -> 0.041666667 | O57: =O56/M56-1 -> 0.33333333 | ... AI57: =AI56/AG56-1 -> 0.11999135
A58: 0 | B58: Margin | C58: % | H58: =H56/H$10 -> 0.090483287 | I58: =I56/I$10 -> 0.096254355 | J58: =J56/J$10 -> 0.064356436 | K58: =K56/K$10 -> 0.05360134 | L58: =L56/L$10 -> 0.042674253 | M58: =M56/M$10 -> 0.04540163 | N58: =N56/N$10 -> 0.039961637 | O58: =O56/O$10 -> 0.051155927 | ... AI58: =AI56/AI$10 -> 0.071004455
A59: 0
A60: 0 | B60: D&A
A61: D&A-Depreciation | B61: Depreciation | C61: AUDm | D61: Pres
A62: D&A-Depreciation of right of use assets | B62: Depreciation of right of use assets
A63: D&A-Amortisation | B63: Amortisation | C63: AUDm | D63: Preso | N63: -3.3 | O63: =INDEX(Annual!$A:$Y,MATCH(Segments!$A63,Annual!$A:$A,0),MATCH(Segments!O$1,Annual!$A$1:$Y$1,0))-N63 -> -4.6
A64: D&A-D&A | B64: D&A | C64: AUDm | G64: =INDEX(Annual!$A:$Y,MATCH(Segments!$A64,Annual!$A:$A,0),MATCH(Segments!G$1,Annual!$A$1:$Y$1,0))-F64 -> -2.1 | H64: -1.1 | I64: =INDEX(Annual!$A:$Y,MATCH(Segments!$A64,Annual!$A:$A,0),MATCH(Segments!I$1,Annual!$A$1:$Y$1,0))-H64 -> -3 | J64: -3.4 | K64: =INDEX(Annual!$A:$Y,MATCH(Segments!$A64,Annual!$A:$A,0),MATCH(Segments!K$1,Annual!$A$1:$Y$1,0))-J64 -> -3.6 | L64: -3.6 | M64: =INDEX(Annual!$A:$Y,MATCH(Segments!$A64,Annual!$A:$A,0),MATCH(Segments!M$1,Annual!$A$1:$Y$1,0))-L64 -> -3.8 | N64: -4.6 | O64: =INDEX(Annual!$A:$Y,MATCH(Segments!$A64,Annual!$A:$A,0),MATCH(Segments!O$1,Annual!$A$1:$Y$1,0))-N64 -> -5.9 | P64: =P10*P65 -> -7.3596173 | Q64: =Q10*Q65 -> -6.9067082 | R64: =R10*R65 -> -8.2717811 | S64: =S10*S65 -> -7.8231127 | T64: =T10*T65 -> -9.1598923 | U64: =U10*U65 -> -8.6479008 | V64: =V10*V65 -> -10.127152 | W64: =W10*W65 -> -9.5463928 | ... AI64: =AI10*AI65 -> -17.1196
A65: 0 | B65: D&A / Revenue | C65: % | G65: =G64/G$10 -> -0.002811245 | H65: =H64/H$10 -> -0.0023419204 | I65: =I64/I$10 -> -0.006533101 | J65: =J64/J$10 -> -0.0064737243 | K65: =K64/K$10 -> -0.0075376884 | L65: =L64/L$10 -> -0.006401138 | M65: =M64/M$10 -> -0.0073729142 | N65: =N64/N$10 -> -0.0073529412 | O65: =O64/O$10 -> -0.009673717 | P65: =O65 -> -0.009673717 | Q65: =O65 -> -0.009673717 | R65: =P65 -> -0.009673717 | S65: =Q65 -> -0.009673717 | T65: =R65 -> -0.009673717 | U65: =S65 -> -0.009673717 | V65: =T65 -> -0.009673717 | W65: =U65 -> -0.009673717 | X65: =V65 -> -0.009673717 | ... AI65: =AG65 -> -0.009673717
A66: 0
A67: 0 | B67: EBIT
A68: EBIT | B68: EBIT | C68: AUDm | G68: =INDEX(Annual!$A:$Y,MATCH(Segments!$A68,Annual!$A:$A,0),MATCH(Segments!G$1,Annual!$A$1:$Y$1,0))-F68 -> 70.2 | H68: =H82-H76 -> 41.4 | I68: =INDEX(Annual!$A:$Y,MATCH(Segments!$A68,Annual!$A:$A,0),MATCH(Segments!I$1,Annual!$A$1:$Y$1,0))-H68 -> 41.2 | J68: =J82-J76 -> 30.4 | K68: =INDEX(Annual!$A:$Y,MATCH(Segments!$A68,Annual!$A:$A,0),MATCH(Segments!K$1,Annual!$A$1:$Y$1,0))-J68 -> 22 | L68: =L82-L76 -> 20.4 | M68: =INDEX(Annual!$A:$Y,MATCH(Segments!$A68,Annual!$A:$A,0),MATCH(Segments!M$1,Annual!$A$1:$Y$1,0))-L68 -> 19.6 | N68: =N82-N76 -> 20.4 | O68: =INDEX(Annual!$A:$Y,MATCH(Segments!$A68,Annual!$A:$A,0),MATCH(Segments!O$1,Annual!$A$1:$Y$1,0))-N68 -> 25.3 | P68: =P56+P64 -> 30.400103 | Q68: =Q56+Q64 -> 35.479512 | R68: =R56+R64 -> 35.543837 | S68: =S56+S64 -> 41.477296 | T68: =T56+T64 -> 41.019656 | U68: =U56+U64 -> 47.386452 | V68: =V56+V64 -> 46.977346 | W68: =W56+W64 -> 53.996958 | ... AI68: =AI56+AI64 -> 108.53715
A69: 0 | B69: Underlying EBIT Growth | C69: % YoY | G69: =G68/E68-1 -> #DIV/0! | H69: =H68/F68-1 -> #DIV/0! | I69: =I68/G68-1 -> -0.41310541 | J69: =J68/H68-1 -> -0.26570048 | K69: =K68/I68-1 -> -0.46601942 | L69: =L68/J68-1 -> -0.32894737 | M69: =M68/K68-1 -> -0.10909091 | N69: =N68/L68-1 -> 0 | ... AI69: =AI68/AG68-1 -> 0.12276263
A70: 0 | B70: EBIT Margin | C70: % | G70: =G68/G$10 -> 0.093975904 | H70: =H68/H$10 -> 0.088141367 | I70: =I68/I$10 -> 0.089721254 | J70: =J68/J$10 -> 0.057882711 | K70: =K68/K$10 -> 0.046063652 | L70: =L68/L$10 -> 0.036273115 | M70: =M68/M$10 -> 0.038028716 | N70: =N68/N$10 -> 0.032608696 | ... AI70: =AI68/AI$10 -> 0.061330738
A71: 0
A72: 0 | B72: Interest
A73: Interest income | B73: Interest income | C73: AUDm | D73: AR | G73: =INDEX(Annual!$A:$Y,MATCH(Segments!$A73,Annual!$A:$A,0),MATCH(Segments!G$1,Annual!$A$1:$Y$1,0))-F73 -> 0.8 | H73: 0.1 | I73: =INDEX(Annual!$A:$Y,MATCH(Segments!$A73,Annual!$A:$A,0),MATCH(Segments!I$1,Annual!$A$1:$Y$1,0))-H73 -> 0.2 | J73: 2.4 | K73: =INDEX(Annual!$A:$Y,MATCH(Segments!$A73,Annual!$A:$A,0),MATCH(Segments!K$1,Annual!$A$1:$Y$1,0))-J73 -> 3.8 | L73: 4.1 | M73: =INDEX(Annual!$A:$Y,MATCH(Segments!$A73,Annual!$A:$A,0),MATCH(Segments!M$1,Annual!$A$1:$Y$1,0))-L73 -> 3.5 | N73: 3.9 | O73: =INDEX(Annual!$A:$Y,MATCH(Segments!$A73,Annual!$A:$A,0),MATCH(Segments!O$1,Annual!$A$1:$Y$1,0))-N73 -> 3.1 | P73: =INDEX(Annual!$A:$Y,MATCH(Segments!$A73,Annual!$A:$A,0),MATCH(Segments!P$1,Annual!$A$1:$Y$1,0))*0.5 -> 3.637 | Q73: =INDEX(Annual!$A:$Y,MATCH(Segments!$A73,Annual!$A:$A,0),MATCH(Segments!Q$1,Annual!$A$1:$Y$1,0))-P73 -> 3.637 | R73: =INDEX(Annual!$A:$Y,MATCH(Segments!$A73,Annual!$A:$A,0),MATCH(Segments!R$1,Annual!$A$1:$Y$1,0))*0.5 -> 3.6653733 | S73: =INDEX(Annual!$A:$Y,MATCH(Segments!$A73,Annual!$A:$A,0),MATCH(Segments!S$1,Annual!$A$1:$Y$1,0))-R73 -> 3.6653733 | T73: =INDEX(Annual!$A:$Y,MATCH(Segments!$A73,Annual!$A:$A,0),MATCH(Segments!T$1,Annual!$A$1:$Y$1,0))*0.5 -> 3.6303402 | U73: =INDEX(Annual!$A:$Y,MATCH(Segments!$A73,Annual!$A:$A,0),MATCH(Segments!U$1,Annual!$A$1:$Y$1,0))-T73 -> 3.6303402 | V73: =INDEX(Annual!$A:$Y,MATCH(Segments!$A73,Annual!$A:$A,0),MATCH(Segments!V$1,Annual!$A$1:$Y$1,0))*0.5 -> 3.6086595 | W73: =INDEX(Annual!$A:$Y,MATCH(Segments!$A73,Annual!$A:$A,0),MATCH(Segments!W$1,Annual!$A$1:$Y$1,0))-V73 -> 3.6086595 | X73: =INDEX(Annual!$A:$Y,MATCH(Segments!$A73,Annual!$A:$A,0),MATCH(Segments!X$1,Annual!$A$1:$Y$1,0))*0.5 -> 3.5996547 | Y73: =INDEX(Annual!$A:$Y,MATCH(Segments!$A73,Annual!$A:$A,0),MATCH(Segments!Y$1,Annual!$A$1:$Y$1,0))-X73 -> 3.5996547 | Z73: =INDEX(Annual!$A:$Y,MATCH(Segments!$A73,Annual!$A:$A,0),MATCH(Segments!Z$1,Annual!$A$1:$Y$1,0))*0.5 -> 3.6012158 | AA73: =INDEX(Annual!$A:$Y,MATCH(Segments!$A73,Annual!$A:$A,0),MATCH(Segments!AA$1,Annual!$A$1:$Y$1,0))-Z73 -> 3.6012158 | AB73: =INDEX(Annual!$A:$Y,MATCH(Segments!$A73,Annual!$A:$A,0),MATCH(Segments!AB$1,Annual!$A$1:$Y$1,0))*0.5 -> 3.6132968 | AC73: =INDEX(Annual!$A:$Y,MATCH(Segments!$A73,Annual!$A:$A,0),MATCH(Segments!AC$1,Annual!$A$1:$Y$1,0))-AB73 -> 3.6132968 | AD73: =INDEX(Annual!$A:$Y,MATCH(Segments!$A73,Annual!$A:$A,0),MATCH(Segments!AD$1,Annual!$A$1:$Y$1,0))*0.5 -> 3.6362277 | AE73: =INDEX(Annual!$A:$Y,MATCH(Segments!$A73,Annual!$A:$A,0),MATCH(Segments!AE$1,Annual!$A$1:$Y$1,0))-AD73 -> 3.6362277 | AF73: =INDEX(Annual!$A:$Y,MATCH(Segments!$A73,Annual!$A:$A,0),MATCH(Segments!AF$1,Annual!$A$1:$Y$1,0))*0.5 -> 3.6708074 | AG73: =INDEX(Annual!$A:$Y,MATCH(Segments!$A73,Annual!$A:$A,0),MATCH(Segments!AG$1,Annual!$A$1:$Y$1,0))-AF73 -> 3.6708074 | AH73: =INDEX(Annual!$A:$Y,MATCH(Segments!$A73,Annual!$A:$A,0),MATCH(Segments!AH$1,Annual!$A$1:$Y$1,0))*0.5 -> 3.7179075 | AI73: =INDEX(Annual!$A:$Y,MATCH(Segments!$A73,Annual!$A:$A,0),MATCH(Segments!AI$1,Annual!$A$1:$Y$1,0))-AH73 -> 3.7179075
A74: Interest on lease liabilities | B74: Interest on lease liabilities
A75: Interest expense | B75: Interest expense | C75: AUDm | G75: =INDEX(Annual!$A:$Y,MATCH(Segments!$A75,Annual!$A:$A,0),MATCH(Segments!G$1,Annual!$A$1:$Y$1,0))-F75 -> -0.2 | H75: -0.1 | I75: =INDEX(Annual!$A:$Y,MATCH(Segments!$A75,Annual!$A:$A,0),MATCH(Segments!I$1,Annual!$A$1:$Y$1,0))-H75 -> -1 | J75: -1.6 | K75: =INDEX(Annual!$A:$Y,MATCH(Segments!$A75,Annual!$A:$A,0),MATCH(Segments!K$1,Annual!$A$1:$Y$1,0))-J75 -> -1.6 | L75: -1.9 | M75: =INDEX(Annual!$A:$Y,MATCH(Segments!$A75,Annual!$A:$A,0),MATCH(Segments!M$1,Annual!$A$1:$Y$1,0))-L75 -> -1.7 | N75: -2 | O75: =INDEX(Annual!$A:$Y,MATCH(Segments!$A75,Annual!$A:$A,0),MATCH(Segments!O$1,Annual!$A$1:$Y$1,0))-N75 -> -1.9 | P75: =INDEX(Annual!$A:$Y,MATCH(Segments!$A75,Annual!$A:$A,0),MATCH(Segments!P$1,Annual!$A$1:$Y$1,0))*0.5 -> -1.6708182 | Q75: =INDEX(Annual!$A:$Y,MATCH(Segments!$A75,Annual!$A:$A,0),MATCH(Segments!Q$1,Annual!$A$1:$Y$1,0))-P75 -> -1.6708182 | R75: =INDEX(Annual!$A:$Y,MATCH(Segments!$A75,Annual!$A:$A,0),MATCH(Segments!R$1,Annual!$A$1:$Y$1,0))*0.5 -> -1.9831059 | S75: =INDEX(Annual!$A:$Y,MATCH(Segments!$A75,Annual!$A:$A,0),MATCH(Segments!S$1,Annual!$A$1:$Y$1,0))-R75 -> -1.9831059 | T75: =INDEX(Annual!$A:$Y,MATCH(Segments!$A75,Annual!$A:$A,0),MATCH(Segments!T$1,Annual!$A$1:$Y$1,0))*0.5 -> -2.3917948 | U75: =INDEX(Annual!$A:$Y,MATCH(Segments!$A75,Annual!$A:$A,0),MATCH(Segments!U$1,Annual!$A$1:$Y$1,0))-T75 -> -2.3917948 | V75: =INDEX(Annual!$A:$Y,MATCH(Segments!$A75,Annual!$A:$A,0),MATCH(Segments!V$1,Annual!$A$1:$Y$1,0))*0.5 -> -2.8508125 | W75: =INDEX(Annual!$A:$Y,MATCH(Segments!$A75,Annual!$A:$A,0),MATCH(Segments!W$1,Annual!$A$1:$Y$1,0))-V75 -> -2.8508125 | X75: =INDEX(Annual!$A:$Y,MATCH(Segments!$A75,Annual!$A:$A,0),MATCH(Segments!X$1,Annual!$A$1:$Y$1,0))*0.5 -> -3.3664146 | Y75: =INDEX(Annual!$A:$Y,MATCH(Segments!$A75,Annual!$A:$A,0),MATCH(Segments!Y$1,Annual!$A$1:$Y$1,0))-X75 -> -3.3664146 | Z75: =INDEX(Annual!$A:$Y,MATCH(Segments!$A75,Annual!$A:$A,0),MATCH(Segments!Z$1,Annual!$A$1:$Y$1,0))*0.5 -> -3.9453003 | AA75: =INDEX(Annual!$A:$Y,MATCH(Segments!$A75,Annual!$A:$A,0),MATCH(Segments!AA$1,Annual!$A$1:$Y$1,0))-Z75 -> -3.9453003 | AB75: =INDEX(Annual!$A:$Y,MATCH(Segments!$A75,Annual!$A:$A,0),MATCH(Segments!AB$1,Annual!$A$1:$Y$1,0))*0.5 -> -4.5949246 | AC75: =INDEX(Annual!$A:$Y,MATCH(Segments!$A75,Annual!$A:$A,0),MATCH(Segments!AC$1,Annual!$A$1:$Y$1,0))-AB75 -> -4.5949246 | AD75: =INDEX(Annual!$A:$Y,MATCH(Segments!$A75,Annual!$A:$A,0),MATCH(Segments!AD$1,Annual!$A$1:$Y$1,0))*0.5 -> -5.3241905 | AE75: =INDEX(Annual!$A:$Y,MATCH(Segments!$A75,Annual!$A:$A,0),MATCH(Segments!AE$1,Annual!$A$1:$Y$1,0))-AD75 -> -5.3241905 | AF75: =INDEX(Annual!$A:$Y,MATCH(Segments!$A75,Annual!$A:$A,0),MATCH(Segments!AF$1,Annual!$A$1:$Y$1,0))*0.5 -> -6.1431486 | AG75: =INDEX(Annual!$A:$Y,MATCH(Segments!$A75,Annual!$A:$A,0),MATCH(Segments!AG$1,Annual!$A$1:$Y$1,0))-AF75 -> -6.1431486 | AH75: =INDEX(Annual!$A:$Y,MATCH(Segments!$A75,Annual!$A:$A,0),MATCH(Segments!AH$1,Annual!$A$1:$Y$1,0))*0.5 -> -7.0631475 | AI75: =INDEX(Annual!$A:$Y,MATCH(Segments!$A75,Annual!$A:$A,0),MATCH(Segments!AI$1,Annual!$A$1:$Y$1,0))-AH75 -> -7.0631475
A76: Net Interest (underlying) | B76: Net Interest (underlying) | C76: AUDm | D76: AR | G76: =INDEX(Annual!$A:$Y,MATCH(Segments!$A76,Annual!$A:$A,0),MATCH(Segments!G$1,Annual!$A$1:$Y$1,0))-F76 -> 0.6 | H76: =SUM(H73:H75) -> 0 | I76: =INDEX(Annual!$A:$Y,MATCH(Segments!$A76,Annual!$A:$A,0),MATCH(Segments!I$1,Annual!$A$1:$Y$1,0))-H76 -> -0.8 | J76: =SUM(J73:J75) -> 0.8 | K76: =INDEX(Annual!$A:$Y,MATCH(Segments!$A76,Annual!$A:$A,0),MATCH(Segments!K$1,Annual!$A$1:$Y$1,0))-J76 -> 2.2 | L76: =SUM(L73:L75) -> 2.2 | M76: =INDEX(Annual!$A:$Y,MATCH(Segments!$A76,Annual!$A:$A,0),MATCH(Segments!M$1,Annual!$A$1:$Y$1,0))-L76 -> 1.7 | N76: =SUM(N73:N75) -> 1.9 | O76: =INDEX(Annual!$A:$Y,MATCH(Segments!$A76,Annual!$A:$A,0),MATCH(Segments!O$1,Annual!$A$1:$Y$1,0))-N76 -> 1 | P76: =SUM(P73:P75) -> 1.9661818 | Q76: =SUM(Q73:Q75) -> 1.9661818 | R76: =SUM(R73:R75) -> 1.6822674 | S76: =SUM(S73:S75) -> 1.6822674 | T76: =SUM(T73:T75) -> 1.2385453 | U76: =SUM(U73:U75) -> 1.2385453 | V76: =SUM(V73:V75) -> 0.75784693 | W76: =SUM(W73:W75) -> 0.75784693 | ... AI76: =SUM(AI73:AI75) -> -3.34524
A78: 0 | B78: PBT
B79: Distribution | G79: =INDEX(Annual!$A:$Y,MATCH(Segments!$A79,Annual!$A:$A,0),MATCH(Segments!G$1,Annual!$A$1:$Y$1,0))-F79 -> #N/A | H79: 16.4 | I79: =INDEX(Annual!$A:$Y,MATCH(Segments!$A79,Annual!$A:$A,0),MATCH(Segments!I$1,Annual!$A$1:$Y$1,0))-H79 -> #N/A | J79: 25 | K79: =INDEX(Annual!$A:$Y,MATCH(Segments!$A79,Annual!$A:$A,0),MATCH(Segments!K$1,Annual!$A$1:$Y$1,0))-J79 -> #N/A | L79: 26.7 | M79: =INDEX(Annual!$A:$Y,MATCH(Segments!$A79,Annual!$A:$A,0),MATCH(Segments!M$1,Annual!$A$1:$Y$1,0))-L79 -> #N/A | N79: 28.9 | O79: =INDEX(Annual!$A:$Y,MATCH(Segments!$A79,Annual!$A:$A,0),MATCH(Segments!O$1,Annual!$A$1:$Y$1,0))-N79 -> #N/A
B80: Manuracturing | G80: =INDEX(Annual!$A:$Y,MATCH(Segments!$A80,Annual!$A:$A,0),MATCH(Segments!G$1,Annual!$A$1:$Y$1,0))-F80 -> #N/A | H80: 25.4 | I80: =INDEX(Annual!$A:$Y,MATCH(Segments!$A80,Annual!$A:$A,0),MATCH(Segments!I$1,Annual!$A$1:$Y$1,0))-H80 -> #N/A | J80: 18.6 | K80: =INDEX(Annual!$A:$Y,MATCH(Segments!$A80,Annual!$A:$A,0),MATCH(Segments!K$1,Annual!$A$1:$Y$1,0))-J80 -> #N/A | L80: 8.6 | M80: =INDEX(Annual!$A:$Y,MATCH(Segments!$A80,Annual!$A:$A,0),MATCH(Segments!M$1,Annual!$A$1:$Y$1,0))-L80 -> #N/A | N80: 8.4 | O80: =INDEX(Annual!$A:$Y,MATCH(Segments!$A80,Annual!$A:$A,0),MATCH(Segments!O$1,Annual!$A$1:$Y$1,0))-N80 -> #N/A
B81: Central | G81: =INDEX(Annual!$A:$Y,MATCH(Segments!$A81,Annual!$A:$A,0),MATCH(Segments!G$1,Annual!$A$1:$Y$1,0))-F81 -> #N/A | H81: -0.4 | I81: =INDEX(Annual!$A:$Y,MATCH(Segments!$A81,Annual!$A:$A,0),MATCH(Segments!I$1,Annual!$A$1:$Y$1,0))-H81 -> #N/A | J81: -12.3 | K81: =INDEX(Annual!$A:$Y,MATCH(Segments!$A81,Annual!$A:$A,0),MATCH(Segments!K$1,Annual!$A$1:$Y$1,0))-J81 -> #N/A | L81: -12.7 | M81: =INDEX(Annual!$A:$Y,MATCH(Segments!$A81,Annual!$A:$A,0),MATCH(Segments!M$1,Annual!$A$1:$Y$1,0))-L81 -> #N/A | N81: -15 | O81: =INDEX(Annual!$A:$Y,MATCH(Segments!$A81,Annual!$A:$A,0),MATCH(Segments!O$1,Annual!$A$1:$Y$1,0))-N81 -> #N/A
A82: PBT | B82: PBT | C82: AUDm | G82: =INDEX(Annual!$A:$Y,MATCH(Segments!$A82,Annual!$A:$A,0),MATCH(Segments!G$1,Annual!$A$1:$Y$1,0))-F82 -> 70.8 | H82: 41.4 | I82: =INDEX(Annual!$A:$Y,MATCH(Segments!$A82,Annual!$A:$A,0),MATCH(Segments!I$1,Annual!$A$1:$Y$1,0))-H82 -> 40.4 | J82: 31.2 | K82: =INDEX(Annual!$A:$Y,MATCH(Segments!$A82,Annual!$A:$A,0),MATCH(Segments!K$1,Annual!$A$1:$Y$1,0))-J82 -> 24.2 | L82: 22.6 | M82: =INDEX(Annual!$A:$Y,MATCH(Segments!$A82,Annual!$A:$A,0),MATCH(Segments!M$1,Annual!$A$1:$Y$1,0))-L82 -> 21.3 | N82: 22.3 | O82: =INDEX(Annual!$A:$Y,MATCH(Segments!$A82,Annual!$A:$A,0),MATCH(Segments!O$1,Annual!$A$1:$Y$1,0))-N82 -> 26.3 | P82: =P68+P76 -> 32.366285 | Q82: =Q68+Q76 -> 37.445693 | R82: =R68+R76 -> 37.226105 | S82: =S68+S76 -> 43.159563 | T82: =T68+T76 -> 42.258201 | U82: =U68+U76 -> 48.624997 | V82: =V68+V76 -> 47.735193 | W82: =W68+W76 -> 54.754805 | ... AI82: =AI68+AI76 -> 105.19191
A83: 0
A84: 0 | B84: Tax
A85: Tax expense | B85: Tax expense | C85: AUDm | D85: Preso | G85: =INDEX(Annual!$A:$Y,MATCH(Segments!$A85,Annual!$A:$A,0),MATCH(Segments!G$1,Annual!$A$1:$Y$1,0))-F85 -> -19.5 | H85: =H89-H82 -> -11.4 | I85: =INDEX(Annual!$A:$Y,MATCH(Segments!$A85,Annual!$A:$A,0),MATCH(Segments!I$1,Annual!$A$1:$Y$1,0))-H85 -> -30.7 | J85: =J89-J82 -> -8.6 | K85: =INDEX(Annual!$A:$Y,MATCH(Segments!$A85,Annual!$A:$A,0),MATCH(Segments!K$1,Annual!$A$1:$Y$1,0))-J85 -> -7.7 | L85: =L89-L82 -> -7.3 | M85: =INDEX(Annual!$A:$Y,MATCH(Segments!$A85,Annual!$A:$A,0),MATCH(Segments!M$1,Annual!$A$1:$Y$1,0))-L85 -> -6.1 | N85: =N89-N82 -> -6.6 | O85: =INDEX(Annual!$A:$Y,MATCH(Segments!$A85,Annual!$A:$A,0),MATCH(Segments!O$1,Annual!$A$1:$Y$1,0))-N85 -> -6.6 | P85: =-P82*P86 -> -9.7098854 | Q85: =-Q82*Q86 -> -11.233708 | R85: =-R82*R86 -> -11.167831 | S85: =-S82*S86 -> -12.947869 | T85: =-T82*T86 -> -12.67746 | U85: =-U82*U86 -> -14.587499 | V85: =-V82*V86 -> -14.320558 | W85: =-W82*W86 -> -16.426441 | ... AI85: =-AI82*AI86 -> -31.557573
A86: Underlying Tax rate | B86: Underlying Tax rate | C86: % | G86: =-G85/G82 -> 0.27542373 | H86: =-H85/H82 -> 0.27536232 | I86: =-I85/I82 -> 0.75990099 | J86: =-J85/J82 -> 0.27564103 | K86: =-K85/K82 -> 0.31818182 | L86: =-L85/L82 -> 0.32300885 | M86: =-M85/M82 -> 0.28638498 | N86: =-N85/N82 -> 0.29596413 | O86: =-O85/O82 -> 0.25095057 | P86: 0.3 | Q86: 0.3 | R86: 0.3 | S86: 0.3 | T86: 0.3 | U86: 0.3 | V86: 0.3 | W86: 0.3 | X86: 0.3 | Y86: 0.3 | Z86: 0.3 | AA86: 0.3 | AB86: 0.3 | AC86: 0.3 | AD86: 0.3 | AE86: 0.3 | AF86: 0.3 | AG86: 0.3 | AH86: 0.3 | AI86: 0.3
A87: 0
A88: 0 | B88: NPAT
A89: Statutory NPAT pre-NCI | B89: Statutory NPAT pre-NCI | C89: AUDm | G89: 51.3 | H89: 30 | I89: 9.7 | J89: 22.6 | K89: 16.5 | L89: 15.3 | M89: 15.2 | N89: 15.7 | O89: =INDEX(Annual!$A:$Y,MATCH(Segments!$A89,Annual!$A:$A,0),MATCH(Segments!O$1,Annual!$A$1:$Y$1,0))-N89 -> 19.7 | P89: =P82+P85 -> 22.656399 | Q89: =Q82+Q85 -> 26.211985 | R89: =R82+R85 -> 26.058273 | S89: =S82+S85 -> 30.211694 | T89: =T82+T85 -> 29.580741 | U89: =U82+U85 -> 34.037498 | V89: =V82+V85 -> 33.414635 | W89: =W82+W85 -> 38.328363 | ... AI89: =AI82+AI85 -> 73.634338
A90: Non-controlling Interests | B90: Non-controlling Interests | G90: 0 | H90: 0 | I90: -0.9 | J90: -0.8 | K90: -1 | L90: -0.9 | M90: -0.6 | N90: -0.4 | O90: =INDEX(Annual!$A:$Y,MATCH(Segments!$A90,Annual!$A:$A,0),MATCH(Segments!O$1,Annual!$A$1:$Y$1,0))-N90 -> 0 | P90: 0 | Q90: 0 | R90: 0 | S90: 0 | T90: 0 | U90: 0 | V90: 0 | W90: 0 | X90: 0 | Y90: 0 | Z90: 0 | AA90: 0 | AB90: 0 | AC90: 0 | AD90: 0 | AE90: 0 | AF90: 0 | AG90: 0 | AH90: 0 | AI90: 0
A91: Statutory NPAT | B91: Statutory NPAT | C91: AUDm | G91: 51.3 | H91: =H89+H90 -> 30 | I91: 8.7 | J91: =J89+J90 -> 21.8 | K91: 15.4 | L91: =L89+L90 -> 14.4 | M91: 14.6 | N91: =N89+N90 -> 15.3 | O91: =INDEX(Annual!$A:$Y,MATCH(Segments!$A91,Annual!$A:$A,0),MATCH(Segments!O$1,Annual!$A$1:$Y$1,0))-N91 -> 19.7 | P91: =P89+P90 -> 22.656399 | Q91: =Q89+Q90 -> 26.211985 | R91: =R89+R90 -> 26.058273 | S91: =S89+S90 -> 30.211694 | T91: =T89+T90 -> 29.580741 | U91: =U89+U90 -> 34.037498 | V91: =V89+V90 -> 33.414635 | W91: =W89+W90 -> 38.328363 | ... AI91: =AI89+AI90 -> 73.634338
A92: Amortisation of intangibles | B92: Amortisation of intangibles | N92: 1.2 | O92: =INDEX(Annual!$A:$Y,MATCH(Segments!$A92,Annual!$A:$A,0),MATCH(Segments!O$1,Annual!$A$1:$Y$1,0))-N92 -> 1.2 | P92: =N92*P64/N64 -> 1.9199002 | Q92: =O92*Q64/O64 -> 1.4047542 | R92: =P92*R64/P64 -> 2.157856 | S92: =Q92*S64/Q64 -> 1.5911416 | T92: =R92*T64/R64 -> 2.3895371 | U92: =S92*U64/S64 -> 1.7588951 | V92: =T92*V64/T64 -> 2.6418657 | W92: =U92*W64/U64 -> 1.9416392 | ... AI92: =AG92*AI64/AG64 -> 3.4819525
A93: Significant items after tax | B93: Significant items after tax | G93: =INDEX(Annual!$A:$Y,MATCH(Segments!$A93,Annual!$A:$A,0),MATCH(Segments!G$1,Annual!$A$1:$Y$1,0))-F93 -> -1.7 | H93: =H94-H92-H91 -> -4 | I93: =INDEX(Annual!$A:$Y,MATCH(Segments!$A93,Annual!$A:$A,0),MATCH(Segments!I$1,Annual!$A$1:$Y$1,0))-H93 -> 21 | J93: =J94-J92-J91 -> 3.8 | K93: =INDEX(Annual!$A:$Y,MATCH(Segments!$A93,Annual!$A:$A,0),MATCH(Segments!K$1,Annual!$A$1:$Y$1,0))-J93 -> 7.2 | L93: =L94-L92-L91 -> 3.5 | M93: =INDEX(Annual!$A:$Y,MATCH(Segments!$A93,Annual!$A:$A,0),MATCH(Segments!M$1,Annual!$A$1:$Y$1,0))-L93 -> 1.2 | N93: =N94-N92-N91 -> 0.4 | O93: =INDEX(Annual!$A:$Y,MATCH(Segments!$A93,Annual!$A:$A,0),MATCH(Segments!O$1,Annual!$A$1:$Y$1,0))-N93 -> 3 | P93: =N93*P10/N10 -> 0.48643532 | Q93: =O93*Q10/O10 -> 3.5118855 | R93: =P93*R10/P10 -> 0.54672497 | S93: =Q93*S10/Q10 -> 3.9778539 | T93: =R93*T10/R10 -> 0.60542485 | U93: =S93*U10/S10 -> 4.3972377 | V93: =T93*V10/T10 -> 0.66935605 | W93: =U93*W10/U10 -> 4.854098 | ... AI93: =AG93*AI10/AG10 -> 8.7048813
A94: Underlying NPATA | B94: Underlying NPATA | C94: AUDm | G94: 49.6 | H94: 26 | I94: 29.8 | J94: 25.6 | K94: 22.7 | L94: 17.9 | M94: 18.2 | N94: 16.9 | O94: =INDEX(Annual!$A:$Y,MATCH(Segments!$A94,Annual!$A:$A,0),MATCH(Segments!O$1,Annual!$A$1:$Y$1,0))-N94 -> 23.9 | P94: =P91+P92+P93 -> 25.062735 | Q94: =Q91+Q92+Q93 -> 31.128625 | R94: =R91+R92+R93 -> 28.762854 | S94: =S91+S92+S93 -> 35.78069 | T94: =T91+T92+T93 -> 32.575703 | U94: =U91+U92+U93 -> 40.193631 | V94: =V91+V92+V93 -> 36.725857 | W94: =W91+W92+W93 -> 45.124101 | ... AI94: =AI91+AI92+AI93 -> 85.821171
A95: 0 | B95: Underlying NPAT Growth | C95: % YoY | I95: =I94/G94-1 -> -0.39919355 | J95: =J94/H94-1 -> -0.015384615 | K95: =K94/I94-1 -> -0.23825503 | L95: =L94/J94-1 -> -0.30078125 | M95: =M94/K94-1 -> -0.19823789 | N95: =N94/L94-1 -> -0.055865922 | O95: =O94/M94-1 -> 0.31318681 | P95: =P94/N94-1 -> 0.48300206 | ... AI95: =AI94/AG94-1 -> 0.11471083
A96: 0 | B96: Underlying NPAT margin | C96: % | G96: =G94/G$10 -> 0.066398929 | H96: =H94/H$10 -> 0.055354482 | I96: =I94/I$10 -> 0.06489547 | J96: =J94/J$10 -> 0.048743336 | K96: =K94/K$10 -> 0.047529313 | L96: =L94/L$10 -> 0.031827881 | M96: =M94/M$10 -> 0.035312379 | N96: =N94/N$10 -> 0.027014066 | ... AI96: =AI94/AI$10 -> 0.048494692
A97: 0
A98: 0 | B98: Operating metrics
A99: 0
A100: 0 | B100: Distribution
A101: 0
A102: 0 | B102: Settlements
...

Sheet IRR
D2: EBITDA | E2: =Segments!P34 -> 0.425
D3: EV/EBITDA capex | E3: 12
D4: DA/Sales | E4: =Segments!P65 -> -0.009673717
D5: EBITDA margin | E5: =Segments!O47/Segments!O7 -> 0.082676278
D6: Tax rate | E6: 0.3
D7: WACC | E7: 0.1
D8: Growth rate nominal | E8: 0.06
D9: Terminal growth rate nominal | E9: 0.025
E11: 0 | F11: 1 | G11: 2 | H11: 3 | I11: 4 | J11: 5 | K11: 6 | L11: 7 | M11: 8 | N11: 9 | O11: 10 | P11: 11 | Q11: 12 | R11: 13 | S11: 14 | T11: 15 | U11: 16 | V11: 17 | W11: 18 | X11: 19 | Y11: 20 | Z11: Terminal
D12: Rev | F12: =F13/$E$5 -> 5.1405313 | G12: =G13/$E$5 -> 5.4489632 | H12: =H13/$E$5 -> 5.775901 | I12: =I13/$E$5 -> 6.1224551 | J12: =J13/$E$5 -> 6.4898024 | K12: =K13/$E$5 -> 6.8791905 | L12: =L13/$E$5 -> 7.2919419 | M12: =M13/$E$5 -> 7.7294585 | ... Y12: =Y13/$E$5 -> 15.553189
D13: EBITDA | F13: =$E$2 -> 0.425 | G13: =F13*(1+$E$8) -> 0.4505 | H13: =G13*(1+$E$8) -> 0.47753 | I13: =H13*(1+$E$8) -> 0.5061818 | J13: =I13*(1+$E$8) -> 0.53655271 | K13: =J13*(1+$E$8) -> 0.56874587 | L13: =K13*(1+$E$8) -> 0.60287062 | M13: =L13*(1+$E$8) -> 0.63904286 | N13: =M13*(1+$E$8) -> 0.67738543 | ... Y13: =X13*(1+$E$8) -> 1.2858798
D14: DA | F14: =F12*$E$4 -> -0.049728045 | G14: =G12*$E$4 -> -0.052711728 | H14: =H12*$E$4 -> -0.055874432 | I14: =I12*$E$4 -> -0.059226898 | J14: =J12*$E$4 -> -0.062780512 | K14: =K12*$E$4 -> -0.066547342 | L14: =L12*$E$4 -> -0.070540183 | M14: =M12*$E$4 -> -0.074772594 | ... Y14: =Y12*$E$4 -> -0.15045715
D15: EBIT | F15: =F13+F14 -> 0.37527195 | G15: =G13+G14 -> 0.39778827 | H15: =H13+H14 -> 0.42165557 | I15: =I13+I14 -> 0.4469549 | J15: =J13+J14 -> 0.4737722 | K15: =K13+K14 -> 0.50219853 | L15: =L13+L14 -> 0.53233044 | M15: =M13+M14 -> 0.56427027 | ... Y15: =Y13+Y14 -> 1.1354226
D16: Tax | F16: =-$E$6*F15 -> -0.11258159 | G16: =-$E$6*G15 -> -0.11933648 | H16: =-$E$6*H15 -> -0.12649667 | I16: =-$E$6*I15 -> -0.13408647 | J16: =-$E$6*J15 -> -0.14213166 | K16: =-$E$6*K15 -> -0.15065956 | L16: =-$E$6*L15 -> -0.15969913 | M16: =-$E$6*M15 -> -0.16928108 | ... Y16: =-$E$6*Y15 -> -0.34062679
D17: Capex | E17: =-E2*E3 -> -5.1 | F17: =F14 -> -0.049728045 | G17: =G14 -> -0.052711728 | H17: =H14 -> -0.055874432 | I17: =I14 -> -0.059226898 | J17: =J14 -> -0.062780512 | K17: =K14 -> -0.066547342 | L17: =L14 -> -0.070540183 | M17: =M14 -> -0.074772594 | ... Y17: =Y14 -> -0.15045715
D18: FCF | E18: =E13+E16+E17 -> -5.1 | F18: =F13+F16+F17 -> 0.26269037 | G18: =G13+G16+G17 -> 0.27845179 | H18: =H13+H16+H17 -> 0.2951589 | I18: =I13+I16+I17 -> 0.31286843 | J18: =J13+J16+J17 -> 0.33164054 | K18: =K13+K16+K17 -> 0.35153897 | L18: =L13+L16+L17 -> 0.37263131 | ... Y18: =Y13+Y16+Y17 -> 0.79479585 | Z18: =Y18*(1+E9)/(E7-E9) -> 10.86221
D19: NPV | E19: =NPV($E$7,E18:Z18) -> -0.17788148
D20: IRR | E20: =IRR(E18:Z18,0.1) -> 0.096660154

Sheet Vs cons
E8: FY25 | F8: FY26 | G8: FY27 | H8: FY28
D9: NPAT
D10: MQG | E10: 35 | F10: 43.6 | G10: 49.3 | H10: 53.1
D11: Citi | E11: 35 | F11: 46.6 | G11: 54.8 | H11: 62.1
D12: Avg | E12: =AVERAGE(E10:E11) -> 35 | F12: =AVERAGE(F10:F11) -> 45.1 | G12: =AVERAGE(G10:G11) -> 52.05 | H12: =AVERAGE(H10:H11) -> 57.6
D14: NPAT Adj
D15: MQG | E15: 38.2 | F15: 46 | G15: 51.7 | H15: 55.5
D16: Citi
D17: Avg | E17: =AVERAGE(E15:E16) -> 38.2 | F17: =AVERAGE(F15:F16) -> 46 | G17: =AVERAGE(G15:G16) -> 51.7 | H17: =AVERAGE(H15:H16) -> 55.5
D21: EBITDA
D22: MQG | E22: 57.1 | F22: 73.9 | G22: 83 | H22: 88.8 | O22: =E8 -> FY25 | P22: FY26E | Q22: FY27E | R22: FY28E | U22: =O22 -> FY25 | V22: =P22 -> FY26E | W22: =Q22 -> FY27E | X22: =R22 -> FY28E
D23: Citi | E23: =E33+E39 -> 53.4 | F23: =F33+F39 -> 72.3 | G23: =G33+G39 -> 84.4 | H23: =H33+H39 -> 94.5 | N23: Gross Profit (AUDm) | T23: NPAT (AUDm)
D24: Avg | E24: =AVERAGE(E22:E23) -> 55.25 | F24: =AVERAGE(F22:F23) -> 73.1 | G24: =AVERAGE(G22:G23) -> 83.7 | H24: =AVERAGE(H22:H23) -> 91.65 | N24: Consensus | O24: =E29 -> 120 | P24: =F29 -> 136.4 | Q24: =G29 -> 150.7 | R24: =H29 -> 161.9 | T24: Consensus | U24: =E12 -> 35 | V24: =F12 -> 45.1 | W24: =G12 -> 52.05 | X24: =H12 -> 57.6
N25: Forecast | O25: =Value!R29 -> 120 | P25: =Value!S29 -> 145.43329 | Q25: =Value!T29 -> 165.34413 | R25: =Value!U29 -> 184.71041 | T25: Forecast | U25: =Value!K24 -> 35 | V25: =Value!L24 -> 48.868385 | W25: =Value!M24 -> 56.269968 | X25: =Value!N24 -> 63.618239
D26: GP exc other income | N26: Difference | P26: =P25/P24-1 -> 0.066226476 | Q26: =Q25/Q24-1 -> 0.097174044 | R26: =R25/R24-1 -> 0.14089199 | T26: Difference | V26: =V25/V24-1 -> 0.083556201 | W26: =W25/W24-1 -> 0.081075265 | X26: =X25/X24-1 -> 0.10448331
D27: MQG | F27: 137.4 | G27: 150.4 | H27: 160.2
D28: Citi | E28: =120 -> 120 | F28: =135.4 -> 135.4 | G28: =151 -> 151 | H28: =163.6 -> 163.6 | J28: =G28/F28-1 -> 0.11521418 | N28: EBITDA (AUDm)
D29: Avg | E29: =AVERAGE(E27:E28) -> 120 | F29: =AVERAGE(F27:F28) -> 136.4 | G29: =AVERAGE(G27:G28) -> 150.7 | H29: =AVERAGE(H27:H28) -> 161.9 | N29: Consensus | O29: =E24 -> 55.25 | P29: =F24 -> 73.1 | Q29: =G24 -> 83.7 | R29: =H24 -> 91.65
F30: =F29/E29-1 -> 0.13666667 | G30: =G29/F29-1 -> 0.10483871 | H30: =H29/G29-1 -> 0.074319841 | N30: Forecast | O30: =Value!R24 -> 56.2 | P30: =Value!S24 -> 80.14594 | Q30: =Value!T24 -> 93.116027 | R30: =Value!U24 -> 106.2139
D31: EBIT | N31: Difference | P31: =P30/P29-1 -> 0.096387688 | Q31: =Q30/Q29-1 -> 0.11249733 | R31: =R30/R29-1 -> 0.15890781
D32: MQG | E32: 46.6 | F32: 61.3 | G32: 70.4 | H32: 76.1
D33: Citi | E33: 42.9 | F33: 59.7 | G33: 71.8 | H33: 81.8
D34: Avg | E34: =AVERAGE(E32:E33) -> 44.75 | F34: =AVERAGE(F32:F33) -> 60.5 | G34: =AVERAGE(G32:G33) -> 71.1 | H34: =AVERAGE(H32:H33) -> 78.95
D36: DA
D37: MQG | E37: =E22-E32 -> 10.5 | F37: =F22-F32 -> 12.6 | G37: =G22-G32 -> 12.6 | H37: =H22-H32 -> 12.7
D38: Citi | P38: =P24/O24-1 -> 0.13666667 | Q38: =Q24/P24-1 -> 0.10483871
D39: Avg | E39: =AVERAGE(E37:E38) -> 10.5 | F39: =AVERAGE(F37:F38) -> 12.6 | G39: =AVERAGE(G37:G38) -> 12.6 | H39: =AVERAGE(H37:H38) -> 12.7 | P39: =P25/O25-1 -> 0.21194409 | Q39: =Q25/P25-1 -> 0.13690701

Sheet ABS Resi Refi
A1: Value of refinanced loan commitments, seasonally adjusted and trend, Australia
B2: Owner occupier, external refinancing (seasadj) ($b) | C2: Owner occupier, internal refinancing (seasadj) ($b) | D2: Investor, external refinancing (seasadj) ($b) | E2: Investor, internal refinancing (seasadj) ($b) | F2: Owner occupier, external refinancing (trend) ($b) | G2: Owner occupier, internal refinancing (trend) ($b) | H2: Investor, external refinancing (trend) ($b) | I2: Investor, internal refinancing (trend) ($b) | J2: Total external
A3: 42156 | B3: 15.434 | C3: NA | D3: 12.124 | E3: NA | F3: 15.696 | G3: NA | H3: 11.674 | I3: NA | J3: =B3+D3 -> 27.558
A4: 42248 | B4: 16.84 | C4: NA | D4: 9.875 | E4: NA | F4: 16.883 | G4: NA | H4: 10.441 | I4: NA | J4: =B4+D4 -> 26.715
A5: 42339 | B5: 18.367 | C5: NA | D5: 9.523 | E5: NA | F5: 17.839 | G5: NA | H5: 9.689 | I5: NA | J5: =B5+D5 -> 27.89
A6: 42430 | B6: 17.765 | C6: NA | D6: 9.924 | E6: NA | F6: 18.394 | G6: NA | H6: 9.843 | I6: NA | J6: =B6+D6 -> 27.689
A7: 42522 | B7: 18.822 | C7: NA | D7: 10.336 | E7: NA | F7: 18.358 | G7: NA | H7: 10.302 | I7: NA | J7: =B7+D7 -> 29.158
A8: 42614 | B8: 17.917 | C8: NA | D8: 10.751 | E8: NA | F8: 17.877 | G8: NA | H8: 10.407 | I8: NA | J8: =B8+D8 -> 28.668
A9: 42705 | B9: 16.905 | C9: NA | D9: 9.922 | E9: NA | F9: 17.172 | G9: NA | H9: 10.239 | I9: NA | J9: =B9+D9 -> 26.827
A10: 42795 | B10: 16.523 | C10: NA | D10: 10.151 | E10: NA | F10: 16.403 | G10: NA | H10: 10.144 | I10: NA | J10: =B10+D10 -> 26.674
A11: 42887 | B11: 16.073 | C11: NA | D11: 10.18 | E11: NA | F11: 16.023 | G11: NA | H11: 10.113 | I11: NA | J11: =B11+D11 -> 26.253
A12: 42979 | B12: 15.727 | C12: NA | D12: 10.483 | E12: NA | F12: 16.041 | G12: NA | H12: 10.331 | I12: NA | J12: =B12+D12 -> 26.21
A13: 43070 | B13: 16.512 | C13: NA | D13: 10.011 | E13: NA | F13: 16.353 | G13: NA | H13: 10.678 | I13: NA | J13: =B13+D13 -> 26.523
A14: 43160 | B14: 16.857 | C14: NA | D14: 11.689 | E14: NA | F14: 16.74 | G14: NA | H14: 10.898 | I14: NA | J14: =B14+D14 -> 28.546
... A19: 43617 | B19: 15.358 | C19: NA | D19: 9.599 | E19: NA | F19: 15.78 | G19: NA | H19: 9.829 | I19: NA | J19: =B19+D19 -> 24.957
A20: 43709 | B20: 17.08 | C20: 10.897 | D20: 10.489 | E20: 4.342 | F20: 16.962 | G20: 10.874 | H20: 10.366 | I20: 4.532 | J20: =B20+D20 -> 27.569
A21: 43800 | B21: 18.713 | C21: 10.545 | D21: 11.447 | E21: 4.811 | F21: 18.809 | G21: 10.489 | H21: 11.305 | I21: 4.497 | J21: =B21+D21 -> 30.16
A22: 43891 | B22: 20.782 | C22: 10.054 | D22: 11.758 | E22: 4.18 | F22: 20.387 | G22: 10.13 | H22: 12.24 | I22: 4.393 | J22: =B22+D22 -> 32.54
A23: 43983 | B23: 26.099 | C23: 9.882 | D23: 13.538 | E23: 4.355 | F23: 21.355 | G23: 9.838 | H23: 12.782 | I23: 4.246 | J23: =B23+D23 -> 39.637
A24: 44075 | B24: 21.845 | C24: 9.874 | D24: 12.787 | E24: 4.107 | F24: 22.219 | G24: 9.906 | H24: 12.991 | I24: 4.186 | J24: =B24+D24 -> 34.632
A25: 44166 | B25: 20.86 | C25: 10.302 | D25: 12.824 | E25: 4.271 | F25: 23.568 | G25: 10.454 | H25: 13.196 | I25: 4.251 | J25: =B25+D25 -> 33.684
A26: 44256 | B26: 25.867 | C26: 11.517 | D26: 13.997 | E26: 4.48 | F26: 26.052 | G26: 11.484 | H26: 13.785 | I26: 4.437 | J26: =B26+D26 -> 39.864
A27: 44348 | B27: 28.549 | C27: 12.659 | D27: 14.787 | E27: 4.557 | F27: 28.908 | G27: 12.739 | H27: 14.926 | I27: 4.78 | J27: =B27+D27 -> 43.336
A28: 44440 | B28: 32.219 | C28: 13.84 | D28: 18.236 | E28: 5.297 | F28: 30.793 | G28: 13.606 | H28: 15.918 | I28: 5.052 | J28: =B28+D28 -> 50.455
A29: 44531 | B29: 31.365 | C29: 14.026 | D29: 16.863 | E29: 5.118 | F29: 31.868 | G29: 13.895 | H29: 16.383 | I29: 5.099 | J29: =B29+D29 -> 48.228
A30: 44621 | B30: 31.923 | C30: 13.297 | D30: 16.214 | E30: 4.81 | F30: 33.036 | G30: 13.68 | H30: 16.499 | I30: 4.893 | J30: =B30+D30 -> 48.137
A31: 44713 | B31: 35.868 | C31: 13.52 | D31: 16.42 | E31: 4.595 | F31: 34.852 | G31: 13.139 | H31: 16.589 | I31: 4.563 | J31: =B31+D31 -> 52.288
... A43: 45809 | B43: 40.081 | C43: 23.235 | D43: 21.856 | E43: 8.202 | F43: 40.735 | G43: 23.105 | H43: 21.902 | I43: 8.146 | J43: =B43+D43 -> 61.937
J44: =SUM(B44:E44) -> 0
A45: Some series only commenced collection in the September quarter 2019 with the introduction of the Economic and Financial Statistics collection. | J45: =SUM(B45:E45) -> 0
J46: =SUM(B46:E46) -> 0
A47: Source: Australian Bureau of Statistics, Lending indicators June Quarter 2025 | J47: =SUM(B47:E47) -> 0
B48: 0.1 | C48: #VALUE! | J48: =SUM(B48:E48) -> #VALUE!
J49: =SUM(B49:E49) -> 0
J50: =SUM(B50:E50) -> 0
J51: =SUM(B51:E51) -> 0
J52: =SUM(B52:E52) -> 0
J53: =SUM(B53:E53) -> 0
J54: =SUM(B54:E54) -> 0
J55: =SUM(B55:E55) -> 0
J56: =SUM(B56:E56) -> 0
J57: =SUM(B57:E57) -> 0
J58: =SUM(B58:E58) -> 0
J59: =SUM(B59:E59) -> 0
J60: =SUM(B60:E60) -> 0
... J77: =SUM(B77:E77) -> 0

Sheet ABS Resi New Loans
A1: Value of new loan commitments for dwellings (a), seasonally adjusted and trend, Australia
B2: Total dwellings (seasadj) ($b) | C2: Owner occupier (seasadj) ($b) | D2: Investor (seasadj) ($b) | E2: Owner occupier first home buyers (seasadj) ($b) | F2: Total dwellings (trend) ($b) | G2: Owner occupier (trend) ($b) | H2: Investor (trend) ($b) | I2: Owner occupier first home buyers (trend) ($b)
A3: 42156 | B3: 58.332 | C3: 32.222 | D3: 26.11 | E3: 7.354 | F3: 58.929 | G3: 33.624 | H3: 25.305 | I3: 7.378
A4: 42248 | B4: 59.715 | C4: 36.487 | D4: 23.229 | E4: 7.392 | F4: 58.039 | G4: 35.289 | H4: 22.749 | I4: 7.294
A5: 42339 | B5: 55.701 | C5: 36.752 | D5: 18.949 | E5: 7.159 | F5: 56.153 | G5: 36.149 | H5: 20.003 | I5: 7.217
A6: 42430 | B6: 53.262 | C6: 34.686 | D6: 18.576 | E6: 7.068 | F6: 54.724 | G6: 35.847 | H6: 18.877 | I6: 7.183
A7: 42522 | B7: 56.221 | C7: 35.941 | D7: 20.28 | E7: 7.363 | F7: 55.062 | G7: 35.066 | H7: 19.996 | I7: 7.155
A8: 42614 | B8: 56.557 | C8: 34.533 | D8: 22.024 | E8: 7.041 | F8: 57.432 | G8: 35.109 | H8: 22.324 | I8: 7.118
A9: 42705 | B9: 60.041 | C9: 35.635 | D9: 24.406 | E9: 7.048 | F9: 59.933 | G9: 35.842 | H9: 24.091 | I9: 7.122
A10: 42795 | B10: 62.643 | C10: 37.476 | D10: 25.168 | E10: 7.272 | F10: 61.551 | G10: 37.091 | H10: 24.46 | I10: 7.24
A11: 42887 | B11: 61.047 | C11: 38.163 | D11: 22.884 | E11: 7.506 | F11: 61.932 | G11: 38.459 | H11: 23.474 | I11: 7.468
A12: 42979 | B12: 61.447 | C12: 39.594 | D12: 21.853 | E12: 9.223 | F12: 60.939 | G12: 39.085 | H12: 21.854 | I12: 9.279
A13: 43070 | B13: 59.384 | C13: 38.959 | D13: 20.424 | E13: 9.55 | F13: 59.585 | G13: 39.235 | H13: 20.35 | I13: 9.522
A14: 43160 | B14: 57.778 | C14: 38.747 | D14: 19.031 | E14: 9.681 | F14: 58.175 | G14: 39.063 | H14: 19.112 | I14: 9.736
... A34: 44986 | B34: 66.105 | C34: 43.772 | D34: 22.333 | E34: 12.78 | F34: 66.659 | G34: 44.295 | H34: 22.364 | I34: 13.04
A35: 45078 | B35: 66.916 | C35: 44.182 | D35: 22.734 | E35: 13.948 | F35: 66.552 | G35: 43.642 | H35: 22.909 | I35: 13.749 | M35: 45292
A36: 45170 | B36: 68.771 | C36: 44.304 | D36: 24.467 | E36: 13.435 | F36: 68.318 | G36: 43.951 | H36: 24.367 | I36: 14.633 | M36: 503.308
A37: 45261 | B37: 74.974 | C37: 48.383 | D37: 26.591 | E37: 15.144 | F37: 71.45 | G37: 45.197 | H37: 26.253 | I37: 15.305
A38: 45352 | B38: 75.326 | C38: 47.326 | D38: 28.001 | E38: 14.563 | F38: 75.985 | G38: 47.427 | H38: 28.557 | I38: 15.671 | M38: 346.217
A39: 45444 | B39: 81.765 | C39: 50.98 | D39: 30.785 | E39: 15.938 | F39: 81.197 | G39: 50.343 | H39: 30.855 | I39: 15.859
A40: 45536 | B40: 85.617 | C40: 52.241 | D40: 33.376 | E40: 15.669 | F40: 85.037 | G40: 52.621 | H40: 32.416 | I40: 15.798
A41: 45627 | B41: 86.973 | C41: 54.469 | D41: 32.504 | E41: 15.89 | F41: 86.437 | G41: 53.616 | H41: 32.821 | I41: 15.712
A42: 45717 | B42: 85.963 | C42: 53.485 | D42: 32.478 | E42: 15.404 | F42: 86.915 | G42: 54.167 | H42: 32.748 | I42: 15.787
A43: 45809 | B43: 87.664 | C43: 54.743 | D43: 32.921 | E43: 16.285 | F43: 87.256 | G43: 54.638 | H43: 32.618 | I43: 15.99
A44: 45694
A45: a. All series exclude refinancingSome series only commenced collection in the September quarter 2019 with the introduction of the Economic and Financial Statistics collection.Loan commitments for dwellings includes loans for the purpose of ‘Construction of new dwellings’, ‘Purchase of new dwellings’ and ‘Purchase of existing dwellings’. 'Residential land' and 'Alterations and additions' are available as separate series.
A46: All series exclude refinancing
A47: Some series only commenced collection in the September quarter 2019 with the introduction of the Economic and Financial Statistics collection.
A48: Loan commitments for dwellings includes loans for the purpose of ‘Construction of new dwellings’, ‘Purchase of new dwellings’ and ‘Purchase of existing dwellings’. 'Residential land' and 'Alterations and additions' are available as separate series. | B48: 0.04
A50: Source: Australian Bureau of Statistics, Lending indicators June Quarter 2025
