Workbook
Name A_ALL_COL.AX: #REF!
Name Abnormals_PostTAX: #REF!
Name AEndDrinks_Sales: #REF!
Name Continuing_sales: #REF!
Name DCF_INF: #REF!
Name DPS: #REF!
Name E_ALL_COL.AX: #REF!
Name EPS_Pre_Goodwill: #REF!
Name L_ALL_COL.AX: #REF!
Name NET_PROFIT: #REF!
Name NPAT_post_Abn: #REF!
Name Sales_Aust_FL: #REF!
Name Sales_NZ_FL: #REF!
Name TOTAL_SALES: #REF!
Name V_ALL_COL.AX: #REF!

Sheet __FDSCACHE__
B1: This sheet contains FactSet XML data for use with this workbook's =FDS codes. Modifying the worksheet's contents may damage the workbook's =FDS functionality.

Sheet Cover
B5: Coles Group (COL.AX)
B6: Rating | C6: Neutral
B7: Target Price/ Target price period/ Upside/downside to target price | C7: A$23/ 12 Month/ 5.7%
B8: M&A probability (1 = high, 3 = low) | C8: 3
B9: Market Cap (US$ mn) (price as of ______):
B10: Current shares outstanding (mn):
B11: Currency: | C11: AUD
B12: Current Publication Date: | C12: 46066
B13: Previous Publication Date:
B15: Team Contacts:
B16: Lead Analyst
B17: Peter Marks, peter.marks@gs.com, +61 2 9321 8846, Goldman Sachs Australia Pty Ltd
B18: Consumer Team
B19: James Leigh, james.leigh@gs.com, +61 2 , Goldman Sachs Australia Pty Ltd
B20: Consumer Team
B21: Rayanne Haidar, rayanne.haidar@gs.com +61 2 9321 8739, Goldman Sachs Australia Pty Ltd

Sheet Summary
D1: Coles Group (COL.AX)
D6: Goldman Sachs | Coles Group | COL-AU
D8: Price target | F8: =Valuation!$E$26 -> 23
D9: Current share price | F9: 21.76
D10: Upside / downside | F10: =F8/F9-1 -> 0.056985294
D11: Recommendation | F11: NEUTRAL
A13: Col C | B13: Col K | D13: P&L | E13: FY23 | F13: FY24 | G13: FY25 | H13: FY26E | I13: FY27E | J13: FY28E | L13: Balance sheet | M13: =E$13 -> FY23 | N13: =F$13 -> FY24 | O13: =G$13 -> FY25 | P13: =H$13 -> FY26E | Q13: =I$13 -> FY27E | R13: =J$13 -> FY28E
A14: - | B14: Cash | D14: Sales | L14: Cash | M14: =VLOOKUP($B14,BS!$1:$1048576,MATCH(Summary!M$13,CF!$3:$3,0),FALSE) -> 597 | N14: =VLOOKUP($B14,BS!$1:$1048576,MATCH(Summary!N$13,CF!$3:$3,0),FALSE) -> 675 | O14: =VLOOKUP($B14,BS!$1:$1048576,MATCH(Summary!O$13,CF!$3:$3,0),FALSE) -> 705 | P14: =VLOOKUP($B14,BS!$1:$1048576,MATCH(Summary!P$13,CF!$3:$3,0),FALSE) -> 737.00077 | Q14: =VLOOKUP($B14,BS!$1:$1048576,MATCH(Summary!Q$13,CF!$3:$3,0),FALSE) -> 781.50581 | R14: =VLOOKUP($B14,BS!$1:$1048576,MATCH(Summary!R$13,CF!$3:$3,0),FALSE) -> 852.91405
A15: Food Sales | B15: TR | D15: Food | E15: =VLOOKUP($A15,Model!$1:$1048576,MATCH(Summary!E$13,Model!$3:$3,0),FALSE) -> 36746 | F15: =VLOOKUP($A15,Model!$1:$1048576,MATCH(Summary!F$13,Model!$3:$3,0),FALSE) -> 39042 | G15: =VLOOKUP($A15,Model!$1:$1048576,MATCH(Summary!G$13,Model!$3:$3,0),FALSE) -> 39987 | H15: =VLOOKUP($A15,Model!$1:$1048576,MATCH(Summary!H$13,Model!$3:$3,0),FALSE) -> 41681.565 | I15: =VLOOKUP($A15,Model!$1:$1048576,MATCH(Summary!I$13,Model!$3:$3,0),FALSE) -> 43506.93 | J15: =VLOOKUP($A15,Model!$1:$1048576,MATCH(Summary!J$13,Model!$3:$3,0),FALSE) -> 45404.069 | L15: Trade receivables | M15: =VLOOKUP($B15,BS!$1:$1048576,MATCH(Summary!M$13,CF!$3:$3,0),FALSE) -> 605 | N15: =VLOOKUP($B15,BS!$1:$1048576,MATCH(Summary!N$13,CF!$3:$3,0),FALSE) -> 496 | O15: =VLOOKUP($B15,BS!$1:$1048576,MATCH(Summary!O$13,CF!$3:$3,0),FALSE) -> 487 | P15: =VLOOKUP($B15,BS!$1:$1048576,MATCH(Summary!P$13,CF!$3:$3,0),FALSE) -> 503.09134 | Q15: =VLOOKUP($B15,BS!$1:$1048576,MATCH(Summary!Q$13,CF!$3:$3,0),FALSE) -> 518.65139 | R15: =VLOOKUP($B15,BS!$1:$1048576,MATCH(Summary!R$13,CF!$3:$3,0),FALSE) -> 540.50588
A16: Liquor Sales | B16: Inventory | D16: Liquor | E16: =VLOOKUP($A16,Model!$1:$1048576,MATCH(Summary!E$13,Model!$3:$3,0),FALSE) -> 3610 | F16: =VLOOKUP($A16,Model!$1:$1048576,MATCH(Summary!F$13,Model!$3:$3,0),FALSE) -> 3692 | G16: =VLOOKUP($A16,Model!$1:$1048576,MATCH(Summary!G$13,Model!$3:$3,0),FALSE) -> 3667 | H16: =VLOOKUP($A16,Model!$1:$1048576,MATCH(Summary!H$13,Model!$3:$3,0),FALSE) -> 3636.7032 | I16: =VLOOKUP($A16,Model!$1:$1048576,MATCH(Summary!I$13,Model!$3:$3,0),FALSE) -> 3727.6207 | J16: =VLOOKUP($A16,Model!$1:$1048576,MATCH(Summary!J$13,Model!$3:$3,0),FALSE) -> 3820.8113 | L16: Inventories | M16: =VLOOKUP($B16,BS!$1:$1048576,MATCH(Summary!M$13,CF!$3:$3,0),FALSE) -> 2323 | N16: =VLOOKUP($B16,BS!$1:$1048576,MATCH(Summary!N$13,CF!$3:$3,0),FALSE) -> 2703 | O16: =VLOOKUP($B16,BS!$1:$1048576,MATCH(Summary!O$13,CF!$3:$3,0),FALSE) -> 2733 | P16: =VLOOKUP($B16,BS!$1:$1048576,MATCH(Summary!P$13,CF!$3:$3,0),FALSE) -> 2823.3032 | Q16: =VLOOKUP($B16,BS!$1:$1048576,MATCH(Summary!Q$13,CF!$3:$3,0),FALSE) -> 2910.6247 | R16: =VLOOKUP($B16,BS!$1:$1048576,MATCH(Summary!R$13,CF!$3:$3,0),FALSE) -> 3033.2702
A17: Corporate/Other Sales | D17: Corporate / Other | E17: =VLOOKUP($A17,Model!$1:$1048576,MATCH(Summary!E$13,Model!$3:$3,0),FALSE) -> 127 | F17: =VLOOKUP($A17,Model!$1:$1048576,MATCH(Summary!F$13,Model!$3:$3,0),FALSE) -> 837 | G17: =VLOOKUP($A17,Model!$1:$1048576,MATCH(Summary!G$13,Model!$3:$3,0),FALSE) -> 698 | H17: =VLOOKUP($A17,Model!$1:$1048576,MATCH(Summary!H$13,Model!$3:$3,0),FALSE) -> 499.2 | I17: =VLOOKUP($A17,Model!$1:$1048576,MATCH(Summary!I$13,Model!$3:$3,0),FALSE) -> 0 | J17: =VLOOKUP($A17,Model!$1:$1048576,MATCH(Summary!J$13,Model!$3:$3,0),FALSE) -> 0 | L17: Other current assets | M17: =M18-SUM(M14:M16) -> 227 | N17: =N18-SUM(N14:N16) -> 112 | O17: =O18-SUM(O14:O16) -> 253 | P17: =P18-SUM(P14:P16) -> 253 | Q17: =Q18-SUM(Q14:Q16) -> 253 | R17: =R18-SUM(R14:R16) -> 253
A18: Total Sales | B18: CA | D18: Total sales | E18: =VLOOKUP($A18,Model!$1:$1048576,MATCH(Summary!E$13,Model!$3:$3,0),FALSE) -> 40483 | F18: =VLOOKUP($A18,Model!$1:$1048576,MATCH(Summary!F$13,Model!$3:$3,0),FALSE) -> 43571 | G18: =VLOOKUP($A18,Model!$1:$1048576,MATCH(Summary!G$13,Model!$3:$3,0),FALSE) -> 44352 | H18: =VLOOKUP($A18,Model!$1:$1048576,MATCH(Summary!H$13,Model!$3:$3,0),FALSE) -> 45817.469 | I18: =VLOOKUP($A18,Model!$1:$1048576,MATCH(Summary!I$13,Model!$3:$3,0),FALSE) -> 47234.551 | J18: =VLOOKUP($A18,Model!$1:$1048576,MATCH(Summary!J$13,Model!$3:$3,0),FALSE) -> 49224.881 | L18: Current assets | M18: =VLOOKUP($B18,BS!$1:$1048576,MATCH(Summary!M$13,CF!$3:$3,0),FALSE) -> 3752 | N18: =VLOOKUP($B18,BS!$1:$1048576,MATCH(Summary!N$13,CF!$3:$3,0),FALSE) -> 3986 | O18: =VLOOKUP($B18,BS!$1:$1048576,MATCH(Summary!O$13,CF!$3:$3,0),FALSE) -> 4178 | P18: =VLOOKUP($B18,BS!$1:$1048576,MATCH(Summary!P$13,CF!$3:$3,0),FALSE) -> 4316.3953 | Q18: =VLOOKUP($B18,BS!$1:$1048576,MATCH(Summary!Q$13,CF!$3:$3,0),FALSE) -> 4463.7819 | R18: =VLOOKUP($B18,BS!$1:$1048576,MATCH(Summary!R$13,CF!$3:$3,0),FALSE) -> 4679.6901
A19: EBITDA | B19: Fixed Assets | D19: EBITDA | E19: =VLOOKUP($A19,PL!$1:$1048576,MATCH(Summary!E$13,PL!$3:$3,0),FALSE) -> 3382 | F19: =VLOOKUP($A19,PL!$1:$1048576,MATCH(Summary!F$13,PL!$3:$3,0),FALSE) -> 3659 | G19: =VLOOKUP($A19,PL!$1:$1048576,MATCH(Summary!G$13,PL!$3:$3,0),FALSE) -> 3941 | H19: =VLOOKUP($A19,PL!$1:$1048576,MATCH(Summary!H$13,PL!$3:$3,0),FALSE) -> 4356.119 | I19: =VLOOKUP($A19,PL!$1:$1048576,MATCH(Summary!I$13,PL!$3:$3,0),FALSE) -> 4637.2421 | J19: =VLOOKUP($A19,PL!$1:$1048576,MATCH(Summary!J$13,PL!$3:$3,0),FALSE) -> 4872.858 | L19: PPE | M19: =VLOOKUP($B19,BS!$1:$1048576,MATCH(Summary!M$13,CF!$3:$3,0),FALSE) -> 4985 | N19: =VLOOKUP($B19,BS!$1:$1048576,MATCH(Summary!N$13,CF!$3:$3,0),FALSE) -> 5619 | O19: =VLOOKUP($B19,BS!$1:$1048576,MATCH(Summary!O$13,CF!$3:$3,0),FALSE) -> 5866 | P19: =VLOOKUP($B19,BS!$1:$1048576,MATCH(Summary!P$13,CF!$3:$3,0),FALSE) -> 6072.925 | Q19: =VLOOKUP($B19,BS!$1:$1048576,MATCH(Summary!Q$13,CF!$3:$3,0),FALSE) -> 6271.353 | R19: =VLOOKUP($B19,BS!$1:$1048576,MATCH(Summary!R$13,CF!$3:$3,0),FALSE) -> 6460.4169
A20: D&A | B20: ROU | D20: D&A | E20: =VLOOKUP($A20,PL!$1:$1048576,MATCH(Summary!E$13,PL!$3:$3,0),FALSE) -> -1523 | F20: =VLOOKUP($A20,PL!$1:$1048576,MATCH(Summary!F$13,PL!$3:$3,0),FALSE) -> -1602 | G20: =VLOOKUP($A20,PL!$1:$1048576,MATCH(Summary!G$13,PL!$3:$3,0),FALSE) -> -1829 | H20: =VLOOKUP($A20,PL!$1:$1048576,MATCH(Summary!H$13,PL!$3:$3,0),FALSE) -> -1947.885 | I20: =VLOOKUP($A20,PL!$1:$1048576,MATCH(Summary!I$13,PL!$3:$3,0),FALSE) -> -2025.8004 | J20: =VLOOKUP($A20,PL!$1:$1048576,MATCH(Summary!J$13,PL!$3:$3,0),FALSE) -> -2106.8324 | L20: RoU Assets | M20: =VLOOKUP($B20,BS!$1:$1048576,MATCH(Summary!M$13,CF!$3:$3,0),FALSE) -> 6507 | N20: =VLOOKUP($B20,BS!$1:$1048576,MATCH(Summary!N$13,CF!$3:$3,0),FALSE) -> 7048 | O20: =VLOOKUP($B20,BS!$1:$1048576,MATCH(Summary!O$13,CF!$3:$3,0),FALSE) -> 6942 | P20: =VLOOKUP($B20,BS!$1:$1048576,MATCH(Summary!P$13,CF!$3:$3,0),FALSE) -> 6987.19 | Q20: =VLOOKUP($B20,BS!$1:$1048576,MATCH(Summary!Q$13,CF!$3:$3,0),FALSE) -> 7048.9616 | R20: =VLOOKUP($B20,BS!$1:$1048576,MATCH(Summary!R$13,CF!$3:$3,0),FALSE) -> 7128.6453
B21: Intangibles | D21: EBIT | L21: Intangibles | M21: =VLOOKUP($B21,BS!$1:$1048576,MATCH(Summary!M$13,CF!$3:$3,0),FALSE) -> 2035 | N21: =VLOOKUP($B21,BS!$1:$1048576,MATCH(Summary!N$13,CF!$3:$3,0),FALSE) -> 2203 | O21: =VLOOKUP($B21,BS!$1:$1048576,MATCH(Summary!O$13,CF!$3:$3,0),FALSE) -> 2246 | P21: =VLOOKUP($B21,BS!$1:$1048576,MATCH(Summary!P$13,CF!$3:$3,0),FALSE) -> 2246 | Q21: =VLOOKUP($B21,BS!$1:$1048576,MATCH(Summary!Q$13,CF!$3:$3,0),FALSE) -> 2246 | R21: =VLOOKUP($B21,BS!$1:$1048576,MATCH(Summary!R$13,CF!$3:$3,0),FALSE) -> 2246
A22: Food EBIT | D22: Food | E22: =VLOOKUP($A22,Model!$1:$1048576,MATCH(Summary!E$13,Model!$3:$3,0),FALSE) -> 1765 | F22: =VLOOKUP($A22,Model!$1:$1048576,MATCH(Summary!F$13,Model!$3:$3,0),FALSE) -> 2018 | G22: =VLOOKUP($A22,Model!$1:$1048576,MATCH(Summary!G$13,Model!$3:$3,0),FALSE) -> 2108 | H22: =VLOOKUP($A22,Model!$1:$1048576,MATCH(Summary!H$13,Model!$3:$3,0),FALSE) -> 2430.6327 | I22: =VLOOKUP($A22,Model!$1:$1048576,MATCH(Summary!I$13,Model!$3:$3,0),FALSE) -> 2618.7813 | J22: =VLOOKUP($A22,Model!$1:$1048576,MATCH(Summary!J$13,Model!$3:$3,0),FALSE) -> 2771.5222 | L22: Other non current assets | M22: =M23-SUM(M19:M21) -> 1013 | N22: =N23-SUM(N19:N21) -> 1014 | O22: =O23-SUM(O19:O21) -> 1062 | P22: =P23-SUM(P19:P21) -> 1062 | Q22: =Q23-SUM(Q19:Q21) -> 1062 | R22: =R23-SUM(R19:R21) -> 1062
A23: Liquor EBIT | B23: NCA | D23: Liquor | E23: =VLOOKUP($A23,Model!$1:$1048576,MATCH(Summary!E$13,Model!$3:$3,0),FALSE) -> 157 | F23: =VLOOKUP($A23,Model!$1:$1048576,MATCH(Summary!F$13,Model!$3:$3,0),FALSE) -> 133 | G23: =VLOOKUP($A23,Model!$1:$1048576,MATCH(Summary!G$13,Model!$3:$3,0),FALSE) -> 113 | H23: =VLOOKUP($A23,Model!$1:$1048576,MATCH(Summary!H$13,Model!$3:$3,0),FALSE) -> 86.374645 | I23: =VLOOKUP($A23,Model!$1:$1048576,MATCH(Summary!I$13,Model!$3:$3,0),FALSE) -> 111.17674 | J23: =VLOOKUP($A23,Model!$1:$1048576,MATCH(Summary!J$13,Model!$3:$3,0),FALSE) -> 116.42514 | L23: Non-current assets | M23: =VLOOKUP($B23,BS!$1:$1048576,MATCH(Summary!M$13,CF!$3:$3,0),FALSE) -> 14540 | N23: =VLOOKUP($B23,BS!$1:$1048576,MATCH(Summary!N$13,CF!$3:$3,0),FALSE) -> 15884 | O23: =VLOOKUP($B23,BS!$1:$1048576,MATCH(Summary!O$13,CF!$3:$3,0),FALSE) -> 16116 | P23: =VLOOKUP($B23,BS!$1:$1048576,MATCH(Summary!P$13,CF!$3:$3,0),FALSE) -> 16368.115 | Q23: =VLOOKUP($B23,BS!$1:$1048576,MATCH(Summary!Q$13,CF!$3:$3,0),FALSE) -> 16628.315 | R23: =VLOOKUP($B23,BS!$1:$1048576,MATCH(Summary!R$13,CF!$3:$3,0),FALSE) -> 16897.062
A24: Corporate/Other EBIT | B24: TP | D24: Corporate / Other | E24: =VLOOKUP($A24,Model!$1:$1048576,MATCH(Summary!E$13,Model!$3:$3,0),FALSE) -> -63 | F24: =VLOOKUP($A24,Model!$1:$1048576,MATCH(Summary!F$13,Model!$3:$3,0),FALSE) -> -94 | G24: =VLOOKUP($A24,Model!$1:$1048576,MATCH(Summary!G$13,Model!$3:$3,0),FALSE) -> -109 | H24: =VLOOKUP($A24,Model!$1:$1048576,MATCH(Summary!H$13,Model!$3:$3,0),FALSE) -> -108.77332 | I24: =VLOOKUP($A24,Model!$1:$1048576,MATCH(Summary!I$13,Model!$3:$3,0),FALSE) -> -118.5163 | J24: =VLOOKUP($A24,Model!$1:$1048576,MATCH(Summary!J$13,Model!$3:$3,0),FALSE) -> -121.92179 | L24: Trade payables | M24: =VLOOKUP($B24,BS!$1:$1048576,MATCH(Summary!M$13,CF!$3:$3,0),FALSE) -> 4434 | N24: =VLOOKUP($B24,BS!$1:$1048576,MATCH(Summary!N$13,CF!$3:$3,0),FALSE) -> 4584 | O24: =VLOOKUP($B24,BS!$1:$1048576,MATCH(Summary!O$13,CF!$3:$3,0),FALSE) -> 4637 | P24: =VLOOKUP($B24,BS!$1:$1048576,MATCH(Summary!P$13,CF!$3:$3,0),FALSE) -> 4790.2147 | Q24: =VLOOKUP($B24,BS!$1:$1048576,MATCH(Summary!Q$13,CF!$3:$3,0),FALSE) -> 4938.3706 | R24: =VLOOKUP($B24,BS!$1:$1048576,MATCH(Summary!R$13,CF!$3:$3,0),FALSE) -> 5146.4595
A25: Total EBIT | B25: C Borrowings | D25: Total EBIT | E25: =VLOOKUP($A25,Model!$1:$1048576,MATCH(Summary!E$13,Model!$3:$3,0),FALSE) -> 1859 | F25: =VLOOKUP($A25,Model!$1:$1048576,MATCH(Summary!F$13,Model!$3:$3,0),FALSE) -> 2057 | G25: =VLOOKUP($A25,Model!$1:$1048576,MATCH(Summary!G$13,Model!$3:$3,0),FALSE) -> 2112 | H25: =VLOOKUP($A25,Model!$1:$1048576,MATCH(Summary!H$13,Model!$3:$3,0),FALSE) -> 2408.234 | I25: =VLOOKUP($A25,Model!$1:$1048576,MATCH(Summary!I$13,Model!$3:$3,0),FALSE) -> 2611.4417 | J25: =VLOOKUP($A25,Model!$1:$1048576,MATCH(Summary!J$13,Model!$3:$3,0),FALSE) -> 2766.0256 | L25: Borrowings | M25: =VLOOKUP($B25,BS!$1:$1048576,MATCH(Summary!M$13,CF!$3:$3,0),FALSE) -> 0 | N25: =VLOOKUP($B25,BS!$1:$1048576,MATCH(Summary!N$13,CF!$3:$3,0),FALSE) -> 0 | O25: =VLOOKUP($B25,BS!$1:$1048576,MATCH(Summary!O$13,CF!$3:$3,0),FALSE) -> 150 | P25: =VLOOKUP($B25,BS!$1:$1048576,MATCH(Summary!P$13,CF!$3:$3,0),FALSE) -> 150 | Q25: =VLOOKUP($B25,BS!$1:$1048576,MATCH(Summary!Q$13,CF!$3:$3,0),FALSE) -> 150 | R25: =VLOOKUP($B25,BS!$1:$1048576,MATCH(Summary!R$13,CF!$3:$3,0),FALSE) -> 150
A26: Net Interest | D26: Net interest | E26: =VLOOKUP($A26,PL!$1:$1048576,MATCH(Summary!E$13,PL!$3:$3,0),FALSE) -> -394 | F26: =VLOOKUP($A26,PL!$1:$1048576,MATCH(Summary!F$13,PL!$3:$3,0),FALSE) -> -442 | G26: =VLOOKUP($A26,PL!$1:$1048576,MATCH(Summary!G$13,PL!$3:$3,0),FALSE) -> -541 | H26: =VLOOKUP($A26,PL!$1:$1048576,MATCH(Summary!H$13,PL!$3:$3,0),FALSE) -> -552.75 | I26: =VLOOKUP($A26,PL!$1:$1048576,MATCH(Summary!I$13,PL!$3:$3,0),FALSE) -> -565.8825 | J26: =VLOOKUP($A26,PL!$1:$1048576,MATCH(Summary!J$13,PL!$3:$3,0),FALSE) -> -579.40898 | L26: Other current liabilities | M26: =M27-SUM(M24:M25) -> 1974 | N26: =N27-SUM(N24:N25) -> 2187 | O26: =O27-SUM(O24:O25) -> 2069 | P26: =P27-SUM(P24:P25) -> 2069 | Q26: =Q27-SUM(Q24:Q25) -> 2069 | R26: =R27-SUM(R24:R25) -> 2069
A27: PBT | B27: CL | D27: PBT | E27: =VLOOKUP($A27,PL!$1:$1048576,MATCH(Summary!E$13,PL!$3:$3,0),FALSE) -> 1465 | F27: =VLOOKUP($A27,PL!$1:$1048576,MATCH(Summary!F$13,PL!$3:$3,0),FALSE) -> 1615 | G27: =VLOOKUP($A27,PL!$1:$1048576,MATCH(Summary!G$13,PL!$3:$3,0),FALSE) -> 1571 | H27: =VLOOKUP($A27,PL!$1:$1048576,MATCH(Summary!H$13,PL!$3:$3,0),FALSE) -> 1855.484 | I27: =VLOOKUP($A27,PL!$1:$1048576,MATCH(Summary!I$13,PL!$3:$3,0),FALSE) -> 2045.5592 | J27: =VLOOKUP($A27,PL!$1:$1048576,MATCH(Summary!J$13,PL!$3:$3,0),FALSE) -> 2186.6166 | L27: Current liabilities | M27: =VLOOKUP($B27,BS!$1:$1048576,MATCH(Summary!M$13,CF!$3:$3,0),FALSE) -> 6408 | N27: =VLOOKUP($B27,BS!$1:$1048576,MATCH(Summary!N$13,CF!$3:$3,0),FALSE) -> 6771 | O27: =VLOOKUP($B27,BS!$1:$1048576,MATCH(Summary!O$13,CF!$3:$3,0),FALSE) -> 6856 | P27: =VLOOKUP($B27,BS!$1:$1048576,MATCH(Summary!P$13,CF!$3:$3,0),FALSE) -> 7009.2147 | Q27: =VLOOKUP($B27,BS!$1:$1048576,MATCH(Summary!Q$13,CF!$3:$3,0),FALSE) -> 7157.3706 | R27: =VLOOKUP($B27,BS!$1:$1048576,MATCH(Summary!R$13,CF!$3:$3,0),FALSE) -> 7365.4595
A28: Tax | B28: NC Lease | D28: Tax | E28: =VLOOKUP($A28,PL!$1:$1048576,MATCH(Summary!E$13,PL!$3:$3,0),FALSE) -> -423 | F28: =VLOOKUP($A28,PL!$1:$1048576,MATCH(Summary!F$13,PL!$3:$3,0),FALSE) -> -487 | G28: =VLOOKUP($A28,PL!$1:$1048576,MATCH(Summary!G$13,PL!$3:$3,0),FALSE) -> -467 | H28: =VLOOKUP($A28,PL!$1:$1048576,MATCH(Summary!H$13,PL!$3:$3,0),FALSE) -> -556.64521 | I28: =VLOOKUP($A28,PL!$1:$1048576,MATCH(Summary!I$13,PL!$3:$3,0),FALSE) -> -613.66776 | J28: =VLOOKUP($A28,PL!$1:$1048576,MATCH(Summary!J$13,PL!$3:$3,0),FALSE) -> -655.98498 | L28: Lease liabilities | M28: =VLOOKUP($B28,BS!$1:$1048576,MATCH(Summary!M$13,CF!$3:$3,0),FALSE) -> 7029 | N28: =VLOOKUP($B28,BS!$1:$1048576,MATCH(Summary!N$13,CF!$3:$3,0),FALSE) -> 7506 | O28: =VLOOKUP($B28,BS!$1:$1048576,MATCH(Summary!O$13,CF!$3:$3,0),FALSE) -> 7415 | P28: =VLOOKUP($B28,BS!$1:$1048576,MATCH(Summary!P$13,CF!$3:$3,0),FALSE) -> 7458.45 | Q28: =VLOOKUP($B28,BS!$1:$1048576,MATCH(Summary!Q$13,CF!$3:$3,0),FALSE) -> 7504.0725 | R28: =VLOOKUP($B28,BS!$1:$1048576,MATCH(Summary!R$13,CF!$3:$3,0),FALSE) -> 7551.9761
A29: NPAT | B29: NC Borrowings | D29: NPAT | E29: =VLOOKUP($A29,PL!$1:$1048576,MATCH(Summary!E$13,PL!$3:$3,0),FALSE) -> 1042 | F29: =VLOOKUP($A29,PL!$1:$1048576,MATCH(Summary!F$13,PL!$3:$3,0),FALSE) -> 1128 | G29: =VLOOKUP($A29,PL!$1:$1048576,MATCH(Summary!G$13,PL!$3:$3,0),FALSE) -> 1104 | H29: =VLOOKUP($A29,PL!$1:$1048576,MATCH(Summary!H$13,PL!$3:$3,0),FALSE) -> 1298.8388 | I29: =VLOOKUP($A29,PL!$1:$1048576,MATCH(Summary!I$13,PL!$3:$3,0),FALSE) -> 1431.8914 | J29: =VLOOKUP($A29,PL!$1:$1048576,MATCH(Summary!J$13,PL!$3:$3,0),FALSE) -> 1530.6316 | L29: Borrowings | M29: =VLOOKUP($B29,BS!$1:$1048576,MATCH(Summary!M$13,CF!$3:$3,0),FALSE) -> 1118 | N29: =VLOOKUP($B29,BS!$1:$1048576,MATCH(Summary!N$13,CF!$3:$3,0),FALSE) -> 1652 | O29: =VLOOKUP($B29,BS!$1:$1048576,MATCH(Summary!O$13,CF!$3:$3,0),FALSE) -> 1834 | P29: =VLOOKUP($B29,BS!$1:$1048576,MATCH(Summary!P$13,CF!$3:$3,0),FALSE) -> 1834 | Q29: =VLOOKUP($B29,BS!$1:$1048576,MATCH(Summary!Q$13,CF!$3:$3,0),FALSE) -> 1834 | R29: =VLOOKUP($B29,BS!$1:$1048576,MATCH(Summary!R$13,CF!$3:$3,0),FALSE) -> 1834
A30: Shares Diluted | D30: Shares (m) | E30: =VLOOKUP($A30,PL!$1:$1048576,MATCH(Summary!E$13,PL!$3:$3,0),FALSE) -> 1338 | F30: =VLOOKUP($A30,PL!$1:$1048576,MATCH(Summary!F$13,PL!$3:$3,0),FALSE) -> 1338 | G30: =VLOOKUP($A30,PL!$1:$1048576,MATCH(Summary!G$13,PL!$3:$3,0),FALSE) -> 1340 | H30: =VLOOKUP($A30,PL!$1:$1048576,MATCH(Summary!H$13,PL!$3:$3,0),FALSE) -> 1342 | I30: =VLOOKUP($A30,PL!$1:$1048576,MATCH(Summary!I$13,PL!$3:$3,0),FALSE) -> 1344 | J30: =VLOOKUP($A30,PL!$1:$1048576,MATCH(Summary!J$13,PL!$3:$3,0),FALSE) -> 1346 | L30: Other non-current liabilities | M30: =M31-SUM(M28:M29) -> 381 | N30: =N31-SUM(N28:N29) -> 324 | O30: =O31-SUM(O28:O29) -> 383 | P30: =P31-SUM(P28:P29) -> 383 | Q30: =Q31-SUM(Q28:Q29) -> 383 | R30: =R31-SUM(R28:R29) -> 383
A31: EPS | B31: NCL | D31: EPS | E31: =VLOOKUP($A31,PL!$1:$1048576,MATCH(Summary!E$13,PL!$3:$3,0),FALSE) -> 0.77877429 | F31: =VLOOKUP($A31,PL!$1:$1048576,MATCH(Summary!F$13,PL!$3:$3,0),FALSE) -> 0.84304933 | G31: =VLOOKUP($A31,PL!$1:$1048576,MATCH(Summary!G$13,PL!$3:$3,0),FALSE) -> 0.8238806 | H31: =VLOOKUP($A31,PL!$1:$1048576,MATCH(Summary!H$13,PL!$3:$3,0),FALSE) -> 0.96783816 | I31: =VLOOKUP($A31,PL!$1:$1048576,MATCH(Summary!I$13,PL!$3:$3,0),FALSE) -> 1.0653954 | J31: =VLOOKUP($A31,PL!$1:$1048576,MATCH(Summary!J$13,PL!$3:$3,0),FALSE) -> 1.1371706 | L31: Non-current liabilities | M31: =VLOOKUP($B31,BS!$1:$1048576,MATCH(Summary!M$13,CF!$3:$3,0),FALSE) -> 8528 | N31: =VLOOKUP($B31,BS!$1:$1048576,MATCH(Summary!N$13,CF!$3:$3,0),FALSE) -> 9482 | O31: =VLOOKUP($B31,BS!$1:$1048576,MATCH(Summary!O$13,CF!$3:$3,0),FALSE) -> 9632 | P31: =VLOOKUP($B31,BS!$1:$1048576,MATCH(Summary!P$13,CF!$3:$3,0),FALSE) -> 9675.45 | Q31: =VLOOKUP($B31,BS!$1:$1048576,MATCH(Summary!Q$13,CF!$3:$3,0),FALSE) -> 9721.0725 | R31: =VLOOKUP($B31,BS!$1:$1048576,MATCH(Summary!R$13,CF!$3:$3,0),FALSE) -> 9768.9761
A32: DPS | B32: Contributed Equity | D32: DPS | E32: =VLOOKUP($A32,PL!$1:$1048576,MATCH(Summary!E$13,PL!$3:$3,0),FALSE) -> 0.66 | F32: =VLOOKUP($A32,PL!$1:$1048576,MATCH(Summary!F$13,PL!$3:$3,0),FALSE) -> 0.68 | G32: =VLOOKUP($A32,PL!$1:$1048576,MATCH(Summary!G$13,PL!$3:$3,0),FALSE) -> 0.69 | H32: =VLOOKUP($A32,PL!$1:$1048576,MATCH(Summary!H$13,PL!$3:$3,0),FALSE) -> 0.82266244 | I32: =VLOOKUP($A32,PL!$1:$1048576,MATCH(Summary!I$13,PL!$3:$3,0),FALSE) -> 0.9055861 | J32: =VLOOKUP($A32,PL!$1:$1048576,MATCH(Summary!J$13,PL!$3:$3,0),FALSE) -> 0.96659501 | L32: Contributed equity | M32: =VLOOKUP($B32,BS!$1:$1048576,MATCH(Summary!M$13,CF!$3:$3,0),FALSE) -> 1644 | N32: =VLOOKUP($B32,BS!$1:$1048576,MATCH(Summary!N$13,CF!$3:$3,0),FALSE) -> 1672 | O32: =VLOOKUP($B32,BS!$1:$1048576,MATCH(Summary!O$13,CF!$3:$3,0),FALSE) -> 1704 | P32: =VLOOKUP($B32,BS!$1:$1048576,MATCH(Summary!P$13,CF!$3:$3,0),FALSE) -> 1704 | Q32: =VLOOKUP($B32,BS!$1:$1048576,MATCH(Summary!Q$13,CF!$3:$3,0),FALSE) -> 1704 | R32: =VLOOKUP($B32,BS!$1:$1048576,MATCH(Summary!R$13,CF!$3:$3,0),FALSE) -> 1704
B33: Reserves | L33: Reserves | M33: =VLOOKUP($B33,BS!$1:$1048576,MATCH(Summary!M$13,CF!$3:$3,0),FALSE) -> 104 | N33: =VLOOKUP($B33,BS!$1:$1048576,MATCH(Summary!N$13,CF!$3:$3,0),FALSE) -> 103 | O33: =VLOOKUP($B33,BS!$1:$1048576,MATCH(Summary!O$13,CF!$3:$3,0),FALSE) -> 106 | P33: =VLOOKUP($B33,BS!$1:$1048576,MATCH(Summary!P$13,CF!$3:$3,0),FALSE) -> 106 | Q33: =VLOOKUP($B33,BS!$1:$1048576,MATCH(Summary!Q$13,CF!$3:$3,0),FALSE) -> 106 | R33: =VLOOKUP($B33,BS!$1:$1048576,MATCH(Summary!R$13,CF!$3:$3,0),FALSE) -> 106
B34: Retained Profits | D34: Cash flow | E34: FY23 | F34: FY24 | G34: FY25 | H34: FY26E | I34: FY27E | J34: FY28E | L34: Retained Profits | M34: =VLOOKUP($B34,BS!$1:$1048576,MATCH(Summary!M$13,CF!$3:$3,0),FALSE) -> 1608 | N34: =VLOOKUP($B34,BS!$1:$1048576,MATCH(Summary!N$13,CF!$3:$3,0),FALSE) -> 1842 | O34: =VLOOKUP($B34,BS!$1:$1048576,MATCH(Summary!O$13,CF!$3:$3,0),FALSE) -> 1996 | P34: =VLOOKUP($B34,BS!$1:$1048576,MATCH(Summary!P$13,CF!$3:$3,0),FALSE) -> 2189.8456 | Q34: =VLOOKUP($B34,BS!$1:$1048576,MATCH(Summary!Q$13,CF!$3:$3,0),FALSE) -> 2403.6534 | R34: =VLOOKUP($B34,BS!$1:$1048576,MATCH(Summary!R$13,CF!$3:$3,0),FALSE) -> 2632.3167
A35: EBIT | B35: Total Equity | D35: EBIT | E35: =VLOOKUP($A35,CF!$1:$1048576,MATCH(Summary!E$13,CF!$3:$3,0),FALSE) -> 1859 | F35: =VLOOKUP($A35,CF!$1:$1048576,MATCH(Summary!F$13,CF!$3:$3,0),FALSE) -> 2057 | G35: =VLOOKUP($A35,CF!$1:$1048576,MATCH(Summary!G$13,CF!$3:$3,0),FALSE) -> 2112 | H35: =VLOOKUP($A35,CF!$1:$1048576,MATCH(Summary!H$13,CF!$3:$3,0),FALSE) -> 2408.234 | I35: =VLOOKUP($A35,CF!$1:$1048576,MATCH(Summary!I$13,CF!$3:$3,0),FALSE) -> 2611.4417 | J35: =VLOOKUP($A35,CF!$1:$1048576,MATCH(Summary!J$13,CF!$3:$3,0),FALSE) -> 2766.0256 | L35: Total Equity | M35: =VLOOKUP($B35,BS!$1:$1048576,MATCH(Summary!M$13,CF!$3:$3,0),FALSE) -> 3356 | N35: =VLOOKUP($B35,BS!$1:$1048576,MATCH(Summary!N$13,CF!$3:$3,0),FALSE) -> 3617 | O35: =VLOOKUP($B35,BS!$1:$1048576,MATCH(Summary!O$13,CF!$3:$3,0),FALSE) -> 3806 | P35: =VLOOKUP($B35,BS!$1:$1048576,MATCH(Summary!P$13,CF!$3:$3,0),FALSE) -> 3999.8456 | Q35: =VLOOKUP($B35,BS!$1:$1048576,MATCH(Summary!Q$13,CF!$3:$3,0),FALSE) -> 4213.6534 | R35: =VLOOKUP($B35,BS!$1:$1048576,MATCH(Summary!R$13,CF!$3:$3,0),FALSE) -> 4442.3167
A36: D&A | B36: Net Debt | D36: D&A | E36: =VLOOKUP($A36,CF!$1:$1048576,MATCH(Summary!E$13,CF!$3:$3,0),FALSE) -> 1523 | F36: =VLOOKUP($A36,CF!$1:$1048576,MATCH(Summary!F$13,CF!$3:$3,0),FALSE) -> 1602 | G36: =VLOOKUP($A36,CF!$1:$1048576,MATCH(Summary!G$13,CF!$3:$3,0),FALSE) -> 1829 | H36: =VLOOKUP($A36,CF!$1:$1048576,MATCH(Summary!H$13,CF!$3:$3,0),FALSE) -> 1947.885 | I36: =VLOOKUP($A36,CF!$1:$1048576,MATCH(Summary!I$13,CF!$3:$3,0),FALSE) -> 2025.8004 | J36: =VLOOKUP($A36,CF!$1:$1048576,MATCH(Summary!J$13,CF!$3:$3,0),FALSE) -> 2106.8324 | L36: Net debt ex leases | M36: =VLOOKUP($B36,BS!$1:$1048576,MATCH(Summary!M$13,CF!$3:$3,0),FALSE) -> 521 | N36: =VLOOKUP($B36,BS!$1:$1048576,MATCH(Summary!N$13,CF!$3:$3,0),FALSE) -> 977 | O36: =VLOOKUP($B36,BS!$1:$1048576,MATCH(Summary!O$13,CF!$3:$3,0),FALSE) -> 1279 | P36: =VLOOKUP($B36,BS!$1:$1048576,MATCH(Summary!P$13,CF!$3:$3,0),FALSE) -> 1246.9992 | Q36: =VLOOKUP($B36,BS!$1:$1048576,MATCH(Summary!Q$13,CF!$3:$3,0),FALSE) -> 1202.4942 | R36: =VLOOKUP($B36,BS!$1:$1048576,MATCH(Summary!R$13,CF!$3:$3,0),FALSE) -> 1131.086
A37: Net interest | D37: Net interest | E37: =VLOOKUP($A37,CF!$1:$1048576,MATCH(Summary!E$13,CF!$3:$3,0),FALSE) -> -394 | F37: =VLOOKUP($A37,CF!$1:$1048576,MATCH(Summary!F$13,CF!$3:$3,0),FALSE) -> -442 | G37: =VLOOKUP($A37,CF!$1:$1048576,MATCH(Summary!G$13,CF!$3:$3,0),FALSE) -> -541 | H37: =VLOOKUP($A37,CF!$1:$1048576,MATCH(Summary!H$13,CF!$3:$3,0),FALSE) -> -552.75 | I37: =VLOOKUP($A37,CF!$1:$1048576,MATCH(Summary!I$13,CF!$3:$3,0),FALSE) -> -565.8825 | J37: =VLOOKUP($A37,CF!$1:$1048576,MATCH(Summary!J$13,CF!$3:$3,0),FALSE) -> -579.40898 | L37: Divisional key metrics | M37: =E$13 -> FY23 | N37: =F$13 -> FY24 | O37: =G$13 -> FY25 | P37: =H$13 -> FY26E | Q37: =I$13 -> FY27E | R37: =J$13 -> FY28E
A38: Tax | B38: Food Comp | D38: Tax | E38: =VLOOKUP($A38,CF!$1:$1048576,MATCH(Summary!E$13,CF!$3:$3,0),FALSE) -> -423 | F38: =VLOOKUP($A38,CF!$1:$1048576,MATCH(Summary!F$13,CF!$3:$3,0),FALSE) -> -487 | G38: =VLOOKUP($A38,CF!$1:$1048576,MATCH(Summary!G$13,CF!$3:$3,0),FALSE) -> -467 | H38: =VLOOKUP($A38,CF!$1:$1048576,MATCH(Summary!H$13,CF!$3:$3,0),FALSE) -> -556.64521 | I38: =VLOOKUP($A38,CF!$1:$1048576,MATCH(Summary!I$13,CF!$3:$3,0),FALSE) -> -613.66776 | J38: =VLOOKUP($A38,CF!$1:$1048576,MATCH(Summary!J$13,CF!$3:$3,0),FALSE) -> -655.98498 | L38: Food LFL Sales Growth | M38: =VLOOKUP($B38,Model!$1:$1048576,MATCH(Summary!M$13,CF!$3:$3,0),FALSE) -> 0.058 | N38: =VLOOKUP($B38,Model!$1:$1048576,MATCH(Summary!N$13,CF!$3:$3,0),FALSE) -> 0.034 | O38: =VLOOKUP($B38,Model!$1:$1048576,MATCH(Summary!O$13,CF!$3:$3,0),FALSE) -> 0.037 | P38: =VLOOKUP($B38,Model!$1:$1048576,MATCH(Summary!P$13,CF!$3:$3,0),FALSE) -> 0.03875 | Q38: =VLOOKUP($B38,Model!$1:$1048576,MATCH(Summary!Q$13,CF!$3:$3,0),FALSE) -> 0.035 | R38: =VLOOKUP($B38,Model!$1:$1048576,MATCH(Summary!R$13,CF!$3:$3,0),FALSE) -> 0.035
A39: Chg WC | B39: Food EBIT Margin | D39: Change in net working capital | E39: =VLOOKUP($A39,CF!$1:$1048576,MATCH(Summary!E$13,CF!$3:$3,0),FALSE) -> 89 | F39: =VLOOKUP($A39,CF!$1:$1048576,MATCH(Summary!F$13,CF!$3:$3,0),FALSE) -> -121 | G39: =VLOOKUP($A39,CF!$1:$1048576,MATCH(Summary!G$13,CF!$3:$3,0),FALSE) -> 32 | H39: =VLOOKUP($A39,CF!$1:$1048576,MATCH(Summary!H$13,CF!$3:$3,0),FALSE) -> 46.820186 | I39: =VLOOKUP($A39,CF!$1:$1048576,MATCH(Summary!I$13,CF!$3:$3,0),FALSE) -> 45.274309 | J39: =VLOOKUP($A39,CF!$1:$1048576,MATCH(Summary!J$13,CF!$3:$3,0),FALSE) -> 63.588944 | L39: Food EBIT Margin | M39: =VLOOKUP($B39,Model!$1:$1048576,MATCH(Summary!M$13,CF!$3:$3,0),FALSE) -> 0.048032439 | N39: =VLOOKUP($B39,Model!$1:$1048576,MATCH(Summary!N$13,CF!$3:$3,0),FALSE) -> 0.051687926 | O39: =VLOOKUP($B39,Model!$1:$1048576,MATCH(Summary!O$13,CF!$3:$3,0),FALSE) -> 0.052717133 | P39: =VLOOKUP($B39,Model!$1:$1048576,MATCH(Summary!P$13,CF!$3:$3,0),FALSE) -> 0.058314333 | Q39: =VLOOKUP($B39,Model!$1:$1048576,MATCH(Summary!Q$13,CF!$3:$3,0),FALSE) -> 0.060192278 | R39: =VLOOKUP($B39,Model!$1:$1048576,MATCH(Summary!R$13,CF!$3:$3,0),FALSE) -> 0.061041274
A40: Other | B40: Liquor Comp | D40: Other | E40: =VLOOKUP($A40,CF!$1:$1048576,MATCH(Summary!E$13,CF!$3:$3,0),FALSE) -> 153 | F40: =VLOOKUP($A40,CF!$1:$1048576,MATCH(Summary!F$13,CF!$3:$3,0),FALSE) -> 184 | G40: =VLOOKUP($A40,CF!$1:$1048576,MATCH(Summary!G$13,CF!$3:$3,0),FALSE) -> -29 | H40: =VLOOKUP($A40,CF!$1:$1048576,MATCH(Summary!H$13,CF!$3:$3,0),FALSE) -> 0 | I40: =VLOOKUP($A40,CF!$1:$1048576,MATCH(Summary!I$13,CF!$3:$3,0),FALSE) -> 0 | J40: =VLOOKUP($A40,CF!$1:$1048576,MATCH(Summary!J$13,CF!$3:$3,0),FALSE) -> 0 | L40: Liquor LFL Sales Growth | M40: =VLOOKUP($B40,Model!$1:$1048576,MATCH(Summary!M$13,CF!$3:$3,0),FALSE) -> 0.007 | N40: =VLOOKUP($B40,Model!$1:$1048576,MATCH(Summary!N$13,CF!$3:$3,0),FALSE) -> -0.01 | O40: =VLOOKUP($B40,Model!$1:$1048576,MATCH(Summary!O$13,CF!$3:$3,0),FALSE) -> -0.013 | P40: =VLOOKUP($B40,Model!$1:$1048576,MATCH(Summary!P$13,CF!$3:$3,0),FALSE) -> -0.01125 | Q40: =VLOOKUP($B40,Model!$1:$1048576,MATCH(Summary!Q$13,CF!$3:$3,0),FALSE) -> 0.025 | R40: =VLOOKUP($B40,Model!$1:$1048576,MATCH(Summary!R$13,CF!$3:$3,0),FALSE) -> 0.025
A41: OCF | B41: Liquor EBIT Margin | D41: Operating cashflow | E41: =VLOOKUP($A41,CF!$1:$1048576,MATCH(Summary!E$13,CF!$3:$3,0),FALSE) -> 2807 | F41: =VLOOKUP($A41,CF!$1:$1048576,MATCH(Summary!F$13,CF!$3:$3,0),FALSE) -> 2793 | G41: =VLOOKUP($A41,CF!$1:$1048576,MATCH(Summary!G$13,CF!$3:$3,0),FALSE) -> 2936 | H41: =VLOOKUP($A41,CF!$1:$1048576,MATCH(Summary!H$13,CF!$3:$3,0),FALSE) -> 3293.544 | I41: =VLOOKUP($A41,CF!$1:$1048576,MATCH(Summary!I$13,CF!$3:$3,0),FALSE) -> 3502.9661 | J41: =VLOOKUP($A41,CF!$1:$1048576,MATCH(Summary!J$13,CF!$3:$3,0),FALSE) -> 3701.053 | L41: Liquor EBIT Margin | M41: =VLOOKUP($B41,Model!$1:$1048576,MATCH(Summary!M$13,CF!$3:$3,0),FALSE) -> 0.043490305 | N41: =VLOOKUP($B41,Model!$1:$1048576,MATCH(Summary!N$13,CF!$3:$3,0),FALSE) -> 0.036023835 | O41: =VLOOKUP($B41,Model!$1:$1048576,MATCH(Summary!O$13,CF!$3:$3,0),FALSE) -> 0.03081538 | P41: =VLOOKUP($B41,Model!$1:$1048576,MATCH(Summary!P$13,CF!$3:$3,0),FALSE) -> 0.02375081 | Q41: =VLOOKUP($B41,Model!$1:$1048576,MATCH(Summary!Q$13,CF!$3:$3,0),FALSE) -> 0.02982512 | R41: =VLOOKUP($B41,Model!$1:$1048576,MATCH(Summary!R$13,CF!$3:$3,0),FALSE) -> 0.030471315
A42: Capex | D42: Capex | E42: =VLOOKUP($A42,CF!$1:$1048576,MATCH(Summary!E$13,CF!$3:$3,0),FALSE) -> -1514 | F42: =VLOOKUP($A42,CF!$1:$1048576,MATCH(Summary!F$13,CF!$3:$3,0),FALSE) -> -1671 | G42: =VLOOKUP($A42,CF!$1:$1048576,MATCH(Summary!G$13,CF!$3:$3,0),FALSE) -> -1487 | H42: =VLOOKUP($A42,CF!$1:$1048576,MATCH(Summary!H$13,CF!$3:$3,0),FALSE) -> -1200 | I42: =VLOOKUP($A42,CF!$1:$1048576,MATCH(Summary!I$13,CF!$3:$3,0),FALSE) -> -1236 | J42: =VLOOKUP($A42,CF!$1:$1048576,MATCH(Summary!J$13,CF!$3:$3,0),FALSE) -> -1273.08 | L42: Group key metrics | M42: =E$13 -> FY23 | N42: =F$13 -> FY24 | O42: =G$13 -> FY25 | P42: =H$13 -> FY26E | Q42: =I$13 -> FY27E | R42: =J$13 -> FY28E
A43: Acquisitions | B43: Total Sales Growth | D43: Acquisitions | E43: =VLOOKUP($A43,CF!$1:$1048576,MATCH(Summary!E$13,CF!$3:$3,0),FALSE) -> -14 | F43: =VLOOKUP($A43,CF!$1:$1048576,MATCH(Summary!F$13,CF!$3:$3,0),FALSE) -> -23 | G43: =VLOOKUP($A43,CF!$1:$1048576,MATCH(Summary!G$13,CF!$3:$3,0),FALSE) -> -20 | H43: =VLOOKUP($A43,CF!$1:$1048576,MATCH(Summary!H$13,CF!$3:$3,0),FALSE) -> 0 | I43: =VLOOKUP($A43,CF!$1:$1048576,MATCH(Summary!I$13,CF!$3:$3,0),FALSE) -> 0 | J43: =VLOOKUP($A43,CF!$1:$1048576,MATCH(Summary!J$13,CF!$3:$3,0),FALSE) -> 0 | L43: Sales Growth | M43: =VLOOKUP($B43,PL!$1:$1048576,MATCH(Summary!M$13,CF!$3:$3,0),FALSE) -> 0.058738918 | N43: =VLOOKUP($B43,PL!$1:$1048576,MATCH(Summary!N$13,CF!$3:$3,0),FALSE) -> 0.076278932 | O43: =VLOOKUP($B43,PL!$1:$1048576,MATCH(Summary!O$13,CF!$3:$3,0),FALSE) -> 0.017924766 | P43: =VLOOKUP($B43,PL!$1:$1048576,MATCH(Summary!P$13,CF!$3:$3,0),FALSE) -> 0.033041769 | Q43: =VLOOKUP($B43,PL!$1:$1048576,MATCH(Summary!Q$13,CF!$3:$3,0),FALSE) -> 0.030928873 | R43: =VLOOKUP($B43,PL!$1:$1048576,MATCH(Summary!R$13,CF!$3:$3,0),FALSE) -> 0.042137152
A44: Proceeds PPE | B44: Total EBIT Growth | D44: Proceeds from asset sales | E44: =VLOOKUP($A44,CF!$1:$1048576,MATCH(Summary!E$13,CF!$3:$3,0),FALSE) -> 248 | F44: =VLOOKUP($A44,CF!$1:$1048576,MATCH(Summary!F$13,CF!$3:$3,0),FALSE) -> 255 | G44: =VLOOKUP($A44,CF!$1:$1048576,MATCH(Summary!G$13,CF!$3:$3,0),FALSE) -> 205 | H44: =VLOOKUP($A44,CF!$1:$1048576,MATCH(Summary!H$13,CF!$3:$3,0),FALSE) -> 0 | I44: =VLOOKUP($A44,CF!$1:$1048576,MATCH(Summary!I$13,CF!$3:$3,0),FALSE) -> 0 | J44: =VLOOKUP($A44,CF!$1:$1048576,MATCH(Summary!J$13,CF!$3:$3,0),FALSE) -> 0 | L44: EBIT Growth | M44: =VLOOKUP($B44,PL!$1:$1048576,MATCH(Summary!M$13,CF!$3:$3,0),FALSE) -> 0.017515052 | N44: =VLOOKUP($B44,PL!$1:$1048576,MATCH(Summary!N$13,CF!$3:$3,0),FALSE) -> 0.10650888 | O44: =VLOOKUP($B44,PL!$1:$1048576,MATCH(Summary!O$13,CF!$3:$3,0),FALSE) -> 0.026737968 | P44: =VLOOKUP($B44,PL!$1:$1048576,MATCH(Summary!P$13,CF!$3:$3,0),FALSE) -> 0.14026232 | Q44: =VLOOKUP($B44,PL!$1:$1048576,MATCH(Summary!Q$13,CF!$3:$3,0),FALSE) -> 0.084380366 | R44: =VLOOKUP($B44,PL!$1:$1048576,MATCH(Summary!R$13,CF!$3:$3,0),FALSE) -> 0.059194848
A45: Lease Repayment | B45: NPAT Growth | D45: Lease repayments | E45: =VLOOKUP($A45,CF!$1:$1048576,MATCH(Summary!E$13,CF!$3:$3,0),FALSE) -> -907 | F45: =VLOOKUP($A45,CF!$1:$1048576,MATCH(Summary!F$13,CF!$3:$3,0),FALSE) -> -834 | G45: =VLOOKUP($A45,CF!$1:$1048576,MATCH(Summary!G$13,CF!$3:$3,0),FALSE) -> -911 | H45: =VLOOKUP($A45,CF!$1:$1048576,MATCH(Summary!H$13,CF!$3:$3,0),FALSE) -> -956.55 | I45: =VLOOKUP($A45,CF!$1:$1048576,MATCH(Summary!I$13,CF!$3:$3,0),FALSE) -> -1004.3775 | J45: =VLOOKUP($A45,CF!$1:$1048576,MATCH(Summary!J$13,CF!$3:$3,0),FALSE) -> -1054.5964 | L45: NPAT Growth | M45: =VLOOKUP($B45,PL!$1:$1048576,MATCH(Summary!M$13,CF!$3:$3,0),FALSE) -> -0.0028708134 | N45: =VLOOKUP($B45,PL!$1:$1048576,MATCH(Summary!N$13,CF!$3:$3,0),FALSE) -> 0.082533589 | O45: =VLOOKUP($B45,PL!$1:$1048576,MATCH(Summary!O$13,CF!$3:$3,0),FALSE) -> -0.021276596 | P45: =VLOOKUP($B45,PL!$1:$1048576,MATCH(Summary!P$13,CF!$3:$3,0),FALSE) -> 0.17648443 | Q45: =VLOOKUP($B45,PL!$1:$1048576,MATCH(Summary!Q$13,CF!$3:$3,0),FALSE) -> 0.10243967 | R45: =VLOOKUP($B45,PL!$1:$1048576,MATCH(Summary!R$13,CF!$3:$3,0),FALSE) -> 0.068957877
A46: Other investing | D46: Other investing | E46: =VLOOKUP($A46,CF!$1:$1048576,MATCH(Summary!E$13,CF!$3:$3,0),FALSE) -> 266 | F46: =VLOOKUP($A46,CF!$1:$1048576,MATCH(Summary!F$13,CF!$3:$3,0),FALSE) -> -97 | G46: =VLOOKUP($A46,CF!$1:$1048576,MATCH(Summary!G$13,CF!$3:$3,0),FALSE) -> -82 | H46: =VLOOKUP($A46,CF!$1:$1048576,MATCH(Summary!H$13,CF!$3:$3,0),FALSE) -> 0 | I46: =VLOOKUP($A46,CF!$1:$1048576,MATCH(Summary!I$13,CF!$3:$3,0),FALSE) -> 0 | J46: =VLOOKUP($A46,CF!$1:$1048576,MATCH(Summary!J$13,CF!$3:$3,0),FALSE) -> 0 | L46: EPS Growth | M46: =VLOOKUP($B47,PL!$1:$1048576,MATCH(Summary!M$13,CF!$3:$3,0),FALSE) -> -0.0080874833 | N46: =VLOOKUP($B47,PL!$1:$1048576,MATCH(Summary!N$13,CF!$3:$3,0),FALSE) -> 0.082533589 | O46: =VLOOKUP($B47,PL!$1:$1048576,MATCH(Summary!O$13,CF!$3:$3,0),FALSE) -> -0.022737377 | P46: =VLOOKUP($B47,PL!$1:$1048576,MATCH(Summary!P$13,CF!$3:$3,0),FALSE) -> 0.1747311 | Q46: =VLOOKUP($B47,PL!$1:$1048576,MATCH(Summary!Q$13,CF!$3:$3,0),FALSE) -> 0.10079913 | R46: =VLOOKUP($B47,PL!$1:$1048576,MATCH(Summary!R$13,CF!$3:$3,0),FALSE) -> 0.067369529
B47: EPS Growth | D47: FCF | E47: =SUM(E41:E46) -> 886 | F47: =SUM(F41:F46) -> 423 | G47: =SUM(G41:G46) -> 641 | H47: =SUM(H41:H46) -> 1136.994 | I47: =SUM(I41:I46) -> 1262.5886 | J47: =SUM(J41:J46) -> 1373.3766 | L47: RoE | M47: =E29/M35 -> 0.31048868 | N47: =F29/N35 -> 0.31186066 | O47: =G29/O35 -> 0.29006831 | P47: =H29/P35 -> 0.32472224 | Q47: =I29/Q35 -> 0.33982183 | R47: =J29/R35 -> 0.34455707
A48: Dividends paid | D48: Dividends paid | E48: =VLOOKUP($A48,CF!$1:$1048576,MATCH(Summary!E$13,CF!$3:$3,0),FALSE) -> -844 | F48: =VLOOKUP($A48,CF!$1:$1048576,MATCH(Summary!F$13,CF!$3:$3,0),FALSE) -> -853 | G48: =VLOOKUP($A48,CF!$1:$1048576,MATCH(Summary!G$13,CF!$3:$3,0),FALSE) -> -889 | H48: =VLOOKUP($A48,CF!$1:$1048576,MATCH(Summary!H$13,CF!$3:$3,0),FALSE) -> -1104.9932 | I48: =VLOOKUP($A48,CF!$1:$1048576,MATCH(Summary!I$13,CF!$3:$3,0),FALSE) -> -1218.0836 | J48: =VLOOKUP($A48,CF!$1:$1048576,MATCH(Summary!J$13,CF!$3:$3,0),FALSE) -> -1301.9684 | L48: Valuation | M48: FY23 | N48: FY24 | O48: FY25 | P48: FY26E | Q48: FY27E | R48: FY28E
A49: Other financing | D49: Other financing | E49: =VLOOKUP($A49,CF!$1:$1048576,MATCH(Summary!E$13,CF!$3:$3,0),FALSE) -> -71 | F49: =VLOOKUP($A49,CF!$1:$1048576,MATCH(Summary!F$13,CF!$3:$3,0),FALSE) -> -40 | G49: =VLOOKUP($A49,CF!$1:$1048576,MATCH(Summary!G$13,CF!$3:$3,0),FALSE) -> -42 | H49: =VLOOKUP($A49,CF!$1:$1048576,MATCH(Summary!H$13,CF!$3:$3,0),FALSE) -> 0 | I49: =VLOOKUP($A49,CF!$1:$1048576,MATCH(Summary!I$13,CF!$3:$3,0),FALSE) -> 0 | J49: =VLOOKUP($A49,CF!$1:$1048576,MATCH(Summary!J$13,CF!$3:$3,0),FALSE) -> 0 | L49: P/E | M49: =$F$9/E31 -> 27.941344 | N49: =$F$9/F31 -> 25.811064 | O49: =$F$9/G31 -> 26.411594 | P49: =$F$9/H31 -> 22.483098 | Q49: =$F$9/I31 -> 20.424342 | R49: =$F$9/J31 -> 19.135212
A50: Other FCF | D50: FCF post financing | E50: =E47+E48+E49 -> -29 | F50: =F47+F48+F49 -> -470 | G50: =G47+G48+G49 -> -290 | H50: =H47+H48+H49 -> 32.000767 | I50: =I47+I48+I49 -> 44.505048 | J50: =J47+J48+J49 -> 71.408231 | L50: Div Yield | M50: =E32/$F$9 -> 0.030330882 | N50: =F32/$F$9 -> 0.03125 | O50: =G32/$F$9 -> 0.031709559 | P50: =H32/$F$9 -> 0.037806178 | Q50: =I32/$F$9 -> 0.041617008 | R50: =J32/$F$9 -> 0.044420727
A51: Net Chg Cash | D51: Change in net debt | E51: =VLOOKUP($A52,BS!$1:$1048576,MATCH(Summary!E$13,CF!$3:$3,0),FALSE) -> 15 | F51: =VLOOKUP($A52,BS!$1:$1048576,MATCH(Summary!F$13,CF!$3:$3,0),FALSE) -> 456 | G51: =VLOOKUP($A52,BS!$1:$1048576,MATCH(Summary!G$13,CF!$3:$3,0),FALSE) -> 302 | H51: =VLOOKUP($A52,BS!$1:$1048576,MATCH(Summary!H$13,CF!$3:$3,0),FALSE) -> -32.000767 | I51: =VLOOKUP($A52,BS!$1:$1048576,MATCH(Summary!I$13,CF!$3:$3,0),FALSE) -> -44.505048 | J51: =VLOOKUP($A52,BS!$1:$1048576,MATCH(Summary!J$13,CF!$3:$3,0),FALSE) -> -71.408231 | L51: Return on Equity | M51: =E29/M35 -> 0.31048868 | N51: =F29/N35 -> 0.31186066 | O51: =G29/O35 -> 0.29006831 | P51: =H29/P35 -> 0.32472224 | Q51: =I29/Q35 -> 0.33982183 | R51: =J29/R35 -> 0.34455707
A52: Chg in Net Debt | L52: Payout Ratio | M52: =VLOOKUP($B53,PL!$1:$1048576,MATCH(Summary!M$13,PL!$3:$3,0),FALSE) -> 0.84495202 | N52: =VLOOKUP($B53,PL!$1:$1048576,MATCH(Summary!N$13,PL!$3:$3,0),FALSE) -> 0.80745141 | O52: =VLOOKUP($B53,PL!$1:$1048576,MATCH(Summary!O$13,PL!$3:$3,0),FALSE) -> 0.83831592 | P52: =VLOOKUP($B53,PL!$1:$1048576,MATCH(Summary!P$13,PL!$3:$3,0),FALSE) -> 0.85 | Q52: =VLOOKUP($B53,PL!$1:$1048576,MATCH(Summary!Q$13,PL!$3:$3,0),FALSE) -> 0.85 | R52: =VLOOKUP($B53,PL!$1:$1048576,MATCH(Summary!R$13,PL!$3:$3,0),FALSE) -> 0.85
B53: Payout Ratio | L53: FCF Yield | M53: =(E47/E30)/$F$9 -> 0.030431175 | N53: =(F47/F30)/$F$9 -> 0.014528653 | O53: =(G47/G30)/$F$9 -> 0.021983374 | P53: =(H47/H30)/$F$9 -> 0.038935591 | Q53: =(I47/I30)/$F$9 -> 0.043172154 | R53: =(J47/J30)/$F$9 -> 0.04689059
D54: Note: FY24 includes 53 weeks vs. all other years include 52 weeks.

Sheet Model
B1: Coles Group (COL.AX)
B2: A$M
C3: FY17 | D3: FY18 | E3: FY19 | F3: FY20 | G3: FY21 | H3: FY22 | I3: FY23 | J3: FY24 | K3: FY25 | L3: FY26E | M3: FY27E | N3: FY28E | O3: FY29E | P3: FY30E | S3: 1H17 | T3: 2H17 | U3: 1H18 | V3: 2H18 | W3: 1H19 | X3: 2H19 | Y3: 1H20 | Z3: 2H20 | AA3: 1H21 | AB3: 2H21 | AC3: 1H22 | AD3: 2H22 | AE3: 1H23 | AF3: 2H23 | AG3: 1H24 | AH3: 2H24 | AI3: 1H25 | AJ3: 2H25 | AK3: 1H26E | AL3: 2H26E
B4: Model Summary
B6: Sales
A7: Food Sales | B7: Food | C7: =C23 -> 29754 | D7: =D23 -> 29919 | E7: =E23 -> 30890 | F7: =F23 -> 32993 | G7: =G23 -> 33868 | H7: =H23 -> 34624 | I7: =I23 -> 36746 | J7: =J23 -> 39042 | ... P7: =P23 -> 49424.403 | U7: =U23 -> 15525 | V7: =V23 -> 14394 | W7: =W23 -> 16069 | X7: =X23 -> 14821 | Y7: =Y23 -> 16593 | Z7: =Z23 -> 16400 | AA7: =AA23 -> 17812 | AB7: =AB23 -> 16056 | ... AL7: =AL23 -> 20175.977
A8: Liquor Sales | B8: Liquor | C8: =C93 -> 3223 | D8: =D93 -> 3314 | E8: =E93 -> 3063 | F8: =F93 -> 3308 | G8: =G93 -> 3525 | H8: =H93 -> 3613 | I8: =I93 -> 3610 | J8: =J93 -> 3692 | ... P8: =P93 -> 4014.2398 | U8: =U93 -> 1721 | V8: =V93 -> 1593 | W8: =W93 -> 1637 | X8: =X93 -> 1426 | Y8: =Y93 -> 1691 | Z8: =Z93 -> 1617 | AA8: =AA93 -> 1946 | AB8: =AB93 -> 1579 | ... AL8: =AL93 -> 1651.7412
B9: Coles Express (Divested FY23) | C9: 6133 | D9: 5761 | E9: 1048 | F9: 1107 | G9: 1192 | U9: 2992 | V9: =D9-U9 -> 2769 | W9: 547 | X9: =E9-W9 -> 501 | Y9: 572 | Z9: =F9-Y9 -> 535 | AA9: 632 | AB9: =G9-AA9 -> 560
A10: Corporate/Other Sales | B10: Corporate / Other | C10: =C153 -> 16 | D10: =D153 -> 13 | E10: =E153 -> 0 | F10: =F153 -> 0 | G10: =G153 -> 0 | H10: =H153 -> 0 | I10: =I153 -> 127 | J10: =J153 -> 837 | ... P10: =P153 -> 0 | U10: =U153 -> 8 | V10: =V153 -> 5 | W10: =W153 -> 13 | X10: =X153 -> -13 | Y10: =Y153 -> 0 | Z10: =Z153 -> 0 | AA10: =AA153 -> 0 | AB10: =AB153 -> 0 | ... AL10: =AL153 -> 177.6
A11: Total Sales | B11: Group Sales from Continuing Ops. | C11: 39125 | D11: =SUM(D7:D10) -> 39007 | E11: =SUM(E7:E10) -> 35001 | F11: =SUM(F7:F10) -> 37408 | G11: =SUM(G7:G10) -> 38585 | H11: =SUM(H7:H10) -> 38237 | I11: =SUM(I7:I10) -> 40483 | J11: =SUM(J7:J10) -> 43571 | K11: =SUM(K7:K10) -> 44352 | ... P11: =SUM(P7:P10) -> 53438.643 | U11: =SUM(U7:U10) -> 20246 | V11: =SUM(V7:V10) -> 18761 | W11: =SUM(W7:W10) -> 18266 | X11: =SUM(X7:X10) -> 16735 | Y11: =SUM(Y7:Y10) -> 18856 | Z11: =SUM(Z7:Z10) -> 18552 | AA11: =SUM(AA7:AA10) -> 20390 | AB11: =SUM(AB7:AB10) -> 18195 | ... AL11: =SUM(AL7:AL10) -> 22005.318
B12: Discontinued Ops | C12: 0 | D12: 0 | E12: 0 | F12: 0 | G12: 0 | H12: 1132 | I12: 988 | J12: 0 | K12: 0 | U12: 0 | V12: =D12-U12 -> 0 | W12: 0 | X12: =E12-W12 -> 0 | Y12: 0 | Z12: =F12-Y12 -> 0 | AA12: 0 | AB12: =G12-AA12 -> 0 | AC12: 578 | AD12: =H12-AC12 -> 554 | AE12: 578 | AF12: =I12-AE12 -> 410 | AG12: 0 | AH12: =J12-AG12 -> 0 | AI12: 0 | AJ12: =K12-AI12 -> 0
B13: Total Group Sales (Reported) | C13: =C11+C12 -> 39125 | D13: =D11+D12 -> 39007 | E13: =E11+E12 -> 35001 | F13: =F11+F12 -> 37408 | G13: =G11+G12 -> 38585 | H13: =H11+H12 -> 39369 | I13: =I11+I12 -> 41471 | J13: =J11+J12 -> 43571 | K13: =K11+K12 -> 44352 | U13: =SUM(U11:U12) -> 20246 | V13: =SUM(V11:V12) -> 18761 | W13: =SUM(W11:W12) -> 18266 | X13: =SUM(X11:X12) -> 16735 | Y13: =SUM(Y11:Y12) -> 18856 | Z13: =SUM(Z11:Z12) -> 18552 | AA13: =SUM(AA11:AA12) -> 20390 | AB13: =SUM(AB11:AB12) -> 18195 | ... AJ13: =SUM(AJ11:AJ12) -> 21317
B15: EBIT
A16: Food EBIT | B16: Food | C16: =C50 -> 1186 | D16: =D50 -> 1157 | E16: =E50 -> 1183 | F16: =F50 -> 1618 | G16: =G50 -> 1702 | H16: =H50 -> 1715 | I16: =I50 -> 1765 | J16: =J50 -> 2018 | ... P16: =P50 -> 2994.765 | U16: =U50 -> 600 | V16: =V50 -> 557 | W16: =W50 -> 602 | X16: =X50 -> 581 | Y16: =Y50 -> 789 | Z16: =Z50 -> 829 | AA16: =AA50 -> 903 | AB16: =AB50 -> 799 | ... AL16: =AL50 -> 1186.2023
A17: Liquor EBIT | B17: Liquor | C17: =C119 -> 138 | D17: =D119 -> 130 | E17: =E119 -> 120 | F17: =F119 -> 138 | G17: =G119 -> 165 | H17: =H119 -> 163 | I17: =I119 -> 157 | J17: =J119 -> 133 | ... P17: =P119 -> 143.50449 | U17: =U119 -> 80 | V17: =V119 -> 50 | W17: =W119 -> 74 | X17: =X119 -> 46 | Y17: =Y119 -> 76 | Z17: =Z119 -> 62 | AA17: =AA119 -> 104 | AB17: =AB119 -> 61 | ... AL17: =AL119 -> 38.929383
B18: Coles Express (Divested FY23) | C18: 190 | D18: 133 | E18: 50 | F18: 33 | G18: 67 | U18: 84 | V18: =D18-U18 -> 49 | W18: 51 | X18: =E18-W18 -> -1 | Y18: 28 | Z18: =F18-Y18 -> 5 | AA18: 32 | AB18: =G18-AA18 -> 35
A19: Corporate/Other EBIT | B19: Corporate / Other | C19: =C166 -> 0 | D19: =D166 -> -25 | E19: =E166 -> -28 | F19: =F166 -> -27 | G19: =G166 -> -61 | H19: =H166 -> -51 | I19: =I166 -> -63 | J19: =J166 -> -94 | ... P19: =P166 -> -129.04233 | U19: =U166 -> 15 | V19: =V166 -> -40 | W19: =W166 -> -5 | X19: =X166 -> -23 | Y19: =Y166 -> 17 | Z19: =Z166 -> -44 | AA19: =AA166 -> -19 | AB19: =AB166 -> -42 | ... AL19: =AL166 -> -68.543324
A20: Total EBIT | B20: Group EBIT | C20: =SUM(C16:C19) -> 1514 | D20: =SUM(D16:D19) -> 1395 | E20: =SUM(E16:E19) -> 1325 | F20: =SUM(F16:F19) -> 1762 | G20: =SUM(G16:G19) -> 1873 | H20: =SUM(H16:H19) -> 1827 | I20: =SUM(I16:I19) -> 1859 | J20: =SUM(J16:J19) -> 2057 | ... P20: =SUM(P16:P19) -> 3009.2272 | U20: =SUM(U16:U19) -> 779 | V20: =SUM(V16:V19) -> 616 | W20: =SUM(W16:W19) -> 722 | X20: =SUM(X16:X19) -> 603 | Y20: =SUM(Y16:Y19) -> 910 | Z20: =SUM(Z16:Z19) -> 852 | AA20: =SUM(AA16:AA19) -> 1020 | AB20: =SUM(AB16:AB19) -> 853 | ... AL20: =SUM(AL16:AL19) -> 1156.5883
B22: Food
B23: Sales | C23: 29754 | D23: 29919 | E23: 30890 | F23: 32993 | G23: 33868 | H23: 34624 | I23: 36746 | J23: 39042 | K23: 39987 | L23: =K23*(1+L24) -> 41681.565 | M23: =L23*(1+M24) -> 43506.93 | N23: =M23*(1+N24) -> 45404.069 | O23: =N23*(1+O24) -> 47375.642 | P23: =O23*(1+P24) -> 49424.403 | U23: 15525 | V23: =D23-U23 -> 14394 | W23: 16069 | X23: =E23-W23 -> 14821 | Y23: 16593 | Z23: =F23-Y23 -> 16400 | AA23: 17812 | AB23: =G23-AA23 -> 16056 | AC23: 18016 | AD23: =H23-AC23 -> 16608 | AE23: 18857 | AF23: =I23-AE23 -> 17889 | AG23: 19778 | AH23: =J23-AG23 -> 19264 | AI23: 20629 | AJ23: =K23-AI23 -> 19358 | AK23: =AI23*(1+AK24) -> 21505.588 | AL23: =L23-AK23 -> 20175.977
A24: Food Growth | B24: Growth % | D24: =D23/C23-1 -> 0.0055454729 | E24: =E23/D23-1 -> 0.032454293 | F24: =F23/E23-1 -> 0.068080285 | G24: =G23/F23-1 -> 0.026520777 | H24: =H23/G23-1 -> 0.022321956 | I24: =I23/H23-1 -> 0.061286969 | J24: =J23/I23-1 -> 0.062482991 | K24: =K23/J23-1 -> 0.024204703 | L24: =SUM(L26:L28) -> 0.042377907 | M24: =SUM(M26:M28) -> 0.043793103 | N24: =SUM(N26:N28) -> 0.043605442 | O24: =SUM(O26:O28) -> 0.043422819 | P24: =SUM(P26:P28) -> 0.043245033 | W24: =W23/U23-1 -> 0.035040258 | X24: =X23/V23-1 -> 0.029665138 | Y24: =Y23/W23-1 -> 0.032609372 | Z24: =Z23/X23-1 -> 0.10653802 | AA24: =AA23/Y23-1 -> 0.073464714 | AB24: =AB23/Z23-1 -> -0.02097561 | AC24: =AC23/AA23-1 -> 0.011452953 | AD24: =AD23/AB23-1 -> 0.034379671 | ... AJ24: =AJ23/AH23-1 -> 0.0048795681 | AK24: =SUM(AK26:AK28) -> 0.042493007 | AL24: =AL23/AJ23-1 -> 0.04225525
A25: Food Growth ex Tobacco | B25: Growth ex Tobacco % | I25: 0.074 | J25: 0.057 | K25: 0.057
A26: Food Comp | B26: LFL Sales Growth % | D26: 0.011 | E26: 0.027 | F26: 0.059 | G26: 0.025 | H26: 0.026 | I26: 0.058 | J26: 0.034 | K26: 0.037 | L26: =VLOOKUP($A26,Quarterly!$1:$1048576,MATCH(Model!L$3,Quarterly!$3:$3,0),FALSE) -> 0.03875 | M26: 0.035 | N26: 0.035 | O26: 0.035 | P26: 0.035 | U26: 0.009 | V26: =D26 -> 0.011 | W26: 0.032 | X26: 0.022 | Y26: 0.02 | Z26: 0.1 | AA26: 0.072 | AB26: -0.022 | AC26: 0.015 | AD26: 0.038 | AE26: 0.049 | AF26: 0.067 | AG26: 0.04 | AH26: 0.026 | AI26: 0.034 | AJ26: 0.041 | AK26: =VLOOKUP($A26,Quarterly!$1:$1048576,MATCH(Model!AK$3,Quarterly!$3:$3,0),FALSE) -> 0.0405 | AL26: =VLOOKUP($A26,Quarterly!$1:$1048576,MATCH(Model!AL$3,Quarterly!$3:$3,0),FALSE) -> 0.037
B27: Store Growth % | E27: =E66/D66-1 -> 0.014833127 | F27: =F66/E66-1 -> 0.0036540804 | G27: =G66/F66-1 -> 0.012135922 | H27: =H66/G66-1 -> 0.0011990408 | I27: =I66/H66-1 -> 0.013173653 | J27: =J66/I66-1 -> 0.011820331 | K27: =K66/J66-1 -> 0.0046728972 | L27: =L66/K66-1 -> 0.011627907 | ... P27: =P66/O66-1 -> 0.013245033 | Y27: =Y66/W66-1 -> 0.0085784314 | Z27: =Z66/X66-1 -> 0.0036540804 | AA27: =AA66/Y66-1 -> 0.012150668 | AB27: =AB66/Z66-1 -> 0.012135922 | AC27: =AC66/AA66-1 -> 0.0024009604 | AD27: =AD66/AB66-1 -> 0.0011990408 | AE27: =AE66/AC66-1 -> 0.0083832335 | AF27: =AF66/AD66-1 -> 0.013173653 | ... AL27: =AL66/AJ66-1 -> 0.011627907
B28: Other | E28: =E24-SUM(E26:E27) -> -0.0093788341 | F28: =F24-SUM(F26:F27) -> 0.0054262045 | G28: =G24-SUM(G26:G27) -> -0.010615145 | H28: =H24-SUM(H26:H27) -> -0.0048770849 | I28: =I24-SUM(I26:I27) -> -0.0098866841 | J28: =J24-SUM(J26:J27) -> 0.01666266 | K28: =K24-SUM(K26:K27) -> -0.017468195 | L28: -0.008 | M28: -0.005 | N28: -0.005 | O28: -0.005 | P28: -0.005 | Y28: =Y24-SUM(Y26:Y27) -> 0.0040309407 | Z28: =Z24-SUM(Z26:Z27) -> 0.00288394 | AA28: =AA24-SUM(AA26:AA27) -> -0.010685954 | AB28: =AB24-SUM(AB26:AB27) -> -0.011111532 | AC28: =AC24-SUM(AC26:AC27) -> -0.0059480073 | AD28: =AD24-SUM(AD26:AD27) -> -0.0048193696 | AE28: =AE24-SUM(AE26:AE27) -> -0.010702505 | AF28: =AF24-SUM(AF26:AF27) -> -0.0030421498 | ... AJ28: =AJ24-SUM(AJ26:AJ27) -> -0.040793329 | AK28: -0.005 | AL28: =AL24-SUM(AL26:AL27) -> -0.0063726572
A30: Food GP | B30: Gross Profit | D30: =D32*D23 -> 7360.074 | E30: =E32*E23 -> 7660.72 | F30: =F32*F23 -> 8413.215 | G30: =G32*G23 -> 8771.812 | H30: =H32*H23 -> 9106.112 | I30: =I32*I23 -> 9700.944 | J30: =J32*J23 -> 10424.214 | K30: =K32*K23 -> 10996.425 | ... P30: =P32*P23 -> 13967.336 | U30: =U32*U23 -> 3726 | V30: =D30-U30 -> 3634.074 | W30: =W32*W23 -> 3920.836 | X30: =E30-W30 -> 3739.884 | Y30: =Y32*Y23 -> 4164.843 | Z30: =F30-Y30 -> 4248.372 | AA30: =AA32*AA23 -> 4613.308 | AB30: =G30-AA30 -> 4158.504 | AC30: =AC32*AC23 -> 4702.176 | AD30: =H30-AC30 -> 4403.936 | AE30: =AE32*AE23 -> 4997.105 | AF30: =I30-AE30 -> 4703.839 | AG30: =AG32*AG23 -> 5260.948 | AH30: =J30-AG30 -> 5163.266 | AI30: =AI32*AI23 -> 5672.975 | AJ30: =K30-AI30 -> 5323.45 | AK30: =AK32*AK23 -> 6025.8658 | AL30: =L30-AK30 -> 5649.1406
B31: Growth % | E31: =E30/D30-1 -> 0.040848231 | F31: =F30/E30-1 -> 0.098227712 | G31: =G30/F30-1 -> 0.042623064 | H31: =H30/G30-1 -> 0.038110712 | I31: =I30/H30-1 -> 0.06532228 | J31: =J30/I30-1 -> 0.074556662 | K31: =K30/J30-1 -> 0.054892484 | L31: =L30/K30-1 -> 0.061709279 | ... P31: =P30/O30-1 -> 0.043245033 | W31: =W30/U30-1 -> 0.052290929 | X31: =X30/V30-1 -> 0.029116083 | Y31: =Y30/W30-1 -> 0.062233411 | Z31: =Z30/X30-1 -> 0.13596358 | AA31: =AA30/Y30-1 -> 0.10767873 | AB31: =AB30/Z30-1 -> -0.021153515 | AC31: =AC30/AA30-1 -> 0.019263401 | AD31: =AD30/AB30-1 -> 0.059019301 | ... AJ31: =AJ30/AH30-1 -> 0.031023774 | AK31: =AK30/AJ30-1 -> 0.13194748 | AL31: =AL30/AJ30-1 -> 0.061180369
A32: Food GPM | B32: Gross Margin | D32: 0.246 | E32: 0.248 | F32: 0.255 | G32: 0.259 | H32: 0.263 | I32: 0.264 | J32: 0.267 | K32: 0.275 | L32: =K32+L33 -> 0.2801 | M32: =L32+M33 -> 0.2821 | N32: =M32+N33 -> 0.2826 | O32: =N32+O33 -> 0.2826 | P32: =O32+P33 -> 0.2826 | U32: 0.24 | V32: =V30/V23 -> 0.25247145 | W32: 0.244 | X32: =X30/X23 -> 0.25233682 | Y32: 0.251 | Z32: =Z30/Z23 -> 0.25904707 | AA32: 0.259 | AB32: =AB30/AB23 -> 0.259 | AC32: 0.261 | AD32: =AD30/AD23 -> 0.26516956 | AE32: 0.265 | AF32: =AF30/AF23 -> 0.26294589 | AG32: 0.266 | AH32: =AH30/AH23 -> 0.26802668 | AI32: 0.275 | AJ32: =AJ30/AJ23 -> 0.275 | AK32: =AI32+AK33 -> 0.2802 | AL32: =AL30/AL23 -> 0.27999341
B33: Change YoY % | E33: 0.002 | F33: 0.003 | G33: 0.0035 | H33: 0.0042 | I33: 0.0005 | J33: 0.005 | K33: 0.0079 | L33: 0.0051 | M33: 0.002 | N33: 0.0005 | O33: 0 | P33: 0 | V33: =V32-T32 -> 0.25247145 | W33: =W32-U32 -> 0.004 | X33: =X32-V32 -> -0.00013462706 | Y33: =Y32-W32 -> 0.007 | Z33: =Z32-X32 -> 0.0067102538 | AA33: =AA32-Y32 -> 0.008 | AB33: =AB32-Z32 -> -4.7073171e-05 | AC33: =AC32-AA32 -> 0.002 | ... AF33: =AF32-AD32 -> -0.0022236683 | AG33: 0.0007 | AH33: =AH32-AF32 -> 0.0050807934 | AI33: 0.0088 | AJ33: =AJ32-AH32 -> 0.0069733181 | AK33: 0.0052 | AL33: =AL32-AJ32 -> 0.0049934099
B35: CODB | G35: =G40-G30 -> -5770.812 | H35: =H40-H30 -> -6084.112 | I35: =I40-I30 -> -6543.944 | J35: =J40-J30 -> -6937.214 | K35: =K40-K30 -> -7208.425 | L35: =K35*(1+L36) -> -7438.3738 | M35: =L35*(1+M36) -> -7758.2238 | N35: =M35*(1+N36) -> -8068.5528 | O35: =N35*(1+O36) -> -8415.5006 | P35: =O35*(1+P36) -> -8777.3671 | U35: =U40-U30 -> -2835 | V35: =V40-V30 -> -2811.074 | W35: =W40-W30 -> -3033.836 | X35: =X40-X30 -> -2891.884 | Y35: =Y40-Y30 -> -2743.843 | Z35: =Z40-Z30 -> -2802.372 | AA35: =AA40-AA30 -> -3058.308 | AB35: =AB40-AB30 -> -2712.504 | ... AJ35: =AJ40-AJ30 -> -3470.45 | AK35: =AI35*(1+AK36) -> -3859.0854 | AL35: =L35-AK35 -> -3579.2884
B36: Growth % | H36: =H35/G35-1 -> 0.054290453 | I36: =I35/H35-1 -> 0.075579148 | J36: =J35/I35-1 -> 0.060096786 | K36: =K35/J35-1 -> 0.039095089 | L36: 0.0319 | M36: 0.043 | N36: 0.04 | O36: 0.043 | P36: 0.043 | W36: =W35/U35-1 -> 0.070136155 | X36: =X35/V35-1 -> 0.02874702 | Y36: =Y35/W35-1 -> -0.095586248 | Z36: =Z35/X35-1 -> -0.030952832 | AA36: =AA35/Y35-1 -> 0.1146075 | AB36: =AB35/Z35-1 -> -0.032068548 | AC36: =AC35/AA35-1 -> 0.030038832 | AD36: =AD35/AB35-1 -> 0.081633797 | ... AJ36: =AJ35/AH35-1 -> 0.018842921 | AK36: 0.0324 | AL36: =AL35/AJ35-1 -> 0.031361457
B37: % of Sales | G37: =G35/G23 -> -0.17039128 | H37: =H35/H23 -> -0.1757195 | I37: =I35/I23 -> -0.17808589 | J37: =J35/J23 -> -0.17768593 | K37: =K35/K23 -> -0.18026921 | L37: =L35/L23 -> -0.17845716 | M37: =M35/M23 -> -0.17832156 | N37: =N35/N23 -> -0.1777055 | ... P37: =P35/P23 -> -0.17759177 | U37: =U35/U23 -> -0.1826087 | V37: =V35/V23 -> -0.19529485 | W37: =W35/W23 -> -0.18880055 | X37: =X35/X23 -> -0.19512071 | Y37: =Y35/Y23 -> -0.16536148 | Z37: =Z35/Z23 -> -0.17087634 | AA37: =AA35/AA23 -> -0.1716993 | AB37: =AB35/AB23 -> -0.16894021 | ... AL37: =AL35/AL23 -> -0.17740347
B38: Change YoY % | H38: =H37-G37 -> -0.0053282171 | I38: =I37-H37 -> -0.002366386 | J38: =J37-I37 -> 0.00039995892 | K38: =K37-J37 -> -0.0025832845 | L38: =L37/K37-1 -> -0.010051927 | M38: =M37/L37-1 -> -0.00075982821 | N38: =N37/M37-1 -> -0.0034547943 | O38: =O37/N37-1 -> -0.00040522287 | P38: =P37/O37-1 -> -0.0002348759 | U38: =U37-T37 -> -0.1826087 | V38: =V37-U37 -> -0.012686149 | W38: =W37-V37 -> 0.0064942974 | X38: =X37-W37 -> -0.0063201595 | Y38: =Y37-X37 -> 0.029759229 | Z38: =Z37-Y37 -> -0.0055148637 | AA38: =AA37-Z37 -> -0.00082296238 | AB38: =AB37-AA37 -> 0.0027590946 | ... AJ38: =AJ37-AI37 -> 0.0019227083 | AK38: =AK37/AJ37-1 -> 0.00093933332 | AL38: =AL37/AK37-1 -> -0.011380778
B40: EBITDA | D40: 1714 | E40: 1735 | F40: 2867 | G40: 3001 | H40: 3022 | I40: 3157 | J40: 3487 | K40: 3788 | L40: =L30+L35 -> 4236.6327 | M40: =M30+M35 -> 4515.0813 | N40: =N30+N35 -> 4762.6372 | O40: =O30+O35 -> 4972.8559 | P40: =P30+P35 -> 5189.9693 | U40: 891 | V40: =D40-U40 -> 823 | W40: 887 | X40: =E40-W40 -> 848 | Y40: 1421 | Z40: =F40-Y40 -> 1446 | AA40: 1555 | AB40: =G40-AA40 -> 1446 | AC40: 1552 | AD40: =H40-AC40 -> 1470 | AE40: 1676 | AF40: =I40-AE40 -> 1481 | AG40: 1730 | AH40: =J40-AG40 -> 1757 | AI40: 1935 | AJ40: =K40-AI40 -> 1853 | AK40: =AK30+AK35 -> 2166.7804 | AL40: =L40-AK40 -> 2069.8523
B41: Growth % | E41: =E40/D40-1 -> 0.012252042 | F41: =F40/E40-1 -> 0.65244957 | G41: =G40/F40-1 -> 0.046738751 | H41: =H40/G40-1 -> 0.0069976674 | I41: =I40/H40-1 -> 0.044672402 | J41: =J40/I40-1 -> 0.10452962 | K41: =K40/J40-1 -> 0.086320619 | L41: =L40/K40-1 -> 0.11843524 | ... P41: =P40/O40-1 -> 0.0436597 | W41: =W40/U40-1 -> -0.0044893378 | X41: =X40/V40-1 -> 0.030376671 | Y41: =Y40/W40-1 -> 0.60202931 | Z41: =Z40/X40-1 -> 0.70518868 | AA41: =AA40/Y40-1 -> 0.094299789 | AB41: =AB40/Z40-1 -> 0 | AC41: =AC40/AA40-1 -> -0.0019292605 | AD41: =AD40/AB40-1 -> 0.01659751 | ... AL41: =AL40/AJ40-1 -> 0.11702767
B42: EBITDA Margin | D42: =D40/D23 -> 0.057288011 | E42: =E40/E23 -> 0.056167044 | F42: =F40/F23 -> 0.086897221 | G42: =G40/G23 -> 0.088608716 | H42: =H40/H23 -> 0.087280499 | I42: =I40/I23 -> 0.085914113 | J42: =J40/J23 -> 0.089314072 | K42: =K40/K23 -> 0.094730788 | ... P42: =P40/P23 -> 0.10500823 | U42: =U40/U23 -> 0.057391304 | V42: =V40/V23 -> 0.057176601 | W42: =W40/W23 -> 0.055199452 | X42: =X40/X23 -> 0.057216112 | Y42: =Y40/Y23 -> 0.085638522 | Z42: =Z40/Z23 -> 0.088170732 | AA42: =AA40/AA23 -> 0.087300696 | AB42: =AB40/AB23 -> 0.090059791 | ... AL42: =AL40/AL23 -> 0.10258994
B43: Change YoY % | D43: =D42-C42 -> 0.057288011 | E43: =E42-D42 -> -0.0011209666 | F43: =F42-E42 -> 0.030730176 | G43: =G42-F42 -> 0.0017114956 | H43: =H42-G42 -> -0.0013282171 | I43: =I42-H42 -> -0.001366386 | J43: =J42-I42 -> 0.0033999589 | K43: =K42-J42 -> 0.0054167155 | ... P43: =P42-O42 -> 4.1721825e-05 | U43: =U42-S42 -> 0.057391304 | V43: =V42-T42 -> 0.057176601 | W43: =W42-U42 -> -0.002191852 | X43: =X42-V42 -> 3.9510911e-05 | Y43: =Y42-W42 -> 0.03043907 | Z43: =Z42-X42 -> 0.030954619 | AA43: =AA42-Y42 -> 0.0016621739 | AB43: =AB42-Z42 -> 0.001889059 | ... AL43: =AL42-AJ42 -> 0.0068672406
L44: =L45-K45 -> -126
B45: D&A | D45: -557 | E45: -552 | F45: -1249 | G45: -1299 | H45: -1307 | I45: -1392 | J45: -1460 | K45: -1680 | L45: =K45*(1+L46) -> -1806 | M45: =L45*(1+M46) -> -1896.3 | N45: =M45*(1+N46) -> -1991.115 | O45: =N45*(1+O46) -> -2090.6708 | P45: =O45*(1+P46) -> -2195.2043 | U45: -291 | V45: =V50-V40 -> -266 | W45: -285 | X45: -285 | Y45: -632 | Z45: -632 | AA45: -652 | AB45: =G45-AA45 -> -647 | AC45: -656 | AD45: =H45-AC45 -> -651 | AE45: -685 | AF45: =I45-AE45 -> -707 | AG45: -723 | AH45: =J45-AG45 -> -737 | AI45: -858 | AJ45: =K45-AI45 -> -822 | AK45: =AI45*(1+AK46) -> -922.35 | AL45: =L45-AK45 -> -883.65
B46: Growth % | E46: =E45/D45-1 -> -0.0089766607 | F46: =F45/E45-1 -> 1.2626812 | G46: =G45/F45-1 -> 0.040032026 | H46: =H45/G45-1 -> 0.0061585835 | I46: =I45/H45-1 -> 0.06503443 | J46: =J45/I45-1 -> 0.048850575 | K46: =K45/J45-1 -> 0.15068493 | L46: 0.075 | M46: 0.05 | N46: 0.05 | O46: 0.05 | P46: 0.05 | W46: =W45/U45-1 -> -0.020618557 | X46: =X45/V45-1 -> 0.071428571 | Y46: =Y45/W45-1 -> 1.2175439 | Z46: =Z45/X45-1 -> 1.2175439 | AA46: =AA45/Y45-1 -> 0.03164557 | AB46: =AB45/Z45-1 -> 0.023734177 | AC46: =AC45/AA45-1 -> 0.0061349693 | AD46: =AD45/AB45-1 -> 0.0061823802 | ... AJ46: =AJ45/AH45-1 -> 0.11533243 | AK46: 0.075 | AL46: =AL45/AJ45-1 -> 0.075
B47: % of Sales | D47: =D45/D23 -> -0.018616932 | E47: =E45/E23 -> -0.017869861 | F47: =F45/F23 -> -0.037856515 | G47: =G45/G23 -> -0.038354789 | H47: =H45/H23 -> -0.037748383 | I47: =I45/I23 -> -0.037881674 | J47: =J45/J23 -> -0.037395625 | K47: =K45/K23 -> -0.042013654 | ... P47: =P45/P23 -> -0.044415393 | U47: =U45/U23 -> -0.018743961 | V47: =V45/V23 -> -0.018479922 | W47: =W45/W23 -> -0.017736013 | X47: =X45/X23 -> -0.019229472 | Y47: =Y45/Y23 -> -0.038088351 | Z47: =Z45/Z23 -> -0.038536585 | AA47: =AA45/AA23 -> -0.036604536 | AB47: =AB45/AB23 -> -0.040296462 | ... AL47: =AL45/AL23 -> -0.043797135
B48: Change YoY % | D48: =D47-C47 -> -0.018616932 | E48: =E47-D47 -> 0.00074707159 | F48: =F47-E47 -> -0.019986654 | G48: =G47-F47 -> -0.00049827416 | H48: =H47-G47 -> 0.00060640656 | I48: =I47-H47 -> -0.00013329157 | J48: =J47-I47 -> 0.00048604897 | K48: =K47-J47 -> -0.0046180292 | ... P48: =P47-O47 -> -0.00028573763 | U48: =U47-S47 -> -0.018743961 | V48: =V47-T47 -> -0.018479922 | W48: =W47-U47 -> 0.0010079479 | X48: =X47-V47 -> -0.00074954951 | Y48: =Y47-W47 -> -0.020352337 | Z48: =Z47-X47 -> -0.019307114 | AA48: =AA47-Y47 -> 0.0014838142 | AB48: =AB47-Z47 -> -0.001759877 | ... AL48: =AL47-AJ47 -> -0.0013340709
B50: EBIT | C50: 1186 | D50: 1157 | E50: 1183 | F50: 1618 | G50: 1702 | H50: 1715 | I50: 1765 | J50: 2018 | K50: 2108 | L50: =L40+L45 -> 2430.6327 | M50: =M40+M45 -> 2618.7813 | N50: =N40+N45 -> 2771.5222 | O50: =O40+O45 -> 2882.1852 | P50: =P40+P45 -> 2994.765 | U50: 600 | V50: =D50-U50 -> 557 | W50: 602 | X50: =E50-W50 -> 581 | Y50: 789 | Z50: =F50-Y50 -> 829 | AA50: 903 | AB50: =G50-AA50 -> 799 | AC50: 896 | AD50: =H50-AC50 -> 819 | AE50: 991 | AF50: =I50-AE50 -> 774 | AG50: 1007 | AH50: =J50-AG50 -> 1011 | AI50: 1077 | AJ50: =K50-AI50 -> 1031 | AK50: =AK40+AK45 -> 1244.4304 | AL50: =L50-AK50 -> 1186.2023
B51: Growth % | D51: =D50/C50-1 -> -0.024451939 | E51: =E50/D50-1 -> 0.02247191 | F51: =F50/E50-1 -> 0.36770921 | G51: =G50/F50-1 -> 0.051915946 | H51: =H50/G50-1 -> 0.0076380729 | I51: =I50/H50-1 -> 0.029154519 | J51: =J50/I50-1 -> 0.14334278 | K51: =K50/J50-1 -> 0.044598612 | ... P51: =P50/O50-1 -> 0.039060592 | W51: =W50/U50-1 -> 0.0033333333 | X51: =X50/V50-1 -> 0.043087971 | Y51: =Y50/W50-1 -> 0.31063123 | Z51: =Z50/X50-1 -> 0.42685026 | AA51: =AA50/Y50-1 -> 0.14448669 | AB51: =AB50/Z50-1 -> -0.036188179 | AC51: =AC50/AA50-1 -> -0.007751938 | AD51: =AD50/AB50-1 -> 0.025031289 | ... AL51: =AL50/AJ50-1 -> 0.15053566
A52: Food EBIT Margin | B52: EBIT Margin | C52: =C50/C23 -> 0.039860187 | D52: =D50/D23 -> 0.038671079 | E52: =E50/E23 -> 0.038297184 | F52: =F50/F23 -> 0.049040706 | G52: =G50/G23 -> 0.050253927 | H52: =H50/H23 -> 0.049532116 | I52: =I50/I23 -> 0.048032439 | J52: =J50/J23 -> 0.051687926 | ... P52: =P50/P23 -> 0.060592841 | U52: =U50/U23 -> 0.038647343 | V52: =V50/V23 -> 0.038696679 | W52: =W50/W23 -> 0.037463439 | X52: =X50/X23 -> 0.039201134 | Y52: =Y50/Y23 -> 0.047550172 | Z52: =Z50/Z23 -> 0.05054878 | AA52: =AA50/AA23 -> 0.05069616 | AB52: =AB50/AB23 -> 0.049763328 | ... AL52: =AL50/AL23 -> 0.058792804
B53: Change YoY % | D53: =D52-C52 -> -0.0011891083 | E53: =E52-D52 -> -0.00037389502 | F53: =F52-E52 -> 0.010743522 | G53: =G52-F52 -> 0.0012132214 | H53: =H52-G52 -> -0.00072181056 | I53: =I52-H52 -> -0.0014996775 | J53: =J52-I52 -> 0.0036554869 | K53: =K52-J52 -> 0.0010292072 | ... P53: =P52-O52 -> -0.0002440158 | U53: =U52-S52 -> 0.038647343 | V53: =V52-T52 -> 0.038696679 | W53: =W52-U52 -> -0.0011839041 | X53: =X52-V52 -> 0.00050445435 | Y53: =Y52-W52 -> 0.010086733 | Z53: =Z52-X52 -> 0.011347647 | AA53: =AA52-Y52 -> 0.0031459881 | AB53: =AB52-Z52 -> -0.00078545214 | ... AL53: =AL52-AJ52 -> 0.0055331696
A55: Total AASB16 impact | B55: AASB16 adjustment | C55: =C58-C50 -> 0 | D55: =D58-D50 -> 0 | E55: =E58-E50 -> 0 | F55: =F58-F50 -> -308 | G55: =F55*(1+G27+3%) -> -320.97786 | H55: =G55*(1+H27+3%) -> -330.99207 | I55: =H55*(1+I27+3%) -> -345.2822 | J55: =I55*(1+J27+3%) -> -359.72202 | K55: =J55*(1+K27+3%) -> -372.19462 | L55: =K55*(1+L27+3%) -> -387.68831 | M55: =L55*(1+M27+3%) -> -404.66638 | N55: =M55*(1+N27+3%) -> -422.31204 | ... P55: =O55*(1+P27+3%) -> -459.70594 | Y55: =Y58-Y50 -> -152 | Z55: =Z58-Z50 -> -156 | AA55: =Y55*(1+AA27+3%) -> -158.4069 | AB55: =G55-AA55 -> -162.57096 | AC55: =AA55*(1+AC27+3%) -> -163.53944 | AD55: =H55-AC55 -> -167.45263 | AE55: =AC55*(1+AE27+3%) -> -169.81661 | AF55: =I55-AE55 -> -175.46559 | AG55: =AE55*(1+AG27+3%) -> -176.52457 | AH55: =J55-AG55 -> -183.19745 | AI55: =AG55*(1+AI27+3%) -> -183.48171 | AJ55: =K55-AI55 -> -188.71291 | AK55: =AI55*(1+AK27+3%) -> -190.26925 | AL55: =L55-AK55 -> -197.41905
B56: % of sales | F56: =-F55/F23 -> 0.0093353136 | G56: =-G55/G23 -> 0.0094773197 | H56: =-H55/H23 -> 0.0095596137 | I56: =-I55/I23 -> 0.0093964568 | J56: =-J55/J23 -> 0.009213719 | K56: =-K55/K23 -> 0.0093078906 | L56: =-L55/L23 -> 0.0093011935 | M56: =-M55/M23 -> 0.0093011935 | ... P56: =-P55/P23 -> 0.0093011935 | Y56: =-Y55/Y23 -> 0.0091604894 | Z56: =-Z55/Z23 -> 0.0095121951 | AA56: =-AA55/AA23 -> 0.0088932687 | AB56: =-AB55/AB23 -> 0.010125247 | AC56: =-AC55/AC23 -> 0.0090774554 | AD56: =-AD55/AD23 -> 0.010082649 | AE56: =-AE55/AE23 -> 0.0090054945 | AF56: =-AF55/AF23 -> 0.0098085747 | ... AL56: =-AL55/AL23 -> 0.0097848571
B58: EBIT pre AASB16 | C58: =C50 -> 1186 | D58: =D50 -> 1157 | E58: =E50 -> 1183 | F58: 1310 | G58: =G55+G50 -> 1381.0221 | H58: =H55+H50 -> 1384.0079 | I58: =I55+I50 -> 1419.7178 | J58: =J55+J50 -> 1658.278 | K58: =K55+K50 -> 1735.8054 | L58: =L55+L50 -> 2042.9444 | M58: =M55+M50 -> 2214.1149 | N58: =N55+N50 -> 2349.2102 | ... P58: =P55+P50 -> 2535.0591 | U58: =U50 -> 600 | V58: =V50 -> 557 | W58: =W50 -> 602 | X58: =X50 -> 581 | Y58: 637 | Z58: =F58-Y58 -> 673 | AA58: =AA55+AA50 -> 744.5931 | AB58: =AB55+AB50 -> 636.42904 | AC58: =AC55+AC50 -> 732.46056 | AD58: =AD55+AD50 -> 651.54737 | AE58: =AE55+AE50 -> 821.18339 | AF58: =AF55+AF50 -> 598.53441 | AG58: =AG55+AG50 -> 830.47543 | AH58: =AH55+AH50 -> 827.80255 | ... AL58: =AL55+AL50 -> 988.78321
B59: Growth % | D59: =D58/C58-1 -> -0.024451939 | E59: =E58/D58-1 -> 0.02247191 | F59: =F58/E58-1 -> 0.10735418 | G59: =G58/F58-1 -> 0.054215371 | H59: =H58/G58-1 -> 0.0021620208 | I59: =I58/H58-1 -> 0.025801777 | J59: =J58/I58-1 -> 0.16803352 | K59: =K58/J58-1 -> 0.046751749 | ... P59: =P58/O58-1 -> 0.038305381 | W59: =W58/U58-1 -> 0.0033333333 | X59: =X58/V58-1 -> 0.043087971 | Y59: =Y58/W58-1 -> 0.058139535 | Z59: =Z58/X58-1 -> 0.15834768 | AA59: =AA58/Y58-1 -> 0.16890596 | AB59: =AB58/Z58-1 -> -0.054340212 | AC59: =AC58/AA58-1 -> -0.016294182 | AD59: =AD58/AB58-1 -> 0.023754941 | ... AL59: =AL58/AJ58-1 -> 0.17392659
B60: EBIT pre AASB16 Margin | C60: =C58/C23 -> 0.039860187 | D60: =D58/D23 -> 0.038671079 | E60: =E58/E23 -> 0.038297184 | F60: =F58/F23 -> 0.039705392 | G60: =G58/G23 -> 0.040776607 | H60: =H58/H23 -> 0.039972503 | I60: =I58/I23 -> 0.038635982 | J60: =J58/J23 -> 0.042474207 | ... P60: =P58/P23 -> 0.051291647 | U60: =U58/U23 -> 0.038647343 | V60: =V58/V23 -> 0.038696679 | W60: =W58/W23 -> 0.037463439 | X60: =X58/X23 -> 0.039201134 | Y60: =Y58/Y23 -> 0.038389682 | Z60: =Z58/Z23 -> 0.041036585 | AA60: =AA58/AA23 -> 0.041802891 | AB60: =AB58/AB23 -> 0.039638082 | ... AL60: =AL58/AL23 -> 0.049007947
B61: Change YoY % | D61: =D60-C60 -> -0.0011891083 | E61: =E60-D60 -> -0.00037389502 | F61: =F60-E60 -> 0.0014082085 | G61: =G60-F60 -> 0.0010712152 | H61: =H60-G60 -> -0.00080410457 | I61: =I60-H60 -> -0.0013365206 | J61: =J60-I60 -> 0.0038382247 | K61: =K60-J60 -> 0.00093503564 | ... P61: =P60-O60 -> -0.0002440158 | U61: =U60-S60 -> 0.038647343 | V61: =V60-T60 -> 0.038696679 | W61: =W60-U60 -> -0.0011839041 | X61: =X60-V60 -> 0.00050445435 | Y61: =Y60-W60 -> 0.00092624348 | Z61: =Z60-X60 -> 0.0018354518 | AA61: =AA60-Y60 -> 0.0034132088 | AB61: =AB60-Z60 -> -0.0013985038 | ... AL61: =AL60-AJ60 -> 0.0054968873
B63: Store Numbers and Trading Area
B64: Net New Stores
B65: Australian Supermarkets | D65: 8 | E65: 12 | F65: 3 | G65: 10 | H65: 1 | I65: 11 | J65: 10 | K65: 4 | L65: 10 | M65: 12 | N65: 12 | O65: 12 | P65: 12 | W65: 7 | X65: =E65-W65 -> 5 | Y65: 2 | Z65: =F65-Y65 -> 1 | AA65: 9 | AB65: =G65-AA65 -> 1 | AC65: 1 | AD65: =H65-AC65 -> 0 | AE65: 7 | AF65: =I65-AE65 -> 4 | AG65: 4 | AH65: =J65-AG65 -> 6 | AI65: 2 | AJ65: =K65-AI65 -> 2 | AK65: 4 | AL65: =L65-AK65 -> 6
B66: Ending Stores | D66: 809 | E66: 821 | F66: 824 | G66: 834 | H66: 835 | I66: 846 | J66: 856 | K66: 860 | L66: =L65+K66 -> 870 | M66: =M65+L66 -> 882 | N66: =N65+M66 -> 894 | O66: =O65+N66 -> 906 | P66: =P65+O66 -> 918 | W66: 816 | X66: =W66+X65 -> 821 | Y66: 823 | Z66: =Y66+Z65 -> 824 | AA66: 833 | AB66: =AA66+AB65 -> 834 | AC66: 835 | AD66: =AC66+AD65 -> 835 | AE66: 842 | AF66: =AE66+AF65 -> 846 | AG66: 850 | AH66: =AG66+AH65 -> 856 | AI66: 858 | AJ66: =AI66+AJ65 -> 860 | AK66: =AJ66+AK65 -> 864 | AL66: =AK66+AL65 -> 870
B68: Net Selling Area | E68: =E23/E71*1000 -> 1849.2577 | F68: 1915.798 | G68: 1939.907 | H68: =H23/H71*1000 -> 1901.4773 | I68: =I23/I71*1000 -> 1913.7545 | J68: =J23/J71*1000 -> 2035.664 | K68: =K23/K71*1000 -> 2022.2009 | U68: =U23/U71*1000 -> 942.68019 | V68: =AVERAGE(U68,D68) -> 942.68019 | W68: =W23/W71*1000 -> 971.93492 | X68: =AVERAGE(W68,E68) -> 1410.5963 | Y68: 1907.692 | Z68: =AVERAGE(Y68,F68) -> 1911.745 | AA68: 1926.42 | AB68: =AVERAGE(AA68,G68) -> 1933.1635 | AC68: 1952 | AD68: =AVERAGE(AC68,H68) -> 1926.7386 | AE68: =AE23/AE71*1000 -> 1011.045 | AF68: =AVERAGE(AE68,I68) -> 1462.3997 | AG68: =AG23/AG71*1000 -> 1008.1558 | AH68: =AVERAGE(AG68,J68) -> 1521.9099 | AI68: =AI23/AI71*1000 -> 1061.4902 | AJ68: =AVERAGE(AI68,K68) -> 1541.8455
B69: Growth % | F69: =F68/E68-1 -> 0.035982188 | G69: =G68/F68-1 -> 0.012584312 | H69: =H68/G68-1 -> -0.019810078 | I69: =I68/H68-1 -> 0.0064566643 | J69: =J68/I68-1 -> 0.063701753 | K69: =K68/J68-1 -> -0.0066136345 | W69: =W68/U68-1 -> 0.031033569 | X69: =X68/V68-1 -> 0.49636781 | Y69: =Y68/W68-1 -> 0.96277751 | Z69: =Z68/X68-1 -> 0.35527437 | AA69: =AA68/Y68-1 -> 0.0098170984 | AB69: =AB68/Z68-1 -> 0.011203639 | AC69: =AC68/AA68-1 -> 0.013278517 | AD69: =AD68/AB68-1 -> -0.0033234924 | ... AJ69: =AJ68/AH68-1 -> 0.013099087
A71: Food Density | B71: Sales Density per sqm | E71: 16704 | F71: 17547 | G71: 17847 | H71: 18209 | I71: 19201 | J71: 19179 | K71: 19774 | U71: 16469 | V71: =AVERAGE(U71,E71) -> 16586.5 | W71: 16533 | X71: 16704 | Y71: 16800 | Z71: 17547 | AA71: 18101 | AB71: 17847 | AC71: 17919 | AD71: 18209 | AE71: 18651 | AF71: 19201 | AG71: 19618 | AH71: 19816 | AI71: 19434 | AJ71: 19774
B72: Growth % | F72: =F71/E71-1 -> 0.050466954 | G72: =G71/F71-1 -> 0.01709694 | H72: =H71/G71-1 -> 0.020283521 | I72: =I71/H71-1 -> 0.054478555 | J72: =J71/I71-1 -> -0.0011457737 | K72: =K71/J71-1 -> 0.031023515 | W72: =W71/U71-1 -> 0.003886089 | X72: =X71/V71-1 -> 0.0070840744 | Y72: =Y71/W71-1 -> 0.016149519 | Z72: =Z71/X71-1 -> 0.050466954 | AA72: =AA71/Y71-1 -> 0.077440476 | AB72: =AB71/Z71-1 -> 0.01709694 | AC72: =AC71/AA71-1 -> -0.010054693 | AD72: =AD71/AB71-1 -> 0.020283521 | ... AJ72: =AJ71/AH71-1 -> -0.0021194994
B74: Area per store | E74: =(E68*1000)/E66 -> 2252.4454 | F74: =(F68*1000)/F66 -> 2324.9976 | G74: =(G68*1000)/G66 -> 2326.0276 | H74: =(H68*1000)/H66 -> 2277.2183 | I74: =(I68*1000)/I66 -> 2262.1211 | J74: =(J68*1000)/J66 -> 2378.1122 | K74: =(K68*1000)/K66 -> 2351.3964 | W74: =(W68*1000)/W66 -> 1191.0967 | X74: =(X68*1000)/X66 -> 1718.1441 | Y74: =(Y68*1000)/Y66 -> 2317.9733 | Z74: =(Z68*1000)/Z66 -> 2320.0789 | AA74: =(AA68*1000)/AA66 -> 2312.6291 | AB74: =(AB68*1000)/AB66 -> 2317.9418 | AC74: =(AC68*1000)/AC66 -> 2337.7246 | AD74: =(AD68*1000)/AD66 -> 2307.4714 | ... AJ74: =(AJ68*1000)/AJ66 -> 1792.8436
B75: Growth % | F75: =F74/E74-1 -> 0.032210408 | G75: =G74/F74-1 -> 0.00044301342 | H75: =H74/G74-1 -> -0.020983958 | I75: =I74/H74-1 -> -0.0066296517 | J75: =J74/I74-1 -> 0.05127533 | K75: =K74/J74-1 -> -0.011234036 | Y75: =Y74/W74-1 -> 0.94608317 | Z75: =Z74/X74-1 -> 0.35034012 | AA75: =AA74/Y74-1 -> -0.0023055559 | AB75: =AB74/Z74-1 -> -0.00092110531 | AC75: =AC74/AA74-1 -> 0.010851502 | AD75: =AD74/AB74-1 -> -0.004517117 | AE75: =AE74/AC74-1 -> -0.48635265 | AF75: =AF74/AD74-1 -> -0.25086618 | ... AJ75: =AJ74/AH74-1 -> 0.0083869978
B77: Store Locations
B78: NSW & ACT | F78: 256 | G78: 255 | H78: 261 | I78: 260 | J78: 263 | K78: 266
B79: QLD | F79: 176 | G79: 180 | H79: 182 | I79: 182 | J79: 183 | K79: 185
B80: VIC & TAS | F80: 229 | G80: 231 | H80: 234 | I80: 236 | J80: 239 | K80: 243
B81: SA & NT | F81: 63 | G81: 62 | H81: 61 | I81: 60 | J81: 61 | K81: 61
B82: WA | F82: 97 | G82: 96 | H82: 96 | I82: 97 | J82: 100 | K82: 101
B83: Total | F83: =SUM(F78:F82) -> 821 | G83: =SUM(G78:G82) -> 824 | H83: =SUM(H78:H82) -> 834 | I83: =SUM(I78:I82) -> 835 | J83: =SUM(J78:J82) -> 846 | K83: =SUM(K78:K82) -> 856
B85: Online
A86: Food Online | B86: Online Sales | D86: 855 | E86: =E88*E23 -> 1112.04 | F86: 1301 | G86: 2000 | H86: 2800 | I86: 2800 | J86: 3700 | K86: 4500 | L86: =K86*(1+L87) -> 5625 | M86: =L86*(1+M87) -> 6187.5 | N86: =M86*(1+N87) -> 6806.25 | O86: =N86*(1+O87) -> 7486.875 | P86: =O86*(1+P87) -> 8235.5625 | Z86: =F86-Y86 -> 1301 | AA86: 1000 | AB86: =G86-AA86 -> 1000 | AC86: 1500 | AD86: =H86-AC86 -> 1300 | AE86: 1400 | AF86: =I86-AE86 -> 1400 | AG86: 1800 | AH86: =J86-AG86 -> 1900 | AI86: 2200 | AJ86: =K86-AI86 -> 2300 | AK86: =AI86*(1+AK87) -> 2816 | AL86: =L86-AK86 -> 2809
B87: Growth % | E87: 0.3 | F87: =F86/E86-1 -> 0.16992195 | G87: =G86/F86-1 -> 0.53727902 | H87: =H86/G86-1 -> 0.4 | I87: =I86/H86-1 -> 0 | J87: =J86/I86-1 -> 0.32142857 | K87: =K86/J86-1 -> 0.21621622 | L87: 0.25 | M87: 0.1 | N87: 0.1 | O87: 0.1 | P87: 0.1 | W87: =W86/U86-1 -> #DIV/0! | X87: =X86/V86-1 -> #DIV/0! | Y87: =Y86/W86-1 -> #DIV/0! | Z87: =Z86/X86-1 -> #DIV/0! | AA87: =AA86/Y86-1 -> #DIV/0! | AB87: =AB86/Z86-1 -> -0.23136049 | AC87: =AC86/AA86-1 -> 0.5 | AD87: =AD86/AB86-1 -> 0.3 | ... AJ87: =AJ86/AH86-1 -> 0.21052632 | AK87: 0.28 | AL87: =AL86/AJ86-1 -> 0.22130435
B88: eComm Penetration % | E88: 0.036 | F88: =F86/F23 -> 0.039432607 | G88: =G86/G23 -> 0.059052793 | H88: =H86/H23 -> 0.080868762 | I88: =I86/I23 -> 0.07619877 | J88: =J86/J23 -> 0.094769735 | K88: =K86/K23 -> 0.11253657 | L88: =L86/L23 -> 0.13495175 | M88: =M86/M23 -> 0.14221872 | ... P88: =P86/P23 -> 0.16662948 | U88: =U86/U23 -> 0 | V88: =V86/V23 -> 0 | W88: =W86/W23 -> 0 | X88: =X86/X23 -> 0 | Y88: =Y86/Y23 -> 0 | Z88: =Z86/Z23 -> 0.079329268 | AA88: =AA86/AA23 -> 0.056141927 | AB88: =AB86/AB23 -> 0.062282013 | ... AL88: =AL86/AL23 -> 0.13922498
B89: Change YoY % | G89: =G88-F88 -> 0.019620186 | H89: =H88-G88 -> 0.021815968 | I89: =I88-H88 -> -0.0046699916 | J89: =J88-I88 -> 0.018570965 | K89: =K88-J88 -> 0.017766839 | L89: =L88-K88 -> 0.022415171 | M89: =M88-L88 -> 0.0072669754 | N89: =N88-M88 -> 0.0076852434 | ... P89: =P88-O88 -> 0.0085973186 | W89: =W88-U88 -> 0 | X89: =X88-V88 -> 0 | Y89: =Y88-W88 -> 0 | Z89: =Z88-X88 -> 0.079329268 | AA89: =AA88-Y88 -> 0.056141927 | AB89: =AB88-Z88 -> -0.017047255 | AC89: =AC88-AA88 -> 0.027117398 | AD89: =AD88-AB88 -> 0.015993517 | ... AL89: =AL88-AJ88 -> 0.020411052
B90: Online Contribution to LFL | E90: =(E86-D86)/D23 -> 0.0085911962 | F90: =(F86-E86)/E23 -> 0.00611719 | G90: =(G86-F86)/F23 -> 0.021186312 | H90: =(H86-G86)/G23 -> 0.023621117 | I90: =(I86-H86)/H23 -> 0 | J90: =(J86-I86)/I23 -> 0.024492462 | K90: =(K86-J86)/J23 -> 0.020490754 | L90: =(L86-K86)/K23 -> 0.028134144 | ... P90: =(P86-O86)/O23 -> 0.015803216
B92: Liquor
B93: Sales | C93: 3223 | D93: 3314 | E93: 3063 | F93: 3308 | G93: 3525 | H93: 3613 | I93: 3610 | J93: 3692 | K93: 3667 | L93: =K93*(1+L94) -> 3636.7032 | M93: =L93*(1+M94) -> 3727.6207 | N93: =M93*(1+N94) -> 3820.8113 | O93: =N93*(1+O94) -> 3916.3315 | P93: =O93*(1+P94) -> 4014.2398 | U93: 1721 | V93: =D93-U93 -> 1593 | W93: 1637 | X93: =E93-W93 -> 1426 | Y93: 1691 | Z93: =F93-Y93 -> 1617 | AA93: 1946 | AB93: =G93-AA93 -> 1579 | AC93: 1999 | AD93: =H93-AC93 -> 1614 | AE93: 1952 | AF93: =I93-AE93 -> 1658 | AG93: 1988 | AH93: =J93-AG93 -> 1704 | AI93: 2004 | AJ93: =K93-AI93 -> 1663 | AK93: =AI93*(1+AK94) -> 1984.962 | AL93: =L93-AK93 -> 1651.7412
A94: Liquor Growth | B94: Growth % | D94: =D93/C93-1 -> 0.028234564 | E94: =E93/D93-1 -> -0.075739288 | F94: =F93/E93-1 -> 0.079986941 | G94: =G93/F93-1 -> 0.065598549 | H94: =H93/G93-1 -> 0.024964539 | I94: =I93/H93-1 -> -0.0008303349 | J94: =J93/I93-1 -> 0.022714681 | K94: =K93/J93-1 -> -0.0067713976 | L94: =SUM(L95:L97) -> -0.008262024 | M94: =SUM(M95:M97) -> 0.025 | N94: =SUM(N95:N97) -> 0.025 | O94: =SUM(O95:O97) -> 0.025 | P94: =SUM(P95:P97) -> 0.025 | W94: =W93/U93-1 -> -0.048808832 | X94: =X93/V93-1 -> -0.10483365 | Y94: =Y93/W93-1 -> 0.032987172 | Z94: =Z93/X93-1 -> 0.13394109 | AA94: =AA93/Y93-1 -> 0.15079834 | AB94: =AB93/Z93-1 -> -0.023500309 | AC94: =AC93/AA93-1 -> 0.027235355 | AD94: =AD93/AB93-1 -> 0.022165928 | ... AJ94: =AJ93/AH93-1 -> -0.024061033 | AK94: =SUM(AK95:AK97) -> -0.0095 | AL94: =AL93/AJ93-1 -> -0.0067701998
A95: Liquor Comp | B95: LFL Sales Growth % | C95: 0.012 | D95: 0.018 | E95: 0.027 | F95: 0.073 | G95: 0.063 | H95: 0.021 | I95: 0.007 | J95: -0.01 | K95: -0.013 | L95: =VLOOKUP($A95,Quarterly!$1:$1048576,MATCH(Model!L$3,Quarterly!$3:$3,0),FALSE) -> -0.01125 | M95: 0.025 | N95: 0.025 | O95: 0.025 | P95: 0.025 | U95: 0.016 | V95: =D95 -> 0.018 | W95: 0.011 | X95: 0.012 | Y95: 0.015 | Z95: 0.139 | AA95: 0.151 | AB95: -0.029 | AC95: 0.018 | AD95: 0.024 | AE95: -0.023 | AF95: 0.013 | AG95: 0.002 | AH95: -0.024 | AI95: -0.013 | AJ95: -0.012 | AK95: =VLOOKUP($A95,Quarterly!$1:$1048576,MATCH(Model!AK$3,Quarterly!$3:$3,0),FALSE) -> -0.0125 | AL95: =VLOOKUP($A95,Quarterly!$1:$1048576,MATCH(Model!AL$3,Quarterly!$3:$3,0),FALSE) -> -0.01
B96: Store Growth % | E96: =E134/D134-1 -> 0.012235818 | F96: =F134/E134-1 -> 0 | G96: =G134/F134-1 -> 0.020879121 | H96: =H134/G134-1 -> 0.0043057051 | I96: =I134/H134-1 -> 0.025723473 | J96: =J134/I134-1 -> 0.036572623 | K96: =K134/J134-1 -> 0.0060483871 | L96: =L134/K134-1 -> -0.006012024 | ... P96: =P134/O134-1 -> 0 | Y96: =Y134/W134-1 -> 0.0099118943 | Z96: =Z134/X134-1 -> -0.013015184 | AA96: =AA134/Y134-1 -> 0.0087241003 | AB96: =AB134/Z134-1 -> 0.020879121 | AC96: =AC134/AA134-1 -> 0.0064864865 | AD96: =AD134/AB134-1 -> 0.0043057051 | AE96: =AE134/AC134-1 -> 0.0096670247 | AF96: =AF134/AD134-1 -> 0.025723473 | ... AL96: =AL134/AJ134-1 -> -0.006012024
B97: Other | E97: =E94-SUM(E95:E96) -> -0.11497511 | F97: =F94-SUM(F95:F96) -> 0.0069869409 | G97: =G94-SUM(G95:G96) -> -0.018280572 | H97: =H94-SUM(H95:H96) -> -0.00034116605 | I97: =I94-SUM(I95:I96) -> -0.033553808 | J97: =J94-SUM(J95:J96) -> -0.0038579413 | K97: =K94-SUM(K95:K96) -> 0.00018021529 | L97: 0.009 | M97: 0 | N97: 0 | O97: 0 | P97: 0 | Y97: =Y94-SUM(Y95:Y96) -> 0.0080752774 | Z97: =Z94-SUM(Z95:Z96) -> 0.0079562784 | AA97: =AA94-SUM(AA95:AA96) -> -0.0089257562 | AB97: =AB94-SUM(AB95:AB96) -> -0.01537943 | AC97: =AC94-SUM(AC95:AC96) -> 0.0027488681 | AD97: =AD94-SUM(AD95:AD96) -> -0.0061397773 | AE97: =AE94-SUM(AE95:AE96) -> -0.010178781 | AF97: =AF94-SUM(AF95:AF96) -> -0.01146201 | ... AJ97: =AJ94-SUM(AJ95:AJ96) -> -0.01810942 | AK97: 0.003 | AL97: =AL94-SUM(AL95:AL96) -> 0.0092418243
B99: Gross Profit | D99: =D101*D93 -> 725.766 | E99: =E101*E93 -> 683.049 | F99: =F101*F93 -> 714.528 | G99: =G101*G93 -> 768.45 | H99: =H101*H93 -> 812.925 | I99: =I101*I93 -> 844.74 | J99: =J101*J93 -> 867.62 | K99: =K101*K93 -> 865.412 | ... P99: =P101*P93 -> 971.44604 | U99: =U101*U93 -> 485.322 | V99: =D99-U99 -> 240.444 | W99: =W101*W93 -> 365.051 | X99: =E99-W99 -> 317.998 | Y99: =Y101*Y93 -> 370.329 | Z99: =F99-Y99 -> 344.199 | AA99: =AA101*AA93 -> 418.39 | AB99: =G99-AA99 -> 350.06 | AC99: =AC101*AC93 -> 435.782 | AD99: =H99-AC99 -> 377.143 | AE99: =AE101*AE93 -> 441.152 | AF99: =I99-AE99 -> 403.588 | AG99: =AG101*AG93 -> 455.252 | AH99: =J99-AG99 -> 412.368 | AI99: =AI101*AI93 -> 462.924 | AJ99: =K99-AI99 -> 402.488 | AK99: =AK101*AK93 -> 458.52622 | AL99: =L99-AK99 -> 399.73572
B100: Growth % | E100: =E99/D99-1 -> -0.058857814 | F100: =F99/E99-1 -> 0.046086006 | G100: =G99/F99-1 -> 0.075465202 | H100: =H99/G99-1 -> 0.057876244 | I100: =I99/H99-1 -> 0.039136452 | J100: =J99/I99-1 -> 0.027085257 | K100: =K99/J99-1 -> -0.0025448929 | L100: =L99/K99-1 -> -0.008262024 | ... P100: =P99/O99-1 -> 0.033541667 | W100: =W99/U99-1 -> -0.24781691 | X100: =X99/V99-1 -> 0.32254496 | Y100: =Y99/W99-1 -> 0.014458254 | Z100: =Z99/X99-1 -> 0.0823936 | AA100: =AA99/Y99-1 -> 0.1297792 | AB100: =AB99/Z99-1 -> 0.01702794 | AC100: =AC99/AA99-1 -> 0.041568871 | AD100: =AD99/AB99-1 -> 0.077366737 | ... AJ100: =AJ99/AH99-1 -> -0.023959182 | AK100: =AK99/AJ99-1 -> 0.13922955 | AL100: =AL99/AJ99-1 -> -0.0068381585
B101: Gross Margin | D101: 0.219 | E101: 0.223 | F101: 0.216 | G101: 0.218 | H101: 0.225 | I101: 0.234 | J101: 0.235 | K101: 0.236 | L101: =K101+L102 -> 0.236 | M101: =L101+M102 -> 0.238 | N101: =M101+N102 -> 0.238 | O101: =N101+O102 -> 0.24 | P101: =O101+P102 -> 0.242 | U101: 0.282 | V101: =V99/V93 -> 0.15093785 | W101: 0.223 | X101: =X99/X93 -> 0.223 | Y101: 0.219 | Z101: =Z99/Z93 -> 0.21286271 | AA101: 0.215 | AB101: =AB99/AB93 -> 0.22169728 | AC101: 0.218 | AD101: =AD99/AD93 -> 0.23366976 | AE101: 0.226 | AF101: =AF99/AF93 -> 0.24341858 | AG101: 0.229 | AH101: =AH99/AH93 -> 0.242 | AI101: 0.231 | AJ101: =AJ99/AJ93 -> 0.24202526 | AK101: =AI101+AK102 -> 0.231 | AL101: =AL99/AL93 -> 0.2420087
B102: Change YoY % | E102: 0.0041 | F102: 0.003 | G102: 0.0023 | H102: 0.0064 | I102: 0.0091 | J102: 0.0009 | K102: 0.0015 | L102: 0 | M102: 0.002 | N102: 0 | O102: 0.002 | P102: 0.002 | V102: =V101-T101 -> 0.15093785 | W102: -0.0009 | X102: =X101-V101 -> 0.072062147 | Y102: -0.0041 | Z102: =Z101-X101 -> -0.010137291 | AA102: -0.0034 | AB102: =AB101-Z101 -> 0.008834568 | AC102: 0.0023 | AD102: =AD101-AB101 -> 0.011972488 | AE102: 0.0083 | AF102: =AF101-AD101 -> 0.009748812 | AG102: 0.0027 | AH102: =AH101-AF101 -> -0.0014185766 | AI102: 0.0022 | AJ102: =AJ101-AH101 -> 2.5255562e-05 | AK102: 0 | AL102: =AL101-AJ101 -> -1.6559858e-05
B104: CODB | G104: =G109-G99 -> -492.45 | H104: =H109-H99 -> -534.925 | I104: =I109-I99 -> -565.74 | J104: =J109-J99 -> -606.62 | K104: =K109-K99 -> -619.412 | L104: =K104*(1+L105) -> -634.8973 | M104: =L104*(1+M105) -> -634.8973 | N104: =M104*(1+N105) -> -647.59525 | O104: =N104*(1+O105) -> -660.54715 | P104: =O104*(1+P105) -> -673.75809 | AC104: =AC109-AC99 -> -279.782 | AD104: =AD109-AD99 -> -255.143 | AE104: =AE109-AE99 -> -300.152 | AF104: =AF109-AF99 -> -265.588 | AG104: =AG109-AG99 -> -307.252 | AH104: =AH109-AH99 -> -299.368 | AI104: =AI109-AI99 -> -327.924 | AJ104: =AJ109-AJ99 -> -291.488 | AK104: =AI104*(1+AK105) -> -341.04096 | AL104: =L104-AK104 -> -293.85634
B105: Growth % | H105: =H104/G104-1 -> 0.086252411 | I105: =I104/H104-1 -> 0.057606206 | J105: =J104/I104-1 -> 0.072259342 | K105: =K104/J104-1 -> 0.021087336 | L105: 0.025 | M105: 0 | N105: 0.02 | O105: 0.02 | P105: 0.02 | AE105: =AE104/AC104-1 -> 0.072806685 | AF105: =AF104/AD104-1 -> 0.040937827 | AG105: =AG104/AE104-1 -> 0.023654682 | AH105: =AH104/AF104-1 -> 0.12718948 | AI105: =AI104/AG104-1 -> 0.067280278 | AJ105: =AJ104/AH104-1 -> -0.026322119 | AK105: 0.04 | AL105: =AL104/AJ104-1 -> 0.008125
B106: % of Sales | G106: =G104/G93 -> -0.13970213 | H106: =H104/H93 -> -0.14805563 | I106: =I104/I93 -> -0.15671468 | J106: =J104/J93 -> -0.16430661 | K106: =K104/K93 -> -0.16891519 | L106: =L104/L93 -> -0.17458046 | M106: =M104/M93 -> -0.1703224 | N106: =N104/N93 -> -0.16949156 | ... P106: =P104/P93 -> -0.16784201 | AC106: =AC104/AC93 -> -0.13996098 | AD106: =AD104/AD93 -> -0.15808116 | AE106: =AE104/AE93 -> -0.15376639 | AF106: =AF104/AF93 -> -0.16018577 | AG106: =AG104/AG93 -> -0.15455332 | AH106: =AH104/AH93 -> -0.17568545 | AI106: =AI104/AI93 -> -0.16363473 | AJ106: =AJ104/AJ93 -> -0.17527841 | ... AL106: =AL104/AL93 -> -0.17790702
B107: Change YoY % | H107: =H106-G106 -> -0.0083535048 | I107: =I106-H106 -> -0.008659049 | J107: =J106-I106 -> -0.0075919274 | K107: =K106-J106 -> -0.0046085806 | L107: =L106/K106-1 -> 0.033539125 | M107: =M106/L106-1 -> -0.024390244 | N107: =N106/M106-1 -> -0.0048780488 | O107: =O106/N106-1 -> -0.0048780488 | P107: =P106/O106-1 -> -0.0048780488 | AE107: =AE106-AC106 -> -0.013805413 | AF107: =AF106-AD106 -> -0.0021046012 | AG107: =AG106-AE106 -> -0.00078692648 | AH107: =AH106-AF106 -> -0.01549968 | AI107: =AI106-AG106 -> -0.0090814106 | AJ107: =AJ106-AH106 -> 0.0004070335 | AK107: =AK106/AJ106-1 -> -0.019774686 | AL107: =AL106/AK106-1 -> 0.035472882
B109: EBITDA | D109: 146 | E109: 153 | F109: 242 | G109: 276 | H109: 278 | I109: 279 | J109: 261 | K109: 246 | L109: =L99+L104 -> 223.36465 | M109: =M99+M104 -> 252.27644 | N109: =N99+N104 -> 261.75783 | O109: =O99+O104 -> 279.37242 | P109: =P99+P104 -> 297.68794 | U109: 106 | V109: =D109-U109 -> 40 | W109: 91 | X109: =E109-W109 -> 62 | Y109: 127 | Z109: =F109-Y109 -> 115 | AA109: 159 | AB109: =G109-AA109 -> 117 | AC109: 156 | AD109: =H109-AC109 -> 122 | AE109: 141 | AF109: =I109-AE109 -> 138 | AG109: 148 | AH109: =J109-AG109 -> 113 | AI109: 135 | AJ109: =K109-AI109 -> 111 | AK109: =AK99+AK104 -> 117.48526 | AL109: =L109-AK109 -> 105.87938
B110: Growth % | H110: =H109/G109-1 -> 0.0072463768 | I110: =I109/H109-1 -> 0.0035971223 | J110: =J109/I109-1 -> -0.064516129 | K110: =K109/J109-1 -> -0.057471264 | L110: =L109/K109-1 -> -0.092013637 | M110: =M109/L109-1 -> 0.12943763 | N110: =N109/M109-1 -> 0.037583365 | O110: =O109/N109-1 -> 0.06729344 | P110: =P109/O109-1 -> 0.065559535 | AE110: =AE109/AC109-1 -> -0.096153846 | AF110: =AF109/AD109-1 -> 0.13114754 | AG110: =AG109/AE109-1 -> 0.04964539 | AH110: =AH109/AF109-1 -> -0.18115942 | AI110: =AI109/AG109-1 -> -0.087837838 | AJ110: =AJ109/AH109-1 -> -0.017699115 | AK110: =AK109/AI109-1 -> -0.1297388 | AL110: =AL109/AJ109-1 -> -0.046131682
B111: EBITDA Margin | G111: =G109/G93 -> 0.078297872 | H111: =H109/H93 -> 0.076944368 | I111: =I109/I93 -> 0.077285319 | J111: =J109/J93 -> 0.070693391 | K111: =K109/K93 -> 0.06708481 | L111: =L109/L93 -> 0.061419543 | M111: =M109/M93 -> 0.067677603 | N111: =N109/N93 -> 0.068508444 | ... P111: =P109/P93 -> 0.074157987 | AC111: =AC109/AC93 -> 0.07803902 | AD111: =AD109/AD93 -> 0.0755886 | AE111: =AE109/AE93 -> 0.072233607 | AF111: =AF109/AF93 -> 0.083232811 | AG111: =AG109/AG93 -> 0.07444668 | AH111: =AH109/AH93 -> 0.066314554 | AI111: =AI109/AI93 -> 0.067365269 | AJ111: =AJ109/AJ93 -> 0.066746843 | ... AL111: =AL109/AL93 -> 0.06410168
B112: Change YoY % | H112: =H111-G111 -> -0.0013535048 | I112: =I111-H111 -> 0.000340951 | J112: =J111-I111 -> -0.0065919274 | K112: =K111-J111 -> -0.0036085806 | L112: =L111-K111 -> -0.0056652677 | M112: =M111-L111 -> 0.0062580599 | N112: =N111-M111 -> 0.00083084096 | O112: =O111-N111 -> 0.0028267881 | P112: =P111-O111 -> 0.002822755 | AE112: =AE111-AC111 -> -0.005805413 | AF112: =AF111-AD111 -> 0.0076442109 | AG112: =AG111-AE111 -> 0.0022130735 | AH112: =AH111-AF111 -> -0.016918257 | AI112: =AI111-AG111 -> -0.0070814106 | AJ112: =AJ111-AH111 -> 0.00043228906 | AK112: =AK111-AI111 -> -0.0081776064 | AL112: =AL111-AJ111 -> -0.002645163
B114: D&A | D114: -35 | E114: -33 | F114: -104 | G114: -111 | H114: -115 | I114: -122 | J114: -128 | K114: -133 | L114: =K114*(1+L115) -> -136.99 | M114: =L114*(1+M115) -> -141.0997 | N114: =M114*(1+N115) -> -145.33269 | O114: =N114*(1+O115) -> -149.69267 | P114: =O114*(1+P115) -> -154.18345 | U114: -26 | V114: =D114-U114 -> -9 | W114: -17 | X114: =E114-W114 -> -16 | Y114: -51 | Z114: =F114-Y114 -> -53 | AA114: -55 | AB114: =G114-AA114 -> -56 | AC114: -57 | AD114: =H114-AC114 -> -58 | AE114: -61 | AF114: =I114-AE114 -> -61 | AG114: -64 | AH114: =J114-AG114 -> -64 | AI114: -68 | AJ114: =K114-AI114 -> -65 | AK114: =AI114*(1+AK115) -> -70.04 | AL114: =L114-AK114 -> -66.95
B115: Growth % | H115: =H114/G114-1 -> 0.036036036 | I115: =I114/H114-1 -> 0.060869565 | J115: =J114/I114-1 -> 0.049180328 | K115: =K114/J114-1 -> 0.0390625 | L115: 0.03 | M115: 0.03 | N115: 0.03 | O115: 0.03 | P115: 0.03 | AE115: =AE114/AC114-1 -> 0.070175439 | AF115: =AF114/AD114-1 -> 0.051724138 | AG115: =AG114/AE114-1 -> 0.049180328 | AH115: =AH114/AF114-1 -> 0.049180328 | AI115: =AI114/AG114-1 -> 0.0625 | AJ115: =AJ114/AH114-1 -> 0.015625 | AK115: 0.03 | AL115: =AL114/AJ114-1 -> 0.03
B116: % of Sales | G116: =G114/G93 -> -0.031489362 | H116: =H114/H93 -> -0.031829505 | I116: =I114/I93 -> -0.033795014 | J116: =J114/J93 -> -0.034669556 | K116: =K114/K93 -> -0.03626943 | L116: =L114/L93 -> -0.037668733 | M116: =M114/M93 -> -0.037852483 | N116: =N114/N93 -> -0.038037129 | ... P116: =P114/P93 -> -0.038409128 | AC116: =AC114/AC93 -> -0.028514257 | AD116: =AD114/AD93 -> -0.035935564 | AE116: =AE114/AE93 -> -0.03125 | AF116: =AF114/AF93 -> -0.036791315 | AG116: =AG114/AG93 -> -0.032193159 | AH116: =AH114/AH93 -> -0.037558685 | AI116: =AI114/AI93 -> -0.033932136 | AJ116: =AJ114/AJ93 -> -0.039085989 | ... AL116: =AL114/AL93 -> -0.040532985
B117: Change YoY % | H117: =H116-G116 -> -0.00034014286 | I117: =I116-H116 -> -0.0019655093 | J117: =J116-I116 -> -0.00087454195 | K117: =K116-J116 -> -0.0015998743 | L117: =L116-K116 -> -0.0013993029 | M117: =M116-L116 -> -0.00018374992 | N117: =N116-M116 -> -0.00018464626 | O117: =O116-N116 -> -0.00018554697 | P117: =P116-O116 -> -0.00018645208 | AE117: =AE116-AC116 -> -0.0027357429 | AF117: =AF116-AD116 -> -0.00085575102 | AG117: =AG116-AE116 -> -0.00094315895 | AH117: =AH116-AF116 -> -0.00076737061 | AI117: =AI116-AG116 -> -0.0017389768 | AJ117: =AJ116-AH116 -> -0.0015273037 | AK117: =AK116-AI116 -> -0.0013531745 | AL117: =AL116-AJ116 -> -0.0014469961
B119: EBIT | C119: 138 | D119: 130 | E119: 120 | F119: 138 | G119: 165 | H119: 163 | I119: 157 | J119: 133 | K119: 113 | L119: =L109+L114 -> 86.374645 | M119: =M109+M114 -> 111.17674 | N119: =N109+N114 -> 116.42514 | O119: =O109+O114 -> 129.67975 | P119: =P109+P114 -> 143.50449 | U119: 80 | V119: =D119-U119 -> 50 | W119: 74 | X119: =E119-W119 -> 46 | Y119: 76 | Z119: =F119-Y119 -> 62 | AA119: 104 | AB119: =G119-AA119 -> 61 | AC119: 99 | AD119: =H119-AC119 -> 64 | AE119: 80 | AF119: =I119-AE119 -> 77 | AG119: 84 | AH119: =J119-AG119 -> 49 | AI119: 67 | AJ119: =K119-AI119 -> 46 | AK119: =AK109+AK114 -> 47.445262 | AL119: =AL109+AL114 -> 38.929383
B120: Growth % | D120: =D119/C119-1 -> -0.057971014 | E120: =E119/D119-1 -> -0.076923077 | F120: =F119/E119-1 -> 0.15 | G120: =G119/F119-1 -> 0.19565217 | H120: =H119/G119-1 -> -0.012121212 | I120: =I119/H119-1 -> -0.036809816 | J120: =J119/I119-1 -> -0.15286624 | K120: =K119/J119-1 -> -0.15037594 | ... P120: =P119/O119-1 -> 0.10660682 | W120: =W119/U119-1 -> -0.075 | X120: =X119/V119-1 -> -0.08 | Y120: =Y119/W119-1 -> 0.027027027 | Z120: =Z119/X119-1 -> 0.34782609 | AA120: =AA119/Y119-1 -> 0.36842105 | AB120: =AB119/Z119-1 -> -0.016129032 | AC120: =AC119/AA119-1 -> -0.048076923 | AD120: =AD119/AB119-1 -> 0.049180328 | ... AL120: =AL119/AJ119-1 -> -0.15370906
A121: Liquor EBIT Margin | B121: EBIT Margin | C121: =C119/C93 -> 0.042817251 | D121: =D119/D93 -> 0.03922752 | E121: =E119/E93 -> 0.039177277 | F121: =F119/F93 -> 0.04171705 | G121: =G119/G93 -> 0.046808511 | H121: =H119/H93 -> 0.045114863 | I121: =I119/I93 -> 0.043490305 | J121: =J119/J93 -> 0.036023835 | ... P121: =P119/P93 -> 0.035748859 | U121: =U119/U93 -> 0.046484602 | V121: =V119/V93 -> 0.03138732 | W121: =W119/W93 -> 0.045204643 | X121: =X119/X93 -> 0.032258065 | Y121: =Y119/Y93 -> 0.04494382 | Z121: =Z119/Z93 -> 0.03834261 | AA121: =AA119/AA93 -> 0.05344296 | AB121: =AB119/AB93 -> 0.038632046 | ... AL121: =AL119/AL93 -> 0.023568695
...

Sheet PL
B1: Coles Group (COL.AX)
B2: A$M
C3: =Model!C3 -> FY17 | D3: =Model!D3 -> FY18 | E3: =Model!E3 -> FY19 | F3: =Model!F3 -> FY20 | G3: =Model!G3 -> FY21 | H3: =Model!H3 -> FY22 | I3: =Model!I3 -> FY23 | J3: =Model!J3 -> FY24 | K3: =Model!K3 -> FY25 | L3: FY26E | M3: FY27E | N3: FY28E | O3: FY29E | P3: FY30E | R3: =Model!S3 -> 1H17 | S3: =Model!T3 -> 2H17 | T3: =Model!U3 -> 1H18 | U3: =Model!V3 -> 2H18 | V3: =Model!W3 -> 1H19 | W3: =Model!X3 -> 2H19 | X3: =Model!Y3 -> 1H20 | Y3: =Model!Z3 -> 2H20 | ... AI3: =Model!AJ3 -> 2H25 | AJ3: 1H26E | AK3: 2H26E
B4: P&L
A5: Total Sales | B5: Sales | C5: =VLOOKUP($A$5,Model!1:1048576,MATCH(PL!C3,Model!3:3,0),FALSE) -> 39125 | D5: =VLOOKUP($A$5,Model!1:1048576,MATCH(PL!D3,Model!3:3,0),FALSE) -> 39007 | E5: =VLOOKUP($A$5,Model!1:1048576,MATCH(PL!E3,Model!3:3,0),FALSE) -> 35001 | F5: =VLOOKUP($A$5,Model!1:1048576,MATCH(PL!F3,Model!3:3,0),FALSE) -> 37408 | G5: =VLOOKUP($A$5,Model!1:1048576,MATCH(PL!G3,Model!3:3,0),FALSE) -> 38585 | H5: =VLOOKUP($A$5,Model!1:1048576,MATCH(PL!H3,Model!3:3,0),FALSE) -> 38237 | I5: =VLOOKUP($A$5,Model!1:1048576,MATCH(PL!I3,Model!3:3,0),FALSE) -> 40483 | J5: =VLOOKUP($A$5,Model!1:1048576,MATCH(PL!J3,Model!3:3,0),FALSE) -> 43571 | ... P5: =VLOOKUP($A$5,Model!1:1048576,MATCH(PL!P3,Model!3:3,0),FALSE) -> 53438.643 | T5: =VLOOKUP($A$5,Model!1:1048576,MATCH(PL!T3,Model!3:3,0),FALSE) -> 20246 | U5: =VLOOKUP($A$5,Model!1:1048576,MATCH(PL!U3,Model!3:3,0),FALSE) -> 18761 | V5: =VLOOKUP($A$5,Model!1:1048576,MATCH(PL!V3,Model!3:3,0),FALSE) -> 18266 | W5: =VLOOKUP($A$5,Model!1:1048576,MATCH(PL!W3,Model!3:3,0),FALSE) -> 16735 | X5: =VLOOKUP($A$5,Model!1:1048576,MATCH(PL!X3,Model!3:3,0),FALSE) -> 18856 | Y5: =VLOOKUP($A$5,Model!1:1048576,MATCH(PL!Y3,Model!3:3,0),FALSE) -> 18552 | Z5: =VLOOKUP($A$5,Model!1:1048576,MATCH(PL!Z3,Model!3:3,0),FALSE) -> 20390 | AA5: =VLOOKUP($A$5,Model!1:1048576,MATCH(PL!AA3,Model!3:3,0),FALSE) -> 18195 | ... AK5: =VLOOKUP($A$5,Model!1:1048576,MATCH(PL!AK3,Model!3:3,0),FALSE) -> 22005.318
A6: Total Sales Growth | B6: Growth % | D6: =D5/C5-1 -> -0.0030159744 | E6: =E5/D5-1 -> -0.10269952 | F6: =F5/E5-1 -> 0.068769464 | G6: =G5/F5-1 -> 0.031463858 | H6: =H5/G5-1 -> -0.0090190489 | I6: =I5/H5-1 -> 0.058738918 | J6: =J5/I5-1 -> 0.076278932 | K6: =K5/J5-1 -> 0.017924766 | ... P6: =P5/O5-1 -> 0.041851957 | V6: =V5/T5-1 -> -0.097797096 | W6: =W5/U5-1 -> -0.10798998 | X6: =X5/V5-1 -> 0.032300449 | Y6: =Y5/W5-1 -> 0.10857484 | Z6: =Z5/X5-1 -> 0.081353415 | AA6: =AA5/Y5-1 -> -0.019243208 | AB6: =AB5/Z5-1 -> -0.018391368 | AC6: =AC5/AA5-1 -> 0.0014839242 | ... AK6: =AK5/AI5-1 -> 0.032289641
B8: Other Revenue | D8: 211 | E8: 288.4 | F8: 376 | G8: 370 | H8: 377 | I8: 108 | J8: 113 | K8: 135 | T8: 110 | U8: =D8-T8 -> 101 | V8: 200 | W8: =E8-V8 -> 88.4 | X8: 191 | Y8: =F8-X8 -> 185 | Z8: 191 | AA8: =G8-Z8 -> 179 | AB8: 55 | AC8: =H8-AB8 -> 322 | AD8: 63 | AE8: =I8-AD8 -> 45 | AF8: 58 | AG8: =J8-AF8 -> 55 | AH8: 71 | AI8: =K8-AH8 -> 64
B9: Cost of Sales | C9: =C10-C5 -> -30129 | D9: =D10-D5 -> -29981 | E9: =E10-E5 -> -25790 | F9: =F10-F5 -> -27667 | G9: =G10-G5 -> -28426 | H9: =H10-H5 -> -28292 | I9: =I10-I5 -> -29926 | J9: =J10-J8-J5 -> -32392 | K9: =K10-K8-K5 -> -32649 | L9: =L10-L5 -> -33284.2 | M9: =M10-M5 -> -34074.072 | N9: =N10-N5 -> -35484.338 | O9: =O10-O5 -> -36963.698 | P9: =P10-P5 -> -38499.861 | T9: =T10-T5 -> -15742 | U9: =U10-U5 -> -14239 | V9: =V10-V5 -> -13652 | W9: =W10-W5 -> -12138 | X9: =X10-X5 -> -14058 | Y9: =Y10-Y5 -> -13609 | Z9: =Z10-Z5 -> -15035 | AA9: =G9-Z9 -> -13391 | AB9: =AB10-AB5 -> -14875 | AC9: =H9-AB9 -> -13417 | AD9: =AD10-AD5 -> -15363 | AE9: =AE10-AE5 -> -14563 | AF9: =AF10-AF5 -> -16487 | AG9: =AG10-AG5 -> -15792 | AH9: =AH10-AH5 -> -16914 | AI9: =AI10-AI5 -> -15600 | AJ9: =AJ10-AJ5 -> -18086.212 | AK9: =AK10-AK5 -> -15197.988
A10: Gross Profit | B10: Gross Profit Reported | C10: 8996 | D10: 9026 | E10: 9211 | F10: 9741 | G10: 10159 | H10: 9945 | I10: 10557 | J10: 11292 | K10: 11838 | L10: =Model!L30+Model!L99 -> 12533.268 | M10: =Model!M30+Model!M99 -> 13160.479 | N10: =Model!N30+Model!N99 -> 13740.543 | O10: =Model!O30+Model!O99 -> 14328.276 | P10: =Model!P30+Model!P99 -> 14938.782 | T10: 4504 | U10: =D10-T10 -> 4522 | V10: 4614 | W10: =E10-V10 -> 4597 | X10: 4798 | Y10: =F10-X10 -> 4943 | Z10: 5355 | AA10: =G10-Z10 -> 4804 | AB10: 5140 | AC10: =H10-AB10 -> 4805 | AD10: 5446 | AE10: =I10-AD10 -> 5111 | AF10: 5729 | AG10: =J10-AF10 -> 5563 | AH10: 6121 | AI10: =K10-AH10 -> 5717 | AJ10: =Model!AJ30+Model!AJ99 -> 5725.938 | AK10: =L10-AJ10 -> 6807.3304
B11: Gross Margin | C11: =C10/C5 -> 0.22992971 | D11: =D10/D5 -> 0.23139437 | E11: =E10/E5 -> 0.26316391 | F11: =F10/F5 -> 0.26039885 | G11: =G10/G5 -> 0.26328884 | H11: =H10/H5 -> 0.2600884 | I11: =I10/I5 -> 0.26077613 | J11: =J10/J5 -> 0.2591632 | K11: =K10/K5 -> 0.26691017 | T11: =T10/T5 -> 0.2224637 | U11: =U10/U5 -> 0.24103193 | V11: =V10/V5 -> 0.25260046 | W11: =W10/W5 -> 0.27469376 | X11: =X10/X5 -> 0.25445482 | Y11: =Y10/Y5 -> 0.26644028 | Z11: =Z10/Z5 -> 0.26262874 | AA11: =AA10/AA5 -> 0.26402858 | ... AI11: =AI10/AI5 -> 0.26818971
B12: Change YoY % | D12: =D11-C11 -> 0.0014646527 | E12: =E11-D11 -> 0.031769544 | F12: =F11-E11 -> -0.0027650644 | G12: =G11-F11 -> 0.0028899976 | H12: =H11-G11 -> -0.0032004468 | I12: =I11-H11 -> 0.0006877322 | J12: =J11-I11 -> -0.0016129234 | K12: =K11-J11 -> 0.0077469683 | V12: =V11-T11 -> 0.030136763 | W12: =W11-U11 -> 0.033661828 | X12: =X11-V11 -> 0.0018543556 | Y12: =Y11-W11 -> -0.0082534796 | Z12: =Z11-X11 -> 0.0081739241 | AA12: =AA11-Y11 -> -0.0024116967 | AB12: =AB11-Z11 -> -0.0058213451 | AC12: =AC11-AA11 -> -0.00033633913 | ... AI12: =AI11-AG11 -> 0.0076886541
B14: Branch & Administration Expenses
B15: Employee Expenses | D15: -4321.4 | E15: -4533 | F15: -4768 | G15: -4898 | H15: -4804 | I15: -5118 | J15: -5512 | K15: -5798
B16: Occupancy | D16: -1600.3 | E16: -1635 | F16: -652 | G16: -707 | H16: -701 | I16: -774 | J16: -898 | K16: -960
B17: D&A | D17: -649.6 | E17: -640 | F17: -1440 | G17: -1513 | H17: -1385 | I17: -1461 | J17: -1398 | K17: -1569
B18: Marketing | D18: -212.5 | E18: -213 | F18: -216 | G18: -242 | H18: -230 | I18: -234 | J18: -233 | K18: -244
B19: Impairment | D19: -49 | E19: -42 | F19: 41 | G19: 3 | H19: 11 | I19: 11 | J19: -55 | K19: -4
B20: Other store expenses | D20: 0 | E20: -651 | F20: -659 | G20: -623 | H20: -551 | I20: -668 | J20: -655 | K20: -704
B21: Other administrative expenses | D21: =(898.9)*-1 -> -898.9 | E21: -317 | F21: -387 | G21: -412 | H21: -537 | I21: -604 | J21: -621 | K21: -609
B22: Total | D22: =SUM(D15:D21) -> -7731.7 | E22: =SUM(E15:E21) -> -8031 | F22: =SUM(F15:F21) -> -8081 | G22: =SUM(G15:G21) -> -8392 | H22: =SUM(H15:H21) -> -8197 | I22: =SUM(I15:I21) -> -8848 | J22: =SUM(J15:J21) -> -9372 | K22: =SUM(K15:K21) -> -9888
A24: EBITDA | B24: EBITDA Normalised | C24: =C31-C29 -> 2157 | D24: =D31-D29 -> 2044.6 | E24: =E31-E29 -> 1964.6 | F24: =F31-F29 -> 3257 | G24: =G31-G29 -> 3432 | H24: =H31-H29 -> 3259 | I24: =I31-I29 -> 3382 | J24: =J31-J29 -> 3659 | ... P24: =P31-P29 -> 5287.9771 | T24: =T31-T29 -> 1109 | U24: =U31-U29 -> 935.6 | V24: =V31-V29 -> 1043 | W24: =W31-W29 -> 921.6 | X24: =X31-X29 -> 1665 | Y24: =Y31-Y29 -> 1592 | Z24: =Z31-Z29 -> 1802 | AA24: =AA31-AA29 -> 1630 | ... AK24: =AK31-AK29 -> 2130.0733
B25: Growth % | D25: =D24/C24-1 -> -0.052109411 | E25: =E24/D24-1 -> -0.039127458 | F25: =F24/E24-1 -> 0.65784384 | G25: =G24/F24-1 -> 0.053730427 | H25: =H24/G24-1 -> -0.050407925 | I25: =I24/H24-1 -> 0.037741639 | J25: =J24/I24-1 -> 0.081904199 | K25: =K24/J24-1 -> 0.077070238 | ... P25: =P24/O24-1 -> 0.041444459 | V25: =V24/T24-1 -> -0.059513075 | W25: =W24/U24-1 -> -0.01496366 | X25: =X24/V24-1 -> 0.59635666 | Y25: =Y24/W24-1 -> 0.72743056 | Z25: =Z24/X24-1 -> 0.082282282 | AA25: =AA24/Y24-1 -> 0.023869347 | AB25: =AB24/Z24-1 -> -0.067147614 | AC25: =AC24/AA24-1 -> -0.03190184 | ... AK25: =AK24/AI24-1 -> 0.1234564
B27: RoU D&A | F27: -861 | G27: -903 | H27: -895 | I27: -847 | J27: -830 | K27: -927 | L27: =K27*1.03 -> -954.81 | M27: =L27*1.035 -> -988.22835 | N27: =M27*1.035 -> -1022.8163 | O27: =N27*1.035 -> -1058.6149 | P27: =O27*1.035 -> -1095.6664
A28: D&A ex leases | B28: Non RoU D&A | F28: =F29-F27 -> -634 | G28: =G29-G27 -> -656 | H28: =H29-H27 -> -537 | I28: =I29-I27 -> -676 | J28: =J29-J27 -> -772 | K28: =K29-K27 -> -902 | L28: =L29-L27 -> -993.075 | M28: =M29-M27 -> -1037.5721 | ... P28: =P29-P27 -> -1183.0835
A29: D&A | B29: D&A | C29: -643 | D29: -649.6 | E29: -639.6 | F29: -1495 | G29: -1559 | H29: -1432 | I29: -1523 | J29: -1602 | K29: -1829 | L29: =K29*1.065 -> -1947.885 | M29: =L29*1.04 -> -2025.8004 | N29: =M29*1.04 -> -2106.8324 | O29: =N29*1.04 -> -2191.1057 | P29: =O29*1.04 -> -2278.7499 | T29: -330 | U29: =D29-T29 -> -319.6 | V29: -321 | W29: =E29-V29 -> -318.6 | X29: -755 | Y29: =F29-X29 -> -740 | Z29: -782 | AA29: =G29-Z29 -> -777 | AB29: -718 | AC29: =H29-AB29 -> -714 | AD29: -751 | AE29: =I29-AD29 -> -772 | AF29: -790 | AG29: =J29-AF29 -> -812 | AH29: -928 | AI29: =K29-AH29 -> -901 | AJ29: =AH29*1.05 -> -974.4 | AK29: =L29-AJ29 -> -973.485
A31: Total EBIT | B31: EBIT Normalised | C31: =VLOOKUP($A$31,Model!1:1048576,MATCH(PL!C3,Model!3:3,0),FALSE) -> 1514 | D31: =VLOOKUP($A$31,Model!1:1048576,MATCH(PL!D3,Model!3:3,0),FALSE) -> 1395 | E31: =VLOOKUP($A$31,Model!1:1048576,MATCH(PL!E3,Model!3:3,0),FALSE) -> 1325 | F31: =VLOOKUP($A$31,Model!1:1048576,MATCH(PL!F3,Model!3:3,0),FALSE) -> 1762 | G31: =VLOOKUP($A$31,Model!1:1048576,MATCH(PL!G3,Model!3:3,0),FALSE) -> 1873 | H31: =VLOOKUP($A$31,Model!1:1048576,MATCH(PL!H3,Model!3:3,0),FALSE) -> 1827 | I31: =VLOOKUP($A$31,Model!1:1048576,MATCH(PL!I3,Model!3:3,0),FALSE) -> 1859 | J31: =VLOOKUP($A$31,Model!1:1048576,MATCH(PL!J3,Model!3:3,0),FALSE) -> 2057 | ... P31: =VLOOKUP($A$31,Model!1:1048576,MATCH(PL!P3,Model!3:3,0),FALSE) -> 3009.2272 | T31: =VLOOKUP($A$31,Model!1:1048576,MATCH(PL!T3,Model!3:3,0),FALSE) -> 779 | U31: =VLOOKUP($A$31,Model!1:1048576,MATCH(PL!U3,Model!3:3,0),FALSE) -> 616 | V31: =VLOOKUP($A$31,Model!1:1048576,MATCH(PL!V3,Model!3:3,0),FALSE) -> 722 | W31: =VLOOKUP($A$31,Model!1:1048576,MATCH(PL!W3,Model!3:3,0),FALSE) -> 603 | X31: =VLOOKUP($A$31,Model!1:1048576,MATCH(PL!X3,Model!3:3,0),FALSE) -> 910 | Y31: =VLOOKUP($A$31,Model!1:1048576,MATCH(PL!Y3,Model!3:3,0),FALSE) -> 852 | Z31: =VLOOKUP($A$31,Model!1:1048576,MATCH(PL!Z3,Model!3:3,0),FALSE) -> 1020 | AA31: =VLOOKUP($A$31,Model!1:1048576,MATCH(PL!AA3,Model!3:3,0),FALSE) -> 853 | ... AK31: =VLOOKUP($A$31,Model!1:1048576,MATCH(PL!AK3,Model!3:3,0),FALSE) -> 1156.5883
A32: Total EBIT Growth | B32: Growth % | D32: =D31/C31-1 -> -0.078599736 | E32: =E31/D31-1 -> -0.050179211 | F32: =F31/E31-1 -> 0.32981132 | G32: =G31/F31-1 -> 0.062996595 | H32: =H31/G31-1 -> -0.02455953 | I32: =I31/H31-1 -> 0.017515052 | J32: =J31/I31-1 -> 0.10650888 | K32: =K31/J31-1 -> 0.026737968 | ... P32: =P31/O31-1 -> 0.042540954 | V32: =V31/T31-1 -> -0.073170732 | W32: =W31/U31-1 -> -0.021103896 | X32: =X31/V31-1 -> 0.26038781 | Y32: =Y31/W31-1 -> 0.41293532 | Z32: =Z31/X31-1 -> 0.12087912 | AA32: =AA31/Y31-1 -> 0.0011737089 | AB32: =AB31/Z31-1 -> -0.055882353 | AC32: =AC31/AA31-1 -> 0.012895662 | ... AK32: =AK31/AI31-1 -> 0.16240033
B34: Significant Items | D34: =D36-D31 -> 84.4 | E34: =E36-E31 -> 142 | F34: =F36-F31 -> 0 | G34: =G36-G31 -> 0 | H34: =H36-H31 -> 0 | I34: =I36-I31 -> 0 | J34: =J36-J31 -> 0 | K34: =K36-K31 -> -35 | L34: 0 | M34: 0 | N34: 0 | O34: 0 | P34: 0 | T34: =T31-T36 -> 0 | U34: =U31-U36 -> -84.4 | V34: =V31-V36 -> -11 | W34: =W31-W36 -> -131 | X34: =X31-X36 -> 0 | Y34: =Y31-Y36 -> 0 | Z34: =Z31-Z36 -> 0 | AA34: =AA31-AA36 -> 0 | ... AI34: =AI31-AI36 -> 0 | AJ34: 0 | AK34: =L34-AJ34 -> 0
B36: EBIT Statutory | C36: =C31+C34 -> 1514 | D36: 1479.4 | E36: 1467 | F36: 1762 | G36: 1873 | H36: 1827 | I36: 1859 | J36: 2057 | K36: 2077 | L36: =L31+L34 -> 2408.234 | M36: =M31+M34 -> 2611.4417 | N36: =N31+N34 -> 2766.0256 | O36: =O31+O34 -> 2886.4355 | P36: =P31+P34 -> 3009.2272 | T36: 779 | U36: =D36-T36 -> 700.4 | V36: 733 | W36: =E36-V36 -> 734 | X36: 910 | Y36: =F36-X36 -> 852 | Z36: 1020 | AA36: =G36-Z36 -> 853 | AB36: 963 | AC36: =H36-AB36 -> 864 | AD36: 1058 | AE36: =I36-AD36 -> 801 | AF36: 1064 | AG36: =J36-AF36 -> 993 | AH36: 1082 | AI36: =K36-AH36 -> 995 | AJ36: =AJ31+AJ34 -> 1251.6457 | AK36: =AK31+AK34 -> 1156.5883
B38: Least Interest | E38: 0 | F38: -399 | G38: -390 | H38: -363 | I38: -372 | J38: -363 | K38: -425 | L38: =K38*1.03 -> -437.75 | M38: =L38*1.03 -> -450.8825 | N38: =M38*1.03 -> -464.40897 | O38: =N38*1.03 -> -478.34124 | P38: =O38*1.03 -> -492.69148 | AH38: -210 | AI38: =K38-AH38 -> -215
B39: Non-Lease Interest | F39: =F40-F38 -> -44 | G39: =G40-G38 -> -37 | H39: =H40-H38 -> 3 | I39: =I40-I38 -> -22 | J39: =J40-J38 -> -79 | K39: =K40-K38 -> -116 | L39: -115 | M39: -115 | N39: -115 | O39: -115 | P39: -115 | AH39: =AH40-AH38 -> -61 | AI39: =AI40-AI38 -> -55
A40: Net Interest | B40: Net Interest Income / (Expense) | D40: -0.1 | E40: -41.5 | F40: -443 | G40: -427 | H40: -360 | I40: -394 | J40: -442 | K40: -541 | L40: =SUM(L38:L39) -> -552.75 | M40: =SUM(M38:M39) -> -565.8825 | N40: =SUM(N38:N39) -> -579.40898 | O40: =SUM(O38:O39) -> -593.34124 | P40: =SUM(P38:P39) -> -607.69148 | T40: 0 | U40: =D40-T40 -> -0.1 | V40: -7 | W40: =E40-V40 -> -34.5 | X40: -220 | Y40: =F40-X40 -> -223 | Z40: -219 | AA40: =G40-Z40 -> -208 | AB40: -180 | AC40: =H40-AB40 -> -180 | AD40: -187 | AE40: =I40-AD40 -> -207 | AF40: -213 | AG40: =J40-AF40 -> -229 | AH40: -271 | AI40: =K40-AH40 -> -270 | AJ40: -280 | AK40: =L40-AJ40 -> -272.75
A42: PBT | B42: PBT Normalised | C42: =C31+C40 -> 1514 | D42: =D31+D40 -> 1394.9 | E42: =E31+E40 -> 1283.5 | F42: =F31+F40 -> 1319 | G42: =G31+G40 -> 1446 | H42: =H31+H40 -> 1467 | I42: =I31+I40 -> 1465 | J42: =J31+J40 -> 1615 | ... P42: =P31+P40 -> 2401.5357 | T42: =T31+T40 -> 779 | U42: =U31+U40 -> 615.9 | V42: =V31+V40 -> 715 | W42: =W31+W40 -> 568.5 | X42: =X31+X40 -> 690 | Y42: =Y31+Y40 -> 629 | Z42: =Z31+Z40 -> 801 | AA42: =AA31+AA40 -> 645 | ... AJ42: =AJ31+AJ40 -> 971.6457 | AK42: =L42-AJ42 -> 883.83833
A43: PBT Growth | B43: Growth % | D43: =D42/C42-1 -> -0.078665786 | E43: =E42/D42-1 -> -0.079862356 | F43: =F42/E42-1 -> 0.027658746 | G43: =G42/F42-1 -> 0.096285064 | H43: =H42/G42-1 -> 0.014522822 | I43: =I42/H42-1 -> -0.0013633265 | J43: =J42/I42-1 -> 0.10238908 | K43: =K42/J42-1 -> -0.027244582 | ... P43: =P42/O42-1 -> 0.047290461 | V43: =V42/T42-1 -> -0.082156611 | W43: =W42/U42-1 -> -0.076960546 | X43: =X42/V42-1 -> -0.034965035 | Y43: =Y42/W42-1 -> 0.1064204 | Z43: =Z42/X42-1 -> 0.16086957 | AA43: =AA42/Y42-1 -> 0.025437202 | AB43: =AB42/Z42-1 -> -0.02247191 | AC43: =AC42/AA42-1 -> 0.060465116 | ... AK43: =AK42/AI42-1 -> 0.21908735
A45: Tax | B45: Income Tax Normalised | D45: -456.1 | E45: -347 | F45: -341 | G45: -441 | H45: -422 | I45: -423 | J45: -487 | K45: -467 | L45: =L63 -> -556.64521 | M45: =M63 -> -613.66776 | N45: =N63 -> -655.98498 | O45: =O63 -> -687.92826 | P45: =P63 -> -720.46071 | T45: -239 | U45: =D45-T45 -> -217.1 | V45: -223 | W45: =E45-V45 -> -124 | X45: -201 | Y45: =F45-X45 -> -140 | Z45: -241 | AA45: =G45-Z45 -> -200 | AB45: -230 | AC45: =H45-AB45 -> -192 | AD45: -255 | AE45: =I45-AD45 -> -168 | AF45: -257 | AG45: =J45-AF45 -> -230 | AH45: -245 | AI45: =K45-AH45 -> -222 | AJ45: =AJ63 -> -291.49371 | AK45: =AK63 -> -265.1515
B47: Minority Interest | D47: 0 | E47: 0 | F47: 0 | G47: 0 | H47: 0 | I47: 0 | J47: 0 | K47: 0 | L47: =K47 -> 0 | M47: =L47 -> 0 | N47: =M47 -> 0 | O47: =N47 -> 0 | P47: =O47 -> 0 | T47: 0 | U47: =D47-T47 -> 0 | V47: 0 | W47: =E47-V47 -> 0 | X47: 0 | Y47: =F47-X47 -> 0 | Z47: 0 | AA47: =G47-Z47 -> 0 | AB47: 0 | AC47: =H47-AB47 -> 0 | AD47: 0 | AE47: =I47-AD47 -> 0 | AF47: 0 | AG47: =J47-AF47 -> 0 | AH47: 0 | AI47: =K47-AH47 -> 0 | AJ47: -1 | AK47: =L47-AJ47 -> 1
A49: NPAT | B49: NPAT Normalised | C49: =C47+C45+C42 -> 1514 | D49: =D47+D45+D42 -> 938.8 | E49: =E47+E45+E42 -> 936.5 | F49: =F47+F45+F42 -> 978 | G49: =G47+G45+G42 -> 1005 | H49: =H47+H45+H42 -> 1045 | I49: =I47+I45+I42 -> 1042 | J49: =J47+J45+J42 -> 1128 | ... P49: =P47+P45+P42 -> 1681.075 | T49: =T47+T45+T42 -> 540 | U49: =U47+U45+U42 -> 398.8 | V49: =V47+V45+V42 -> 492 | W49: =W47+W45+W42 -> 444.5 | X49: =X47+X45+X42 -> 489 | Y49: =Y47+Y45+Y42 -> 489 | Z49: =Z47+Z45+Z42 -> 560 | AA49: =AA47+AA45+AA42 -> 445 | ... AK49: =AK47+AK45+AK42 -> 619.68683
A50: NPAT Growth | B50: Growth % | D50: =D49/C49-1 -> -0.37992074 | E50: =E49/D49-1 -> -0.0024499361 | F50: =F49/E49-1 -> 0.044313935 | G50: =G49/F49-1 -> 0.027607362 | H50: =H49/G49-1 -> 0.039800995 | I50: =I49/H49-1 -> -0.0028708134 | J50: =J49/I49-1 -> 0.082533589 | K50: =K49/J49-1 -> -0.021276596 | ... P50: =P49/O49-1 -> 0.047290461 | V50: =V49/T49-1 -> -0.088888889 | W50: =W49/U49-1 -> 0.11459378 | X50: =X49/V49-1 -> -0.006097561 | Y50: =Y49/W49-1 -> 0.10011249 | Z50: =Z49/X49-1 -> 0.14519427 | AA50: =AA49/Y49-1 -> -0.08997955 | AB50: =AB49/Z49-1 -> -0.0125 | AC50: =AC49/AA49-1 -> 0.10561798 | ... AK50: =AK49/AI49-1 -> 0.23198177
B52: Significant Items | C52: =C54-C49 -> 19.5 | D52: =D54-D49 -> 640 | E52: =E54-E49 -> 498.2 | F52: =F54-F49 -> 0 | G52: =G54-G49 -> 0 | H52: =H54-H49 -> 3 | I52: =I54-I49 -> 56 | J52: =J54-J49 -> -10 | K52: =K54-K49 -> -25 | L52: =L34+L64 -> 0 | M52: =M34+M64 -> 0 | N52: =N34+N64 -> 0 | O52: =O34+O64 -> 0 | P52: =P34+P64 -> 0 | T52: =T49-T54 -> 0 | U52: =U49-U54 -> -640 | V52: =V49-V54 -> -13.5 | W52: =W49-W54 -> -484.7 | X52: =X49-X54 -> 0 | Y52: =Y49-Y54 -> 0 | Z52: =Z49-Z54 -> 0 | AA52: =AA49-AA54 -> 0 | ... AI52: =AI49-AI54 -> 0 | AJ52: 0 | AK52: =L52-AJ52 -> 0
B54: NPAT Statutory | C54: 1533.5 | D54: 1578.8 | E54: 1434.7 | F54: 978 | G54: 1005 | H54: 1048 | I54: 1098 | J54: 1118 | K54: 1079 | L54: =L49+L52 -> 1298.8388 | M54: =M49+M52 -> 1431.8914 | N54: =N49+N52 -> 1530.6316 | O54: =O49+O52 -> 1605.1659 | P54: =P49+P52 -> 1681.075 | T54: 540 | U54: =D54-T54 -> 1038.8 | V54: 505.5 | W54: =E54-V54 -> 929.2 | X54: 489 | Y54: =F54-X54 -> 489 | Z54: 560 | AA54: =G54-Z54 -> 445 | AB54: 553 | AC54: =H54-AB54 -> 495 | AD54: 616 | AE54: =I54-AD54 -> 482 | AF54: 589 | AG54: =J54-AF54 -> 529 | AH54: 576 | AI54: =K54-AH54 -> 503 | AJ54: =L54-AI54 -> 795.83882 | AK54: =M54-AJ54 -> 636.05262
B55: Growth % | D55: =D54/C54-1 -> 0.029540267 | E55: =E54/D54-1 -> -0.091271852 | F55: =F54/E54-1 -> -0.31832439 | G55: =G54/F54-1 -> 0.027607362 | H55: =H54/G54-1 -> 0.04278607 | I55: =I54/H54-1 -> 0.047709924 | J55: =J54/I54-1 -> 0.018214936 | K55: =K54/J54-1 -> -0.034883721 | V55: =V54/T54-1 -> -0.063888889 | W55: =W54/U54-1 -> -0.10550635 | X55: =X54/V54-1 -> -0.03264095 | Y55: =Y54/W54-1 -> -0.47374085 | Z55: =Z54/X54-1 -> 0.14519427 | AA55: =AA54/Y54-1 -> -0.08997955 | AB55: =AB54/Z54-1 -> -0.0125 | AC55: =AC54/AA54-1 -> 0.11235955 | ... AK55: =AK54/AI54-1 -> 0.26451813
A57: Shares Diluted | B57: Shares (Diluted) | C57: =C79 -> 0 | D57: =D79 -> 1333.9 | E57: =E79 -> 1334 | F57: =F79 -> 1334 | G57: =G79 -> 1335 | H57: =H79 -> 1331 | I57: =I79 -> 1338 | J57: =J79 -> 1338 | ... P57: =P79 -> 1350 | T57: =T79 -> 1334 | U57: =U79 -> 1333.9 | V57: =V79 -> 1334 | W57: =W79 -> 1334 | X57: =X79 -> 1334 | Y57: =Y79 -> 1334 | Z57: =Z79 -> 1334 | AA57: =AA79 -> 1335 | ... AK57: =AK79 -> 1342
A59: EPS | B59: EPS Normalised | D59: =D49/D57 -> 0.70380088 | E59: =E49/E57 -> 0.70202399 | F59: =F49/F57 -> 0.73313343 | G59: =G49/G57 -> 0.75280899 | H59: =H49/H57 -> 0.78512397 | I59: =I49/I57 -> 0.77877429 | J59: =J49/J57 -> 0.84304933 | K59: =K49/K57 -> 0.8238806 | ... P59: =P49/P57 -> 1.2452407 | T59: =T49/T57 -> 0.4047976 | U59: =U49/U57 -> 0.29897294 | V59: =V49/V57 -> 0.36881559 | W59: =W49/W57 -> 0.3332084 | X59: =X49/X57 -> 0.36656672 | Y59: =Y49/Y57 -> 0.36656672 | Z59: =Z49/Z57 -> 0.4197901 | AA59: =AA49/AA57 -> 0.33333333 | ... AK59: =AK49/AK57 -> 0.46176366
A60: EPS Growth | B60: Growth % | E60: =E59/D59-1 -> -0.002524715 | F60: =F59/E59-1 -> 0.044313935 | G60: =G59/F59-1 -> 0.026837619 | H60: =H59/G59-1 -> 0.042925867 | I60: =I59/H59-1 -> -0.0080874833 | J60: =J59/I59-1 -> 0.082533589 | K60: =K59/J59-1 -> -0.022737377 | L60: =L59/K59-1 -> 0.1747311 | ... P60: =P59/O59-1 -> 0.045738919 | V60: =V59/T59-1 -> -0.088888889 | W60: =W59/U59-1 -> 0.11451023 | X60: =X59/V59-1 -> -0.006097561 | Y60: =Y59/W59-1 -> 0.10011249 | Z60: =Z59/X59-1 -> 0.14519427 | AA60: =AA59/Y59-1 -> -0.090661213 | AB60: =AB59/Z59-1 -> -0.0132397 | AC60: =AC59/AA59-1 -> 0.10894065 | ... AK60: =AK59/AI59-1 -> 0.23014573
B62: Tax Modelling
B63: Tax Normalised | D63: =D45 -> -456.1 | E63: =E45 -> -347 | F63: =F45 -> -341 | G63: =G45 -> -441 | H63: =H45 -> -422 | I63: =I45 -> -423 | J63: =J45 -> -487 | K63: =K45 -> -467 | L63: =L73*-L68 -> -556.64521 | M63: =M73*-M68 -> -613.66776 | N63: =N73*-N68 -> -655.98498 | O63: =O73*-O68 -> -687.92826 | P63: =P73*-P68 -> -720.46071 | T63: =T45 -> -239 | U63: =U45 -> -217.1 | V63: =V45 -> -223 | W63: =W45 -> -124 | X63: =X45 -> -201 | Y63: =Y45 -> -140 | Z63: =Z45 -> -241 | AA63: =AA45 -> -200 | ... AI63: =AI45 -> -222 | AJ63: =AJ73*-AJ68 -> -291.49371 | AK63: =L63-AJ63 -> -265.1515
B64: Significant Items | D64: =D65-D63 -> 0 | E64: =E65-E63 -> 0 | F64: =F65-F63 -> 0 | G64: =G65-G63 -> 0 | H64: =H65-H63 -> 0 | I64: =I65-I63 -> 0 | J64: =J65-J63 -> 0 | K64: =K65-K63 -> 10 | L64: =L74*-L69 -> 0 | M64: =M74*-M69 -> 0 | N64: =N74*-N69 -> 0 | O64: =O74*-O69 -> 0 | P64: =P74*-P69 -> 0 | T64: =T65-T63 -> 0 | U64: =U65-U63 -> -172.9 | V64: =V65-V63 -> 0 | W64: =W65-W63 -> -266 | X64: =X65-X63 -> 0 | Y64: =Y65-Y63 -> -250 | Z64: =Z65-Z63 -> 0 | AA64: =AA65-AA63 -> 0 | ... AI64: =AI65-AI63 -> 0 | AJ64: =AJ74*-AJ69 -> 0 | AK64: =L64-AJ64 -> 0
B65: Tax Statutory | D65: -456.1 | E65: -347 | F65: -341 | G65: -441 | H65: -422 | I65: -423 | J65: -487 | K65: -457 | L65: =L63+L64 -> -556.64521 | M65: =M63+M64 -> -613.66776 | N65: =N63+N64 -> -655.98498 | O65: =O63+O64 -> -687.92826 | P65: =P63+P64 -> -720.46071 | T65: -239 | U65: -390 | V65: -223 | W65: -390 | X65: -201 | Y65: -390 | Z65: -241 | AA65: =G65-Z65 -> -200 | AB65: -230 | AC65: =H65-AB65 -> -192 | AD65: -255 | AE65: =I65-AD65 -> -168 | AF65: -257 | AG65: =J65-AF65 -> -230 | AH65: -235 | AI65: =K65-AH65 -> -222 | AJ65: =AJ63+AJ64 -> -291.49371 | AK65: =L65-AJ65 -> -265.1515
B67: Tax Rates
B68: Tax Normalised | D68: =-D63/D73 -> 0.32697684 | E68: =-E63/E73 -> 0.2703545 | F68: =-F63/F73 -> 0.25852919 | G68: =-G63/G73 -> 0.30497925 | H68: =-H63/H73 -> 0.2876619 | I68: =-I63/I73 -> 0.2887372 | J68: =-J63/J73 -> 0.30154799 | K68: =-K63/K73 -> 0.29726289 | L68: 0.3 | M68: 0.3 | N68: 0.3 | O68: 0.3 | P68: 0.3 | T68: =-T63/T73 -> 0.30680359 | U68: =-U63/U73 -> 0.35249229 | V68: =-V63/V73 -> 0.31188811 | W68: =-W63/W73 -> 0.21811785 | X68: =-X63/X73 -> 0.29130435 | Y68: =-Y63/Y73 -> 0.22257552 | Z68: =-Z63/Z73 -> 0.30087391 | AA68: =-AA63/AA73 -> 0.31007752 | ... AI68: =-AI63/AI73 -> 0.3062069 | AJ68: 0.3 | AK68: =-AK63/AK73 -> 0.3
B69: Significant items | D69: =-D64/D74 -> 0 | E69: =-E64/E74 -> 0 | K69: =-K64/K74 -> 0.28571429 | L69: 0.3 | M69: 0.3 | N69: 0.3 | O69: 0.3 | P69: 0.3 | U69: =-U64/U74 -> 2.0485782 | V69: =-V64/V74 -> 0 | W69: =-W64/W74 -> 2.0383142 | AH69: =-AH64/AH74 -> 0.28571429 | AJ69: 0.3
B70: Tax Statutory | D70: =-D65/D75 -> 0.3083215 | E70: =-E65/E75 -> 0.24350877 | F70: =-F65/F75 -> 0.25852919 | G70: =-G65/G75 -> 0.30497925 | H70: =-H65/H75 -> 0.2876619 | I70: =-I65/I75 -> 0.2887372 | J70: =-J65/J75 -> 0.30154799 | K70: =-K65/K75 -> 0.29752604 | ... P70: =-P65/P75 -> 0.3 | T70: =-T65/T75 -> 0.30680359 | U70: =-U65/U75 -> 0.55690418 | V70: =-V65/V75 -> 0.30716253 | W70: =-W65/W75 -> 0.55793991 | X70: =-X65/X75 -> 0.29130435 | Y70: =-Y65/Y75 -> 0.6200318 | Z70: =-Z65/Z75 -> 0.30087391 | AA70: =-AA65/AA75 -> 0.31007752 | ... AK70: =-AK65/AK75 -> 0.3
B72: PBT
B73: PBT Normalised | D73: =D42 -> 1394.9 | E73: =E42 -> 1283.5 | F73: =F42 -> 1319 | G73: =G42 -> 1446 | H73: =H42 -> 1467 | I73: =I42 -> 1465 | J73: =J42 -> 1615 | K73: =K42 -> 1571 | ... P73: =P42 -> 2401.5357 | T73: =T42 -> 779 | U73: =U42 -> 615.9 | V73: =V42 -> 715 | W73: =W42 -> 568.5 | X73: =X42 -> 690 | Y73: =Y42 -> 629 | Z73: =Z42 -> 801 | AA73: =AA42 -> 645 | ... AJ73: =AJ42 -> 971.6457 | AK73: =L73-AJ73 -> 883.83833
B74: Significant items | D74: =D75-D73 -> 84.4 | E74: =E75-E73 -> 141.5 | F74: =F75-F73 -> 0 | G74: =G75-G73 -> 0 | H74: =H75-H73 -> 0 | I74: =I75-I73 -> 0 | J74: =J75-J73 -> 0 | K74: =K75-K73 -> -35 | L74: =L34 -> 0 | M74: =M34 -> 0 | N74: =N34 -> 0 | O74: =O34 -> 0 | P74: =P34 -> 0 | T74: =T75-T73 -> 0 | U74: =U75-U73 -> 84.4 | V74: =V75-V73 -> 11 | W74: =W75-W73 -> 130.5 | X74: =X75-X73 -> 0 | Y74: =Y75-Y73 -> 0 | Z74: =Z75-Z73 -> 0 | AA74: =AA75-AA73 -> 0 | AB74: =AB75-AB73 -> 0 | AC74: =H74-AB74 -> 0 | AD74: =AD75-AD73 -> 0 | AE74: =AE75-AE73 -> 0 | AF74: =AF75-AF73 -> 0 | AG74: =AG75-AG73 -> 0 | AH74: =AH75-AH73 -> -35 | AI74: =AI75-AI73 -> 0 | AJ74: =AJ34 -> 0 | AK74: =L74-AJ74 -> 0
B75: PBT statutory | D75: 1479.3 | E75: 1425 | F75: 1319 | G75: 1446 | H75: 1467 | I75: 1465 | J75: 1615 | K75: 1536 | L75: =L73+L74 -> 1855.484 | M75: =M73+M74 -> 2045.5592 | N75: =N73+N74 -> 2186.6166 | O75: =O73+O74 -> 2293.0942 | P75: =P73+P74 -> 2401.5357 | T75: 779 | U75: =D75-T75 -> 700.3 | V75: 726 | W75: =E75-V75 -> 699 | X75: 690 | Y75: =F75-X75 -> 629 | Z75: 801 | AA75: =G75-Z75 -> 645 | AB75: 783 | AC75: =H75-AB75 -> 684 | AD75: 871 | AE75: =I75-AD75 -> 594 | AF75: 851 | AG75: =J75-AF75 -> 764 | AH75: 811 | AI75: =K75-AH75 -> 725 | AJ75: =AJ73+AJ74 -> 971.6457 | AK75: =L75-AJ75 -> 883.83833
A77: Shares EOP | B77: Period End Shares | C77: 1333.9294 | D77: 1334 | E77: 1334 | F77: 1334 | G77: 1334 | H77: 1330 | I77: 1334 | J77: 1339.4194 | K77: 1341.3055 | L77: =K77+(K77-J77) -> 1343.1915 | M77: =L77+(L77-K77) -> 1345.0776 | N77: =M77+(M77-L77) -> 1346.9637 | O77: =N77+(N77-M77) -> 1348.8498 | P77: =O77+(O77-N77) -> 1350.7358 | T77: =C77 -> 1333.9294 | U77: =D77 -> 1334 | V77: =D77 -> 1334 | W77: =E77 -> 1334 | X77: =E77 -> 1334 | Y77: =F77 -> 1334 | Z77: =F77 -> 1334 | AA77: =G77 -> 1334 | AB77: =G77 -> 1334 | AC77: =H77 -> 1330 | AD77: =H77 -> 1330 | AE77: =I77 -> 1334 | AF77: =I77 -> 1334 | AG77: =J77 -> 1339.4194 | AH77: =J77 -> 1339.4194 | AI77: =K77 -> 1341.3055 | AJ77: =AVERAGE(K77:L77) -> 1342.2485 | AK77: =L77 -> 1343.1915
B78: Weighted Average Basic | D78: 1334 | E78: 1334 | F78: 1334 | G78: 1334 | H78: 1330 | I78: 1334 | J78: 1334 | K78: 1336 | L78: =K78+(K78-J78) -> 1338 | M78: =L78+(L78-K78) -> 1340 | N78: =M78+(M78-L78) -> 1342 | O78: =N78+(N78-M78) -> 1344 | P78: =O78+(O78-N78) -> 1346 | T78: 1334 | U78: =D78 -> 1334 | V78: 1334 | W78: =E78 -> 1334 | X78: 1334 | Y78: =F78 -> 1334 | Z78: 1334 | AA78: =G78 -> 1334 | AB78: 1335 | AC78: =H78 -> 1330 | AD78: 1332 | AE78: =I78 -> 1334 | AF78: 1334 | AG78: =J78 -> 1334 | AH78: 1336 | AI78: =K78 -> 1336 | AJ78: =AVERAGE(K78:L78) -> 1337 | AK78: =L78 -> 1338
B79: Weighted Average Diluted | D79: 1333.9 | E79: 1334 | F79: 1334 | G79: 1335 | H79: 1331 | I79: 1338 | J79: 1338 | K79: 1340 | L79: =K79+(K79-J79) -> 1342 | M79: =L79+(L79-K79) -> 1344 | N79: =M79+(M79-L79) -> 1346 | O79: =N79+(N79-M79) -> 1348 | P79: =O79+(O79-N79) -> 1350 | T79: 1334 | U79: =D79 -> 1333.9 | V79: 1334 | W79: =E79 -> 1334 | X79: 1334 | Y79: =F79 -> 1334 | Z79: 1334 | AA79: =G79 -> 1335 | AB79: 1335 | AC79: =H79 -> 1331 | AD79: 1336 | AE79: =I79 -> 1338 | AF79: 1337 | AG79: =J79 -> 1338 | AH79: 1339 | AI79: =K79 -> 1340 | AJ79: =AVERAGE(K79:L79) -> 1341 | AK79: =L79 -> 1342
B81: Ordinary Dividend | D81: 0 | E81: 0.36 | F81: 0.57 | G81: 0.61 | H81: 0.63 | I81: 0.66 | J81: 0.68 | K81: 0.69 | L81: =L84*L59 -> 0.82266244 | M81: =M84*M59 -> 0.9055861 | N81: =N84*N59 -> 0.96659501 | O81: =O84*O59 -> 1.0121595 | P81: =P84*P59 -> 1.0584546 | T81: 0 | U81: =D81-T81 -> 0 | V81: 0 | W81: =E81-V81 -> 0.36 | X81: 0.3 | Y81: =F81-X81 -> 0.27 | Z81: 0.33 | AA81: =G81-Z81 -> 0.28 | AB81: 0.33 | AC81: =H81-AB81 -> 0.3 | AD81: 0.36 | AE81: =I81-AD81 -> 0.3 | AF81: 0.36 | AG81: =J81-AF81 -> 0.32 | AH81: 0.37 | AI81: =K81-AH81 -> 0.32 | AJ81: =AJ84*AJ59 -> 0.41762072 | AK81: =L81-AJ81 -> 0.40504172
B82: Special Dividend | D82: 0 | E82: 0.115 | F82: 0 | G82: 0 | H82: 0 | I82: 0 | J82: 0 | K82: 0 | L82: 0 | M82: 0 | N82: 0 | O82: 0 | P82: 0 | T82: 0 | U82: =D82-T82 -> 0 | V82: 0 | W82: =E82-V82 -> 0.115 | X82: 0 | Y82: =F82-X82 -> 0 | Z82: 0 | AA82: =G82-Z82 -> 0 | AB82: 0 | AC82: =H82-AB82 -> 0 | AD82: 0 | AE82: =I82-AD82 -> 0 | AF82: 0 | AG82: =J82-AF82 -> 0 | AH82: 0 | AI82: =K82-AH82 -> 0 | AJ82: 0 | AK82: =L82-AJ82 -> 0
A83: DPS | B83: Total Dividend Per Share | D83: =SUM(D81:D82) -> 0 | E83: =SUM(E81:E82) -> 0.475 | F83: =SUM(F81:F82) -> 0.57 | G83: =SUM(G81:G82) -> 0.61 | H83: =SUM(H81:H82) -> 0.63 | I83: =SUM(I81:I82) -> 0.66 | J83: =SUM(J81:J82) -> 0.68 | K83: =SUM(K81:K82) -> 0.69 | ... P83: =SUM(P81:P82) -> 1.0584546 | T83: =SUM(T81:T82) -> 0 | U83: =D83-T83 -> 0 | V83: =SUM(V81:V82) -> 0 | W83: =E83-V83 -> 0.475 | X83: =SUM(X81:X82) -> 0.3 | Y83: =F83-X83 -> 0.27 | Z83: =SUM(Z81:Z82) -> 0.33 | AA83: =G83-Z83 -> 0.28 | AB83: =SUM(AB81:AB82) -> 0.33 | AC83: =H83-AB83 -> 0.3 | AD83: =SUM(AD81:AD82) -> 0.36 | AE83: =I83-AD83 -> 0.3 | AF83: =SUM(AF81:AF82) -> 0.36 | AG83: =J83-AF83 -> 0.32 | AH83: =SUM(AH81:AH82) -> 0.37 | AI83: =K83-AH83 -> 0.32 | AJ83: =SUM(AJ81:AJ82) -> 0.41762072 | AK83: =L83-AJ83 -> 0.40504172
A84: Payout Ratio | B84: Payout Ratio % | D84: =(D83*D77)/D49 -> 0 | E84: =(E83*E77)/E49 -> 0.67661506 | F84: =(F83*F77)/F49 -> 0.77748466 | G84: =(G83*G77)/G49 -> 0.80969154 | H84: =(H83*H77)/H49 -> 0.80181818 | I84: =(I83*I77)/I49 -> 0.84495202 | J84: =(J83*J77)/J49 -> 0.80745141 | K84: =(K83*K77)/K49 -> 0.83831592 | L84: 0.85 | M84: 0.85 | N84: 0.85 | O84: 0.85 | P84: 0.85 | T84: =(T83*T77)/T49 -> 0 | U84: =(U83*U77)/U49 -> 0 | V84: =(V83*V77)/V49 -> 0 | W84: =(W83*W77)/W49 -> 1.4255343 | X84: =(X83*X77)/X49 -> 0.81840491 | Y84: =(Y83*Y77)/Y49 -> 0.73656442 | Z84: =(Z83*Z77)/Z49 -> 0.78610714 | AA84: =(AA83*AA77)/AA49 -> 0.83937079 | ... AI84: =(AI83*AI77)/AI49 -> 0.85331561 | AJ84: =AH84 -> 0.82460097 | AK84: =(AK83*AK77)/AK49 -> 0.87794123
B86: Franking | D86: 1 | E86: 1 | F86: 1 | G86: 1 | H86: 1 | I86: 1 | J86: 1 | K86: 1 | L86: =K86 -> 1 | M86: =L86 -> 1 | N86: =M86 -> 1 | O86: =N86 -> 1 | P86: =O86 -> 1 | T86: 1 | U86: 1 | V86: 1 | W86: =E86 -> 1 | X86: 1 | Y86: =F86 -> 1 | Z86: 1 | AA86: =G86 -> 1 | AB86: 1 | AC86: =H86 -> 1 | AD86: 1 | AE86: =I86 -> 1 | AF86: 1 | AG86: =J86 -> 1 | AH86: 1 | AI86: =K86 -> 1
B87: Franking Rate | D87: 0.3 | E87: 0.3 | F87: 0.3 | G87: 0.3 | H87: 0.3 | I87: 0.3 | J87: 0.3 | K87: 0.3 | L87: =K87 -> 0.3 | M87: =L87 -> 0.3 | N87: =M87 -> 0.3 | O87: =N87 -> 0.3 | P87: =O87 -> 0.3 | T87: 0.3 | U87: 0.3 | V87: 0.3 | W87: =E87 -> 0.3 | X87: 0.3 | Y87: =F87 -> 0.3 | Z87: 0.3 | AA87: =G87 -> 0.3 | AB87: 0.3 | AC87: =H87 -> 0.3 | AD87: 0.3 | AE87: =I87 -> 0.3 | AF87: 0.3 | AG87: =J87 -> 0.3 | AH87: 0.3 | AI87: =K87 -> 0.3
B88: Franking Credits | D88: 0 | E88: 277 | F88: 408 | G88: 420 | H88: 558 | I88: 549 | J88: 553 | K88: 672
L90: =L49/L78 -> 0.97073155 | M90: =M49/M78 -> 1.0685757 | N90: =N49/N78 -> 1.1405601 | O90: =O49/O78 -> 1.1943199

Sheet CF
B1: Coles Group (COL.AX)
B2: A$M
C3: =Model!C3 -> FY17 | D3: =Model!D3 -> FY18 | E3: =Model!E3 -> FY19 | F3: =Model!F3 -> FY20 | G3: =Model!G3 -> FY21 | H3: =Model!H3 -> FY22 | I3: =Model!I3 -> FY23 | J3: =Model!J3 -> FY24 | K3: =Model!K3 -> FY25 | L3: FY26E | M3: FY27E | N3: FY28E | O3: FY29E | P3: FY30E | R3: =Model!S3 -> 1H17 | S3: =Model!T3 -> 2H17 | T3: =Model!U3 -> 1H18 | U3: =Model!V3 -> 2H18 | V3: =Model!W3 -> 1H19 | W3: =Model!X3 -> 2H19 | X3: =Model!Y3 -> 1H20 | Y3: =Model!Z3 -> 2H20 | ... AI3: =Model!AJ3 -> 2H25
B4: CFS
B5: Operating cash flow
A6: EBIT | B6: EBIT | D6: =PL!D31 -> 1395 | E6: =PL!E31 -> 1325 | F6: =PL!F31 -> 1762 | G6: =PL!G31 -> 1873 | H6: =PL!H31 -> 1827 | I6: =PL!I31 -> 1859 | J6: =PL!J31 -> 2057 | K6: =PL!K31 -> 2112 | ... P6: =PL!P31 -> 3009.2272 | T6: =PL!T31 -> 779 | U6: =PL!U31 -> 616 | V6: =PL!V31 -> 722 | W6: =PL!W31 -> 603 | X6: =PL!X31 -> 910 | Y6: =PL!Y31 -> 852 | Z6: =PL!Z31 -> 1020 | AA6: =PL!AA31 -> 853 | ... AI6: =PL!AI31 -> 995
A7: D&A | B7: Depreciation and Amortisation | D7: =-PL!D29 -> 649.6 | E7: =-PL!E29 -> 639.6 | F7: =-PL!F29 -> 1495 | G7: =-PL!G29 -> 1559 | H7: =-PL!H29 -> 1432 | I7: =-PL!I29 -> 1523 | J7: =-PL!J29 -> 1602 | K7: =-PL!K29 -> 1829 | ... P7: =-PL!P29 -> 2278.7499 | T7: =-PL!T29 -> 330 | U7: =-PL!U29 -> 319.6 | V7: =-PL!V29 -> 321 | W7: =-PL!W29 -> 318.6 | X7: =-PL!X29 -> 755 | Y7: =-PL!Y29 -> 740 | Z7: =-PL!Z29 -> 782 | AA7: =-PL!AA29 -> 777 | ... AI7: =-PL!AI29 -> 901
A8: Chg WC | B8: Change in Net Working Capital | D8: =BS!D61 -> 4069 | E8: =BS!E61 -> -3013.5 | F8: =BS!F61 -> 81.5 | G8: =BS!G61 -> 48 | H8: =BS!H61 -> 232 | I8: =BS!I61 -> 89 | J8: =BS!J61 -> -121 | K8: =BS!K61 -> 32 | ... P8: =BS!P61 -> 68.583845 | T8: =BS!T61 -> -3212 | U8: =BS!U61 -> 7281 | V8: =BS!V61 -> 3067 | W8: =BS!W61 -> -6080.5 | X8: =BS!X61 -> 216.5 | Y8: =BS!Y61 -> -135 | Z8: =BS!Z61 -> -198 | AA8: =BS!AA61 -> 246 | ... AI8: =BS!AI61 -> -602
A9: Tax | B9: Tax Paid | D9: =PL!D45 -> -456.1 | E9: =PL!E45 -> -347 | F9: =PL!F45 -> -341 | G9: =PL!G45 -> -441 | H9: =PL!H45 -> -422 | I9: =PL!I45 -> -423 | J9: =PL!J45 -> -487 | K9: =PL!K45 -> -467 | ... P9: =PL!P45 -> -720.46071 | T9: =PL!T45 -> -239 | U9: =PL!U45 -> -217.1 | V9: =PL!V45 -> -223 | W9: =PL!W45 -> -124 | X9: =PL!X45 -> -201 | Y9: =PL!Y45 -> -140 | Z9: =PL!Z45 -> -241 | AA9: =PL!AA45 -> -200 | ... AI9: =PL!AI45 -> -222
A10: Net interest | B10: Net interest | D10: =PL!D40 -> -0.1 | E10: =PL!E40 -> -41.5 | F10: =PL!F40 -> -443 | G10: =PL!G40 -> -427 | H10: =PL!H40 -> -360 | I10: =PL!I40 -> -394 | J10: =PL!J40 -> -442 | K10: =PL!K40 -> -541 | ... P10: =PL!P40 -> -607.69148 | T10: =PL!T40 -> 0 | U10: =PL!U40 -> -0.1 | V10: =PL!V40 -> -7 | W10: =PL!W40 -> -34.5 | X10: =PL!X40 -> -220 | Y10: =PL!Y40 -> -223 | Z10: =PL!Z40 -> -219 | AA10: =PL!AA40 -> -208 | ... AI10: =PL!AI40 -> -270
A11: Other | B11: Other | D11: =D12-SUM(D6:D10) -> -3747.5 | E11: =E12-SUM(E6:E10) -> 3712.4 | F11: =F12-SUM(F6:F10) -> -2.5 | G11: =G12-SUM(G6:G10) -> 225 | H11: =H12-SUM(H6:H10) -> -19 | I11: =I12-SUM(I6:I10) -> 153 | J11: =J12-SUM(J6:J10) -> 184 | K11: =K12-SUM(K6:K10) -> -29 | L11: 0 | M11: 0 | N11: 0 | O11: 0 | P11: 0 | T11: =T12-SUM(T6:T10) -> 3569 | U11: =U12-SUM(U6:U10) -> -7316.5 | V11: =V12-SUM(V6:V10) -> -2166 | W11: =W12-SUM(W6:W10) -> 5878.4 | X11: =X12-SUM(X6:X10) -> -436.5 | Y11: =Y12-SUM(Y6:Y10) -> 434 | Z11: =Z12-SUM(Z6:Z10) -> 592 | AA11: =AA12-SUM(AA6:AA10) -> -367 | ... AI11: =AI12-SUM(AI6:AI10) -> 1284
A12: OCF | B12: Net Operating Cash Flow | D12: =D21 -> 1909.9 | E12: =E21 -> 2275 | F12: =F21 -> 2552 | G12: =G21 -> 2837 | H12: =H21 -> 2690 | I12: =I21 -> 2807 | J12: =J21 -> 2793 | K12: =K21 -> 2936 | L12: =SUM(L6:L11) -> 3293.544 | M12: =SUM(M6:M11) -> 3502.9661 | N12: =SUM(N6:N11) -> 3701.053 | O12: =SUM(O6:O11) -> 3862.3131 | P12: =SUM(P6:P11) -> 4028.4088 | T12: =T21 -> 1227 | U12: =D12-T12 -> 682.9 | V12: =V21 -> 1714 | W12: =E12-V12 -> 561 | X12: =X21 -> 1024 | Y12: =F12-X12 -> 1528 | Z12: =Z21 -> 1736 | AA12: =G12-Z12 -> 1101 | AB12: =AB21 -> 1603 | AC12: =H12-AB12 -> 1087 | AD12: =AD21 -> 1593 | AE12: =I12-AD12 -> 1214 | AF12: =AF21 -> 1504 | AG12: =J12-AF12 -> 1289 | AH12: =AH21 -> 850 | AI12: =K12-AH12 -> 2086
B14: Reported Operating Cash Flow Items
B15: Receipts from customers | D15: 41756.1 | E15: =41126+137 -> 41263 | F15: 39971 | G15: 41138 | H15: 41887 | I15: 44043 | J15: 46145 | K15: 46787 | T15: 21039 | U15: =D15-T15 -> 20717.1 | V15: 21828 | W15: =E15-V15 -> 19435 | X15: 20221 | Y15: =F15-X15 -> 19750 | Z15: 22202 | AA15: =G15-Z15 -> 18936 | AB15: 21956 | AC15: =H15-AB15 -> 19931 | AD15: 22858 | AE15: =I15-AD15 -> 21185 | AF15: 23542 | AG15: =J15-AF15 -> 22603 | AH15: 24332 | AI15: =K15-AH15 -> 22455
B16: Payments to suppliers | D16: -39351.4 | E16: -38665 | F16: -36486 | G16: -37510 | H16: -38309 | I16: -40439 | J16: -42556 | K16: -42806 | T16: -19529 | U16: =D16-T16 -> -19822.4 | V16: -20094 | W16: =E16-V16 -> -18571 | X16: -18685 | Y16: =F16-X16 -> -17801 | Z16: -20045 | AA16: =G16-Z16 -> -17465 | AB16: -19892 | AC16: =H16-AB16 -> -18417 | AD16: -20814 | AE16: =I16-AD16 -> -19625 | AF16: -21656 | AG16: =J16-AF16 -> -20900 | AH16: -22940 | AI16: =K16-AH16 -> -19866
B17: Interest paid | E17: -33 | F17: -37 | G17: -47 | H17: -41 | I17: -57 | J17: -57 | K17: -108 | T17: 1 | U17: =D17-T17 -> -1 | V17: -4 | W17: =E17-V17 -> -29 | X17: -20 | Y17: =F17-X17 -> -17 | Z17: -18 | AA17: =G17-Z17 -> -29 | AB17: -21 | AC17: =H17-AB17 -> -20 | AD17: -27 | AE17: =I17-AD17 -> -30 | AF17: -19 | AG17: =J17-AF17 -> -38 | AH17: -62 | AI17: =K17-AH17 -> -46
B18: Interest component of lease payments | F18: -399 | G18: -390 | H18: -363 | I18: -372 | J18: -363 | K18: -425 | U18: =D18-T18 -> 0 | W18: =E18-V18 -> 0 | X18: -193 | Y18: =F18-X18 -> -206 | Z18: -199 | AA18: =G18-Z18 -> -191 | AB18: -181 | AC18: =H18-AB18 -> -182 | AD18: -184 | AE18: =I18-AD18 -> -188 | AF18: -179 | AG18: =J18-AF18 -> -184 | AH18: -210 | AI18: =K18-AH18 -> -215
B19: Interest received | D19: 2.7 | E19: 4 | F19: 7 | G19: 4 | H19: 1 | I19: 2 | J19: 6 | K19: 3 | U19: =D19-T19 -> 2.7 | W19: =E19-V19 -> 4 | X19: 2 | Y19: =F19-X19 -> 5 | Z19: 3 | AA19: =G19-Z19 -> 1 | AC19: =H19-AB19 -> 1 | AD19: 1 | AE19: =I19-AD19 -> 1 | AF19: 3 | AG19: =J19-AF19 -> 3 | AH19: 2 | AI19: =K19-AH19 -> 1
B20: Income tax paid | D20: -497.5 | E20: -294 | F20: -504 | G20: -358 | H20: -485 | I20: -370 | J20: -382 | K20: -515 | T20: -284 | U20: =D20-T20 -> -213.5 | V20: =-405+389 -> -16 | W20: =E20-V20 -> -278 | X20: -301 | Y20: =F20-X20 -> -203 | Z20: -207 | AA20: =G20-Z20 -> -151 | AB20: -259 | AC20: 0 | AD20: -241 | AE20: =I20-AD20 -> -129 | AF20: -187 | AG20: =J20-AF20 -> -195 | AH20: -272 | AI20: =K20-AH20 -> -243
B21: Total Operating Cash Flow | D21: =SUM(D15:D20) -> 1909.9 | E21: =SUM(E15:E20) -> 2275 | F21: =SUM(F15:F20) -> 2552 | G21: =SUM(G15:G20) -> 2837 | H21: =SUM(H15:H20) -> 2690 | I21: =SUM(I15:I20) -> 2807 | J21: =SUM(J15:J20) -> 2793 | K21: =SUM(K15:K20) -> 2936 | L21: =L12 -> 3293.544 | M21: =M12 -> 3502.9661 | N21: =N12 -> 3701.053 | O21: =O12 -> 3862.3131 | P21: =P12 -> 4028.4088 | T21: =SUM(T14:T20) -> 1227 | U21: =D21-T21 -> 682.9 | V21: =SUM(V14:V20) -> 1714 | W21: =E21-V21 -> 561 | X21: =SUM(X14:X20) -> 1024 | Y21: =F21-X21 -> 1528 | Z21: =SUM(Z14:Z20) -> 1736 | AA21: =G21-Z21 -> 1101 | AB21: =SUM(AB14:AB20) -> 1603 | AC21: =H21-AB21 -> 1087 | AD21: =SUM(AD14:AD20) -> 1593 | AE21: =I21-AD21 -> 1214 | AF21: =SUM(AF14:AF20) -> 1504 | AG21: =J21-AF21 -> 1289 | AH21: =SUM(AH14:AH20) -> 850 | AI21: =K21-AH21 -> 2086
A23: Capex | B23: Purchase of PP&E | D23: -714.7 | E23: -1104 | F23: -833 | G23: -1279 | H23: -1272 | I23: -1514 | J23: -1671 | K23: -1487 | L23: =-Model!L183 -> -1200 | M23: =-Model!M183 -> -1236 | N23: =-Model!N183 -> -1273.08 | O23: =-Model!O183 -> -1311.2724 | P23: =-Model!P183 -> -1350.6106 | T23: -377 | U23: =D23-T23 -> -337.7 | V23: -556 | W23: =E23-V23 -> -548 | X23: -372 | Y23: =F23-X23 -> -461 | Z23: -615 | AA23: =G23-Z23 -> -664 | AB23: -451 | AC23: =H23-AB23 -> -821 | AD23: -667 | AE23: =I23-AD23 -> -847 | AF23: -863 | AG23: =J23-AF23 -> -808 | AH23: -657 | AI23: =K23-AH23 -> -830
A24: Proceeds PPE | B24: Proceeds from sale of PP&E | D24: 213 | E24: 288 | F24: 211 | G24: 181 | H24: 136 | I24: 248 | J24: 255 | K24: 205 | L24: =-Model!L187 -> 0 | M24: =-Model!M187 -> 0 | N24: =-Model!N187 -> 0 | O24: =-Model!O187 -> 0 | P24: =-Model!P187 -> 0 | T24: 92 | U24: =D24-T24 -> 121 | V24: 88 | W24: =E24-V24 -> 200 | X24: 221 | Y24: =F24-X24 -> -10 | Z24: 112 | AA24: =G24-Z24 -> 69 | AB24: 77 | AC24: =H24-AB24 -> 59 | AD24: 101 | AE24: =I24-AD24 -> 147 | AF24: 188 | AG24: =J24-AF24 -> 67 | AH24: 125 | AI24: =K24-AH24 -> 80
A25: Acquisitions | B25: Investments in JV and associates | E25: -6 | F25: -11 | G25: -8 | H25: -6 | I25: -14 | J25: -23 | K25: -20 | U25: =D25-T25 -> 0 | V25: -6 | W25: =E25-V25 -> 0 | X25: -9 | Y25: =F25-X25 -> -2 | Z25: -4 | AA25: =G25-Z25 -> -4 | AB25: -3 | AC25: =H25-AB25 -> -3 | AD25: -12 | AE25: =I25-AD25 -> -2 | AF25: -23 | AG25: =J25-AF25 -> 0 | AH25: -16 | AI25: =K25-AH25 -> -4
B26: Net advances to related parties | K26: -37 | U26: =D26-T26 -> 0 | W26: =E26-V26 -> 0 | Y26: =F26-X26 -> 0 | AA26: =G26-Z26 -> 0 | AC26: =H26-AB26 -> 0 | AE26: =I26-AD26 -> 0 | AG26: =J26-AF26 -> 0 | AH26: -37 | AI26: =K26-AH26 -> 0
B27: Payments for acquisitions | D27: -0.8 | E27: -2 | F27: -25 | J27: -74 | U27: =D27-T27 -> -0.8 | V27: -2 | W27: =E27-V27 -> 0 | Y27: =F27-X27 -> -25 | AA27: =G27-Z27 -> 0 | AC27: =H27-AB27 -> 0 | AE27: =I27-AD27 -> 0 | AG27: =J27-AF27 -> -74 | AI27: =K27-AH27 -> 0
B28: Other | E28: 544 | I28: 280 | K28: -25 | U28: =D28-T28 -> 0 | V28: 359 | W28: =E28-V28 -> 185 | Y28: =F28-X28 -> 0 | AA28: =G28-Z28 -> 0 | AC28: =H28-AB28 -> 0 | AE28: =I28-AD28 -> 280 | AG28: =J28-AF28 -> 0 | AI28: =K28-AH28 -> -25
B29: Total Investing Cash Flow | D29: =SUM(D23:D28) -> -502.5 | E29: =SUM(E23:E28) -> -280 | F29: =SUM(F23:F28) -> -658 | G29: =SUM(G23:G28) -> -1106 | H29: =SUM(H23:H28) -> -1142 | I29: =SUM(I23:I28) -> -1000 | J29: =SUM(J23:J28) -> -1513 | K29: =SUM(K23:K28) -> -1364 | ... P29: =SUM(P23:P28) -> -1350.6106 | T29: =SUM(T23:T28) -> -285 | U29: =D29-T29 -> -217.5 | V29: =SUM(V23:V28) -> -117 | W29: =E29-V29 -> -163 | X29: =SUM(X23:X28) -> -160 | Y29: =F29-X29 -> -498 | Z29: =SUM(Z23:Z28) -> -507 | AA29: =G29-Z29 -> -599 | AB29: =SUM(AB23:AB28) -> -377 | AC29: =H29-AB29 -> -765 | AD29: =SUM(AD23:AD28) -> -578 | AE29: =I29-AD29 -> -422 | AF29: =SUM(AF23:AF28) -> -698 | AG29: =J29-AF29 -> -815 | AH29: =SUM(AH23:AH28) -> -585 | AI29: =K29-AH29 -> -779
B31: Proceeds from borrowings | E31: =10260+170 -> 10430 | F31: 5120 | G31: 7232 | H31: 5082 | I31: 10812 | J31: 600 | K31: 300 | U31: =D31-T31 -> 0 | V31: =3725+170 -> 3895 | W31: =E31-V31 -> 6535 | X31: 3520 | Y31: =F31-X31 -> 1600 | Z31: 4236 | AA31: =G31-Z31 -> 2996 | AB31: 2158 | AC31: =H31-AB31 -> 2924 | AD31: 5020 | AE31: =I31-AD31 -> 5792 | AF31: 600 | AG31: =J31-AF31 -> 0 | AI31: =K31-AH31 -> 300
B32: Repayments | D32: -131 | E32: =-8800-3678 -> -12478 | F32: -5226 | G32: -7444 | H32: -5129 | I32: -10789 | J32: -75 | K32: 0 | T32: -711 | U32: =D32-T32 -> 580 | V32: =-2095-3678 -> -5773 | W32: =E32-V32 -> -6705 | X32: -3625 | Y32: =F32-X32 -> -1601 | Z32: -4450 | AA32: =G32-Z32 -> -2994 | AB32: -2256 | AC32: =H32-AB32 -> -2873 | AD32: -5054 | AE32: =I32-AD32 -> -5735 | AF32: -75 | AG32: =J32-AF32 -> 0 | AH32: 618 | AI32: =K32-AH32 -> -618
A33: Lease Repayment | B33: Payment of principal element of lease payment | E33: 0 | F33: -846 | G33: -891 | H33: -901 | I33: -907 | J33: -834 | K33: -911 | L33: =K33*1.05 -> -956.55 | M33: =L33*1.05 -> -1004.3775 | N33: =M33*1.05 -> -1054.5964 | O33: =N33*1.05 -> -1107.3262 | P33: =O33*1.05 -> -1162.6925 | U33: =D33-T33 -> 0 | W33: =E33-V33 -> 0 | X33: -416 | Y33: =F33-X33 -> -430 | Z33: -441 | AA33: =G33-Z33 -> -450 | AB33: -444 | AC33: =H33-AB33 -> -457 | AD33: -458 | AE33: =I33-AD33 -> -449 | AF33: -410 | AG33: =J33-AF33 -> -424 | AH33: -453 | AI33: =K33-AH33 -> -458
A34: Dividends paid | B34: Dividends paid | E34: 0 | F34: -873 | G34: -807 | H34: -798 | I34: -844 | J34: -853 | K34: -889 | L34: =-PL!L77*PL!L83 -> -1104.9932 | M34: =-PL!M77*PL!M83 -> -1218.0836 | N34: =-PL!N77*PL!N83 -> -1301.9684 | O34: =-PL!O77*PL!O83 -> -1365.2511 | P34: =-PL!P77*PL!P83 -> -1429.6926 | U34: =D34-T34 -> 0 | W34: =E34-V34 -> 0 | X34: -474 | Y34: =F34-X34 -> -399 | Z34: -367 | AA34: =G34-Z34 -> -440 | AB34: -373 | AC34: =H34-AB34 -> -425 | AD34: -382 | AE34: =I34-AD34 -> -462 | AF34: -388 | AG34: =J34-AF34 -> -465 | AH34: -412 | AI34: =K34-AH34 -> -477
B35: Purchase of shares to satisfy DRP | I35: -21 | J35: -14 | U35: =D35-T35 -> 0 | W35: =E35-V35 -> 0 | Y35: =F35-X35 -> 0 | AA35: =G35-Z35 -> 0 | AC35: =H35-AB35 -> 0 | AE35: =I35-AD35 -> -21 | AF35: -14 | AG35: =J35-AF35 -> 0 | AI35: =K35-AH35 -> 0
B36: Purchase of shares to satisfy employee equity incentive and share plans | E36: -27 | F36: -17 | G36: -26 | I36: -50 | J36: -26 | K36: -42 | U36: =D36-T36 -> 0 | V36: -24 | W36: =E36-V36 -> -3 | X36: -20 | Y36: =F36-X36 -> 3 | Z36: -21 | AA36: =G36-Z36 -> -5 | AC36: =H36-AB36 -> 0 | AD36: -27 | AE36: =I36-AD36 -> -23 | AF36: -24 | AG36: =J36-AF36 -> -2 | AH36: -43 | AI36: =K36-AH36 -> 1
B37: Other | D37: -1106 | E37: =-320+1322-538 -> 464 | U37: =D37-T37 -> -1106 | V37: =-320+1322-538 -> 464 | W37: =E37-V37 -> 0 | Y37: =F37-X37 -> 0 | AA37: =G37-Z37 -> 0 | AC37: =H37-AB37 -> 0 | AE37: =I37-AD37 -> 0 | AG37: =J37-AF37 -> 0 | AI37: =K37-AH37 -> 0
B38: Total Financing Cash Flow | D38: =SUM(D31:D37) -> -1237 | E38: =SUM(E31:E37) -> -1611 | F38: =SUM(F31:F37) -> -1842 | G38: =SUM(G31:G37) -> -1936 | H38: =SUM(H31:H37) -> -1746 | I38: =SUM(I31:I37) -> -1799 | J38: =SUM(J31:J37) -> -1202 | K38: =SUM(K31:K37) -> -1542 | L38: =SUM(L31:L36) -> -2061.5432 | M38: =SUM(M31:M36) -> -2222.4611 | N38: =SUM(N31:N36) -> -2356.5648 | O38: =SUM(O31:O36) -> -2472.5773 | P38: =SUM(P31:P36) -> -2592.3851 | T38: =SUM(T31:T37) -> -711 | U38: =D38-T38 -> -526 | V38: =SUM(V31:V37) -> -1438 | W38: =E38-V38 -> -173 | X38: =SUM(X31:X37) -> -1015 | Y38: =F38-X38 -> -827 | Z38: =SUM(Z31:Z37) -> -1043 | AA38: =G38-Z38 -> -893 | AB38: =SUM(AB31:AB37) -> -915 | AC38: =H38-AB38 -> -831 | AD38: =SUM(AD31:AD37) -> -901 | AE38: =I38-AD38 -> -898 | AF38: =SUM(AF31:AF37) -> -311 | AG38: =J38-AF38 -> -891 | AH38: =SUM(AH31:AH37) -> -290 | AI38: =K38-AH38 -> -1252
B40: Cash at Beginning | D40: 385.6 | E40: =D42 -> 556 | F40: =E42 -> 940 | G40: =F42 -> 992 | H40: =G42 -> 787 | I40: =H42 -> 589 | J40: =I42 -> 597 | K40: =J42 -> 675 | L40: =K42 -> 705 | ... P40: =O42 -> 931.37742 | T40: 288 | U40: =D40-T40 -> 97.6 | V40: =D42 -> 556 | W40: =E40-V40 -> 0 | X40: =E42 -> 940 | Y40: =F40-X40 -> 0 | Z40: =F42 -> 992 | AA40: =G40-Z40 -> 0 | AB40: =G42 -> 787 | AC40: =H40-AB40 -> 0 | AD40: =H42 -> 589 | AE40: =I40-AD40 -> 0 | AF40: =I42 -> 597 | AG40: =J40-AF40 -> 0 | AH40: =J42 -> 675 | AI40: =K40-AH40 -> 0
A41: Net Chg Cash | B41: Net Increase in Cash | D41: =D38+D29+D21 -> 170.4 | E41: =E38+E29+E21 -> 384 | F41: =F38+F29+F21 -> 52 | G41: =G38+G29+G21 -> -205 | H41: =H38+H29+H21 -> -198 | I41: =I38+I29+I21 -> 8 | J41: =J38+J29+J21 -> 78 | K41: =K38+K29+K21 -> 30 | ... P41: =P38+P29+P21 -> 85.413113 | T41: =T38+T29+T21 -> 231 | U41: =D41-T41 -> -60.6 | V41: =V38+V29+V21 -> 159 | W41: =E41-V41 -> 225 | X41: =X38+X29+X21 -> -151 | Y41: =F41-X41 -> 203 | Z41: =Z38+Z29+Z21 -> 186 | AA41: =G41-Z41 -> -391 | AB41: =AB38+AB29+AB21 -> 311 | AC41: =H41-AB41 -> -509 | AD41: =AD38+AD29+AD21 -> 114 | AE41: =I41-AD41 -> -106 | AF41: =AF38+AF29+AF21 -> 495 | AG41: =J41-AF41 -> -417 | AH41: =AH38+AH29+AH21 -> -25 | AI41: =K41-AH41 -> 55
B42: Cash at Ending | D42: =D40+D41 -> 556 | E42: =E40+E41 -> 940 | F42: =F40+F41 -> 992 | G42: =G40+G41 -> 787 | H42: =H40+H41 -> 589 | I42: =I40+I41 -> 597 | J42: =J40+J41 -> 675 | K42: =K40+K41 -> 705 | ... P42: =P40+P41 -> 1016.7905 | T42: =T40+T41 -> 519 | U42: =U40+U41 -> 37 | V42: =V40+V41 -> 715 | W42: =W40+W41 -> 225 | X42: =X40+X41 -> 789 | Y42: =Y40+Y41 -> 203 | Z42: =Z40+Z41 -> 1178 | AA42: =AA40+AA41 -> -391 | ... AI42: =AI40+AI41 -> 55
A44: Net Capex | B44: Net Capex | D44: =D23+D24 -> -501.7 | E44: =E23+E24 -> -816 | F44: =F23+F24 -> -622 | G44: =G23+G24 -> -1098 | H44: =H23+H24 -> -1136 | I44: =I23+I24 -> -1266 | J44: =J23+J24 -> -1416 | K44: =K23+K24 -> -1282 | ... P44: =P23+P24 -> -1350.6106
A48: Other financing | I48: =I36+I35 -> -71 | J48: =J36+J35 -> -40 | K48: =K36+K35 -> -42 | L48: =L36+L35 -> 0 | M48: =M36+M35 -> 0 | N48: =N36+N35 -> 0 | O48: =O36+O35 -> 0 | P48: =P36+P35 -> 0
A50: Other investing | I50: =I25+I26+I28+I27 -> 266 | J50: =J25+J26+J28+J27 -> -97 | K50: =K25+K26+K28+K27 -> -82 | L50: =L25+L26+L28+L27 -> 0 | M50: =M25+M26+M28+M27 -> 0 | N50: =N25+N26+N28+N27 -> 0 | O50: =O25+O26+O28+O27 -> 0 | P50: =P25+P26+P28+P27 -> 0

Sheet BS
B1: Coles Group (COL.AX)
B2: A$M
C3: =Model!C3 -> FY17 | D3: =Model!D3 -> FY18 | E3: =Model!E3 -> FY19 | F3: =Model!F3 -> FY20 | G3: =Model!G3 -> FY21 | H3: =Model!H3 -> FY22 | I3: =Model!I3 -> FY23 | J3: =Model!J3 -> FY24 | K3: =Model!K3 -> FY25 | L3: FY26E | M3: FY27E | N3: FY28E | O3: FY29E | P3: FY30E | S3: =Model!T3 -> 2H17 | T3: =Model!U3 -> 1H18 | U3: =Model!V3 -> 2H18 | V3: =Model!W3 -> 1H19 | W3: =Model!X3 -> 2H19 | X3: =Model!Y3 -> 1H20 | Y3: =Model!Z3 -> 2H20 | Z3: =Model!AA3 -> 1H21 | ... AI3: =Model!AJ3 -> 2H25
B4: BS
B5: Assets
A6: Cash | B6: Cash and cash equivalents | D6: 686.1 | E6: 940.4 | F6: 992 | G6: 787 | H6: 589 | I6: 597 | J6: 675 | K6: 705 | L6: =CF!L42 -> 737.00077 | M6: =CF!M42 -> 781.50581 | N6: =CF!N42 -> 852.91405 | O6: =CF!O42 -> 931.37742 | P6: =CF!P42 -> 1016.7905 | T6: 669 | V6: 484 | X6: 797 | Z6: 1178 | AB6: 1098 | AD6: 698 | AF6: 1092 | AH6: 625
A7: TR | B7: Trade and other receivables | D7: 497.2 | E7: 359.7 | F7: 434 | G7: 368 | H7: 470 | I7: 605 | J7: 496 | K7: 487 | L7: =L48 -> 503.09134 | M7: =M48 -> 518.65139 | N7: =N48 -> 540.50588 | O7: =O48 -> 563.20326 | P7: =P48 -> 586.77442 | T7: 721 | V7: 560 | X7: 353 | Z7: 415 | AB7: 336 | AD7: 473 | AF7: 553 | AH7: 500
A8: Inventory | B8: Inventories | D8: 3442.3 | E8: 1964.7 | F8: 2166 | G8: 2107 | H8: 2448 | I8: 2323 | J8: 2703 | K8: 2733 | L8: =L52 -> 2823.3032 | M8: =M52 -> 2910.6247 | N8: =N52 -> 3033.2702 | O8: =O52 -> 3160.6458 | P8: =P52 -> 3292.925 | T8: 3863 | V8: 2429 | X8: 2473 | Z8: 2423 | AB8: 2387 | AD8: 2825 | AF8: 2868 | AH8: 2957
B9: Income tax receivables | F9: 42 | H9: 42 | I9: 4 | K9: 28 | L9: =K9 -> 28 | M9: =L9 -> 28 | N9: =M9 -> 28 | O9: =N9 -> 28 | P9: =O9 -> 28 | V9: 118 | X9: 53 | AD9: 55
B10: Assets held for sale | E10: 94.1 | F10: 75 | G10: 85 | H10: 82 | I10: 127 | J10: 3 | K10: 105 | L10: =K10 -> 105 | M10: =L10 -> 105 | N10: =M10 -> 105 | O10: =N10 -> 105 | P10: =O10 -> 105 | T10: 59 | V10: 125 | X10: 106 | Z10: 48 | AB10: 57 | AD10: 1209 | AF10: 47 | AH10: 76
A11: Other CA | B11: Other | D11: 99.5 | E11: 47 | F11: 70 | G11: 87 | H11: 120 | I11: 96 | J11: 109 | K11: 120 | L11: =K11 -> 120 | M11: =L11 -> 120 | N11: =M11 -> 120 | O11: =N11 -> 120 | P11: =O11 -> 120 | T11: 165 | X11: 63 | Z11: 69 | AB11: 97 | AD11: 122 | AF11: 121 | AH11: 128
A12: CA | B12: Total Current Assets | D12: =SUM(D6:D11) -> 4725.1 | E12: =SUM(E6:E11) -> 3405.9 | F12: =SUM(F6:F11) -> 3779 | G12: =SUM(G6:G11) -> 3434 | H12: =SUM(H6:H11) -> 3751 | I12: =SUM(I6:I11) -> 3752 | J12: =SUM(J6:J11) -> 3986 | K12: =SUM(K6:K11) -> 4178 | ... P12: =SUM(P6:P11) -> 5149.49 | T12: =SUM(T6:T11) -> 5477 | V12: =SUM(V6:V11) -> 3716 | X12: =SUM(X6:X11) -> 3845 | Z12: =SUM(Z6:Z11) -> 4133 | AB12: =SUM(AB6:AB11) -> 3975 | AD12: =SUM(AD6:AD11) -> 5382 | AF12: =SUM(AF6:AF11) -> 4681 | AH12: =SUM(AH6:AH11) -> 4286
A14: Fixed Assets | B14: PPE | D14: 5223 | E14: 4119.2 | F14: 4127 | G14: 4463 | H14: 4807 | I14: 4985 | J14: 5619 | K14: 5866 | L14: =K14+PL!L28-CF!L23 -> 6072.925 | M14: =L14+PL!M28-CF!M23 -> 6271.353 | N14: =M14+PL!N28-CF!N23 -> 6460.4169 | O14: =N14+PL!O28-CF!O23 -> 6639.1985 | P14: =O14+PL!P28-CF!P23 -> 6806.7255 | T14: 5199 | V14: 4201 | X14: 3918 | Z14: 4276 | AB14: 4432 | AD14: 4755 | AF14: 5252 | AH14: 5562
A15: ROU | B15: RoU Assets | F15: 7660 | G15: 7288 | H15: 7199 | I15: 6507 | J15: 7048 | K15: 6942 | L15: =K15+PL!L27+L69 -> 6987.19 | M15: =L15+PL!M27+M69 -> 7048.9616 | N15: =M15+PL!N27+N69 -> 7128.6453 | O15: =N15+PL!O27+O69 -> 7227.6554 | P15: =O15+PL!P27+P69 -> 7347.4952 | X15: 7347 | Z15: 7703 | AB15: 7162 | AD15: 6434 | AF15: 6363 | AH15: 7041
A16: Intangibles | B16: Intangible assets | D16: 1965.7 | E16: 1540.6 | F16: 1597 | G16: 1698 | H16: 1864 | I16: 2035 | J16: 2203 | K16: 2246 | L16: =K16 -> 2246 | M16: =L16 -> 2246 | N16: =M16 -> 2246 | O16: =N16 -> 2246 | P16: =O16 -> 2246 | T16: 1950 | V16: 1660 | X16: 1553 | Z16: 1620 | AB16: 1806 | AD16: 1887 | AF16: 2094 | AH16: 2247
B17: DTA | D17: 540.3 | E17: 364.9 | F17: 849 | G17: 873 | H17: 822 | I17: 740 | J17: 717 | K17: 671 | L17: =K17 -> 671 | M17: =L17 -> 671 | N17: =M17 -> 671 | O17: =N17 -> 671 | P17: =O17 -> 671 | T17: 718 | V17: 537 | X17: 772 | Z17: 870 | AB17: 852 | AD17: 725 | AF17: 729 | AH17: 706
B18: Investments | E18: 212.3 | F18: 217 | G18: 220 | H18: 219 | I18: 220 | J18: 225 | K18: 240 | L18: =K18-CF!L25-CF!L26-CF!L27 -> 240 | M18: =L18-CF!M25-CF!M26-CF!M27 -> 240 | N18: =M18-CF!N25-CF!N26-CF!N27 -> 240 | O18: =N18-CF!O25-CF!O26-CF!O27 -> 240 | P18: =O18-CF!P25-CF!P26-CF!P27 -> 240 | V18: 12 | X18: 221 | Z18: 220 | AB18: 221 | AD18: 226 | AF18: 237 | AH18: 239
B19: Other | D19: 90.6 | E19: 134.1 | F19: 120 | G19: 147 | H19: 174 | I19: 53 | J19: 72 | K19: 151 | L19: =K19 -> 151 | M19: =L19 -> 151 | N19: =M19 -> 151 | O19: =N19 -> 151 | P19: =O19 -> 151 | T19: 135 | V19: 24 | X19: 118 | Z19: 137 | AB19: 144 | AD19: 59 | AF19: 129 | AH19: 118
A20: NCA | B20: Total Non-Current Assets | D20: =SUM(D14:D19) -> 7819.6 | E20: =SUM(E14:E19) -> 6371.1 | F20: =SUM(F14:F19) -> 14570 | G20: =SUM(G14:G19) -> 14689 | H20: =SUM(H14:H19) -> 15085 | I20: =SUM(I14:I19) -> 14540 | J20: =SUM(J14:J19) -> 15884 | K20: =SUM(K14:K19) -> 16116 | ... P20: =SUM(P14:P19) -> 17462.221 | T20: =SUM(T14:T19) -> 8002 | V20: =SUM(V14:V19) -> 6434 | X20: =SUM(X14:X19) -> 13929 | Z20: =SUM(Z14:Z19) -> 14826 | AB20: =SUM(AB14:AB19) -> 14617 | AD20: =SUM(AD14:AD19) -> 14086 | AF20: =SUM(AF14:AF19) -> 14804 | AH20: =SUM(AH14:AH19) -> 15913
B22: Total Assets | D22: =D20+D12 -> 12544.7 | E22: =E20+E12 -> 9777 | F22: =F20+F12 -> 18349 | G22: =G20+G12 -> 18123 | H22: =H20+H12 -> 18836 | I22: =I20+I12 -> 18292 | J22: =J20+J12 -> 19870 | K22: =K20+K12 -> 20294 | ... P22: =P20+P12 -> 22611.711 | T22: =T20+T12 -> 13479 | V22: =V20+V12 -> 10150 | X22: =X20+X12 -> 17774 | Z22: =Z20+Z12 -> 18959 | AB22: =AB20+AB12 -> 18592 | AD22: =AD20+AD12 -> 19468 | AF22: =AF20+AF12 -> 19485 | AH22: =AH20+AH12 -> 20199
B24: Liabilities
A25: TP | B25: Trade Payables | D25: 8008.5 | E25: 3379.9 | F25: 3737 | G25: 3660 | H25: 4335 | I25: 4434 | J25: 4584 | K25: 4637 | L25: =L56 -> 4790.2147 | M25: =M56 -> 4938.3706 | N25: =N56 -> 5146.4595 | O25: =O56 -> 5362.574 | P25: =P56 -> 5587.0082 | T25: 7796 | V25: 3991 | X25: 3665 | Z25: 4173 | AB25: 4282 | AD25: 4978 | AF25: 5020 | AH25: 4208
A26: C Borrowings | B26: Interest bearing liabilities | K26: 150 | L26: =K26 -> 150 | M26: =L26 -> 150 | N26: =M26 -> 150 | O26: =N26 -> 150 | P26: =O26 -> 150 | X26: 8 | Z26: 0 | AH26: 150
B27: Income tax payable | D27: -25.3 | E27: 1 | G27: 60 | J27: 73 | L27: =K27 -> 0 | M27: =L27 -> 0 | N27: =M27 -> 0 | O27: =N27 -> 0 | P27: =O27 -> 0 | T27: 21 | V27: 78 | Z27: 10 | AB27: 11 | AF27: 52 | AH27: 27
B28: Provisions | D28: 819.3 | E28: 742.9 | F28: 861 | G28: 950 | H28: 854 | I28: 905 | J28: 943 | K28: 894 | L28: =K28 -> 894 | M28: =L28 -> 894 | N28: =M28 -> 894 | O28: =N28 -> 894 | P28: =O28 -> 894 | T28: 807 | V28: 703 | X28: 754 | Z28: 877 | AB28: 834 | AD28: 821 | AF28: 853 | AH28: 836
B29: Lease liabilities | E29: 167.6 | F29: 885 | G29: 897 | H29: 914 | I29: 820 | J29: 911 | K29: 928 | L29: =K29 -> 928 | M29: =L29 -> 928 | N29: =M29 -> 928 | O29: =N29 -> 928 | P29: =O29 -> 928 | X29: 1205 | Z29: 910 | AB29: 905 | AD29: 795 | AF29: 815 | AH29: 914
B30: Other | D30: 178.4 | F30: 198 | G30: 252 | H30: 312 | I30: 249 | J30: 260 | K30: 247 | L30: =K30 -> 247 | M30: =L30 -> 247 | N30: =M30 -> 247 | O30: =N30 -> 247 | P30: =O30 -> 247 | T30: 256 | V30: 233 | X30: 226 | Z30: 294 | AB30: 313 | AD30: =309+792 -> 1101 | AF30: 310 | AH30: 284
A31: CL | B31: Total Current liabilities | D31: =SUM(D25:D30) -> 8980.9 | E31: =SUM(E25:E30) -> 4291.4 | F31: =SUM(F25:F30) -> 5681 | G31: =SUM(G25:G30) -> 5819 | H31: =SUM(H25:H30) -> 6415 | I31: =SUM(I25:I30) -> 6408 | J31: =SUM(J25:J30) -> 6771 | K31: =SUM(K25:K30) -> 6856 | ... P31: =SUM(P25:P30) -> 7806.0082 | T31: =SUM(T25:T30) -> 8880 | V31: =SUM(V25:V30) -> 5005 | X31: =SUM(X25:X30) -> 5858 | Z31: =SUM(Z25:Z30) -> 6264 | AB31: =SUM(AB25:AB30) -> 6345 | AD31: =SUM(AD25:AD30) -> 7695 | AF31: =SUM(AF25:AF30) -> 7050 | AH31: =SUM(AH25:AH30) -> 6419
A33: NC Borrowings | B33: Interest bearing liabilities | D33: 0 | E33: 1460 | F33: 1354 | G33: 1142 | H33: 1095 | I33: 1118 | J33: 1652 | K33: 1834 | L33: =K33+CF!L32+CF!L31 -> 1834 | M33: =L33+CF!M32+CF!M31 -> 1834 | N33: =M33+CF!N32+CF!N31 -> 1834 | O33: =N33+CF!O32+CF!O31 -> 1834 | P33: =O33+CF!P32+CF!P31 -> 1834 | V33: 1630 | X33: 1355 | Z33: 1140 | AB33: 1044 | AD33: 1060 | AF33: 1666 | AH33: 2126
A34: NC Lease | B34: Lease liabilities | D34: 41.8 | E34: 71 | F34: 8198 | G34: 7859 | H34: 7767 | I34: 7029 | J34: 7506 | K34: 7415 | L34: =K34+CF!L33+L69 -> 7458.45 | M34: =L34+CF!M33+M69 -> 7504.0725 | N34: =M34+CF!N33+N69 -> 7551.9761 | O34: =N34+CF!O33+O69 -> 7602.2749 | P34: =O34+CF!P33+P69 -> 7655.0887 | T34: 272 | V34: 589 | X34: 464 | Z34: 481 | AB34: 459 | AD34: 369 | AF34: 319 | AH34: 362
B35: Provisions | D35: 272.4 | E35: 598.4 | F35: 472 | G35: 458 | H35: 424 | I35: 376 | J35: 323 | K35: 381 | L35: =K35 -> 381 | M35: =L35 -> 381 | N35: =M35 -> 381 | O35: =N35 -> 381 | P35: =O35 -> 381 | X35: 7556 | Z35: 8258 | AB35: 7730 | AD35: 6964 | AF35: 6910 | AH35: 7525
B36: Other | E36: 0 | F36: 29 | G36: 32 | H36: 11 | I36: 5 | J36: 1 | K36: 2 | L36: =K36 -> 2 | M36: =L36 -> 2 | N36: =M36 -> 2 | O36: =N36 -> 2 | P36: =O36 -> 2 | T36: =25+165 -> 190 | V36: =62+192 -> 254 | X36: 22 | Z36: 24 | AB36: 5 | AD36: 1 | AF36: 3 | AH36: 3
A37: NCL | B37: Total Non-Current liabilities | D37: =SUM(D33:D36) -> 314.2 | E37: =SUM(E33:E36) -> 2129.4 | F37: =SUM(F33:F36) -> 10053 | G37: =SUM(G33:G36) -> 9491 | H37: =SUM(H33:H36) -> 9297 | I37: =SUM(I33:I36) -> 8528 | J37: =SUM(J33:J36) -> 9482 | K37: =SUM(K33:K36) -> 9632 | ... P37: =SUM(P33:P36) -> 9872.0887 | T37: =SUM(T33:T36) -> 462 | V37: =SUM(V33:V36) -> 2473 | X37: =SUM(X33:X36) -> 9397 | Z37: =SUM(Z33:Z36) -> 9903 | AB37: =SUM(AB33:AB36) -> 9238 | AD37: =SUM(AD33:AD36) -> 8394 | AF37: =SUM(AF33:AF36) -> 8898 | AH37: =SUM(AH33:AH36) -> 10016
B39: Total Liabilities | D39: =D37+D31 -> 9295.1 | E39: =E37+E31 -> 6420.8 | F39: =F37+F31 -> 15734 | G39: =G37+G31 -> 15310 | H39: =H37+H31 -> 15712 | I39: =I37+I31 -> 14936 | J39: =J37+J31 -> 16253 | K39: =K37+K31 -> 16488 | ... P39: =P37+P31 -> 17678.097 | T39: =T37+T31 -> 9342 | V39: =V37+V31 -> 7478 | X39: =X37+X31 -> 15255 | Z39: =Z37+Z31 -> 16167 | AB39: =AB37+AB31 -> 15583 | AD39: =AD37+AD31 -> 16089 | AF39: =AF37+AF31 -> 15948 | AH39: =AH37+AH31 -> 16435
A41: Contributed Equity | B41: Contributed equity | D41: 2192.6 | E41: 1627.8 | F41: 1611 | G41: 1585 | H41: 1636 | I41: 1644 | J41: 1672 | K41: 1704 | L41: =K41+CF!L36 -> 1704 | M41: =L41+CF!M36 -> 1704 | N41: =M41+CF!N36 -> 1704 | O41: =N41+CF!O36 -> 1704 | P41: =O41+CF!P36 -> 1704 | T41: 2193 | V41: 1631 | X41: 1608 | Z41: 1590 | AB41: 1602 | AD41: 1651 | AF41: 1651 | AH41: 1683
A42: Reserves | B42: Reserves | D42: 38.8 | E42: 42 | F42: 43 | G42: 69 | H42: 95 | I42: 104 | J42: 103 | K42: 106 | L42: =K42 -> 106 | M42: =L42 -> 106 | N42: =M42 -> 106 | O42: =N42 -> 106 | P42: =O42 -> 106 | T42: 39 | V42: 51 | X42: 40 | Z42: 48 | AB42: 72 | AD42: 93 | AF42: 91 | AH42: 92
A43: Retained Profits | B43: Retained Profits | D43: 1018.2 | E43: 1687.3 | F43: 961 | G43: 1159 | H43: 1393 | I43: 1608 | J43: 1842 | K43: 1996 | L43: =K43+PL!L54+CF!L34 -> 2189.8456 | M43: =L43+PL!M54+CF!M34 -> 2403.6534 | N43: =M43+PL!N54+CF!N34 -> 2632.3167 | O43: =N43+PL!O54+CF!O34 -> 2872.2315 | P43: =O43+PL!P54+CF!P34 -> 3123.6139 | T43: 1905 | V43: 990 | X43: 871 | Z43: 1154 | AB43: 1335 | AD43: 1635 | AF43: 1795 | AH43: 1989
A44: Total Equity | B44: Total Equity | D44: =SUM(D41:D43) -> 3249.6 | E44: =SUM(E41:E43) -> 3357.1 | F44: =SUM(F41:F43) -> 2615 | G44: =SUM(G41:G43) -> 2813 | H44: =SUM(H41:H43) -> 3124 | I44: =SUM(I41:I43) -> 3356 | J44: =SUM(J41:J43) -> 3617 | K44: =SUM(K41:K43) -> 3806 | ... P44: =SUM(P41:P43) -> 4933.6139 | T44: =SUM(T41:T43) -> 4137 | V44: =SUM(V41:V43) -> 2672 | X44: =SUM(X41:X43) -> 2519 | Z44: =SUM(Z41:Z43) -> 2792 | AB44: =SUM(AB41:AB43) -> 3009 | AD44: =SUM(AD41:AD43) -> 3379 | AF44: =SUM(AF41:AF43) -> 3537 | AH44: =SUM(AH41:AH43) -> 3764
B45: Check | D45: =D22-D39-D44 -> 0 | E45: =E22-E39-E44 -> -0.9 | F45: =F22-F39-F44 -> 0 | G45: =G22-G39-G44 -> 0 | H45: =H22-H39-H44 -> 0 | I45: =I22-I39-I44 -> 0 | J45: =J22-J39-J44 -> 0 | K45: =K22-K39-K44 -> 0 | ... P45: =P22-P39-P44 -> 0 | T45: =T22-T39-T44 -> 0 | V45: =V22-V39-V44 -> 0 | X45: =X22-X39-X44 -> 0 | Z45: =Z22-Z39-Z44 -> 0 | AB45: =AB22-AB39-AB44 -> 0 | AD45: =AD22-AD39-AD44 -> 0 | AF45: =AF22-AF39-AF44 -> 0 | AH45: =AH22-AH39-AH44 -> 0
B47: Balance Sheet Metrics
B48: Receivables | D48: =D7 -> 497.2 | E48: =E7 -> 359.7 | F48: =F7 -> 434 | G48: =G7 -> 368 | H48: =H7 -> 470 | I48: =I7 -> 605 | J48: =J7 -> 496 | K48: =K7 -> 487 | L48: =L49*Model!L11 -> 503.09134 | M48: =M49*Model!M11 -> 518.65139 | N48: =N49*Model!N11 -> 540.50588 | O48: =O49*Model!O11 -> 563.20326 | P48: =P49*Model!P11 -> 586.77442
B49: % of Sales | D49: =(D48)/Model!D11 -> 0.01274643 | E49: =(E48)/Model!E11 -> 0.010276849 | F49: =(F48)/Model!F11 -> 0.011601796 | G49: =(G48)/Model!G11 -> 0.009537385 | H49: =(H48)/Model!H11 -> 0.012291759 | I49: =(I48)/Model!I11 -> 0.014944545 | J49: =(J48)/Model!J11 -> 0.011383719 | K49: =(K48)/Model!K11 -> 0.010980339 | L49: =K49 -> 0.010980339 | M49: =L49 -> 0.010980339 | N49: =M49 -> 0.010980339 | O49: =N49 -> 0.010980339 | P49: =O49 -> 0.010980339 | T49: =T7/Model!U11 -> 0.035611973 | V49: =V7/Model!W11 -> 0.030658053 | X49: =X7/Model!Y11 -> 0.018720832 | Z49: =Z7/Model!AA11 -> 0.020353114 | AB49: =AB7/Model!AC11 -> 0.016787409 | AD49: =AD7/Model!AE11 -> 0.022730549 | AF49: =AF7/Model!AG11 -> 0.02489197 | AH49: =AH7/Model!AI11 -> 0.021706099
B50: Receivables Days | D50: =D48/Model!D11*365 -> 4.652447 | E50: =E48/Model!E11*365 -> 3.75105 | F50: =F48/Model!F11*365 -> 4.2346557 | G50: =G48/Model!G11*365 -> 3.4811455 | H50: =H48/Model!H11*365 -> 4.4864921 | I50: =I48/Model!I11*365 -> 5.4547588 | J50: =J48/Model!J11*365 -> 4.1550573 | K50: =K48/Model!K11*365 -> 4.0078238 | L50: =L7/Model!L11*365 -> 4.0078238 | M50: =M7/Model!M11*365 -> 4.0078238 | N50: =N7/Model!N11*365 -> 4.0078238 | O50: =O7/Model!O11*365 -> 4.0078238 | P50: =P7/Model!P11*365 -> 4.0078238 | T50: =T7/Model!U11*365 -> 12.99837 | V50: =V7/Model!W11*365 -> 11.190189 | X50: =X7/Model!Y11*365 -> 6.8331035 | Z50: =Z7/Model!AA11*365 -> 7.4288867 | AB50: =AB7/Model!AC11*365 -> 6.1274044 | AD50: =AD7/Model!AE11*365 -> 8.2966505 | AF50: =AF7/Model!AG11*365 -> 9.085569 | AH50: =AH7/Model!AI11*365 -> 7.9227263
B52: Inventory | D52: =D8 -> 3442.3 | E52: =E8 -> 1964.7 | F52: =F8 -> 2166 | G52: =G8 -> 2107 | H52: =H8 -> 2448 | I52: =I8 -> 2323 | J52: =J8 -> 2703 | K52: =K8 -> 2733 | L52: =L53*Model!L11 -> 2823.3032 | M52: =M53*Model!M11 -> 2910.6247 | N52: =N53*Model!N11 -> 3033.2702 | O52: =O53*Model!O11 -> 3160.6458 | P52: =P53*Model!P11 -> 3292.925
B53: % of Sales | D53: =D52/Model!D11 -> 0.088248263 | E53: =E52/Model!E11 -> 0.056132682 | F53: =F52/Model!F11 -> 0.057902053 | G53: =G52/Model!G11 -> 0.054606712 | H53: =H52/Model!H11 -> 0.064021759 | I53: =I52/Model!I11 -> 0.057382111 | J53: =J52/Model!J11 -> 0.062036676 | K53: =K52/Model!K11 -> 0.061620671 | L53: =K53 -> 0.061620671 | M53: =L53 -> 0.061620671 | N53: =M53 -> 0.061620671 | O53: =N53 -> 0.061620671 | P53: =O53 -> 0.061620671 | T53: =T8/Model!U11 -> 0.19080312 | V53: =V8/Model!W11 -> 0.13297931 | X53: =X8/Model!Y11 -> 0.13115189 | Z53: =Z8/Model!AA11 -> 0.11883276 | AB53: =AB8/Model!AC11 -> 0.11926055 | AD53: =AD8/Model!AE11 -> 0.13575857 | AF53: =AF8/Model!AG11 -> 0.12909615 | AH53: =AH8/Model!AI11 -> 0.12836987
B54: Inventory Days | D54: =D52/PL!D5*365 -> 32.210616 | E54: =E52/PL!E5*365 -> 20.488429 | F54: =F52/PL!F5*365 -> 21.134249 | G54: =G52/PL!G5*365 -> 19.93145 | H54: =H52/PL!H5*365 -> 23.367942 | I54: =I52/PL!I5*365 -> 20.944471 | J54: =J52/PL!J5*365 -> 22.643387 | K54: =K52/PL!K5*365 -> 22.491545 | ... P54: =P52/PL!P5*365 -> 22.491545 | T54: =T8/PL!T5*365 -> 69.643139 | V54: =V8/PL!V5*365 -> 48.537447 | X54: =X8/PL!X5*365 -> 47.870439 | Z54: =Z8/PL!Z5*365 -> 43.373958 | AB54: =AB8/PL!AB5*365 -> 43.530102 | AD54: =AD8/PL!AD5*365 -> 49.551877 | AF54: =AF8/PL!AF5*365 -> 47.120094 | AH54: =AH8/PL!AH5*365 -> 46.855003
B56: Payables | D56: =D25 -> 8008.5 | E56: =E25 -> 3379.9 | F56: =F25 -> 3737 | G56: =G25 -> 3660 | H56: =H25 -> 4335 | I56: =I25 -> 4434 | J56: =J25 -> 4584 | K56: =K25 -> 4637 | L56: =L57*Model!L11 -> 4790.2147 | M56: =M57*Model!M11 -> 4938.3706 | N56: =N57*Model!N11 -> 5146.4595 | O56: =O57*Model!O11 -> 5362.574 | P56: =P57*Model!P11 -> 5587.0082
B57: % of Sales | D57: =D25/Model!D11 -> 0.2053093 | E57: =E25/Model!E11 -> 0.096565812 | F57: =F25/Model!F11 -> 0.099898417 | G57: =G25/Model!G11 -> 0.094855514 | H57: =H25/Model!H11 -> 0.11337186 | I57: =I25/Model!I11 -> 0.10952746 | J57: =J25/Model!J11 -> 0.10520759 | K57: =K25/Model!K11 -> 0.10454996 | L57: =K57 -> 0.10454996 | M57: =L57 -> 0.10454996 | N57: =M57 -> 0.10454996 | O57: =N57 -> 0.10454996 | P57: =O57 -> 0.10454996 | T57: =T25/Model!U11 -> 0.38506372 | V57: =V25/Model!W11 -> 0.21849338 | X57: =X25/Model!Y11 -> 0.19436784 | Z57: =Z25/Model!AA11 -> 0.20465915 | AB57: =AB25/Model!AC11 -> 0.21393955 | AD57: =AD25/Model!AE11 -> 0.23922341 | AF57: =AF25/Model!AG11 -> 0.22596327 | AH57: =AH25/Model!AI11 -> 0.18267853
B58: Payables Days | D58: =D56/PL!D5*365 -> 74.937896 | E58: =E56/PL!E5*365 -> 35.246522 | F58: =F56/PL!F5*365 -> 36.462922 | G58: =G56/PL!G5*365 -> 34.622263 | H58: =H56/PL!H5*365 -> 41.380731 | I58: =I56/PL!I5*365 -> 39.977521 | J58: =J56/PL!J5*365 -> 38.400771 | K58: =K56/PL!K5*365 -> 38.160737 | L58: =L25/PL!L5*365 -> 38.160737 | M58: =M25/PL!M5*365 -> 38.160737 | N58: =N25/PL!N5*365 -> 38.160737 | O58: =O25/PL!O5*365 -> 38.160737 | P58: =P25/PL!P5*365 -> 38.160737 | T58: =T25/PL!T5*365 -> 140.54826 | V58: =V25/PL!V5*365 -> 79.750082 | X58: =X25/PL!X5*365 -> 70.944262 | Z58: =Z25/PL!Z5*365 -> 74.700589 | AB58: =AB25/PL!AB5*365 -> 78.087934 | AD58: =AD25/PL!AD5*365 -> 87.316546 | AF58: =AF25/PL!AF5*365 -> 82.476593 | AH58: =AH25/PL!AH5*365 -> 66.677664
B60: Net Working Capital | D60: =D48+D52-D56 -> -4069 | E60: =E48+E52-E56 -> -1055.5 | F60: =F48+F52-F56 -> -1137 | G60: =G48+G52-G56 -> -1185 | H60: =H48+H52-H56 -> -1417 | I60: =I48+I52-I56 -> -1506 | J60: =J48+J52-J56 -> -1385 | K60: =K48+K52-K56 -> -1417 | ... P60: =P48+P52-P56 -> -1707.3087 | T60: =T7+T8-T25 -> -3212 | V60: =V7+V8-V25 -> -1002 | X60: =X7+X8-X25 -> -839 | Z60: =Z7+Z8-Z25 -> -1335 | AB60: =AB7+AB8-AB25 -> -1559 | AD60: =AD7+AD8-AD25 -> -1680 | AF60: =AF7+AF8-AF25 -> -1599 | AH60: =AH7+AH8-AH25 -> -751
A61: Chg in NWC | B61: Change in Net Working Capital | D61: =-(D60-C60) -> 4069 | E61: =-(E60-D60) -> -3013.5 | F61: =-(F60-E60) -> 81.5 | G61: =-(G60-F60) -> 48 | H61: =-(H60-G60) -> 232 | I61: =-(I60-H60) -> 89 | J61: =-(J60-I60) -> -121 | K61: =-(K60-J60) -> 32 | ... P61: =-(P60-O60) -> 68.583845 | T61: =T60-C60 -> -3212 | U61: =D61-T61 -> 7281 | V61: =V60-D60 -> 3067 | W61: =E61-V61 -> -6080.5 | X61: =X60-E60 -> 216.5 | Y61: =F61-X61 -> -135 | Z61: =Z60-F60 -> -198 | AA61: =G61-Z61 -> 246 | AB61: =AB60-G60 -> -374 | AC61: =H61-AB61 -> 606 | AD61: =AD60-H60 -> -263 | AE61: =I61-AD61 -> 352 | AF61: =AF60-I60 -> -93 | AG61: =J61-AF61 -> -28 | AH61: =AH60-J60 -> 634 | AI61: =K61-AH61 -> -602
B62: Change YoY % | E62: =E60/D60-1 -> -0.74059966 | F62: =F60/E60-1 -> 0.07721459 | G62: =G60/F60-1 -> 0.042216359 | H62: =H60/G60-1 -> 0.19578059 | I62: =I60/H60-1 -> 0.062808751 | J62: =J60/I60-1 -> -0.080345286 | K62: =K60/J60-1 -> 0.023104693 | L62: =L60/K60-1 -> 0.033041769 | ... P62: =P60/O60-1 -> 0.041851957 | V62: =V60/T60-1 -> -0.68804483 | X62: =X60/V60-1 -> -0.16267465 | Z62: =Z60/X60-1 -> 0.59117998 | AB62: =AB60/Z60-1 -> 0.16779026 | AD62: =AD60/AB60-1 -> 0.077613855 | AF62: =AF60/AD60-1 -> -0.048214286 | AH62: =AH60/AF60-1 -> -0.53033146
B64: Cash | D64: =D6 -> 686.1 | E64: =E6 -> 940.4 | F64: =F6 -> 992 | G64: =G6 -> 787 | H64: =H6 -> 589 | I64: =I6 -> 597 | J64: =J6 -> 675 | K64: =K6 -> 705 | ... P64: =P6 -> 1016.7905 | T64: =T6 -> 669 | V64: =V6 -> 484 | X64: =X6 -> 797 | Z64: =Z6 -> 1178 | AB64: =AB6 -> 1098 | AD64: =AD6 -> 698 | AF64: =AF6 -> 1092 | AH64: =AH6 -> 625
B65: Borrowings | D65: =D33+D26 -> 0 | E65: =E33+E26 -> 1460 | F65: =F33+F26 -> 1354 | G65: =G33+G26 -> 1142 | H65: =H33+H26 -> 1095 | I65: =I33+I26 -> 1118 | J65: =J33+J26 -> 1652 | K65: =K33+K26 -> 1984 | ... P65: =P33+P26 -> 1984 | T65: =T26+T33 -> 0 | V65: =V26+V33 -> 1630 | X65: =X26+X33 -> 1363 | Z65: =Z26+Z33 -> 1140 | AB65: =AB26+AB33 -> 1044 | AD65: =AD26+AD33 -> 1060 | AF65: =AF26+AF33 -> 1666 | AH65: =AH26+AH33 -> 2276
A66: Net Debt | B66: Net Debt | D66: =D65-D64 -> -686.1 | E66: =E65-E64 -> 519.6 | F66: =F65-F64 -> 362 | G66: =G65-G64 -> 355 | H66: =H65-H64 -> 506 | I66: =I65-I64 -> 521 | J66: =J65-J64 -> 977 | K66: =K65-K64 -> 1279 | ... P66: =P65-P64 -> 967.20947 | T66: =T65-T64 -> -669 | V66: =V65-V64 -> 1146 | X66: =X65-X64 -> 566 | Z66: =Z65-Z64 -> -38 | AB66: =AB65-AB64 -> -54 | AD66: =AD65-AD64 -> 362 | AF66: =AF65-AF64 -> 574 | AH66: =AH65-AH64 -> 1651
A67: Chg in Net Debt | B67: Change in Net Debt | D67: =D66-C66 -> -686.1 | E67: =E66-D66 -> 1205.7 | F67: =F66-E66 -> -157.6 | G67: =G66-F66 -> -7 | H67: =H66-G66 -> 151 | I67: =I66-H66 -> 15 | J67: =J66-I66 -> 456 | K67: =K66-J66 -> 302 | ... P67: =P66-O66 -> -85.413113 | T67: =T66-C66 -> -669 | U67: =D67-T67 -> -17.1 | V67: =V66-D66 -> 1832.1 | W67: =E67-V67 -> -626.4 | X67: =X66-E66 -> 46.4 | Y67: =F67-X67 -> -204 | Z67: =Z66-F66 -> -400 | AA67: =G67-Z67 -> 393 | AB67: =AB66-G66 -> -409 | AC67: =H67-AB67 -> 560 | AD67: =AD66-H66 -> -144 | AE67: =I67-AD67 -> 159 | AF67: =AF66-I66 -> 53 | AG67: =J67-AF67 -> 403 | AH67: =AH66-J66 -> 674 | AI67: =K67-AH67 -> -372
B69: Lease Modelling Adjustment | L69: 1000 | M69: =L69*1.05 -> 1050 | N69: =M69*1.05 -> 1102.5 | O69: =N69*1.05 -> 1157.625 | P69: =O69*1.05 -> 1215.5063

Sheet Quarterly
B1: Coles Group (COL.AX)
B2: A$M
B3: Quarterly Sales | C3: 1Q17 | D3: 2Q17 | E3: 3Q17 | F3: 4Q17 | G3: 1Q18 | H3: 2Q18 | I3: 3Q18 | J3: 4Q18 | K3: 1Q19 | L3: 2Q19 | M3: 3Q19 | N3: 4Q19 | O3: 1Q20 | P3: 2Q20 | Q3: 3Q20 | R3: 4Q20 | S3: 1Q21 | T3: 2Q21 | U3: 3Q21 | V3: 4Q21 | W3: 1Q22 | X3: 2Q22 | Y3: 3Q22 | Z3: 4Q22 | AA3: 1Q23 | AB3: 2Q23 | AC3: 3Q23 | AD3: 4Q23 | AE3: 1Q24 | AF3: 2Q24 | AG3: 3Q24 | AH3: 4Q24 | AI3: 1Q25 | AJ3: 2Q25 | AK3: 3Q25 | AL3: 4Q25 | AM3: 1Q26 | AN3: 2Q26E | AO3: 3Q26E | AP3: 4Q26E | AV3: 1H17 | AW3: 2H17 | AX3: 1H18 | AY3: 2H18 | AZ3: 1H19 | BA3: 2H19 | BB3: 1H20 | BC3: 2H20 | BD3: 1H21 | BE3: 2H21 | BF3: 1H22 | BG3: 2H22 | BH3: 1H23 | BI3: 2H23 | BJ3: 1H24 | BK3: 2H24 | BL3: 1H25 | BM3: 2H25 | BN3: 1H26E | BO3: 2H26E | BQ3: FY17 | BR3: FY18 | BS3: FY19 | BT3: FY20 | BU3: FY21 | BV3: FY22 | BW3: FY23 | BX3: FY24 | BY3: FY25 | BZ3: FY26E
B4: Weeks in period | C4: 14 | D4: 13 | E4: 13 | F4: 12 | G4: 14 | H4: 13 | I4: 13 | J4: 12 | K4: 14 | L4: 13 | M4: 13 | N4: 12 | O4: 14 | P4: 13 | Q4: 13 | R4: 12 | S4: 14 | T4: 13 | U4: 13 | V4: 12 | W4: 14 | X4: 13 | Y4: 13 | Z4: 12 | AA4: 14 | AB4: 13 | AC4: 13 | AD4: 12 | AE4: 14 | AF4: 13 | AG4: 13 | AH4: 13 | AI4: 14 | AJ4: 13 | AK4: 13 | AL4: 12 | AM4: 14 | AN4: 13 | AO4: 13 | AP4: 12 | AQ4: 14 | AR4: 13 | AS4: 13 | AT4: 12 | BJ4: =AE4+AF4 -> 27 | BK4: =AG4+AH4 -> 26 | BL4: =AI4+AJ4 -> 27 | BM4: =AK4+AL4 -> 25 | BN4: =AM4+AN4 -> 27 | BO4: =AO4+AP4 -> 25
B5: Sales from Continuing Ops.
A6: Food Sales | B6: Food | G6: 7239 | H6: =AX6-G6 -> 8286 | I6: 7049 | J6: =AY6-I6 -> 7345 | K6: 7586 | L6: 8467 | M6: 7232 | N6: =BA6-M6 -> 7589 | O6: 7705 | P6: =BB6-O6 -> 8888 | Q6: 8230 | R6: =BC6-Q6 -> 8170 | S6: 8464 | T6: =BD6-S6 -> 9348 | U6: 7895 | V6: =BE6-U6 -> 8161 | W6: 8620 | X6: =BF6-W6 -> 9396 | Y6: 8032 | Z6: =BG6-Y6 -> 8576 | AA6: 8771 | AB6: =BH6-AA6 -> 10086 | AC6: 8629 | AD6: =BI6-AC6 -> 9260 | AE6: 9186 | AF6: =BJ6-AE6 -> 10592 | AG6: 9065 | AH6: =BK6-AG6 -> 10199 | AI6: 9507 | AJ6: =BL6-AI6 -> 11122 | AK6: 9401 | AL6: =BM6-AK6 -> 9957 | AM6: 9965 | AN6: =BN6-AM6 -> 11540.588 | AO6: =AK6*(1+AO16) -> 9795.842 | AP6: =BO6-AO6 -> 10380.135 | AX6: =VLOOKUP($A6,Model!$1:$1048576,MATCH(Quarterly!AX$3,Model!$3:$3,0),FALSE) -> 15525 | AY6: =VLOOKUP($A6,Model!$1:$1048576,MATCH(Quarterly!AY$3,Model!$3:$3,0),FALSE) -> 14394 | AZ6: =VLOOKUP($A6,Model!$1:$1048576,MATCH(Quarterly!AZ$3,Model!$3:$3,0),FALSE) -> 16069 | BA6: =VLOOKUP($A6,Model!$1:$1048576,MATCH(Quarterly!BA$3,Model!$3:$3,0),FALSE) -> 14821 | BB6: =VLOOKUP($A6,Model!$1:$1048576,MATCH(Quarterly!BB$3,Model!$3:$3,0),FALSE) -> 16593 | BC6: =VLOOKUP($A6,Model!$1:$1048576,MATCH(Quarterly!BC$3,Model!$3:$3,0),FALSE) -> 16400 | BD6: =VLOOKUP($A6,Model!$1:$1048576,MATCH(Quarterly!BD$3,Model!$3:$3,0),FALSE) -> 17812 | BE6: =VLOOKUP($A6,Model!$1:$1048576,MATCH(Quarterly!BE$3,Model!$3:$3,0),FALSE) -> 16056 | ... BO6: =VLOOKUP($A6,Model!$1:$1048576,MATCH(Quarterly!BO$3,Model!$3:$3,0),FALSE) -> 20175.977 | BQ6: =VLOOKUP($A6,Model!$1:$1048576,MATCH(Quarterly!BQ$3,Model!$3:$3,0),FALSE) -> 29754 | BR6: =VLOOKUP($A6,Model!$1:$1048576,MATCH(Quarterly!BR$3,Model!$3:$3,0),FALSE) -> 29919 | BS6: =VLOOKUP($A6,Model!$1:$1048576,MATCH(Quarterly!BS$3,Model!$3:$3,0),FALSE) -> 30890 | BT6: =VLOOKUP($A6,Model!$1:$1048576,MATCH(Quarterly!BT$3,Model!$3:$3,0),FALSE) -> 32993 | BU6: =VLOOKUP($A6,Model!$1:$1048576,MATCH(Quarterly!BU$3,Model!$3:$3,0),FALSE) -> 33868 | BV6: =VLOOKUP($A6,Model!$1:$1048576,MATCH(Quarterly!BV$3,Model!$3:$3,0),FALSE) -> 34624 | BW6: =VLOOKUP($A6,Model!$1:$1048576,MATCH(Quarterly!BW$3,Model!$3:$3,0),FALSE) -> 36746 | BX6: =VLOOKUP($A6,Model!$1:$1048576,MATCH(Quarterly!BX$3,Model!$3:$3,0),FALSE) -> 39042 | ... BZ6: =VLOOKUP($A6,Model!$1:$1048576,MATCH(Quarterly!BZ$3,Model!$3:$3,0),FALSE) -> 41681.565
A7: Liquor Sales | B7: Liquor | G7: 729 | H7: =AX7-G7 -> 992 | I7: 705 | J7: =AY7-I7 -> 888 | K7: 701 | L7: 936 | M7: 697 | N7: =BA7-M7 -> 729 | O7: 726 | P7: =BB7-O7 -> 965 | Q7: 740 | R7: =BC7-Q7 -> 877 | S7: 852 | T7: =BD7-S7 -> 1094 | U7: 763 | V7: =BE7-U7 -> 816 | W7: 874 | X7: =BF7-W7 -> 1125 | Y7: 781 | Z7: =BG7-Y7 -> 833 | AA7: 836 | AB7: =BH7-AA7 -> 1116 | AC7: 801 | AD7: =BI7-AC7 -> 857 | AE7: 851 | AF7: =BJ7-AE7 -> 1137 | AG7: 786 | AH7: =BK7-AG7 -> 918 | AI7: 851 | AJ7: =BL7-AI7 -> 1153 | AK7: 813 | AL7: =BM7-AK7 -> 850 | AM7: 842 | AN7: =BN7-AM7 -> 1142.962 | AO7: =AK7*(1+AO17) -> 806.496 | AP7: =BO7-AO7 -> 845.24516 | AX7: =VLOOKUP($A7,Model!$1:$1048576,MATCH(Quarterly!AX$3,Model!$3:$3,0),FALSE) -> 1721 | AY7: =VLOOKUP($A7,Model!$1:$1048576,MATCH(Quarterly!AY$3,Model!$3:$3,0),FALSE) -> 1593 | AZ7: =VLOOKUP($A7,Model!$1:$1048576,MATCH(Quarterly!AZ$3,Model!$3:$3,0),FALSE) -> 1637 | BA7: =VLOOKUP($A7,Model!$1:$1048576,MATCH(Quarterly!BA$3,Model!$3:$3,0),FALSE) -> 1426 | BB7: =VLOOKUP($A7,Model!$1:$1048576,MATCH(Quarterly!BB$3,Model!$3:$3,0),FALSE) -> 1691 | BC7: =VLOOKUP($A7,Model!$1:$1048576,MATCH(Quarterly!BC$3,Model!$3:$3,0),FALSE) -> 1617 | BD7: =VLOOKUP($A7,Model!$1:$1048576,MATCH(Quarterly!BD$3,Model!$3:$3,0),FALSE) -> 1946 | BE7: =VLOOKUP($A7,Model!$1:$1048576,MATCH(Quarterly!BE$3,Model!$3:$3,0),FALSE) -> 1579 | ... BO7: =VLOOKUP($A7,Model!$1:$1048576,MATCH(Quarterly!BO$3,Model!$3:$3,0),FALSE) -> 1651.7412 | BQ7: =VLOOKUP($A7,Model!$1:$1048576,MATCH(Quarterly!BQ$3,Model!$3:$3,0),FALSE) -> 3223 | BR7: =VLOOKUP($A7,Model!$1:$1048576,MATCH(Quarterly!BR$3,Model!$3:$3,0),FALSE) -> 3314 | BS7: =VLOOKUP($A7,Model!$1:$1048576,MATCH(Quarterly!BS$3,Model!$3:$3,0),FALSE) -> 3063 | BT7: =VLOOKUP($A7,Model!$1:$1048576,MATCH(Quarterly!BT$3,Model!$3:$3,0),FALSE) -> 3308 | BU7: =VLOOKUP($A7,Model!$1:$1048576,MATCH(Quarterly!BU$3,Model!$3:$3,0),FALSE) -> 3525 | BV7: =VLOOKUP($A7,Model!$1:$1048576,MATCH(Quarterly!BV$3,Model!$3:$3,0),FALSE) -> 3613 | BW7: =VLOOKUP($A7,Model!$1:$1048576,MATCH(Quarterly!BW$3,Model!$3:$3,0),FALSE) -> 3610 | BX7: =VLOOKUP($A7,Model!$1:$1048576,MATCH(Quarterly!BX$3,Model!$3:$3,0),FALSE) -> 3692 | ... BZ7: =VLOOKUP($A7,Model!$1:$1048576,MATCH(Quarterly!BZ$3,Model!$3:$3,0),FALSE) -> 3636.7032
A8: Corporate/Other Sales | B8: Corporate / Other | G8: 1402 | H8: =AX8-G8 -> -1394 | I8: 1292 | J8: =AY8-I8 -> -1287 | K8: 256 | L8: 291 | N8: =BA8-M8 -> -13 | AC8: 271 | AD8: =BI8-AC8 -> -144 | AE8: 214 | AF8: =BJ8-AE8 -> 236 | AG8: 182 | AH8: =BK8-AG8 -> 205 | AI8: 190 | AJ8: =BL8-AI8 -> 212 | AK8: 165 | AL8: =BM8-AK8 -> 131 | AM8: 156 | AN8: =BN8-AM8 -> 165.6 | AO8: =AK8*(1+AO18) -> 135.3 | AP8: =BO8-AO8 -> 42.3 | AX8: =VLOOKUP($A8,Model!$1:$1048576,MATCH(Quarterly!AX$3,Model!$3:$3,0),FALSE) -> 8 | AY8: =VLOOKUP($A8,Model!$1:$1048576,MATCH(Quarterly!AY$3,Model!$3:$3,0),FALSE) -> 5 | AZ8: =VLOOKUP($A8,Model!$1:$1048576,MATCH(Quarterly!AZ$3,Model!$3:$3,0),FALSE) -> 13 | BA8: =VLOOKUP($A8,Model!$1:$1048576,MATCH(Quarterly!BA$3,Model!$3:$3,0),FALSE) -> -13 | BB8: =VLOOKUP($A8,Model!$1:$1048576,MATCH(Quarterly!BB$3,Model!$3:$3,0),FALSE) -> 0 | BC8: =VLOOKUP($A8,Model!$1:$1048576,MATCH(Quarterly!BC$3,Model!$3:$3,0),FALSE) -> 0 | BD8: =VLOOKUP($A8,Model!$1:$1048576,MATCH(Quarterly!BD$3,Model!$3:$3,0),FALSE) -> 0 | BE8: =VLOOKUP($A8,Model!$1:$1048576,MATCH(Quarterly!BE$3,Model!$3:$3,0),FALSE) -> 0 | ... BO8: =VLOOKUP($A8,Model!$1:$1048576,MATCH(Quarterly!BO$3,Model!$3:$3,0),FALSE) -> 177.6 | BQ8: =VLOOKUP($A8,Model!$1:$1048576,MATCH(Quarterly!BQ$3,Model!$3:$3,0),FALSE) -> 16 | BR8: =VLOOKUP($A8,Model!$1:$1048576,MATCH(Quarterly!BR$3,Model!$3:$3,0),FALSE) -> 13 | BS8: =VLOOKUP($A8,Model!$1:$1048576,MATCH(Quarterly!BS$3,Model!$3:$3,0),FALSE) -> 0 | BT8: =VLOOKUP($A8,Model!$1:$1048576,MATCH(Quarterly!BT$3,Model!$3:$3,0),FALSE) -> 0 | BU8: =VLOOKUP($A8,Model!$1:$1048576,MATCH(Quarterly!BU$3,Model!$3:$3,0),FALSE) -> 0 | BV8: =VLOOKUP($A8,Model!$1:$1048576,MATCH(Quarterly!BV$3,Model!$3:$3,0),FALSE) -> 0 | BW8: =VLOOKUP($A8,Model!$1:$1048576,MATCH(Quarterly!BW$3,Model!$3:$3,0),FALSE) -> 127 | BX8: =VLOOKUP($A8,Model!$1:$1048576,MATCH(Quarterly!BX$3,Model!$3:$3,0),FALSE) -> 837 | ... BZ8: =VLOOKUP($A8,Model!$1:$1048576,MATCH(Quarterly!BZ$3,Model!$3:$3,0),FALSE) -> 499.2
A9: Total Sales | B9: Sales from Continuing Ops. | G9: =SUM(G6:G8) -> 9370 | H9: =SUM(H6:H8) -> 7884 | I9: =SUM(I6:I8) -> 9046 | J9: =SUM(J6:J8) -> 6946 | K9: =SUM(K6:K8) -> 8543 | L9: =SUM(L6:L8) -> 9694 | M9: =SUM(M6:M8) -> 7929 | N9: =SUM(N6:N8) -> 8305 | ... AM9: =SUM(AM6:AM8) -> 10963 | AN9: =BN9-AM9 -> 12849.15 | AO9: =SUM(AO6:AO8) -> 10737.638 | AP9: =BO9-AO9 -> 11267.68 | AX9: =VLOOKUP($A9,Model!$1:$1048576,MATCH(Quarterly!AX$3,Model!$3:$3,0),FALSE) -> 20246 | AY9: =VLOOKUP($A9,Model!$1:$1048576,MATCH(Quarterly!AY$3,Model!$3:$3,0),FALSE) -> 18761 | AZ9: =VLOOKUP($A9,Model!$1:$1048576,MATCH(Quarterly!AZ$3,Model!$3:$3,0),FALSE) -> 18266 | BA9: =VLOOKUP($A9,Model!$1:$1048576,MATCH(Quarterly!BA$3,Model!$3:$3,0),FALSE) -> 16735 | BB9: =VLOOKUP($A9,Model!$1:$1048576,MATCH(Quarterly!BB$3,Model!$3:$3,0),FALSE) -> 18856 | BC9: =VLOOKUP($A9,Model!$1:$1048576,MATCH(Quarterly!BC$3,Model!$3:$3,0),FALSE) -> 18552 | BD9: =VLOOKUP($A9,Model!$1:$1048576,MATCH(Quarterly!BD$3,Model!$3:$3,0),FALSE) -> 20390 | BE9: =VLOOKUP($A9,Model!$1:$1048576,MATCH(Quarterly!BE$3,Model!$3:$3,0),FALSE) -> 18195 | ... BO9: =VLOOKUP($A9,Model!$1:$1048576,MATCH(Quarterly!BO$3,Model!$3:$3,0),FALSE) -> 22005.318 | BQ9: =VLOOKUP($A9,Model!$1:$1048576,MATCH(Quarterly!BQ$3,Model!$3:$3,0),FALSE) -> 39125 | BR9: =VLOOKUP($A9,Model!$1:$1048576,MATCH(Quarterly!BR$3,Model!$3:$3,0),FALSE) -> 39007 | BS9: =VLOOKUP($A9,Model!$1:$1048576,MATCH(Quarterly!BS$3,Model!$3:$3,0),FALSE) -> 35001 | BT9: =VLOOKUP($A9,Model!$1:$1048576,MATCH(Quarterly!BT$3,Model!$3:$3,0),FALSE) -> 37408 | BU9: =VLOOKUP($A9,Model!$1:$1048576,MATCH(Quarterly!BU$3,Model!$3:$3,0),FALSE) -> 38585 | BV9: =VLOOKUP($A9,Model!$1:$1048576,MATCH(Quarterly!BV$3,Model!$3:$3,0),FALSE) -> 38237 | BW9: =VLOOKUP($A9,Model!$1:$1048576,MATCH(Quarterly!BW$3,Model!$3:$3,0),FALSE) -> 40483 | BX9: =VLOOKUP($A9,Model!$1:$1048576,MATCH(Quarterly!BX$3,Model!$3:$3,0),FALSE) -> 43571 | ... BZ9: =VLOOKUP($A9,Model!$1:$1048576,MATCH(Quarterly!BZ$3,Model!$3:$3,0),FALSE) -> 45817.469
B11: Total Growth % (reported)
B12: Food | K12: =K6/G6-1 -> 0.047934798 | L12: =L6/H6-1 -> 0.021844074 | M12: 0.032 | N12: =N6/J6-1 -> 0.033219877 | O12: 0.016 | P12: =P6/L6-1 -> 0.049722452 | Q12: 0.138 | R12: =R6/N6-1 -> 0.076558176 | S12: 0.098 | T12: =T6/P6-1 -> 0.051755176 | U12: -0.061 | V12: =V6/R6-1 -> -0.0011015912 | W12: 0.018 | X12: =X6/T6-1 -> 0.0051347882 | Y12: 0.042 | Z12: 0.03 | AA12: 0.017 | AB12: 0.074 | AC12: 0.074 | AD12: =AD6/Z6-1 -> 0.079757463 | AE12: 0.047 | AF12: =AF6/AB6-1 -> 0.05016855 | AG12: 0.051 | AH12: 0.026 | AI12: 0.035 | AJ12: =AJ6/AF6-1 -> 0.050037764 | AK12: 0.037 | AL12: 0.048 | AM12: 0.048
B13: Liquor | K13: =K7/G7-1 -> -0.038408779 | L13: =L7/H7-1 -> -0.056451613 | M13: 0.043 | N13: =N7/J7-1 -> -0.17905405 | O13: 0.035 | P13: =P7/L7-1 -> 0.030982906 | Q13: 0.061 | R13: =R7/N7-1 -> 0.20301783 | S13: 0.174 | T13: =T7/P7-1 -> 0.13367876 | U13: -0.026 | V13: =V7/R7-1 -> -0.069555302 | W13: 0.026 | X13: =X7/T7-1 -> 0.02833638 | Y13: 0.028 | Z13: 0.016 | AA13: -0.043 | AB13: =AB7/X7-1 -> -0.008 | AC13: -0.019 | AD13: =AD7/Z7-1 -> 0.028811525 | AE13: 0.018 | AF13: =AF7/AB7-1 -> 0.018817204 | AG13: -0.019 | AH13: -0.004 | AI13: 0 | AJ13: =AJ7/AF7-1 -> 0.01407212 | AK13: 0.034 | AL13: -0.005 | AM13: -0.011
AN14: =50/AJ6 -> 0.0044955943
B15: Total Growth % (calculated) | AN15: =120/AJ6 -> 0.010789426
B16: Food | K16: =K6/G6-1 -> 0.047934798 | L16: =L6/H6-1 -> 0.021844074 | M16: =M6/I6-1 -> 0.025961129 | N16: =N6/J6-1 -> 0.033219877 | O16: =O6/K6-1 -> 0.015686791 | P16: =P6/L6-1 -> 0.049722452 | Q16: =Q6/M6-1 -> 0.13799779 | R16: =R6/N6-1 -> 0.076558176 | ... AN16: =AN6/AJ6-1 -> 0.037636058 | AO16: =AO22+AO26 -> 0.042 | AP16: =AP6/AL6-1 -> 0.042496246 | AZ16: =AZ6/AX6-1 -> 0.035040258 | BA16: =BA6/AY6-1 -> 0.029665138 | BB16: =BB6/AZ6-1 -> 0.032609372 | BC16: =BC6/BA6-1 -> 0.10653802 | BD16: =BD6/BB6-1 -> 0.073464714 | BE16: =BE6/BC6-1 -> -0.02097561 | BF16: =BF6/BD6-1 -> 0.011452953 | BG16: =BG6/BE6-1 -> 0.034379671 | ... BO16: =BO6/BM6-1 -> 0.04225525 | BR16: =BR6/BQ6-1 -> 0.0055454729 | BS16: =BS6/BR6-1 -> 0.032454293 | BT16: =BT6/BS6-1 -> 0.068080285 | BU16: =BU6/BT6-1 -> 0.026520777 | BV16: =BV6/BU6-1 -> 0.022321956 | BW16: =BW6/BV6-1 -> 0.061286969 | BX16: =BX6/BW6-1 -> 0.062482991 | BY16: =BY6/BX6-1 -> 0.024204703 | BZ16: =BZ6/BY6-1 -> 0.042377907
B17: Liquor | K17: =K7/G7-1 -> -0.038408779 | L17: =L7/H7-1 -> -0.056451613 | M17: =M7/I7-1 -> -0.011347518 | N17: =N7/J7-1 -> -0.17905405 | O17: =O7/K7-1 -> 0.035663338 | P17: =P7/L7-1 -> 0.030982906 | Q17: =Q7/M7-1 -> 0.06169297 | R17: =R7/N7-1 -> 0.20301783 | ... AN17: =AN7/AJ7-1 -> -0.0087059844 | AO17: =AO23+AO27 -> -0.008 | AP17: =AP7/AL7-1 -> -0.005593932 | BE17: =BE7/BC7-1 -> -0.023500309 | BF17: =BF7/BD7-1 -> 0.027235355 | BG17: =BG7/BE7-1 -> 0.022165928 | BH17: =BH7/BF7-1 -> -0.023511756 | BI17: =BI7/BG7-1 -> 0.027261462 | BJ17: =BJ7/BH7-1 -> 0.018442623 | BK17: =BK7/BI7-1 -> 0.02774427 | BL17: =BL7/BJ7-1 -> 0.0080482897 | ... BO17: =BO7/BM7-1 -> -0.0067701998 | BR17: =BR7/BQ7-1 -> 0.028234564 | BS17: =BS7/BR7-1 -> -0.075739288 | BT17: =BT7/BS7-1 -> 0.079986941 | BU17: =BU7/BT7-1 -> 0.065598549 | BV17: =BV7/BU7-1 -> 0.024964539 | BW17: =BW7/BV7-1 -> -0.0008303349 | BX17: =BX7/BW7-1 -> 0.022714681 | BY17: =BY7/BX7-1 -> -0.0067713976 | BZ17: =BZ7/BY7-1 -> -0.008262024
B18: Corporate / Other | AG18: =AG8/AC8-1 -> -0.32841328 | AH18: =AH8/AD8-1 -> -2.4236111 | AI18: =AI8/AE8-1 -> -0.11214953 | AJ18: =AJ8/AF8-1 -> -0.10169492 | AK18: =AK8/AG8-1 -> -0.093406593 | AL18: =AL8/AH8-1 -> -0.36097561 | AM18: =AM8/AI8-1 -> -0.17894737 | AN18: =AN8/AJ8-1 -> -0.21886792 | AO18: -0.18 | AP18: =AP8/AL8-1 -> -0.67709924 | BK18: =BK8/BI8-1 -> 2.0472441 | BL18: =BL8/BJ8-1 -> -0.10666667 | BM18: =BM8/BK8-1 -> -0.23514212 | BN18: =BN8/BL8-1 -> -0.2 | BO18: =BO8/BM8-1 -> -0.4 | BX18: =BX8/BW8-1 -> 5.5905512 | BY18: =BY8/BX8-1 -> -0.1660693 | BZ18: =BZ8/BY8-1 -> -0.28481375
B19: Sales from Continuing Ops. % | K19: =K9/G9-1 -> -0.088260406 | L19: =L9/H9-1 -> 0.22957889 | M19: =M9/I9-1 -> -0.12347999 | N19: =N9/J9-1 -> 0.19565217 | O19: =O9/K9-1 -> -0.013110149 | P19: =P9/L9-1 -> 0.016401898 | Q19: =Q9/M9-1 -> 0.1312902 | R19: =R9/N9-1 -> 0.089343769 | ... AP19: =AP9/AL9-1 -> 0.030140819 | AY19: =AY9/AX9-1 -> -0.073347822 | AZ19: =AZ9/AY9-1 -> -0.026384521 | BA19: =BA9/AZ9-1 -> -0.083816928 | BB19: =BB9/BA9-1 -> 0.12674036 | BC19: =BC9/BB9-1 -> -0.016122189 | BD19: =BD9/BC9-1 -> 0.099072876 | BE19: =BE9/BD9-1 -> -0.10765081 | BF19: =BF9/BE9-1 -> 0.10002748 | ... BO19: =BO9/BN9-1 -> -0.075878572 | BT19: =BT9/BS9-1 -> 0.068769464 | BU19: =BU9/BT9-1 -> 0.031463858 | BV19: =BV9/BU9-1 -> -0.0090190489 | BW19: =BW9/BV9-1 -> 0.058738918 | BX19: =BX9/BW9-1 -> 0.076278932 | BY19: =BY9/BX9-1 -> 0.017924766 | BZ19: =BZ9/BY9-1 -> 0.033041769
B21: LFL Sales Growth %
A22: Food Comp | B22: Food | G22: 0.003 | H22: 0.014 | I22: 0.009 | J22: =(AY22-0.5*I22)/0.5 -> 0.013 | K22: 0.051 | L22: =(AZ22-0.5*K22)/0.5 -> 0.013 | M22: 0.032 | N22: =(BA22-0.5*M22)/0.5 -> 0.012 | O22: 0.001 | P22: =(BB22-0.5*O22)/0.5 -> 0.039 | Q22: 0.131 | R22: =(BC22-0.5*Q22)/0.5 -> 0.069 | S22: 0.097 | T22: =(BD22-0.5*S22)/0.5 -> 0.047 | U22: -0.064 | V22: 0.021 | W22: 0.014 | X22: =(BF22-0.5*W22)/0.5 -> 0.016 | Y22: 0.039 | Z22: 0.037 | AA22: 0.021 | AB22: =(BH22-0.5*AA22)/0.5 -> 0.077 | AC22: 0.065 | AD22: =(BI22-0.5*AC22)/0.5 -> 0.069 | AE22: 0.046 | AF22: =(BJ22-0.5*AE22)/0.5 -> 0.034 | AG22: 0.047 | AH22: =(BK22-0.5*AG22)/0.5 -> 0.005 | AI22: 0.024 | AJ22: 0.042 | AK22: 0.03 | AL22: 0.051 | AM22: 0.046 | AN22: 0.035 | AO22: 0.04 | AP22: 0.034 | AX22: =VLOOKUP($A22,Model!$1:$1048576,MATCH(Quarterly!AX$3,Model!$3:$3,0),FALSE) -> 0.009 | AY22: =VLOOKUP($A22,Model!$1:$1048576,MATCH(Quarterly!AY$3,Model!$3:$3,0),FALSE) -> 0.011 | AZ22: =VLOOKUP($A22,Model!$1:$1048576,MATCH(Quarterly!AZ$3,Model!$3:$3,0),FALSE) -> 0.032 | BA22: =VLOOKUP($A22,Model!$1:$1048576,MATCH(Quarterly!BA$3,Model!$3:$3,0),FALSE) -> 0.022 | BB22: =VLOOKUP($A22,Model!$1:$1048576,MATCH(Quarterly!BB$3,Model!$3:$3,0),FALSE) -> 0.02 | BC22: =VLOOKUP($A22,Model!$1:$1048576,MATCH(Quarterly!BC$3,Model!$3:$3,0),FALSE) -> 0.1 | BD22: =VLOOKUP($A22,Model!$1:$1048576,MATCH(Quarterly!BD$3,Model!$3:$3,0),FALSE) -> 0.072 | BE22: =VLOOKUP($A22,Model!$1:$1048576,MATCH(Quarterly!BE$3,Model!$3:$3,0),FALSE) -> -0.022 | ... BM22: =VLOOKUP($A22,Model!$1:$1048576,MATCH(Quarterly!BM$3,Model!$3:$3,0),FALSE) -> 0.041 | BN22: =AVERAGE(AM22:AN22) -> 0.0405 | BO22: =AVERAGE(AO22:AP22) -> 0.037 | BR22: =VLOOKUP($A22,Model!$1:$1048576,MATCH(Quarterly!BR$3,Model!$3:$3,0),FALSE) -> 0.011 | BS22: =VLOOKUP($A22,Model!$1:$1048576,MATCH(Quarterly!BS$3,Model!$3:$3,0),FALSE) -> 0.027 | BT22: =VLOOKUP($A22,Model!$1:$1048576,MATCH(Quarterly!BT$3,Model!$3:$3,0),FALSE) -> 0.059 | BU22: =VLOOKUP($A22,Model!$1:$1048576,MATCH(Quarterly!BU$3,Model!$3:$3,0),FALSE) -> 0.025 | BV22: =VLOOKUP($A22,Model!$1:$1048576,MATCH(Quarterly!BV$3,Model!$3:$3,0),FALSE) -> 0.026 | BW22: =VLOOKUP($A22,Model!$1:$1048576,MATCH(Quarterly!BW$3,Model!$3:$3,0),FALSE) -> 0.058 | BX22: =VLOOKUP($A22,Model!$1:$1048576,MATCH(Quarterly!BX$3,Model!$3:$3,0),FALSE) -> 0.034 | BY22: =VLOOKUP($A22,Model!$1:$1048576,MATCH(Quarterly!BY$3,Model!$3:$3,0),FALSE) -> 0.037 | BZ22: =AVERAGE(AM22:AP22) -> 0.03875
A23: Liquor Comp | B23: Liquor | H23: 0.013 | I23: 0.009 | J23: =(AY23-0.5*I23)/0.5 -> 0.027 | K23: 0.013 | L23: =(AZ23-0.5*K23)/0.5 -> 0.009 | M23: 0.01 | N23: =(BA23-0.5*M23)/0.5 -> 0.014 | O23: 0.007 | P23: =(BB23-0.5*O23)/0.5 -> 0.023 | Q23: 0.072 | R23: =(BC23-0.5*Q23)/0.5 -> 0.206 | S23: 0.178 | T23: =(BD23-0.5*S23)/0.5 -> 0.124 | U23: 0.021 | V23: =(BE23-0.5*U23)/0.5 -> -0.079 | W23: 0.014 | X23: =(BF23-0.5*W23)/0.5 -> 0.022 | Y23: 0.028 | Z23: 0.019 | AA23: -0.041 | AB23: =(BH23-0.5*AA23)/0.5 -> -0.005 | AC23: 0.015 | AD23: =(BI23-0.5*AC23)/0.5 -> 0.011 | AE23: 0.001 | AF23: =(BJ23-0.5*AE23)/0.5 -> 0.003 | AG23: -0.031 | AH23: =(BK23-0.5*AG23)/0.5 -> -0.017 | AI23: -0.044 | AJ23: =(BL23-0.5*AI23)/0.5 -> 0.018 | AK23: -0.02 | AL23: -0.006 | AM23: -0.014 | AN23: -0.011 | AO23: -0.01 | AP23: -0.01 | AX23: =VLOOKUP($A23,Model!$1:$1048576,MATCH(Quarterly!AX$3,Model!$3:$3,0),FALSE) -> 0.016 | AY23: =VLOOKUP($A23,Model!$1:$1048576,MATCH(Quarterly!AY$3,Model!$3:$3,0),FALSE) -> 0.018 | AZ23: =VLOOKUP($A23,Model!$1:$1048576,MATCH(Quarterly!AZ$3,Model!$3:$3,0),FALSE) -> 0.011 | BA23: =VLOOKUP($A23,Model!$1:$1048576,MATCH(Quarterly!BA$3,Model!$3:$3,0),FALSE) -> 0.012 | BB23: =VLOOKUP($A23,Model!$1:$1048576,MATCH(Quarterly!BB$3,Model!$3:$3,0),FALSE) -> 0.015 | BC23: =VLOOKUP($A23,Model!$1:$1048576,MATCH(Quarterly!BC$3,Model!$3:$3,0),FALSE) -> 0.139 | BD23: =VLOOKUP($A23,Model!$1:$1048576,MATCH(Quarterly!BD$3,Model!$3:$3,0),FALSE) -> 0.151 | BE23: =VLOOKUP($A23,Model!$1:$1048576,MATCH(Quarterly!BE$3,Model!$3:$3,0),FALSE) -> -0.029 | ... BM23: =VLOOKUP($A23,Model!$1:$1048576,MATCH(Quarterly!BM$3,Model!$3:$3,0),FALSE) -> -0.012 | BN23: =AVERAGE(AM23:AN23) -> -0.0125 | BO23: =AVERAGE(AO23:AP23) -> -0.01 | BR23: =VLOOKUP($A23,Model!$1:$1048576,MATCH(Quarterly!BR$3,Model!$3:$3,0),FALSE) -> 0.018 | BS23: =VLOOKUP($A23,Model!$1:$1048576,MATCH(Quarterly!BS$3,Model!$3:$3,0),FALSE) -> 0.027 | BT23: =VLOOKUP($A23,Model!$1:$1048576,MATCH(Quarterly!BT$3,Model!$3:$3,0),FALSE) -> 0.073 | BU23: =VLOOKUP($A23,Model!$1:$1048576,MATCH(Quarterly!BU$3,Model!$3:$3,0),FALSE) -> 0.063 | BV23: =VLOOKUP($A23,Model!$1:$1048576,MATCH(Quarterly!BV$3,Model!$3:$3,0),FALSE) -> 0.021 | BW23: =VLOOKUP($A23,Model!$1:$1048576,MATCH(Quarterly!BW$3,Model!$3:$3,0),FALSE) -> 0.007 | BX23: =VLOOKUP($A23,Model!$1:$1048576,MATCH(Quarterly!BX$3,Model!$3:$3,0),FALSE) -> -0.01 | BY23: =VLOOKUP($A23,Model!$1:$1048576,MATCH(Quarterly!BY$3,Model!$3:$3,0),FALSE) -> -0.013 | BZ23: =AVERAGE(AM23:AP23) -> -0.01125
B25: Other Growth (space/timing) %
B26: Food | K26: =K16-K22 -> -0.0030652024 | L26: =L16-L22 -> 0.0088440743 | M26: =M16-M22 -> -0.0060388708 | N26: =N16-N22 -> 0.021219877 | O26: =O16-O22 -> 0.014686791 | P26: =P16-P22 -> 0.010722452 | Q26: =Q16-Q22 -> 0.0069977876 | R26: =R16-R22 -> 0.0075581763 | ... AN26: =AN16-AN22 -> 0.0026360584 | AO26: 0.002 | AP26: =AP16-AP22 -> 0.0084962464 | AX26: =AX16-AX22 -> -0.009 | AY26: =AY16-AY22 -> -0.011 | AZ26: =AZ16-AZ22 -> 0.0030402576 | BA26: =BA16-BA22 -> 0.0076651383 | BB26: =BB16-BB22 -> 0.012609372 | BC26: =BC16-BC22 -> 0.0065380204 | BD26: =BD16-BD22 -> 0.001464714 | BE26: =BE16-BE22 -> 0.0010243902 | ... BO26: =BO16-BO22 -> 0.0052552498 | BR26: =BR16-BR22 -> -0.0054545271 | BS26: =BS16-BS22 -> 0.0054542933 | BT26: =BT16-BT22 -> 0.0090802849 | BU26: =BU16-BU22 -> 0.0015207771 | BV26: =BV16-BV22 -> -0.0036780442 | BW26: =BW16-BW22 -> 0.0032869686 | BX26: =BX16-BX22 -> 0.028482991 | BY26: =BY16-BY22 -> -0.012795297 | BZ26: =BZ16-BZ22 -> 0.003627907
B27: Liquor | K27: =K17-K23 -> -0.051408779 | L27: =L17-L23 -> -0.065451613 | M27: =M17-M23 -> -0.021347518 | N27: =N17-N23 -> -0.19305405 | O27: =O17-O23 -> 0.028663338 | P27: =P17-P23 -> 0.007982906 | Q27: =Q17-Q23 -> -0.01030703 | R27: =R17-R23 -> -0.0029821674 | ... AN27: =AN17-AN23 -> 0.0022940156 | AO27: 0.002 | AP27: =AP17-AP23 -> 0.004406068 | AX27: =AX17-AX23 -> -0.016 | AY27: =AY17-AY23 -> -0.018 | AZ27: =AZ17-AZ23 -> -0.011 | BA27: =BA17-BA23 -> -0.012 | BB27: =BB17-BB23 -> -0.015 | BC27: =BC17-BC23 -> -0.139 | BD27: =BD17-BD23 -> -0.151 | BE27: =BE17-BE23 -> 0.0054996908 | ... BO27: =BO17-BO23 -> 0.0032298002 | BR27: =BR17-BR23 -> 0.010234564 | BS27: =BS17-BS23 -> -0.10273929 | BT27: =BT17-BT23 -> 0.0069869409 | BU27: =BU17-BU23 -> 0.002598549 | BV27: =BV17-BV23 -> 0.003964539 | BW27: =BW17-BW23 -> -0.0078303349 | BX27: =BX17-BX23 -> 0.032714681 | BY27: =BY17-BY23 -> 0.0062286024 | BZ27: =BZ17-BZ23 -> 0.002987976
B29: Food Key Metrics
B30: Sales Productivity Measures
B31: Total Sales Growth % | K31: =K12 -> 0.047934798 | L31: =L12 -> 0.021844074 | M31: =M12 -> 0.032 | N31: =N12 -> 0.033219877 | O31: =O12 -> 0.016 | P31: =P12 -> 0.049722452 | Q31: =Q12 -> 0.138 | R31: =R12 -> 0.076558176 | ... AM31: =AM12 -> 0.048 | AZ31: =AVERAGE(K31:L31) -> 0.034889436 | BA31: =AVERAGE(M31:N31) -> 0.032609939 | BB31: =AVERAGE(O31:P31) -> 0.032861226 | BC31: =AVERAGE(Q31:R31) -> 0.10727909 | BD31: =AVERAGE(S31:T31) -> 0.074877588 | BE31: =AVERAGE(U31:V31) -> -0.031050796 | BF31: =AVERAGE(W31:X31) -> 0.011567394 | BG31: =AVERAGE(Y31:Z31) -> 0.036 | BH31: =AVERAGE(AA31:AB31) -> 0.0455 | BI31: =AVERAGE(AC31:AD31) -> 0.076878731 | BJ31: =AVERAGE(AE31:AF31) -> 0.048584275 | BK31: =AVERAGE(AG31:AH31) -> 0.0385 | BL31: =AVERAGE(AI31:AJ31) -> 0.042518882 | BM31: =AVERAGE(AK31:AL31) -> 0.0425 | BU31: =AVERAGE(BD31:BE31) -> 0.021913396 | BV31: =AVERAGE(BF31:BG31) -> 0.023783697 | BW31: =AVERAGE(BH31:BI31) -> 0.061189366 | BX31: =AVERAGE(BJ31:BK31) -> 0.043542138 | BY31: =AVERAGE(BL31:BM31) -> 0.042509441
B32: Total Sales Growth ex. Tobacco % | AC32: 0.087 | AE32: 0.059 | AF32: =(BJ32-0.5*AE32)/0.5 -> 0.065 | AG32: 0.066 | AH32: =(BK32-0.5*AG32)/0.5 -> 0.038 | AI32: 0.049 | AJ32: =(BL32-0.5*AI32)/0.5 -> 0.063 | AK32: 0.047 | AL32: 0.07 | AM32: 0.07 | BJ32: 0.062 | BK32: 0.052 | BL32: 0.056 | BM32: 0.059 | BX32: =AVERAGE(BJ32:BK32) -> 0.057 | BY32: =AVERAGE(BL32:BM32) -> 0.0575
B33: Tobacco Impact % | AC33: =AC31-AC32 -> -0.013 | AD33: =AD31-AD32 -> 0.079757463 | AE33: =AE31-AE32 -> -0.012 | AF33: =AF31-AF32 -> -0.01483145 | AG33: =AG31-AG32 -> -0.015 | AH33: =AH31-AH32 -> -0.012 | AI33: =AI31-AI32 -> -0.014 | AJ33: =AJ31-AJ32 -> -0.012962236 | ... AM33: =AM31-AM32 -> -0.022
B34: Total Sales Growth ex. Tobacco ex. Online % | AC34: =AC32-AC44 -> 0.08264243 | AE34: =AE32-AE44 -> 0.041670163 | AF34: =AF32-AF44 -> 0.040411461 | AG34: =AG32-AG44 -> 0.041547572 | AH34: =AH32-AH44 -> 0.0067904968 | AI34: =AI32-AI44 -> 0.029296103 | AJ34: =AJ32-AJ44 -> 0.042324018 | AK34: =AK32-AK44 -> 0.023061776 | AL34: =AL32-AL44 -> 0.052057064 | AM34: =AM32-AM44 -> 0.039706532
B35: Comparable Sales % | K35: =K22 -> 0.051 | L35: =L22 -> 0.013 | M35: =M22 -> 0.032 | N35: =N22 -> 0.012 | O35: =O22 -> 0.001 | P35: =P22 -> 0.039 | Q35: =Q22 -> 0.131 | R35: =R22 -> 0.069 | ... AM35: =AM22 -> 0.046 | AZ35: =AVERAGE(K35:L35) -> 0.032 | BA35: =AVERAGE(M35:N35) -> 0.022 | BB35: =AVERAGE(O35:P35) -> 0.02 | BC35: =AVERAGE(Q35:R35) -> 0.1 | BD35: =AVERAGE(S35:T35) -> 0.072 | BE35: =AVERAGE(U35:V35) -> -0.0215 | BF35: =AVERAGE(W35:X35) -> 0.015 | BG35: =AVERAGE(Y35:Z35) -> 0.038 | BH35: =AVERAGE(AA35:AB35) -> 0.049 | BI35: =AVERAGE(AC35:AD35) -> 0.067 | BJ35: =AVERAGE(AE35:AF35) -> 0.04 | BK35: =AVERAGE(AG35:AH35) -> 0.026 | BL35: =AVERAGE(AI35:AJ35) -> 0.033 | BM35: =AVERAGE(AK35:AL35) -> 0.0405 | BU35: =AVERAGE(BD35:BE35) -> 0.02525 | BV35: =AVERAGE(BF35:BG35) -> 0.0265 | BW35: =AVERAGE(BH35:BI35) -> 0.058 | BX35: =AVERAGE(BJ35:BK35) -> 0.033 | BY35: =AVERAGE(BL35:BM35) -> 0.03675
B36: Implied Other Growth % | K36: =K31-K35 -> -0.0030652024 | L36: =L31-L35 -> 0.0088440743 | M36: =M31-M35 -> 0 | N36: =N31-N35 -> 0.021219877 | O36: =O31-O35 -> 0.015 | P36: =P31-P35 -> 0.010722452 | Q36: =Q31-Q35 -> 0.007 | R36: =R31-R35 -> 0.0075581763 | ... AM36: =AM31-AM35 -> 0.002 | AZ36: =AVERAGE(K36:L36) -> 0.002889436 | BA36: =AVERAGE(M36:N36) -> 0.010609939 | BB36: =AVERAGE(O36:P36) -> 0.012861226 | BC36: =AVERAGE(Q36:R36) -> 0.0072790882 | BD36: =AVERAGE(S36:T36) -> 0.0028775878 | BE36: =AVERAGE(U36:V36) -> -0.0095507956 | BF36: =AVERAGE(W36:X36) -> -0.0034326059 | BG36: =AVERAGE(Y36:Z36) -> -0.002 | BH36: =AVERAGE(AA36:AB36) -> -0.0035 | BI36: =AVERAGE(AC36:AD36) -> 0.0098787313 | BJ36: =AVERAGE(AE36:AF36) -> 0.0085842752 | BK36: =AVERAGE(AG36:AH36) -> 0.0125 | BL36: =AVERAGE(AI36:AJ36) -> 0.0095188822 | BM36: =AVERAGE(AK36:AL36) -> 0.002 | BU36: =AVERAGE(BD36:BE36) -> -0.0033366039 | BV36: =AVERAGE(BF36:BG36) -> -0.002716303 | BW36: =AVERAGE(BH36:BI36) -> 0.0031893657 | BX36: =AVERAGE(BJ36:BK36) -> 0.010542138 | BY36: =AVERAGE(BL36:BM36) -> 0.0057594411
A38: Food Density | B38: Sales Density per sqm | M38: 16612 | N38: =(BA38-0.5*M38)/0.5 -> 16796 | O38: 16664 | P38: =(BB38-0.5*O38)/0.5 -> 16936 | Q38: 17295 | R38: =(BC38-0.5*Q38)/0.5 -> 17799 | S38: 17709 | T38: =(BD38-0.5*S38)/0.5 -> 18493 | U38: 17789 | V38: =(BE38-0.5*U38)/0.5 -> 17905 | W38: 17868 | X38: =(BF38-0.5*W38)/0.5 -> 17970 | Y38: 18066 | Z38: =(BG38-0.5*Y38)/0.5 -> 18352 | AA38: 18295 | AB38: =(BH38-0.5*AA38)/0.5 -> 19007 | AC38: 18907 | AD38: =(BI38-0.5*AC38)/0.5 -> 19495 | AE38: 19377 | AF38: =(BJ38-0.5*AE38)/0.5 -> 19859 | AG38: 19786 | AH38: =(BK38-0.5*AG38)/0.5 -> 19846 | AI38: 19253 | AJ38: =(BL38-0.5*AI38)/0.5 -> 19615 | AK38: 20173 | AL38: =(BM38-0.5*AK38)/0.5 -> 19375 | AM38: 20003 | AX38: =VLOOKUP($A38,Model!$1:$1048576,MATCH(Quarterly!AX$3,Model!$3:$3,0),FALSE) -> 16469 | AY38: =VLOOKUP($A38,Model!$1:$1048576,MATCH(Quarterly!AY$3,Model!$3:$3,0),FALSE) -> 16586.5 | AZ38: =VLOOKUP($A38,Model!$1:$1048576,MATCH(Quarterly!AZ$3,Model!$3:$3,0),FALSE) -> 16533 | BA38: =VLOOKUP($A38,Model!$1:$1048576,MATCH(Quarterly!BA$3,Model!$3:$3,0),FALSE) -> 16704 | BB38: =VLOOKUP($A38,Model!$1:$1048576,MATCH(Quarterly!BB$3,Model!$3:$3,0),FALSE) -> 16800 | BC38: =VLOOKUP($A38,Model!$1:$1048576,MATCH(Quarterly!BC$3,Model!$3:$3,0),FALSE) -> 17547 | BD38: =VLOOKUP($A38,Model!$1:$1048576,MATCH(Quarterly!BD$3,Model!$3:$3,0),FALSE) -> 18101 | BE38: =VLOOKUP($A38,Model!$1:$1048576,MATCH(Quarterly!BE$3,Model!$3:$3,0),FALSE) -> 17847 | ... BM38: =VLOOKUP($A38,Model!$1:$1048576,MATCH(Quarterly!BM$3,Model!$3:$3,0),FALSE) -> 19774 | BS38: =VLOOKUP($A38,Model!$1:$1048576,MATCH(Quarterly!BS$3,Model!$3:$3,0),FALSE) -> 16704 | BT38: =VLOOKUP($A38,Model!$1:$1048576,MATCH(Quarterly!BT$3,Model!$3:$3,0),FALSE) -> 17547 | BU38: =VLOOKUP($A38,Model!$1:$1048576,MATCH(Quarterly!BU$3,Model!$3:$3,0),FALSE) -> 17847 | BV38: =VLOOKUP($A38,Model!$1:$1048576,MATCH(Quarterly!BV$3,Model!$3:$3,0),FALSE) -> 18209 | BW38: =VLOOKUP($A38,Model!$1:$1048576,MATCH(Quarterly!BW$3,Model!$3:$3,0),FALSE) -> 19201 | BX38: =VLOOKUP($A38,Model!$1:$1048576,MATCH(Quarterly!BX$3,Model!$3:$3,0),FALSE) -> 19179 | BY38: =VLOOKUP($A38,Model!$1:$1048576,MATCH(Quarterly!BY$3,Model!$3:$3,0),FALSE) -> 19774
B40: Online
A41: Food Online | B41: eCommerce Online Sales | U41: 400 | V41: =BE41-U41 -> 600 | W41: 800 | X41: =BF41-W41 -> 700 | Y41: 600 | Z41: =BG41-Y41 -> 700 | AA41: 700 | AB41: =BH41-AA41 -> 700 | AC41: 635 | AD41: =BI41-AC41 -> 765 | AE41: 852 | AF41: =BJ41-AE41 -> 948 | AG41: 846 | AH41: =BK41-AG41 -> 1054 | AI41: 1033 | AJ41: =BL41-AI41 -> 1167 | AK41: 1063 | AL41: =BM41-AK41 -> 1237 | AM41: 1321 | BE41: =VLOOKUP($A41,Model!$1:$1048576,MATCH(Quarterly!BE$3,Model!$3:$3,0),FALSE) -> 1000 | BF41: =VLOOKUP($A41,Model!$1:$1048576,MATCH(Quarterly!BF$3,Model!$3:$3,0),FALSE) -> 1500 | BG41: =VLOOKUP($A41,Model!$1:$1048576,MATCH(Quarterly!BG$3,Model!$3:$3,0),FALSE) -> 1300 | BH41: =VLOOKUP($A41,Model!$1:$1048576,MATCH(Quarterly!BH$3,Model!$3:$3,0),FALSE) -> 1400 | BI41: =VLOOKUP($A41,Model!$1:$1048576,MATCH(Quarterly!BI$3,Model!$3:$3,0),FALSE) -> 1400 | BJ41: =VLOOKUP($A41,Model!$1:$1048576,MATCH(Quarterly!BJ$3,Model!$3:$3,0),FALSE) -> 1800 | BK41: =VLOOKUP($A41,Model!$1:$1048576,MATCH(Quarterly!BK$3,Model!$3:$3,0),FALSE) -> 1900 | BL41: =VLOOKUP($A41,Model!$1:$1048576,MATCH(Quarterly!BL$3,Model!$3:$3,0),FALSE) -> 2200 | BM41: =VLOOKUP($A41,Model!$1:$1048576,MATCH(Quarterly!BM$3,Model!$3:$3,0),FALSE) -> 2300 | BU41: =VLOOKUP($A41,Model!$1:$1048576,MATCH(Quarterly!BU$3,Model!$3:$3,0),FALSE) -> 2000 | BV41: =VLOOKUP($A41,Model!$1:$1048576,MATCH(Quarterly!BV$3,Model!$3:$3,0),FALSE) -> 2800 | BW41: =VLOOKUP($A41,Model!$1:$1048576,MATCH(Quarterly!BW$3,Model!$3:$3,0),FALSE) -> 2800 | BX41: =VLOOKUP($A41,Model!$1:$1048576,MATCH(Quarterly!BX$3,Model!$3:$3,0),FALSE) -> 3700 | BY41: =VLOOKUP($A41,Model!$1:$1048576,MATCH(Quarterly!BY$3,Model!$3:$3,0),FALSE) -> 4500
B42: eCommerce Online Sales Growth % | Y42: =Y41/U41-1 -> 0.5 | Z42: =Z41/V41-1 -> 0.16666667 | AA42: =AA41/W41-1 -> -0.125 | AB42: =AB41/X41-1 -> 0 | AC42: =AC41/Y41-1 -> 0.058333333 | AD42: =AD41/Z41-1 -> 0.092857143 | AE42: =AE41/AA41-1 -> 0.21714286 | AF42: =AF41/AB41-1 -> 0.35428571 | ... AM42: =AM41/AI41-1 -> 0.27879961 | BG42: =BG41/BE41-1 -> 0.3 | BH42: =BH41/BF41-1 -> -0.066666667 | BI42: =BI41/BG41-1 -> 0.076923077 | BJ42: =BJ41/BH41-1 -> 0.28571429 | BK42: =BK41/BI41-1 -> 0.35714286 | BL42: =BL41/BJ41-1 -> 0.22222222 | BM42: =BM41/BK41-1 -> 0.21052632 | BV42: =BV41/BU41-1 -> 0.4 | BW42: =BW41/BV41-1 -> 0 | BX42: =BX41/BW41-1 -> 0.32142857 | BY42: =BY41/BX41-1 -> 0.21621622
B43: eCommerce Online Penetration | U43: 0.056 | W43: 0.088 | X43: =X41/X6 -> 0.074499787 | Y43: 0.078 | Z43: =Z41/Z6 -> 0.081623134 | AA43: 0.076 | AB43: =AB41/AB6 -> 0.069403133 | AC43: 0.073 | AD43: =AD41/AD6 -> 0.082613391 | AE43: 0.091 | AF43: =AF41/AF6 -> 0.089501511 | AG43: 0.093 | AH43: =AH41/AH6 -> 0.10334347 | AI43: 0.109 | AJ43: =AJ41/AJ6 -> 0.10492717 | AK43: 0.113 | AL43: =AL41/AL6 -> 0.12423421 | AM43: 0.133 | BE43: =AVERAGE(U43:V43) -> 0.056 | BF43: =AVERAGE(W43:X43) -> 0.081249894 | BG43: =AVERAGE(Y43:Z43) -> 0.079811567 | BH43: =AVERAGE(AA43:AB43) -> 0.072701567 | BI43: =AVERAGE(AC43:AD43) -> 0.077806695 | BJ43: =AVERAGE(AE43:AF43) -> 0.090250755 | BK43: =AVERAGE(AG43:AH43) -> 0.098171733 | BL43: =AVERAGE(AI43:AJ43) -> 0.10696359 | BM43: =AVERAGE(AK43:AL43) -> 0.1186171 | BU43: =AVERAGE(BD43:BE43) -> 0.056 | BV43: =AVERAGE(BF43:BG43) -> 0.08053073 | BW43: =AVERAGE(BH43:BI43) -> 0.075254131 | BX43: =AVERAGE(BJ43:BK43) -> 0.094211244 | BY43: =AVERAGE(BL43:BM43) -> 0.11279034
B44: Online Contribution to LFL | Y44: =(Y41-U41)/U6 -> 0.025332489 | Z44: =(Z41-V41)/V6 -> 0.0122534 | AA44: =(AA41-W41)/W6 -> -0.011600928 | AB44: =(AB41-X41)/X6 -> 0 | AC44: =(AC41-Y41)/Y6 -> 0.0043575697 | AD44: =(AD41-Z41)/Z6 -> 0.007579291 | AE44: =(AE41-AA41)/AA6 -> 0.017329837 | AF44: =(AF41-AB41)/AB6 -> 0.024588539 | ... AM44: =(AM41-AI41)/AI6 -> 0.030293468
B46: Price Metrics
B47: Inflation / (deflation) (%) | G47: -0.023 | H47: -0.009 | I47: -0.007 | J47: -0.006 | K47: 0.006 | L47: 0.004 | M47: 0.009 | N47: 0.014 | O47: 0.014 | P47: =(BB47-0.5*O47)/0.5 -> 0.02 | Q47: 0.018 | R47: 0.036 | S47: 0.026 | T47: =(BD47-0.5*S47)/0.5 -> 0.02 | U47: -0.002 | V47: -0.011 | W47: -0.003 | X47: =(BF47-0.5*W47)/0.5 -> -0.001 | Y47: 0.033 | Z47: =(BG47-0.5*Y47)/0.5 -> 0.043 | AA47: 0.071 | AB47: =(BH47-0.5*AA47)/0.5 -> 0.077 | AC47: 0.062 | AD47: =(BI47-0.5*AC47)/0.5 -> 0.058 | AE47: 0.031 | AF47: =(BJ47-0.5*AE47)/0.5 -> 0.029 | AG47: 0.022 | AH47: =(BK47-0.5*AG47)/0.5 -> 0.014 | AI47: 0.015 | AJ47: =(BL47-0.5*AI47)/0.5 -> 0.013 | AK47: 0.015 | AL47: =(BM47-0.5*AK47)/0.5 -> 0.015 | AM47: 0.016 | AX47: =AVERAGE(G47:H47) -> -0.016 | AY47: =AVERAGE(I47:J47) -> -0.0065 | AZ47: 0.005 | BA47: 0.012 | BB47: 0.017 | BC47: 0.031 | BD47: 0.023 | BE47: -0.006 | BF47: -0.002 | BG47: 0.038 | BH47: 0.074 | BI47: 0.06 | BJ47: 0.03 | BK47: 0.018 | BL47: 0.014 | BM47: 0.015 | BR47: =AVERAGE(AX47:AY47) -> -0.01125 | BS47: =AVERAGE(AZ47:BA47) -> 0.0085 | BT47: =AVERAGE(BB47:BC47) -> 0.024 | BU47: =AVERAGE(BD47:BE47) -> 0.0085 | BV47: =AVERAGE(BF47:BG47) -> 0.018 | BW47: =AVERAGE(BH47:BI47) -> 0.067 | BX47: =AVERAGE(BJ47:BK47) -> 0.024 | BY47: =AVERAGE(BL47:BM47) -> 0.0145
B48: Inflation / (deflation) excl. tobacco (%) | K48: -0.004 | L48: -0.007 | M48: 0 | N48: 0.007 | AC48: 0.064 | AD48: =(BI48-0.5*AC48)/0.5 -> -0.064 | AE48: 0.031 | AF48: =(BJ48-0.5*AE48)/0.5 -> 0.027 | AG48: 0.019 | AH48: =(BK48-0.5*AG48)/0.5 -> 0.011 | AI48: 0.01 | AJ48: =(BL48-0.5*AI48)/0.5 -> 0.01 | AK48: 0.011 | AL48: =(BM48-0.5*AK48)/0.5 -> 0.017 | AM48: 0.012 | BJ48: 0.029 | BK48: 0.015 | BL48: 0.01 | BM48: 0.014 | BX48: =AVERAGE(BJ48:BK48) -> 0.022 | BY48: =AVERAGE(BL48:BM48) -> 0.012
B49: Inflation / (deflation) excl. tobacco and fresh (%) | K49: -0.012 | L49: -0.011 | M49: -0.014 | N49: -0.009 | O49: 0.002 | P49: =(BB49-0.5*O49)/0.5 -> 0.006 | Q49: 0.026 | R49: 0.033 | S49: 0.008 | T49: =(BD49-0.5*S49)/0.5 -> 0.006 | U49: -0.008 | V49: -0.037 | W49: -0.008 | X49: =(BF49-0.5*W49)/0.5 -> 0.004 | Y49: 0.029 | Z49: =(BG49-0.5*Y49)/0.5 -> 0.043 | AA49: 0.067 | AB49: =(BH49-0.5*AA49)/0.5 -> 0.085 | AC49: 0.076 | AD49: =(BI49-0.5*AC49)/0.5 -> 0.078 | AE49: 0.063 | AF49: =(BJ49-0.5*AE49)/0.5 -> 0.033 | AG49: 0.033 | AH49: =(BK49-0.5*AG49)/0.5 -> 0.007 | AI49: 0.001 | AJ49: =(BL49-0.5*AI49)/0.5 -> 0.001 | AK49: -0.003 | AL49: =(BM49-0.5*AK49)/0.5 -> 0.011 | AM49: 0.009 | AZ49: -0.012 | BA49: -0.012 | BB49: 0.004 | BC49: 0.026 | BD49: 0.007 | BE49: -0.022 | BF49: -0.002 | BG49: 0.036 | BH49: 0.076 | BI49: 0.077 | BJ49: 0.048 | BK49: 0.02 | BL49: 0.001 | BM49: 0.004 | BS49: =AVERAGE(AZ49:BA49) -> -0.012 | BT49: =AVERAGE(BB49:BC49) -> 0.015 | BU49: =AVERAGE(BD49:BE49) -> -0.0075 | BV49: =AVERAGE(BF49:BG49) -> 0.017 | BW49: =AVERAGE(BH49:BI49) -> 0.0765 | BX49: =AVERAGE(BJ49:BK49) -> 0.034 | BY49: =AVERAGE(BL49:BM49) -> 0.0025
B51: # of stores
B52: Supermarkets | M52: 818 | O52: 824 | Q52: 825 | S52: 830 | U52: 831 | W52: 836 | Y52: 834 | AA52: 838 | AC52: 851 | AE52: 857 | AG52: 857 | AI52: 857 | AK52: 858 | AM52: 862
B54: Liquor Key Metrics
B55: Sales Productivity Measures
B56: Total Sales Growth % | K56: =K13 -> -0.038408779 | L56: =L13 -> -0.056451613 | M56: =M13 -> 0.043 | N56: =N13 -> -0.17905405 | O56: =O13 -> 0.035 | P56: =P13 -> 0.030982906 | Q56: =Q13 -> 0.061 | R56: =R13 -> 0.20301783 | ... AM56: =AM13 -> -0.011 | BD56: =AVERAGE(S56:T56) -> 0.15383938 | BE56: =AVERAGE(U56:V56) -> -0.047777651 | BF56: =AVERAGE(W56:X56) -> 0.02716819 | BG56: =AVERAGE(Y56:Z56) -> 0.022 | BH56: =AVERAGE(AA56:AB56) -> -0.0255 | BI56: =AVERAGE(AC56:AD56) -> 0.0049057623 | BJ56: =AVERAGE(AE56:AF56) -> 0.018408602 | BK56: =AVERAGE(AG56:AH56) -> -0.0115 | BL56: =AVERAGE(AI56:AJ56) -> 0.0070360598 | BM56: =AVERAGE(AK56:AL56) -> 0.0145 | BU56: =AVERAGE(BD56:BE56) -> 0.053030864 | BV56: =AVERAGE(BF56:BG56) -> 0.024584095 | BW56: =AVERAGE(BH56:BI56) -> -0.010297119 | BX56: =AVERAGE(BJ56:BK56) -> 0.0034543011 | BY56: =AVERAGE(BL56:BM56) -> 0.01076803
B57: Comparable Sales % | K57: =K23 -> 0.013 | L57: =L23 -> 0.009 | M57: =M23 -> 0.01 | N57: =N23 -> 0.014 | O57: =O23 -> 0.007 | P57: =P23 -> 0.023 | Q57: =Q23 -> 0.072 | R57: =R23 -> 0.206 | ... AM57: =AM23 -> -0.014 | BD57: =AVERAGE(S57:T57) -> 0.151 | BE57: =AVERAGE(U57:V57) -> -0.029 | BF57: =AVERAGE(W57:X57) -> 0.018 | BG57: =AVERAGE(Y57:Z57) -> 0.0235 | BH57: =AVERAGE(AA57:AB57) -> -0.023 | BI57: =AVERAGE(AC57:AD57) -> 0.013 | BJ57: =AVERAGE(AE57:AF57) -> 0.002 | BK57: =AVERAGE(AG57:AH57) -> -0.024 | BL57: =AVERAGE(AI57:AJ57) -> -0.013 | BM57: =AVERAGE(AK57:AL57) -> -0.013 | BU57: =AVERAGE(BD57:BE57) -> 0.061 | BV57: =AVERAGE(BF57:BG57) -> 0.02075 | BW57: =AVERAGE(BH57:BI57) -> -0.005 | BX57: =AVERAGE(BJ57:BK57) -> -0.011 | BY57: =AVERAGE(BL57:BM57) -> -0.013
B58: Implied Other Growth % | K58: =K56-K57 -> -0.051408779 | L58: =L56-L57 -> -0.065451613 | M58: =M56-M57 -> 0.033 | N58: =N56-N57 -> -0.19305405 | O58: =O56-O57 -> 0.028 | P58: =P56-P57 -> 0.007982906 | Q58: =Q56-Q57 -> -0.011 | R58: =R56-R57 -> -0.0029821674 | ... AM58: =AM56-AM57 -> 0.003 | BD58: =AVERAGE(S58:T58) -> 0.0028393782 | BE58: =AVERAGE(U58:V58) -> -0.018777651 | BF58: =AVERAGE(W58:X58) -> 0.0091681901 | BG58: =AVERAGE(Y58:Z58) -> -0.0015 | BH58: =AVERAGE(AA58:AB58) -> -0.0025 | BI58: =AVERAGE(AC58:AD58) -> -0.0080942377 | BJ58: =AVERAGE(AE58:AF58) -> 0.016408602 | BK58: =AVERAGE(AG58:AH58) -> 0.0125 | BL58: =AVERAGE(AI58:AJ58) -> 0.02003606 | BM58: =AVERAGE(AK58:AL58) -> 0.0275 | BU58: =AVERAGE(BD58:BE58) -> -0.0079691364 | BV58: =AVERAGE(BF58:BG58) -> 0.0038340951 | BW58: =AVERAGE(BH58:BI58) -> -0.0052971188 | BX58: =AVERAGE(BJ58:BK58) -> 0.014454301 | BY58: =AVERAGE(BL58:BM58) -> 0.02376803
A60: Liquor Density | B60: Sales Density per sqm | M60: 14282 | N60: =(BA60-0.5*M60)/0.5 -> 14426 | O60: 14381 | P60: =(BB60-0.5*O60)/0.5 -> 14359 | Q60: 14720 | R60: =(BC60-0.5*Q60)/0.5 -> 16156 | S60: 16023 | T60: =(BD60-0.5*S60)/0.5 -> 17183 | U60: 16632 | V60: =(BE60-0.5*U60)/0.5 -> 15942 | W60: 16265 | X60: =(BF60-0.5*W60)/0.5 -> 16365 | Y60: 16291 | Z60: =(BG60-0.5*Y60)/0.5 -> 16417 | AA60: 16123 | AB60: =(BH60-0.5*AA60)/0.5 -> 15935 | AC60: 16088 | AD60: =(BI60-0.5*AC60)/0.5 -> 16188 | AE60: 16137 | AF60: =(BJ60-0.5*AE60)/0.5 -> 16131 | AG60: 15983 | AH60: =(BK60-0.5*AG60)/0.5 -> 15737 | AI60: 15627 | AJ60: =(BL60-0.5*AI60)/0.5 -> 15751 | AK60: 15683 | AL60: =(BM60-0.5*AK60)/0.5 -> 15607 | AM60: 15610 | AZ60: =VLOOKUP($A60,Model!$1:$1048576,MATCH(Quarterly!AZ$3,Model!$3:$3,0),FALSE) -> 14161 | BA60: =VLOOKUP($A60,Model!$1:$1048576,MATCH(Quarterly!BA$3,Model!$3:$3,0),FALSE) -> 14354 | BB60: =VLOOKUP($A60,Model!$1:$1048576,MATCH(Quarterly!BB$3,Model!$3:$3,0),FALSE) -> 14370 | BC60: =VLOOKUP($A60,Model!$1:$1048576,MATCH(Quarterly!BC$3,Model!$3:$3,0),FALSE) -> 15438 | BD60: =VLOOKUP($A60,Model!$1:$1048576,MATCH(Quarterly!BD$3,Model!$3:$3,0),FALSE) -> 16603 | BE60: =VLOOKUP($A60,Model!$1:$1048576,MATCH(Quarterly!BE$3,Model!$3:$3,0),FALSE) -> 16287 | BF60: =VLOOKUP($A60,Model!$1:$1048576,MATCH(Quarterly!BF$3,Model!$3:$3,0),FALSE) -> 16315 | BG60: =VLOOKUP($A60,Model!$1:$1048576,MATCH(Quarterly!BG$3,Model!$3:$3,0),FALSE) -> 16354 | ... BM60: =VLOOKUP($A60,Model!$1:$1048576,MATCH(Quarterly!BM$3,Model!$3:$3,0),FALSE) -> 15645 | BS60: =VLOOKUP($A60,Model!$1:$1048576,MATCH(Quarterly!BS$3,Model!$3:$3,0),FALSE) -> 14354 | BT60: =VLOOKUP($A60,Model!$1:$1048576,MATCH(Quarterly!BT$3,Model!$3:$3,0),FALSE) -> 15438 | BU60: =VLOOKUP($A60,Model!$1:$1048576,MATCH(Quarterly!BU$3,Model!$3:$3,0),FALSE) -> 16287 | BV60: =VLOOKUP($A60,Model!$1:$1048576,MATCH(Quarterly!BV$3,Model!$3:$3,0),FALSE) -> 16354 | BW60: =VLOOKUP($A60,Model!$1:$1048576,MATCH(Quarterly!BW$3,Model!$3:$3,0),FALSE) -> 16138 | BX60: =VLOOKUP($A60,Model!$1:$1048576,MATCH(Quarterly!BX$3,Model!$3:$3,0),FALSE) -> 15823 | BY60: =VLOOKUP($A60,Model!$1:$1048576,MATCH(Quarterly!BY$3,Model!$3:$3,0),FALSE) -> 15645
B62: Online
A63: Liquor Online | B63: eCommerce Online Sales | U63: 22 | V63: =BE63-U63 -> -22 | W63: 40 | X63: =BF63-W63 -> 55 | Y63: 33 | Z63: =BG63-Y63 -> 37 | AA63: 41 | AB63: =BH63-AA63 -> 67 | AC63: 43 | AD63: =BI63-AC63 -> 52 | AE63: 54 | AF63: =BJ63-AE63 -> 70 | AG63: 44 | AH63: =BK63-AG63 -> 57 | AI63: 59 | AJ63: =BL63-AI63 -> 89 | AK63: 52 | AL63: =BM63-AK63 -> 69 | AM63: 63 | BF63: =VLOOKUP($A63,Model!$1:$1048576,MATCH(Quarterly!BF$3,Model!$3:$3,0),FALSE) -> 95 | BG63: =VLOOKUP($A63,Model!$1:$1048576,MATCH(Quarterly!BG$3,Model!$3:$3,0),FALSE) -> 70 | BH63: =VLOOKUP($A63,Model!$1:$1048576,MATCH(Quarterly!BH$3,Model!$3:$3,0),FALSE) -> 108 | BI63: =VLOOKUP($A63,Model!$1:$1048576,MATCH(Quarterly!BI$3,Model!$3:$3,0),FALSE) -> 95 | BJ63: =VLOOKUP($A63,Model!$1:$1048576,MATCH(Quarterly!BJ$3,Model!$3:$3,0),FALSE) -> 124 | BK63: =VLOOKUP($A63,Model!$1:$1048576,MATCH(Quarterly!BK$3,Model!$3:$3,0),FALSE) -> 101 | BL63: =VLOOKUP($A63,Model!$1:$1048576,MATCH(Quarterly!BL$3,Model!$3:$3,0),FALSE) -> 148 | BM63: =VLOOKUP($A63,Model!$1:$1048576,MATCH(Quarterly!BM$3,Model!$3:$3,0),FALSE) -> 121 | BV63: =VLOOKUP($A63,Model!$1:$1048576,MATCH(Quarterly!BV$3,Model!$3:$3,0),FALSE) -> 165 | BW63: =VLOOKUP($A63,Model!$1:$1048576,MATCH(Quarterly!BW$3,Model!$3:$3,0),FALSE) -> 203 | BX63: =VLOOKUP($A63,Model!$1:$1048576,MATCH(Quarterly!BX$3,Model!$3:$3,0),FALSE) -> 225 | BY63: =VLOOKUP($A63,Model!$1:$1048576,MATCH(Quarterly!BY$3,Model!$3:$3,0),FALSE) -> 269
B64: eCommerce Online Sales Growth % | Y64: =Y63/U63-1 -> 0.5 | Z64: =Z63/V63-1 -> -2.6818182 | AA64: =AA63/W63-1 -> 0.025 | AB64: =AB63/X63-1 -> 0.21818182 | AC64: =AC63/Y63-1 -> 0.3030303 | AD64: =AD63/Z63-1 -> 0.40540541 | AE64: =AE63/AA63-1 -> 0.31707317 | AF64: =AF63/AB63-1 -> 0.044776119 | ... AM64: =AM63/AI63-1 -> 0.06779661 | BH64: =BH63/BF63-1 -> 0.13684211 | BI64: =BI63/BG63-1 -> 0.35714286 | BJ64: =BJ63/BH63-1 -> 0.14814815 | BK64: =BK63/BI63-1 -> 0.063157895 | BL64: =BL63/BJ63-1 -> 0.19354839 | BM64: =BM63/BK63-1 -> 0.1980198 | BW64: =BW63/BV63-1 -> 0.23030303 | BX64: =BX63/BW63-1 -> 0.10837438 | BY64: =BY63/BX63-1 -> 0.19555556
