Workbook
Name \0: #REF!
Name \a: #REF!
Name \b: #REF!
Name \c: #REF!
Name \d: #REF!
Name \e: #REF!
Name \f: #REF!
Name \g: #REF!
Name \h: #REF!
Name \i: #REF!
Name \j: #REF!
Name \k: #REF!
Name \l: #REF!
Name \m: #REF!
Name \p: #REF!
Name \s: #REF!
Name \u: #REF!
Name \z: #REF!
Name _: #REF!
Name _.dbf: #REF!
Name _?: #REF!
Name _??????: #REF!
Name __?: #REF!
Name __??????: #REF!
Name ___________________2010: #REF!
Name __________________2010: #REF!
Name _________________2010: #REF!
Name ________________2010: #REF!
Name _______________2010: #REF!
Name _______________KY1: #REF!
Name ______________2010: #REF!
Name ______________KY1: #REF!
Name _____________2010: #REF!
Name _____________KY1: #REF!
Name ____________2010: #REF!
Name ____________dep08: #REF!
Name ____________KY1: #REF!
Name ____________to020831: #REF!
Name ____________x2: #REF!
Name ____________X4: #REF!
Name ___________2010: #REF!
Name ___________dep08: #REF!
Name ___________KY1: #REF!
Name ___________to020831: #REF!
Name ___________x2: #REF!
Name ___________X4: #REF!
Name __________2010: #REF!
Name __________dep08: #REF!
Name __________KY1: #REF!
Name __________to020831: #REF!
Name __________x2: #REF!
Name __________X4: #REF!
Name _________2010: #REF!
Name _________dep08: #REF!
Name _________KY1: #REF!
Name _________to020831: #REF!
Name _________x2: #REF!
Name _________X4: #REF!
Name ________2010: #REF!
Name ________dep08: #REF!

Sheet Cover
D8: Mixue (2097.HK)
D10: Michelle Cheng | G10: Xinyu Ruan | J10: Carol Chen | M10: Molly Dai
D11: 852 2978 6631 | G11: 852 2978 7347 | J11: 852 2978 7999 | M11: +852 3966-4000
D12: Michelle.Cheng@gs.com | G12: xinyu.ruan@gs.com | J12: carol.chen@gs.com | M12: molly.dai@gs.com
D13: Goldman Sachs (Asia) L.L.C. | G13: Goldman Sachs (Asia) L.L.C. | J13: Goldman Sachs (Asia) L.L.C. | M13: Goldman Sachs (Asia) L.L.C.
D15: Consolidated basis | L15: Published date: | N15: =G37 -> 45897
D21: Key statistics
D22: Rating | G22: Buy
D24: Ticker | G24: 2097.HK
D26: Currency | G26: HKD
D27: 12-m target price | G27: 579
D28: Price as of | E28: 45896 | G28: 460.4
D29: Upside/downside % | G29: 0.25760209
D31: Market cap. (USD mn) | G31: 22441.048
D32: ADS outstanding (mn) | G32: 379.6188
D34: M&A probability | G34: 3
D35: Valuation methodology | G35: P/E
D37: Current publication date | G37: 45897
D38: Previous publication date | G38: 45896

Sheet IS
B4: Rmb mn | C4: 43800 | D4: 44166 | E4: 44561 | F4: 44926 | G4: 45291 | H4: 45657 | I4: 46022 | J4: 46387 | K4: =EDATE(J4,12) -> 46752 | L4: RMB/HKD | M4: 45473 | N4: =EDATE(M4,6) -> 45656 | O4: 45838 | P4: =EDATE(O4,6) -> 46021
B5: Accounting standards: IFRS | C5: 2019 | D5: =C5+1 -> 2020 | E5: 2021 | F5: 2022 | G5: 2023 | H5: 2024 | I5: 2025E | J5: 2026E | K5: 2027E | L5: 1.09 | M5: 2024 | N5: 2024 | O5: 2025E | P5: 2025E
B6: Income statement
B7: Revenue | C7: 2566.03 | D7: 4679.9973 | E7: 10350.986 | F7: 13575.577 | G7: 20302.465 | H7: 24828.874 | I7: =Driver!I384 -> 32331.616 | J7: =Driver!J384 -> 37879.877 | K7: =Driver!K384 -> 43890.622 | M7: 10677.054 | N7: =H7-M7 -> 14151.82 | O7: 14874.809 | P7: =Driver!P384 -> 17456.807
B8: yoy | D8: =D7/C7-1 -> 0.82382798 | E8: =E7/D7-1 -> 1.2117504 | F8: =F7/E7-1 -> 0.31152501 | G8: =G7/F7-1 -> 0.49551397 | H8: =H7/G7-1 -> 0.22294874 | I8: =I7/H7-1 -> 0.30217812 | J8: =J7/I7-1 -> 0.17160479 | K8: =K7/J7-1 -> 0.15867912 | O8: =O7/M7-1 -> 0.39315667 | P8: =P7/N7-1 -> 0.23353798
A9: =B9 -> Cost of sales | B9: Cost of sales | E9: -7107.124 | F9: -9728.74 | G9: -14303.498 | H9: -16768.667 | I9: =Driver!I584 -> -22194.396 | J9: =Driver!J584 -> -26071.256 | K9: =Driver!K584 -> -30188.089 | M9: -7274.359 | N9: =H9-M9 -> -9494.308 | O9: -10168.436 | P9: =Driver!P584 -> -12025.96
B10: % of company sales | E10: =E9/E7 -> -0.68661324 | F10: =F9/F7 -> -0.71663547 | G10: =G9/G7 -> -0.70452026 | H10: =H9/H7 -> -0.67536961 | I10: =I9/I7 -> -0.68646107 | J10: =J9/J7 -> -0.68826137 | K10: =K9/K7 -> -0.68780272 | M10: =M9/M7 -> -0.68130769 | N10: =N9/N7 -> -0.67088954 | O10: =O9/O7 -> -0.68360111 | P10: =P9/P7 -> -0.68889801
A11: =B11 -> Selling and distribution expenses | B11: Selling and distribution expenses | E11: -405.766 | F11: -774.431 | G11: -1318.588 | H11: -1599.474 | I11: =I166 -> -2011.6705 | J11: =J166 -> -2292.487 | K11: =K166 -> -2603.5881 | M11: -651.491 | N11: =H11-M11 -> -947.983 | O11: -913.679 | P11: =P166 -> -1097.9915
B12: % of company sales | E12: =E11/E7 -> -0.03920071 | F12: =F11/F7 -> -0.057045899 | G12: =G11/G7 -> -0.064947187 | H12: =H11/H7 -> -0.064419917 | I12: =I11/I7 -> -0.062219917 | J12: =J11/J7 -> -0.060519917 | K12: =K11/K7 -> -0.059319917 | M12: =M11/M7 -> -0.061017861 | N12: =N11/N7 -> -0.066986649 | O12: =O11/O7 -> -0.061424587 | P12: =P11/P7 -> -0.062897611
A13: =B13 -> Administrative expenses | B13: Administrative expenses | E13: -374.665 | F13: -496.506 | G13: -610.622 | H13: -755.115 | I13: =I194 -> -942.67249 | J13: =J194 -> -1031.6104 | K13: =K194 -> -1116.3023 | M13: -279.515 | N13: =H13-M13 -> -475.6 | O13: -437.65 | P13: =P194 -> -505.02249
B14: % of company sales | E14: =E13/E7 -> -0.036196069 | F14: -0.0364 | G14: =G13/G7 -> -0.030076249 | H14: =H13/H7 -> -0.030412777 | I14: =I13/I7 -> -0.029156367 | J14: =J13/J7 -> -0.027233732 | K14: =K13/K7 -> -0.025433732 | M14: =M13/M7 -> -0.026179038 | N14: =N13/N7 -> -0.033606985 | O14: =O13/O7 -> -0.029422227 | P14: =P13/P7 -> -0.028929831
A15: =B15 -> Research and development expenses | B15: Research and development expenses | E15: -17.151 | F15: -32.304 | G15: -85 | H15: -104.87 | I15: =I220 -> -104.2278 | J15: =J220 -> -114.53782 | K15: =K220 -> -123.93445 | M15: -40.327 | N15: =H15-M15 -> -64.543 | O15: -41.037 | P15: =P220 -> -63.190803
B16: % of company sales | E16: =E15/E7 -> -0.0016569436 | F16: =F15/F7 -> -0.0023795674 | G16: =G15/G7 -> -0.0041866837 | H16: =H15/H7 -> -0.0042237115 | I16: =I15/I7 -> -0.0032237115 | J16: =J15/J7 -> -0.0030237115 | K16: =K15/K7 -> -0.0028237115 | M16: =M15/M7 -> -0.0037769782 | N16: =N15/N7 -> -0.0045607561 | O16: =O15/O7 -> -0.0027588253 | P16: =P15/P7 -> -0.0036198373
A18: =B18 -> Adjusted operating profit | B18: Adjusted operating profit | E18: =E7+E9+E11+E13+E15 -> 2446.28 | F18: =F7+F9+F11+F13+F15 -> 2543.596 | G18: =G7+G9+G11+G13+G15 -> 3984.757 | H18: =H7+H9+H11+H13+H15 -> 5600.748 | I18: =I7+I9+I11+I13+I15 -> 7078.6497 | J18: =J7+J9+J11+J13+J15 -> 8369.9858 | K18: =K7+K9+K11+K13+K15 -> 9858.7079 | M18: =M7+M9+M11+M13+M15 -> 2431.362 | N18: =N7+N9+N11+N13+N15 -> 3169.386 | O18: =O7+O9+O11+O13+O15 -> 3314.007 | P18: =P7+P9+P11+P13+P15 -> 3764.6427
B19: Operating Margin | E19: =E18/E7 -> 0.23633304 | F19: =F18/F7 -> 0.18736559 | G19: =G18/G7 -> 0.19626962 | H19: =H18/H7 -> 0.22557398 | I19: =I18/I7 -> 0.21893894 | J19: =J18/J7 -> 0.22096127 | K19: =K18/K7 -> 0.22461992 | M19: =M18/M7 -> 0.22771843 | N19: =N18/N7 -> 0.22395607 | O19: =O18/O7 -> 0.22279325 | P19: =P18/P7 -> 0.21565471
A21: =B21 -> EBITDA | B21: EBITDA | E21: =E18-E314-E316 -> 2504.716 | F21: =F18-F314-F316 -> 2651.578 | G21: =G18-G314-G316 -> 4149.061 | H21: =H18-H314-H316 -> 5920.925 | I21: =I18-I314-I316 -> 7292.5092 | J21: =J18-J314-J316 -> 8736.6541 | K21: =K18-K314-K316 -> 10279.973
A23: =B23 -> Other income and gains (net) | B23: Other income and gains (net) | E23: 135.181 | F23: 127.915 | G23: 247.632 | H23: 219.547 | I23: =I155 -> 363.963 | J23: =J155 -> 450.0968 | K23: =K155 -> 548.74908 | M23: 80.889 | N23: =H23-M23 -> 138.658 | O23: 158.602 | P23: =P155 -> 205.361
A24: =B24 -> Finance costs | B24: Finance costs | E24: -5.973 | F24: -9.19 | G24: -14.697 | H24: -6.367 | I24: =I353+I357 -> -3.0212545 | J24: =J353+J357 -> -3.0212545 | K24: =K353+K357 -> -3.0212545 | M24: -4.405 | N24: =H24-M24 -> -1.962 | O24: -2.072 | P24: =I24-O24 -> -0.94925453
A25: =B25 -> (Impairment losses)/reversal of impairment losses on financial assets | B25: (Impairment losses)/reversal of impairment losses on financial assets | E25: -1.787 | F25: -4.098 | G25: 1.638 | H25: -0.329 | M25: -3.077 | N25: =H25-M25 -> 2.748 | O25: -1.101 | P25: =I25-O25 -> 1.101
A26: =B26 -> Impairment of property, plant and equipment | B26: Impairment of property, plant and equipment | E26: -14.827 | F26: 0 | G26: -65.524 | H26: 0 | N26: =H26-M26 -> 0 | P26: =I26-O26 -> 0
A27: =B27 -> Share of (losses)/profits of an associate | B27: Share of (losses)/profits of an associate | E27: 0 | F27: -0.18 | G27: 0.196 | H27: -3.016 | M27: -3.016 | N27: =H27-M27 -> 0 | O27: -1.154 | P27: =I27-O27 -> 1.154
A29: =B29 -> Profit before tax | B29: Profit before tax | C29: 600.02287 | D29: 944.39943 | E29: =E7+E9+E23+E11+E13+E15+SUM(E24:E27) -> 2558.874 | F29: =F7+F9+F23+F11+F13+F15+SUM(F24:F27) -> 2658.043 | G29: =G7+G9+G23+G11+G13+G15+SUM(G24:G27) -> 4154.002 | H29: =H7+H9+H23+H11+H13+H15+SUM(H24:H27) -> 5810.583 | I29: =I7+I9+I23+I11+I13+I15+SUM(I24:I27) -> 7439.5915 | J29: =J7+J9+J23+J11+J13+J15+SUM(J24:J27) -> 8817.0613 | K29: =K7+K9+K23+K11+K13+K15+SUM(K24:K27) -> 10404.436 | M29: =M7+M9+M23+M11+M13+M15+SUM(M24:M27) -> 2501.753 | N29: =N7+N9+N23+N11+N13+N15+SUM(N24:N27) -> 3308.83 | O29: =O7+O9+O23+O11+O13+O15+SUM(O24:O27) -> 3468.282 | P29: =P7+P9+P23+P11+P13+P15+SUM(P24:P27) -> 3971.3095
A30: =B30 -> Income tax expense | B30: Income tax expense | C30: -158.30353 | D30: -313.57961 | E30: -646.932 | F30: -644.952 | G30: -967.397 | H30: -1356.38 | I30: =I29*I31 -> -1736.6438 | J30: =J29*J31 -> -2058.1903 | K30: =K29*K31 -> -2428.7354 | M30: -614.854 | N30: =H30-M30 -> -741.526 | O30: -750.068 | P30: =I30-O30 -> -986.57583
B31: Tax rate | C31: =C30/C29 -> -0.26382916 | D31: =D30/D29 -> -0.3320413 | E31: =E30/E29 -> -0.25281901 | F31: =F30/F29 -> -0.24264167 | G31: =G30/G29 -> -0.23288313 | H31: =H30/H29 -> -0.23343269 | I31: =H31 -> -0.23343269 | J31: =I31 -> -0.23343269 | K31: =J31 -> -0.23343269 | M31: =H31 -> -0.23343269 | N31: =N30/N29 -> -0.2241052 | O31: =I31 -> -0.23343269 | P31: =P30/P29 -> -0.24842582
A32: =B32 -> Profit for the year (Before Non-Controlling Interests) | B32: Profit for the year (Before Non-Controlling Interests) | C32: =C29+C30 -> 441.71934 | D32: =D29+D30 -> 630.81982 | E32: =E30+E29 -> 1911.942 | F32: =F30+F29 -> 2013.091 | G32: =G30+G29 -> 3186.605 | H32: =H30+H29 -> 4454.203 | I32: =I30+I29 -> 5702.9477 | J32: =J30+J29 -> 6758.871 | K32: =K30+K29 -> 7975.7003 | M32: =M30+M29 -> 1886.899 | N32: =N30+N29 -> 2567.304 | O32: =O30+O29 -> 2718.214 | P32: =P30+P29 -> 2984.7337
A33: =B33 -> Non-controlling interests | B33: Non-controlling interests | C33: 3.0481697 | D33: 1.1468928 | E33: -1.581 | F33: -16.376 | G33: -49.264 | H33: -17.699 | I33: -50 | J33: =I33*(1+J75) -> -54.476979 | K33: =J33*(1+K75) -> -61.146541 | M33: -2.441 | N33: =H33-M33 -> -15.258 | O33: -25.33 | P33: =I33-O33 -> -24.67
A34: =B34 -> Profit attributed to Owners of the parent | B34: Profit attributed to Owners of the parent | C34: =SUM(C32:C33) -> 444.76751 | D34: =SUM(D32:D33) -> 631.96671 | E34: =SUM(E32:E33) -> 1910.361 | F34: =SUM(F32:F33) -> 1996.715 | G34: =SUM(G32:G33) -> 3137.341 | H34: =SUM(H32:H33) -> 4436.504 | I34: =SUM(I32:I33) -> 5652.9477 | J34: =SUM(J32:J33) -> 6704.394 | K34: =SUM(K32:K33) -> 7914.5538 | M34: =SUM(M32:M33) -> 1884.458 | N34: =SUM(N32:N33) -> 2552.046 | O34: =SUM(O32:O33) -> 2692.884 | P34: =SUM(P32:P33) -> 2960.0637
B35: NPM | C35: =C34/C7 -> 0.17332904 | D35: =D34/D7 -> 0.1350357 | E35: =E34/E7 -> 0.18455836 | F35: =F34/F7 -> 0.14708141 | G35: =G34/G7 -> 0.15453005 | H35: =H34/H7 -> 0.17868325 | I35: =I34/I7 -> 0.17484272 | J35: =J34/J7 -> 0.17699091 | K35: =K34/K7 -> 0.18032448 | M35: =M34/M7 -> 0.17649606 | N35: =N34/N7 -> 0.18033341 | O35: =O34/O7 -> 0.18103654 | P35: =P34/P7 -> 0.16956501
B36: yoy | D36: =D34/C34-1 -> 0.42089226 | E36: =E34/D34-1 -> 2.0228823 | F36: =F34/E34-1 -> 0.045202975 | G36: =G34/F34-1 -> 0.57125128 | H36: =H34/G34-1 -> 0.41409684 | I36: =I34/H34-1 -> 0.27418969 | J36: =J34/I34-1 -> 0.18599966 | K36: =K34/J34-1 -> 0.18050248
B38: Adjusted NI after minority interest | C38: =C34-C40-C41-C42 -> 444.76751 | D38: =D34-D40-D41-D42 -> 631.96671 | E38: =E34-E40-E41-E42 -> 1946.0714 | F38: =F34-F40-F41-F42 -> 2024.9231 | G38: =G34-G40-G41-G42 -> 3186.6182 | H38: =H34-H40-H41-H42 -> 4493.5145 | I38: =I34-I40-I41-I42 -> 5684.209 | J38: =J34-J40-J41-J42 -> 6724.6898 | K38: =K34-K40-K41-K42 -> 7933.681 | M38: =M34-M40-M41-M42 -> 1898.22 | N38: =N34-N40-N41-N42 -> 2595.2945 | O38: =O34-O40-O41-O42 -> 2713.6991 | P38: =P34-P40-P41-P42 -> 2970.5098
B39: Adjusted NPM | C39: =C38/C7 -> 0.17332904 | D39: =D38/D7 -> 0.1350357 | E39: =E38/E7 -> 0.18800831 | F39: =F38/F7 -> 0.14915927 | G39: =G38/G7 -> 0.15695721 | H39: =H38/H7 -> 0.18097939 | I39: =I38/I7 -> 0.17580961 | J39: =J38/J7 -> 0.17752671 | K39: =K38/K7 -> 0.18076028 | M39: =M38/M7 -> 0.177785 | N39: =N38/N7 -> 0.18338945 | O39: =O38/O7 -> 0.1824359 | P39: =P38/P7 -> 0.17016341
B40: Equity-settled share-based payment expenses | E40: =E242 -> -22.554 | F40: =F242 -> -24.981 | G40: =G242 -> -16.427 | H40: =H242 -> -15.786 | I40: =I7*I92 -> -20.556184 | J40: =J7*J92 -> -20.295736 | K40: =K7*K92 -> -19.127183 | M40: -6.521 | N40: =H40-M40 -> -9.265 | O40: -9.266 | P40: =I40-O40 -> -11.290184
B41: Listing expenses, after tax | G41: =-10.9*(1+G31) -> -8.3615739 | H41: =-59.069*(1+H31) -> -45.280365 | I41: =O41 -> -3.0394394 | J41: 0 | K41: 0 | M41: =-9.179*(1+H31) -> -7.0363214 | N41: =H41-M41 -> -38.244043 | O41: =-3.965*(1+H31) -> -3.0394394 | P41: =I41-O41 -> 0
B42: Other one-offs incl. impairment, FX | E42: =(E25+E26+E152)*(1+E31) -> -13.156363 | F42: =(F25+F26+F152)*(1+F31) -> -3.2271038 | G42: =(G25+G26+G152)*(1+G31) -> -24.488672 | H42: =(H25+H26+H152)*(1+H31) -> 4.0559077 | I42: =(I25+I26+I152)*(1+I31) -> -7.6656731 | J42: =(J25+J26+J152)*(1+J31) -> 0 | K42: =(K25+K26+K152)*(1+K31) -> 0 | M42: =(M25+M26+M152)*(1+M31) -> -0.20467347 | N42: =H42-M42 -> 4.2605811 | O42: =(O25+O26+O152)*(1+O31) -> -8.5096637 | P42: =I42-O42 -> 0.84399061
B43: yoy | D43: =D38/C38-1 -> 0.42089226 | E43: =E38/D38-1 -> 2.079389 | F43: =F38/E38-1 -> 0.040518422 | G43: =G38/F38-1 -> 0.5736984 | H43: =H38/G38-1 -> 0.41012011 | I43: =I38/H38-1 -> 0.26498068 | J43: =J38/I38-1 -> 0.1830476 | K43: =K38/J38-1 -> 0.17978394
B44: Other comprehensive income | E44: =SUM(E45:E46) -> -0.181 | F44: =SUM(F45:F46) -> -1.035 | G44: =SUM(G45:G46) -> -0.809 | H44: =SUM(H45:H46) -> -4.107
B45: Exchange differences on translation of foreign operations | E45: -0.181 | F45: -1.035 | G45: 0.131 | H45: -3.237
B46: Changes in fair value of equity investments designated at fair value through other comprehensive income | E46: 0 | F46: 0 | G46: -0.94 | H46: -0.87
B48: EPS - Basic | H48: =H38/H54 -> 11.836912 | I48: =I38/I54 -> 14.973465 | J48: =J38/J54 -> 17.714322 | K48: =K38/K54 -> 20.899073 | M48: =M38/M54 -> 5.0003319 | N48: =N38/N54 -> 6.8365804 | O48: =O38/O54 -> 7.1484845 | P48: =P38/P54 -> 7.8249809
B49: EPS - Diluted | H49: =H38/H55 -> 11.836912 | I49: =I38/I55 -> 14.973465 | J49: =J38/J55 -> 17.714322 | K49: =K38/K55 -> 20.899073 | M49: =M38/M55 -> 5.0003319 | N49: =N38/N55 -> 6.8365804 | O49: =O38/O55 -> 7.1484845 | P49: =P38/P55 -> 7.8249809
B50: DPS | H50: =H58/H54 -> 0 | I50: =I58/I54 -> 0 | J50: =J58/J54 -> 0 | K50: =K58/K54 -> 0 | M50: =M58/M54 -> 0 | N50: =N58/N54 -> 0 | O50: =O58/O54 -> 0 | P50: =P58/P54 -> 0
B52: Offer shares | I52: =17.0599+379.6188-377.0599 -> 19.6188
B54: Weighted avg. adj. shares outstanding (mn) basic | H54: =I54 -> 379.6188 | I54: 379.6188 | J54: =AVERAGE(I56:J56) -> 379.6188 | K54: =AVERAGE(J56:K56) -> 379.6188 | M54: =INDEX($B54:$K54,MATCH(M$5,$B$5:$K$5,0)) -> 379.6188 | N54: =INDEX($B54:$K54,MATCH(N$5,$B$5:$K$5,0)) -> 379.6188 | O54: =INDEX($B54:$K54,MATCH(O$5,$B$5:$K$5,0)) -> 379.6188 | P54: =INDEX($B54:$K54,MATCH(P$5,$B$5:$K$5,0)) -> 379.6188
B55: Weighted avg. adj. shares outstanding (mn) diluted | H55: =H54 -> 379.6188 | I55: =AVERAGE(H57:I57) -> 379.6188 | J55: =AVERAGE(I57:J57) -> 379.6188 | K55: =AVERAGE(J57:K57) -> 379.6188 | M55: =INDEX($B55:$K55,MATCH(M$5,$B$5:$K$5,0)) -> 379.6188 | N55: =INDEX($B55:$K55,MATCH(N$5,$B$5:$K$5,0)) -> 379.6188 | O55: =INDEX($B55:$K55,MATCH(O$5,$B$5:$K$5,0)) -> 379.6188 | P55: =INDEX($B55:$K55,MATCH(P$5,$B$5:$K$5,0)) -> 379.6188
B56: Period end shares outstanding (mn) basic | H56: =H54 -> 379.6188 | I56: =H56 -> 379.6188 | J56: =I56 -> 379.6188 | K56: =J56 -> 379.6188 | M56: =INDEX($B56:$K56,MATCH(M$5,$B$5:$K$5,0)) -> 379.6188 | N56: =INDEX($B56:$K56,MATCH(N$5,$B$5:$K$5,0)) -> 379.6188 | O56: =INDEX($B56:$K56,MATCH(O$5,$B$5:$K$5,0)) -> 379.6188 | P56: =INDEX($B56:$K56,MATCH(P$5,$B$5:$K$5,0)) -> 379.6188
B57: Period end shares outstanding (mn) diluted | H57: =H55 -> 379.6188 | I57: =H57 -> 379.6188 | J57: =I57 -> 379.6188 | K57: =J57 -> 379.6188 | M57: =INDEX($B57:$K57,MATCH(M$5,$B$5:$K$5,0)) -> 379.6188 | N57: =INDEX($B57:$K57,MATCH(N$5,$B$5:$K$5,0)) -> 379.6188 | O57: =INDEX($B57:$K57,MATCH(O$5,$B$5:$K$5,0)) -> 379.6188 | P57: =INDEX($B57:$K57,MATCH(P$5,$B$5:$K$5,0)) -> 379.6188
B58: Dividend Declared | D58: =-CF!D58 -> 404.4 | E58: =-CF!E58 -> 104.4 | F58: =-CF!F58 -> 100 | G58: =G60*G34 -> 0 | H58: =H60*H34 -> 0 | I58: =I60*I34 -> 0 | J58: =J60*J34 -> 0 | K58: =K60*K34 -> 0 | M58: 0 | N58: =H58 -> 0 | O58: 0 | P58: =I58 -> 0
B59: Dividend declared before listing
B60: Dividend Payout Ratio | D60: =D58/D34 -> 0.63990712 | E60: =E58/E34 -> 0.054649357 | F60: =F58/F34 -> 0.05008226 | G60: 0 | H60: 0 | I60: 0 | J60: 0 | K60: 0 | M60: =M58/M34 -> 0 | N60: =N58/N34 -> 0 | O60: =O58/O34 -> 0 | P60: =P58/P34 -> 0
B62: yoy (%)
B63: Revenue | D63: =D7/C7-1 -> 0.82382798 | E63: =E7/D7-1 -> 1.2117504 | F63: =F7/E7-1 -> 0.31152501 | G63: =G7/F7-1 -> 0.49551397 | H63: =H7/G7-1 -> 0.22294874 | I63: =I7/H7-1 -> 0.30217812 | J63: =J7/I7-1 -> 0.17160479 | K63: =K7/J7-1 -> 0.15867912
B64: Average store count growth
B66: Cost of sales | F66: =F9/E9-1 -> 0.36887157 | G66: =G9/F9-1 -> 0.47023129 | H66: =H9/G9-1 -> 0.17234728 | I66: =I9/H9-1 -> 0.32356352 | J66: =J9/I9-1 -> 0.17467742 | K66: =K9/J9-1 -> 0.157907
B67: Other income and gains (net) | F67: =F23/E23-1 -> -0.053750157 | G67: =G23/F23-1 -> 0.93591057 | H67: =H23/G23-1 -> -0.11341426 | I67: =I23/H23-1 -> 0.65779083 | J67: =J23/I23-1 -> 0.23665535 | K67: =K23/J23-1 -> 0.21918015
B68: Selling and distribution expenses | F68: =F11/E11-1 -> 0.90856553 | G68: =G11/F11-1 -> 0.70265395 | H68: =H11/G11-1 -> 0.21302029 | I68: =I11/H11-1 -> 0.25770752 | J68: =J11/I11-1 -> 0.13959369 | K68: =K11/J11-1 -> 0.13570461
B69: Administrative expenses | F69: =F13/E13-1 -> 0.32519985 | G69: =G13/F13-1 -> 0.22983811 | H69: =H13/G13-1 -> 0.23663248 | I69: =I13/H13-1 -> 0.24838268 | J69: =J13/I13-1 -> 0.094346581 | K69: =K13/J13-1 -> 0.082096796
B70: Research and development expenses | F70: =F15/E15-1 -> 0.88350533 | G70: =G15/F15-1 -> 1.6312531 | H70: =H15/G15-1 -> 0.23376471 | I70: =I15/H15-1 -> -0.0061237463 | J70: =J15/I15-1 -> 0.09891809 | K70: =K15/J15-1 -> 0.082039588
B72: Gross profits | F72: =(F7+F9)/(E7+E9)-1 -> 0.18588183 | G72: =(G7+G9)/(F7+F9)-1 -> 0.55945443 | H72: =(H7+H9)/(G7+G9)-1 -> 0.34359916 | I72: =(I7+I9)/(H7+H9)-1 -> 0.25768737 | J72: =(J7+J9)/(I7+I9)-1 -> 0.16487759 | K72: =(K7+K9)/(J7+J9)-1 -> 0.16038382
B73: Operating profit | F73: =F18/E18-1 -> 0.039781219 | G73: =G18/F18-1 -> 0.56658408 | H73: =H18/G18-1 -> 0.40554317 | I73: =I18/H18-1 -> 0.26387578 | J73: =J18/I18-1 -> 0.18242689 | K73: =K18/J18-1 -> 0.17786436
B74: EBITDA | F74: =F21/E21-1 -> 0.058634192 | G74: =G21/F21-1 -> 0.56475163 | H74: =H21/G21-1 -> 0.42705181 | I74: =I21/H21-1 -> 0.23165032 | J74: =J21/I21-1 -> 0.19803129 | K74: =K21/J21-1 -> 0.17664875
B75: Non-controlling interests | F75: =F33/E33-1 -> 9.3580013 | G75: =G33/F33-1 -> 2.0083048 | H75: =H33/G33-1 -> -0.64073157 | I75: 0.5 | J75: =Driver!J460*0.5 -> 0.089539575 | K75: =Driver!K460*0.5 -> 0.122429
B76: Profit attributed to Owners of the parent | F76: =F34/E34-1 -> 0.045202975 | G76: =G34/F34-1 -> 0.57125128 | H76: =H34/G34-1 -> 0.41409684 | I76: =I34/H34-1 -> 0.27418969 | J76: =J34/I34-1 -> 0.18599966 | K76: =K34/J34-1 -> 0.18050248
B77: Adjusted NI after non-controlling interest - GS definition | F77: =F38/E38-1 -> 0.040518422 | G77: =G38/F38-1 -> 0.5736984 | H77: =H38/G38-1 -> 0.41012011 | I77: =I38/H38-1 -> 0.26498068 | J77: =J38/I38-1 -> 0.1830476 | K77: =K38/J38-1 -> 0.17978394
B79: As % of company sales
B80: Gross margin | E80: =1+E10 -> 0.31338676 | F80: =1+F10 -> 0.28336453 | G80: =1+G10 -> 0.29547974 | H80: =1+H10 -> 0.32463039 | I80: =1+I10 -> 0.31353893 | J80: =1+J10 -> 0.31173863 | K80: =1+K10 -> 0.31219728
B81: OP margin | E81: =E19 -> 0.23633304 | F81: =F19 -> 0.18736559 | G81: =G19 -> 0.19626962 | H81: =H19 -> 0.22557398 | I81: =I19 -> 0.21893894 | J81: =J19 -> 0.22096127 | K81: =K19 -> 0.22461992
B82: EBITDA margin | E82: =E21/E7 -> 0.24197849 | F82: =F21/F7 -> 0.19531973 | G82: =G21/G7 -> 0.20436243 | H82: =H21/H7 -> 0.23846933 | I82: =I21/I7 -> 0.2255535 | J82: =J21/J7 -> 0.23064104 | K82: =K21/K7 -> 0.23421799
B83: Net margin (Before non-controlling interest) | C83: =C32/C7 -> 0.17214114 | D83: =D32/D7 -> 0.13479064 | E83: =E32/E7 -> 0.1847111 | F83: =F32/F7 -> 0.14828769 | G83: =G32/G7 -> 0.15695656 | H83: =H32/H7 -> 0.17939609 | I83: =I32/I7 -> 0.17638919 | J83: =J32/J7 -> 0.17842907 | K83: =K32/K7 -> 0.18171764
B84: Net margin (After non-controlling interest) | C84: =C35 -> 0.17332904 | D84: =D35 -> 0.1350357 | E84: =E35 -> 0.18455836 | F84: =F35 -> 0.14708141 | G84: =G35 -> 0.15453005 | H84: =H35 -> 0.17868325 | I84: =I35 -> 0.17484272 | J84: =J35 -> 0.17699091 | K84: =K35 -> 0.18032448
B85: Adj. Net margin (After non-controlling interest) | E85: =E39 -> 0.18800831 | F85: =F39 -> 0.14915927 | G85: =G39 -> 0.15695721 | H85: =H39 -> 0.18097939 | I85: =I39 -> 0.17580961 | J85: =J39 -> 0.17752671 | K85: =K39 -> 0.18076028
B87: Cost of sales | E87: =E10 -> -0.68661324 | F87: =F10 -> -0.71663547 | G87: =G10 -> -0.70452026 | H87: =H10 -> -0.67536961 | I87: =I10 -> -0.68646107 | J87: =J10 -> -0.68826137 | K87: =K10 -> -0.68780272
B88: Other income and gains (net) | E88: =E23/E7 -> 0.013059722 | F88: =F23/F7 -> 0.0094224356 | G88: =G23/G7 -> 0.01219714 | H88: =H23/H7 -> 0.0088424066 | I88: =I23/I7 -> 0.011257186 | J88: =J23/J7 -> 0.011882214 | K88: =K23/K7 -> 0.01250265
B89: Selling and distribution expenses | E89: =E12 -> -0.03920071 | F89: =F12 -> -0.057045899 | G89: =G12 -> -0.064947187 | H89: =H12 -> -0.064419917 | I89: =I12 -> -0.062219917 | J89: =J12 -> -0.060519917 | K89: =K12 -> -0.059319917
B90: Administrative expenses | E90: =E14 -> -0.036196069 | F90: =F14 -> -0.0364 | G90: =G14 -> -0.030076249 | H90: =H14 -> -0.030412777 | I90: =I14 -> -0.029156367 | J90: =J14 -> -0.027233732 | K90: =K14 -> -0.025433732
B91: Research and development expenses | E91: =E16 -> -0.0016569436 | F91: =F16 -> -0.0023795674 | G91: =G16 -> -0.0041866837 | H91: =H16 -> -0.0042237115 | I91: =I16 -> -0.0032237115 | J91: =J16 -> -0.0030237115 | K91: =K16 -> -0.0028237115
B92: ESOP | E92: =E40/E7 -> -0.0021789229 | F92: =F40/F7 -> -0.0018401428 | G92: =G40/G7 -> -0.00080911357 | H92: =H40/H7 -> -0.00063579202 | I92: =H92 -> -0.00063579202 | J92: =I92+0.01% -> -0.00053579202 | K92: =J92+0.01% -> -0.00043579202
B94: Tax rate | C94: =C31 -> -0.26382916 | D94: =D31 -> -0.3320413 | E94: =E31 -> -0.25281901 | F94: =F31 -> -0.24264167 | G94: =G31 -> -0.23288313 | H94: =H31 -> -0.23343269 | I94: =I31 -> -0.23343269 | J94: =J31 -> -0.23343269 | K94: =K31 -> -0.23343269
B96: Other assumptions
B97: Sales breakdown
B98: Goods | E98: 9457.66 | F98: 12551.043 | G98: 19160.21 | H98: 23452.457 | I98: =Driver!I387 -> 30545.045 | J98: =Driver!J387 -> 36043.381 | K98: =Driver!K387 -> 41932.047 | M98: 9926.304 | N98: =H98-M98 -> 13526.153 | O98: 13843.184 | P98: =I98-O98 -> 16701.861
B99: Equipments | E99: 696.944 | F99: 748.387 | G99: 736.537 | H99: 756.372 | I99: =Driver!I391 -> 1017.6628 | J99: =Driver!J391 -> 914.4794 | K99: =Driver!K391 -> 885.73548 | M99: 457.894 | N99: =H99-M99 -> 298.478 | O99: 651.504 | P99: =I99-O99 -> 366.1588
B100: Franchise and related services | E100: 196.382 | F100: 276.147 | G100: 405.718 | H100: 620.045 | I100: =Driver!I392 -> 768.9089 | J100: =Driver!J392 -> 922.01627 | K100: =Driver!K392 -> 1072.8399 | M100: 292.856 | N100: =H100-M100 -> 327.189 | O100: 380.121 | P100: =I100-O100 -> 388.7879
B102: % breakdown
B103: Goods | E103: =E98/E$7 -> 0.91369653 | F103: =F98/F$7 -> 0.92453109 | G103: =G98/G$7 -> 0.94373811 | H103: =H98/H$7 -> 0.94456386 | I103: =I98/I$7 -> 0.94474227 | J103: =J98/J$7 -> 0.95151791 | K103: =K98/K$7 -> 0.95537599 | M103: =M98/M$7 -> 0.92968566 | N103: =N98/N$7 -> 0.95578894 | O103: =O98/O$7 -> 0.93064617 | P103: =P98/P$7 -> 0.95675345
B104: Equipments | E104: =E99/E$7 -> 0.06733117 | F104: =F99/F$7 -> 0.055127454 | G104: =G99/G$7 -> 0.036278206 | H104: =H99/H$7 -> 0.030463403 | I104: =I99/I$7 -> 0.031475779 | J104: =J99/J$7 -> 0.024141562 | K104: =K99/K$7 -> 0.020180518 | M104: =M99/M$7 -> 0.0428858 | N104: =N99/N$7 -> 0.021091139 | O104: =O99/O$7 -> 0.043799151 | P104: =P99/P$7 -> 0.02097513
B105: Franchise and related services | E105: =E100/E$7 -> 0.018972299 | F105: =F100/F$7 -> 0.020341456 | G105: =G100/G$7 -> 0.019983682 | H105: =H100/H$7 -> 0.024972739 | I105: =I100/I$7 -> 0.023781951 | J105: =J100/J$7 -> 0.02434053 | K105: =K100/K$7 -> 0.024443488 | M105: =M100/M$7 -> 0.02742854 | N105: =N100/N$7 -> 0.023119924 | O105: =O100/O$7 -> 0.025554681 | P105: =P100/P$7 -> 0.022271421
B107: yoy
B108: Goods | F108: =F98/E98-1 -> 0.32707699 | G108: =G98/F98-1 -> 0.52658309 | H108: =H98/G98-1 -> 0.22401879 | I108: =I98/H98-1 -> 0.30242408 | J108: =J98/I98-1 -> 0.18000748 | K108: =K98/J98-1 -> 0.16337717
B109: Equipments | F109: =F99/E99-1 -> 0.073812243 | G109: =G99/F99-1 -> -0.015834054 | H109: =H99/G99-1 -> 0.02693008 | I109: =I99/H99-1 -> 0.34545277 | J109: =J99/I99-1 -> -0.10139252 | K109: =K99/J99-1 -> -0.031432011
B110: Franchise and related services | F110: =F100/E100-1 -> 0.40617266 | G110: =G100/F100-1 -> 0.46921024 | H110: =H100/G100-1 -> 0.52826594 | I110: =I100/H100-1 -> 0.24008564 | J110: =J100/I100-1 -> 0.19912289 | K110: =K100/J100-1 -> 0.16358023
B112: Cost of sales
B113: % breakdown
B114: COGS
B115: Goods | E115: =E121-E98 -> -6483.793 | F115: =F121-F98 -> -9060.836 | G115: =G121-G98 -> -13652.209 | H115: =H121-H98 -> -16041.481 | I115: =I121-I98 -> -21228.806 | J115: =J121-J98 -> -25158.28 | K115: =K121-K98 -> -29268.569
B116: Equipments | E116: =E122-E99 -> -567.373 | F116: =F122-F99 -> -607.746 | G116: =G122-G99 -> -568.377 | H116: =H122-H99 -> -605.65759 | I116: =I122-I99 -> -814.88368 | J116: =J122-J99 -> -732.26057 | K116: =K122-K99 -> -709.24415
B117: Franchise and related services | E117: =E123-E100 -> -55.958 | F117: =F123-F100 -> -60.158 | G117: =G123-G100 -> -82.912 | H117: =H123-H100 -> -121.52882 | I117: =I123-I100 -> -150.70615 | J117: =J123-J100 -> -180.71519 | K117: =K123-K100 -> -210.27662
B118: Total | E118: =SUM(E115:E117) -> -7107.124 | F118: =SUM(F115:F117) -> -9728.74 | G118: =SUM(G115:G117) -> -14303.498 | H118: =SUM(H115:H117) -> -16768.667 | I118: =SUM(I115:I117) -> -22194.396 | J118: =SUM(J115:J117) -> -26071.256 | K118: =SUM(K115:K117) -> -30188.089 | M118: =M9 -> -7274.359 | N118: =N9 -> -9494.308 | O118: =O9 -> -10168.436 | P118: =P9 -> -12025.96
B120: GP
B121: Goods | E121: 2973.867 | F121: 3490.207 | G121: 5508.001 | H121: =Driver!H540 -> 7410.9764 | I121: =Driver!I540 -> 9316.2386 | J121: =Driver!J540 -> 10885.101 | K121: =Driver!K540 -> 12663.478
B122: Equipments | E122: 129.571 | F122: 140.641 | G122: 168.16 | H122: =Driver!H541 -> 150.71441 | I122: =Driver!I541 -> 202.77912 | J122: =Driver!J541 -> 182.21883 | K122: =Driver!K541 -> 176.49133
...

Sheet Driver
B2: Rmb mn | C2: 43830 | D2: =EOMONTH(C2,12) -> 44196 | E2: =EOMONTH(D2,12) -> 44561 | F2: =EOMONTH(E2,12) -> 44926 | G2: =EOMONTH(F2,12) -> 45291 | H2: =EOMONTH(G2,12) -> 45657 | I2: 45992 | J2: 46357 | K2: =EDATE(J2,12) -> 46722 | M2: 45473 | N2: =EDATE(M2,6) -> 45656 | O2: 45838 | P2: =EDATE(O2,6) -> 46021
B3: Accounting standards: IFRS | C3: 2019 | D3: =C3+1 -> 2020 | E3: =D3+1 -> 2021 | F3: =E3+1 -> 2022 | G3: =F3+1 -> 2023 | H3: =G3+1 -> 2024 | I3: 2025E | J3: 2026E | K3: 2027E | M3: 2024 | N3: 2024 | O3: 2025 | P3: 2025E
B4: Summary
B5: Total GMV (RMBbn) | E5: =E42/1000 -> 22.8 | F5: =F42/1000 -> 30.654187 | G5: =G42/1000 -> 47.848012 | H5: =H42/1000 -> 58.268246 | I5: =I42/1000 -> 78.146545 | J5: =J42/1000 -> 88.899978 | K5: =K42/1000 -> 103.57748
B6: ML China | F6: =F43/1000 -> 29.9 | G6: =G43/1000 -> 44.67 | H6: =H43/1000 -> 55.157208 | I6: =I43/1000 -> 74.867849 | J6: =J43/1000 -> 85.336029 | K6: =K43/1000 -> 99.167588
B7: Mixue | G7: =G44/1000 -> 42.74 | H7: =H44/1000 -> 52.50616 | I7: =I44/1000 -> 68.583306 | J7: =J44/1000 -> 75.50376 | K7: =K44/1000 -> 86.25536
B8: Lucky Cup | G8: =G45/1000 -> 1.93 | H8: =H45/1000 -> 2.651048 | I8: =I45/1000 -> 6.2845432 | J8: =J45/1000 -> 9.8322692 | K8: =K45/1000 -> 12.912228
B9: Overseas | F9: =F46/1000 -> 0.7541872 | G9: =G46/1000 -> 3.178012 | H9: =H46/1000 -> 3.1110382 | I9: =I46/1000 -> 3.2786957 | J9: =J46/1000 -> 3.5639492 | K9: =K46/1000 -> 4.4098947
G10: =G14/G11 -> 0.077199521
B11: Total store count (k) | E11: =E54/1000 -> 20.001 | F11: =F54/1000 -> 28.983 | G11: =G54/1000 -> 37.565 | H11: =H54/1000 -> 46.479 | I11: =I54/1000 -> 56.129 | J11: =J54/1000 -> 65.129 | K11: =K54/1000 -> 74.129
B12: ML China | E12: =E55/1000 -> 19.731 | F12: =F55/1000 -> 27.188 | G12: =G55/1000 -> 33.234 | H12: =H55/1000 -> 41.584 | I12: =I55/1000 -> 51.584 | J12: =J55/1000 -> 60.084 | K12: =K55/1000 -> 68.084
B13: Mixue | G13: =G56/1000 -> 30.334 | H13: =H56/1000 -> 37.684 | I13: =I56/1000 -> 43.084 | J13: =J56/1000 -> 48.584 | K13: =K56/1000 -> 54.084
B14: Lucky Cup | G14: =G57/1000 -> 2.9 | H14: =H57/1000 -> 3.9 | I14: =I57/1000 -> 8.5 | J14: =J57/1000 -> 11.5 | K14: =K57/1000 -> 14
B15: Overseas | E15: =E58/1000 -> 0.27 | F15: =F58/1000 -> 1.795 | G15: =G58/1000 -> 4.331 | H15: =H58/1000 -> 4.895 | I15: =I58/1000 -> 4.545 | J15: =J58/1000 -> 5.045 | K15: =K58/1000 -> 6.045
B17: Net store increase (k) | F17: =F11-E11 -> 8.982 | G17: =G11-F11 -> 8.582 | H17: =H11-G11 -> 8.914 | I17: =I11-H11 -> 9.65 | J17: =J11-I11 -> 9 | K17: =K11-J11 -> 9
B18: ML China | F18: =F12-E12 -> 7.457 | G18: =G12-F12 -> 6.046 | H18: =H12-G12 -> 8.35 | I18: =I12-H12 -> 10 | J18: =J12-I12 -> 8.5 | K18: =K12-J12 -> 8
B19: Mixue | H19: =H13-G13 -> 7.35 | I19: =I13-H13 -> 5.4 | J19: =J13-I13 -> 5.5 | K19: =K13-J13 -> 5.5
B20: Lucky Cup | H20: =H14-G14 -> 1 | I20: =I14-H14 -> 4.6 | J20: =J14-I14 -> 3 | K20: =K14-J14 -> 2.5
B21: Overseas | F21: =F15-E15 -> 1.525 | G21: =G15-F15 -> 2.536 | H21: =H15-G15 -> 0.564 | I21: =I15-H15 -> -0.35 | J21: =J15-I15 -> 0.5 | K21: =K15-J15 -> 1
B23: Average GMV per store (RMBk) | E23: =E307*1000 -> 1401.8 | F23: =F307*1000 -> 1251.6 | G23: =G307*1000 -> 1438 | H23: =H307*1000 -> 1386.6129 | I23: =I307*1000 -> 1523.2057 | J23: =J307*1000 -> 1466.2946 | K23: =K307*1000 -> 1487.5624
B24: ML China | F24: =F6*1000/AVERAGE(E55:F55)*1000 -> 1274.537 | G24: =G6*1000/AVERAGE(F55:G55)*1000 -> 1478.6005 | H24: =H6*1000/AVERAGE(G55:H55)*1000 -> 1474.4369 | I24: =I6*1000/AVERAGE(H55:I55)*1000 -> 1607.158 | J24: =J6*1000/AVERAGE(I55:J55)*1000 -> 1528.3882 | K24: =K6*1000/AVERAGE(J55:K55)*1000 -> 1547.4625
B25: Mixue | G25: =G331*1000 -> 1542.3478 | H25: =H331*1000 -> 1543.8902 | I25: =I331*1000 -> 1698.2792 | J25: =J331*1000 -> 1647.3308 | K25: =K331*1000 -> 1680.2774
B26: Lucky Cup | G26: =G332*1000 -> 772 | H26: =H332*1000 -> 779.72 | I26: =I332*1000 -> 1013.636 | J26: =J332*1000 -> 983.22692 | K26: =K332*1000 -> 1012.7237
B27: Overseas | F27: =F9*1000/AVERAGE(E58:F58)*1000 -> 730.44765 | G27: =G9*1000/AVERAGE(F58:G58)*1000 -> 1037.5488 | H27: =H9*1000/AVERAGE(G58:H58)*1000 -> 674.40673 | I27: =I9*1000/AVERAGE(H58:I58)*1000 -> 694.63893 | J27: =J9*1000/AVERAGE(I58:J58)*1000 -> 743.26365 | K27: =K9*1000/AVERAGE(J58:K58)*1000 -> 795.29211
B29: Total number of cups sold (bn) | E29: =E362/1000 -> 3.6 | F29: =F362/1000 -> 4.7 | G29: =G362/1000 -> 7.4 | H29: =H362/1000 -> 9.045284 | I29: =I362/1000 -> 12.039723 | J29: =J362/1000 -> 13.601441 | K29: =K362/1000 -> 15.789998
B30: ASP (RMB) | E30: =E351 -> 6.3333333 | F30: =F351 -> 6.5221675 | G30: =G351 -> 6.4659476 | H30: =H351 -> 6.4418372 | I30: =I351 -> 6.4907262 | J30: =J351 -> 6.5360707 | K30: =K351 -> 6.5596896
B31: Number of cups sold per day per store | E31: =E48*1000/E30/365*1000 -> 606.40231 | F31: =F48*1000/F30/365*1000 -> 525.75177 | G31: =G48*1000/G30/365*1000 -> 609.30374 | H31: =H48*1000/H30/365*1000 -> 589.72919 | I31: =I48*1000/I30/365*1000 -> 642.94289 | J31: =J48*1000/J30/365*1000 -> 614.62701 | K31: =K48*1000/K30/365*1000 -> 621.29669
B33: Total reported revenue (RMBmn) | E33: =E384 -> 10350.986 | F33: =F384 -> 13575.577 | G33: =G384 -> 20302.465 | H33: =H384 -> 24828.874 | I33: =I384 -> 32331.616 | J33: =J384 -> 37879.877 | K33: =K384 -> 43890.622
B34: By market
A35: ="Rev"&B35 -> RevML China | B35: ML China | E35: =E395 -> 10300.917 | F35: =F395 -> 13034.937 | G35: =G395 -> 18815.533 | H35: =H395 -> 23488.694 | I35: =I395 -> 30953.193 | J35: =J395 -> 36254.607 | K35: =K395 -> 41867.392
A36: ="Rev"&B36 -> RevOverseas | B36: Overseas | E36: =E401 -> 50.069 | F36: =F401 -> 540.64 | G36: =G401 -> 1486.932 | H36: =H401 -> 1340.1797 | I36: =I401 -> 1378.4231 | J36: =J401 -> 1625.2699 | K36: =K401 -> 2023.2302
B37: By revenues stream
B38: Goods | E38: =E387 -> 9457.66 | F38: =F387 -> 12551.043 | G38: =G387 -> 19160.21 | H38: =H387 -> 23452.457 | I38: =I387 -> 30545.045 | J38: =J387 -> 36043.381 | K38: =K387 -> 41932.047
B39: Equipments | E39: =E391 -> 696.944 | F39: =F391 -> 748.387 | G39: =G391 -> 736.537 | H39: =H391 -> 756.372 | I39: =I391 -> 1017.6628 | J39: =J391 -> 914.4794 | K39: =K391 -> 885.73548
B40: Franchise and related services | E40: =E392 -> 196.382 | F40: =F392 -> 276.147 | G40: =G392 -> 405.718 | H40: =H392 -> 620.045 | I40: =I392 -> 768.9089 | J40: =J392 -> 922.01627 | K40: =K392 -> 1072.8399
B42: Total GMV | E42: =E350 -> 22800 | F42: =F350 -> 30654.187 | G42: =G350 -> 47848.012 | H42: =H350 -> 58268.246 | I42: =I350 -> 78146.545 | J42: =J350 -> 88899.978 | K42: =K350 -> 103577.48
B43: ML China | E43: =E136 -> 22700 | F43: =F136 -> 29900 | G43: =G136 -> 44670 | H43: =H136 -> 55157.208 | I43: =I136 -> 74867.849 | J43: =J136 -> 85336.029 | K43: =K136 -> 99167.588
B44: Mixue | F44: =F137 -> 29150 | G44: =G137 -> 42740 | H44: =H137 -> 52506.16 | I44: =I137 -> 68583.306 | J44: =J137 -> 75503.76 | K44: =K137 -> 86255.36
B45: Lucky Cup | F45: =F138 -> 750 | G45: =G138 -> 1930 | H45: =H138 -> 2651.048 | I45: =I138 -> 6284.5432 | J45: =J138 -> 9832.2692 | K45: =K138 -> 12912.228
B46: Overseas | E46: =E139 -> 100 | F46: =F139 -> 754.1872 | G46: =G139 -> 3178.012 | H46: =H139 -> 3111.0382 | I46: =I139 -> 3278.6957 | J46: =J139 -> 3563.9492 | K46: =K139 -> 4409.8947
B48: GMV per store | E48: =E307 -> 1.4018 | F48: =F307 -> 1.2516 | G48: =G307 -> 1.438 | H48: =H307 -> 1.3866129 | I48: =I307 -> 1.5232057 | J48: =J307 -> 1.4662946 | K48: =K307 -> 1.4875624
B49: ML China | F49: =F330 -> 1.274537 | G49: =G330 -> 1.4786005 | H49: =H330 -> 1.4744369 | I49: =I330 -> 1.607158 | J49: =J330 -> 1.5283882 | K49: =K330 -> 1.5474625
B50: Mixue | F50: =F331 -> 1.3125014 | G50: =G331 -> 1.5423478 | H50: =H331 -> 1.5438902 | I50: =I331 -> 1.6982792 | J50: =J331 -> 1.6473308 | K50: =K331 -> 1.6802774
B51: Lucky Cup | F51: =F332 -> 0.6 | G51: =G332 -> 0.772 | H51: =H332 -> 0.77972 | I51: =I332 -> 1.013636 | J51: =J332 -> 0.98322692 | K51: =K332 -> 1.0127237
B52: Overseas | F52: =F333 -> 0.73044765 | G52: =G333 -> 1.0375488 | H52: =H333 -> 0.67440673 | I52: =I333 -> 0.69463893 | J52: =J333 -> 0.74326365 | K52: =K333 -> 0.79529211
B54: Total store count | D54: =E42*2/E307-E54 -> 12528.605 | E54: =E55+E58 -> 20001 | F54: =F55+F58 -> 28983 | G54: =G55+G58 -> 37565 | H54: =H55+H58 -> 46479 | I54: =I55+I58 -> 56129 | J54: =J55+J58 -> 65129 | K54: =K55+K58 -> 74129
B55: ML China | E55: =E187 -> 19731 | F55: =F187 -> 27188 | G55: =G187 -> 33234 | H55: =H187 -> 41584 | I55: =I187 -> 51584 | J55: =J187 -> 60084 | K55: =K187 -> 68084
B56: Mixue | F56: =F188 -> 25088 | G56: =G188 -> 30334 | H56: =H188 -> 37684 | I56: =I188 -> 43084 | J56: =J188 -> 48584 | K56: =K188 -> 54084
B57: Lucky Cup | F57: =F189 -> 2100 | G57: =G189 -> 2900 | H57: =H189 -> 3900 | I57: =I189 -> 8500 | J57: =J189 -> 11500 | K57: =K189 -> 14000
B58: Overseas | E58: =E190 -> 270 | F58: =F190 -> 1795 | G58: =G190 -> 4331 | H58: =H190 -> 4895 | I58: =I190 -> 4545 | J58: =J190 -> 5045 | K58: =K190 -> 6045
B60: Net store increase | F60: =F54-E54 -> 8982 | G60: =G54-F54 -> 8582 | H60: =H54-G54 -> 8914 | I60: =I54-H54 -> 9650 | J60: =J54-I54 -> 9000 | K60: =K54-J54 -> 9000
B61: ML China | F61: =F55-E55 -> 7457 | G61: =G55-F55 -> 6046 | H61: =H55-G55 -> 8350 | I61: =I55-H55 -> 10000 | J61: =J55-I55 -> 8500 | K61: =K55-J55 -> 8000
B62: Mixue | G62: =G56-F56 -> 5246 | H62: =H56-G56 -> 7350 | I62: =I56-H56 -> 5400 | J62: =J56-I56 -> 5500 | K62: =K56-J56 -> 5500
B63: Lucky Cup | G63: =G57-F57 -> 800 | H63: =H57-G57 -> 1000 | I63: =I57-H57 -> 4600 | J63: =J57-I57 -> 3000 | K63: =K57-J57 -> 2500
B64: Overseas | F64: =F58-E58 -> 1525 | G64: =G58-F58 -> 2536 | H64: =H58-G58 -> 564 | I64: =I58-H58 -> -350 | J64: =J58-I58 -> 500 | K64: =K58-J58 -> 1000
B66: % breakdown
B67: Total GMV
B68: ML China | E68: =E43/E$42 -> 0.99561404 | F68: =F43/F$42 -> 0.97539693 | G68: =G43/G$42 -> 0.93358111 | H68: =H43/H$42 -> 0.94660834 | I68: =I43/I$42 -> 0.95804426 | J68: =J43/J$42 -> 0.95991057 | K68: =K43/K$42 -> 0.95742419
B69: Mixue | F69: =F44/F$42 -> 0.95093045 | G69: =G44/G$42 -> 0.89324505 | H69: =H44/H$42 -> 0.90111104 | I69: =I44/I$42 -> 0.87762429 | J69: =J44/J$42 -> 0.84931134 | K69: =K44/K$42 -> 0.8327617
B70: Lucky Cup | F70: =F45/F$42 -> 0.024466478 | G70: =G45/G$42 -> 0.040336054 | H70: =H45/H$42 -> 0.045497302 | I70: =I45/I$42 -> 0.080419975 | J70: =J45/J$42 -> 0.11059923 | K70: =K45/K$42 -> 0.1246625
B71: Overseas | E71: =E46/E$42 -> 0.0043859649 | F71: =F46/F$42 -> 0.024603073 | G71: =G46/G$42 -> 0.066418893 | H71: =H46/H$42 -> 0.053391657 | I71: =I46/I$42 -> 0.041955735 | J71: =J46/J$42 -> 0.040089427 | K71: =K46/K$42 -> 0.042575805
B73: Total store count
B74: ML China | E74: =E55/E$54 -> 0.98650067 | F74: =F55/F$54 -> 0.93806714 | G74: =G55/G$54 -> 0.88470651 | H74: =H55/H$54 -> 0.89468362 | I74: =I55/I$54 -> 0.91902582 | J74: =J55/J$54 -> 0.92253835 | K74: =K55/K$54 -> 0.91845297
B75: Mixue | F75: =F56/F$54 -> 0.86561088 | G75: =G56/G$54 -> 0.80750699 | H75: =H56/H$54 -> 0.81077476 | I75: =I56/I$54 -> 0.76758895 | J75: =J56/J$54 -> 0.7459657 | K75: =K56/K$54 -> 0.72959301
B76: Lucky Cup | F76: =F57/F$54 -> 0.072456267 | G76: =G57/G$54 -> 0.077199521 | H76: =H57/H$54 -> 0.083908862 | I76: =I57/I$54 -> 0.15143687 | J76: =J57/J$54 -> 0.17657265 | K76: =K57/K$54 -> 0.18885996
B77: Overseas | E77: =E58/E$54 -> 0.013499325 | F77: =F58/F$54 -> 0.061932857 | G77: =G58/G$54 -> 0.11529349 | H77: =H58/H$54 -> 0.10531638 | I77: =I58/I$54 -> 0.080974184 | J77: =J58/J$54 -> 0.077461653 | K77: =K58/K$54 -> 0.081547033
B79: Total Reported sales
B80: By market
B81: ML China | E81: =E35/E$33 -> 0.99516288 | F81: =F35/F$33 -> 0.96017554 | G81: =G35/G$33 -> 0.92676101 | H81: =H35/H$33 -> 0.94602334 | I81: =I35/I$33 -> 0.95736609 | J81: =J35/J$33 -> 0.95709411 | K81: =K35/K$33 -> 0.9539029
B82: Overseas | E82: =E36/E$33 -> 0.0048371237 | F82: =F36/F$33 -> 0.039824458 | G82: =G36/G$33 -> 0.073238988 | H82: =H36/H$33 -> 0.053976662 | I82: =I36/I$33 -> 0.042633906 | J82: =J36/J$33 -> 0.042905893 | K82: =K36/K$33 -> 0.046097097
B83: By revenues stream
B84: Goods | E84: =E38/E$33 -> 0.91369653 | F84: =F38/F$33 -> 0.92453109 | G84: =G38/G$33 -> 0.94373811 | H84: =H38/H$33 -> 0.94456386 | I84: =I38/I$33 -> 0.94474227 | J84: =J38/J$33 -> 0.95151791 | K84: =K38/K$33 -> 0.95537599
B85: Equipments | E85: =E39/E$33 -> 0.06733117 | F85: =F39/F$33 -> 0.055127454 | G85: =G39/G$33 -> 0.036278206 | H85: =H39/H$33 -> 0.030463403 | I85: =I39/I$33 -> 0.031475779 | J85: =J39/J$33 -> 0.024141562 | K85: =K39/K$33 -> 0.020180518
B86: Franchise and related services | E86: =E40/E$33 -> 0.018972299 | F86: =F40/F$33 -> 0.020341456 | G86: =G40/G$33 -> 0.019983682 | H86: =H40/H$33 -> 0.024972739 | I86: =I40/I$33 -> 0.023781951 | J86: =J40/J$33 -> 0.02434053 | K86: =K40/K$33 -> 0.024443488
B87: yoy
B88: Total GMV | F88: =F42/E42-1 -> 0.34448189 | G88: =G42/F42-1 -> 0.56089645 | H88: =H42/G42-1 -> 0.21777779 | I88: =I42/H42-1 -> 0.34115148 | J88: =J42/I42-1 -> 0.137606 | K88: =K42/J42-1 -> 0.16510133
B89: ML China | F89: =F43/E43-1 -> 0.31718062 | G89: =G43/F43-1 -> 0.49397993 | H89: =H43/G43-1 -> 0.23477072 | I89: =I43/H43-1 -> 0.35735385 | J89: =J43/I43-1 -> 0.1398221 | K89: =K43/J43-1 -> 0.16208347
B90: Mixue | G90: =G44/F44-1 -> 0.46620926 | H90: =H44/G44-1 -> 0.22850164 | I90: =I44/H44-1 -> 0.30619542 | J90: =J44/I44-1 -> 0.1009058 | K90: =K44/J44-1 -> 0.14239822
B91: Lucky Cup | G91: =G45/F45-1 -> 1.5733333 | H91: =H45/G45-1 -> 0.3736 | I91: =I45/H45-1 -> 1.3705882 | J91: =J45/I45-1 -> 0.56451613 | K91: =K45/J45-1 -> 0.31325
B92: Overseas | F92: =F46/E46-1 -> 6.541872 | G92: =G46/F46-1 -> 3.2138238 | H92: =H46/G46-1 -> -0.02107411 | I92: =I46/H46-1 -> 0.053891177 | J92: =J46/I46-1 -> 0.087002119 | K92: =K46/J46-1 -> 0.23736184
B94: Total Reported sales | F94: =F33/E33-1 -> 0.31152501 | G94: =G33/F33-1 -> 0.49551397 | H94: =H33/G33-1 -> 0.22294874 | I94: =I33/H33-1 -> 0.30217812 | J94: =J33/I33-1 -> 0.17160479 | K94: =K33/J33-1 -> 0.15867912
B95: ML China | F95: =F35/E35-1 -> 0.26541521 | G95: =G35/F35-1 -> 0.44346942 | H95: =H35/G35-1 -> 0.2483672 | I95: =I35/H35-1 -> 0.31779114 | J95: =J35/I35-1 -> 0.17127194 | K95: =K35/J35-1 -> 0.15481578
B96: Mixue
B97: Lucky Cup
B98: Overseas | F98: =F36/E36-1 -> 9.7978989 | G98: =G36/F36-1 -> 1.7503181 | H98: =H36/G36-1 -> -0.098694672 | I98: =I36/H36-1 -> 0.028535987 | J98: =J36/I36-1 -> 0.17907915 | K98: =K36/J36-1 -> 0.24485799
B100: Total store count | F100: =F54/E54-1 -> 0.44907755 | G100: =G54/F54-1 -> 0.29610461 | H100: =H54/G54-1 -> 0.23729535 | I100: =I54/H54-1 -> 0.20762065 | J100: =J54/I54-1 -> 0.16034492 | K100: =K54/J54-1 -> 0.13818729
B101: ML China | F101: =F55/E55-1 -> 0.3779332 | G101: =G55/F55-1 -> 0.22237752 | H101: =H55/G55-1 -> 0.25124872 | I101: =I55/H55-1 -> 0.24047711 | J101: =J55/I55-1 -> 0.16477978 | K101: =K55/J55-1 -> 0.13314693
B102: Mixue | F102: =F56/E56-1 -> #DIV/0! | G102: =G56/F56-1 -> 0.20910395 | H102: =H56/G56-1 -> 0.24230237 | I102: =I56/H56-1 -> 0.14329689 | J102: =J56/I56-1 -> 0.1276576 | K102: =K56/J56-1 -> 0.11320599
B103: Lucky Cup | F103: =F57/E57-1 -> #DIV/0! | G103: =G57/F57-1 -> 0.38095238 | H103: =H57/G57-1 -> 0.34482759 | I103: =I57/H57-1 -> 1.1794872 | J103: =J57/I57-1 -> 0.35294118 | K103: =K57/J57-1 -> 0.2173913
B104: Overseas | F104: =F58/E58-1 -> 5.6481481 | G104: =G58/F58-1 -> 1.4128134 | H104: =H58/G58-1 -> 0.13022397 | I104: =I58/H58-1 -> -0.071501532 | J104: =J58/I58-1 -> 0.110011 | K104: =K58/J58-1 -> 0.19821606
B106: Total store productivity | F106: =(1+F88)/(1+F100) -> 0.92781915 | G106: =(1+G88)/(1+G100) -> 1.2042982 | H106: =(1+H88)/(1+H100) -> 0.98422562 | I106: =(1+I88)/(1+I100) -> 1.1105735 | J106: =(1+J88)/(1+J100) -> 0.98040331 | K106: =(1+K88)/(1+K100) -> 1.0236464
B107: ML China | F107: =(1+F89)/(1+F101) -> 0.95591036 | G107: =(1+G89)/(1+G101) -> 1.2221919 | H107: =(1+H89)/(1+H101) -> 0.98683076 | I107: =(1+I89)/(1+I101) -> 1.0942192 | J107: =(1+J89)/(1+J101) -> 0.97857305 | K107: =(1+K89)/(1+K101) -> 1.0255364
B108: Mixue
B109: Lucky Cup
B110: Overseas | F110: =(1+F92)/(1+F104) -> 1.134432 | G110: =(1+G92)/(1+G104) -> 1.7464359 | H110: =(1+H92)/(1+H104) -> 0.86613443 | I110: =(1+I92)/(1+I104) -> 1.1350489 | J110: =(1+J92)/(1+J104) -> 0.97927148 | K110: =(1+K92)/(1+K104) -> 1.0326701
B112: GMV per store | G112: =G48/F48-1 -> 0.14892937 | H112: =H48/G48-1 -> -0.035735133 | I112: =I48/H48-1 -> 0.098508253 | J112: =J48/I48-1 -> -0.037362681 | K112: =K48/J48-1 -> 0.014504426
B113: ML China | G113: =G49/F49-1 -> 0.16010798 | H113: =H49/G49-1 -> -0.0028159454 | I113: =I49/H49-1 -> 0.090014819 | J113: =J49/I49-1 -> -0.049011847 | K113: =K49/J49-1 -> 0.012479998
B114: Mixue | G114: =G50/F50-1 -> 0.17512088 | H114: =H50/G50-1 -> 0.001 | I114: =I50/H50-1 -> 0.1 | J114: =J50/I50-1 -> -0.03 | K114: =K50/J50-1 -> 0.02
B115: Lucky Cup | G115: =G51/F51-1 -> 0.28666667 | H115: =H51/G51-1 -> 0.01 | I115: =I51/H51-1 -> 0.3 | J115: =J51/I51-1 -> -0.03 | K115: =K51/J51-1 -> 0.03
B116: Overseas | G116: =G52/F52-1 -> 0.4204287 | H116: =H52/G52-1 -> -0.35 | I116: =I52/H52-1 -> 0.03 | J116: =J52/I52-1 -> 0.07 | K116: =K52/J52-1 -> 0.07
...

Sheet BS
A1: Rmb mn | D1: 44561 | E1: 44926 | F1: 45291 | G1: 45657 | H1: 46022 | I1: 46387 | J1: 46752 | L1: =IS!O4 -> 45838
A2: Accounting standards: IFRS | D2: 2021 | E2: 2022 | F2: 2023 | G2: 2024 | H2: 2025E | I2: 2026E | J2: 2027E | L2: 1H25
A3: Balance Sheet
A4: Assets
A5: Inventories | D5: 1251.915 | E5: 1541.156 | F5: 2231.714 | G5: 2215.352 | H5: =H70 -> 3670.6223 | I5: =I70 -> 3243.4988 | J5: =J70 -> 4762.4104 | L5: 2991.706
A6: Trade receivables | D6: 2.03 | E6: 15.41 | F6: 28.473 | G6: 25.624 | H6: =H82 -> 29.101908 | I6: =I82 -> 35.18338 | J6: =J82 -> 39.253004 | L6: 34.75
A7: Prepayments, other receivables and other assets | D7: 181.892 | E7: 304.539 | F7: 404.428 | G7: 512.505 | H7: =H86 -> 673.09064 | I7: =I86 -> 786.55438 | J7: =J86 -> 907.08404 | L7: 485.2
A8: Financial assets at fair value through profit or loss | D8: 900.237 | E8: 1865.676 | F8: 746.046 | G8: 3491.643 | H8: =G8 -> 3491.643 | I8: =H8 -> 3491.643 | J8: =I8 -> 3491.643 | L8: 5113.517
A9: Restricted cash and time deposits | D9: 61.865 | E9: 65.146 | F9: 115.62 | G9: 1315.804 | H9: =G9 -> 1315.804 | I9: =H9 -> 1315.804 | J9: =I9 -> 1315.804 | L9: 1350.469
A10: Cash and cash equivalents | D10: 2675.827 | E10: 2764.138 | F10: 5621.904 | G10: 4335.123 | H10: =CF!H69 -> 10782.547 | I10: =CF!I69 -> 16541.122 | J10: =CF!J69 -> 22068.983 | L10: 8405.472
A12: Total current assets | D12: =SUM(D5:D10) -> 5073.766 | E12: =SUM(E5:E10) -> 6556.065 | F12: =SUM(F5:F10) -> 9148.185 | G12: =SUM(G5:G10) -> 11896.051 | H12: =SUM(H5:H10) -> 19962.809 | I12: =SUM(I5:I10) -> 25413.805 | J12: =SUM(J5:J10) -> 32585.177 | L12: =SUM(L5:L10) -> 18381.114
D13: =D10+D21+D9 -> 2737.692 | E13: =E10+E21+E9 -> 2829.284 | F13: =F10+F21+F9 -> 6037.524 | G13: =G10+G21+G9 -> 7617.853
A14: Property, plant and equipment | D14: 1033.497 | E14: 1701.086 | F14: 3390.053 | G14: 5317.826 | H14: =H126 -> 7434.5976 | I14: =I126 -> 9398.5602 | J14: =J126 -> 11307.926 | L14: 5382.169
A15: Investment properties | H15: =L15 -> 17.529 | I15: =H15 -> 17.529 | J15: =I15 -> 17.529 | L15: 17.529
A16: Right-of-use assets | D16: 166.031 | E16: 445.56 | F16: 426.986 | G16: 382.189 | H16: =H164 -> 340.38708 | I16: =I164 -> 285.15739 | J16: =J164 -> 225.13402 | L16: 393.8
A17: Other intangible assets | D17: 9.029 | E17: 20.591 | F17: 25.624 | G17: 41.964 | H17: =H174 -> 53.674 | I17: =I174 -> 65.384 | J17: =J174 -> 77.094 | L17: 41.773
A18: Investment in an associate | D18: 0 | E18: 2.82 | F18: 3.016 | G18: 0 | H18: =L18 -> 103.846 | I18: =H18 -> 103.846 | J18: =I18 -> 103.846 | L18: 103.846
A19: Equity investment designated at fair value through other comprehensive income | D19: 11.4 | E19: 11.4 | F19: 10.46 | G19: 6.59 | H19: =G19 -> 6.59 | I19: =H19 -> 6.59 | J19: =I19 -> 6.59 | L19: 6.59
A20: Deferred tax assets | D20: 23.613 | E20: 41.598 | F20: 111.889 | G20: 76.005 | H20: =G20 -> 76.005 | I20: =H20 -> 76.005 | J20: =I20 -> 76.005 | L20: 106.716
A21: Restricted cash and time deposits | D21: 0 | E21: 0 | F21: 300 | G21: 1966.926 | H21: =G21 -> 1966.926 | I21: =H21 -> 1966.926 | J21: =I21 -> 1966.926 | L21: 2742.349
A22: Other non-current assets | D22: 999.047 | E22: 1166.236 | F22: 1177.353 | G22: =G24-SUM(G14:G21) -> 95.771 | H22: =G22 -> 95.771 | I22: =H22 -> 95.771 | J22: =I22 -> 95.771 | L22: =L24-SUM(L14:L21) -> 117.018
A24: Total non-current assets | D24: =SUM(D14:D22) -> 2242.617 | E24: =SUM(E14:E22) -> 3389.291 | F24: =SUM(F14:F22) -> 5445.381 | G24: 7887.271 | H24: =SUM(H14:H22) -> 10095.326 | I24: =SUM(I14:I22) -> 12015.769 | J24: =SUM(J14:J22) -> 13876.821 | L24: 8911.79
A26: Total assets | D26: =D12+D24 -> 7316.383 | E26: =E12+E24 -> 9945.356 | F26: =F12+F24 -> 14593.566 | G26: =G12+G24 -> 19783.322 | H26: =H12+H24 -> 30058.134 | I26: =I12+I24 -> 37429.574 | J26: =J12+J24 -> 46461.998 | L26: =L12+L24 -> 27292.904
A28: Liabilities
A29: Trade payables | D29: 596.681 | E29: 881.806 | F29: 1316.78 | G29: 1767.263 | H29: =H95 -> 2314.6638 | I29: =I95 -> 2480.2835 | J29: =J95 -> 3071.8195 | L29: 2507.498
A30: Other payables and accruals | D30: 600.753 | E30: 910.196 | F30: 1571.615 | G30: 2043.625 | H30: =H100 -> 2683.9638 | I30: =I100 -> 3136.4029 | J30: =J100 -> 3617.0176 | L30: 2077.385
A31: Contract liabilities | D31: 305.817 | E31: 198.305 | F31: 259.271 | G31: 359.636 | H31: =H108 -> 250.65548 | I31: =I108 -> 297.8311 | J31: =J108 -> 345.97955 | L31: 535.386
A32: Interest-bearing bank borrowings | D32: 30.03 | E32: 140.088 | F32: 259.748 | G32: 0 | H32: =G32 -> 0 | I32: =H32 -> 0 | J32: =I32 -> 0 | L32: 0
A33: Lease liabilities | D33: 50.321 | E33: 78.813 | F33: 72.065 | G33: 52.004 | H33: =G33 -> 52.004 | I33: =H33 -> 52.004 | J33: =I33 -> 52.004 | L33: 63.719
A34: Tax payables | D34: 122.576 | E34: 129.445 | F34: 254.834 | G34: 294.31 | H34: =G34*IS!I29/IS!H29 -> 376.82039 | I34: =H34*IS!J29/IS!I29 -> 446.59018 | J34: =I34*IS!K29/IS!J29 -> 526.99178 | L34: 506.549
A36: Total current liabilities | D36: =SUM(D29:D34) -> 1706.178 | E36: =SUM(E29:E34) -> 2338.653 | F36: =SUM(F29:F34) -> 3734.313 | G36: =SUM(G29:G34) -> 4516.838 | H36: =SUM(H29:H34) -> 5678.1075 | I36: =SUM(I29:I34) -> 6413.1117 | J36: =SUM(J29:J34) -> 7613.8125 | L36: =SUM(L29:L34) -> 5690.537
A38: Deferred income | D38: 2.001 | E38: 58.024 | F38: 122.407 | G38: 134.09 | H38: =G38*IS!I7/IS!H7 -> 174.60906 | I38: =H38*IS!J7/IS!I7 -> 204.57282 | J38: =I38*IS!K7/IS!J7 -> 237.03425 | L38: 141.773
A39: Lease liabilities | D39: 62.408 | E39: 62.736 | F39: 54.36 | G39: 40.548 | H39: =G39 -> 40.548 | I39: =H39 -> 40.548 | J39: =I39 -> 40.548 | L39: 47.388
A40: Deferred tax liabilities | D40: 2.559 | E40: 0.081 | F40: 1.638 | G40: 20.712 | H40: =G40 -> 20.712 | I40: =H40 -> 20.712 | J40: =I40 -> 20.712 | L40: 19.945
A41: Other payables and accruals | D41: 0 | E41: 0 | F41: 60.408 | G41: 2.492 | H41: =G41 -> 2.492 | I41: =H41 -> 2.492 | J41: =I41 -> 2.492 | L41: 3.446
A42: Other liabilities | H42: =L42 -> 5 | I42: =H42 -> 5 | J42: =I42 -> 5 | L42: 5
A43: Contract liabilities | D43: 0.527 | E43: 6.595 | F43: 24.975 | G43: 7.822 | H43: =H115 -> 9.6999499 | I43: =I115 -> 11.631432 | J43: =J115 -> 13.534104 | L43: 3.351
A45: Total non-current liabilities | D45: =SUM(D38:D43) -> 67.495 | E45: =SUM(E38:E43) -> 127.436 | F45: =SUM(F38:F43) -> 263.788 | G45: =SUM(G38:G43) -> 205.664 | H45: =SUM(H38:H43) -> 253.06101 | I45: =SUM(I38:I43) -> 284.95625 | J45: =SUM(J38:J43) -> 319.32035 | L45: =SUM(L38:L43) -> 220.903
A47: Total Liabilities | D47: =D36+D45 -> 1773.673 | E47: =E36+E45 -> 2466.089 | F47: =F36+F45 -> 3998.101 | G47: =G36+G45 -> 4722.502 | H47: =H36+H45 -> 5931.1685 | I47: =I36+I45 -> 6698.0679 | J47: =J36+J45 -> 7933.1328 | L47: =L36+L45 -> 5911.44
A49: Equity
A50: Share capital | D50: 360 | E50: 360 | F50: 360 | G50: 360 | H50: =G50 -> 360 | I50: =H50 -> 360 | J50: =I50 -> 360 | L50: 379.619
A51: Additional paid in capital | H51: =CF!H59+CF!H60 -> 3495.367 | I51: =H51 -> 3495.367 | J51: =I51 -> 3495.367
A52: Reserves | D52: 5177.351 | E52: 7094.297 | F52: 10146.993 | G52: 14595.519 | H52: =H181 -> 20116.298 | I52: =I181 -> 26666.361 | J52: =J181 -> 34402.574 | L52: 20870.625
A53: Non-controlling interests | D53: 5.359 | E53: 24.97 | F53: 88.472 | G53: 105.301 | H53: =G53-IS!I33 -> 155.301 | I53: =H53-IS!J33 -> 209.77798 | J53: =I53-IS!K33 -> 270.92452 | L53: 131.22
A55: Total equity | D55: =SUM(D50:D53) -> 5542.71 | E55: =SUM(E50:E53) -> 7479.267 | F55: =SUM(F50:F53) -> 10595.465 | G55: =SUM(G50:G53) -> 15060.82 | H55: =SUM(H50:H53) -> 24126.966 | I55: =SUM(I50:I53) -> 30731.506 | J55: =SUM(J50:J53) -> 38528.866 | L55: =SUM(L50:L53) -> 21381.464
A57: Total Liabilities & Equity | D57: =D47+D55 -> 7316.383 | E57: =E47+E55 -> 9945.356 | F57: =F47+F55 -> 14593.566 | G57: =G47+G55 -> 19783.322 | H57: =H47+H55 -> 30058.134 | I57: =I47+I55 -> 37429.574 | J57: =J47+J55 -> 46461.998 | L57: =L47+L55 -> 27292.904
A59: Check (TA=TL&E) | D59: =D57-D26 -> 0 | E59: =E57-E26 -> 0 | F59: =F57-F26 -> 0 | G59: =G57-G26 -> 0 | H59: =H57-H26 -> 0 | I59: =I57-I26 -> 0 | J59: =J57-J26 -> 0 | L59: =L57-L26 -> 0
A61: Balance Sheet analysis
A62: Total debt (excl lease liab) | D62: =D32 -> 30.03 | E62: =E32 -> 140.088 | F62: =F32 -> 259.748 | G62: =G32 -> 0 | H62: =H32 -> 0 | I62: =I32 -> 0 | J62: =J32 -> 0
A63: Cash and ST investments | D63: =D10+D9+D8+D21 -> 3637.929 | E63: =E10+E9+E8+E21 -> 4694.96 | F63: =F10+F9+F8+F21 -> 6783.57 | G63: =G10+G9+G8+G21 -> 11109.496 | H63: =H10+H9+H8+H21 -> 17556.92 | I63: =I10+I9+I8+I21 -> 23315.495 | J63: =J10+J9+J8 -> 26876.43
A64: Net debt | D64: =D62-D63 -> -3607.899 | E64: =E62-E63 -> -4554.872 | F64: =F62-F63 -> -6523.822 | G64: =G62-G63 -> -11109.496 | H64: =H62-H63 -> -17556.92 | I64: =I62-I63 -> -23315.495 | J64: =J62-J63 -> -26876.43
A65: Total common equity | D65: =D55 -> 5542.71 | E65: =E55 -> 7479.267 | F65: =F55 -> 10595.465 | G65: =G55 -> 15060.82 | H65: =H55 -> 24126.966 | I65: =I55 -> 30731.506 | J65: =J55 -> 38528.866
A66: Net debt to equity | D66: =D64/D65 -> -0.65092689 | E66: =E64/E65 -> -0.60899979 | F66: =F64/F65 -> -0.61571833 | G66: =G64/G65 -> -0.73764217 | H66: =H64/H65 -> -0.72768868 | I66: =I64/I65 -> -0.75868377 | J66: =J64/J65 -> -0.69756609
A68: Working capital analysis
A70: Inventories | D70: =D5 -> 1251.915 | E70: =E5 -> 1541.156 | F70: =F5 -> 2231.714 | G70: =G5 -> 2215.352 | H70: =-H77/365*IS!I9*2-BS!G70 -> 3670.6223 | I70: =-I77/365*IS!J9*2-BS!H70 -> 3243.4988 | J70: =-J77/365*IS!K9*2-BS!I70 -> 4762.4104
A71: Finished goods | D71: 699.806 | E71: 1001.747 | F71: 1278.341 | G71: 1533.5778
A72: Raw materials | D72: 555.119 | E72: 513.808 | F72: 899.048 | G72: 634.637
A73: Work in progress | D73: 0.827 | E73: 28.387 | F73: 89.645 | G73: 94.411
A74: Provision for impairment of inventories | D74: -3.837 | E74: -2.786 | F74: -35.32 | G74: -47.274
A76: Inventory days, period end | D76: =-365*D70/IS!E9 -> 64.294499 | E76: =-365*E70/IS!F9 -> 57.820637 | F76: =-365*F70/IS!G9 -> 56.949399 | G76: =-365*G70/IS!H9 -> 48.221095
A77: Inventory days, avg | E77: =-365*AVERAGE(D70:E70)/IS!F9 -> 52.394807 | F77: =-365*AVERAGE(E70:F70)/IS!G9 -> 48.138489 | G77: =-365*AVERAGE(F70:G70)/IS!H9 -> 48.399169 | H77: =G77 -> 48.399169 | I77: =H77 -> 48.399169 | J77: =I77 -> 48.399169
A78: Inventory days - reported | D78: 42.7 | E78: 52.4 | F78: 48.1
A81: Trade and other receivables
A82: Trade receivables | D82: =D6 -> 2.03 | E82: =E6 -> 15.41 | F82: =F6 -> 28.473 | G82: =G6 -> 25.624 | H82: =-H84/365*IS!I9*2-BS!G82 -> 29.101908 | I82: =-I84/365*IS!J9*2-BS!H82 -> 35.18338 | J82: =-J84/365*IS!K9*2-BS!I82 -> 39.253004
A83: Receivable days, period end | D83: =365*D82/IS!E7 -> 0.071582553 | E83: =365*E82/IS!F7 -> 0.41432125 | F83: =365*F82/IS!G7 -> 0.5118908 | G83: =365*G82/IS!H7 -> 0.37668885
A84: Receivable days, avg | D84: =D83 -> 0.071582553 | E84: =365*AVERAGE(D82:E82)/IS!F7 -> 0.23445044 | F84: =365*AVERAGE(E82:F82)/IS!G7 -> 0.39446676 | G84: =365*AVERAGE(F82:G82)/IS!H7 -> 0.39762989 | H84: 0.45 | I84: =H84 -> 0.45 | J84: =I84 -> 0.45
A86: Prepayments, other receivables and other assets | D86: =D7 -> 181.892 | E86: =E7 -> 304.539 | F86: =F7 -> 404.428 | G86: =G7 -> 512.505 | H86: =H87*(IS!I9+IS!I11+IS!I13+IS!I15) -> 673.09064 | I86: =I87*(IS!J9+IS!J11+IS!J13+IS!J15) -> 786.55438 | J86: =J87*(IS!K9+IS!K11+IS!K13+IS!K15) -> 907.08404
A87: as % of expenses (COGS+SG&A, excl. amounts due from related parties) | D87: =D86/(IS!E9+IS!E11+IS!E13+IS!E15) -> -0.023010596 | E87: =E86/(IS!F9+IS!F11+IS!F13+IS!F15) -> -0.027605106 | F87: =F86/(IS!G9+IS!G11+IS!G13+IS!G15) -> -0.024784608 | G87: =G86/(IS!H9+IS!H11+IS!H13+IS!H15) -> -0.026653924 | H87: =G87 -> -0.026653924 | I87: =H87 -> -0.026653924 | J87: =I87 -> -0.026653924
A88: Prepayments | D88: 110.723 | E88: 131.998 | F88: 108.002 | G88: 103.485
A89: Deposits and other receivables | D89: 26.785 | E89: 57.948 | F89: 27.132 | G89: 55.238
A90: Recoverable VAT | D90: 26.987 | E90: 85.57 | F90: 216.147 | G90: 277.234
A91: Other assets | D91: 23.383 | E91: 37.422 | F91: 54.862 | G91: 76.58
A92: Impairment allowance | D92: -5.986 | E92: -8.399 | F92: -1.715 | G92: -0.032
A94: Trade and other payables
A95: Trade payables | D95: =D29 -> 596.681 | E95: =E29 -> 881.806 | F95: =F29 -> 1316.78 | G95: =G29 -> 1767.263 | H95: =-H97/365*IS!I9*2-BS!G95 -> 2314.6638 | I95: =-I97/365*IS!J9*2-BS!H95 -> 2480.2835 | J95: =-J97/365*IS!K9*2-BS!I95 -> 3071.8195
A96: Payable days, period end | D96: =-365*D95/IS!E9 -> 30.643698 | E96: =-365*E95/IS!F9 -> 33.083338 | F96: =-365*F95/IS!G9 -> 33.601899 | G96: =-365*G95/IS!H9 -> 38.467637
A97: Payable days, avg | D97: =D98 -> 23.9 | E97: =-365*AVERAGE(D95:E95)/IS!F9 -> 27.73472 | F97: =-365*AVERAGE(E95:F95)/IS!G9 -> 28.052015 | G97: =-365*AVERAGE(F95:G95)/IS!H9 -> 33.564853 | H97: =G97 -> 33.564853 | I97: =H97 -> 33.564853 | J97: =I97 -> 33.564853
A98: Payable days - reported | D98: 23.9 | E98: 27.7 | F98: 28.1
A100: Other payables and accruals | D100: =D30 -> 600.753 | E100: =E30 -> 910.196 | F100: =F30 -> 1571.615 | G100: =G30 -> 2043.625 | H100: =H101*(IS!I9+IS!I11+IS!I13+IS!I15) -> 2683.9638 | I100: =I101*(IS!J9+IS!J11+IS!J13+IS!J15) -> 3136.4029 | J100: =J101*(IS!K9+IS!K11+IS!K13+IS!K15) -> 3617.0176
A101: as % of expenses (COGS+SG&A, excl. amounts due from related parties) | D101: =D100/(IS!E9+IS!E11+IS!E13+IS!E15) -> -0.075999411 | E101: =E100/(IS!F9+IS!F11+IS!F13+IS!F15) -> -0.082505218 | F101: =F100/(IS!G9+IS!G11+IS!G13+IS!G15) -> -0.096313465 | G101: =G100/(IS!H9+IS!H11+IS!H13+IS!H15) -> -0.10628311 | H101: =G101 -> -0.10628311 | I101: =H101 -> -0.10628311 | J101: =I101 -> -0.10628311
A102: Deposit payables | D102: 261.527 | E102: 466.082 | F102: 689.513 | G102: 960.953
A103: Payroll and welfare payables | D103: 170.35 | E103: 256.886 | F103: 336.072 | G103: 472.348
A104: Accruals and other payables | D104: 132.15 | E104: 146.435 | F104: 498.708 | G104: 499.013
A105: Other tax payables | D105: 36.726 | E105: 40.793 | F105: 47.322 | G105: 111.311
A107: Contract liabilities
A108: Current | D108: =D31 -> 305.817 | E108: =E31 -> 198.305 | F108: =F31 -> 259.271 | G108: =G31 -> 359.636 | H108: =H109+H111 -> 250.65548 | I108: =I109+I111 -> 297.8311 | J108: =J109+J111 -> 345.97955
A109: Sales of goods and equipment | D109: 192.462 | E109: 74.436 | F109: 25.711 | G109: 74.436 | H109: =H110*(IS!I98+IS!I99) -> 97.047308 | I109: =I110*(IS!J98+IS!J99) -> 113.63603 | J109: =J110*(IS!K98+IS!K99) -> 131.6538
A110: as %of goods and equipment sales | D110: =D109/(IS!E98+IS!E99) -> 0.018953176 | E110: =E109/(IS!F98+IS!F99) -> 0.0055969316 | F110: =F109/(IS!G98+IS!G99) -> 0.0012922213 | G110: =G109/(IS!H98+IS!H99) -> 0.003074746 | H110: =G110 -> 0.003074746 | I110: =H110 -> 0.003074746 | J110: =I110 -> 0.003074746
A111: Franchise and related services | D111: 113.355 | E111: 123.869 | F111: 233.56 | G111: 123.869 | H111: =H112*IS!I100 -> 153.60817 | I111: =I112*IS!J100 -> 184.19507 | J111: =J112*IS!K100 -> 214.32574
A112: as %of franchise and related services | D112: =D111/IS!E100 -> 0.57721685 | E112: =E111/IS!F100 -> 0.44856182 | F112: =F111/IS!G100 -> 0.57567079 | G112: =G111/IS!H100 -> 0.19977421 | H112: =G112 -> 0.19977421 | I112: =H112 -> 0.19977421 | J112: =I112 -> 0.19977421
A114: Non-current
A115: Franchise and related services | D115: =D43 -> 0.527 | E115: =E43 -> 6.595 | F115: =F43 -> 24.975 | G115: =G43 -> 7.822 | H115: =H116*IS!I100 -> 9.6999499 | I115: =I116*IS!J100 -> 11.631432 | J115: =J116*IS!K100 -> 13.534104
A116: as %of franchise and related services | D116: =D115/IS!E100 -> 0.0026835453 | E116: =E115/IS!F100 -> 0.023882208 | F116: =F115/IS!G100 -> 0.061557535 | G116: =G115/IS!H100 -> 0.012615213 | H116: =G116 -> 0.012615213 | I116: =H116 -> 0.012615213 | J116: =I116 -> 0.012615213
A118: Net working capital | D118: =D5+D6+D7-D29-D30 -> 238.403 | E118: =E5+E6+E7-E29-E30 -> 69.103 | F118: =F5+F6+F7-F29-F30 -> -223.78 | G118: =G5+G6+G7-G29-G30 -> -1057.407 | H118: =H5+H6+H7-H29-H30 -> -625.81273 | I118: =I5+I6+I7-I29-I30 -> -1551.4498 | J118: =J5+J6+J7-J29-J30 -> -980.08969
A120: PP&E
A121: PPE, beginning | D121: 423.422 | E121: =D126 -> 1033.497 | F121: =E126 -> 1701.086 | G121: =F126 -> 3390.053 | H121: =G126 -> 5317.826 | I121: =H126 -> 7434.5976 | J121: =I126 -> 9398.5602
A122: Additions | D122: =D134 -> 685.925 | E122: =E134 -> 778.001 | F122: =F134 -> 1924.441 | G122: =G134 -> 2325.341 | H122: =H134 -> 2325.341 | I122: =I134 -> 2325.341 | J122: =J134 -> 2325.341
A123: Depreciation | D123: -57.239 | E123: -105.31 | F123: -160.504 | G123: -314.887 | H123: =H151 -> -208.56942 | I123: =I151 -> -361.37836 | J123: =J151 -> -415.97526
A124: Disposal | D124: -3.784 | E124: -1.657 | F124: -4.555 | G124: -64.031
A125: Others | D125: =D126-D121-D122-D124-D123 -> -14.827 | E125: =E126-E121-E122-E124-E123 -> -3.445 | F125: =F126-F121-F122-F124-F123 -> -70.415 | G125: =G126-G121-G122-G124-G123 -> -18.65 | H125: 0 | I125: 0 | J125: 0
...

Sheet CF
A1: Rmb mn | D1: 44561 | E1: 44926 | F1: 45291 | G1: 45657 | H1: 46022 | I1: 46387 | J1: 46387
A2: Accounting standards: IFRS | D2: 2021 | E2: 2022 | F2: 2023 | G2: 2024 | H2: 2025E | I2: 2026E | J2: 2027E
A3: Cash flow statement
A4: Cash flows from operating activities
A5: Profit before tax | D5: =IS!E29 -> 2558.874 | E5: =IS!F29 -> 2658.043 | F5: =IS!G29 -> 4154.002 | G5: =IS!H29 -> 5810.583 | H5: =IS!I29 -> 7439.5915 | I5: =IS!J29 -> 8817.0613 | J5: =IS!K29 -> 10404.436
A6: Finance costs | D6: 5.973 | E6: 9.19 | F6: 14.697 | G6: 6.367 | H6: =-IS!I24 -> 3.0212545 | I6: =-IS!J24 -> 3.0212545 | J6: =-IS!K24 -> 3.0212545
A7: Share of losses/(profits) of an associate | D7: 0 | E7: 0.18 | F7: -0.196 | G7: 3.016 | H7: =-IS!I27 -> 0 | I7: =-IS!J27 -> 0 | J7: =-IS!K27 -> 0
A8: Gain on disposal of a subsidiary | D8: 0 | E8: 0 | F8: -1.272 | G8: 0
A9: Interest income | D9: -38.221 | E9: -44.322 | F9: -53.801 | G9: -107.015 | H9: =-IS!I149 -> -153.59067 | I9: =-IS!J149 -> -196.91388 | J9: =-IS!K149 -> -277.53392
A10: Loss/(gain) on disposal of items of property, plant and equipment | D10: 1.156 | E10: 0.303 | F10: -0.198 | G10: 5.836 | H10: =-IS!I151 -> 0 | I10: =-IS!J151 -> 0 | J10: =-IS!K151 -> 0
A11: (Gain)/loss on early termination of leases | D11: -1.248 | E11: 3.851 | F11: -0.168 | G11: -3.424
A12: Investment income on financial assets at fair value through profit or loss | D12: -25.999 | E12: -25.644 | F12: -53.333 | G12: -45.17 | H12: =-IS!I150 -> -104.74929 | I12: =-IS!J150 -> -104.74929 | J12: =-IS!K150 -> -104.74929
A13: Depreciation of property, plant and equipment | D13: 57.239 | E13: 105.31 | F13: 160.504 | G13: 314.887 | H13: =-BS!H123 -> 208.56942 | I13: =-BS!I123 -> 361.37836 | J13: =-BS!J123 -> 415.97526
A14: Depreciation of right-of-use assets | D14: 42.363 | E14: 75.782 | F14: 103.472 | G14: 99.178 | H14: =-BS!H162 -> 129.14742 | I14: =-BS!I162 -> 151.30974 | J14: =-BS!J162 -> 175.31943
A15: Amortisation of other intangible assets | D15: 1.197 | E15: 2.672 | F15: 3.8 | G15: 5.29 | H15: =-BS!H172 -> 5.29 | I15: =-BS!I172 -> 5.29 | J15: =-BS!J172 -> 5.29
A16: Impairment of inventories | D16: 2.297 | E16: 2.076 | F16: 32.189 | G16: 36.995
A17: Impairment losses/(reversal of impairment losses) on financial assets | D17: 1.787 | E17: 4.098 | F17: -1.638 | G17: 0.329
A18: Impairment of property, plant and equipment | D18: 14.827 | E18: 0 | F18: 65.524 | G18: 0
A19: Equity-settled share-based payment expenses | D19: 22.554 | E19: 24.981 | F19: 16.427 | G19: 15.786
A20: Foreign exchange differences (net) | D20: 0.994 | E20: 0.163 | F20: -31.963 | G20: -5.62
A21: Others | H21: =BS!H33-BS!G33+BS!H39-BS!G39+BS!H42-BS!G42 -> 5 | I21: =BS!I33-BS!H33+BS!I39-BS!H39+BS!I42-BS!H42 -> 0 | J21: =BS!J33-BS!I33+BS!J39-BS!I39+BS!J42-BS!I42 -> 0
A22: Change in working capitals | D22: =SUM(D23:D31) -> -399.544 | E22: =SUM(E23:E31) -> 228.172 | F22: =SUM(F23:F31) -> 242.767 | G22: =SUM(G23:G31) -> 1076.74 | H22: =SUM(H23:H31) -> -310.9181 | I22: =SUM(I23:I31) -> 1179.227 | J22: =SUM(J23:J31) -> -303.69669
A23: Increase in inventories | D23: -842.719 | E23: -291.317 | F23: -725.819 | G23: -20.633 | H23: =BS!G5-BS!H5 -> -1455.2703 | I23: =BS!H5-BS!I5 -> 427.1235 | J23: =BS!I5-BS!J5 -> -1518.9116
A24: Decrease/(increase) in trade receivables | D24: 0.294 | E24: -14.114 | F24: -8.955 | G24: 5.064 | H24: =BS!G6-BS!H6-H12 -> 101.27138 | I24: =BS!H6-BS!I6-I12 -> 98.667817 | J24: =BS!I6-BS!J6-J12 -> 100.67967
A25: Increase in prepayments, other receivables and other assets | D25: -88.419 | E25: -62.411 | F25: 50.804 | G25: 2.314 | H25: =BS!G7-BS!H7+BS!G20-BS!H20 -> -160.58564 | I25: =BS!H7-BS!I7+BS!H20-BS!I20 -> -113.46373 | J25: =BS!I7-BS!J7+BS!I20-BS!J20 -> -120.52966
A26: (Increase)/decrease in restricted cash | D26: -57.825 | E26: 59.969 | F26: -14.633 | G26: 16.414
A27: Increase in other non-current assets | D27: 0 | E27: 0 | F27: -11.986 | G27: 3.257 | H27: =BS!G22-BS!H22 -> 0 | I27: =BS!H22-BS!I22 -> 0 | J27: =BS!I22-BS!J22 -> 0
A28: Increase in trade payables | D28: 261.205 | E28: 286.16 | F28: 466.094 | G28: 452.782 | H28: =BS!H29-BS!G29 -> 547.4008 | I28: =BS!I29-BS!H29 -> 165.61965 | J28: =BS!J29-BS!I29 -> 591.53606
A29: Increase in other payables and accruals | D29: 194.118 | E29: 295.306 | F29: 343.32 | G29: 522.647 | H29: =BS!H30-BS!G30+BS!H34-BS!G34+BS!H40-BS!G40+BS!H41-BS!G41 -> 722.84919 | I29: =BS!I30-BS!H30+BS!I34-BS!H34+BS!I40-BS!H40+BS!I41-BS!H41 -> 522.20894 | J29: =BS!J30-BS!I30+BS!J34-BS!I34+BS!J40-BS!I40+BS!J41-BS!I41 -> 561.01629
A30: Increase/(decrease) in contract liabilities | D30: 131.801 | E30: -101.444 | F30: 79.559 | G30: 83.212 | H30: =BS!H43-BS!G43+BS!H31-BS!G31 -> -107.10257 | I30: =BS!I43-BS!H43+BS!I31-BS!H31 -> 49.107109 | J30: =BS!J43-BS!I43+BS!J31-BS!I31 -> 50.051115
A31: Increase in deferred income | D31: 2.001 | E31: 56.023 | F31: 64.383 | G31: 11.683 | H31: =BS!H38-BS!G38 -> 40.519064 | I31: =BS!I38-BS!H38 -> 29.963752 | J31: =BS!J38-BS!I38 -> 32.461434
A32: Cash generated from operations | D32: =SUM(D5:D22) -> 2244.249 | E32: =SUM(E5:E22) -> 3044.855 | F32: =SUM(F5:F22) -> 4650.813 | G32: =SUM(G5:G22) -> 7213.778 | H32: =SUM(H5:H22) -> 7221.3615 | I32: =SUM(I5:I22) -> 10215.625 | J32: =SUM(J5:J22) -> 10318.062
A34: Income tax paid | D34: -590.081 | E34: -658.546 | F34: -910.742 | G34: -1280.166 | H34: =IS!I30 -> -1736.6438 | I34: =IS!J30 -> -2058.1903 | J34: =IS!K30 -> -2428.7354
A35: Interest received | D35: 38.221 | E35: 44.322 | F35: 53.801 | G35: 75.096 | H35: =-H9-H7 -> 153.59067 | I35: =-I9-I7 -> 196.91388 | J35: =-J9-J7 -> 277.53392
A36: Net cash flows generated from operating activities | D36: =D32+D34+D35 -> 1692.389 | E36: =E32+E34+E35 -> 2430.631 | F36: =F32+F34+F35 -> 3793.872 | G36: =G32+G34+G35 -> 6008.708 | H36: =H32+H34+H35 -> 5638.3084 | I36: =I32+I34+I35 -> 8354.3481 | J36: =J32+J34+J35 -> 8166.8603
E37: =E43+E44+E45 -> -939.795 | F37: =F43+F44+F45 -> 862.907 | G37: =G43+G44+G45 -> -5640.427
A38: Cash flows from investing activities
A39: Purchases of items of property, plant and equipment | D39: -944.523 | E39: -997.293 | F39: -1685.292 | G39: -1438.614 | H39: =-BS!H122-BS!H125-H10-BS!H15+BS!G15 -> -2342.87 | I39: =-BS!I122-BS!I125-I10-BS!I15+BS!H15 -> -2325.341 | J39: =-BS!J122-BS!J125-J10-BS!J15+BS!I15 -> -2325.341
A40: Proceeds from disposal of items of property, plant and equipment | D40: 5.073 | E40: 0.893 | F40: 4.753 | G40: 58.195 | H40: =-BS!H124 -> 0 | I40: =-BS!I124 -> 0 | J40: =-BS!J124 -> 0
A41: Purchases of other intangible assets | D41: -7.177 | E41: -8.723 | F41: -5.433 | G41: -9.858 | H41: =-BS!H171 -> -17 | I41: =-BS!I171 -> -17 | J41: =-BS!J171 -> -17
A42: Purchases of and prepayments for right-ofuse assets — land use rights | D42: -0.673 | E42: -253.943 | F42: -0.041 | G42: -1.34 | H42: =-BS!H161 -> -87.3455 | I42: =-BS!I161 -> -96.08005 | J42: =-BS!J161 -> -115.29606
A43: Purchases of financial assets at fair value through profit or loss | D43: -2150 | E43: -4336 | F43: -5161 | G43: -3213 | H43: =BS!G8-BS!H8 -> 0 | I43: =BS!H8-BS!I8 -> 0 | J43: =BS!I8-BS!J8 -> 0
A44: Proceeds from disposal of financial assets at fair value through profit or loss | D44: 1277.07 | E44: 3396.205 | F44: 6333.963 | G44: 512.573
A45: Placement of time deposits with original maturity of more than three months when acquired | D45: 0 | E45: 0 | F45: -310.056 | G45: -2940 | H45: =BS!G21-BS!H21 -> 0 | I45: =BS!H21-BS!I21 -> 0 | J45: =BS!I21-BS!J21 -> 0
A47: Others | D47: =D48-SUM(D39:D46) -> -11.4 | E47: =E48-SUM(E39:E46) -> -3 | F47: =F48-SUM(F39:F46) -> -2.238 | G47: =G48-SUM(G39:G46) -> 13.056 | H47: =BS!G18-BS!H18+BS!G19-BS!H19 -> -103.846 | I47: =BS!H18-BS!I18+BS!H19-BS!I19 -> 0 | J47: =BS!I18-BS!J18+BS!I19-BS!J19 -> 0
A48: Net cash flows used in investing activities | D48: -1831.63 | E48: -2201.861 | F48: -825.344 | G48: -7018.988 | H48: =SUM(H39:H47) -> -2551.0615 | I48: =SUM(I39:I47) -> -2438.421 | J48: =SUM(J39:J47) -> -2457.6371
A50: Cash flows from financing activities
A51: Proceeds from bank loans | D51: 30 | E51: 140 | F51: 259.537 | G51: 4.536
A52: Repayment of bank loans | D52: 0 | E52: -30 | F52: -140 | G52: -264.073 | H52: =BS!H32-BS!G32 -> 0 | I52: =BS!I32-BS!H32 -> 0
A53: Interest paid for interest-bearing bank and other borrowings | D53: -1.143 | E53: -3.22 | F53: -7.118 | G53: -2.451 | H53: =-H6 -> -3.0212545 | I53: =-I6 -> -3.0212545 | J53: =-J6 -> -3.0212545
A54: Principal portion of lease payments | D54: -41.71 | E54: -76.399 | F54: -99.875 | G54: -83.49 | H54: =BS!H162 -> -129.14742 | I54: =BS!I162 -> -151.30974 | J54: =BS!J162 -> -175.31943
A55: Interest portion of lease payments | D55: -4.8 | E55: -5.912 | F55: -7.456 | G55: -4.127 | H55: =IS!I357 -> -3.0212545 | I55: =IS!J357 -> -3.0212545 | J55: =IS!K357 -> -3.0212545
A56: Increase in restricted cash | D56: 0 | E56: -63.25 | F56: -89.035 | G56: -7.035 | H56: =BS!G9-BS!H9 -> 0 | I56: =BS!H9-BS!I9 -> 0 | J56: =BS!I9-BS!J9 -> 0
A57: Decrease in restricted cash | D57: 28.9 | E57: 0 | F57: 63.25 | G57: 85.374
A58: Dividends paid | D58: -404.4 | E58: -104.4 | F58: -100 | G58: 0 | H58: =BS!H179 -> 0 | I58: =BS!I179 -> 0 | J58: =BS!J179 -> 0
A59: net proceeds from issue of shares | D59: 1120 | H59: =3313/IS!$L$5*1.15 -> 3495.367
A62: Others | D62: =D63-SUM(D51:D61) -> -0.199 | E62: =E63-SUM(E51:E61) -> 3.92 | F62: =F63-SUM(F51:F61) -> 9.378 | G62: =G63-SUM(G51:G61) -> -6.172
A63: Net cash flows from/(used in) financing activities | D63: 726.648 | E63: -139.261 | F63: -111.319 | G63: -277.438 | H63: =SUM(H51:H61) -> 3360.177 | I63: =SUM(I51:I61) -> -157.35225 | J63: =SUM(J51:J61) -> -181.36194
A65: Net increase in cash and cash equivalents | D65: =D36+D48+D63 -> 587.407 | E65: =E36+E48+E63 -> 89.509 | F65: =F36+F48+F63 -> 2857.209 | G65: =G36+G48+G63 -> -1287.718 | H65: =H36+H48+H63 -> 6447.4239 | I65: =I36+I48+I63 -> 5758.5748 | J65: =J36+J48+J63 -> 5527.8613
A67: Cash and cash equivalents at beginning of year/period | D67: 2089.486 | E67: =BS!D10 -> 2675.827 | F67: =E69 -> 2764.138 | G67: =F69 -> 5621.904 | H67: =G69 -> 4335.123 | I67: =H69 -> 10782.547 | J67: =I69 -> 16541.122
A68: Effect of foreign exchange differences (net) | D68: -1.066 | E68: -1.198 | F68: 0.557 | G68: 0.937
A69: Cash and cash equivalents at year end | D69: =D65+D67+D68 -> 2675.827 | E69: =E65+E67+E68 -> 2764.138 | F69: =F65+F67+F68 -> 5621.904 | G69: =G65+G67+G68 -> 4335.123 | H69: =H65+H67+H68 -> 10782.547 | I69: =I65+I67+I68 -> 16541.122 | J69: =J65+J67+J68 -> 22068.983
A70: Check | D70: =D69-BS!D10 -> 0 | E70: =E69-BS!E10 -> 0 | F70: =F69-BS!F10 -> 0 | G70: =G69-BS!G10 -> 0 | H70: =H69-BS!H10 -> 0 | I70: =I69-BS!I10 -> 0 | J70: =J69-BS!J10 -> 0
A72: Free cash flow | D72: =D36+D39-D14 -> 705.503 | E72: =E36+E39-E14 -> 1357.556 | F72: =F36+F39-F14 -> 2005.108 | G72: =G36+G39-G14 -> 4470.916 | H72: =H36+H39-H14 -> 3166.2909 | I72: =I36+I39-I14 -> 5877.6973 | J72: =J32+J39-J14 -> 7817.4013
A73: as % of sales | D73: =D72/IS!E7 -> 0.068158048 | E73: =E72/IS!F7 -> 0.099999875 | F73: =F72/IS!G7 -> 0.098761801 | G73: =G72/IS!H7 -> 0.18006922 | H73: =H72/IS!I7 -> 0.097931724 | I73: =I72/IS!J7 -> 0.15516675 | J73: =J72/IS!K7 -> 0.17811097
