Workbook
Name A_ALL_GYG.AX: #REF!
Name E_ALL_GYG.AX: #REF!
Name L_ALL_GYG.AX: #REF!
Name V_ALL_GYG.AX: #REF!

Sheet GYG model ->
D2: Guzman y Gomez (GYG.ASX)
D3: Australia Small & Mid Cap
B8: Goldman SMID Analysts
B10: Elijah Mayr
B11: elijah.mayr@gs.com
B12: +61 2 9321 8995
B14: Elise Bailey
B15: elise.bailey@gs.com
B16: +61 3 9679 1344

Sheet Summary
B1: =+'GYG model ->'!D2 -> Guzman y Gomez (GYG.ASX)
B2: Summary
B8: Profit & Loss | U8: Valuation data
B9: A$m June y/e | D9: =+'Income & Cash Flow'!L$4 -> FY22A | G9: =+'Income & Cash Flow'!O$4 -> FY23A | J9: =+'Income & Cash Flow'!R$4 -> FY24A | M9: =+'Income & Cash Flow'!U$4 -> FY25A | P9: =+'Income & Cash Flow'!X$4 -> FY26E | S9: =+'Income & Cash Flow'!AA$4 -> FY27E | U9: A$m June y/e | W9: =+'Income & Cash Flow'!L$4 -> FY22A | Z9: =+'Income & Cash Flow'!O$4 -> FY23A | AC9: =+'Income & Cash Flow'!R$4 -> FY24A | AF9: =+'Income & Cash Flow'!U$4 -> FY25A | AI9: =+'Income & Cash Flow'!X$4 -> FY26E | AL9: =+'Income & Cash Flow'!AA$4 -> FY27E
B10: Revenue | C10: A$m | D10: ='Income & Cash Flow'!L8 -> 171.792 | E10: ='Income & Cash Flow'!M8 -> 121.185 | F10: ='Income & Cash Flow'!N8 -> 137.859 | G10: ='Income & Cash Flow'!O8 -> 259.044 | H10: ='Income & Cash Flow'!P8 -> 167.517 | I10: ='Income & Cash Flow'!Q8 -> 174.697 | J10: ='Income & Cash Flow'!R8 -> 342.214 | K10: ='Income & Cash Flow'!S8 -> 212.419 | ... S10: ='Income & Cash Flow'!AA8 -> 641.83544 | U10: Diluted no. of shares | V10: m | W10: =+'Income & Cash Flow'!L49 -> 0 | X10: =+'Income & Cash Flow'!M49 -> 0 | Y10: =+'Income & Cash Flow'!N49 -> 0 | Z10: =+'Income & Cash Flow'!O49 -> 83.992295 | AA10: =+'Income & Cash Flow'!P49 -> 0 | AB10: =+'Income & Cash Flow'!Q49 -> 85.568408 | AC10: =+'Income & Cash Flow'!R49 -> 85.568408 | AD10: =+'Income & Cash Flow'!S49 -> 106.13463 | ... AL10: =+'Income & Cash Flow'!AA49 -> 102.86055
B11: CoGS | C11: A$m | D11: ='Income & Cash Flow'!L11 -> -44.194 | E11: ='Income & Cash Flow'!M11 -> -32.906 | F11: ='Income & Cash Flow'!N11 -> -37.522 | G11: ='Income & Cash Flow'!O11 -> -70.428 | H11: ='Income & Cash Flow'!P11 -> -43.237 | I11: ='Income & Cash Flow'!Q11 -> -44.343 | J11: ='Income & Cash Flow'!R11 -> -87.58 | K11: ='Income & Cash Flow'!S11 -> -55.071 | ... S11: ='Income & Cash Flow'!AA11 -> -147.96261 | U11: Adj. diluted EPS | V11: cps | W11: =+'Income & Cash Flow'!L51 -> 0 | X11: =+'Income & Cash Flow'!M51 -> 0 | Y11: =+'Income & Cash Flow'!N51 -> 0 | Z11: =+'Income & Cash Flow'!O51 -> 3.5717562 | AA11: =+'Income & Cash Flow'!P51 -> 0 | AB11: =+'Income & Cash Flow'!Q51 -> 2.2204457 | AC11: =+'Income & Cash Flow'!R51 -> 6.661337 | AD11: =+'Income & Cash Flow'!S51 -> 0 | ... AL11: =+'Income & Cash Flow'!AA51 -> 31.059832
B12: Opex | C12: A$m | D12: =+D13-D11-D10 -> -103.692 | E12: =+E13-E11-E10 -> -73.742 | F12: =+F13-F11-F10 -> -85.253 | G12: =+G13-G11-G10 -> -158.995 | H12: =+H13-H11-H10 -> -105.376 | I12: =+I13-I11-I10 -> -121.984 | J12: =+J13-J11-J10 -> -227.36 | K12: =+K13-K11-K10 -> -125.77 | ... S12: =+S13-S11-S10 -> -384.11485 | U12: Adj. EPS growth | V12: % | W12: =+'Income & Cash Flow'!L66 -> 0 | X12: =+'Income & Cash Flow'!M66 -> 0 | Y12: =+'Income & Cash Flow'!N66 -> 0 | Z12: =+'Income & Cash Flow'!O66 -> 0 | AA12: =+'Income & Cash Flow'!P66 -> 0 | AB12: =+'Income & Cash Flow'!Q66 -> 0 | AC12: =+'Income & Cash Flow'!R66 -> 0 | AD12: =+'Income & Cash Flow'!S66 -> 0 | ... AL12: =+'Income & Cash Flow'!AA66 -> 0.53694344
B13: Ebitda | C13: A$m | D13: =+'Income & Cash Flow'!L18 -> 23.906 | E13: =+'Income & Cash Flow'!M18 -> 14.537 | F13: =+'Income & Cash Flow'!N18 -> 15.084 | G13: =+'Income & Cash Flow'!O18 -> 29.621 | H13: =+'Income & Cash Flow'!P18 -> 18.904 | I13: =+'Income & Cash Flow'!Q18 -> 8.37 | J13: =+'Income & Cash Flow'!R18 -> 27.274 | K13: =+'Income & Cash Flow'!S18 -> 31.578 | ... S13: =+'Income & Cash Flow'!AA18 -> 109.75798 | U13: Dividends | V13: cps | W13: =+'Balance Sheet'!L179 -> 0 | X13: =+'Balance Sheet'!M179 -> 0 | Y13: =+'Balance Sheet'!N179 -> 0 | Z13: =+'Balance Sheet'!O179 -> 0 | AA13: =+'Balance Sheet'!P179 -> 0 | AB13: =+'Balance Sheet'!Q179 -> 0 | AC13: =+'Balance Sheet'!R179 -> 0 | AD13: =+'Balance Sheet'!S179 -> 0 | ... AL13: =+'Balance Sheet'!AA179 -> 0
B14: Adjustments | C14: A$m | D14: =+D15-D13 -> -2.206 | E14: =+E15-E13 -> -0.337 | F14: =+F15-F13 -> 0.016 | G14: =+G15-G13 -> -0.321 | H14: =+H15-H13 -> 5.796 | I14: =+I15-I13 -> 11.73 | J14: =+J15-J13 -> 17.526 | K14: =+K15-K13 -> 0 | ... S14: =+S15-S13 -> 0 | U14: Dividend yield | V14: % | W14: =+'Income & Cash Flow'!L154 -> 0 | X14: =+'Income & Cash Flow'!M154 -> 0 | Y14: =+'Income & Cash Flow'!N154 -> 0 | Z14: =+'Income & Cash Flow'!O154 -> 0 | AA14: =+'Income & Cash Flow'!P154 -> 0 | AB14: =+'Income & Cash Flow'!Q154 -> 0 | AC14: =+'Income & Cash Flow'!R154 -> 0 | AD14: =+'Income & Cash Flow'!S154 -> 0 | ... AL14: =+'Income & Cash Flow'!AA154 -> 0
B15: Adj. Ebitda | C15: A$m | D15: =+'Income & Cash Flow'!L20 -> 21.7 | E15: =+'Income & Cash Flow'!M20 -> 14.2 | F15: =+'Income & Cash Flow'!N20 -> 15.1 | G15: =+'Income & Cash Flow'!O20 -> 29.3 | H15: =+'Income & Cash Flow'!P20 -> 24.7 | I15: =+'Income & Cash Flow'!Q20 -> 20.1 | J15: =+'Income & Cash Flow'!R20 -> 44.8 | K15: =+'Income & Cash Flow'!S20 -> 31.578 | ... S15: =+'Income & Cash Flow'!AA20 -> 109.75798
B16: D&A&I | C16: A$m | D16: =SUM('Income & Cash Flow'!L22:L24) -> -14.46 | E16: =SUM('Income & Cash Flow'!M22:M24) -> -12.567 | F16: =SUM('Income & Cash Flow'!N22:N24) -> -12.988 | G16: =SUM('Income & Cash Flow'!O22:O24) -> -25.555 | H16: =SUM('Income & Cash Flow'!P22:P24) -> -15.9 | I16: =SUM('Income & Cash Flow'!Q22:Q24) -> -15.223 | J16: =SUM('Income & Cash Flow'!R22:R24) -> -31.123 | K16: =SUM('Income & Cash Flow'!S22:S24) -> -19.08 | ... S16: =SUM('Income & Cash Flow'!AA22:AA24) -> -57.252137 | U16: PE | V16: x | W16: =+'Income & Cash Flow'!L148 -> 0 | X16: =+'Income & Cash Flow'!M148 -> 0 | Y16: =+'Income & Cash Flow'!N148 -> 0 | Z16: =+'Income & Cash Flow'!O148 -> 0 | AA16: =+'Income & Cash Flow'!P148 -> 0 | AB16: =+'Income & Cash Flow'!Q148 -> 0 | AC16: =+'Income & Cash Flow'!R148 -> 358.03623 | AD16: =+'Income & Cash Flow'!S148 -> 0 | ... AL16: =+'Income & Cash Flow'!AA148 -> 76.78728
B17: EBIT | C17: A$m | D17: =+D16+D13 -> 9.446 | E17: =+E16+E13 -> 1.97 | F17: =+F16+F13 -> 2.096 | G17: =+G16+G13 -> 4.066 | H17: =+H16+H13 -> 3.004 | I17: =+I16+I13 -> -6.853 | J17: =+J16+J13 -> -3.849 | K17: =+K16+K13 -> 12.498 | ... S17: =+S16+S13 -> 52.505847 | U17: P/B | V17: x | W17: =+'Income & Cash Flow'!L150 -> 0 | X17: =+'Income & Cash Flow'!M150 -> 0 | Y17: =+'Income & Cash Flow'!N150 -> 0 | Z17: =+'Income & Cash Flow'!O150 -> 22.772878 | AA17: =+'Income & Cash Flow'!P150 -> 0 | AB17: =+'Income & Cash Flow'!Q150 -> 5.7653322 | AC17: =+'Income & Cash Flow'!R150 -> 5.7653322 | AD17: =+'Income & Cash Flow'!S150 -> 6.8854291 | ... AL17: =+'Income & Cash Flow'!AA150 -> 5.667487
B18: Net interest | C18: A$m | D18: =+'Income & Cash Flow'!L29+'Income & Cash Flow'!L30+'Income & Cash Flow'!L31 -> -2.835 | E18: =+'Income & Cash Flow'!M29+'Income & Cash Flow'!M30+'Income & Cash Flow'!M31 -> -1.622 | F18: =+'Income & Cash Flow'!N29+'Income & Cash Flow'!N30+'Income & Cash Flow'!N31 -> -2.288 | G18: =+'Income & Cash Flow'!O29+'Income & Cash Flow'!O30+'Income & Cash Flow'!O31 -> -3.91 | H18: =+'Income & Cash Flow'!P29+'Income & Cash Flow'!P30+'Income & Cash Flow'!P31 -> -4.083 | I18: =+'Income & Cash Flow'!Q29+'Income & Cash Flow'!Q30+'Income & Cash Flow'!Q31 -> -3.629 | J18: =+'Income & Cash Flow'!R29+'Income & Cash Flow'!R30+'Income & Cash Flow'!R31 -> -7.712 | K18: =+'Income & Cash Flow'!S29+'Income & Cash Flow'!S30+'Income & Cash Flow'!S31 -> 2.693 | ... S18: =+'Income & Cash Flow'!AA29+'Income & Cash Flow'!AA30+'Income & Cash Flow'!AA31 -> -6.8653998 | U18: EV / Ebitda | V18: x | W18: =+'Income & Cash Flow'!L143 -> 95.793605 | X18: =+'Income & Cash Flow'!M143 -> 0 | Y18: =+'Income & Cash Flow'!N143 -> 0 | Z18: =+'Income & Cash Flow'!O143 -> 73.427619 | AA18: =+'Income & Cash Flow'!P143 -> 7.9938462 | AB18: =+'Income & Cash Flow'!Q143 -> 98.79724 | AC18: =+'Income & Cash Flow'!R143 -> 44.32644 | AD18: =+'Income & Cash Flow'!S143 -> 80.149248 | ... AL18: =+'Income & Cash Flow'!AA143 -> 22.843579
B19: Pre-tax profit | C19: A$m | D19: =+D18+D17 -> 6.611 | E19: =+E18+E17 -> 0.348 | F19: =+F18+F17 -> -0.192 | G19: =+G18+G17 -> 0.156 | H19: =+H18+H17 -> -1.079 | I19: =+I18+I17 -> -10.482 | J19: =+J18+J17 -> -11.561 | K19: =+K18+K17 -> 15.191 | ... S19: =+S18+S17 -> 45.640447 | U19: EV / Ebit | V19: x | W19: =+'Income & Cash Flow'!L144 -> 288.71128 | X19: =+'Income & Cash Flow'!M144 -> 0 | Y19: =+'Income & Cash Flow'!N144 -> 0 | Z19: =+'Income & Cash Flow'!O144 -> 581.46736 | AA19: =+'Income & Cash Flow'!P144 -> 22.437273 | AB19: =+'Income & Cash Flow'!Q144 -> 413.71344 | AC19: =+'Income & Cash Flow'!R144 -> 146.01651 | AD19: =+'Income & Cash Flow'!S144 -> 202.50864 | ... AL19: =+'Income & Cash Flow'!AA144 -> 47.752114
B20: Tax | C20: A$m | D20: =+'Income & Cash Flow'!L38 -> -2.7 | E20: =+'Income & Cash Flow'!M38 -> -1.469 | F20: =+'Income & Cash Flow'!N38 -> -0.954 | G20: =+'Income & Cash Flow'!O38 -> -2.423 | H20: =+'Income & Cash Flow'!P38 -> -2.881 | I20: =+'Income & Cash Flow'!Q38 -> 0.694 | J20: =+'Income & Cash Flow'!R38 -> -2.187 | K20: =+'Income & Cash Flow'!S38 -> -7.89 | ... S20: =+'Income & Cash Flow'!AA38 -> -13.692134 | U20: Price / NTA | V20: x | W20: =+'Income & Cash Flow'!L151 -> 0 | X20: =+'Income & Cash Flow'!M151 -> 0 | Y20: =+'Income & Cash Flow'!N151 -> 0 | Z20: =+'Income & Cash Flow'!O151 -> 6.4765078 | AA20: =+'Income & Cash Flow'!P151 -> 0 | AB20: =+'Income & Cash Flow'!Q151 -> 3.1338637 | AC20: =+'Income & Cash Flow'!R151 -> 3.1338637 | AD20: =+'Income & Cash Flow'!S151 -> 3.7455623 | ... AL20: =+'Income & Cash Flow'!AA151 -> 2.8242601
B21: Reported NPAT | C21: A$m | D21: =+D20+D19 -> 3.911 | E21: =+E20+E19 -> -1.121 | F21: =+F20+F19 -> -1.146 | G21: =+G20+G19 -> -2.267 | H21: =+H20+H19 -> -3.96 | I21: =+I20+I19 -> -9.788 | J21: =+J20+J19 -> -13.748 | K21: =+K20+K19 -> 7.301 | ... S21: =+S20+S19 -> 31.948313
B22: Adjustments | C22: A$m | D22: =+D23-D21 -> -0.711 | E22: =+E23-E21 -> 2.021 | F22: =+F23-F21 -> 3.246 | G22: =+G23-G21 -> 5.267 | H22: =+H23-H21 -> 7.76 | I22: =+I23-I21 -> 11.688 | J22: =+J23-J21 -> 19.448 | K22: =+K23-K21 -> 0 | ... S22: =+S23-S21 -> 0 | U22: Net debt (ex-leases) | V22: A$m | W22: =+'Balance Sheet'!L60 -> -51.069 | X22: =+'Balance Sheet'!M60 -> 0 | Y22: =+'Balance Sheet'!N60 -> 0 | Z22: =+'Balance Sheet'!O60 -> -33.504 | AA22: =+'Balance Sheet'!P60 -> -10.619 | AB22: =+'Balance Sheet'!Q60 -> -294.48 | AC22: =+'Balance Sheet'!R60 -> -294.48 | AD22: =+'Balance Sheet'!S60 -> -274.493 | ... AL22: =+'Balance Sheet'!AA60 -> -296.67325
B23: Adj. NPAT | C23: A$m | D23: =+'Income & Cash Flow'!L42 -> 3.2 | E23: =+'Income & Cash Flow'!M42 -> 0.9 | F23: =+'Income & Cash Flow'!N42 -> 2.1 | G23: =+'Income & Cash Flow'!O42 -> 3 | H23: =+'Income & Cash Flow'!P42 -> 3.8 | I23: =+'Income & Cash Flow'!Q42 -> 1.9 | J23: =+'Income & Cash Flow'!R42 -> 5.7 | K23: =+'Income & Cash Flow'!S42 -> 7.301 | ... S23: =+'Income & Cash Flow'!AA42 -> 31.948313 | U23: Net debt / Ebitda | V23: x | W23: =+'Balance Sheet'!L64 -> -2.3534101 | X23: =+'Balance Sheet'!M64 -> 0 | Y23: =+'Balance Sheet'!N64 -> 0 | Z23: =+'Balance Sheet'!O64 -> -1.1434812 | AA23: =+'Balance Sheet'!P64 -> -0.42991903 | AB23: =+'Balance Sheet'!Q64 -> -14.650746 | AC23: =+'Balance Sheet'!R64 -> -6.5732143 | AD23: =+'Balance Sheet'!S64 -> -8.6925391 | ... AL23: =+'Balance Sheet'!AA64 -> -2.7029764
U24: Ebitda / Interest | V24: x | W24: =+'Balance Sheet'!L54 -> 7.654321 | X24: =+'Balance Sheet'!M54 -> 0 | Y24: =+'Balance Sheet'!N54 -> 0 | Z24: =+'Balance Sheet'!O54 -> 7.4936061 | AA24: =+'Balance Sheet'!P54 -> 6.0494734 | AB24: =+'Balance Sheet'!Q54 -> 5.5387159 | AC24: =+'Balance Sheet'!R54 -> 5.8091286 | AD24: =+'Balance Sheet'!S54 -> -11.725956 | ... AL24: =+'Balance Sheet'!AA54 -> 15.987122
B25: Profitability ratios
B26: A$m June y/e | D26: =+'Income & Cash Flow'!L$4 -> FY22A | G26: =+'Income & Cash Flow'!O$4 -> FY23A | J26: =+'Income & Cash Flow'!R$4 -> FY24A | M26: =+'Income & Cash Flow'!U$4 -> FY25A | P26: =+'Income & Cash Flow'!X$4 -> FY26E | S26: =+'Income & Cash Flow'!AA$4 -> FY27E | U26: Segmental analysis
B27: Sales growth | C27: % | G27: =+'Income & Cash Flow'!O56 -> 0.50789327 | H27: =+'Income & Cash Flow'!P56 -> 0.38232455 | I27: =+'Income & Cash Flow'!Q56 -> 0.26721505 | J27: =+'Income & Cash Flow'!R56 -> 0.32106515 | K27: =+'Income & Cash Flow'!S56 -> 0.26804444 | L27: =+'Income & Cash Flow'!T56 -> 0.2797186 | M27: =+'Income & Cash Flow'!U56 -> 0.27400399 | N27: =+'Income & Cash Flow'!V56 -> 0.24864904 | ... S27: =+'Income & Cash Flow'!AA56 -> 0.1911543 | U27: A$m June y/e | W27: =+'Income & Cash Flow'!L$4 -> FY22A | Z27: =+'Income & Cash Flow'!O$4 -> FY23A | AC27: =+'Income & Cash Flow'!R$4 -> FY24A | AF27: =+'Income & Cash Flow'!U$4 -> FY25A | AI27: =+'Income & Cash Flow'!X$4 -> FY26E | AL27: =+'Income & Cash Flow'!AA$4 -> FY27E
B28: Adj. Ebitda growth | C28: % | G28: =+'Income & Cash Flow'!O59 -> 0.35023041 | H28: =+'Income & Cash Flow'!P59 -> 0.73943662 | I28: =+'Income & Cash Flow'!Q59 -> 0.33112583 | J28: =+'Income & Cash Flow'!R59 -> 0.52901024 | K28: =+'Income & Cash Flow'!S59 -> 0.27846154 | L28: =+'Income & Cash Flow'!T59 -> 0.66870647 | M28: =+'Income & Cash Flow'!U59 -> 0.45354911 | N28: =+'Income & Cash Flow'!V59 -> 0.34386748 | ... S28: =+'Income & Cash Flow'!AA59 -> 0.32199265 | U28: Australia network | V28: A$m | W28: =+Segments!L10 -> 535.4 | X28: =+Segments!M10 -> 334.9 | Y28: =+Segments!N10 -> 368 | Z28: =+Segments!O10 -> 702.9 | AA28: =+Segments!P10 -> 438.6 | AB28: =+Segments!Q10 -> 456 | AC28: =+Segments!R10 -> 894.6 | AD28: =+Segments!S10 -> 538.24 | ... AL28: =+Segments!AA10 -> 1501.9638
B29: Adj. NPAT growth | C29: % | G29: =+'Income & Cash Flow'!O63 -> -0.0625 | H29: =+'Income & Cash Flow'!P63 -> 3.2222222 | I29: =+'Income & Cash Flow'!Q63 -> -0.095238095 | J29: =+'Income & Cash Flow'!R63 -> 0.9 | K29: =+'Income & Cash Flow'!S63 -> 0.92131579 | L29: =+'Income & Cash Flow'!T63 -> 2.7763158 | M29: =+'Income & Cash Flow'!U63 -> 1.5396491 | N29: =+'Income & Cash Flow'!V63 -> 0.49350195 | ... S29: =+'Income & Cash Flow'!AA63 -> 0.53694344 | U29: Singapore master | V29: A$m | W29: =+Segments!L11 -> 31.4 | X29: =+Segments!M11 -> 21.5 | Y29: =+Segments!N11 -> 21.6 | Z29: =+Segments!O11 -> 43.1 | AA29: =+Segments!P11 -> 22.2 | AB29: =+Segments!Q11 -> 24.2 | AC29: =+Segments!R11 -> 46.4 | AD29: =+Segments!S11 -> 30.194 | ... AL29: =+Segments!AA11 -> 85.56575
U30: Japan master | V30: A$m | W30: =+Segments!L12 -> 5.8 | X30: =+Segments!M12 -> 3.2 | Y30: =+Segments!N12 -> 3.8 | Z30: =+Segments!O12 -> 7 | AA30: =+Segments!P12 -> 4.2 | AB30: =+Segments!Q12 -> 3.7 | AC30: =+Segments!R12 -> 7.9 | AD30: =+Segments!S12 -> 4.606 | ... AL30: =+Segments!AA12 -> 14.266867
B31: Adj. Ebitda margin | C31: % | D31: =+'Income & Cash Flow'!L80 -> 0.12631554 | E31: =+'Income & Cash Flow'!M80 -> 0.11717622 | F31: =+'Income & Cash Flow'!N80 -> 0.1095322 | G31: =+'Income & Cash Flow'!O80 -> 0.1131082 | H31: =+'Income & Cash Flow'!P80 -> 0.14744772 | I31: =+'Income & Cash Flow'!Q80 -> 0.11505635 | J31: =+'Income & Cash Flow'!R80 -> 0.13091224 | K31: =+'Income & Cash Flow'!S80 -> 0.14865902 | ... S31: =+'Income & Cash Flow'!AA80 -> 0.17100642 | U31: USA corporate | V31: A$m | W31: =+Segments!L13 -> 2.5 | X31: =+Segments!M13 -> 1.5 | Y31: =+Segments!N13 -> 4.5 | Z31: =+Segments!O13 -> 6 | AA31: =+Segments!P13 -> 5.6 | AB31: =+Segments!Q13 -> 5.234 | AC31: =+Segments!R13 -> 10.834 | AD31: =+Segments!S13 -> 4.907 | ... AL31: =+Segments!AA13 -> 19.490138
B32: Adj. NPAT margin | C32: % | D32: =+'Income & Cash Flow'!L81 -> 0.018627177 | E32: =+'Income & Cash Flow'!M81 -> 0.0074266617 | F32: =+'Income & Cash Flow'!N81 -> 0.015232955 | G32: =+'Income & Cash Flow'!O81 -> 0.011581044 | H32: =+'Income & Cash Flow'!P81 -> 0.022684265 | I32: =+'Income & Cash Flow'!Q81 -> 0.010875974 | J32: =+'Income & Cash Flow'!R81 -> 0.016656244 | K32: =+'Income & Cash Flow'!S81 -> 0.034370748 | ... S32: =+'Income & Cash Flow'!AA81 -> 0.049776486 | U32: Network sales | V32: A$m | W32: =SUM(W28:W31) -> 575.1 | X32: =SUM(X28:X31) -> 361.1 | Y32: =SUM(Y28:Y31) -> 397.9 | Z32: =SUM(Z28:Z31) -> 759 | AA32: =SUM(AA28:AA31) -> 470.6 | AB32: =SUM(AB28:AB31) -> 489.134 | AC32: =SUM(AC28:AC31) -> 959.734 | AD32: =SUM(AD28:AD31) -> 577.947 | ... AL32: =SUM(AL28:AL31) -> 1621.2865
U33: Australia corporate | V33: A$m | W33: =+Segments!L16 -> 139.217 | X33: =+Segments!M16 -> 100.639 | Y33: =+Segments!N16 -> 111.336 | Z33: =+Segments!O16 -> 211.975 | AA33: =+Segments!P16 -> 136.574 | AB33: =+Segments!Q16 -> 142.303 | AC33: =+Segments!R16 -> 278.877 | AD33: =+Segments!S16 -> 176.051 | ... AL33: =+Segments!AA16 -> 526.34527
B34: ROE | C34: % | D34: =+'Balance Sheet'!L73 -> 0.043412788 | E34: =+'Balance Sheet'!M73 -> 0 | F34: =+'Balance Sheet'!N73 -> 0 | G34: =+'Balance Sheet'!O73 -> 0.035489519 | H34: =+'Balance Sheet'!P73 -> 0.046928064 | I34: =+'Balance Sheet'!Q73 -> 0.0088792515 | J34: =+'Balance Sheet'!R73 -> 0.025795123 | K34: =+'Balance Sheet'!S73 -> 0.020235251 | ... S34: =+'Balance Sheet'!AA73 -> 0.076635781 | U34: APAC royalty | V34: A$m | W34: =+Segments!L17+Segments!L18+Segments!L19+Segments!L20 -> 29.426 | X34: =+Segments!M17+Segments!M18+Segments!M19+Segments!M20 -> 18.567 | Y34: =+Segments!N17+Segments!N18+Segments!N19+Segments!N20 -> 21.422 | Z34: =+Segments!O17+Segments!O18+Segments!O19+Segments!O20 -> 39.989 | AA34: =+Segments!P17+Segments!P18+Segments!P19+Segments!P20 -> 24.7 | AB34: =+Segments!Q17+Segments!Q18+Segments!Q19+Segments!Q20 -> 27.803 | AC34: =+Segments!R17+Segments!R18+Segments!R19+Segments!R20 -> 52.503 | AD34: =+Segments!S17+Segments!S18+Segments!S19+Segments!S20 -> 33.136 | ... AL34: =+Segments!AA17+Segments!AA18+Segments!AA19+Segments!AA20 -> 98.172727
B35: ROCE | C35: % | D35: =+'Balance Sheet'!L74 -> 0.039340715 | E35: =+'Balance Sheet'!M74 -> 0 | F35: =+'Balance Sheet'!N74 -> 0 | G35: =+'Balance Sheet'!O74 -> 0.016320517 | H35: =+'Balance Sheet'!P74 -> 0.033266045 | I35: =+'Balance Sheet'!Q74 -> 0.01131359 | J35: =+'Balance Sheet'!R74 -> 0.032553369 | K35: =+'Balance Sheet'!S74 -> 0.020713178 | ... S35: =+'Balance Sheet'!AA74 -> 0.070155979 | U35: USA corporate | V35: A$m | W35: =+Segments!L21 -> 2.5 | X35: =+Segments!M21 -> 1.5 | Y35: =+Segments!N21 -> 4.5 | Z35: =+Segments!O21 -> 6 | AA35: =+Segments!P21 -> 5.6 | AB35: =+Segments!Q21 -> 5.234 | AC35: =+Segments!R21 -> 10.834 | AD35: =+Segments!S21 -> 3.232 | ... AL35: =+Segments!AA21 -> 17.317443
B36: Cash conversion | C36: % | D36: =+'Income & Cash Flow'!L136 -> 0.90525346 | E36: =+'Income & Cash Flow'!M136 -> 0.96295775 | F36: =+'Income & Cash Flow'!N136 -> 1.4088079 | G36: =+'Income & Cash Flow'!O136 -> 1.1927304 | H36: =+'Income & Cash Flow'!P136 -> 0.57149798 | I36: =+'Income & Cash Flow'!Q136 -> 1.1268159 | J36: =+'Income & Cash Flow'!R136 -> 0.82064732 | K36: =+'Income & Cash Flow'!S136 -> 0.60782823 | ... S36: =+'Income & Cash Flow'!AA136 -> 1.004422 | U36: Group revenue | V36: A$m | W36: =SUM(W33:W35) -> 171.143 | X36: =SUM(X33:X35) -> 120.706 | Y36: =SUM(Y33:Y35) -> 137.258 | Z36: =SUM(Z33:Z35) -> 257.964 | AA36: =SUM(AA33:AA35) -> 166.874 | AB36: =SUM(AB33:AB35) -> 175.34 | AC36: =SUM(AC33:AC35) -> 342.214 | AD36: =SUM(AD33:AD35) -> 212.419 | ... AL36: =SUM(AL33:AL35) -> 641.83544
B37: FCF Conversion | C37: % | D37: =+'Income & Cash Flow'!L137 -> -0.57990783 | E37: =+'Income & Cash Flow'!M137 -> -0.55415493 | F37: =+'Income & Cash Flow'!N137 -> -0.41596026 | G37: =+'Income & Cash Flow'!O137 -> -0.48293515 | H37: =+'Income & Cash Flow'!P137 -> -0.030769231 | I37: =+'Income & Cash Flow'!Q137 -> 0.041691542 | J37: =+'Income & Cash Flow'!R137 -> 0.0017410714 | K37: =+'Income & Cash Flow'!S137 -> -0.46738235 | ... S37: =+'Income & Cash Flow'!AA137 -> 0.422232 | U37: Adj. Australia segment | V37: A$m | W37: =+Segments!L24 -> 18.3 | X37: =+Segments!M24 -> 13.4 | Y37: =+Segments!N24 -> 17.3 | Z37: =+Segments!O24 -> 30.7 | AA37: =+Segments!P24 -> 23.1 | AB37: =+Segments!Q24 -> 22.5 | AC37: =+Segments!R24 -> 45.6 | AD37: =+Segments!S24 -> 31.781 | ... AL37: =+Segments!AA24 -> 107.14617
U38: Adj. USA segment | V38: A$m | W38: =+Segments!L25 -> -2.9 | X38: =+Segments!M25 -> -1.7 | Y38: =+Segments!N25 -> -2.596 | Z38: =+Segments!O25 -> -4.296 | AA38: =+Segments!P25 -> -3.1 | AB38: =+Segments!Q25 -> -3.444 | AC38: =+Segments!R25 -> -6.544 | AD38: =+Segments!S25 -> -5.014 | ... AL38: =+Segments!AA25 -> -17.938269
B39: Cashflow Statement | U39: Adj. Segment Ebitda | V39: A$m | W39: =SUM(W37:W38) -> 15.4 | X39: =SUM(X37:X38) -> 11.7 | Y39: =SUM(Y37:Y38) -> 14.704 | Z39: =SUM(Z37:Z38) -> 26.404 | AA39: =SUM(AA37:AA38) -> 20 | AB39: =SUM(AB37:AB38) -> 19.056 | AC39: =SUM(AC37:AC38) -> 39.056 | AD39: =SUM(AD37:AD38) -> 26.767 | ... AL39: =SUM(AL37:AL38) -> 89.207897
B40: A$m June y/e | D40: =+'Income & Cash Flow'!L$4 -> FY22A | G40: =+'Income & Cash Flow'!O$4 -> FY23A | J40: =+'Income & Cash Flow'!R$4 -> FY24A | M40: =+'Income & Cash Flow'!U$4 -> FY25A | P40: =+'Income & Cash Flow'!X$4 -> FY26E | S40: =+'Income & Cash Flow'!AA$4 -> FY27E | U40: Share payments | V40: A$m | W40: =+Segments!L28 -> -1.436 | X40: =+Segments!M28 -> -2.8 | Y40: =+Segments!N28 -> -1.44 | Z40: =+Segments!O28 -> -4.24 | AA40: =+Segments!P28 -> -3.6 | AB40: =+Segments!Q28 -> -7.5 | AC40: =+Segments!R28 -> -11.1 | AD40: =+Segments!S28 -> -4.587 | ... AL40: =+Segments!AA28 -> -7
B41: Operating cash flow | C41: A$m | D41: =+'Income & Cash Flow'!L98 -> 19.644 | G41: =+'Income & Cash Flow'!O98 -> 34.947 | J41: =+'Income & Cash Flow'!R98 -> 36.765 | M41: =+'Income & Cash Flow'!U98 -> 57.327 | P41: =+'Income & Cash Flow'!X98 -> 91.663678 | S41: =+'Income & Cash Flow'!AA98 -> 110.24333 | U41: Rent and outgoings | V41: A$m | W41: =+Segments!L29 -> 8 | X41: =+Segments!M29 -> 5.7 | Y41: =+Segments!N29 -> 5.5 | Z41: =+Segments!O29 -> 11.2 | AA41: =+Segments!P29 -> 8.2 | AB41: =+Segments!Q29 -> 8.9 | AC41: =+Segments!R29 -> 17.1 | AD41: =+Segments!S29 -> 9.398 | ... AL41: =+Segments!AA29 -> 27.550087
B42: FCF | C42: A$m | D42: =+'Income & Cash Flow'!L134 -> -12.584 | G42: =+'Income & Cash Flow'!O134 -> -14.15 | J42: =+'Income & Cash Flow'!R134 -> 0.078 | M42: =+'Income & Cash Flow'!U134 -> -19.509 | P42: =+'Income & Cash Flow'!X134 -> 31.663678 | S42: =+'Income & Cash Flow'!AA134 -> 46.343333 | U42: Other | V42: A$m | W42: =+Segments!L30 -> -0.264 | X42: =+Segments!M30 -> -0.4 | Y42: =+Segments!N30 -> -3.664 | Z42: =+Segments!O30 -> -4.064 | AA42: =+Segments!P30 -> 0.1 | AB42: =+Segments!Q30 -> -0.356 | AC42: =+Segments!R30 -> -0.256 | AD42: =+Segments!S30 -> 0 | ... AL42: =+Segments!AA30 -> 0
B43: Investing cash flow | C43: A$m | D43: =+'Income & Cash Flow'!L106 -> -31.698 | G43: =+'Income & Cash Flow'!O106 -> -48.403 | J43: =+'Income & Cash Flow'!R106 -> -311.818 | M43: =+'Income & Cash Flow'!U106 -> -34.551 | P43: =+'Income & Cash Flow'!X106 -> -60 | S43: =+'Income & Cash Flow'!AA106 -> -63.9 | U43: Adj. Group Ebitda | V43: A$m | W43: =SUM(W39:W42) -> 21.7 | X43: =SUM(X39:X42) -> 14.2 | Y43: =SUM(Y39:Y42) -> 15.1 | Z43: =SUM(Z39:Z42) -> 29.3 | AA43: =SUM(AA39:AA42) -> 24.7 | AB43: =SUM(AB39:AB42) -> 20.1 | AC43: =SUM(AC39:AC42) -> 44.8 | AD43: =SUM(AD39:AD42) -> 31.578 | ... AL43: =SUM(AL39:AL42) -> 109.75798
B44: Financing cash flow | C44: A$m | D44: =+'Income & Cash Flow'!L119 -> 4.39 | G44: =+'Income & Cash Flow'!O119 -> -4.467 | J44: =+'Income & Cash Flow'!R119 -> 254.934 | M44: =+'Income & Cash Flow'!U119 -> 0.679 | P44: =+'Income & Cash Flow'!X119 -> -30.798962 | S44: =+'Income & Cash Flow'!AA119 -> -32.277803
B45: Net change in cash | C45: A$m | D45: =+D44+D43+D41 -> -7.664 | G45: =+G44+G43+G41 -> -17.923 | J45: =+J44+J43+J41 -> -20.119 | M45: =+M44+M43+M41 -> 23.455 | P45: =+P44+P43+P41 -> 0.86471543 | S45: =+S44+S43+S41 -> 14.06553 | U45: Adj. Australia margin | V45: % | W45: =+W37/SUM(W33:W34) -> 0.10851325 | X45: =+X37/SUM(X33:X34) -> 0.11241045 | Y45: =+Y37/SUM(Y33:Y34) -> 0.1303123 | Z45: =+Z37/SUM(Z33:Z34) -> 0.1218428 | AA45: =+AA37/SUM(AA33:AA34) -> 0.1432345 | AB45: =+AB37/SUM(AB33:AB34) -> 0.13227047 | AC45: =+AC37/SUM(AC33:AC34) -> 0.13760637 | AD45: =+AD37/SUM(AD33:AD34) -> 0.15192627 | ... AL45: =+AL37/SUM(AL33:AL34) -> 0.17156618
B46: Closing cash balance | C46: A$m | D46: =+'Income & Cash Flow'!L124 -> 54.427 | G46: =+'Income & Cash Flow'!O124 -> 36.504 | J46: =+'Income & Cash Flow'!R124 -> 16.385 | M46: =+'Income & Cash Flow'!U124 -> 39.675 | P46: =+'Income & Cash Flow'!X124 -> 40.539715 | S46: =+'Income & Cash Flow'!AA124 -> 54.605246 | U46: Adj. USA margin | V46: % | W46: =+W38/W35 -> -1.16 | X46: =+X38/X35 -> -1.1333333 | Y46: =+Y38/Y35 -> -0.57688889 | Z46: =+Z38/Z35 -> -0.716 | AA46: =+AA38/AA35 -> -0.55357143 | AB46: =+AB38/AB35 -> -0.65800535 | AC46: =+AC38/AC35 -> -0.60402437 | AD46: =+AD38/AD35 -> -1.5513614 | ... AL46: =+AL38/AL35 -> -1.0358498
U47: Adj. Segment margin | V47: % | W47: =+W39/W36 -> 0.08998323 | X47: =+X39/X36 -> 0.09692973 | Y47: =+Y39/Y36 -> 0.10712672 | Z47: =+Z39/Z36 -> 0.10235537 | AA47: =+AA39/AA36 -> 0.11985091 | AB47: =+AB39/AB36 -> 0.10868028 | AC47: =+AC39/AC36 -> 0.11412742 | AD47: =+AD39/AD36 -> 0.12601039 | ... AL47: =+AL39/AL36 -> 0.13898874
B48: Balance Sheet | U48: Adj. Group margin | V48: % | W48: =+W43/W36 -> 0.12679455 | X48: =+X43/X36 -> 0.11764121 | Y48: =+Y43/Y36 -> 0.1100118 | Z48: =+Z43/Z36 -> 0.11358174 | AA48: =+AA43/AA36 -> 0.14801587 | AB48: =+AB43/AB36 -> 0.11463442 | AC48: =+AC43/AC36 -> 0.13091224 | AD48: =+AD43/AD36 -> 0.14865902 | ... AL48: =+AL43/AL36 -> 0.17100642
B49: A$m June y/e | D49: =+'Income & Cash Flow'!L$4 -> FY22A | G49: =+'Income & Cash Flow'!O$4 -> FY23A | J49: =+'Income & Cash Flow'!R$4 -> FY24A | M49: =+'Income & Cash Flow'!U$4 -> FY25A | P49: =+'Income & Cash Flow'!X$4 -> FY26E | S49: =+'Income & Cash Flow'!AA$4 -> FY27E
B50: Cash | C50: A$m | D50: =+'Balance Sheet'!L6 -> 54.427 | E50: =+'Balance Sheet'!M6 -> 0 | F50: =+'Balance Sheet'!N6 -> 0 | G50: =+'Balance Sheet'!O6 -> 36.504 | H50: =+'Balance Sheet'!P6 -> 13.619 | I50: =+'Balance Sheet'!Q6 -> 16.385 | J50: =+'Balance Sheet'!R6 -> 16.385 | K50: =+'Balance Sheet'!S6 -> 16.882 | ... S50: =+'Balance Sheet'!AA6 -> 54.605246 | U50: Valuation
B51: Receivables | C51: A$m | D51: =+'Balance Sheet'!L7 -> 16.352 | E51: =+'Balance Sheet'!M7 -> 0 | F51: =+'Balance Sheet'!N7 -> 0 | G51: =+'Balance Sheet'!O7 -> 23.947 | H51: =+'Balance Sheet'!P7 -> 21.198 | I51: =+'Balance Sheet'!Q7 -> 26.02 | J51: =+'Balance Sheet'!R7 -> 26.02 | K51: =+'Balance Sheet'!S7 -> 18.852 | ... S51: =+'Balance Sheet'!AA7 -> 36.366779 | U51: DCF valuation | AC51: PE Multiple
B52: PPE | C52: A$m | D52: =+'Balance Sheet'!L15 -> 36.563 | E52: =+'Balance Sheet'!M15 -> 0 | F52: =+'Balance Sheet'!N15 -> 0 | G52: =+'Balance Sheet'!O15 -> 69.486 | H52: =+'Balance Sheet'!P15 -> 77.953 | I52: =+'Balance Sheet'!Q15 -> 87.63 | J52: =+'Balance Sheet'!R15 -> 87.63 | K52: =+'Balance Sheet'!S15 -> 103.028 | ... S52: =+'Balance Sheet'!AA15 -> 192.20474 | U52: EV (A$m) | W52: =+Valuation!C43 -> 2138.452 | AC52: =+Valuation!E43 -> Blended Ebitda (A$m) | AL52: =+Valuation!H43 -> 86.906481
B53: Intangibles | C53: A$m | D53: =+'Balance Sheet'!L17 -> 15.41 | E53: =+'Balance Sheet'!M17 -> 0 | F53: =+'Balance Sheet'!N17 -> 0 | G53: =+'Balance Sheet'!O17 -> 15.202 | H53: =+'Balance Sheet'!P17 -> 11.697 | I53: =+'Balance Sheet'!Q17 -> 10.586 | J53: =+'Balance Sheet'!R17 -> 10.586 | K53: =+'Balance Sheet'!S17 -> 19.153 | ... S53: =+'Balance Sheet'!AA17 -> 4.2900725 | U53: Net Debt (A$m) | W53: =+Valuation!C44 -> 58.29346 | AC53: Applied multiple (x) | AL53: =+Valuation!H45 -> 30
B54: Other assets | C54: A$m | D54: =+D55-SUM(D50:D53) -> 125.677 | E54: =+E55-SUM(E50:E53) -> 0 | F54: =+F55-SUM(F50:F53) -> 0 | G54: =+G55-SUM(G50:G53) -> 179.368 | H54: =+H55-SUM(H50:H53) -> 206.047 | I54: =+I55-SUM(I50:I53) -> 521.176 | J54: =+J55-SUM(J50:J53) -> 521.176 | K54: =+K55-SUM(K50:K53) -> 537.054 | ... S54: =+S55-SUM(S50:S53) -> 585.44864 | U54: Equity value (A$m) | W54: =+Valuation!C45 -> 2080.1585 | AC54: Multiple Valuation (A$/sh) | AL54: =+Valuation!H46 -> 24.780161
B55: Total assets | C55: A$m | D55: =+'Balance Sheet'!L23 -> 248.429 | E55: =+'Balance Sheet'!M23 -> 0 | F55: =+'Balance Sheet'!N23 -> 0 | G55: =+'Balance Sheet'!O23 -> 324.507 | H55: =+'Balance Sheet'!P23 -> 330.514 | I55: =+'Balance Sheet'!Q23 -> 661.797 | J55: =+'Balance Sheet'!R23 -> 661.797 | K55: =+'Balance Sheet'!S23 -> 694.969 | ... S55: =+'Balance Sheet'!AA23 -> 872.91548 | U55: EFPO (m) | W55: =+Valuation!C46 -> 102.86055
B56: Payables | C56: A$m | D56: =+'Balance Sheet'!L25 -> 28.008 | E56: =+'Balance Sheet'!M25 -> 0 | F56: =+'Balance Sheet'!N25 -> 0 | G56: =+'Balance Sheet'!O25 -> 32.635 | H56: =+'Balance Sheet'!P25 -> 22.035 | I56: =+'Balance Sheet'!Q25 -> 39.387 | J56: =+'Balance Sheet'!R25 -> 39.387 | K56: =+'Balance Sheet'!S25 -> 30.198 | ... S56: =+'Balance Sheet'!AA25 -> 58.017867 | U56: Intrinsic value (A$/sh) | W56: =+Valuation!C47 -> 20.223094
B57: Borrowings | C57: A$m | D57: =+'Balance Sheet'!L27+'Balance Sheet'!L34 -> 3.358 | E57: =+'Balance Sheet'!M27+'Balance Sheet'!M34 -> 0 | F57: =+'Balance Sheet'!N27+'Balance Sheet'!N34 -> 0 | G57: =+'Balance Sheet'!O27+'Balance Sheet'!O34 -> 3 | H57: =+'Balance Sheet'!P27+'Balance Sheet'!P34 -> 3 | I57: =+'Balance Sheet'!Q27+'Balance Sheet'!Q34 -> 0 | J57: =+'Balance Sheet'!R27+'Balance Sheet'!R34 -> 0 | K57: =+'Balance Sheet'!S27+'Balance Sheet'!S34 -> 0 | ... S57: =+'Balance Sheet'!AA27+'Balance Sheet'!AA34 -> 0 | U57: DCF Valuation (A$/sh) | W57: =+Valuation!C48 -> 22.265626
B58: Other | C58: A$m | D58: =+D59-SUM(D56:D57) -> 135.964 | E58: =+E59-SUM(E56:E57) -> 0 | F58: =+F59-SUM(F56:F57) -> 0 | G58: =+G59-SUM(G56:G57) -> 200.907 | H58: =+H59-SUM(H56:H57) -> 231.494 | I58: =+I59-SUM(I56:I57) -> 268.431 | J58: =+J59-SUM(J56:J57) -> 268.431 | K58: =+K59-SUM(K56:K57) -> 297.138 | ... S58: =+S59-SUM(S56:S57) -> 382.03839
B59: Total liabilities | C59: A$m | D59: =+'Balance Sheet'!L39 -> 167.33 | E59: =+'Balance Sheet'!M39 -> 0 | F59: =+'Balance Sheet'!N39 -> 0 | G59: =+'Balance Sheet'!O39 -> 236.542 | H59: =+'Balance Sheet'!P39 -> 256.529 | I59: =+'Balance Sheet'!Q39 -> 307.818 | J59: =+'Balance Sheet'!R39 -> 307.818 | K59: =+'Balance Sheet'!S39 -> 327.336 | ... S59: =+'Balance Sheet'!AA39 -> 440.05625 | U59: Valuation
B60: Net assets | C60: A$m | D60: =+'Balance Sheet'!L41 -> 81.099 | E60: =+'Balance Sheet'!M41 -> 0 | F60: =+'Balance Sheet'!N41 -> 0 | G60: =+'Balance Sheet'!O41 -> 87.965 | H60: =+'Balance Sheet'!P41 -> 73.985 | I60: =+'Balance Sheet'!Q41 -> 353.979 | J60: =+'Balance Sheet'!R41 -> 353.979 | K60: =+'Balance Sheet'!S41 -> 367.633 | ... S60: =+'Balance Sheet'!AA41 -> 432.85923 | U60: Target price (A$/sh) | W60: =+Valuation!S10 -> 23.5
B62: Check | D62: =+D21-'Income & Cash Flow'!L40 -> 0 | E62: =+E21-'Income & Cash Flow'!M40 -> 0 | F62: =+F21-'Income & Cash Flow'!N40 -> 0 | G62: =+G21-'Income & Cash Flow'!O40 -> 0 | H62: =+H21-'Income & Cash Flow'!P40 -> 0 | I62: =+I21-'Income & Cash Flow'!Q40 -> 0 | J62: =+J21-'Income & Cash Flow'!R40 -> 0 | K62: =+K21-'Income & Cash Flow'!S40 -> 0 | ... S62: =+S21-'Income & Cash Flow'!AA40 -> 0
W63: - | Z63: - | AC63: - | AF63: - | AI63: - | AL63: -
B64: Marketing
B66: Key financials | D66: =+'Income & Cash Flow'!L$4 -> FY22A | G66: =+'Income & Cash Flow'!O$4 -> FY23A | J66: =+'Income & Cash Flow'!R$4 -> FY24A | M66: =+'Income & Cash Flow'!U$4 -> FY25A | P66: =+'Income & Cash Flow'!X$4 -> FY26E | S66: =+'Income & Cash Flow'!AA$4 -> FY27E
B67: Revenue | C67: A$m | D67: =+D10 -> 171.792 | G67: =+G10 -> 259.044 | J67: =+J10 -> 342.214 | M67: =+M10 -> 435.982 | P67: =+P10 -> 538.83484 | S67: =+S10 -> 641.83544
B68: Adj. Ebitda | C68: A$m | D68: =+'Income & Cash Flow'!L20 -> 21.7 | E68: =+'Income & Cash Flow'!M20 -> 14.2 | F68: =+'Income & Cash Flow'!N20 -> 15.1 | G68: =+'Income & Cash Flow'!O20 -> 29.3 | H68: =+'Income & Cash Flow'!P20 -> 24.7 | I68: =+'Income & Cash Flow'!Q20 -> 20.1 | J68: =+'Income & Cash Flow'!R20 -> 44.8 | K68: =+'Income & Cash Flow'!S20 -> 31.578 | ... S68: =+'Income & Cash Flow'!AA20 -> 109.75798
B69: Adj. Ebitda margin | C69: % | D69: =+D31 -> 0.12631554 | G69: =+G31 -> 0.1131082 | J69: =+J31 -> 0.13091224 | M69: =+M31 -> 0.14936167 | P69: =+P31 -> 0.15408182 | S69: =+S31 -> 0.17100642
B70: Adj. NPAT | C70: A$m | D70: =+'Income & Cash Flow'!L45 -> 3.919 | E70: =+'Income & Cash Flow'!M45 -> -1.111 | F70: =+'Income & Cash Flow'!N45 -> -0.757 | G70: =+'Income & Cash Flow'!O45 -> -1.868 | H70: =+'Income & Cash Flow'!P45 -> -4.347 | I70: =+'Income & Cash Flow'!Q45 -> -9.331 | J70: =+'Income & Cash Flow'!R45 -> -13.678 | K70: =+'Income & Cash Flow'!S45 -> 8.119 | ... S70: =+'Income & Cash Flow'!AA45 -> 31.948313
B71: Adj. NPAT margin | C71: % | D71: =+D32 -> 0.018627177 | G71: =+G32 -> 0.011581044 | J71: =+J32 -> 0.016656244 | M71: =+M32 -> 0.033203206 | P71: =+P32 -> 0.038577526 | S71: =+S32 -> 0.049776486
B73: FCF | C73: A$m | D73: =+D42 -> -12.584 | G73: =+G42 -> -14.15 | J73: =+J42 -> 0.078 | M73: =+M42 -> -19.509 | P73: =+P42 -> 31.663678 | S73: =+S42 -> 46.343333
B74: Net debt | C74: A$m | D74: =+W22 -> -51.069 | G74: =+Z22 -> -33.504 | J74: =+AC22 -> -294.48 | M74: =+AF22 -> -281.743 | P74: =+AI22 -> -282.60772 | S74: =+AO24 -> 0
B75: Dividend yield | C75: % | D75: =+W14 -> 0 | G75: =+Z14 -> 0 | J75: =+AC14 -> 0 | M75: =+AF14 -> 0 | P75: =+AI14 -> 0 | S75: =+AO16 -> 0
B76: PE | C76: x | D76: =+W16 -> 0 | G76: =+Z16 -> 0 | J76: =+AC16 -> 358.03623 | M76: =+AF16 -> 174.48424 | P76: =+AI16 -> 118.01771 | S76: =+AO18 -> 0
B77: EV / Ebitda | C77: x | D77: =+W18 -> 95.793605 | G77: =+Z18 -> 73.427619 | J77: =+AC18 -> 44.32644 | M77: =+AF18 -> 39.549163 | P77: =+AI18 -> 30.250261 | S77: =+AO20 -> 0

Sheet Income & Cash Flow
B1: =+'GYG model ->'!D2 -> Guzman y Gomez (GYG.ASX)
B2: Income & Cash Flow
O3: Pro Forma
B4: Year-end 30th June (A$m) | D4: 1H20A | E4: 2H20A | F4: FY20A | G4: 1H21A | H4: 2H21A | I4: FY21A | J4: 1H22A | K4: 2H22A | L4: FY22A | M4: 1H23A | N4: 2H23A | O4: FY23A | P4: 1H24A | Q4: 2H24A | R4: FY24A | S4: 1H25A | T4: 2H25A | U4: FY25A | V4: 1H26E | W4: 2H26E | X4: FY26E | Y4: 1H27E | Z4: 2H27E | AA4: FY27E | AB4: 1H28E | AC4: 2H28E | AD4: FY28E | AE4: 1H29E | AF4: 2H29E | AG4: FY29E | AH4: 1H30E | AI4: 2H30E | AJ4: FY30E | AK4: 1H31E | AL4: 2H31E | AM4: FY31E | AN4: 1H32E | AO4: 2H32E | AP4: FY32E | AQ4: 1H33E | AR4: 2H33E | AS4: FY33E | AT4: 1H34E | AU4: 2H34E | AV4: FY34E | AW4: 1H35E | AX4: 2H35E | AY4: FY35E
B5: Statement of Income
B6: Revenue | I6: 119.531 | L6: 171.792 | M6: 121.185 | N6: =+O6-M6 -> 137.859 | O6: 259.044 | P6: 167.517 | Q6: =+R6-P6 -> 174.697 | R6: 342.214 | S6: 212.419 | T6: =+U6-S6 -> 223.563 | U6: 435.982 | V6: =+Segments!V22 -> 265.23678 | W6: =+Segments!W22 -> 273.59806 | X6: =+Segments!X22 -> 538.83484 | Y6: =+Segments!Y22 -> 316.62802 | Z6: =+Segments!Z22 -> 325.20742 | AA6: =+Segments!AA22 -> 641.83544 | AB6: =+Segments!AB22 -> 373.19481 | AC6: =+Segments!AC22 -> 380.40127 | ... AY6: =+Segments!AY22 -> 1672.8283
B7: Other | I7: 0 | L7: 0 | M7: 0 | N7: =+O7-M7 -> 0 | O7: 0 | P7: 0 | Q7: =+R7-P7 -> 0 | R7: 0 | S7: 0 | T7: =+U7-S7 -> 0 | U7: 0 | V7: 0 | W7: 0 | X7: =+W7+V7 -> 0 | Y7: 0 | Z7: 0 | AA7: =+Z7+Y7 -> 0 | AB7: 0 | AC7: 0 | AD7: =+AC7+AB7 -> 0 | AE7: 0 | AF7: 0 | AG7: =+AF7+AE7 -> 0 | AH7: 0 | AI7: 0 | AJ7: =+AI7+AH7 -> 0 | AK7: 0 | AL7: 0 | AM7: =+AL7+AK7 -> 0 | AN7: 0 | AO7: 0 | AP7: =+AO7+AN7 -> 0 | AQ7: 0 | AR7: 0 | AS7: =+AR7+AQ7 -> 0 | AT7: 0 | AU7: 0 | AV7: =+AU7+AT7 -> 0 | AW7: 0 | AX7: 0 | AY7: =+AX7+AW7 -> 0
B8: Total revenue | I8: =I7+I6 -> 119.531 | L8: =L7+L6 -> 171.792 | M8: =M7+M6 -> 121.185 | N8: =N7+N6 -> 137.859 | O8: =O7+O6 -> 259.044 | P8: =P7+P6 -> 167.517 | Q8: =Q7+Q6 -> 174.697 | R8: =R7+R6 -> 342.214 | S8: =S7+S6 -> 212.419 | ... U8: =U7+U6 -> 435.982 | V8: =+V7+V6 -> 265.23678 | W8: =+W7+W6 -> 273.59806 | X8: =+X7+X6 -> 538.83484 | Y8: =+Y7+Y6 -> 316.62802 | Z8: =+Z7+Z6 -> 325.20742 | AA8: =+AA7+AA6 -> 641.83544 | AB8: =+AB7+AB6 -> 373.19481 | AC8: =+AC7+AC6 -> 380.40127 | ... AY8: =+AY7+AY6 -> 1672.8283
B10: Other revenue and income | I10: 11.429 | L10: 12.787 | M10: 9.792 | N10: =+O10-M10 -> 7.933 | O10: 17.725 | P10: 11.719 | Q10: =+R10-P10 -> 11.055 | R10: 22.774 | S10: 14.711 | T10: =+U10-S10 -> 17.313 | U10: 32.024 | V10: =+Segments!V259 -> 11.140007 | W10: =+Segments!W259 -> 11.650503 | X10: =+W10+V10 -> 22.790509 | Y10: =+Segments!Y259 -> 13.058918 | Z10: =+Segments!Z259 -> 13.544954 | AA10: =+Z10+Y10 -> 26.603873 | AB10: =+Segments!AB259 -> 15.010455 | AC10: =+Segments!AC259 -> 15.44467 | AD10: =+AC10+AB10 -> 30.455125 | AE10: =+Segments!AE259 -> 16.882749 | AF10: =+Segments!AF259 -> 17.296085 | AG10: =+AF10+AE10 -> 34.178834 | AH10: =+Segments!AH259 -> 18.830786 | AI10: =+Segments!AI259 -> 19.222709 | AJ10: =+AI10+AH10 -> 38.053494 | AK10: =+Segments!AK259 -> 21.318751 | AL10: =+Segments!AL259 -> 21.582391 | AM10: =+AL10+AK10 -> 42.901142 | AN10: =+Segments!AN259 -> 23.749568 | AO10: =+Segments!AO259 -> 23.979049 | AP10: =+AO10+AN10 -> 47.728617 | AQ10: =+Segments!AQ259 -> 26.326675 | AR10: =+Segments!AR259 -> 26.519699 | AS10: =+AR10+AQ10 -> 52.846373 | AT10: =+Segments!AT259 -> 29.058311 | AU10: =+Segments!AU259 -> 29.21247 | AV10: =+AU10+AT10 -> 58.270781 | AW10: =+Segments!AW259 -> 31.95319 | AX10: =+Segments!AX259 -> 32.065965 | AY10: =+AX10+AW10 -> 64.019155
B11: Cost of food and packaging | I11: -31.796 | L11: -44.194 | M11: -32.906 | N11: =+O11-M11 -> -37.522 | O11: -70.428 | P11: -43.237 | Q11: =+R11-P11 -> -44.343 | R11: -87.58 | S11: -55.071 | T11: =+U11-S11 -> -58.877 | U11: -113.948 | V11: =+Segments!V260 -> -61.957311 | W11: =+Segments!W260 -> -64.796535 | X11: =+W11+V11 -> -126.75385 | Y11: =+Segments!Y260 -> -72.629712 | Z11: =+Segments!Z260 -> -75.332896 | AA11: =+Z11+Y11 -> -147.96261 | AB11: =+Segments!AB260 -> -83.483562 | AC11: =+Segments!AC260 -> -85.898533 | AD11: =+AC11+AB11 -> -169.38209 | AE11: =+Segments!AE260 -> -93.896689 | AF11: =+Segments!AF260 -> -96.195537 | AG11: =+AF11+AE11 -> -190.09223 | AH11: =+Segments!AH260 -> -104.73107 | AI11: =+Segments!AI260 -> -106.91083 | AJ11: =+AI11+AH11 -> -211.6419 | AK11: =+Segments!AK260 -> -118.56837 | AL11: =+Segments!AL260 -> -120.03466 | AM11: =+AL11+AK11 -> -238.60304 | AN11: =+Segments!AN260 -> -132.08784 | AO11: =+Segments!AO260 -> -133.36414 | AP11: =+AO11+AN11 -> -265.45198 | AQ11: =+Segments!AQ260 -> -146.42092 | AR11: =+Segments!AR260 -> -147.49446 | AS11: =+AR11+AQ11 -> -293.91537 | AT11: =+Segments!AT260 -> -161.61344 | AU11: =+Segments!AU260 -> -162.47083 | AV11: =+AU11+AT11 -> -324.08427 | AW11: =+Segments!AW260 -> -177.71387 | AX11: =+Segments!AX260 -> -178.3411 | AY11: =+AX11+AW11 -> -356.05497
B12: Employee benefits expense | I12: -42.953 | L12: -65.13 | M12: -49.458 | N12: =+O12-M12 -> -53.711 | O12: -103.169 | P12: -67.015 | Q12: =+R12-P12 -> -86.718 | R12: -153.733 | S12: -89.003 | T12: =+U12-S12 -> -95.653 | U12: -184.656 | V12: =+Segments!V261 -> -108.75638 | W12: =+Segments!W261 -> -113.74019 | X12: =+W12+V12 -> -222.49656 | Y12: =+Segments!Y261 -> -127.49011 | Z12: =+Segments!Z261 -> -132.23512 | AA12: =+Z12+Y12 -> -259.72523 | AB12: =+Segments!AB261 -> -146.54234 | AC12: =+Segments!AC261 -> -150.78145 | AD12: =+AC12+AB12 -> -297.32379 | AE12: =+Segments!AE261 -> -164.82096 | AF12: =+Segments!AF261 -> -168.85623 | AG12: =+AF12+AE12 -> -333.67719 | AH12: =+Segments!AH261 -> -183.83903 | AI12: =+Segments!AI261 -> -187.66525 | AJ12: =+AI12+AH12 -> -371.50428 | AK12: =+Segments!AK261 -> -208.12825 | AL12: =+Segments!AL261 -> -210.70209 | AM12: =+AL12+AK12 -> -418.83034 | AN12: =+Segments!AN261 -> -231.85955 | AO12: =+Segments!AO261 -> -234.0999 | AP12: =+AO12+AN12 -> -465.95945 | AQ12: =+Segments!AQ261 -> -257.01903 | AR12: =+Segments!AR261 -> -258.90347 | AS12: =+AR12+AQ12 -> -515.9225 | AT12: =+Segments!AT261 -> -283.68714 | AU12: =+Segments!AU261 -> -285.19214 | AV12: =+AU12+AT12 -> -568.87928 | AW12: =+Segments!AW261 -> -311.94893 | AX12: =+Segments!AX261 -> -313.04992 | AY12: =+AX12+AW12 -> -624.99884
B13: Administrative expense | I13: =-61.741+42.953 -> -18.788 | L13: =-92.536+65.13 -> -27.406 | M13: =-68.504+49.458 -> -19.046 | N13: =+O13-M13 -> -22.93 | O13: =-145.145+103.169 -> -41.976 | P13: =-95.73+67.015 -> -28.715 | Q13: =+R13-P13 -> -31.88 | R13: -60.595 | S13: -25.865 | T13: =+U13-S13 -> -27.75 | U13: -53.615 | V13: =+Segments!V262 -> -42.86713 | W13: =+Segments!W262 -> -44.831537 | X13: =+W13+V13 -> -87.698668 | Y13: =+Segments!Y262 -> -50.251169 | Z13: =+Segments!Z262 -> -52.121453 | AA13: =+Z13+Y13 -> -102.37262 | AB13: =+Segments!AB262 -> -57.760749 | AC13: =+Segments!AC262 -> -59.431624 | AD13: =+AC13+AB13 -> -117.19237 | AE13: =+Segments!AE262 -> -64.965402 | AF13: =+Segments!AF262 -> -66.555933 | AG13: =+AF13+AE13 -> -131.52133 | AH13: =+Segments!AH262 -> -72.461513 | AI13: =+Segments!AI262 -> -73.969648 | AJ13: =+AI13+AH13 -> -146.43116 | AK13: =+Segments!AK262 -> -82.03529 | AL13: =+Segments!AL262 -> -83.049787 | AM13: =+AL13+AK13 -> -165.08508 | AN13: =+Segments!AN262 -> -91.389159 | AO13: =+Segments!AO262 -> -92.272209 | AP13: =+AO13+AN13 -> -183.66137 | AQ13: =+Segments!AQ262 -> -101.30595 | AR13: =+Segments!AR262 -> -102.04872 | AS13: =+AR13+AQ13 -> -203.35467 | AT13: =+Segments!AT262 -> -111.81739 | AU13: =+Segments!AU262 -> -112.41059 | AV13: =+AU13+AT13 -> -224.22798 | AW13: =+Segments!AW262 -> -122.95698 | AX13: =+Segments!AX262 -> -123.39094 | AY13: =+AX13+AW13 -> -246.34792
B14: Marketing expense | I14: -10.725 | L14: -13.987 | M14: -8.76 | N14: =+O14-M14 -> -8.82 | O14: -17.58 | P14: -10.704 | Q14: =+R14-P14 -> -7.234 | R14: -17.938 | S14: -11.302 | T14: =+U14-S14 -> -9.985 | U14: -21.287 | V14: =+Segments!V263 -> -12.690001 | W14: =+Segments!W263 -> -13.271526 | X14: =+W14+V14 -> -25.961527 | Y14: =+Segments!Y263 -> -14.875905 | Z14: =+Segments!Z263 -> -15.429567 | AA14: =+Z14+Y14 -> -30.305472 | AB14: =+Segments!AB263 -> -17.098974 | AC14: =+Segments!AC263 -> -17.593604 | AD14: =+AC14+AB14 -> -34.692578 | AE14: =+Segments!AE263 -> -19.231774 | AF14: =+Segments!AF263 -> -19.702621 | AG14: =+AF14+AE14 -> -38.934395 | AH14: =+Segments!AH263 -> -21.450856 | AI14: =+Segments!AI263 -> -21.897311 | AJ14: =+AI14+AH14 -> -43.348167 | AK14: =+Segments!AK263 -> -24.284991 | AL14: =+Segments!AL263 -> -24.585314 | AM14: =+AL14+AK14 -> -48.870305 | AN14: =+Segments!AN263 -> -27.054027 | AO14: =+Segments!AO263 -> -27.315437 | AP14: =+AO14+AN14 -> -54.369463 | AQ14: =+Segments!AQ263 -> -29.989705 | AR14: =+Segments!AR263 -> -30.209587 | AS14: =+AR14+AQ14 -> -60.199292 | AT14: =+Segments!AT263 -> -33.101415 | AU14: =+Segments!AU263 -> -33.277023 | AV14: =+AU14+AT14 -> -66.378439 | AW14: =+Segments!AW263 -> -36.39908 | AX14: =+Segments!AX263 -> -36.527547 | AY14: =+AX14+AW14 -> -72.926628
B15: Other expense | I15: =-2.088-5.957 -> -8.045 | L15: =-8.275-1.681 -> -9.956 | M15: =-5.787-0.483 -> -6.27 | N15: =+O15-M15 -> -7.725 | O15: =-11.714-2.281 -> -13.995 | P15: =-9.274-1.387 -> -10.661 | Q15: =+R15-P15 -> -7.207 | R15: -17.868 | S15: -14.311 | T15: =+U15-S15 -> -15.07 | U15: -29.381 | V15: =+Segments!V264 -> -7.6693219 | W15: =+Segments!W264 -> -8.0207723 | X15: =+W15+V15 -> -15.690094 | Y15: =+Segments!Y264 -> -8.990394 | Z15: =+Segments!Z264 -> -9.3250048 | AA15: =+Z15+Y15 -> -18.315399 | AB15: =+Segments!AB264 -> -10.333927 | AC15: =+Segments!AC264 -> -10.632861 | AD15: =+AC15+AB15 -> -20.966788 | AE15: =+Segments!AE264 -> -11.622905 | AF15: =+Segments!AF264 -> -11.907465 | AG15: =+AF15+AE15 -> -23.53037 | AH15: =+Segments!AH264 -> -12.964028 | AI15: =+Segments!AI264 -> -13.233847 | AJ15: =+AI15+AH15 -> -26.197875 | AK15: =+Segments!AK264 -> -14.676864 | AL15: =+Segments!AL264 -> -14.858367 | AM15: =+AL15+AK15 -> -29.535231 | AN15: =+Segments!AN264 -> -16.350357 | AO15: =+Segments!AO264 -> -16.508343 | AP15: =+AO15+AN15 -> -32.858699 | AQ15: =+Segments!AQ264 -> -18.124562 | AR15: =+Segments!AR264 -> -18.257449 | AS15: =+AR15+AQ15 -> -36.382011 | AT15: =+Segments!AT264 -> -20.005154 | AU15: =+Segments!AU264 -> -20.111284 | AV15: =+AU15+AT15 -> -40.116437 | AW15: =+Segments!AW264 -> -21.998129 | AX15: =+Segments!AX264 -> -22.075769 | AY15: =+AX15+AW15 -> -44.073897
B16: Opex | I16: =SUM(I10:I15) -> -100.878 | L16: =SUM(L10:L15) -> -147.886 | M16: =SUM(M10:M15) -> -106.648 | N16: =SUM(N10:N15) -> -122.775 | O16: =SUM(O10:O15) -> -229.423 | P16: =SUM(P10:P15) -> -148.613 | Q16: =SUM(Q10:Q15) -> -166.327 | R16: =SUM(R10:R15) -> -314.94 | S16: =SUM(S10:S15) -> -180.841 | ... AY16: =SUM(AY10:AY15) -> -1280.3831
B18: Reported Ebitda | I18: =+I8+I16 -> 18.653 | L18: =+L8+L16 -> 23.906 | M18: =+M8+M16 -> 14.537 | N18: =+N8+N16 -> 15.084 | O18: =+O8+O16 -> 29.621 | P18: =+P8+P16 -> 18.904 | Q18: =+Q8+Q16 -> 8.37 | R18: =+R8+R16 -> 27.274 | S18: =+S8+S16 -> 31.578 | ... U18: =+U8+U16 -> 65.119 | V18: =+Segments!V33 -> 42.436647 | W18: =+Segments!W33 -> 40.588008 | X18: =+W18+V18 -> 83.024656 | Y18: =+Segments!Y33 -> 55.449649 | Z18: =+Segments!Z33 -> 54.308335 | AA18: =+Z18+Y18 -> 109.75798 | AB18: =+Segments!AB33 -> 72.985707 | AC18: =+Segments!AC33 -> 71.507867 | AD18: =+AC18+AB18 -> 144.49357 | AE18: =+Segments!AE33 -> 91.082529 | AF18: =+Segments!AF33 -> 89.097936 | AG18: =+AF18+AE18 -> 180.18046 | AH18: =+Segments!AH33 -> 111.58203 | AI18: =+Segments!AI33 -> 107.23519 | AJ18: =+AI18+AH18 -> 218.81722 | AK18: =+Segments!AK33 -> 123.45882 | AL18: =+Segments!AL33 -> 120.37774 | AM18: =+AL18+AK18 -> 243.83656 | AN18: =+Segments!AN33 -> 140.45118 | AO18: =+Segments!AO33 -> 136.65717 | AP18: =+AO18+AN18 -> 277.10835 | AQ18: =+Segments!AQ33 -> 158.71687 | AR18: =+Segments!AR33 -> 154.15381 | AS18: =+AR18+AQ18 -> 312.87068 | AT18: =+Segments!AT33 -> 178.32926 | AU18: =+Segments!AU33 -> 172.93733 | AV18: =+AU18+AT18 -> 351.26659 | AW18: =+Segments!AW33 -> 199.36486 | AX18: =+Segments!AX33 -> 193.08033 | AY18: =+AX18+AW18 -> 392.4452
B19: Adjustments | I19: =+I20-I18 -> -2.732 | L19: =+L20-L18 -> -2.206 | M19: =+M20-M18 -> -0.337 | N19: =+N20-N18 -> 0.016 | O19: =+O20-O18 -> -0.321 | P19: =+P20-P18 -> 5.796 | Q19: =+Q20-Q18 -> 11.73 | R19: =+R20-R18 -> 17.526 | S19: =+S20-S18 -> 0 | ... U19: =+U20-U18 -> 0 | V19: =+Segments!V32 -> 0 | W19: =+Segments!W32 -> 0 | X19: =+W19+V19 -> 0 | Y19: =+Segments!Y32 -> 0 | Z19: =+Segments!Z32 -> 0 | AA19: =+Z19+Y19 -> 0 | AB19: =+Segments!AB32 -> 0 | AC19: =+Segments!AC32 -> 0 | AD19: =+AC19+AB19 -> 0 | AE19: =+Segments!AE32 -> 0 | AF19: =+Segments!AF32 -> 0 | AG19: =+AF19+AE19 -> 0 | AH19: =+Segments!AH32 -> 0 | AI19: =+Segments!AI32 -> 0 | AJ19: =+AI19+AH19 -> 0 | AK19: =+Segments!AK32 -> 0 | AL19: =+Segments!AL32 -> 0 | AM19: =+AL19+AK19 -> 0 | AN19: =+Segments!AN32 -> 0 | AO19: =+Segments!AO32 -> 0 | AP19: =+AO19+AN19 -> 0 | AQ19: =+Segments!AQ32 -> 0 | AR19: =+Segments!AR32 -> 0 | AS19: =+AR19+AQ19 -> 0 | AT19: =+Segments!AT32 -> 0 | AU19: =+Segments!AU32 -> 0 | AV19: =+AU19+AT19 -> 0 | AW19: =+Segments!AW32 -> 0 | AX19: =+Segments!AX32 -> 0 | AY19: =+AX19+AW19 -> 0
B20: Adj. Ebitda | I20: 15.921 | L20: 21.7 | M20: 14.2 | N20: =+O20-M20 -> 15.1 | O20: 29.3 | P20: 24.7 | Q20: =+R20-P20 -> 20.1 | R20: 44.8 | S20: 31.578 | T20: =+U20-S20 -> 33.541 | U20: 65.119 | V20: =+Segments!V31 -> 42.436647 | W20: =+Segments!W31 -> 40.588008 | X20: =+Segments!X31 -> 83.024656 | Y20: =+Segments!Y31 -> 55.449649 | Z20: =+Segments!Z31 -> 54.308335 | AA20: =+Segments!AA31 -> 109.75798 | AB20: =+Segments!AB31 -> 72.985707 | AC20: =+Segments!AC31 -> 71.507867 | ... AY20: =+Segments!AY31 -> 392.4452
B22: Depreciation (PPE) | I22: =-8.708-I23 -> -3.537 | L22: =-11.997-L23 -> -5.341 | M22: =-9.197-M23 -> -3.798 | N22: =+O22-M22 -> -4.592 | O22: -8.39 | P22: =-12.386-P23 -> -6.062 | Q22: =+R22-P22 -> -6.898 | R22: -12.96 | S22: -7.832 | T22: =+U22-S22 -> -11.464 | U22: -19.296 | V22: =+'Balance Sheet'!V105 -> -13.0056 | W22: =+'Balance Sheet'!W105 -> -14.70504 | X22: =+W22+V22 -> -27.71064 | Y22: =+'Balance Sheet'!Y105 -> -16.234536 | Z22: =+'Balance Sheet'!Z105 -> -17.806082 | AA22: =+Z22+Y22 -> -34.040618 | AB22: =+'Balance Sheet'!AB105 -> -19.220474 | AC22: =+'Balance Sheet'!AC105 -> -20.717077 | AD22: =+AC22+AB22 -> -39.937551 | AE22: =+'Balance Sheet'!AE105 -> -22.064019 | AF22: =+'Balance Sheet'!AF105 -> -23.515573 | AG22: =+AF22+AE22 -> -45.579592 | AH22: =+'Balance Sheet'!AH105 -> -24.821971 | AI22: =+'Balance Sheet'!AI105 -> -26.253786 | AJ22: =+AI22+AH22 -> -51.075757 | AK22: =+'Balance Sheet'!AK105 -> -27.54242 | AL22: =+'Balance Sheet'!AL105 -> -28.976171 | AM22: =+AL22+AK22 -> -56.518591 | AN22: =+'Balance Sheet'!AN105 -> -30.266547 | AO22: =+'Balance Sheet'!AO105 -> -31.721045 | AP22: =+AO22+AN22 -> -61.987593 | AQ22: =+'Balance Sheet'!AQ105 -> -33.030094 | AR22: =+'Balance Sheet'!AR105 -> -34.521918 | AS22: =+AR22+AQ22 -> -67.552011 | AT22: =+'Balance Sheet'!AT105 -> -35.864559 | AU22: =+'Balance Sheet'!AU105 -> -37.408575 | AV22: =+AU22+AT22 -> -73.273135 | AW22: =+'Balance Sheet'!AW105 -> -38.79819 | AX22: =+'Balance Sheet'!AX105 -> -40.407975 | AY22: =+AX22+AW22 -> -79.206165
B23: Depreciation (RoU) | I23: -5.171 | L23: -6.656 | M23: -5.399 | N23: =+O23-M23 -> -4.933 | O23: -10.332 | P23: -6.324 | Q23: =+R23-P23 -> -4.923 | R23: -11.247 | S23: -7.743 | T23: =+U23-S23 -> -6.131 | U23: -13.874 | V23: =+'Balance Sheet'!V127 -> -8.323725 | W23: =+'Balance Sheet'!W127 -> -6.590825 | X23: =+W23+V23 -> -14.91455 | Y23: =+'Balance Sheet'!Y127 -> -8.9480044 | Z23: =+'Balance Sheet'!Z127 -> -7.0851369 | AA23: =+Z23+Y23 -> -16.033141 | AB23: =+'Balance Sheet'!AB127 -> -9.6191047 | AC23: =+'Balance Sheet'!AC127 -> -7.6165221 | AD23: =+AC23+AB23 -> -17.235627 | AE23: =+'Balance Sheet'!AE127 -> -10.340538 | AF23: =+'Balance Sheet'!AF127 -> -8.1877613 | AG23: =+AF23+AE23 -> -18.528299 | AH23: =+'Balance Sheet'!AH127 -> -11.116078 | AI23: =+'Balance Sheet'!AI127 -> -8.8018434 | AJ23: =+AI23+AH23 -> -19.917921 | AK23: =+'Balance Sheet'!AK127 -> -11.949784 | AL23: =+'Balance Sheet'!AL127 -> -9.4619817 | AM23: =+AL23+AK23 -> -21.411765 | AN23: =+'Balance Sheet'!AN127 -> -12.846017 | AO23: =+'Balance Sheet'!AO127 -> -10.17163 | AP23: =+AO23+AN23 -> -23.017648 | AQ23: =+'Balance Sheet'!AQ127 -> -13.809469 | AR23: =+'Balance Sheet'!AR127 -> -10.934503 | AS23: =+AR23+AQ23 -> -24.743971 | AT23: =+'Balance Sheet'!AT127 -> -14.845179 | AU23: =+'Balance Sheet'!AU127 -> -11.75459 | AV23: =+AU23+AT23 -> -26.599769 | AW23: =+'Balance Sheet'!AW127 -> -15.958567 | AX23: =+'Balance Sheet'!AX127 -> -12.636185 | AY23: =+AX23+AW23 -> -28.594752
B24: Amortisation | I24: -1.4 | L24: -2.463 | M24: -3.37 | N24: =+O24-M24 -> -3.463 | O24: -6.833 | P24: -3.514 | Q24: =+R24-P24 -> -3.402 | R24: -6.916 | S24: =-1.89-1.615 -> -3.505 | T24: =+U24-S24 -> -3.006 | U24: =-3.668-2.843 -> -6.511 | V24: =+'Balance Sheet'!V117 -> -3.68025 | W24: =+'Balance Sheet'!W117 -> -3.1563 | X24: =+W24+V24 -> -6.83655 | Y24: =+'Balance Sheet'!Y117 -> -3.8642625 | Z24: =+'Balance Sheet'!Z117 -> -3.314115 | AA24: =+Z24+Y24 -> -7.1783775 | AB24: =+'Balance Sheet'!AB117 -> -4.0574756 | AC24: =+'Balance Sheet'!AC117 -> -3.4798208 | AD24: =+AC24+AB24 -> -7.5372964 | AE24: =+'Balance Sheet'!AE117 -> -4.2603494 | AF24: =+'Balance Sheet'!AF117 -> -3.6538118 | AG24: =+AF24+AE24 -> -7.9141612 | AH24: =+'Balance Sheet'!AH117 -> -4.4733669 | AI24: =+'Balance Sheet'!AI117 -> -3.8365024 | AJ24: =+AI24+AH24 -> -8.3098693 | AK24: =+'Balance Sheet'!AK117 -> -4.6970352 | AL24: =+'Balance Sheet'!AL117 -> -4.0283275 | AM24: =+AL24+AK24 -> -8.7253627 | AN24: =+'Balance Sheet'!AN117 -> -4.931887 | AO24: =+'Balance Sheet'!AO117 -> -4.2297439 | AP24: =+AO24+AN24 -> -9.1616309 | AQ24: =+'Balance Sheet'!AQ117 -> -5.1784813 | AR24: =+'Balance Sheet'!AR117 -> -4.4412311 | AS24: =+AR24+AQ24 -> -9.6197124 | AT24: =+'Balance Sheet'!AT117 -> -5.4374054 | AU24: =+'Balance Sheet'!AU117 -> -4.6632926 | AV24: =+AU24+AT24 -> -10.100698 | AW24: =+'Balance Sheet'!AW117 -> -5.7092757 | AX24: =+'Balance Sheet'!AX117 -> -4.8964572 | AY24: =+AX24+AW24 -> -10.605733
B25: Ebit | I25: =I18+SUM(I22:I24) -> 8.545 | L25: =L18+SUM(L22:L24) -> 9.446 | M25: =M18+SUM(M22:M24) -> 1.97 | N25: =N18+SUM(N22:N24) -> 2.096 | O25: =O18+SUM(O22:O24) -> 4.066 | P25: =P18+SUM(P22:P24) -> 3.004 | Q25: =Q18+SUM(Q22:Q24) -> -6.853 | R25: =R18+SUM(R22:R24) -> -3.849 | S25: =S18+SUM(S22:S24) -> 12.498 | ... AY25: =AY18+SUM(AY22:AY24) -> 274.03855
B26: Adjustments | I26: =+I27-I25 -> -4.845 | L26: =+L27-L25 -> -2.246 | M26: =+M27-M25 -> -0.37 | N26: =+N27-N25 -> 0.004 | O26: =+O27-O25 -> -0.366 | P26: =+P27-P25 -> 5.796 | Q26: =+Q27-Q25 -> 11.653 | R26: =+R27-R25 -> 17.449 | S26: =+S27-S25 -> 0 | ... U26: =+U27-U25 -> -0.038 | V26: =+V19 -> 0 | W26: =+W19 -> 0 | X26: =+X19 -> 0 | Y26: =+Y19 -> 0 | Z26: =+Z19 -> 0 | AA26: =+AA19 -> 0 | AB26: =+AB19 -> 0 | AC26: =+AC19 -> 0 | ... AY26: =+AY19 -> 0
B27: Adj. Ebit | I27: 3.7 | L27: 7.2 | M27: 1.6 | N27: =+O27-M27 -> 2.1 | O27: 3.7 | P27: 8.8 | Q27: =+R27-P27 -> 4.8 | R27: 13.6 | S27: 12.498 | T27: =+U27-S27 -> 12.902 | U27: 25.4 | V27: =+V26+V25 -> 17.427072 | W27: =+W26+W25 -> 16.135843 | X27: =+X26+X25 -> 33.562916 | Y27: =+Y26+Y25 -> 26.402846 | Z27: =+Z26+Z25 -> 26.103001 | AA27: =+AA26+AA25 -> 52.505847 | AB27: =+AB26+AB25 -> 40.088652 | AC27: =+AC26+AC25 -> 39.694447 | ... AY27: =+AY26+AY25 -> 274.03855
B29: Financial income | I29: 2.935 | L29: 3.173 | M29: 2.138 | N29: =+O29-M29 -> 2.455 | O29: 4.593 | P29: 2.327 | Q29: =+R29-P29 -> 3.685 | R29: 6.012 | S29: 11.445 | T29: =+U29-S29 -> 11.229 | U29: 22.674 | V29: =+'Balance Sheet'!V154 -> 7.5 | W29: =+'Balance Sheet'!W154 -> 7.5 | X29: =+W29+V29 -> 15 | Y29: =+'Balance Sheet'!Y154 -> 7.5 | Z29: =+'Balance Sheet'!Z154 -> 5.0858899 | AA29: =+Z29+Y29 -> 12.58589 | AB29: =+'Balance Sheet'!AB154 -> 5.1917818 | AC29: =+'Balance Sheet'!AC154 -> 5.4784885 | AD29: =+AC29+AB29 -> 10.67027 | AE29: =+'Balance Sheet'!AE154 -> 5.768177 | AF29: =+'Balance Sheet'!AF154 -> 6.2444804 | AG29: =+AF29+AE29 -> 12.012657 | AH29: =+'Balance Sheet'!AH154 -> 6.7243346 | AI29: =+'Balance Sheet'!AI154 -> 7.4203883 | AJ29: =+AI29+AH29 -> 14.144723 | AK29: =+'Balance Sheet'!AK154 -> 8.1006885 | AL29: =+'Balance Sheet'!AL154 -> 8.9495724 | AM29: =+AL29+AK29 -> 17.050261 | AN29: =+'Balance Sheet'!AN154 -> 9.7641801 | AO29: =+'Balance Sheet'!AO154 -> 10.784464 | AP29: =+AO29+AN29 -> 20.548644 | AQ29: =+'Balance Sheet'!AQ154 -> 11.775775 | AR29: =+'Balance Sheet'!AR154 -> 12.994904 | AS29: =+AR29+AQ29 -> 24.770679 | AT29: =+'Balance Sheet'!AT154 -> 14.178976 | AU29: =+'Balance Sheet'!AU154 -> 15.614541 | AV29: =+AU29+AT29 -> 29.793517 | AW29: =+'Balance Sheet'!AW154 -> 17.008675 | AX29: =+'Balance Sheet'!AX154 -> 18.679586 | AY29: =+AX29+AW29 -> 35.688261
B30: Financial expense | I30: 0 | L30: =-0.07-0.139 -> -0.209 | M30: =-0.049-0.075 -> -0.124 | N30: =+O30-M30 -> -0.18 | O30: -0.304 | P30: =-0.076-0.073 -> -0.149 | Q30: =+R30-P30 -> -0.181 | R30: -0.33 | S30: -0.066 | T30: =+U30-S30 -> -0.065 | U30: =-18.902--18.771 -> -0.131 | V30: =+'Balance Sheet'!V151 -> 0 | W30: =+'Balance Sheet'!W151 -> 0 | X30: =+W30+V30 -> 0 | Y30: =+'Balance Sheet'!Y151 -> 0 | Z30: =+'Balance Sheet'!Z151 -> 0 | AA30: =+Z30+Y30 -> 0 | AB30: =+'Balance Sheet'!AB151 -> 0 | AC30: =+'Balance Sheet'!AC151 -> 0 | AD30: =+AC30+AB30 -> 0 | AE30: =+'Balance Sheet'!AE151 -> 0 | AF30: =+'Balance Sheet'!AF151 -> 0 | AG30: =+AF30+AE30 -> 0 | AH30: =+'Balance Sheet'!AH151 -> 0 | AI30: =+'Balance Sheet'!AI151 -> 0 | AJ30: =+AI30+AH30 -> 0 | AK30: =+'Balance Sheet'!AK151 -> 0 | AL30: =+'Balance Sheet'!AL151 -> 0 | AM30: =+AL30+AK30 -> 0 | AN30: =+'Balance Sheet'!AN151 -> 0 | AO30: =+'Balance Sheet'!AO151 -> 0 | AP30: =+AO30+AN30 -> 0 | AQ30: =+'Balance Sheet'!AQ151 -> 0 | AR30: =+'Balance Sheet'!AR151 -> 0 | AS30: =+AR30+AQ30 -> 0 | AT30: =+'Balance Sheet'!AT151 -> 0 | AU30: =+'Balance Sheet'!AU151 -> 0 | AV30: =+AU30+AT30 -> 0 | AW30: =+'Balance Sheet'!AW151 -> 0 | AX30: =+'Balance Sheet'!AX151 -> 0 | AY30: =+AX30+AW30 -> 0
B31: Financial expense (leases) | I31: -5.156 | L31: -5.799 | M31: -3.636 | N31: =+O31-M31 -> -4.563 | O31: -8.199 | P31: -6.261 | Q31: =+R31-P31 -> -7.133 | R31: -13.394 | S31: -8.686 | T31: =+U31-S31 -> -10.085 | U31: =-18.771 -> -18.771 | V31: =+'Balance Sheet'!V140 -> -9.3498471 | W31: =+'Balance Sheet'!W140 -> -9.5174753 | X31: =+W31+V31 -> -18.867322 | Y31: =+'Balance Sheet'!Y140 -> -9.6394182 | Z31: =+'Balance Sheet'!Z140 -> -9.8118716 | AA31: =+Z31+Y31 -> -19.45129 | AB31: =+'Balance Sheet'!AB140 -> -9.9345549 | AC31: =+'Balance Sheet'!AC140 -> -10.110822 | AD31: =+AC31+AB31 -> -20.045377 | AE31: =+'Balance Sheet'!AE140 -> -10.232812 | AF31: =+'Balance Sheet'!AF140 -> -10.411564 | AG31: =+AF31+AE31 -> -20.644376 | AH31: =+'Balance Sheet'!AH140 -> -10.531054 | AI31: =+'Balance Sheet'!AI140 -> -10.710573 | AJ31: =+AI31+AH31 -> -21.241627 | AK31: =+'Balance Sheet'!AK140 -> -10.825312 | AL31: =+'Balance Sheet'!AL140 -> -11.003417 | AM31: =+AL31+AK31 -> -21.828729 | AN31: =+'Balance Sheet'!AN140 -> -11.110618 | AO31: =+'Balance Sheet'!AO140 -> -11.284564 | AP31: =+AO31+AN31 -> -22.395182 | AQ31: =+'Balance Sheet'!AQ140 -> -11.380801 | AR31: =+'Balance Sheet'!AR140 -> -11.547174 | AS31: =+AR31+AQ31 -> -22.927976 | AT31: =+'Balance Sheet'!AT140 -> -11.628256 | AU31: =+'Balance Sheet'!AU140 -> -11.782834 | AV31: =+AU31+AT31 -> -23.41109 | AW31: =+'Balance Sheet'!AW140 -> -11.84366 | AX31: =+'Balance Sheet'!AX140 -> -11.981254 | AY31: =+AX31+AW31 -> -23.824913
B32: Net finance | I32: =SUM(I29:I31) -> -2.221 | J32: =SUM(J29:J31) -> 0 | K32: =SUM(K29:K31) -> 0 | L32: =SUM(L29:L31) -> -2.835 | M32: =SUM(M29:M31) -> -1.622 | N32: =SUM(N29:N31) -> -2.288 | O32: =SUM(O29:O31) -> -3.91 | P32: =SUM(P29:P31) -> -4.083 | ... AY32: =SUM(AY29:AY31) -> 11.863347
B34: Pbt | I34: =+I32+I25 -> 6.324 | J34: =+J32+J25 -> 0 | K34: =+K32+K25 -> 0 | L34: =+L32+L25 -> 6.611 | M34: =+M32+M25 -> 0.348 | N34: =+N32+N25 -> -0.192 | O34: =+O32+O25 -> 0.156 | P34: =+P32+P25 -> -1.079 | ... AY34: =+AY32+AY25 -> 285.90189
B35: Adjustments | I35: =+I36-I34 -> 1.276 | L35: =+L36-L34 -> -1.011 | M35: =+M36-M34 -> 2.952 | N35: =+N36-N34 -> 4.492 | O35: =+O36-O34 -> 7.444 | P35: =+P36-P34 -> 11.179 | Q35: =+Q36-Q34 -> 16.682 | R35: =+R36-R34 -> 27.861 | S35: =+S36-S34 -> 0 | ... U35: =+U36-U34 -> -0.01 | V35: 0 | W35: 0 | X35: =+W35+V35 -> 0 | Y35: 0 | Z35: 0 | AA35: =+Z35+Y35 -> 0 | AB35: 0 | AC35: 0 | AD35: =+AC35+AB35 -> 0 | AE35: 0 | AF35: 0 | AG35: =+AF35+AE35 -> 0 | AH35: 0 | AI35: 0 | AJ35: =+AI35+AH35 -> 0 | AK35: 0 | AL35: 0 | AM35: =+AL35+AK35 -> 0 | AN35: 0 | AO35: 0 | AP35: =+AO35+AN35 -> 0 | AQ35: 0 | AR35: 0 | AS35: =+AR35+AQ35 -> 0 | AT35: 0 | AU35: 0 | AV35: =+AU35+AT35 -> 0 | AW35: 0 | AX35: 0 | AY35: =+AX35+AW35 -> 0
B36: Adj. Pbt | I36: 7.6 | L36: 5.6 | M36: 3.3 | N36: =+O36-M36 -> 4.3 | O36: 7.6 | P36: 10.1 | Q36: =+R36-P36 -> 6.2 | R36: 16.3 | S36: 15.191 | T36: =+U36-S36 -> 14.009 | U36: 29.2 | V36: =+V35+V34 -> 15.577225 | W36: =+W35+W34 -> 14.118368 | X36: =+X35+X34 -> 29.695593 | Y36: =+Y35+Y34 -> 24.263428 | Z36: =+Z35+Z34 -> 21.377019 | AA36: =+AA35+AA34 -> 45.640447 | AB36: =+AB35+AB34 -> 35.345879 | AC36: =+AC35+AC34 -> 35.062113 | ... AY36: =+AY35+AY34 -> 285.90189
B38: Tax | I38: -2.336 | L38: -2.7 | M38: -1.469 | N38: =+O38-M38 -> -0.954 | O38: -2.423 | P38: -2.881 | Q38: =+R38-P38 -> 0.694 | R38: -2.187 | S38: -7.89 | T38: =+U38-S38 -> -6.844 | U38: -14.734 | V38: =+-V34*V39 -> -4.6731676 | W38: =+-W34*W39 -> -4.2355104 | X38: =+W38+V38 -> -8.908678 | Y38: =+-Y34*Y39 -> -7.2790283 | Z38: =+-Z34*Z39 -> -6.4131058 | AA38: =+Z38+Y38 -> -13.692134 | AB38: =+-AB34*AB39 -> -10.603764 | AC38: =+-AC34*AC39 -> -10.518634 | AD38: =+AC38+AB38 -> -21.122398 | AE38: =+-AE34*AE39 -> -14.985896 | AF38: =+-AF34*AF39 -> -14.872112 | AG38: =+AF38+AE38 -> -29.858008 | AH38: =+-AH34*AH39 -> -20.209169 | AI38: =+-AI34*AI39 -> -19.515862 | AJ38: =+AI38+AH38 -> -39.725031 | AK38: =+-AK34*AK39 -> -22.963489 | AL38: =+-AL34*AL39 -> -22.757224 | AM38: =+AL38+AK38 -> -45.720713 | AN38: =+-AN34*AN39 -> -27.318089 | AO38: =+-AO34*AO39 -> -27.010394 | AP38: =+AO38+AN38 -> -54.328483 | AQ38: =+-AQ34*AQ39 -> -32.128141 | AR38: =+-AR34*AR39 -> -31.711166 | AS38: =+AR38+AQ38 -> -63.839307 | AT38: =+-AT34*AT39 -> -37.41985 | AU38: =+-AU34*AU39 -> -36.882775 | AV38: =+AU38+AT38 -> -74.302625 | AW38: =+-AW34*AW39 -> -43.219154 | AX38: =+-AX34*AX39 -> -42.551414 | AY38: =+AX38+AW38 -> -85.770568
B39: Implied tax rate | I39: =-I38/I34 -> 0.36938646 | L39: =+-L38/L34 -> 0.40841023 | M39: =+-M38/M34 -> 4.2212644 | N39: =+-N38/N34 -> -4.96875 | O39: =+-O38/O34 -> 15.532051 | P39: =+-P38/P34 -> -2.6700649 | Q39: =+-Q38/Q34 -> 0.066208739 | R39: =+-R38/R34 -> -0.18917049 | S39: =+-S38/S34 -> 0.51938648 | ... U39: =+-U38/U34 -> 0.5044163 | V39: 0.3 | W39: 0.3 | X39: =-X38/X34 -> 0.3 | Y39: 0.3 | Z39: 0.3 | AA39: =-AA38/AA34 -> 0.3 | AB39: 0.3 | AC39: 0.3 | AD39: =-AD38/AD34 -> 0.3 | AE39: 0.3 | AF39: 0.3 | AG39: =-AG38/AG34 -> 0.3 | AH39: 0.3 | AI39: 0.3 | AJ39: =-AJ38/AJ34 -> 0.3 | AK39: 0.3 | AL39: 0.3 | AM39: =-AM38/AM34 -> 0.3 | AN39: 0.3 | AO39: 0.3 | AP39: =-AP38/AP34 -> 0.3 | AQ39: 0.3 | AR39: 0.3 | AS39: =-AS38/AS34 -> 0.3 | AT39: 0.3 | AU39: 0.3 | AV39: =-AV38/AV34 -> 0.3 | AW39: 0.3 | AX39: 0.3 | AY39: =-AY38/AY34 -> 0.3
B40: Reported Npat | I40: =+I38+I34 -> 3.988 | L40: =+L38+L34 -> 3.911 | M40: =+M38+M34 -> -1.121 | N40: =+N38+N34 -> -1.146 | O40: =+O38+O34 -> -2.267 | P40: =+P38+P34 -> -3.96 | Q40: =+Q38+Q34 -> -9.788 | R40: =+R38+R34 -> -13.748 | S40: =+S38+S34 -> 7.301 | ... AY40: =+AY38+AY34 -> 200.13132
B41: Adjustments | I41: =+I42-I40 -> -3.988 | L41: =+L42-L40 -> -0.711 | M41: =+M42-M40 -> 2.021 | N41: =+N42-N40 -> 3.246 | O41: =+O42-O40 -> 5.267 | P41: =+P42-P40 -> 7.76 | Q41: =+Q42-Q40 -> 11.688 | R41: =+R42-R40 -> 19.448 | S41: =+S42-S40 -> 0 | ... U41: =+U42-U40 -> -7.8159701e-14 | V41: 0 | W41: 0 | X41: =+W41+V41 -> 0 | Y41: 0 | Z41: 0 | AA41: =+Z41+Y41 -> 0 | AB41: 0 | AC41: 0 | AD41: =+AC41+AB41 -> 0 | AE41: 0 | AF41: 0 | AG41: =+AF41+AE41 -> 0 | AH41: 0 | AI41: 0 | AJ41: =+AI41+AH41 -> 0 | AK41: 0 | AL41: 0 | AM41: =+AL41+AK41 -> 0 | AN41: 0 | AO41: 0 | AP41: =+AO41+AN41 -> 0 | AQ41: 0 | AR41: 0 | AS41: =+AR41+AQ41 -> 0 | AT41: 0 | AU41: 0 | AV41: =+AU41+AT41 -> 0 | AW41: 0 | AX41: 0 | AY41: =+AX41+AW41 -> 0
B42: Adj. Npat | L42: 3.2 | M42: 0.9 | N42: =+O42-M42 -> 2.1 | O42: 3 | P42: 3.8 | Q42: =+R42-P42 -> 1.9 | R42: 5.7 | S42: 7.301 | T42: =+U42-S42 -> 7.175 | U42: 14.476 | V42: =+V41+V40 -> 10.904058 | W42: =+W41+W40 -> 9.8828575 | X42: =+X41+X40 -> 20.786915 | Y42: =+Y41+Y40 -> 16.984399 | Z42: =+Z41+Z40 -> 14.963914 | AA42: =+AA41+AA40 -> 31.948313 | AB42: =+AB41+AB40 -> 24.742115 | AC42: =+AC41+AC40 -> 24.543479 | ... AY42: =+AY41+AY40 -> 200.13132
B44: Other comprehensive income/expense | I44: -0.009 | L44: 0.008 | M44: 0.01 | N44: =+N45-N40 -> 0.389 | O44: 0.399 | P44: -0.387 | Q44: =+Q45-Q40 -> 0.457 | R44: 0.07 | S44: 0.818 | T44: =+T45-T40 -> -1.223 | U44: -0.405 | V44: 0 | W44: 0 | X44: =+W44+V44 -> 0 | Y44: 0 | Z44: 0 | AA44: =+Z44+Y44 -> 0 | AB44: 0 | AC44: 0 | AD44: =+AC44+AB44 -> 0 | AE44: 0 | AF44: 0 | AG44: =+AF44+AE44 -> 0 | AH44: 0 | AI44: 0 | AJ44: =+AI44+AH44 -> 0 | AK44: 0 | AL44: 0 | AM44: =+AL44+AK44 -> 0 | AN44: 0 | AO44: 0 | AP44: =+AO44+AN44 -> 0 | AQ44: 0 | AR44: 0 | AS44: =+AR44+AQ44 -> 0 | AT44: 0 | AU44: 0 | AV44: =+AU44+AT44 -> 0 | AW44: 0 | AX44: 0 | AY44: =+AX44+AW44 -> 0
B45: Total comprehensive NPAT | I45: =+I40+I44 -> 3.979 | L45: =+L40+L44 -> 3.919 | M45: =+M40+M44 -> -1.111 | N45: =+O45-M45 -> -0.757 | O45: =+O40+O44 -> -1.868 | P45: =+P40+P44 -> -4.347 | Q45: =+R45-P45 -> -9.331 | R45: =+R40+R44 -> -13.678 | S45: =+S40+S44 -> 8.119 | T45: =+U45-S45 -> 5.952 | U45: =+U40+U44 -> 14.071 | V45: =+V40+V44 -> 10.904058 | W45: =+W40+W44 -> 9.8828575 | X45: =+X40+X44 -> 20.786915 | Y45: =+Y40+Y44 -> 16.984399 | Z45: =+Z40+Z44 -> 14.963914 | AA45: =+AA40+AA44 -> 31.948313 | AB45: =+AB40+AB44 -> 24.742115 | ... AY45: =+AY40+AY44 -> 200.13132
B47: Check - NPAT | I47: =ROUND(3.988-I40,3) -> 0 | L47: =ROUND(3.911-L40,3) -> 0 | M47: =ROUND(-1.121-M40,3) -> 0 | O47: =ROUND(-2.267-O40,3) -> 0 | P47: =ROUND(-3.96-P40,3) -> 0 | R47: =ROUND(-13.748-R40,3) -> 0 | S47: =ROUND(7.301-S40,3) -> 0 | U47: =ROUND(14.476-U40,3) -> 0
R48: hem
B49: # Shares (diluted) | I49: =+'Balance Sheet'!I174 -> 0 | L49: =+'Balance Sheet'!L174 -> 0 | M49: =+'Balance Sheet'!M174 -> 0 | N49: =+'Balance Sheet'!N174 -> 0 | O49: =+'Balance Sheet'!O174 -> 83.992295 | P49: =+'Balance Sheet'!P174 -> 0 | Q49: =+'Balance Sheet'!Q174 -> 85.568408 | R49: =+'Balance Sheet'!R174 -> 85.568408 | S49: =+'Balance Sheet'!S174 -> 106.13463 | ... AY49: =+'Balance Sheet'!AY174 -> 102.86055
B50: Reported EPS (cps) | O50: =O40/O49*100 -> -2.6990571 | Q50: =Q40/Q49*100 -> -11.438801 | R50: =R40/R49*100 -> -16.066677 | T50: =T40/T49*100 -> 6.7749407 | U50: =U40/U49*100 -> 13.668856 | V50: =V40/V49*100 -> 10.600816 | W50: =W40/W49*100 -> 9.6080156 | X50: =X40/X49*100 -> 20.208832 | Y50: =Y40/Y49*100 -> 16.512064 | Z50: =Z40/Z49*100 -> 14.547768 | AA50: =AA40/AA49*100 -> 31.059832 | ... AY50: =AY40/AY49*100 -> 194.56568
B51: Adjusted EPS (cps) | O51: =+O42/O49*100 -> 3.5717562 | Q51: =+Q42/Q49*100 -> 2.2204457 | R51: =+R42/R49*100 -> 6.661337 | T51: =+T42/T49*100 -> 6.7749407 | U51: =+U42/U49*100 -> 13.668856 | V51: =+V42/V49*100 -> 10.600816 | W51: =+W42/W49*100 -> 9.6080156 | X51: =+X42/X49*100 -> 20.208832 | Y51: =+Y42/Y49*100 -> 16.512064 | Z51: =+Z42/Z49*100 -> 14.547768 | AA51: =+AA42/AA49*100 -> 31.059832 | ... AY51: =+AY42/AY49*100 -> 194.56568
B52: DPS (cps) | I52: =+'Balance Sheet'!I179 -> 0 | L52: =+'Balance Sheet'!L179 -> 0 | M52: =+'Balance Sheet'!M179 -> 0 | N52: =+'Balance Sheet'!N179 -> 0 | O52: =+'Balance Sheet'!O179 -> 0 | P52: =+'Balance Sheet'!P179 -> 0 | Q52: =+'Balance Sheet'!Q179 -> 0 | R52: =+'Balance Sheet'!R179 -> 0 | S52: =+'Balance Sheet'!S179 -> 0 | ... AY52: =+'Balance Sheet'!AY179 -> 0
B54: Statement of Income Analysis
B55: Growth
B56: Revenue growth | O56: =O8/L8-1 -> 0.50789327 | P56: =P8/M8-1 -> 0.38232455 | Q56: =Q8/N8-1 -> 0.26721505 | R56: =R8/O8-1 -> 0.32106515 | S56: =S8/P8-1 -> 0.26804444 | T56: =T8/Q8-1 -> 0.2797186 | U56: =U8/R8-1 -> 0.27400399 | V56: =V8/S8-1 -> 0.24864904 | ... AY56: =AY8/AV8-1 -> 0.1029524
B57: Opex growth | O57: =O16/L16-1 -> 0.55135036 | P57: =P16/M16-1 -> 0.39349074 | Q57: =Q16/N16-1 -> 0.3547302 | R57: =R16/O16-1 -> 0.37274816 | S57: =S16/P16-1 -> 0.21685855 | T57: =T16/Q16-1 -> 0.14246033 | U57: =U16/R16-1 -> 0.17756716 | V57: =V16/S16-1 -> 0.23202223 | ... AY57: =AY16/AV16-1 -> 0.098649335
B58: Ebitda growth | O58: =O18/L18-1 -> 0.23906132 | P58: =P18/M18-1 -> 0.30040586 | Q58: =Q18/N18-1 -> -0.4451074 | R58: =R18/O18-1 -> -0.079234327 | S58: =S18/P18-1 -> 0.67044012 | T58: =T18/Q18-1 -> 3.0072879 | U58: =U18/R18-1 -> 1.3875852 | V58: =V18/S18-1 -> 0.34386748 | ... AY58: =AY18/AV18-1 -> 0.11722892
B59: Adj. Ebitda growth | O59: =O20/L20-1 -> 0.35023041 | P59: =P20/M20-1 -> 0.73943662 | Q59: =Q20/N20-1 -> 0.33112583 | R59: =R20/O20-1 -> 0.52901024 | S59: =S20/P20-1 -> 0.27846154 | T59: =T20/Q20-1 -> 0.66870647 | U59: =U20/R20-1 -> 0.45354911 | V59: =V20/S20-1 -> 0.34386748 | ... AY59: =AY20/AV20-1 -> 0.11722892
B60: Ebit growth | O60: =+O25/L25-1 -> -0.56955325 | P60: =+P25/M25-1 -> 0.5248731 | Q60: =+Q25/N25-1 -> -4.2695611 | R60: =+R25/O25-1 -> -1.9466306 | S60: =+S25/P25-1 -> 3.1604527 | T60: =+T25/Q25-1 -> -2.8882241 | U60: =+U25/R25-1 -> -7.6089893 | V60: =+V25/S25-1 -> 0.39438889 | ... AY60: =+AY25/AV25-1 -> 0.13570869
B61: Adj. Ebit growth | O61: =+O27/L27-1 -> -0.48611111 | P61: =+P27/M27-1 -> 4.5 | Q61: =+Q27/N27-1 -> 1.2857143 | R61: =+R27/O27-1 -> 2.6756757 | S61: =+S27/P27-1 -> 0.42022727 | T61: =+T27/Q27-1 -> 1.6879167 | U61: =+U27/R27-1 -> 0.86764706 | V61: =+V27/S27-1 -> 0.39438889 | ... AY61: =+AY27/AV27-1 -> 0.13570869
B62: Reported NPAT growth | O62: =+O40/L40-1 -> -1.5796471 | P62: =+P40/M40-1 -> 2.5325602 | Q62: =+Q40/N40-1 -> 7.5410122 | R62: =+R40/O40-1 -> 5.0644023 | S62: =+S40/P40-1 -> -2.8436869 | T62: =+T40/Q40-1 -> -1.7330405 | U62: =+U40/R40-1 -> -2.0529532 | V62: =+V40/S40-1 -> 0.49350195 | ... AY62: =+AY40/AV40-1 -> 0.15434102
B63: Adj. Npat growth | O63: =+O42/L42-1 -> -0.0625 | P63: =+P42/M42-1 -> 3.2222222 | Q63: =+Q42/N42-1 -> -0.095238095 | R63: =+R42/O42-1 -> 0.9 | S63: =+S42/P42-1 -> 0.92131579 | T63: =+T42/Q42-1 -> 2.7763158 | U63: =+U42/R42-1 -> 1.5396491 | V63: =+V42/S42-1 -> 0.49350195 | ... AY63: =+AY42/AV42-1 -> 0.15434102
B65: Reported EPS growth | V65: =+V50/S50-1 -> #DIV/0! | W65: =+W50/T50-1 -> 0.4181697 | X65: =+X50/U50-1 -> 0.47845818 | Y65: =+Y50/V50-1 -> 0.55762193 | Z65: =+Z50/W50-1 -> 0.51412824 | AA65: =+AA50/X50-1 -> 0.53694344 | AB65: =+AB50/Y50-1 -> 0.4567554 | AC65: =+AC50/Z50-1 -> 0.64017783 | ... AY65: =+AY50/AV50-1 -> 0.15434102
B66: Adj. EPS growth | V66: =+V51/S51-1 -> #DIV/0! | W66: =+W51/T51-1 -> 0.4181697 | X66: =+X51/U51-1 -> 0.47845818 | Y66: =+Y51/V51-1 -> 0.55762193 | Z66: =+Z51/W51-1 -> 0.51412824 | AA66: =+AA51/X51-1 -> 0.53694344 | AB66: =+AB51/Y51-1 -> 0.4567554 | AC66: =+AC51/Z51-1 -> 0.64017783 | ... AY66: =+AY51/AV51-1 -> 0.15434102
B67: DPS growth
B69: 3yr CAGR - Revenue | I69: =(R8/I8)^(1/3)-1 -> 0.41994789 | L69: =(U8/L8)^(1/3)-1 -> 0.36402357 | M69: =(V8/M8)^(1/3)-1 -> 0.2983595 | N69: =(W8/N8)^(1/3)-1 -> 0.25668365 | O69: =(X8/O8)^(1/3)-1 -> 0.27651928 | P69: =(Y8/P8)^(1/3)-1 -> 0.23641278 | Q69: =(Z8/Q8)^(1/3)-1 -> 0.23015075 | R69: =(AA8/R8)^(1/3)-1 -> 0.23322402 | S69: =(AB8/S8)^(1/3)-1 -> 0.20664841 | ... AP69: =(AY8/AP8)^(1/3)-1 -> 0.10743372
B70: 3yr CAGR - Adj. Ebitda | I70: =(R20/I20)^(1/3)-1 -> 0.41178715 | L70: =(U20/L20)^(1/3)-1 -> 0.44238987 | M70: =(V20/M20)^(1/3)-1 -> 0.44040374 | N70: =(W20/N20)^(1/3)-1 -> 0.39040162 | O70: =(X20/O20)^(1/3)-1 -> 0.41507618 | P70: =(Y20/P20)^(1/3)-1 -> 0.30938476 | Q70: =(Z20/Q20)^(1/3)-1 -> 0.39280445 | R70: =(AA20/R20)^(1/3)-1 -> 0.3480915 | S70: =(AB20/S20)^(1/3)-1 -> 0.32216117 | ... AP70: =(AY20/AP20)^(1/3)-1 -> 0.1229915
B71: 3yr CAGR - Adj. Npat | L71: =(U42/L42)^(1/3)-1 -> 0.653863 | M71: =(V42/M42)^(1/3)-1 -> 1.2967579 | N71: =(W42/N42)^(1/3)-1 -> 0.67579573 | O71: =(X42/O42)^(1/3)-1 -> 0.90643907 | P71: =(Y42/P42)^(1/3)-1 -> 0.64723489 | Q71: =(Z42/Q42)^(1/3)-1 -> 0.98959126 | R71: =(AA42/R42)^(1/3)-1 -> 0.7763329 | S71: =(AB42/S42)^(1/3)-1 -> 0.50205151 | ... AP71: =(AY42/AP42)^(1/3)-1 -> 0.16440368
B73: Margin
B74: Opex / Revenue | I74: =I16/I8 -> -0.84394843 | L74: =L16/L8 -> -0.86084335 | M74: =M16/M8 -> -0.88004291 | N74: =N16/N8 -> -0.89058386 | O74: =O16/O8 -> -0.88565263 | P74: =P16/P8 -> -0.88715175 | Q74: =Q16/Q8 -> -0.95208847 | R74: =R16/R8 -> -0.92030133 | S74: =S16/S8 -> -0.85134098 | ... AY74: =AY16/AY8 -> -0.76540019
B75: Ebitda margin | I75: =I18/I8 -> 0.15605157 | L75: =L18/L8 -> 0.13915665 | M75: =M18/M8 -> 0.11995709 | N75: =N18/N8 -> 0.10941614 | O75: =O18/O8 -> 0.11434737 | P75: =P18/P8 -> 0.11284825 | Q75: =Q18/Q8 -> 0.047911527 | R75: =R18/R8 -> 0.079698668 | S75: =S18/S8 -> 0.14865902 | ... AY75: =AY18/AY8 -> 0.23459981
B76: Ebit margin | I76: =I25/I8 -> 0.071487731 | L76: =L25/L8 -> 0.054985098 | M76: =M25/M8 -> 0.016256137 | N76: =N25/N8 -> 0.01520394 | O76: =O25/O8 -> 0.015696175 | P76: =P25/P8 -> 0.017932508 | Q76: =Q25/Q8 -> -0.03922792 | R76: =R25/R8 -> -0.011247348 | S76: =S25/S8 -> 0.058836545 | ... AY76: =AY25/AY8 -> 0.1638175
B77: Reported NPAT margin | I77: =I40/I8 -> 0.03336373 | L77: =L40/L8 -> 0.022765903 | M77: =M40/M8 -> -0.0092503198 | N77: =N40/N8 -> -0.0083128414 | O77: =O40/O8 -> -0.008751409 | P77: =P40/P8 -> -0.023639392 | Q77: =Q40/Q8 -> -0.056028438 | R77: =R40/R8 -> -0.040173692 | S77: =S40/S8 -> 0.034370748 | ... AY77: =AY40/AY8 -> 0.1196365
B79: Gross margin | I79: =(I8+I11)/I8 -> 0.73399369 | L79: =(L8+L11)/L8 -> 0.74274704 | M79: =(M8+M11)/M8 -> 0.72846474 | N79: =(N8+N11)/N8 -> 0.72782336 | O79: =(O8+O11)/O8 -> 0.72812341 | P79: =(P8+P11)/P8 -> 0.74189485 | Q79: =(Q8+Q11)/Q8 -> 0.74617194 | R79: =(R8+R11)/R8 -> 0.74407827 | S79: =(S8+S11)/S8 -> 0.74074353 | ... AY79: =(AY8+AY11)/AY8 -> 0.78715391
B80: Adj. Ebitda margin | I80: =I20/I8 -> 0.13319557 | L80: =L20/L8 -> 0.12631554 | M80: =M20/M8 -> 0.11717622 | N80: =N20/N8 -> 0.1095322 | O80: =O20/O8 -> 0.1131082 | P80: =P20/P8 -> 0.14744772 | Q80: =Q20/Q8 -> 0.11505635 | R80: =R20/R8 -> 0.13091224 | S80: =S20/S8 -> 0.14865902 | ... AY80: =AY20/AY8 -> 0.23459981
B81: Adj. NPAT margin | I81: =I42/I8 -> 0 | L81: =L42/L8 -> 0.018627177 | M81: =M42/M8 -> 0.0074266617 | N81: =N42/N8 -> 0.015232955 | O81: =O42/O8 -> 0.011581044 | P81: =P42/P8 -> 0.022684265 | Q81: =Q42/Q8 -> 0.010875974 | R81: =R42/R8 -> 0.016656244 | S81: =S42/S8 -> 0.034370748 | ... AY81: =AY42/AY8 -> 0.1196365
B84: Statement of Cash Flows
B85: Operating activities (forecast)
B86: Ebitda | I86: =+I18 -> 18.653 | L86: =+L18 -> 23.906 | M86: =+M18 -> 14.537 | N86: =+N18 -> 15.084 | O86: =+O18 -> 29.621 | P86: =+P18 -> 18.904 | Q86: =+Q18 -> 8.37 | R86: =+R18 -> 27.274 | S86: =+S18 -> 31.578 | ... W86: =+W18 -> 40.588008 | X86: =+W86+V86 -> 83.024656 | Y86: =+Y18 -> 55.449649 | Z86: =+Z18 -> 54.308335 | AA86: =+Z86+Y86 -> 109.75798 | AB86: =+AB18 -> 72.985707 | AC86: =+AC18 -> 71.507867 | AD86: =+AC86+AB86 -> 144.49357 | AE86: =+AE18 -> 91.082529 | AF86: =+AF18 -> 89.097936 | AG86: =+AF86+AE86 -> 180.18046 | AH86: =+AH18 -> 111.58203 | AI86: =+AI18 -> 107.23519 | AJ86: =+AI86+AH86 -> 218.81722 | AK86: =+AK18 -> 123.45882 | AL86: =+AL18 -> 120.37774 | AM86: =+AL86+AK86 -> 243.83656 | AN86: =+AN18 -> 140.45118 | AO86: =+AO18 -> 136.65717 | AP86: =+AO86+AN86 -> 277.10835 | AQ86: =+AQ18 -> 158.71687 | AR86: =+AR18 -> 154.15381 | AS86: =+AR86+AQ86 -> 312.87068 | AT86: =+AT18 -> 178.32926 | AU86: =+AU18 -> 172.93733 | AV86: =+AU86+AT86 -> 351.26659 | AW86: =+AW18 -> 199.36486 | AX86: =+AX18 -> 193.08033 | AY86: =+AX86+AW86 -> 392.4452
B87: - Increase in Working Capital | I87: =+'Balance Sheet'!I92 -> -10.452 | L87: =+'Balance Sheet'!L92 -> 0.783 | M87: =+'Balance Sheet'!M92 -> 0 | N87: =+'Balance Sheet'!N92 -> 0 | O87: =+'Balance Sheet'!O92 -> 3.134 | P87: =+'Balance Sheet'!P92 -> 8.869 | Q87: =+'Balance Sheet'!Q92 -> -12.876 | R87: =+'Balance Sheet'!R92 -> -4.007 | S87: =+'Balance Sheet'!S92 -> 3.445 | ... U87: =+'Balance Sheet'!U92 -> -1.433 | V87: =+'Balance Sheet'!V92+V112 -> -11.330139 | W87: =+'Balance Sheet'!W92+W112 -> -10.084884 | X87: =+W87+V87 -> -21.415023 | Y87: =+'Balance Sheet'!Y92+Y112 -> -10.731186 | Z87: =+'Balance Sheet'!Z92+Z112 -> -10.311697 | AA87: =+Z87+Y87 -> -21.042883 | AB87: =+'Balance Sheet'!AB92+AB112 -> -10.560409 | AC87: =+'Balance Sheet'!AC92+AC112 -> -10.587272 | AD87: =+AC87+AB87 -> -21.147681 | AE87: =+'Balance Sheet'!AE92+AE112 -> -10.670136 | AF87: =+'Balance Sheet'!AF92+AF112 -> -10.902827 | AG87: =+AF87+AE87 -> -21.572964 | AH87: =+'Balance Sheet'!AH92+AH112 -> -10.772395 | AI87: =+'Balance Sheet'!AI92+AI112 -> -11.337324 | AJ87: =+AI87+AH87 -> -22.109718 | AK87: =+'Balance Sheet'!AK92+AK112 -> -13.002013 | AL87: =+'Balance Sheet'!AL92+AL112 -> -11.435274 | AM87: =+AL87+AK87 -> -24.437287 | AN87: =+'Balance Sheet'!AN92+AN112 -> -12.714235 | AO87: =+'Balance Sheet'!AO92+AO112 -> -11.733075 | AP87: =+AO87+AN87 -> -24.44731 | AQ87: =+'Balance Sheet'!AQ92+AQ112 -> -13.057525 | AR87: =+'Balance Sheet'!AR92+AR112 -> -12.013992 | AS87: =+AR87+AQ87 -> -25.071517 | AT87: =+'Balance Sheet'!AT92+AT112 -> -13.381278 | AU87: =+'Balance Sheet'!AU92+AU112 -> -12.269755 | AV87: =+AU87+AT87 -> -25.651033 | AW87: =+'Balance Sheet'!AW92+AW112 -> -13.676434 | AX87: =+'Balance Sheet'!AX92+AX112 -> -12.490239 | AY87: =+AX87+AW87 -> -26.166673
B88: - Net Interest Paid | I88: =-I32 -> 2.221 | L88: =-L32 -> 2.835 | M88: =-M32 -> 1.622 | N88: =-N32 -> 2.288 | O88: =-O32 -> 3.91 | P88: =-P32 -> 4.083 | Q88: =-Q32 -> 3.629 | R88: =-R32 -> 7.712 | S88: =-S32 -> -2.693 | ... W88: =-W32 -> 2.0174753 | X88: =+W88+V88 -> 3.8673224 | Y88: =-Y32 -> 2.1394182 | Z88: =-Z32 -> 4.7259816 | AA88: =+Z88+Y88 -> 6.8653998 | AB88: =-AB32 -> 4.7427731 | AC88: =-AC32 -> 4.632334 | AD88: =+AC88+AB88 -> 9.3751071 | AE88: =-AE32 -> 4.464635 | AF88: =-AF32 -> 4.1670833 | AG88: =+AF88+AE88 -> 8.6317183 | AH88: =-AH32 -> 3.8067192 | AI88: =-AI32 -> 3.2901848 | AJ88: =+AI88+AH88 -> 7.096904 | AK88: =-AK32 -> 2.7246235 | AL88: =-AL32 -> 2.0538441 | AM88: =+AL88+AK88 -> 4.7784677 | AN88: =-AN32 -> 1.3464374 | AO88: =-AO32 -> 0.50010048 | AP88: =+AO88+AN88 -> 1.8465379 | AQ88: =-AQ32 -> -0.39497395 | AR88: =-AR32 -> -1.4477299 | AS88: =+AR88+AQ88 -> -1.8427038 | AT88: =-AT32 -> -2.5507197 | AU88: =-AU32 -> -3.8317076 | AV88: =+AU88+AT88 -> -6.3824273 | AW88: =-AW32 -> -5.1650156 | AX88: =-AX32 -> -6.6983317 | AY88: =+AX88+AW88 -> -11.863347
B89: - Tax Paid | I89: =+-I38 -> 2.336 | L89: =+-L38 -> 2.7 | M89: =+-M38 -> 1.469 | N89: =+-N38 -> 0.954 | O89: =+-O38 -> 2.423 | P89: =+-P38 -> 2.881 | Q89: =+-Q38 -> -0.694 | R89: =+-R38 -> 2.187 | S89: =+-S38 -> 7.89 | ... W89: =+-W38 -> 4.2355104 | X89: =+W89+V89 -> 8.908678 | Y89: =+-Y38 -> 7.2790283 | Z89: =+-Z38 -> 6.4131058 | AA89: =+Z89+Y89 -> 13.692134 | AB89: =+-AB38 -> 10.603764 | AC89: =+-AC38 -> 10.518634 | AD89: =+AC89+AB89 -> 21.122398 | AE89: =+-AE38 -> 14.985896 | AF89: =+-AF38 -> 14.872112 | AG89: =+AF89+AE89 -> 29.858008 | AH89: =+-AH38 -> 20.209169 | AI89: =+-AI38 -> 19.515862 | AJ89: =+AI89+AH89 -> 39.725031 | AK89: =+-AK38 -> 22.963489 | AL89: =+-AL38 -> 22.757224 | AM89: =+AL89+AK89 -> 45.720713 | AN89: =+-AN38 -> 27.318089 | AO89: =+-AO38 -> 27.010394 | AP89: =+AO89+AN89 -> 54.328483 | AQ89: =+-AQ38 -> 32.128141 | AR89: =+-AR38 -> 31.711166 | AS89: =+AR89+AQ89 -> 63.839307 | AT89: =+-AT38 -> 37.41985 | AU89: =+-AU38 -> 36.882775 | AV89: =+AU89+AT89 -> 74.302625 | AW89: =+-AW38 -> 43.219154 | AX89: =+-AX38 -> 42.551414 | AY89: =+AX89+AW89 -> 85.770568
B90: + Other | I90: =+I89+I88+I87-I86+I91 -> -1.482 | L90: =+L89+L88+L87-L86+L91 -> 2.056 | M90: =+M89+M88+M87-M86+M91 -> 2.228 | N90: =+N89+N88+N87-N86+N91 -> 9.431 | O90: =+O89+O88+O87-O86+O91 -> 14.793 | P90: =+P89+P88+P87-P86+P91 -> 11.045 | Q90: =+Q89+Q88+Q87-Q86+Q91 -> 4.338 | R90: =+R89+R88+R87-R86+R91 -> 15.383 | S90: =+S89+S88+S87-S86+S91 -> -3.742 | ... U90: =+U89+U88+U87-U86+U91 -> 1.737 | V90: 0 | W90: 0 | X90: =+W90+V90 -> 0 | Y90: 0 | Z90: 0 | AA90: =+Z90+Y90 -> 0 | AB90: 0 | AC90: 0 | AD90: =+AC90+AB90 -> 0 | AE90: 0 | AF90: 0 | AG90: =+AF90+AE90 -> 0 | AH90: 0 | AI90: 0 | AJ90: =+AI90+AH90 -> 0 | AK90: 0 | AL90: 0 | AM90: =+AL90+AK90 -> 0 | AN90: 0 | AO90: 0 | AP90: =+AO90+AN90 -> 0 | AQ90: 0 | AR90: 0 | AS90: =+AR90+AQ90 -> 0 | AT90: 0 | AU90: 0 | AV90: =+AU90+AT90 -> 0 | AW90: 0 | AX90: 0 | AY90: =+AX90+AW90 -> 0
B91: Operating cash flow | I91: =+I98 -> 23.066 | L91: =+L98 -> 19.644 | M91: =+M98 -> 13.674 | N91: =+N98 -> 21.273 | O91: =+O98 -> 34.947 | P91: =+P98 -> 14.116 | Q91: =+Q98 -> 22.649 | R91: =+R98 -> 36.765 | S91: =+S98 -> 19.194 | ... U91: =+U98 -> 57.327 | V91: =+V86-V87-V88-V89+V90 -> 47.243771 | W91: =+W86-W87-W88-W89+W90 -> 44.419907 | X91: =+X86-X87-X88-X89+X90 -> 91.663678 | Y91: =+Y86-Y87-Y88-Y89+Y90 -> 56.762388 | Z91: =+Z86-Z87-Z88-Z89+Z90 -> 53.480945 | AA91: =+AA86-AA87-AA88-AA89+AA90 -> 110.24333 | AB91: =+AB86-AB87-AB88-AB89+AB90 -> 68.199579 | AC91: =+AC86-AC87-AC88-AC89+AC90 -> 66.944171 | ... AY91: =+AY86-AY87-AY88-AY89+AY90 -> 344.70465
B93: Operating activities
B94: Receipts from customers | I94: 140.762 | L94: 190.582 | M94: 143.465 | N94: =+O94-M94 -> 152.124 | O94: 295.589 | P94: 200.826 | Q94: =+R94-P94 -> 199.752 | R94: 400.578 | S94: 256.298 | T94: =+U94-S94 -> 258.579 | U94: 514.877
B95: Payments to suppliers & employees | I95: -115.976 | L95: -167.681 | M95: -129.849 | N95: =+O95-M95 -> -130.495 | O95: -260.344 | P95: -187.583 | Q95: =+R95-P95 -> -171.741 | R95: -359.324 | S95: -223.423 | T95: =+U95-S95 -> -214.738 | U95: -438.161
B96: Net Interest paid | I96: -2.221 | L96: =3.173-6.008 -> -2.835 | M96: =0.261-0.124 -> 0.137 | N96: =+O96-M96 -> -0.137 | O96: 0 | P96: =0.503-0.149 -> 0.354 | Q96: =+R96-P96 -> -0.354 | R96: 0 | S96: 0 | T96: =+U96-S96 -> 0 | U96: 0
B97: Income tax paid/refunded | I97: 0.501 | L97: -0.422 | M97: -0.079 | N97: =+O97-M97 -> -0.219 | O97: -0.298 | P97: 0.519 | Q97: =+R97-P97 -> -5.008 | R97: -4.489 | S97: -13.681 | T97: =+U97-S97 -> -5.708 | U97: -19.389
B98: Operating cash flow | I98: =SUM(I94:I97) -> 23.066 | L98: =SUM(L94:L97) -> 19.644 | M98: =SUM(M94:M97) -> 13.674 | N98: =SUM(N94:N97) -> 21.273 | O98: =SUM(O94:O97) -> 34.947 | P98: =SUM(P94:P97) -> 14.116 | Q98: =SUM(Q94:Q97) -> 22.649 | R98: =SUM(R94:R97) -> 36.765 | S98: =SUM(S94:S97) -> 19.194 | ... U98: =SUM(U94:U97) -> 57.327 | V98: =+V91 -> 47.243771 | W98: =+W91 -> 44.419907 | X98: =+X91 -> 91.663678 | Y98: =+Y91 -> 56.762388 | Z98: =+Z91 -> 53.480945 | AA98: =+AA91 -> 110.24333 | AB98: =+AB91 -> 68.199579 | AC98: =+AC91 -> 66.944171 | ... AY98: =+AY91 -> 344.70465
B100: Investing activities
B101: Payment for purchase of business | I101: -2.393 | L101: -5.825 | M101: -5.427 | N101: =+O101-M101 -> -1.013 | O101: -6.44 | P101: 0 | Q101: =+R101-P101 -> -3.128 | R101: -3.128 | S101: -12.09 | T101: =+U101-S101 -> -3.383 | U101: -15.473 | V101: =+-'Balance Sheet'!V115 -> 0 | W101: =+-'Balance Sheet'!W115 -> 0 | X101: =+W101+V101 -> 0 | Y101: =+-'Balance Sheet'!Y115 -> 0 | Z101: =+-'Balance Sheet'!Z115 -> 0 | AA101: =+Z101+Y101 -> 0 | AB101: =+-'Balance Sheet'!AB115 -> 0 | AC101: =+-'Balance Sheet'!AC115 -> 0 | AD101: =+AC101+AB101 -> 0 | AE101: =+-'Balance Sheet'!AE115 -> 0 | AF101: =+-'Balance Sheet'!AF115 -> 0 | AG101: =+AF101+AE101 -> 0 | AH101: =+-'Balance Sheet'!AH115 -> 0 | AI101: =+-'Balance Sheet'!AI115 -> 0 | AJ101: =+AI101+AH101 -> 0 | AK101: =+-'Balance Sheet'!AK115 -> 0 | AL101: =+-'Balance Sheet'!AL115 -> 0 | AM101: =+AL101+AK101 -> 0 | AN101: =+-'Balance Sheet'!AN115 -> 0 | AO101: =+-'Balance Sheet'!AO115 -> 0 | AP101: =+AO101+AN101 -> 0 | AQ101: =+-'Balance Sheet'!AQ115 -> 0 | AR101: =+-'Balance Sheet'!AR115 -> 0 | AS101: =+AR101+AQ101 -> 0 | AT101: =+-'Balance Sheet'!AT115 -> 0 | AU101: =+-'Balance Sheet'!AU115 -> 0 | AV101: =+AU101+AT101 -> 0 | AW101: =+-'Balance Sheet'!AW115 -> 0 | AX101: =+-'Balance Sheet'!AX115 -> 0 | AY101: =+AX101+AW101 -> 0
B102: Payments for PPE (capex) | I102: -11.667 | L102: -19.392 | M102: -14.667 | N102: =+O102-M102 -> -25.046 | O102: -39.713 | P102: -14.867 | Q102: =+R102-P102 -> -18.629 | R102: -33.496 | S102: -21.855 | T102: =+U102-S102 -> -39.471 | U102: -61.326 | V102: =+-'Balance Sheet'!V102 -> -30 | W102: =+-'Balance Sheet'!W102 -> -30 | X102: =+W102+V102 -> -60 | Y102: =+-'Balance Sheet'!Y102 -> -31.95 | Z102: =+-'Balance Sheet'!Z102 -> -31.95 | AA102: =+Z102+Y102 -> -63.9 | AB102: =+-'Balance Sheet'!AB102 -> -34.1865 | AC102: =+-'Balance Sheet'!AC102 -> -34.1865 | AD102: =+AC102+AB102 -> -68.373 | AE102: =+-'Balance Sheet'!AE102 -> -36.579555 | AF102: =+-'Balance Sheet'!AF102 -> -36.579555 | AG102: =+AF102+AE102 -> -73.15911 | AH102: =+-'Balance Sheet'!AH102 -> -39.140124 | AI102: =+-'Balance Sheet'!AI102 -> -39.140124 | AJ102: =+AI102+AH102 -> -78.280248 | AK102: =+-'Balance Sheet'!AK102 -> -41.879933 | AL102: =+-'Balance Sheet'!AL102 -> -41.879933 | AM102: =+AL102+AK102 -> -83.759865 | AN102: =+-'Balance Sheet'!AN102 -> -44.811528 | AO102: =+-'Balance Sheet'!AO102 -> -44.811528 | AP102: =+AO102+AN102 -> -89.623056 | AQ102: =+-'Balance Sheet'!AQ102 -> -47.948335 | AR102: =+-'Balance Sheet'!AR102 -> -47.948335 | AS102: =+AR102+AQ102 -> -95.896669 | AT102: =+-'Balance Sheet'!AT102 -> -51.304718 | AU102: =+-'Balance Sheet'!AU102 -> -51.304718 | AV102: =+AU102+AT102 -> -102.60944 | AW102: =+-'Balance Sheet'!AW102 -> -54.896048 | AX102: =+-'Balance Sheet'!AX102 -> -54.896048 | AY102: =+AX102+AW102 -> -109.7921
B103: Payments for intangibles (capex) | I103: -3.496 | L103: -7.011 | M103: -1.449 | N103: =+O103-M103 -> -1.495 | O103: -2.944 | P103: -0.009 | Q103: =+R103-P103 -> -0.054 | R103: -0.063 | S103: -0.008 | T103: =+U103-S103 -> -0.029 | U103: -0.037 | V103: =-'Balance Sheet'!V103-'Balance Sheet'!V114 -> 0 | W103: =-'Balance Sheet'!W103-'Balance Sheet'!W114 -> 0 | X103: =+W103+V103 -> 0 | Y103: =-'Balance Sheet'!Y103-'Balance Sheet'!Y114 -> 0 | Z103: =-'Balance Sheet'!Z103-'Balance Sheet'!Z114 -> 0 | AA103: =+Z103+Y103 -> 0 | AB103: =-'Balance Sheet'!AB103-'Balance Sheet'!AB114 -> 0 | AC103: =-'Balance Sheet'!AC103-'Balance Sheet'!AC114 -> 0 | AD103: =+AC103+AB103 -> 0 | AE103: =-'Balance Sheet'!AE103-'Balance Sheet'!AE114 -> 0 | AF103: =-'Balance Sheet'!AF103-'Balance Sheet'!AF114 -> 0 | AG103: =+AF103+AE103 -> 0 | AH103: =-'Balance Sheet'!AH103-'Balance Sheet'!AH114 -> 0 | AI103: =-'Balance Sheet'!AI103-'Balance Sheet'!AI114 -> 0 | AJ103: =+AI103+AH103 -> 0 | AK103: =-'Balance Sheet'!AK103-'Balance Sheet'!AK114 -> 0 | AL103: =-'Balance Sheet'!AL103-'Balance Sheet'!AL114 -> 0 | AM103: =+AL103+AK103 -> 0 | AN103: =-'Balance Sheet'!AN103-'Balance Sheet'!AN114 -> 0 | AO103: =-'Balance Sheet'!AO103-'Balance Sheet'!AO114 -> 0 | AP103: =+AO103+AN103 -> 0 | AQ103: =-'Balance Sheet'!AQ103-'Balance Sheet'!AQ114 -> 0 | AR103: =-'Balance Sheet'!AR103-'Balance Sheet'!AR114 -> 0 | AS103: =+AR103+AQ103 -> 0 | AT103: =-'Balance Sheet'!AT103-'Balance Sheet'!AT114 -> 0 | AU103: =-'Balance Sheet'!AU103-'Balance Sheet'!AU114 -> 0 | AV103: =+AU103+AT103 -> 0 | AW103: =-'Balance Sheet'!AW103-'Balance Sheet'!AW114 -> 0 | AX103: =-'Balance Sheet'!AX103-'Balance Sheet'!AX114 -> 0 | AY103: =+AX103+AW103 -> 0
B104: Proceeds from disposal of business | I104: 0 | L104: 0.53 | M104: 0.019 | N104: =+O104-M104 -> 0.675 | O104: 0.694 | P104: 0 | Q104: =+R104-P104 -> 2.964 | R104: 2.964 | S104: 0 | T104: =+U104-S104 -> 3.879 | U104: 3.879 | V104: =-'Balance Sheet'!V104-'Balance Sheet'!V116 -> 0 | W104: =-'Balance Sheet'!W104-'Balance Sheet'!W116 -> 0 | X104: =+W104+V104 -> 0 | Y104: =-'Balance Sheet'!Y104-'Balance Sheet'!Y116 -> 0 | Z104: =-'Balance Sheet'!Z104-'Balance Sheet'!Z116 -> 0 | AA104: =+Z104+Y104 -> 0 | AB104: =-'Balance Sheet'!AB104-'Balance Sheet'!AB116 -> 0 | AC104: =-'Balance Sheet'!AC104-'Balance Sheet'!AC116 -> 0 | AD104: =+AC104+AB104 -> 0 | AE104: =-'Balance Sheet'!AE104-'Balance Sheet'!AE116 -> 0 | AF104: =-'Balance Sheet'!AF104-'Balance Sheet'!AF116 -> 0 | AG104: =+AF104+AE104 -> 0 | AH104: =-'Balance Sheet'!AH104-'Balance Sheet'!AH116 -> 0 | AI104: =-'Balance Sheet'!AI104-'Balance Sheet'!AI116 -> 0 | AJ104: =+AI104+AH104 -> 0 | AK104: =-'Balance Sheet'!AK104-'Balance Sheet'!AK116 -> 0 | AL104: =-'Balance Sheet'!AL104-'Balance Sheet'!AL116 -> 0 | AM104: =+AL104+AK104 -> 0 | AN104: =-'Balance Sheet'!AN104-'Balance Sheet'!AN116 -> 0 | AO104: =-'Balance Sheet'!AO104-'Balance Sheet'!AO116 -> 0 | AP104: =+AO104+AN104 -> 0 | AQ104: =-'Balance Sheet'!AQ104-'Balance Sheet'!AQ116 -> 0 | AR104: =-'Balance Sheet'!AR104-'Balance Sheet'!AR116 -> 0 | AS104: =+AR104+AQ104 -> 0 | AT104: =-'Balance Sheet'!AT104-'Balance Sheet'!AT116 -> 0 | AU104: =-'Balance Sheet'!AU104-'Balance Sheet'!AU116 -> 0 | AV104: =+AU104+AT104 -> 0 | AW104: =-'Balance Sheet'!AW104-'Balance Sheet'!AW116 -> 0 | AX104: =-'Balance Sheet'!AX104-'Balance Sheet'!AX116 -> 0 | AY104: =+AX104+AW104 -> 0
B105: Other | I105: 0 | L105: 0 | M105: 0 | N105: =+O105-M105 -> 0 | O105: 0 | P105: 0 | Q105: =+R105-P105 -> -278.095 | R105: -278.095 | S105: 25.873 | T105: =+U105-S105 -> 12.533 | U105: 38.406 | V105: 0 | W105: 0 | X105: =+W105+V105 -> 0 | Y105: 0 | Z105: 0 | AA105: =+Z105+Y105 -> 0 | AB105: 0 | AC105: 0 | AD105: =+AC105+AB105 -> 0 | AE105: 0 | AF105: 0 | AG105: =+AF105+AE105 -> 0 | AH105: 0 | AI105: 0 | AJ105: =+AI105+AH105 -> 0 | AK105: 0 | AL105: 0 | AM105: =+AL105+AK105 -> 0 | AN105: 0 | AO105: 0 | AP105: =+AO105+AN105 -> 0 | AQ105: 0 | AR105: 0 | AS105: =+AR105+AQ105 -> 0 | AT105: 0 | AU105: 0 | AV105: =+AU105+AT105 -> 0 | AW105: 0 | AX105: 0 | AY105: =+AX105+AW105 -> 0
B106: Investing cash flow | I106: =SUM(I101:I105) -> -17.556 | L106: =SUM(L101:L105) -> -31.698 | M106: =SUM(M101:M105) -> -21.524 | N106: =SUM(N101:N105) -> -26.879 | O106: =SUM(O101:O105) -> -48.403 | P106: =SUM(P101:P105) -> -14.876 | Q106: =SUM(Q101:Q105) -> -296.942 | R106: =SUM(R101:R105) -> -311.818 | S106: =SUM(S101:S105) -> -8.08 | ... AY106: =SUM(AY101:AY105) -> -109.7921
B108: Financing activities
B109: Proceeds from borrowings | I109: 0.674 | L109: 0 | M109: 0 | N109: =+O109-M109 -> 0 | O109: 0 | P109: 0 | Q109: =+R109-P109 -> 0 | R109: 0 | S109: 0 | T109: =+U109-S109 -> 0 | U109: 0
B110: Repayment of borrowings | I110: -0.501 | L110: -0.489 | M110: -0.233 | N110: =+O110-M110 -> -0.125 | O110: -0.358 | P110: 0 | Q110: =+R110-P110 -> -3 | R110: -3 | S110: 0 | T110: =+U110-S110 -> 0 | U110: 0 | V110: =+'Balance Sheet'!V145 -> 0 | W110: =+'Balance Sheet'!W145 -> 0 | X110: =+W110+V110 -> 0 | Y110: =+'Balance Sheet'!Y145 -> 0 | Z110: =+'Balance Sheet'!Z145 -> 0 | AA110: =+Z110+Y110 -> 0 | AB110: =+'Balance Sheet'!AB145 -> 0 | AC110: =+'Balance Sheet'!AC145 -> 0 | AD110: =+AC110+AB110 -> 0 | AE110: =+'Balance Sheet'!AE145 -> 0 | AF110: =+'Balance Sheet'!AF145 -> 0 | AG110: =+AF110+AE110 -> 0 | AH110: =+'Balance Sheet'!AH145 -> 0 | AI110: =+'Balance Sheet'!AI145 -> 0 | AJ110: =+AI110+AH110 -> 0 | AK110: =+'Balance Sheet'!AK145 -> 0 | AL110: =+'Balance Sheet'!AL145 -> 0 | AM110: =+AL110+AK110 -> 0 | AN110: =+'Balance Sheet'!AN145 -> 0 | AO110: =+'Balance Sheet'!AO145 -> 0 | AP110: =+AO110+AN110 -> 0 | AQ110: =+'Balance Sheet'!AQ145 -> 0 | AR110: =+'Balance Sheet'!AR145 -> 0 | AS110: =+AR110+AQ110 -> 0 | AT110: =+'Balance Sheet'!AT145 -> 0 | AU110: =+'Balance Sheet'!AU145 -> 0 | AV110: =+AU110+AT110 -> 0 | AW110: =+'Balance Sheet'!AW145 -> 0 | AX110: =+'Balance Sheet'!AX145 -> 0 | AY110: =+AX110+AW110 -> 0
B111: Payments of lease liabilities (principal) | I111: 0 | L111: 0 | M111: -4.931 | N111: =+O111-M111 -> -1.789 | O111: -6.72 | P111: -3.552 | Q111: =+R111-P111 -> -6.36 | R111: -9.912 | S111: -7.515 | T111: =+U111-S111 -> -3.315 | U111: -10.83 | V111: =+'Balance Sheet'!V136 -> -6.65898 | W111: =+'Balance Sheet'!W136 -> -5.27266 | X111: =+W111+V111 -> -11.93164 | Y111: =+'Balance Sheet'!Y136 -> -7.1584035 | Z111: =+'Balance Sheet'!Z136 -> -5.6681095 | AA111: =+Z111+Y111 -> -12.826513 | AB111: =+'Balance Sheet'!AB136 -> -7.6952838 | AC111: =+'Balance Sheet'!AC136 -> -6.0932177 | AD111: =+AC111+AB111 -> -13.788501 | AE111: =+'Balance Sheet'!AE136 -> -8.27243 | AF111: =+'Balance Sheet'!AF136 -> -6.550209 | AG111: =+AF111+AE111 -> -14.822639 | AH111: =+'Balance Sheet'!AH136 -> -8.8928623 | AI111: =+'Balance Sheet'!AI136 -> -7.0414747 | AJ111: =+AI111+AH111 -> -15.934337 | AK111: =+'Balance Sheet'!AK136 -> -9.559827 | AL111: =+'Balance Sheet'!AL136 -> -7.5695853 | AM111: =+AL111+AK111 -> -17.129412 | AN111: =+'Balance Sheet'!AN136 -> -10.276814 | AO111: =+'Balance Sheet'!AO136 -> -8.1373042 | AP111: =+AO111+AN111 -> -18.414118 | AQ111: =+'Balance Sheet'!AQ136 -> -11.047575 | AR111: =+'Balance Sheet'!AR136 -> -8.747602 | AS111: =+AR111+AQ111 -> -19.795177 | AT111: =+'Balance Sheet'!AT136 -> -11.876143 | AU111: =+'Balance Sheet'!AU136 -> -9.4036722 | AV111: =+AU111+AT111 -> -21.279815 | AW111: =+'Balance Sheet'!AW136 -> -12.766854 | AX111: =+'Balance Sheet'!AX136 -> -10.108948 | AY111: =+AX111+AW111 -> -22.875802
B112: Payments of lease liabilities (interest) | I112: -3.676 | L112: -4.108 | M112: =-1.759 -> -1.759 | N112: =+O112-M112 -> -2.847 | O112: =-4.606 -> -4.606 | P112: =-2.995 -> -2.995 | Q112: =+R112-P112 -> -3.325 | R112: =-6.32 -> -6.32 | S112: -3.914 | T112: =+U112-S112 -> -4.712 | U112: -8.626 | V112: =+'Balance Sheet'!V140 -> -9.3498471 | W112: =+'Balance Sheet'!W140 -> -9.5174753 | X112: =+W112+V112 -> -18.867322 | Y112: =+'Balance Sheet'!Y140 -> -9.6394182 | Z112: =+'Balance Sheet'!Z140 -> -9.8118716 | AA112: =+Z112+Y112 -> -19.45129 | AB112: =+'Balance Sheet'!AB140 -> -9.9345549 | AC112: =+'Balance Sheet'!AC140 -> -10.110822 | AD112: =+AC112+AB112 -> -20.045377 | AE112: =+'Balance Sheet'!AE140 -> -10.232812 | AF112: =+'Balance Sheet'!AF140 -> -10.411564 | AG112: =+AF112+AE112 -> -20.644376 | AH112: =+'Balance Sheet'!AH140 -> -10.531054 | AI112: =+'Balance Sheet'!AI140 -> -10.710573 | AJ112: =+AI112+AH112 -> -21.241627 | AK112: =+'Balance Sheet'!AK140 -> -10.825312 | AL112: =+'Balance Sheet'!AL140 -> -11.003417 | AM112: =+AL112+AK112 -> -21.828729 | AN112: =+'Balance Sheet'!AN140 -> -11.110618 | AO112: =+'Balance Sheet'!AO140 -> -11.284564 | AP112: =+AO112+AN112 -> -22.395182 | AQ112: =+'Balance Sheet'!AQ140 -> -11.380801 | AR112: =+'Balance Sheet'!AR140 -> -11.547174 | AS112: =+AR112+AQ112 -> -22.927976 | AT112: =+'Balance Sheet'!AT140 -> -11.628256 | AU112: =+'Balance Sheet'!AU140 -> -11.782834 | AV112: =+AU112+AT112 -> -23.41109 | AW112: =+'Balance Sheet'!AW140 -> -11.84366 | AX112: =+'Balance Sheet'!AX140 -> -11.981254 | AY112: =+AX112+AW112 -> -23.824913
B113: Dividends | I113: 0 | L113: 0 | M113: 0 | N113: =+O113-M113 -> 0 | O113: 0 | P113: 0 | Q113: =+R113-P113 -> 0 | R113: 0 | S113: 0 | T113: =+U113-S113 -> 0 | U113: 0 | V113: =+'Balance Sheet'!V185 -> 0 | W113: =+'Balance Sheet'!W185 -> 0 | X113: =+W113+V113 -> 0 | Y113: =+'Balance Sheet'!Y185 -> 0 | Z113: =+'Balance Sheet'!Z185 -> 0 | AA113: =+Z113+Y113 -> 0 | AB113: =+'Balance Sheet'!AB185 -> 0 | AC113: =+'Balance Sheet'!AC185 -> 0 | AD113: =+AC113+AB113 -> 0 | AE113: =+'Balance Sheet'!AE185 -> 0 | AF113: =+'Balance Sheet'!AF185 -> 0 | AG113: =+AF113+AE113 -> 0 | AH113: =+'Balance Sheet'!AH185 -> 0 | AI113: =+'Balance Sheet'!AI185 -> 0 | AJ113: =+AI113+AH113 -> 0 | AK113: =+'Balance Sheet'!AK185 -> 0 | AL113: =+'Balance Sheet'!AL185 -> 0 | AM113: =+AL113+AK113 -> 0 | AN113: =+'Balance Sheet'!AN185 -> 0 | AO113: =+'Balance Sheet'!AO185 -> 0 | AP113: =+AO113+AN113 -> 0 | AQ113: =+'Balance Sheet'!AQ185 -> 0 | AR113: =+'Balance Sheet'!AR185 -> 0 | AS113: =+AR113+AQ113 -> 0 | AT113: =+'Balance Sheet'!AT185 -> 0 | AU113: =+'Balance Sheet'!AU185 -> 0 | AV113: =+AU113+AT113 -> 0 | AW113: =+'Balance Sheet'!AW185 -> 0 | AX113: =+'Balance Sheet'!AX185 -> 0 | AY113: =+AX113+AW113 -> 0
B114: Proceeds from issue of shares | I114: 35.664 | L114: 8.908 | M114: 4.458 | N114: =+O114-M114 -> 0.425 | O114: 4.883 | P114: 0.142 | Q114: =+R114-P114 -> 284.157 | R114: 284.299 | S114: 0 | T114: =+U114-S114 -> 0 | U114: 0 | V114: 0 | W114: 0 | X114: =+W114+V114 -> 0 | Y114: 0 | Z114: 0 | AA114: =+Z114+Y114 -> 0 | AB114: 0 | AC114: 0 | AD114: =+AC114+AB114 -> 0 | AE114: 0 | AF114: 0 | AG114: =+AF114+AE114 -> 0 | AH114: 0 | AI114: 0 | AJ114: =+AI114+AH114 -> 0 | AK114: 0 | AL114: 0 | AM114: =+AL114+AK114 -> 0 | AN114: 0 | AO114: 0 | AP114: =+AO114+AN114 -> 0 | AQ114: 0 | AR114: 0 | AS114: =+AR114+AQ114 -> 0 | AT114: 0 | AU114: 0 | AV114: =+AU114+AT114 -> 0 | AW114: 0 | AX114: 0 | AY114: =+AX114+AW114 -> 0
B115: Lease incentives received | I115: 0 | L115: 0 | M115: 0 | N115: =+O115-M115 -> 1.429 | O115: 1.429 | P115: 0 | Q115: =+R115-P115 -> 6.1 | R115: 6.1 | S115: 0.088 | T115: =+U115-S115 -> 3.152 | U115: =0.96+2.28 -> 3.24 | V115: 0 | W115: 0 | X115: =+W115+V115 -> 0 | Y115: 0 | Z115: 0 | AA115: =+Z115+Y115 -> 0 | AB115: 0 | AC115: 0 | AD115: =+AC115+AB115 -> 0 | AE115: 0 | AF115: 0 | AG115: =+AF115+AE115 -> 0 | AH115: 0 | AI115: 0 | AJ115: =+AI115+AH115 -> 0 | AK115: 0 | AL115: 0 | AM115: =+AL115+AK115 -> 0 | AN115: 0 | AO115: 0 | AP115: =+AO115+AN115 -> 0 | AQ115: 0 | AR115: 0 | AS115: =+AR115+AQ115 -> 0 | AT115: 0 | AU115: 0 | AV115: =+AU115+AT115 -> 0 | AW115: 0 | AX115: 0 | AY115: =+AX115+AW115 -> 0
B116: Option fees received | I116: 0.061 | L116: 0.079 | M116: 0.29 | N116: =+O116-M116 -> -0.045 | O116: 0.245 | P116: 0.173 | Q116: =+R116-P116 -> 7.618 | R116: 7.791 | S116: 0.885 | T116: =+U116-S116 -> 7.649 | U116: 8.534 | V116: 0 | W116: 0 | X116: =+W116+V116 -> 0 | Y116: 0 | Z116: 0 | AA116: =+Z116+Y116 -> 0 | AB116: 0 | AC116: 0 | AD116: =+AC116+AB116 -> 0 | AE116: 0 | AF116: 0 | AG116: =+AF116+AE116 -> 0 | AH116: 0 | AI116: 0 | AJ116: =+AI116+AH116 -> 0 | AK116: 0 | AL116: 0 | AM116: =+AL116+AK116 -> 0 | AN116: 0 | AO116: 0 | AP116: =+AO116+AN116 -> 0 | AQ116: 0 | AR116: 0 | AS116: =+AR116+AQ116 -> 0 | AT116: 0 | AU116: 0 | AV116: =+AU116+AT116 -> 0 | AW116: 0 | AX116: 0 | AY116: =+AX116+AW116 -> 0
B117: Payments for share buy-backs | I117: 0 | L117: 0 | M117: 0 | N117: =+O117-M117 -> 0 | O117: 0 | P117: -15.893 | Q117: =+R117-P117 -> -0.001 | R117: -15.894 | S117: 0 | T117: =+U117-S117 -> 0 | V117: 0 | W117: 0 | X117: =+W117+V117 -> 0 | Y117: 0 | Z117: 0 | AA117: =+Z117+Y117 -> 0 | AB117: 0 | AC117: 0 | AD117: =+AC117+AB117 -> 0 | AE117: 0 | AF117: 0 | AG117: =+AF117+AE117 -> 0 | AH117: 0 | AI117: 0 | AJ117: =+AI117+AH117 -> 0 | AK117: 0 | AL117: 0 | AM117: =+AL117+AK117 -> 0 | AN117: 0 | AO117: 0 | AP117: =+AO117+AN117 -> 0 | AQ117: 0 | AR117: 0 | AS117: =+AR117+AQ117 -> 0 | AT117: 0 | AU117: 0 | AV117: =+AU117+AT117 -> 0 | AW117: 0 | AX117: 0 | AY117: =+AX117+AW117 -> 0
B118: Other | I118: 0 | L118: 0 | M118: 0 | N118: =+O118-M118 -> 0.66 | O118: =0.964-0.304 -> 0.66 | P118: 0 | Q118: =+R118-P118 -> -8.13 | R118: =-8.973+1.172-0.329 -> -8.13 | S118: =-1.693+0.162+1.261-0.066 -> -0.336 | T118: =+U118-S118 -> 8.697 | U118: =-1.693-0.131+10.185 -> 8.361 | V118: 0 | W118: 0 | X118: =+W118+V118 -> 0 | Y118: 0 | Z118: 0 | AA118: =+Z118+Y118 -> 0 | AB118: 0 | AC118: 0 | AD118: =+AC118+AB118 -> 0 | AE118: 0 | AF118: 0 | AG118: =+AF118+AE118 -> 0 | AH118: 0 | AI118: 0 | AJ118: =+AI118+AH118 -> 0 | AK118: 0 | AL118: 0 | AM118: =+AL118+AK118 -> 0 | AN118: 0 | AO118: 0 | AP118: =+AO118+AN118 -> 0 | AQ118: 0 | AR118: 0 | AS118: =+AR118+AQ118 -> 0 | AT118: 0 | AU118: 0 | AV118: =+AU118+AT118 -> 0 | AW118: 0 | AX118: 0 | AY118: =+AX118+AW118 -> 0
...

Sheet Balance Sheet
B1: =+'GYG model ->'!D2 -> Guzman y Gomez (GYG.ASX)
B2: Balance Sheet
B4: Year-end 30th June (A$m) | D4: =+'Income & Cash Flow'!D4 -> 1H20A | E4: =+'Income & Cash Flow'!E4 -> 2H20A | F4: =+'Income & Cash Flow'!F4 -> FY20A | G4: =+'Income & Cash Flow'!G4 -> 1H21A | H4: =+'Income & Cash Flow'!H4 -> 2H21A | I4: =+'Income & Cash Flow'!I4 -> FY21A | J4: =+'Income & Cash Flow'!J4 -> 1H22A | K4: =+'Income & Cash Flow'!K4 -> 2H22A | ... AY4: =+'Income & Cash Flow'!AY4 -> FY35E
B5: Balance Sheet
B6: Cash & equivalents | I6: 62.091 | L6: 54.427 | O6: 36.504 | P6: 13.619 | Q6: =+R6 -> 16.385 | R6: =16.385 -> 16.385 | S6: 16.882 | T6: =+U6 -> 39.675 | U6: 39.675 | V6: =+'Income & Cash Flow'!V124 -> 40.909944 | W6: =+X6 -> 40.539715 | X6: =+'Income & Cash Flow'!X124 -> 40.539715 | Y6: =+'Income & Cash Flow'!Y124 -> 48.554282 | Z6: =+AA6 -> 54.605246 | AA6: =+'Income & Cash Flow'!AA124 -> 54.605246 | AB6: =+'Income & Cash Flow'!AB124 -> 70.988486 | AC6: =+AD6 -> 87.542117 | AD6: =+'Income & Cash Flow'!AD124 -> 87.542117 | AE6: =+'Income & Cash Flow'!AE124 -> 114.75945 | AF6: =+AG6 -> 142.17969 | AG6: =+'Income & Cash Flow'!AG124 -> 142.17969 | AH6: =+'Income & Cash Flow'!AH124 -> 181.95419 | AI6: =+AJ6 -> 220.82849 | AJ6: =+'Income & Cash Flow'!AJ124 -> 220.82849 | AK6: =+'Income & Cash Flow'!AK124 -> 269.33614 | AL6: =+AM6 -> 315.88515 | AM6: =+'Income & Cash Flow'!AM124 -> 315.88515 | AN6: =+'Income & Cash Flow'!AN124 -> 374.18708 | AO6: =+AP6 -> 430.83343 | AP6: =+'Income & Cash Flow'!AP124 -> 430.83343 | AQ6: =+'Income & Cash Flow'!AQ124 -> 500.49796 | AR6: =+AS6 -> 568.15921 | AS6: =+'Income & Cash Flow'!AS124 -> 568.15921 | AT6: =+'Income & Cash Flow'!AT124 -> 650.1915 | AU6: =+AV6 -> 729.85629 | AV6: =+'Income & Cash Flow'!AV124 -> 729.85629 | AW6: =+'Income & Cash Flow'!AW124 -> 825.33689 | AX6: =+AY6 -> 918.06813 | AY6: =+'Income & Cash Flow'!AY124 -> 918.06813
B7: Receivables | I7: 4.993 | L7: 16.352 | O7: 23.947 | P7: 21.198 | Q7: =+R7 -> 26.02 | R7: 26.02 | S7: 18.852 | T7: =+U7 -> 24.703 | U7: 24.703 | V7: =+V79 -> 30.056948 | W7: =+X7 -> 30.530703 | X7: =+X79 -> 30.530703 | Y7: =+Y79 -> 35.880664 | Z7: =+AA7 -> 36.366779 | AA7: =+AA79 -> 36.366779 | AB7: =+AB79 -> 42.29088 | AC7: =+AD7 -> 42.699203 | AD7: =+AD79 -> 42.699203 | AE7: =+AE79 -> 48.585046 | AF7: =+AG7 -> 48.940995 | AG7: =+AG79 -> 48.940995 | AH7: =+AH79 -> 55.32315 | AI7: =+AJ7 -> 55.520988 | AJ7: =+AJ79 -> 55.520988 | AK7: =+AK79 -> 62.307826 | AL7: =+AM7 -> 62.432011 | AM7: =+AM79 -> 62.432011 | AN7: =+AN79 -> 69.742683 | AO7: =+AP7 -> 69.787763 | AP7: =+AP79 -> 69.787763 | AQ7: =+AQ79 -> 77.653388 | AR7: =+AS7 -> 77.61358 | AS7: =+AS79 -> 77.61358 | AT7: =+AT79 -> 86.066934 | AU7: =+AV7 -> 85.936118 | AV7: =+AV79 -> 85.936118 | AW7: =+AW79 -> 95.011735 | AX7: =+AY7 -> 94.783448 | AY7: =+AY79 -> 94.783448
B8: Inventories | I8: 1.652 | L8: 1.987 | O8: 2.153 | P8: 3.171 | Q8: =+R8 -> 2.825 | R8: 2.825 | S8: 4.249 | T8: =+U8 -> 3.761 | U8: 3.761 | V8: =+V83 -> 4.5761317 | W8: =+X8 -> 4.6482604 | X8: =+X83 -> 4.6482604 | Y8: =+Y83 -> 5.462785 | Z8: =+AA8 -> 5.5367953 | AA8: =+AA83 -> 5.5367953 | AB8: =+AB83 -> 6.4387322 | AC8: =+AD8 -> 6.5008987 | AD8: =+AD83 -> 6.5008987 | AE8: =+AE83 -> 7.3970108 | AF8: =+AG8 -> 7.4512036 | AG8: =+AG83 -> 7.4512036 | AH8: =+AH83 -> 8.4228785 | AI8: =+AJ8 -> 8.452999 | AJ8: =+AJ83 -> 8.452999 | AK8: =+AK83 -> 9.4862865 | AL8: =+AM8 -> 9.5051934 | AM8: =+AM83 -> 9.5051934 | AN8: =+AN83 -> 10.618234 | AO8: =+AP8 -> 10.625097 | AP8: =+AP83 -> 10.625097 | AQ8: =+AQ83 -> 11.822629 | AR8: =+AS8 -> 11.816568 | AS8: =+AS83 -> 11.816568 | AT8: =+AT83 -> 13.10358 | AU8: =+AV8 -> 13.083664 | AV8: =+AV83 -> 13.083664 | AW8: =+AW83 -> 14.465415 | AX8: =+AY8 -> 14.430658 | AY8: =+AY83 -> 14.430658
B9: Finance lease receivable | I9: 10.731 | L9: 10.898 | O9: 10.772 | P9: 10.514 | Q9: =R9 -> 11.999 | R9: 11.999 | S9: 12.25 | T9: =U9 -> 12.497 | U9: 12.497 | V9: =+U9 -> 12.497 | W9: =+X9 -> 12.497 | X9: =+V9 -> 12.497 | Y9: =+X9 -> 12.497 | Z9: =+AA9 -> 12.497 | AA9: =+Y9 -> 12.497 | AB9: =+AA9 -> 12.497 | AC9: =+AD9 -> 12.497 | AD9: =+AB9 -> 12.497 | AE9: =+AD9 -> 12.497 | AF9: =+AG9 -> 12.497 | AG9: =+AE9 -> 12.497 | AH9: =+AG9 -> 12.497 | AI9: =+AJ9 -> 12.497 | AJ9: =+AH9 -> 12.497 | AK9: =+AJ9 -> 12.497 | AL9: =+AM9 -> 12.497 | AM9: =+AK9 -> 12.497 | AN9: =+AM9 -> 12.497 | AO9: =+AP9 -> 12.497 | AP9: =+AN9 -> 12.497 | AQ9: =+AP9 -> 12.497 | AR9: =+AS9 -> 12.497 | AS9: =+AQ9 -> 12.497 | AT9: =+AS9 -> 12.497 | AU9: =+AV9 -> 12.497 | AV9: =+AT9 -> 12.497 | AW9: =+AV9 -> 12.497 | AX9: =+AY9 -> 12.497 | AY9: =+AW9 -> 12.497
B10: Term deposit | I10: 0 | L10: 0 | O10: 0 | P10: 0 | Q10: =R10 -> 278.095 | R10: 278.095 | S10: 257.611 | T10: =U10 -> 242.068 | U10: 242.068 | V10: =+U10 -> 242.068 | W10: =+X10 -> 242.068 | X10: =+V10 -> 242.068 | Y10: =+X10 -> 242.068 | Z10: =+AA10 -> 242.068 | AA10: =+Y10 -> 242.068 | AB10: =+AA10 -> 242.068 | AC10: =+AD10 -> 242.068 | AD10: =+AB10 -> 242.068 | AE10: =+AD10 -> 242.068 | AF10: =+AG10 -> 242.068 | AG10: =+AE10 -> 242.068 | AH10: =+AG10 -> 242.068 | AI10: =+AJ10 -> 242.068 | AJ10: =+AH10 -> 242.068 | AK10: =+AJ10 -> 242.068 | AL10: =+AM10 -> 242.068 | AM10: =+AK10 -> 242.068 | AN10: =+AM10 -> 242.068 | AO10: =+AP10 -> 242.068 | AP10: =+AN10 -> 242.068 | AQ10: =+AP10 -> 242.068 | AR10: =+AS10 -> 242.068 | AS10: =+AQ10 -> 242.068 | AT10: =+AS10 -> 242.068 | AU10: =+AV10 -> 242.068 | AV10: =+AT10 -> 242.068 | AW10: =+AV10 -> 242.068 | AX10: =+AY10 -> 242.068 | AY10: =+AW10 -> 242.068
B11: Other current assets | I11: 2.056 | L11: 2.799 | O11: 3.56 | P11: 4.43 | Q11: =+R11 -> 3.302 | R11: =3.302 -> 3.302 | S11: 4.604 | T11: =+U11 -> 4.51 | U11: 4.51 | V11: =+U11 -> 4.51 | W11: =+X11 -> 4.51 | X11: =+V11 -> 4.51 | Y11: =+X11 -> 4.51 | Z11: =+AA11 -> 4.51 | AA11: =+Y11 -> 4.51 | AB11: =+AA11 -> 4.51 | AC11: =+AD11 -> 4.51 | AD11: =+AB11 -> 4.51 | AE11: =+AD11 -> 4.51 | AF11: =+AG11 -> 4.51 | AG11: =+AE11 -> 4.51 | AH11: =+AG11 -> 4.51 | AI11: =+AJ11 -> 4.51 | AJ11: =+AH11 -> 4.51 | AK11: =+AJ11 -> 4.51 | AL11: =+AM11 -> 4.51 | AM11: =+AK11 -> 4.51 | AN11: =+AM11 -> 4.51 | AO11: =+AP11 -> 4.51 | AP11: =+AN11 -> 4.51 | AQ11: =+AP11 -> 4.51 | AR11: =+AS11 -> 4.51 | AS11: =+AQ11 -> 4.51 | AT11: =+AS11 -> 4.51 | AU11: =+AV11 -> 4.51 | AV11: =+AT11 -> 4.51 | AW11: =+AV11 -> 4.51 | AX11: =+AY11 -> 4.51 | AY11: =+AW11 -> 4.51
B12: Total current assets | I12: =SUM(I6:I11) -> 81.523 | L12: =SUM(L6:L11) -> 86.463 | O12: =SUM(O6:O11) -> 76.936 | P12: =SUM(P6:P11) -> 52.932 | Q12: =SUM(Q6:Q11) -> 338.626 | R12: =SUM(R6:R11) -> 338.626 | S12: =SUM(S6:S11) -> 314.448 | T12: =SUM(T6:T11) -> 327.214 | U12: =SUM(U6:U11) -> 327.214 | V12: =SUM(V6:V11) -> 334.61802 | ... AY12: =SUM(AY6:AY11) -> 1286.3572
B14: Receivables | I14: 0.389 | L14: 0.594 | O14: 1.14 | P14: 1.001 | Q14: =+R14 -> 0.479 | R14: 0.479 | S14: 0.238 | T14: =+U14 -> 0.137 | U14: 0.137 | V14: =+U14 -> 0.137 | W14: =+X14 -> 0.137 | X14: =+V14 -> 0.137 | Y14: =+X14 -> 0.137 | Z14: =+AA14 -> 0.137 | AA14: =+Y14 -> 0.137 | AB14: =+AA14 -> 0.137 | AC14: =+AD14 -> 0.137 | AD14: =+AB14 -> 0.137 | AE14: =+AD14 -> 0.137 | AF14: =+AG14 -> 0.137 | AG14: =+AE14 -> 0.137 | AH14: =+AG14 -> 0.137 | AI14: =+AJ14 -> 0.137 | AJ14: =+AH14 -> 0.137 | AK14: =+AJ14 -> 0.137 | AL14: =+AM14 -> 0.137 | AM14: =+AK14 -> 0.137 | AN14: =+AM14 -> 0.137 | AO14: =+AP14 -> 0.137 | AP14: =+AN14 -> 0.137 | AQ14: =+AP14 -> 0.137 | AR14: =+AS14 -> 0.137 | AS14: =+AQ14 -> 0.137 | AT14: =+AS14 -> 0.137 | AU14: =+AV14 -> 0.137 | AV14: =+AT14 -> 0.137 | AW14: =+AV14 -> 0.137 | AX14: =+AY14 -> 0.137 | AY14: =+AW14 -> 0.137
B15: PPE | I15: 21.516 | L15: 36.563 | O15: 69.486 | P15: 77.953 | Q15: =+R15 -> 87.63 | R15: 87.63 | S15: 103.028 | T15: =+U15 -> 130.056 | U15: 130.056 | V15: =+V107 -> 147.0504 | W15: =+X15 -> 162.34536 | X15: =+X107 -> 162.34536 | Y15: =+Y107 -> 178.06082 | Z15: =+AA15 -> 192.20474 | AA15: =+AA107 -> 192.20474 | AB15: =+AB107 -> 207.17077 | AC15: =+AD15 -> 220.64019 | AD15: =+AD107 -> 220.64019 | AE15: =+AE107 -> 235.15573 | AF15: =+AG15 -> 248.21971 | AG15: =+AG107 -> 248.21971 | AH15: =+AH107 -> 262.53786 | AI15: =+AJ15 -> 275.4242 | AJ15: =+AJ107 -> 275.4242 | AK15: =+AK107 -> 289.76171 | AL15: =+AM15 -> 302.66547 | AM15: =+AM107 -> 302.66547 | AN15: =+AN107 -> 317.21045 | AO15: =+AP15 -> 330.30094 | AP15: =+AP107 -> 330.30094 | AQ15: =+AQ107 -> 345.21918 | AR15: =+AS15 -> 358.64559 | AS15: =+AS107 -> 358.64559 | AT15: =+AT107 -> 374.08575 | AU15: =+AV15 -> 387.9819 | AV15: =+AV107 -> 387.9819 | AW15: =+AW107 -> 404.07975 | AX15: =+AY15 -> 418.56783 | AY15: =+AY107 -> 418.56783
B16: RoU assets | I16: 46.032 | L16: 49.127 | O16: 98.939 | P16: 122.29 | Q16: =+R16 -> 93.796 | R16: 93.796 | S16: 104.149 | T16: =+U16 -> 125.43 | U16: 125.43 | V16: =+V129 -> 127.76783 | W16: =+X16 -> 132.03727 | X16: =+X129 -> 132.03727 | Y16: =+Y129 -> 134.31243 | Z16: =+AA16 -> 138.64385 | AA16: =+AA129 -> 138.64385 | AB16: =+AB129 -> 140.80947 | AC16: =+AD16 -> 145.16175 | AD16: =+AD129 -> 145.16175 | AE16: =+AE129 -> 147.15996 | AF16: =+AG16 -> 151.4808 | AG16: =+AG129 -> 151.4808 | AH16: =+AH129 -> 153.24059 | AI16: =+AJ16 -> 157.4642 | AJ16: =+AJ129 -> 157.4642 | AK16: =+AK129 -> 158.89887 | AL16: =+AM16 -> 162.94329 | AM16: =+AM129 -> 162.94329 | AN16: =+AN129 -> 163.94745 | AO16: =+AP16 -> 167.71136 | AP16: =+AP129 -> 167.71136 | AQ16: =+AQ129 -> 168.15735 | AR16: =+AS16 -> 171.51623 | AS16: =+AS129 -> 171.51623 | AT16: =+AT129 -> 171.24993 | AU16: =+AV16 -> 174.05158 | AV16: =+AV129 -> 174.05158 | AW16: =+AW129 -> 172.8874 | AX16: =+AY16 -> 174.94664 | AY16: =+AY129 -> 174.94664
B17: Intangible assets | I17: 6.494 | L17: 15.41 | O17: 15.202 | P17: 11.697 | Q17: =+R17 -> 10.586 | R17: 10.586 | S17: 19.153 | T17: =+U17 -> 18.305 | U17: 18.305 | V17: =+V119 -> 14.62475 | W17: =+X17 -> 11.46845 | X17: =+X119 -> 11.46845 | Y17: =+Y119 -> 7.6041875 | Z17: =+AA17 -> 4.2900725 | AA17: =+AA119 -> 4.2900725 | AB17: =+AB119 -> 0.23259687 | AC17: =+AD17 -> -3.2472239 | AD17: =+AD119 -> -3.2472239 | AE17: =+AE119 -> -7.5075733 | AF17: =+AG17 -> -11.161385 | AG17: =+AG119 -> -11.161385 | AH17: =+AH119 -> -15.634752 | AI17: =+AJ17 -> -19.471254 | AJ17: =+AJ119 -> -19.471254 | AK17: =+AK119 -> -24.16829 | AL17: =+AM17 -> -28.196617 | AM17: =+AM119 -> -28.196617 | AN17: =+AN119 -> -33.128504 | AO17: =+AP17 -> -37.358248 | AP17: =+AP119 -> -37.358248 | AQ17: =+AQ119 -> -42.536729 | AR17: =+AS17 -> -46.97796 | AS17: =+AS119 -> -46.97796 | AT17: =+AT119 -> -52.415366 | AU17: =+AV17 -> -57.078658 | AV17: =+AV119 -> -57.078658 | AW17: =+AW119 -> -62.787934 | AX17: =+AY17 -> -67.684391 | AY17: =+AY119 -> -67.684391
B18: Finance lease receivable | I18: 48.873 | L18: 57.54 | O18: 58.561 | P18: 57.603 | Q18: =+R18 -> 114.404 | R18: 114.404 | S18: 137.32 | T18: =+U18 -> 162.347 | U18: 162.347 | V18: =+U18 -> 162.347 | W18: =+X18 -> 162.347 | X18: =+V18 -> 162.347 | Y18: =+X18 -> 162.347 | Z18: =+AA18 -> 162.347 | AA18: =+Y18 -> 162.347 | AB18: =+AA18 -> 162.347 | AC18: =+AD18 -> 162.347 | AD18: =+AB18 -> 162.347 | AE18: =+AD18 -> 162.347 | AF18: =+AG18 -> 162.347 | AG18: =+AE18 -> 162.347 | AH18: =+AG18 -> 162.347 | AI18: =+AJ18 -> 162.347 | AJ18: =+AH18 -> 162.347 | AK18: =+AJ18 -> 162.347 | AL18: =+AM18 -> 162.347 | AM18: =+AK18 -> 162.347 | AN18: =+AM18 -> 162.347 | AO18: =+AP18 -> 162.347 | AP18: =+AN18 -> 162.347 | AQ18: =+AP18 -> 162.347 | AR18: =+AS18 -> 162.347 | AS18: =+AQ18 -> 162.347 | AT18: =+AS18 -> 162.347 | AU18: =+AV18 -> 162.347 | AV18: =+AT18 -> 162.347 | AW18: =+AV18 -> 162.347 | AX18: =+AY18 -> 162.347 | AY18: =+AW18 -> 162.347
B19: Deferred tax assets | I19: 5.554 | L19: 2.732 | O19: 4.243 | P19: 7.038 | Q19: =+R19 -> 16.276 | R19: 16.276 | S19: 16.633 | T19: =+U19 -> 19.709 | U19: 19.709 | V19: =+U19 -> 19.709 | W19: =+X19 -> 19.709 | X19: =+V19 -> 19.709 | Y19: =+X19 -> 19.709 | Z19: =+AA19 -> 19.709 | AA19: =+Y19 -> 19.709 | AB19: =+AA19 -> 19.709 | AC19: =+AD19 -> 19.709 | AD19: =+AB19 -> 19.709 | AE19: =+AD19 -> 19.709 | AF19: =+AG19 -> 19.709 | AG19: =+AE19 -> 19.709 | AH19: =+AG19 -> 19.709 | AI19: =+AJ19 -> 19.709 | AJ19: =+AH19 -> 19.709 | AK19: =+AJ19 -> 19.709 | AL19: =+AM19 -> 19.709 | AM19: =+AK19 -> 19.709 | AN19: =+AM19 -> 19.709 | AO19: =+AP19 -> 19.709 | AP19: =+AN19 -> 19.709 | AQ19: =+AP19 -> 19.709 | AR19: =+AS19 -> 19.709 | AS19: =+AQ19 -> 19.709 | AT19: =+AS19 -> 19.709 | AU19: =+AV19 -> 19.709 | AV19: =+AT19 -> 19.709 | AW19: =+AV19 -> 19.709 | AX19: =+AY19 -> 19.709 | AY19: =+AW19 -> 19.709
B20: Other non-current assets | I20: 0 | L20: 0 | O20: 0 | P20: 0 | Q20: =+R20 -> 0 | R20: 0 | S20: 0 | T20: =+U20 -> 0 | U20: 0 | V20: =+U20 -> 0 | W20: =+X20 -> 0 | X20: =+V20 -> 0 | Y20: =+X20 -> 0 | Z20: =+AA20 -> 0 | AA20: =+Y20 -> 0 | AB20: =+AA20 -> 0 | AC20: =+AD20 -> 0 | AD20: =+AB20 -> 0 | AE20: =+AD20 -> 0 | AF20: =+AG20 -> 0 | AG20: =+AE20 -> 0 | AH20: =+AG20 -> 0 | AI20: =+AJ20 -> 0 | AJ20: =+AH20 -> 0 | AK20: =+AJ20 -> 0 | AL20: =+AM20 -> 0 | AM20: =+AK20 -> 0 | AN20: =+AM20 -> 0 | AO20: =+AP20 -> 0 | AP20: =+AN20 -> 0 | AQ20: =+AP20 -> 0 | AR20: =+AS20 -> 0 | AS20: =+AQ20 -> 0 | AT20: =+AS20 -> 0 | AU20: =+AV20 -> 0 | AV20: =+AT20 -> 0 | AW20: =+AV20 -> 0 | AX20: =+AY20 -> 0 | AY20: =+AW20 -> 0
B21: Total non-current assets | I21: =SUM(I14:I20) -> 128.858 | L21: =SUM(L14:L20) -> 161.966 | O21: =SUM(O14:O20) -> 247.571 | P21: =SUM(P14:P20) -> 277.582 | Q21: =SUM(Q14:Q20) -> 323.171 | R21: =SUM(R14:R20) -> 323.171 | S21: =SUM(S14:S20) -> 380.521 | T21: =SUM(T14:T20) -> 455.984 | U21: =SUM(U14:U20) -> 455.984 | V21: =SUM(V14:V20) -> 471.63598 | ... AY21: =SUM(AY14:AY20) -> 708.02308
B23: Total assets | I23: =+I21+I12 -> 210.381 | L23: =+L21+L12 -> 248.429 | O23: =+O21+O12 -> 324.507 | P23: =+P21+P12 -> 330.514 | Q23: =+Q21+Q12 -> 661.797 | R23: =+R21+R12 -> 661.797 | S23: =+S21+S12 -> 694.969 | T23: =+T21+T12 -> 783.198 | U23: =+U21+U12 -> 783.198 | V23: =+V21+V12 -> 806.254 | ... AY23: =+AY21+AY12 -> 1994.3803
B25: Trade and other payables | I25: 17.097 | L25: 28.008 | O25: 32.635 | P25: 22.035 | Q25: =+R25 -> 39.387 | R25: 39.387 | S25: 30.198 | T25: =+U25 -> 40.439 | U25: 40.439 | V25: =+V87 -> 48.588371 | W25: =+X25 -> 49.701664 | X25: =+X87 -> 49.701664 | Y25: =+Y87 -> 56.957917 | Z25: =+AA25 -> 58.017867 | AA25: =+AA87 -> 58.017867 | AB25: =+AB87 -> 65.46976 | AC25: =+AD25 -> 66.416698 | AD25: =+AD87 -> 66.416698 | AE25: =+AE87 -> 73.635978 | AF25: =+AG25 -> 74.537383 | AG25: =+AG87 -> 74.537383 | AH25: =+AH87 -> 82.132554 | AI25: =+AJ25 -> 82.987263 | AJ25: =+AJ87 -> 82.987263 | AK25: =+AK87 -> 92.98409 | AL25: =+AM25 -> 93.559039 | AM25: =+AM87 -> 93.559039 | AN25: =+AN87 -> 103.58637 | AO25: =+AP25 -> 104.08682 | AP25: =+AP87 -> 104.08682 | AQ25: =+AQ87 -> 114.8267 | AR25: =+AS25 -> 115.24765 | AS25: =+AS87 -> 115.24765 | AT25: =+AT87 -> 126.74104 | AU25: =+AV25 -> 127.07723 | AV25: =+AV87 -> 127.07723 | AW25: =+AW87 -> 139.36737 | AX25: =+AY25 -> 139.61331 | AY25: =+AY87 -> 139.61331
B26: Contract liabilities | I26: 1.293 | L26: 1.352 | O26: 1.681 | P26: 2.351 | Q26: =+R26 -> 2.054 | R26: 2.054 | S26: 1.397 | T26: =+U26 -> 2.267 | U26: 2.267 | V26: =+U26 -> 2.267 | W26: =+X26 -> 2.267 | X26: =+V26 -> 2.267 | Y26: =+X26 -> 2.267 | Z26: =+AA26 -> 2.267 | AA26: =+Y26 -> 2.267 | AB26: =+AA26 -> 2.267 | AC26: =+AD26 -> 2.267 | AD26: =+AB26 -> 2.267 | AE26: =+AD26 -> 2.267 | AF26: =+AG26 -> 2.267 | AG26: =+AE26 -> 2.267 | AH26: =+AG26 -> 2.267 | AI26: =+AJ26 -> 2.267 | AJ26: =+AH26 -> 2.267 | AK26: =+AJ26 -> 2.267 | AL26: =+AM26 -> 2.267 | AM26: =+AK26 -> 2.267 | AN26: =+AM26 -> 2.267 | AO26: =+AP26 -> 2.267 | AP26: =+AN26 -> 2.267 | AQ26: =+AP26 -> 2.267 | AR26: =+AS26 -> 2.267 | AS26: =+AQ26 -> 2.267 | AT26: =+AS26 -> 2.267 | AU26: =+AV26 -> 2.267 | AV26: =+AT26 -> 2.267 | AW26: =+AV26 -> 2.267 | AX26: =+AY26 -> 2.267 | AY26: =+AW26 -> 2.267
B27: Borrowings | I27: 0.491 | L27: 3.358 | O27: 0 | P27: 0 | Q27: =+R27 -> 0 | R27: 0 | S27: 0 | T27: =+U27 -> 0 | U27: 0 | V27: =+U27 -> 0 | W27: =+X27 -> 0 | X27: =+V27 -> 0 | Y27: =+X27 -> 0 | Z27: =+AA27 -> 0 | AA27: =+Y27 -> 0 | AB27: =+AA27 -> 0 | AC27: =+AD27 -> 0 | AD27: =+AB27 -> 0 | AE27: =+AD27 -> 0 | AF27: =+AG27 -> 0 | AG27: =+AE27 -> 0 | AH27: =+AG27 -> 0 | AI27: =+AJ27 -> 0 | AJ27: =+AH27 -> 0 | AK27: =+AJ27 -> 0 | AL27: =+AM27 -> 0 | AM27: =+AK27 -> 0 | AN27: =+AM27 -> 0 | AO27: =+AP27 -> 0 | AP27: =+AN27 -> 0 | AQ27: =+AP27 -> 0 | AR27: =+AS27 -> 0 | AS27: =+AQ27 -> 0 | AT27: =+AS27 -> 0 | AU27: =+AV27 -> 0 | AV27: =+AT27 -> 0 | AW27: =+AV27 -> 0 | AX27: =+AY27 -> 0 | AY27: =+AW27 -> 0
B28: Lease liabilities | I28: 15.388 | L28: 16.811 | O28: 20.165 | P28: 20.012 | Q28: =+R28 -> 22.201 | R28: 22.201 | S28: 19.687 | T28: =+U28 -> 23.652 | U28: 23.652 | V28: =+U28 -> 23.652 | W28: =+X28 -> 23.652 | X28: =+V28 -> 23.652 | Y28: =+X28 -> 23.652 | Z28: =+AA28 -> 23.652 | AA28: =+Y28 -> 23.652 | AB28: =+AA28 -> 23.652 | AC28: =+AD28 -> 23.652 | AD28: =+AB28 -> 23.652 | AE28: =+AD28 -> 23.652 | AF28: =+AG28 -> 23.652 | AG28: =+AE28 -> 23.652 | AH28: =+AG28 -> 23.652 | AI28: =+AJ28 -> 23.652 | AJ28: =+AH28 -> 23.652 | AK28: =+AJ28 -> 23.652 | AL28: =+AM28 -> 23.652 | AM28: =+AK28 -> 23.652 | AN28: =+AM28 -> 23.652 | AO28: =+AP28 -> 23.652 | AP28: =+AN28 -> 23.652 | AQ28: =+AP28 -> 23.652 | AR28: =+AS28 -> 23.652 | AS28: =+AQ28 -> 23.652 | AT28: =+AS28 -> 23.652 | AU28: =+AV28 -> 23.652 | AV28: =+AT28 -> 23.652 | AW28: =+AV28 -> 23.652 | AX28: =+AY28 -> 23.652 | AY28: =+AW28 -> 23.652
B29: Income tax | I29: 0 | L29: 0 | O29: 3.636 | P29: 9.733 | Q29: =+R29 -> 10.138 | R29: 10.138 | S29: 4.704 | T29: =+U29 -> 8.916 | U29: 8.916 | V29: =+U29 -> 8.916 | W29: =+X29 -> 8.916 | X29: =+V29 -> 8.916 | Y29: =+X29 -> 8.916 | Z29: =+AA29 -> 8.916 | AA29: =+Y29 -> 8.916 | AB29: =+AA29 -> 8.916 | AC29: =+AD29 -> 8.916 | AD29: =+AB29 -> 8.916 | AE29: =+AD29 -> 8.916 | AF29: =+AG29 -> 8.916 | AG29: =+AE29 -> 8.916 | AH29: =+AG29 -> 8.916 | AI29: =+AJ29 -> 8.916 | AJ29: =+AH29 -> 8.916 | AK29: =+AJ29 -> 8.916 | AL29: =+AM29 -> 8.916 | AM29: =+AK29 -> 8.916 | AN29: =+AM29 -> 8.916 | AO29: =+AP29 -> 8.916 | AP29: =+AN29 -> 8.916 | AQ29: =+AP29 -> 8.916 | AR29: =+AS29 -> 8.916 | AS29: =+AQ29 -> 8.916 | AT29: =+AS29 -> 8.916 | AU29: =+AV29 -> 8.916 | AV29: =+AT29 -> 8.916 | AW29: =+AV29 -> 8.916 | AX29: =+AY29 -> 8.916 | AY29: =+AW29 -> 8.916
B30: Provisions | I30: 5.455 | L30: 3.524 | O30: 8.349 | P30: 5.356 | Q30: =+R30 -> 10.507 | R30: 10.507 | S30: 9.725 | T30: =+U30 -> 10.766 | U30: 10.766 | V30: =+U30 -> 10.766 | W30: =+X30 -> 10.766 | X30: =+V30 -> 10.766 | Y30: =+X30 -> 10.766 | Z30: =+AA30 -> 10.766 | AA30: =+Y30 -> 10.766 | AB30: =+AA30 -> 10.766 | AC30: =+AD30 -> 10.766 | AD30: =+AB30 -> 10.766 | AE30: =+AD30 -> 10.766 | AF30: =+AG30 -> 10.766 | AG30: =+AE30 -> 10.766 | AH30: =+AG30 -> 10.766 | AI30: =+AJ30 -> 10.766 | AJ30: =+AH30 -> 10.766 | AK30: =+AJ30 -> 10.766 | AL30: =+AM30 -> 10.766 | AM30: =+AK30 -> 10.766 | AN30: =+AM30 -> 10.766 | AO30: =+AP30 -> 10.766 | AP30: =+AN30 -> 10.766 | AQ30: =+AP30 -> 10.766 | AR30: =+AS30 -> 10.766 | AS30: =+AQ30 -> 10.766 | AT30: =+AS30 -> 10.766 | AU30: =+AV30 -> 10.766 | AV30: =+AT30 -> 10.766 | AW30: =+AV30 -> 10.766 | AX30: =+AY30 -> 10.766 | AY30: =+AW30 -> 10.766
B31: Total current liabilities | I31: =SUM(I25:I30) -> 39.724 | L31: =SUM(L25:L30) -> 53.053 | O31: =SUM(O25:O30) -> 66.466 | P31: =SUM(P25:P30) -> 59.487 | Q31: =SUM(Q25:Q30) -> 84.287 | R31: =SUM(R25:R30) -> 84.287 | S31: =SUM(S25:S30) -> 65.711 | T31: =SUM(T25:T30) -> 86.04 | U31: =SUM(U25:U30) -> 86.04 | V31: =SUM(V25:V30) -> 94.189371 | ... AY31: =SUM(AY25:AY30) -> 185.21431
B33: Contract liabilities | I33: 2.08 | L33: 1.9 | O33: 2.177 | P33: 2.224 | Q33: =+R33 -> 2.429 | R33: 2.429 | S33: 2.519 | T33: =+U33 -> 2.936 | U33: 2.936 | V33: =+U33 -> 2.936 | W33: =+X33 -> 2.936 | X33: =+V33 -> 2.936 | Y33: =+X33 -> 2.936 | Z33: =+AA33 -> 2.936 | AA33: =+Y33 -> 2.936 | AB33: =+AA33 -> 2.936 | AC33: =+AD33 -> 2.936 | AD33: =+AB33 -> 2.936 | AE33: =+AD33 -> 2.936 | AF33: =+AG33 -> 2.936 | AG33: =+AE33 -> 2.936 | AH33: =+AG33 -> 2.936 | AI33: =+AJ33 -> 2.936 | AJ33: =+AH33 -> 2.936 | AK33: =+AJ33 -> 2.936 | AL33: =+AM33 -> 2.936 | AM33: =+AK33 -> 2.936 | AN33: =+AM33 -> 2.936 | AO33: =+AP33 -> 2.936 | AP33: =+AN33 -> 2.936 | AQ33: =+AP33 -> 2.936 | AR33: =+AS33 -> 2.936 | AS33: =+AQ33 -> 2.936 | AT33: =+AS33 -> 2.936 | AU33: =+AV33 -> 2.936 | AV33: =+AT33 -> 2.936 | AW33: =+AV33 -> 2.936 | AX33: =+AY33 -> 2.936 | AY33: =+AW33 -> 2.936
B34: Borrowings | I34: 3.356 | L34: 0 | O34: 3 | P34: 3 | Q34: =+R34 -> 0 | R34: 0 | S34: 0 | T34: =+U34 -> 0 | U34: 0 | V34: =+V146 -> 0 | W34: =+X34 -> 0 | X34: =+X146 -> 0 | Y34: =+Y146 -> 0 | Z34: =+AA34 -> 0 | AA34: =+AA146 -> 0 | AB34: =+AB146 -> 0 | AC34: =+AD34 -> 0 | AD34: =+AD146 -> 0 | AE34: =+AE146 -> 0 | AF34: =+AG34 -> 0 | AG34: =+AG146 -> 0 | AH34: =+AH146 -> 0 | AI34: =+AJ34 -> 0 | AJ34: =+AJ146 -> 0 | AK34: =+AK146 -> 0 | AL34: =+AM34 -> 0 | AM34: =+AM146 -> 0 | AN34: =+AN146 -> 0 | AO34: =+AP34 -> 0 | AP34: =+AP146 -> 0 | AQ34: =+AQ146 -> 0 | AR34: =+AS34 -> 0 | AS34: =+AS146 -> 0 | AT34: =+AT146 -> 0 | AU34: =+AV34 -> 0 | AV34: =+AV146 -> 0 | AW34: =+AW146 -> 0 | AX34: =+AY34 -> 0 | AY34: =+AY146 -> 0
B35: Lease liabilities | I35: 96.709 | L35: 109.763 | O35: 161.552 | P35: 188.055 | Q35: =+R35 -> 217.297 | R35: 217.297 | S35: 254.448 | T35: =+U35 -> 307.659 | U35: 307.659 | V35: =+V138 -> 311.66157 | W35: =+X35 -> 317.24918 | X35: =+X138 -> 317.24918 | Y35: =+Y138 -> 321.31394 | Z35: =+AA35 -> 327.06239 | AA35: =+AA138 -> 327.06239 | AB35: =+AB138 -> 331.15183 | AC35: =+AD35 -> 337.02742 | AD35: =+AD138 -> 337.02742 | AE35: =+AE138 -> 341.09374 | AF35: =+AG35 -> 347.05212 | AG35: =+AG138 -> 347.05212 | AH35: =+AH138 -> 351.03513 | AI35: =+AJ35 -> 357.0191 | AJ35: =+AJ138 -> 357.0191 | AK35: =+AK138 -> 360.84373 | AL35: =+AM35 -> 366.78055 | AM35: =+AM138 -> 366.78055 | AN35: =+AN138 -> 370.35392 | AO35: =+AP35 -> 376.15215 | AP35: =+AP138 -> 376.15215 | AQ35: =+AQ138 -> 379.36004 | AR35: =+AS35 -> 384.90581 | AS35: =+AS138 -> 384.90581 | AT35: =+AT138 -> 387.60855 | AU35: =+AV35 -> 392.76112 | AV35: =+AV138 -> 392.76112 | AW35: =+AW138 -> 394.78865 | AX35: =+AY35 -> 399.37513 | AY35: =+AY138 -> 399.37513
B36: Provisions | I36: 2.189 | L36: 2.614 | O36: 3.347 | P36: 3.763 | Q36: =+R36 -> 3.805 | R36: 3.805 | S36: 4.658 | T36: =+U36 -> 6.439 | U36: 6.439 | V36: =+U36 -> 6.439 | W36: =+X36 -> 6.439 | X36: =+V36 -> 6.439 | Y36: =+X36 -> 6.439 | Z36: =+AA36 -> 6.439 | AA36: =+Y36 -> 6.439 | AB36: =+AA36 -> 6.439 | AC36: =+AD36 -> 6.439 | AD36: =+AB36 -> 6.439 | AE36: =+AD36 -> 6.439 | AF36: =+AG36 -> 6.439 | AG36: =+AE36 -> 6.439 | AH36: =+AG36 -> 6.439 | AI36: =+AJ36 -> 6.439 | AJ36: =+AH36 -> 6.439 | AK36: =+AJ36 -> 6.439 | AL36: =+AM36 -> 6.439 | AM36: =+AK36 -> 6.439 | AN36: =+AM36 -> 6.439 | AO36: =+AP36 -> 6.439 | AP36: =+AN36 -> 6.439 | AQ36: =+AP36 -> 6.439 | AR36: =+AS36 -> 6.439 | AS36: =+AQ36 -> 6.439 | AT36: =+AS36 -> 6.439 | AU36: =+AV36 -> 6.439 | AV36: =+AT36 -> 6.439 | AW36: =+AV36 -> 6.439 | AX36: =+AY36 -> 6.439 | AY36: =+AW36 -> 6.439
B37: Total non-current liabilities | I37: =SUM(I33:I36) -> 104.334 | L37: =SUM(L33:L36) -> 114.277 | O37: =SUM(O33:O36) -> 170.076 | P37: =SUM(P33:P36) -> 197.042 | Q37: =SUM(Q33:Q36) -> 223.531 | R37: =SUM(R33:R36) -> 223.531 | S37: =SUM(S33:S36) -> 261.625 | T37: =SUM(T33:T36) -> 317.034 | U37: =SUM(U33:U36) -> 317.034 | V37: =SUM(V33:V36) -> 321.03657 | ... AY37: =SUM(AY33:AY36) -> 408.75013
B39: Total liabilities | I39: =+I37+I31 -> 144.058 | L39: =+L37+L31 -> 167.33 | O39: =+O37+O31 -> 236.542 | P39: =+P37+P31 -> 256.529 | Q39: =+Q37+Q31 -> 307.818 | R39: =+R37+R31 -> 307.818 | S39: =+S37+S31 -> 327.336 | T39: =+T37+T31 -> 403.074 | U39: =+U37+U31 -> 403.074 | V39: =+V37+V31 -> 415.22594 | ... AY39: =+AY37+AY31 -> 593.96444
B41: Net assets | I41: =+I23-I39 -> 66.323 | L41: =+L23-L39 -> 81.099 | O41: =+O23-O39 -> 87.965 | P41: =+P23-P39 -> 73.985 | Q41: =+Q23-Q39 -> 353.979 | R41: =+R23-R39 -> 353.979 | S41: =+S23-S39 -> 367.633 | T41: =+T23-T39 -> 380.124 | U41: =+U23-U39 -> 380.124 | V41: =+V23-V39 -> 391.02806 | ... AY41: =+AY23-AY39 -> 1400.4159
B43: Issued capital | I43: 90.255 | L43: 99.163 | O43: 104.046 | P43: 88.295 | Q43: =+R43 -> 372.708 | R43: 372.708 | S43: 373.593 | T43: =+U43 -> 374.988 | U43: 374.988 | V43: =+U43 -> 374.988 | W43: =+X43 -> 374.988 | X43: =+V43 -> 374.988 | Y43: =+X43 -> 374.988 | Z43: =+AA43 -> 374.988 | AA43: =+Y43 -> 374.988 | AB43: =+AA43 -> 374.988 | AC43: =+AD43 -> 374.988 | AD43: =+AB43 -> 374.988 | AE43: =+AD43 -> 374.988 | AF43: =+AG43 -> 374.988 | AG43: =+AE43 -> 374.988 | AH43: =+AG43 -> 374.988 | AI43: =+AJ43 -> 374.988 | AJ43: =+AH43 -> 374.988 | AK43: =+AJ43 -> 374.988 | AL43: =+AM43 -> 374.988 | AM43: =+AK43 -> 374.988 | AN43: =+AM43 -> 374.988 | AO43: =+AP43 -> 374.988 | AP43: =+AN43 -> 374.988 | AQ43: =+AP43 -> 374.988 | AR43: =+AS43 -> 374.988 | AS43: =+AQ43 -> 374.988 | AT43: =+AS43 -> 374.988 | AU43: =+AV43 -> 374.988 | AV43: =+AT43 -> 374.988 | AW43: =+AV43 -> 374.988 | AX43: =+AY43 -> 374.988 | AY43: =+AW43 -> 374.988
B44: Reserves | I44: 4.569 | L44: 6.526 | O44: 10.776 | P44: 16.507 | Q44: =+R44 -> 17.418 | R44: 17.418 | S44: =1.293+21.593 -> 22.886 | T44: =+U44 -> 26.807 | U44: =26.737+0.07 -> 26.807 | V44: =+U44 -> 26.807 | W44: =+X44 -> 26.807 | X44: =+V44 -> 26.807 | Y44: =+X44 -> 26.807 | Z44: =+AA44 -> 26.807 | AA44: =+Y44 -> 26.807 | AB44: =+AA44 -> 26.807 | AC44: =+AD44 -> 26.807 | AD44: =+AB44 -> 26.807 | AE44: =+AD44 -> 26.807 | AF44: =+AG44 -> 26.807 | AG44: =+AE44 -> 26.807 | AH44: =+AG44 -> 26.807 | AI44: =+AJ44 -> 26.807 | AJ44: =+AH44 -> 26.807 | AK44: =+AJ44 -> 26.807 | AL44: =+AM44 -> 26.807 | AM44: =+AK44 -> 26.807 | AN44: =+AM44 -> 26.807 | AO44: =+AP44 -> 26.807 | AP44: =+AN44 -> 26.807 | AQ44: =+AP44 -> 26.807 | AR44: =+AS44 -> 26.807 | AS44: =+AQ44 -> 26.807 | AT44: =+AS44 -> 26.807 | AU44: =+AV44 -> 26.807 | AV44: =+AT44 -> 26.807 | AW44: =+AV44 -> 26.807 | AX44: =+AY44 -> 26.807 | AY44: =+AW44 -> 26.807
B45: Accumulated Losses | I45: -28.501 | L45: -24.59 | O45: -26.857 | P45: -30.817 | Q45: =+R45 -> -36.147 | R45: -36.147 | S45: -28.846 | T45: =+U45 -> -21.671 | U45: -21.671 | V45: =+V164 -> -10.766942 | W45: =+X45 -> -0.88408477 | X45: =+X164 -> -0.88408477 | Y45: =+Y164 -> 16.100315 | Z45: =+AA45 -> 31.064228 | AA45: =+AA164 -> 31.064228 | AB45: =+AB164 -> 55.806344 | AC45: =+AD45 -> 80.349823 | AD45: =+AD164 -> 80.349823 | AE45: =+AE164 -> 115.31691 | AF45: =+AG45 -> 150.01851 | AG45: =+AG164 -> 150.01851 | AH45: =+AH164 -> 197.17324 | AI45: =+AJ45 -> 242.71025 | AJ45: =+AJ164 -> 242.71025 | AK45: =+AK164 -> 296.29172 | AL45: =+AM45 -> 349.39191 | AM45: =+AM164 -> 349.39191 | AN45: =+AN164 -> 413.13412 | AO45: =+AP45 -> 476.15837 | AP45: =+AP164 -> 476.15837 | AQ45: =+AQ164 -> 551.12403 | AR45: =+AS45 -> 625.11675 | AS45: =+AS164 -> 625.11675 | AT45: =+AT164 -> 712.42974 | AU45: =+AV45 -> 798.48955 | AV45: =+AV164 -> 798.48955 | AW45: =+AW164 -> 899.33424 | AX45: =+AY45 -> 998.62087 | AY45: =+AY164 -> 998.62087
B46: Total equity | I46: =SUM(I43:I45) -> 66.323 | L46: =SUM(L43:L45) -> 81.099 | O46: =SUM(O43:O45) -> 87.965 | P46: =SUM(P43:P45) -> 73.985 | Q46: =SUM(Q43:Q45) -> 353.979 | R46: =SUM(R43:R45) -> 353.979 | S46: =SUM(S43:S45) -> 367.633 | T46: =SUM(T43:T45) -> 380.124 | U46: =SUM(U43:U45) -> 380.124 | V46: =SUM(V43:V45) -> 391.02806 | ... AY46: =SUM(AY43:AY45) -> 1400.4159
B47: Check | I47: =ROUND(I41-I46,3) -> 0 | L47: =ROUND(L41-L46,3) -> 0 | O47: =ROUND(O41-O46,3) -> 0 | P47: =ROUND(P41-P46,3) -> 0 | Q47: =ROUND(Q41-Q46,5) -> 0 | R47: =ROUND(R41-R46,3) -> 0 | S47: =ROUND(S41-S46,3) -> 0 | T47: =ROUND(T41-T46,5) -> 0 | U47: =ROUND(U41-U46,3) -> 0 | V47: =ROUND(V41-V46,3) -> 0 | W47: =ROUND(W41-W46,3) -> 0 | X47: =ROUND(X41-X46,3) -> 0 | Y47: =ROUND(Y41-Y46,3) -> 0 | Z47: =ROUND(Z41-Z46,3) -> 0 | AA47: =ROUND(AA41-AA46,3) -> 0 | AB47: =ROUND(AB41-AB46,3) -> 0 | ... AY47: =ROUND(AY41-AY46,3) -> 0
B50: Key Metrics
B52: Current ratio | I52: =I12/I31 -> 2.0522354 | L52: =L12/L31 -> 1.6297476 | O52: =O12/O31 -> 1.1575241 | P52: =P12/P31 -> 0.88980786 | Q52: =Q12/Q31 -> 4.0175353 | R52: =R12/R31 -> 4.0175353 | S52: =S12/S31 -> 4.7853175 | T52: =T12/T31 -> 3.8030451 | U52: =U12/U31 -> 3.8030451 | V52: =V12/V31 -> 3.5526092 | ... AY52: =AY12/AY31 -> 6.9452366
B53: Quick ratio | I53: =(I6+I7)/I31 -> 1.6887524 | L53: =(L6+L7)/L31 -> 1.3341187 | O53: =(O6+O7)/O31 -> 0.9095026 | P53: =(P6+P7)/P31 -> 0.58528754 | Q53: =(Q6+Q7)/Q31 -> 0.5031025 | R53: =(R6+R7)/R31 -> 0.5031025 | S53: =(S6+S7)/S31 -> 0.54380545 | T53: =(T6+T7)/T31 -> 0.74823338 | U53: =(U6+U7)/U31 -> 0.74823338 | V53: =(V6+V7)/V31 -> 0.75344905 | ... AY53: =(AY6+AY7)/AY31 -> 5.4685384
B54: Ebitda / Interest | I54: =IFERROR(-'Income & Cash Flow'!I20/'Income & Cash Flow'!I32,0) -> 7.1683926 | L54: =IFERROR(-'Income & Cash Flow'!L20/'Income & Cash Flow'!L32,0) -> 7.654321 | O54: =IFERROR(-'Income & Cash Flow'!O20/'Income & Cash Flow'!O32,0) -> 7.4936061 | P54: =IFERROR(-'Income & Cash Flow'!P20/'Income & Cash Flow'!P32,0) -> 6.0494734 | Q54: =IFERROR(-'Income & Cash Flow'!Q20/'Income & Cash Flow'!Q32,0) -> 5.5387159 | R54: =IFERROR(-'Income & Cash Flow'!R20/'Income & Cash Flow'!R32,0) -> 5.8091286 | S54: =IFERROR(-'Income & Cash Flow'!S20/'Income & Cash Flow'!S32,0) -> -11.725956 | T54: =IFERROR(-'Income & Cash Flow'!T20/'Income & Cash Flow'!T32,0) -> -31.085264 | U54: =IFERROR(-'Income & Cash Flow'!U20/'Income & Cash Flow'!U32,0) -> -17.263786 | V54: =IFERROR(-'Income & Cash Flow'!V20/'Income & Cash Flow'!V32,0) -> 22.940624 | ... AY54: =IFERROR(-'Income & Cash Flow'!AY20/'Income & Cash Flow'!AY32,0) -> -33.080478
B55: Ebit / Interest | I55: =IFERROR(-'Income & Cash Flow'!I27/'Income & Cash Flow'!I32,0) -> 1.6659163 | L55: =IFERROR(-'Income & Cash Flow'!L27/'Income & Cash Flow'!L32,0) -> 2.5396825 | O55: =IFERROR(-'Income & Cash Flow'!O27/'Income & Cash Flow'!O32,0) -> 0.94629156 | P55: =IFERROR(-'Income & Cash Flow'!P27/'Income & Cash Flow'!P32,0) -> 2.155278 | Q55: =IFERROR(-'Income & Cash Flow'!Q27/'Income & Cash Flow'!Q32,0) -> 1.3226784 | R55: =IFERROR(-'Income & Cash Flow'!R27/'Income & Cash Flow'!R32,0) -> 1.7634855 | S55: =IFERROR(-'Income & Cash Flow'!S27/'Income & Cash Flow'!S32,0) -> -4.6409209 | T55: =IFERROR(-'Income & Cash Flow'!T27/'Income & Cash Flow'!T32,0) -> -11.957368 | U55: =IFERROR(-'Income & Cash Flow'!U27/'Income & Cash Flow'!U32,0) -> -6.7338282 | V55: =IFERROR(-'Income & Cash Flow'!V27/'Income & Cash Flow'!V32,0) -> 9.4208177 | ... AY55: =IFERROR(-'Income & Cash Flow'!AY27/'Income & Cash Flow'!AY32,0) -> -23.099597
B56: CFO / current liabilities | I56: ='Income & Cash Flow'!I98/'Balance Sheet'!I31 -> 0.58065653 | L56: ='Income & Cash Flow'!L98/'Balance Sheet'!L31 -> 0.37027124 | O56: ='Income & Cash Flow'!O98/'Balance Sheet'!O31 -> 0.52578762 | P56: ='Income & Cash Flow'!P98/'Balance Sheet'!P31 -> 0.23729554 | Q56: ='Income & Cash Flow'!Q98/'Balance Sheet'!Q31 -> 0.26871285 | R56: ='Income & Cash Flow'!R98/'Balance Sheet'!R31 -> 0.43618826 | S56: ='Income & Cash Flow'!S98/'Balance Sheet'!S31 -> 0.29209721 | T56: ='Income & Cash Flow'!T98/'Balance Sheet'!T31 -> 0.44320084 | U56: ='Income & Cash Flow'!U98/'Balance Sheet'!U31 -> 0.66628312 | V56: ='Income & Cash Flow'!V98/'Balance Sheet'!V31 -> 0.50158283 | ... AY56: ='Income & Cash Flow'!AY98/'Balance Sheet'!AY31 -> 1.8611124
B58: Net cash (ex-leases) | I58: =-I60 -> 58.244 | J58: =-J60 -> 0 | K58: =-K60 -> 0 | L58: =-L60 -> 51.069 | M58: =-M60 -> 0 | N58: =-N60 -> 0 | O58: =-O60 -> 33.504 | P58: =-P60 -> 10.619 | ... AY58: =-AY60 -> 1160.1361
B59: Net debt | I59: =+I35+I27+I34-I6-I10+I28 -> 53.853 | L59: =+L35+L27+L34-L6-L10+L28 -> 75.505 | O59: =+O35+O27+O34-O6-O10+O28 -> 148.213 | P59: =+P35+P27+P34-P6-P10+P28 -> 197.448 | Q59: =+Q35+Q27+Q34-Q6-Q10+Q28 -> -54.982 | R59: =+R35+R27+R34-R6-R10+R28 -> -54.982 | S59: =+S35+S27+S34-S6-S10+S28 -> -0.358 | T59: =+T35+T27+T34-T6-T10+T28 -> 49.568 | U59: =+U35+U27+U34-U6-U10+U28 -> 49.568 | V59: =+V35+V27+V34-V6-V10+V28 -> 52.335626 | ... AY59: =+AY35+AY27+AY34-AY6-AY10+AY28 -> -737.109
B60: Net debt (ex-leases) | I60: =+I34-I6-I10+I27 -> -58.244 | L60: =+L34-L6-L10+L27 -> -51.069 | O60: =+O34-O6-O10+O27 -> -33.504 | P60: =+P34-P6-P10+P27 -> -10.619 | Q60: =+Q34-Q6-Q10+Q27 -> -294.48 | R60: =+R34-R6-R10+R27 -> -294.48 | S60: =+S34-S6-S10+S27 -> -274.493 | T60: =+T34-T6-T10+T27 -> -281.743 | U60: =+U34-U6-U10+U27 -> -281.743 | V60: =+V34-V6-V10+V27 -> -282.97794 | ... AY60: =+AY34-AY6-AY10+AY27 -> -1160.1361
B61: Net debt / equity | I61: =I59/I46 -> 0.81198076 | L61: =L59/L46 -> 0.93102258 | O61: =O59/O46 -> 1.6849088 | P61: =P59/P46 -> 2.6687572 | Q61: =Q59/Q46 -> -0.1553256 | R61: =R59/R46 -> -0.1553256 | S61: =S59/S46 -> -0.00097379724 | T61: =T59/T46 -> 0.13039955 | U61: =U59/U46 -> 0.13039955 | V61: =V59/V46 -> 0.1338411 | ... AY61: =AY59/AY46 -> -0.52635007
B62: Net debt / (net debt + equity) | I62: =I59/(I59+I46) -> 0.44811776 | L62: =L59/(L59+L46) -> 0.48213966 | O62: =O59/(O59+O46) -> 0.62754787 | P62: =P59/(P59+P46) -> 0.72742813 | Q62: =Q59/(Q59+Q46) -> -0.18388813 | R62: =R59/(R59+R46) -> -0.18388813 | S62: =S59/(S59+S46) -> -0.00097474644 | T62: =T59/(T59+T46) -> 0.11535705 | U62: =U59/(U59+U46) -> 0.11535705 | V62: =V59/(V59+V46) -> 0.1180422 | ... AY62: =AY59/(AY59+AY46) -> -1.1112639
B63: Net debt / Ebitda | I63: =I59/'Income & Cash Flow'!I20 -> 3.3825137 | L63: =L59/'Income & Cash Flow'!L20 -> 3.4794931 | O63: =O59/'Income & Cash Flow'!O20 -> 5.0584642 | P63: =P59/'Income & Cash Flow'!P20 -> 7.9938462 | Q63: =Q59/'Income & Cash Flow'!Q20 -> -2.7354229 | R63: =R59/'Income & Cash Flow'!R20 -> -1.2272768 | S63: =S59/'Income & Cash Flow'!S20 -> -0.011337007 | T63: =T59/'Income & Cash Flow'!T20 -> 1.4778331 | U63: =U59/'Income & Cash Flow'!U20 -> 0.76119105 | V63: =V59/'Income & Cash Flow'!V20 -> 1.2332649 | ... AY63: =AY59/'Income & Cash Flow'!AY20 -> -1.878247
B64: Net debt / Ebitda (ex-leases) | I64: =I60/'Income & Cash Flow'!I20 -> -3.6583129 | L64: =L60/'Income & Cash Flow'!L20 -> -2.3534101 | O64: =O60/'Income & Cash Flow'!O20 -> -1.1434812 | P64: =P60/'Income & Cash Flow'!P20 -> -0.42991903 | Q64: =Q60/'Income & Cash Flow'!Q20 -> -14.650746 | R64: =R60/'Income & Cash Flow'!R20 -> -6.5732143 | S64: =S60/'Income & Cash Flow'!S20 -> -8.6925391 | T64: =T60/'Income & Cash Flow'!T20 -> -8.3999583 | U64: =U60/'Income & Cash Flow'!U20 -> -4.3265867 | V64: =V60/'Income & Cash Flow'!V20 -> -6.6682446 | ... AY64: =AY60/'Income & Cash Flow'!AY20 -> -2.9561736
B65: Debt / Equity | I65: =I39/I46 -> 2.172067 | L65: =L39/L46 -> 2.0632807 | O65: =O39/O46 -> 2.6890468 | P65: =P39/P46 -> 3.4673109 | Q65: =Q39/Q46 -> 0.86959396 | R65: =R39/R46 -> 0.86959396 | S65: =S39/S46 -> 0.89038797 | T65: =T39/T46 -> 1.060375 | U65: =U39/U46 -> 1.060375 | V65: =V39/V46 -> 1.0618827 | ... AY65: =AY39/AY46 -> 0.42413433
B67: Tangible Net Worth | I67: =I23-I39-I17 -> 59.829 | L67: =L23-L39-L17 -> 65.689 | O67: =O23-O39-O17 -> 72.763 | P67: =P23-P39-P17 -> 62.288 | Q67: =Q23-Q39-Q17 -> 343.393 | R67: =R23-R39-R17 -> 343.393 | S67: =S23-S39-S17 -> 348.48 | T67: =T23-T39-T17 -> 361.819 | U67: =U23-U39-U17 -> 361.819 | V67: =V23-V39-V17 -> 376.40331 | ... AY67: =AY23-AY39-AY17 -> 1468.1003
B68: Working capital | I68: =I91 -> -10.452 | L68: =L91 -> -9.669 | O68: =O91 -> -6.535 | P68: =P91 -> 2.334 | Q68: =Q91 -> -10.542 | R68: =R91 -> -10.542 | S68: =S91 -> -7.097 | T68: =T91 -> -11.975 | U68: =U91 -> -11.975 | V68: =V91 -> -13.955291 | ... AY68: =AY91 -> -30.399207
B69: Capital employed | I69: =I23-I31 -> 170.657 | L69: =L23-L31 -> 195.376 | O69: =O23-O31 -> 258.041 | P69: =P23-P31 -> 271.027 | Q69: =Q23-Q31 -> 577.51 | R69: =R23-R31 -> 577.51 | S69: =S23-S31 -> 629.258 | T69: =T23-T31 -> 697.158 | U69: =U23-U31 -> 697.158 | V69: =V23-V31 -> 712.06463 | ... AY69: =AY23-AY31 -> 1809.166
B70: Invested capital | I70: =I68+I17+I15 -> 17.558 | L70: =L68+L17+L15 -> 42.304 | O70: =O68+O17+O15 -> 78.153 | P70: =P68+P17+P15 -> 91.984 | Q70: =Q68+Q17+Q15 -> 87.674 | R70: =R68+R17+R15 -> 87.674 | S70: =S68+S17+S15 -> 115.084 | T70: =T68+T17+T15 -> 136.386 | U70: =U68+U17+U15 -> 136.386 | V70: =V68+V17+V15 -> 147.71986 | ... AY70: =AY68+AY17+AY15 -> 320.48423
B71: Book value (Net assets) | I71: =+I41 -> 66.323 | L71: =+L41 -> 81.099 | O71: =+O41 -> 87.965 | P71: =+P41 -> 73.985 | Q71: =+Q41 -> 353.979 | R71: =+R41 -> 353.979 | S71: =+S41 -> 367.633 | T71: =+T41 -> 380.124 | U71: =+U41 -> 380.124 | V71: =+V41 -> 391.02806 | ... AY71: =+AY41 -> 1400.4159
B73: ROE | I73: ='Income & Cash Flow'!I42/AVERAGE(I46,F46) -> 0 | L73: ='Income & Cash Flow'!L42/AVERAGE(L46,I46) -> 0.043412788 | O73: ='Income & Cash Flow'!O42/AVERAGE(O46,L46) -> 0.035489519 | P73: ='Income & Cash Flow'!P42/AVERAGE(P46,O46) -> 0.046928064 | Q73: ='Income & Cash Flow'!Q42/AVERAGE(Q46,P46) -> 0.0088792515 | R73: ='Income & Cash Flow'!R42/AVERAGE(R46,O46) -> 0.025795123 | S73: ='Income & Cash Flow'!S42/AVERAGE(S46,R46) -> 0.020235251 | T73: ='Income & Cash Flow'!T42/AVERAGE(T46,S46) -> 0.019190726 | U73: ='Income & Cash Flow'!U42/AVERAGE(U46,R46) -> 0.039438607 | V73: ='Income & Cash Flow'!V42/AVERAGE(V46,U46) -> 0.028279916 | W73: ='Income & Cash Flow'!W42/AVERAGE(W46,V46) -> 0.024958634 | X73: ='Income & Cash Flow'!X42/AVERAGE(X46,U46) -> 0.053229157 | Y73: ='Income & Cash Flow'!Y42/AVERAGE(Y46,X46) -> 0.04148576 | Z73: ='Income & Cash Flow'!Z42/AVERAGE(Z46,Y46) -> 0.035177981 | AA73: ='Income & Cash Flow'!AA42/AVERAGE(AA46,X46) -> 0.076635781 | AB73: ='Income & Cash Flow'!AB42/AVERAGE(AB46,AA46) -> 0.055571501 | AC73: ='Income & Cash Flow'!AC42/AVERAGE(AC46,AB46) -> 0.052234274 | AD73: ='Income & Cash Flow'!AD42/AVERAGE(AD46,AA46) -> 0.1077276 | AE73: ='Income & Cash Flow'!AE42/AVERAGE(AE46,AD46) -> 0.069986201 | AF73: ='Income & Cash Flow'!AF42/AVERAGE(AF46,AE46) -> 0.064928 | AG73: ='Income & Cash Flow'!AG42/AVERAGE(AG46,AD46) -> 0.13476111 | AH73: ='Income & Cash Flow'!AH42/AVERAGE(AH46,AG46) -> 0.081952512 | AI73: ='Income & Cash Flow'!AI42/AVERAGE(AI46,AH46) -> 0.073241627 | AJ73: ='Income & Cash Flow'!AJ42/AVERAGE(AJ46,AG46) -> 0.15496161 | AK73: ='Income & Cash Flow'!AK42/AVERAGE(AK46,AJ46) -> 0.079817957 | AL73: ='Income & Cash Flow'!AL42/AVERAGE(AL46,AK46) -> 0.07327835 | AM73: ='Income & Cash Flow'!AM42/AVERAGE(AM46,AJ46) -> 0.15287277 | AN73: ='Income & Cash Flow'!AN42/AVERAGE(AN46,AM46) -> 0.08140164 | AO73: ='Income & Cash Flow'!AO42/AVERAGE(AO46,AN46) -> 0.074457918 | AP73: ='Income & Cash Flow'!AP42/AVERAGE(AP46,AM46) -> 0.15562375 | AQ73: ='Income & Cash Flow'!AQ42/AVERAGE(AQ46,AP46) -> 0.081890646 | AR73: ='Income & Cash Flow'!AR42/AVERAGE(AR46,AQ46) -> 0.074746511 | AS73: ='Income & Cash Flow'!AS42/AVERAGE(AS46,AP46) -> 0.15639783 | AT73: ='Income & Cash Flow'!AT42/AVERAGE(AT46,AS46) -> 0.081557606 | AU73: ='Income & Cash Flow'!AU42/AVERAGE(AU46,AT46) -> 0.074365489 | AV73: ='Income & Cash Flow'!AV42/AVERAGE(AV46,AS46) -> 0.15568703 | AW73: ='Income & Cash Flow'!AW42/AVERAGE(AW46,AV46) -> 0.080630157 | AX73: ='Income & Cash Flow'!AX42/AVERAGE(AX46,AW46) -> 0.07350359 | AY73: ='Income & Cash Flow'!AY42/AVERAGE(AY46,AV46) -> 0.15390571
B74: ROCE | I74: ='Income & Cash Flow'!I27/AVERAGE(I69,F69) -> 0.021680916 | L74: ='Income & Cash Flow'!L27/AVERAGE(L69,I69) -> 0.039340715 | O74: ='Income & Cash Flow'!O27/AVERAGE(O69,L69) -> 0.016320517 | P74: ='Income & Cash Flow'!P27/AVERAGE(P69,O69) -> 0.033266045 | Q74: ='Income & Cash Flow'!Q27/AVERAGE(Q69,P69) -> 0.01131359 | R74: ='Income & Cash Flow'!R27/AVERAGE(R69,O69) -> 0.032553369 | S74: ='Income & Cash Flow'!S27/AVERAGE(S69,R69) -> 0.020713178 | T74: ='Income & Cash Flow'!T27/AVERAGE(T69,S69) -> 0.019453927 | U74: ='Income & Cash Flow'!U27/AVERAGE(U69,R69) -> 0.039853515 | V74: ='Income & Cash Flow'!V27/AVERAGE(V69,U69) -> 0.024732888 | W74: ='Income & Cash Flow'!W27/AVERAGE(W69,V69) -> 0.022417125 | X74: ='Income & Cash Flow'!X27/AVERAGE(X69,U69) -> 0.047115994 | Y74: ='Income & Cash Flow'!Y27/AVERAGE(Y69,X69) -> 0.035773321 | Z74: ='Income & Cash Flow'!Z27/AVERAGE(Z69,Y69) -> 0.034394005 | AA74: ='Income & Cash Flow'!AA27/AVERAGE(AA69,X69) -> 0.070155979 | AB74: ='Income & Cash Flow'!AB27/AVERAGE(AB69,AA69) -> 0.05115225 | AC74: ='Income & Cash Flow'!AC27/AVERAGE(AC69,AB69) -> 0.048804386 | AD74: ='Income & Cash Flow'!AD27/AVERAGE(AD69,AA69) -> 0.09986345 | AE74: ='Income & Cash Flow'!AE27/AVERAGE(AE69,AD69) -> 0.064166887 | AF74: ='Income & Cash Flow'!AF27/AVERAGE(AF69,AE69) -> 0.060524998 | AG74: ='Income & Cash Flow'!AG27/AVERAGE(AG69,AD69) -> 0.12454994 | AH74: ='Income & Cash Flow'!AH27/AVERAGE(AH69,AG69) -> 0.076215347 | AI74: ='Income & Cash Flow'!AI27/AVERAGE(AI69,AH69) -> 0.069374035 | AJ74: ='Income & Cash Flow'!AJ27/AVERAGE(AJ69,AG69) -> 0.14539187 | AK74: ='Income & Cash Flow'!AK27/AVERAGE(AK69,AJ69) -> 0.076249906 | AL74: ='Income & Cash Flow'!AL27/AVERAGE(AL69,AK69) -> 0.070968809 | AM74: ='Income & Cash Flow'!AM27/AVERAGE(AM69,AJ69) -> 0.14701877 | AN74: ='Income & Cash Flow'!AN27/AVERAGE(AN69,AM69) -> 0.079592345 | AO74: ='Income & Cash Flow'!AO27/AVERAGE(AO69,AN69) -> 0.073661224 | AP74: ='Income & Cash Flow'!AP27/AVERAGE(AP69,AM69) -> 0.15303641 | AQ74: ='Income & Cash Flow'!AQ27/AVERAGE(AQ69,AP69) -> 0.081914255 | AR74: ='Income & Cash Flow'!AR27/AVERAGE(AR69,AQ69) -> 0.075470101 | AS74: ='Income & Cash Flow'!AS27/AVERAGE(AS69,AP69) -> 0.15715507 | AT74: ='Income & Cash Flow'!AT27/AVERAGE(AT69,AS69) -> 0.083332478 | AU74: ='Income & Cash Flow'!AU27/AVERAGE(AU69,AT69) -> 0.076509357 | AV74: ='Income & Cash Flow'!AV27/AVERAGE(AV69,AS69) -> 0.15960572 | AW74: ='Income & Cash Flow'!AW27/AVERAGE(AW69,AV69) -> 0.083984801 | AX74: ='Income & Cash Flow'!AX27/AVERAGE(AX69,AW69) -> 0.076904991 | AY74: ='Income & Cash Flow'!AY27/AVERAGE(AY69,AV69) -> 0.16065167
B75: ROIC | I75: ='Income & Cash Flow'!I42/AVERAGE(I70,F70) -> 0 | L75: ='Income & Cash Flow'!L42/AVERAGE(L70,I70) -> 0.10691257 | O75: ='Income & Cash Flow'!O42/AVERAGE(O70,L70) -> 0.049810306 | P75: ='Income & Cash Flow'!P42/AVERAGE(P70,O70) -> 0.044669884 | Q75: ='Income & Cash Flow'!Q42/AVERAGE(Q70,P70) -> 0.021151299 | R75: ='Income & Cash Flow'!R42/AVERAGE(R70,O70) -> 0.068746344 | S75: ='Income & Cash Flow'!S42/AVERAGE(S70,R70) -> 0.072016887 | T75: ='Income & Cash Flow'!T42/AVERAGE(T70,S70) -> 0.057064461 | U75: ='Income & Cash Flow'!U42/AVERAGE(U70,R70) -> 0.12921539 | V75: ='Income & Cash Flow'!V42/AVERAGE(V70,U70) -> 0.076760527 | W75: ='Income & Cash Flow'!W42/AVERAGE(W70,V70) -> 0.064381136 | X75: ='Income & Cash Flow'!X42/AVERAGE(X70,U70) -> 0.14060551 | Y75: ='Income & Cash Flow'!Y42/AVERAGE(Y70,X70) -> 0.10314152 | Z75: ='Income & Cash Flow'!Z42/AVERAGE(Z70,Y70) -> 0.085402895 | AA75: ='Income & Cash Flow'!AA42/AVERAGE(AA70,X70) -> 0.18811293 | AB75: ='Income & Cash Flow'!AB42/AVERAGE(AB70,AA70) -> 0.13336495 | AC75: ='Income & Cash Flow'!AC42/AVERAGE(AC70,AB70) -> 0.12559362 | AD75: ='Income & Cash Flow'!AD42/AVERAGE(AD70,AA70) -> 0.25901828 | AE75: ='Income & Cash Flow'!AE42/AVERAGE(AE70,AD70) -> 0.17050023 | AF75: ='Income & Cash Flow'!AF42/AVERAGE(AF70,AE70) -> 0.16181393 | AG75: ='Income & Cash Flow'!AG42/AVERAGE(AG70,AD70) -> 0.3324764 | AH75: ='Income & Cash Flow'!AH42/AVERAGE(AH70,AG70) -> 0.21078049 | AI75: ='Income & Cash Flow'!AI42/AVERAGE(AI70,AH70) -> 0.19566612 | AJ75: ='Income & Cash Flow'!AJ42/AVERAGE(AJ70,AG70) -> 0.40667398 | AK75: ='Income & Cash Flow'!AK42/AVERAGE(AK70,AJ70) -> 0.22263318 | AL75: ='Income & Cash Flow'!AL42/AVERAGE(AL70,AK70) -> 0.21357522 | AM75: ='Income & Cash Flow'!AM42/AVERAGE(AM70,AJ70) -> 0.435625 | AN75: ='Income & Cash Flow'!AN42/AVERAGE(AN70,AM70) -> 0.2481673 | AO75: ='Income & Cash Flow'!AO42/AVERAGE(AO70,AN70) -> 0.23777119 | AP75: ='Income & Cash Flow'!AP42/AVERAGE(AP70,AM70) -> 0.48558757 | AQ75: ='Income & Cash Flow'!AQ42/AVERAGE(AQ70,AP70) -> 0.27429782 | AR75: ='Income & Cash Flow'!AR42/AVERAGE(AR70,AQ70) -> 0.26276669 | AS75: ='Income & Cash Flow'!AS42/AVERAGE(AS70,AP70) -> 0.53667204 | AT75: ='Income & Cash Flow'!AT42/AVERAGE(AT70,AS70) -> 0.30110522 | AU75: ='Income & Cash Flow'!AU42/AVERAGE(AU70,AT70) -> 0.28833381 | AV75: ='Income & Cash Flow'!AV42/AVERAGE(AV70,AS70) -> 0.58900626 | AW75: ='Income & Cash Flow'!AW42/AVERAGE(AW70,AV70) -> 0.32835204 | AX75: ='Income & Cash Flow'!AX42/AVERAGE(AX70,AW70) -> 0.31425497 | AY75: ='Income & Cash Flow'!AY42/AVERAGE(AY70,AV70) -> 0.64213601
B77: Balance Sheet Forecasts
B78: Working Capital
B79: Receivables | I79: =+I7 -> 4.993 | L79: =+L7 -> 16.352 | O79: =+O7 -> 23.947 | P79: =+P7 -> 21.198 | Q79: =+Q7 -> 26.02 | R79: =+R7 -> 26.02 | S79: =+S7 -> 18.852 | T79: =+T7 -> 24.703 | U79: =+U7 -> 24.703 | V79: =+'Income & Cash Flow'!V8*'Balance Sheet'!V81 -> 30.056948 | W79: =+X79 -> 30.530703 | X79: =+'Income & Cash Flow'!X8*'Balance Sheet'!X81 -> 30.530703 | Y79: =+'Income & Cash Flow'!Y8*'Balance Sheet'!Y81 -> 35.880664 | Z79: =+AA79 -> 36.366779 | AA79: =+'Income & Cash Flow'!AA8*'Balance Sheet'!AA81 -> 36.366779 | AB79: =+'Income & Cash Flow'!AB8*'Balance Sheet'!AB81 -> 42.29088 | AC79: =+AD79 -> 42.699203 | AD79: =+'Income & Cash Flow'!AD8*'Balance Sheet'!AD81 -> 42.699203 | AE79: =+'Income & Cash Flow'!AE8*'Balance Sheet'!AE81 -> 48.585046 | AF79: =+AG79 -> 48.940995 | AG79: =+'Income & Cash Flow'!AG8*'Balance Sheet'!AG81 -> 48.940995 | AH79: =+'Income & Cash Flow'!AH8*'Balance Sheet'!AH81 -> 55.32315 | AI79: =+AJ79 -> 55.520988 | AJ79: =+'Income & Cash Flow'!AJ8*'Balance Sheet'!AJ81 -> 55.520988 | AK79: =+'Income & Cash Flow'!AK8*'Balance Sheet'!AK81 -> 62.307826 | AL79: =+AM79 -> 62.432011 | AM79: =+'Income & Cash Flow'!AM8*'Balance Sheet'!AM81 -> 62.432011 | AN79: =+'Income & Cash Flow'!AN8*'Balance Sheet'!AN81 -> 69.742683 | AO79: =+AP79 -> 69.787763 | AP79: =+'Income & Cash Flow'!AP8*'Balance Sheet'!AP81 -> 69.787763 | AQ79: =+'Income & Cash Flow'!AQ8*'Balance Sheet'!AQ81 -> 77.653388 | AR79: =+AS79 -> 77.61358 | AS79: =+'Income & Cash Flow'!AS8*'Balance Sheet'!AS81 -> 77.61358 | AT79: =+'Income & Cash Flow'!AT8*'Balance Sheet'!AT81 -> 86.066934 | AU79: =+AV79 -> 85.936118 | AV79: =+'Income & Cash Flow'!AV8*'Balance Sheet'!AV81 -> 85.936118 | AW79: =+'Income & Cash Flow'!AW8*'Balance Sheet'!AW81 -> 95.011735 | AX79: =+AY79 -> 94.783448 | AY79: =+'Income & Cash Flow'!AY8*'Balance Sheet'!AY81 -> 94.783448
B80: DSO | I80: =I79/'Income & Cash Flow'!I$8*365 -> 15.246631 | L80: =L79/'Income & Cash Flow'!L$8*365 -> 34.742479 | O80: =O79/'Income & Cash Flow'!O$8*365 -> 33.74197 | P80: =P79/'Income & Cash Flow'!P$8*182.5 -> 23.093984 | Q80: =Q79/'Income & Cash Flow'!Q$8*182.5 -> 27.182207 | R80: =R79/'Income & Cash Flow'!R$8*365 -> 27.752517 | S80: =S79/'Income & Cash Flow'!S$8*182.5 -> 16.196715 | T80: =T79/'Income & Cash Flow'!T$8*182.5 -> 20.165669 | U80: =U79/'Income & Cash Flow'!U$8*365 -> 20.681118 | V80: =V79/'Income & Cash Flow'!V$8*182.5 -> 20.681118 | W80: =W79/'Income & Cash Flow'!W$8*182.5 -> 20.365105 | X80: =X79/'Income & Cash Flow'!X$8*365 -> 20.681118 | Y80: =Y79/'Income & Cash Flow'!Y$8*182.5 -> 20.681118 | Z80: =Z79/'Income & Cash Flow'!Z$8*182.5 -> 20.40832 | AA80: =AA79/'Income & Cash Flow'!AA$8*365 -> 20.681118 | AB80: =AB79/'Income & Cash Flow'!AB$8*182.5 -> 20.681118 | AC80: =AC79/'Income & Cash Flow'!AC$8*182.5 -> 20.485222 | AD80: =AD79/'Income & Cash Flow'!AD$8*365 -> 20.681118 | AE80: =AE79/'Income & Cash Flow'!AE$8*182.5 -> 20.681118 | AF80: =AF79/'Income & Cash Flow'!AF$8*182.5 -> 20.531789 | AG80: =AG79/'Income & Cash Flow'!AG$8*365 -> 20.681118 | AH80: =AH79/'Income & Cash Flow'!AH$8*182.5 -> 20.681118 | AI80: =AI79/'Income & Cash Flow'!AI$8*182.5 -> 20.607686 | AJ80: =AJ79/'Income & Cash Flow'!AJ$8*365 -> 20.681118 | AK80: =AK79/'Income & Cash Flow'!AK$8*182.5 -> 20.681118 | AL80: =AL79/'Income & Cash Flow'!AL$8*182.5 -> 20.640062 | AM80: =AM79/'Income & Cash Flow'!AM$8*365 -> 20.681118 | AN80: =AN79/'Income & Cash Flow'!AN$8*182.5 -> 20.681118 | AO80: =AO79/'Income & Cash Flow'!AO$8*182.5 -> 20.667767 | AP80: =AP79/'Income & Cash Flow'!AP$8*365 -> 20.681118 | AQ80: =AQ79/'Income & Cash Flow'!AQ$8*182.5 -> 20.681118 | AR80: =AR79/'Income & Cash Flow'!AR$8*182.5 -> 20.69173 | AS80: =AS79/'Income & Cash Flow'!AS$8*365 -> 20.681118 | AT80: =AT79/'Income & Cash Flow'!AT$8*182.5 -> 20.681118 | AU80: =AU79/'Income & Cash Flow'!AU$8*182.5 -> 20.712647 | AV80: =AV79/'Income & Cash Flow'!AV$8*365 -> 20.681118 | AW80: =AW79/'Income & Cash Flow'!AW$8*182.5 -> 20.681118 | AX80: =AX79/'Income & Cash Flow'!AX$8*182.5 -> 20.731048 | AY80: =AY79/'Income & Cash Flow'!AY$8*365 -> 20.681118
B81: % Sales | I81: =I79/'Income & Cash Flow'!I$8 -> 0.041771591 | L81: =L79/'Income & Cash Flow'!L$8 -> 0.095184875 | O81: =O79/'Income & Cash Flow'!O$8 -> 0.092443755 | P81: =P79/'Income & Cash Flow'!P$8 -> 0.12654238 | Q81: =Q79/'Income & Cash Flow'!Q$8 -> 0.1489436 | R81: =R79/'Income & Cash Flow'!R$8 -> 0.076034294 | S81: =S79/'Income & Cash Flow'!S$8 -> 0.088749123 | T81: =T79/'Income & Cash Flow'!T$8 -> 0.11049682 | U81: =U79/'Income & Cash Flow'!U$8 -> 0.056660596 | V81: =+X81*2 -> 0.11332119 | W81: =W79/'Income & Cash Flow'!W$8 -> 0.11158962 | X81: =+U81 -> 0.056660596 | Y81: =+AA81*2 -> 0.11332119 | Z81: =Z79/'Income & Cash Flow'!Z$8 -> 0.11182641 | AA81: =+X81 -> 0.056660596 | AB81: =+AD81*2 -> 0.11332119 | AC81: =AC79/'Income & Cash Flow'!AC$8 -> 0.11224779 | AD81: =+AA81 -> 0.056660596 | AE81: =+AG81*2 -> 0.11332119 | AF81: =AF79/'Income & Cash Flow'!AF$8 -> 0.11250296 | AG81: =+AD81 -> 0.056660596 | AH81: =+AJ81*2 -> 0.11332119 | AI81: =AI79/'Income & Cash Flow'!AI$8 -> 0.11291883 | AJ81: =+AG81 -> 0.056660596 | AK81: =+AM81*2 -> 0.11332119 | AL81: =AL79/'Income & Cash Flow'!AL$8 -> 0.11309623 | AM81: =+AJ81 -> 0.056660596 | AN81: =+AP81*2 -> 0.11332119 | AO81: =AO79/'Income & Cash Flow'!AO$8 -> 0.11324804 | AP81: =+AM81 -> 0.056660596 | AQ81: =+AS81*2 -> 0.11332119 | AR81: =AR79/'Income & Cash Flow'!AR$8 -> 0.11337935 | AS81: =+AP81 -> 0.056660596 | AT81: =+AV81*2 -> 0.11332119 | AU81: =AU79/'Income & Cash Flow'!AU$8 -> 0.11349396 | AV81: =+AS81 -> 0.056660596 | AW81: =+AY81*2 -> 0.11332119 | AX81: =AX79/'Income & Cash Flow'!AX$8 -> 0.11359479 | AY81: =+AV81 -> 0.056660596
B83: Inventories | I83: =+I8 -> 1.652 | L83: =+L8 -> 1.987 | O83: =+O8 -> 2.153 | P83: =+P8 -> 3.171 | Q83: =+Q8 -> 2.825 | R83: =+R8 -> 2.825 | S83: =+S8 -> 4.249 | T83: =+T8 -> 3.761 | U83: =+U8 -> 3.761 | V83: =+'Income & Cash Flow'!V8*'Balance Sheet'!V85 -> 4.5761317 | W83: =+X83 -> 4.6482604 | X83: =+'Income & Cash Flow'!X8*'Balance Sheet'!X85 -> 4.6482604 | Y83: =+'Income & Cash Flow'!Y8*'Balance Sheet'!Y85 -> 5.462785 | Z83: =+AA83 -> 5.5367953 | AA83: =+'Income & Cash Flow'!AA8*'Balance Sheet'!AA85 -> 5.5367953 | AB83: =+'Income & Cash Flow'!AB8*'Balance Sheet'!AB85 -> 6.4387322 | AC83: =+AD83 -> 6.5008987 | AD83: =+'Income & Cash Flow'!AD8*'Balance Sheet'!AD85 -> 6.5008987 | AE83: =+'Income & Cash Flow'!AE8*'Balance Sheet'!AE85 -> 7.3970108 | AF83: =+AG83 -> 7.4512036 | AG83: =+'Income & Cash Flow'!AG8*'Balance Sheet'!AG85 -> 7.4512036 | AH83: =+'Income & Cash Flow'!AH8*'Balance Sheet'!AH85 -> 8.4228785 | AI83: =+AJ83 -> 8.452999 | AJ83: =+'Income & Cash Flow'!AJ8*'Balance Sheet'!AJ85 -> 8.452999 | AK83: =+'Income & Cash Flow'!AK8*'Balance Sheet'!AK85 -> 9.4862865 | AL83: =+AM83 -> 9.5051934 | AM83: =+'Income & Cash Flow'!AM8*'Balance Sheet'!AM85 -> 9.5051934 | AN83: =+'Income & Cash Flow'!AN8*'Balance Sheet'!AN85 -> 10.618234 | AO83: =+AP83 -> 10.625097 | AP83: =+'Income & Cash Flow'!AP8*'Balance Sheet'!AP85 -> 10.625097 | AQ83: =+'Income & Cash Flow'!AQ8*'Balance Sheet'!AQ85 -> 11.822629 | AR83: =+AS83 -> 11.816568 | AS83: =+'Income & Cash Flow'!AS8*'Balance Sheet'!AS85 -> 11.816568 | AT83: =+'Income & Cash Flow'!AT8*'Balance Sheet'!AT85 -> 13.10358 | AU83: =+AV83 -> 13.083664 | AV83: =+'Income & Cash Flow'!AV8*'Balance Sheet'!AV85 -> 13.083664 | AW83: =+'Income & Cash Flow'!AW8*'Balance Sheet'!AW85 -> 14.465415 | AX83: =+AY83 -> 14.430658 | AY83: =+'Income & Cash Flow'!AY8*'Balance Sheet'!AY85 -> 14.430658
B84: DIO | I84: =I83/'Income & Cash Flow'!I$8*365 -> 5.0445491 | L84: =L83/'Income & Cash Flow'!L$8*365 -> 4.2217042 | O84: =O83/'Income & Cash Flow'!O$8*365 -> 3.0336352 | P84: =P83/'Income & Cash Flow'!P$8*182.5 -> 3.4546195 | Q84: =Q83/'Income & Cash Flow'!Q$8*182.5 -> 2.9511812 | R84: =R83/'Income & Cash Flow'!R$8*365 -> 3.0131 | S84: =S83/'Income & Cash Flow'!S$8*182.5 -> 3.6505327 | T84: =T83/'Income & Cash Flow'!T$8*182.5 -> 3.0701972 | U84: =U83/'Income & Cash Flow'!U$8*365 -> 3.1486736 | V84: =V83/'Income & Cash Flow'!V$8*182.5 -> 3.1486736 | W84: =W83/'Income & Cash Flow'!W$8*182.5 -> 3.1005611 | X84: =X83/'Income & Cash Flow'!X$8*365 -> 3.1486736 | Y84: =Y83/'Income & Cash Flow'!Y$8*182.5 -> 3.1486736 | Z84: =Z83/'Income & Cash Flow'!Z$8*182.5 -> 3.1071405 | AA84: =AA83/'Income & Cash Flow'!AA$8*365 -> 3.1486736 | AB84: =AB83/'Income & Cash Flow'!AB$8*182.5 -> 3.1486736 | AC84: =AC83/'Income & Cash Flow'!AC$8*182.5 -> 3.1188488 | AD84: =AD83/'Income & Cash Flow'!AD$8*365 -> 3.1486736 | AE84: =AE83/'Income & Cash Flow'!AE$8*182.5 -> 3.1486736 | AF84: =AF83/'Income & Cash Flow'!AF$8*182.5 -> 3.1259385 | AG84: =AG83/'Income & Cash Flow'!AG$8*365 -> 3.1486736 | AH84: =AH83/'Income & Cash Flow'!AH$8*182.5 -> 3.1486736 | AI84: =AI83/'Income & Cash Flow'!AI$8*182.5 -> 3.1374938 | AJ84: =AJ83/'Income & Cash Flow'!AJ$8*365 -> 3.1486736 | AK84: =AK83/'Income & Cash Flow'!AK$8*182.5 -> 3.1486736 | AL84: =AL83/'Income & Cash Flow'!AL$8*182.5 -> 3.1424229 | AM84: =AM83/'Income & Cash Flow'!AM$8*365 -> 3.1486736 | AN84: =AN83/'Income & Cash Flow'!AN$8*182.5 -> 3.1486736 | AO84: =AO83/'Income & Cash Flow'!AO$8*182.5 -> 3.146641 | AP84: =AP83/'Income & Cash Flow'!AP$8*365 -> 3.1486736 | AQ84: =AQ83/'Income & Cash Flow'!AQ$8*182.5 -> 3.1486736 | AR84: =AR83/'Income & Cash Flow'!AR$8*182.5 -> 3.1502894 | AS84: =AS83/'Income & Cash Flow'!AS$8*365 -> 3.1486736 | AT84: =AT83/'Income & Cash Flow'!AT$8*182.5 -> 3.1486736 | AU84: =AU83/'Income & Cash Flow'!AU$8*182.5 -> 3.1534739 | AV84: =AV83/'Income & Cash Flow'!AV$8*365 -> 3.1486736 | AW84: =AW83/'Income & Cash Flow'!AW$8*182.5 -> 3.1486736 | AX84: =AX83/'Income & Cash Flow'!AX$8*182.5 -> 3.1562755 | AY84: =AY83/'Income & Cash Flow'!AY$8*365 -> 3.1486736
B85: % Sales | I85: =I83/'Income & Cash Flow'!I$8 -> 0.013820683 | L85: =L83/'Income & Cash Flow'!L$8 -> 0.011566313 | O85: =O83/'Income & Cash Flow'!O$8 -> 0.0083113293 | P85: =P83/'Income & Cash Flow'!P$8 -> 0.018929422 | Q85: =Q83/'Income & Cash Flow'!Q$8 -> 0.016170856 | R85: =R83/'Income & Cash Flow'!R$8 -> 0.0082550685 | S85: =S83/'Income & Cash Flow'!S$8 -> 0.020002919 | T85: =T83/'Income & Cash Flow'!T$8 -> 0.016822998 | U85: =U83/'Income & Cash Flow'!U$8 -> 0.0086265029 | V85: =+X85*2 -> 0.017253006 | W85: =W83/'Income & Cash Flow'!W$8 -> 0.016989376 | X85: =+U85 -> 0.0086265029 | Y85: =+AA85*2 -> 0.017253006 | Z85: =Z83/'Income & Cash Flow'!Z$8 -> 0.017025427 | AA85: =+X85 -> 0.0086265029 | AB85: =+AD85*2 -> 0.017253006 | AC85: =AC83/'Income & Cash Flow'!AC$8 -> 0.017089582 | AD85: =+AA85 -> 0.0086265029 | AE85: =+AG85*2 -> 0.017253006 | AF85: =AF83/'Income & Cash Flow'!AF$8 -> 0.01712843 | AG85: =+AD85 -> 0.0086265029 | AH85: =+AJ85*2 -> 0.017253006 | AI85: =AI83/'Income & Cash Flow'!AI$8 -> 0.017191747 | AJ85: =+AG85 -> 0.0086265029 | AK85: =+AM85*2 -> 0.017253006 | AL85: =AL83/'Income & Cash Flow'!AL$8 -> 0.017218756 | AM85: =+AJ85 -> 0.0086265029 | AN85: =+AP85*2 -> 0.017253006 | AO85: =AO83/'Income & Cash Flow'!AO$8 -> 0.017241869 | AP85: =+AM85 -> 0.0086265029 | AQ85: =+AS85*2 -> 0.017253006 | AR85: =AR83/'Income & Cash Flow'!AR$8 -> 0.01726186 | AS85: =+AP85 -> 0.0086265029 | AT85: =+AV85*2 -> 0.017253006 | AU85: =AU83/'Income & Cash Flow'!AU$8 -> 0.017279309 | AV85: =+AS85 -> 0.0086265029 | AW85: =+AY85*2 -> 0.017253006 | AX85: =AX83/'Income & Cash Flow'!AX$8 -> 0.01729466 | AY85: =+AV85 -> 0.0086265029
B87: Payables | I87: =+I25 -> 17.097 | L87: =+L25 -> 28.008 | O87: =+O25 -> 32.635 | P87: =+P25 -> 22.035 | Q87: =+Q25 -> 39.387 | R87: =+R25 -> 39.387 | S87: =+S25 -> 30.198 | T87: =+T25 -> 40.439 | U87: =+U25 -> 40.439 | V87: =+'Income & Cash Flow'!V16*'Balance Sheet'!V89 -> 48.588371 | W87: =+X87 -> 49.701664 | X87: =+'Income & Cash Flow'!X16*'Balance Sheet'!X89 -> 49.701664 | Y87: =+'Income & Cash Flow'!Y16*'Balance Sheet'!Y89 -> 56.957917 | Z87: =+AA87 -> 58.017867 | AA87: =+'Income & Cash Flow'!AA16*'Balance Sheet'!AA89 -> 58.017867 | AB87: =+'Income & Cash Flow'!AB16*'Balance Sheet'!AB89 -> 65.46976 | AC87: =+AD87 -> 66.416698 | AD87: =+'Income & Cash Flow'!AD16*'Balance Sheet'!AD89 -> 66.416698 | AE87: =+'Income & Cash Flow'!AE16*'Balance Sheet'!AE89 -> 73.635978 | AF87: =+AG87 -> 74.537383 | AG87: =+'Income & Cash Flow'!AG16*'Balance Sheet'!AG89 -> 74.537383 | AH87: =+'Income & Cash Flow'!AH16*'Balance Sheet'!AH89 -> 82.132554 | AI87: =+AJ87 -> 82.987263 | AJ87: =+'Income & Cash Flow'!AJ16*'Balance Sheet'!AJ89 -> 82.987263 | AK87: =+'Income & Cash Flow'!AK16*'Balance Sheet'!AK89 -> 92.98409 | AL87: =+AM87 -> 93.559039 | AM87: =+'Income & Cash Flow'!AM16*'Balance Sheet'!AM89 -> 93.559039 | AN87: =+'Income & Cash Flow'!AN16*'Balance Sheet'!AN89 -> 103.58637 | AO87: =+AP87 -> 104.08682 | AP87: =+'Income & Cash Flow'!AP16*'Balance Sheet'!AP89 -> 104.08682 | AQ87: =+'Income & Cash Flow'!AQ16*'Balance Sheet'!AQ89 -> 114.8267 | AR87: =+AS87 -> 115.24765 | AS87: =+'Income & Cash Flow'!AS16*'Balance Sheet'!AS89 -> 115.24765 | AT87: =+'Income & Cash Flow'!AT16*'Balance Sheet'!AT89 -> 126.74104 | AU87: =+AV87 -> 127.07723 | AV87: =+'Income & Cash Flow'!AV16*'Balance Sheet'!AV89 -> 127.07723 | AW87: =+'Income & Cash Flow'!AW16*'Balance Sheet'!AW89 -> 139.36737 | AX87: =+AY87 -> 139.61331 | AY87: =+'Income & Cash Flow'!AY16*'Balance Sheet'!AY89 -> 139.61331
B88: DPO | I88: =-I87/'Income & Cash Flow'!I16*365 -> 61.860911 | L88: =-L87/'Income & Cash Flow'!L16*365 -> 69.12703 | O88: =-O87/'Income & Cash Flow'!O16*365 -> 51.920579 | P88: =-P87/'Income & Cash Flow'!P16*365 -> 54.11892 | Q88: =-Q87/'Income & Cash Flow'!Q16*365 -> 86.433682 | R88: =-R87/'Income & Cash Flow'!R16*365 -> 45.6476 | S88: =-S87/'Income & Cash Flow'!S16*365 -> 60.950061 | T88: =-T87/'Income & Cash Flow'!T16*365 -> 77.676453 | U88: =-U87/'Income & Cash Flow'!U16*365 -> 39.799697 | V88: =-V87/'Income & Cash Flow'!V16*365 -> 79.599394 | ... AY88: =-AY87/'Income & Cash Flow'!AY16*365 -> 39.799697
B89: % Operating expenses | I89: =I87/'Income & Cash Flow'!I16 -> -0.16948195 | L89: =L87/'Income & Cash Flow'!L16 -> -0.18938912 | O89: =O87/'Income & Cash Flow'!O16 -> -0.14224816 | P89: =P87/'Income & Cash Flow'!P16 -> -0.14827101 | Q89: =Q87/'Income & Cash Flow'!Q16 -> -0.23680461 | R89: =R87/'Income & Cash Flow'!R16 -> -0.12506192 | S89: =S87/'Income & Cash Flow'!S16 -> -0.16698647 | T89: =T87/'Income & Cash Flow'!T16 -> -0.2128122 | U89: =U87/'Income & Cash Flow'!U16 -> -0.10904027 | V89: =+X89*2 -> -0.21808053 | W89: =W87/'Income & Cash Flow'!W$8 -> 0.18165941 | X89: =+U89 -> -0.10904027 | Y89: =+AA89*2 -> -0.21808053 | Z89: =Z87/'Income & Cash Flow'!Z$8 -> 0.17840265 | AA89: =+X89 -> -0.10904027 | AB89: =+AD89*2 -> -0.21808053 | AC89: =AC87/'Income & Cash Flow'!AC$8 -> 0.17459642 | AD89: =+AA89 -> -0.10904027 | AE89: =+AG89*2 -> -0.21808053 | AF89: =AF87/'Income & Cash Flow'!AF$8 -> 0.17134257 | AG89: =+AD89 -> -0.10904027 | AH89: =+AJ89*2 -> -0.21808053 | AI89: =AI87/'Income & Cash Flow'!AI$8 -> 0.16877986 | AJ89: =+AG89 -> -0.10904027 | AK89: =+AM89*2 -> -0.21808053 | AL89: =AL87/'Income & Cash Flow'!AL$8 -> 0.16948316 | AM89: =+AJ89 -> -0.10904027 | AN89: =+AP89*2 -> -0.21808053 | AO89: =AO87/'Income & Cash Flow'!AO$8 -> 0.16890681 | AP89: =+AM89 -> -0.10904027 | AQ89: =+AS89*2 -> -0.21808053 | AR89: =AR87/'Income & Cash Flow'!AR$8 -> 0.16835589 | AS89: =+AP89 -> -0.10904027 | AT89: =+AV89*2 -> -0.21808053 | AU89: =AU87/'Income & Cash Flow'!AU$8 -> 0.16782812 | AV89: =+AS89 -> -0.10904027 | AW89: =+AY89*2 -> -0.21808053 | AX89: =AX87/'Income & Cash Flow'!AX$8 -> 0.16732188 | AY89: =+AV89 -> -0.10904027
B91: Working Capital | I91: =I79+I83-I87 -> -10.452 | L91: =L79+L83-L87 -> -9.669 | O91: =O79+O83-O87 -> -6.535 | P91: =P79+P83-P87 -> 2.334 | Q91: =Q79+Q83-Q87 -> -10.542 | R91: =R79+R83-R87 -> -10.542 | S91: =S79+S83-S87 -> -7.097 | T91: =T79+T83-T87 -> -11.975 | U91: =U79+U83-U87 -> -11.975 | V91: =V79+V83-V87 -> -13.955291 | ... AY91: =AY79+AY83-AY87 -> -30.399207
B92: Change in WC | I92: =+I91-F91 -> -10.452 | L92: =+L91-I91 -> 0.783 | O92: =+O91-L91 -> 3.134 | P92: =+P91-O91 -> 8.869 | Q92: =+Q91-P91 -> -12.876 | R92: =+R91-O91 -> -4.007 | S92: =+S91-R91 -> 3.445 | T92: =+T91-S91 -> -4.878 | U92: =+U91-R91 -> -1.433 | V92: =+V91-U91 -> -1.9802914 | W92: =+W91-V91 -> -0.5674088 | X92: =+X91-U91 -> -2.5477002 | Y92: =+Y91-X91 -> -1.0917677 | Z92: =+Z91-Y91 -> -0.49982531 | AA92: =+AA91-X91 -> -1.591593 | AB92: =+AB91-AA91 -> -0.6258541 | AC92: =+AC91-AB91 -> -0.47644945 | AD92: =+AD91-AA91 -> -1.1023036 | AE92: =+AE91-AD91 -> -0.43732425 | AF92: =+AF91-AE91 -> -0.49126349 | AG92: =+AG91-AD91 -> -0.92858774 | AH92: =+AH91-AG91 -> -0.24134102 | AI92: =+AI91-AH91 -> -0.62675044 | AJ92: =+AJ91-AG91 -> -0.86809146 | AK92: =+AK91-AJ91 -> -2.1767012 | AL92: =+AL91-AK91 -> -0.43185728 | AM92: =+AM91-AJ91 -> -2.6085585 | AN92: =+AN91-AM91 -> -1.6036174 | AO92: =+AO91-AN91 -> -0.44851059 | AP92: =+AP91-AM91 -> -2.052128 | AQ92: =+AQ91-AP91 -> -1.6767243 | AR92: =+AR91-AQ91 -> -0.46681768 | AS92: =+AS91-AP91 -> -2.1435419 | AT92: =+AT91-AS91 -> -1.7530211 | AU92: =+AU91-AT91 -> -0.48692172 | AV92: =+AV91-AS91 -> -2.2399428 | AW92: =+AW91-AV91 -> -1.8327748 | AX92: =+AX91-AW91 -> -0.50898469 | AY92: =+AY91-AV91 -> -2.3417595
B93: WC days | I93: =I91/'Income & Cash Flow'!I$8*365 -> -31.916239 | L93: =L91/'Income & Cash Flow'!L$8*365 -> -20.543361 | O93: =O91/'Income & Cash Flow'!O$8*365 -> -9.2079917 | P93: =P91/'Income & Cash Flow'!P$8*365 -> 5.0855137 | Q93: =Q91/'Income & Cash Flow'!Q$8*365 -> -22.025736 | R93: =R91/'Income & Cash Flow'!R$8*365 -> -11.243929 | S93: =S91/'Income & Cash Flow'!S$8*365 -> -12.19479 | T93: =T91/'Income & Cash Flow'!T$8*365 -> -19.550977 | U93: =U91/'Income & Cash Flow'!U$8*365 -> -10.025357 | V93: =V91/'Income & Cash Flow'!V$8*365 -> -19.20428 | ... AY93: =AY91/'Income & Cash Flow'!AY$8*365 -> -6.6329046
B95: WC / Sales | I95: =I91/'Income & Cash Flow'!I$8 -> -0.087441752 | L95: =L91/'Income & Cash Flow'!L$8 -> -0.05628318 | O95: =O91/'Income & Cash Flow'!O$8 -> -0.025227375 | P95: =P91/'Income & Cash Flow'!P$8 -> 0.013932914 | Q95: =Q91/'Income & Cash Flow'!Q$8 -> -0.060344482 | R95: =R91/'Income & Cash Flow'!R$8 -> -0.030805286 | S95: =S91/'Income & Cash Flow'!S$8 -> -0.033410382 | T95: =T91/'Income & Cash Flow'!T$8 -> -0.05356432 | U95: =U91/'Income & Cash Flow'!U$8 -> -0.02746673 | V95: =V91/'Income & Cash Flow'!V$8 -> -0.052614465 | ... AY95: =AY91/'Income & Cash Flow'!AY$8 -> -0.018172341
B96: Change WC / Sales | I96: =I92/'Income & Cash Flow'!I$8 -> -0.087441752 | L96: =L92/'Income & Cash Flow'!L$8 -> 0.0045578374 | O96: =O92/'Income & Cash Flow'!O$8 -> 0.012098331 | P96: =P92/'Income & Cash Flow'!P$8 -> 0.05294388 | Q96: =Q92/'Income & Cash Flow'!Q$8 -> -0.073704757 | R96: =R92/'Income & Cash Flow'!R$8 -> -0.011709048 | S96: =S92/'Income & Cash Flow'!S$8 -> 0.016217947 | T96: =T92/'Income & Cash Flow'!T$8 -> -0.021819353 | U96: =U92/'Income & Cash Flow'!U$8 -> -0.0032868329 | V96: =V92/'Income & Cash Flow'!V$8 -> -0.0074661267 | ... AY96: =AY92/'Income & Cash Flow'!AY$8 -> -0.0013998804
B97: DPO | I97: =-I88 -> -61.860911 | L97: =-L88 -> -69.12703 | O97: =-O88 -> -51.920579 | P97: =-P88 -> -54.11892 | Q97: =-Q88 -> -86.433682 | R97: =-R88 -> -45.6476 | S97: =-S88 -> -60.950061 | T97: =-T88 -> -77.676453 | U97: =-U88 -> -39.799697 | V97: =-V88 -> -79.599394 | ... AY97: =-AY88 -> -39.799697
B99: PPE
B100: At cost:
B101: Opening balance | I101: =+F14 -> 0 | L101: =+I14 -> 0.389 | O101: =+L15 -> 36.563 | P101: =+O15 -> 69.486 | Q101: =+P15 -> 77.953 | R101: =+O15 -> 69.486 | S101: =+R15 -> 87.63 | T101: =+S15 -> 103.028 | U101: =+R15 -> 87.63 | V101: =+U15 -> 130.056 | W101: =+T15 -> 130.056 | X101: =+U15 -> 130.056 | Y101: =+X15 -> 162.34536 | Z101: =+W15 -> 162.34536 | AA101: =+X15 -> 162.34536 | AB101: =+AA15 -> 192.20474 | AC101: =+Z15 -> 192.20474 | AD101: =+AA15 -> 192.20474 | AE101: =+AD15 -> 220.64019 | AF101: =+AC15 -> 220.64019 | AG101: =+AD15 -> 220.64019 | AH101: =+AG15 -> 248.21971 | AI101: =+AF15 -> 248.21971 | AJ101: =+AG15 -> 248.21971 | AK101: =+AJ15 -> 275.4242 | AL101: =+AI15 -> 275.4242 | AM101: =+AJ15 -> 275.4242 | AN101: =+AM15 -> 302.66547 | AO101: =+AL15 -> 302.66547 | AP101: =+AM15 -> 302.66547 | AQ101: =+AP15 -> 330.30094 | AR101: =+AO15 -> 330.30094 | AS101: =+AP15 -> 330.30094 | AT101: =+AS15 -> 358.64559 | AU101: =+AR15 -> 358.64559 | AV101: =+AS15 -> 358.64559 | AW101: =+AV15 -> 387.9819 | AX101: =+AU15 -> 387.9819 | AY101: =+AV15 -> 387.9819
B102: Capex (+) | I102: =+-'Income & Cash Flow'!I102 -> 11.667 | L102: =+-'Income & Cash Flow'!L102 -> 19.392 | O102: =-'Income & Cash Flow'!O102 -> 39.713 | P102: =+-'Income & Cash Flow'!P102 -> 14.867 | Q102: =+-'Income & Cash Flow'!Q102 -> 18.629 | R102: =+-'Income & Cash Flow'!R102 -> 33.496 | S102: =+-'Income & Cash Flow'!S102 -> 21.855 | T102: =+-'Income & Cash Flow'!T102 -> 39.471 | U102: =+-'Income & Cash Flow'!U102 -> 61.326 | V102: 30 | W102: 30 | X102: =+W102+V102 -> 60 | Y102: =+V102*1.065 -> 31.95 | Z102: =+W102*1.065 -> 31.95 | AA102: =+Z102+Y102 -> 63.9 | AB102: =+Y102*1.07 -> 34.1865 | AC102: =+Z102*1.07 -> 34.1865 | AD102: =+AC102+AB102 -> 68.373 | AE102: =+AB102*1.07 -> 36.579555 | AF102: =+AC102*1.07 -> 36.579555 | AG102: =+AF102+AE102 -> 73.15911 | AH102: =+AE102*1.07 -> 39.140124 | AI102: =+AF102*1.07 -> 39.140124 | AJ102: =+AI102+AH102 -> 78.280248 | AK102: =+AH102*1.07 -> 41.879933 | AL102: =+AI102*1.07 -> 41.879933 | AM102: =+AL102+AK102 -> 83.759865 | AN102: =+AK102*1.07 -> 44.811528 | AO102: =+AL102*1.07 -> 44.811528 | AP102: =+AO102+AN102 -> 89.623056 | AQ102: =+AN102*1.07 -> 47.948335 | AR102: =+AO102*1.07 -> 47.948335 | AS102: =+AR102+AQ102 -> 95.896669 | AT102: =+AQ102*1.07 -> 51.304718 | AU102: =+AR102*1.07 -> 51.304718 | AV102: =+AU102+AT102 -> 102.60944 | AW102: =+AT102*1.07 -> 54.896048 | AX102: =+AU102*1.07 -> 54.896048 | AY102: =+AX102+AW102 -> 109.7921
B103: Acquisitions (+) | I103: =-'Income & Cash Flow'!I103 -> 3.496 | L103: =-'Income & Cash Flow'!L103 -> 7.011 | O103: =-'Income & Cash Flow'!O101 -> 6.44 | P103: =-'Income & Cash Flow'!P103 -> 0.009 | Q103: =-'Income & Cash Flow'!Q103 -> 0.054 | R103: =-'Income & Cash Flow'!R103 -> 0.063 | S103: =-'Income & Cash Flow'!S103 -> 0.008 | T103: =-'Income & Cash Flow'!T103 -> 0.029 | U103: =-'Income & Cash Flow'!U103 -> 0.037 | V103: 0 | W103: 0 | X103: =+W103+V103 -> 0 | Y103: 0 | Z103: 0 | AA103: =+Z103+Y103 -> 0 | AB103: 0 | AC103: 0 | AD103: =+AC103+AB103 -> 0 | AE103: 0 | AF103: 0 | AG103: =+AF103+AE103 -> 0 | AH103: 0 | AI103: 0 | AJ103: =+AI103+AH103 -> 0 | AK103: 0 | AL103: 0 | AM103: =+AL103+AK103 -> 0 | AN103: 0 | AO103: 0 | AP103: =+AO103+AN103 -> 0 | AQ103: 0 | AR103: 0 | AS103: =+AR103+AQ103 -> 0 | AT103: 0 | AU103: 0 | AV103: =+AU103+AT103 -> 0 | AW103: 0 | AX103: 0 | AY103: =+AX103+AW103 -> 0
B104: Disposals (-) | I104: 0 | L104: 0 | O104: 0 | P104: 0 | Q104: 0 | R104: 0 | S104: 0 | T104: 0 | U104: 0 | V104: 0 | W104: 0 | X104: =+W104+V104 -> 0 | Y104: 0 | Z104: 0 | AA104: =+Z104+Y104 -> 0 | AB104: 0 | AC104: 0 | AD104: =+AC104+AB104 -> 0 | AE104: 0 | AF104: 0 | AG104: =+AF104+AE104 -> 0 | AH104: 0 | AI104: 0 | AJ104: =+AI104+AH104 -> 0 | AK104: 0 | AL104: 0 | AM104: =+AL104+AK104 -> 0 | AN104: 0 | AO104: 0 | AP104: =+AO104+AN104 -> 0 | AQ104: 0 | AR104: 0 | AS104: =+AR104+AQ104 -> 0 | AT104: 0 | AU104: 0 | AV104: =+AU104+AT104 -> 0 | AW104: 0 | AX104: 0 | AY104: =+AX104+AW104 -> 0
B105: Depreciation (-) | I105: ='Income & Cash Flow'!I22 -> -3.537 | L105: ='Income & Cash Flow'!L22 -> -5.341 | M105: ='Income & Cash Flow'!M22 -> -3.798 | N105: ='Income & Cash Flow'!N22 -> -4.592 | O105: ='Income & Cash Flow'!O22 -> -8.39 | P105: ='Income & Cash Flow'!P22 -> -6.062 | Q105: ='Income & Cash Flow'!Q22 -> -6.898 | R105: ='Income & Cash Flow'!R22 -> -12.96 | S105: ='Income & Cash Flow'!S22 -> -7.832 | ... U105: ='Income & Cash Flow'!U22 -> -19.296 | V105: =+U107*V109 -> -13.0056 | W105: =+V107*W109 -> -14.70504 | X105: =+W105+V105 -> -27.71064 | Y105: =+X107*Y109 -> -16.234536 | Z105: =+Y107*Z109 -> -17.806082 | AA105: =+Z105+Y105 -> -34.040618 | AB105: =+AA107*AB109 -> -19.220474 | AC105: =+AB107*AC109 -> -20.717077 | AD105: =+AC105+AB105 -> -39.937551 | AE105: =+AD107*AE109 -> -22.064019 | AF105: =+AE107*AF109 -> -23.515573 | AG105: =+AF105+AE105 -> -45.579592 | AH105: =+AG107*AH109 -> -24.821971 | AI105: =+AH107*AI109 -> -26.253786 | AJ105: =+AI105+AH105 -> -51.075757 | AK105: =+AJ107*AK109 -> -27.54242 | AL105: =+AK107*AL109 -> -28.976171 | AM105: =+AL105+AK105 -> -56.518591 | AN105: =+AM107*AN109 -> -30.266547 | AO105: =+AN107*AO109 -> -31.721045 | AP105: =+AO105+AN105 -> -61.987593 | AQ105: =+AP107*AQ109 -> -33.030094 | AR105: =+AQ107*AR109 -> -34.521918 | AS105: =+AR105+AQ105 -> -67.552011 | AT105: =+AS107*AT109 -> -35.864559 | AU105: =+AT107*AU109 -> -37.408575 | AV105: =+AU105+AT105 -> -73.273135 | AW105: =+AV107*AW109 -> -38.79819 | AX105: =+AW107*AX109 -> -40.407975 | AY105: =+AX105+AW105 -> -79.206165
B106: Other (+/-) | I106: =I107-SUM(I101:I105) -> -11.237 | L106: =L107-SUM(L101:L105) -> 15.112 | O106: =O107-SUM(O101:O105) -> -4.84 | P106: =P107-SUM(P101:P105) -> -0.347 | Q106: =Q107-SUM(Q101:Q105) -> -2.108 | R106: =R107-SUM(R101:R105) -> -2.455 | S106: =S107-SUM(S101:S105) -> 1.367 | T106: =T107-SUM(T101:T105) -> -1.008 | U106: =U107-SUM(U101:U105) -> 0.359 | V106: 0 | W106: 0 | X106: =+W106+V106 -> 0 | Y106: 0 | Z106: 0 | AA106: =+Z106+Y106 -> 0 | AB106: 0 | AC106: 0 | AD106: =+AC106+AB106 -> 0 | AE106: 0 | AF106: 0 | AG106: =+AF106+AE106 -> 0 | AH106: 0 | AI106: 0 | AJ106: =+AI106+AH106 -> 0 | AK106: 0 | AL106: 0 | AM106: =+AL106+AK106 -> 0 | AN106: 0 | AO106: 0 | AP106: =+AO106+AN106 -> 0 | AQ106: 0 | AR106: 0 | AS106: =+AR106+AQ106 -> 0 | AT106: 0 | AU106: 0 | AV106: =+AU106+AT106 -> 0 | AW106: 0 | AX106: 0 | AY106: =+AX106+AW106 -> 0
B107: Total PP&E | I107: =+I14 -> 0.389 | L107: =+L15 -> 36.563 | O107: =+O15 -> 69.486 | P107: =+P15 -> 77.953 | Q107: =+Q15 -> 87.63 | R107: =+R15 -> 87.63 | S107: =+S15 -> 103.028 | T107: =+T15 -> 130.056 | U107: =+U15 -> 130.056 | V107: =SUM(V101:V106) -> 147.0504 | W107: =SUM(W101:W106) -> 145.35096 | X107: =SUM(X101:X106) -> 162.34536 | Y107: =SUM(Y101:Y106) -> 178.06082 | Z107: =SUM(Z101:Z106) -> 176.48928 | AA107: =SUM(AA101:AA106) -> 192.20474 | AB107: =SUM(AB101:AB106) -> 207.17077 | AC107: =SUM(AC101:AC106) -> 205.67416 | ... AY107: =SUM(AY101:AY106) -> 418.56783
B109: Dep rate | I109: =I105/AVERAGE(I107,F107) -> -9.092545 | L109: =L105/AVERAGE(L107,I107) -> -0.28907772 | O109: =O105/AVERAGE(O107,L107) -> -0.15822874 | P109: =P105/AVERAGE(P107,O107) -> -0.082230617 | Q109: =Q105/AVERAGE(Q107,P107) -> -0.083317732 | R109: =R105/AVERAGE(R107,O107) -> -0.16497365 | S109: =S105/AVERAGE(S107,R107) -> -0.082157581 | T109: =T105/AVERAGE(T107,S107) -> -0.09836797 | U109: =U105/AVERAGE(U107,R107) -> -0.17728288 | V109: -0.1 | W109: -0.1 | X109: =X105/AVERAGE(X107,U107) -> -0.18953838 | Y109: -0.1 | Z109: -0.1 | AA109: =AA105/AVERAGE(AA107,X107) -> -0.19202148 | AB109: -0.1 | AC109: -0.1 | AD109: =AD105/AVERAGE(AD107,AA107) -> -0.19347483 | AE109: -0.1 | AF109: -0.1 | AG109: =AG105/AVERAGE(AG107,AD107) -> -0.19442734 | AH109: -0.1 | AI109: -0.1 | AJ109: =AJ105/AVERAGE(AJ107,AG107) -> -0.19507821 | AK109: -0.1 | AL109: -0.1 | AM109: =AM105/AVERAGE(AM107,AJ107) -> -0.19553572 | AN109: -0.1 | AO109: -0.1 | AP109: =AP105/AVERAGE(AP107,AM107) -> -0.19586377 | AQ109: -0.1 | AR109: -0.1 | AS109: =AS105/AVERAGE(AS107,AP107) -> -0.19610233 | AT109: -0.1 | AU109: -0.1 | AV109: =AV105/AVERAGE(AV107,AS107) -> -0.19627762 | AW109: -0.1 | AX109: -0.1 | AY109: =AY105/AVERAGE(AY107,AV107) -> -0.19640739
B110: Capex / sales (%) | I110: =I102/'Income & Cash Flow'!I$8 -> 0.097606479 | L110: =L102/'Income & Cash Flow'!L$8 -> 0.11288069 | O110: =O102/'Income & Cash Flow'!O$8 -> 0.153306 | P110: =P102/'Income & Cash Flow'!P$8 -> 0.088749202 | Q110: =Q102/'Income & Cash Flow'!Q$8 -> 0.10663606 | R110: =R102/'Income & Cash Flow'!R$8 -> 0.097880274 | S110: =S102/'Income & Cash Flow'!S$8 -> 0.10288628 | T110: =T102/'Income & Cash Flow'!T$8 -> 0.17655426 | U110: =U102/'Income & Cash Flow'!U$8 -> 0.14066177 | V110: =V102/'Income & Cash Flow'!V$8 -> 0.11310649 | ... AY110: =AY102/'Income & Cash Flow'!AY$8 -> 0.065632616
B112: Intangibles
B113: Opening Balance | I113: =F119 -> 0 | L113: =I119 -> 6.494 | O113: =L119 -> 15.41 | P113: =O119 -> 15.202 | Q113: =P119 -> 11.697 | R113: =O119 -> 15.202 | S113: =R119 -> 10.586 | T113: =S119 -> 19.153 | U113: =R119 -> 10.586 | V113: =U119 -> 18.305 | W113: =V119 -> 14.62475 | X113: =U119 -> 18.305 | Y113: =X119 -> 11.46845 | Z113: =Y119 -> 7.6041875 | AA113: =X119 -> 11.46845 | AB113: =AA119 -> 4.2900725 | AC113: =AB119 -> 0.23259687 | AD113: =AA119 -> 4.2900725 | AE113: =AD119 -> -3.2472239 | AF113: =AE119 -> -7.5075733 | AG113: =AD119 -> -3.2472239 | AH113: =AG119 -> -11.161385 | AI113: =AH119 -> -15.634752 | AJ113: =AG119 -> -11.161385 | AK113: =AJ119 -> -19.471254 | AL113: =AK119 -> -24.16829 | AM113: =AJ119 -> -19.471254 | AN113: =AM119 -> -28.196617 | AO113: =AN119 -> -33.128504 | AP113: =AM119 -> -28.196617 | AQ113: =AP119 -> -37.358248 | AR113: =AQ119 -> -42.536729 | AS113: =AP119 -> -37.358248 | AT113: =AS119 -> -46.97796 | AU113: =AT119 -> -52.415366 | AV113: =AS119 -> -46.97796 | AW113: =AV119 -> -57.078658 | AX113: =AW119 -> -62.787934 | AY113: =AV119 -> -57.078658
B114: Capex (+) | I114: =-'Income & Cash Flow'!I103 -> 3.496 | L114: =-'Income & Cash Flow'!L103 -> 7.011 | O114: =-'Income & Cash Flow'!O103 -> 2.944 | P114: =-'Income & Cash Flow'!P103 -> 0.009 | Q114: =-'Income & Cash Flow'!Q103 -> 0.054 | R114: =-'Income & Cash Flow'!R103 -> 0.063 | S114: =-'Income & Cash Flow'!S103 -> 0.008 | T114: =-'Income & Cash Flow'!T103 -> 0.029 | U114: =-'Income & Cash Flow'!U103 -> 0.037 | V114: 0 | W114: 0 | X114: =+W114+V114 -> 0 | Y114: 0 | Z114: 0 | AA114: =+Z114+Y114 -> 0 | AB114: 0 | AC114: 0 | AD114: =+AC114+AB114 -> 0 | AE114: 0 | AF114: 0 | AG114: =+AF114+AE114 -> 0 | AH114: 0 | AI114: 0 | AJ114: =+AI114+AH114 -> 0 | AK114: 0 | AL114: 0 | AM114: =+AL114+AK114 -> 0 | AN114: 0 | AO114: 0 | AP114: =+AO114+AN114 -> 0 | AQ114: 0 | AR114: 0 | AS114: =+AR114+AQ114 -> 0 | AT114: 0 | AU114: 0 | AV114: =+AU114+AT114 -> 0 | AW114: 0 | AX114: 0 | AY114: =+AX114+AW114 -> 0
B115: Acquisitions (+) | I115: =+H115+G115 -> 0 | L115: =+K115+J115 -> 0 | O115: =+N115+M115 -> 0 | P115: 0 | Q115: 0 | R115: =+Q115+P115 -> 0 | S115: 0 | T115: 0 | U115: =+T115+S115 -> 0 | V115: 0 | W115: 0 | X115: =+W115+V115 -> 0 | Y115: 0 | Z115: 0 | AA115: =+Z115+Y115 -> 0 | AB115: 0 | AC115: 0 | AD115: =+AC115+AB115 -> 0 | AE115: 0 | AF115: 0 | AG115: =+AF115+AE115 -> 0 | AH115: 0 | AI115: 0 | AJ115: =+AI115+AH115 -> 0 | AK115: 0 | AL115: 0 | AM115: =+AL115+AK115 -> 0 | AN115: 0 | AO115: 0 | AP115: =+AO115+AN115 -> 0 | AQ115: 0 | AR115: 0 | AS115: =+AR115+AQ115 -> 0 | AT115: 0 | AU115: 0 | AV115: =+AU115+AT115 -> 0 | AW115: 0 | AX115: 0 | AY115: =+AX115+AW115 -> 0
B116: Disposals (-) | I116: =+H116+G116 -> 0 | L116: =+K116+J116 -> 0 | O116: =+N116+M116 -> 0 | P116: 0 | Q116: 0 | R116: =+Q116+P116 -> 0 | S116: 0 | T116: 0 | U116: =+T116+S116 -> 0 | V116: 0 | W116: 0 | X116: =+W116+V116 -> 0 | Y116: 0 | Z116: 0 | AA116: =+Z116+Y116 -> 0 | AB116: 0 | AC116: 0 | AD116: =+AC116+AB116 -> 0 | AE116: 0 | AF116: 0 | AG116: =+AF116+AE116 -> 0 | AH116: 0 | AI116: 0 | AJ116: =+AI116+AH116 -> 0 | AK116: 0 | AL116: 0 | AM116: =+AL116+AK116 -> 0 | AN116: 0 | AO116: 0 | AP116: =+AO116+AN116 -> 0 | AQ116: 0 | AR116: 0 | AS116: =+AR116+AQ116 -> 0 | AT116: 0 | AU116: 0 | AV116: =+AU116+AT116 -> 0 | AW116: 0 | AX116: 0 | AY116: =+AX116+AW116 -> 0
B117: Amortisation (-) | L117: =+'Income & Cash Flow'!L24 -> -2.463 | M117: =+'Income & Cash Flow'!M24 -> -3.37 | N117: =+'Income & Cash Flow'!N24 -> -3.463 | O117: =+'Income & Cash Flow'!O24 -> -6.833 | P117: =+'Income & Cash Flow'!P24 -> -3.514 | Q117: =+'Income & Cash Flow'!Q24 -> -3.402 | R117: =+'Income & Cash Flow'!R24 -> -6.916 | S117: =+'Income & Cash Flow'!S24 -> -3.505 | ... U117: =+'Income & Cash Flow'!U24 -> -6.511 | V117: =+S117*1.05 -> -3.68025 | W117: =+T117*1.05 -> -3.1563 | X117: =+W117+V117 -> -6.83655 | Y117: =+V117*1.05 -> -3.8642625 | Z117: =+W117*1.05 -> -3.314115 | AA117: =+Z117+Y117 -> -7.1783775 | AB117: =+Y117*1.05 -> -4.0574756 | AC117: =+Z117*1.05 -> -3.4798208 | AD117: =+AC117+AB117 -> -7.5372964 | AE117: =+AB117*1.05 -> -4.2603494 | AF117: =+AC117*1.05 -> -3.6538118 | AG117: =+AF117+AE117 -> -7.9141612 | AH117: =+AE117*1.05 -> -4.4733669 | AI117: =+AF117*1.05 -> -3.8365024 | AJ117: =+AI117+AH117 -> -8.3098693 | AK117: =+AH117*1.05 -> -4.6970352 | AL117: =+AI117*1.05 -> -4.0283275 | AM117: =+AL117+AK117 -> -8.7253627 | AN117: =+AK117*1.05 -> -4.931887 | AO117: =+AL117*1.05 -> -4.2297439 | AP117: =+AO117+AN117 -> -9.1616309 | AQ117: =+AN117*1.05 -> -5.1784813 | AR117: =+AO117*1.05 -> -4.4412311 | AS117: =+AR117+AQ117 -> -9.6197124 | AT117: =+AQ117*1.05 -> -5.4374054 | AU117: =+AR117*1.05 -> -4.6632926 | AV117: =+AU117+AT117 -> -10.100698 | AW117: =+AT117*1.05 -> -5.7092757 | AX117: =+AU117*1.05 -> -4.8964572 | AY117: =+AX117+AW117 -> -10.605733
B118: Other (+/-) | I118: =+H118+G118 -> 0 | L118: =+K118+J118 -> 0 | O118: =+N118+M118 -> 0 | P118: =P119-SUM(P113:P117) -> 0 | Q118: =Q119-SUM(Q113:Q117) -> 2.237 | R118: =+Q118+P118 -> 2.237 | S118: =S119-SUM(S113:S117) -> 12.064 | T118: =T119-SUM(T113:T117) -> 2.129 | U118: =+T118+S118 -> 14.193 | V118: 0 | W118: 0 | X118: =+W118+V118 -> 0 | Y118: 0 | Z118: 0 | AA118: =+Z118+Y118 -> 0 | AB118: 0 | AC118: 0 | AD118: =+AC118+AB118 -> 0 | AE118: 0 | AF118: 0 | AG118: =+AF118+AE118 -> 0 | AH118: 0 | AI118: 0 | AJ118: =+AI118+AH118 -> 0 | AK118: 0 | AL118: 0 | AM118: =+AL118+AK118 -> 0 | AN118: 0 | AO118: 0 | AP118: =+AO118+AN118 -> 0 | AQ118: 0 | AR118: 0 | AS118: =+AR118+AQ118 -> 0 | AT118: 0 | AU118: 0 | AV118: =+AU118+AT118 -> 0 | AW118: 0 | AX118: 0 | AY118: =+AX118+AW118 -> 0
B119: Total intangibles | I119: =I17 -> 6.494 | L119: =L17 -> 15.41 | O119: =O17 -> 15.202 | P119: =P17 -> 11.697 | Q119: =Q17 -> 10.586 | R119: =R17 -> 10.586 | S119: =S17 -> 19.153 | T119: =T17 -> 18.305 | U119: =U17 -> 18.305 | V119: =SUM(V113:V118) -> 14.62475 | W119: =SUM(W113:W118) -> 11.46845 | X119: =SUM(X113:X118) -> 11.46845 | Y119: =SUM(Y113:Y118) -> 7.6041875 | Z119: =SUM(Z113:Z118) -> 4.2900725 | AA119: =SUM(AA113:AA118) -> 4.2900725 | AB119: =SUM(AB113:AB118) -> 0.23259687 | AC119: =SUM(AC113:AC118) -> -3.2472239 | ... AY119: =SUM(AY113:AY118) -> -67.684391
B121: Amort rate | I121: =I117/AVERAGE(I119,F119) -> 0 | L121: =L117/AVERAGE(L119,I119) -> -0.22489043 | O121: =O117/AVERAGE(O119,L119) -> -0.44642624 | P121: =P117/AVERAGE(P119,O119) -> -0.26127365 | Q121: =Q117/AVERAGE(Q119,P119) -> -0.30534488 | R121: =R117/AVERAGE(R119,O119) -> -0.53637351 | S121: =S117/AVERAGE(S119,R119) -> -0.23571741 | T121: =T117/AVERAGE(T119,S119) -> -0.16049976 | U121: =U117/AVERAGE(U119,R119) -> -0.4507286 | V121: =+T121 -> -0.16049976 | W121: =+V121 -> -0.16049976 | X121: =X117/AVERAGE(X119,U119) -> -0.45923801 | Y121: =+W121 -> -0.16049976 | Z121: =+Y121 -> -0.16049976 | AA121: =AA117/AVERAGE(AA119,X119) -> -0.91104702 | AB121: =+Z121 -> -0.16049976 | AC121: =+AB121 -> -0.16049976 | AD121: =AD117/AVERAGE(AD119,AA119) -> -14.455207 | AE121: =+AC121 -> -0.16049976 | AF121: =+AE121 -> -0.16049976 | AG121: =AG117/AVERAGE(AG119,AD119) -> 1.0985323 | AH121: =+AF121 -> -0.16049976 | AI121: =+AH121 -> -0.16049976 | AJ121: =AJ117/AVERAGE(AJ119,AG119) -> 0.54255 | AK121: =+AI121 -> -0.16049976 | AL121: =+AK121 -> -0.16049976 | AM121: =AM117/AVERAGE(AM119,AJ119) -> 0.36608988 | AN121: =+AL121 -> -0.16049976 | AO121: =+AN121 -> -0.16049976 | AP121: =AP117/AVERAGE(AP119,AM119) -> 0.27951033 | AQ121: =+AO121 -> -0.16049976 | AR121: =+AQ121 -> -0.16049976 | AS121: =AS117/AVERAGE(AS119,AP119) -> 0.2281277 | AT121: =+AR121 -> -0.16049976 | AU121: =+AT121 -> -0.16049976 | AV121: =AV117/AVERAGE(AV119,AS119) -> 0.1941385 | AW121: =+AU121 -> -0.16049976 | AX121: =+AW121 -> -0.16049976 | AY121: =AY117/AVERAGE(AY119,AV119) -> 0.17001401
B122: Capex / sales % | I122: =I114/'Income & Cash Flow'!I$8 -> 0.029247643 | L122: =L114/'Income & Cash Flow'!L$8 -> 0.040810981 | O122: =O114/'Income & Cash Flow'!O$8 -> 0.011364865 | P122: =P114/'Income & Cash Flow'!P$8 -> 5.3725891e-05 | Q122: =Q114/'Income & Cash Flow'!Q$8 -> 0.00030910662 | R122: =R114/'Income & Cash Flow'!R$8 -> 0.00018409533 | S122: =S114/'Income & Cash Flow'!S$8 -> 3.7661414e-05 | T122: =T114/'Income & Cash Flow'!T$8 -> 0.00012971735 | U122: =U114/'Income & Cash Flow'!U$8 -> 8.4865889e-05 | V122: =+T122 -> 0.00012971735 | W122: =+V122 -> 0.00012971735 | X122: =X114/'Income & Cash Flow'!X$8 -> 0 | Y122: =+W122 -> 0.00012971735 | Z122: =+Y122 -> 0.00012971735 | AA122: =AA114/'Income & Cash Flow'!AA$8 -> 0 | AB122: =+Z122 -> 0.00012971735 | AC122: =+AB122 -> 0.00012971735 | AD122: =AD114/'Income & Cash Flow'!AD$8 -> 0 | AE122: =+AC122 -> 0.00012971735 | AF122: =+AE122 -> 0.00012971735 | AG122: =AG114/'Income & Cash Flow'!AG$8 -> 0 | AH122: =+AF122 -> 0.00012971735 | AI122: =+AH122 -> 0.00012971735 | AJ122: =AJ114/'Income & Cash Flow'!AJ$8 -> 0 | AK122: =+AI122 -> 0.00012971735 | AL122: =+AK122 -> 0.00012971735 | AM122: =AM114/'Income & Cash Flow'!AM$8 -> 0 | AN122: =+AL122 -> 0.00012971735 | AO122: =+AN122 -> 0.00012971735 | AP122: =AP114/'Income & Cash Flow'!AP$8 -> 0 | AQ122: =+AO122 -> 0.00012971735 | AR122: =+AQ122 -> 0.00012971735 | AS122: =AS114/'Income & Cash Flow'!AS$8 -> 0 | AT122: =+AR122 -> 0.00012971735 | AU122: =+AT122 -> 0.00012971735 | AV122: =AV114/'Income & Cash Flow'!AV$8 -> 0 | AW122: =+AU122 -> 0.00012971735 | AX122: =+AW122 -> 0.00012971735 | AY122: =AY114/'Income & Cash Flow'!AY$8 -> 0
B124: Right-of-use assets
...

Sheet Segments
B1: =+'GYG model ->'!D2 -> Guzman y Gomez (GYG.ASX)
B2: Segment Analysis
B4: Year-end 30th June (A$m) | D4: =+'Income & Cash Flow'!D4 -> 1H20A | E4: =+'Income & Cash Flow'!E4 -> 2H20A | F4: =+'Income & Cash Flow'!F4 -> FY20A | G4: =+'Income & Cash Flow'!G4 -> 1H21A | H4: =+'Income & Cash Flow'!H4 -> 2H21A | I4: =+'Income & Cash Flow'!I4 -> FY21A | J4: =+'Income & Cash Flow'!J4 -> 1H22A | K4: =+'Income & Cash Flow'!K4 -> 2H22A | ... AY4: =+'Income & Cash Flow'!AY4 -> FY35E
B6: Group Summary
B7: Network sales
B8: Australia corporate | L8: =+L61 -> 139.217 | M8: =+M61 -> 100.639 | N8: =+N61 -> 111.336 | O8: =+O61 -> 211.975 | P8: =+P61 -> 136.574 | Q8: =+Q61 -> 142.303 | R8: =+R61 -> 278.877 | S8: =+S61 -> 176.051 | ... AY8: =+AY61 -> 1335.9619
B9: Australia franchise | L9: =+L62 -> 396.183 | M9: =+M62 -> 234.261 | N9: =+N62 -> 256.664 | O9: =+O62 -> 490.925 | P9: =+P62 -> 302.026 | Q9: =+Q62 -> 313.697 | R9: =+R62 -> 615.723 | S9: =+S62 -> 362.189 | ... AY9: =+AY62 -> 2332.4684
B10: Australia network | L10: =+L63 -> 535.4 | M10: =+M63 -> 334.9 | N10: =+N63 -> 368 | O10: =+O63 -> 702.9 | P10: =+P63 -> 438.6 | Q10: =+Q63 -> 456 | R10: =+R63 -> 894.6 | S10: =+S63 -> 538.24 | ... AY10: =+AY63 -> 3668.4303
B11: Singapore master franchise | L11: =+L64 -> 31.4 | M11: =+M64 -> 21.5 | N11: =+N64 -> 21.6 | O11: =+O64 -> 43.1 | P11: =+P64 -> 22.2 | Q11: =+Q64 -> 24.2 | R11: =+R64 -> 46.4 | S11: =+S64 -> 30.194 | ... AY11: =+AY64 -> 261.74759
B12: Japan master franchise | L12: =+L65 -> 5.8 | M12: =+M65 -> 3.2 | N12: =+N65 -> 3.8 | O12: =+O65 -> 7 | P12: =+P65 -> 4.2 | Q12: =+Q65 -> 3.7 | R12: =+R65 -> 7.9 | S12: =+S65 -> 4.606 | ... AY12: =+AY65 -> 41.1314
B13: USA corporate | L13: =+L210 -> 2.5 | M13: =+M210 -> 1.5 | N13: =+N210 -> 4.5 | O13: =+O210 -> 6 | P13: =+P210 -> 5.6 | Q13: =+Q210 -> 5.234 | R13: =+R210 -> 10.834 | S13: =+S210 -> 4.907 | ... AY13: =+AY210 -> 43.049268
B14: Total network sales | F14: 306 | I14: 448 | L14: =+SUM(L10:L13) -> 575.1 | M14: =+SUM(M10:M13) -> 361.1 | N14: =+SUM(N10:N13) -> 397.9 | O14: =+SUM(O10:O13) -> 759 | P14: =+SUM(P10:P13) -> 470.6 | Q14: =+SUM(Q10:Q13) -> 489.134 | R14: =+SUM(R10:R13) -> 959.734 | S14: =+SUM(S10:S13) -> 577.947 | ... AY14: =+SUM(AY10:AY13) -> 4014.3585
B16: Australia corporate sales | L16: =+L61 -> 139.217 | M16: =+M61 -> 100.639 | N16: =+N61 -> 111.336 | O16: =+O61 -> 211.975 | P16: =+P61 -> 136.574 | Q16: =+Q61 -> 142.303 | R16: =+R61 -> 278.877 | S16: =+S61 -> 176.051 | ... AY16: =+AY61 -> 1335.9619
B17: Australia franchise revenue | L17: =+L72 -> 27.557 | M17: =+M72 -> 17.4515 | N17: =+N72 -> 20.219 | O17: =+O72 -> 37.6705 | P17: =+P72 -> 23.496 | Q17: =+Q72 -> 26.501 | R17: =+R72 -> 49.997 | S17: =+S72 -> 30.99203 | ... AY17: =+AY72 -> 285.72738
B18: Singapore master franchise revenue | L18: =+L73 -> 1.099 | M18: =+M73 -> 0.7525 | N18: =+N73 -> 0.756 | O18: =+O73 -> 1.5085 | P18: =+P73 -> 0.777 | Q18: =+Q73 -> 0.847 | R18: =+R73 -> 1.624 | S18: =+S73 -> 1.05679 | ... AY18: =+AY73 -> 9.1611655
B19: Japan master franchise revenue | L19: =+L74 -> 0.174 | M19: =+M74 -> 0.096 | N19: =+N74 -> 0.114 | O19: =+O74 -> 0.21 | P19: =+P74 -> 0.126 | Q19: =+Q74 -> 0.111 | R19: =+R74 -> 0.237 | S19: =+S74 -> 0.13818 | ... AY19: =+AY74 -> 1.233942
B20: APAC franchise fee revenue | L20: =+L76 -> 0.596 | M20: =+M76 -> 0.267 | N20: =+N76 -> 0.333 | O20: =+O76 -> 0.6 | P20: =+P76 -> 0.301 | Q20: =+Q76 -> 0.344 | R20: =+R76 -> 0.645 | S20: =+S76 -> 0.949 | ... AY20: =+AY76 -> 1.9995905
B21: USA corporate revenue | L21: =+L210 -> 2.5 | M21: =+M210 -> 1.5 | N21: =+N210 -> 4.5 | O21: =+O210 -> 6 | P21: =+P210 -> 5.6 | Q21: =+Q210 -> 5.234 | R21: =+R210 -> 10.834 | S21: =+S216 -> 3.232 | T21: =+T210 -> 7.399 | U21: =+U210 -> 12.306 | V21: =+V216 -> 6.4357192 | W21: =+W216 -> 6.73309 | X21: =+W21+V21 -> 13.168809 | Y21: =+Y216 -> 8.6284853 | Z21: =+Z216 -> 8.6889572 | AA21: =+Z21+Y21 -> 17.317443 | AB21: =+AB216 -> 10.267898 | AC21: =+AC216 -> 9.6140756 | AD21: =+AC21+AB21 -> 19.881973 | AE21: =+AE216 -> 11.294687 | AF21: =+AF216 -> 10.575483 | AG21: =+AF21+AE21 -> 21.87017 | AH21: =+AH216 -> 12.424156 | AI21: =+AI216 -> 11.633032 | AJ21: =+AI21+AH21 -> 24.057187 | AK21: =+AK216 -> 13.666572 | AL21: =+AL216 -> 12.796335 | AM21: =+AL21+AK21 -> 26.462906 | AN21: =+AN216 -> 15.033229 | AO21: =+AO216 -> 14.075968 | AP21: =+AO21+AN21 -> 29.109197 | AQ21: =+AQ216 -> 16.536552 | AR21: =+AR216 -> 15.483565 | AS21: =+AR21+AQ21 -> 32.020117 | AT21: =+AT216 -> 18.190207 | AU21: =+AU216 -> 17.031921 | AV21: =+AU21+AT21 -> 35.222128 | AW21: =+AW216 -> 20.009227 | AX21: =+AX216 -> 18.735114 | AY21: =+AX21+AW21 -> 38.744341
B22: Total revenue | L22: =+SUM(L16:L21) -> 171.143 | M22: =+SUM(M16:M21) -> 120.706 | N22: =+SUM(N16:N21) -> 137.258 | O22: =+SUM(O16:O21) -> 257.964 | P22: =+SUM(P16:P21) -> 166.874 | Q22: =+SUM(Q16:Q21) -> 175.34 | R22: =+SUM(R16:R21) -> 342.214 | S22: =+SUM(S16:S21) -> 212.419 | ... AY22: =+SUM(AY16:AY21) -> 1672.8283
B24: Adj. Australia segment Ebitda | L24: =+L82 -> 18.3 | M24: =+M82 -> 13.4 | N24: =+N82 -> 17.3 | O24: =+O82 -> 30.7 | P24: =+P82 -> 23.1 | Q24: =+Q82 -> 22.5 | R24: =+R82 -> 45.6 | S24: =+S82 -> 31.781 | ... AY24: =+AY82 -> 360.25206
B25: Adj. USA segment Ebitda | L25: =+L214 -> -2.9 | M25: =+M214 -> -1.7 | N25: =+N214 -> -2.596 | O25: =+O214 -> -4.296 | P25: =+P214 -> -3.1 | Q25: =+Q214 -> -3.444 | R25: =+R214 -> -6.544 | S25: =+S214 -> -5.014 | ... AY25: =+AY214 -> -30.764586
B26: Adj. Segment Ebitda | L26: =+L25+L24 -> 15.4 | M26: =+M25+M24 -> 11.7 | N26: =+N25+N24 -> 14.704 | O26: =+O25+O24 -> 26.404 | P26: =+P25+P24 -> 20 | Q26: =+Q25+Q24 -> 19.056 | R26: =+R25+R24 -> 39.056 | S26: =+S25+S24 -> 26.767 | ... AY26: =+AY25+AY24 -> 329.48748
B28: Share based payments | I28: 2.119 | L28: -1.436 | M28: -2.8 | N28: =+O28-M28 -> -1.44 | O28: -4.24 | P28: -3.6 | Q28: =+R28-P28 -> -7.5 | R28: -11.1 | S28: -4.587 | T28: =+U28-S28 -> -4.431 | U28: -9.018 | V28: -4 | W28: -4 | X28: =+W28+V28 -> -8 | Y28: -3.5 | Z28: -3.5 | AA28: =+Z28+Y28 -> -7 | AB28: -3 | AC28: -3 | AD28: =+AC28+AB28 -> -6 | AE28: -3 | AF28: -3 | AG28: =+AF28+AE28 -> -6 | AH28: -3 | AI28: -3 | AJ28: =+AI28+AH28 -> -6 | AK28: -3 | AL28: -3 | AM28: =+AL28+AK28 -> -6 | AN28: -3 | AO28: -3 | AP28: =+AO28+AN28 -> -6 | AQ28: -3 | AR28: -3 | AS28: =+AR28+AQ28 -> -6 | AT28: -3 | AU28: -3 | AV28: =+AU28+AT28 -> -6 | AW28: -3 | AX28: -3 | AY28: =+AX28+AW28 -> -6
B29: Rent and outgoings | L29: 8 | M29: 5.7 | N29: =+O29-M29 -> 5.5 | O29: 11.2 | P29: 8.2 | Q29: =+R29-P29 -> 8.9 | R29: 17.1 | S29: 9.398 | T29: =+U29-S29 -> 9.075 | U29: 18.473 | V29: =V55*AVERAGE(V40+V45,U40+U45) -> 12.058728 | W29: =W55*AVERAGE(W40+W45,V40+V45) -> 11.100375 | X29: =+W29+V29 -> 23.159103 | Y29: =Y55*AVERAGE(Y40+Y45,X40+X45) -> 14.411513 | Z29: =Z55*AVERAGE(Z40+Z45,Y40+Y45) -> 13.138575 | AA29: =+Z29+Y29 -> 27.550087 | AB29: =AB55*AVERAGE(AB40+AB45,AA40+AA45) -> 16.842852 | AC29: =AC55*AVERAGE(AC40+AC45,AB40+AB45) -> 15.122912 | AD29: =+AC29+AB29 -> 31.965764 | AE29: =AE55*AVERAGE(AE40+AE45,AD40+AD45) -> 19.205134 | AF29: =AF55*AVERAGE(AF40+AF45,AE40+AE45) -> 17.166944 | AG29: =+AF29+AE29 -> 36.372078 | AH29: =AH55*AVERAGE(AH40+AH45,AG40+AG45) -> 21.712142 | AI29: =AI55*AVERAGE(AI40+AI45,AH40+AH45) -> 19.335533 | AJ29: =+AI29+AH29 -> 41.047675 | AK29: =AK55*AVERAGE(AK40+AK45,AJ40+AJ45) -> 24.371115 | AL29: =AL55*AVERAGE(AL40+AL45,AK40+AK45) -> 21.634894 | AM29: =+AL29+AK29 -> 46.006009 | AN29: =AN55*AVERAGE(AN40+AN45,AM40+AM45) -> 27.189619 | AO29: =AO55*AVERAGE(AO40+AO45,AN40+AN45) -> 24.071524 | AP29: =+AO29+AN29 -> 51.261142 | AQ29: =AQ55*AVERAGE(AQ40+AQ45,AP40+AP45) -> 30.175563 | AR29: =AR55*AVERAGE(AR40+AR45,AQ40+AQ45) -> 26.652215 | AS29: =+AR29+AQ29 -> 56.827778 | AT29: =AT55*AVERAGE(AT40+AT45,AS40+AS45) -> 33.337216 | AU29: =AU55*AVERAGE(AU40+AU45,AT40+AT45) -> 29.384067 | AV29: =+AU29+AT29 -> 62.721283 | AW29: =AW55*AVERAGE(AW40+AW45,AV40+AV45) -> 36.68322 | AX29: =AX55*AVERAGE(AX40+AX45,AW40+AW45) -> 32.2745 | AY29: =+AX29+AW29 -> 68.957719
B30: Adjustments | L30: =+L31-L29-L28-L26 -> -0.264 | M30: =+M31-M29-M28-M26 -> -0.4 | N30: =+O30-M30 -> -3.664 | O30: =+O31-O29-O28-O26 -> -4.064 | P30: =+P31-P29-P28-P26 -> 0.1 | Q30: =+R30-P30 -> -0.356 | R30: =+R31-R29-R28-R26 -> -0.256 | S30: =+S31-S29-S28-S26 -> 0 | T30: =+U30-S30 -> 2.888 | U30: =+U31-U29-U28-U26 -> 2.888 | V30: 0 | W30: 0 | X30: =+W30+V30 -> 0 | Y30: 0 | Z30: 0 | AA30: =+Z30+Y30 -> 0 | AB30: 0 | AC30: 0 | AD30: =+AC30+AB30 -> 0 | AE30: 0 | AF30: 0 | AG30: =+AF30+AE30 -> 0 | AH30: 0 | AI30: 0 | AJ30: =+AI30+AH30 -> 0 | AK30: 0 | AL30: 0 | AM30: =+AL30+AK30 -> 0 | AN30: 0 | AO30: 0 | AP30: =+AO30+AN30 -> 0 | AQ30: 0 | AR30: 0 | AS30: =+AR30+AQ30 -> 0 | AT30: 0 | AU30: 0 | AV30: =+AU30+AT30 -> 0 | AW30: 0 | AX30: 0 | AY30: =+AX30+AW30 -> 0
B31: Adj. Group Ebitda | L31: 21.7 | M31: 14.2 | N31: =+O31-M31 -> 15.1 | O31: 29.3 | P31: 24.7 | Q31: =+R31-P31 -> 20.1 | R31: 44.8 | S31: 31.578 | T31: =+U31-S31 -> 33.541 | U31: 65.119 | V31: =+V26+V28+V29+V30 -> 42.436647 | W31: =+W26+W28+W29+W30 -> 40.588008 | X31: =+X26+X28+X29+X30 -> 83.024656 | Y31: =+Y26+Y28+Y29+Y30 -> 55.449649 | Z31: =+Z26+Z28+Z29+Z30 -> 54.308335 | AA31: =+AA26+AA28+AA29+AA30 -> 109.75798 | AB31: =+AB26+AB28+AB29+AB30 -> 72.985707 | AC31: =+AC26+AC28+AC29+AC30 -> 71.507867 | ... AY31: =+AY26+AY28+AY29+AY30 -> 392.4452
B32: Adjustments | L32: =+L33-L31 -> 2.2 | M32: =+M33-M31 -> 0.3 | N32: =+N33-N31 -> 0.021 | O32: =+O33-O31 -> 0.321 | P32: =+P33-P31 -> -5.8 | Q32: =+Q33-Q31 -> -11.727 | R32: =+R33-R31 -> -17.527 | S32: =+S33-S31 -> 0 | ... U32: =+U33-U31 -> -39.681 | V32: 0 | W32: 0 | X32: =+W32+V32 -> 0 | Y32: 0 | Z32: 0 | AA32: =+Z32+Y32 -> 0 | AB32: 0 | AC32: 0 | AD32: =+AC32+AB32 -> 0 | AE32: 0 | AF32: 0 | AG32: =+AF32+AE32 -> 0 | AH32: 0 | AI32: 0 | AJ32: =+AI32+AH32 -> 0 | AK32: 0 | AL32: 0 | AM32: =+AL32+AK32 -> 0 | AN32: 0 | AO32: 0 | AP32: =+AO32+AN32 -> 0 | AQ32: 0 | AR32: 0 | AS32: =+AR32+AQ32 -> 0 | AT32: 0 | AU32: 0 | AV32: =+AU32+AT32 -> 0 | AW32: 0 | AX32: 0 | AY32: =+AX32+AW32 -> 0
B33: Statutory Ebitda | L33: 23.9 | M33: 14.5 | N33: =+O33-M33 -> 15.121 | O33: 29.621 | P33: 18.9 | Q33: =+R33-P33 -> 8.373 | R33: 27.273 | S33: 31.578 | T33: =+U33-S33 -> -6.14 | U33: 25.438 | V33: =+V32+V31 -> 42.436647 | W33: =+W32+W31 -> 40.588008 | X33: =+X32+X31 -> 83.024656 | Y33: =+Y32+Y31 -> 55.449649 | Z33: =+Z32+Z31 -> 54.308335 | AA33: =+AA32+AA31 -> 109.75798 | AB33: =+AB32+AB31 -> 72.985707 | AC33: =+AC32+AC31 -> 71.507867 | ... AY33: =+AY32+AY31 -> 392.4452
B35: Adjustments | L35: =+L36-L31 -> -8 | M35: =+M36-M31 -> -5.7 | N35: =+O35-M35 -> -5.5 | O35: =+O36-O31 -> -11.2 | P35: =+P36-P31 -> -8.2 | Q35: =+R35-P35 -> -8.9 | R35: =+R36-R31 -> -17.1 | S35: =+S36-S31 -> -9.398 | T35: =+U35-S35 -> -9.075 | U35: =+U36-U31 -> -18.473 | V35: =+V36-V31 -> -12.058728 | W35: =+W36-W31 -> -11.100375 | X35: =+X36-X31 -> -23.159103 | Y35: =+Y36-Y31 -> -14.411513 | Z35: =+Z36-Z31 -> -13.138575 | AA35: =+AA36-AA31 -> -27.550087 | AB35: =+AB36-AB31 -> -16.842852 | ... AY35: =+AY36-AY31 -> -68.957719
B36: GSe Ebitda | L36: =+L26+L28+L30 -> 13.7 | M36: =+M26+M28+M30 -> 8.5 | N36: =+N26+N28+N30 -> 9.6 | O36: =+O26+O28+O30 -> 18.1 | P36: =+P26+P28+P30 -> 16.5 | Q36: =+Q26+Q28+Q30 -> 11.2 | R36: =+R26+R28+R30 -> 27.7 | S36: =+S26+S28+S30 -> 22.18 | ... AY36: =+AY26+AY28+AY30 -> 323.48748
B39: Network stores
B40: Australia corporate | L40: =+L136 -> 46 | O40: =+O136 -> 55 | P40: =+P136 -> 62 | Q40: =+Q136 -> 64 | R40: =+R136 -> 64 | S40: =+S136 -> 74 | T40: =+T136 -> 81 | U40: =+U136 -> 81 | V40: =+V136 -> 87 | ... AY40: =+AY136 -> 201
B41: Australia franchise | L41: =+L137 -> 104 | O41: =+O137 -> 116 | P41: =+P137 -> 121 | Q41: =+Q137 -> 130 | R41: =+R137 -> 130 | S41: =+S137 -> 136 | T41: =+T137 -> 143 | U41: =+U137 -> 143 | V41: =+V137 -> 152 | ... AY41: =+AY137 -> 323
B42: Australia network | L42: =+L138 -> 150 | O42: =+O138 -> 171 | P42: =+P138 -> 183 | Q42: =+Q138 -> 194 | R42: =+R138 -> 194 | S42: =+S138 -> 210 | T42: =+T138 -> 224 | U42: =+U138 -> 224 | V42: =+V138 -> 239 | ... AY42: =+AY138 -> 524
B43: Singapore master franchise | L43: =+L139 -> 13 | O43: =+O139 -> 16 | P43: =+P139 -> 16 | Q43: =+Q139 -> 17 | R43: =+R139 -> 17 | S43: =+S139 -> 20 | T43: =+T139 -> 21 | U43: =+U139 -> 21 | V43: =+V139 -> 22 | ... AY43: =+AY139 -> 41
B44: Japan master franchise | L44: =+L140 -> 4 | O44: =+O140 -> 4 | P44: =+P140 -> 5 | Q44: =+Q140 -> 5 | R44: =+R140 -> 5 | S44: =+S140 -> 5 | T44: =+T140 -> 5 | U44: =+U140 -> 5 | V44: =+V140 -> 6 | ... AY44: =+AY140 -> 25
B45: USA corporate | L45: =+L234 -> 1 | O45: =+O234 -> 3 | P45: =+P234 -> 4 | Q45: =+Q234 -> 4 | R45: =+R234 -> 4 | S45: =+S234 -> 4 | T45: =+T234 -> 6 | U45: =+U234 -> 6 | V45: =+V234 -> 7 | ... AY45: =+AY234 -> 10
B46: Total network stores | L46: =+SUM(L42:L45) -> 168 | O46: =+SUM(O42:O45) -> 194 | P46: =+SUM(P42:P45) -> 208 | Q46: =+SUM(Q42:Q45) -> 220 | R46: =+SUM(R42:R45) -> 220 | S46: =+SUM(S42:S45) -> 239 | T46: =+SUM(T42:T45) -> 256 | U46: =+SUM(U42:U45) -> 256 | V46: =+SUM(V42:V45) -> 274 | ... AY46: =+SUM(AY42:AY45) -> 600
B49: Margins
B50: Adj. Segment Ebitda margin | L50: =+L26/L22 -> 0.08998323 | O50: =+O26/O22 -> 0.10235537 | P50: =+P26/P22 -> 0.11985091 | Q50: =+Q26/Q22 -> 0.10868028 | R50: =+R26/R22 -> 0.11412742 | S50: =+S26/S22 -> 0.12601039 | T50: =+T26/T22 -> 0.11542883 | U50: =+U26/U22 -> 0.12010405 | V50: =+V26/V22 -> 0.12961219 | ... AY50: =+AY26/AY22 -> 0.19696431
B51: Adj. Group Ebitda margin | L51: =+L31/L22 -> 0.12679455 | O51: =+O31/O22 -> 0.11358174 | P51: =+P31/P22 -> 0.14801587 | Q51: =+Q31/Q22 -> 0.11463442 | R51: =+R31/R22 -> 0.13091224 | S51: =+S31/S22 -> 0.14865902 | T51: =+T31/T22 -> 0.1488561 | U51: =+U31/U22 -> 0.14819341 | V51: =+V31/V22 -> 0.15999533 | ... AY51: =+AY31/AY22 -> 0.23459981
B52: Statutory Ebitda margin | L52: =+L33/L22 -> 0.1396493 | O52: =+O33/O22 -> 0.1148261 | P52: =+P33/P22 -> 0.11325911 | Q52: =+Q33/Q22 -> 0.047752937 | R52: =+R33/R22 -> 0.079695746 | S52: =+S33/S22 -> 0.14865902 | T52: =+T33/T22 -> -0.027249528 | U52: =+U33/U22 -> 0.057890078 | V52: =+V33/V22 -> 0.15999533 | ... AY52: =+AY33/AY22 -> 0.23459981
B53: GSe Ebitda (pre AASB16 & AASB2) margin | L53: =+L36/L22 -> 0.080050017 | O53: =+O36/O22 -> 0.070164829 | P53: =+P36/P22 -> 0.098876997 | Q53: =+Q36/Q22 -> 0.063875898 | R53: =+R36/R22 -> 0.080943503 | S53: =+S36/S22 -> 0.10441627 | T53: =+T36/T22 -> 0.10858094 | U53: =+U36/U22 -> 0.10615381 | V53: =+V36/V22 -> 0.11453132 | ... AY53: =+AY36/AY22 -> 0.19337757
B55: Rent / avg. stores | O55: =O29/AVERAGE(O40+O45,L40+L45) -> 0.21333333 | P55: =P29/AVERAGE(P40+P45,O40+O45) -> 0.13225806 | Q55: =Q29/AVERAGE(Q40+Q45,P40+P45) -> 0.13283582 | R55: =R29/AVERAGE(R40+R45,O40+O45) -> 0.27142857 | S55: =S29/AVERAGE(S40+S45,R40+R45) -> 0.12873973 | T55: =T29/AVERAGE(T40+T45,S40+S45) -> 0.11 | U55: =U29/AVERAGE(U40+U45,R40+R45) -> 0.23836129 | V55: =+S55*(1+V56) -> 0.13324562 | W55: =+T55*(1+W56) -> 0.11385 | X55: =X29/AVERAGE(X40+X45,U40+U45) -> 0.24637344 | Y55: =+V55*(1+Y56) -> 0.13790921 | Z55: =+W55*(1+Z56) -> 0.11783475 | AA55: =AA29/AVERAGE(AA40+AA45,X40+X45) -> 0.2550934 | AB55: =+Y55*(1+AB56) -> 0.14273604 | AC55: =+Z55*(1+AC56) -> 0.12195897 | AD55: =AD29/AVERAGE(AD40+AD45,AA40+AA45) -> 0.26417987 | AE55: =+AB55*(1+AE56) -> 0.1477318 | AF55: =+AC55*(1+AF56) -> 0.12622753 | AG55: =AG29/AVERAGE(AG40+AG45,AD40+AD45) -> 0.27347427 | AH55: =+AE55*(1+AH56) -> 0.15290241 | AI55: =+AF55*(1+AI56) -> 0.13064549 | AJ55: =AJ29/AVERAGE(AJ40+AJ45,AG40+AG45) -> 0.28308742 | AK55: =+AH55*(1+AK56) -> 0.15825399 | AL55: =+AI55*(1+AL56) -> 0.13521809 | AM55: =AM29/AVERAGE(AM40+AM45,AJ40+AJ45) -> 0.2930319 | AN55: =+AK55*(1+AN56) -> 0.16379288 | AO55: =+AL55*(1+AO56) -> 0.13995072 | AP55: =AP29/AVERAGE(AP40+AP45,AM40+AM45) -> 0.30332037 | AQ55: =+AN55*(1+AQ56) -> 0.16952563 | AR55: =+AO55*(1+AR56) -> 0.14484899 | AS55: =AS29/AVERAGE(AS40+AS45,AP40+AP45) -> 0.31396562 | AT55: =+AQ55*(1+AT56) -> 0.17545903 | AU55: =+AR55*(1+AU56) -> 0.14991871 | AV55: =AV29/AVERAGE(AV40+AV45,AS40+AS45) -> 0.32498074 | AW55: =+AT55*(1+AW56) -> 0.1816001 | AX55: =+AU55*(1+AX56) -> 0.15516586 | AY55: =AY29/AVERAGE(AY40+AY45,AV40+AV45) -> 0.33637912
B56: Growth | R56: =+R55/O55-1 -> 0.27232143 | S56: =+S55/P55-1 -> -0.026602072 | U56: =+U55/R55-1 -> -0.12182683 | V56: 0.035 | W56: 0.035 | X56: =+X55/U55-1 -> 0.033613465 | Y56: 0.035 | Z56: 0.035 | AA56: =+AA55/X55-1 -> 0.035393273 | AB56: 0.035 | AC56: 0.035 | AD56: =+AD55/AA55-1 -> 0.035620153 | AE56: 0.035 | AF56: 0.035 | AG56: =+AG55/AD55-1 -> 0.035182092 | AH56: 0.035 | AI56: 0.035 | AJ56: =+AJ55/AG55-1 -> 0.035151926 | AK56: 0.035 | AL56: 0.035 | AM56: =+AM55/AJ55-1 -> 0.035128683 | AN56: 0.035 | AO56: 0.035 | AP56: =+AP55/AM55-1 -> 0.035110394 | AQ56: 0.035 | AR56: 0.035 | AS56: =+AS55/AP55-1 -> 0.035095746 | AT56: 0.035 | AU56: 0.035 | AV56: =+AV55/AS55-1 -> 0.035083832 | AW56: 0.035 | AX56: 0.035 | AY56: =+AY55/AV55-1 -> 0.035074012
B59: APAC segment
B60: Financials
B61: Australia corporate sales | I61: 93.346 | L61: 139.217 | M61: 100.639 | N61: =+O61-M61 -> 111.336 | O61: 211.975 | P61: 136.574 | Q61: =+R61-P61 -> 142.303 | R61: 278.877 | S61: 176.051 | T61: =+U61-S61 -> 183.671 | U61: 359.722 | V61: =+V63*V136/V138*0.95 -> 218.79368 | W61: =+W63*W136/W138*0.95 -> 225.78059 | X61: =+W61+V61 -> 444.57427 | Y61: =+Y63*Y136/Y138*0.95 -> 260.0324 | Z61: =+Z63*Z136/Z138*0.95 -> 266.31287 | AA61: =+Z61+Y61 -> 526.34527 | AB61: =+AB63*AB136/AB138*0.95 -> 304.66642 | AC61: =+AC63*AC136/AC138*0.95 -> 310.16847 | AD61: =+AC61+AB61 -> 614.83489 | AE61: =+AE63*AE136/AE138*0.95 -> 348.34199 | AF61: =+AF63*AF136/AF138*0.95 -> 352.90611 | AG61: =+AF61+AE61 -> 701.2481 | AH61: =+AH63*AH136/AH138*0.95 -> 394.58978 | AI61: =+AI63*AI136/AI138*0.95 -> 398.15235 | AJ61: =+AI61+AH61 -> 792.74213 | AK61: =+AK63*AK136/AK138*0.95 -> 443.54292 | AL61: =+AL63*AL136/AL138*0.95 -> 446.03611 | AM61: =+AL61+AK61 -> 889.57902 | AN61: =+AN63*AN136/AN138*0.95 -> 495.33953 | AO61: =+AO63*AO136/AO138*0.95 -> 496.69125 | AP61: =+AO61+AN61 -> 992.03078 | AQ61: =+AQ63*AQ136/AQ138*0.95 -> 550.12318 | AR61: =+AR63*AR136/AR138*0.95 -> 550.25703 | AS61: =+AR61+AQ61 -> 1100.3802 | AT61: =+AT63*AT136/AT138*0.95 -> 608.04328 | AU61: =+AU63*AU136/AU138*0.95 -> 606.87841 | AV61: =+AU61+AT61 -> 1214.9217 | AW61: =+AW63*AW136/AW138*0.95 -> 669.25543 | AX61: =+AX63*AX136/AX138*0.95 -> 666.70645 | AY61: =+AX61+AW61 -> 1335.9619
B62: Australia franchise sales | L62: =L63-L61 -> 396.183 | M62: =M63-M61 -> 234.261 | N62: =N63-N61 -> 256.664 | O62: =O63-O61 -> 490.925 | P62: =P63-P61 -> 302.026 | Q62: =Q63-Q61 -> 313.697 | R62: =R63-R61 -> 615.723 | S62: =S63-S61 -> 362.189 | ... U62: =U63-U61 -> 734.878 | V62: =+V63-V61 -> 413.89463 | W62: =+W63-W61 -> 423.32263 | X62: =+W62+V62 -> 837.21726 | Y62: =+Y63-Y61 -> 483.70726 | Z62: =+Z63-Z61 -> 491.91125 | AA62: =+Z62+Y62 -> 975.61851 | AB62: =+AB63-AB61 -> 559.20517 | AC62: =+AC63-AC61 -> 566.06095 | AD62: =+AC62+AB62 -> 1125.2661 | AE62: =+AE63-AE61 -> 632.44119 | AF62: =+AF63-AF61 -> 637.70753 | AG62: =+AF62+AE62 -> 1270.1487 | AH62: =+AH63-AH61 -> 709.95392 | AI62: =+AI63-AI61 -> 713.52349 | AJ62: =+AI62+AH62 -> 1423.4774 | AK62: =+AK63-AK61 -> 791.96152 | AL62: =+AL63-AL61 -> 793.72025 | AM62: =+AL62+AK62 -> 1585.6818 | AN62: =+AN63-AN61 -> 878.69068 | AO62: =+AO63-AO61 -> 878.5177 | AP62: =+AO62+AN62 -> 1757.2084 | AQ62: =+AQ63-AQ61 -> 970.37733 | AR62: =+AR63-AR61 -> 968.14476 | AS62: =+AR62+AQ62 -> 1938.5221 | AT62: =+AT63-AT61 -> 1067.2672 | AU62: =+AU63-AU61 -> 1062.84 | AV62: =+AU62+AT62 -> 2130.1072 | AW62: =+AW63-AW61 -> 1169.6164 | AX62: =+AX63-AX61 -> 1162.852 | AY62: =+AX62+AW62 -> 2332.4684
