Workbook
Name africa: 0
Name africaCountries: #REF!
Name allRegions: #REF!
Name americaRegion: #REF!
Name americas: 0
Name americasStates: #REF!
Name AppVersion: "GEG-1.0"
Name asiaPacific: 1
Name asiaPacificExJapan: 1
Name asiaPacificExJapanCountries: #REF!
Name asiaPacificRegion: #REF!
Name asiaPacificStates: #REF!
Name ASSNet: CFS!ASSNet
Name ASSNet: Content!ASSNet
Name ASSNet: Drivers!ASSNet
Name ASSNet: 'P&L'!ASSNet
Name ASSNet: Summary!ASSNet
Name ASSNet: CFS!ASSNet
Name ASSOPS: CFS!ASSOPS
Name ASSOPS: Content!ASSOPS
Name ASSOPS: Drivers!ASSOPS
Name ASSOPS: 'P&L'!ASSOPS
Name ASSOPS: Summary!ASSOPS
Name ASSOPS: CFS!ASSOPS
Name ASX: CFS!ASX
Name ASX: Content!ASX
Name ASX: Drivers!ASX
Name ASX: 'P&L'!ASX
Name ASX: Summary!ASX
Name ASX: CFS!ASX
Name australasia: 1
Name BaseYear: "2005"
Name BRICS: 0
Name CapTO: OFFSET('P&L'!_1088__FDSAUDITLINK__,6,0)
Name CapTO: OFFSET(Drivers!XRange2,6,0)
Name CapTO: OFFSET([0]!_1089__FDSAUDITLINK__,6,0)
Name CapTO: OFFSET([0]!XRange2,6,0)
Name CapTO: OFFSET(CFS!_109__FDSAUDITLINK__,6,0)
Name CashTax: OFFSET('P&L'!_1088__FDSAUDITLINK__,7,0)
Name CashTax: OFFSET(Drivers!XRange2,7,0)
Name CashTax: OFFSET([0]!_1089__FDSAUDITLINK__,7,0)
Name CashTax: OFFSET([0]!XRange2,7,0)
Name CashTax: OFFSET(CFS!_109__FDSAUDITLINK__,7,0)
Name centralEasternEurope: 0
Name centralEasternEuropeCountries: #REF!
Name china: 0
Name Consol: CFS!Consol
Name Consol: Content!Consol
Name Consol: Drivers!Consol
Name Consol: 'P&L'!Consol
Name Consol: Summary!Consol
Name Consol: CFS!Consol
Name consumerDemandExposure: #REF!
Name consumersExposure: 0.95
Name countryList: "Country Mapping"
Name DB: "WIREAUPROD"
Name developedEuropeExUK: 0
Name developedEuropeExUKCountries: #REF!
Name DocType: Word
Name DocType: Word

Sheet CircularReferenceAlert
B2: This workbook contains formulas which intentionally use circular reference calculation. These calculations can be resolved as intended by the originating analyst by applying the following settings in the File >> Options >> Formulas:
B5: 1) Select the Enable iterative calculation check box
B6: 2) Set Maximum Iterations = 100
B7: 3) Set Maximum Change = 0.001
B9: Failure to apply these settings can result in incorrect calculation or unexpected termination of your Microsoft Excel session.

Sheet ImportantDisclosures
A2: 1 Austin Road West
A3: Kowloon
A4: Hong Kong
A5: Tel: +852 2848 5200
A7: Authors: Melinda Baxter,Mac Ross
A8: Date: 17 Feb 2026
A10: Ticker: JBH.AX
A11: Stock Rating: Underweight
A12: Industry: Australia Consumer
A13: Industry View: In-Line
A14: Price as of 17 Feb 2026: 88.58
A15: Target Price: 75.40
... A127: Equal-weight and Not-Rated to hold and Underweight to sell recommendations, respectively.
B129: Coverage Universe | D129: Investment Banking Clients (IBC) | G129: Other Material Investment Services Clients (MISC)
A130: Stock Rating Category | B130: Count | C130: % of Total | D130: Count | E130: % of Total IBC | F130: % of Rating Category | G130: Count | H130: % of Total Other MISC
A131: Overweight/Buy | B131: 1520 | C131: 0.41 | D131: 425 | E131: 0.48 | F131: 0.28 | G131: 685 | H131: 0.42
A132: Equal-weight/Hold | B132: 1579 | C132: 0.43 | D132: 375 | E132: 0.42 | F132: 0.24 | G132: 713 | H132: 0.44
A133: Not-Rated/Hold | B133: 4 | C133: 0 | D133: 1 | E133: 0 | F133: 0.25 | G133: 1 | H133: 0
A134: Underweight/Sell | B134: 592 | C134: 0.16 | D134: 89 | E134: 0.1 | F134: 0.15 | G134: 232 | H134: 0.14
A135: Total | B135: 3695 | D135: 890 | G135: 1631
A137: Data include common stock and ADRs currently assigned ratings. Investment Banking Clients are companies
A138: from whom Morgan Stanley received investment banking compensation in the last 12 months. Due to rounding
A139: off of decimals, the percentages provided in the "% of total" column may not add up to exactly 100
A140: percent.
A142: Analyst Stock Ratings
A144: Overweight (O). The stock's total return is expected to exceed the average total return of the analyst's
A145: industry (or industry team's) coverage universe, on a risk-adjusted basis, over the next 12-18 months.
A147: Equal-weight (E). The stock's total return is expected to be in line with the average total return of
A148: the analyst's industry (or industry team's) coverage universe, on a risk-adjusted basis, over the next
A149: 12-18 months.
A151: Not-Rated (NR). Currently the analyst does not have adequate conviction about the stock's total return
A152: relative to the average total return of the analyst's industry (or industry team's) coverage universe,
... A433: © Copyright 2026 Morgan Stanley

Sheet Content
B1: JBH Model | C1: Australian Consumer Team
C4: Melinda Baxter | D4: +61 2 97701176
C5: melinda.baxter@morganstanley.com
C7: Mac Ross | D7: +61 2 9770 1579
C8: mac.ross@morganstanley.com
C10: Julia de Sterke | D10: +61 2 9770 1658
C11: julia.de.sterke@morganstanley.com

Sheet Summary
D1: FY13 | E1: FY14 | F1: FY15 | G1: FY16 | H1: FY17 | I1: FY18 | J1: FY19 | K1: FY20 | L1: FY21 | M1: FY22 | N1: FY23 | O1: FY24 | P1: FY25 | Q1: FY26e | R1: FY27e | S1: FY28e | W1: FY13 | X1: FY14 | Y1: FY15 | Z1: FY16 | AA1: FY17 | AB1: FY18 | AC1: FY19 | AD1: FY20 | AE1: FY21 | AF1: FY22 | AG1: FY23 | AH1: FY24 | AI1: FY25 | AJ1: FY26e | AK1: FY27e | AL1: FY28e
B4: Financial Summary | M4: Last | N4: 88.1 | O4: PT | P4: 75.4 | U4: Diff to PT | AD4: =P4/N4-1 -> -0.14415437
B7: P&L | D7: 2013a | E7: 2014a | F7: 2015a | G7: 2016a | H7: 2017a | I7: 2018a | J7: 2019a | K7: 2020a | L7: 2021a | M7: 2022a | N7: 2023a | O7: 2024a | P7: 2025a | Q7: 2026e | R7: 2027e | S7: 2028e | U7: Balance Sheet | W7: =+D7 -> 2013a | X7: =+E7 -> 2014a | Y7: =+F7 -> 2015a | Z7: =+G7 -> 2016a | AA7: =+H7 -> 2017a | AB7: =+I7 -> 2018a | AC7: =+J7 -> 2019a | AD7: =+K7 -> 2020a | ... AI7: =+P7 -> 2025a | AJ7: 2026 | AK7: 2027e | AL7: 2028e
A8: JBH_Sales | B8: Revenue | C8: A$m | D8: =VLOOKUP($A$8,'P&L'!$1:$1048576,MATCH(D1,'P&L'!$4:$4,FALSE),FALSE) -> 3308.4 | E8: =VLOOKUP($A$8,'P&L'!1:1048576,MATCH(E1,'P&L'!4:4,FALSE),FALSE) -> 3483.775 | F8: =VLOOKUP($A$8,'P&L'!1:1048576,MATCH(F1,'P&L'!4:4,FALSE),FALSE) -> 3652.136 | G8: =VLOOKUP($A$8,'P&L'!1:1048576,MATCH(G1,'P&L'!4:4,FALSE),FALSE) -> 3954.467 | H8: =VLOOKUP($A$8,'P&L'!1:1048576,MATCH(H1,'P&L'!4:4,FALSE),FALSE) -> 5628 | I8: =VLOOKUP($A$8,'P&L'!1:1048576,MATCH(I1,'P&L'!4:4,FALSE),FALSE) -> 6854.3 | J8: =VLOOKUP($A$8,'P&L'!1:1048576,MATCH(J1,'P&L'!4:4,FALSE),FALSE) -> 7095.3 | K8: =VLOOKUP($A$8,'P&L'!1:1048576,MATCH(K1,'P&L'!4:4,FALSE),FALSE) -> 7918.9 | L8: =VLOOKUP($A$8,'P&L'!1:1048576,MATCH(L1,'P&L'!4:4,FALSE),FALSE) -> 8916.1 | ... S8: =VLOOKUP($A$8,'P&L'!1:1048576,MATCH(S1,'P&L'!4:4,FALSE),FALSE) -> 12107.395 | U8: Current assets | V8: A$m | W8: =VLOOKUP($AM$8,BS!1:1048576,MATCH(1:1,BS!4:4,FALSE),FALSE) -> 563.652 | X8: =VLOOKUP($AM$8,BS!1:1048576,MATCH(1:1,BS!4:4,FALSE),FALSE) -> 578.147 | Y8: =VLOOKUP($AM$8,BS!1:1048576,MATCH(1:1,BS!4:4,FALSE),FALSE) -> 616.898 | Z8: =VLOOKUP($AM$8,BS!1:1048576,MATCH(1:1,BS!4:4,FALSE),FALSE) -> 702.518 | AA8: =VLOOKUP($AM$8,BS!1:1048576,MATCH(1:1,BS!4:4,FALSE),FALSE) -> 1170.7 | AB8: =VLOOKUP($AM$8,BS!1:1048576,MATCH(1:1,BS!4:4,FALSE),FALSE) -> 1210.5 | AC8: =VLOOKUP($AM$8,BS!1:1048576,MATCH(1:1,BS!4:4,FALSE),FALSE) -> 1294.9 | AD8: =VLOOKUP($AM$8,BS!1:1048576,MATCH(1:1,BS!4:4,FALSE),FALSE) -> 1245.8 | ... AL8: =VLOOKUP($AM$8,BS!1:1048576,MATCH(1:1,BS!4:4,FALSE),FALSE) -> 2137.6458 | AM8: CA
A9: JBH_Sales_AUS | B9: JBH - Aus | C9: A$m | D9: =VLOOKUP($A$9,Drivers!$1:$1048576,MATCH(D1,Drivers!$2:$2,FALSE),FALSE) -> 3140.817 | E9: =VLOOKUP($A$9,Drivers!$1:$1048576,MATCH(E1,Drivers!$2:$2,FALSE),FALSE) -> 3292.848 | F9: =VLOOKUP($A$9,Drivers!$1:$1048576,MATCH(F1,Drivers!$2:$2,FALSE),FALSE) -> 3456.016 | G9: =VLOOKUP($A$9,Drivers!$1:$1048576,MATCH(G1,Drivers!$2:$2,FALSE),FALSE) -> 3739.358 | H9: =VLOOKUP($A$9,Drivers!$1:$1048576,MATCH(H1,Drivers!$2:$2,FALSE),FALSE) -> 4148.6 | I9: =VLOOKUP($A$9,Drivers!$1:$1048576,MATCH(I1,Drivers!$2:$2,FALSE),FALSE) -> 4539.7 | J9: =VLOOKUP($A$9,Drivers!$1:$1048576,MATCH(J1,Drivers!$2:$2,FALSE),FALSE) -> 4726 | K9: =VLOOKUP($A$9,Drivers!$1:$1048576,MATCH(K1,Drivers!$2:$2,FALSE),FALSE) -> 5318.9 | ... S9: =VLOOKUP($A$9,Drivers!$1:$1048576,MATCH(S1,Drivers!$2:$2,FALSE),FALSE) -> 8157.1784 | U9: Net plant & equipment | V9: A$m | W9: =VLOOKUP($AM$9,BS!1:1048576,MATCH(1:1,BS!4:4,FALSE),FALSE) -> 181.098 | X9: =VLOOKUP($AM$9,BS!1:1048576,MATCH(1:1,BS!4:4,FALSE),FALSE) -> 181.564 | Y9: =VLOOKUP($AM$9,BS!1:1048576,MATCH(1:1,BS!4:4,FALSE),FALSE) -> 176.208 | Z9: =VLOOKUP($AM$9,BS!1:1048576,MATCH(1:1,BS!4:4,FALSE),FALSE) -> 183.57 | AA9: =VLOOKUP($AM$9,BS!1:1048576,MATCH(1:1,BS!4:4,FALSE),FALSE) -> 208.2 | AB9: =VLOOKUP($AM$9,BS!1:1048576,MATCH(1:1,BS!4:4,FALSE),FALSE) -> 198 | AC9: =VLOOKUP($AM$9,BS!1:1048576,MATCH(1:1,BS!4:4,FALSE),FALSE) -> 191.5 | AD9: =VLOOKUP($AM$9,BS!1:1048576,MATCH(1:1,BS!4:4,FALSE),FALSE) -> 172.3 | ... AL9: =VLOOKUP($AM$9,BS!1:1048576,MATCH(1:1,BS!4:4,FALSE),FALSE) -> 279.29574 | AM9: PPE
A10: JBH_Sales_NZ_AUD | B10: JBH - NZ (A$m) | C10: A$m | D10: =VLOOKUP($A$10,Drivers!$1:$1048576,MATCH(D1,Drivers!$2:$2,FALSE),FALSE) -> 167.583 | E10: =VLOOKUP($A$10,Drivers!$1:$1048576,MATCH(E1,Drivers!$2:$2,FALSE),FALSE) -> 190.927 | F10: =VLOOKUP($A$10,Drivers!$1:$1048576,MATCH(F1,Drivers!$2:$2,FALSE),FALSE) -> 196.12 | G10: =VLOOKUP($A$10,Drivers!$1:$1048576,MATCH(G1,Drivers!$2:$2,FALSE),FALSE) -> 215.109 | H10: =VLOOKUP($A$10,Drivers!$1:$1048576,MATCH(H1,Drivers!$2:$2,FALSE),FALSE) -> 221 | I10: =VLOOKUP($A$10,Drivers!$1:$1048576,MATCH(I1,Drivers!$2:$2,FALSE),FALSE) -> 213.3 | J10: =VLOOKUP($A$10,Drivers!$1:$1048576,MATCH(J1,Drivers!$2:$2,FALSE),FALSE) -> 221.4 | K10: =VLOOKUP($A$10,Drivers!$1:$1048576,MATCH(K1,Drivers!$2:$2,FALSE),FALSE) -> 211.2 | ... S10: =VLOOKUP($A$10,Drivers!$1:$1048576,MATCH(S1,Drivers!$2:$2,FALSE),FALSE) -> 500.40116 | U10: Net intangibles | V10: A$m | W10: =VLOOKUP($AM$10,BS!1:1048576,MATCH(1:1,BS!4:4,FALSE),FALSE) -> 83.712 | X10: =VLOOKUP($AM$10,BS!1:1048576,MATCH(1:1,BS!4:4,FALSE),FALSE) -> 85.218 | Y10: =VLOOKUP($AM$10,BS!1:1048576,MATCH(1:1,BS!4:4,FALSE),FALSE) -> 84.541 | Z10: =VLOOKUP($AM$10,BS!1:1048576,MATCH(1:1,BS!4:4,FALSE),FALSE) -> 85.59 | AA10: =VLOOKUP($AM$10,BS!1:1048576,MATCH(1:1,BS!4:4,FALSE),FALSE) -> 1026.6 | AB10: =VLOOKUP($AM$10,BS!1:1048576,MATCH(1:1,BS!4:4,FALSE),FALSE) -> 1037.3 | AC10: =VLOOKUP($AM$10,BS!1:1048576,MATCH(1:1,BS!4:4,FALSE),FALSE) -> 1037.3 | AD10: =VLOOKUP($AM$10,BS!1:1048576,MATCH(1:1,BS!4:4,FALSE),FALSE) -> 1031.4 | ... AL10: =VLOOKUP($AM$10,BS!1:1048576,MATCH(1:1,BS!4:4,FALSE),FALSE) -> 1080.7 | AM10: INTANG
A11: TGG_SEG_SALES | B11: The Good Guys | C11: A$m | H11: =VLOOKUP($A$11,Drivers!$1:$1048576,MATCH(H1,Drivers!$2:$2,FALSE),FALSE) -> 1258.4 | I11: =VLOOKUP($A$11,Drivers!$1:$1048576,MATCH(I1,Drivers!$2:$2,FALSE),FALSE) -> 2101.3 | J11: =VLOOKUP($A$11,Drivers!$1:$1048576,MATCH(J1,Drivers!$2:$2,FALSE),FALSE) -> 2147.9 | K11: =VLOOKUP($A$11,Drivers!$1:$1048576,MATCH(K1,Drivers!$2:$2,FALSE),FALSE) -> 2388.8 | L11: =VLOOKUP($A$11,Drivers!$1:$1048576,MATCH(L1,Drivers!$2:$2,FALSE),FALSE) -> 2715.7 | M11: =VLOOKUP($A$11,Drivers!$1:$1048576,MATCH(M1,Drivers!$2:$2,FALSE),FALSE) -> 2789.4 | N11: =VLOOKUP($A$11,Drivers!$1:$1048576,MATCH(N1,Drivers!$2:$2,FALSE),FALSE) -> 2813 | O11: =VLOOKUP($A$11,Drivers!$1:$1048576,MATCH(O1,Drivers!$2:$2,FALSE),FALSE) -> 2679.1 | ... S11: =VLOOKUP($A$11,Drivers!$1:$1048576,MATCH(S1,Drivers!$2:$2,FALSE),FALSE) -> 3157.1451 | U11: Other non current assets | V11: A$m | W11: =W12-SUM(W8:W10) -> 14.842 | X11: =X12-SUM(X8:X10) -> 14.912 | Y11: =Y12-SUM(Y8:Y10) -> 17.366 | Z11: =Z12-SUM(Z8:Z10) -> 20.703 | AA11: =AA12-SUM(AA8:AA10) -> 46.8 | AB11: =AB12-SUM(AB8:AB10) -> 45.9 | AC11: =AC12-SUM(AC8:AC10) -> 43.5 | AD11: =AD12-SUM(AD8:AD10) -> 702.8 | ... AL11: =AL12-SUM(AL8:AL10) -> 824.9785
A12: EBITDA | B12: EBITDA | C12: A$m | D12: =VLOOKUP($A$12,'P&L'!1:1048576,MATCH(D1,'P&L'!4:4,FALSE),FALSE) -> 210.985 | E12: =VLOOKUP($A$12,'P&L'!1:1048576,MATCH(E1,'P&L'!4:4,FALSE),FALSE) -> 226.65 | F12: =VLOOKUP($A$12,'P&L'!1:1048576,MATCH(F1,'P&L'!4:4,FALSE),FALSE) -> 240.031 | G12: =VLOOKUP($A$12,'P&L'!1:1048576,MATCH(G1,'P&L'!4:4,FALSE),FALSE) -> 262.076 | H12: =VLOOKUP($A$12,'P&L'!1:1048576,MATCH(H1,'P&L'!4:4,FALSE),FALSE) -> 360.3 | I12: =VLOOKUP($A$12,'P&L'!1:1048576,MATCH(I1,'P&L'!4:4,FALSE),FALSE) -> 411.7 | J12: =VLOOKUP($A$12,'P&L'!1:1048576,MATCH(J1,'P&L'!4:4,FALSE),FALSE) -> 429.1 | K12: =VLOOKUP($A$12,'P&L'!1:1048576,MATCH(K1,'P&L'!4:4,FALSE),FALSE) -> 717.9 | ... S12: =VLOOKUP($A$12,'P&L'!1:1048576,MATCH(S1,'P&L'!4:4,FALSE),FALSE) -> 1088.2741 | U12: Total assets | V12: A$m | W12: =VLOOKUP($AM$12,BS!1:1048576,MATCH(1:1,BS!4:4,FALSE),FALSE) -> 843.304 | X12: =VLOOKUP($AM$12,BS!1:1048576,MATCH(1:1,BS!4:4,FALSE),FALSE) -> 859.841 | Y12: =VLOOKUP($AM$12,BS!1:1048576,MATCH(1:1,BS!4:4,FALSE),FALSE) -> 895.013 | Z12: =VLOOKUP($AM$12,BS!1:1048576,MATCH(1:1,BS!4:4,FALSE),FALSE) -> 992.381 | AA12: =VLOOKUP($AM$12,BS!1:1048576,MATCH(1:1,BS!4:4,FALSE),FALSE) -> 2452.3 | AB12: =VLOOKUP($AM$12,BS!1:1048576,MATCH(1:1,BS!4:4,FALSE),FALSE) -> 2491.7 | AC12: =VLOOKUP($AM$12,BS!1:1048576,MATCH(1:1,BS!4:4,FALSE),FALSE) -> 2567.2 | AD12: =VLOOKUP($AM$12,BS!1:1048576,MATCH(1:1,BS!4:4,FALSE),FALSE) -> 3152.3 | ... AL12: =VLOOKUP($AM$12,BS!1:1048576,MATCH(1:1,BS!4:4,FALSE),FALSE) -> 4322.6201 | AM12: TA
A13: TOTAL_D&A | B13: D&A | C13: A$m | D13: =VLOOKUP($A$13,'P&L'!1:1048576,MATCH(D1,'P&L'!4:4,FALSE),FALSE) -> -33.232 | E13: =VLOOKUP($A$13,'P&L'!1:1048576,MATCH(E1,'P&L'!4:4,FALSE),FALSE) -> -35.53 | F13: =VLOOKUP($A$13,'P&L'!1:1048576,MATCH(F1,'P&L'!4:4,FALSE),FALSE) -> -39.124 | G13: =VLOOKUP($A$13,'P&L'!1:1048576,MATCH(G1,'P&L'!4:4,FALSE),FALSE) -> -40.901 | H13: =VLOOKUP($A$13,'P&L'!1:1048576,MATCH(H1,'P&L'!4:4,FALSE),FALSE) -> -53.9 | I13: =VLOOKUP($A$13,'P&L'!1:1048576,MATCH(I1,'P&L'!4:4,FALSE),FALSE) -> -61.1 | J13: =VLOOKUP($A$13,'P&L'!1:1048576,MATCH(J1,'P&L'!4:4,FALSE),FALSE) -> -56.2 | K13: =VLOOKUP($A$13,'P&L'!1:1048576,MATCH(K1,'P&L'!4:4,FALSE),FALSE) -> -229.3 | ... S13: =VLOOKUP($A$13,'P&L'!1:1048576,MATCH(S1,'P&L'!4:4,FALSE),FALSE) -> -282.25135 | U13: Current liabilities | V13: A$m | W13: =VLOOKUP($AM$13,BS!1:1048576,MATCH(Summary!1:1,BS!4:4,FALSE),FALSE) -> 442.379 | X13: =VLOOKUP($AM$13,BS!1:1048576,MATCH(Summary!1:1,BS!4:4,FALSE),FALSE) -> 352.193 | Y13: =VLOOKUP($AM$13,BS!1:1048576,MATCH(Summary!1:1,BS!4:4,FALSE),FALSE) -> 380.336 | Z13: =VLOOKUP($AM$13,BS!1:1048576,MATCH(Summary!1:1,BS!4:4,FALSE),FALSE) -> 446.833 | AA13: =VLOOKUP($AM$13,BS!1:1048576,MATCH(Summary!1:1,BS!4:4,FALSE),FALSE) -> 885.8 | AB13: =VLOOKUP($AM$13,BS!1:1048576,MATCH(Summary!1:1,BS!4:4,FALSE),FALSE) -> 917.2 | AC13: =VLOOKUP($AM$13,BS!1:1048576,MATCH(Summary!1:1,BS!4:4,FALSE),FALSE) -> 945.5 | AD13: =VLOOKUP($AM$13,BS!1:1048576,MATCH(Summary!1:1,BS!4:4,FALSE),FALSE) -> 1345.9 | ... AL13: =VLOOKUP($AM$13,BS!1:1048576,MATCH(Summary!1:1,BS!4:4,FALSE),FALSE) -> 1695.7108 | AM13: CL
A14: JBH_AUS_EBIT | B14: JBH - Aus | C14: A$m | D14: =VLOOKUP($A$14,Drivers!$1:$1048576,MATCH(D1,Drivers!$2:$2,FALSE),FALSE) -> 175.853 | E14: =VLOOKUP($A$14,Drivers!$1:$1048576,MATCH(E1,Drivers!$2:$2,FALSE),FALSE) -> 188.32 | F14: =VLOOKUP($A$14,Drivers!$1:$1048576,MATCH(F1,Drivers!$2:$2,FALSE),FALSE) -> 199.447 | G14: =VLOOKUP($A$14,Drivers!$1:$1048576,MATCH(G1,Drivers!$2:$2,FALSE),FALSE) -> 220.315 | H14: =VLOOKUP($A$14,Drivers!$1:$1048576,MATCH(H1,Drivers!$2:$2,FALSE),FALSE) -> 262.4 | I14: =VLOOKUP($A$14,Drivers!$1:$1048576,MATCH(I1,Drivers!$2:$2,FALSE),FALSE) -> 292.3 | J14: =VLOOKUP($A$14,Drivers!$1:$1048576,MATCH(J1,Drivers!$2:$2,FALSE),FALSE) -> 301.7 | K14: =VLOOKUP($A$14,Drivers!$1:$1048576,MATCH(K1,Drivers!$2:$2,FALSE),FALSE) -> 391.6 | ... S14: =VLOOKUP($A$14,Drivers!$1:$1048576,MATCH(S1,Drivers!$2:$2,FALSE),FALSE) -> 601.24959 | U14: Borrowings | V14: A$m | W14: =VLOOKUP($AM$14,BS!1:1048576,MATCH(Summary!1:1,BS!4:4,FALSE),FALSE) -> 124.331 | X14: =VLOOKUP($AM$14,BS!1:1048576,MATCH(Summary!1:1,BS!4:4,FALSE),FALSE) -> 179.653 | Y14: =VLOOKUP($AM$14,BS!1:1048576,MATCH(Summary!1:1,BS!4:4,FALSE),FALSE) -> 139.461 | Z14: =VLOOKUP($AM$14,BS!1:1048576,MATCH(Summary!1:1,BS!4:4,FALSE),FALSE) -> 109.736 | AA14: =VLOOKUP($AM$14,BS!1:1048576,MATCH(Summary!1:1,BS!4:4,FALSE),FALSE) -> 558.8 | AB14: =VLOOKUP($AM$14,BS!1:1048576,MATCH(Summary!1:1,BS!4:4,FALSE),FALSE) -> 469.4 | AC14: =VLOOKUP($AM$14,BS!1:1048576,MATCH(Summary!1:1,BS!4:4,FALSE),FALSE) -> 439.1 | AD14: =VLOOKUP($AM$14,BS!1:1048576,MATCH(Summary!1:1,BS!4:4,FALSE),FALSE) -> 0 | ... AL14: =VLOOKUP($AM$14,BS!1:1048576,MATCH(Summary!1:1,BS!4:4,FALSE),FALSE) -> 0 | AM14: BORR
A15: JBH_NZ_EBIT | B15: JBH - NZ (A$m) | C15: A$m | D15: =VLOOKUP($A$15,Drivers!$1:$1048576,MATCH(D1,Drivers!$2:$2,FALSE),FALSE) -> 1.9 | E15: =VLOOKUP($A$15,Drivers!$1:$1048576,MATCH(E1,Drivers!$2:$2,FALSE),FALSE) -> 2.8 | F15: =VLOOKUP($A$15,Drivers!$1:$1048576,MATCH(F1,Drivers!$2:$2,FALSE),FALSE) -> 1.46 | G15: =VLOOKUP($A$15,Drivers!$1:$1048576,MATCH(G1,Drivers!$2:$2,FALSE),FALSE) -> 0.9 | H15: =VLOOKUP($A$15,Drivers!$1:$1048576,MATCH(H1,Drivers!$2:$2,FALSE),FALSE) -> -2.5 | I15: =VLOOKUP($A$15,Drivers!$1:$1048576,MATCH(I1,Drivers!$2:$2,FALSE),FALSE) -> -2.6 | J15: =VLOOKUP($A$15,Drivers!$1:$1048576,MATCH(J1,Drivers!$2:$2,FALSE),FALSE) -> -1.7 | K15: =VLOOKUP($A$15,Drivers!$1:$1048576,MATCH(K1,Drivers!$2:$2,FALSE),FALSE) -> -1.4 | ... S15: =VLOOKUP($A$15,Drivers!$1:$1048576,MATCH(S1,Drivers!$2:$2,FALSE),FALSE) -> 8.6730217 | U15: Other non current liabilities | V15: A$m | W15: =W16-SUM(W13:W14) -> 32.766 | X15: =X16-SUM(X13:X14) -> 33.362 | Y15: =Y16-SUM(Y13:Y14) -> 31.737 | Z15: =Z16-SUM(Z13:Z14) -> 31.11 | AA15: =AA16-SUM(AA13:AA14) -> 154.2 | AB15: =AB16-SUM(AB13:AB14) -> 157.5 | AC15: =AC16-SUM(AC13:AC14) -> 138.5 | AD15: =AD16-SUM(AD13:AD14) -> 700.7 | ... AL15: =AL16-SUM(AL13:AL14) -> 718.1
A16: TGG_SEG_EBIT | B16: The Good Guys | C16: A$m | H16: =VLOOKUP($A$16,Drivers!$1:$1048576,MATCH(H1,Drivers!$2:$2,FALSE),FALSE) -> 46.4 | I16: =VLOOKUP($A$16,Drivers!$1:$1048576,MATCH(I1,Drivers!$2:$2,FALSE),FALSE) -> 60.9 | J16: =VLOOKUP($A$16,Drivers!$1:$1048576,MATCH(J1,Drivers!$2:$2,FALSE),FALSE) -> 72.9 | K16: =VLOOKUP($A$16,Drivers!$1:$1048576,MATCH(K1,Drivers!$2:$2,FALSE),FALSE) -> 112.8 | L16: =VLOOKUP($A$16,Drivers!$1:$1048576,MATCH(L1,Drivers!$2:$2,FALSE),FALSE) -> 214.7 | M16: =VLOOKUP($A$16,Drivers!$1:$1048576,MATCH(M1,Drivers!$2:$2,FALSE),FALSE) -> 241.4 | N16: =VLOOKUP($A$16,Drivers!$1:$1048576,MATCH(N1,Drivers!$2:$2,FALSE),FALSE) -> 213 | O16: =VLOOKUP($A$16,Drivers!$1:$1048576,MATCH(O1,Drivers!$2:$2,FALSE),FALSE) -> 158.1 | ... S16: =VLOOKUP($A$16,Drivers!$1:$1048576,MATCH(S1,Drivers!$2:$2,FALSE),FALSE) -> 192.66406 | U16: Total liabilities | V16: A$m | W16: =VLOOKUP($AM$16,BS!1:1048576,MATCH(Summary!1:1,BS!4:4,FALSE),FALSE) -> 599.476 | X16: =VLOOKUP($AM$16,BS!1:1048576,MATCH(Summary!1:1,BS!4:4,FALSE),FALSE) -> 565.208 | Y16: =VLOOKUP($AM$16,BS!1:1048576,MATCH(Summary!1:1,BS!4:4,FALSE),FALSE) -> 551.534 | Z16: =VLOOKUP($AM$16,BS!1:1048576,MATCH(Summary!1:1,BS!4:4,FALSE),FALSE) -> 587.679 | AA16: =VLOOKUP($AM$16,BS!1:1048576,MATCH(Summary!1:1,BS!4:4,FALSE),FALSE) -> 1598.8 | AB16: =VLOOKUP($AM$16,BS!1:1048576,MATCH(Summary!1:1,BS!4:4,FALSE),FALSE) -> 1544.1 | AC16: =VLOOKUP($AM$16,BS!1:1048576,MATCH(Summary!1:1,BS!4:4,FALSE),FALSE) -> 1523.1 | AD16: =VLOOKUP($AM$16,BS!1:1048576,MATCH(Summary!1:1,BS!4:4,FALSE),FALSE) -> 2046.6 | ... AL16: =VLOOKUP($AM$16,BS!1:1048576,MATCH(Summary!1:1,BS!4:4,FALSE),FALSE) -> 2413.8108 | AM16: TL
A17: EBIT_NORM | B17: EBIT | C17: A$m | D17: =VLOOKUP($A$17,'P&L'!1:1048576,MATCH(D1,'P&L'!4:4,FALSE),FALSE) -> 177.753 | E17: =VLOOKUP($A$17,'P&L'!1:1048576,MATCH(E1,'P&L'!4:4,FALSE),FALSE) -> 191.12 | F17: =VLOOKUP($A$17,'P&L'!1:1048576,MATCH(F1,'P&L'!4:4,FALSE),FALSE) -> 200.907 | G17: =VLOOKUP($A$17,'P&L'!1:1048576,MATCH(G1,'P&L'!4:4,FALSE),FALSE) -> 221.175 | H17: =VLOOKUP($A$17,'P&L'!1:1048576,MATCH(H1,'P&L'!4:4,FALSE),FALSE) -> 306.4 | I17: =VLOOKUP($A$17,'P&L'!1:1048576,MATCH(I1,'P&L'!4:4,FALSE),FALSE) -> 350.6 | J17: =VLOOKUP($A$17,'P&L'!1:1048576,MATCH(J1,'P&L'!4:4,FALSE),FALSE) -> 372.9 | K17: =VLOOKUP($A$17,'P&L'!1:1048576,MATCH(K1,'P&L'!4:4,FALSE),FALSE) -> 502.9 | ... S17: =VLOOKUP($A$17,'P&L'!1:1048576,MATCH(S1,'P&L'!4:4,FALSE),FALSE) -> 806.02273 | U17: Outside equity interests | V17: A$m | W17: =VLOOKUP($AM$17,BS!1:1048576,MATCH(1:1,BS!4:4,FALSE),FALSE) -> 0.483 | X17: =VLOOKUP($AM$17,BS!1:1048576,MATCH(1:1,BS!4:4,FALSE),FALSE) -> 0 | Y17: =VLOOKUP($AM$17,BS!1:1048576,MATCH(1:1,BS!4:4,FALSE),FALSE) -> 0 | Z17: =VLOOKUP($AM$17,BS!1:1048576,MATCH(1:1,BS!4:4,FALSE),FALSE) -> 0 | AA17: =VLOOKUP($AM$17,BS!1:1048576,MATCH(1:1,BS!4:4,FALSE),FALSE) -> 0 | AB17: =VLOOKUP($AM$17,BS!1:1048576,MATCH(1:1,BS!4:4,FALSE),FALSE) -> 0 | AC17: =VLOOKUP($AM$17,BS!1:1048576,MATCH(1:1,BS!4:4,FALSE),FALSE) -> 0 | AD17: =VLOOKUP($AM$17,BS!1:1048576,MATCH(1:1,BS!4:4,FALSE),FALSE) -> 0 | ... AL17: =VLOOKUP($AM$17,BS!1:1048576,MATCH(1:1,BS!4:4,FALSE),FALSE) -> 6.9518941 | AM17: NCI
A18: NET_INT | B18: Net Interest Expense | C18: A$m | D18: =VLOOKUP($A$18,'P&L'!1:1048576,MATCH(D1,'P&L'!4:4,FALSE),FALSE) -> -9.701 | E18: =VLOOKUP($A$18,'P&L'!1:1048576,MATCH(E1,'P&L'!4:4,FALSE),FALSE) -> -8.443 | F18: =VLOOKUP($A$18,'P&L'!1:1048576,MATCH(F1,'P&L'!4:4,FALSE),FALSE) -> -5.375 | G18: =VLOOKUP($A$18,'P&L'!1:1048576,MATCH(G1,'P&L'!4:4,FALSE),FALSE) -> -3.336 | H18: =VLOOKUP($A$18,'P&L'!1:1048576,MATCH(H1,'P&L'!4:4,FALSE),FALSE) -> -9 | I18: =VLOOKUP($A$18,'P&L'!1:1048576,MATCH(I1,'P&L'!4:4,FALSE),FALSE) -> -16.1 | J18: =VLOOKUP($A$18,'P&L'!1:1048576,MATCH(J1,'P&L'!4:4,FALSE),FALSE) -> -13.6 | K18: =VLOOKUP($A$18,'P&L'!1:1048576,MATCH(K1,'P&L'!4:4,FALSE),FALSE) -> -35.3 | ... S18: =VLOOKUP($A$18,'P&L'!1:1048576,MATCH(S1,'P&L'!4:4,FALSE),FALSE) -> -37.071549 | U18: Shareholders’ funds | V18: A$m | W18: =W12-W16-W17 -> 243.345 | X18: =X12-X16-X17 -> 294.633 | Y18: =Y12-Y16-Y17 -> 343.479 | Z18: =Z12-Z16-Z17 -> 404.702 | AA18: =AA12-AA16-AA17 -> 853.5 | AB18: =AB12-AB16-AB17 -> 947.6 | AC18: =AC12-AC16-AC17 -> 1044.1 | AD18: =AD12-AD16-AD17 -> 1105.7 | ... AL18: =AL12-AL16-AL17 -> 1901.8574
A19: PBT | B19: Profit before tax | C19: A$m | D19: =VLOOKUP($A$19,'P&L'!1:1048576,MATCH(D1,'P&L'!4:4,FALSE),FALSE) -> 168.052 | E19: =VLOOKUP($A$19,'P&L'!1:1048576,MATCH(E1,'P&L'!4:4,FALSE),FALSE) -> 182.677 | F19: =VLOOKUP($A$19,'P&L'!1:1048576,MATCH(F1,'P&L'!4:4,FALSE),FALSE) -> 195.532 | G19: =VLOOKUP($A$19,'P&L'!1:1048576,MATCH(G1,'P&L'!4:4,FALSE),FALSE) -> 217.839 | H19: =VLOOKUP($A$19,'P&L'!1:1048576,MATCH(H1,'P&L'!4:4,FALSE),FALSE) -> 259.2 | I19: =VLOOKUP($A$19,'P&L'!1:1048576,MATCH(I1,'P&L'!4:4,FALSE),FALSE) -> 334.5 | J19: =VLOOKUP($A$19,'P&L'!1:1048576,MATCH(J1,'P&L'!4:4,FALSE),FALSE) -> 359.3 | K19: =VLOOKUP($A$19,'P&L'!1:1048576,MATCH(K1,'P&L'!4:4,FALSE),FALSE) -> 447.9 | ... S19: =VLOOKUP($A$19,'P&L'!1:1048576,MATCH(S1,'P&L'!4:4,FALSE),FALSE) -> 768.95118 | U19: Net debt | V19: A$m | W19: =VLOOKUP($AM$19,BS!1:1048576,MATCH(1:1,BS!4:4,FALSE),FALSE) -> 56.963 | X19: =VLOOKUP($AM$19,BS!1:1048576,MATCH(1:1,BS!4:4,FALSE),FALSE) -> 136.208 | Y19: =VLOOKUP($AM$19,BS!1:1048576,MATCH(1:1,BS!4:4,FALSE),FALSE) -> 90.33 | Z19: =VLOOKUP($AM$19,BS!1:1048576,MATCH(1:1,BS!4:4,FALSE),FALSE) -> 57.852 | AA19: =VLOOKUP($AM$19,BS!1:1048576,MATCH(1:1,BS!4:4,FALSE),FALSE) -> 486 | AB19: =VLOOKUP($AM$19,BS!1:1048576,MATCH(1:1,BS!4:4,FALSE),FALSE) -> 397.4 | AC19: =VLOOKUP($AM$19,BS!1:1048576,MATCH(1:1,BS!4:4,FALSE),FALSE) -> 319.9 | AD19: =VLOOKUP($AM$19,BS!1:1048576,MATCH(1:1,BS!4:4,FALSE),FALSE) -> -251.5 | ... AL19: =VLOOKUP($AM$19,BS!1:1048576,MATCH(1:1,BS!4:4,FALSE),FALSE) -> -401.13494 | AM19: ND
A20: TAX | B20: Income Tax | C20: A$m | D20: =VLOOKUP($A$20,'P&L'!1:1048576,MATCH(D1,'P&L'!4:4,FALSE),FALSE) -> -51.42 | E20: =VLOOKUP($A$20,'P&L'!1:1048576,MATCH(E1,'P&L'!4:4,FALSE),FALSE) -> -54.23 | F20: =VLOOKUP($A$20,'P&L'!1:1048576,MATCH(F1,'P&L'!4:4,FALSE),FALSE) -> -59.021 | G20: =VLOOKUP($A$20,'P&L'!1:1048576,MATCH(G1,'P&L'!4:4,FALSE),FALSE) -> -65.658 | H20: =VLOOKUP($A$20,'P&L'!1:1048576,MATCH(H1,'P&L'!4:4,FALSE),FALSE) -> -86.8 | I20: =VLOOKUP($A$20,'P&L'!1:1048576,MATCH(I1,'P&L'!4:4,FALSE),FALSE) -> -101.3 | J20: =VLOOKUP($A$20,'P&L'!1:1048576,MATCH(J1,'P&L'!4:4,FALSE),FALSE) -> -109.5 | K20: =VLOOKUP($A$20,'P&L'!1:1048576,MATCH(K1,'P&L'!4:4,FALSE),FALSE) -> -145.7 | ... S20: =VLOOKUP($A$20,'P&L'!1:1048576,MATCH(S1,'P&L'!4:4,FALSE),FALSE) -> -231.46367 | U20: Capital employed | V20: A$m | W20: =W18+W19 -> 300.308 | X20: =X18+X19 -> 430.841 | Y20: =Y18+Y19 -> 433.809 | Z20: =Z18+Z19 -> 462.554 | AA20: =AA18+AA19 -> 1339.5 | AB20: =AB18+AB19 -> 1345 | AC20: =AC18+AC19 -> 1364 | AD20: =AD18+AD19 -> 854.2 | ... AL20: =AL18+AL19 -> 1500.7225
A21: NPAT | B21: NPAT before sig. items | C21: A$m | D21: =VLOOKUP($A$21,'P&L'!1:1048576,MATCH(D1,'P&L'!4:4,FALSE),FALSE) -> 116.383 | E21: =VLOOKUP($A$21,'P&L'!1:1048576,MATCH(E1,'P&L'!4:4,FALSE),FALSE) -> 128.359 | F21: =VLOOKUP($A$21,'P&L'!1:1048576,MATCH(F1,'P&L'!4:4,FALSE),FALSE) -> 136.511 | G21: =VLOOKUP($A$21,'P&L'!1:1048576,MATCH(G1,'P&L'!4:4,FALSE),FALSE) -> 152.181 | H21: =VLOOKUP($A$21,'P&L'!1:1048576,MATCH(H1,'P&L'!4:4,FALSE),FALSE) -> 205.12603 | I21: =VLOOKUP($A$21,'P&L'!1:1048576,MATCH(I1,'P&L'!4:4,FALSE),FALSE) -> 233.2 | J21: =VLOOKUP($A$21,'P&L'!1:1048576,MATCH(J1,'P&L'!4:4,FALSE),FALSE) -> 249.8 | K21: =VLOOKUP($A$21,'P&L'!1:1048576,MATCH(K1,'P&L'!4:4,FALSE),FALSE) -> 326.2 | ... S21: =VLOOKUP($A$21,'P&L'!1:1048576,MATCH(S1,'P&L'!4:4,FALSE),FALSE) -> 536.8862
A22: NPAT_REPORTED | B22: Reported NPAT | C22: A$m | D22: =VLOOKUP($A$22,'P&L'!1:1048576,MATCH(D1,'P&L'!4:4,FALSE),FALSE) -> 116.383 | E22: =VLOOKUP($A$22,'P&L'!1:1048576,MATCH(E1,'P&L'!4:4,FALSE),FALSE) -> 128.359 | F22: =VLOOKUP($A$22,'P&L'!1:1048576,MATCH(F1,'P&L'!4:4,FALSE),FALSE) -> 136.511 | G22: =VLOOKUP($A$22,'P&L'!1:1048576,MATCH(G1,'P&L'!4:4,FALSE),FALSE) -> 152.181 | H22: =VLOOKUP($A$22,'P&L'!1:1048576,MATCH(H1,'P&L'!4:4,FALSE),FALSE) -> 172.4 | I22: =VLOOKUP($A$22,'P&L'!1:1048576,MATCH(I1,'P&L'!4:4,FALSE),FALSE) -> 233.2 | J22: =VLOOKUP($A$22,'P&L'!1:1048576,MATCH(J1,'P&L'!4:4,FALSE),FALSE) -> 249.8 | K22: =VLOOKUP($A$22,'P&L'!1:1048576,MATCH(K1,'P&L'!4:4,FALSE),FALSE) -> 302.2 | ... S22: =VLOOKUP($A$22,'P&L'!1:1048576,MATCH(S1,'P&L'!4:4,FALSE),FALSE) -> 536.8862 | U22: Ratio Analysis | W22: =+W7 -> 2013a | X22: =+X7 -> 2014a | Y22: =+Y7 -> 2015a | Z22: =+Z7 -> 2016a | AA22: =+AA7 -> 2017a | AB22: =+AB7 -> 2018a | AC22: =+AC7 -> 2019a | AD22: =+AD7 -> 2020a | ... AI22: =+AI7 -> 2025a | AJ22: 2026e | AK22: =+AK7 -> 2027e | AL22: =+AL7 -> 2028e
A23: Normalised EPS | B23: EPS | C23: Cents | D23: =VLOOKUP($A$23,'P&L'!1:1048576,MATCH(D1,'P&L'!4:4,FALSE),FALSE) -> 117.02312 | E23: =VLOOKUP($A$23,'P&L'!1:1048576,MATCH(E1,'P&L'!4:4,FALSE),FALSE) -> 126.88586 | F23: =VLOOKUP($A$23,'P&L'!1:1048576,MATCH(F1,'P&L'!4:4,FALSE),FALSE) -> 136.46051 | G23: =VLOOKUP($A$23,'P&L'!$1:$1048576,MATCH(G1,'P&L'!4:4,FALSE),FALSE) -> 152.12471 | H23: =VLOOKUP($A$23,'P&L'!1:1048576,MATCH(H1,'P&L'!4:4,FALSE),FALSE) -> 182.01068 | I23: =VLOOKUP($A$23,'P&L'!1:1048576,MATCH(I1,'P&L'!4:4,FALSE),FALSE) -> 201.20794 | J23: =VLOOKUP($A$23,'P&L'!1:1048576,MATCH(J1,'P&L'!4:4,FALSE),FALSE) -> 215.15935 | K23: =VLOOKUP($A$23,'P&L'!1:1048576,MATCH(K1,'P&L'!4:4,FALSE),FALSE) -> 281.2069 | L23: =VLOOKUP($A$23,'P&L'!1:1048576,MATCH(L1,'P&L'!4:4,FALSE),FALSE) -> 444.55017 | M23: =VLOOKUP($A$23,'P&L'!1:1048576,MATCH(M1,'P&L'!4:4,FALSE),FALSE) -> 480.73555 | N23: =VLOOKUP($A$23,'P&L'!1:1048576,MATCH(N1,'P&L'!4:4,FALSE),FALSE) -> 477.77778 | O23: =VLOOKUP($A$23,'P&L'!1:1048576,MATCH(O1,'P&L'!4:4,FALSE),FALSE) -> 400.73059 | ... S23: =VLOOKUP($A$23,'P&L'!1:1048576,MATCH(S1,'P&L'!4:4,FALSE),FALSE) -> 489.26157 | U23: Growth (%)
A24: DPS | B24: DPS | C24: =+C23 -> Cents | D24: =VLOOKUP($A$24,'P&L'!1:1048576,MATCH(D1,'P&L'!4:4,FALSE),FALSE) -> 72 | E24: =VLOOKUP($A$24,'P&L'!1:1048576,MATCH(E1,'P&L'!4:4,FALSE),FALSE) -> 84 | F24: =VLOOKUP($A$24,'P&L'!1:1048576,MATCH(F1,'P&L'!4:4,FALSE),FALSE) -> 90 | G24: =VLOOKUP($A$24,'P&L'!1:1048576,MATCH(G1,'P&L'!4:4,FALSE),FALSE) -> 100 | H24: =VLOOKUP($A$24,'P&L'!1:1048576,MATCH(H1,'P&L'!4:4,FALSE),FALSE) -> 118 | I24: =VLOOKUP($A$24,'P&L'!1:1048576,MATCH(I1,'P&L'!4:4,FALSE),FALSE) -> 132 | J24: =VLOOKUP($A$24,'P&L'!1:1048576,MATCH(J1,'P&L'!4:4,FALSE),FALSE) -> 142 | K24: =VLOOKUP($A$24,'P&L'!1:1048576,MATCH(K1,'P&L'!4:4,FALSE),FALSE) -> 189 | ... S24: =VLOOKUP($A$24,'P&L'!1:1048576,MATCH(S1,'P&L'!4:4,FALSE),FALSE) -> 378.10969 | U24: Revenue | V24: % | X24: =(E8/D8-1)*100 -> 5.3009007 | Y24: =(F8/E8-1)*100 -> 4.8327174 | Z24: =(G8/F8-1)*100 -> 8.2781966 | AA24: =(H8/G8-1)*100 -> 42.320065 | AB24: =(I8/H8-1)*100 -> 21.789268 | AC24: =(J8/I8-1)*100 -> 3.516041 | AD24: =(K8/J8-1)*100 -> 11.607684 | AE24: =(L8/K8-1)*100 -> 12.592658 | ... AL24: =(S8/R8-1)*100 -> 4.2020917
U25: EBIT | V25: % | X25: =(E17/D17-1)*100 -> 7.5199856 | Y25: =(F17/E17-1)*100 -> 5.1208665 | Z25: =(G17/F17-1)*100 -> 10.08825 | AA25: =(H17/G17-1)*100 -> 38.532836 | AB25: =(I17/H17-1)*100 -> 14.425587 | AC25: =(J17/I17-1)*100 -> 6.3605248 | AD25: =(K17/J17-1)*100 -> 34.861893 | AE25: =(L17/K17-1)*100 -> 47.762975 | ... AL25: =(S17/R17-1)*100 -> 4.9936418
U26: EBITDA | V26: % | X26: =(E12/D12-1)*100 -> 7.4246984 | Y26: =(F12/E12-1)*100 -> 5.9038165 | Z26: =(G12/F12-1)*100 -> 9.1842304 | AA26: =(H12/G12-1)*100 -> 37.479205 | AB26: =(I12/H12-1)*100 -> 14.26589 | AC26: =(J12/I12-1)*100 -> 4.2263784 | AD26: =(K12/J12-1)*100 -> 67.303659 | AE26: =(L12/K12-1)*100 -> 33.946232 | ... AL26: =(S12/R12-1)*100 -> 4.3448766
B27: Cash flow | D27: =+D7 -> 2013a | E27: =+E7 -> 2014a | F27: =+F7 -> 2015a | G27: =+G7 -> 2016a | H27: =+H7 -> 2017a | I27: =+I7 -> 2018a | J27: =+J7 -> 2019a | K27: =+K7 -> 2020a | ... N27: =+N7 -> 2023a | O27: 2024a | P27: 2025a | Q27: 2026e | R27: =+R7 -> 2027e | S27: =+S7 -> 2028e | U27: Normalised NPAT | V27: % | X27: =(E21/D21-1)*100 -> 10.290163 | Y27: =(F21/E21-1)*100 -> 6.3509376 | Z27: =(G21/F21-1)*100 -> 11.478928 | AA27: =(H21/G21-1)*100 -> 34.790829 | AB27: =(I21/H21-1)*100 -> 13.686205 | AC27: =(J21/I21-1)*100 -> 7.1183533 | AD27: =(K21/J21-1)*100 -> 30.584468 | AE27: =(L21/K21-1)*100 -> 57.541386 | ... AL27: =(S21/R21-1)*100 -> 5.1009225
A28: EBIT_NORM | B28: EBIT | C28: A$m | D28: =VLOOKUP($A$28,Drivers!1:1048576,MATCH(1:1,Drivers!2:2,FALSE),FALSE) -> 177.753 | E28: =VLOOKUP($A$28,Drivers!1:1048576,MATCH(1:1,Drivers!2:2,FALSE),FALSE) -> 191.12 | F28: =VLOOKUP($A$28,Drivers!1:1048576,MATCH(1:1,Drivers!2:2,FALSE),FALSE) -> 200.907 | G28: =VLOOKUP($A$28,Drivers!1:1048576,MATCH(1:1,Drivers!2:2,FALSE),FALSE) -> 221.175 | H28: =VLOOKUP($A$28,Drivers!1:1048576,MATCH(1:1,Drivers!2:2,FALSE),FALSE) -> 306.4 | I28: =VLOOKUP($A$28,Drivers!1:1048576,MATCH(1:1,Drivers!2:2,FALSE),FALSE) -> 350.6 | J28: =VLOOKUP($A$28,Drivers!1:1048576,MATCH(1:1,Drivers!2:2,FALSE),FALSE) -> 372.9 | K28: =VLOOKUP($A$28,Drivers!1:1048576,MATCH(1:1,Drivers!2:2,FALSE),FALSE) -> 502.9 | ... S28: =VLOOKUP($A$28,Drivers!1:1048576,MATCH(1:1,Drivers!2:2,FALSE),FALSE) -> 806.02273 | U28: Reported NPAT | V28: % | X28: =(E22/D22-1)*100 -> 10.290163 | Y28: =(F22/E22-1)*100 -> 6.3509376 | Z28: =(G22/F22-1)*100 -> 11.478928 | AA28: =(H22/G22-1)*100 -> 13.286153 | AB28: =(I22/H22-1)*100 -> 35.266821 | AC28: =(J22/I22-1)*100 -> 7.1183533 | AD28: =(K22/J22-1)*100 -> 20.976781 | AE28: =(L22/K22-1)*100 -> 68.596956 | ... AL28: =(S22/R22-1)*100 -> 5.1009225
A29: TOTAL_D&A | B29: D&A | C29: A$m | D29: =VLOOKUP($A$29,Drivers!1:1048576,MATCH(1:1,Drivers!2:2,FALSE),FALSE) -> 33.232 | E29: =VLOOKUP($A$29,Drivers!1:1048576,MATCH(1:1,Drivers!2:2,FALSE),FALSE) -> 35.53 | F29: =VLOOKUP($A$29,Drivers!1:1048576,MATCH(1:1,Drivers!2:2,FALSE),FALSE) -> 39.124 | G29: =VLOOKUP($A$29,Drivers!1:1048576,MATCH(1:1,Drivers!2:2,FALSE),FALSE) -> 40.901 | H29: =VLOOKUP($A$29,Drivers!1:1048576,MATCH(1:1,Drivers!2:2,FALSE),FALSE) -> 53.9 | I29: =VLOOKUP($A$29,Drivers!1:1048576,MATCH(1:1,Drivers!2:2,FALSE),FALSE) -> 61.1 | J29: =VLOOKUP($A$29,Drivers!1:1048576,MATCH(1:1,Drivers!2:2,FALSE),FALSE) -> 56.2 | K29: =VLOOKUP($A$29,Drivers!1:1048576,MATCH(1:1,Drivers!2:2,FALSE),FALSE) -> 229.3 | ... S29: =VLOOKUP($A$29,Drivers!1:1048576,MATCH(1:1,Drivers!2:2,FALSE),FALSE) -> 282.25135 | U29: EPS | V29: % | X29: =(E23/D23-1)*100 -> 8.4280261 | Y29: =(F23/E23-1)*100 -> 7.54588 | Z29: =(G23/F23-1)*100 -> 11.478928 | AA29: =(H23/G23-1)*100 -> 19.645698 | AB29: =(I23/H23-1)*100 -> 10.547328 | AC29: =(J23/I23-1)*100 -> 6.9338256 | AD29: =(K23/J23-1)*100 -> 30.69704 | AE29: =(L23/K23-1)*100 -> 58.086512 | ... AL29: =(S23/R23-1)*100 -> 5.1009225
A30: TAX | B30: Tax paid | C30: A$m | D30: =VLOOKUP($A$30,'P&L'!1:1048576,MATCH(1:1,'P&L'!4:4,FALSE),FALSE) -> -51.42 | E30: =VLOOKUP($A$30,'P&L'!1:1048576,MATCH(1:1,'P&L'!4:4,FALSE),FALSE) -> -54.23 | F30: =VLOOKUP($A$30,'P&L'!1:1048576,MATCH(1:1,'P&L'!4:4,FALSE),FALSE) -> -59.021 | G30: =VLOOKUP($A$30,'P&L'!1:1048576,MATCH(1:1,'P&L'!4:4,FALSE),FALSE) -> -65.658 | H30: =VLOOKUP($A$30,'P&L'!1:1048576,MATCH(1:1,'P&L'!4:4,FALSE),FALSE) -> -86.8 | I30: =VLOOKUP($A$30,'P&L'!1:1048576,MATCH(1:1,'P&L'!4:4,FALSE),FALSE) -> -101.3 | J30: =VLOOKUP($A$30,'P&L'!1:1048576,MATCH(1:1,'P&L'!4:4,FALSE),FALSE) -> -109.5 | K30: =VLOOKUP($A$30,'P&L'!1:1048576,MATCH(1:1,'P&L'!4:4,FALSE),FALSE) -> -145.7 | ... S30: =VLOOKUP($A$30,'P&L'!1:1048576,MATCH(1:1,'P&L'!4:4,FALSE),FALSE) -> -231.46367
A31: NET_INT | B31: Net Interest | C31: A$m | D31: =VLOOKUP($A$31,'P&L'!1:1048576,MATCH(1:1,'P&L'!4:4,FALSE),FALSE) -> -9.701 | E31: =VLOOKUP($A$31,'P&L'!1:1048576,MATCH(1:1,'P&L'!4:4,FALSE),FALSE) -> -8.443 | F31: =VLOOKUP($A$31,'P&L'!1:1048576,MATCH(1:1,'P&L'!4:4,FALSE),FALSE) -> -5.375 | G31: =VLOOKUP($A$31,'P&L'!1:1048576,MATCH(1:1,'P&L'!4:4,FALSE),FALSE) -> -3.336 | H31: =VLOOKUP($A$31,'P&L'!1:1048576,MATCH(1:1,'P&L'!4:4,FALSE),FALSE) -> -9 | I31: =VLOOKUP($A$31,'P&L'!1:1048576,MATCH(1:1,'P&L'!4:4,FALSE),FALSE) -> -16.1 | J31: =VLOOKUP($A$31,'P&L'!1:1048576,MATCH(1:1,'P&L'!4:4,FALSE),FALSE) -> -13.6 | K31: =VLOOKUP($A$31,'P&L'!1:1048576,MATCH(1:1,'P&L'!4:4,FALSE),FALSE) -> -35.3 | ... S31: =VLOOKUP($A$31,'P&L'!1:1048576,MATCH(1:1,'P&L'!4:4,FALSE),FALSE) -> -37.071549 | U31: Margins (%)
B32: Gross Cashflow | C32: A$m | D32: =SUM(D28:D31) -> 149.864 | E32: =SUM(E28:E31) -> 163.977 | F32: =SUM(F28:F31) -> 175.635 | G32: =SUM(G28:G31) -> 193.082 | H32: =SUM(H28:H31) -> 264.5 | I32: =SUM(I28:I31) -> 294.3 | J32: =SUM(J28:J31) -> 306 | K32: =SUM(K28:K31) -> 551.2 | ... S32: =SUM(S28:S31) -> 819.73886 | U32: Gross Margin | V32: % | W32: =+'P&L'!AG12 -> 0.21527203 | X32: =+'P&L'!AJ12 -> 0.21700052 | Y32: =+'P&L'!AM12 -> 0.21857154 | Z32: =+'P&L'!AP12 -> 0.21884315 | AA32: =+'P&L'!AS12 -> 0.21862799 | AB32: =+'P&L'!AV12 -> 0.21450768 | AC32: =+'P&L'!AY12 -> 0.21510014 | AD32: =+'P&L'!BB12 -> 0.21393123 | AE32: =+'P&L'!BE12 -> 0.22175615 | AF32: =VLOOKUP($AM32,'P&L'!$1:$1048576,MATCH(Summary!AF$1,'P&L'!$4:$4,0),FALSE) -> 0.22534662 | AG32: =VLOOKUP($AM32,'P&L'!$1:$1048576,MATCH(Summary!AG$1,'P&L'!$4:$4,0),FALSE) -> 0.22672027 | AH32: =VLOOKUP($AM32,'P&L'!$1:$1048576,MATCH(Summary!AH$1,'P&L'!$4:$4,0),FALSE) -> 0.22313498 | AI32: =VLOOKUP($AM32,'P&L'!$1:$1048576,MATCH(Summary!AI$1,'P&L'!$4:$4,0),FALSE) -> 0.22363285 | AJ32: =VLOOKUP($AM32,'P&L'!$1:$1048576,MATCH(Summary!AJ$1,'P&L'!$4:$4,0),FALSE) -> 0.22450152 | AK32: =VLOOKUP($AM32,'P&L'!$1:$1048576,MATCH(Summary!AK$1,'P&L'!$4:$4,0),FALSE) -> 0.22237293 | AL32: =VLOOKUP($AM32,'P&L'!$1:$1048576,MATCH(Summary!AL$1,'P&L'!$4:$4,0),FALSE) -> 0.22234797 | AM32: JBH_GM
A33: WORKCAP_CHG | B33: (Inc)/dec in working cap | C33: A$m | D33: =VLOOKUP($A$33,CFS!1:1048576,MATCH(1:1,CFS!4:4,FALSE),FALSE) -> -17.361 | E33: =VLOOKUP($A$33,CFS!1:1048576,MATCH(1:1,CFS!4:4,FALSE),FALSE) -> -123.165 | F33: =VLOOKUP($A$33,CFS!1:1048576,MATCH(1:1,CFS!4:4,FALSE),FALSE) -> -8.356 | G33: =VLOOKUP($A$33,CFS!1:1048576,MATCH(1:1,CFS!4:4,FALSE),FALSE) -> -24.835 | H33: =VLOOKUP($A$33,CFS!1:1048576,MATCH(1:1,CFS!4:4,FALSE),FALSE) -> -149.118 | I33: =VLOOKUP($A$33,CFS!1:1048576,MATCH(1:1,CFS!4:4,FALSE),FALSE) -> -21.8 | J33: =VLOOKUP($A$33,CFS!1:1048576,MATCH(1:1,CFS!4:4,FALSE),FALSE) -> -37.9 | K33: =VLOOKUP($A$33,CFS!1:1048576,MATCH(1:1,CFS!4:4,FALSE),FALSE) -> 362.9 | ... S33: =VLOOKUP($A$33,CFS!1:1048576,MATCH(1:1,CFS!4:4,FALSE),FALSE) -> -27.787275 | U33: CODB Margin | V33: % | W33: =+'P&L'!AG47 -> 0.15149952 | X33: =+'P&L'!AJ47 -> 0.15194179 | Y33: =+'P&L'!AM47 -> 0.15284809 | Z33: =+'P&L'!AP47 -> 0.15256974 | AA33: =+'P&L'!AS47 -> 0.1546088 | AB33: =+'P&L'!AV47 -> 0.1544432 | AC33: =+'P&L'!AY47 -> 0.15462348 | AD33: =+'P&L'!BB47 -> 0.1232747 | AE33: =+'P&L'!BE47 -> 0.1139063 | AF33: =VLOOKUP($AM33,'P&L'!$1:$1048576,MATCH(Summary!AF$1,'P&L'!$4:$4,0),FALSE) -> 0.1155221 | AG33: =VLOOKUP($AM33,'P&L'!$1:$1048576,MATCH(Summary!AG$1,'P&L'!$4:$4,0),FALSE) -> 0.12354567 | AH33: =VLOOKUP($AM33,'P&L'!$1:$1048576,MATCH(Summary!AH$1,'P&L'!$4:$4,0),FALSE) -> 0.13094742 | AI33: =VLOOKUP($AM33,'P&L'!$1:$1048576,MATCH(Summary!AI$1,'P&L'!$4:$4,0),FALSE) -> 0.13205366 | AJ33: =VLOOKUP($AM33,'P&L'!$1:$1048576,MATCH(Summary!AJ$1,'P&L'!$4:$4,0),FALSE) -> 0.13283201 | AK33: =VLOOKUP($AM33,'P&L'!$1:$1048576,MATCH(Summary!AK$1,'P&L'!$4:$4,0),FALSE) -> 0.13261086 | AL33: =VLOOKUP($AM33,'P&L'!$1:$1048576,MATCH(Summary!AL$1,'P&L'!$4:$4,0),FALSE) -> 0.1324629 | AM33: CODB_M_EX_D&A
B34: Others | C34: A$m | D34: =+CFS!M21 -> 13.751 | E34: =+CFS!N21 -> -8.331 | F34: =+CFS!O21 -> 6.69 | G34: =+CFS!P21 -> 13.036 | H34: =+CFS!Q21 -> 102.718 | I34: =+CFS!R21 -> 19.6 | J34: =+CFS!S21 -> 33.5 | K34: =+CFS!T21 -> 86.9 | ... M34: =+CFS!V21 -> 36.5 | N34: =+CFS!Y21 -> -51.8 | O34: =+CFS!AB21 -> 57.7 | P34: =+CFS!AE21 -> 81.2 | Q34: =+CFS!AH21 -> 26.5 | R34: =+CFS!AK21 -> 0 | S34: =+CFS!AL21 -> 0 | U34: EBITDA margin | V34: % | W34: =D12/D8 -> 0.063772518 | X34: =E12/E8 -> 0.065058737 | Y34: =F12/F8 -> 0.065723456 | Z34: =G12/G8 -> 0.066273407 | AA34: =H12/H8 -> 0.06401919 | AB34: =I12/I8 -> 0.060064485 | AC34: =J12/J8 -> 0.060476654 | AD34: =K12/K8 -> 0.090656531 | ... AL34: =S12/S8 -> 0.08988507
A35: OCF | B35: Operating cashflow | C35: A$m | D35: =SUM(D32:D34) -> 146.254 | E35: =SUM(E32:E34) -> 32.481 | F35: =SUM(F32:F34) -> 173.969 | G35: =SUM(G32:G34) -> 181.283 | H35: =SUM(H32:H34) -> 218.1 | I35: =SUM(I32:I34) -> 292.1 | J35: =SUM(J32:J34) -> 301.6 | K35: =SUM(K32:K34) -> 1001 | ... S35: =SUM(S32:S34) -> 791.95158 | U35: EBIT margin | V35: % | W35: =D17/D8 -> 0.053727784 | X35: =E17/E8 -> 0.05486003 | Y35: =F17/F8 -> 0.055010821 | Z35: =G17/G8 -> 0.05593042 | AA35: =H17/H8 -> 0.054442075 | AB35: =I17/I8 -> 0.051150373 | AC35: =J17/J8 -> 0.052555917 | AD35: =K17/K8 -> 0.063506295 | ... AL35: =S17/S8 -> 0.066572761
A36: CAPEX | B36: Capital expenditure | C36: A$m | D36: =VLOOKUP($A$36,CFS!1:1048576,MATCH(1:1,CFS!4:4,FALSE),FALSE) -> -35.307 | E36: =VLOOKUP($A$36,CFS!1:1048576,MATCH(1:1,CFS!4:4,FALSE),FALSE) -> -35.914 | F36: =VLOOKUP($A$36,CFS!1:1048576,MATCH(1:1,CFS!4:4,FALSE),FALSE) -> -42.466 | G36: =VLOOKUP($A$36,CFS!1:1048576,MATCH(1:1,CFS!4:4,FALSE),FALSE) -> -52.343 | H36: =VLOOKUP($A$36,CFS!1:1048576,MATCH(1:1,CFS!4:4,FALSE),FALSE) -> -49.1 | I36: =VLOOKUP($A$36,CFS!1:1048576,MATCH(1:1,CFS!4:4,FALSE),FALSE) -> -54.4 | J36: =VLOOKUP($A$36,CFS!1:1048576,MATCH(1:1,CFS!4:4,FALSE),FALSE) -> -59.3 | K36: =VLOOKUP($A$36,CFS!1:1048576,MATCH(1:1,CFS!4:4,FALSE),FALSE) -> -43.1 | ... S36: =VLOOKUP($A$36,CFS!1:1048576,MATCH(1:1,CFS!4:4,FALSE),FALSE) -> -102.91286 | U36: NPAT margin | V36: % | W36: =D21/D8 -> 0.035178032 | X36: =E21/E8 -> 0.036844802 | Y36: =F21/F8 -> 0.0373784 | Z36: =G21/G8 -> 0.038483315 | AA36: =H21/H8 -> 0.036447411 | AB36: =I21/I8 -> 0.034022438 | AC36: =J21/J8 -> 0.035206404 | AD36: =K21/K8 -> 0.04119259 | ... AL36: =S21/S8 -> 0.044343659
B37: Free cashflow | C37: A$m | D37: =SUM(D35:D36) -> 110.947 | E37: =SUM(E35:E36) -> -3.433 | F37: =SUM(F35:F36) -> 131.503 | G37: =SUM(G35:G36) -> 128.94 | H37: =SUM(H35:H36) -> 169 | I37: =SUM(I35:I36) -> 237.7 | J37: =SUM(J35:J36) -> 242.3 | K37: =SUM(K35:K36) -> 957.9 | ... S37: =SUM(S35:S36) -> 689.03872 | U37: Other Value Drivers
A38: DIVIDENDS | B38: Dividends paid | C38: A$m | D38: =VLOOKUP($A$38,CFS!1:1048576,MATCH(1:1,CFS!4:4,FALSE),FALSE) -> -65.263 | E38: =VLOOKUP($A$38,CFS!1:1048576,MATCH(1:1,CFS!4:4,FALSE),FALSE) -> -77.183 | F38: =VLOOKUP($A$38,CFS!1:1048576,MATCH(1:1,CFS!4:4,FALSE),FALSE) -> -87.174 | G38: =VLOOKUP($A$38,CFS!1:1048576,MATCH(1:1,CFS!4:4,FALSE),FALSE) -> -93.205 | H38: =VLOOKUP($A$38,CFS!1:1048576,MATCH(1:1,CFS!4:4,FALSE),FALSE) -> -119.1 | I38: =VLOOKUP($A$38,CFS!1:1048576,MATCH(1:1,CFS!4:4,FALSE),FALSE) -> -151.6 | J38: =VLOOKUP($A$38,CFS!1:1048576,MATCH(1:1,CFS!4:4,FALSE),FALSE) -> -157.4 | K38: =VLOOKUP($A$38,CFS!1:1048576,MATCH(1:1,CFS!4:4,FALSE),FALSE) -> -172.3 | ... S38: =VLOOKUP($A$38,CFS!1:1048576,MATCH(1:1,CFS!4:4,FALSE),FALSE) -> -406.9324 | U38: ROFE | V38: % | W38: =D17/AVERAGE(U20:W20) -> 0.59190231 | X38: =E17/AVERAGE(W20:X20) -> 0.52279358 | Y38: =F17/AVERAGE(X20:Y20) -> 0.46471289 | Z38: =G17/AVERAGE(Y20:Z20) -> 0.49349427 | AA38: =H17/AVERAGE(Z20:AA20) -> 0.3400564 | AB38: =I17/AVERAGE(AA20:AB20) -> 0.2612032 | AC38: =J17/AVERAGE(AB20:AC20) -> 0.27530454 | AD38: =K17/AVERAGE(AC20:AD20) -> 0.45343071 | AE38: =L17/AVERAGE(AD20:AE20) -> 0.78245762 | ... AL38: =S17/AVERAGE(AK20:AL20) -> 0.54907559
A39: TOTAL_CASH_FLOW | B39: Net free Cashflow | C39: A$m | D39: =SUM(D37:D38) -> 45.684 | E39: =SUM(E37:E38) -> -80.616 | F39: =SUM(F37:F38) -> 44.329 | G39: =SUM(G37:G38) -> 35.735 | H39: =SUM(H37:H38) -> 49.9 | I39: =SUM(I37:I38) -> 86.1 | J39: =SUM(J37:J38) -> 84.9 | K39: =SUM(K37:K38) -> 785.6 | ... S39: =SUM(S37:S38) -> 282.10632 | U39: EBIT to net interest | V39: x | W39: =D17/-D18 -> 18.323163 | X39: =E17/-E18 -> 22.636504 | Y39: =F17/-F18 -> 37.378047 | Z39: =G17/-G18 -> 66.29946 | AA39: =H17/-H18 -> 34.044444 | AB39: =I17/-I18 -> 21.776398 | AC39: =J17/-J18 -> 27.419118 | AD39: =K17/-K18 -> 14.246459 | ... AL39: =S17/-S18 -> 21.742354
A40: Proceeds_issue_shr | B40: Equity raised | C40: A$m | D40: =+CFS!M34 -> 1.082 | E40: =+CFS!N34 -> -4.307 | F40: =+CFS!O34 -> -1.845 | G40: =+CFS!P34 -> -7.226 | H40: =+CFS!Q34 -> 395.9 | I40: =+CFS!R34 -> 3 | J40: =+CFS!S34 -> 1.9 | K40: =+CFS!T34 -> 1.3 | L40: =VLOOKUP($A$40,CFS!$1:$1048576,MATCH(Summary!L$1,CFS!$4:$4,0),FALSE) -> 0 | M40: =VLOOKUP($A$40,CFS!$1:$1048576,MATCH(Summary!M$1,CFS!$4:$4,0),FALSE) -> 0 | N40: =VLOOKUP($A$40,CFS!$1:$1048576,MATCH(Summary!N$1,CFS!$4:$4,0),FALSE) -> 0 | O40: =VLOOKUP($A$40,CFS!$1:$1048576,MATCH(Summary!O$1,CFS!$4:$4,0),FALSE) -> 0 | P40: =VLOOKUP($A$40,CFS!$1:$1048576,MATCH(Summary!P$1,CFS!$4:$4,0),FALSE) -> 0 | Q40: =VLOOKUP($A$40,CFS!$1:$1048576,MATCH(Summary!Q$1,CFS!$4:$4,0),FALSE) -> 0 | R40: =VLOOKUP($A$40,CFS!$1:$1048576,MATCH(Summary!R$1,CFS!$4:$4,0),FALSE) -> 0 | S40: =VLOOKUP($A$40,CFS!$1:$1048576,MATCH(Summary!S$1,CFS!$4:$4,0),FALSE) -> 0 | U40: Capex-to-D&A | V40: x | W40: =D36/D13 -> 1.0624398 | X40: =E36/E13 -> 1.0108078 | Y40: =F36/F13 -> 1.0854207 | Z40: =G36/G13 -> 1.2797487 | AA40: =H36/H13 -> 0.9109462 | AB40: =I36/I13 -> 0.8903437 | AC40: =J36/J13 -> 1.0551601 | AD40: =K36/K13 -> 0.18796337 | ... AL40: =S36/S13 -> 0.36461424
B41: Other financing | C41: A$m | D41: =CFS!M36+CFS!M37 -> -0.632 | E41: =CFS!N36+CFS!N37 -> -0.182 | F41: =CFS!O36+CFS!O37 -> -0.508 | G41: =CFS!P36+CFS!P37 -> -0.134 | H41: =CFS!Q36+CFS!Q37 -> -10.9 | I41: =CFS!R36+CFS!R37 -> -0.8 | J41: =CFS!S36+CFS!S37 -> -9.4 | K41: =VLOOKUP($A$59,CFS!$1:$1048576,MATCH(Summary!K$1,CFS!$4:$4,0),FALSE)+VLOOKUP(Summary!$A$60,CFS!$1:$1048576,MATCH(Summary!K$1,CFS!$4:$4,0),FALSE)+VLOOKUP(Summary!$A$61,CFS!$1:$1048576,MATCH(Summary!K$1,CFS!$4:$4,0),FALSE) -> -194.8 | L41: =VLOOKUP($A$59,CFS!$1:$1048576,MATCH(Summary!L$1,CFS!$4:$4,0),FALSE)+VLOOKUP(Summary!$A$60,CFS!$1:$1048576,MATCH(Summary!L$1,CFS!$4:$4,0),FALSE)+VLOOKUP(Summary!$A$61,CFS!$1:$1048576,MATCH(Summary!L$1,CFS!$4:$4,0),FALSE) -> -179.1 | M41: =VLOOKUP($A$59,CFS!$1:$1048576,MATCH(Summary!M$1,CFS!$4:$4,0),FALSE)+VLOOKUP(Summary!$A$60,CFS!$1:$1048576,MATCH(Summary!M$1,CFS!$4:$4,0),FALSE)+VLOOKUP(Summary!$A$61,CFS!$1:$1048576,MATCH(Summary!M$1,CFS!$4:$4,0),FALSE) -> -456.4 | N41: =VLOOKUP($A$59,CFS!$1:$1048576,MATCH(Summary!N$1,CFS!$4:$4,0),FALSE)+VLOOKUP(Summary!$A$60,CFS!$1:$1048576,MATCH(Summary!N$1,CFS!$4:$4,0),FALSE)+VLOOKUP(Summary!$A$61,CFS!$1:$1048576,MATCH(Summary!N$1,CFS!$4:$4,0),FALSE) -> -200.4 | O41: =VLOOKUP($A$59,CFS!$1:$1048576,MATCH(Summary!O$1,CFS!$4:$4,0),FALSE)+VLOOKUP(Summary!$A$60,CFS!$1:$1048576,MATCH(Summary!O$1,CFS!$4:$4,0),FALSE)+VLOOKUP(Summary!$A$61,CFS!$1:$1048576,MATCH(Summary!O$1,CFS!$4:$4,0),FALSE) -> -204.6 | P41: =VLOOKUP($A$59,CFS!$1:$1048576,MATCH(Summary!P$1,CFS!$4:$4,0),FALSE)+VLOOKUP(Summary!$A$60,CFS!$1:$1048576,MATCH(Summary!P$1,CFS!$4:$4,0),FALSE)+VLOOKUP(Summary!$A$61,CFS!$1:$1048576,MATCH(Summary!P$1,CFS!$4:$4,0),FALSE) -> -220.1 | Q41: =VLOOKUP($A$59,CFS!$1:$1048576,MATCH(Summary!Q$1,CFS!$4:$4,0),FALSE)+VLOOKUP(Summary!$A$60,CFS!$1:$1048576,MATCH(Summary!Q$1,CFS!$4:$4,0),FALSE)+VLOOKUP(Summary!$A$61,CFS!$1:$1048576,MATCH(Summary!Q$1,CFS!$4:$4,0),FALSE) -> -232.076 | R41: =VLOOKUP($A$59,CFS!$1:$1048576,MATCH(Summary!R$1,CFS!$4:$4,0),FALSE)+VLOOKUP(Summary!$A$60,CFS!$1:$1048576,MATCH(Summary!R$1,CFS!$4:$4,0),FALSE)+VLOOKUP(Summary!$A$61,CFS!$1:$1048576,MATCH(Summary!R$1,CFS!$4:$4,0),FALSE) -> -211.33128 | S41: =VLOOKUP($A$59,CFS!$1:$1048576,MATCH(Summary!S$1,CFS!$4:$4,0),FALSE)+VLOOKUP(Summary!$A$60,CFS!$1:$1048576,MATCH(Summary!S$1,CFS!$4:$4,0),FALSE)+VLOOKUP(Summary!$A$61,CFS!$1:$1048576,MATCH(Summary!S$1,CFS!$4:$4,0),FALSE) -> -217.67122 | U41: Capex-to-sales | V41: % | W41: =-D36/D8 -> 0.010671926 | X41: =-E36/E8 -> 0.010308932 | Y41: =-F36/F8 -> 0.011627716 | Z41: =-G36/G8 -> 0.013236424 | AA41: =-H36/H8 -> 0.008724236 | AB41: =-I36/I8 -> 0.0079366237 | AC41: =-J36/J8 -> 0.0083576452 | AD41: =-K36/K8 -> 0.0054426751 | ... AL41: =-S36/S8 -> 0.0085
A42: CHG_DEBT | B42: Change in net debt | C42: A$m | D42: =VLOOKUP($A$42,CFS!1:1048576,MATCH(1:1,CFS!4:4,FALSE),FALSE) -> -26.21 | E42: =VLOOKUP($A$42,CFS!1:1048576,MATCH(1:1,CFS!4:4,FALSE),FALSE) -> 54.063 | F42: =VLOOKUP($A$42,CFS!1:1048576,MATCH(1:1,CFS!4:4,FALSE),FALSE) -> -40.113 | G42: =VLOOKUP($A$42,CFS!1:1048576,MATCH(1:1,CFS!4:4,FALSE),FALSE) -> -30 | H42: =VLOOKUP($A$42,CFS!1:1048576,MATCH(1:1,CFS!4:4,FALSE),FALSE) -> 450 | I42: =VLOOKUP($A$42,CFS!1:1048576,MATCH(1:1,CFS!4:4,FALSE),FALSE) -> -89.7 | J42: =VLOOKUP($A$42,CFS!1:1048576,MATCH(1:1,CFS!4:4,FALSE),FALSE) -> -30.5 | K42: =VLOOKUP($A$42,CFS!1:1048576,MATCH(1:1,CFS!4:4,FALSE),FALSE) -> -440 | ... S42: =VLOOKUP($A$42,CFS!1:1048576,MATCH(1:1,CFS!4:4,FALSE),FALSE) -> 0 | U42: D&A-to-sales | V42: % | W42: =-D13/D8 -> 0.010044735 | X42: =-E13/E8 -> 0.010198707 | Y42: =-F13/F8 -> 0.010712635 | Z42: =-G13/G8 -> 0.010342987 | AA42: =-H13/H8 -> 0.0095771144 | AB42: =-I13/I8 -> 0.0089141123 | AC42: =-J13/J8 -> 0.0079207363 | AD42: =-K13/K8 -> 0.028956042 | ... AL42: =-S13/S8 -> 0.02331231
B43: JB Hi Fi (Aus) metrics | D43: =W49 -> 2013a | E43: =X49 -> 2014a | F43: =Y49 -> 2015a | G43: =G27 -> 2016a | H43: =H27 -> 2017a | I43: =I27 -> 2018a | J43: =J27 -> 2019a | K43: =K27 -> 2020a | L43: =L27 -> 2021a | M43: =M27 -> 2022a | N43: =N27 -> 2023a | ... P43: =P27 -> 2025a | Q43: 2026e | R43: =+R27 -> 2027e | S43: =+S27 -> 2028e | U43: Net debt/equity | V43: x | W43: =W19/W18 -> 0.2340833 | X43: =X19/X18 -> 0.46229716 | Y43: =Y19/Y18 -> 0.26298551 | Z43: =Z19/Z18 -> 0.14294963 | AA43: =AA19/AA18 -> 0.56942004 | AB43: =AB19/AB18 -> 0.41937526 | AC43: =AC19/AC18 -> 0.30638828 | AD43: =AD19/AD18 -> -0.22745772 | ... AL43: =AL19/AL18 -> -0.21091746
A44: JBH_SalesG | B44: JB Hi Fi (Aus) LFL sales | C44: % | I44: =Drivers!U73 -> 0.062 | J44: =VLOOKUP($A44,Drivers!$1:$1048576,MATCH(Summary!J$1,Drivers!$2:$2,0),FALSE) -> 0.028 | K44: =VLOOKUP($A44,Drivers!$1:$1048576,MATCH(Summary!K$1,Drivers!$2:$2,0),FALSE) -> 0.122 | L44: =VLOOKUP($A44,Drivers!$1:$1048576,MATCH(Summary!L$1,Drivers!$2:$2,0),FALSE) -> 0.12 | M44: =VLOOKUP($A44,Drivers!$1:$1048576,MATCH(Summary!M$1,Drivers!$2:$2,0),FALSE) -> 0.034 | N44: =VLOOKUP($A44,Drivers!$1:$1048576,MATCH(Summary!N$1,Drivers!$2:$2,0),FALSE) -> 0.048 | O44: =VLOOKUP($A44,Drivers!$1:$1048576,MATCH(Summary!O$1,Drivers!$2:$2,0),FALSE) -> 0.006 | P44: =VLOOKUP($A44,Drivers!$1:$1048576,MATCH(Summary!P$1,Drivers!$2:$2,0),FALSE) -> 0.072 | Q44: =VLOOKUP($A44,Drivers!$1:$1048576,MATCH(Summary!Q$1,Drivers!$2:$2,0),FALSE) -> 0.0375 | ... S44: =VLOOKUP($A44,Drivers!$1:$1048576,MATCH(Summary!S$1,Drivers!$2:$2,0),FALSE) -> 0.04 | U44: Net debt/(Net debt + Equity) | V44: x | W44: =W19/(W18+W19) -> 0.18968193 | X44: =X19/(X18+X19) -> 0.31614447 | Y44: =Y19/(Y18+Y19) -> 0.20822528 | Z44: =Z19/(Z18+Z19) -> 0.1250708 | AA44: =AA19/(AA18+AA19) -> 0.36282195 | AB44: =AB19/(AB18+AB19) -> 0.29546468 | AC44: =AC19/(AC18+AC19) -> 0.23453079 | AD44: =AD19/(AD18+AD19) -> -0.29442753 | ... AL44: =AL19/(AL18+AL19) -> -0.26729455
A45: JBH AUS GP MARGIN | B45: GM - Aus | C45: % | D45: =Drivers!P253 -> 0.21730206 | E45: =Drivers!Q253 -> 0.21913584 | F45: =Drivers!R253 -> 0.2206587 | G45: =Drivers!S253 -> 0.22084005 | H45: =Drivers!T253 -> 0.22243648 | I45: =Drivers!U253 -> 0.22171069 | J45: =VLOOKUP($A45,Drivers!$1:$1048576,MATCH(Summary!J$1,Drivers!$2:$2,0),FALSE) -> 0.22137114 | K45: =VLOOKUP($A45,Drivers!$1:$1048576,MATCH(Summary!K$1,Drivers!$2:$2,0),FALSE) -> 0.21978229 | L45: =VLOOKUP($A45,Drivers!$1:$1048576,MATCH(Summary!L$1,Drivers!$2:$2,0),FALSE) -> 0.22246844 | M45: =VLOOKUP($A45,Drivers!$1:$1048576,MATCH(Summary!M$1,Drivers!$2:$2,0),FALSE) -> 0.223949 | N45: =VLOOKUP($A45,Drivers!$1:$1048576,MATCH(Summary!N$1,Drivers!$2:$2,0),FALSE) -> 0.22630268 | O45: =VLOOKUP($A45,Drivers!$1:$1048576,MATCH(Summary!O$1,Drivers!$2:$2,0),FALSE) -> 0.22206085 | P45: =VLOOKUP($A45,Drivers!$1:$1048576,MATCH(Summary!P$1,Drivers!$2:$2,0),FALSE) -> 0.21994312 | Q45: =VLOOKUP($A45,Drivers!$1:$1048576,MATCH(Summary!Q$1,Drivers!$2:$2,0),FALSE) -> 0.22044312 | ... S45: =VLOOKUP($A45,Drivers!$1:$1048576,MATCH(Summary!S$1,Drivers!$2:$2,0),FALSE) -> 0.21794312 | U45: NTA/share | V45: A$m | W45: =+(W12-W16-W10)/'P&L'!AG103 -> 1.6099665 | X45: =+(X12-X16-X10)/'P&L'!AJ103 -> 2.070116 | Y45: =+(Y12-Y16-Y10)/'P&L'!AM103 -> 2.5884223 | Z45: =+(Z12-Z16-Z10)/'P&L'!AP103 -> 3.1899397 | AA45: =+(AA12-AA16-AA10)/'P&L'!AS103 -> -1.5359361 | AB45: =+(AB12-AB16-AB10)/'P&L'!AV103 -> -0.77394305 | AC45: =+(AC12-AC16-AC10)/'P&L'!AY103 -> 0.058570198 | AD45: =+(AD12-AD16-AD10)/'P&L'!BB103 -> 0.64051724 | AE45: =+(AE12-AE16-AE10)/'P&L'!BE103 -> 2.3961938 | AF45: =+(AF12-AF16-AF10)/VLOOKUP($AM45,'P&L'!$1:$1048576,MATCH(Summary!AF$1,'P&L'!$4:$4,0),FALSE) -> 2.1795096 | AG45: =+(AG12-AG16-AG10)/VLOOKUP($AM45,'P&L'!$1:$1048576,MATCH(Summary!AG$1,'P&L'!$4:$4,0),FALSE) -> 3.5355191 | AH45: =+(AH12-AH16-AH10)/VLOOKUP($AM45,'P&L'!$1:$1048576,MATCH(Summary!AH$1,'P&L'!$4:$4,0),FALSE) -> 4.8191781 | AI45: =+(AI12-AI16-AI10)/VLOOKUP($AM45,'P&L'!$1:$1048576,MATCH(Summary!AI$1,'P&L'!$4:$4,0),FALSE) -> 4.9323974 | AJ45: =+(AJ12-AJ16-AJ10)/VLOOKUP($AM45,'P&L'!$1:$1048576,MATCH(Summary!AJ$1,'P&L'!$4:$4,0),FALSE) -> 5.2577481 | AK45: =+(AK12-AK16-AK10)/VLOOKUP($AM45,'P&L'!$1:$1048576,MATCH(Summary!AK$1,'P&L'!$4:$4,0),FALSE) -> 6.3567749 | AL45: =+(AL12-AL16-AL10)/VLOOKUP($AM45,'P&L'!$1:$1048576,MATCH(Summary!AL$1,'P&L'!$4:$4,0),FALSE) -> 7.5465167 | AM45: SharesOutstand
A46: JBH_AU_EBIT_MARGIN | B46: EBIT margin - Aus | C46: % | D46: =Drivers!P271 -> 0.055989572 | E46: =Drivers!Q271 -> 0.057190614 | F46: =Drivers!R271 -> 0.057710092 | G46: =Drivers!S271 -> 0.058917868 | H46: =Drivers!T271 -> 0.063250253 | I46: =Drivers!U271 -> 0.064387515 | J46: =VLOOKUP($A46,Drivers!$1:$1048576,MATCH(Summary!J$1,Drivers!$2:$2,0),FALSE) -> 0.063838341 | K46: =VLOOKUP($A46,Drivers!$1:$1048576,MATCH(Summary!K$1,Drivers!$2:$2,0),FALSE) -> 0.073624246 | L46: =VLOOKUP($A46,Drivers!$1:$1048576,MATCH(Summary!L$1,Drivers!$2:$2,0),FALSE) -> 0.087798818 | M46: =VLOOKUP($A46,Drivers!$1:$1048576,MATCH(Summary!M$1,Drivers!$2:$2,0),FALSE) -> 0.087936738 | N46: =VLOOKUP($A46,Drivers!$1:$1048576,MATCH(Summary!N$1,Drivers!$2:$2,0),FALSE) -> 0.084309742 | O46: =VLOOKUP($A46,Drivers!$1:$1048576,MATCH(Summary!O$1,Drivers!$2:$2,0),FALSE) -> 0.074312773 | P46: =VLOOKUP($A46,Drivers!$1:$1048576,MATCH(Summary!P$1,Drivers!$2:$2,0),FALSE) -> 0.074656493 | Q46: =VLOOKUP($A46,Drivers!$1:$1048576,MATCH(Summary!Q$1,Drivers!$2:$2,0),FALSE) -> 0.075489622 | ... S46: =VLOOKUP($A46,Drivers!$1:$1048576,MATCH(Summary!S$1,Drivers!$2:$2,0),FALSE) -> 0.073708035 | U46: Price/NTA | V46: A$m | W46: =+$N$4/W45 -> 54.721635 | X46: =+$N$4/X45 -> 42.558003 | Y46: =+$N$4/Y45 -> 34.036177 | Z46: =+$N$4/Z45 -> 27.618077 | AA46: =+$N$4/AA45 -> -57.359157 | AB46: =+$N$4/AB45 -> -113.83266 | AC46: =+$N$4/AC45 -> 1504.1779 | AD46: =+$N$4/AD45 -> 137.54509 | ... AL46: =+$N$4/AL45 -> 11.67426
A47: JBH_space_YoY% | B47: Space growth | C47: % | D47: =Drivers!P169 -> 0.078200148 | E47: =Drivers!Q202 -> 0.065345437 | F47: =Drivers!R202 -> 0.080693907 | G47: =Drivers!S202 -> 0.092082776 | H47: =Drivers!T202 -> 0.083292688 | I47: =Drivers!U202 -> 0.061882785 | J47: =VLOOKUP($A47,Drivers!$1:$1048576,MATCH(Summary!J$1,Drivers!$2:$2,0),FALSE) -> 0.028055208 | K47: =VLOOKUP($A47,Drivers!$1:$1048576,MATCH(Summary!K$1,Drivers!$2:$2,0),FALSE) -> 0.008670037 | L47: =VLOOKUP($A47,Drivers!$1:$1048576,MATCH(Summary!L$1,Drivers!$2:$2,0),FALSE) -> 0.0024008894 | M47: =VLOOKUP($A47,Drivers!$1:$1048576,MATCH(Summary!M$1,Drivers!$2:$2,0),FALSE) -> 0.0047902779 | N47: =VLOOKUP($A47,Drivers!$1:$1048576,MATCH(Summary!N$1,Drivers!$2:$2,0),FALSE) -> 0.011918601 | O47: =VLOOKUP($A47,Drivers!$1:$1048576,MATCH(Summary!O$1,Drivers!$2:$2,0),FALSE) -> 0.024024338 | P47: =VLOOKUP($A47,Drivers!$1:$1048576,MATCH(Summary!P$1,Drivers!$2:$2,0),FALSE) -> 0.0265867 | Q47: =VLOOKUP($A47,Drivers!$1:$1048576,MATCH(Summary!Q$1,Drivers!$2:$2,0),FALSE) -> 0.020253174 | ... S47: =VLOOKUP($A47,Drivers!$1:$1048576,MATCH(Summary!S$1,Drivers!$2:$2,0),FALSE) -> 0.0079671802 | U47: NAV/share | V47: A$m | W47: =+W18/'P&L'!AG103 -> 2.4468342 | X47: =+X18/'P&L'!AJ103 -> 2.9125157 | Y47: =+Y18/'P&L'!AM103 -> 3.4335196 | Z47: =+Z18/'P&L'!AP103 -> 4.0455232 | AA47: =+AA18/'P&L'!AS103 -> 7.5732032 | AB47: =+AB18/'P&L'!AV103 -> 8.1760138 | AC47: =+AC18/'P&L'!AY103 -> 8.9931094 | AD47: =+AD18/'P&L'!BB103 -> 9.5318966 | AE47: =+AE18/'P&L'!BE103 -> 11.318339 | AF47: =+AF18/VLOOKUP($AM47,'P&L'!$1:$1048576,MATCH(Summary!AF$1,'P&L'!$4:$4,0),FALSE) -> 11.211033 | AG47: =+AG18/VLOOKUP($AM47,'P&L'!$1:$1048576,MATCH(Summary!AG$1,'P&L'!$4:$4,0),FALSE) -> 12.928962 | AH47: =+AH18/VLOOKUP($AM47,'P&L'!$1:$1048576,MATCH(Summary!AH$1,'P&L'!$4:$4,0),FALSE) -> 14.238356 | AI47: =+AI18/VLOOKUP($AM47,'P&L'!$1:$1048576,MATCH(Summary!AI$1,'P&L'!$4:$4,0),FALSE) -> 14.736408 | AJ47: =+AJ18/VLOOKUP($AM47,'P&L'!$1:$1048576,MATCH(Summary!AJ$1,'P&L'!$4:$4,0),FALSE) -> 15.053558 | AK47: =+AK18/VLOOKUP($AM47,'P&L'!$1:$1048576,MATCH(Summary!AK$1,'P&L'!$4:$4,0),FALSE) -> 16.147265 | AL47: =+AL18/VLOOKUP($AM47,'P&L'!$1:$1048576,MATCH(Summary!AL$1,'P&L'!$4:$4,0),FALSE) -> 17.331527 | AM47: SharesOutstand
A48: JBH_stores | B48: Period end stores | C48: k | D48: =+Drivers!P198 -> 177 | E48: =+Drivers!Q198 -> 182 | F48: =+Drivers!R198 -> 187 | G48: =+Drivers!S198 -> 194 | H48: =+Drivers!T198 -> 201 | I48: =+Drivers!U198 -> 208 | J48: =VLOOKUP($A48,Drivers!$1:$1048576,MATCH(Summary!J$1,Drivers!$2:$2,0),FALSE) -> 210 | K48: =VLOOKUP($A48,Drivers!$1:$1048576,MATCH(Summary!K$1,Drivers!$2:$2,0),FALSE) -> 209 | L48: =VLOOKUP($A48,Drivers!$1:$1048576,MATCH(Summary!L$1,Drivers!$2:$2,0),FALSE) -> 209 | M48: =VLOOKUP($A48,Drivers!$1:$1048576,MATCH(Summary!M$1,Drivers!$2:$2,0),FALSE) -> 213 | N48: =VLOOKUP($A48,Drivers!$1:$1048576,MATCH(Summary!N$1,Drivers!$2:$2,0),FALSE) -> 216 | O48: =VLOOKUP($A48,Drivers!$1:$1048576,MATCH(Summary!O$1,Drivers!$2:$2,0),FALSE) -> 224 | P48: =VLOOKUP($A48,Drivers!$1:$1048576,MATCH(Summary!P$1,Drivers!$2:$2,0),FALSE) -> 229 | Q48: =VLOOKUP($A48,Drivers!$1:$1048576,MATCH(Summary!Q$1,Drivers!$2:$2,0),FALSE) -> 234 | ... S48: =VLOOKUP($A48,Drivers!$1:$1048576,MATCH(Summary!S$1,Drivers!$2:$2,0),FALSE) -> 238 | U48: Price/NAV | V48: A$m | W48: =+$N$4/W47 -> 36.005709 | X48: =+$N$4/X47 -> 30.248764 | Y48: =+$N$4/Y47 -> 25.658802 | Z48: =+$N$4/Z47 -> 21.777159 | AA48: =+$N$4/AA47 -> 11.633122 | AB48: =+$N$4/AB47 -> 10.775422 | AC48: =+$N$4/AC47 -> 9.7963892 | AD48: =+$N$4/AD47 -> 9.2426517 | ... AL48: =+$N$4/AL47 -> 5.0832221
B49: The Good Guys metrics | E49: =E43 -> 2014a | F49: =F43 -> 2015a | G49: =G43 -> 2016a | H49: =H43 -> 2017a | I49: =I43 -> 2018a | J49: =J43 -> 2019a | K49: =K43 -> 2020a | L49: =L43 -> 2021a | ... P49: =P43 -> 2025a | Q49: 2026e | R49: =+R43 -> 2027e | S49: =+S43 -> 2028e | U49: Valuation metrics | W49: =+D27 -> 2013a | X49: =+E27 -> 2014a | Y49: =+F27 -> 2015a | Z49: =+G27 -> 2016a | AA49: =+H27 -> 2017a | AB49: =+I27 -> 2018a | AC49: =+J27 -> 2019a | AD49: =+K27 -> 2020a | ... AI49: =+P27 -> 2025a | AJ49: 2026e | AK49: =+AK22 -> 2027e | AL49: =+AL22 -> 2028e
A50: TGG_SalesG | B50: The Good Guys LFL sales | C50: % | H50: =Drivers!T309 -> -0.013 | I50: =Drivers!U309 -> 0.009 | J50: =Drivers!X309 -> 0.009 | K50: =VLOOKUP($A50,Drivers!$1:$1048576,MATCH(Summary!K$1,Drivers!$2:$2,0),FALSE) -> 0.108 | L50: =VLOOKUP($A50,Drivers!$1:$1048576,MATCH(Summary!L$1,Drivers!$2:$2,0),FALSE) -> 0.137 | M50: =VLOOKUP($A50,Drivers!$1:$1048576,MATCH(Summary!M$1,Drivers!$2:$2,0),FALSE) -> 0.027 | N50: =VLOOKUP($A50,Drivers!$1:$1048576,MATCH(Summary!N$1,Drivers!$2:$2,0),FALSE) -> 0.008 | O50: =VLOOKUP($A50,Drivers!$1:$1048576,MATCH(Summary!O$1,Drivers!$2:$2,0),FALSE) -> -0.048 | P50: =VLOOKUP($A50,Drivers!$1:$1048576,MATCH(Summary!P$1,Drivers!$2:$2,0),FALSE) -> 0.065 | Q50: =VLOOKUP($A50,Drivers!$1:$1048576,MATCH(Summary!Q$1,Drivers!$2:$2,0),FALSE) -> 0.0325 | R50: =VLOOKUP($A50,Drivers!$1:$1048576,MATCH(Summary!R$1,Drivers!$2:$2,0),FALSE) -> 0.03 | S50: =VLOOKUP($A50,Drivers!$1:$1048576,MATCH(Summary!S$1,Drivers!$2:$2,0),FALSE) -> 0.035 | U50: P/E (x) | W50: =+$N$4/D23*100 -> 75.284271 | Y50: =+$N$4/F23*100 -> 64.560802 | Z50: =+$N$4/G23*100 -> 57.91301 | AA50: =+$N$4/H23*100 -> 48.403754 | AB50: =+$N$4/I23*100 -> 43.785549 | AC50: =+$N$4/J23*100 -> 40.946397 | AD50: =+$N$4/K23*100 -> 31.329246 | AE50: =+$N$4/L23*100 -> 19.817786 | AF50: =+$N$4/M23*100 -> 18.326084 | ... AL50: =+$N$4/S23*100 -> 18.006728
A51: TGG_GM | B51: Gross Margin | C51: % | H51: =Drivers!T334 -> 0.21265099 | I51: =Drivers!U334 -> 0.20277923 | J51: =Drivers!X334 -> 0.20610829 | K51: =VLOOKUP($A51,Drivers!$1:$1048576,MATCH(Summary!K$1,Drivers!$2:$2,0),FALSE) -> 0.20520764 | L51: =VLOOKUP($A51,Drivers!$1:$1048576,MATCH(Summary!L$1,Drivers!$2:$2,0),FALSE) -> 0.22410428 | M51: =VLOOKUP($A51,Drivers!$1:$1048576,MATCH(Summary!M$1,Drivers!$2:$2,0),FALSE) -> 0.23298917 | N51: =VLOOKUP($A51,Drivers!$1:$1048576,MATCH(Summary!N$1,Drivers!$2:$2,0),FALSE) -> 0.23405617 | O51: =VLOOKUP($A51,Drivers!$1:$1048576,MATCH(Summary!O$1,Drivers!$2:$2,0),FALSE) -> 0.23186891 | P51: =VLOOKUP($A51,Drivers!$1:$1048576,MATCH(Summary!P$1,Drivers!$2:$2,0),FALSE) -> 0.23469459 | Q51: =VLOOKUP($A51,Drivers!$1:$1048576,MATCH(Summary!Q$1,Drivers!$2:$2,0),FALSE) -> 0.23569459 | R51: =VLOOKUP($A51,Drivers!$1:$1048576,MATCH(Summary!R$1,Drivers!$2:$2,0),FALSE) -> 0.23469459 | S51: =VLOOKUP($A51,Drivers!$1:$1048576,MATCH(Summary!S$1,Drivers!$2:$2,0),FALSE) -> 0.23469459 | U51: EV/EBITDA (x) | W51: =+'P&L'!AG168 -> 0 | Y51: =+'P&L'!AM168 -> 36.898229 | Z51: =+'P&L'!AP168 -> 33.695364 | AA51: =+'P&L'!AS168 -> 25.745373 | AB51: =+'P&L'!AV168 -> 25.625275 | AC51: =+'P&L'!AY168 -> 24.610406 | AD51: =+'P&L'!BB168 -> 14.098377 | AE51: =+'P&L'!BE168 -> 10.5254 | AF51: =VLOOKUP($AM51,'P&L'!$1:$1048576,MATCH(Summary!AF$1,'P&L'!$4:$4,0),FALSE) -> 10.041054 | AG51: =VLOOKUP($AM51,'P&L'!$1:$1048576,MATCH(Summary!AG$1,'P&L'!$4:$4,0),FALSE) -> 9.7484129 | AH51: =VLOOKUP($AM51,'P&L'!$1:$1048576,MATCH(Summary!AH$1,'P&L'!$4:$4,0),FALSE) -> 10.90956 | AI51: =VLOOKUP($AM51,'P&L'!$1:$1048576,MATCH(Summary!AI$1,'P&L'!$4:$4,0),FALSE) -> 9.9651601 | AJ51: =VLOOKUP($AM51,'P&L'!$1:$1048576,MATCH(Summary!AJ$1,'P&L'!$4:$4,0),FALSE) -> 9.4230672 | AK51: =VLOOKUP($AM51,'P&L'!$1:$1048576,MATCH(Summary!AK$1,'P&L'!$4:$4,0),FALSE) -> 9.2355745 | AL51: =VLOOKUP($AM51,'P&L'!$1:$1048576,MATCH(Summary!AL$1,'P&L'!$4:$4,0),FALSE) -> 8.8510091 | AM51: EV/EBITDA
A52: TGG_EBIT_Margin | B52: EBIT margin | C52: % | H52: =Drivers!T351 -> 0.036872219 | I52: =Drivers!U351 -> 0.028982059 | J52: =Drivers!X351 -> 0.033940128 | K52: =VLOOKUP($A52,Drivers!$1:$1048576,MATCH(Summary!K$1,Drivers!$2:$2,0),FALSE) -> 0.047220362 | L52: =VLOOKUP($A52,Drivers!$1:$1048576,MATCH(Summary!L$1,Drivers!$2:$2,0),FALSE) -> 0.079058806 | M52: =VLOOKUP($A52,Drivers!$1:$1048576,MATCH(Summary!M$1,Drivers!$2:$2,0),FALSE) -> 0.086541909 | N52: =VLOOKUP($A52,Drivers!$1:$1048576,MATCH(Summary!N$1,Drivers!$2:$2,0),FALSE) -> 0.075719872 | O52: =VLOOKUP($A52,Drivers!$1:$1048576,MATCH(Summary!O$1,Drivers!$2:$2,0),FALSE) -> 0.059012355 | P52: =VLOOKUP($A52,Drivers!$1:$1048576,MATCH(Summary!P$1,Drivers!$2:$2,0),FALSE) -> 0.060558464 | Q52: =VLOOKUP($A52,Drivers!$1:$1048576,MATCH(Summary!Q$1,Drivers!$2:$2,0),FALSE) -> 0.061558178 | R52: =VLOOKUP($A52,Drivers!$1:$1048576,MATCH(Summary!R$1,Drivers!$2:$2,0),FALSE) -> 0.060714718 | S52: =VLOOKUP($A52,Drivers!$1:$1048576,MATCH(Summary!S$1,Drivers!$2:$2,0),FALSE) -> 0.061024773 | U52: EV/EBIT (x) | Y52: ='P&L'!AM167 -> 44.083675 | Z52: ='P&L'!AP167 -> 39.926512 | AA52: ='P&L'!AS167 -> 34.586346 | AB52: ='P&L'!AV167 -> 30.09106 | AC52: ='P&L'!AY167 -> 28.319456 | AD52: ='P&L'!BB167 -> 20.946244 | AE52: ='P&L'!BE167 -> 13.620273 | AF52: =VLOOKUP($AM52,'P&L'!$1:$1048576,MATCH(Summary!AF$1,'P&L'!$4:$4,0),FALSE) -> 12.812264 | AG52: =VLOOKUP($AM52,'P&L'!$1:$1048576,MATCH(Summary!AG$1,'P&L'!$4:$4,0),FALSE) -> 12.590538 | AH52: =VLOOKUP($AM52,'P&L'!$1:$1048576,MATCH(Summary!AH$1,'P&L'!$4:$4,0),FALSE) -> 14.906248 | AI52: =VLOOKUP($AM52,'P&L'!$1:$1048576,MATCH(Summary!AI$1,'P&L'!$4:$4,0),FALSE) -> 13.877429 | AJ52: =VLOOKUP($AM52,'P&L'!$1:$1048576,MATCH(Summary!AJ$1,'P&L'!$4:$4,0),FALSE) -> 12.779339 | AK52: =VLOOKUP($AM52,'P&L'!$1:$1048576,MATCH(Summary!AK$1,'P&L'!$4:$4,0),FALSE) -> 12.547199 | AL52: =VLOOKUP($AM52,'P&L'!$1:$1048576,MATCH(Summary!AL$1,'P&L'!$4:$4,0),FALSE) -> 11.950437 | AM52: EV/EBIT
A53: Space_Growth_TGG | B53: Space growth | C53: % | H53: =Drivers!T310 -> 0.004950495 | I53: =Drivers!U310 -> 0.0098522167 | J53: =Drivers!X310 -> 0.019512195 | K53: =VLOOKUP($A53,Drivers!$1:$1048576,MATCH(Summary!K$1,Drivers!$2:$2,0),FALSE) -> 0.004784689 | L53: =VLOOKUP($A53,Drivers!$1:$1048576,MATCH(Summary!L$1,Drivers!$2:$2,0),FALSE) -> 0 | M53: =VLOOKUP($A53,Drivers!$1:$1048576,MATCH(Summary!M$1,Drivers!$2:$2,0),FALSE) -> 0.0047619048 | N53: =VLOOKUP($A53,Drivers!$1:$1048576,MATCH(Summary!N$1,Drivers!$2:$2,0),FALSE) -> 0.0047393365 | O53: =VLOOKUP($A53,Drivers!$1:$1048576,MATCH(Summary!O$1,Drivers!$2:$2,0),FALSE) -> 0 | P53: =VLOOKUP($A53,Drivers!$1:$1048576,MATCH(Summary!P$1,Drivers!$2:$2,0),FALSE) -> 0.0047169811 | Q53: =VLOOKUP($A53,Drivers!$1:$1048576,MATCH(Summary!Q$1,Drivers!$2:$2,0),FALSE) -> 0.0046948357 | R53: =VLOOKUP($A53,Drivers!$1:$1048576,MATCH(Summary!R$1,Drivers!$2:$2,0),FALSE) -> 0 | S53: =VLOOKUP($A53,Drivers!$1:$1048576,MATCH(Summary!S$1,Drivers!$2:$2,0),FALSE) -> 0 | U53: EV/Sales (x) | AA53: ='P&L'!AS166/H8 -> 1.6481979 | AB53: ='P&L'!AV166/I8 -> 1.5391689 | AC53: ='P&L'!AY166/J8 -> 1.488355 | AD53: ='P&L'!BB166/K8 -> 1.27811 | AE53: ='P&L'!BE166/L8 -> 1.1351628 | AF53: =VLOOKUP($AM53,'P&L'!$1:$1048576,MATCH(Summary!AF$1,'P&L'!$4:$4,0),FALSE)/M8 -> 1.102754 | AG53: =VLOOKUP($AM53,'P&L'!$1:$1048576,MATCH(Summary!AG$1,'P&L'!$4:$4,0),FALSE)/N8 -> 1.0057886 | AH53: =VLOOKUP($AM53,'P&L'!$1:$1048576,MATCH(Summary!AH$1,'P&L'!$4:$4,0),FALSE)/O8 -> 1.0057258 | AI53: =VLOOKUP($AM53,'P&L'!$1:$1048576,MATCH(Summary!AI$1,'P&L'!$4:$4,0),FALSE)/P8 -> 0.91260125 | AJ53: =VLOOKUP($AM53,'P&L'!$1:$1048576,MATCH(Summary!AJ$1,'P&L'!$4:$4,0),FALSE)/Q8 -> 0.86380797 | AK53: =VLOOKUP($AM53,'P&L'!$1:$1048576,MATCH(Summary!AK$1,'P&L'!$4:$4,0),FALSE)/R8 -> 0.82900431 | AL53: =VLOOKUP($AM53,'P&L'!$1:$1048576,MATCH(Summary!AL$1,'P&L'!$4:$4,0),FALSE)/S8 -> 0.79557358 | AM53: EV
A54: Stores_TGG | B54: Period end stores | C54: k | H54: =Drivers!T321 -> 102 | I54: =Drivers!U321 -> 103 | J54: =Drivers!X321 -> 105 | K54: =VLOOKUP($A54,Drivers!$1:$1048576,MATCH(Summary!K$1,Drivers!$2:$2,0),FALSE) -> 105 | L54: =VLOOKUP($A54,Drivers!$1:$1048576,MATCH(Summary!L$1,Drivers!$2:$2,0),FALSE) -> 105 | M54: =VLOOKUP($A54,Drivers!$1:$1048576,MATCH(Summary!M$1,Drivers!$2:$2,0),FALSE) -> 106 | N54: =VLOOKUP($A54,Drivers!$1:$1048576,MATCH(Summary!N$1,Drivers!$2:$2,0),FALSE) -> 106 | O54: =VLOOKUP($A54,Drivers!$1:$1048576,MATCH(Summary!O$1,Drivers!$2:$2,0),FALSE) -> 106 | P54: =VLOOKUP($A54,Drivers!$1:$1048576,MATCH(Summary!P$1,Drivers!$2:$2,0),FALSE) -> 107 | Q54: =VLOOKUP($A54,Drivers!$1:$1048576,MATCH(Summary!Q$1,Drivers!$2:$2,0),FALSE) -> 107 | R54: =VLOOKUP($A54,Drivers!$1:$1048576,MATCH(Summary!R$1,Drivers!$2:$2,0),FALSE) -> 107 | S54: =VLOOKUP($A54,Drivers!$1:$1048576,MATCH(Summary!S$1,Drivers!$2:$2,0),FALSE) -> 107 | U54: Dividend yield (%) | W54: =+D24/$N$4/100 -> 0.0081725312 | X54: =+E24/$N$4/100 -> 0.0095346198 | Y54: =+F24/$N$4/100 -> 0.010215664 | Z54: =+G24/$N$4/100 -> 0.011350738 | AA54: =+H24/$N$4/100 -> 0.013393871 | AB54: =+I24/$N$4/100 -> 0.014982974 | AC54: =+J24/$N$4/100 -> 0.016118048 | AD54: =+K24/$N$4/100 -> 0.021452894 | ... AL54: =+S24/$N$4/100 -> 0.042918239
U55: Dividend payout (%) | W55: =+D24/D23 -> 0.61526305 | X55: =+E24/E23 -> 0.66201232 | Y55: =+F24/F23 -> 0.65953147 | Z55: =+G24/G23 -> 0.65735539 | AA55: =+H24/H23 -> 0.64831362 | AB55: =+I24/I23 -> 0.65603774 | AC55: =+J24/J23 -> 0.65997598 | AD55: =+K24/K23 -> 0.672103 | ... AL55: =+S24/S23 -> 0.77281706
A56: MWEPS
A59: debt_issue_cost
A60: buyback_cost
A61: lease_payments
H68: 0.08
H69: 3200
H70: =H68*H69 -> 256
H74: 160
H75: 81.5

Sheet P&L
B2: JBH Profit & Loss Statement
B4: (A$mn, Year ending June) | C4: FY03 | D4: 1H04 | E4: 2H04 | F4: FY04 | G4: 1H05 | H4: 2H05 | I4: FY05 | J4: 1H06 | K4: 2H06 | L4: FY06 | M4: 1H07 | N4: 2H07 | O4: FY07 | P4: 1H08 | Q4: 2H08 | R4: FY08 | S4: 1H09 | T4: 2H09 | U4: FY09 | V4: 1H10 | W4: 2H10 | X4: FY10 | Y4: 1H11 | Z4: 2H11 | AA4: FY11 | AB4: 1H12 | AC4: 2H12 | AD4: FY12 | AE4: 1H13 | AF4: 2H13 | AG4: FY13 | AH4: 1H14 | AI4: 2H14 | AJ4: FY14 | AK4: 1H15 | AL4: 2H15 | AM4: FY15 | AN4: 1H16 | AO4: 2H16 | AP4: FY16 | AQ4: 1H17 | AR4: 2H17 | AS4: FY17 | AT4: 1H18 | AU4: 2H18 | AV4: FY18 | AW4: 1H19 | AX4: 2H19 | AY4: FY19 | AZ4: 1H20 | BA4: 2H20 | BB4: FY20 | BC4: 1H21 | BD4: 2H21 | BE4: FY21 | BF4: 1H22 | BG4: 2H22 | BH4: FY22 | BI4: 1H23 | BJ4: 2H23 | BK4: FY23 | BL4: 1H24 | BM4: 2H24 | BN4: FY24 | BO4: 1H25 | BP4: 2H25 | BQ4: FY25 | BR4: 1H26E | BS4: 2H26E | BT4: =Drivers!AS2 -> FY26E | BU4: 1H27E | BV4: 2H27E | BW4: =Drivers!AV2 -> FY27E | BX4: 1H28E | BY4: 2H28E | BZ4: =Drivers!AY2 -> FY28E | CA4: 1H29E | CB4: 2H29E | CC4: =Drivers!BB2 -> FY29E
A6: JBH_Sales | B6: Sales | C6: =VLOOKUP($A$6,Drivers!1:1048576,MATCH('P&L'!C4,Drivers!2:2,FALSE),FALSE) -> 355.835 | D6: =VLOOKUP($A$6,Drivers!1:1048576,MATCH('P&L'!D4,Drivers!2:2,FALSE),FALSE) -> 234.599 | E6: =VLOOKUP($A$6,Drivers!1:1048576,MATCH('P&L'!E4,Drivers!2:2,FALSE),FALSE) -> 217.758 | F6: =VLOOKUP($A$6,Drivers!1:1048576,MATCH('P&L'!F4,Drivers!2:2,FALSE),FALSE) -> 452.357 | G6: =VLOOKUP($A$6,Drivers!1:1048576,MATCH('P&L'!G4,Drivers!2:2,FALSE),FALSE) -> 376.177 | H6: =VLOOKUP($A$6,Drivers!1:1048576,MATCH('P&L'!H4,Drivers!2:2,FALSE),FALSE) -> 317.766 | I6: =VLOOKUP($A$6,Drivers!1:1048576,MATCH('P&L'!I4,Drivers!2:2,FALSE),FALSE) -> 693.943 | J6: =VLOOKUP($A$6,Drivers!1:1048576,MATCH('P&L'!J4,Drivers!2:2,FALSE),FALSE) -> 509.836 | ... CC6: =VLOOKUP($A$6,Drivers!1:1048576,MATCH('P&L'!CC4,Drivers!2:2,FALSE),FALSE) -> 12616.76
B7: Reported Growth (%) | F7: =F6/C6-1 -> 0.27125494 | G7: =G6/D6-1 -> 0.60348936 | H7: =H6/E6-1 -> 0.45926212 | I7: =I6/F6-1 -> 0.53406049 | J7: =J6/G6-1 -> 0.3553088 | K7: =K6/H6-1 -> 0.37203162 | L7: =L6/I6-1 -> 0.36296641 | M7: =M6/J6-1 -> 0.29237245 | ... U7: =U6/R6-1 -> 0.27272876 | V7: =V6/T6-1 -> 0.45798306 | W7: =W6/U6-1 -> -0.49402174 | X7: =X6/U6-1 -> 0.17361745 | Y7: =Y6/V6-1 -> 0.082933554 | Z7: =Z6/W6-1 -> 0.084135142 | AA7: =AA6/X6-1 -> 0.083451591 | AB7: =AB6/Y6-1 -> 0.054732639 | AC7: =AC6/Z6-1 -> 0.059880043 | AD7: =AD6/AA6-1 -> 0.056953224 | AE7: =AE6/AB6-1 -> 0.023394558 | ... CC7: =CC6/BZ6-1 -> 0.04207057
BF8: =108.4/BF6 -> 0.022296269 | BI8: =108.4/BI6 -> 0.020536137 | BJ8: =(BJ6+BL6)/(BI6+BG6)-1 -> -0.014374994 | BK8: =108.4/BK6 -> 0.0112607 | BL8: =108.4/BL6 -> 0.020999206 | BM8: =(BM6+BO6)/(BL6+BJ6)-1 -> 0.062113565 | BN8: =108.4/BN6 -> 0.011300613 | BO8: =108.4/BO6 -> 0.019116817 | BQ8: =108.4/BQ6 -> 0.010270209
A10: COGS | B10: Cost of Sales | C10: =C11-C6 -> -275.901 | D10: =D11-D6 -> -180.068 | E10: =E11-E6 -> -166.353 | F10: =F11-F6 -> -346.421 | G10: =G11-G6 -> -289.641 | H10: =H11-H6 -> -245.621 | I10: =I11-I6 -> -535.262 | J10: =J11-J6 -> -395.024 | ... CC10: =CC11-CC6 -> -9812.3039
A11: JBH_GP | B11: Gross Profit | C11: =VLOOKUP($A$11,Drivers!1:1048576,MATCH('P&L'!C4,Drivers!2:2,FALSE),FALSE) -> 79.934 | D11: =VLOOKUP($A$11,Drivers!1:1048576,MATCH('P&L'!D4,Drivers!2:2,FALSE),FALSE) -> 54.531 | E11: =VLOOKUP($A$11,Drivers!1:1048576,MATCH('P&L'!E4,Drivers!2:2,FALSE),FALSE) -> 51.405 | F11: =VLOOKUP($A$11,Drivers!1:1048576,MATCH('P&L'!F4,Drivers!2:2,FALSE),FALSE) -> 105.936 | G11: =VLOOKUP($A$11,Drivers!1:1048576,MATCH('P&L'!G4,Drivers!2:2,FALSE),FALSE) -> 86.536 | H11: =VLOOKUP($A$11,Drivers!1:1048576,MATCH('P&L'!H4,Drivers!2:2,FALSE),FALSE) -> 72.145 | I11: =VLOOKUP($A$11,Drivers!1:1048576,MATCH('P&L'!I4,Drivers!2:2,FALSE),FALSE) -> 158.681 | J11: =VLOOKUP($A$11,Drivers!1:1048576,MATCH('P&L'!J4,Drivers!2:2,FALSE),FALSE) -> 114.812 | ... CC11: =VLOOKUP($A$11,Drivers!1:1048576,MATCH('P&L'!CC4,Drivers!2:2,FALSE),FALSE) -> 2804.4564
A12: JBH_GM | B12: Gross Margin | C12: =C11/C6 -> 0.22463782 | D12: =D11/D6 -> 0.23244345 | E12: =E11/E6 -> 0.23606481 | F12: =F11/F6 -> 0.23418672 | G12: =G11/G6 -> 0.23004065 | H12: =H11/H6 -> 0.22703813 | I12: =I11/I6 -> 0.22866575 | J12: =J11/J6 -> 0.22519398 | ... CC12: =CC11/CC6 -> 0.22228023
B13: YoY change | F13: =F12-C12 -> 0.0095488916 | G13: =G12-D12 -> -0.0024028003 | H13: =H12-E12 -> -0.0090266709 | I13: =I12-F12 -> -0.0055209604 | J13: =J12-G12 -> -0.0048466618 | K13: =K12-H12 -> -0.0031451111 | L13: =L12-I12 -> -0.0040714607 | M13: =M12-J12 -> -0.0037818686 | ... CC13: =CC12-BZ12 -> -6.7739412e-05
BG14: =(BG11+BI11)/(BG6+BI6) -> 0.2298548
B15: Group
B16: Operating costs | Y16: =Y17/(Y17+Z17) -> 0.51574316 | Z16: =1-Y16 -> 0.48425684 | AB16: =AB17/(AB17+AC17) -> 0.51897307 | AC16: =1-AB16 -> 0.48102693 | AE16: =AE17/(AE17+AF17) -> 0.49936021 | AF16: =1-AE16 -> 0.50063979 | AH16: =AH17/(AH17+AI17) -> 0.51271599 | AI16: =1-AH16 -> 0.48728401 | AK16: =AK17/(AK17+AL17) -> 0.50049989 | AL16: =1-AK16 -> 0.49950011
B17: Sales & Marketing | C17: 42.267 | F17: 56.025 | G17: 42.101 | H17: =I17-G17 -> 42.629 | I17: 84.73 | J17: 58.203 | K17: =L17-J17 -> 55.718 | L17: 113.921 | M17: 70.349 | N17: =O17-M17 -> 71.671 | O17: 142.02 | P17: 100.388 | Q17: =R17-P17 -> 93.048 | R17: 193.436 | S17: 116.14 | T17: =U17-S17 -> 114.271 | U17: 230.411 | V17: 139.024 | W17: =X17-V17 -> 126.118 | X17: 265.142 | Y17: 147.927 | Z17: =AA17-Y17 -> 138.896 | AA17: 286.823 | AB17: 160.604 | AC17: =AD17-AB17 -> 148.861 | AD17: 309.465 | AE17: 168.2 | AF17: =AG17-AE17 -> 168.631 | AG17: 336.831 | AH17: 182.37 | AI17: =AJ17-AH17 -> 173.324 | AJ17: 355.694 | AK17: 187.229 | AL17: =AM17-AK17 -> 186.855 | AM17: 374.084 | AN17: 202.786 | AO17: =AP17-AN17 -> 201.789 | AP17: 404.575 | AQ17: 249.3 | AR17: =AS17-AQ17 -> 330.8 | AS17: 580.1 | AT17: 357.4 | AU17: =AV17-AT17 -> 337.7 | AV17: 695.1 | AW17: 379.3 | AX17: =AY17-AW17 -> 351.7 | AY17: 731 | AZ17: 395.7 | BA17: =BB17-AZ17 -> 390.7 | BB17: 786.4 | BE17: 845.8 | BF17: 448.3 | BG17: =BH17-BF17 -> 432.8 | BH17: 881.1 | BI17: 504.5 | BJ17: =BK17-BI17 -> 473.8 | BK17: 978.3 | BL17: 532.7 | BM17: =BN17-BL17 -> 506.4 | BN17: 1039.1 | BO17: 595.2 | BP17: =BQ17-BO17 -> 571.8 | BQ17: 1167 | BR17: 644.6
B18: - % of sales | C18: =C17/Drivers!F90 -> 0.11878258 | F18: =F17/Drivers!G90 -> 0.12385129 | G18: =G17/Drivers!BM90 -> 0.11191806 | H18: =H17/Drivers!BN90 -> 0.13415217 | I18: =I17/Drivers!H90 -> 0.12209937 | J18: =J17/Drivers!BO90 -> 0.11416024 | K18: =K17/Drivers!BP90 -> 0.12779797 | L18: =L17/Drivers!I90 -> 0.12044668 | M18: =M17/Drivers!BQ90 -> 0.10676766 | N18: =N17/Drivers!BR90 -> 0.115053 | O18: =O17/Drivers!J90 -> 0.11079412 | P18: =P17/Drivers!BS90 -> 0.10155158 | Q18: =Q17/Drivers!BT90 -> 0.11076853 | R18: =R17/Drivers!K90 -> 0.10578574 | S18: =S17/Drivers!BU90 -> 0.092060258 | T18: =T17/Drivers!BV90 -> 0.10722614 | U18: =U17/Drivers!L90 -> 0.099005013 | V18: =V17/Drivers!BW90 -> 0.089475046 | W18: =W17/Drivers!BX90 -> 0.1071024 | X18: =X17/Drivers!M90 -> 0.097074675 | Y18: =Y17/Drivers!BY90 -> 0.087913949 | Z18: =Z17/Drivers!BZ90 -> 0.10879988 | AA18: =AA17/Drivers!N90 -> 0.096924122 | AB18: =AB17/Drivers!CA90 -> 0.090494943 | AC18: =AC17/Drivers!CB90 -> 0.11001779 | AD18: =AD17/Drivers!O90 -> 0.098940403 | AE18: =AE17/Drivers!CC90 -> 0.092608498 | AF18: =AF17/Drivers!CD90 -> 0.11301195 | AG18: =AG17/Drivers!P90 -> 0.10181085 | AH18: =AH17/Drivers!CE90 -> 0.0940116 | AI18: =AI17/Drivers!CF90 -> 0.11226317 | AJ18: =AJ17/Drivers!Q90 -> 0.10210016 | AK18: =AK17/Drivers!CG90 -> 0.095274758 | AL18: =AL17/Drivers!CH90 -> 0.1107625 | AM18: =AM17/Drivers!R90 -> 0.10242883 | AN18: =AN17/Drivers!CI90 -> 0.095797606 | AO18: =AO17/Drivers!CJ90 -> 0.10980818 | AP18: =AP17/Drivers!S90 -> 0.10230835 | AQ18: =AQ17/Drivers!CK90 -> 0.10594535 | AR18: =AR17/Drivers!CL90 -> 0.16404662 | AS18: =AS17/Drivers!T7 -> 0.10307392 | AT18: =AT17/Drivers!CM90 -> 0.13799228 | AU18: =AU17/Drivers!CN90 -> 0.15612575 | AV18: =AV17/Drivers!U7 -> 0.10141079 | AW18: =AW17/Drivers!V90 -> 0.13980833 | AX18: =AX17/Drivers!W90 -> 0.15740243 | AY18: =AY17/Drivers!X7 -> 0.10302595 | AZ18: =AZ17/Drivers!Y90 -> 0.13895424 | BA18: =BA17/Drivers!Z90 -> 0.14565315 | BB18: =BB17/Drivers!AA7 -> 0.099306722 | BE18: =BE17/Drivers!AD7 -> 0.094862103 | BF18: =BF17/Drivers!AE90 -> 0.13098995 | BG18: =BG17/Drivers!AF90 -> 0.14330177 | BH18: =BH17/Drivers!AG7 -> 0.095439775 | BI18: =BI17/Drivers!AH90 -> 0.13509171 | BJ18: =BJ17/Drivers!AI7 -> 0.10897215 | BK18: =BK17/Drivers!AJ7 -> 0.10162678 | BL18: =BL17/Drivers!AK90 -> 0.14125477 | BM18: =BM17/Drivers!AL7 -> 0.11430377 | BN18: =BN17/Drivers!AM7 -> 0.10832534 | BO18: =BO17/Drivers!AN90 -> 0.14662627 | BP18: =BP17/Drivers!AO7 -> 0.11706658 | BQ18: =BQ17/Drivers!AP7 -> 0.11056581
B19: - growth | F19: =F17/C17-1 -> 0.32550216 | I19: =I17/F17-1 -> 0.51236055 | J19: =J17/G17-1 -> 0.38246122 | K19: =K17/H17-1 -> 0.3070445 | L19: =L17/I17-1 -> 0.34451788 | M19: =M17/J17-1 -> 0.2086834 | N19: =N17/K17-1 -> 0.28631681 | O19: =O17/L17-1 -> 0.24665338 | P19: =P17/M17-1 -> 0.42699967 | ... BB19: =BB17/AY17-1 -> 0.075786594 | BE19: =BE17/BB17-1 -> 0.075534079 | BF19: =IFERROR(BF17/BC17-1,"NA") -> NA | BG19: =IFERROR(BG17/BD17-1,"NA") -> NA | BH19: =BH17/BE17-1 -> 0.041735635 | BI19: =IFERROR(BI17/BF17-1,"NA") -> 0.12536248 | BJ19: =BJ17/BG17-1 -> 0.094731978 | BK19: =BK17/BH17-1 -> 0.11031665 | BL19: =IFERROR(BL17/BI17-1,"NA") -> 0.055896928 | BM19: =BM17/BJ17-1 -> 0.068805403 | BN19: =BN17/BK17-1 -> 0.062148625 | BO19: =IFERROR(BO17/BL17-1,"NA") -> 0.11732683 | BP19: =BP17/BM17-1 -> 0.12914692 | BQ19: =BQ17/BN17-1 -> 0.12308729
AC20: =AC21/Z21-1 -> 0.12039594 | AE20: =AE21/AB21-1 -> 0.070290783 | AF20: =AF21/AC21-1 -> 0.098072241 | AH20: =AH21/AE21-1 -> 0.071306632 | AI20: =AI21/AF21-1 -> 0.049613743
B21: Occupancy | C21: 9.754 | F21: 14.496 | G21: 10.309 | H21: =I21-G21 -> 12.681 | I21: 22.99 | J21: 14.975 | K21: =L21-J21 -> 18.206 | L21: 33.181 | M21: 20.589 | N21: =O21-M21 -> 26.226 | O21: 46.815 | P21: 30.095 | Q21: =R21-P21 -> 34.985 | R21: 65.08 | S21: 40.339 | T21: =U21-S21 -> 44.212 | U21: 84.551 | V21: 49.199 | W21: =X21-V21 -> 51.868 | X21: 101.067 | Y21: 56.509 | Z21: =AA21-Y21 -> 58.291 | AA21: 114.8 | AB21: 64.034 | AC21: =AD21-AB21 -> 65.309 | AD21: 129.343 | AE21: 68.535 | AF21: =AG21-AE21 -> 71.714 | AG21: 140.249 | AH21: 73.422 | AI21: =AJ21-AH21 -> 75.272 | AJ21: 148.694 | AK21: 78.416 | AL21: =AM21-AK21 -> 81.8 | AM21: 160.216 | AN21: 84.904 | AO21: =AP21-AN21 -> 88.888 | AP21: 173.792 | AQ21: 101.2 | AR21: =AS21-AQ21 -> 147.4 | AS21: 248.6 | AT21: 148.4 | AU21: =AV21-AT21 -> 157.3 | AV21: 305.7 | AW21: 151.4 | AX21: =AY21-AW21 -> 155 | AY21: 306.4 | AZ21: 153.5 | BA21: =BB21-AZ21 -> 159.6 | BB21: 313.1 | BE21: 293.6 | BF21: 148.5 | BG21: =BH21-BF21 -> 154.3 | BH21: 302.8 | BI21: 160 | BJ21: =BK21-BI21 -> 161.8 | BK21: 321.8 | BL21: 166.6 | BM21: =BN21-BL21 -> 161.4 | BN21: 328 | BO21: 170.5 | BP21: =BQ21-BO21 -> 179.1 | BQ21: 349.6 | BR21: 184.7
B22: - % of sales | C22: =C21/Drivers!F7 -> 0.027411581 | F22: =F21/Drivers!G7 -> 0.032045486 | G22: =G21/Drivers!BM90 -> 0.027404653 | H22: =H21/Drivers!BN90 -> 0.039906724 | I22: =I21/Drivers!H7 -> 0.033129522 | J22: =J21/Drivers!BO90 -> 0.02937219 | K22: =K21/Drivers!BP90 -> 0.041758317 | L22: =L21/Drivers!I7 -> 0.035081691 | M22: =M21/Drivers!BQ90 -> 0.031247629 | N22: =N21/Drivers!BR90 -> 0.04210043 | O22: =O21/Drivers!J7 -> 0.036521804 | P22: =P21/Drivers!BS90 -> 0.030443825 | Q22: =Q21/Drivers!BT90 -> 0.041647719 | R22: =R21/Drivers!K7 -> 0.03559077 | S22: =S21/Drivers!BU90 -> 0.031975364 | T22: =T21/Drivers!BV90 -> 0.041486308 | U22: =U21/Drivers!L7 -> 0.036330613 | V22: =V21/Drivers!BW90 -> 0.031664193 | W22: =W21/Drivers!BX90 -> 0.044047536 | X22: =X21/Drivers!M7 -> 0.037002988 | Y22: =Y21/Drivers!BY90 -> 0.033583655 | Z22: =Z21/Drivers!BZ90 -> 0.045660452 | AA22: =AA21/Drivers!N7 -> 0.038793574 | AB22: =AB21/Drivers!CA90 -> 0.036081002 | AC22: =AC21/Drivers!CB90 -> 0.048267523 | AD22: =AD21/Drivers!O7 -> 0.041352814 | AE22: =AE21/Drivers!CC90 -> 0.037734384 | AF22: =AF21/Drivers!CD90 -> 0.048060787 | AG22: =AG21/Drivers!P7 -> 0.042391791 | AH22: =AH21/Drivers!CE90 -> 0.037848987 | AI22: =AI21/Drivers!CF90 -> 0.0487542 | AJ22: =AJ21/Drivers!Q7 -> 0.042681861 | AK22: =AK21/Drivers!CG90 -> 0.039903356 | AL22: =AL21/Drivers!CH90 -> 0.048488786 | AM22: =AM21/Drivers!R7 -> 0.043869122 | AN22: =AN21/Drivers!CI90 -> 0.040109277 | AO22: =AO21/Drivers!CJ90 -> 0.048370473 | AP22: =AP21/Drivers!S7 -> 0.043948274 | AQ22: =AQ21/Drivers!CK90 -> 0.043007097 | AR22: =AR21/Drivers!CL90 -> 0.07309695 | AS22: =AS21/Drivers!T7 -> 0.044171997 | AT22: =AT21/Drivers!CM90 -> 0.057297297 | AU22: =AU21/Drivers!CN90 -> 0.07272307 | AV22: =AV21/Drivers!U7 -> 0.04459974 | AW22: =AW21/Drivers!V90 -> 0.055805381 | AX22: =AX21/Drivers!W90 -> 0.069369853 | AY22: =AY21/Drivers!X7 -> 0.043183516 | AZ22: =AZ21/Drivers!Y90 -> 0.05390315 | BA22: =BA21/Drivers!Z90 -> 0.059498956 | BB22: =BB21/Drivers!AA7 -> 0.03953832 | BE22: =BE21/Drivers!AD7 -> 0.032929196 | BF22: =BF21/Drivers!AE90 -> 0.043390603 | BG22: =BG21/Drivers!AF90 -> 0.051089332 | BH22: =BH21/Drivers!AG7 -> 0.03279896 | BI22: =BI21/Drivers!AH90 -> 0.042843754 | BJ22: =BJ21/Drivers!AI90 -> 0.052551236 | BK22: =BK21/Drivers!AJ90 -> 0.047230458 | BL22: =BL21/Drivers!AK90 -> 0.04417692 | BM22: =BM21/Drivers!AL90 -> 0.05136692 | BN22: =BN21/Drivers!AM90 -> 0.04744478 | BO22: =BO21/Drivers!AN90 -> 0.042002316 | BP22: =BP21/Drivers!AO90 -> 0.052594485 | BQ22: =BQ21/Drivers!AP90 -> 0.046834392
B23: D&A | C23: =Drivers!F44-C29 -> 0.98925 | F23: =Drivers!G44-F29 -> 2.376 | I23: =Drivers!H44-I29 -> 3.951 | L23: =Drivers!I44-L29 -> 5.57925 | O23: =Drivers!J44-O29 -> 8.1405 | R23: =Drivers!K44-R29 -> 11.01825 | S23: =Drivers!BU44-S29 -> 6.356375 | T23: =Drivers!BV44-T29 -> 7.705375 | U23: =Drivers!L44-U29 -> 14.06175 | V23: =Drivers!BW44-V29 -> 7.653 | W23: =Drivers!BX44-W29 -> 9.80475 | X23: =Drivers!M44-X29 -> 17.45775 | Y23: =Drivers!BY44-Y29 -> 9.74 | Z23: =Drivers!BZ44-Z29 -> 10.447 | AA23: =Drivers!N44-AA29 -> 20.187 | AB23: =Drivers!CA44-AB29 -> 11.663 | AC23: =Drivers!CB44-AC29 -> 14.469 | AD23: =Drivers!O44-AD29 -> 23.654 | AE23: =Drivers!CC44-AE29 -> 12.7 | AF23: =Drivers!CD44-AF29 -> 13.332 | AG23: =Drivers!P44-AG29 -> 26.032 | AH23: =Drivers!CE44-AH29 -> 13.7 | AI23: =Drivers!CF44-AI29 -> 14.43 | AJ23: =Drivers!Q44-AJ29 -> 28.43 | AK23: =Drivers!CG44-AK29 -> 15.074 | AL23: =AM23-AK23 -> 16.65 | AM23: =Drivers!R44-AM29 -> 31.724 | AN23: =Drivers!CI44-AN29 -> 17.046 | AO23: =AP23-AN23 -> 18.655 | AP23: =Drivers!S44-AP29 -> 35.701 | AQ23: =Drivers!CK44-AQ29 -> 20.5 | AR23: =AS23-AQ23 -> 27.94 | AS23: =Drivers!T44-AS29 -> 48.44 | AT23: =Drivers!CM44-AT29 -> 25.1 | AU23: =AV23-AT23 -> 30.267 | AV23: =Drivers!U44-AV29 -> 55.367 | AW23: =Drivers!V44-AW29 -> 23.3 | AX23: =Drivers!W44-AX29 -> 26.88035 | AY23: =Drivers!X44-AY29 -> 50.18035 | AZ23: =Drivers!Y44-AZ29 -> 104.6 | BA23: =Drivers!Z44-BA29 -> 110.3 | BB23: =Drivers!AA44-BB29 -> 229.3 | BE23: =Drivers!AD44-BE29 -> 218.5 | BF23: =Drivers!AE44-BF29 -> 108.5 | BG23: =Drivers!AF44-BG29 -> 110.8 | BH23: =Drivers!AG44-BH29 -> 219.3 | BI23: =Drivers!AH44-BI29 -> 113.4 | BJ23: =Drivers!AI44-BJ29 -> 110.8 | BK23: =Drivers!AJ44-BK29 -> 224.2 | BL23: =Drivers!AK44-BL29 -> 118.5 | ... BQ23: =Drivers!AP44-BQ29 -> 258.8
B24: Occupancy (ex D&A) | C24: =C21-C23 -> 8.76475 | F24: =F21-F23 -> 12.12 | I24: =I21-I23 -> 19.039 | L24: =L21-L23 -> 27.60175 | O24: =O21-O23 -> 38.6745 | R24: =R21-R23 -> 54.06175 | S24: =S21-S23 -> 33.982625 | T24: =T21-T23 -> 36.506625 | U24: =U21-U23 -> 70.48925 | V24: =V21-V23 -> 41.546 | W24: =W21-W23 -> 42.06325 | X24: =X21-X23 -> 83.60925 | Y24: =Y21-Y23 -> 46.769 | ... BB24: =BB21-BB23 -> 83.8 | BE24: =BE21-BE23 -> 75.1 | BF24: =BF21-BF23 -> 40 | BG24: =BG21-BG23 -> 43.5 | BH24: =BH21-BH23 -> 83.5 | BI24: =BI21-BI23 -> 46.6 | BJ24: =BJ21-BJ23 -> 51 | BK24: =BK21-BK23 -> 97.6 | BL24: =BL21-BL23 -> 48.1 | ... BQ24: =BQ21-BQ23 -> 90.8
B25: Min lease payment | C25: =Drivers!F425 -> 4.683 | F25: =Drivers!G425 -> 7.139 | I25: =Drivers!H425 -> 12.217 | L25: =Drivers!I425 -> 16.872 | O25: =Drivers!J425 -> 28.074 | R25: =Drivers!K425 -> 38.511 | U25: =Drivers!L425 -> 49.806 | X25: =Drivers!M425 -> 58.379 | AA25: =Drivers!N425 -> 65.722 | AD25: =Drivers!O425 -> 73.225 | AG25: =Drivers!P425 -> 82.056 | AJ25: =Drivers!Q425 -> 87.114 | AM25: =Drivers!R425 -> 94.672 | AO25: =AO21/AL21-1 -> 0.086650367 | AP25: =Drivers!S425 -> 102.29 | AS25: =Drivers!T425 -> 152.4 | AV25: =Drivers!U425 -> 193.1 | AY25: =Drivers!X425 -> 0 | BB25: =Drivers!AA425 -> 0 | BE25: =Drivers!AD425 -> 0 | BH25: =Drivers!AG425 -> 0
B26: Occupancy (ex D&A) % sales | C26: =C24/C6 -> 0.024631501 | F26: =F24/F6 -> 0.026792998 | I26: =I24/I6 -> 0.027435971 | L26: =L24/L6 -> 0.029182847 | O26: =O24/O6 -> 0.030171153 | R26: =R24/R6 -> 0.02956514 | U26: =U24/U6 -> 0.030288437 | X26: =X24/X6 -> 0.030611298 | AA26: =AA24/AA6 -> 0.03197192 | AD26: =AD24/AD6 -> 0.03379029 | AE26: =AE27/AC27-1 -> 0.1576999 | AF26: =AF27/AD27-1 -> -0.50716826 | AG26: =AG24/AG6 -> 0.034523335 | AH26: =AH27/AF27-1 -> 0.11013216 | AI26: =AI27/AG27-1 -> -0.52333052 | AJ26: =AJ24/AJ6 -> 0.034521173 | AM26: =AM24/AM6 -> 0.035182699 | AP26: =AP24/AP6 -> 0.034920256 | AS26: =AS24/AS6 -> 0.035565032 | AV26: =AV24/AV6 -> 0.036522037 | AY26: =AY24/AY6 -> 0.036111179 | BB26: =BB24/BB6 -> 0.010582278 | BE26: =BE24/BE6 -> 0.0084229652 | BH26: =BH24/BH6 -> 0.0090446274
B27: Administration | C27: 5.186 | F27: 6.923 | G27: 5.412 | H27: =I27-G27 -> 3.773 | I27: 9.185 | J27: 6.213 | K27: =L27-J27 -> 6.018 | L27: 12.231 | M27: 7.497 | N27: =O27-M27 -> 8.202 | O27: 15.699 | P27: 9.465 | Q27: =R27-P27 -> 9.526 | R27: 18.991 | S27: 10.885 | T27: =U27-S27 -> 10.403 | U27: 21.288 | V27: 12.922 | W27: =X27-V27 -> 11.989 | X27: 24.911 | Y27: 13.713 | Z27: =AA27-Y27 -> 13.185 | AA27: 26.898 | AB27: 14.559 | AC27: =AD27-AB27 -> 12.156 | AD27: 26.715 | AE27: 14.073 | AF27: =AG27-AE27 -> 13.166 | AG27: 27.239 | AH27: 14.616 | AI27: =AJ27-AH27 -> 12.984 | AJ27: 27.6 | AK27: 13.485 | AL27: =AM27-AK27 -> 14.226 | AM27: 27.711 | AN27: 13.874 | AO27: =AP27-AN27 -> 13.3 | AP27: 27.174 | AQ27: 15.8 | AR27: =AS27-AQ27 -> 20.4 | AS27: 36.2 | AT27: 25.6 | AU27: =AV27-AT27 -> 22.6 | AV27: 48.2 | AW27: 24.6 | AX27: =AY27-AW27 -> 19.9 | AY27: 44.5 | AZ27: 21.3 | BA27: =BB27-AZ27 -> 20.4 | BB27: 41.7 | BE27: 41.3 | BF27: 20.7 | BG27: =BH27-BF27 -> 21.1 | BH27: 41.8 | BI27: 25.2 | BJ27: =+BK27-BI27 -> 20.8 | BK27: 46 | BL27: 23.9 | BM27: =+BN27-BL27 -> 24.2 | BN27: 48.1 | BO27: 27.3 | BP27: =+BQ27-BO27 -> 25.4 | BQ27: 52.7 | BR27: 28.7
B28: - % of sales | C28: =C27/Drivers!F90 -> 0.014574171 | F28: =F27/Drivers!G90 -> 0.015304284 | G28: =G27/Drivers!BM90 -> 0.014386844 | H28: =H27/Drivers!BN90 -> 0.011873517 | I28: =I27/Drivers!H90 -> 0.013235957 | J28: =J27/Drivers!BO90 -> 0.012186272 | K28: =K27/Drivers!BP90 -> 0.013803227 | L28: =L27/Drivers!I7 -> 0.012931622 | M28: =M27/Drivers!BQ90 -> 0.011378089 | N28: =N27/Drivers!BR90 -> 0.013166618 | O28: =O27/Drivers!J7 -> 0.012247267 | P28: =P27/Drivers!BS90 -> 0.009574707 | Q28: =Q27/Drivers!BT90 -> 0.011340179 | R28: =R27/Drivers!K7 -> 0.010385745 | S28: =S27/Drivers!BU90 -> 0.0086281722 | T28: =T27/Drivers!BV90 -> 0.0097616498 | U28: =U27/Drivers!L7 -> 0.0091472139 | V28: =V27/Drivers!BW90 -> 0.0083165248 | W28: =W27/Drivers!BX90 -> 0.010181343 | X28: =X27/Drivers!M7 -> 0.0091204985 | Y28: =Y27/Drivers!BY90 -> 0.0081497224 | Z28: =Z27/Drivers!BZ90 -> 0.010328062 | AA28: =AA27/Drivers!N7 -> 0.009089456 | AB28: =AB27/Drivers!CA90 -> 0.008203506 | AC28: =AC27/Drivers!CB90 -> 0.0089840606 | AD28: =AD27/Drivers!O7 -> 0.008541169 | AE28: =AE27/Drivers!CC90 -> 0.0077483912 | AF28: =AF27/Drivers!N90 -> 0.0044490958 | AG28: =AG27/Drivers!P7 -> 0.008233285 | AH28: =AH27/Drivers!CE90 -> 0.0075345372 | AI28: =AI27/Drivers!CF90 -> 0.0084098275 | AJ28: =AJ27/Drivers!Q7 -> 0.0079224405 | AK28: =AK27/Drivers!CG90 -> 0.0068620786 | AL28: =AL27/Drivers!CH90 -> 0.0084327808 | AM28: =AM27/Drivers!R7 -> 0.0075876145 | AN28: =AN27/Drivers!CI90 -> 0.0065541802 | AO28: =AO27/Drivers!CJ90 -> 0.0072375044 | AP28: =AP27/Drivers!S7 -> 0.0068717225 | AQ28: =AQ27/Drivers!CK90 -> 0.0067145468 | AR28: =AR27/Drivers!CL90 -> 0.010116539 | AS28: =AS27/Drivers!T7 -> 0.0064321251 | AT28: =AT27/Drivers!CM90 -> 0.0098841699 | AU28: =AU27/Drivers!CN90 -> 0.010448451 | AV28: =AV27/Drivers!U7 -> 0.0070320821 | AW28: =AW27/Drivers!V90 -> 0.009067453 | AX28: =AX27/Drivers!W90 -> 0.0089061941 | AY28: =AY27/Drivers!X7 -> 0.0062717574 | AZ28: =AZ27/Drivers!Y90 -> 0.0074797205 | BA28: =BA27/Drivers!Z90 -> 0.0076051297 | BF28: =BF27/Drivers!AE90 -> 0.0060483871 | BG28: =BG27/Drivers!AF90 -> 0.0069862923 | BI28: =BI27/Drivers!AH90 -> 0.0067478913 | BJ28: =BJ27/Drivers!AI90 -> 0.0067556595 | BK28: =BK27/Drivers!AJ90 -> 0.0067514016 | BL28: =BL27/Drivers!AK90 -> 0.0063375053 | BM28: =BM27/Drivers!AL90 -> 0.0077018554 | BN28: =BN27/Drivers!AM90 -> 0.0069576035 | BO28: =BO27/Drivers!AN90 -> 0.0067252975 | BP28: =BP27/Drivers!AO90 -> 0.007458961 | BQ28: =BQ27/Drivers!AP90 -> 0.0070599898
B29: D&A | C29: =Drivers!F44*25% -> 0.32975 | F29: =Drivers!G44*25% -> 0.792 | I29: =Drivers!H44*25% -> 1.317 | L29: =Drivers!I44*25% -> 1.85975 | O29: =Drivers!J44*25% -> 2.7135 | R29: =Drivers!K44*25% -> 3.67275 | S29: =U29/2 -> 2.343625 | T29: =U29-S29 -> 2.343625 | U29: =Drivers!L44*25% -> 4.68725 | V29: =AA29/2 -> 3.55 | W29: =X29-V29 -> 2.26925 | X29: =Drivers!M44*25% -> 5.81925 | Y29: =AA29/2 -> 3.55 | Z29: =AD29/2 -> 3.55 | AA29: 7.1 | AB29: 3.7 | AC29: =AD29-AB29 -> 3.4 | AD29: 7.1 | AE29: 3.4 | AF29: =AG29-AE29 -> 3.8 | AG29: 7.2 | AH29: 3.7 | AI29: =AM29-AH29 -> 3.7 | AJ29: 7.1 | AK29: =AM29/2 -> 3.7 | AL29: =AM29-AK29 -> 3.7 | AM29: 7.4 | AN29: =AS29/2 -> 2.73 | AO29: =AP29-AN29 -> 2.47 | AP29: 5.2 | AQ29: 2.6 | AR29: =AS29-AQ29 -> 2.86 | AS29: =AP29*1.05 -> 5.46 | AT29: 5.4 | AU29: =AV29-AT29 -> 0.333 | AV29: =AS29*1.05 -> 5.733 | AW29: 4.4 | AX29: =AY29-AW29 -> 1.61965 | AY29: =AV29*1.05 -> 6.01965 | AZ29: 4.5 | BA29: =BB29-AZ29 -> -4.5 | BF29: =BN29-BD29 -> 0 | BG29: =BH29-BF29 -> 0 | BI29: =BQ29-BG29 -> 0 | BJ29: =BR29-BH29 -> 0 | BK29: =BS29-BI29 -> 0 | BL29: =BT29-BJ29 -> 0 | BM29: =BU29-BK29 -> 0 | BN29: =BV29-BL29 -> 0 | BO29: =BW29-BM29 -> 0 | BP29: =BX29-BN29 -> 0 | BQ29: =BY29-BO29 -> 0
B30: Administration (ex D&A) | C30: =C27-C29 -> 4.85625 | F30: =F27-F29 -> 6.131 | I30: =I27-I29 -> 7.868 | L30: =L27-L29 -> 10.37125 | O30: =O27-O29 -> 12.9855 | R30: =R27-R29 -> 15.31825 | S30: =S27-S29 -> 8.541375 | T30: =T27-T29 -> 8.059375 | U30: =U27-U29 -> 16.60075 | V30: =V27-V29 -> 9.372 | W30: =W27-W29 -> 9.71975 | X30: =X27-X29 -> 19.09175 | Y30: =Y27-Y29 -> 10.163 | ... BA30: =BA27-BA29 -> 24.9 | BF30: =BF27-BF29 -> 20.7 | BG30: =BG27-BG29 -> 21.1 | BI30: =BI27-BI29 -> 25.2 | BJ30: =BJ27-BJ29 -> 20.8 | BK30: =BK27-BK29 -> 46 | BL30: =BL27-BL29 -> 23.9 | BM30: =BM27-BM29 -> 24.2 | BN30: =BN27-BN29 -> 48.1 | BO30: =BO27-BO29 -> 27.3 | BP30: =BP27-BP29 -> 25.4 | BQ30: =BQ27-BQ29 -> 52.7
B31: - Management/Directors comp. | F31: =1.318+0.608 -> 1.926 | I31: =1.651+1.449 -> 3.1 | L31: =2.664+1.754 -> 4.418 | O31: 5.048 | R31: 6.216 | U31: 7.295 | X31: 9.440311 | AA31: 6.451211 | AD31: 3.792752 | AG31: 9.331304 | AJ31: 10.779664 | AM31: 8.036353 | AP31: 9.739503 | AS31: 11.121 | AV31: 12.1468 | AY31: 12.779452
B32: - growth | I32: =I31/F31-1 -> 0.60955348 | L32: =L31/I31-1 -> 0.42516129 | O32: =O31/L31-1 -> 0.14259846 | R32: =R31/O31-1 -> 0.23137876 | U32: =U31/R31-1 -> 0.1735843 | X32: =X31/U31-1 -> 0.29407964 | AA32: =AA31/X31-1 -> -0.31663152 | AD32: =AD31/AA31-1 -> -0.41208682 | AG32: =AG31/AD31-1 -> 1.460299 | AJ32: =AJ31/AG31-1 -> 0.15521518 | AM32: =AM31/AJ31-1 -> -0.25448947 | AP32: =AP31/AM31-1 -> 0.21193071 | AS32: =AS31/AP31-1 -> 0.14184471 | AV32: =AV31/AS31-1 -> 0.092239906 | AY32: =AY31/AV31-1 -> 0.052083841
B33: - Other admin cost | F33: =F30-F31 -> 4.205 | I33: =I30-I31 -> 4.768 | L33: =L30-L31 -> 5.95325 | O33: =O30-O31 -> 7.9375 | R33: =R30-R31 -> 9.10225 | U33: =U30-U31 -> 9.30575 | V33: =V27/S27-1 -> 0.18713826 | W33: =W27/T27-1 -> 0.15245602 | X33: =X30-X31 -> 9.651439 | Y33: =Y27/V27-1 -> 0.061213434 | Z33: =Z27/W27-1 -> 0.099758112 | AA33: =AA30-AA31 -> 13.346789 | AB33: =AB27/Y27-1 -> 0.061693284 | AC33: =AC27/Z27-1 -> -0.078043231 | AD33: =AD30-AD31 -> 15.822248 | AE33: =AE27/AB27-1 -> -0.033381414 | AF33: =AF27/AC27-1 -> 0.083086542 | AG33: =AG30-AG31 -> 10.707696 | AH33: =AH27/AE27-1 -> 0.038584524 | AI33: =AI27/AF27-1 -> -0.013823485 | AJ33: =AJ30-AJ31 -> 9.720336 | AK33: =AK27/AH27-1 -> -0.077380952 | AL33: =AL27/AI27-1 -> 0.095656192 | AM33: =AM30-AM31 -> 12.274647 | AN33: =AN27/AK27-1 -> 0.028846867 | AO33: =AO27/AL27-1 -> -0.065092085 | AP33: =AP30-AP31 -> 12.234497 | AQ33: =AQ27/AN27-1 -> 0.13882082 | AR33: =AR27/AO27-1 -> 0.53383459 | AS33: =AS30-AS31 -> 19.619 | AT33: =AT27/AQ27-1 -> 0.62025316 | AU33: =AU27/AR27-1 -> 0.10784314 | AV33: =AV30-AV31 -> 30.3202 | AW33: =AW27/AT27-1 -> -0.0390625 | AX33: =AX27/AU27-1 -> -0.11946903 | AY33: =AY30-AY31 -> 25.700898 | AZ33: =AZ27/AW27-1 -> -0.13414634 | BA33: =BA27/AX27-1 -> 0.025125628 | BF33: =IFERROR(BF27/BC27-1,"NA") -> NA | BG33: =IFERROR(BG27/BD27-1,"NA") -> NA | BI33: =IFERROR(BI27/BF27-1,"NA") -> 0.2173913 | BJ33: =IFERROR(BJ27/BG27-1,"NA") -> -0.014218009 | BK33: =IFERROR(BK27/BH27-1,"NA") -> 0.10047847 | BL33: =IFERROR(BL27/BI27-1,"NA") -> -0.051587302 | BM33: =IFERROR(BM27/BJ27-1,"NA") -> 0.16346154 | BN33: =IFERROR(BN27/BK27-1,"NA") -> 0.045652174 | BO33: =IFERROR(BO27/BL27-1,"NA") -> 0.14225941 | BP33: =IFERROR(BP27/BM27-1,"NA") -> 0.049586777 | BQ33: =IFERROR(BQ27/BN27-1,"NA") -> 0.095634096
B34: - growth | I34: =I33/F33-1 -> 0.13388823 | L34: =L33/I33-1 -> 0.24858431 | O34: =O33/L33-1 -> 0.33330534 | R34: =R33/O33-1 -> 0.14674016 | U34: =U33/R33-1 -> 0.02235711 | X34: =X33/U33-1 -> 0.037147892 | AA34: =AA33/X33-1 -> 0.38288073 | AD34: =AD33/AA33-1 -> 0.18547225 | AG34: =AG33/AD33-1 -> -0.32325065 | AJ34: =AJ33/AG33-1 -> -0.092210313 | AM34: =AM33/AJ33-1 -> 0.26278011 | AP34: =AP33/AM33-1 -> -0.0032709698 | AS34: =AS33/AP33-1 -> 0.60358043 | AV34: =AV33/AS33-1 -> 0.54545084 | AY34: =AY33/AV33-1 -> -0.15235064
F35: =F31/Drivers!G90 -> 0.0042576991 | I35: =I31/Drivers!H90 -> 0.0044672257 | L35: =L31/Drivers!I90 -> 0.0046710741 | O35: =O31/Drivers!J90 -> 0.0039380982 | R35: =R31/Drivers!K90 -> 0.0033993888 | U35: =U31/Drivers!L90 -> 0.0031345794 | X35: =X31/Drivers!M90 -> 0.0034563182 | AA35: =AA31/Drivers!N90 -> 0.0021800133 | AD35: =AD31/Drivers!O90 -> 0.0012125973 | AE35: =AE36/AB36-1 -> -0.031260997 | AF35: =AF36/AC36-1 -> -0.13324497 | AG35: =AG31/Drivers!P90 -> 0.0028204885 | AH35: =AH36/AE36-1 -> -0.0081733971 | AI35: =AI36/AF36-1 -> 0.18948442 | AJ35: =AJ31/Drivers!Q90 -> 0.003094248 | AM35: =AM31/Drivers!R90 -> 0.0022004528 | AP35: =AP31/Drivers!S90 -> 0.0024629117 | AS35: =AS31/Drivers!T90 -> 0.0025450842 | AV35: =AV31/Drivers!U90 -> 0.002555607 | AY35: =AY31/Drivers!X90 -> 0.0025830642
B36: Other expenses | C36: 6.789 | F36: 6.235 | I36: 7.64 | L36: 9.603 | O36: =13.922 -> 13.922 | P36: 9.728 | Q36: =R36-P36 -> 10.676 | R36: =20.404 -> 20.404 | S36: 13.043 | T36: =U36-S36 -> 12.422 | U36: 25.465 | V36: 15.358 | W36: =X36-V36 -> 12.848 | X36: 28.206 | Y36: 17.084 | Z36: =AA36-Y36 -> 10.574 | AA36: 27.658 | AB36: 17.05 | AC36: =AD36-AB36 -> 15.843 | AD36: 32.893 | AE36: 16.517 | AF36: =AG36-AE36 -> 13.732 | AG36: 30.249 | AH36: 16.382 | AI36: =AJ36-AH36 -> 16.334 | AJ36: 32.716 | AK36: 18.162 | AL36: =AM36-AK36 -> 17.252 | AM36: 35.414 | AN36: 19.853 | AO36: =AP36-AN36 -> 18.864 | AP36: =38.717 -> 38.717 | AQ36: 24.2 | AR36: =AS36-AQ36 -> 51.1 | AS36: =75.3 -> 75.3 | AT36: 37.1 | AU36: =AV36-AT36 -> 40.1 | AV36: 77.2 | AW36: 36.9 | AX36: =AY36-AW36 -> 37.1 | AY36: 74 | AZ36: 34.9 | BA36: =BB36-AZ36 -> 37.2 | BB36: 72.1 | BE36: 54.7 | BF36: 28.3 | BG36: =BH36-BF36 -> 34 | BH36: 62.3 | BI36: 34.5 | BJ36: =+BK36-BI36 -> 36.1 | BK36: 70.6 | BL36: 37.9 | BM36: =+BN36-BL36 -> 41.9 | BN36: 79.8 | BO36: 41.4 | BP36: =+BQ36-BO36 -> 56.6 | BQ36: 98 | BR36: 48.2
B37: - % of sales | C37: =C36/Drivers!F7 -> 0.019079068 | F37: =F36/Drivers!G7 -> 0.013783361 | I37: =I36/Drivers!H7 -> 0.01100955 | L37: =L36/Drivers!I7 -> 0.010153084 | O37: =O36/Drivers!J7 -> 0.010860975 | P37: =P36/Drivers!BS90 -> 0.0098407554 | Q37: =Q36/Drivers!BT90 -> 0.012709191 | R37: =R36/Drivers!K7 -> 0.011158483 | S37: =S36/Drivers!BU90 -> 0.010338746 | T37: =T36/Drivers!BV90 -> 0.011656177 | U37: =U36/Drivers!L7 -> 0.010942024 | V37: =V36/Drivers!BW90 -> 0.0098843204 | W37: =W36/Drivers!BX90 -> 0.010910826 | X37: =X36/Drivers!M7 -> 0.010326875 | Y37: =Y36/Drivers!BY90 -> 0.010153129 | Z37: =Z36/Drivers!BZ90 -> 0.0082828158 | AA37: =AA36/Drivers!N7 -> 0.0093462776 | AD37: =AD36/Drivers!O7 -> 0.010516364 | AE37: =AE36/Drivers!CC90 -> 0.0090940224 | AF37: =AF36/Drivers!CD90 -> 0.0092028158 | AG37: =AG36/Drivers!P7 -> 0.0091430903 | AH37: =AH36/Drivers!CE90 -> 0.0084449089 | AI37: =AI36/Drivers!CF90 -> 0.010579646 | AJ37: =AJ36/Drivers!Q7 -> 0.0093909624 | AK37: =AK36/Drivers!CG90 -> 0.009242052 | AL37: =AL36/Drivers!CH90 -> 0.01022651 | AM37: =AM36/Drivers!R7 -> 0.0096967911 | AN37: =AN36/Drivers!CI90 -> 0.009378704 | AO37: =AO36/Drivers!CJ90 -> 0.010265284 | AP37: =AP36/Drivers!S7 -> 0.0097907 | AQ37: =AQ36/AQ6 -> 0.0092500573 | AR37: =AR36/Drivers!CL90 -> 0.025340937 | AS37: =AS36/Drivers!T7 -> 0.013379531 | AT37: =AT36/AT6 -> 0.010054746 | AU37: =AU36/Drivers!CN90 -> 0.018539066 | AV37: =AV36/Drivers!U7 -> 0.011263003 | AW37: =AW36/AW6 -> 0.0096001249 | AX37: =AX36/AX6 -> 0.011409767 | AY37: =AY36/Drivers!X7 -> 0.010429439 | AZ37: =AZ36/AZ6 -> 0.0087354826 | BA37: =BA36/BA6 -> 0.0094808472 | BB37: =BB36/Drivers!AA7 -> 0.0091047999 | BE37: =BE36/Drivers!AD7 -> 0.0061349693 | BF37: =BF36/BF6 -> 0.0058208894 | BG37: =BG36/BG6 -> 0.0077799643 | BH37: =BH36/Drivers!AG7 -> 0.0067482669 | BI37: =BI36/BI6 -> 0.0065359477 | BJ37: =BJ36/BJ6 -> 0.0083028589 | BK37: =BK36/Drivers!AJ7 -> 0.0073339982 | BL37: =BL36/BL6 -> 0.0073419732 | BM37: =BM36/BM6 -> 0.0094575988 | BN37: =BN36/Drivers!AM7 -> 0.0083190859 | BO37: =BO36/BO6 -> 0.0073010722 | BP37: =BP36/BP6 -> 0.011587913 | BQ37: =BQ36/Drivers!AP7 -> 0.0092848751
B38: Merchant fees on credit card transactions | C38: =C39*Drivers!F90 -> 1.310291 | F38: =F39*Drivers!G90 -> 1.6657139 | I38: =I39*Drivers!H90 -> 2.5553058 | L38: =L39*Drivers!I90 -> 3.482796 | O38: =O39*Drivers!J90 -> 4.7201075 | R38: =33%*R36 -> 6.73332 | U38: =33%*U36 -> 8.40345 | X38: =33%*X36 -> 9.30798 | AA38: =33%*AA36 -> 9.12714 | AD38: =33%*AD36 -> 10.85469 | AG38: =33%*AG36 -> 9.98217 | AJ38: =33%*AJ36 -> 10.79628 | AM38: =33%*AM36 -> 11.68662 | AP38: =33%*AP36 -> 12.77661 | AS38: =AS39*Drivers!T7 -> 18.0096 | AV38: =AV39*Drivers!U7 -> 21.93376 | AY38: =AY39*Drivers!X7 -> 22.70496 | BB38: =BB39*Drivers!AA7 -> 25.34048 | BE38: =BE39*Drivers!AD7 -> 28.53152 | BH38: =BH39*Drivers!AG7 -> 29.5424 | BI38: =BI39*Drivers!AH7 -> 16.8912 | BJ38: =BJ39*Drivers!AI7 -> 13.91328 | BK38: =BK39*Drivers!AJ7 -> 30.80448 | BL38: =BL39*Drivers!AK7 -> 16.51872 | BM38: =BM39*Drivers!AL7 -> 14.17696 | BN38: =BN39*Drivers!AM7 -> 30.69568 | BO38: =BO39*Drivers!AN7 -> 18.14528 | ... BQ38: =BQ39*Drivers!AP7 -> 33.77536
B39: - % of sales | C39: =F39 -> 0.0036822993 | F39: =I39 -> 0.0036822993 | I39: =L39 -> 0.0036822993 | L39: =O39 -> 0.0036822993 | O39: =R39 -> 0.0036822993 | R39: =R38/Drivers!K90 -> 0.0036822993 | U39: =U38/Drivers!L90 -> 0.0036108679 | X39: =X38/Drivers!M90 -> 0.0034078687 | AA39: =AA38/Drivers!N90 -> 0.0030842716 | AD39: =AD38/Drivers!O90 -> 0.0034704002 | AG39: =AG38/Drivers!P90 -> 0.0030172198 | AJ39: =AJ38/Drivers!Q90 -> 0.0030990176 | AM39: =AM38/Drivers!R90 -> 0.0031999411 | AP39: =AP38/Drivers!S90 -> 0.003230931 | AS39: 0.0032 | AV39: 0.0032 | AY39: 0.0032 | BB39: 0.0032 | BE39: 0.0032 | BH39: 0.0032 | BI39: 0.0032 | BJ39: 0.0032 | BK39: 0.0032 | BL39: 0.0032 | BM39: 0.0032 | BN39: 0.0032 | BO39: 0.0032 | BP39: 0.0032 | BQ39: 0.0032
B40: "Other" other expenses | C40: =C36-C38 -> 5.478709 | F40: =F36-F38 -> 4.5692861 | I40: =I36-I38 -> 5.0846942 | L40: =L36-L38 -> 6.120204 | O40: =O36-O38 -> 9.2018925 | R40: =R36-R38 -> 13.67068 | U40: =U36-U38 -> 17.06155 | X40: =X36-X38 -> 18.89802 | AA40: =AA36-AA38 -> 18.53086 | AD40: =AD36-AD38 -> 22.03831 | AG40: =AG36-AG38 -> 20.26683 | AJ40: =AJ36-AJ38 -> 21.91972 | AM40: =AM36-AM38 -> 23.72738 | AP40: =AP36-AP38 -> 25.94039 | AS40: =AS36-AS38 -> 57.2904 | AV40: =AV36-AV38 -> 55.26624 | AY40: =AY36-AY38 -> 51.29504 | BB40: =BB36-BB38 -> 46.75952 | BE40: =BE36-BE38 -> 26.16848 | BH40: =BH36-BH38 -> 32.7576 | BI40: =BI36-BI38 -> 17.6088 | BJ40: =BJ36-BJ38 -> 22.18672 | BK40: =BK36-BK38 -> 39.79552 | BL40: =BL36-BL38 -> 21.38128 | BM40: =BM36-BM38 -> 27.72304 | BN40: =BN36-BN38 -> 49.10432 | BO40: =BO36-BO38 -> 23.25472 | ... BQ40: =BQ36-BQ38 -> 64.22464
B41: - % of sales | C41: =C40/Drivers!F90 -> 0.015396768 | F41: =F40/Drivers!G90 -> 0.010101062 | I41: =I40/Drivers!H7 -> 0.0073272504 | L41: =L40/Drivers!I7 -> 0.0064707846 | O41: =O40/Drivers!J7 -> 0.007178676 | R41: =R40/Drivers!K7 -> 0.0074761835 | U41: =U40/Drivers!L7 -> 0.007331156 | X41: =X40/Drivers!M7 -> 0.0069190062 | AA41: =AA40/Drivers!N7 -> 0.006262006 | AD41: =AD40/Drivers!O7 -> 0.0070459641 | AG41: =AG40/Drivers!P7 -> 0.0061258705 | AJ41: =AJ40/Drivers!Q7 -> 0.0062919448 | AM41: =AM40/Drivers!R7 -> 0.0064968501 | AP41: =AP40/Drivers!S7 -> 0.006559769 | AS41: =AS40/Drivers!T7 -> 0.010179531 | AV41: =AV40/Drivers!U7 -> 0.0080630028 | AY41: =AY40/Drivers!X7 -> 0.0072294392 | BB41: =BB40/Drivers!AA7 -> 0.0059047999 | BE41: =BE40/Drivers!AD7 -> 0.0029349693 | BH41: =BH40/Drivers!AG7 -> 0.0035482669 | BI41: =BI40/Drivers!AH7 -> 0.0033359477 | BJ41: =BJ40/Drivers!AI7 -> 0.0051028589 | BK41: =BK40/Drivers!AJ7 -> 0.0041339982 | BL41: =BL40/Drivers!AK7 -> 0.0041419732 | BM41: =BM40/Drivers!AL7 -> 0.0062575988 | BN41: =BN40/Drivers!AM7 -> 0.0051190859 | BO41: =BO40/Drivers!AN7 -> 0.0041010722 | ... BQ41: =BQ40/Drivers!AP7 -> 0.0060848751
S42: =S36/P36-1 -> 0.34076891 | T42: =T36/Q36-1 -> 0.1635444 | V42: =V36/S36-1 -> 0.17748984 | W42: =W36/T36-1 -> 0.034293995 | Y42: =Y36/V36-1 -> 0.11238443 | Z42: =Z36/W36-1 -> -0.17699253 | AB42: =AB36/Y36-1 -> -0.0019901662 | AC42: =AC36/Z36-1 -> 0.49829771 | AE42: =AE36/AB36-1 -> -0.031260997 | AF42: =AF36/AC36-1 -> -0.13324497 | AH42: =AH36/AE36-1 -> -0.0081733971 | AI42: =AI36/AF36-1 -> 0.18948442 | AK42: =AK36/AH36-1 -> 0.10865584 | AL42: =AL36/AI36-1 -> 0.056201788 | AN42: =AN36/AK36-1 -> 0.093106486 | AO42: =AO36/AL36-1 -> 0.093438442 | AQ42: =AQ36/AN36-1 -> 0.21895935 | AR42: =AR36/AO36-1 -> 1.7088634 | AT42: =AT36/AQ36-1 -> 0.53305785 | AU42: =AU36/AR36-1 -> -0.21526419 | AW42: =AW36/AT36-1 -> -0.0053908356 | AX42: =AX36/AU36-1 -> -0.074812968 | AZ42: =AZ36/AW36-1 -> -0.054200542 | BF42: =IFERROR(BF36/BC36-1,"NA") -> NA
B43: Adjustments | C43: 0 | F43: 0 | I43: 0 | L43: 0 | O43: -1.9 | R43: -3.2 | U43: 0 | X43: 0 | AA43: 0 | AD43: 0 | AG43: 0 | AJ43: 0 | AM43: 0 | AP43: 0 | AQ43: =Drivers!CK25-AQ36-AQ27-AQ21-AQ17 -> -75 | AR43: =Drivers!CL25-AR36-AR27-AR21-AR17 -> 21.1 | AS43: 0 | AT43: =Drivers!CM25-AT36-AT27-AT21-AT17 -> -30.9 | AU43: =Drivers!CN25-AU36-AU27-AU21-AU17 -> -30.2 | AV43: 0 | AW43: =Drivers!V25-AW36-AW27-AW21-AW17 -> -28.5 | AX43: =Drivers!W25-AX36-AX27-AX21-AX17 -> -27.7 | AY43: 0 | AZ43: =Drivers!Y25-AZ36-AZ27-AZ21-AZ17 -> -117.3 | BF43: =Drivers!AE25-BF36-BF27-BF21-BF17 -> -110.4
B46: CODB (ex D&A) | C46: =C49-C11 -> -61.834 | D46: =D49-D11 -> -38.631 | E46: =E49-E11 -> -41.405 | F46: =F49-F11 -> -80.036 | G46: =G49-G11 -> -59.436 | H46: =H49-H11 -> -56.945 | I46: =I49-I11 -> -116.381 | J46: =J49-J11 -> -80.112 | ... AD46: =AD49-AD11 -> -467.617 | AG46: =AG49-AG11 -> -501.221 | AH46: =AH49-AH11 -> -269.265 | AI46: =AI49-AI11 -> -260.066 | AJ46: =AJ49-AJ11 -> -529.331 | AK46: =AK49-AK11 -> -278.506 | AL46: =AL49-AL11 -> -279.716 | AM46: =AM49-AM11 -> -558.222 | AN46: =AN49-AN11 -> -301.637 | ... CC46: =CC49-CC11 -> -1669.3561
A47: CODB_M_EX_D&A | B47: CODB (ex D&A) margin | C47: =-C46/C6 -> 0.17377155 | D47: =-D46/D6 -> 0.16466822 | E47: =-E46/E6 -> 0.19014227 | F47: =-F46/F6 -> 0.17693105 | G47: =-G46/G6 -> 0.15800009 | H47: =-H46/H6 -> 0.17920419 | I47: =-I46/I6 -> 0.16770974 | J47: =-J46/J6 -> 0.15713288 | ... AD47: =-AD46/AD6 -> 0.14950387 | AG47: =-AG46/AG6 -> 0.15149952 | AH47: =-AH46/AH6 -> 0.13880262 | AI47: =-AI46/AI6 -> 0.16845158 | AJ47: =-AJ46/AJ6 -> 0.15194179 | AK47: =-AK46/AK6 -> 0.14172266 | AL47: =-AL46/AL6 -> 0.16580794 | AM47: =-AM46/AM6 -> 0.15284809 | AN47: =-AN46/AN6 -> 0.14249555 | ... CC47: =-CC46/CC6 -> 0.13231258
A49: EBITDA | B49: EBITDA | C49: =VLOOKUP($A$49,Drivers!1:1048576,MATCH('P&L'!C4,Drivers!2:2,FALSE),FALSE) -> 18.1 | D49: =VLOOKUP($A$49,Drivers!1:1048576,MATCH('P&L'!D4,Drivers!2:2,FALSE),FALSE) -> 15.9 | E49: =VLOOKUP($A$49,Drivers!1:1048576,MATCH('P&L'!E4,Drivers!2:2,FALSE),FALSE) -> 10 | F49: =VLOOKUP($A$49,Drivers!1:1048576,MATCH('P&L'!F4,Drivers!2:2,FALSE),FALSE) -> 25.9 | G49: =VLOOKUP($A$49,Drivers!1:1048576,MATCH('P&L'!G4,Drivers!2:2,FALSE),FALSE) -> 27.1 | H49: =VLOOKUP($A$49,Drivers!1:1048576,MATCH('P&L'!H4,Drivers!2:2,FALSE),FALSE) -> 15.2 | I49: =VLOOKUP($A$49,Drivers!1:1048576,MATCH('P&L'!I4,Drivers!2:2,FALSE),FALSE) -> 42.3 | J49: =VLOOKUP($A$49,Drivers!1:1048576,MATCH('P&L'!J4,Drivers!2:2,FALSE),FALSE) -> 34.7 | ... CC49: =VLOOKUP($A$49,Drivers!1:1048576,MATCH('P&L'!CC4,Drivers!2:2,FALSE),FALSE) -> 1135.1003
B50: EBITDA margin | C50: =C49/C6 -> 0.050866272 | D50: =D49/D6 -> 0.067775225 | E50: =E49/E6 -> 0.045922538 | F50: =F49/F6 -> 0.057255663 | G50: =G49/G6 -> 0.072040555 | H50: =H49/H6 -> 0.047833941 | I50: =I49/I6 -> 0.060956015 | J50: =J49/J6 -> 0.068061102 | ... CC50: =CC49/CC6 -> 0.089967652
A52: TOTAL_D&A | B52: D&A | C52: =-VLOOKUP($A$52,Drivers!1:1048576,MATCH('P&L'!C4,Drivers!2:2,FALSE),FALSE) -> -1.319 | D52: =-VLOOKUP($A$52,Drivers!1:1048576,MATCH('P&L'!D4,Drivers!2:2,FALSE),FALSE) -> -1.4 | E52: =-VLOOKUP($A$52,Drivers!1:1048576,MATCH('P&L'!E4,Drivers!2:2,FALSE),FALSE) -> -1.768 | F52: =-VLOOKUP($A$52,Drivers!1:1048576,MATCH('P&L'!F4,Drivers!2:2,FALSE),FALSE) -> -3.168 | G52: =-VLOOKUP($A$52,Drivers!1:1048576,MATCH('P&L'!G4,Drivers!2:2,FALSE),FALSE) -> -2.5 | H52: =-VLOOKUP($A$52,Drivers!1:1048576,MATCH('P&L'!H4,Drivers!2:2,FALSE),FALSE) -> -2.768 | I52: =-VLOOKUP($A$52,Drivers!1:1048576,MATCH('P&L'!I4,Drivers!2:2,FALSE),FALSE) -> -5.268 | J52: =-VLOOKUP($A$52,Drivers!1:1048576,MATCH('P&L'!J4,Drivers!2:2,FALSE),FALSE) -> -3.6 | ... CC52: =-VLOOKUP($A$52,Drivers!1:1048576,MATCH('P&L'!CC4,Drivers!2:2,FALSE),FALSE) -> -289.4085
B53: % of sales | C53: =-C52/C6 -> 0.0037067742 | D53: =-D52/D6 -> 0.0059676299 | E53: =-E52/E6 -> 0.0081191047 | F53: =-F52/F6 -> 0.0070033182 | G53: =-G52/G6 -> 0.0066458077 | H53: =-H52/H6 -> 0.0087108124 | I53: =-I52/I6 -> 0.0075914016 | J53: =-J52/J6 -> 0.0070610942 | ... CC53: =-CC52/CC6 -> 0.022938417
A55: EXP_CODB | B55: CODB (inc D&A) | C55: =C58-C11 -> -63.153 | D55: =D58-D11 -> -40.031 | E55: =E58-E11 -> -43.173 | F55: =F58-F11 -> -83.204 | G55: =G58-G11 -> -61.936 | H55: =H58-H11 -> -59.713 | I55: =I58-I11 -> -121.649 | J55: =J58-J11 -> -83.712 | ... CC55: =CC58-CC11 -> -1958.7646
A56: CODB_M | B56: CODB margin | C56: =-C55/C6 -> 0.17747833 | D56: =-D55/D6 -> 0.17063585 | E56: =-E55/E6 -> 0.19826137 | F56: =-F55/F6 -> 0.18393437 | G56: =-G55/G6 -> 0.1646459 | H56: =-H55/H6 -> 0.18791501 | I56: =-I55/I6 -> 0.17530114 | J56: =-J55/J6 -> 0.16419398 | ... CC56: =-CC55/CC6 -> 0.15525099
A58: EBIT_NORM | B58: EBIT before exceptional items | C58: =VLOOKUP($A$58,Drivers!1:1048576,MATCH('P&L'!C4,Drivers!2:2,FALSE),FALSE) -> 16.781 | D58: =VLOOKUP($A$58,Drivers!1:1048576,MATCH('P&L'!D4,Drivers!2:2,FALSE),FALSE) -> 14.5 | E58: =VLOOKUP($A$58,Drivers!1:1048576,MATCH('P&L'!E4,Drivers!2:2,FALSE),FALSE) -> 8.232 | F58: =VLOOKUP($A$58,Drivers!1:1048576,MATCH('P&L'!F4,Drivers!2:2,FALSE),FALSE) -> 22.732 | G58: =VLOOKUP($A$58,Drivers!1:1048576,MATCH('P&L'!G4,Drivers!2:2,FALSE),FALSE) -> 24.6 | H58: =VLOOKUP($A$58,Drivers!1:1048576,MATCH('P&L'!H4,Drivers!2:2,FALSE),FALSE) -> 12.432 | I58: =VLOOKUP($A$58,Drivers!1:1048576,MATCH('P&L'!I4,Drivers!2:2,FALSE),FALSE) -> 37.032 | J58: =VLOOKUP($A$58,Drivers!1:1048576,MATCH('P&L'!J4,Drivers!2:2,FALSE),FALSE) -> 31.1 | ... CC58: =VLOOKUP($A$58,Drivers!1:1048576,MATCH('P&L'!CC4,Drivers!2:2,FALSE),FALSE) -> 845.69179
B59: EBIT-Margin | C59: =C58/C6 -> 0.047159498 | D59: =D58/D6 -> 0.061807595 | E59: =E58/E6 -> 0.037803433 | F59: =F58/F6 -> 0.050252345 | G59: =G58/G6 -> 0.065394748 | H59: =H58/H6 -> 0.039123128 | I59: =I58/I6 -> 0.053364614 | J59: =J58/J6 -> 0.061000008 | ... CC59: =CC58/CC6 -> 0.067029236
B60: EBIT Growth | F60: =F58/C58-1 -> 0.35462726 | G60: =G58/D58-1 -> 0.69655172 | H60: =H58/E58-1 -> 0.51020408 | I60: =I58/F58-1 -> 0.62906915 | J60: =J58/G58-1 -> 0.26422764 | K60: =K58/H58-1 -> 0.08277027 | L60: =L58/I58-1 -> 0.20331065 | M60: =M58/J58-1 -> 0.34405145 | ... CC60: =CC58/BZ58-1 -> 0.049215819
A62: Except_Items | B62: Exceptional Items | Z62: =AA62-Y62 -> -33.4 | AA62: -33.4 | AJ62: 0 | AM62: 0 | AN62: 0 | AP62: 0 | AQ62: -15.3 | AR62: =AS62-AQ62 -> -22.9 | AS62: -38.2 | AT62: 0 | AU62: =AV62-AT62 -> 0 | AW62: 0 | AX62: =AY62-AW62 -> 0 | AY62: 0 | AZ62: =AY62-AX62 -> 0 | BA62: =BB62-AZ62 -> -19.7 | BB62: -19.7 | BE62: 0 | BH62: 0 | BK62: 0 | BN62: 0 | BP62: =+BQ62 -> -13.7 | BQ62: -13.7
A64: EBIT_REPORTED | B64: EBIT | C64: =C58+C62 -> 16.781 | D64: =D58+D62 -> 14.5 | E64: =E58+E62 -> 8.232 | F64: =F58+F62 -> 22.732 | G64: =G58+G62 -> 24.6 | H64: =H58+H62 -> 12.432 | I64: =I58+I62 -> 37.032 | J64: =J58+J62 -> 31.1 | ... AE64: =AE58+AE62 -> 123.7 | AF64: =AG64-AE64 -> 54.053 | AG64: =AG58+AG62 -> 177.753 | AH64: =AH58+AH62 -> 132.9 | AI64: =AJ64-AH64 -> 58.22 | AJ64: =AJ58+AJ62 -> 191.12 | AK64: =AK58+AK62 -> 129.971 | AL64: =AL58+AL62 -> 70.936 | AM64: =AM58+AM62 -> 200.907 | AN64: =AN58+AN62 -> 138.159 | AO64: =AO58+AO62 -> 83.016 | AP64: =AP58+AP62 -> 221.175 | AQ64: =AQ58+AQ62 -> 165.5 | ... CC64: =CC58+CC62 -> 845.69179
B65: EBIT-Margin | C65: =C64/C6 -> 0.047159498 | D65: =D64/D6 -> 0.061807595 | E65: =E64/E6 -> 0.037803433 | F65: =F64/F6 -> 0.050252345 | G65: =G64/G6 -> 0.065394748 | H65: =H64/H6 -> 0.039123128 | I65: =I64/I6 -> 0.053364614 | J65: =J64/J6 -> 0.061000008 | ... CC65: =CC64/CC6 -> 0.067029236
A67: Finance_Income | B67: Finance Income (Interest revenue in notes) | C67: 0.316 | E67: =F67-D67 -> 0.356 | F67: 0.356 | H67: =I67-G67 -> 0.56 | I67: 0.56 | K67: =L67-J67 -> 0.672 | L67: 0.672 | N67: =O67-M67 -> 1.302 | O67: 1.302 | Q67: =R67-P67 -> 1.008 | R67: 1.008 | S67: 1 | T67: =U67-S67 -> 0.562 | U67: 1.562 | V67: 0.576 | W67: =X67-V67 -> 0.872 | X67: 1.448 | Y67: 1.205 | Z67: =AA67-Y67 -> 1.031 | AA67: 2.236 | AB67: 0.288 | AC67: =AD67-AB67 -> 0.28 | AD67: 0.568 | AE67: 0.258 | AF67: =AG67-AE67 -> 0.197 | AG67: 0.455 | AH67: 0.233 | AI67: =AJ67-AH67 -> 0.169 | AJ67: 0.402 | AK67: 0.235 | AL67: =AM67-AK67 -> 0.317 | AM67: 0.552 | AN67: 0.239 | AO67: =AP67-AN67 -> 0.282 | AP67: =3.857-3.336 -> 0.521 | AQ67: 1.3 | AR67: =AS67-AQ67 -> 0.4 | AS67: =10.7-9 -> 1.7 | AT67: 0.2 | AU67: =AV67-AT67 -> 0.3 | AV67: 0.5 | AW67: 0.4 | AX67: =AY67-AW67 -> 0.3 | AY67: 0.7 | AZ67: =BB67*0.5 -> 0.55 | BA67: =BB67-AZ67 -> 0.55 | BB67: 1.1 | BC67: 1.1 | BD67: =BE67-BC67 -> 0.5 | BE67: 1.6 | BF67: 0.4 | BG67: =BH67-BF67 -> 0.4 | BH67: 0.8 | BI67: 1.8 | BJ67: =BK67-BI67 -> 2.6 | BK67: 4.4 | BL67: 5.5 | BM67: =BN67-BL67 -> 5.7 | BN67: 11.2 | BO67: 6.8 | BP67: =BQ67-BO67 -> 4.7 | BQ67: 11.5 | BR67: 3.8 | BS67: =BT67-BR67 -> 3.6011006 | BT67: =BS!AH101 -> 7.4011006 | BU67: =BS!AI101 -> 2.649883 | BV67: =BW67-BU67 -> 2.905769 | BW67: =BS!AK101 -> 5.555652 | BX67: =BS!AL101 -> 2.7400211 | BY67: =BZ67-BX67 -> 2.9831774 | BZ67: =BS!AN101 -> 5.7231984 | CA67: =BS!AO101 -> 2.159113 | CB67: =CC67-CA67 -> 2.3274587 | CC67: =BS!AQ101 -> 4.4865717
A68: Finance_Expense | B68: Finance Costs | AV68: =AV69+AV70 -> -16.6 | AW68: =AW69+AW70 -> -7.1 | AX68: =AX69+AX70 -> -7.2 | AY68: =AY69+AY70 -> -14.3 | AZ68: =AZ69+AZ70 -> -18.35 | BA68: =BA69+BA70 -> -18.05 | BB68: =BB69+BB70 -> -36.4 | BC68: =BC69+BC70 -> -13.4 | ... CC68: =CC69+CC70 -> -44.030589
A69: Lease_interest_exp | B69: Interest on leases | C69: -4.423 | D69: -1.03 | E69: =F69-D69 -> -2.028 | F69: -3.058 | G69: -2.574 | H69: =I69-G69 -> -3.131 | I69: -5.705 | J69: -3.037 | K69: =L69-J69 -> -3.373 | L69: -6.41 | M69: -3.796 | N69: =O69-M69 -> -3.661 | O69: -7.457 | P69: -4.193 | Q69: =R69-P69 -> -5.104 | R69: -9.297 | S69: -4.78 | T69: =U69-S69 -> -3.256 | U69: -8.036 | V69: -3.234 | W69: =X69-V69 -> -3.723 | X69: -6.957 | Y69: -2.611 | Z69: =AA69-Y69 -> -3.657 | AA69: -6.268 | AB69: -7.215 | AC69: =AD69-AB69 -> -6.439 | AD69: -13.654 | AE69: -5.425 | AF69: =AG69-AE69 -> -4.731 | AG69: -10.156 | AH69: -4.148 | AI69: =AJ69-AH69 -> -4.697 | AJ69: -8.845 | AK69: -3.136 | AL69: =AM69-AK69 -> -2.791 | AM69: -5.927 | AN69: -1.984 | AO69: =AP69-AN69 -> -1.873 | AP69: -3.857 | AQ69: -2.7 | AR69: =AS69-AQ69 -> -8 | AS69: -10.7 | AT69: -8.3 | AU69: =AV69-AT69 -> -8.3 | AV69: -16.6 | AW69: -7.1 | AX69: =AY69-AW69 -> -7.2 | AY69: -14.3 | AZ69: =AZ71-AZ67 -> -18.35 | BA69: =BB69-AZ69 -> -18.05 | BB69: -36.4 | BC69: =BC71-BC67 -> -13.4 | BD69: =BE69-BC69 -> -7.9 | BE69: -21.3 | BF69: -9.7 | BG69: =BH69-BF69 -> -9 | BH69: -18.7 | BI69: -9.4 | BJ69: =BK69-BI69 -> -12.5 | BK69: -21.9 | BL69: -13.9 | BM69: =BN69-BL69 -> -15.3 | BN69: -29.2 | BO69: -16.8 | BP69: =BQ69-BO69 -> -18.5 | BQ69: -35.3 | BR69: -19.2 | BS69: =BT69-BR69 -> -19.63 | BT69: =+BQ69*1.1 -> -38.83 | BU69: =0.5*BW69 -> -19.99745 | BV69: =BW69-BU69 -> -19.99745 | BW69: =+BT69*1.03 -> -39.9949 | BX69: =0.5*BZ69 -> -20.597373 | BY69: =BZ69-BX69 -> -20.597373 | BZ69: =+BW69*1.03 -> -41.194747 | CA69: =0.5*CC69 -> -21.215295 | CB69: =CC69-CA69 -> -21.215295 | CC69: =+BZ69*1.03 -> -42.430589
B70: Other finance costs | BE70: -3.4 | BF70: -0.7 | BG70: =BH70-BF70 -> -0.7 | BH70: -1.4 | BI70: -1.4 | BJ70: =BK70-BI70 -> -3 | BK70: =-4-0.4 -> -4.4 | BL70: -1 | BM70: =BN70-BL70 -> -0.8 | BN70: -1.8 | BO70: -1.2 | BP70: =+BQ70-BO70 -> -1.1 | BQ70: -2.3 | BR70: -0.8 | BS70: =+BT70-BR70 -> -0.8 | BT70: =+BS!AH92 -> -1.6 | BU70: =+BS!AI92 -> -0.8 | BV70: =+BW70-BU70 -> -0.8 | BW70: =+BS!AK92 -> -1.6 | BX70: =+BS!AL92 -> -0.8 | BY70: =+BZ70-BX70 -> -0.8 | BZ70: =+BS!AN92 -> -1.6 | CA70: =+BS!AO92 -> -0.8 | CB70: =+CC70-CA70 -> -0.8 | CC70: =+BS!AQ92 -> -1.6
A71: NET_INT | B71: Net interest expense | C71: =C67+C69 -> -4.107 | D71: =D69+D67 -> -1.03 | E71: =E69+E67 -> -1.672 | F71: =F67+F69 -> -2.702 | G71: =G69+G67 -> -2.574 | H71: =H69+H67 -> -2.571 | I71: =I67+I69 -> -5.145 | J71: =J69+J67 -> -3.037 | K71: =K69+K67 -> -2.701 | L71: =L67+L69 -> -5.738 | M71: =M69+M67 -> -3.796 | N71: =N69+N67 -> -2.359 | O71: =O67+O69 -> -6.155 | P71: =P69+P67 -> -4.193 | Q71: =Q69+Q67 -> -4.096 | R71: =R67+R69 -> -8.289 | S71: =S69+S67 -> -3.78 | T71: =T69+T67 -> -2.694 | U71: =U67+U69 -> -6.474 | V71: =V69+V67 -> -2.658 | W71: =W69+W67 -> -2.851 | X71: =X67+X69 -> -5.509 | Y71: =Y69+Y67 -> -1.406 | Z71: =Z69+Z67 -> -2.626 | AA71: =AA67+AA69 -> -4.032 | AB71: =AB69+AB67 -> -6.927 | AC71: =AC69+AC67 -> -6.159 | AD71: =AD67+AD69 -> -13.086 | AE71: =AE69+AE67 -> -5.167 | AF71: =AF69+AF67 -> -4.534 | AG71: =AG67+AG69 -> -9.701 | AH71: =AH69+AH67 -> -3.915 | AI71: =AI69+AI67 -> -4.528 | AJ71: =AJ67+AJ69 -> -8.443 | AK71: =AK69+AK67 -> -2.901 | AL71: =AL69+AL67 -> -2.474 | AM71: =AM67+AM69 -> -5.375 | AN71: =AN69+AN67 -> -1.745 | AO71: =AP71-AN71 -> -1.591 | AP71: =AP67+AP69 -> -3.336 | AQ71: =AQ69+AQ67 -> -1.4 | AR71: =AR69+AR67 -> -7.6 | AS71: =AS67+AS69 -> -9 | AT71: =AT69+AT67 -> -8.1 | AU71: =AU69+AU67 -> -8 | AV71: =AV67+AV69 -> -16.1 | AW71: =AW69+AW67 -> -6.7 | AX71: =AX69+AX67 -> -6.9 | AY71: =AY67+AY69 -> -13.6 | AZ71: -17.8 | BA71: =BA69+BA67 -> -17.5 | BB71: =BB67+BB69 -> -35.3 | BC71: =-11.1-1.2 -> -12.3 | BD71: =BD69+BD67 -> -7.4 | BE71: =BE67+BE69 -> -19.7 | BF71: =BF67+BF69+BF70 -> -10 | BG71: =BG67+BG69+BG70 -> -9.3 | BH71: =BH67+BH69+BH70 -> -19.3 | BI71: =BI67+BI69+BI70 -> -9 | BJ71: =BJ69+BJ67+BJ70 -> -12.9 | BK71: =BK67+BK69+BK70 -> -21.9 | BL71: =BL67+BL69+BL70 -> -9.4 | BM71: =BM69+BM67+BM70 -> -10.4 | BN71: =BN67+BN69+BN70 -> -19.8 | BO71: =BO67+BO69+BO70 -> -11.2 | BP71: =BP69+BP67+BP70 -> -14.9 | BQ71: =BQ67+BQ69+BQ70 -> -26.1 | BR71: =BR69+BR67+BR70 -> -16.2 | BS71: =BS69+BS67+BS70 -> -16.828899 | BT71: =BT69+BT67+BT70 -> -33.028899 | BU71: =BU69+BU67+BU70 -> -18.147567 | BV71: =BV69+BV67+BV70 -> -17.891681 | BW71: =BW69+BW67+BW70 -> -36.039248 | BX71: =BX69+BX67+BX70 -> -18.657352 | BY71: =BY69+BY67+BY70 -> -18.414196 | ... CC71: =CC69+CC67+CC70 -> -39.544018
A73: PBT | B73: Earnings before tax | C73: =C71+C64 -> 12.674 | D73: =D71+D64 -> 13.47 | E73: =E71+E64 -> 6.56 | F73: =F71+F64 -> 20.03 | G73: =G71+G64 -> 22.026 | H73: =H71+H64 -> 9.861 | I73: =I71+I64 -> 31.887 | J73: =J71+J64 -> 28.063 | ... AE73: =AE71+AE64 -> 118.533 | AF73: =AG73-AE73 -> 49.519 | AG73: =AG71+AG64 -> 168.052 | AH73: =AH71+AH64 -> 128.985 | AI73: =AJ73-AH73 -> 53.692 | AJ73: =AJ71+AJ64 -> 182.677 | AK73: =AK71+AK64 -> 127.07 | AL73: =AM73-AK73 -> 68.462 | AM73: =AM71+AM64 -> 195.532 | AN73: =AN71+AN64 -> 136.414 | AO73: =AP73-AN73 -> 81.425 | AP73: =AP71+AP64 -> 217.839 | AQ73: =AQ71+AQ64 -> 164.1 | AR73: =AS73-AQ73 -> 95.1 | AS73: =AS71+AS64 -> 259.2 | AT73: =AT71+AT64 -> 217.7 | AU73: =AV73-AT73 -> 116.8 | AV73: =AV71+AV64 -> 334.5 | AW73: =AW71+AW64 -> 229.9 | AX73: =AY73-AW73 -> 129.4 | AY73: =AY71+AY64 -> 359.3 | AZ73: =AZ71+AZ64 -> 245.2 | BA73: =BB73-AZ73 -> 202.7 | BB73: =BB71+BB64 -> 447.9 | BC73: =BC71+BC64 -> 450.5 | BD73: =BD71+BD64 -> 272.9 | BE73: =BE71+BE64 -> 723.4 | BF73: =BF71+BF64 -> 410.5 | BG73: =BG71+BG64 -> 364.8 | BH73: =BH71+BH64 -> 775.3 | BI73: =BI71+BI64 -> 470.2 | ... CC73: =CC71+CC64 -> 806.14778
A75: TAX | B75: Tax | C75: =C198 -> -3.716 | D75: =D198 -> -3.97 | E75: =F75-D75 -> -1.929 | F75: =F198 -> -5.899 | G75: =G198 -> -6.648 | H75: =H198 -> -2.794 | I75: =I198 -> -9.442 | J75: =J198 -> -8.508 | K75: =K198 -> -3.446 | L75: =L198 -> -11.954 | M75: =M198 -> -11.556 | ... AK75: =AK198 -> -38.532 | AL75: =AM75-AK75 -> -20.489 | AM75: =AM198 -> -59.021 | AN75: =AN198 -> -41.218 | AO75: =AO198 -> -24.4275 | AP75: =AP198 -> -65.658 | AQ75: =AQ198 -> -53.7 | AR75: =AR198 -> -32.980226 | AS75: =AS198 -> -86.8 | AT75: =AT198 -> -66 | ... BI75: =BI198 -> -140.3 | BJ75: =+BK75-BI75 -> -82.2 | BK75: =BK198 -> -222.5 | BL75: =BL198 -> -113 | BM75: =+BN75-BL75 -> -75.6 | BN75: =BN198 -> -188.6 | BO75: =BO198 -> -123.2 | BP75: =+BQ75-BO75 -> -82 | BQ75: =BQ198 -> -205.2 | BR75: =BR198 -> -131.9 | BS75: =+BT75-BR75 -> -85.043396 | BT75: =BT198 -> -216.9434 | BU75: =BU198 -> -133.24423 | BV75: =+BW75-BU75 -> -86.990706 | BW75: =BW198 -> -220.23494 | BX75: =BX198 -> -141.01612 | BY75: =+BZ75-BX75 -> -90.447544 | BZ75: =BZ198 -> -231.46367 | CA75: =CA198 -> -147.76804 | CB75: =+CC75-CA75 -> -94.892252 | CC75: =CC198 -> -242.6603
B76: Reported Tax Rate (%) | C76: =C203 -> 0.29319867 | D76: =D203 -> 0.29472903 | E76: =E203 -> 0.29405488 | F76: =F203 -> 0.29450824 | G76: =G203 -> 0.30182512 | H76: =H203 -> 0.2833384 | I76: =I203 -> 0.29610813 | J76: =J203 -> 0.303175 | ... CC76: =CC203 -> 0.30101218
A77: Tax rate | B77: Underlying Tax Rate (%) | C77: =C201 -> 0.29319867 | D77: =D201 -> 0.29472903 | E77: =E201 -> 0.29405488 | F77: =F201 -> 0.29450824 | G77: =G201 -> 0.30182512 | H77: =H201 -> 0.2833384 | I77: =I201 -> 0.29610813 | J77: =J201 -> 0.303175 | ... CC77: =CC201 -> 0.30101218
B79: Net Earnings from continuing operations | C79: =C75+C73 -> 8.958 | D79: =D75+D73 -> 9.5 | E79: =E75+E73 -> 4.631 | F79: =F75+F73 -> 14.131 | G79: =G75+G73 -> 15.378 | H79: =H75+H73 -> 7.067 | I79: =I75+I73 -> 22.445 | J79: =J75+J73 -> 19.555 | ... AH79: =AH75+AH73 -> 90.405 | AI79: =AJ79-AH79 -> 38.042 | AJ79: =AJ75+AJ73 -> 128.447 | AK79: =AK75+AK73 -> 88.538 | AL79: =AL75+AL73 -> 47.973 | AM79: =AM75+AM73 -> 136.511 | AN79: =AN75+AN73 -> 95.196 | AO79: =AP79-AN79 -> 56.985 | AP79: =AP75+AP73 -> 152.181 | AQ79: =AQ75+AQ73 -> 110.4 | AR79: =AS79-AQ79 -> 62 | AS79: =AS75+AS73 -> 172.4 | AT79: =AT75+AT73 -> 151.7 | AU79: =AV79-AT79 -> 81.5 | AV79: =AV75+AV73 -> 233.2 | AW79: =AW75+AW73 -> 160.1 | AX79: =AY79-AW79 -> 89.7 | AY79: =AY75+AY73 -> 249.8 | AZ79: =AZ75+AZ73 -> 170.6 | BA79: =BB79-AZ79 -> 131.6 | BB79: =BB75+BB73 -> 302.2 | BC79: =BC75+BC73 -> 317.7 | BD79: =BD75+BD73 -> 191.8 | BE79: =BE75+BE73 -> 509.5 | BF79: =BF75+BF73 -> 287.9 | BG79: =BG75+BG73 -> 257 | BH79: =BH75+BH73 -> 544.9 | BI79: =BI75+BI73 -> 329.9 | ... CC79: =CC75+CC73 -> 563.48748
B81: Net earnings from discontinuing operations
B82: Significant items from discontinuing operations
B84: Net Earnings from total operations | C84: =C79+C81+C82 -> 8.958 | D84: =D79+D81+D82 -> 9.5 | E84: =E79+E81+E82 -> 4.631 | F84: =F79+F81+F82 -> 14.131 | G84: =G79+G81+G82 -> 15.378 | H84: =H79+H81+H82 -> 7.067 | I84: =I79+I81+I82 -> 22.445 | J84: =J79+J81+J82 -> 19.555 | ... AE84: =AE79+AE81+AE82 -> 82.07 | AF84: =AG84-AE84 -> 34.562 | AG84: =AG79+AG81+AG82 -> 116.632 | AH84: =AH79+AH81+AH82 -> 90.405 | AI84: =AJ84-AH84 -> 38.042 | AJ84: =AJ79+AJ81+AJ82 -> 128.447 | AK84: =AK79+AK81+AK82 -> 88.538 | AL84: =AL79+AL81+AL82 -> 47.973 | AM84: =AM79+AM81+AM82 -> 136.511 | AN84: =AN79+AN81+AN82 -> 95.196 | AO84: =AO79+AO81+AO82 -> 56.985 | AP84: =AP79+AP81+AP82 -> 152.181 | AQ84: =AQ79+AQ81+AQ82 -> 110.4 | ... AZ84: =AZ79+AZ81+AZ82 -> 170.6 | BA84: =BB84-AZ84 -> 131.6 | BB84: =BB79+BB81+BB82 -> 302.2 | BC84: =BC79+BC81+BC82 -> 317.7 | BD84: =BE84-BC84 -> 191.8 | BE84: =BE79+BE81+BE82 -> 509.5 | BF84: =BF79+BF81+BF82 -> 287.9 | BG84: =BH84-BF84 -> 257 | BH84: =BH79+BH81+BH82 -> 544.9 | BI84: =BI79+BI81+BI82 -> 329.9 | BJ84: =BK84-BI84 -> 194.7 | BK84: =BK79+BK81+BK82 -> 524.6 | BL84: =BL79+BL81+BL82 -> 264.3 | BM84: =BN84-BL84 -> 174.5 | BN84: =BN79+BN81+BN82 -> 438.8 | BO84: =BO79+BO81+BO82 -> 285.5 | BP84: =BQ84-BO84 -> 177.3 | BQ84: =BQ79+BQ81+BQ82 -> 462.8 | BR84: =BR79+BR81+BR82 -> 305.9 | BS84: =BT84-BR84 -> 197.86963 | BT84: =BT79+BT81+BT82 -> 503.76963 | BU84: =BU79+BU81+BU82 -> 310.9032 | BV84: =BW84-BU84 -> 200.50979 | BW84: =BW79+BW81+BW82 -> 511.413 | BX84: =BX79+BX81+BX82 -> 329.03762 | BY84: =BZ84-BX84 -> 208.44989 | BZ84: =BZ79+BZ81+BZ82 -> 537.48751 | CA84: =CA79+CA81+CA82 -> 344.7921 | CB84: =CC84-CA84 -> 218.69538 | CC84: =CC79+CC81+CC82 -> 563.48748
A86: MI | B86: Minority interests | C86: 0 | D86: -0.2 | F86: 0 | G86: -0.752 | I86: -1.089 | J86: -0.705 | L86: -1.033 | M86: -0.578 | O86: -0.987 | R86: 0 | U86: 0 | X86: 0 | AA86: 0 | AD86: 0 | AF86: =AG86-AE86 -> -0.249 | AG86: -0.249 | AH86: -0.088 | AI86: =AJ86-AH86 -> 0 | AJ86: -0.088 | AK86: 0 | AL86: =AM86-AK86 -> 0 | AP86: =AM86 -> 0 | AS86: =AP86 -> 0 | AT86: 0 | AU86: =AV86-AT86 -> 0 | AV86: =AS86 -> 0 | AW86: 0 | AX86: =AY86-AW86 -> 0 | AY86: =AV86 -> 0 | AZ86: 0 | BA86: 0 | BB86: 0 | BC86: 0 | BD86: 0 | BE86: 0 | BF86: 0 | BG86: 0 | BH86: 0 | BI86: 0 | BJ86: 0 | BK86: 0 | BL86: 0 | BM86: 0 | BN86: 0 | BO86: 0 | BP86: =BQ86-BO86 -> -0.4 | BQ86: -0.4 | BR86: -0.1 | BS86: =BT86-BR86 -> -0.46679092 | BT86: =-0.25*Drivers!AS397 -> -0.56679092 | BU86: =-0.25*Drivers!AT397 -> -0.306425 | BV86: =BW86-BU86 -> -0.27736965 | BW86: =-0.25*Drivers!AV397 -> -0.58379465 | BX86: =-0.25*Drivers!AW397 -> -0.31561775 | BY86: =BZ86-BX86 -> -0.28569074 | BZ86: =-0.25*Drivers!AY397 -> -0.60130849 | CA86: =-0.25*Drivers!AZ397 -> -0.32508628 | CB86: =CC86-CA86 -> -0.29426146 | CC86: =-0.25*Drivers!BB397 -> -0.61934774
A88: NPAT_REPORTED | B88: Reported NPAT | C88: =C79+C86+C81+C82 -> 8.958 | D88: =D79+D86+D81+D82 -> 9.3 | E88: =F88-D88 -> 4.831 | F88: =F79+F86+F81+F82 -> 14.131 | G88: =G79+G86+G81+G82 -> 14.626 | H88: =H79+H86+H81+H82 -> 7.067 | I88: =I79+I86+I81+I82 -> 21.356 | J88: =J79+J86+J81+J82 -> 18.85 | K88: =K79+K86+K81+K82 -> 7.314 | L88: =L79+L86+L81+L82 -> 25.836 | M88: =M79+M86+M81+M82 -> 25.87 | ... AE88: =AE79+AE86+AE81+AE82 -> 82.07 | AF88: =AG88-AE88 -> 34.313 | AG88: =AG79+AG86+AG81+AG82 -> 116.383 | AH88: =AH79+AH86+AH81+AH82 -> 90.317 | AI88: =AJ88-AH88 -> 38.042 | AJ88: =AJ79+AJ86+AJ81+AJ82 -> 128.359 | AK88: =AK79+AK86+AK81+AK82 -> 88.538 | AL88: =AL79+AL86+AL81+AL82 -> 47.973 | AM88: =AM79+AM86+AM81+AM82 -> 136.511 | AN88: =AN79+AN86+AN81+AN82 -> 95.196 | AO88: =AP88-AN88 -> 56.985 | AP88: =AP79+AP86+AP81+AP82 -> 152.181 | AQ88: =AQ79+AQ86+AQ81+AQ82 -> 110.4 | AR88: =AS88-AQ88 -> 62 | AS88: =AS79+AS86+AS81+AS82 -> 172.4 | AT88: =AT79+AT86+AT81+AT82 -> 151.7 | AU88: =AV88-AT88 -> 81.5 | AV88: =AV79+AV86+AV81+AV82 -> 233.2 | AW88: =AW79+AW86+AW81+AW82 -> 160.1 | AX88: =AY88-AW88 -> 89.7 | AY88: =AY79+AY86+AY81+AY82 -> 249.8 | AZ88: =AZ79+AZ86+AZ81+AZ82 -> 170.6 | BA88: =BB88-AZ88 -> 131.6 | BB88: =BB79+BB86+BB81+BB82 -> 302.2 | BC88: =BC79+BC86+BC81+BC82 -> 317.7 | BD88: =BD79+BD86+BD81+BD82 -> 191.8 | BE88: =BE79+BE86+BE81+BE82 -> 509.5 | BF88: =BF79+BF86+BF81+BF82 -> 287.9 | BG88: =BG79+BG86+BG81+BG82 -> 257 | BH88: =BH79+BH86+BH81+BH82 -> 544.9 | BI88: =BI79+BI86+BI81+BI82 -> 329.9 | ... CC88: =CC79+CC86+CC81+CC82 -> 562.86813
B89: Growth % | G89: =G88/D88-1 -> 0.57268817 | H89: =H88/E88-1 -> 0.46284413 | I89: =I88/F88-1 -> 0.51128724 | J89: =J88/G88-1 -> 0.28880077 | K89: =K88/H88-1 -> 0.034951182 | L89: =L88/I88-1 -> 0.20977711 | M89: =M88/J88-1 -> 0.37241379 | N89: =N88/K88-1 -> 1.0410172 | ... CC89: =CC88/BZ88-1 -> 0.048393739
B91: Reported EPS basic (EPS) | C91: =C88/C102*100 -> 10.852525 | D91: =D88/D102*100 -> 9.1051048 | E91: =F91-D91 -> 7.4337934 | F91: =F88/F102*100 -> 16.538898 | G91: =G88/G102*100 -> 14.249944 | H91: =I91-G91 -> 6.5569618 | I91: =I88/I102*100 -> 20.806906 | J91: =J88/J102*100 -> 18.280206 | K91: =K88/K102*100 -> 7.0929139 | L91: =L88/L102*100 -> 25.055035 | M91: =M88/M102*100 -> 24.977454 | N91: =N88/N102*100 -> 14.333861 | O91: =O88/O102*100 -> 38.781507 | P91: =P88/P102*100 -> 40.297857 | ... S91: =S88/S102*100 -> 55.322776 | T91: =U91-S91 -> 32.940227 | U91: =U88/U102*100 -> 88.263003 | V91: =V88/V102*100 -> 70.471314 | W91: =W88/W102*100 -> 39.406019 | X91: =X88/X102*100 -> 109.74306 | Y91: =Y88/Y102*100 -> 80.666716 | Z91: =Z88/Z102*100 -> 20.229128 | AA91: =AA88/AA102*100 -> 101.75788 | AB91: =AB88/AB102*100 -> 80.670388 | ... AE91: =AE88/AE102*100 -> 83.023945 | AF91: =AG91-AE91 -> 34.672548 | AG91: =AG88/AG102*100 -> 117.69649 | AH91: =AH88/AH102*100 -> 90.53519 | AI91: =AI88/AI102*100 -> 38.051513 | AJ91: =AJ88/AJ102*100 -> 128.3911 | AK91: =AK88/AK102*100 -> 89.443165 | AL91: =AL88/AL102*100 -> 48.46345 | AM91: =AM88/AM102*100 -> 137.91497 | AN91: =AN88/AN102*100 -> 96.138154 | ... AQ91: =AQ88/AQ102*100 -> 102.31696 | AR91: =AS91-AQ91 -> 52.025027 | AS91: =AS88/AS102*100 -> 154.34199 | AT91: =AT88/AT102*100 -> 132.25806 | AU91: =AV91-AT91 -> 70.877824 | AV91: =AV88/AV102*100 -> 203.13589 | AW91: =AW88/AW102*100 -> 139.33856 | AX91: =AY91-AW91 -> 78.067885 | AY91: =AY88/AY102*100 -> 217.40644 | AZ91: =AZ88/AZ102*100 -> 148.47694 | BA91: =BB91-AZ91 -> 114.53438 | BB91: =BB88/BB102*100 -> 263.01131 | BC91: =BC88/BC102*100 -> 276.50131 | BD91: =BE91-BC91 -> 167.31403 | BE91: =BE88/BE102*100 -> 443.81533 | BF91: =BF88/BF102*100 -> 250.56571 | BG91: =BH91-BF91 -> 228.67791 | BH91: =BH88/BH102*100 -> 479.24362 | BI91: =BI88/BI102*100 -> 301.82983 | BJ91: =BK91-BI91 -> 178.13358 | BK91: =BK88/BK102*100 -> 479.9634 | BL91: =BL88/BL102*100 -> 241.81153 | BM91: =BN91-BL91 -> 159.65233 | BN91: =BN88/BN102*100 -> 401.46386 | BO91: =BO88/BO102*100 -> 261.20769 | BP91: =BQ91-BO91 -> 161.84812 | BQ91: =BQ88/BQ102*100 -> 423.05581 | BR91: =BR88/BR102*100 -> 279.78042 | BS91: =BT91-BR91 -> 180.46335 | BT91: =BT88/BT102*100 -> 460.24377 | BU91: =BU88/BU102*100 -> 284.08074 | BV91: =BW91-BU91 -> 183.13833 | BW91: =BW88/BW102*100 -> 467.21906 | BX91: =BX88/BX102*100 -> 300.65859 | BY91: =BZ91-BX91 -> 190.39296 | BZ91: =BZ88/BZ102*100 -> 491.05154 | CA91: =CA88/CA102*100 -> 315.05943 | CB91: =CC91-CA91 -> 199.75594 | CC91: =CC88/CC102*100 -> 514.81536
A93: EPS_REPORTED | B93: Reported EPS diluted (in cents) | C93: =C88/C103*100 -> 10.768768 | D93: =D88/D103*100 -> 8.9252015 | E93: =E88/E103*100 -> 5.5930535 | F93: =F88/F103*100 -> 16.360058 | G93: =G88/G103*100 -> 14.032563 | H93: =H88/G103*100 -> 6.7802627 | I93: =I88/I103*100 -> 20.489499 | J93: =J88/J103*100 -> 17.909228 | K93: =K88/K103*100 -> 6.9489706 | L93: =L88/L103*100 -> 24.546569 | M93: =M88/M103*100 -> 24.325095 | N93: =N88/N103*100 -> 14.075848 | O93: =O88/O103*100 -> 38.083429 | P93: =P88/P103*100 -> 39.541705 | ... AE93: =AE88/AE103*100 -> 83.018066 | AF93: =AG93-AE93 -> 34.00505 | AG93: =AG88/AG103*100 -> 117.02312 | AH93: =AH88/AH103*100 -> 89.239875 | AI93: =AJ93-AH93 -> 37.645981 | AJ93: =AJ88/AJ103*100 -> 126.88586 | AK93: =AK88/AK103*100 -> 88.418635 | AL93: =AM93-AK93 -> 48.041875 | AM93: =AM88/AM103*100 -> 136.46051 | AN93: =AN88/AN103*100 -> 95.166498 | AO93: =AO88/AO103*100 -> 56.96734 | AP93: =AP88/AP103*100 -> 152.12471 | AQ93: =AQ88/AQ103*100 -> 101.37741 | AR93: =AS93-AQ93 -> 51.595083 | AS93: =AS88/AS103*100 -> 152.97249 | AT93: =AT88/AT103*100 -> 131.00173 | AU93: =AV93-AT93 -> 70.206211 | AV93: =AV88/AV103*100 -> 201.20794 | AW93: =AW88/AW103*100 -> 138.01724 | AX93: =AY93-AW93 -> 77.142104 | AY93: =AY88/AY103*100 -> 215.15935 | AZ93: =AZ88/AZ103*100 -> 147.4503 | BA93: =BB93-AZ93 -> 113.06694 | BB93: =BB88/BB103*100 -> 260.51724 | BC93: =BC88/BC103*100 -> 274.58946 | BD93: =BE93-BC93 -> 166.15449 | BE93: =BE88/BE103*100 -> 440.74394 | BF93: =BF88/BF103*100 -> 249.48007 | BG93: =BH93-BF93 -> 227.66529 | BH93: =BH88/BH103*100 -> 477.14536 | BI93: =BI88/BI103*100 -> 300.72926 | BJ93: =BK93-BI93 -> 177.04852 | BK93: =BK88/BK103*100 -> 477.77778 | BL93: =BL88/BL103*100 -> 240.71038 | BM93: =BN93-BL93 -> 160.02021 | BN93: =BN88/BN103*100 -> 400.73059 | BO93: =BO88/BO103*100 -> 260.25524 | BP93: =BQ93-BO93 -> 161.25798 | BQ93: =BQ88/BQ103*100 -> 421.51322 | BR93: =BR88/BR103*100 -> 279.0146 | BS93: =BT93-BR93 -> 179.5515 | BT93: =BT88/BT103*100 -> 458.5661 | BU93: =BU88/BU103*100 -> 283.04521 | BV93: =BW93-BU93 -> 182.47076 | BW93: =BW88/BW103*100 -> 465.51597 | BX93: =BX88/BX103*100 -> 299.56263 | BY93: =BZ93-BX93 -> 189.69894 | BZ93: =BZ88/BZ103*100 -> 489.26157 | CA93: =CA88/CA103*100 -> 313.91098 | CB93: =CC93-CA93 -> 199.02779 | CC93: =CC88/CC103*100 -> 512.93877
B94: EPS Growth | F94: =F93/C93-1 -> 0.51921346 | G94: =G93/D93-1 -> 0.57224046 | H94: =H93/E93-1 -> 0.21226493 | I94: =I93/F93-1 -> 0.25240994 | J94: =J93/G93-1 -> 0.2762621 | K94: =K93/H93-1 -> 0.024882205 | L94: =L93/I93-1 -> 0.19800726 | M94: =M93/J93-1 -> 0.3582436 | ... CC94: =CC93/BZ93-1 -> 0.048393739
BE95: =506.1-BE88 -> -3.4 | BH95: =544.9-BH88 -> 0
B100: Shares Outstanding | AT100: =AY100 -> 0 | AU100: 42916 | BN100: =+BN118/BN102 -> 4.0146386 | BQ100: =+BQ111/BQ102 -> 4.2305581
AT101: =AT100-AQ100 -> 0 | AU101: =AU100-AT100 -> 42916
A102: WAFPO | B102: Av Ordinary Shares Outstanding (mn) - basic | C102: 82.543 | D102: 102.1405 | E102: =F102 -> 85.441 | F102: 85.441 | G102: =I102 -> 102.639 | H102: =I102 -> 102.639 | I102: 102.639 | J102: =L102 -> 103.117 | K102: =L102 -> 103.117 | L102: 103.117 | M102: 103.57341 | N102: =O102 -> 104.145 | O102: 104.145 | P102: 104.92369 | Q102: =R102 -> 105.348 | R102: 105.348 | S102: 106.78423 | T102: =U102 -> 106.995 | U102: 106.995 | V102: 107.91199 | W102: =X102 -> 108.118 | X102: 108.118 | Y102: 108.952 | Z102: =AA102 -> 107.8 | AA102: 107.8 | AB102: 98.719 | AC102: =AD102 -> 98.782 | AD102: 98.782 | AE102: 98.851 | AF102: =AG102 -> 98.884 | AG102: 98.884 | AH102: 99.759 | AI102: =AJ102 -> 99.975 | AJ102: 99.975 | AK102: 98.988 | AL102: =AK102 -> 98.988 | AM102: 98.982 | AN102: 99.02 | AO102: =AN102 -> 99.02 | AP102: 98.976 | AQ102: 107.9 | AR102: =AR107 -> 114.4214 | AS102: 111.7 | AT102: 114.7 | AU102: =AV102 -> 114.8 | AV102: 114.8 | AW102: 114.9 | AX102: =AY102 -> 114.9 | AY102: 114.9 | AZ102: 114.9 | BA102: =BB102 -> 114.9 | BB102: 114.9 | BC102: 114.9 | BD102: =BE102 -> 114.8 | BE102: 114.8 | BF102: 114.9 | BG102: =BH102 -> 113.7 | BH102: 113.7 | BI102: 109.3 | BJ102: =BK102 -> 109.3 | BK102: 109.3 | BL102: 109.3 | BM102: =BN102 -> 109.3 | BN102: 109.3 | BO102: 109.3 | BP102: =BQ102 -> 109.3 | BQ102: 109.3 | BR102: 109.3 | BS102: =BT102 -> 109.33398 | BT102: =AVERAGE(BQ107,BT107) -> 109.33398 | BU102: =BW102 -> 109.33398 | BV102: =BW102 -> 109.33398 | BW102: =AVERAGE(BT107,BW107) -> 109.33398 | BX102: =BZ102 -> 109.33398 | BY102: =BZ102 -> 109.33398 | BZ102: =AVERAGE(BW107,BZ107) -> 109.33398 | CA102: =CC102 -> 109.33398 | CB102: =CC102 -> 109.33398 | CC102: =AVERAGE(BZ107,CC107) -> 109.33398
A103: SharesOutstand | B103: Av Ordinary Shares Outstanding (mn) - diluted | C103: 83.185 | D103: 104.19933 | E103: =F103 -> 86.375 | F103: 86.375 | G103: =I103 -> 104.229 | H103: =I103 -> 104.229 | I103: 104.229 | J103: =L103 -> 105.253 | K103: =L103 -> 105.253 | L103: 105.253 | M103: 106.35108 | N103: =O103 -> 106.054 | O103: 106.054 | P103: 106.93014 | Q103: =R103 -> 107.255 | R103: 107.255 | S103: 107.582 | T103: =U103 -> 107.769 | U103: 107.769 | V103: 109.59204 | W103: =X103 -> 109.433 | X103: 109.433 | Y103: 109.775 | Z103: =AA103 -> 108.496 | AA103: 108.496 | AB103: 98.935 | AC103: =AD103 -> 98.842 | AD103: 98.842 | AE103: 98.858 | AF103: =AG103 -> 99.453 | AG103: 99.453 | AH103: 101.207 | AI103: =AJ103 -> 101.161 | AJ103: 101.161 | AK103: 100.135 | AL103: =AK103 -> 100.135 | AM103: 100.037 | AN103: 100.031 | AO103: =AN103 -> 100.031 | AP103: 100.037 | AQ103: 108.9 | AR103: =AR102 -> 114.4214 | AS103: 112.7 | AT103: 115.8 | AU103: =AV103 -> 115.9 | AV103: 115.9 | AW103: 116 | AX103: =AY103 -> 116.1 | AY103: 116.1 | AZ103: 115.7 | BA103: =BB103 -> 116 | BB103: 116 | BC103: 115.7 | BD103: =BC103 -> 115.7 | BE103: 115.6 | BF103: 115.4 | BG103: =BF103 -> 115.4 | BH103: 114.2 | BI103: 109.7 | BJ103: =BK103 -> 109.8 | BK103: 109.8 | BL103: 109.8 | BM103: =BN103 -> 109.5 | BN103: 109.5 | BO103: 109.7 | BP103: =BQ103 -> 109.7 | BQ103: 109.7 | BR103: 109.6 | BS103: =BT103 -> 109.73398 | BT103: =(BQ103-BQ102)+BT102 -> 109.73398 | BU103: =BW103 -> 109.73398 | BV103: =BW103 -> 109.73398 | BW103: =(BT103-BT102)+BW102 -> 109.73398 | BX103: =BZ103 -> 109.73398 | BY103: =BZ103 -> 109.73398 | BZ103: =(BW103-BW102)+BZ102 -> 109.73398 | CA103: =CC103 -> 109.73398 | CB103: =CC103 -> 109.73398 | CC103: =(BZ103-BZ102)+CC102 -> 109.73398
B105: Start of period | C105: 21.9 | F105: =C107 -> 102.453 | I105: =F107 -> 102.453 | L105: =I107 -> 102.839 | O105: =L107 -> 103.466 | R105: =O107 -> 104.629 | U105: =R107 -> 105.885 | X105: =U107 -> 107.24667 | AA105: =X107 -> 108.34499 | AD105: =AA107 -> 98.530763 | AG105: =AD107 -> 98.850643 | AJ105: =AG107 -> 98.947309 | AM105: =AJ107 -> 98.947309 | AP105: =AM107 -> 98.989901 | AS105: =AP107 -> 98.947309 | AV105: =AS107 -> 114.4214 | AW105: =AV107 -> 114.88337 | AX105: =AW107 -> 114.88337 | AY105: =AV107 -> 114.88337 | AZ105: =AY107 -> 114.88337 | BA105: =AZ107 -> 114.88337 | BB105: =AY107 -> 114.88337 | BC105: =BB107 -> 114.88337 | BD105: =BC107 -> 114.88337 | BE105: =BB107 -> 114.88337 | BF105: =BE107 -> 114.88337 | BG105: =BF107 -> 114.88337 | BH105: =BE107 -> 114.88337 | BI105: =BH107 -> 109.33398 | BJ105: =BI107 -> 109.33398 | BK105: =BH107 -> 109.33398 | BL105: =BK107 -> 109.33398 | BM105: =BL107 -> 109.33398 | BN105: =BK107 -> 109.33398 | BO105: =BN107 -> 109.33398 | BP105: =+BO107 -> 109.33398 | BQ105: =BN107 -> 109.33398 | BR105: =BT105 -> 109.33398 | BS105: =BT105 -> 109.33398 | BT105: =BQ107 -> 109.33398 | BU105: =BW105 -> 109.33398 | BV105: =BW105 -> 109.33398 | BW105: =BT107 -> 109.33398 | BX105: =BZ105 -> 109.33398 | BY105: =BZ105 -> 109.33398 | BZ105: =BW107 -> 109.33398 | CA105: =CC105 -> 109.33398 | CB105: =CC105 -> 109.33398 | CC105: =BZ107 -> 109.33398
B106: Change | C106: =C107-C105 -> 80.553 | F106: =F107-F105 -> 0 | I106: =I107-I105 -> 0.386 | L106: =L107-L105 -> 0.627 | O106: =O107-O105 -> 1.163 | R106: =R107-R105 -> 1.256 | U106: =U107-U105 -> 1.361666 | X106: =X107-X105 -> 1.098321 | AA106: =AA107-AA105 -> -9.814224 | AD106: =AD107-AD105 -> 0.31988 | AG106: =AG107-AG105 -> 0.096666 | AJ106: =AJ107-AJ105 -> 0 | AM106: =+AM250+AM252 -> 0 | AP106: =+AP250+AP252 -> 0 | AS106: =+AS250+AS252 -> 15.046182 | AV106: =+AV250+AV252 -> 0 | AY106: =+AY250+AY252 -> 0 | BB106: =+BB250+BB252 -> 0 | BE106: =+BE250+BE252 -> 0 | BH106: =+BH250+BH252 -> 0 | BI106: =+BI250+BI252 -> 0 | BJ106: =+BJ250+BJ252 -> 0 | BK106: =+BK250+BK252 -> 0 | BL106: =+BL250+BL252 -> 0 | BM106: =+BM250+BM252 -> 0 | BN106: =+BN250+BN252 -> 0 | BO106: =+BO107-BO105 -> 0 | BP106: =+BP250+BP252 -> 0 | BQ106: =+BQ250+BQ252 -> 0 | BR106: =+BR250+BR252 -> 0 | BS106: =+BS250+BS252 -> 0 | BT106: =+BT250+BT252 -> 0 | BU106: =+BU250+BU252 -> 0 | BV106: =+BV250+BV252 -> 0 | BW106: =+BW250+BW252 -> 0 | ... CC106: =+CC250+CC252 -> 0
A107: END_SHARES | B107: End Ordinary shares (mn) - basic | C107: 102.453 | D107: =F107 -> 102.453 | E107: =D107 -> 102.453 | F107: 102.453 | G107: =I107 -> 102.839 | H107: =G107 -> 102.839 | I107: 102.839 | J107: =L107 -> 103.466 | K107: =J107 -> 103.466 | L107: 103.466 | M107: =O107 -> 104.629 | N107: =M107 -> 104.629 | O107: 104.629 | P107: =R107 -> 105.885 | Q107: =P107 -> 105.885 | R107: 105.885 | S107: =U107 -> 107.24667 | T107: =S107 -> 107.24667 | U107: 107.24667 | V107: =X107 -> 108.34499 | W107: =V107 -> 108.34499 | X107: 108.34499 | Y107: =AA107 -> 98.530763 | Z107: =Y107 -> 98.530763 | AA107: 98.530763 | AB107: =AD107 -> 98.850643 | AC107: =AB107 -> 98.850643 | AD107: 98.850643 | AE107: =AG107 -> 98.947309 | AF107: =AE107 -> 98.947309 | AG107: 98.947309 | AH107: =AJ107 -> 98.947309 | AI107: =AH107 -> 98.947309 | AJ107: 98.947309 | AK107: =AM107 -> 98.989901 | AL107: =AK107 -> 98.989901 | AM107: 98.989901 | AN107: =AP107 -> 98.947309 | AO107: =AN107 -> 98.947309 | AP107: 98.947309 | AQ107: 114.3655 | AR107: =AS107 -> 114.4214 | AS107: =114.421403 -> 114.4214 | AT107: 114.86664 | AU107: =AV107 -> 114.88337 | AV107: 114.88337 | AW107: 114.88337 | AX107: =AY107 -> 114.88337 | AY107: 114.88337 | AZ107: =AX107 -> 114.88337 | BA107: =BB107 -> 114.88337 | BB107: 114.88337 | BC107: =BA107 -> 114.88337 | BD107: =BE107 -> 114.88337 | BE107: 114.88337 | BF107: =BD107 -> 114.88337 | BG107: =BH107 -> 109.33398 | BH107: 109.33398 | BI107: 109.33398 | BJ107: =BJ105-BS!S214+BJ106 -> 109.33398 | BK107: 109.33398 | BL107: 109.33398 | BM107: =BM105-BS!V214+BM106 -> 109.33398 | BN107: 109.33398 | BO107: 109.33398 | BP107: =BP105-BS!Y214+BP106 -> 109.33398 | BQ107: 109.33398 | BR107: 109.3 | BS107: =BS105-BS!AB214+BS106 -> 109.33398 | BT107: =BT105-BS!AC214+BT106 -> 109.33398 | BU107: =BU105-BS!AD214+BU106 -> 109.33398 | BV107: =BV105-BS!AE214+BV106 -> 109.33398 | BW107: =BW105-BS!AF214+BW106 -> 109.33398 | BX107: =BX105-BS!AG214+BX106 -> 109.33398 | BY107: =BY105-BS!AH214+BY106 -> 109.33398 | BZ107: =BZ105-BS!AI214+BZ106 -> 109.33398 | ... CC107: =CC105-BS!AL214+CC106 -> 109.33398
A109: MWEPS | B109: EPS - ModelWare Calculation | C109: 13.471671 | F109: 18.927578 | I109: 23.116414 | L109: 27.977255 | O109: 41.167022 | R109: 62.274403 | U109: 88.611791 | X109: 108.47269 | AA109: 123.03485 | AD109: 102.38349 | AG109: 114.35483 | AJ109: 124.80911 | AM109: 131.45327 | AP109: 140.1419 | AS109: 133.57109 | AV109: 205.09328 | AY109: 216.09054 | BB109: 278.96215 | BE109: 438.4153 | BH109: 470.39068 | BK109: 438.51833 | BN109: 400.73059 | BQ109: 394.88533 | BT109: 418.29678 | BW109: 465.51597 | BZ109: 489.26157 | CC109: 512.93877
B111: Reported Net Income | C111: =C88 -> 8.958 | D111: =D88 -> 9.3 | E111: =E88 -> 4.831 | F111: =F88 -> 14.131 | G111: =G88 -> 14.626 | H111: =H88 -> 7.067 | I111: =I88 -> 21.356 | J111: =J88 -> 18.85 | ... CC111: =CC88 -> 562.86813
B114: less exceptionals costs / gains | C114: =C62 -> 0 | D114: =D62 -> 0 | E114: =E62 -> 0 | F114: =F62 -> 0 | I114: =I62 -> 0 | J114: =J62 -> 0 | K114: =K62 -> 0 | L114: =L62 -> 0 | M114: =M62 -> 0 | N114: =N62 -> 0 | O114: =O62 -> 0 | P114: =P62 -> 0 | ... AN114: =AN62 -> 0 | AP114: =AP62 -> 0 | AQ114: =AQ62 -> -15.3 | AR114: =AS114-AQ114 -> -22.9 | AS114: =AS62 -> -38.2 | AV114: =AV62 -> 0 | AW114: =AW62 -> 0 | AX114: =AX62 -> 0 | AY114: =AY62 -> 0 | AZ114: =AZ62 -> 0 | BA114: =BA62 -> -19.7 | BB114: =BB62 -> -19.7 | BC114: =BC62 -> 0 | ... CC114: =CC62 -> 0
B115: Remove tax on exceptionals | C115: =C197 -> 0 | D115: =D197 -> 0 | E115: =E197 -> 0 | F115: =F197 -> 0 | I115: =I197 -> 0 | J115: =J197 -> 0 | K115: =K197 -> 0 | L115: =L197 -> 0 | M115: =M197 -> 0 | N115: =N197 -> 0 | O115: =O197 -> 0 | P115: =P197 -> 0 | ... AN115: =AN197 -> 0 | AP115: =AP197 -> 0 | AQ115: =AQ197 -> 0.3 | AR115: =AS115-AQ115 -> 2.538169 | AS115: =AS197 -> 2.838169 | AV115: =AV197 -> 0 | AW115: =AW197 -> 0 | AX115: =AX197 -> 0 | AY115: =AY197 -> 0 | AZ115: =AZ197 -> 0 | BA115: =BA197 -> -4.3 | BB115: =BB197 -> -4.3 | BC115: =BC197 -> 0 | ... CC115: =CC197 -> 0
B116: Remove significant items from discontinued operations | C116: =C82 -> 0 | D116: =D82 -> 0 | E116: =E82 -> 0 | F116: =F82 -> 0 | I116: =I82 -> 0 | J116: =J82 -> 0 | K116: =K82 -> 0 | L116: =L82 -> 0 | M116: =M82 -> 0 | N116: =N82 -> 0 | O116: =O82 -> 0 | P116: =P82 -> 0 | ... AN116: =AN82 -> 0 | AP116: =AP82 -> 0 | AQ116: =AQ82 -> 0 | AR116: =AS116-AQ116 -> 2.6358 | AS116: =AS114*-6.9% -> 2.6358 | AV116: =AV114*-6.9% -> 0 | AW116: =AW82 -> 0 | AX116: =AX82 -> 0 | AY116: =AY82 -> 0 | AZ116: =AZ82 -> 0 | BA116: =BA82 -> 0 | BB116: =BB82 -> 0 | BC116: =BC82 -> 0 | BD116: =BD82 -> 0 | ... CC116: =CC82 -> 0
A118: NPAT | B118: Normalised NPAT | C118: =C111-C114-C115-C116-C113 -> 8.958 | D118: =D111-D114-D115-D116-D113 -> 9.3 | E118: =E111-E114-E115-E116-E113 -> 4.831 | F118: =F111-F114-F115-F116-F113 -> 14.131 | G118: =G111-G114-G115-G116-G113 -> 14.626 | H118: =H111-H114-H115-H116-H113 -> 7.067 | I118: =I111-I114-I115-I116-I113 -> 21.356 | J118: =J111-J114-J115-J116-J113 -> 18.85 | ... CC118: =CC111-CC114-CC115-CC116-CC113 -> 562.86813
B119: Growth % | O119: =O118/L118-1 -> 0.56328379 | P119: =P118/M118-1 -> 0.63440278 | Q119: =Q118/N118-1 -> 0.53088156 | R119: =R118/O118-1 -> 0.61269157 | S119: =S118/P118-1 -> 0.39719029 | T119: =T118/Q118-1 -> 0.5473242 | U119: =U118/R118-1 -> 0.44986566 | V119: =V118/S118-1 -> 0.28727402 | ... CC119: =CC118/BZ118-1 -> 0.048393739
BE120: =+BE118-BC118-BD118 -> 4.4 | BH120: =+BH118-BF118-BG118 -> 0 | BK120: =+BK118-BI118-BJ118 -> 0 | BN120: =+BN118-BL118-BM118 -> 0 | BQ120: =+BQ118-BO118-BP118 -> 0
B121: Diluted Shares Outstanding | C121: =C103 -> 83.185 | D121: =D103 -> 104.19933 | E121: =E103 -> 86.375 | F121: =F103 -> 86.375 | G121: =G103 -> 104.229 | H121: =G103 -> 104.229 | I121: =I103 -> 104.229 | J121: =J103 -> 105.253 | K121: =K103 -> 105.253 | L121: =L103 -> 105.253 | M121: =M103 -> 106.35108 | N121: =N103 -> 106.054 | O121: =O103 -> 106.054 | P121: =P103 -> 106.93014 | ... CC121: =CC103 -> 109.73398
BA122: =BA120-AX120 -> 0
A123: Normalised EPS | B123: Normalised EPS | C123: =C118/C121*100 -> 10.768768 | D123: =D118/D121*100 -> 8.9252015 | E123: =E118/E121*100 -> 5.5930535 | F123: =F118/F121*100 -> 16.360058 | G123: =G118/G121*100 -> 14.032563 | H123: =H118/H121*100 -> 6.7802627 | I123: =I118/I121*100 -> 20.489499 | J123: =J118/J121*100 -> 17.909228 | ... CC123: =CC118/CC121*100 -> 512.93877
B124: Growth % | F124: =F123/C123-1 -> 0.51921346 | G124: =G123/D123-1 -> 0.57224046 | H124: =H123/E123-1 -> 0.21226493 | I124: =I123/F123-1 -> 0.25240994 | J124: =J123/G123-1 -> 0.2762621 | K124: =K123/H123-1 -> 0.024882205 | L124: =L123/I123-1 -> 0.19800726 | M124: =M123/J123-1 -> 0.3582436 | ... CC124: =CC123/BZ123-1 -> 0.048393739
B126: ModelWare EPS (in cents) | C126: =C123 -> 10.768768 | D126: =D123 -> 8.9252015 | E126: =E123 -> 5.5930535 | F126: =F123 -> 16.360058 | G126: =G123 -> 14.032563 | H126: =H123 -> 6.7802627 | I126: =I123 -> 20.489499 | J126: =J123 -> 17.909228 | ... CC126: =CC123 -> 512.93877
B127: ModelWare EPS Growth % | C127: =C124 -> 0 | D127: =D124 -> 0 | E127: =E124 -> 0 | F127: =F124 -> 0.51921346 | G127: =G124 -> 0.57224046 | H127: =H124 -> 0.21226493 | I127: =I124 -> 0.25240994 | J127: =J124 -> 0.2762621 | ... CC127: =CC124 -> 0.048393739
C128: =C118-C88 -> 0 | F128: =F118-F88 -> 0 | I128: =I118-I88 -> 0 | L128: =L118-L88 -> 0 | O128: =O118-O88 -> 0 | R128: =R118-R88 -> 0 | U128: =U118-U88 -> 0 | X128: =X118-X88 -> 0 | AA128: =AA118-AA88 -> 24.7 | AD128: =AD118-AD88 -> 0 | AG128: =AG118-AG88 -> 0 | AJ128: =AJ118-AJ88 -> 0 | AM128: =AM118-AM88 -> 0 | AN128: =63/AN118 -> 0.66179251 | AO128: =37/AO118 -> 0.64929367 | AP128: =AP118-AP88 -> 0 | AS128: =AS118-AS88 -> 32.726031 | AV128: =AV118-AV88 -> 0
B130: MW PTOP / EBITDA / NOPAT / FCFE / RNOA / ROE / EV / PE
A132: EBITDA | B132: ModelWare EBITDA | C132: =C139+C134 -> 18.1 | F132: =F139+F134 -> 25.9 | I132: =I139+I134 -> 42.3 | L132: =L139+L134 -> 52 | O132: =O139+O134 -> 76.388 | R132: =R139+R134 -> 116.99 | U132: =U139+U134 -> 160.715 | X132: =X139+X134 -> 198.387 | AA132: =AA139+AA134 -> 223.3 | AD132: =AD139+AD134 -> 192.213 | AG132: =AG139+AG134 -> 210.985 | AJ132: =AJ139+AJ134 -> 226.65 | AM132: =AM139+AM134 -> 240.031 | AP132: =AP139+AP134 -> 262.076 | AS132: =AS139+AS134 -> 360.3 | AV132: =AV139+AV134 -> 411.7 | AW132: =AW139+AW134 -> 27.7 | AX132: =AX139+AX134 -> 28.5 | AY132: =AY139+AY134 -> 429.1 | AZ132: =AZ139+AZ134 -> 109.1 | BA132: =BA139+BA134 -> 105.8 | BB132: =BB139+BB134 -> 732.2 | BC132: =BC139+BC134 -> 109.1 | ... CC132: =CC139+CC134 -> 1135.1003
A134: D&A | B134: Depreciation | C134: =-C52 -> 1.319 | F134: =-F52 -> 3.168 | I134: =-I52 -> 5.268 | L134: =-L52 -> 7.439 | O134: =-O52 -> 10.854 | R134: =-R52 -> 14.691 | U134: =-U52 -> 18.749 | X134: =-X52 -> 23.277 | AA134: =-AA52 -> 27.287 | AD134: =-AD52 -> 30.754 | AG134: =-AG52 -> 33.232 | AJ134: =-AJ52 -> 35.53 | AM134: =-AM52 -> 39.124 | AP134: =-AP52 -> 40.901 | AS134: =-AS52 -> 53.9 | AV134: =-AV52 -> 61.1 | AW134: =-AW52 -> 27.7 | AX134: =-AX52 -> 28.5 | AY134: =-AY52 -> 56.2 | AZ134: =-AZ52 -> 109.1 | BA134: =-BA52 -> 105.8 | BB134: =-BB52 -> 229.3 | BC134: =-BC52 -> 109.1 | ... CC134: =-CC52 -> 289.4085
B136: EBIT | C136: =C64 -> 16.781 | F136: =F64 -> 22.732 | I136: =I64 -> 37.032 | L136: =L64 -> 44.561 | O136: =O64 -> 65.534 | R136: =R64 -> 102.299 | U136: =U64 -> 141.966 | X136: =X64 -> 175.11 | AA136: =AA64 -> 162.613 | AD136: =AD64 -> 161.459 | AG136: =AG64 -> 177.753 | AJ136: =AJ64 -> 191.12 | AM136: =AM64 -> 200.907 | AP136: =AP64 -> 221.175 | AS136: =AS64 -> 268.2 | AV136: =AV64 -> 350.6 | AW136: =AW64 -> 236.6 | AX136: =AX64 -> 136.3 | AY136: =AY64 -> 372.9 | AZ136: =AZ64 -> 263 | BA136: =BA64 -> 220.2 | BB136: =BB64 -> 483.2 | BC136: =BC64 -> 462.8 | ... CC136: =CC64 -> 845.69179
B137: Add back Non Restructuring Exceptionals | C137: =-C62 -> 0 | F137: =-F62 -> 0 | I137: =-I62 -> 0 | L137: =-L62 -> 0 | O137: =-O62 -> 0 | R137: =-R62 -> 0 | U137: =-U62 -> 0 | X137: =-X62 -> 0 | AA137: =-AA62 -> 33.4 | AD137: =-AD62 -> 0 | AG137: =-AG62 -> 0 | AJ137: =-AJ62 -> 0 | AM137: =-AM62 -> 0 | AP137: =-AP62 -> 0 | AS137: =-AS62 -> 38.2 | AV137: =-AV62 -> 0 | AY137: =-AY62 -> 0 | BB137: =-BB62 -> 19.7 | BE137: =-BE62 -> 0 | BH137: =-BH62 -> 0 | BI137: =-BI62 -> 0 | BK137: =-BK62 -> 0 | BL137: =-BL62 -> 0 | BN137: =-BN62 -> 0 | BO137: =-BO62 -> 0 | BQ137: =-BQ62 -> 13.7 | BT137: =-BT62 -> 0 | BW137: =-BW62 -> 0 | BZ137: =-BZ62 -> 0 | CC137: =-CC62 -> 0
...

Sheet CFS
B2: JBH Statement of Cash Flows
B4: (A$mn, Year ending June) | C4: FY03 | D4: FY04 | E4: FY05 | F4: FY06 | G4: FY07 | H4: FY08 | I4: FY09 | J4: FY10 | K4: FY11 | L4: FY12 | M4: FY13 | N4: FY14 | O4: FY15 | P4: FY16 | Q4: FY17 | R4: FY18 | S4: FY19 | T4: FY20 | U4: FY21 | V4: FY22 | W4: 1H23 | X4: 2H23 | Y4: FY23 | Z4: 1H24 | AA4: 2H24 | AB4: FY24 | AC4: 1H25 | AD4: 2H25 | AE4: FY25 | AF4: 1H26e | AG4: 2H26e | AH4: =BS!AH4 -> FY26E | AI4: 1H27e | AJ4: 2H27e | AK4: =BS!AK4 -> FY27E | AL4: 1H28e | AM4: 2H28e | AN4: =BS!AN4 -> FY28E | AO4: 1H29e | AP4: 2H29e | AQ4: =BS!AQ4 -> FY29E
B6: Cash flows from Operating Activities
B7: Receipts from customers/tenants | C7: 388.991 | D7: 491.736 | E7: 757.964 | F7: 1038.663 | G7: 1397.827 | H7: 1985.141 | I7: 2511.888 | J7: 2965.823 | K7: 3267.49 | L7: 3448.13 | M7: 3646.509 | N7: 3832.979 | O7: 4012.13 | P7: 4355.75 | Q7: 6205.5 | R7: 7551.9 | S7: 7804.9 | T7: 8759.3 | U7: 9837.1 | V7: 10194.5 | W7: 5791.5 | X7: =Y7-W7 -> 4810.5 | Y7: 10602 | Z7: 5765.3 | AA7: =AB7-Z7 -> 4853.2 | AB7: 10618.5 | AC7: 6236.5 | AD7: =AE7-AC7 -> 5389.9 | AE7: 11626.4 | AF7: 6674
B8: Payments to suppliers & employees | C8: -358.242 | D8: -468.959 | E8: -747.094 | F8: -1006.089 | G8: -1311.465 | H8: -1905.792 | I8: -2318.308 | J8: -2755.14 | K8: -3101.569 | L8: -3171.643 | M8: -3442.104 | N8: -3723.982 | O8: -3767.211 | P8: -4101.228 | Q8: -5908.8 | R8: -7130.5 | S8: -7373.8 | T8: -7624.5 | U8: -9096.7 | V8: -9283.5 | W8: -4984 | X8: =Y8-W8 -> -4597.9 | Y8: -9581.9 | Z8: -5035.3 | AA8: =AB8-Z8 -> -4633 | AB8: -9668.3 | AC8: -5451.8 | AD8: =AE8-AC8 -> -5212.8 | AE8: -10664.6 | AF8: -5933.7
B9: Interest and costs of finance paid | C9: -3.337 | D9: -3.058 | E9: -5.705 | F9: -6.41 | G9: -8.393 | H9: -9.957 | I9: -8.31 | J9: -6.491 | K9: -6.047 | L9: -12.765 | M9: -8.896 | N9: -7.496 | O9: -5.689 | P9: -3.657 | Q9: -9.3 | R9: -15 | S9: -13.8 | T9: -11.5 | U9: -3.3 | V9: -1.3 | W9: -0.9 | X9: =Y9-W9 -> -2.8 | Y9: -3.7 | Z9: -0.8 | AA9: =AB9-Z9 -> -1.1 | AB9: -1.9 | AC9: -1.2 | AD9: =AE9-AC9 -> -0.5 | AE9: -1.7 | AF9: -0.2
B10: Interest received | C10: 0.316 | D10: 0.356 | E10: 0.56 | F10: =0.672+0.118 -> 0.79 | G10: 1.289 | H10: 1.008 | I10: 1.564 | J10: 1.448 | K10: 2.236 | L10: 0.568 | M10: 0.455 | N10: 0.402 | O10: 0.552 | P10: 0.521 | Q10: 1.7 | R10: 0.5 | S10: 0.7 | T10: 1.1 | U10: 1.6 | V10: 0.8 | W10: 1.8 | X10: =Y10-W10 -> 2.6 | Y10: 4.4 | Z10: 5.5 | AA10: =AB10-Z10 -> 5.7 | AB10: 11.2 | AC10: 6.8 | AD10: =AE10-AC10 -> 4.7 | AE10: 11.5 | AF10: 3.8
B11: Income tax paid | C11: -4.082 | D11: -5.282 | E11: -9.142 | F11: -11.333 | G11: -15.229 | H11: -27.963 | I11: -41.257 | J11: -53.537 | K11: -52.165 | L11: -49.283 | M11: -39.554 | N11: -60.577 | O11: -59.886 | P11: -66.246 | Q11: -98.5 | R11: -114.8 | S11: -116.4 | T11: -118.2 | U11: -158.7 | V11: -264.4 | W11: -163.9 | X11: =Y11-W11 -> -118.6 | Y11: -282.5 | Z11: -89 | AA11: =AB11-Z11 -> -88.7 | AB11: -177.7 | AC11: -117.9 | AD11: =AE11-AC11 -> -106.8 | AE11: -224.7 | AF11: -115.6
B12: Interest on lease liabilities | T12: -24.9 | U12: -21.3 | V12: -18.7 | W12: -9.4 | X12: =Y12-W12 -> -12.5 | Y12: -21.9 | Z12: -13.9 | AA12: =AB12-Z12 -> -15.3 | AB12: -29.2 | AC12: -16.8 | AD12: =AE12-AC12 -> -18.5 | AE12: -35.3 | AF12: -19.2
B13: Net Cash flows from operating activities | C13: =SUM(C7:C11) -> 23.646 | D13: =SUM(D7:D11) -> 14.793 | E13: =SUM(E7:E11) -> -3.417 | F13: =SUM(F7:F11) -> 15.621 | G13: =SUM(G7:G11) -> 64.029 | H13: =SUM(H7:H11) -> 42.437 | I13: =SUM(I7:I11) -> 145.577 | J13: =SUM(J7:J11) -> 152.103 | ... S13: =SUM(S7:S11) -> 301.6 | T13: =SUM(T7:T12) -> 981.3 | U13: =SUM(U7:U12) -> 558.7 | V13: =SUM(V7:V12) -> 627.4 | W13: =SUM(W7:W12) -> 635.1 | X13: =SUM(X7:X12) -> 81.3 | Y13: =SUM(Y7:Y12) -> 716.4 | Z13: =SUM(Z7:Z12) -> 631.8 | AA13: =SUM(AA7:AA12) -> 120.8 | ... AQ13: =SUM(AQ7:AQ12) -> 0
A15: EBIT_REPORTED | B15: EBIT | C15: =VLOOKUP($A$15,'P&L'!1:1048576,MATCH(CFS!C$4,'P&L'!$4:$4,FALSE),FALSE) -> 16.781 | D15: =VLOOKUP($A$15,'P&L'!1:1048576,MATCH(CFS!D$4,'P&L'!$4:$4,FALSE),FALSE) -> 22.732 | E15: =VLOOKUP($A$15,'P&L'!1:1048576,MATCH(CFS!E$4,'P&L'!$4:$4,FALSE),FALSE) -> 37.032 | F15: =VLOOKUP($A$15,'P&L'!1:1048576,MATCH(CFS!F$4,'P&L'!$4:$4,FALSE),FALSE) -> 44.561 | G15: =VLOOKUP($A$15,'P&L'!1:1048576,MATCH(CFS!G$4,'P&L'!$4:$4,FALSE),FALSE) -> 65.534 | H15: =VLOOKUP($A$15,'P&L'!1:1048576,MATCH(CFS!H$4,'P&L'!$4:$4,FALSE),FALSE) -> 102.299 | I15: =VLOOKUP($A$15,'P&L'!1:1048576,MATCH(CFS!I$4,'P&L'!$4:$4,FALSE),FALSE) -> 141.966 | J15: =VLOOKUP($A$15,'P&L'!1:1048576,MATCH(CFS!J$4,'P&L'!$4:$4,FALSE),FALSE) -> 175.11 | ... AQ15: =VLOOKUP($A$15,'P&L'!1:1048576,MATCH(CFS!AQ$4,'P&L'!$4:$4,FALSE),FALSE) -> 845.69179
A16: TOTAL_D&A | B16: Depreciation & Amortisation | C16: =VLOOKUP($A$16,Drivers!1:1048576,MATCH(CFS!C$4,Drivers!2:2,FALSE),FALSE) -> 1.319 | D16: =VLOOKUP($A$16,Drivers!1:1048576,MATCH(CFS!D$4,Drivers!2:2,FALSE),FALSE) -> 3.168 | E16: =VLOOKUP($A$16,Drivers!1:1048576,MATCH(CFS!E$4,Drivers!2:2,FALSE),FALSE) -> 5.268 | F16: =VLOOKUP($A$16,Drivers!1:1048576,MATCH(CFS!F$4,Drivers!2:2,FALSE),FALSE) -> 7.439 | G16: =VLOOKUP($A$16,Drivers!1:1048576,MATCH(CFS!G$4,Drivers!2:2,FALSE),FALSE) -> 10.854 | H16: =VLOOKUP($A$16,Drivers!1:1048576,MATCH(CFS!H$4,Drivers!2:2,FALSE),FALSE) -> 14.691 | I16: =VLOOKUP($A$16,Drivers!1:1048576,MATCH(CFS!I$4,Drivers!2:2,FALSE),FALSE) -> 18.749 | J16: =VLOOKUP($A$16,Drivers!1:1048576,MATCH(CFS!J$4,Drivers!2:2,FALSE),FALSE) -> 23.277 | ... AQ16: =VLOOKUP($A$16,Drivers!1:1048576,MATCH(CFS!AQ$4,Drivers!2:2,FALSE),FALSE) -> 289.4085
A17: TAX | B17: Tax paid | C17: =VLOOKUP($A$17,'P&L'!1:1048576,MATCH(CFS!C$4,'P&L'!4:4,FALSE),FALSE) -> -3.716 | D17: =VLOOKUP($A$17,'P&L'!1:1048576,MATCH(CFS!D$4,'P&L'!4:4,FALSE),FALSE) -> -5.899 | E17: =VLOOKUP($A$17,'P&L'!1:1048576,MATCH(CFS!E$4,'P&L'!4:4,FALSE),FALSE) -> -9.442 | F17: =VLOOKUP($A$17,'P&L'!1:1048576,MATCH(CFS!F$4,'P&L'!4:4,FALSE),FALSE) -> -11.954 | G17: =VLOOKUP($A$17,'P&L'!1:1048576,MATCH(CFS!G$4,'P&L'!4:4,FALSE),FALSE) -> -18.003 | H17: =VLOOKUP($A$17,'P&L'!1:1048576,MATCH(CFS!H$4,'P&L'!4:4,FALSE),FALSE) -> -28.875 | I17: =VLOOKUP($A$17,'P&L'!1:1048576,MATCH(CFS!I$4,'P&L'!4:4,FALSE),FALSE) -> -41.055 | J17: =VLOOKUP($A$17,'P&L'!1:1048576,MATCH(CFS!J$4,'P&L'!4:4,FALSE),FALSE) -> -50.949 | ... AQ17: =VLOOKUP($A$17,'P&L'!1:1048576,MATCH(CFS!AQ$4,'P&L'!4:4,FALSE),FALSE) -> -242.6603
A18: Finance_Expense | B18: Interest paid | C18: =VLOOKUP($A$18,'P&L'!1:1048576,MATCH(CFS!C$4,'P&L'!4:4,FALSE),FALSE) -> 0 | D18: =VLOOKUP($A$18,'P&L'!1:1048576,MATCH(CFS!D$4,'P&L'!4:4,FALSE),FALSE) -> 0 | E18: =VLOOKUP($A$18,'P&L'!1:1048576,MATCH(CFS!E$4,'P&L'!4:4,FALSE),FALSE) -> 0 | F18: =VLOOKUP($A$18,'P&L'!1:1048576,MATCH(CFS!F$4,'P&L'!4:4,FALSE),FALSE) -> 0 | G18: =VLOOKUP($A$18,'P&L'!1:1048576,MATCH(CFS!G$4,'P&L'!4:4,FALSE),FALSE) -> 0 | H18: =VLOOKUP($A$18,'P&L'!1:1048576,MATCH(CFS!H$4,'P&L'!4:4,FALSE),FALSE) -> 0 | I18: =VLOOKUP($A$18,'P&L'!1:1048576,MATCH(CFS!I$4,'P&L'!4:4,FALSE),FALSE) -> 0 | J18: =VLOOKUP($A$18,'P&L'!1:1048576,MATCH(CFS!J$4,'P&L'!4:4,FALSE),FALSE) -> 0 | ... AQ18: =VLOOKUP($A$18,'P&L'!1:1048576,MATCH(CFS!AQ$4,'P&L'!4:4,FALSE),FALSE) -> -44.030589
A19: Finance_Income | B19: Interest received | C19: =VLOOKUP($A$19,'P&L'!1:1048576,MATCH(CFS!C$4,'P&L'!4:4,FALSE),FALSE) -> 0.316 | D19: =VLOOKUP($A$19,'P&L'!1:1048576,MATCH(CFS!D$4,'P&L'!4:4,FALSE),FALSE) -> 0.356 | E19: =VLOOKUP($A$19,'P&L'!1:1048576,MATCH(CFS!E$4,'P&L'!4:4,FALSE),FALSE) -> 0.56 | F19: =VLOOKUP($A$19,'P&L'!1:1048576,MATCH(CFS!F$4,'P&L'!4:4,FALSE),FALSE) -> 0.672 | G19: =VLOOKUP($A$19,'P&L'!1:1048576,MATCH(CFS!G$4,'P&L'!4:4,FALSE),FALSE) -> 1.302 | H19: =VLOOKUP($A$19,'P&L'!1:1048576,MATCH(CFS!H$4,'P&L'!4:4,FALSE),FALSE) -> 1.008 | I19: =VLOOKUP($A$19,'P&L'!1:1048576,MATCH(CFS!I$4,'P&L'!4:4,FALSE),FALSE) -> 1.562 | J19: =VLOOKUP($A$19,'P&L'!1:1048576,MATCH(CFS!J$4,'P&L'!4:4,FALSE),FALSE) -> 1.448 | ... AQ19: =VLOOKUP($A$19,'P&L'!1:1048576,MATCH(CFS!AQ$4,'P&L'!4:4,FALSE),FALSE) -> 4.4865717
A20: WORKCAP_CHG | B20: Change in working capital | C20: =-VLOOKUP($A$20,BS!1:1048576,MATCH(CFS!C$4,BS!4:4,FALSE),FALSE) -> 0 | D20: =-VLOOKUP($A$20,BS!1:1048576,MATCH(CFS!D$4,BS!4:4,FALSE),FALSE) -> -4.702 | E20: =-VLOOKUP($A$20,BS!1:1048576,MATCH(CFS!E$4,BS!4:4,FALSE),FALSE) -> -29.269 | F20: =-VLOOKUP($A$20,BS!1:1048576,MATCH(CFS!F$4,BS!4:4,FALSE),FALSE) -> -22.831 | G20: =-VLOOKUP($A$20,BS!1:1048576,MATCH(CFS!G$4,BS!4:4,FALSE),FALSE) -> -4.322 | H20: =-VLOOKUP($A$20,BS!1:1048576,MATCH(CFS!H$4,BS!4:4,FALSE),FALSE) -> -47.791 | I20: =-VLOOKUP($A$20,BS!1:1048576,MATCH(CFS!I$4,BS!4:4,FALSE),FALSE) -> 7.932 | J20: =-VLOOKUP($A$20,BS!1:1048576,MATCH(CFS!J$4,BS!4:4,FALSE),FALSE) -> 2.09 | ... AQ20: =-VLOOKUP($A$20,BS!1:1048576,MATCH(CFS!AQ$4,BS!4:4,FALSE),FALSE) -> -29.01674
B21: Other | C21: =C13-SUM(C15:C20) -> 8.946 | D21: =D13-SUM(D15:D20) -> -0.862 | E21: =E13-SUM(E15:E20) -> -7.566 | F21: =F13-SUM(F15:F20) -> -2.266 | G21: =G13-SUM(G15:G20) -> 8.664 | H21: =H13-SUM(H15:H20) -> 1.105 | I21: =I13-SUM(I15:I20) -> 16.423 | J21: =J13-SUM(J15:J20) -> 1.127 | ... W21: =W13-SUM(W15:W20) -> -17.2 | X21: =Y21-W21 -> -34.6 | Y21: =Y13-SUM(Y15:Y20) -> -51.8 | Z21: =Z13-SUM(Z15:Z20) -> 59.5 | AA21: =AB21-Z21 -> -1.8 | AB21: =AB13-SUM(AB15:AB20) -> 57.7 | AC21: =AC13-SUM(AC15:AC20) -> 96.2 | AD21: =AD13-SUM(AD15:AD20) -> -15 | AE21: =AE13-SUM(AE15:AE20) -> 81.2 | AF21: =AF13-SUM(AF15:AF20) -> 26.5 | AG21: 0 | AH21: =+AF21+AG21 -> 26.5 | AI21: =AK21*0.5 -> 0 | AJ21: =AK21-AI21 -> 0 | AK21: 0 | AL21: =AN21*0.5 -> 0 | AM21: =AN21-AL21 -> 0 | AN21: =AK21*1.03 -> 0 | AO21: =AQ21*0.5 -> 0 | AP21: =AQ21-AO21 -> 0 | AQ21: =AN21*1.03 -> 0
A22: OCF | B22: Net Cash flows from operating activities | C22: =C13 -> 23.646 | D22: =D13 -> 14.793 | E22: =E13 -> -3.417 | F22: =F13 -> 15.621 | G22: =G13 -> 64.029 | H22: =H13 -> 42.437 | I22: =I13 -> 145.577 | J22: =J13 -> 152.103 | ... P22: =P13 -> 185.14 | Q22: =SUM(Q14:Q21) -> 190.6 | R22: =SUM(R14:R21) -> 292.1 | S22: =SUM(S14:S21) -> 301.6 | T22: =SUM(T14:T21) -> 981.3 | U22: =SUM(U14:U21) -> 558.7 | V22: =SUM(V14:V21) -> 627.4 | W22: =SUM(W14:W21) -> 635.1 | X22: =SUM(X14:X21) -> 81.3 | ... AQ22: =SUM(AQ14:AQ21) -> 823.87924
B24: Cash flows from Investing Activities
B25: Proceeds from sale of PP&E | C25: 0.478 | D25: 0.145 | E25: 0.052 | F25: 0.2 | G25: 0.18 | H25: 0.234 | I25: 0.591 | J25: 1.063 | K25: 1.144 | L25: 1.257 | M25: 1.203 | N25: 0.674 | O25: 0.496 | P25: 0.342 | Q25: 0.2 | R25: 0.4 | S25: 0.2 | T25: 0.1 | U25: 0 | V25: 0.2 | W25: 0.1 | X25: =+Y25-W25 -> 0.2 | Y25: 0.3 | Z25: 0.1 | AA25: =+AB25-Z25 -> 0 | AB25: 0.1 | AC25: 0 | AD25: =+AE25-AC25 -> 0.2 | AE25: 0.2 | AF25: 0 | AG25: 0 | AH25: =+AF25+AG25 -> 0 | AI25: 0 | AJ25: 0 | AK25: =+AI25+AJ25 -> 0 | AL25: 0 | AM25: 0 | AN25: =+AL25+AM25 -> 0 | AO25: 0 | AP25: 0 | AQ25: =+AO25+AP25 -> 0
A26: CAPEX | B26: Payments for PP&E | C26: -6.253 | D26: -10.282 | E26: -15.812 | F26: -29.046 | G26: -34.406 | H26: -51.573 | I26: -44.444 | J26: -54.46 | K26: -45.063 | L26: -46.078 | M26: -35.307 | N26: -35.914 | O26: -42.466 | P26: -52.343 | Q26: -49.1 | R26: -54.4 | S26: -59.3 | T26: -43.1 | U26: -57.7 | V26: -57.6 | W26: -34.1 | X26: =+Y26-W26 -> -37.9 | Y26: -72 | Z26: -36.7 | AA26: =+AB26-Z26 -> -37.8 | AB26: -74.5 | AC26: -38.7 | AD26: =+AE26-AC26 -> -43.6 | AE26: -82.3 | AF26: -46.9 | AG26: =-Drivers!AR412 -> -42.30801 | AH26: =-Drivers!AS412 -> -89.20801 | AI26: =-Drivers!AT412 -> -49.381379 | AJ26: =-Drivers!AU412 -> -49.381379 | AK26: =-Drivers!AV412 -> -98.762758 | AL26: =-Drivers!AW412 -> -51.45643 | AM26: =-Drivers!AX412 -> -51.45643 | AN26: =-Drivers!AY412 -> -102.91286 | ... AQ26: =-Drivers!BB412 -> -107.24246
B27: Payments for Intangibles | D27: -3.543 | F27: 0 | G27: 0 | H27: 0 | I27: 0 | J27: -2.388 | K27: 0 | L27: 0 | M27: 0 | N27: 0 | O27: 0 | P27: 0 | R27: 0 | S27: 0 | T27: 0 | U27: 0 | V27: 0 | W27: 0 | X27: =Y27-W27 -> 0 | Y27: 0 | Z27: 0 | AA27: =AB27-Z27 -> 0 | AB27: 0 | AC27: 0 | AD27: =AE27-AC27 -> 0 | AE27: 0 | AF27: 0 | AG27: =AH27-AF27 -> 0 | AH27: 0 | AI27: 0 | AJ27: =AK27-AI27 -> 0 | AK27: 0 | AL27: 0 | AM27: =AN27-AL27 -> 0 | AN27: 0 | AO27: 0 | AP27: =AQ27-AO27 -> 0 | AQ27: 0
B28: Payments for acquisition of subsidiary/business, net of cash acquired | C28: -0.006 | E28: =-0.45-21.66 -> -22.11 | F28: 0 | G28: -19.231 | H28: -8.185 | I28: 0 | J28: 0 | K28: 0 | L28: 0 | M28: -4.197 | N28: 0 | O28: 0 | P28: 0 | Q28: -836.6 | R28: 0 | S28: 0 | T28: 0 | U28: 0 | V28: 0 | W28: 0 | X28: =Y28-W28 -> 0 | Y28: 0 | Z28: 0 | AA28: =AB28-Z28 -> 0 | AB28: 0 | AC28: -41 | AD28: =AE28-AC28 -> 0.2 | AE28: -40.8 | AF28: 0 | AG28: =AH28-AF28 -> 0 | AH28: 0 | AI28: 0 | AJ28: =AK28-AI28 -> 0 | AK28: 0 | AL28: 0 | AM28: =AN28-AL28 -> 0 | AN28: 0 | AO28: 0 | AP28: =AQ28-AO28 -> 0 | AQ28: 0
B29: Acquisition of non-controlling interest | E29: 0 | F29: 0 | G29: 0 | H29: 0 | I29: 0 | J29: 0 | K29: 0 | L29: 0 | M29: 0 | N29: -3 | O29: -2.4 | P29: 0 | Q29: 0 | R29: 0 | S29: 0 | T29: 0 | U29: 0 | V29: 0 | W29: 0 | X29: =Y29-W29 -> 0 | Y29: 0 | Z29: 0 | AA29: =AB29-Z29 -> 0 | AB29: 0 | AC29: 0 | AD29: =AE29-AC29 -> 0 | AE29: 0 | AF29: 0 | AG29: =AH29-AF29 -> 0 | AH29: 0 | AI29: 0 | AJ29: =AK29-AI29 -> 0 | AK29: 0 | AL29: 0 | AM29: =AN29-AL29 -> 0 | AN29: 0 | AO29: 0 | AP29: =AQ29-AO29 -> 0 | AQ29: 0
B30: Other investing activities | X30: 0 | Y30: 0 | AA30: 0 | AB30: 0 | AD30: 0
B31: Net Cash flows from investing activities | C31: =SUM(C23:C29) -> -5.781 | D31: =SUM(D23:D29) -> -13.68 | E31: =SUM(E23:E29) -> -37.87 | F31: =SUM(F23:F29) -> -28.846 | G31: =SUM(G23:G29) -> -53.457 | H31: =SUM(H23:H29) -> -59.524 | I31: =SUM(I23:I29) -> -43.853 | J31: =SUM(J23:J29) -> -55.785 | ... W31: =SUM(W23:W29) -> -34 | X31: =SUM(X23:X30) -> -37.7 | Y31: =SUM(Y23:Y30) -> -71.7 | Z31: =SUM(Z23:Z29) -> -36.6 | AA31: =SUM(AA23:AA30) -> -37.8 | AB31: =SUM(AB23:AB30) -> -74.4 | AC31: =SUM(AC23:AC29) -> -79.7 | AD31: =SUM(AD23:AD29) -> -43.2 | AE31: =SUM(AE23:AE29) -> -122.9 | AF31: =SUM(AF23:AF29) -> -46.9 | AG31: =SUM(AG23:AG29) -> -42.30801 | AH31: =SUM(AH23:AH29) -> -89.20801 | AI31: =SUM(AI23:AI29) -> -49.381379 | AJ31: =SUM(AJ23:AJ29) -> -49.381379 | ... AQ31: =SUM(AQ23:AQ29) -> -107.24246
B33: Cash flows from Financing Activities
A34: Proceeds_issue_shr | B34: Proceeds from issue of shares (sharebuyback) | D34: 10.296 | E34: 0.232 | F34: 0.608 | G34: 2.235 | H34: 2.96 | I34: 4.159 | J34: 6.838 | K34: =9.305-173.333 -> -164.028 | L34: 3.514 | M34: =1.082 -> 1.082 | N34: =21.523-25.83 -> -4.307 | O34: =3.125-4.97 -> -1.845 | P34: =5.955-13.181 -> -7.226 | Q34: 395.9 | R34: 3 | S34: 1.9 | T34: 1.3 | U34: 0 | W34: =+'P&L'!BI249+'P&L'!BI251 -> 0 | X34: =Y34-W34 -> 0 | Y34: 0 | Z34: 0 | AA34: =AB34-Z34 -> 0 | AB34: 0 | AC34: =+'P&L'!BO249+'P&L'!BO251 -> 0 | AD34: =AE34-AC34 -> 0 | AE34: 0 | AF34: =+'P&L'!BR249+'P&L'!BR251 -> 0 | AG34: =+'P&L'!BS249+'P&L'!BS251 -> 0 | AH34: =+'P&L'!BT249+'P&L'!BT251 -> 0 | AI34: =+'P&L'!BU249+'P&L'!BU251 -> 0 | AJ34: =+'P&L'!BV249+'P&L'!BV251 -> 0 | AK34: =+'P&L'!BW249+'P&L'!BW251 -> 0 | AL34: =+'P&L'!BX249+'P&L'!BX251 -> 0 | AM34: =+'P&L'!BY249+'P&L'!BY251 -> 0 | ... AQ34: =+'P&L'!CC249+'P&L'!CC251 -> 0
B35: Proceeds/ (repayment) of borrowings | C35: =32-35.171-4.024+3.105 -> -4.09 | D35: =-0.601-3.368+9.69 -> 5.721 | E35: =13.142-4.495+25 -> 33.647 | F35: =-20.117+43.024 -> 22.907 | G35: 15.793 | H35: 5.841 | I35: -35.278 | J35: -20 | K35: 163.334 | L35: -84.174 | M35: -26.21 | N35: 54.063 | O35: -40.113 | P35: -30 | Q35: 450 | R35: -89.7 | S35: -30.5 | T35: -440 | U35: 0 | V35: =60-0.6 -> 59.4 | W35: -60 | X35: =Y35-W35 -> 50 | Y35: -10 | Z35: -50 | AA35: =AB35-Z35 -> 15.2 | AB35: -34.8 | AC35: -15 | AD35: =AE35-AC35 -> -1.4 | AE35: -16.4 | AF35: =AH35*0.5 -> 0 | AG35: =AH35-AF35 -> 0 | AI35: =AK35*0.5 -> 0 | AJ35: =AK35-AI35 -> 0 | AL35: =AN35*0.5 -> 0 | AM35: =AN35-AL35 -> 0 | AO35: =AQ35*0.5 -> 0 | AP35: =AQ35-AO35 -> 0
A36: debt_issue_cost | B36: Payments for debt issue costs | C36: -1.347 | D36: 0 | E36: 0 | F36: 0 | G36: 0 | I36: 0 | J36: 0 | K36: -0.955 | L36: -0.013 | M36: -0.632 | N36: -0.064 | O36: -0.484 | P36: -0.09 | Q36: -1.7 | R36: -0.8 | S36: -0.6 | T36: -0.1 | W36: 0 | X36: =Y36-W36 -> 0 | Y36: 0 | Z36: 0 | AA36: =AB36-Z36 -> 0 | AB36: 0 | AD36: =AE36-AC36 -> 0 | AE36: 0
A37: buyback_cost | B37: Share issue and buy back costs | D37: 0 | E37: 0 | F37: 0 | G37: 0 | I37: 0 | J37: 0 | K37: -0.801 | L37: -0.04 | M37: 0 | N37: -0.118 | O37: -0.024 | P37: -0.044 | Q37: -9.2 | R37: 0 | S37: -8.8 | T37: -32.9 | U37: -10.2 | V37: =-250-0.6-28.2 -> -278.8 | W37: =-0.4-17.3 -> -17.7 | X37: =Y37-W37 -> 0.1 | Y37: =-17.3-0.3 -> -17.6 | Z37: -17 | AA37: =AB37-Z37 -> 0 | AB37: -17 | AC37: -20.9 | AD37: =AE37-AC37 -> 0 | AE37: -20.9 | AF37: =-26.9+0 -> -26.9 | AG37: 0 | AH37: =+AF37+AG37 -> -26.9
A38: DIVIDENDS | B38: Dividends paid | D38: -13.688 | E38: -7.393 | F38: -7.428 | G38: -9.386 | H38: -16.913 | I38: -33.217 | J38: -67.083 | K38: -88.411 | L38: -77.031 | M38: -65.263 | N38: -77.183 | O38: -87.174 | P38: -93.205 | Q38: -119.1 | R38: -151.6 | S38: -157.4 | T38: -172.3 | U38: -310.2 | V38: -310.2 | W38: -167.3 | X38: =Y38-W38 -> -215.4 | Y38: -382.7 | Z38: -125.7 | AA38: =AB38-Z38 -> -172.8 | AB38: -298.5 | AC38: -200.1 | AD38: =AE38-AC38 -> -185.8 | AE38: -385.9 | AF38: -224.1 | AG38: =-BS!AF184 -> -224.1 | AH38: =+AG38+AF38 -> -448.2 | AI38: =-BS!AG184 -> -157.86483 | AJ38: =-BS!AI184 -> -232.94758 | AK38: =+AJ38+AI38 -> -390.81241 | AL38: =-BS!AJ184 -> -160.3909 | AM38: =-BS!AL184 -> -246.5415 | AN38: =+AM38+AL38 -> -406.9324 | AO38: =-BS!AM184 -> -166.86087 | AP38: =-BS!AO184 -> -258.35026 | AQ38: =+AP38+AO38 -> -425.21114
A39: lease_payments | B39: Payments of lease liabilities | T39: -161.8 | U39: -168.9 | V39: -177.6 | W39: -91.1 | X39: =Y39-W39 -> -91.7 | Y39: -182.8 | Z39: -91.9 | AA39: =AB39-Z39 -> -95.7 | AB39: -187.6 | AC39: -101.1 | AD39: =AE39-AC39 -> -98.1 | AE39: -199.2 | AF39: -105.2 | AG39: =+AH39-AF39 -> -99.976 | AH39: =+AE39*1.03 -> -205.176 | AI39: =0.5*AK39 -> -105.66564 | AJ39: =+AK39-AI39 -> -105.66564 | AK39: =+AH39*1.03 -> -211.33128 | AL39: =0.5*AN39 -> -108.83561 | AM39: =+AN39-AL39 -> -108.83561 | AN39: =+AK39*1.03 -> -217.67122 | AO39: =0.5*AQ39 -> -112.10068 | AP39: =+AQ39-AO39 -> -112.10068 | AQ39: =+AN39*1.03 -> -224.20135
B40: Net Cash flows from financing activities | C40: =SUM(C34:C38) -> -5.437 | D40: =SUM(D34:D38) -> 2.329 | E40: =SUM(E34:E39) -> 26.486 | F40: =SUM(F34:F38) -> 16.087 | G40: =SUM(G34:G38) -> 8.642 | H40: =SUM(H34:H38) -> -8.112 | I40: =SUM(I34:I38) -> -64.336 | J40: =SUM(J34:J38) -> -80.245 | K40: =SUM(K34:K38) -> -90.861 | L40: =SUM(L34:L38) -> -157.744 | M40: =SUM(M34:M38) -> -91.023 | ... S40: =SUM(S34:S38) -> -195.4 | T40: =SUM(T34:T39) -> -805.8 | U40: =SUM(U34:U39) -> -489.3 | V40: =SUM(V34:V39) -> -707.2 | W40: =SUM(W34:W39) -> -336.1 | X40: =SUM(X34:X39) -> -257 | Y40: =SUM(Y34:Y39) -> -593.1 | Z40: =SUM(Z34:Z39) -> -284.6 | AA40: =SUM(AA34:AA39) -> -253.3 | ... AQ40: =SUM(AQ34:AQ39) -> -649.41249
A42: TOTAL_CASH_FLOW | B42: Total Cash Flows from activities | C42: =C22+C31+C40 -> 12.428 | D42: =D22+D31+D40 -> 3.442 | E42: =E22+E31+E40 -> -14.801 | F42: =F22+F31+F40 -> 2.862 | G42: =G22+G31+G40 -> 19.214 | H42: =H22+H31+H40 -> -25.199 | I42: =I22+I31+I40 -> 37.388 | J42: =J22+J31+J40 -> 16.073 | ... AQ42: =AQ22+AQ31+AQ40 -> 67.224289
B44: Cash & Equivalents at beginning of year | C44: 0.562 | D44: =C47 -> 12.99 | E44: =D47 -> 16.432 | F44: =E47 -> 1.631 | G44: =F47 -> 4.493 | H44: =G47 -> 23.707 | I44: =H47 -> -1.492 | J44: =I47 -> 35.79 | K44: =J47 -> 51.735 | ... X44: =W47 -> 391.184 | Y44: =+V47 -> 125.584 | Z44: =Y47 -> 177.284 | AA44: =Z47 -> 487.984 | AB44: =+Y47 -> 177.284 | AC44: =AB47 -> 317.684 | AD44: =AC47 -> 556.384 | AE44: =AB47 -> 317.684 | AF44: =AE47 -> 284.084 | AG44: =AF47 -> 489.484 | AH44: =AE47 -> 284.084 | AI44: =AH47 -> 278.73729 | AJ44: =AI47 -> 326.68173 | AK44: =AH47 -> 278.73729 | AL44: =AK47 -> 336.69984 | AM44: =AL47 -> 392.7342 | AN44: =AK47 -> 336.69984 | AO44: =AN47 -> 401.13494 | AP44: =AO47 -> 460.65711 | AQ44: =AN47 -> 401.13494
B45: Effects of FX | E45: 0 | F45: 0 | G45: 0 | H45: 0 | I45: -0.106 | J45: -0.128 | K45: 0.346 | L45: 0.022 | M45: 0.572 | N45: 0.6 | O45: -0.2 | P45: 0.179 | Q45: -0.1 | R45: 0.2 | S45: 0.1 | T45: -0.2 | U45: 0 | V45: -0.4 | W45: 0.6 | X45: =+Y45-W45 -> -0.5 | Y45: 0.1 | Z45: 0.1 | AA45: =+AB45-Z45 -> 0 | AB45: 0.1 | AC45: -0.1 | AD45: =+AE45-AC45 -> 0.2 | AE45: 0.1 | AF45: -0.6 | AG45: 0 | AH45: =+AF45+AG45 -> -0.6 | AI45: 0 | AJ45: =AK45-AI45 -> 0 | AK45: 0 | AL45: 0 | AM45: =AN45-AL45 -> 0 | AN45: 0 | AO45: 0 | AP45: =AQ45-AO45 -> 0 | AQ45: 0
B46: Restatement of Cash Balance
B47: Cash & Equivalents at end of year | C47: =C42+C44+C45 -> 12.99 | D47: =D42+D44+D45 -> 16.432 | E47: =E42+E44+E45 -> 1.631 | F47: =F42+F44+F45 -> 4.493 | G47: =G42+G44+G45 -> 23.707 | H47: =H42+H44+H45 -> -1.492 | I47: =I42+I44+I45 -> 35.79 | J47: =J42+J44+J45 -> 51.735 | ... AQ47: =AQ42+AQ44+AQ45 -> 468.35923
B50: Bank overdraft | H50: -1.492
B51: Change in Bank overdraft | D51: =+D50-C50 -> 0 | E51: =+E50-D50 -> 0 | F51: =+F50-E50 -> 0 | G51: =+G50-F50 -> 0 | H51: =+H50-G50 -> -1.492 | I51: =+I50-H50 -> 1.492 | J51: =+J50-I50 -> 0 | K51: =+K50-J50 -> 0 | ... X51: =+X50-W50 -> 0 | Y51: =+Y50-V50 -> 0 | Z51: =+Z50-Y50 -> 0 | AA51: =+AA50-Z50 -> 0 | AB51: =+AB50-Y50 -> 0 | AC51: =+AC50-AB50 -> 0 | AD51: =+AD50-AC50 -> 0 | AE51: =+AE50-AB50 -> 0 | AF51: =+AF50-AE50 -> 0 | AG51: =+AG50-AF50 -> 0 | AH51: =+AH50-AE50 -> 0 | AI51: =+AI50-AH50 -> 0 | AJ51: =+AJ50-AI50 -> 0 | AK51: =+AK50-AH50 -> 0 | AL51: =+AL50-AK50 -> 0 | AM51: =+AM50-AL50 -> 0 | AN51: =+AN50-AK50 -> 0 | AO51: =+AO50-AN50 -> 0 | AP51: =+AP50-AO50 -> 0 | AQ51: =+AQ50-AN50 -> 0
B52: Cash at bank and on hand from discontinued operations
B53: Chane in cash at bank and on hand from discontinued operations | D53: =+D52-C52 -> 0 | E53: =+E52-D52 -> 0 | F53: =+F52-E52 -> 0 | G53: =+G52-F52 -> 0 | H53: =+H52-G52 -> 0 | I53: =+I52-H52 -> 0 | J53: =+J52-I52 -> 0 | K53: =+K52-J52 -> 0 | ... X53: =+X52-W52 -> 0 | Y53: =+Y52-V52 -> 0 | Z53: =+Z52-Y52 -> 0 | AA53: =+AA52-Z52 -> 0 | AB53: =+AB52-Y52 -> 0 | AC53: =+AC52-AB52 -> 0 | AD53: =+AD52-AC52 -> 0 | AE53: =+AE52-AB52 -> 0 | AF53: =+AF52-AE52 -> 0 | AG53: =+AG52-AF52 -> 0 | AH53: =+AH52-AE52 -> 0 | AI53: =+AI52-AH52 -> 0 | AJ53: =+AJ52-AI52 -> 0 | AK53: =+AK52-AH52 -> 0 | AL53: =+AL52-AK52 -> 0 | AM53: =+AM52-AL52 -> 0 | AN53: =+AN52-AK52 -> 0 | AO53: =+AO52-AN52 -> 0 | AP53: =+AP52-AO52 -> 0 | AQ53: =+AQ52-AN52 -> 0
B54: check | C54: =BS!C2 -> 0 | D54: =BS!D2 -> 0 | E54: =BS!E2 -> 0 | F54: =BS!F2 -> 0 | G54: =BS!G2 -> 0 | H54: =BS!H2 -> 0 | I54: =BS!I2 -> 0 | J54: =BS!J2 -> 0 | ... AQ54: =BS!AQ2 -> 0
A55: ACQ_DIV | B55: Acquisitions / Divestments | C55: =C28 -> -0.006 | D55: =D28 -> 0 | E55: =E28 -> -22.11 | F55: =F28 -> 0 | G55: =G28 -> -19.231 | H55: =H28 -> -8.185 | I55: =I28 -> 0 | J55: =J28 -> 0 | ... AQ55: =AQ28 -> 0
A56: CHG_DEBT | B56: Change in net debt / other | C56: =C35 -> -4.09 | D56: =D35 -> 5.721 | E56: =E35 -> 33.647 | F56: =F35 -> 22.907 | G56: =G35 -> 15.793 | H56: =H35 -> 5.841 | I56: =I35 -> -35.278 | J56: =J35 -> -20 | ... AQ56: =AQ35 -> 0
B58: ModelWare Free Cash Flow Calculation
B60: ModelWare PTOP | C60: ='P&L'!C139 -> 16.781 | D60: ='P&L'!F139 -> 22.732 | E60: ='P&L'!I139 -> 37.032 | F60: ='P&L'!L139 -> 44.561 | G60: ='P&L'!O139 -> 65.534 | H60: ='P&L'!R139 -> 102.299 | I60: ='P&L'!U139 -> 141.966 | J60: ='P&L'!X139 -> 175.11 | K60: ='P&L'!AA139 -> 196.013 | L60: ='P&L'!AD139 -> 161.459 | M60: ='P&L'!AG139 -> 177.753 | N60: ='P&L'!AJ139 -> 191.12 | O60: ='P&L'!AM139 -> 200.907 | P60: ='P&L'!AP139 -> 221.175 | Q60: ='P&L'!AS139 -> 306.4 | R60: ='P&L'!AV139 -> 350.6 | S60: ='P&L'!AY139 -> 372.9 | T60: ='P&L'!BB139 -> 502.9 | U60: ='P&L'!BE139 -> 743.1 | V60: ='P&L'!BH139 -> 794.6 | W60: ='P&L'!BI139 -> 479.2 | Y60: ='P&L'!BK139 -> 769 | Z60: ='P&L'!BL139 -> 386.7 | AB60: ='P&L'!BN139 -> 647.2
B62: add Depreciation | C62: =C16 -> 1.319 | D62: =D16 -> 3.168 | E62: =E16 -> 5.268 | F62: =F16 -> 7.439 | G62: =G16 -> 10.854 | H62: =H16 -> 14.691 | I62: =I16 -> 18.749 | J62: =J16 -> 23.277 | ... W62: =W16 -> 113.4 | Y62: =Y16 -> 224.2 | Z62: =Z16 -> 118.5 | AB62: =AB16 -> 237.1
B63: less Capital Expenditures | C63: =C26 -> -6.253 | D63: =D26 -> -10.282 | E63: =E26 -> -15.812 | F63: =F26 -> -29.046 | G63: =G26 -> -34.406 | H63: =H26 -> -51.573 | I63: =I26 -> -44.444 | J63: =J26 -> -54.46 | ... W63: =W26 -> -34.1 | Y63: =Y26 -> -72 | Z63: =Z26 -> -36.7 | AB63: =AB26 -> -74.5
B64: Change in Working Capital | C64: =C20 -> 0 | D64: =D20 -> -4.702 | E64: =E20 -> -29.269 | F64: =F20 -> -22.831 | G64: =G20 -> -4.322 | H64: =H20 -> -47.791 | I64: =I20 -> 7.932 | J64: =J20 -> 2.09 | ... W64: =W20 -> 209 | Y64: =Y20 -> 19.4 | Z64: =Z20 -> 189.5 | AB64: =AB20 -> 19
B65: Movement in Provisions & Reserves
A66: NET_INT | B66: Less Debt Service | C66: =VLOOKUP($A$66,'P&L'!1:1048576,MATCH(C4,'P&L'!4:4,FALSE),FALSE) -> -4.107 | D66: =VLOOKUP($A$66,'P&L'!1:1048576,MATCH(D4,'P&L'!4:4,FALSE),FALSE) -> -2.702 | E66: =VLOOKUP($A$66,'P&L'!1:1048576,MATCH(E4,'P&L'!4:4,FALSE),FALSE) -> -5.145 | F66: =VLOOKUP($A$66,'P&L'!1:1048576,MATCH(F4,'P&L'!4:4,FALSE),FALSE) -> -5.738 | G66: =VLOOKUP($A$66,'P&L'!1:1048576,MATCH(G4,'P&L'!4:4,FALSE),FALSE) -> -6.155 | H66: =VLOOKUP($A$66,'P&L'!1:1048576,MATCH(H4,'P&L'!4:4,FALSE),FALSE) -> -8.289 | I66: =VLOOKUP($A$66,'P&L'!1:1048576,MATCH(I4,'P&L'!4:4,FALSE),FALSE) -> -6.474 | J66: =VLOOKUP($A$66,'P&L'!1:1048576,MATCH(J4,'P&L'!4:4,FALSE),FALSE) -> -5.509 | ... W66: =VLOOKUP($A$66,'P&L'!1:1048576,MATCH(W4,'P&L'!4:4,FALSE),FALSE) -> -9 | Y66: =VLOOKUP($A$66,'P&L'!1:1048576,MATCH(Y4,'P&L'!4:4,FALSE),FALSE) -> -21.9 | Z66: =VLOOKUP($A$66,'P&L'!1:1048576,MATCH(Z4,'P&L'!4:4,FALSE),FALSE) -> -9.4 | AB66: =VLOOKUP($A$66,'P&L'!1:1048576,MATCH(AB4,'P&L'!4:4,FALSE),FALSE) -> -19.8
A67: TAX | B67: Less Tax Paid | C67: =VLOOKUP($A$67,'P&L'!1:1048576,MATCH(C4,'P&L'!4:4,FALSE),FALSE) -> -3.716 | D67: =VLOOKUP($A$67,'P&L'!1:1048576,MATCH(D4,'P&L'!4:4,FALSE),FALSE) -> -5.899 | E67: =VLOOKUP($A$67,'P&L'!1:1048576,MATCH(E4,'P&L'!4:4,FALSE),FALSE) -> -9.442 | F67: =VLOOKUP($A$67,'P&L'!1:1048576,MATCH(F4,'P&L'!4:4,FALSE),FALSE) -> -11.954 | G67: =VLOOKUP($A$67,'P&L'!1:1048576,MATCH(G4,'P&L'!4:4,FALSE),FALSE) -> -18.003 | H67: =VLOOKUP($A$67,'P&L'!1:1048576,MATCH(H4,'P&L'!4:4,FALSE),FALSE) -> -28.875 | I67: =VLOOKUP($A$67,'P&L'!1:1048576,MATCH(I4,'P&L'!4:4,FALSE),FALSE) -> -41.055 | J67: =VLOOKUP($A$67,'P&L'!1:1048576,MATCH(J4,'P&L'!4:4,FALSE),FALSE) -> -50.949 | ... W67: =VLOOKUP($A$67,'P&L'!1:1048576,MATCH(W4,'P&L'!4:4,FALSE),FALSE) -> -140.3 | Y67: =VLOOKUP($A$67,'P&L'!1:1048576,MATCH(Y4,'P&L'!4:4,FALSE),FALSE) -> -222.5 | Z67: =VLOOKUP($A$67,'P&L'!1:1048576,MATCH(Z4,'P&L'!4:4,FALSE),FALSE) -> -113 | AB67: =VLOOKUP($A$67,'P&L'!1:1048576,MATCH(AB4,'P&L'!4:4,FALSE),FALSE) -> -188.6
B68: Other | C68: =+C21 -> 8.946 | D68: =+D21 -> -0.862 | E68: =+E21 -> -7.566 | F68: =+F21 -> -2.266 | G68: =+G21 -> 8.664 | H68: =+H21 -> 1.105 | I68: =+I21 -> 16.423 | J68: =+J21 -> 1.127 | ... N68: =+N21 -> -8.331
B69: ModelWare Free Cash Flow | C69: =SUM(C60:C68) -> 12.97 | D69: =SUM(D60:D68) -> 1.453 | E69: =SUM(E60:E68) -> -24.934 | F69: =SUM(F60:F68) -> -19.835 | G69: =SUM(G60:G68) -> 22.166 | H69: =SUM(H60:H68) -> -18.433 | I69: =SUM(I60:I68) -> 93.097 | J69: =SUM(J60:J68) -> 90.686 | ... W69: =SUM(W60:W68) -> 618.2 | Y69: =SUM(Y60:Y68) -> 696.2 | Z69: =SUM(Z60:Z68) -> 535.6 | AB69: =SUM(AB60:AB68) -> 620.4
B70: Growth | D70: =D69/C69-1 -> -0.88797224 | E70: =E69/D69-1 -> -18.160358 | F70: =F69/E69-1 -> -0.20449988 | G70: =G69/F69-1 -> -2.1175195 | H70: =H69/G69-1 -> -1.8315889 | I70: =I69/H69-1 -> -6.0505615 | J70: =J69/I69-1 -> -0.02589772 | K70: =K69/J69-1 -> 0.014643936 | ... W70: =W69/V69-1 -> 0.15919745 | Z70: =Z69/Y69-1 -> -0.23068084
B72: =B38 -> Dividends paid | C72: =C38 -> 0 | D72: =D38 -> -13.688 | E72: =E38 -> -7.393 | F72: =F38 -> -7.428 | G72: =G38 -> -9.386 | H72: =H38 -> -16.913 | I72: =I38 -> -33.217 | ... W72: =W38 -> -167.3 | Y72: =Y38 -> -382.7 | Z72: =Z38 -> -125.7 | AB72: =AB38 -> -298.5
B73: FCF post dividends | C73: =C69+C72 -> 12.97 | D73: =D69+D72 -> -12.235 | E73: =E69+E72 -> -32.327 | F73: =F69+F72 -> -27.263 | G73: =G69+G72 -> 12.78 | H73: =H69+H72 -> -35.346 | I73: =I69+I72 -> 59.88 | J73: =J69+J72 -> 23.603 | ... W73: =W69+W72 -> 450.9 | Y73: =Y69+Y72 -> 313.5 | Z73: =Z69+Z72 -> 409.9 | AB73: =AB69+AB72 -> 321.9
B75: Diluted shares outstanding | C75: ='P&L'!C103 -> 83.185 | D75: ='P&L'!F103 -> 86.375 | E75: ='P&L'!I103 -> 104.229 | F75: ='P&L'!L103 -> 105.253 | G75: ='P&L'!O103 -> 106.054 | H75: ='P&L'!R103 -> 107.255 | I75: ='P&L'!U103 -> 107.769 | J75: ='P&L'!X103 -> 109.433 | K75: ='P&L'!AA103 -> 108.496 | L75: ='P&L'!AD103 -> 98.842 | M75: ='P&L'!AG103 -> 99.453 | N75: ='P&L'!AJ103 -> 101.161 | O75: ='P&L'!AM103 -> 100.037 | P75: ='P&L'!AP103 -> 100.037 | Q75: ='P&L'!AS103 -> 112.7 | R75: ='P&L'!AV103 -> 115.9 | S75: ='P&L'!AY103 -> 116.1 | T75: ='P&L'!BB103 -> 116 | U75: ='P&L'!BE103 -> 115.6 | V75: ='P&L'!BH103 -> 114.2 | W75: ='P&L'!BI103 -> 109.7 | Y75: ='P&L'!BK103 -> 109.8 | Z75: ='P&L'!BL103 -> 109.8 | AB75: ='P&L'!BN103 -> 109.5
B77: ModelWare Free Cash Flow per share | C77: =C69/C75*100 -> 15.591753 | D77: =D69/D75*100 -> 1.6821997 | E77: =E69/E75*100 -> -23.922325 | F77: =F69/F75*100 -> -18.845069 | G77: =G69/G75*100 -> 20.900673 | H77: =H69/H75*100 -> -17.186145 | I77: =I69/I75*100 -> 86.385695 | J77: =J69/J75*100 -> 82.86897 | ... W77: =W69/W75*100 -> 563.53692 | Y77: =Y69/Y75*100 -> 634.06193 | Z77: =Z69/Z75*100 -> 487.79599 | AB77: =AB69/AB75*100 -> 566.57534
B78: Growth | D78: =D77/C77-1 -> -0.89210965 | E78: =E77/D77-1 -> -15.220859 | F78: =F77/E77-1 -> -0.21223925 | G78: =G77/F77-1 -> -2.1090792 | H78: =H77/G77-1 -> -1.8222771 | I78: =I77/H77-1 -> -6.026473 | J78: =J77/I77-1 -> -0.040709579 | K78: =K77/J77-1 -> 0.023406668 | ... W78: =W77/V77-1 -> 0.20674885 | Z78: =Z77/Y77-1 -> -0.23068084
C82: =C4 -> FY03 | D82: =D4 -> FY04 | E82: =E4 -> FY05 | F82: =F4 -> FY06 | G82: =G4 -> FY07 | H82: =H4 -> FY08 | I82: =I4 -> FY09 | J82: =J4 -> FY10 | ... N82: =N4 -> FY14
B83: EBITDA | C83: 619.7 | D83: 683.2 | E83: 752.5 | F83: 781.1 | G83: 834 | H83: 866.9 | I83: 964.8 | J83: 1036.5 | K83: 1074.1 | L83: 1128.9
B84: Operating cash flow to EBITDA | C84: =C22/C83 -> 0.038157173 | D84: =D22/D83 -> 0.021652518 | E84: =E22/E83 -> -0.0045408638 | F84: =F22/F83 -> 0.01999872 | G84: =G22/G83 -> 0.076773381 | H84: =H22/H83 -> 0.04895259 | I84: =I22/I83 -> 0.15088827 | J84: =J22/J83 -> 0.14674674 | ... L84: =L22/L83 -> 0.19045708
W91: 1H23 | X91: 2H23 | Y91: FY23 | Z91: 1H24 | AA91: 2H24 | AB91: FY24 | AC91: 1H25 | AF91: 1H26

Sheet BS
B2: JBH Balance Sheet | C2: =C48 -> 0 | D2: =D48 -> 0 | E2: =E48 -> 0 | F2: =F48 -> 0 | G2: =G48 -> 0 | H2: =H48 -> 0 | I2: =I48 -> 0 | J2: =J48 -> 0 | ... AQ2: =AQ48 -> 0
B4: (A$mn, Year ending June) | C4: FY03 | D4: FY04 | E4: FY05 | F4: FY06 | G4: FY07 | H4: FY08 | I4: FY09 | J4: FY10 | K4: FY11 | L4: FY12 | M4: FY13 | N4: FY14 | O4: FY15 | P4: FY16 | Q4: FY17 | R4: FY18 | S4: FY19 | T4: FY20 | U4: FY21 | V4: FY22 | W4: 1H23 | X4: 2H23 | Y4: FY23 | Z4: 1H24 | AA4: 2H24 | AB4: FY24 | AC4: 1H25 | AD4: 2H25 | AE4: FY25 | AF4: 1H26e | AG4: 2H26e | AH4: ='P&L'!BT4 -> FY26E | AI4: 1H27e | AJ4: 2H27e | AK4: ='P&L'!BW4 -> FY27E | AL4: 1H28e | AM4: 2H28e | AN4: ='P&L'!BZ4 -> FY28E | AO4: 1H29e | AP4: 2H29e | AQ4: ='P&L'!CC4 -> FY29E
B6: Cash & Equivalents | C6: 12.99 | D6: 16.432 | E6: 1.631 | F6: 4.493 | G6: 23.707 | H6: 0 | I6: 35.79 | J6: 51.735 | K6: 27.246 | L6: 39.71 | M6: 67.368 | N6: 43.445 | O6: 49.131 | P6: 51.884 | Q6: 72.8 | R6: 72 | S6: 119.2 | T6: 251.5 | U6: 263.2 | V6: 125.6 | W6: =CFS!W47 -> 391.184 | X6: =+Y6 -> 177.3 | Y6: 177.3 | Z6: =CFS!Z47 -> 487.984 | AA6: =+AB6 -> 317.7 | AB6: 317.7 | AC6: =CFS!AC47 -> 556.384 | AD6: =+AE6 -> 284.084 | AE6: =CFS!AE47 -> 284.084 | AF6: =CFS!AF47 -> 489.484 | AG6: =CFS!AG47 -> 278.73729 | AH6: =CFS!AH47 -> 278.73729 | AI6: =CFS!AI47 -> 326.68173 | AJ6: =CFS!AJ47 -> 336.69984 | AK6: =CFS!AK47 -> 336.69984 | AL6: =CFS!AL47 -> 392.7342 | ... AQ6: =CFS!AQ47 -> 468.35923
B7: Receivables | C7: =C55 -> 7.699 | D7: =D55 -> 13.17 | E7: =E55 -> 19.852 | F7: =F55 -> 28.282 | G7: =G55 -> 45.177 | H7: =H55 -> 52.996 | I7: =I55 -> 60.269 | J7: =J55 -> 63.499 | ... AQ7: =AQ55 -> 227.10168
B8: Inventories | C8: =C62 -> 49.074 | D8: =D62 -> 70.349 | E8: =E62 -> 102.157 | F8: =F62 -> 161.137 | G8: =G62 -> 211.189 | H8: =H62 -> 271.878 | I8: =I62 -> 324.519 | J8: =J62 -> 334.754 | ... AQ8: =AQ62 -> 1520.9071
B9: Other Current assets | C9: 0.681 | D9: 1.127 | E9: 2.648 | F9: 2.845 | G9: 3.549 | H9: 5.328 | I9: 5.661 | J9: 4.52 | K9: 8.634 | L9: 7.682 | M9: 6.038 | N9: 5.332 | O9: 7.416 | P9: 6.124 | Q9: 41.4 | R9: 42.7 | S9: 34.6 | T9: 34.7 | U9: 35.7 | V9: 31.2 | W9: 37.2 | X9: =Y9 -> 34.6 | Y9: 34.6 | Z9: 43.9 | AA9: =AB9 -> 39.9 | AB9: 39.9 | AC9: 50.9 | AD9: =AE9 -> 46.5 | AE9: 46.5 | AF9: 59.2 | AG9: =AF9 -> 59.2 | AH9: =AG9 -> 59.2 | AI9: =AH9 -> 59.2 | AJ9: =AI9 -> 59.2 | AK9: =AJ9 -> 59.2 | AL9: =AK9 -> 59.2 | AM9: =AL9 -> 59.2 | AN9: =AM9 -> 59.2 | ... AQ9: =AP9 -> 59.2
A10: CA | B10: Total Current Assets | C10: =SUM(C6:C9) -> 70.444 | D10: =SUM(D6:D9) -> 101.078 | E10: =SUM(E6:E9) -> 126.288 | F10: =SUM(F6:F9) -> 196.757 | G10: =SUM(G6:G9) -> 283.622 | H10: =SUM(H6:H9) -> 330.202 | I10: =SUM(I6:I9) -> 426.239 | J10: =SUM(J6:J9) -> 454.508 | ... AQ10: =SUM(AQ6:AQ9) -> 2275.568
B12: Other Financial Assets | C12: =0.006+0.781 -> 0.787 | D12: =0.006+0.247 -> 0.253 | E12: =0.006+0.568+0.205 -> 0.779 | F12: =0.689+0.674 -> 1.363 | G12: =0.689+0.847 -> 1.536 | H12: 0.609 | I12: 0.003 | J12: 0.003 | K12: 0.003 | L12: 0.003 | M12: 0.003 | N12: 0.003 | O12: 0.003 | P12: 0 | Q12: 46.8 | R12: 45.9 | S12: 40.8 | T12: 38.4 | U12: 39 | V12: 44.1 | W12: 48.6 | X12: =Y12 -> 50.2 | Y12: 50.2 | Z12: 52.3 | AA12: =AB12 -> 53.5 | AB12: 53.5 | AC12: 55.7 | AD12: =AE12 -> 57.2 | AE12: 57.2 | AF12: 58.9 | AG12: =AF12 -> 58.9 | AH12: =AG12 -> 58.9 | AI12: =AH12 -> 58.9 | AJ12: =AI12 -> 58.9 | AK12: =AJ12 -> 58.9 | AL12: =AK12 -> 58.9 | AM12: =AL12 -> 58.9 | AN12: =AM12 -> 58.9 | ... AQ12: =AP12 -> 58.9
A13: PPE | B13: Property, Plant & Equipment | C13: 14.88 | D13: 21.94 | E13: 35.908 | F13: 57.206 | G13: 80.144 | H13: 112.923 | I13: 136.063 | J13: 163.982 | K13: 169.59 | L13: 182.048 | M13: 181.098 | N13: 181.564 | O13: 176.208 | P13: 183.57 | Q13: 208.2 | R13: 198 | S13: 191.5 | T13: 172.3 | U13: 169 | V13: 169 | W13: 173.7 | X13: =X132 -> 182.8 | Y13: 182.8 | Z13: 190.3 | AA13: =AA132 -> 196.9 | AB13: 196.9 | AC13: 214 | AD13: =AD132 -> 224.8 | AE13: 224.8 | AF13: 237.4 | AG13: =AG132 -> 240.54309 | AH13: =AH132 -> 240.54309 | AI13: =AI132 -> 250.14247 | AJ13: =AJ132 -> 261.33423 | AK13: =AK132 -> 261.33423 | AL13: =AL132 -> 271.23964 | AM13: =AM132 -> 279.29574 | AN13: =AN132 -> 279.29574 | ... AQ13: =AQ132 -> 294.4297
A14: INTANG | B14: Intangibles | C14: 43.094 | D14: =46.518 -> 46.518 | E14: =20.015+46.636 -> 66.651 | F14: =20.015+46.636 -> 66.651 | G14: =46.636+34.017 -> 80.653 | H14: =46.636+34.538 -> 81.174 | I14: 81.352 | J14: 83.861 | K14: 78.672 | L14: 78.842 | M14: 83.712 | N14: 85.218 | O14: 84.541 | P14: 85.59 | Q14: 1026.6 | R14: 1037.3 | S14: 1037.3 | T14: 1031.4 | U14: 1031.4 | V14: 1031.4 | W14: 1031.4 | X14: =X147 -> 1031.4 | Y14: 1031.4 | Z14: 1031.4 | AA14: =AA147 -> 1031.4 | AB14: 1031.4 | AC14: 1080.1 | AD14: =AD147 -> 1080.7 | AE14: 1080.7 | AF14: 1080.7 | AG14: =AG147 -> 1080.7 | AH14: =AH147 -> 1080.7 | AI14: =AI147 -> 1080.7 | AJ14: =AJ147 -> 1080.7 | AK14: =AK147 -> 1080.7 | AL14: =AL147 -> 1080.7 | AM14: =AM147 -> 1080.7 | AN14: =AN147 -> 1080.7 | ... AQ14: =AQ147 -> 1080.7
B15: Deferred tax Assets | C15: 1.727 | D15: 0.414 | E15: 1.984 | F15: 4.867 | G15: 7.446 | H15: 10.927 | I15: 17.994 | J15: 11.968 | K15: 17.802 | L15: 16.196 | M15: 14.839 | N15: 14.909 | O15: 17.363 | P15: 20.703 | Q15: 0 | R15: =Q15 -> 0 | S15: 2.7 | T15: 22.2 | U15: 30.3 | V15: 30.6 | W15: 41.9 | X15: =Y15 -> 41.1 | Y15: 41.1 | Z15: 46.7 | AA15: =AB15 -> 50.2 | AB15: 50.2 | AC15: 63.2 | AD15: =AE15 -> 65.7 | AE15: 65.7 | AF15: 69.8 | AG15: =AF15 -> 69.8 | AH15: =AG15 -> 69.8 | AI15: =AH15 -> 69.8 | AJ15: =AI15 -> 69.8 | AK15: =AJ15 -> 69.8 | AL15: =AK15 -> 69.8 | AM15: =AL15 -> 69.8 | AN15: =AM15 -> 69.8 | ... AQ15: =AP15 -> 69.8
B16: Right of use asset | T16: 642.2 | U16: 536.3 | V16: 461.6 | W16: 488.9 | X16: =+Y16 -> 530.1 | Y16: 530.1 | Z16: 548.6 | AA16: =+AB16 -> 568.3 | AB16: 568.3 | AC16: 619.8 | AD16: =+AE16 -> 638.7 | AE16: 638.7 | AF16: 656.2 | AG16: =AF16-CFS!AG39-AG168 -> 661.876 | AH16: =AG16 -> 661.876 | AI16: =AH16-CFS!AI39-AI168 -> 668.89164 | AJ16: =AI16-CFS!AJ39-AJ168 -> 675.90728 | AK16: =AJ16 -> 675.90728 | AL16: =AK16-CFS!AL39-AL168 -> 686.09289 | AM16: =AL16-CFS!AM39-AM168 -> 696.2785 | AN16: =AM16 -> 696.2785 | AO16: =AN16-CFS!AO39-AO168 -> 709.72918 | AP16: =AO16-CFS!AP39-AP168 -> 723.17985 | AQ16: =AP16 -> 723.17985
B17: Total Non-Current Assets | C17: =SUM(C12:C15) -> 60.488 | D17: =SUM(D12:D15) -> 69.125 | E17: =SUM(E12:E15) -> 105.322 | F17: =SUM(F12:F15) -> 130.087 | G17: =SUM(G12:G15) -> 169.779 | H17: =SUM(H12:H15) -> 205.633 | I17: =SUM(I12:I15) -> 235.412 | J17: =SUM(J12:J15) -> 259.814 | ... S17: =SUM(S12:S15) -> 1272.3 | T17: =SUM(T12:T16) -> 1906.5 | U17: =SUM(U12:U16) -> 1806 | V17: =SUM(V12:V16) -> 1736.7 | W17: =SUM(W12:W16) -> 1784.5 | X17: =SUM(X12:X16) -> 1835.6 | Y17: =SUM(Y12:Y16) -> 1835.6 | Z17: =SUM(Z12:Z16) -> 1869.3 | AA17: =SUM(AA12:AA16) -> 1900.3 | ... AQ17: =SUM(AQ12:AQ16) -> 2227.0096
A19: TA | B19: Total assets | C19: =C10+C17 -> 130.932 | D19: =D10+D17 -> 170.203 | E19: =E10+E17 -> 231.61 | F19: =F10+F17 -> 326.844 | G19: =G10+G17 -> 453.401 | H19: =H10+H17 -> 535.835 | I19: =I10+I17 -> 661.651 | J19: =J10+J17 -> 714.322 | ... AQ19: =AQ10+AQ17 -> 4502.5776
B21: Payables | C21: =C69 -> 46.918 | D21: =D69 -> 68.962 | E21: =E69 -> 78.183 | F21: =F69 -> 122.762 | G21: =G69 -> 185.387 | H21: =H69 -> 206.104 | I21: =I69 -> 273.95 | J21: =J69 -> 289.505 | ... AQ21: =AQ69 -> 1030.2919
B22: Borrowings | C22: =C82 -> 3.289 | D22: =D82 -> 4.364 | E22: =E82 -> 6.345 | F22: =F82 -> 0.519 | G22: =G82 -> 0.702 | H22: =H82 -> 1.502 | I22: =I82 -> 0 | J22: =J82 -> 35 | ... Z22: =Z82 -> 0 | AA22: =AB22 -> 15 | AB22: =AB82 -> 15 | AC22: =AC82 -> 0.3 | AD22: =AE22 -> 0 | AE22: =AE82 -> 0 | AF22: =AF82 -> 0 | AG22: =AG82 -> 0 | AH22: =AH82 -> 0 | AI22: =AI82 -> 0 | AJ22: =AJ82 -> 0 | AK22: =AK82 -> 0 | AL22: =AL82 -> 0 | ... AQ22: =AQ82 -> 0
B23: Current Tax Liabilities | C23: 2.081 | D23: 2.448 | E23: 2.284 | F23: 4.453 | G23: 7.576 | H23: 12.173 | I23: 18.204 | J23: 10.011 | K23: 12.064 | L23: 4.374 | M23: 14.932 | N23: 8.184 | O23: 9.474 | P23: 10.92 | Q23: 11.8 | R23: 9.6 | S23: 5.1 | T23: 32.3 | U23: 92.2 | V23: 54.8 | W23: 41.9 | X23: =Y23 -> 4.3 | Y23: 4.3 | Z23: 33.5 | AA23: =AB23 -> 23.9 | AB23: 23.9 | AC23: 38.9 | AD23: =AE23 -> 15.4 | AE23: 15.4 | AF23: 34.3 | AG23: =AF23 -> 34.3 | AH23: =AG23 -> 34.3 | AI23: =AH23 -> 34.3 | AJ23: =AI23 -> 34.3 | AK23: =AJ23 -> 34.3 | AL23: =AK23 -> 34.3 | AM23: =AL23 -> 34.3 | AN23: =AM23 -> 34.3 | ... AQ23: =AP23 -> 34.3
B24: Other | C24: 0 | D24: 0 | E24: 0.843 | F24: 1.102 | G24: 1.244 | H24: 1.185 | I24: =1.554+1.781 -> 3.335 | J24: =0.684+1.964 -> 2.648 | K24: =0.645+2.311 -> 2.956 | L24: =1.303+2.328 -> 3.631 | M24: =0.956+3.08 -> 4.036 | N24: =4.111+0.079 -> 4.19 | O24: =4.566+0.107 -> 4.673 | P24: 4.953 | Q24: =9+141.8 -> 150.8 | R24: =150.5+8.3 -> 158.8 | S24: =165.8+8 -> 173.8 | T24: 196.6 | U24: 212.9 | V24: 253.5 | W24: 256.4 | X24: =Y24 -> 231 | Y24: 231 | Z24: 263.5 | AA24: =AB24 -> 248.1 | AB24: 248.1 | AC24: =328.2 -> 328.2 | AD24: =AE24 -> 311.5 | AE24: 311.5 | AF24: 327.2 | AG24: =AF24 -> 327.2 | AH24: =AG24 -> 327.2 | AI24: =AH24 -> 327.2 | AJ24: =AI24 -> 327.2 | AK24: =AJ24 -> 327.2 | AL24: =AK24 -> 327.2 | AM24: =AL24 -> 327.2 | AN24: =AM24 -> 327.2 | ... AQ24: =AP24 -> 327.2
B25: Provisions | C25: 3.538 | D25: 5.17 | E25: 7.128 | F25: 9.508 | G25: 14.49 | H25: 18.453 | I25: 28.235 | J25: =25.975 -> 25.975 | K25: 29.316 | L25: 30.673 | M25: 36.391 | N25: 36.84 | O25: 40.585 | P25: 46.032 | Q25: 75.4 | R25: 83.5 | S25: 93.9 | T25: 98.9 | U25: 105.5 | V25: 109.4 | W25: =109.7-0.016 -> 109.684 | X25: =Y25 -> 115 | Y25: 115 | Z25: 114.7 | AA25: =AB25 -> 120.4 | AB25: 120.4 | AC25: 128.1 | AD25: =AE25 -> 137 | AE25: 137 | AF25: 139 | AG25: =AF25 -> 139 | AH25: =AG25 -> 139 | AI25: =AH25 -> 139 | AJ25: =AI25 -> 139 | AK25: =AJ25 -> 139 | AL25: =AK25 -> 139 | AM25: =AL25 -> 139 | AN25: =AM25 -> 139 | ... AQ25: =AP25 -> 139
B26: Lease laibilities | T26: 164 | U26: 167.3 | V26: 167 | W26: 167.6 | X26: =Y26 -> 174.1 | Y26: 174.1 | Z26: 182.5 | AA26: =AB26 -> 182.6 | AB26: 182.6 | AC26: 195.3 | AD26: =AE26 -> 201.2 | AE26: 201.2 | AF26: 206.6 | AG26: =AF26 -> 206.6 | AH26: =AG26 -> 206.6 | AI26: =AH26 -> 206.6 | AJ26: =AI26 -> 206.6 | AK26: =AJ26 -> 206.6 | AL26: =AK26 -> 206.6 | AM26: =AL26 -> 206.6 | AN26: =AM26 -> 206.6 | ... AQ26: =AP26 -> 206.6
A27: CL | B27: Total Current Liabilities | C27: =SUM(C21:C25) -> 55.826 | D27: =SUM(D21:D25) -> 80.944 | E27: =SUM(E21:E25) -> 94.783 | F27: =SUM(F21:F25) -> 138.344 | G27: =SUM(G21:G25) -> 209.399 | H27: =SUM(H21:H25) -> 239.417 | I27: =SUM(I21:I25) -> 323.724 | J27: =SUM(J21:J25) -> 363.139 | ... S27: =SUM(S21:S25) -> 945.5 | T27: =SUM(T21:T26) -> 1345.9 | U27: =SUM(U21:U26) -> 1355.3 | V27: =SUM(V21:V26) -> 1306.3 | W27: =SUM(W21:W26) -> 1623.984 | X27: =SUM(X21:X26) -> 1184.9 | Y27: =SUM(Y21:Y26) -> 1184.9 | Z27: =SUM(Z21:Z26) -> 1598.8 | AA27: =SUM(AA21:AA26) -> 1310.8 | ... AQ27: =SUM(AQ21:AQ26) -> 1737.3919
B29: Borrowings (LT) | C29: =C87 -> 34.589 | D29: =D87 -> 39.235 | E29: =E87 -> 71.291 | F29: =F87 -> 100.042 | G29: =G87 -> 117.732 | H29: =H87 -> 123.015 | I29: =I87 -> 89.358 | J29: =J87 -> 34.624 | ... AQ29: =AQ87 -> 0
B30: Other financial liabilities | C30: 1.387 | D30: 0.323 | E30: 0 | F30: 0 | G30: 0 | H30: 0 | I30: 0.588 | J30: 0.079 | K30: 0.292 | L30: 0.803 | M30: 0 | N30: 0.025 | O30: 0 | P30: 0 | R30: =Q30 -> 0 | S30: =R30 -> 0 | T30: =S30 -> 0 | U30: 0 | V30: 0 | W30: 0 | X30: =Y30 -> 0 | Y30: 0 | Z30: 0 | AA30: =AB30 -> 0 | AB30: 0 | AC30: 0 | AD30: =AE30 -> 17.9 | AE30: 17.9 | AF30: 18.4 | AG30: =AH30 -> 17.9 | AH30: =AE30 -> 17.9 | AI30: =AH30 -> 17.9 | AJ30: =AK30 -> 17.9 | AK30: =AH30 -> 17.9 | AL30: =AK30 -> 17.9 | AM30: =AN30 -> 17.9 | AN30: =AK30 -> 17.9 | AO30: =AN30 -> 17.9 | AP30: =AQ30 -> 17.9 | AQ30: =AN30 -> 17.9
B31: Provisions (LT) | C31: 0.668 | D31: 0.825 | E31: 0.734 | F31: 0.771 | G31: 0.682 | H31: 0.712 | I31: 3.829 | J31: 4.421 | K31: 14.466 | L31: 13.792 | M31: 9.416 | N31: 8.699 | O31: 6.073 | P31: 6.381 | Q31: 11.8 | R31: 12.5 | S31: 15.2 | T31: 41.5 | U31: 42.6 | V31: 42.7 | W31: 42.1 | X31: =Y31 -> 42.5 | Y31: 42.5 | Z31: 42.9 | AA31: =AB31 -> 41.9 | AB31: 41.9 | AC31: 44.9 | AD31: =AE31 -> 46.8 | AE31: 46.8 | AF31: 47.5 | AG31: =AF31 -> 47.5 | AH31: =AG31 -> 47.5 | AI31: =AH31 -> 47.5 | AJ31: =AI31 -> 47.5 | AK31: =AJ31 -> 47.5 | AL31: =AK31 -> 47.5 | AM31: =AL31 -> 47.5 | AN31: =AM31 -> 47.5 | ... AQ31: =AP31 -> 47.5
B32: Other | D32: 0 | E32: =2+0.564 -> 2.564 | F32: =3.37+0.66 -> 4.03 | G32: 6.786 | H32: 8.801 | I32: 14.9 | J32: 18.763 | K32: 21.548 | L32: =22.797 -> 22.797 | M32: 23.35 | N32: 24.638 | O32: 25.664 | P32: 24.729 | Q32: =34.6+99.6+8.2 -> 142.4 | R32: =35.6+5.7+103.7 -> 145 | S32: =90.1+33.2 -> 123.3 | T32: 81.6 | U32: 85 | V32: 94.7 | W32: 101.1 | X32: =Y32 -> 106.9 | Y32: 106.9 | Z32: 110.9 | AA32: =AB32 -> 115 | AB32: 115 | AC32: =130.6+17 -> 147.6 | AD32: =AE32 -> 132 | AE32: 132 | AF32: 128.9 | AG32: =AF32 -> 128.9 | AH32: =AG32 -> 128.9 | AI32: =AH32 -> 128.9 | AJ32: =AI32 -> 128.9 | AK32: =AJ32 -> 128.9 | AL32: =AK32 -> 128.9 | AM32: =AL32 -> 128.9 | AN32: =AM32 -> 128.9 | ... AQ32: =AP32 -> 128.9
B33: Lease laibilities | T33: 577.6 | U33: 464 | V33: 378 | W33: 397.9 | X33: =+Y33 -> 431.2 | Y33: 431.2 | Z33: 441.4 | AA33: =+AB33 -> 459.8 | AB33: 459.8 | AC33: 495.4 | AD33: =+AE33 -> 513.2 | AE33: 513.2 | AF33: 523.8 | AG33: =AF33 -> 523.8 | AH33: =AG33 -> 523.8 | AI33: =AH33 -> 523.8 | AJ33: =AI33 -> 523.8 | AK33: =AJ33 -> 523.8 | AL33: =AK33 -> 523.8 | AM33: =AL33 -> 523.8 | AN33: =AM33 -> 523.8 | ... AQ33: =AP33 -> 523.8
B34: Total Non-current Liabilities | C34: =SUM(C29:C32) -> 36.644 | D34: =SUM(D29:D32) -> 40.383 | E34: =SUM(E29:E32) -> 74.589 | F34: =SUM(F29:F32) -> 104.843 | G34: =SUM(G29:G32) -> 125.2 | H34: =SUM(H29:H32) -> 132.528 | I34: =SUM(I29:I32) -> 108.675 | J34: =SUM(J29:J32) -> 57.887 | ... S34: =SUM(S29:S32) -> 577.6 | T34: =SUM(T29:T33) -> 700.7 | U34: =SUM(U29:U33) -> 591.6 | V34: =SUM(V29:V33) -> 574.8 | W34: =SUM(W29:W33) -> 541.1 | X34: =SUM(X29:X33) -> 630.4 | Y34: =SUM(Y29:Y33) -> 630.4 | Z34: =SUM(Z29:Z33) -> 595.2 | AA34: =SUM(AA29:AA33) -> 616.7 | ... AQ34: =SUM(AQ29:AQ33) -> 718.1
A36: TL | B36: Total Liabilities | C36: =C27+C34 -> 92.47 | D36: =D27+D34 -> 121.327 | E36: =E27+E34 -> 169.372 | F36: =F27+F34 -> 243.187 | G36: =G27+G34 -> 334.599 | H36: =H27+H34 -> 371.945 | I36: =I27+I34 -> 432.399 | J36: =J27+J34 -> 421.026 | ... AQ36: =AQ27+AQ34 -> 2455.4919
A38: Net_assets | B38: Net Assets | C38: =C19-C36 -> 38.462 | D38: =D19-D36 -> 48.876 | E38: =E19-E36 -> 62.238 | F38: =F19-F36 -> 83.657 | G38: =G19-G36 -> 118.802 | H38: =H19-H36 -> 163.89 | I38: =I19-I36 -> 229.252 | J38: =J19-J36 -> 293.296 | ... AQ38: =AQ19-AQ36 -> 2047.0857
B40: Issued capital | C40: 21.9 | D40: 32.196 | E40: 32.428 | F40: 33.036 | G40: 35.883 | H40: 39.544 | I40: 44.783 | J40: 53.578 | K40: 58.206 | L40: 61.692 | M40: 62.774 | N40: 58.383 | O40: 56.521 | P40: 49.264 | Q40: 438.7 | R40: 441.7 | S40: 434.8 | T40: 403.2 | U40: 393 | V40: 346.8 | W40: 329.3 | X40: =W40+CFS!X34 -> 329.3 | Y40: 329.3 | Z40: 312.3 | AA40: =+AB40 -> 312.3 | AB40: 312.3 | AC40: 291.4 | AD40: =+AE40 -> 291.4 | AE40: 291.4 | AF40: 264.5 | AG40: =AF40+CFS!AG34 -> 264.5 | AH40: =AG40+CFS!AH34 -> 264.5 | AI40: =AH40+CFS!AI34 -> 264.5 | AJ40: =AI40+CFS!AJ34 -> 264.5 | AK40: =AJ40+CFS!AK34 -> 264.5 | AL40: =AK40+CFS!AL34 -> 264.5 | AM40: =AL40+CFS!AM34 -> 264.5 | AN40: =AM40+CFS!AN34 -> 264.5 | ... AQ40: =AP40+CFS!AQ34 -> 264.5
B41: Reserves | C41: 0 | D41: 0 | E41: 0.644 | F41: 2.036 | G41: 2.344 | H41: 1.291 | I41: 0.193 | J41: 3.873 | K41: 4.028 | L41: 5.12 | M41: 11.762 | N41: 16.265 | O41: 17.636 | P41: 27.14 | Q41: 33.2 | R41: 42.7 | S41: 53.7 | T41: 66.8 | U41: 83.8 | V41: 22.8 | W41: 17.3 | X41: =+Y41 -> 25.4 | Y41: 25.4 | Z41: 21.1 | AA41: =+AB41 -> 28.5 | AB41: 28.5 | AC41: 7.6 | AD41: =+AE41 -> 14.9 | AE41: 14.9 | AF41: =5.4-0.016 -> 5.384 | AG41: =AF41+0.484+0.016 -> 5.884 | AH41: =AG41 -> 5.884 | AI41: =AH41 -> 5.884 | AJ41: =AI41 -> 5.884 | AK41: =AJ41 -> 5.884 | AL41: =AK41 -> 5.884 | AM41: =AL41 -> 5.884 | AN41: =AM41 -> 5.884 | AO41: =AN41 -> 5.884 | ... AQ41: =AP41 -> 5.884
B42: Retained Earnings | C42: 16.562 | D42: 16.68 | E42: 25.494 | F42: 43.88 | G42: 74.883 | H42: 123.055 | I42: 184.276 | J42: 235.845 | K42: 90.079 | L42: 117.689 | M42: 168.809 | N42: 219.985 | O42: 269.322 | P42: 328.298 | Q42: 381.6 | R42: 463.2 | S42: 555.6 | T42: =T186 -> 635.7 | U42: 831.6 | V42: =V186 -> 910.7 | W42: 1086.9 | X42: =X186 -> 1064.9 | Y42: 1064.9 | Z42: =1215.8-0.016 -> 1215.784 | AA42: =+AB42 -> 1218.3 | AB42: 1218.3 | AC42: 1316.1 | AD42: =+AE42 -> 1310.3 | AE42: 1310.3 | AF42: 1408.2 | AG42: =AG186 -> 1381.5028 | AH42: =AH186 -> 1381.5028 | AI42: =AI186 -> 1534.2348 | AJ42: =AJ186 -> 1501.5196 | AK42: =AK186 -> 1501.5196 | AL42: =AL186 -> 1669.8507 | AM42: =AM186 -> 1631.4734 | AN42: =AN186 -> 1631.4734 | ... AQ42: =AQ186 -> 1769.1304
B43: Total Parent Entity Interest | C43: =SUM(C40:C42) -> 38.462 | D43: =SUM(D40:D42) -> 48.876 | E43: =SUM(E40:E42) -> 58.566 | F43: =SUM(F40:F42) -> 78.952 | G43: =SUM(G40:G42) -> 113.11 | H43: =SUM(H40:H42) -> 163.89 | I43: =SUM(I40:I42) -> 229.252 | J43: =SUM(J40:J42) -> 293.296 | ... AQ43: =SUM(AQ40:AQ42) -> 2039.5144
A45: NCI | B45: Non Controlling Interest | C45: 0 | D45: 0 | E45: 3.672 | F45: 4.705 | G45: 5.692 | H45: 0 | I45: 0 | J45: 0 | K45: 0 | L45: 0 | M45: 0.483 | N45: 0 | O45: 0 | P45: 0 | Q45: =-'P&L'!AS86+P45 -> 0 | R45: =-'P&L'!AV86+Q45 -> 0 | S45: =-'P&L'!AY86+R45 -> 0 | T45: =-'P&L'!BB86+S45 -> 0 | U45: =-'P&L'!BE86+T45 -> 0 | V45: =-'P&L'!BH86+U45 -> 0 | W45: =-'P&L'!BI86+V45 -> 0 | X45: =-'P&L'!BJ86+W45 -> 0 | Y45: =-'P&L'!BK86+X45 -> 0 | Z45: =-'P&L'!BL86+Y45 -> 0 | AA45: =-'P&L'!BM86+Z45 -> 0 | AB45: =-'P&L'!BN86+AA45 -> 0 | AC45: 5.3 | AD45: =+AE45 -> 5.2 | AE45: 5.2 | AF45: 5.3 | AG45: =-'P&L'!BS86+AF45 -> 5.7667909 | AH45: =-'P&L'!BT86+AE45 -> 5.7667909 | AI45: =-'P&L'!BU86+AH45 -> 6.0732159 | AJ45: =-'P&L'!BV86+AI45 -> 6.3505856 | AK45: =-'P&L'!BW86+AH45 -> 6.3505856 | AL45: =-'P&L'!BX86+AK45 -> 6.6662033 | AM45: =-'P&L'!BY86+AL45 -> 6.9518941 | AN45: =-'P&L'!BZ86+AK45 -> 6.9518941 | AO45: =-'P&L'!CA86+AN45 -> 7.2769803 | AP45: =-'P&L'!CB86+AO45 -> 7.5712418 | AQ45: =-'P&L'!CC86+AN45 -> 7.5712418
A47: TE | B47: Total Equity | C47: =C43+C45 -> 38.462 | D47: =D43+D45 -> 48.876 | E47: =E43+E45 -> 62.238 | F47: =F43+F45 -> 83.657 | G47: =G43+G45 -> 118.802 | H47: =H43+H45 -> 163.89 | I47: =I43+I45 -> 229.252 | J47: =J43+J45 -> 293.296 | ... AQ47: =AQ43+AQ45 -> 2047.0857
B48: check | C48: =C38-C47 -> 0 | D48: =D38-D47 -> 0 | E48: =E38-E47 -> 0 | F48: =F38-F47 -> 0 | G48: =G38-G47 -> 0 | H48: =H38-H47 -> 0 | I48: =I38-I47 -> 0 | J48: =J38-J47 -> 0 | ... AQ48: =AQ38-AQ47 -> 0
B50: ASSUMPTIONS & WORKINGS
B51: Working Capital | N51: =N55+N62-N69 -> 226.391 | O51: =O55+O62-O69 -> 234.747 | P51: =P55+P62-P69 -> 259.582 | Q51: =Q55+Q62-Q69 -> 408.7 | R51: =R55+R62-R69 -> 430.5 | S51: =S55+S62-S69 -> 468.4 | T51: =T55+T62-T69 -> 105.5 | U51: =U55+U62-U69 -> 373 | ... AQ51: =AQ55+AQ62-AQ69 -> 717.71688
B52: Receivables
B53: BoP | D53: =+C55 -> 7.699 | E53: =+D55 -> 13.17 | F53: =+E55 -> 19.852 | G53: =+F55 -> 28.282 | H53: =+G55 -> 45.177 | I53: =+H55 -> 52.996 | J53: =+I55 -> 60.269 | K53: =+J55 -> 63.499 | ... V53: =+U55 -> 211.6 | W53: =V55 -> 132.6 | X53: =W55 -> 174.3 | Y53: =+V55 -> 132.6 | Z53: =Y55 -> 146.5 | AA53: =Z55 -> 178.2 | AB53: =+Y55 -> 146.5 | AC53: =AB55 -> 135.1 | AD53: =AC55 -> 205.2 | AE53: =+AB55 -> 135.1 | AF53: =AE55 -> 186.5 | AG53: =AF55 -> 242.1 | AH53: =+AE55 -> 186.5 | AI53: =AH55 -> 200.71802 | AJ53: =AI55 -> 228.0666 | AK53: =+AH55 -> 200.71802 | AL53: =AK55 -> 209.14466 | AM53: =AL55 -> 238.11168 | AN53: =+AK55 -> 209.14466 | AO53: =AN55 -> 217.93311 | AP53: =AO55 -> 248.12947 | AQ53: =+AN55 -> 217.93311
B54: Increase/(Decr.) | D54: =D55-D53 -> 5.471 | E54: =E55-E53 -> 6.682 | F54: =F55-F53 -> 8.43 | G54: =G55-G53 -> 16.895 | H54: =H55-H53 -> 7.819 | I54: =I55-I53 -> 7.273 | J54: =J55-J53 -> 3.23 | K54: =K55-K53 -> -5.246 | ... AQ54: =AQ55-AQ53 -> 9.1685704
B55: EoP - Current Receivables | C55: 7.699 | D55: 13.17 | E55: 19.852 | F55: 28.282 | G55: 45.177 | H55: 52.996 | I55: 60.269 | J55: 63.499 | K55: 58.253 | L55: 58.378 | M55: 64.246 | N55: 70.745 | O55: 81.48 | P55: 98.073 | Q55: 196.6 | R55: 204.7 | S55: 254.4 | T55: 220.3 | U55: 211.6 | V55: 132.6 | W55: 174.3 | X55: =Y55 -> 146.5 | Y55: 146.5 | Z55: 178.2 | AA55: =AB55 -> 135.1 | AB55: 135.1 | AC55: 205.2 | AD55: =AE55 -> 186.5 | AE55: 186.5 | AF55: 242.1 | AG55: =AH55 -> 200.71802 | AH55: =AH56*'P&L'!BT6 -> 200.71802 | AI55: =AI56*'P&L'!BU6 -> 228.0666 | AJ55: =AK55 -> 209.14466 | AK55: =AK56*'P&L'!BW6 -> 209.14466 | AL55: =AL56*'P&L'!BX6 -> 238.11168 | AM55: =AN55 -> 217.93311 | AN55: =AN56*'P&L'!BZ6 -> 217.93311 | AO55: =AO56*'P&L'!CA6 -> 248.12947 | AP55: =AQ55 -> 227.10168 | AQ55: =AQ56*'P&L'!CC6 -> 227.10168
B56: EoP as % of Sales | C56: =C55/'P&L'!C6 -> 0.021636433 | D56: =D55/'P&L'!F6 -> 0.029114173 | E56: =E55/'P&L'!I6 -> 0.028607537 | F56: =F55/'P&L'!L6 -> 0.029902064 | G56: =G55/'P&L'!O6 -> 0.035243951 | H56: =H55/'P&L'!R6 -> 0.028982305 | I56: =I55/'P&L'!U6 -> 0.025896911 | J56: =J55/'P&L'!X6 -> 0.023248466 | K56: =K55/'P&L'!AA6 -> 0.019685035 | L56: =L55/'P&L'!AD6 -> 0.018664285 | M56: =M55/'P&L'!AG6 -> 0.019419055 | N56: =N55/'P&L'!AJ6 -> 0.020306995 | O56: =O55/'P&L'!AM6 -> 0.022310232 | P56: =P55/'P&L'!AP6 -> 0.024800561 | Q56: =Q55/'P&L'!AS6 -> 0.03493248 | R56: =R55/'P&L'!AV6 -> 0.029864465 | S56: =S55/'P&L'!AY6 -> 0.035854721 | T56: =T55/'P&L'!BB6 -> 0.02781952 | U56: =U55/'P&L'!BE6 -> 0.023732349 | V56: =V55/'P&L'!BH6 -> 0.014363085 | W56: =W55/'P&L'!BI6*0.5 -> 0.016510372 | X56: =X55/'P&L'!BJ6*0.5 -> 0.016847214 | Y56: =Y55/'P&L'!BK6 -> 0.015218566 | Z56: =Z55/'P&L'!BL6*0.5 -> 0.017260417 | AA56: =AA55/'P&L'!BM6*0.5 -> 0.015247274 | AB56: =AB55/'P&L'!BN6 -> 0.014084067 | AC56: =AC55/'P&L'!BO6*0.5 -> 0.018093962 | AD56: =AD55/'P&L'!BP6*0.5 -> 0.019091393 | AE56: =AE55/'P&L'!BQ6 -> 0.017669686 | AF56: =AF55/'P&L'!BR6*0.5 -> 0.019892199 | AG56: =AG55/'P&L'!BS6*0.5 -> 0.019811475 | AH56: 0.018 | AI56: =AK56*2 -> 0.036 | AJ56: =AJ55/'P&L'!BV6 -> 0.03958101 | AK56: 0.018 | AL56: =AN56*2 -> 0.036 | AM56: =AM55/'P&L'!BY6 -> 0.039673384 | AN56: 0.018 | AO56: =AQ56*2 -> 0.036 | AP56: =AP55/'P&L'!CB6 -> 0.03967344 | AQ56: 0.018
