Workbook
Name A_ALL_SIG.AX: #REF!
Name Abnormals_PostTAX: #REF!
Name AEndDrinks_Sales: #REF!
Name Continuing_sales: #REF!
Name DCF_INF: #REF!
Name DPS: #REF!
Name E_ALL_SIG.AX: #REF!
Name EPS_Pre_Goodwill: #REF!
Name L_ALL_SIG.AX: #REF!
Name NET_PROFIT: #REF!
Name NPAT_post_Abn: #REF!
Name Sales_Aust_FL: #REF!
Name Sales_NZ_FL: #REF!
Name TOTAL_SALES: #REF!
Name V_ALL_SIG.AX: #REF!

Sheet Cover
B5: Sigma Healthcare (SIG.AX)
B6: Rating | C6: Buy
B7: Target Price/ Target price period/ Upside/downside to target price | C7: A$3.5/ 12 Month/ 19.9%
B8: M&A probability (1 = high, 3 = low) | C8: 3
B9: Market Cap (US$ mn) (price as of ______):
B10: Current shares outstanding (mn):
B11: Currency: | C11: AUD
B12: Current Publication Date: | C12: 46043
B13: Previous Publication Date:
B15: Team Contacts:
B16: Lead Analyst
B17: Peter Marks, peter.marks@gs.com, +61 2 9321 8846, Goldman Sachs Australia Pty Ltd
B18: Consumer Team
B19: James Leigh, james.leigh@gs.com, +61 2 , Goldman Sachs Australia Pty Ltd
B20: Consumer Team
B21: Rayanne Haidar, rayanne.haidar@gs.com +61 2 9321 8739, Goldman Sachs Australia Pty Ltd

Sheet Summary
D1: Sigma Healthcare (SIG.AX)
D6: Goldman Sachs | Sigma Healthcare | SIG-AU
D8: Price target | F8: =Valuation!E22 -> 3.5
D9: Current share price | F9: 2.92
D10: Upside / downside | F10: =F8/F9-1 -> 0.19863014
D11: Recommendation | F11: BUY
A13: Col D | B13: Col K | D13: P&L | E13: FY24 | F13: FY25 | G13: FY26E | H13: FY27E | I13: FY28E | K13: Balance Sheet | L13: =E$13 -> FY24 | M13: =F$13 -> FY25 | N13: =G$13 -> FY26E | O13: =H$13 -> FY27E | P13: =I$13 -> FY28E
B14: Cash | D14: Network Sales | K14: Cash | M14: =VLOOKUP($B14,BS!$1:$1048576,MATCH(F$37,BS!$3:$3,0),FALSE) -> 138.774 | N14: =VLOOKUP($B14,BS!$1:$1048576,MATCH(G$37,BS!$3:$3,0),FALSE) -> 262.54586 | O14: =VLOOKUP($B14,BS!$1:$1048576,MATCH(H$37,BS!$3:$3,0),FALSE) -> 477.70275 | P14: =VLOOKUP($B14,BS!$1:$1048576,MATCH(I$37,BS!$3:$3,0),FALSE) -> 723.6438
A15: Australia Sales | B15: TR | D15: Australia | E15: =VLOOKUP($A15,Model!$1:$1048576,MATCH(L$51,Model!$3:$3,0),FALSE) -> 7909.9 | F15: =VLOOKUP($A15,Model!$1:$1048576,MATCH(M$51,Model!$3:$3,0),FALSE) -> 8968.9 | G15: =VLOOKUP($A15,Model!$1:$1048576,MATCH(N$51,Model!$3:$3,0),FALSE) -> 10113.441 | H15: =VLOOKUP($A15,Model!$1:$1048576,MATCH(O$51,Model!$3:$3,0),FALSE) -> 11091.441 | I15: =VLOOKUP($A15,Model!$1:$1048576,MATCH(P$51,Model!$3:$3,0),FALSE) -> 11821.77 | K15: Trade receivables | M15: =VLOOKUP($B15,BS!$1:$1048576,MATCH(F$37,BS!$3:$3,0),FALSE) -> 1575.136 | N15: =VLOOKUP($B15,BS!$1:$1048576,MATCH(G$37,BS!$3:$3,0),FALSE) -> 1709.8835 | O15: =VLOOKUP($B15,BS!$1:$1048576,MATCH(H$37,BS!$3:$3,0),FALSE) -> 1838.0483 | P15: =VLOOKUP($B15,BS!$1:$1048576,MATCH(I$37,BS!$3:$3,0),FALSE) -> 1992.8447
A16: NZ Sales | B16: Inventories | D16: New Zealand | E16: =VLOOKUP($A16,Model!$1:$1048576,MATCH(L$51,Model!$3:$3,0),FALSE) -> 886 | F16: =VLOOKUP($A16,Model!$1:$1048576,MATCH(M$51,Model!$3:$3,0),FALSE) -> 1050 | G16: =VLOOKUP($A16,Model!$1:$1048576,MATCH(N$51,Model!$3:$3,0),FALSE) -> 1297.6967 | H16: =VLOOKUP($A16,Model!$1:$1048576,MATCH(O$51,Model!$3:$3,0),FALSE) -> 1533.3311 | I16: =VLOOKUP($A16,Model!$1:$1048576,MATCH(P$51,Model!$3:$3,0),FALSE) -> 1788.292 | K16: Inventories | M16: =VLOOKUP($B16,BS!$1:$1048576,MATCH(F$37,BS!$3:$3,0),FALSE) -> 1019.778 | N16: =VLOOKUP($B16,BS!$1:$1048576,MATCH(G$37,BS!$3:$3,0),FALSE) -> 1171.1085 | O16: =VLOOKUP($B16,BS!$1:$1048576,MATCH(H$37,BS!$3:$3,0),FALSE) -> 1247.247 | P16: =VLOOKUP($B16,BS!$1:$1048576,MATCH(I$37,BS!$3:$3,0),FALSE) -> 1281.1144
A17: Ireland Sales | B17: Lease CA | D17: Ireland | E17: =VLOOKUP($A17,Model!$1:$1048576,MATCH(L$51,Model!$3:$3,0),FALSE) -> 105.69921 | F17: =VLOOKUP($A17,Model!$1:$1048576,MATCH(M$51,Model!$3:$3,0),FALSE) -> 167.47139 | G17: =VLOOKUP($A17,Model!$1:$1048576,MATCH(N$51,Model!$3:$3,0),FALSE) -> 266.16179 | H17: =VLOOKUP($A17,Model!$1:$1048576,MATCH(O$51,Model!$3:$3,0),FALSE) -> 368.14378 | I17: =VLOOKUP($A17,Model!$1:$1048576,MATCH(P$51,Model!$3:$3,0),FALSE) -> 467.54261 | K17: Lease Receivables | M17: =VLOOKUP($B17,BS!$1:$1048576,MATCH(F$37,BS!$3:$3,0),FALSE) -> 139.656 | N17: =VLOOKUP($B17,BS!$1:$1048576,MATCH(G$37,BS!$3:$3,0),FALSE) -> 139.656 | O17: =VLOOKUP($B17,BS!$1:$1048576,MATCH(H$37,BS!$3:$3,0),FALSE) -> 139.656 | P17: =VLOOKUP($B17,BS!$1:$1048576,MATCH(I$37,BS!$3:$3,0),FALSE) -> 139.656
A18: China Sales | B18: Other CA | D18: China | E18: =VLOOKUP($A18,Model!$1:$1048576,MATCH(L$51,Model!$3:$3,0),FALSE) -> 100.30079 | F18: =VLOOKUP($A18,Model!$1:$1048576,MATCH(M$51,Model!$3:$3,0),FALSE) -> 72.128605 | G18: =VLOOKUP($A18,Model!$1:$1048576,MATCH(N$51,Model!$3:$3,0),FALSE) -> 80 | H18: =VLOOKUP($A18,Model!$1:$1048576,MATCH(O$51,Model!$3:$3,0),FALSE) -> 80 | I18: =VLOOKUP($A18,Model!$1:$1048576,MATCH(P$51,Model!$3:$3,0),FALSE) -> 80 | K18: Other current assets | M18: =VLOOKUP($B18,BS!$1:$1048576,MATCH(F$37,BS!$3:$3,0),FALSE) -> 34.573 | N18: =VLOOKUP($B18,BS!$1:$1048576,MATCH(G$37,BS!$3:$3,0),FALSE) -> 34.573 | O18: =VLOOKUP($B18,BS!$1:$1048576,MATCH(H$37,BS!$3:$3,0),FALSE) -> 34.573 | P18: =VLOOKUP($B18,BS!$1:$1048576,MATCH(I$37,BS!$3:$3,0),FALSE) -> 34.573
A19: Dubai Sales | B19: CA | D19: Dubai | E19: =VLOOKUP($A19,Model!$1:$1048576,MATCH(L$51,Model!$3:$3,0),FALSE) -> 0 | F19: =VLOOKUP($A19,Model!$1:$1048576,MATCH(M$51,Model!$3:$3,0),FALSE) -> 10 | G19: =VLOOKUP($A19,Model!$1:$1048576,MATCH(N$51,Model!$3:$3,0),FALSE) -> 35 | H19: =VLOOKUP($A19,Model!$1:$1048576,MATCH(O$51,Model!$3:$3,0),FALSE) -> 56 | I19: =VLOOKUP($A19,Model!$1:$1048576,MATCH(P$51,Model!$3:$3,0),FALSE) -> 77 | K19: Current assets | M19: =VLOOKUP($B19,BS!$1:$1048576,MATCH(F$37,BS!$3:$3,0),FALSE) -> 2908.429 | N19: =VLOOKUP($B19,BS!$1:$1048576,MATCH(G$37,BS!$3:$3,0),FALSE) -> 3318.2789 | O19: =VLOOKUP($B19,BS!$1:$1048576,MATCH(H$37,BS!$3:$3,0),FALSE) -> 3737.7391 | P19: =VLOOKUP($B19,BS!$1:$1048576,MATCH(I$37,BS!$3:$3,0),FALSE) -> 4172.3439
A20: Total network sales | B20: PPE | D20: Total Network Sales | E20: =VLOOKUP($A20,Model!$1:$1048576,MATCH(L$51,Model!$3:$3,0),FALSE) -> 9001.9 | F20: =VLOOKUP($A20,Model!$1:$1048576,MATCH(M$51,Model!$3:$3,0),FALSE) -> 10268.5 | G20: =VLOOKUP($A20,Model!$1:$1048576,MATCH(N$51,Model!$3:$3,0),FALSE) -> 11792.3 | H20: =VLOOKUP($A20,Model!$1:$1048576,MATCH(O$51,Model!$3:$3,0),FALSE) -> 13128.916 | I20: =VLOOKUP($A20,Model!$1:$1048576,MATCH(P$51,Model!$3:$3,0),FALSE) -> 14234.605 | K20: PPE | M20: =VLOOKUP($B20,BS!$1:$1048576,MATCH(F$37,BS!$3:$3,0),FALSE) -> 320.438 | N20: =VLOOKUP($B20,BS!$1:$1048576,MATCH(G$37,BS!$3:$3,0),FALSE) -> 340.93442 | O20: =VLOOKUP($B20,BS!$1:$1048576,MATCH(H$37,BS!$3:$3,0),FALSE) -> 364.10258 | P20: =VLOOKUP($B20,BS!$1:$1048576,MATCH(I$37,BS!$3:$3,0),FALSE) -> 390.17511
A21: Total network sales growth | B21: Lease NCA | D21: Growth % | E21: =VLOOKUP($A21,Model!$1:$1048576,MATCH(L$51,Model!$3:$3,0),FALSE) -> 0.1412145 | F21: =VLOOKUP($A21,Model!$1:$1048576,MATCH(M$51,Model!$3:$3,0),FALSE) -> 0.14070363 | G21: =VLOOKUP($A21,Model!$1:$1048576,MATCH(N$51,Model!$3:$3,0),FALSE) -> 0.14839558 | H21: =VLOOKUP($A21,Model!$1:$1048576,MATCH(O$51,Model!$3:$3,0),FALSE) -> 0.11334653 | I21: =VLOOKUP($A21,Model!$1:$1048576,MATCH(P$51,Model!$3:$3,0),FALSE) -> 0.0842178 | K21: Lease assets | M21: =VLOOKUP($B21,BS!$1:$1048576,MATCH(F$37,BS!$3:$3,0),FALSE) -> 821.668 | N21: =VLOOKUP($B21,BS!$1:$1048576,MATCH(G$37,BS!$3:$3,0),FALSE) -> 686.24127 | O21: =VLOOKUP($B21,BS!$1:$1048576,MATCH(H$37,BS!$3:$3,0),FALSE) -> 545.70053 | P21: =VLOOKUP($B21,BS!$1:$1048576,MATCH(I$37,BS!$3:$3,0),FALSE) -> 398.15169
A22: Total Revenue | B22: Intangibles | D22: Revenue | E22: =VLOOKUP($A22,Model!$1:$1048576,MATCH(L$51,Model!$3:$3,0),FALSE) -> 6655.7 | F22: =VLOOKUP($A22,Model!$1:$1048576,MATCH(M$51,Model!$3:$3,0),FALSE) -> 9591.3 | G22: =VLOOKUP($A22,Model!$1:$1048576,MATCH(N$51,Model!$3:$3,0),FALSE) -> 10928.785 | H22: =VLOOKUP($A22,Model!$1:$1048576,MATCH(O$51,Model!$3:$3,0),FALSE) -> 12084.819 | I22: =VLOOKUP($A22,Model!$1:$1048576,MATCH(P$51,Model!$3:$3,0),FALSE) -> 12985.047 | K22: Intangibles | M22: =VLOOKUP($B22,BS!$1:$1048576,MATCH(F$37,BS!$3:$3,0),FALSE) -> 3860.481 | N22: =VLOOKUP($B22,BS!$1:$1048576,MATCH(G$37,BS!$3:$3,0),FALSE) -> 3860.481 | O22: =VLOOKUP($B22,BS!$1:$1048576,MATCH(H$37,BS!$3:$3,0),FALSE) -> 3860.481 | P22: =VLOOKUP($B22,BS!$1:$1048576,MATCH(I$37,BS!$3:$3,0),FALSE) -> 3860.481
A23: Gross Profit | B23: Other NCA | D23: Gross Profit | E23: =VLOOKUP($A23,Model!$1:$1048576,MATCH(L$51,Model!$3:$3,0),FALSE) -> 1312.3 | F23: =VLOOKUP($A23,Model!$1:$1048576,MATCH(M$51,Model!$3:$3,0),FALSE) -> 1698.6 | G23: =VLOOKUP($A23,Model!$1:$1048576,MATCH(N$51,Model!$3:$3,0),FALSE) -> 1947.127 | H23: =VLOOKUP($A23,Model!$1:$1048576,MATCH(O$51,Model!$3:$3,0),FALSE) -> 2185.1573 | I23: =VLOOKUP($A23,Model!$1:$1048576,MATCH(P$51,Model!$3:$3,0),FALSE) -> 2390.5383 | K23: Other non current assets | M23: =VLOOKUP($B23,BS!$1:$1048576,MATCH(F$37,BS!$3:$3,0),FALSE) -> 6.781 | N23: =VLOOKUP($B23,BS!$1:$1048576,MATCH(G$37,BS!$3:$3,0),FALSE) -> 6.781 | O23: =VLOOKUP($B23,BS!$1:$1048576,MATCH(H$37,BS!$3:$3,0),FALSE) -> 6.781 | P23: =VLOOKUP($B23,BS!$1:$1048576,MATCH(I$37,BS!$3:$3,0),FALSE) -> 6.781
A24: CoDB | B24: NCA | D24: CoDB | E24: =VLOOKUP($A24,Model!$1:$1048576,MATCH(L$51,Model!$3:$3,0),FALSE) -> -705.4 | F24: =VLOOKUP($A24,Model!$1:$1048576,MATCH(M$51,Model!$3:$3,0),FALSE) -> -783 | G24: =VLOOKUP($A24,Model!$1:$1048576,MATCH(N$51,Model!$3:$3,0),FALSE) -> -841.67909 | H24: =VLOOKUP($A24,Model!$1:$1048576,MATCH(O$51,Model!$3:$3,0),FALSE) -> -901.83369 | I24: =VLOOKUP($A24,Model!$1:$1048576,MATCH(P$51,Model!$3:$3,0),FALSE) -> -944.87431 | K24: Non-current assets | M24: =VLOOKUP($B24,BS!$1:$1048576,MATCH(F$37,BS!$3:$3,0),FALSE) -> 5379.373 | N24: =VLOOKUP($B24,BS!$1:$1048576,MATCH(G$37,BS!$3:$3,0),FALSE) -> 5396.7423 | O24: =VLOOKUP($B24,BS!$1:$1048576,MATCH(H$37,BS!$3:$3,0),FALSE) -> 5416.2441 | P24: =VLOOKUP($B24,BS!$1:$1048576,MATCH(I$37,BS!$3:$3,0),FALSE) -> 5437.9115
A25: EBITDA | B25: TP | D25: EBITDA | E25: =VLOOKUP($A25,Model!$1:$1048576,MATCH(L$51,Model!$3:$3,0),FALSE) -> 675.1 | F25: =VLOOKUP($A25,Model!$1:$1048576,MATCH(M$51,Model!$3:$3,0),FALSE) -> 968.5 | G25: =VLOOKUP($A25,Model!$1:$1048576,MATCH(N$51,Model!$3:$3,0),FALSE) -> 1201.5729 | H25: =VLOOKUP($A25,Model!$1:$1048576,MATCH(O$51,Model!$3:$3,0),FALSE) -> 1424.6573 | I25: =VLOOKUP($A25,Model!$1:$1048576,MATCH(P$51,Model!$3:$3,0),FALSE) -> 1633.2645 | K25: Trade payables | M25: =VLOOKUP($B25,BS!$1:$1048576,MATCH(F$37,BS!$3:$3,0),FALSE) -> 1323.603 | N25: =VLOOKUP($B25,BS!$1:$1048576,MATCH(G$37,BS!$3:$3,0),FALSE) -> 1520.0198 | O25: =VLOOKUP($B25,BS!$1:$1048576,MATCH(H$37,BS!$3:$3,0),FALSE) -> 1692.3088 | P25: =VLOOKUP($B25,BS!$1:$1048576,MATCH(I$37,BS!$3:$3,0),FALSE) -> 1834.8313
A26: D&A | B26: Current Borrowings | D26: D&A | E26: =VLOOKUP($A26,Model!$1:$1048576,MATCH(L$51,Model!$3:$3,0),FALSE) -> -69.6 | F26: =VLOOKUP($A26,Model!$1:$1048576,MATCH(M$51,Model!$3:$3,0),FALSE) -> -65.1 | G26: =VLOOKUP($A26,Model!$1:$1048576,MATCH(N$51,Model!$3:$3,0),FALSE) -> -68.355 | H26: =VLOOKUP($A26,Model!$1:$1048576,MATCH(O$51,Model!$3:$3,0),FALSE) -> -71.77275 | I26: =VLOOKUP($A26,Model!$1:$1048576,MATCH(P$51,Model!$3:$3,0),FALSE) -> -75.361388 | K26: Borrowings | M26: =VLOOKUP($B26,BS!$1:$1048576,MATCH(F$37,BS!$3:$3,0),FALSE) -> 35.643 | N26: =VLOOKUP($B26,BS!$1:$1048576,MATCH(G$37,BS!$3:$3,0),FALSE) -> 35.643 | O26: =VLOOKUP($B26,BS!$1:$1048576,MATCH(H$37,BS!$3:$3,0),FALSE) -> 35.643 | P26: =VLOOKUP($B26,BS!$1:$1048576,MATCH(I$37,BS!$3:$3,0),FALSE) -> 35.643
A27: EBIT | B27: Lease CL | D27: Total EBIT | E27: =VLOOKUP($A27,Model!$1:$1048576,MATCH(L$51,Model!$3:$3,0),FALSE) -> 605.5 | F27: =VLOOKUP($A27,Model!$1:$1048576,MATCH(M$51,Model!$3:$3,0),FALSE) -> 903.4 | G27: =VLOOKUP($A27,Model!$1:$1048576,MATCH(N$51,Model!$3:$3,0),FALSE) -> 1133.2179 | H27: =VLOOKUP($A27,Model!$1:$1048576,MATCH(O$51,Model!$3:$3,0),FALSE) -> 1352.8846 | I27: =VLOOKUP($A27,Model!$1:$1048576,MATCH(P$51,Model!$3:$3,0),FALSE) -> 1557.9031 | K27: Lease liabilities | M27: =VLOOKUP($B27,BS!$1:$1048576,MATCH(F$37,BS!$3:$3,0),FALSE) -> 157.975 | N27: =VLOOKUP($B27,BS!$1:$1048576,MATCH(G$37,BS!$3:$3,0),FALSE) -> 157.975 | O27: =VLOOKUP($B27,BS!$1:$1048576,MATCH(H$37,BS!$3:$3,0),FALSE) -> 157.975 | P27: =VLOOKUP($B27,BS!$1:$1048576,MATCH(I$37,BS!$3:$3,0),FALSE) -> 157.975
A28: Net interest | B28: CL | D28: Net interest | F28: =VLOOKUP($A28,PL!$1:$1048576,MATCH(M$51,PL!$3:$3,0),FALSE) -> -24.1 | G28: =VLOOKUP($A28,PL!$1:$1048576,MATCH(N$51,PL!$3:$3,0),FALSE) -> -50 | H28: =VLOOKUP($A28,PL!$1:$1048576,MATCH(O$51,PL!$3:$3,0),FALSE) -> -46 | I28: =VLOOKUP($A28,PL!$1:$1048576,MATCH(P$51,PL!$3:$3,0),FALSE) -> -40 | K28: Current liabilities | M28: =VLOOKUP($B28,BS!$1:$1048576,MATCH(F$37,BS!$3:$3,0),FALSE) -> 1702.865 | N28: =VLOOKUP($B28,BS!$1:$1048576,MATCH(G$37,BS!$3:$3,0),FALSE) -> 1899.2818 | O28: =VLOOKUP($B28,BS!$1:$1048576,MATCH(H$37,BS!$3:$3,0),FALSE) -> 2071.5708 | P28: =VLOOKUP($B28,BS!$1:$1048576,MATCH(I$37,BS!$3:$3,0),FALSE) -> 2214.0933
A29: PBT | B29: Lease NCA | D29: PBT | F29: =VLOOKUP($A29,PL!$1:$1048576,MATCH(M$51,PL!$3:$3,0),FALSE) -> 879.3 | G29: =VLOOKUP($A29,PL!$1:$1048576,MATCH(N$51,PL!$3:$3,0),FALSE) -> 1083.2179 | H29: =VLOOKUP($A29,PL!$1:$1048576,MATCH(O$51,PL!$3:$3,0),FALSE) -> 1306.8846 | I29: =VLOOKUP($A29,PL!$1:$1048576,MATCH(P$51,PL!$3:$3,0),FALSE) -> 1517.9031 | K29: Lease liabilities | M29: =VLOOKUP($B29,BS!$1:$1048576,MATCH(F$37,BS!$3:$3,0),FALSE) -> 821.668 | N29: =VLOOKUP($B29,BS!$1:$1048576,MATCH(G$37,BS!$3:$3,0),FALSE) -> 686.24127 | O29: =VLOOKUP($B29,BS!$1:$1048576,MATCH(H$37,BS!$3:$3,0),FALSE) -> 545.70053 | P29: =VLOOKUP($B29,BS!$1:$1048576,MATCH(I$37,BS!$3:$3,0),FALSE) -> 398.15169
A30: Tax | B30: NC Borrowings | D30: Tax | F30: =VLOOKUP($A30,PL!$1:$1048576,MATCH(M$51,PL!$3:$3,0),FALSE) -> -254.997 | G30: =VLOOKUP($A30,PL!$1:$1048576,MATCH(N$51,PL!$3:$3,0),FALSE) -> -314.1332 | H30: =VLOOKUP($A30,PL!$1:$1048576,MATCH(O$51,PL!$3:$3,0),FALSE) -> -378.99653 | I30: =VLOOKUP($A30,PL!$1:$1048576,MATCH(P$51,PL!$3:$3,0),FALSE) -> -440.19191 | K30: Borrowings | M30: =VLOOKUP($B30,BS!$1:$1048576,MATCH(F$37,BS!$3:$3,0),FALSE) -> 855.292 | N30: =VLOOKUP($B30,BS!$1:$1048576,MATCH(G$37,BS!$3:$3,0),FALSE) -> 855.292 | O30: =VLOOKUP($B30,BS!$1:$1048576,MATCH(H$37,BS!$3:$3,0),FALSE) -> 855.292 | P30: =VLOOKUP($B30,BS!$1:$1048576,MATCH(I$37,BS!$3:$3,0),FALSE) -> 855.292
A31: Minorities | B31: Other NCL | D31: Minority interest | F31: =VLOOKUP($A31,PL!$1:$1048576,MATCH(M$51,PL!$3:$3,0),FALSE) -> -4.5 | G31: =VLOOKUP($A31,PL!$1:$1048576,MATCH(N$51,PL!$3:$3,0),FALSE) -> -7.8058614 | H31: =VLOOKUP($A31,PL!$1:$1048576,MATCH(O$51,PL!$3:$3,0),FALSE) -> -11.184447 | I31: =VLOOKUP($A31,PL!$1:$1048576,MATCH(P$51,PL!$3:$3,0),FALSE) -> -14.100187 | K31: Other non-current liabilities | M31: =VLOOKUP($B31,BS!$1:$1048576,MATCH(F$37,BS!$3:$3,0),FALSE) -> 17.104 | N31: =VLOOKUP($B31,BS!$1:$1048576,MATCH(G$37,BS!$3:$3,0),FALSE) -> 17.104 | O31: =VLOOKUP($B31,BS!$1:$1048576,MATCH(H$37,BS!$3:$3,0),FALSE) -> 17.104 | P31: =VLOOKUP($B31,BS!$1:$1048576,MATCH(I$37,BS!$3:$3,0),FALSE) -> 17.104
A32: NPAT | B32: NCL | D32: NPAT | F32: =VLOOKUP($A32,PL!$1:$1048576,MATCH(M$51,PL!$3:$3,0),FALSE) -> 619.803 | G32: =VLOOKUP($A32,PL!$1:$1048576,MATCH(N$51,PL!$3:$3,0),FALSE) -> 761.27888 | H32: =VLOOKUP($A32,PL!$1:$1048576,MATCH(O$51,PL!$3:$3,0),FALSE) -> 916.70362 | I32: =VLOOKUP($A32,PL!$1:$1048576,MATCH(P$51,PL!$3:$3,0),FALSE) -> 1063.611 | K32: Non-current liabilities | M32: =VLOOKUP($B32,BS!$1:$1048576,MATCH(F$37,BS!$3:$3,0),FALSE) -> 1924.342 | N32: =VLOOKUP($B32,BS!$1:$1048576,MATCH(G$37,BS!$3:$3,0),FALSE) -> 1926.0548 | O32: =VLOOKUP($B32,BS!$1:$1048576,MATCH(H$37,BS!$3:$3,0),FALSE) -> 1927.8323 | P32: =VLOOKUP($B32,BS!$1:$1048576,MATCH(I$37,BS!$3:$3,0),FALSE) -> 1929.6985
A33: Shares Diluted | B33: Contributed Equity | D33: Shares (m) | F33: =VLOOKUP($A33,PL!$1:$1048576,MATCH(M$51,PL!$3:$3,0),FALSE) -> 11540 | G33: =VLOOKUP($A33,PL!$1:$1048576,MATCH(N$51,PL!$3:$3,0),FALSE) -> 11540 | H33: =VLOOKUP($A33,PL!$1:$1048576,MATCH(O$51,PL!$3:$3,0),FALSE) -> 11540 | I33: =VLOOKUP($A33,PL!$1:$1048576,MATCH(P$51,PL!$3:$3,0),FALSE) -> 11540 | K33: Contributed equity | M33: =VLOOKUP($B33,BS!$1:$1048576,MATCH(F$37,BS!$3:$3,0),FALSE) -> 4403.299 | N33: =VLOOKUP($B33,BS!$1:$1048576,MATCH(G$37,BS!$3:$3,0),FALSE) -> 4403.299 | O33: =VLOOKUP($B33,BS!$1:$1048576,MATCH(H$37,BS!$3:$3,0),FALSE) -> 4403.299 | P33: =VLOOKUP($B33,BS!$1:$1048576,MATCH(I$37,BS!$3:$3,0),FALSE) -> 4403.299
A34: EPS | B34: Reserves | D34: EPS | F34: =VLOOKUP($A34,PL!$1:$1048576,MATCH(M$51,PL!$3:$3,0),FALSE) -> 0.053709099 | G34: =VLOOKUP($A34,PL!$1:$1048576,MATCH(N$51,PL!$3:$3,0),FALSE) -> 0.065968707 | H34: =VLOOKUP($A34,PL!$1:$1048576,MATCH(O$51,PL!$3:$3,0),FALSE) -> 0.079437055 | I34: =VLOOKUP($A34,PL!$1:$1048576,MATCH(P$51,PL!$3:$3,0),FALSE) -> 0.092167335 | K34: Reserves | M34: =VLOOKUP($B34,BS!$1:$1048576,MATCH(F$37,BS!$3:$3,0),FALSE) -> -6.023 | N34: =VLOOKUP($B34,BS!$1:$1048576,MATCH(G$37,BS!$3:$3,0),FALSE) -> -6.023 | O34: =VLOOKUP($B34,BS!$1:$1048576,MATCH(H$37,BS!$3:$3,0),FALSE) -> -6.023 | P34: =VLOOKUP($B34,BS!$1:$1048576,MATCH(I$37,BS!$3:$3,0),FALSE) -> -6.023
A35: DPS | B35: Retained Profits | D35: DPS total | G35: =VLOOKUP($A35,PL!$1:$1048576,MATCH(N$51,PL!$3:$3,0),FALSE) -> 0.046178095 | H35: =VLOOKUP($A35,PL!$1:$1048576,MATCH(O$51,PL!$3:$3,0),FALSE) -> 0.055605939 | I35: =VLOOKUP($A35,PL!$1:$1048576,MATCH(P$51,PL!$3:$3,0),FALSE) -> 0.064517134 | K35: Retained Profits | M35: =VLOOKUP($B35,BS!$1:$1048576,MATCH(F$37,BS!$3:$3,0),FALSE) -> 273.263 | N35: =VLOOKUP($B35,BS!$1:$1048576,MATCH(G$37,BS!$3:$3,0),FALSE) -> 494.54666 | O35: =VLOOKUP($B35,BS!$1:$1048576,MATCH(H$37,BS!$3:$3,0),FALSE) -> 748.25775 | P35: =VLOOKUP($B35,BS!$1:$1048576,MATCH(I$37,BS!$3:$3,0),FALSE) -> 1046.0411
B36: Minorities | K36: Minority Interests | M36: =VLOOKUP($B36,BS!$1:$1048576,MATCH(F$37,BS!$3:$3,0),FALSE) -> -9.944 | N36: =VLOOKUP($B36,BS!$1:$1048576,MATCH(G$37,BS!$3:$3,0),FALSE) -> -2.1381386 | O36: =VLOOKUP($B36,BS!$1:$1048576,MATCH(H$37,BS!$3:$3,0),FALSE) -> 9.0463083 | P36: =VLOOKUP($B36,BS!$1:$1048576,MATCH(I$37,BS!$3:$3,0),FALSE) -> 23.146495
B37: Equity | D37: Cash Flow | E37: FY24 | F37: FY25 | G37: FY26E | H37: FY27E | I37: FY28E | K37: Total Equity | M37: =VLOOKUP($B37,BS!$1:$1048576,MATCH(F$37,BS!$3:$3,0),FALSE) -> 4660.595 | N37: =VLOOKUP($B37,BS!$1:$1048576,MATCH(G$37,BS!$3:$3,0),FALSE) -> 4889.6845 | O37: =VLOOKUP($B37,BS!$1:$1048576,MATCH(H$37,BS!$3:$3,0),FALSE) -> 5154.5801 | P37: =VLOOKUP($B37,BS!$1:$1048576,MATCH(I$37,BS!$3:$3,0),FALSE) -> 5466.4636
A38: EBIT | B38: Net Debt | D38: EBIT | F38: =VLOOKUP($A38,CF!$1:$1048576,MATCH(F$37,CF!$3:$3,0),FALSE) -> 903.4 | G38: =VLOOKUP($A38,CF!$1:$1048576,MATCH(G$37,CF!$3:$3,0),FALSE) -> 1133.2179 | H38: =VLOOKUP($A38,CF!$1:$1048576,MATCH(H$37,CF!$3:$3,0),FALSE) -> 1352.8846 | I38: =VLOOKUP($A38,CF!$1:$1048576,MATCH(I$37,CF!$3:$3,0),FALSE) -> 1557.9031 | K38: Net debt ex leases | M38: =VLOOKUP($B38,BS!$1:$1048576,MATCH(F$37,BS!$3:$3,0),FALSE) -> 752.161 | N38: =VLOOKUP($B38,BS!$1:$1048576,MATCH(G$37,BS!$3:$3,0),FALSE) -> 628.38914 | O38: =VLOOKUP($B38,BS!$1:$1048576,MATCH(H$37,BS!$3:$3,0),FALSE) -> 413.23225 | P38: =VLOOKUP($B38,BS!$1:$1048576,MATCH(I$37,BS!$3:$3,0),FALSE) -> 167.2912
A39: D&A | D39: D&A | F39: =VLOOKUP($A39,CF!$1:$1048576,MATCH(F$37,CF!$3:$3,0),FALSE) -> 65.1 | G39: =VLOOKUP($A39,CF!$1:$1048576,MATCH(G$37,CF!$3:$3,0),FALSE) -> 68.355 | H39: =VLOOKUP($A39,CF!$1:$1048576,MATCH(H$37,CF!$3:$3,0),FALSE) -> 71.77275 | I39: =VLOOKUP($A39,CF!$1:$1048576,MATCH(I$37,CF!$3:$3,0),FALSE) -> 75.361388 | K39: Divisional Key Metrics | L39: =E$13 -> FY24 | M39: =F$13 -> FY25 | N39: =G$13 -> FY26E | O39: =H$13 -> FY27E | P39: =I$13 -> FY28E
A40: Net interest | D40: Net interest | F40: =VLOOKUP($A40,CF!$1:$1048576,MATCH(F$37,CF!$3:$3,0),FALSE) -> -24.1 | G40: =VLOOKUP($A40,CF!$1:$1048576,MATCH(G$37,CF!$3:$3,0),FALSE) -> -50 | H40: =VLOOKUP($A40,CF!$1:$1048576,MATCH(H$37,CF!$3:$3,0),FALSE) -> -46 | I40: =VLOOKUP($A40,CF!$1:$1048576,MATCH(I$37,CF!$3:$3,0),FALSE) -> -40 | K40: LFL Sales Growth
A41: Tax | B41: Australia LFL | D41: Tax | F41: =VLOOKUP($A41,CF!$1:$1048576,MATCH(F$37,CF!$3:$3,0),FALSE) -> -254.997 | G41: =VLOOKUP($A41,CF!$1:$1048576,MATCH(G$37,CF!$3:$3,0),FALSE) -> -314.1332 | H41: =VLOOKUP($A41,CF!$1:$1048576,MATCH(H$37,CF!$3:$3,0),FALSE) -> -378.99653 | I41: =VLOOKUP($A41,CF!$1:$1048576,MATCH(I$37,CF!$3:$3,0),FALSE) -> -440.19191 | K41: Australia LFL | L41: =VLOOKUP($B41,Model!$1:$1048576,MATCH(L$51,Model!$3:$3,0),FALSE) -> 0.098 | M41: =VLOOKUP($B41,Model!$1:$1048576,MATCH(M$51,Model!$3:$3,0),FALSE) -> 0.113 | N41: =VLOOKUP($B41,Model!$1:$1048576,MATCH(N$51,Model!$3:$3,0),FALSE) -> 0.11 | O41: =VLOOKUP($B41,Model!$1:$1048576,MATCH(O$51,Model!$3:$3,0),FALSE) -> 0.08 | P41: =VLOOKUP($B41,Model!$1:$1048576,MATCH(P$51,Model!$3:$3,0),FALSE) -> 0.05
A42: Chg WC | B42: International LFL | D42: Change in net working capital | F42: =VLOOKUP($A42,CF!$1:$1048576,MATCH(F$37,CF!$3:$3,0),FALSE) -> -722.22 | G42: =VLOOKUP($A42,CF!$1:$1048576,MATCH(G$37,CF!$3:$3,0),FALSE) -> -89.661211 | H42: =VLOOKUP($A42,CF!$1:$1048576,MATCH(H$37,CF!$3:$3,0),FALSE) -> -32.014301 | I42: =VLOOKUP($A42,CF!$1:$1048576,MATCH(I$37,CF!$3:$3,0),FALSE) -> -46.141237 | K42: International LFL | L42: =VLOOKUP($B42,Model!$1:$1048576,MATCH(L$51,Model!$3:$3,0),FALSE) -> 0.144 | M42: =VLOOKUP($B42,Model!$1:$1048576,MATCH(M$51,Model!$3:$3,0),FALSE) -> 0.081 | N42: =VLOOKUP($B42,Model!$1:$1048576,MATCH(N$51,Model!$3:$3,0),FALSE) -> 0.1 | O42: =VLOOKUP($B42,Model!$1:$1048576,MATCH(O$51,Model!$3:$3,0),FALSE) -> 0.08 | P42: =VLOOKUP($B42,Model!$1:$1048576,MATCH(P$51,Model!$3:$3,0),FALSE) -> 0.08
A43: Other | D43: Other | F43: =VLOOKUP($A43,CF!$1:$1048576,MATCH(F$37,CF!$3:$3,0),FALSE) -> 631.645 | G43: =VLOOKUP($A43,CF!$1:$1048576,MATCH(G$37,CF!$3:$3,0),FALSE) -> -7.1 | H43: =VLOOKUP($A43,CF!$1:$1048576,MATCH(H$37,CF!$3:$3,0),FALSE) -> -21.3 | I43: =VLOOKUP($A43,CF!$1:$1048576,MATCH(I$37,CF!$3:$3,0),FALSE) -> -21.3 | K43: Store Count
A44: OCF | B44: Australia Stores | D44: Operating cashflow | F44: =VLOOKUP($A44,CF!$1:$1048576,MATCH(F$37,CF!$3:$3,0),FALSE) -> 598.828 | G44: =VLOOKUP($A44,CF!$1:$1048576,MATCH(G$37,CF!$3:$3,0),FALSE) -> 740.67853 | H44: =VLOOKUP($A44,CF!$1:$1048576,MATCH(H$37,CF!$3:$3,0),FALSE) -> 946.34651 | I44: =VLOOKUP($A44,CF!$1:$1048576,MATCH(I$37,CF!$3:$3,0),FALSE) -> 1085.6314 | K44: Australia | L44: =VLOOKUP($B44,Model!$1:$1048576,MATCH(L$51,Model!$3:$3,0),FALSE) -> 567 | M44: =VLOOKUP($B44,Model!$1:$1048576,MATCH(M$51,Model!$3:$3,0),FALSE) -> 569 | N44: =VLOOKUP($B44,Model!$1:$1048576,MATCH(N$51,Model!$3:$3,0),FALSE) -> 587 | O44: =VLOOKUP($B44,Model!$1:$1048576,MATCH(O$51,Model!$3:$3,0),FALSE) -> 605 | P44: =VLOOKUP($B44,Model!$1:$1048576,MATCH(P$51,Model!$3:$3,0),FALSE) -> 623
A45: Capex | B45: NZ Stores | D45: Net capex | F45: =VLOOKUP($A45,CF!$1:$1048576,MATCH(F$37,CF!$3:$3,0),FALSE) -> -52.562 | G45: =VLOOKUP($A45,CF!$1:$1048576,MATCH(G$37,CF!$3:$3,0),FALSE) -> -60 | H45: =VLOOKUP($A45,CF!$1:$1048576,MATCH(H$37,CF!$3:$3,0),FALSE) -> -65 | I45: =VLOOKUP($A45,CF!$1:$1048576,MATCH(I$37,CF!$3:$3,0),FALSE) -> -70 | K45: New Zealand | L45: =VLOOKUP($B45,Model!$1:$1048576,MATCH(L$51,Model!$3:$3,0),FALSE) -> 50 | M45: =VLOOKUP($B45,Model!$1:$1048576,MATCH(M$51,Model!$3:$3,0),FALSE) -> 61 | N45: =VLOOKUP($B45,Model!$1:$1048576,MATCH(N$51,Model!$3:$3,0),FALSE) -> 76 | O45: =VLOOKUP($B45,Model!$1:$1048576,MATCH(O$51,Model!$3:$3,0),FALSE) -> 86 | P45: =VLOOKUP($B45,Model!$1:$1048576,MATCH(P$51,Model!$3:$3,0),FALSE) -> 96
A46: Acquisitions | B46: Ireland Stores | D46: Acquisitions | F46: =VLOOKUP($A46,CF!$1:$1048576,MATCH(F$37,CF!$3:$3,0),FALSE) -> -8.988 | G46: =VLOOKUP($A46,CF!$1:$1048576,MATCH(G$37,CF!$3:$3,0),FALSE) -> 0 | H46: =VLOOKUP($A46,CF!$1:$1048576,MATCH(H$37,CF!$3:$3,0),FALSE) -> 0 | I46: =VLOOKUP($A46,CF!$1:$1048576,MATCH(I$37,CF!$3:$3,0),FALSE) -> 0 | K46: Ireland | L46: =VLOOKUP($B46,Model!$1:$1048576,MATCH(L$51,Model!$3:$3,0),FALSE) -> 10 | M46: =VLOOKUP($B46,Model!$1:$1048576,MATCH(M$51,Model!$3:$3,0),FALSE) -> 14 | N46: =VLOOKUP($B46,Model!$1:$1048576,MATCH(N$51,Model!$3:$3,0),FALSE) -> 19 | O46: =VLOOKUP($B46,Model!$1:$1048576,MATCH(O$51,Model!$3:$3,0),FALSE) -> 24 | P46: =VLOOKUP($B46,Model!$1:$1048576,MATCH(P$51,Model!$3:$3,0),FALSE) -> 30
A47: Proceeds from business sales | B47: China Stores | D47: Proceeds from business sales | F47: =VLOOKUP($A47,CF!$1:$1048576,MATCH(F$37,CF!$3:$3,0),FALSE) -> 55.756 | G47: =VLOOKUP($A47,CF!$1:$1048576,MATCH(G$37,CF!$3:$3,0),FALSE) -> 0 | H47: =VLOOKUP($A47,CF!$1:$1048576,MATCH(H$37,CF!$3:$3,0),FALSE) -> 0 | I47: =VLOOKUP($A47,CF!$1:$1048576,MATCH(I$37,CF!$3:$3,0),FALSE) -> 0 | K47: China | L47: =VLOOKUP($B47,Model!$1:$1048576,MATCH(L$51,Model!$3:$3,0),FALSE) -> 10 | M47: =VLOOKUP($B47,Model!$1:$1048576,MATCH(M$51,Model!$3:$3,0),FALSE) -> 9 | N47: =VLOOKUP($B47,Model!$1:$1048576,MATCH(N$51,Model!$3:$3,0),FALSE) -> 9 | O47: =VLOOKUP($B47,Model!$1:$1048576,MATCH(O$51,Model!$3:$3,0),FALSE) -> 0 | P47: =VLOOKUP($B47,Model!$1:$1048576,MATCH(P$51,Model!$3:$3,0),FALSE) -> 0
A48: Net lease payments | B48: Dubai Stores | D48: Net Lease repayments | F48: =VLOOKUP($A48,CF!$1:$1048576,MATCH(F$37,CF!$3:$3,0),FALSE) -> -12.123 | G48: =VLOOKUP($A48,CF!$1:$1048576,MATCH(G$37,CF!$3:$3,0),FALSE) -> -12.860453 | H48: =VLOOKUP($A48,CF!$1:$1048576,MATCH(H$37,CF!$3:$3,0),FALSE) -> -13.346092 | I48: =VLOOKUP($A48,CF!$1:$1048576,MATCH(I$37,CF!$3:$3,0),FALSE) -> -14.011598 | K48: Dubai | L48: =VLOOKUP($B48,Model!$1:$1048576,MATCH(L$51,Model!$3:$3,0),FALSE) -> 0 | M48: =VLOOKUP($B48,Model!$1:$1048576,MATCH(M$51,Model!$3:$3,0),FALSE) -> 2 | N48: =VLOOKUP($B48,Model!$1:$1048576,MATCH(N$51,Model!$3:$3,0),FALSE) -> 5 | O48: =VLOOKUP($B48,Model!$1:$1048576,MATCH(O$51,Model!$3:$3,0),FALSE) -> 8 | P48: =VLOOKUP($B48,Model!$1:$1048576,MATCH(P$51,Model!$3:$3,0),FALSE) -> 11
A49: Net loans provided | B49: Other Stores | D49: Net loans provided | F49: =VLOOKUP($A49,CF!$1:$1048576,MATCH(F$37,CF!$3:$3,0),FALSE) -> -11.151 | G49: =VLOOKUP($A49,CF!$1:$1048576,MATCH(G$37,CF!$3:$3,0),FALSE) -> -11.151 | H49: =VLOOKUP($A49,CF!$1:$1048576,MATCH(H$37,CF!$3:$3,0),FALSE) -> -11.151 | I49: =VLOOKUP($A49,CF!$1:$1048576,MATCH(I$37,CF!$3:$3,0),FALSE) -> -11.151 | K49: Other | L49: =VLOOKUP($B49,Model!$1:$1048576,MATCH(L$51,Model!$3:$3,0),FALSE) -> 2 | M49: =VLOOKUP($B49,Model!$1:$1048576,MATCH(M$51,Model!$3:$3,0),FALSE) -> 19 | N49: =VLOOKUP($B49,Model!$1:$1048576,MATCH(N$51,Model!$3:$3,0),FALSE) -> 19 | O49: =VLOOKUP($B49,Model!$1:$1048576,MATCH(O$51,Model!$3:$3,0),FALSE) -> 19 | P49: =VLOOKUP($B49,Model!$1:$1048576,MATCH(P$51,Model!$3:$3,0),FALSE) -> 19
B50: Total Stores | D50: FCF | F50: =SUM(F44:F49) -> 569.76 | G50: =SUM(G44:G49) -> 656.66708 | H50: =SUM(H44:H49) -> 856.84942 | I50: =SUM(I44:I49) -> 990.46878 | K50: Total Stores | L50: =VLOOKUP($B50,Model!$1:$1048576,MATCH(L$51,Model!$3:$3,0),FALSE) -> 639 | M50: =VLOOKUP($B50,Model!$1:$1048576,MATCH(M$51,Model!$3:$3,0),FALSE) -> 674 | N50: =VLOOKUP($B50,Model!$1:$1048576,MATCH(N$51,Model!$3:$3,0),FALSE) -> 715 | O50: =VLOOKUP($B50,Model!$1:$1048576,MATCH(O$51,Model!$3:$3,0),FALSE) -> 742 | P50: =VLOOKUP($B50,Model!$1:$1048576,MATCH(P$51,Model!$3:$3,0),FALSE) -> 779
A51: Dividends | D51: Dividends paid | F51: =VLOOKUP($A51,CF!$1:$1048576,MATCH(F$37,CF!$3:$3,0),FALSE) -> -486.036 | G51: =VLOOKUP($A51,CF!$1:$1048576,MATCH(G$37,CF!$3:$3,0),FALSE) -> -532.89521 | H51: =VLOOKUP($A51,CF!$1:$1048576,MATCH(H$37,CF!$3:$3,0),FALSE) -> -641.69253 | I51: =VLOOKUP($A51,CF!$1:$1048576,MATCH(I$37,CF!$3:$3,0),FALSE) -> -744.52773 | K51: Group Key Metrics | L51: =E$13 -> FY24 | M51: =F$13 -> FY25 | N51: =G$13 -> FY26E | O51: =H$13 -> FY27E | P51: =I$13 -> FY28E
A52: Other FCF | B52: Network Sales Growth | D52: Other financing cashflows | F52: =VLOOKUP($A52,CF!$1:$1048576,MATCH(F$37,CF!$3:$3,0),FALSE) -> 0.808 | G52: =VLOOKUP($A52,CF!$1:$1048576,MATCH(G$37,CF!$3:$3,0),FALSE) -> 0 | H52: =VLOOKUP($A52,CF!$1:$1048576,MATCH(H$37,CF!$3:$3,0),FALSE) -> 0 | I52: =VLOOKUP($A52,CF!$1:$1048576,MATCH(I$37,CF!$3:$3,0),FALSE) -> 0 | K52: Network Sales Growth | M52: =VLOOKUP($B52,PL!$1:$1048576,MATCH(M$51,PL!$3:$3,0),FALSE) -> 0.14070363 | N52: =VLOOKUP($B52,PL!$1:$1048576,MATCH(N$51,PL!$3:$3,0),FALSE) -> 0.14839558 | O52: =VLOOKUP($B52,PL!$1:$1048576,MATCH(O$51,PL!$3:$3,0),FALSE) -> 0.11334653 | P52: =VLOOKUP($B52,PL!$1:$1048576,MATCH(P$51,PL!$3:$3,0),FALSE) -> 0.0842178
B53: Revenue Growth | D53: FCF post financing | F53: =SUM(F50:F52) -> 84.532 | G53: =SUM(G50:G52) -> 123.77186 | H53: =SUM(H50:H52) -> 215.15689 | I53: =SUM(I50:I52) -> 245.94105 | K53: Revenue Growth | N53: =VLOOKUP($B53,PL!$1:$1048576,MATCH(N$51,PL!$3:$3,0),FALSE) -> 0.13944769 | O53: =VLOOKUP($B53,PL!$1:$1048576,MATCH(O$51,PL!$3:$3,0),FALSE) -> 0.10577885 | P53: =VLOOKUP($B53,PL!$1:$1048576,MATCH(P$51,PL!$3:$3,0),FALSE) -> 0.074492467
A54: Change in ND | B54: EBIT Growth | D54: Change in net debt | F54: =VLOOKUP($A54,BS!$1:$1048576,MATCH(F$37,BS!$3:$3,0),FALSE) -> 0 | G54: =VLOOKUP($A54,BS!$1:$1048576,MATCH(G$37,BS!$3:$3,0),FALSE) -> -123.77186 | H54: =VLOOKUP($A54,BS!$1:$1048576,MATCH(H$37,BS!$3:$3,0),FALSE) -> -215.15689 | I54: =VLOOKUP($A54,BS!$1:$1048576,MATCH(I$37,BS!$3:$3,0),FALSE) -> -245.94105 | K54: EBIT Growth | N54: =VLOOKUP($B54,PL!$1:$1048576,MATCH(N$51,PL!$3:$3,0),FALSE) -> 0.25439223 | O54: =VLOOKUP($B54,PL!$1:$1048576,MATCH(O$51,PL!$3:$3,0),FALSE) -> 0.19384326 | P54: =VLOOKUP($B54,PL!$1:$1048576,MATCH(P$51,PL!$3:$3,0),FALSE) -> 0.15154178
B55: NPAT Growth | D55: Valuation | E55: FY24 | F55: FY25 | G55: FY26E | H55: FY27E | I55: FY28E | K55: NPAT Growth | N55: =VLOOKUP($B55,PL!$1:$1048576,MATCH(N$51,PL!$3:$3,0),FALSE) -> 0.22825943 | O55: =VLOOKUP($B55,PL!$1:$1048576,MATCH(O$51,PL!$3:$3,0),FALSE) -> 0.20416269 | P55: =VLOOKUP($B55,PL!$1:$1048576,MATCH(P$51,PL!$3:$3,0),FALSE) -> 0.16025618
B56: EPS Growth | D56: P/E | F56: =$F$9/F34 -> 54.366952 | G56: =$F$9/G34 -> 44.263411 | H56: =$F$9/H34 -> 36.758664 | I56: =$F$9/I34 -> 31.681506 | K56: EPS Growth | N56: =VLOOKUP($B56,PL!$1:$1048576,MATCH(N$51,PL!$3:$3,0),FALSE) -> 0.22825943 | O56: =VLOOKUP($B56,PL!$1:$1048576,MATCH(O$51,PL!$3:$3,0),FALSE) -> 0.20416269 | P56: =VLOOKUP($B56,PL!$1:$1048576,MATCH(P$51,PL!$3:$3,0),FALSE) -> 0.16025618
B57: EBIT Margin | D57: Div Yield | G57: =G35/$F$9 -> 0.015814416 | H57: =H35/$F$9 -> 0.01904313 | I57: =I35/$F$9 -> 0.022094909 | K57: EBIT to Network Sales Margin | M57: =VLOOKUP($B57,Model!$1:$1048576,MATCH(M$51,Model!$3:$3,0),FALSE) -> 0.087977796 | N57: =VLOOKUP($B57,Model!$1:$1048576,MATCH(N$51,Model!$3:$3,0),FALSE) -> 0.096098127 | O57: =VLOOKUP($B57,Model!$1:$1048576,MATCH(O$51,Model!$3:$3,0),FALSE) -> 0.10304618 | P57: =VLOOKUP($B57,Model!$1:$1048576,MATCH(P$51,Model!$3:$3,0),FALSE) -> 0.10944478
A58: Payout Ratio | D58: Payout Ratio | G58: =G35/G34 -> 0.7 | H58: =H35/H34 -> 0.7 | I58: =I35/I34 -> 0.7 | K58: RoE | M58: =F32/M37 -> 0.13298796 | N58: =G32/N37 -> 0.1556908 | O58: =H32/O37 -> 0.17784254 | P58: =I32/P37 -> 0.19457022
A59: Shares EOP | D59: FCF Yield | F59: =F63/$F$9 -> 0 | G59: =G63/$F$9 -> 0 | H59: =H63/$F$9 -> 0 | I59: =I63/$F$9 -> 0 | K59: Net debt / EBIT | M59: =M38/F27 -> 0.83258911 | N59: =N38/G27 -> 0.55451746 | O59: =O38/H27 -> 0.30544531 | P59: =P38/I27 -> 0.10738228
K60: Net debt / EBITDA | M60: =M38/F25 -> 0.77662468 | N60: =N38/G25 -> 0.52297211 | O60: =O38/H25 -> 0.29005729 | P60: =P38/I25 -> 0.1024275

Sheet Australia Stores
J2: Australian Franchise Network stores, comprising Chemist Warehouse branded stores, My Chemist branded stores, and Pipeline Stores
C3: Australia Store Count Tracker
C5: Total Stores by state | D5: FY24 | E5: 1H25 | F5: FY25
C6: VIC | D6: =D28+D39+D50+D61+D72+D83 -> 313 | E6: =E28+E39+E50+E61+E72+E83 -> 321 | F6: =F28+F39+F50+F61+F72+F83 -> 323 | G6: =F6-E6 -> 2 | J6: 31. As at 30 June 2024, there were 567 Chemist Warehouse Australian Franchise Network stores, comprising 517 Chemist Warehouse branded stores, 21 My Chemist branded stores, and 29 Pipeline Stores, and 313 Sigma franchise stores, comprising 209 Amcal branded stores, and 104 Discount Drug Stores branded stores. In September 2022, Sigma began a retail brand consolidation process to simplify its retail strategy by seeking to convert Guardian and PharmaSave branded stores to Amcal and Discount Drug Stores. Sigma closed the Guardian brand with effect from 31 January 2024. Since September 2022, Sigma no longer offers the PharmaSave brand to new members. As at 30 June 2024, there were 37 PharmaSave branded stores, which are not included in the Merged Group’s Retail Network figures presented. Sigma continues to provide support to PharmaSave stores in accordance with existing agreements
C7: NSW | D7: =D29+D40+D51+D62+D73+D84 -> 203 | E7: =E29+E40+E51+E62+E73+E84 -> 199 | F7: =F29+F40+F51+F62+F73+F84 -> 196 | G7: =F7-E7 -> -3
C8: QLD | D8: =D30+D41+D52+D63+D74+D85 -> 192 | E8: =E30+E41+E52+E63+E74+E85 -> 188 | F8: =F30+F41+F52+F63+F74+F85 -> 184 | G8: =F8-E8 -> -4
C9: WA | D9: =D31+D42+D53+D64+D75+D86 -> 83 | E9: =E31+E42+E53+E64+E75+E86 -> 87 | F9: =F31+F42+F53+F64+F75+F86 -> 89 | G9: =F9-E9 -> 2 | J9: Rebranding My Chemist into Amcal and DDS (FY25 result)
C10: SA | D10: =D32+D43+D54+D65+D76+D87 -> 45 | E10: =E32+E43+E54+E65+E76+E87 -> 46 | F10: =F32+F43+F54+F65+F76+F87 -> 46 | G10: =F10-E10 -> 0
C11: TAS | D11: =D33+D44+D55+D66+D77+D88 -> 34 | E11: =E33+E44+E55+E66+E77+E88 -> 32 | F11: =F33+F44+F55+F66+F77+F88 -> 33 | G11: =F11-E11 -> 1
C12: ACT | D12: =D34+D45+D56+D67+D78+D89 -> 15 | E12: =E34+E45+E56+E67+E78+E89 -> 15 | F12: =F34+F45+F56+F67+F78+F89 -> 14 | G12: =F12-E12 -> -1
C13: NT | D13: =D35+D46+D57+D68+D79+D90 -> 11 | E13: =E35+E46+E57+E68+E79+E90 -> 10 | F13: =F35+F46+F57+F68+F79+F90 -> 9 | G13: =F13-E13 -> -1
C14: Total | D14: =SUM(D6:D13) -> 896 | E14: =SUM(E6:E13) -> 898 | F14: =SUM(F6:F13) -> 894 | G14: =F14-E14 -> -4
C16: CW + MyChemist + Pipeline Stores by state
C17: VIC | D17: =D28+D61+D83 -> 239 | E17: =E28+E61+E83 -> 245 | F17: =F28+F61+F83 -> 237 | G17: =F17-E17 -> -8 | H17: Driven by 11 MyChemist rebranding to Amcal and DDS (amcal +9 and DDS +1)
C18: NSW | D18: =D29+D62+D84 -> 129 | E18: =E29+E62+E84 -> 129 | F18: =F29+F62+F84 -> 129 | G18: =F18-E18 -> 0 | H18: 1 opening offset by one MyChemist decline
C19: QLD | D19: =D30+D63+D85 -> 96 | E19: =E30+E63+E85 -> 97 | F19: =F30+F63+F85 -> 97 | G19: =F19-E19 -> 0
C20: WA | D20: =D31+D64+D86 -> 40 | E20: =E31+E64+E86 -> 41 | F20: =F31+F64+F86 -> 43 | G20: =F20-E20 -> 2 | M20: Chemist Warehouse | N20: =F36 -> 537
C21: SA | D21: =D32+D65+D87 -> 30 | E21: =E32+E65+E87 -> 30 | F21: =F32+F65+F87 -> 31 | G21: =F21-E21 -> 1 | M21: Amcal | N21: =F47 -> 216
C22: TAS | D22: =D33+D66+D88 -> 18 | E22: =E33+E66+E88 -> 18 | F22: =F33+F66+F88 -> 18 | G22: =F22-E22 -> 0 | M22: Discount Drug Stores | N22: =F58 -> 89
C23: ACT | D23: =D34+D67+D89 -> 6 | E23: =E34+E67+E89 -> 6 | F23: =F34+F67+F89 -> 5 | G23: =F23-E23 -> -1 | M23: MyChemist | N23: =F69 -> 13
C24: NT | D24: =D35+D68+D90 -> 9 | E24: =E35+E68+E90 -> 9 | F24: =F35+F68+F90 -> 9 | G24: =F24-E24 -> 0 | M24: Ultra Beauty Stores | N24: =F80 -> 20
C25: Total | D25: =D36+D69+D91 -> 567 | E25: =E36+E69+E91 -> 575 | F25: =F36+F69+F91 -> 569 | G25: =F25-E25 -> -6 | M25: Pipeline | N25: =F91 -> 19
C27: CW Stores by state
C28: VIC | D28: 206 | E28: 209 | F28: 213 | G28: =F28-E28 -> 4
C29: NSW | D29: 120 | E29: 122 | F29: 123 | G29: =F29-E29 -> 1 | I29: Total stores | J29: 674
C30: QLD | D30: 90 | E30: 94 | F30: 96 | G30: =F30-E30 -> 2 | I30: NZ | J30: 61
C31: WA | D31: 40 | E31: 41 | F31: 43 | G31: =F31-E31 -> 2 | I31: Ireland | J31: 14
C32: SA | D32: 29 | E32: 29 | F32: 30 | G32: =F32-E32 -> 1 | I32: Dubai | J32: 2
C33: TAS | D33: 18 | E33: 18 | F33: 18 | G33: =F33-E33 -> 0 | I33: China | J33: 9
C34: ACT | D34: 5 | E34: 5 | F34: 5 | G34: =F34-E34 -> 0
C35: NT | D35: 9 | E35: 9 | F35: 9 | G35: =F35-E35 -> 0 | I35: Implied Aus stores | J35: =J29-SUM(J30:J33) -> 588
C36: Total | D36: =SUM(D28:D35) -> 517 | E36: =SUM(E28:E35) -> 527 | F36: =SUM(F28:F35) -> 537 | G36: =F36-E36 -> 10 | I36: CW | J36: =F36 -> 537
I37: Pipeline | J37: =F91 -> 19
C38: Amcal Stores by state | I38: MyChemist | J38: =F69 -> 13
C39: VIC | D39: 61 | E39: 61 | F39: 70 | G39: =F39-E39 -> 9 | I39: Implied other | J39: =J35-J36-J37-J38 -> 19
C40: NSW | D40: 42 | E40: 40 | F40: 39 | G40: =F40-E40 -> -1
C41: QLD | D41: 43 | E41: 41 | F41: 41 | G41: =F41-E41 -> 0
C42: WA | D42: 31 | E42: 35 | F42: 36 | G42: =F42-E42 -> 1
C43: SA | D43: 12 | E43: 13 | F43: 13 | G43: =F43-E43 -> 0
C44: TAS | D44: 15 | E44: 13 | F44: 14 | G44: =F44-E44 -> 1
C45: ACT | D45: 3 | E45: 3 | F45: 3 | G45: =F45-E45 -> 0 | J45: 35 new Chemist Warehouse stores were opened during the year, and we had the full year benefit of the new stores, which opened partway through FY 2024
C46: NT | D46: 2 | E46: 1 | F46: 0 | G46: =F46-E46 -> -1 | J46: This implies 19 in Australia given 16 were opened internationally
C47: Total | D47: =SUM(D39:D46) -> 209 | E47: =SUM(E39:E46) -> 207 | F47: =SUM(F39:F46) -> 216 | G47: =F47-E47 -> 9
C49: Discount Drug Stores by state
C50: VIC | D50: 5 | E50: 4 | F50: 5 | G50: =F50-E50 -> 1
C51: NSW | D51: 27 | E51: 25 | F51: 22 | G51: =F51-E51 -> -3
C52: QLD | D52: 52 | E52: 49 | F52: 45 | G52: =F52-E52 -> -4
C53: WA | D53: 12 | E53: 11 | F53: 10 | G53: =F53-E53 -> -1
C54: SA | D54: 2 | E54: 2 | F54: 1 | G54: =F54-E54 -> -1
C55: TAS | D55: 1 | E55: 1 | F55: 1 | G55: =F55-E55 -> 0
C56: ACT | D56: 5 | E56: 5 | F56: 5 | G56: =F56-E56 -> 0
C57: NT | D57: 0 | E57: 0 | F57: 0 | G57: =F57-E57 -> 0
C58: Total | D58: =SUM(D50:D57) -> 104 | E58: =SUM(E50:E57) -> 97 | F58: =SUM(F50:F57) -> 89 | G58: =F58-E58 -> -8
C60: MyChemist Stores by state
C61: VIC | D61: 20 | E61: 24 | F61: 13 | G61: =F61-E61 -> -11
C62: NSW | D62: 1 | E62: 1 | G62: =F62-E62 -> -1
C63: QLD | G63: =F63-E63 -> 0
C64: WA | G64: =F64-E64 -> 0
C65: SA | G65: =F65-E65 -> 0
C66: TAS | G66: =F66-E66 -> 0
C67: ACT | G67: =F67-E67 -> 0
C68: NT | G68: =F68-E68 -> 0
C69: Total | D69: =SUM(D61:D68) -> 21 | E69: =SUM(E61:E68) -> 25 | F69: =SUM(F61:F68) -> 13 | G69: =F69-E69 -> -12
C71: Ultra Stores by state
C72: VIC | D72: 8 | E72: 11 | F72: 11 | G72: =F72-E72 -> 0
C73: NSW | D73: 5 | E73: 5 | F73: 6 | G73: =F73-E73 -> 1
C74: QLD | D74: 1 | E74: 1 | F74: 1 | G74: =F74-E74 -> 0
C75: WA | G75: =F75-E75 -> 0
C76: SA | D76: 1 | E76: 1 | F76: 1 | G76: =F76-E76 -> 0
C77: TAS | G77: =F77-E77 -> 0
C78: ACT | D78: 1 | E78: 1 | F78: 1 | G78: =F78-E78 -> 0
C79: NT | G79: =F79-E79 -> 0
C80: Total | D80: =SUM(D72:D79) -> 16 | E80: =SUM(E72:E79) -> 19 | F80: =SUM(F72:F79) -> 20 | G80: =F80-E80 -> 1
C82: Pipeline Stores by state
C83: VIC | D83: 13 | E83: 12 | F83: 11 | G83: =F83-E83 -> -1
C84: NSW | D84: 8 | E84: 6 | F84: 6 | G84: =F84-E84 -> 0
C85: QLD | D85: 6 | E85: 3 | F85: 1 | G85: =F85-E85 -> -2
C86: WA | G86: =F86-E86 -> 0
C87: SA | D87: 1 | E87: 1 | F87: 1 | G87: =F87-E87 -> 0
C88: TAS | G88: =F88-E88 -> 0
C89: ACT | D89: 1 | E89: 1 | G89: =F89-E89 -> -1
C90: NT | G90: =F90-E90 -> 0
C91: Total | D91: =SUM(D83:D90) -> 29 | E91: =SUM(E83:E90) -> 23 | F91: =SUM(F83:F90) -> 19 | G91: =F91-E91 -> -4
C93: Total Chemist Warehouse Australian Network Franchise Stores | D93: =D91+D69+D36 -> 567 | E93: =E91+E69+E36 -> 575 | F93: =F91+F69+F36 -> 569 | G93: =F93-E93 -> -6

Sheet Model
B1: Sigma Healthcare (SIG.AX) | W1: Pro-forma
B2: A$M | W2: Prospectus
C3: FY04 | D3: FY05 | E3: FY06 | F3: FY07 | G3: FY08 | H3: FY09 | I3: FY10 | J3: FY11 | K3: FY12 | L3: FY13 | M3: FY14 | N3: FY15 | O3: FY16 | P3: FY17 | Q3: FY18 | R3: FY19 | S3: FY20 | T3: FY21 | U3: FY22 | V3: FY23 | W3: FY24 | X3: FY25 | Y3: FY26E | Z3: FY27E | AA3: FY28E | AB3: FY29E | AC3: FY30E | AE3: 1H24 | AF3: 2H24 | AG3: 1H25 | AH3: 2H25 | AI3: 1H26E | AJ3: 2H26E
B5: Summary Network Performance
B6: Network Sales
A7: Australia Sales | B7: Australia | C7: =C19 -> 0 | D7: =D19 -> 0 | E7: =E19 -> 0 | F7: =F19 -> 0 | G7: =G19 -> 0 | H7: =H19 -> 0 | I7: =I19 -> 0 | J7: =J19 -> 0 | ... AC7: =AC19 -> 13399.861 | AE7: =AE19 -> 4011.7 | AF7: =AF19 -> 3898.2 | AG7: =AG19 -> 4505.9 | AH7: =AH19 -> 4463 | AI7: =AI19 -> 5178.9056 | AJ7: =AJ19 -> 4934.5359
A8: NZ Sales | B8: New Zealand | Q8: =Q86 -> 0 | R8: =R86 -> 80 | S8: =S86 -> 171 | T8: =T86 -> 306 | U8: =U86 -> 497 | V8: =V86 -> 652 | W8: =W86 -> 886 | X8: =X86 -> 1050 | ... AC8: =AC86 -> 2361.9021
A9: Ireland Sales | B9: Ireland | R9: =R96 -> 0 | S9: =S96 -> 0 | T9: =T96 -> 7.6347407 | U9: =U96 -> 29.946093 | V9: =V96 -> 59.297278 | W9: =W96 -> 105.69921 | X9: =X96 -> 167.47139 | Y9: =Y96 -> 266.16179 | ... AC9: =AC96 -> 645.17317
A10: China Sales | B10: China | T10: 50 | U10: =U13-SUM(U7:U9) -> 84.953907 | V10: =V13-SUM(V7:V9) -> 108.70272 | W10: =W13-SUM(W7:W9) -> 100.30079 | X10: =X13-SUM(X7:X9)-X11-X12 -> 72.128605 | Y10: 80 | Z10: 80 | AA10: 80 | AB10: 80 | AC10: 80
A11: Dubai Sales | B11: Dubai | X11: 10 | Y11: =Y37*7 -> 35 | Z11: =Z37*7 -> 56 | AA11: =AA37*7 -> 77 | AB11: =AB37*7 -> 105 | AC11: =AC37*7 -> 140
A12: Other Sales | B12: Other
A13: Total network sales | B13: Total | C13: 158 | D13: 238 | E13: 362 | F13: 511 | G13: 701 | H13: 951 | I13: 1231 | J13: 1518 | K13: 1847 | L13: 2183 | M13: 2542 | N13: 3133 | O13: 3825 | P13: 4388 | Q13: 4857 | R13: 5355 | S13: 5756 | T13: 5893 | U13: 6825 | V13: 7888 | W13: 9001.9 | X13: 10268.5 | Y13: =SUM(Y7:Y12) -> 11792.3 | Z13: =SUM(Z7:Z12) -> 13128.916 | AA13: =SUM(AA7:AA12) -> 14234.605 | AB13: =SUM(AB7:AB12) -> 15394.431 | AC13: =SUM(AC7:AC12) -> 16626.936 | AE13: 4559.4 | AF13: =W13-AE13 -> 4442.5 | AG13: 5154.2 | AH13: =X13-AG13 -> 5114.3 | AI13: =AI19+AI25 -> 5995.6835 | AJ13: =Y13-AI13 -> 5796.6164
A14: Total network sales growth | B14: Growth % | D14: =D13/C13-1 -> 0.50632911 | E14: =E13/D13-1 -> 0.5210084 | F14: =F13/E13-1 -> 0.41160221 | G14: =G13/F13-1 -> 0.37181996 | H14: =H13/G13-1 -> 0.35663338 | I14: =I13/H13-1 -> 0.29442692 | J14: =J13/I13-1 -> 0.23314379 | K14: =K13/J13-1 -> 0.21673254 | ... AC14: =AC13/AB13-1 -> 0.080061743 | AG14: =AG13/AE13-1 -> 0.13045576 | AH14: =AH13/AF13-1 -> 0.15122116 | AI14: =AI13/AG13-1 -> 0.16326172 | AJ14: =AJ13/AH13-1 -> 0.13341345
B15: Total LFL Sales Growth % | W15: 0.102 | X15: 0.109 | Y15: =Y7/Y13*Y21+Y25/Y13*Y27 -> 0.10857631 | Z15: =Z7/Z13*Z21+Z25/Z13*Z27 -> 0.08 | AA15: =AA7/AA13*AA21+AA25/AA13*AA27 -> 0.055085146 | AB15: =AB7/AB13*AB21+AB25/AB13*AB27 -> 0.055463932 | AC15: =AC7/AC13*AC21+AC25/AC13*AC27 -> 0.055822616 | AE15: 0.089 | AF15: =(W15-0.5*AE15)/0.5 -> 0.115 | AG15: 0.103 | AH15: =(X15-0.5*AG15)/0.5 -> 0.115 | AI15: =AI7/AI13*AI21+AI25/AI13*AI27 -> 0.12591317 | AJ15: =(Y15-0.5*AI15)/0.5 -> 0.091239449
B16: Store Growth % | W16: =W40 -> 0.059701493 | X16: =X40 -> 0.054773083 | Y16: =Y40 -> 0.060830861 | Z16: =Z40 -> 0.037762238 | AA16: =AA40 -> 0.049865229 | AB16: =AB40 -> 0.047496791 | AC16: =AC40 -> 0.046568627 | AG16: =AG40 -> 0.057877814 | AH16: =AH40 -> 0.054773083 | AI16: =AI40 -> 0.054711246 | AJ16: =AJ40 -> 0.060830861
B17: Other % | W17: =W14-SUM(W15:W16) -> -0.020486989 | X17: =X14-SUM(X15:X16) -> -0.023069454 | Y17: =Y14-SUM(Y15:Y16) -> -0.021011594 | Z17: =Z14-SUM(Z15:Z16) -> -0.0044157126 | AA17: =AA14-SUM(AA15:AA16) -> -0.020732574 | AB17: =AB14-SUM(AB15:AB16) -> -0.021481352 | AC17: =AC14-SUM(AC15:AC16) -> -0.022329501 | AG17: =AG14-SUM(AG15:AG16) -> -0.030422052 | AH17: =AH14-SUM(AH15:AH16) -> -0.018551924 | AI17: =AI14-SUM(AI15:AI16) -> -0.017362699 | AJ17: =AJ14-SUM(AJ15:AJ16) -> -0.018656855
F18: ='Australia Stores'!F28+'Australia Stores'!F61 -> 226
B19: Australia Network sales | U19: 6213.1 | V19: 7068 | W19: 7909.9 | X19: 8968.9 | Y19: =X19*(1+Y20) -> 10113.441 | Z19: =Y19*(1+Z20) -> 11091.441 | AA19: =Z19*(1+AA20) -> 11821.77 | AB19: =AA19*(1+AB20) -> 12590.627 | AC19: =AB19*(1+AC20) -> 13399.861 | AE19: 4011.7 | AF19: =W19-AE19 -> 3898.2 | AG19: 4505.9 | AH19: =X19-AG19 -> 4463 | AI19: =AG19*(1+AI20) -> 5178.9056 | AJ19: =Y19-AI19 -> 4934.5359
B20: Growth % | V20: =V19/U19-1 -> 0.13759637 | W20: =W19/V19-1 -> 0.11911432 | X20: =X19/W19-1 -> 0.13388286 | Y20: =Y21+Y23+Y22 -> 0.12761224 | Z20: =Z21+Z23+Z22 -> 0.09670297 | AA20: =AA21+AA23+AA22 -> 0.065846154 | AB20: =AB21+AB23+AB22 -> 0.065037383 | AC20: =AC21+AC23+AC22 -> 0.064272727 | AG20: =AG19/AE19-1 -> 0.12318967 | AH20: =AH19/AF19-1 -> 0.14488738 | AI20: =AI21+AI23+AI22 -> 0.14936097 | AJ20: =AJ19/AH19-1 -> 0.10565447
A21: Australia LFL | B21: Total LFL Sales Growth % | C21: =C14-C22 -> 0 | D21: =D14-D22 -> 0.16150153 | E21: =E14-E22 -> 0.34152122 | F21: =F14-F22 -> 0.23768917 | G21: =G14-G22 -> 0.01070885 | H21: =H14-H22 -> 0.20697352 | I21: =I14-I22 -> 0.12282929 | J21: =J14-J22 -> 0.066477119 | ... T21: =T14-T22 -> -0.018622992 | U21: 0.121 | V21: 0.118 | W21: 0.098 | X21: 0.113 | Y21: 0.11 | Z21: 0.08 | AA21: 0.05 | AB21: 0.05 | AC21: 0.05 | AE21: 0.087 | AF21: =(W21-0.5*AE21)/0.5 -> 0.109 | AG21: 0.104 | AH21: =(X21-0.5*AG21)/0.5 -> 0.122 | AI21: 0.13 | AJ21: =(Y21-0.5*AI21)/0.5 -> 0.09
B22: Store Growth % | D22: =D61 -> 0.34482759 | E22: =E61 -> 0.17948718 | F22: =F61 -> 0.17391304 | G22: =G61 -> 0.36111111 | H22: =H61 -> 0.14965986 | I22: =I61 -> 0.17159763 | J22: =J61 -> 0.16666667 | K22: =K61 -> 0.15151515 | ... V22: =V61 -> 0.035916824 | W22: =W43 -> 0.036429872 | X22: =X43 -> 0.033391916 | Y22: =Y43 -> 0.030612245 | Z22: =Z43 -> 0.02970297 | AA22: =AA43 -> 0.028846154 | AB22: =AB43 -> 0.028037383 | AC22: =AC43 -> 0.027272727 | AG22: =AG61 -> 0 | AH22: =AH43 -> 0.036906854 | AI22: =AI43 -> 0.029360967 | AJ22: =AJ43 -> 0.027118644
B23: Other % | V23: =V20-V21-V22 -> -0.016320455 | W23: =W20-W21-W22 -> -0.015315554 | X23: =X20-X21-X22 -> -0.01250906 | Y23: -0.013 | Z23: -0.013 | AA23: -0.013 | AB23: -0.013 | AC23: -0.013 | AG23: =AG20-AG21-AG22 -> 0.01918967 | AH23: =AH20-AH21-AH22 -> -0.01401947 | AI23: -0.01 | AJ23: =AJ20-AJ21-AJ22 -> -0.011464178
A25: International Sales | B25: Total International Network Sales | U25: =U13-U19 -> 611.9 | V25: =V13-V19 -> 820 | W25: =W13-W19 -> 1092 | X25: =X13-X19 -> 1299.6 | Y25: =SUM(Y8:Y12) -> 1678.8585 | Z25: =SUM(Z8:Z12) -> 2037.4749 | AA25: =SUM(AA8:AA12) -> 2412.8346 | AB25: =SUM(AB8:AB12) -> 2803.8042 | AC25: =SUM(AC8:AC12) -> 3227.0753 | AE25: =AE13-AE19 -> 547.7 | AF25: =AF13-AF19 -> 544.3 | AG25: =AG13-AG19 -> 648.3 | AH25: =AH13-AH19 -> 651.3 | AI25: =AG25*(1+AI26) -> 816.77796 | AJ25: =Y25-AI25 -> 862.08055
B26: Growth % | V26: =V25/U25-1 -> 0.34008825 | W26: =W25/V25-1 -> 0.33170732 | X26: =X25/W25-1 -> 0.19010989 | Y26: =Y25/X25-1 -> 0.29182711 | Z26: =Z25/Y25-1 -> 0.21360728 | AA26: =AA25/Z25-1 -> 0.18422789 | AB26: =AB25/AA25-1 -> 0.16203748 | AC26: =AC25/AB25-1 -> 0.15096313 | AG26: =AG25/AE25-1 -> 0.1836772 | AH26: =AH25/AF25-1 -> 0.19658277 | AI26: =SUM(AI27:AI29) -> 0.25987654 | AJ26: =AJ25/AH25-1 -> 0.32363051
A27: International LFL | B27: Total LFL Sales Growth % | U27: -0.065 | V27: 0.215 | W27: 0.144 | X27: 0.081 | Y27: =Y88 -> 0.1 | Z27: =Z88 -> 0.08 | AA27: =AA88 -> 0.08 | AB27: =AB88 -> 0.08 | AC27: =AC88 -> 0.08 | AE27: 0.106 | AF27: =(W27-0.5*AE27)/0.5 -> 0.182 | AG27: 0.09 | AH27: =(X27-0.5*AG27)/0.5 -> 0.072 | AI27: 0.1 | AJ27: =(Y27-0.5*AI27)/0.5 -> 0.1
B28: Store Growth % | R28: =R46 -> 0 | S28: =S46 -> 1.5 | T28: =T46 -> 1 | U28: =U46 -> 0.46666667 | V28: =V46 -> 0.22727273 | W28: =W46 -> 0.2962963 | X28: =X46 -> 0.22857143 | Y28: =Y46 -> 0.26744186 | ... AC28: =AC46 -> 0.12820513 | AG28: =AG46 -> 0 | AH28: =AH46 -> 0.19444444 | AI28: =AI46 -> 0.20987654 | AJ28: =AJ46 -> 0.26744186
B29: Other % | V29: =V26-V27-V28 -> -0.10218448 | W29: =W26-W27-W28 -> -0.10858898 | X29: =X26-X27-X28 -> -0.11946154 | Y29: =Y26-Y27-Y28 -> -0.07561475 | Z29: =Z26-Z27-Z28 -> 0.05103847 | AA29: =AA26-AA27-AA28 -> -0.056789063 | AB29: =AB26-AB27-AB28 -> -0.056648653 | AC29: =AC26-AC27-AC28 -> -0.057242001 | AG29: =AG26-AG27-AG28 -> 0.093677196 | AH29: =AH26-AH27-AH28 -> -0.069861678 | AI29: -0.05 | AJ29: =AJ26-AJ27-AJ28 -> -0.043811352
B31: Network Sales Modelling
B32: Group Store Count
A33: Australia Stores | B33: Australia | C33: =C60 -> 58 | D33: =D60 -> 78 | E33: =E60 -> 92 | F33: =F60 -> 108 | G33: =G60 -> 147 | H33: =H60 -> 169 | I33: =I60 -> 198 | J33: =J60 -> 231 | ... AC33: =AC60 -> 659 | AF33: =W33 -> 567 | AG33: =AG60 -> 575 | AH33: =X33 -> 569 | AI33: =AI60 -> 577 | AJ33: =Y33 -> 587
A34: NZ Stores | B34: New Zealand | J34: =J92 -> 0 | K34: =K92 -> 0 | L34: =L92 -> 0 | M34: =M92 -> 0 | N34: =N92 -> 0 | O34: =O92 -> 0 | P34: =P92 -> 0 | Q34: =Q92 -> 0 | ... AC34: =AC92 -> 116 | AF34: =W34 -> 50 | AG34: =AG92 -> 56 | AH34: =X34 -> 61 | AI34: =AI92 -> 70 | AJ34: =Y34 -> 76
A35: Ireland Stores | B35: Ireland | S35: =S102 -> 0 | T35: =T102 -> 2 | U35: =U102 -> 4 | V35: =V102 -> 6 | W35: =W102 -> 10 | X35: =X102 -> 14 | Y35: =Y102 -> 19 | Z35: =Z102 -> 24 | ... AC35: =AC102 -> 40 | AF35: =W35 -> 10 | AG35: =AG102 -> 12 | AH35: =X35 -> 14 | AI35: =AI102 -> 16 | AJ35: =Y35 -> 19
A36: China Stores | B36: China | S36: 1 | T36: 4 | U36: 5 | V36: 6 | W36: 10 | X36: 9 | Y36: =X36 -> 9 | Z36: 0 | AA36: =Z36 -> 0 | AB36: =AA36 -> 0 | AC36: =AB36 -> 0 | AF36: =W36 -> 10 | AG36: 11 | AH36: =X36 -> 9 | AI36: 9 | AJ36: =Y36 -> 9
A37: Dubai Stores | B37: Dubai | X37: 2 | Y37: 5 | Z37: 8 | AA37: 11 | AB37: 15 | AC37: 20 | AG37: 2 | AH37: =X37 -> 2 | AI37: 3 | AJ37: =Y37 -> 5
A38: Other Stores | B38: Other | R38: =R39-SUM(R33:R36) -> 0 | S38: =S39-SUM(S33:S36) -> 0 | T38: =T39-SUM(T33:T36) -> -3 | U38: =U39-SUM(U33:U36) -> 0 | V38: =V39-SUM(V33:V36) -> 1 | W38: =W39-SUM(W33:W36) -> 2 | X38: =X39-SUM(X33:X37) -> 19 | Y38: =X38 -> 19 | Z38: =Y38 -> 19 | AA38: =Z38 -> 19 | AB38: =AA38 -> 19 | AC38: =AB38 -> 19 | AF38: =AF39-SUM(AF33:AF36) -> 2 | AG38: =AG39-SUM(AG33:AG36) -> 4 | AH38: =AH39-SUM(AH33:AH36) -> 21 | AI38: 19 | AJ38: =Y38 -> 19
A39: Total Stores | B39: Total Stores | C39: 58 | D39: 78 | E39: 92 | F39: 108 | G39: 147 | H39: 169 | I39: 198 | J39: 231 | K39: 266 | L39: 297 | M39: 319 | N39: 341 | O39: 369 | P39: 412 | Q39: 446 | R39: 476 | S39: 510 | T39: 543 | U39: 573 | V39: 603 | W39: 639 | X39: 674 | Y39: =SUM(Y33:Y38) -> 715 | Z39: =SUM(Z33:Z38) -> 742 | AA39: =SUM(AA33:AA38) -> 779 | AB39: =SUM(AB33:AB38) -> 816 | AC39: =SUM(AC33:AC38) -> 854 | AE39: 622 | AF39: =W39 -> 639 | AG39: 658 | AH39: =X39 -> 674 | AI39: =SUM(AI33:AI38) -> 694 | AJ39: =SUM(AJ33:AJ38) -> 715
B40: Growth % | D40: =D39/C39-1 -> 0.34482759 | E40: =E39/D39-1 -> 0.17948718 | F40: =F39/E39-1 -> 0.17391304 | G40: =G39/F39-1 -> 0.36111111 | H40: =H39/G39-1 -> 0.14965986 | I40: =I39/H39-1 -> 0.17159763 | J40: =J39/I39-1 -> 0.16666667 | K40: =K39/J39-1 -> 0.15151515 | ... AC40: =AC39/AB39-1 -> 0.046568627 | AG40: =AG39/AE39-1 -> 0.057877814 | AH40: =AH39/AF39-1 -> 0.054773083 | AI40: =AI39/AG39-1 -> 0.054711246 | AJ40: =AJ39/AH39-1 -> 0.060830861
X41: =70/X7 -> 0.0078047475 | Z41: =X41*Z8 -> 11.967262 | AA41: =Z41/Z13 -> 0.00091151944
A42: Australia Stores inc. legacy MyChemist and Opt Warehouse | B42: Australia total adjusted for rebranding & Optometrist Warehouse | V42: =V33+V38 -> 549 | W42: =W33+W38 -> 569 | X42: =X33+X38 -> 588 | Y42: =Y33+Y38 -> 606 | Z42: =Z33+Z38 -> 624 | AA42: =AA33+AA38 -> 642 | AB42: =AB33+AB38 -> 660 | AC42: =AC33+AC38 -> 678 | AF42: =AF33+AF38 -> 569 | AG42: =AG33+AG38 -> 579 | AH42: =AH33+AH38 -> 590 | AI42: =AI33+AI38 -> 596 | AJ42: =AJ33+AJ38 -> 606
B43: Growth % | W43: =W42/V42-1 -> 0.036429872 | X43: =X42/W42-1 -> 0.033391916 | Y43: =Y42/X42-1 -> 0.030612245 | Z43: =Z42/Y42-1 -> 0.02970297 | AA43: =AA42/Z42-1 -> 0.028846154 | AB43: =AB42/AA42-1 -> 0.028037383 | AC43: =AC42/AB42-1 -> 0.027272727 | AH43: =AH42/AF42-1 -> 0.036906854 | AI43: =AI42/AG42-1 -> 0.029360967 | AJ43: =AJ42/AH42-1 -> 0.027118644
B45: Total International Store Count | R45: =R39-R33 -> 6 | S45: =14+1 -> 15 | T45: =24+2+4 -> 30 | U45: =35+4+5 -> 44 | V45: =42+6+6 -> 54 | W45: =50+10+10 -> 70 | X45: =61+14+9+2 -> 86 | Y45: =SUM(Y34:Y37) -> 109 | Z45: =SUM(Z34:Z37) -> 118 | AA45: =SUM(AA34:AA37) -> 137 | AB45: =SUM(AB34:AB37) -> 156 | AC45: =SUM(AC34:AC37) -> 176 | AF45: =AF39-AF33 -> 72 | AG45: =56+12+11+2 -> 81 | AH45: =SUM(AH34:AH37) -> 86 | AI45: =SUM(AI34:AI37) -> 98 | AJ45: =SUM(AJ34:AJ37) -> 109
B46: Growth % | S46: =S45/R45-1 -> 1.5 | T46: =T45/S45-1 -> 1 | U46: =U45/T45-1 -> 0.46666667 | V46: =V45/U45-1 -> 0.22727273 | W46: =W45/V45-1 -> 0.2962963 | X46: =X45/W45-1 -> 0.22857143 | Y46: =Y45/X45-1 -> 0.26744186 | Z46: =Z45/Y45-1 -> 0.082568807 | ... AC46: =AC45/AB45-1 -> 0.12820513 | AH46: =AH45/AF45-1 -> 0.19444444 | AI46: =AI45/AG45-1 -> 0.20987654 | AJ46: =AJ45/AH45-1 -> 0.26744186
B47: Net Change in Store Count | R47: =R45-Q45 -> 6 | S47: =S45-R45 -> 9 | T47: =T45-S45 -> 15 | U47: =U45-T45 -> 14 | V47: =V45-U45 -> 10 | W47: =W45-V45 -> 16 | X47: =X45-W45 -> 16 | Y47: =Y45-X45 -> 23 | ... AC47: =AC45-AB45 -> 20
B49: Average Sales per Store | X49: =(X50/C50)^(1/21)-1 -> 0.08718802
B50: Australia | C50: =C13/C33 -> 2.7241379 | D50: =D13/D33 -> 3.0512821 | E50: =E13/E33 -> 3.9347826 | F50: =F13/F33 -> 4.7314815 | G50: =G13/G33 -> 4.7687075 | H50: =H13/H33 -> 5.6272189 | I50: =I13/I33 -> 6.2171717 | J50: =J13/J33 -> 6.5714286 | ... Q50: =Q13/Q33 -> 10.890135 | R50: =R7/R33 -> 0 | S50: =S7/S33 -> 0 | T50: =T7/T33 -> 0 | U50: =U7/U33 -> 11.744991 | V50: =V7/V33 -> 12.89781 | W50: =W7/W33 -> 13.950441 | X50: =X7/X33 -> 15.762566 | Y50: =Y7/Y33 -> 17.229031 | ... AC50: =AC7/AC33 -> 20.333628
B51: New Zealand | R51: =R8/R34 -> 13.333333 | S51: =S8/S34 -> 12.214286 | T51: =T8/T34 -> 12.75 | U51: =U8/U34 -> 14.2 | V51: =V8/V34 -> 15.52381 | W51: =W8/W34 -> 17.72 | X51: =X8/X34 -> 17.213115 | Y51: =Y8/Y34 -> 17.074957 | ... AC51: =AC8/AC34 -> 20.361225
B52: Ireland | T52: =T9/T35 -> 3.8173703 | U52: =U9/U35 -> 7.4865233 | V52: =V9/V35 -> 9.8828797 | W52: =W9/W35 -> 10.569921 | X52: =X9/X35 -> 11.962242 | Y52: =Y9/Y35 -> 14.008515 | Z52: =Z9/Z35 -> 15.339324 | AA52: =AA9/AA35 -> 15.584754 | ... AC52: =AC9/AC35 -> 16.129329
B53: China | T53: =T10/T36 -> 12.5 | U53: =U10/U36 -> 16.990781 | V53: =V10/V36 -> 18.11712 | W53: =W10/W36 -> 10.030079 | X53: =X10/X36 -> 8.0142895 | Y53: =Y10/Y36 -> 8.8888889
B54: Dubai | X54: =X11/X37 -> 5 | Y54: =Y11/Y37 -> 7 | Z54: =Z11/Z37 -> 7 | AA54: =AA11/AA37 -> 7 | AB54: =AB11/AB37 -> 7 | AC54: =AC11/AC37 -> 7
B55: Other | T55: =T12/T38 -> 0
B56: Total Average Sales per Store | R56: =R13/R39 -> 11.25 | S56: =S13/S39 -> 11.286275 | T56: =T13/T39 -> 10.85267 | U56: =U13/U39 -> 11.910995 | V56: =V13/V39 -> 13.08126 | W56: =W13/W39 -> 14.08748 | X56: =X13/X39 -> 15.235163 | Y56: =Y13/Y39 -> 16.492727 | ... AC56: =AC13/AC39 -> 19.46948 | AE56: =AE13/AE39 -> 7.3302251 | AF56: =AF13/AF39 -> 6.9522692 | AG56: =AG13/AG39 -> 7.8331307 | AH56: =AH13/AH39 -> 7.5879822 | AI56: =AI13/AI39 -> 8.6393135 | AJ56: =AJ13/AJ39 -> 8.1071558
B57: Growth % | S57: =S56/R56-1 -> 0.0032244009 | T57: =T56/S56-1 -> -0.038418715 | U57: =U56/T56-1 -> 0.09751742 | V57: =V56/U56-1 -> 0.09825087 | W57: =W56/V56-1 -> 0.076920728 | X57: =X56/W56-1 -> 0.081468278 | Y57: =Y56/X56-1 -> 0.082543522 | Z57: =Z56/Y56-1 -> 0.072833916 | ... AC57: =AC56/AB56-1 -> 0.032002789 | AG57: =AG56/AE56-1 -> 0.068607118 | AH57: =AH56/AF56-1 -> 0.091439645 | AI57: =AI56/AG56-1 -> 0.10291961 | AJ57: =AJ56/AH56-1 -> 0.068420515
B59: Australia
B60: Australia Total Stores (Chemist Warehouse Australian Franchise Network Stores) | C60: =C39 -> 58 | D60: =D39 -> 78 | E60: =E39 -> 92 | F60: =F39 -> 108 | G60: =G39 -> 147 | H60: =H39 -> 169 | I60: 198 | J60: 231 | K60: 266 | L60: 297 | M60: 319 | N60: 341 | O60: 369 | P60: 412 | Q60: 446 | R60: 470 | S60: 495 | T60: 516 | U60: 529 | V60: 548 | W60: 567 | X60: =X72 -> 569 | Y60: =Y72 -> 587 | Z60: =Z72 -> 605 | AA60: =AA72 -> 623 | AB60: =AB72 -> 641 | AC60: =AC72 -> 659 | AG60: =AG72 -> 575 | AH60: =AH72 -> 569 | AI60: =AI72 -> 577 | AJ60: =AJ72 -> 587
B61: Growth % | D61: =D60/C60-1 -> 0.34482759 | E61: =E60/D60-1 -> 0.17948718 | F61: =F60/E60-1 -> 0.17391304 | G61: =G60/F60-1 -> 0.36111111 | H61: =H60/G60-1 -> 0.14965986 | I61: =I60/H60-1 -> 0.17159763 | J61: =J60/I60-1 -> 0.16666667 | K61: =K60/J60-1 -> 0.15151515 | ... AC61: =AC60/AB60-1 -> 0.028081123 | AI61: =AI60/AG60-1 -> 0.0034782609 | AJ61: =AJ60/AH60-1 -> 0.031634446
B63: Total Chemist Warehouse Network Stores by State
B64: Victoria | S64: 209 | T64: 213 | U64: 219 | V64: 231 | W64: =206+20+13 -> 239 | X64: =213+13+11 -> 237 | Y64: =X64+Y75 -> 242 | Z64: =Y64+Z75 -> 247 | AA64: =Z64+AA75 -> 252 | AB64: =AA64+AB75 -> 257 | AC64: =AB64+AC75 -> 262 | AG64: =209+24+12 -> 245 | AH64: =X64 -> 237 | AI64: =AH64+AI75 -> 239 | AJ64: =AI64+AJ75 -> 242
B65: New South Wales | S65: 119 | T65: 122 | U65: 123 | V65: 125 | W65: =120+1+8 -> 129 | X65: =123+6 -> 129 | Y65: =X65+Y76 -> 132 | Z65: =Y65+Z76 -> 135 | AA65: =Z65+AA76 -> 138 | AB65: =AA65+AB76 -> 141 | AC65: =AB65+AC76 -> 144 | AG65: =122+1+6 -> 129 | AH65: =X65 -> 129 | AI65: =AH65+AI76 -> 130 | AJ65: =AI65+AJ76 -> 132
B66: Queensland | S66: 79 | T66: 86 | U66: 91 | V66: 94 | W66: =90+6 -> 96 | X66: =96+1 -> 97 | Y66: =X66+Y77 -> 101 | Z66: =Y66+Z77 -> 105 | AA66: =Z66+AA77 -> 109 | AB66: =AA66+AB77 -> 113 | AC66: =AB66+AC77 -> 117 | AG66: =94+3 -> 97 | AH66: =X66 -> 97 | AI66: =AH66+AI77 -> 99 | AJ66: =AI66+AJ77 -> 101
B67: Western Australia | S67: 29 | T67: 34 | U67: 35 | V67: 37 | W67: 40 | X67: 43 | Y67: =X67+Y78 -> 45 | Z67: =Y67+Z78 -> 47 | AA67: =Z67+AA78 -> 49 | AB67: =AA67+AB78 -> 51 | AC67: =AB67+AC78 -> 53 | AG67: 41 | AH67: =X67 -> 43 | AI67: =AH67+AI78 -> 44 | AJ67: =AI67+AJ78 -> 45
B68: South Australia | S68: 28 | T68: 29 | U68: 29 | V68: 30 | W68: =29+1 -> 30 | X68: =30+1 -> 31 | Y68: =X68+Y79 -> 32 | Z68: =Y68+Z79 -> 33 | AA68: =Z68+AA79 -> 34 | AB68: =AA68+AB79 -> 35 | AC68: =AB68+AC79 -> 36 | AG68: =29+1 -> 30 | AH68: =X68 -> 31 | AI68: =AH68+AI79 -> 31 | AJ68: =AI68+AJ79 -> 32
B69: Tasmania | S69: 18 | T69: 18 | U69: 18 | V69: 18 | W69: 18 | X69: 18 | Y69: =X69+Y80 -> 19 | Z69: =Y69+Z80 -> 20 | AA69: =Z69+AA80 -> 21 | AB69: =AA69+AB80 -> 22 | AC69: =AB69+AC80 -> 23 | AG69: 18 | AH69: =X69 -> 18 | AI69: =AH69+AI80 -> 19 | AJ69: =AI69+AJ80 -> 19
B70: Australian Capital Territory | S70: 4 | T70: 6 | U70: 6 | V70: 6 | W70: =5+1 -> 6 | X70: 5 | Y70: =X70+Y81 -> 6 | Z70: =Y70+Z81 -> 7 | AA70: =Z70+AA81 -> 8 | AB70: =AA70+AB81 -> 9 | AC70: =AB70+AC81 -> 10 | AG70: =5+1 -> 6 | AH70: =X70 -> 5 | AI70: =AH70+AI81 -> 5 | AJ70: =AI70+AJ81 -> 6
B71: Northern Territory | S71: 9 | T71: 8 | U71: 8 | V71: 8 | W71: 9 | X71: 9 | Y71: =X71+Y82 -> 10 | Z71: =Y71+Z82 -> 11 | AA71: =Z71+AA82 -> 12 | AB71: =AA71+AB82 -> 13 | AC71: =AB71+AC82 -> 14 | AG71: 9 | AH71: =X71 -> 9 | AI71: =AH71+AI82 -> 10 | AJ71: =AI71+AJ82 -> 10
B72: Total Stores | S72: =SUM(S64:S71) -> 495 | T72: =SUM(T64:T71) -> 516 | U72: =SUM(U64:U71) -> 529 | V72: =SUM(V64:V71) -> 549 | W72: =W60 -> 567 | X72: =SUM(X64:X71) -> 569 | Y72: =SUM(Y64:Y71) -> 587 | Z72: =SUM(Z64:Z71) -> 605 | AA72: =SUM(AA64:AA71) -> 623 | AB72: =SUM(AB64:AB71) -> 641 | AC72: =SUM(AC64:AC71) -> 659 | AG72: =SUM(AG64:AG71) -> 575 | AH72: =X72 -> 569 | AI72: =SUM(AI64:AI71) -> 577 | AJ72: =SUM(AJ64:AJ71) -> 587
B74: Net Change in Chemist Warehouse Network Stores by State
B75: Victoria | T75: =T64-S64 -> 4 | U75: =U64-T64 -> 6 | V75: =V64-U64 -> 12 | W75: =W64-V64 -> 8 | X75: =X64-W64 -> -2 | Y75: 5 | Z75: 5 | AA75: 5 | AB75: 5 | AC75: 5 | AI75: 2 | AJ75: =Y75-AI75 -> 3
B76: New South Wales | T76: =T65-S65 -> 3 | U76: =U65-T65 -> 1 | V76: =V65-U65 -> 2 | W76: =W65-V65 -> 4 | X76: =X65-W65 -> 0 | Y76: 3 | Z76: 3 | AA76: 3 | AB76: 3 | AC76: 3 | AI76: 1 | AJ76: =Y76-AI76 -> 2
B77: Queensland | T77: =T66-S66 -> 7 | U77: =U66-T66 -> 5 | V77: =V66-U66 -> 3 | W77: =W66-V66 -> 2 | X77: =X66-W66 -> 1 | Y77: 4 | Z77: 4 | AA77: 4 | AB77: 4 | AC77: 4 | AI77: 2 | AJ77: =Y77-AI77 -> 2
B78: Western Australia | T78: =T67-S67 -> 5 | U78: =U67-T67 -> 1 | V78: =V67-U67 -> 2 | W78: =W67-V67 -> 3 | X78: =X67-W67 -> 3 | Y78: 2 | Z78: 2 | AA78: 2 | AB78: 2 | AC78: 2 | AI78: 1 | AJ78: =Y78-AI78 -> 1
B79: South Australia | T79: =T68-S68 -> 1 | U79: =U68-T68 -> 0 | V79: =V68-U68 -> 1 | W79: =W68-V68 -> 0 | X79: =X68-W68 -> 1 | Y79: 1 | Z79: 1 | AA79: 1 | AB79: 1 | AC79: 1 | AI79: 0 | AJ79: =Y79-AI79 -> 1
B80: Tasmania | T80: =T69-S69 -> 0 | U80: =U69-T69 -> 0 | V80: =V69-U69 -> 0 | W80: =W69-V69 -> 0 | X80: =X69-W69 -> 0 | Y80: 1 | Z80: 1 | AA80: 1 | AB80: 1 | AC80: 1 | AI80: 1 | AJ80: =Y80-AI80 -> 0
B81: Australian Capital Territory | T81: =T70-S70 -> 2 | U81: =U70-T70 -> 0 | V81: =V70-U70 -> 0 | W81: =W70-V70 -> 0 | X81: =X70-W70 -> -1 | Y81: 1 | Z81: 1 | AA81: 1 | AB81: 1 | AC81: 1 | AI81: 0 | AJ81: =Y81-AI81 -> 1
B82: Northern Territory | T82: =T71-S71 -> -1 | U82: =U71-T71 -> 0 | V82: =V71-U71 -> 0 | W82: =W71-V71 -> 1 | X82: =X71-W71 -> 0 | Y82: 1 | Z82: 1 | AA82: 1 | AB82: 1 | AC82: 1 | AI82: 1 | AJ82: =Y82-AI82 -> 0
B83: Total Net Change | T83: =T72-S72 -> 21 | U83: =U72-T72 -> 13 | V83: =V72-U72 -> 20 | W83: =W72-V72 -> 18 | X83: =X72-W72 -> 2 | Y83: =Y72-X72 -> 18 | Z83: =Z72-Y72 -> 18 | AA83: =AA72-Z72 -> 18 | ... AC83: =AC72-AB72 -> 18 | AI83: =SUM(AI75:AI82) -> 8 | AJ83: =Y83-AI83 -> 10
B85: New Zealand
B86: Network Sales | R86: 80 | S86: 171 | T86: 306 | U86: 497 | V86: 652 | W86: 886 | X86: 1050 | Y86: =X86*(1+Y87) -> 1297.6967 | Z86: =Y86*(1+Z87) -> 1533.3311 | AA86: =Z86*(1+AA87) -> 1788.292 | AB86: =AA86*(1+AB87) -> 2063.987 | AC86: =AB86*(1+AC87) -> 2361.9021
B87: Growth % | S87: =S86/R86-1 -> 1.1375 | T87: =T86/S86-1 -> 0.78947368 | U87: =U86/T86-1 -> 0.62418301 | V87: =V86/U86-1 -> 0.31187123 | W87: =W86/V86-1 -> 0.35889571 | X87: =X86/W86-1 -> 0.18510158 | Y87: =SUM(Y88:Y90) -> 0.23590164 | Z87: =SUM(Z88:Z90) -> 0.18157895 | AA87: =SUM(AA88:AA90) -> 0.16627907 | AB87: =SUM(AB88:AB90) -> 0.15416667 | AC87: =SUM(AC88:AC90) -> 0.14433962
B88: Total LFL Sales Growth % | W88: =W27 -> 0.144 | X88: =X27 -> 0.081 | Y88: 0.1 | Z88: 0.08 | AA88: 0.08 | AB88: 0.08 | AC88: 0.08
B89: Store Growth % | S89: =S93 -> 1.3333333 | T89: =T93 -> 0.71428571 | U89: =U93 -> 0.45833333 | V89: =V93 -> 0.2 | W89: =W93 -> 0.19047619 | X89: =X93 -> 0.22 | Y89: =Y93 -> 0.24590164 | Z89: =Z93 -> 0.13157895 | ... AC89: =AC93 -> 0.094339623
B90: Other % | W90: =W87-W88-W89 -> 0.024419515 | X90: =X87-X88-X89 -> -0.11589842 | Y90: -0.11 | Z90: -0.03 | AA90: -0.03 | AB90: -0.03 | AC90: -0.03
B92: Total New Zealand Stores | Q92: 0 | R92: 6 | S92: 14 | T92: 24 | U92: 35 | V92: 42 | W92: 50 | X92: 61 | Y92: 76 | Z92: =Y92+10 -> 86 | AA92: =Z92+10 -> 96 | AB92: =AA92+10 -> 106 | AC92: =AB92+10 -> 116 | AF92: =W92 -> 50 | AG92: 56 | AH92: =X92 -> 61 | AI92: 70 | AJ92: =Y92 -> 76
B93: Growth % | S93: =S92/R92-1 -> 1.3333333 | T93: =T92/S92-1 -> 0.71428571 | U93: =U92/T92-1 -> 0.45833333 | V93: =V92/U92-1 -> 0.2 | W93: =W92/V92-1 -> 0.19047619 | X93: =X92/W92-1 -> 0.22 | Y93: =Y92/X92-1 -> 0.24590164 | Z93: =Z92/Y92-1 -> 0.13157895 | ... AC93: =AC92/AB92-1 -> 0.094339623
B95: Ireland
B96: Network Sales | T96: ='Ireland Model'!T72 -> 7.6347407 | U96: ='Ireland Model'!U72 -> 29.946093 | V96: ='Ireland Model'!V72 -> 59.297278 | W96: ='Ireland Model'!W72 -> 105.69921 | X96: ='Ireland Model'!X72 -> 167.47139 | Y96: ='Ireland Model'!Y72 -> 266.16179 | Z96: ='Ireland Model'!Z72 -> 368.14378 | AA96: ='Ireland Model'!AA72 -> 467.54261 | ... AC96: ='Ireland Model'!AC72 -> 645.17317
B97: Growth % | U97: =U96/T96-1 -> 2.9223458 | V97: =V96/U96-1 -> 0.98013404 | W97: =W96/V96-1 -> 0.78253057 | X97: =X96/W96-1 -> 0.5844148 | Y97: =Y96/X96-1 -> 0.58929704 | Z97: =Z96/Y96-1 -> 0.38315789 | AA97: =AA96/Z96-1 -> 0.27 | AB97: =AB96/AA96-1 -> 0.18666667 | AC97: =AC96/AB96-1 -> 0.16285714
B98: Total LFL Sales Growth %
B99: Store Growth %
B100: Other %
B102: Total Ireland Stores | S102: ='Ireland Model'!S12 -> 0 | T102: ='Ireland Model'!T12 -> 2 | U102: ='Ireland Model'!U12 -> 4 | V102: ='Ireland Model'!V12 -> 6 | W102: ='Ireland Model'!W12 -> 10 | X102: ='Ireland Model'!X12 -> 14 | Y102: ='Ireland Model'!Y12 -> 19 | Z102: ='Ireland Model'!Z12 -> 24 | ... AC102: ='Ireland Model'!AC12 -> 40 | AF102: =W102 -> 10 | AG102: 12 | AH102: =X102 -> 14 | AI102: 16 | AJ102: =Y102 -> 19
B103: Growth % | U103: =U102/T102-1 -> 1 | V103: =V102/U102-1 -> 0.5 | W103: =W102/V102-1 -> 0.66666667 | X103: =X102/W102-1 -> 0.4 | Y103: =Y102/X102-1 -> 0.35714286 | Z103: =Z102/Y102-1 -> 0.26315789 | AA103: =AA102/Z102-1 -> 0.25 | AB103: =AB102/AA102-1 -> 0.16666667 | AC103: =AC102/AB102-1 -> 0.14285714
B105: Dubai
B106: Network Sales
B107: Growth %
B108: Total LFL Sales Growth %
B109: Store Growth %
B110: Other %
B112: Total Dubai Stores
B113: Growth %
B115: Group P&L Modelling
...

Sheet PL
B1: =Model!B1 -> Sigma Healthcare (SIG.AX)
B2: =Model!B2 -> A$M
C3: FY24 | D3: FY25 | E3: FY26E | F3: FY27E | G3: FY28E | H3: FY29E | I3: FY30E | K3: 1H25 | L3: 2H25 | M3: 1H26E | N3: 2H26E
B4: P&L
A5: Total network sales | B5: Network Sales | C5: =VLOOKUP($A5,Model!$1:$1048576,MATCH(C$3,Model!$3:$3,0),FALSE) -> 9001.9 | D5: =VLOOKUP($A5,Model!$1:$1048576,MATCH(D$3,Model!$3:$3,0),FALSE) -> 10268.5 | E5: =VLOOKUP($A5,Model!$1:$1048576,MATCH(E$3,Model!$3:$3,0),FALSE) -> 11792.3 | F5: =VLOOKUP($A5,Model!$1:$1048576,MATCH(F$3,Model!$3:$3,0),FALSE) -> 13128.916 | G5: =VLOOKUP($A5,Model!$1:$1048576,MATCH(G$3,Model!$3:$3,0),FALSE) -> 14234.605 | H5: =VLOOKUP($A5,Model!$1:$1048576,MATCH(H$3,Model!$3:$3,0),FALSE) -> 15394.431 | I5: =VLOOKUP($A5,Model!$1:$1048576,MATCH(I$3,Model!$3:$3,0),FALSE) -> 16626.936 | K5: =VLOOKUP($A5,Model!$1:$1048576,MATCH(K$3,Model!$3:$3,0),FALSE) -> 5154.2 | L5: =VLOOKUP($A5,Model!$1:$1048576,MATCH(L$3,Model!$3:$3,0),FALSE) -> 5114.3 | M5: =VLOOKUP($A5,Model!$1:$1048576,MATCH(M$3,Model!$3:$3,0),FALSE) -> 5995.6835 | N5: =VLOOKUP($A5,Model!$1:$1048576,MATCH(N$3,Model!$3:$3,0),FALSE) -> 5796.6164
A6: Network Sales Growth | B6: Growth % | D6: =D5/C5-1 -> 0.14070363 | E6: =E5/D5-1 -> 0.14839558 | F6: =F5/E5-1 -> 0.11334653 | G6: =G5/F5-1 -> 0.0842178 | H6: =H5/G5-1 -> 0.08147937 | I6: =I5/H5-1 -> 0.080061743 | M6: =M5/K5-1 -> 0.16326172 | N6: =N5/L5-1 -> 0.13341345
A8: Total revenue | B8: Revenue | C8: =VLOOKUP($A8,Model!$1:$1048576,MATCH(C$3,Model!$3:$3,0),FALSE) -> 6655.7 | D8: =VLOOKUP($A8,Model!$1:$1048576,MATCH(D$3,Model!$3:$3,0),FALSE) -> 9591.3 | E8: =VLOOKUP($A8,Model!$1:$1048576,MATCH(E$3,Model!$3:$3,0),FALSE) -> 10928.785 | F8: =VLOOKUP($A8,Model!$1:$1048576,MATCH(F$3,Model!$3:$3,0),FALSE) -> 12084.819 | G8: =VLOOKUP($A8,Model!$1:$1048576,MATCH(G$3,Model!$3:$3,0),FALSE) -> 12985.047 | H8: =VLOOKUP($A8,Model!$1:$1048576,MATCH(H$3,Model!$3:$3,0),FALSE) -> 13921.647 | I8: =VLOOKUP($A8,Model!$1:$1048576,MATCH(I$3,Model!$3:$3,0),FALSE) -> 14912.319 | K8: =VLOOKUP($A8,Model!$1:$1048576,MATCH(K$3,Model!$3:$3,0),FALSE) -> 0 | L8: =VLOOKUP($A8,Model!$1:$1048576,MATCH(L$3,Model!$3:$3,0),FALSE) -> 0 | M8: =VLOOKUP($A8,Model!$1:$1048576,MATCH(M$3,Model!$3:$3,0),FALSE) -> 5556.6373 | N8: =VLOOKUP($A8,Model!$1:$1048576,MATCH(N$3,Model!$3:$3,0),FALSE) -> 5372.1473
A9: Revenue Growth | B9: Growth % | D9: =D8/C8-1 -> 0.44106555 | E9: =E8/D8-1 -> 0.13944769 | F9: =F8/E8-1 -> 0.10577885 | G9: =G8/F8-1 -> 0.074492467 | H9: =H8/G8-1 -> 0.072129106 | I9: =I8/H8-1 -> 0.071160546
A11: EBITDA | B11: EBITDA Normalised | C11: =VLOOKUP($A11,Model!$1:$1048576,MATCH(C$3,Model!$3:$3,0),FALSE) -> 675.1 | D11: =VLOOKUP($A11,Model!$1:$1048576,MATCH(D$3,Model!$3:$3,0),FALSE) -> 968.5 | E11: =VLOOKUP($A11,Model!$1:$1048576,MATCH(E$3,Model!$3:$3,0),FALSE) -> 1201.5729 | F11: =VLOOKUP($A11,Model!$1:$1048576,MATCH(F$3,Model!$3:$3,0),FALSE) -> 1424.6573 | G11: =VLOOKUP($A11,Model!$1:$1048576,MATCH(G$3,Model!$3:$3,0),FALSE) -> 1633.2645 | H11: =VLOOKUP($A11,Model!$1:$1048576,MATCH(H$3,Model!$3:$3,0),FALSE) -> 1837.3141 | I11: =VLOOKUP($A11,Model!$1:$1048576,MATCH(I$3,Model!$3:$3,0),FALSE) -> 2061.6569 | K11: =VLOOKUP($A11,Model!$1:$1048576,MATCH(K$3,Model!$3:$3,0),FALSE) -> 0 | L11: =VLOOKUP($A11,Model!$1:$1048576,MATCH(L$3,Model!$3:$3,0),FALSE) -> 0 | M11: =VLOOKUP($A11,Model!$1:$1048576,MATCH(M$3,Model!$3:$3,0),FALSE) -> 656.1775 | N11: =VLOOKUP($A11,Model!$1:$1048576,MATCH(N$3,Model!$3:$3,0),FALSE) -> 545.39544
B12: Growth % | D12: =D11/C11-1 -> 0.43460228 | E12: =E11/D11-1 -> 0.24065353 | F12: =F11/E11-1 -> 0.18566031 | G12: =G11/F11-1 -> 0.14642621 | H12: =H11/G11-1 -> 0.12493357 | I12: =I11/H11-1 -> 0.12210365
B14: Lease D&A | C14: -18.875 | D14: -27.197 | E14: =D14*(1+Model!Y$16) -> -28.851417 | F14: =E14*(1+Model!Z16) -> -29.940911 | G14: =F14*(1+Model!AA16) -> -31.433921 | H14: =G14*(1+Model!AB16) -> -32.926932 | I14: =H14*(1+Model!AC16) -> -34.460294 | M14: =E14*0.5 -> -14.425708 | N14: =E14-M14 -> -14.425708
A15: D&A non lease | B15: Non Lease D&A | C15: =C16-C14 -> -50.725 | D15: =D16-D14 -> -37.903 | E15: =E16-E14 -> -39.503583 | F15: =F16-F14 -> -41.831839 | G15: =G16-G14 -> -43.927466 | H15: =H16-H14 -> -46.202525 | I15: =I16-I14 -> -48.625636 | M15: =M16-M14 -> -19.751792 | N15: =N16-N14 -> -19.751792
A16: D&A | B16: D&A | C16: =VLOOKUP($A16,Model!$1:$1048576,MATCH(C$3,Model!$3:$3,0),FALSE) -> -69.6 | D16: =VLOOKUP($A16,Model!$1:$1048576,MATCH(D$3,Model!$3:$3,0),FALSE) -> -65.1 | E16: =VLOOKUP($A16,Model!$1:$1048576,MATCH(E$3,Model!$3:$3,0),FALSE) -> -68.355 | F16: =VLOOKUP($A16,Model!$1:$1048576,MATCH(F$3,Model!$3:$3,0),FALSE) -> -71.77275 | G16: =VLOOKUP($A16,Model!$1:$1048576,MATCH(G$3,Model!$3:$3,0),FALSE) -> -75.361388 | H16: =VLOOKUP($A16,Model!$1:$1048576,MATCH(H$3,Model!$3:$3,0),FALSE) -> -79.129457 | I16: =VLOOKUP($A16,Model!$1:$1048576,MATCH(I$3,Model!$3:$3,0),FALSE) -> -83.08593 | K16: =VLOOKUP($A16,Model!$1:$1048576,MATCH(K$3,Model!$3:$3,0),FALSE) -> 0 | L16: =VLOOKUP($A16,Model!$1:$1048576,MATCH(L$3,Model!$3:$3,0),FALSE) -> 0 | M16: =VLOOKUP($A16,Model!$1:$1048576,MATCH(M$3,Model!$3:$3,0),FALSE) -> -34.1775 | N16: =VLOOKUP($A16,Model!$1:$1048576,MATCH(N$3,Model!$3:$3,0),FALSE) -> -34.1775
B17: Growth % | D17: =D16/C16-1 -> -0.064655172 | E17: =E16/D16-1 -> 0.05 | F17: =F16/E16-1 -> 0.05 | G17: =G16/F16-1 -> 0.05 | H17: =H16/G16-1 -> 0.05 | I17: =I16/H16-1 -> 0.05
A19: EBIT | B19: EBIT Normalised | C19: =VLOOKUP($A19,Model!$1:$1048576,MATCH(C$3,Model!$3:$3,0),FALSE) -> 605.5 | D19: =VLOOKUP($A19,Model!$1:$1048576,MATCH(D$3,Model!$3:$3,0),FALSE) -> 903.4 | E19: =VLOOKUP($A19,Model!$1:$1048576,MATCH(E$3,Model!$3:$3,0),FALSE) -> 1133.2179 | F19: =VLOOKUP($A19,Model!$1:$1048576,MATCH(F$3,Model!$3:$3,0),FALSE) -> 1352.8846 | G19: =VLOOKUP($A19,Model!$1:$1048576,MATCH(G$3,Model!$3:$3,0),FALSE) -> 1557.9031 | H19: =VLOOKUP($A19,Model!$1:$1048576,MATCH(H$3,Model!$3:$3,0),FALSE) -> 1758.1846 | I19: =VLOOKUP($A19,Model!$1:$1048576,MATCH(I$3,Model!$3:$3,0),FALSE) -> 1978.5709 | K19: =VLOOKUP($A19,Model!$1:$1048576,MATCH(K$3,Model!$3:$3,0),FALSE) -> 0 | L19: =VLOOKUP($A19,Model!$1:$1048576,MATCH(L$3,Model!$3:$3,0),FALSE) -> 0 | M19: =VLOOKUP($A19,Model!$1:$1048576,MATCH(M$3,Model!$3:$3,0),FALSE) -> 622 | N19: =VLOOKUP($A19,Model!$1:$1048576,MATCH(N$3,Model!$3:$3,0),FALSE) -> 511.21794
A20: EBIT Growth | B20: Growth % | D20: =D19/C19-1 -> 0.49199009 | E20: =E19/D19-1 -> 0.25439223 | F20: =F19/E19-1 -> 0.19384326 | G20: =G19/F19-1 -> 0.15154178 | H20: =H19/G19-1 -> 0.12855837 | I20: =I19/H19-1 -> 0.12534878
B22: Significant Items / Other | C22: =C24-C19 -> -23.964 | D22: =D24-D19 -> -135.5 | E22: -10 | F22: -30 | G22: -30 | H22: -30 | M22: -5 | N22: =E22-M22 -> -5
B24: EBIT Statutory | C24: =574.121+7.415 -> 581.536 | D24: 767.9 | E24: =E19+E22 -> 1123.2179 | F24: =F19+F22 -> 1322.8846 | G24: =G19+G22 -> 1527.9031 | H24: =H19+H22 -> 1728.1846 | I24: =I19+I22 -> 1978.5709 | M24: =M19+M22 -> 617 | N24: =N19+N22 -> 506.21794
A26: Interest leases | B26: Least Interest | C26: =-49.854+44.936 -> -4.918 | D26: =-58.619+50.476 -> -8.143 | E26: =D26*(1+Model!Y$16) -> -8.6383457 | F26: =E26*(1+Model!Z$16) -> -8.964549 | G26: =F26*(1+Model!AA$16) -> -9.4115682 | H26: =G26*(1+Model!AB$16) -> -9.8585875 | I26: =H26*(1+Model!AC$16) -> -10.317688
B27: Non-Lease Interest | C27: =C28-C26 -> -2.497 | D27: =D28-D26 -> -15.957 | E27: =E28-E26 -> -41.361654 | F27: =F28-F26 -> -37.035451 | G27: =G28-G26 -> -30.588432 | H27: =H28-H26 -> -30.141412 | I27: =I28-I26 -> -29.682312
A28: Net interest | B28: Net Interest Income / (Expense) | C28: -7.415 | D28: -24.1 | E28: -50 | F28: -46 | G28: -40 | H28: -40 | I28: -40 | M28: =E28*0.5 -> -25 | N28: =E28-M28 -> -25
B30: PBT Normalised | C30: =C19+C28 -> 598.085 | D30: =D19+D28 -> 879.3 | E30: =E19+E28 -> 1083.2179 | F30: =F19+F28 -> 1306.8846 | G30: =G19+G28 -> 1517.9031 | H30: =H19+H28 -> 1718.1846 | I30: =I19+I28 -> 1938.5709 | M30: =M19+M28 -> 597 | N30: =N19+N28 -> 486.21794
B31: Growth % | E31: =E30/D30-1 -> 0.23190941 | F31: =F30/E30-1 -> 0.20648352 | G31: =G30/F30-1 -> 0.16146685 | H31: =H30/G30-1 -> 0.13194616 | I31: =I30/H30-1 -> 0.12826694
B33: Income Tax Normalised | C33: =C51 -> -170.6 | D33: =D51 -> -254.997 | E33: =E51 -> -314.1332 | F33: =F51 -> -378.99653 | G33: =G51 -> -440.19191 | H33: =H51 -> -498.27354 | I33: =I51 -> -562.18557 | M33: =M51 -> -173.13 | N33: =N51 -> -141.0032
A35: Minorities | B35: Minority Interest | C35: -1.356 | D35: -4.5 | E35: =-4.5-'Ireland Model'!Y99 -> -7.8058614 | F35: =-4.5-'Ireland Model'!Z99 -> -11.184447 | G35: =-4.5-'Ireland Model'!AA99 -> -14.100187 | H35: =-4.5-'Ireland Model'!AB99 -> -17.533169 | I35: =-4.5-'Ireland Model'!AC99 -> -20.983628 | M35: =E35*0.5 -> -3.9029307 | N35: =E35-M35 -> -3.9029307
A37: NPAT | B37: NPAT Normalised | C37: =C30+C33+C35 -> 426.129 | D37: =D30+D33+D35 -> 619.803 | E37: =E30+E33+E35 -> 761.27888 | F37: =F30+F33+F35 -> 916.70362 | G37: =G30+G33+G35 -> 1063.611 | H37: =H30+H33+H35 -> 1202.3779 | I37: =I30+I33+I35 -> 1355.4017 | M37: =M30+M33+M35 -> 419.96707 | N37: =N30+N33+N35 -> 341.31181
A38: NPAT Growth | B38: Growth % | E38: =E37/D37-1 -> 0.22825943 | F38: =F37/E37-1 -> 0.20416269 | G38: =G37/F37-1 -> 0.16025618 | H38: =H37/G37-1 -> 0.13046769 | I38: =I37/H37-1 -> 0.12726765
B40: Significant Items / Other | C40: =C42-C37 -> 114.884 | D40: =D42-D37 -> -89.903 | E40: =E52+E22 -> -7.1 | F40: =F52+F22 -> -21.3 | G40: =G52+G22 -> -21.3 | H40: =H52+H22 -> -21.3 | I40: =I52+I22 -> 0 | M40: =M52+M22 -> -3.55 | N40: =N52+N22 -> -3.55
B42: NPAT Statutory | C42: 541.013 | D42: 529.9 | E42: =E37+E40 -> 754.17888 | F42: =F37+F40 -> 895.40362 | G42: =G37+G40 -> 1042.311 | H42: =H37+H40 -> 1181.0779 | I42: =I37+I40 -> 1355.4017 | M42: =M37+M40 -> 416.41707 | N42: =N37+N40 -> 337.76181
B43: Growth % | F43: =F42/E42-1 -> 0.18725629 | G43: =G42/F42-1 -> 0.16406838 | H43: =H42/G42-1 -> 0.13313385 | I43: =I42/H42-1 -> 0.14759721
A45: Shares Diluted | B45: Shares (Diluted) | D45: =D67 -> 11540 | E45: =E67 -> 11540 | F45: =F67 -> 11540 | G45: =G67 -> 11540 | H45: =H67 -> 11540 | I45: =I67 -> 11540 | M45: =M67 -> 11540 | N45: =N67 -> 11540
A47: EPS | B47: EPS Normalised (Diluted) | D47: =D37/D45 -> 0.053709099 | E47: =E37/E45 -> 0.065968707 | F47: =F37/F45 -> 0.079437055 | G47: =G37/G45 -> 0.092167335 | H47: =H37/H45 -> 0.10419219 | I47: =I37/I45 -> 0.11745249 | M47: =M37/M45 -> 0.036392294 | N47: =N37/N45 -> 0.029576413
A48: EPS Growth | B48: Growth % | E48: =E47/D47-1 -> 0.22825943 | F48: =F47/E47-1 -> 0.20416269 | G48: =G47/F47-1 -> 0.16025618 | H48: =H47/G47-1 -> 0.13046769 | I48: =I47/H47-1 -> 0.12726765
B50: Tax Modelling
A51: Tax | B51: Tax Normalised | C51: -170.6 | D51: =D61*-D56 -> -254.997 | E51: =E61*-E56 -> -314.1332 | F51: =F61*-F56 -> -378.99653 | G51: =G61*-G56 -> -440.19191 | H51: =H61*-H56 -> -498.27354 | I51: =I61*-I56 -> -562.18557 | M51: =M61*-M56 -> -173.13 | N51: =E51-M51 -> -141.0032
B52: Significant Items | E52: =E62*-E57 -> 2.9 | F52: =F62*-F57 -> 8.7 | G52: =G62*-G57 -> 8.7 | H52: =H62*-H57 -> 8.7 | I52: =I62*-I57 -> 0 | M52: =M62*-M57 -> 1.45 | N52: =E52-M52 -> 1.45
B53: Tax Statutory | C53: -34.464 | E53: =E51+E52 -> -311.2332 | F53: =F51+F52 -> -370.29653 | G53: =G51+G52 -> -431.49191 | H53: =H51+H52 -> -489.57354 | I53: =I51+I52 -> -562.18557 | M53: =M51+M52 -> -171.68 | N53: =E53-M53 -> -139.5532
B55: Tax Rates
B56: Tax Normalised | D56: 0.29 | E56: 0.29 | F56: 0.29 | G56: 0.29 | H56: 0.29 | I56: 0.29 | M56: 0.29 | N56: =N51/-N61 -> 0.29
B57: Significant items | E57: =E56 -> 0.29 | F57: =F56 -> 0.29 | G57: =G56 -> 0.29 | H57: =H56 -> 0.29 | I57: =I56 -> 0.29 | M57: 0.29 | N57: =N52/-N62 -> 0.29
B58: Tax Statutory | E58: =E53/-E63 -> 0.29 | F58: =F53/-F63 -> 0.29 | G58: =G53/-G63 -> 0.29 | H58: =H53/-H63 -> 0.29 | I58: =I53/-I63 -> 0.29 | M58: =M53/-M63 -> 0.29 | N58: =N53/-N63 -> 0.29
B60: PBT
A61: PBT | B61: PBT Normalised | D61: =D30 -> 879.3 | E61: =E30 -> 1083.2179 | F61: =F30 -> 1306.8846 | G61: =G30 -> 1517.9031 | H61: =H30 -> 1718.1846 | I61: =I30 -> 1938.5709 | M61: =M30 -> 597 | N61: =E61-M61 -> 486.21794
B62: Significant items | E62: =E22 -> -10 | F62: =F22 -> -30 | G62: =G22 -> -30 | H62: =H22 -> -30 | I62: =I22 -> 0 | M62: =M22 -> -5 | N62: =E62-M62 -> -5
B63: PBT statutory | E63: =E61+E62 -> 1073.2179 | F63: =F61+F62 -> 1276.8846 | G63: =G61+G62 -> 1487.9031 | H63: =H61+H62 -> 1688.1846 | I63: =I61+I62 -> 1938.5709 | M63: =M61+M62 -> 592 | N63: =E63-M63 -> 481.21794
A65: Shares EOP | B65: Period End Shares | D65: 11540 | E65: =D65 -> 11540 | F65: =E65 -> 11540 | G65: =F65 -> 11540 | H65: =G65 -> 11540 | I65: =H65 -> 11540 | M65: =E65 -> 11540 | N65: =E65 -> 11540
B66: Weighted Average Basic | D66: 10477.795 | E66: =E67 -> 11540 | F66: =F67-(E67-E66) -> 11540 | G66: =G67-(F67-F66) -> 11540 | H66: =H67-(G67-G66) -> 11540 | I66: =I67-(H67-H66) -> 11540 | M66: =E66 -> 11540 | N66: =E66 -> 11540
B67: Weighted Average Diluted | D67: =D65 -> 11540 | E67: =D65 -> 11540 | F67: =E65 -> 11540 | G67: =F65 -> 11540 | H67: =G65 -> 11540 | I67: =H65 -> 11540 | M67: =E67 -> 11540 | N67: =E67 -> 11540
B69: Ordinary Dividend | E69: =E72*E47 -> 0.046178095 | F69: =F72*F47 -> 0.055605939 | G69: =G72*G47 -> 0.064517134 | H69: =H72*H47 -> 0.072934536 | I69: =I72*I47 -> 0.082216743 | M69: =M72*M47 -> 0.025474606 | N69: =E69-M69 -> 0.020703489
B70: Special Dividend | E70: 0 | F70: 0 | G70: 0 | H70: 0 | I70: 0 | M70: 0 | N70: =E70-M70 -> 0
A71: DPS | B71: Total Dividend Per Share | E71: =SUM(E69:E70) -> 0.046178095 | F71: =SUM(F69:F70) -> 0.055605939 | G71: =SUM(G69:G70) -> 0.064517134 | H71: =SUM(H69:H70) -> 0.072934536 | I71: =SUM(I69:I70) -> 0.082216743 | M71: =SUM(M69:M70) -> 0.025474606 | N71: =E71-M71 -> 0.020703489
A72: Payout Ratio | B72: Payout Ratio % | E72: 0.7 | F72: 0.7 | G72: 0.7 | H72: 0.7 | I72: 0.7 | M72: 0.7 | N72: =N71/N47 -> 0.7
B74: Franking
B75: Franking Rate | D75: 1 | E75: 1 | F75: 1 | G75: 1 | H75: 1 | I75: 1
B76: Franking Credits | C76: 161.64 | D76: 186.453

Sheet CF
B1: =Model!B1 -> Sigma Healthcare (SIG.AX)
B2: =Model!B2 -> A$M
C3: FY24 | D3: FY25 | E3: FY26E | F3: FY27E | G3: FY28E | H3: FY29E | I3: FY30E
B4: CFS
B5: Operating Cash Flow
A6: EBIT | B6: EBIT | C6: =VLOOKUP($A6,PL!$1:$1048576,MATCH(C$3,PL!$3:$3,0),FALSE) -> 605.5 | D6: =VLOOKUP($A6,PL!$1:$1048576,MATCH(D$3,PL!$3:$3,0),FALSE) -> 903.4 | E6: =VLOOKUP($A6,PL!$1:$1048576,MATCH(E$3,PL!$3:$3,0),FALSE) -> 1133.2179 | F6: =VLOOKUP($A6,PL!$1:$1048576,MATCH(F$3,PL!$3:$3,0),FALSE) -> 1352.8846 | G6: =VLOOKUP($A6,PL!$1:$1048576,MATCH(G$3,PL!$3:$3,0),FALSE) -> 1557.9031 | H6: =VLOOKUP($A6,PL!$1:$1048576,MATCH(H$3,PL!$3:$3,0),FALSE) -> 1758.1846 | I6: =VLOOKUP($A6,PL!$1:$1048576,MATCH(I$3,PL!$3:$3,0),FALSE) -> 1978.5709
A7: D&A | B7: Depreciation and Amortisation | C7: =-VLOOKUP($A7,PL!$1:$1048576,MATCH(C$3,PL!$3:$3,0),FALSE) -> 69.6 | D7: =-VLOOKUP($A7,PL!$1:$1048576,MATCH(D$3,PL!$3:$3,0),FALSE) -> 65.1 | E7: =-VLOOKUP($A7,PL!$1:$1048576,MATCH(E$3,PL!$3:$3,0),FALSE) -> 68.355 | F7: =-VLOOKUP($A7,PL!$1:$1048576,MATCH(F$3,PL!$3:$3,0),FALSE) -> 71.77275 | G7: =-VLOOKUP($A7,PL!$1:$1048576,MATCH(G$3,PL!$3:$3,0),FALSE) -> 75.361388 | H7: =-VLOOKUP($A7,PL!$1:$1048576,MATCH(H$3,PL!$3:$3,0),FALSE) -> 79.129457 | I7: =-VLOOKUP($A7,PL!$1:$1048576,MATCH(I$3,PL!$3:$3,0),FALSE) -> 83.08593
A8: Chg WC | B8: Change in Net Working Capital | C8: =VLOOKUP($A8,BS!$1:$1048576,MATCH(C$3,BS!$3:$3,0),FALSE) -> 0 | D8: =VLOOKUP($A8,BS!$1:$1048576,MATCH(D$3,BS!$3:$3,0),FALSE) -> -722.22 | E8: =VLOOKUP($A8,BS!$1:$1048576,MATCH(E$3,BS!$3:$3,0),FALSE) -> -89.661211 | F8: =VLOOKUP($A8,BS!$1:$1048576,MATCH(F$3,BS!$3:$3,0),FALSE) -> -32.014301 | G8: =VLOOKUP($A8,BS!$1:$1048576,MATCH(G$3,BS!$3:$3,0),FALSE) -> -46.141237 | H8: =VLOOKUP($A8,BS!$1:$1048576,MATCH(H$3,BS!$3:$3,0),FALSE) -> -40.287066 | I8: =VLOOKUP($A8,BS!$1:$1048576,MATCH(I$3,BS!$3:$3,0),FALSE) -> -35.309847
A9: Tax | B9: Tax Paid | C9: =VLOOKUP($A9,PL!$1:$1048576,MATCH(C$3,PL!$3:$3,0),FALSE) -> -170.6 | D9: =VLOOKUP($A9,PL!$1:$1048576,MATCH(D$3,PL!$3:$3,0),FALSE) -> -254.997 | E9: =VLOOKUP($A9,PL!$1:$1048576,MATCH(E$3,PL!$3:$3,0),FALSE) -> -314.1332 | F9: =VLOOKUP($A9,PL!$1:$1048576,MATCH(F$3,PL!$3:$3,0),FALSE) -> -378.99653 | G9: =VLOOKUP($A9,PL!$1:$1048576,MATCH(G$3,PL!$3:$3,0),FALSE) -> -440.19191 | H9: =VLOOKUP($A9,PL!$1:$1048576,MATCH(H$3,PL!$3:$3,0),FALSE) -> -498.27354 | I9: =VLOOKUP($A9,PL!$1:$1048576,MATCH(I$3,PL!$3:$3,0),FALSE) -> -562.18557
A10: Net interest | B10: Net interest | C10: =VLOOKUP($A10,PL!$1:$1048576,MATCH(C$3,PL!$3:$3,0),FALSE) -> -7.415 | D10: =VLOOKUP($A10,PL!$1:$1048576,MATCH(D$3,PL!$3:$3,0),FALSE) -> -24.1 | E10: =VLOOKUP($A10,PL!$1:$1048576,MATCH(E$3,PL!$3:$3,0),FALSE) -> -50 | F10: =VLOOKUP($A10,PL!$1:$1048576,MATCH(F$3,PL!$3:$3,0),FALSE) -> -46 | G10: =VLOOKUP($A10,PL!$1:$1048576,MATCH(G$3,PL!$3:$3,0),FALSE) -> -40 | H10: =VLOOKUP($A10,PL!$1:$1048576,MATCH(H$3,PL!$3:$3,0),FALSE) -> -40 | I10: =VLOOKUP($A10,PL!$1:$1048576,MATCH(I$3,PL!$3:$3,0),FALSE) -> -40
A11: Other | B11: Other | D11: =D12-SUM(D6:D10) -> 631.645 | E11: =PL!E40 -> -7.1 | F11: =PL!F40 -> -21.3 | G11: =PL!G40 -> -21.3 | H11: =PL!H40 -> -21.3 | I11: =PL!I40 -> 0
A12: OCF | B12: Net Operating Cash Flow | C12: =C20 -> 273.177 | D12: =D20 -> 598.828 | E12: =SUM(E6:E11) -> 740.67853 | F12: =SUM(F6:F11) -> 946.34651 | G12: =SUM(G6:G11) -> 1085.6314 | H12: =SUM(H6:H11) -> 1237.4535 | I12: =SUM(I6:I11) -> 1424.1614
B14: Receipts from customers (inc. GST) | C14: 3291.324 | D14: 6448.08
B15: Payments to suppliers and employees (inc. GST) | C15: -2928.743 | D15: -5731.414
B16: Interest and other finance costs paid | C16: -64.227 | D16: -91.715
B17: Interest and other finance income received | C17: 56.812 | D17: 67.566
B18: Income taxes paid | C18: -81.989 | D18: -93.689
B20: Net Cash from Operating Activities | C20: =SUM(C14:C18) -> 273.177 | D20: =SUM(D14:D18) -> 598.828 | E20: =E12 -> 740.67853 | F20: =F12 -> 946.34651 | G20: =G12 -> 1085.6314 | H20: =H12 -> 1237.4535 | I20: =I12 -> 1424.1614
A22: Capex | B22: Payments for PPE | C22: -32.838 | D22: -52.562 | E22: -60 | F22: -65 | G22: -70 | H22: -75 | I22: -80
B23: Payments for financial assets at fair value through other comprehensive income | C23: -2.874 | D23: 0 | E23: 0 | F23: 0 | G23: 0 | H23: 0 | I23: 0
B24: Payments for financial assets at fair value through profit or loss | C24: 0 | D24: -2.762 | E24: 0 | F24: 0 | G24: 0 | H24: 0 | I24: 0
B25: Proceeds from acquisition of subsidiaries, net of acquired cash | C25: 0 | D25: 158.359 | E25: 0 | F25: 0 | G25: 0 | H25: 0 | I25: 0
B26: Payment for acquisition of associates | C26: 0 | D26: -3.988 | E26: 0 | F26: 0 | G26: 0 | H26: 0 | I26: 0
B27: Acquisition of intangibles | C27: -8.5 | D27: -5 | E27: 0 | F27: 0 | G27: 0 | H27: 0 | I27: 0
B28: Loans provided to other entities | C28: -10.072 | D28: -26.946 | E28: =D28 -> -26.946 | F28: =E28 -> -26.946 | G28: =F28 -> -26.946 | H28: =G28 -> -26.946 | I28: =H28 -> -26.946
B29: Loan repayments from other entities | C29: 0 | D29: 15.795 | E29: =D29 -> 15.795 | F29: =E29 -> 15.795 | G29: =F29 -> 15.795 | H29: =G29 -> 15.795 | I29: =H29 -> 15.795
A30: Proceeds from business sales | B30: Proceeds from sale of investment | C30: 3.974 | D30: 55.756 | E30: 0 | F30: 0 | G30: 0 | H30: 0 | I30: 0
B31: Distribution from associates | C31: 0.121 | D31: 0.153 | E31: 0 | F31: 0 | G31: 0 | H31: 0 | I31: 0
A32: Lease payments received | B32: Principal elements of lease receipts | C32: 109.478 | D32: 127.661 | E32: =D32*(1+Model!Y$16) -> 135.42673 | F32: =E32*(1+Model!Z$16) -> 140.54074 | G32: =F32*(1+Model!AA$16) -> 147.54884 | H32: =G32*(1+Model!AB$16) -> 154.55694 | I32: =H32*(1+Model!AC$16) -> 161.75444
B34: Net Cash from Investing Activities | C34: =SUM(C22:C32) -> 59.289 | D34: =SUM(D22:D32) -> 266.466 | E34: =SUM(E22:E32) -> 64.275728 | F34: =SUM(F22:F32) -> 64.389745 | G34: =SUM(G22:G32) -> 66.397841 | H34: =SUM(H22:H32) -> 68.405938 | I34: =SUM(I22:I32) -> 70.603442
B36: Proceeds from employee shares exercised | C36: 0 | D36: 7.182 | E36: 0 | F36: 0 | G36: 0 | H36: 0 | I36: 0
B37: Payment for issuance of shares | C37: 0 | D37: -6.416 | E37: 0 | F37: 0 | G37: 0 | H37: 0 | I37: 0
B38: Repayments of loans | C38: -778.039 | D38: -2678.916 | E38: 0 | F38: 0 | G38: 0 | H38: 0 | I38: 0
B39: Proceeds from loans | C39: 855.919 | D39: 3002.803 | E39: 0 | F39: 0 | G39: 0 | H39: 0 | I39: 0
A40: Lease Repayment | B40: Principal elements of lease payments | C40: -124.957 | D40: -139.784 | E40: =D40*(1+Model!Y$16) -> -148.28718 | F40: =E40*(1+Model!Z$16) -> -153.88684 | G40: =F40*(1+Model!AA$16) -> -161.56044 | H40: =G40*(1+Model!AB$16) -> -169.23404 | I40: =H40*(1+Model!AC$16) -> -177.11504
A41: Dividends | B41: Dividends paid to members of the company | C41: -217.701 | D41: -486.036 | E41: =PL!E71*-PL!E45 -> -532.89521 | F41: =PL!F71*-PL!F45 -> -641.69253 | G41: =PL!G71*-PL!G45 -> -744.52773 | H41: =PL!H71*-PL!H45 -> -841.66454 | I41: =PL!I71*-PL!I45 -> -948.78121
B42: Cash distribution to Chemist Warehouse shareholders | C42: 0 | D42: -700 | E42: 0 | F42: 0 | G42: 0 | H42: 0 | I42: 0
B43: Dividends paid to non-controlling interest | C43: -0.41 | D43: 0 | E43: 0 | F43: 0 | G43: 0 | H43: 0 | I43: 0
B44: Transactions with non-controlling interests | C44: 0 | D44: 0.042 | E44: 0 | F44: 0 | G44: 0 | H44: 0 | I44: 0
B46: Net Cash from Financing Activities | C46: =SUM(C36:C44) -> -265.188 | D46: =SUM(D36:D44) -> -1001.125 | E46: =SUM(E36:E44) -> -681.1824 | F46: =SUM(F36:F44) -> -795.57937 | G46: =SUM(G36:G44) -> -906.08817 | H46: =SUM(H36:H44) -> -1010.8986 | I46: =SUM(I36:I44) -> -1125.8962
B48: Cash at Beginning of the Year | C48: 206.647 | D48: 273.124 | E48: =D51 -> 138.774 | F48: =E51 -> 262.54586 | G48: =F51 -> 477.70275 | H48: =G51 -> 723.6438 | I48: =H51 -> 1018.6046
B49: Net Change in Cash | C49: =C12+C34+C46 -> 67.278 | D49: =D12+D34+D46 -> -135.831 | E49: =E12+E34+E46 -> 123.77186 | F49: =F12+F34+F46 -> 215.15689 | G49: =G12+G34+G46 -> 245.94105 | H49: =H12+H34+H46 -> 294.96083 | I49: =I12+I34+I46 -> 368.86863
B50: FX impact | C50: -0.801 | D50: 1.481 | E50: 0 | F50: 0 | G50: 0 | H50: 0 | I50: 0
B51: Cash at end of the year | C51: =SUM(C48:C50) -> 273.124 | D51: =SUM(D48:D50) -> 138.774 | E51: =SUM(E48:E50) -> 262.54586 | F51: =SUM(F48:F50) -> 477.70275 | G51: =SUM(G48:G50) -> 723.6438 | H51: =SUM(H48:H50) -> 1018.6046 | I51: =SUM(I48:I50) -> 1387.4733
A53: Acquisitions | B53: Acquisitions | C53: =C26+C27 -> -8.5 | D53: =D26+D27 -> -8.988 | E53: =E26+E27 -> 0 | F53: =F26+F27 -> 0 | G53: =G26+G27 -> 0 | H53: =H26+H27 -> 0 | I53: =I26+I27 -> 0
A55: Other FCF | B55: Other financing cashflows | C55: =C46-C38-C39-C40-C41-C42 -> -0.41 | D55: =D46-D38-D39-D40-D41-D42 -> 0.808 | E55: =E46-E38-E39-E40-E41-E42 -> 0 | F55: =F46-F38-F39-F40-F41-F42 -> 0 | G55: =G46-G38-G39-G40-G41-G42 -> 0 | H55: =H46-H38-H39-H40-H41-H42 -> 0 | I55: =I46-I38-I39-I40-I41-I42 -> 0
A57: Net lease payments | B57: Net leases | C57: =C40+C32 -> -15.479 | D57: =D40+D32 -> -12.123 | E57: =E40+E32 -> -12.860453 | F57: =F40+F32 -> -13.346092 | G57: =G40+G32 -> -14.011598 | H57: =H40+H32 -> -14.677104 | I57: =I40+I32 -> -15.360596
A58: Net loans provided | B58: Net loands provided | C58: =C28+C29 -> -10.072 | D58: =D28+D29 -> -11.151 | E58: =E28+E29 -> -11.151 | F58: =F28+F29 -> -11.151 | G58: =G28+G29 -> -11.151 | H58: =H28+H29 -> -11.151 | I58: =I28+I29 -> -11.151

Sheet BS
B1: =Model!B1 -> Sigma Healthcare (SIG.AX)
B2: =Model!B2 -> A$M
C3: FY24 | D3: FY25 | E3: FY26E | F3: FY27E | G3: FY28E | H3: FY29E | I3: FY30E
B4: BS
B5: Assets
A6: Cash | B6: Cash | C6: 273.124 | D6: 138.774 | E6: =CF!E51 -> 262.54586 | F6: =CF!F51 -> 477.70275 | G6: =CF!G51 -> 723.6438 | H6: =CF!H51 -> 1018.6046 | I6: =CF!I51 -> 1387.4733
A7: TR | B7: Trade and other receivables | C7: 695.012 | D7: 1575.136 | E7: =E61 -> 1709.8835 | F7: =F61 -> 1838.0483 | G7: =G61 -> 1992.8447 | H7: =H61 -> 2155.2204 | I7: =I61 -> 2327.7711
A8: Inventories | B8: Inventories | C8: 599.903 | D8: 1019.778 | E8: =E65 -> 1171.1085 | F8: =F65 -> 1247.247 | G8: =G65 -> 1281.1144 | H8: =H65 -> 1308.5267 | I8: =I65 -> 1330.1549
B9: Financial assets at amortised cost | C9: 3.808 | D9: 0.512 | E9: =D9 -> 0.512 | F9: =E9 -> 0.512 | G9: =F9 -> 0.512 | H9: =G9 -> 0.512 | I9: =H9 -> 0.512
A10: Lease CA | B10: Lease receivables | C10: 118.628 | D10: 139.656 | E10: =D10 -> 139.656 | F10: =E10 -> 139.656 | G10: =F10 -> 139.656 | H10: =G10 -> 139.656 | I10: =H10 -> 139.656
A11: Other CA | B11: Other assets | C11: 26.144 | D11: 34.573 | E11: =D11 -> 34.573 | F11: =E11 -> 34.573 | G11: =F11 -> 34.573 | H11: =G11 -> 34.573 | I11: =H11 -> 34.573
A13: CA | B13: Total Current Assets | C13: =SUM(C6:C11) -> 1716.619 | D13: =SUM(D6:D11) -> 2908.429 | E13: =SUM(E6:E11) -> 3318.2789 | F13: =SUM(F6:F11) -> 3737.7391 | G13: =SUM(G6:G11) -> 4172.3439 | H13: =SUM(H6:H11) -> 4657.0927 | I13: =SUM(I6:I11) -> 5220.1402
B15: Investments accounted for using the equity method | C15: 45.02 | D15: 43.099 | E15: =D15 -> 43.099 | F15: =E15 -> 43.099 | G15: =F15 -> 43.099 | H15: =G15 -> 43.099 | I15: =H15 -> 43.099
B16: Financial assets at amortised cost | C16: 9.693 | D16: 22.948 | E16: =D16 -> 22.948 | F16: =E16 -> 22.948 | G16: =F16 -> 22.948 | H16: =G16 -> 22.948 | I16: =H16 -> 22.948
B17: Financial assets at fair value through other comprehensive income | C17: 59.454 | D17: 31.986 | E17: =D17-CF!E28-CF!E29 -> 43.137 | F17: =E17-CF!F28-CF!F29 -> 54.288 | G17: =F17-CF!G28-CF!G29 -> 65.439 | H17: =G17-CF!H28-CF!H29 -> 76.59 | I17: =H17-CF!I28-CF!I29 -> 87.741
B18: Financial assets at fair value through profit or loss | C18: 2.262 | D18: 4.708 | E18: =D18 -> 4.708 | F18: =E18 -> 4.708 | G18: =F18 -> 4.708 | H18: =G18 -> 4.708 | I18: =H18 -> 4.708
A19: PPE | B19: PPE | C19: 73.065 | D19: 320.438 | E19: =D19-CF!E22+PL!E15 -> 340.93442 | F19: =E19-CF!F22+PL!F15 -> 364.10258 | G19: =F19-CF!G22+PL!G15 -> 390.17511 | H19: =G19-CF!H22+PL!H15 -> 418.97259 | I19: =H19-CF!I22+PL!I15 -> 450.34695
A20: RoU | B20: Right of use assets | C20: 113.02 | D20: 238.729 | E20: =D20+PL!E14+BS!E81 -> 359.87758 | F20: =E20+PL!F14+BS!F81 -> 485.60101 | G20: =F20+PL!G14+BS!G81 -> 617.59366 | H20: =G20+PL!H14+BS!H81 -> 755.85554 | I20: =H20+PL!I14+BS!I81 -> 900.55608
A21: Intangibles | B21: Intangible assets | C21: 13.3 | D21: 3860.481 | E21: =D21 -> 3860.481 | F21: =E21 -> 3860.481 | G21: =F21 -> 3860.481 | H21: =G21 -> 3860.481 | I21: =H21 -> 3860.481
B22: Deferred tax assets | C22: 87.332 | D22: 28.535 | E22: =D22 -> 28.535 | F22: =E22 -> 28.535 | G22: =F22 -> 28.535 | H22: =G22 -> 28.535 | I22: =H22 -> 28.535
A23: Lease NCA | B23: Lease receivables | C23: 741.823 | D23: 821.668 | E23: =D23-CF!E32 -> 686.24127 | F23: =E23-CF!F32 -> 545.70053 | G23: =F23-CF!G32 -> 398.15169 | H23: =G23-CF!H32 -> 243.59475 | I23: =H23-CF!I32 -> 81.840306
A24: Other NCA | B24: Other assets | C24: 0 | D24: 6.781 | E24: =D24 -> 6.781 | F24: =E24 -> 6.781 | G24: =F24 -> 6.781 | H24: =G24 -> 6.781 | I24: =H24 -> 6.781
A26: NCA | B26: Total Non-Current Assets | C26: =SUM(C15:C24) -> 1144.969 | D26: =SUM(D15:D24) -> 5379.373 | E26: =SUM(E15:E24) -> 5396.7423 | F26: =SUM(F15:F24) -> 5416.2441 | G26: =SUM(G15:G24) -> 5437.9115 | H26: =SUM(H15:H24) -> 5461.5649 | I26: =SUM(I15:I24) -> 5487.0363
B28: Total Assets | C28: =C13+C26 -> 2861.588 | D28: =D13+D26 -> 8287.802 | E28: =E13+E26 -> 8715.0212 | F28: =F13+F26 -> 9153.9832 | G28: =G13+G26 -> 9610.2553 | H28: =H13+H26 -> 10118.658 | I28: =I13+I26 -> 10707.177
B30: Liabilities
A31: TP | B31: Trade and other payables | C31: 745.824 | D31: 1323.603 | E31: =E69 -> 1520.0198 | F31: =F69 -> 1692.3088 | G31: =G69 -> 1834.8313 | H31: =H69 -> 1984.3322 | I31: =I69 -> 2143.2013
B32: Other liabilities | C32: 20.011 | D32: 16.462 | E32: =D32 -> 16.462 | F32: =E32 -> 16.462 | G32: =F32 -> 16.462 | H32: =G32 -> 16.462 | I32: =H32 -> 16.462
A33: Current Borrowings | B33: Borrowings | C33: 32.776 | D33: 35.643 | E33: =D33 -> 35.643 | F33: =E33 -> 35.643 | G33: =F33 -> 35.643 | H33: =G33 -> 35.643 | I33: =H33 -> 35.643
A34: Lease CL | B34: Lease liabilities | C34: 131.325 | D34: 157.975 | E34: =D34 -> 157.975 | F34: =E34 -> 157.975 | G34: =F34 -> 157.975 | H34: =G34 -> 157.975 | I34: =H34 -> 157.975
B35: Current tax liabilities | C35: 2.777 | D35: 124.906 | E35: =D35 -> 124.906 | F35: =E35 -> 124.906 | G35: =F35 -> 124.906 | H35: =G35 -> 124.906 | I35: =H35 -> 124.906
B36: Provisions | C36: 25.897 | D36: 44.276 | E36: =D36 -> 44.276 | F36: =E36 -> 44.276 | G36: =F36 -> 44.276 | H36: =G36 -> 44.276 | I36: =H36 -> 44.276
A38: CL | B38: Total Current Liabilities | C38: =SUM(C31:C36) -> 958.61 | D38: =SUM(D31:D36) -> 1702.865 | E38: =SUM(E31:E36) -> 1899.2818 | F38: =SUM(F31:F36) -> 2071.5708 | G38: =SUM(G31:G36) -> 2214.0933 | H38: =SUM(H31:H36) -> 2363.5942 | I38: =SUM(I31:I36) -> 2522.4633
A40: Other NCL | B40: Other liabilities | C40: 14.77 | D40: 17.104 | E40: =D40 -> 17.104 | F40: =E40 -> 17.104 | G40: =F40 -> 17.104 | H40: =G40 -> 17.104 | I40: =H40 -> 17.104
A41: NC Borrowings | B41: Borrowings | C41: 300 | D41: 855.292 | E41: =D41+CF!E38+CF!E39 -> 855.292 | F41: =E41+CF!F38+CF!F39 -> 855.292 | G41: =F41+CF!G38+CF!G39 -> 855.292 | H41: =G41+CF!H38+CF!H39 -> 855.292 | I41: =H41+CF!I38+CF!I39 -> 855.292
A42: Lease NCA | B42: Lease liabilities | C42: 849.598 | D42: 1021.846 | E42: =D42+CF!E40+E81 -> 1023.5588 | F42: =E42+CF!F40+F81 -> 1025.3363 | G42: =F42+CF!G40+G81 -> 1027.2025 | H42: =G42+CF!H40+H81 -> 1029.1572 | I42: =H42+CF!I40+I81 -> 1031.203
B43: Provisions | C43: 21.712 | D43: 30.1 | E43: =D43 -> 30.1 | F43: =E43 -> 30.1 | G43: =F43 -> 30.1 | H43: =G43 -> 30.1 | I43: =H43 -> 30.1
A45: NCL | B45: Total Non-Current Liabilities | C45: =SUM(C40:C43) -> 1186.08 | D45: =SUM(D40:D43) -> 1924.342 | E45: =SUM(E40:E43) -> 1926.0548 | F45: =SUM(F40:F43) -> 1927.8323 | G45: =SUM(G40:G43) -> 1929.6985 | H45: =SUM(H40:H43) -> 1931.6532 | I45: =SUM(I40:I43) -> 1933.699
B47: Total Liabilities | C47: =C38+C45 -> 2144.69 | D47: =D38+D45 -> 3627.207 | E47: =E38+E45 -> 3825.3366 | F47: =F38+F45 -> 3999.4031 | G47: =G38+G45 -> 4143.7918 | H47: =H38+H45 -> 4295.2474 | I47: =I38+I45 -> 4456.1623
B49: Net Assets | C49: =C28-C47 -> 716.898 | D49: =D28-D47 -> 4660.595 | E49: =E28-E47 -> 4889.6845 | F49: =F28-F47 -> 5154.5801 | G49: =G28-G47 -> 5466.4636 | H49: =H28-H47 -> 5823.4101 | I49: =I28-I47 -> 6251.0142
A51: Contributed Equity | B51: Contributed equity | C51: 553.699 | D51: 4403.299 | E51: =D51+CF!E36 -> 4403.299 | F51: =E51+CF!F36 -> 4403.299 | G51: =F51+CF!G36 -> 4403.299 | H51: =G51+CF!H36 -> 4403.299 | I51: =H51+CF!I36 -> 4403.299
A52: Reserves | B52: Reserves | C52: -54.187 | D52: -6.023 | E52: =D52 -> -6.023 | F52: =E52 -> -6.023 | G52: =F52 -> -6.023 | H52: =G52 -> -6.023 | I52: =H52 -> -6.023
A53: Retained Profits | B53: Retained profits / (accumulated losses) | C53: 222.906 | D53: 273.263 | E53: =D53+PL!E42+CF!E41 -> 494.54666 | F53: =E53+PL!F42+CF!F41 -> 748.25775 | G53: =F53+PL!G42+CF!G41 -> 1046.0411 | H53: =G53+PL!H42+CF!H41 -> 1385.4544 | I53: =H53+PL!I42+CF!I41 -> 1792.075
B54: Equity attributable to the owners of the Group | C54: =SUM(C51:C53) -> 722.418 | D54: =SUM(D51:D53) -> 4670.539 | E54: =SUM(E51:E53) -> 4891.8227 | F54: =SUM(F51:F53) -> 5145.5337 | G54: =SUM(G51:G53) -> 5443.3171 | H54: =SUM(H51:H53) -> 5782.7304 | I54: =SUM(I51:I53) -> 6189.351
A55: Minorities | B55: Non-controlling interests | C55: -5.527 | D55: -9.944 | E55: =D55-PL!E35 -> -2.1381386 | F55: =E55-PL!F35 -> 9.0463083 | G55: =F55-PL!G35 -> 23.146495 | H55: =G55-PL!H35 -> 40.679664 | I55: =H55-PL!I35 -> 61.663292
A57: Equity | B57: Total Equity | C57: =SUM(C54:C55) -> 716.891 | D57: =SUM(D54:D55) -> 4660.595 | E57: =SUM(E54:E55) -> 4889.6845 | F57: =SUM(F54:F55) -> 5154.5801 | G57: =SUM(G54:G55) -> 5466.4636 | H57: =SUM(H54:H55) -> 5823.4101 | I57: =SUM(I54:I55) -> 6251.0142
B58: Check | C58: =C28-C47-C57 -> 0.007 | D58: =D28-D47-D57 -> 0 | E58: =E28-E47-E57 -> 0 | F58: =F28-F47-F57 -> 0 | G58: =G28-G47-G57 -> 0 | H58: =H28-H47-H57 -> 0 | I58: =I28-I47-I57 -> 0
B60: Balance Sheet Metrics
B61: Receivables | C61: =C7 -> 695.012 | D61: =D7 -> 1575.136 | E61: =PL!E$5*E62 -> 1709.8835 | F61: =PL!F$5*F62 -> 1838.0483 | G61: =PL!G$5*G62 -> 1992.8447 | H61: =PL!H$5*H62 -> 2155.2204 | I61: =PL!I$5*I62 -> 2327.7711
B62: % of Network Sales | C62: =C61/PL!C5 -> 0.077207256 | D62: =D61/PL!D5 -> 0.15339495 | E62: 0.145 | F62: 0.14 | G62: =F62 -> 0.14 | H62: =G62 -> 0.14 | I62: =H62 -> 0.14
B63: Receivables Days
B65: Inventory | C65: =C8 -> 599.903 | D65: =D8 -> 1019.778 | E65: =PL!E$5*E66 -> 1171.1085 | F65: =PL!F$5*F66 -> 1247.247 | G65: =PL!G$5*G66 -> 1281.1144 | H65: =PL!H$5*H66 -> 1308.5267 | I65: =PL!I$5*I66 -> 1330.1549
B66: % of Network Sales | C66: =C65/PL!C$5 -> 0.06664182 | D66: =D65/PL!D$5 -> 0.099311292 | E66: =D66 -> 0.099311292 | F66: 0.095 | G66: 0.09 | H66: 0.085 | I66: 0.08
B67: Inventory Days
B69: Payables | C69: =C31 -> 745.824 | D69: =D31 -> 1323.603 | E69: =PL!E$5*E70 -> 1520.0198 | F69: =PL!F$5*F70 -> 1692.3088 | G69: =PL!G$5*G70 -> 1834.8313 | H69: =PL!H$5*H70 -> 1984.3322 | I69: =PL!I$5*I70 -> 2143.2013
B70: % of Network Sales | C70: =C69/PL!C$5 -> 0.082851842 | D70: =D69/PL!D$5 -> 0.12889935 | E70: =D70 -> 0.12889935 | F70: =E70 -> 0.12889935 | G70: =F70 -> 0.12889935 | H70: =G70 -> 0.12889935 | I70: =H70 -> 0.12889935
B71: Payables Days
B73: Net Working Capital | C73: =C61+C65-C69 -> 549.091 | D73: =D61+D65-D69 -> 1271.311 | E73: =E61+E65-E69 -> 1360.9722 | F73: =F61+F65-F69 -> 1392.9865 | G73: =G61+G65-G69 -> 1439.1277 | H73: =H61+H65-H69 -> 1479.4148 | I73: =I61+I65-I69 -> 1514.7247
A74: Chg WC | B74: Change in Net Working Capital | D74: =-(D73-C73) -> -722.22 | E74: =-(E73-D73) -> -89.661211 | F74: =-(F73-E73) -> -32.014301 | G74: =-(G73-F73) -> -46.141237 | H74: =-(H73-G73) -> -40.287066 | I74: =-(I73-H73) -> -35.309847
E75: =E74/D73 -> -0.070526575 | F75: =F74/E73 -> -0.023523111 | G75: =G74/F73 -> -0.033123965 | H75: =H74/G73 -> -0.027994086 | I75: =I74/H73 -> -0.023867442
B76: Cash | D76: =D6 -> 138.774 | E76: =E6 -> 262.54586 | F76: =F6 -> 477.70275 | G76: =G6 -> 723.6438 | H76: =H6 -> 1018.6046 | I76: =I6 -> 1387.4733
B77: Borrowings | D77: =D41+D33 -> 890.935 | E77: =E41+E33 -> 890.935 | F77: =F41+F33 -> 890.935 | G77: =G41+G33 -> 890.935 | H77: =H41+H33 -> 890.935 | I77: =I41+I33 -> 890.935
A78: Net Debt | B78: Net Debt | D78: =D77-D76 -> 752.161 | E78: =E77-E76 -> 628.38914 | F78: =F77-F76 -> 413.23225 | G78: =G77-G76 -> 167.2912 | H78: =H77-H76 -> -127.66963 | I78: =I77-I76 -> -496.53827
A79: Change in ND | B79: Change in Net Debt | E79: =E78-D78 -> -123.77186 | F79: =F78-E78 -> -215.15689 | G79: =G78-F78 -> -245.94105 | H79: =H78-G78 -> -294.96083 | I79: =I78-H78 -> -368.86863
B81: Lease Modelling Adjustment | E81: 150 | F81: =E81*(1+Model!Z16) -> 155.66434 | G81: =F81*(1+Model!AA16) -> 163.42657 | H81: =G81*(1+Model!AB16) -> 171.18881 | I81: =H81*(1+Model!AC16) -> 179.16084
B83: Fixed charges coverage ratio
B84: Lease expense (interest + repayments) | E84: =PL!E26+CF!E40 -> -156.92553 | F84: =PL!F26+CF!F40 -> -162.85139 | G84: =PL!G26+CF!G40 -> -170.97201 | H84: =PL!H26+CF!H40 -> -179.09263 | I84: =PL!I26+CF!I40 -> -187.43273
B85: Non-lease interest | E85: =PL!E27 -> -41.361654 | F85: =PL!F27 -> -37.035451 | G85: =PL!G27 -> -30.588432 | H85: =PL!H27 -> -30.141412 | I85: =PL!I27 -> -29.682312
B86: Total fixed charges | E86: =E84+E85 -> -198.28718 | F86: =F84+F85 -> -199.88684 | G86: =G84+G85 -> -201.56044 | H86: =H84+H85 -> -209.23404 | I86: =I84+I85 -> -217.11504
B87: EBIT + lease expense | E87: =PL!E19-BS!E84 -> 1290.1435 | F87: =PL!F19-BS!F84 -> 1515.736 | G87: =PL!G19-BS!G84 -> 1728.8751 | H87: =PL!H19-BS!H84 -> 1937.2773 | I87: =PL!I19-BS!I84 -> 2166.0037
B88: Fixed charges coverage ratio | E88: =E87/-E86 -> 6.5064391 | F88: =F87/-F86 -> 7.5829705 | G88: =G87/-G86 -> 8.5774528 | H88: =H87/-H86 -> 9.2589009 | I88: =I87/-I86 -> 9.9762949

Sheet Ireland Model
B1: =Model!B1 -> Sigma Healthcare (SIG.AX)
C4: FY04 | D4: FY05 | E4: FY06 | F4: FY07 | G4: FY08 | H4: FY09 | I4: FY10 | J4: FY11 | K4: FY12 | L4: FY13 | M4: FY14 | N4: FY15 | O4: FY16 | P4: FY17 | Q4: FY18 | R4: FY19 | S4: FY20 | T4: FY21 | U4: FY22 | V4: FY23 | W4: FY24 | X4: FY25 | Y4: FY26E | Z4: FY27E | AA4: FY28E | AB4: FY29E | AC4: FY30E
B5: Ireland EUR
B6: Sales | T6: 4.780242 | U6: 19.294349 | V6: 38.165986 | W6: 64.092794 | X6: =W6*(1+X7) -> 99.343831 | Y6: =X6*(1+Y7) -> 151.71222 | Z6: =Y6*(1+Z7) -> 209.84196 | AA6: =Z6*(1+AA7) -> 266.49929 | AB6: =AA6*(1+AB7) -> 316.24582 | AC6: =AB6*(1+AC7) -> 367.74871
B7: Growth % | U7: =U6/T6-1 -> 3.0362703 | V7: =V6/U6-1 -> 0.97809141 | W7: =W6/V6-1 -> 0.67931713 | X7: =SUM(X8:X10) -> 0.55 | Y7: =SUM(Y8:Y10) -> 0.52714286 | Z7: =SUM(Z8:Z10) -> 0.38315789 | AA7: =SUM(AA8:AA10) -> 0.27 | AB7: =SUM(AB8:AB10) -> 0.18666667 | AC7: =SUM(AC8:AC10) -> 0.16285714
B8: LFL Sales Growth % | X8: 0.2 | Y8: 0.2 | Z8: 0.15 | AA8: 0.05 | AB8: 0.05 | AC8: 0.05
B9: Store Growth % | U9: =U13 -> 1 | V9: =V13 -> 0.5 | W9: =W13 -> 0.66666667 | X9: =X13 -> 0.4 | Y9: =Y13 -> 0.35714286 | Z9: =Z13 -> 0.26315789 | AA9: =AA13 -> 0.25 | AB9: =AB13 -> 0.16666667 | AC9: =AC13 -> 0.14285714
B10: Other | X10: -0.05 | Y10: -0.03 | Z10: -0.03 | AA10: -0.03 | AB10: -0.03 | AC10: -0.03
B12: Stores | S12: 0 | T12: 2 | U12: 4 | V12: 6 | W12: 10 | X12: 14 | Y12: =X12+5 -> 19 | Z12: =Y12+5 -> 24 | AA12: 30 | AB12: =AA12+5 -> 35 | AC12: =AB12+5 -> 40
B13: Growth % | U13: =U12/T12-1 -> 1 | V13: =V12/U12-1 -> 0.5 | W13: =W12/V12-1 -> 0.66666667 | X13: =X12/W12-1 -> 0.4 | Y13: =Y12/X12-1 -> 0.35714286 | Z13: =Z12/Y12-1 -> 0.26315789 | AA13: =AA12/Z12-1 -> 0.25 | AB13: =AB12/AA12-1 -> 0.16666667 | AC13: =AC12/AB12-1 -> 0.14285714
B15: Sales/Store | T15: =T6/T12 -> 2.390121 | U15: =U6/U12 -> 4.8235873 | V15: =V6/V12 -> 6.3609977 | W15: =W6/W12 -> 6.4092794 | X15: =X6/X12 -> 7.0959879 | Y15: =Y6/Y12 -> 7.9848538 | Z15: =Z6/Z12 -> 8.7434149 | AA15: =AA6/AA12 -> 8.8833095 | ... AC15: =AC6/AC12 -> 9.1937177
B16: Growth % | U16: =U15/T15-1 -> 1.0181352 | V16: =V15/U15-1 -> 0.31872761 | W16: =W15/V15-1 -> 0.0075902769 | X16: =X15/W15-1 -> 0.10714286 | Y16: =Y15/X15-1 -> 0.12526316 | Z16: =Z15/Y15-1 -> 0.095 | AA16: =AA15/Z15-1 -> 0.016 | AB16: =AB15/AA15-1 -> 0.017142857 | AC16: =AC15/AB15-1 -> 0.0175
B18: Gross Profit | T18: 0.881843 | U18: 4.125561 | V18: 7.341177 | W18: 15.218017 | X18: =X20*X6 -> 24.084646 | Y18: =Y20*Y6 -> 37.235831 | Z18: =Z20*Z6 -> 52.13256 | AA18: =AA20*AA6 -> 66.208351 | AB18: =AB20*AB6 -> 78.567243 | AC18: =AC20*AC6 -> 91.362479
B19: Growth % | U19: =U18/T18-1 -> 3.6783396 | V19: =V18/U18-1 -> 0.77943727 | W19: =W18/V18-1 -> 1.0729669 | X19: =X18/W18-1 -> 0.5826402 | Y19: =Y18/X18-1 -> 0.54604024 | Z19: =Z18/Y18-1 -> 0.40006435 | AA19: =AA18/Z18-1 -> 0.27 | AB19: =AB18/AA18-1 -> 0.18666667 | AC19: =AC18/AB18-1 -> 0.16285714
B20: Gross Margin | T20: =T18/T$6 -> 0.18447664 | U20: =U18/U$6 -> 0.21382224 | V20: =V18/V$6 -> 0.19234868 | W20: =W18/W$6 -> 0.23743725 | X20: =W20+X21 -> 0.24243725 | Y20: =X20+Y21 -> 0.24543725 | Z20: =Y20+Z21 -> 0.24843725 | AA20: =Z20+AA21 -> 0.24843725 | AB20: =AA20+AB21 -> 0.24843725 | AC20: =AB20+AC21 -> 0.24843725
B21: Change YoY % | U21: =U20-T20 -> 0.0293456 | V21: =V20-U20 -> -0.021473565 | W21: =W20-V20 -> 0.045088575 | X21: 0.005 | Y21: 0.003 | Z21: 0.003 | AA21: 0 | AB21: 0 | AC21: 0
B23: CODB | T23: =T33-T18 -> -2.812957 | U23: =U33-U18 -> -5.984899 | V23: =V33-V18 -> -12.02973 | W23: =W33-W18 -> -16.344329 | X23: =W23*(1+X24) -> -20.430411 | Y23: =X23*(1+Y24) -> -26.559535 | Z23: =Y23*(1+Z24) -> -33.199418 | AA23: =Z23*(1+AA24) -> -39.839302 | AB23: =AA23*(1+AB24) -> -43.823232 | AC23: =AB23*(1+AC24) -> -48.205555
B24: Growth % | U24: =U23/T23-1 -> 1.1276184 | V24: =V23/U23-1 -> 1.0100139 | W24: =W23/V23-1 -> 0.35866133 | X24: 0.25 | Y24: 0.3 | Z24: 0.25 | AA24: 0.2 | AB24: 0.1 | AC24: 0.1
B25: % of Sales | T25: =T23/T$6 -> -0.58845494 | U25: =U23/U$6 -> -0.31018922 | V25: =V23/V$6 -> -0.31519505 | W25: =W23/W$6 -> -0.2550104 | X25: =X23/X$6 -> -0.20565355 | Y25: =Y23/Y$6 -> -0.17506523 | Z25: =Z23/Z$6 -> -0.15821154 | AA25: =AA23/AA$6 -> -0.14949121 | ... AC25: =AC23/AC$6 -> -0.13108287
B26: Change YoY % | T26: . | U26: =U25-T25 -> 0.27826572 | V26: =V25-U25 -> -0.005005837 | W26: =W25-V25 -> 0.060184654 | X26: =X25-W25 -> 0.049356852 | Y26: =Y25-X25 -> 0.03058832 | Z26: =Z25-Y25 -> 0.016853692 | AA26: =AA25-Z25 -> 0.0087203209 | AB26: =AB25-AA25 -> 0.010917898 | AC26: =AC25-AB25 -> 0.0074904496
B28: Staff costs | T28: -1.070332 | U28: -3.67721 | V28: -6.11196 | W28: -10.000083
B29: % of Sales | T29: =T28/T$6 -> -0.22390749 | U29: =U28/U$6 -> -0.19058482 | V29: =V28/V$6 -> -0.16014155 | W29: =W28/W$6 -> -0.15602508
B30: Other costs | T30: =T23-T28 -> -1.742625 | U30: =U23-U28 -> -2.307689 | V30: =V23-V28 -> -5.91777 | W30: =W23-W28 -> -6.344246
B31: % of Sales | T31: =T30/T$6 -> -0.36454744 | U31: =U30/U$6 -> -0.1196044 | V31: =V30/V$6 -> -0.15505351 | W31: =W30/W$6 -> -0.098985324
B33: EBITDA | T33: =T45-T40 -> -1.931114 | U33: =U45-U40 -> -1.859338 | V33: =V45-V40 -> -4.688553 | W33: =W45-W40 -> -1.126312 | X33: =X23+X18 -> 3.6542343 | Y33: =Y23+Y18 -> 10.676296 | Z33: =Z23+Z18 -> 18.933141 | AA33: =AA23+AA18 -> 26.369049 | AB33: =AB23+AB18 -> 34.744011 | AC33: =AC23+AC18 -> 43.156924
B34: Growth % | U34: =U33/T33-1 -> -0.037168184 | V34: =V33/U33-1 -> 1.5216249 | W34: =W33/V33-1 -> -0.75977407 | X34: =X33/W33-1 -> -4.2444245 | Y34: =Y33/X33-1 -> 1.9216234 | Z34: =Z33/Y33-1 -> 0.77338101 | AA34: =AA33/Z33-1 -> 0.39274557 | AB34: =AB33/AA33-1 -> 0.31760577 | AC34: =AC33/AB33-1 -> 0.24213996
B35: EBITDA Margin | T35: =T33/T$6 -> -0.40397829 | U35: =U33/U$6 -> -0.096366973 | V35: =V33/V$6 -> -0.12284637 | W35: =W33/W$6 -> -0.017573146 | X35: =X33/X$6 -> 0.036783706 | Y35: =Y33/Y$6 -> 0.070372026 | Z35: =Z33/Z$6 -> 0.090225718 | AA35: =AA33/AA$6 -> 0.098946039 | ... AC35: =AC33/AC$6 -> 0.11735439
B36: Change YoY % | T36: . | U36: =U35-T35 -> 0.30761132 | V36: =V35-U35 -> -0.026479402 | W36: =W35-V35 -> 0.10527323 | X36: =X35-W35 -> 0.054356852 | Y36: =Y35-X35 -> 0.03358832 | Z36: =Z35-Y35 -> 0.019853692 | AA36: =AA35-Z35 -> 0.0087203209 | AB36: =AB35-AA35 -> 0.010917898 | AC36: =AC35-AB35 -> 0.0074904496
B38: Leases | U38: -0.420089 | W38: -0.766732
B39: Non-leases | U39: =U40-U38 -> -0.227811 | W39: =W40-W38 -> -0.745118
B40: D&A | T40: -0.197601 | U40: -0.6479 | V40: -0.429643 | W40: -1.51185 | X40: =W40*(1+X$9) -> -2.11659 | Y40: =X40*(1+Y$9) -> -2.872515 | Z40: =Y40*(1+Z$9) -> -3.62844 | AA40: =Z40*(1+AA$9) -> -4.53555 | AB40: =AA40*(1+AB$9) -> -5.291475 | AC40: =AB40*(1+AC$9) -> -6.0474
B41: Growth % | U41: =U40/T40-1 -> 2.2788296 | V41: =V40/U40-1 -> -0.33686834 | W41: =W40/V40-1 -> 2.5188517 | X41: =X40/W40-1 -> 0.4 | Y41: =Y40/X40-1 -> 0.35714286 | Z41: =Z40/Y40-1 -> 0.26315789 | AA41: =AA40/Z40-1 -> 0.25 | AB41: =AB40/AA40-1 -> 0.16666667 | AC41: =AC40/AB40-1 -> 0.14285714
B42: % of Sales | U42: =U40/U$6 -> -0.03357978 | V42: =V40/V$6 -> -0.011257223 | W42: =W40/W$6 -> -0.023588455 | X42: =X40/X$6 -> -0.021305701 | Y42: =Y40/Y$6 -> -0.018933972 | Z42: =Z40/Z$6 -> -0.017291299 | AA42: =AA40/AA$6 -> -0.017018995 | AB42: =AB40/AB$6 -> -0.016732158 | AC42: =AC40/AC$6 -> -0.016444381
B43: Change YoY % | U43: =U42-T42 -> -0.03357978 | V43: =V42-U42 -> 0.022322558 | W43: =W42-V42 -> -0.012331233 | X43: =X42-W42 -> 0.0022827537 | Y43: =Y42-X42 -> 0.0023717292 | Z43: =Z42-Y42 -> 0.0016426734 | AA43: =AA42-Z42 -> 0.00027230392 | AB43: =AB42-AA42 -> 0.00028683699 | AC43: =AC42-AB42 -> 0.00028777667
B45: EBIT | T45: -2.128715 | U45: -2.507238 | V45: -5.118196 | W45: -2.638162 | X45: =X33+X40 -> 1.5376443 | Y45: =Y33+Y40 -> 7.8037814 | Z45: =Z33+Z40 -> 15.304701 | AA45: =AA33+AA40 -> 21.833499 | AB45: =AB33+AB40 -> 29.452536 | AC45: =AC33+AC40 -> 37.109524
B46: Growth % | U46: =U45/T45-1 -> 0.1778176 | V46: =V45/U45-1 -> 1.0413682 | W46: =W45/V45-1 -> -0.48455237 | X46: =X45/W45-1 -> -1.5828468 | Y46: =Y45/X45-1 -> 4.075154 | Z46: =Z45/Y45-1 -> 0.96119041 | AA46: =AA45/Z45-1 -> 0.42658771 | AB46: =AB45/AA45-1 -> 0.34896088 | AC46: =AC45/AB45-1 -> 0.25997722
B47: EBIT Margin | T47: =T45/T$6 -> -0.44531532 | U47: =U45/U$6 -> -0.12994675 | V47: =V45/V$6 -> -0.1341036 | W47: =W45/W$6 -> -0.041161601 | X47: =X45/X$6 -> 0.015478004 | Y47: =Y45/Y$6 -> 0.051438054 | Z47: =Z45/Z$6 -> 0.072934419 | AA47: =AA45/AA$6 -> 0.081927044 | ... AC47: =AC45/AC$6 -> 0.10091
B48: Change YoY % | U48: =U47-T47 -> 0.31536857 | V48: =V47-U47 -> -0.004156844 | W48: =W47-V47 -> 0.092941996 | X48: =X47-W47 -> 0.056639605 | Y48: =Y47-X47 -> 0.035960049 | Z48: =Z47-Y47 -> 0.021496365 | AA48: =AA47-Z47 -> 0.0089926248 | AB48: =AB47-AA47 -> 0.011204735 | AC48: =AC47-AB47 -> 0.0077782263
B50: Lease interest | T50: -0.057637 | U50: -0.149509 | V50: -0.191317 | W50: -0.329126 | X50: =X52 -> -0.4607764 | Y50: =Y52 -> -0.6253394 | Z50: =Z52 -> -0.7899024 | AA50: =AA52 -> -0.987378 | AB50: =AB52 -> -1.151941 | AC50: =AC52 -> -1.316504
B51: Non-lease interest | T51: =T52-T50 -> 0 | U51: =U52-U50 -> -0.184517 | V51: =V52-V50 -> 0 | W51: =W52-W50 -> 0
B52: Interest | T52: -0.057637 | U52: -0.334026 | V52: -0.191317 | W52: -0.329126 | X52: =W52*(1+X$9) -> -0.4607764 | Y52: =X52*(1+Y$9) -> -0.6253394 | Z52: =Y52*(1+Z$9) -> -0.7899024 | AA52: =Z52*(1+AA$9) -> -0.987378 | AB52: =AA52*(1+AB$9) -> -1.151941 | AC52: =AB52*(1+AC$9) -> -1.316504
B53: Growth % | U53: =U52/T52-1 -> 4.7953398 | V53: =V52/U52-1 -> -0.4272392 | W53: =W52/V52-1 -> 0.72031759 | X53: =X52/W52-1 -> 0.4 | Y53: =Y52/X52-1 -> 0.35714286 | Z53: =Z52/Y52-1 -> 0.26315789 | AA53: =AA52/Z52-1 -> 0.25 | AB53: =AB52/AA52-1 -> 0.16666667 | AC53: =AC52/AB52-1 -> 0.14285714
B54: % of Sales | U54: =U52/U$6 -> -0.017312116 | V54: =V52/V$6 -> -0.0050127619 | W54: =W52/W$6 -> -0.0051351483 | X54: =X52/X$6 -> -0.0046381984 | Y54: =Y52/Y$6 -> -0.0041218789 | Z54: =Z52/Z$6 -> -0.0037642729 | AA54: =AA52/AA$6 -> -0.0037049931 | AB54: =AB52/AB$6 -> -0.0036425493 | AC54: =AC52/AC$6 -> -0.0035799011
B55: Change YoY % | U55: =U54-T54 -> -0.017312116 | V55: =V54-U54 -> 0.012299354 | W55: =W54-V54 -> -0.00012238638 | X55: =X54-W54 -> 0.00049694983 | Y55: =Y54-X54 -> 0.00051631956 | Z55: =Z54-Y54 -> 0.00035760593 | AA55: =AA54-Z54 -> 5.9279889e-05 | AB55: =AB54-AA54 -> 6.2443703e-05 | AC55: =AC54-AB54 -> 6.2648269e-05
B57: PBT | T57: =T45+T52 -> -2.186352 | U57: =U45+U52 -> -2.841264 | V57: =V45+V52 -> -5.309513 | W57: =W45+W52 -> -2.967288 | X57: =X45+X52 -> 1.0768679 | Y57: =Y45+Y52 -> 7.178442 | Z57: =Z45+Z52 -> 14.514799 | AA57: =AA45+AA52 -> 20.846121 | ... AC57: =AC45+AC52 -> 35.79302
B58: Growth % | U58: =U57/T57-1 -> 0.29954554 | V58: =V57/U57-1 -> 0.86871512 | W58: =W57/V57-1 -> -0.44113745 | X58: =X57/W57-1 -> -1.3629132 | Y58: =Y57/X57-1 -> 5.666038 | Z58: =Z57/Y57-1 -> 1.0219985 | AA58: =AA57/Z57-1 -> 0.4361977 | AB58: =AB57/AA57-1 -> 0.35759526 | AC58: =AC57/AB57-1 -> 0.26474445
B59: PBT Margin | T59: =T57/T$6 -> -0.45737266 | U59: =U57/U$6 -> -0.14725887 | V59: =V57/V$6 -> -0.13911636 | W59: =W57/W$6 -> -0.046296749 | X59: =X57/X$6 -> 0.010839806 | Y59: =Y57/Y$6 -> 0.047316175 | Z59: =Z57/Z$6 -> 0.069170146 | AA59: =AA57/AA$6 -> 0.078222051 | ... AC59: =AC57/AC$6 -> 0.097330104
B60: Change YoY % | U60: =U59-T59 -> 0.31011379 | V60: =V59-U59 -> 0.0081425096 | W60: =W59-V59 -> 0.09281961 | X60: =X59-W59 -> 0.057136555 | Y60: =Y59-X59 -> 0.036476369 | Z60: =Z59-Y59 -> 0.021853971 | AA60: =AA59-Z59 -> 0.0090519047 | AB60: =AB59-AA59 -> 0.011267178 | AC60: =AC59-AB59 -> 0.0078408745
B62: Tax | T62: 0.325126 | U62: 0.522903 | V62: 0.767641 | W62: 0.554769 | X62: =IF(X57>0,X57*-X63,0) -> -0.13460848 | Y62: =IF(Y57>0,Y57*-Y63,0) -> -0.89730525 | Z62: =IF(Z57>0,Z57*-Z63,0) -> -1.8143499 | AA62: =IF(AA57>0,AA57*-AA63,0) -> -2.6057651 | AB62: =IF(AB57>0,AB57*-AB63,0) -> -3.5375743 | AC62: =IF(AC57>0,AC57*-AC63,0) -> -4.4741275
B63: Tax rate | T63: =-T62/T57 -> 0.14870707 | U63: =-U62/U57 -> 0.18403886 | V63: =-V62/V57 -> 0.14457842 | W63: =-W62/W57 -> 0.18696163 | X63: 0.125 | Y63: 0.125 | Z63: 0.125 | AA63: 0.125 | AB63: 0.125 | AC63: 0.125
B65: NPAT | T65: =T57+T62 -> -1.861226 | U65: =U57+U62 -> -2.318361 | V65: =V57+V62 -> -4.541872 | W65: =W57+W62 -> -2.412519 | X65: =X57+X62 -> 0.94225937 | Y65: =Y57+Y62 -> 6.2811367 | Z65: =Z57+Z62 -> 12.700449 | AA65: =AA57+AA62 -> 18.240356 | ... AC65: =AC57+AC62 -> 31.318892
B66: Growth % | U66: =U65/T65-1 -> 0.24560961 | V66: =V65/U65-1 -> 0.95908748 | W66: =W65/V65-1 -> -0.46882717 | X66: =X65/W65-1 -> -1.3905708 | Y66: =Y65/X65-1 -> 5.666038 | Z66: =Z65/Y65-1 -> 1.0219985 | AA66: =AA65/Z65-1 -> 0.4361977 | AB66: =AB65/AA65-1 -> 0.35759526 | AC66: =AC65/AB65-1 -> 0.26474445
B68: Ireland Model Summary AUD $m | T68: =T4 -> FY21 | U68: =U4 -> FY22 | V68: =V4 -> FY23 | W68: =W4 -> FY24 | X68: =X4 -> FY25 | Y68: =Y4 -> FY26E | Z68: =Z4 -> FY27E | AA68: =AA4 -> FY28E | ... AC68: =AC4 -> FY30E
B69: AUD EUR | T69: 0.62611714 | U69: 0.64430271 | V69: 0.64363807 | W69: 0.60636965 | X69: 0.5931988 | Y69: 0.57 | Z69: 0.57 | AA69: 0.57 | AB69: 0.57 | AC69: 0.57
B70: Change YoY % | U70: =U69/T69-1 -> 0.029044997 | V70: =V69/U69-1 -> -0.0010315615 | W70: =W69/V69-1 -> -0.057902761 | X70: =X69/W69-1 -> -0.021720825 | Y70: =Y69/X69-1 -> -0.039107971 | Z70: =Z69/Y69-1 -> 0 | AA70: =AA69/Z69-1 -> 0 | AB70: =AB69/AA69-1 -> 0 | AC70: =AC69/AB69-1 -> 0
B72: Sales | T72: =T6/T$69 -> 7.6347407 | U72: =U6/U$69 -> 29.946093 | V72: =V6/V$69 -> 59.297278 | W72: =W6/W$69 -> 105.69921 | X72: =X6/X$69 -> 167.47139 | Y72: =Y6/Y$69 -> 266.16179 | Z72: =Z6/Z$69 -> 368.14378 | AA72: =AA6/AA$69 -> 467.54261 | ... AC72: =AC6/AC$69 -> 645.17317
B73: Growth % | U73: =U72/T72-1 -> 2.9223458 | V73: =V72/U72-1 -> 0.98013404 | W73: =W72/V72-1 -> 0.78253057 | X73: =X72/W72-1 -> 0.5844148 | Y73: =Y72/X72-1 -> 0.58929704 | Z73: =Z72/Y72-1 -> 0.38315789 | AA73: =AA72/Z72-1 -> 0.27 | AB73: =AB72/AA72-1 -> 0.18666667 | AC73: =AC72/AB72-1 -> 0.16285714
B75: Stores | T75: =T12 -> 2 | U75: =U12 -> 4 | V75: =V12 -> 6 | W75: =W12 -> 10 | X75: =X12 -> 14 | Y75: =Y12 -> 19 | Z75: =Z12 -> 24 | AA75: =AA12 -> 30 | ... AC75: =AC12 -> 40
B76: Growth % | U76: =U75/T75-1 -> 1 | V76: =V75/U75-1 -> 0.5 | W76: =W75/V75-1 -> 0.66666667 | X76: =X75/W75-1 -> 0.4 | Y76: =Y75/X75-1 -> 0.35714286 | Z76: =Z75/Y75-1 -> 0.26315789 | AA76: =AA75/Z75-1 -> 0.25 | AB76: =AB75/AA75-1 -> 0.16666667 | AC76: =AC75/AB75-1 -> 0.14285714
B78: Sales/store | T78: =T15/T$69 -> 3.8173703 | U78: =U15/U$69 -> 7.4865233 | V78: =V15/V$69 -> 9.8828797 | W78: =W15/W$69 -> 10.569921 | X78: =X15/X$69 -> 11.962242 | Y78: =Y15/Y$69 -> 14.008515 | Z78: =Z15/Z$69 -> 15.339324 | AA78: =AA15/AA$69 -> 15.584754 | ... AC78: =AC15/AC$69 -> 16.129329
B79: Growth % | U79: =U78/T78-1 -> 0.96117291 | V79: =V78/U78-1 -> 0.32008936 | W79: =W78/V78-1 -> 0.069518342 | X79: =X78/W78-1 -> 0.13172486 | Y79: =Y78/X78-1 -> 0.17106098 | Z79: =Z78/Y78-1 -> 0.095 | AA79: =AA78/Z78-1 -> 0.016 | AB79: =AB78/AA78-1 -> 0.017142857 | AC79: =AC78/AB78-1 -> 0.0175
B81: CODB | U81: =U23/U69 -> -9.2889552 | V81: =V23/V69 -> -18.690209 | W81: =W23/W69 -> -26.954398 | X81: =X23/X69 -> -34.441087 | Y81: =Y23/Y69 -> -46.595675 | Z81: =Z23/Z69 -> -58.244593 | AA81: =AA23/AA69 -> -69.893512 | AB81: =AB23/AB69 -> -76.882863 | AC81: =AC23/AC69 -> -84.57115
B82: Growth % | V82: =V81/U81-1 -> 1.0120895 | W82: =W81/V81-1 -> 0.44216677 | X82: =X81/W81-1 -> 0.27775387 | Y82: =Y81/X81-1 -> 0.35290955 | Z82: =Z81/Y81-1 -> 0.25 | AA82: =AA81/Z81-1 -> 0.2 | AB82: =AB81/AA81-1 -> 0.1 | AC82: =AC81/AB81-1 -> 0.1
B84: EBITDA | T84: =T33/T$69 -> -3.0842695 | U84: =U33/U$69 -> -2.8858143 | V84: =V33/V$69 -> -7.2844557 | W84: =W33/W$69 -> -1.8574676 | X84: =X33/X$69 -> 6.1602185 | Y84: =Y33/Y$69 -> 18.730345 | Z84: =Z33/Z$69 -> 33.216037 | AA84: =AA33/AA$69 -> 46.261489 | ... AC84: =AC33/AC$69 -> 75.713902
B85: Growth % | U85: =U84/T84-1 -> -0.0643443 | V85: =V84/U84-1 -> 1.5242288 | W85: =W84/V84-1 -> -0.74500941 | X85: =X84/W84-1 -> -4.3164608 | Y85: =Y84/X84-1 -> 2.0405325 | Z85: =Z84/Y84-1 -> 0.77338101 | AA85: =AA84/Z84-1 -> 0.39274557 | AB85: =AB84/AA84-1 -> 0.31760577 | AC85: =AC84/AB84-1 -> 0.24213996
B87: EBIT | T87: =T45/T$69 -> -3.399867 | U87: =U45/U$69 -> -3.8913976 | V87: =V45/V$69 -> -7.9519783 | W87: =W45/W$69 -> -4.3507487 | X87: =X45/X$69 -> 2.592123 | Y87: =Y45/Y$69 -> 13.690845 | Z87: =Z45/Z$69 -> 26.850353 | AA87: =AA45/AA$69 -> 38.304384 | ... AC87: =AC45/AC$69 -> 65.104428
B88: Growth % | U88: =U87/T87-1 -> 0.14457347 | V88: =V87/U87-1 -> 1.0434762 | W88: =W87/V87-1 -> -0.45287216 | X88: =X87/W87-1 -> -1.5957878 | Y88: =Y87/X87-1 -> 4.281711 | Z88: =Z87/Y87-1 -> 0.96119041 | AA88: =AA87/Z87-1 -> 0.42658771 | AB88: =AB87/AA87-1 -> 0.34896088 | AC88: =AC87/AB87-1 -> 0.25997722
B89: Margin % | T89: =T87/T$72 -> -0.44531532 | U89: =U87/U$72 -> -0.12994675 | V89: =V87/V$72 -> -0.1341036 | W89: =W87/W$72 -> -0.041161601 | X89: =X87/X$72 -> 0.015478004 | Y89: =Y87/Y$72 -> 0.051438054 | Z89: =Z87/Z$72 -> 0.072934419 | AA89: =AA87/AA$72 -> 0.081927044 | ... AC89: =AC87/AC$72 -> 0.10091
B91: PBT | T91: =T57/T$69 -> -3.4919217 | U91: =U57/U$69 -> -4.4098278 | V91: =V57/V$69 -> -8.2492215 | W91: =W57/W$69 -> -4.8935299 | X91: =X57/X$69 -> 1.8153574 | Y91: =Y57/Y$69 -> 12.593758 | Z91: =Z57/Z$69 -> 25.464559 | AA91: =AA57/AA$69 -> 36.572141 | ... AC91: =AC57/AC$69 -> 62.794772
B92: Growth % | U92: =U91/T91-1 -> 0.26286562 | V92: =V91/U91-1 -> 0.87064481 | W92: =W91/V91-1 -> -0.40678888 | X92: =X91/W91-1 -> -1.370971 | Y92: =Y91/X91-1 -> 5.9373434 | Z92: =Z91/Y91-1 -> 1.0219985 | AA92: =AA91/Z91-1 -> 0.4361977 | AB92: =AB91/AA91-1 -> 0.35759526 | AC92: =AC91/AB91-1 -> 0.26474445
B93: Margin % | T93: =T91/T$72 -> -0.45737266 | U93: =U91/U$72 -> -0.14725887 | V93: =V91/V$72 -> -0.13911636 | W93: =W91/W$72 -> -0.046296749 | X93: =X91/X$72 -> 0.010839806 | Y93: =Y91/Y$72 -> 0.047316175 | Z93: =Z91/Z$72 -> 0.069170146 | AA93: =AA91/AA$72 -> 0.078222051 | ... AC93: =AC91/AC$72 -> 0.097330104
B95: NPAT | T95: =T65/T$69 -> -2.9726482 | U95: =U65/U$69 -> -3.5982481 | V95: =V65/V$69 -> -7.0565621 | W95: =W65/W$69 -> -3.9786276 | X95: =X65/X$69 -> 1.5884378 | Y95: =Y65/Y$69 -> 11.019538 | Z95: =Z65/Z$69 -> 22.281489 | AA95: =AA65/AA$69 -> 32.000624 | ... AC95: =AC65/AC$69 -> 54.945425
B96: Growth % | U96: =U95/T95-1 -> 0.21045204 | V96: =V95/U95-1 -> 0.96111048 | W96: =W95/V95-1 -> -0.43618046 | X96: =X95/W95-1 -> -1.3992426 | Y96: =Y95/X95-1 -> 5.9373434 | Z96: =Z95/Y95-1 -> 1.0219985 | AA96: =AA95/Z95-1 -> 0.4361977 | AB96: =AB95/AA95-1 -> 0.35759526 | AC96: =AC95/AB95-1 -> 0.26474445
B97: Margin % | T97: =T95/T$72 -> -0.38935811 | U97: =U95/U$72 -> -0.12015751 | V97: =V95/V$72 -> -0.11900314 | W97: =W95/W$72 -> -0.037641033 | X97: =X95/X$72 -> 0.0094848303 | Y97: =Y95/Y$72 -> 0.041401653 | Z97: =Z95/Z$72 -> 0.060523878 | AA97: =AA95/AA$72 -> 0.068444294 | ... AC97: =AC95/AC$72 -> 0.085163841
B99: 30% Minority Interest | U99: =U95*0.3 -> -1.0794744 | V99: =V95*0.3 -> -2.1169686 | W99: =W95*0.3 -> -1.1935883 | X99: =X95*0.3 -> 0.47653133 | Y99: =Y95*0.3 -> 3.3058614 | Z99: =Z95*0.3 -> 6.6844468 | AA99: =AA95*0.3 -> 9.6001871 | AB99: =AB95*0.3 -> 13.033169 | AC99: =AC95*0.3 -> 16.483628
B101: Balance Sheet Metrics
B102: Receivables | V102: =0.263826+0.712154 -> 0.97598 | W102: =0.38956+0.340624+0.226005 -> 0.956189
B103: % of Sales | V103: =V102/V6 -> 0.025571984 | W103: =W102/W6 -> 0.014918822
B104: Receivables Days
B106: Inventory | V106: 11.500427 | W106: 16.334434
B107: % of Sales | V107: =V106/V6 -> 0.30132661 | W107: =W106/W6 -> 0.25485601
B108: Inventory Days
B110: Payables | V110: 0.378256 | W110: 0.798411
B111: % of Sales | V111: =V110/V6 -> 0.0099108143 | W111: =W110/W6 -> 0.01245711
B112: Payables Days
B114: Net Working Capital | V114: =V102+V106-V110 -> 12.098151 | W114: =W102+W106-W110 -> 16.492212
B115: Change in Net Working Capital | W115: =-(W114-V114) -> -4.394061
B116: Change YoY %
B118: Cash | V118: 4.359532 | W118: 3.243819
B119: Borrowings | V119: 0 | W119: 0
B120: Net Debt / (cash) | V120: =V119-V118 -> -4.359532 | W120: =W119-W118 -> -3.243819
B121: Change in Net Debt | W121: =W120-V120 -> 1.115713
B124: Non-Lease Capex | W124: =-9.862476+6.078917 -> -3.783559

Sheet Valuation
C1: =Model!B1 -> Sigma Healthcare (SIG.AX)
C6: VALUATION SUMMARY Sigma Healthcare (SIG.AX)
C9: Goldman Sachs | Sigma Healthcare Valuation | SIG-AU
C11: Discounted Cash Flow | D11: Weighting | E11: Value (A$m)
C12: =T56 -> Present Value of FCF | D12: 1 | E12: =$W$56 -> 19151.292
C13: =T57 -> Terminal Value | E13: =$W$57 -> 22885.368
C14: =T58 -> Total EV | E14: =$W$58 -> 42036.66
C15: =T59 -> Less: Net Debt | E15: =$W$59 -> -628.38914
C16: =T60 -> Less Minority Interest | E16: =$W$60 -> -577
C17: =T61 -> Equity Value | E17: =$W$61 -> 40831.271
C18: =T62 -> Shares | E18: =$W$62 -> 11540
C19: Implied Value Per Share | E19: =$W$63 -> 3.5
C22: Final Price Target | E22: =$E$19 -> 3.5
C23: Upside/Downside to Px | E23: =E22/D65-1 -> 0.19863014
C27: DISCOUNTED CASH FLOW MODEL Sigma Healthcare (SIG.AX)
C30: DISCOUNTED CASH FLOW MODEL Sigma Healthcare (SIG.AX) | G30: 2 | H30: 3 | I30: 4
D31: FY25 | E31: FY26E | F31: FY27E | G31: FY28E | H31: FY29E | I31: FY30E | J31: FY31E | K31: FY32E | L31: FY33E | M31: FY34E | N31: FY35E | O31: FY36E | P31: FY37E | Q31: FY38E | R31: FY39E | S31: FY40E | T31: FY41E | U31: FY42E | V31: FY43E | W31: FY45E
A32: Total network sales | C32: Network Sales | D32: =VLOOKUP($A32,Model!$1:$1048576,MATCH(D$31,Model!$3:$3,0),FALSE) -> 10268.5 | E32: =VLOOKUP($A32,Model!$1:$1048576,MATCH(E$31,Model!$3:$3,0),FALSE) -> 11792.3 | F32: =VLOOKUP($A32,Model!$1:$1048576,MATCH(F$31,Model!$3:$3,0),FALSE) -> 13128.916 | G32: =VLOOKUP($A32,Model!$1:$1048576,MATCH(G$31,Model!$3:$3,0),FALSE) -> 14234.605 | H32: =VLOOKUP($A32,Model!$1:$1048576,MATCH(H$31,Model!$3:$3,0),FALSE) -> 15394.431 | I32: =VLOOKUP($A32,Model!$1:$1048576,MATCH(I$31,Model!$3:$3,0),FALSE) -> 16626.936 | J32: =I32*(1+J33) -> 17957.091 | K32: =J32*(1+K33) -> 19393.658 | L32: =K32*(1+L33) -> 20945.151 | M32: =L32*(1+M33) -> 22620.763 | N32: =M32*(1+N33) -> 24430.424 | O32: =N32*(1+O33) -> 26384.858 | P32: =O32*(1+P33) -> 28495.647 | Q32: =P32*(1+Q33) -> 30775.299 | ... W32: =V32*(1+W33) -> 48836.531
C33: Growth % | E33: =E32/D32-1 -> 0.14839558 | F33: =F32/E32-1 -> 0.11334653 | G33: =G32/F32-1 -> 0.0842178 | H33: =H32/G32-1 -> 0.08147937 | I33: =I32/H32-1 -> 0.080061743 | J33: 0.08 | K33: 0.08 | L33: 0.08 | M33: 0.08 | N33: 0.08 | O33: 0.08 | P33: 0.08 | Q33: 0.08 | R33: 0.08 | S33: 0.08 | T33: 0.08 | U33: 0.08 | V33: 0.08 | W33: 0.08
A34: EBIT | C34: EBIT | D34: =VLOOKUP($A34,Model!$1:$1048576,MATCH(D$31,Model!$3:$3,0),FALSE) -> 903.4 | E34: =VLOOKUP($A34,Model!$1:$1048576,MATCH(E$31,Model!$3:$3,0),FALSE) -> 1133.2179 | F34: =VLOOKUP($A34,Model!$1:$1048576,MATCH(F$31,Model!$3:$3,0),FALSE) -> 1352.8846 | G34: =VLOOKUP($A34,Model!$1:$1048576,MATCH(G$31,Model!$3:$3,0),FALSE) -> 1557.9031 | H34: =VLOOKUP($A34,Model!$1:$1048576,MATCH(H$31,Model!$3:$3,0),FALSE) -> 1758.1846 | I34: =VLOOKUP($A34,Model!$1:$1048576,MATCH(I$31,Model!$3:$3,0),FALSE) -> 1978.5709 | J34: =J36*J32 -> 2208.685 | K34: =K36*K32 -> 2424.1671 | L34: =L36*L32 -> 2659.9907 | M34: =M36*M32 -> 2918.0315 | N34: =N36*N32 -> 3200.3349 | O34: =O36*O32 -> 3456.3617 | P34: =P36*P32 -> 3732.8706 | Q34: =Q36*Q32 -> 4031.5003 | ... W34: =W36*W32 -> 6397.4843
C35: Growth % | E35: =E34/D34-1 -> 0.25439223 | F35: =F34/E34-1 -> 0.19384326 | G35: =G34/F34-1 -> 0.15154178 | H35: =H34/G34-1 -> 0.12855837 | I35: =I34/H34-1 -> 0.12534878 | J35: =J34/I34-1 -> 0.11630315 | K35: =K34/J34-1 -> 0.097561272 | L35: =L34/K34-1 -> 0.097280287 | ... W35: =W34/V34-1 -> 0.08
C36: EBIT Margin % network sales | D36: =D34/D32 -> 0.087977796 | E36: =E34/E32 -> 0.096098127 | F36: =F34/F32 -> 0.10304618 | G36: =G34/G32 -> 0.10944478 | H36: =H34/H32 -> 0.11420913 | I36: =I34/I32 -> 0.11899793 | J36: =I36+J37 -> 0.12299793 | K36: =J36+K37 -> 0.12499793 | L36: =K36+L37 -> 0.12699793 | M36: =L36+M37 -> 0.12899793 | N36: =M36+N37 -> 0.13099793 | O36: =N36+O37 -> 0.13099793 | P36: =O36+P37 -> 0.13099793 | Q36: =P36+Q37 -> 0.13099793 | ... W36: =V36+W37 -> 0.13099793
C37: Change YoY % | E37: =E36-D36 -> 0.008120331 | F37: =F36-E36 -> 0.006948048 | G37: =G36-F36 -> 0.0063986024 | H37: =H36-G36 -> 0.0047643544 | I37: =I36-H36 -> 0.0047887936 | J37: 0.004 | K37: 0.002 | L37: 0.002 | M37: 0.002 | N37: 0.002 | O37: 0 | P37: 0 | Q37: 0 | R37: 0 | S37: 0 | T37: 0 | U37: 0 | V37: 0 | W37: 0
A38: D&A non lease | C38: Add: D&A non leases | D38: =(VLOOKUP($A38,PL!$1:$1048576,MATCH(D$31,PL!$3:$3,0),FALSE))*-1 -> 37.903 | E38: =(VLOOKUP($A38,PL!$1:$1048576,MATCH(E$31,PL!$3:$3,0),FALSE))*-1 -> 39.503583 | F38: =(VLOOKUP($A38,PL!$1:$1048576,MATCH(F$31,PL!$3:$3,0),FALSE))*-1 -> 41.831839 | G38: =(VLOOKUP($A38,PL!$1:$1048576,MATCH(G$31,PL!$3:$3,0),FALSE))*-1 -> 43.927466 | H38: =(VLOOKUP($A38,PL!$1:$1048576,MATCH(H$31,PL!$3:$3,0),FALSE))*-1 -> 46.202525 | I38: =(VLOOKUP($A38,PL!$1:$1048576,MATCH(I$31,PL!$3:$3,0),FALSE))*-1 -> 48.625636 | J38: =(J32*J39) -> 52.515687 | K38: =(K32*K39) -> 56.716942 | L38: =(L32*L39) -> 61.254297 | M38: =(M32*M39) -> 66.154641 | N38: =(N32*N39) -> 71.447012 | O38: =(O32*O39) -> 77.162773 | P38: =(P32*P39) -> 83.335795 | Q38: =(Q32*Q39) -> 90.002659 | ... W38: =(W32*W39) -> 142.82291
C39: % of Sales | D39: =D38/D32 -> 0.0036911915 | E39: =E38/E32 -> 0.0033499473 | F39: =F38/F32 -> 0.003186237 | G39: =G38/G32 -> 0.0030859632 | H39: =H38/H32 -> 0.0030012492 | I39: =I38/I32 -> 0.0029245097 | J39: =I39 -> 0.0029245097 | K39: =J39 -> 0.0029245097 | L39: =K39 -> 0.0029245097 | M39: =L39 -> 0.0029245097 | N39: =M39 -> 0.0029245097 | O39: =N39 -> 0.0029245097 | P39: =O39 -> 0.0029245097 | Q39: =P39 -> 0.0029245097 | ... W39: =V39 -> 0.0029245097
A40: Interest leases | C40: Less: interest leases | D40: =(VLOOKUP($A40,PL!$1:$1048576,MATCH(D$31,PL!$3:$3,0),FALSE)) -> -8.143 | E40: =(VLOOKUP($A40,PL!$1:$1048576,MATCH(E$31,PL!$3:$3,0),FALSE)) -> -8.6383457 | F40: =(VLOOKUP($A40,PL!$1:$1048576,MATCH(F$31,PL!$3:$3,0),FALSE)) -> -8.964549 | G40: =(VLOOKUP($A40,PL!$1:$1048576,MATCH(G$31,PL!$3:$3,0),FALSE)) -> -9.4115682 | H40: =(VLOOKUP($A40,PL!$1:$1048576,MATCH(H$31,PL!$3:$3,0),FALSE)) -> -9.8585875 | I40: =(VLOOKUP($A40,PL!$1:$1048576,MATCH(I$31,PL!$3:$3,0),FALSE)) -> -10.317688 | J40: =J41*J32 -> -11.143104 | K40: =K41*K32 -> -12.034552 | L40: =L41*L32 -> -12.997316 | M40: =M41*M32 -> -14.037101 | N40: =N41*N32 -> -15.160069 | O40: =O41*O32 -> -16.372875 | P40: =P41*P32 -> -17.682705 | Q40: =Q41*Q32 -> -19.097321 | ... W40: =W41*W32 -> -30.305049
C41: % of Sales | D41: =D40/D32 -> -0.00079300774 | E41: =E40/E32 -> -0.00073254121 | F41: =F40/F32 -> -0.00068280952 | G41: =G40/G32 -> -0.00066117525 | H41: =H40/H32 -> -0.00064039959 | I41: =I40/I32 -> -0.00062054057 | J41: =I41 -> -0.00062054057 | K41: =J41 -> -0.00062054057 | L41: =K41 -> -0.00062054057 | M41: =L41 -> -0.00062054057 | N41: =M41 -> -0.00062054057 | O41: =N41 -> -0.00062054057 | P41: =O41 -> -0.00062054057 | Q41: =P41 -> -0.00062054057 | ... W41: =V41 -> -0.00062054057
A42: Chg WC | C42: Change in Net Working Capital | D42: =VLOOKUP($A42,BS!$1:$1048576,MATCH(D$31,BS!$3:$3,0),FALSE) -> -722.22 | E42: =VLOOKUP($A42,BS!$1:$1048576,MATCH(E$31,BS!$3:$3,0),FALSE) -> -89.661211 | F42: =VLOOKUP($A42,BS!$1:$1048576,MATCH(F$31,BS!$3:$3,0),FALSE) -> -32.014301 | G42: =VLOOKUP($A42,BS!$1:$1048576,MATCH(G$31,BS!$3:$3,0),FALSE) -> -46.141237 | H42: =VLOOKUP($A42,BS!$1:$1048576,MATCH(H$31,BS!$3:$3,0),FALSE) -> -40.287066 | I42: =VLOOKUP($A42,BS!$1:$1048576,MATCH(I$31,BS!$3:$3,0),FALSE) -> -35.309847 | J42: =J43*J32 -> -35.914182 | K42: =K43*K32 -> -38.787317 | L42: =L43*L32 -> -41.890302 | M42: =M43*M32 -> -45.241526 | N42: =N43*N32 -> -48.860849 | O42: =O43*O32 -> -52.769716 | P42: =P43*P32 -> -56.991294 | Q42: =Q43*Q32 -> -61.550597 | ... W42: =W43*W32 -> -97.673062
C43: % of Sales | D43: =D42/D32 -> -0.070333544 | E43: =E42/E32 -> -0.0076033692 | F43: =F42/F32 -> -0.0024384573 | G43: =G42/G32 -> -0.0032414835 | H43: =H42/H32 -> -0.0026169896 | I43: =I42/I32 -> -0.0021236532 | J43: -0.002 | K43: =J43 -> -0.002 | L43: =K43 -> -0.002 | M43: =L43 -> -0.002 | N43: =M43 -> -0.002 | O43: =N43 -> -0.002 | P43: =O43 -> -0.002 | Q43: =P43 -> -0.002 | R43: =Q43 -> -0.002 | ... W43: =V43 -> -0.002
A44: Capex | C44: Less: Net Capex | D44: =VLOOKUP($A44,CF!$1:$1048576,MATCH(D$31,CF!$3:$3,0),FALSE) -> -52.562 | E44: =VLOOKUP($A44,CF!$1:$1048576,MATCH(E$31,CF!$3:$3,0),FALSE) -> -60 | F44: =VLOOKUP($A44,CF!$1:$1048576,MATCH(F$31,CF!$3:$3,0),FALSE) -> -65 | G44: =VLOOKUP($A44,CF!$1:$1048576,MATCH(G$31,CF!$3:$3,0),FALSE) -> -70 | H44: =VLOOKUP($A44,CF!$1:$1048576,MATCH(H$31,CF!$3:$3,0),FALSE) -> -75 | I44: =VLOOKUP($A44,CF!$1:$1048576,MATCH(I$31,CF!$3:$3,0),FALSE) -> -80 | J44: =J45*J32 -> -86.4 | K44: =K45*K32 -> -93.312 | L44: =L45*L32 -> -100.77696 | M44: =M45*M32 -> -108.83912 | N44: =N45*N32 -> -117.54625 | O44: =O45*O32 -> -126.94995 | P44: =P45*P32 -> -137.10594 | Q44: =Q45*Q32 -> -148.07442 | ... W44: =W45*W32 -> -234.97549
C45: % of Sales | D45: =D44/D32 -> -0.0051187613 | E45: =E44/E32 -> -0.005088066 | F45: =F44/F32 -> -0.0049509037 | G45: =G44/G32 -> -0.0049175935 | H45: =H44/H32 -> -0.0048718916 | I45: =I44/I32 -> -0.0048114697 | J45: =I45 -> -0.0048114697 | K45: =J45 -> -0.0048114697 | L45: =K45 -> -0.0048114697 | M45: =L45 -> -0.0048114697 | N45: =M45 -> -0.0048114697 | O45: =N45 -> -0.0048114697 | P45: =O45 -> -0.0048114697 | Q45: =P45 -> -0.0048114697 | ... W45: =V45 -> -0.0048114697
A46: Acquisitions | C46: Less: Acquisitions | D46: =VLOOKUP($A46,CF!$1:$1048576,MATCH(D$31,CF!$3:$3,0),FALSE) -> -8.988 | E46: =VLOOKUP($A46,CF!$1:$1048576,MATCH(E$31,CF!$3:$3,0),FALSE) -> 0 | F46: =VLOOKUP($A46,CF!$1:$1048576,MATCH(F$31,CF!$3:$3,0),FALSE) -> 0 | G46: =VLOOKUP($A46,CF!$1:$1048576,MATCH(G$31,CF!$3:$3,0),FALSE) -> 0 | H46: =VLOOKUP($A46,CF!$1:$1048576,MATCH(H$31,CF!$3:$3,0),FALSE) -> 0 | I46: =VLOOKUP($A46,CF!$1:$1048576,MATCH(I$31,CF!$3:$3,0),FALSE) -> 0 | J46: 0 | K46: 0 | L46: 0 | M46: 0 | N46: 0 | O46: 0 | P46: 0 | Q46: 0 | R46: 0 | S46: 0 | T46: 0 | U46: 0 | V46: 0 | W46: 0
C47: Free Cash Flow pre Tax | D47: =D34+D38+D42+D44+D46+D40 -> 149.39 | E47: =E34+E38+E42+E44+E46+E40 -> 1014.422 | F47: =F34+F38+F42+F44+F46+F40 -> 1288.7376 | G47: =G34+G38+G42+G44+G46+G40 -> 1476.2778 | H47: =H34+H38+H42+H44+H46+H40 -> 1679.2415 | I47: =I34+I38+I42+I44+I46+I40 -> 1901.569 | J47: =J34+J38+J42+J44+J46+J40 -> 2127.7434 | K47: =K34+K38+K42+K44+K46+K40 -> 2336.7501 | ... W47: =W34+W38+W42+W44+W46+W40 -> 6177.3536
C48: Less: Tax | D48: =D47*-$D$62 -> -44.817 | E48: =E47*-$D$62 -> -304.32659 | F48: =F47*-$D$62 -> -386.62128 | G48: =G47*-$D$62 -> -442.88334 | H48: =H47*-$D$62 -> -503.77245 | I48: =I47*-$D$62 -> -570.47071 | J48: =J47*-$D$62 -> -638.32301 | K48: =K47*-$D$62 -> -701.02504 | ... W48: =W47*-$D$62 -> -1853.2061
C49: Free Cash Flow | D49: =D47+D48 -> 104.573 | E49: =E47+E48 -> 710.09538 | F49: =F47+F48 -> 902.11631 | G49: =G47+G48 -> 1033.3945 | H49: =H47+H48 -> 1175.4691 | I49: =I47+I48 -> 1331.0983 | J49: =J47+J48 -> 1489.4204 | K49: =K47+K48 -> 1635.7251 | ... W49: =W47+W48 -> 4324.1475
C50: Growth % | E50: =E49/D49-1 -> 5.7904275 | F50: =F49/E49-1 -> 0.27041569 | G50: =G49/F49-1 -> 0.14552242 | H50: =H49/G49-1 -> 0.13748341 | I50: =I49/H49-1 -> 0.13239759 | J50: =J49/I49-1 -> 0.1189409 | K50: =K49/J49-1 -> 0.098229321 | L50: =L49/K49-1 -> 0.097926736 | ... W50: =W49/V49-1 -> 0.08
C51: Timing | D51: 0 | E51: 0.5 | F51: =E51+1 -> 1.5 | G51: =F51+1 -> 2.5 | H51: =G51+1 -> 3.5 | I51: =H51+1 -> 4.5 | J51: =I51+1 -> 5.5 | K51: =J51+1 -> 6.5 | L51: =K51+1 -> 7.5 | M51: =L51+1 -> 8.5 | ... W51: =V51+1 -> 18.5
C52: Discount Factor | E52: =1/(1+$D$64)^E51 -> 0.96367918 | F52: =1/(1+$D$64)^F51 -> 0.89494723 | G52: =1/(1+$D$64)^G51 -> 0.83111742 | H52: =1/(1+$D$64)^H51 -> 0.7718401 | I52: =1/(1+$D$64)^I51 -> 0.71679058 | J52: =1/(1+$D$64)^J51 -> 0.66566733 | K52: =1/(1+$D$64)^K51 -> 0.61819031 | L52: =1/(1+$D$64)^L51 -> 0.57409947 | ... W52: =1/(1+$D$64)^W51 -> 0.25439094
C53: Discounted FCF | D53: =IF(D51>0,D49*D52,0) -> 0 | E53: =IF(E51>0,E49*E52,0) -> 684.30413 | F53: =IF(F51>0,F49*F52,0) -> 807.3465 | G53: =IF(G51>0,G49*G52,0) -> 858.87213 | H53: =IF(H51>0,H49*H52,0) -> 907.27415 | I53: =IF(I51>0,I49*I52,0) -> 954.11873 | J53: =IF(J51>0,J49*J52,0) -> 991.45847 | K53: =IF(K51>0,K49*K52,0) -> 1011.1894 | ... W53: =IF(W51>0,W49*W52,0) -> 1100.0239
C55: DCF Assumptions | T55: DCF Calculation
C56: Terminal Growth Rate | D56: 0.03 | T56: Present Value of FCF | W56: =SUM(D53:W53) -> 19151.292
C57: Risk Free Rate | D57: 0.035 | T57: Terminal Value | W57: =N53/(D64-D56) -> 22885.368
C58: Beta | D58: 0.9 | T58: Total EV | W58: =W56+W57 -> 42036.66
C59: Market Equity Risk Premium | D59: 0.06 | T59: Less: Net Debt | W59: =-BS!E78 -> -628.38914
C60: Cost of Equity | D60: =D57+(D58*D59) -> 0.089 | T60: Less Minority Interest | W60: =-0.05*W62 -> -577
C61: Cost of Debt | D61: 0.04 | T61: Equity Value | W61: =SUM(W58:W60) -> 40831.271
C62: Tax Rate | D62: 0.3 | T62: Shares | W62: =PL!E45 -> 11540
C63: D/E | D63: 0.2 | T63: Equity Value per Share | W63: =ROUND(W61/W62,1) -> 3.5
C64: WACC | D64: =((D63*(0.7)*D61)+((1-D63)*D60)) -> 0.0768
C65: Current Share Price | D65: =Summary!F9 -> 2.92
C70: MULTIPLES VALUATION Sigma Healthcare (SIG.AX) (Check)
C73: P/E Multiple Valuation | D73: FY27E
A74: EPS | C74: EPS (cps) | D74: =PL!F47*100 -> 7.9437055
C75: Applied Multiple (x) | D75: 44
C76: Target Price | D76: =ROUND(D75*D74/100,1) -> 3.5
