Workbook

Sheet Value
B2: Valuation | C2: TNE.AX
I3: DDM | J3: Units
C4: Current Price = | D4: 27.2 | F4: 38 | I4: Risk Free Rate | J4: % | K4: 0.04 | M4: 0.04
C5: Shares Outstanding = | D5: #NAME? | F5: #NAME? | I5: Beta | J5: x | K5: 0.9
C6: AS51 Index | I6: Market Premium | J6: % | K6: 0.06
C7: TARGET Relative Forward PE | I7: Ke | J7: % | K7: =K4+K5*K6 -> 0.094
C8: TARGET Forward PE | I8: ROE | J8: % p.a. | K8: 0.3
C9: PE Price Target = | E9: -1 | I9: LT Payout Ratio | J9: % p.a. | K9: 0.8 | M9: 0.034
I10: LT growth rate | J10: % p.a. | K10: =K8*(1-K9) -> 0.06 | M10: 0.06
J11: Dividend Discount Model | K11: =Annual!D251 -> 34.142188 | L11: =K11/D4-1 -> 0.2552275
I13: Implied 12M PE Ratio | J13: x | K13: 86.2x
B14: Notes | C14: Units | I14: Implied12M EV/EBITDA Ratio | J14: x | K14: #NAME?
B15: Actual Values | C15: 1000 | D15: (hard coded) | I15: EV- market | K15: #NAME?
B16: Formula | C16: 1000 | I16: ND/EV | K16: #NAME?
B17: Manual entry (assumption) | C17: 1000 | D17: (usually from guidance given by management)
C19: Actual ---> | E19: Forecast -----> | J19: Actual ---> | L19: Forecast -----> | Q19: Actual ---> | S19: Forecast ----->
C20: 2024 | D20: =C20+1 -> 2025 | E20: =D20+1 -> 2026 | F20: =E20+1 -> 2027 | G20: =F20+1 -> 2028 | J20: =C20 -> 2024 | K20: =D20 -> 2025 | L20: =E20 -> 2026 | M20: =F20 -> 2027 | N20: =G20 -> 2028 | Q20: =C20 -> 2024 | R20: =D20 -> 2025 | S20: =E20 -> 2026 | T20: =F20 -> 2027 | U20: =G20 -> 2028
B21: PE | I21: NPAT(AUDm) | P21: EBITDA (AUDm)
B22: Consensus | I22: Consensus | P22: Consensus
B23: Blackwattle | C23: =$D$4/C29 -> 75.507661 | D23: =$D$4/D29 -> 65.18426 | E23: =$D$4/E29 -> 54.855736 | F23: =$D$4/F29 -> 45.729443 | G23: =$D$4/G29 -> 37.342755 | H23: Underlying NPAT | I23: Blackwattle | J23: =INDEX(Annual!$A:$AC,MATCH(Value!$H23,Annual!$A:$A,0),MATCH(J$20,Annual!$A$1:$AC$1,0)) -> 118 | K23: =INDEX(Annual!$A:$AC,MATCH(Value!$H23,Annual!$A:$A,0),MATCH(K$20,Annual!$A$1:$AC$1,0)) -> 137.645 | L23: =INDEX(Annual!$A:$AC,MATCH(Value!$H23,Annual!$A:$A,0),MATCH(L$20,Annual!$A$1:$AC$1,0)) -> 162.63255 | M23: =INDEX(Annual!$A:$AC,MATCH(Value!$H23,Annual!$A:$A,0),MATCH(M$20,Annual!$A$1:$AC$1,0)) -> 195.08937 | N23: =INDEX(Annual!$A:$AC,MATCH(Value!$H23,Annual!$A:$A,0),MATCH(N$20,Annual!$A$1:$AC$1,0)) -> 238.90385 | O23: EBITDA-EBITDA | P23: Blackwattle | Q23: =INDEX(Annual!$A:$AC,MATCH($O23,Annual!$A:$A,0),MATCH(Q$20,Annual!$A$1:$AC$1,0)) -> 215.8 | R23: =INDEX(Annual!$A:$AC,MATCH($O23,Annual!$A:$A,0),MATCH(R$20,Annual!$A$1:$AC$1,0)) -> 255.7 | S23: =INDEX(Annual!$A:$AC,MATCH($O23,Annual!$A:$A,0),MATCH(S$20,Annual!$A$1:$AC$1,0)) -> 298.06663 | T23: =INDEX(Annual!$A:$AC,MATCH($O23,Annual!$A:$A,0),MATCH(T$20,Annual!$A$1:$AC$1,0)) -> 350.58886 | U23: =INDEX(Annual!$A:$AC,MATCH($O23,Annual!$A:$A,0),MATCH(U$20,Annual!$A$1:$AC$1,0)) -> 420.92194
B24: Difference | C24: #NAME? | D24: #NAME? | E24: #NAME? | F24: #NAME? | G24: #NAME? | I24: Difference | P24: Difference
B26: EPS (Acps) | I26: PBT (AUDm) | P26: Revenue (AUDm)
A27: =Annual!A96 -> YE Basic Shares Outstanding | B27: Shares Outstanding | D27: =INDEX(Annual!$A:$AC,MATCH($A27,Annual!$A:$A,0),MATCH(D$20,Annual!$A$1:$AC$1,0)) -> 327.36854 | E27: =INDEX(Annual!$A:$AC,MATCH($A27,Annual!$A:$A,0),MATCH(E$20,Annual!$A$1:$AC$1,0)) -> 327.36854 | F27: =INDEX(Annual!$A:$AC,MATCH($A27,Annual!$A:$A,0),MATCH(F$20,Annual!$A$1:$AC$1,0)) -> 327.36854 | G27: =INDEX(Annual!$A:$AC,MATCH($A27,Annual!$A:$A,0),MATCH(G$20,Annual!$A$1:$AC$1,0)) -> 327.36854 | I27: Consensus | P27: Consensus | S27: 687.91 | T27: 787.1
B28: Consensus | E28: 0.49 | F28: 0.59 | H28: PBT | I28: Blackwattle | J28: =INDEX(Annual!$A:$AC,MATCH(Value!$H28,Annual!$A:$A,0),MATCH(J$20,Annual!$A$1:$AC$1,0)) -> 152.9 | K28: =INDEX(Annual!$A:$AC,MATCH(Value!$H28,Annual!$A:$A,0),MATCH(K$20,Annual!$A$1:$AC$1,0)) -> 181.546 | L28: =INDEX(Annual!$A:$AC,MATCH(Value!$H28,Annual!$A:$A,0),MATCH(L$20,Annual!$A$1:$AC$1,0)) -> 214.54063 | M28: =INDEX(Annual!$A:$AC,MATCH(Value!$H28,Annual!$A:$A,0),MATCH(M$20,Annual!$A$1:$AC$1,0)) -> 257.36811 | N28: =INDEX(Annual!$A:$AC,MATCH(Value!$H28,Annual!$A:$A,0),MATCH(N$20,Annual!$A$1:$AC$1,0)) -> 315.19478 | O28: Rev-Total Revenue exc interest | P28: Blackwattle | Q28: =INDEX(Annual!$A:$AC,MATCH($O28,Annual!$A:$A,0),MATCH(Q$20,Annual!$A$1:$AC$1,0)) -> 515.4 | R28: =INDEX(Annual!$A:$AC,MATCH($O28,Annual!$A:$A,0),MATCH(R$20,Annual!$A$1:$AC$1,0)) -> 610.028 | S28: =INDEX(Annual!$A:$AC,MATCH($O28,Annual!$A:$A,0),MATCH(S$20,Annual!$A$1:$AC$1,0)) -> 694.604 | T28: =INDEX(Annual!$A:$AC,MATCH($O28,Annual!$A:$A,0),MATCH(T$20,Annual!$A$1:$AC$1,0)) -> 798.24446 | U28: =INDEX(Annual!$A:$AC,MATCH($O28,Annual!$A:$A,0),MATCH(U$20,Annual!$A$1:$AC$1,0)) -> 936.79645
A29: EPS | B29: Blackwattle | C29: =INDEX(Annual!$A:$AC,MATCH($A29,Annual!$A:$A,0),MATCH(C$20,Annual!$A$1:$AC$1,0)) -> 0.36022835 | D29: =INDEX(Annual!$A:$AC,MATCH($A29,Annual!$A:$A,0),MATCH(D$20,Annual!$A$1:$AC$1,0)) -> 0.41727865 | E29: =INDEX(Annual!$A:$AC,MATCH($A29,Annual!$A:$A,0),MATCH(E$20,Annual!$A$1:$AC$1,0)) -> 0.49584605 | F29: =INDEX(Annual!$A:$AC,MATCH($A29,Annual!$A:$A,0),MATCH(F$20,Annual!$A$1:$AC$1,0)) -> 0.59480279 | G29: =INDEX(Annual!$A:$AC,MATCH($A29,Annual!$A:$A,0),MATCH(G$20,Annual!$A$1:$AC$1,0)) -> 0.72838761 | I29: Difference | P29: Difference | S29: =S28/S27-1 -> 0.009730927 | T29: =T28/T27-1 -> 0.014158882 | U29: =U28/U27-1 -> #DIV/0!
B30: Difference | E30: =E29/E28-1 -> 0.011930713 | F30: =F29/F28-1 -> 0.0081403169 | I30: PBT margin (cons)
I31: EBIT (AUDm) | P31: EV / EBITDA
B32: DPS (Acps) | I32: Consensus | O32: Net debt | P32: Consensus
B33: Consensus | C33: #NAME? | D33: #NAME? | E33: #NAME? | F33: #NAME? | G33: #NAME? | H33: EBIT | I33: Blackwattle | J33: =INDEX(Annual!$A:$AC,MATCH(Value!$H33,Annual!$A:$A,0),MATCH(J$20,Annual!$A$1:$AC$1,0)) -> 147 | K33: =INDEX(Annual!$A:$AC,MATCH(Value!$H33,Annual!$A:$A,0),MATCH(K$20,Annual!$A$1:$AC$1,0)) -> 174.903 | L33: =INDEX(Annual!$A:$AC,MATCH(Value!$H33,Annual!$A:$A,0),MATCH(L$20,Annual!$A$1:$AC$1,0)) -> 205.74063 | M33: =INDEX(Annual!$A:$AC,MATCH(Value!$H33,Annual!$A:$A,0),MATCH(M$20,Annual!$A$1:$AC$1,0)) -> 246.26811 | N33: =INDEX(Annual!$A:$AC,MATCH(Value!$H33,Annual!$A:$A,0),MATCH(N$20,Annual!$A$1:$AC$1,0)) -> 301.49478 | O33: Net debt | P33: Blackwattle | Q33: =(INDEX(Annual!$A:$AC,MATCH($O33,Annual!$A:$A,0),MATCH(Q$20,Annual!$A$1:$AC$1,0))+$D$4*C27)/Q23 -> -1.2914736 | R33: =(INDEX(Annual!$A:$AC,MATCH($O33,Annual!$A:$A,0),MATCH(R$20,Annual!$A$1:$AC$1,0))+$D$4*D27)/R23 -> 33.573654 | S33: =(INDEX(Annual!$A:$AC,MATCH($O33,Annual!$A:$A,0),MATCH(S$20,Annual!$A$1:$AC$1,0))+$D$4*E27)/S23 -> 28.709139 | T33: =(INDEX(Annual!$A:$AC,MATCH($O33,Annual!$A:$A,0),MATCH(T$20,Annual!$A$1:$AC$1,0))+$D$4*F27)/T23 -> 24.206202 | U33: =(INDEX(Annual!$A:$AC,MATCH($O33,Annual!$A:$A,0),MATCH(U$20,Annual!$A$1:$AC$1,0))+$D$4*G27)/U23 -> 19.974314
A34: Dividends | B34: Blackwattle | C34: =INDEX(Annual!$A:$AC,MATCH($A34,Annual!$A:$A,0),MATCH(C$20,Annual!$A$1:$AC$1,0)) -> 0.22 | D34: =INDEX(Annual!$A:$AC,MATCH($A34,Annual!$A:$A,0),MATCH(D$20,Annual!$A$1:$AC$1,0)) -> 0.366 | E34: =INDEX(Annual!$A:$AC,MATCH($A34,Annual!$A:$A,0),MATCH(E$20,Annual!$A$1:$AC$1,0)) -> 0.30742455 | F34: =INDEX(Annual!$A:$AC,MATCH($A34,Annual!$A:$A,0),MATCH(F$20,Annual!$A$1:$AC$1,0)) -> 0.36877773 | G34: =INDEX(Annual!$A:$AC,MATCH($A34,Annual!$A:$A,0),MATCH(G$20,Annual!$A$1:$AC$1,0)) -> 0.45160032 | I34: Difference | P34: Difference
B35: Dividend Yield
B37: FY24 | C37: Consensus | D37: Blackwattle | E37: % Diff | F37: OLD | G37: % Diff | J37: PE | L37: EV/EBITDA | N37: EV/Sales | O37: EBITDA Growth | P37: EBITDA margin | Q37: Revenue Growth | R37: EBIT margin | S37: Rule of 40 (EBIT) | T37: Market Cap | U37: Dividend Yield | V37: Stock
B38: EBITDA | C38: #NAME? | D38: 257 | E38: #NAME? | G38: #DIV/0! | J38: FY1 | K38: FY2 | L38: FY1 | M38: FY2 | N38: NTM | O38: FY0-3 CAGR | P38: FY1 | Q38: FY0-3 CAGR | R38: FY3 | S38: FY3 | T38: AUDm | U38: NTM | V38: Code | Y38: 0.86521739
B39: D&A | C39: #NAME? | D39: 80 | E39: #NAME? | G39: #DIV/0! | I39: #NAME? | J39: #NAME? | K39: #NAME? | L39: #NAME? | M39: #NAME? | N39: #NAME? | O39: #NAME? | P39: #NAME? | Q39: #NAME? | R39: #NAME? | S39: #NAME? | T39: #NAME? | U39: #NAME? | V39: TNE.AX
B40: EBIT | C40: #NAME? | D40: 177 | E40: #NAME? | G40: #DIV/0!
B41: Net Interest | C41: #NAME? | D41: -7 | E41: #NAME? | G41: #DIV/0! | I41: Global SaaS
B42: PBT | C42: #NAME? | D42: 185 | E42: #NAME? | G42: #DIV/0! | I42: #NAME? | J42: #NAME? | K42: #NAME? | L42: #NAME? | M42: #NAME? | N42: #NAME? | O42: #NAME? | P42: #NAME? | Q42: #NAME? | R42: #NAME? | S42: #NAME? | T42: #NAME? | U42: #NAME? | V42: SAP.N
B43: Tax | C43: #NAME? | D43: 43 | E43: #NAME? | G43: #DIV/0! | I43: #NAME? | J43: #NAME? | K43: #NAME? | L43: #NAME? | M43: #NAME? | N43: #NAME? | O43: #NAME? | P43: #NAME? | Q43: #NAME? | R43: #NAME? | S43: #NAME? | T43: #NAME? | U43: #NAME? | V43: ORCL.K
B44: Tax Rate | C44: #NAME? | D44: 0.23 | E44: #NAME? | G44: #DIV/0! | I44: #NAME? | J44: #NAME? | K44: #NAME? | L44: #NAME? | M44: #NAME? | N44: #NAME? | O44: #NAME? | P44: #NAME? | Q44: #NAME? | R44: #NAME? | S44: #NAME? | T44: #NAME? | U44: #NAME? | V44: WDAY.O
B45: NPAT | C45: #NAME? | D45: 142 | E45: #NAME? | G45: #DIV/0! | I45: #NAME? | J45: #NAME? | K45: #NAME? | L45: #NAME? | M45: #NAME? | N45: #NAME? | O45: #NAME? | P45: #NAME? | Q45: #NAME? | R45: #NAME? | S45: #NAME? | T45: #NAME? | U45: #NAME? | V45: CRM.N
I46: #NAME? | J46: #NAME? | K46: #NAME? | L46: #NAME? | M46: #NAME? | N46: #NAME? | O46: #NAME? | P46: #NAME? | Q46: #NAME? | R46: #NAME? | S46: #NAME? | T46: #NAME? | U46: #NAME? | V46: NOW.N
B47: FY25 | C47: Consensus | D47: Blackwattle | E47: % Diff | F47: OLD | G47: % Diff | I47: #NAME? | J47: #NAME? | K47: #NAME? | L47: #NAME? | M47: #NAME? | N47: #NAME? | O47: #NAME? | P47: #NAME? | Q47: #NAME? | R47: #NAME? | S47: #NAME? | T47: #NAME? | U47: #NAME? | V47: MSFT.O
B48: EBITDA | C48: #NAME? | D48: 305 | E48: #NAME? | G48: #DIV/0! | I48: #NAME? | J48: #NAME? | K48: #NAME? | L48: #NAME? | M48: #NAME? | N48: #NAME? | O48: #NAME? | P48: #NAME? | Q48: #NAME? | R48: #NAME? | S48: #NAME? | T48: #NAME? | U48: #NAME? | V48: SGE.L
B49: D&A | C49: #NAME? | D49: 90 | E49: #NAME? | G49: #DIV/0! | I49: #NAME? | J49: #NAME? | K49: #NAME? | L49: #NAME? | M49: #NAME? | N49: #NAME? | O49: #NAME? | P49: #NAME? | Q49: #NAME? | R49: #NAME? | S49: #NAME? | T49: #NAME? | U49: #NAME? | V49: TRBG.L
B50: EBIT | C50: #NAME? | D50: 215 | E50: #NAME? | G50: #DIV/0! | I50: MEDIAN | J50: #NAME? | K50: #NAME? | L50: #NAME? | M50: #NAME? | N50: #NAME? | O50: #NAME? | P50: #NAME? | Q50: #NAME? | R50: #NAME? | S50: #NAME? | T50: #NAME? | U50: #NAME?
B51: Net Interest | C51: #NAME? | D51: -9 | E51: #NAME? | G51: #DIV/0! | I51: MEAN | J51: #NAME? | K51: #NAME? | L51: #NAME? | M51: #NAME? | N51: #NAME? | O51: #NAME? | P51: #NAME? | Q51: #NAME? | R51: #NAME? | S51: #NAME? | T51: #NAME? | U51: #NAME?
B52: PBT | C52: #NAME? | D52: 224 | E52: #NAME? | G52: #DIV/0!
B53: Tax | C53: #NAME? | D53: 52 | E53: #NAME? | G53: #DIV/0! | I53: Aus Tech/SaaS
B54: Tax Rate | C54: #NAME? | D54: 0.23 | E54: #NAME? | G54: #DIV/0! | I54: #NAME? | J54: #NAME? | K54: #NAME? | L54: #NAME? | M54: #NAME? | N54: #NAME? | O54: #NAME? | P54: #NAME? | Q54: #NAME? | R54: #NAME? | S54: #NAME? | T54: #NAME? | U54: #NAME? | V54: OCL.AX
B55: NPAT | C55: #NAME? | D55: 172 | E55: #NAME? | G55: #DIV/0! | I55: #NAME? | J55: #NAME? | K55: #NAME? | L55: #NAME? | M55: #NAME? | N55: #NAME? | O55: #NAME? | P55: #NAME? | Q55: #NAME? | R55: #NAME? | S55: #NAME? | T55: #NAME? | U55: #NAME? | V55: SDR.AX
I56: #NAME? | J56: #NAME? | K56: #NAME? | L56: #NAME? | M56: #NAME? | N56: #NAME? | O56: #NAME? | P56: #NAME? | Q56: #NAME? | R56: #NAME? | S56: #NAME? | T56: #NAME? | U56: #NAME? | V56: RDY.AX
B57: FY26 | C57: Consensus | D57: Blackwattle | E57: % Diff | F57: OLD | G57: % Diff | I57: #NAME? | J57: #NAME? | K57: #NAME? | L57: #NAME? | M57: #NAME? | N57: #NAME? | O57: #NAME? | P57: #NAME? | Q57: #NAME? | R57: #NAME? | S57: #NAME? | T57: #NAME? | U57: #NAME? | V57: RUL.AX
B58: EBITDA | C58: #NAME? | D58: 366 | E58: #NAME? | G58: #DIV/0! | I58: #NAME? | J58: #NAME? | K58: #NAME? | L58: #NAME? | M58: #NAME? | N58: #NAME? | O58: #NAME? | P58: #NAME? | Q58: #NAME? | R58: #NAME? | S58: #NAME? | T58: #NAME? | U58: #NAME? | V58: WTC.AX
B59: D&A | C59: #NAME? | D59: 104 | E59: #NAME? | G59: #DIV/0! | I59: #NAME? | J59: #NAME? | K59: #NAME? | L59: #NAME? | M59: #NAME? | N59: #NAME? | O59: #NAME? | P59: #NAME? | Q59: #NAME? | R59: #NAME? | S59: #NAME? | T59: #NAME? | U59: #NAME? | V59: XRO.AX
B60: EBIT | C60: #NAME? | D60: 262 | E60: #NAME? | G60: #DIV/0! | I60: #NAME? | J60: #NAME? | K60: #NAME? | L60: #NAME? | M60: #NAME? | N60: #NAME? | O60: #NAME? | P60: #NAME? | Q60: #NAME? | R60: #NAME? | S60: #NAME? | T60: #NAME? | U60: #NAME? | V60: 360.AX
B61: Net Interest | C61: #NAME? | D61: -11 | E61: #NAME? | G61: #DIV/0! | I61: MEDIAN | J61: #NAME? | K61: #NAME? | L61: #NAME? | M61: #NAME? | N61: #NAME? | O61: #NAME? | P61: #NAME? | Q61: #NAME? | R61: #NAME? | S61: #NAME? | T61: #NAME? | U61: #NAME? | V61: #NUM!
B62: PBT | C62: #NAME? | D62: 273 | E62: #NAME? | G62: #DIV/0! | I62: MEAN | J62: #NAME? | K62: #NAME? | L62: #NAME? | M62: #NAME? | N62: #NAME? | O62: #NAME? | P62: #NAME? | Q62: #NAME? | R62: #NAME? | S62: #NAME? | T62: #NAME? | U62: #NAME?
B63: Tax | C63: #NAME? | D63: 63 | E63: #NAME? | G63: #DIV/0!
B64: Tax Rate | C64: #NAME? | D64: 0.23 | E64: #NAME? | G64: #DIV/0!
B65: NPAT | C65: #NAME? | D65: 210 | E65: #NAME? | G65: #DIV/0!
I114: Digital Gaming | J114: PE | L114: EV/EBITDA | N114: 2yr EPS | O114: EBITDA | P114: Market Cap
J115: FY1 | K115: FY2 | L115: FY1 | M115: FY2 | N115: CAGR | O115: Margin | P115: USDm | R115: FY3
I116: #NAME? | J116: #NAME? | K116: #NAME? | L116: #NAME? | M116: #NAME? | N116: #NAME? | O116: #NAME? | P116: #NAME? | Q116: SCPL US Equity | R116: #NAME?
I117: #NAME? | J117: #NAME? | K117: #NAME? | L117: #NAME? | M117: #NAME? | N117: #NAME? | O117: #NAME? | P117: #NAME? | Q117: ZNGA US Equity | R117: #NAME?
I118: #NAME? | J118: #NAME? | K118: #NAME? | L118: #NAME? | M118: #NAME? | N118: #NAME? | O118: #NAME? | P118: #NAME? | Q118: TTWO US Equity | R118: #NAME?
I119: #NAME? | J119: #NAME? | K119: #NAME? | L119: #NAME? | M119: #NAME? | N119: #NAME? | O119: #NAME? | P119: #NAME? | Q119: EA US Equity | R119: #NAME?
I120: #NAME? | J120: #NAME? | K120: #NAME? | L120: #NAME? | M120: #NAME? | N120: #NAME? | O120: #NAME? | P120: #NAME? | Q120: ROVIO FH Equity | R120: #NAME?
I121: #NAME? | J121: #NAME? | K121: #NAME? | L121: #NAME? | M121: #NAME? | N121: #NAME? | O121: #NAME? | P121: #NAME? | Q121: ATVI US Equity | R121: #NAME?
I122: #NAME? | J122: #NAME? | K122: #NAME? | L122: #NAME? | M122: #NAME? | N122: #NAME? | O122: #NAME? | P122: #NAME? | Q122: GLUU US Equity | R122: #NAME?
I123: MEDIAN | J123: #NAME? | K123: #NAME? | L123: #NAME? | M123: #NAME? | N123: #NAME? | O123: #NAME? | P123: #NAME?
I124: #NAME? | J124: #NAME? | K124: #NAME? | L124: #NAME? | M124: #NAME? | N124: #NAME? | O124: #NAME? | P124: #NAME? | Q124: ALL AU Equity | R124: #NAME?
I126: Slots Manufacturers | J126: PE | L126: EV/EBITDA | N126: 2yr EPS | O126: EBITDA | P126: Market Cap
J127: FY1 | K127: FY2 | L127: FY1 | M127: FY2 | N127: CAGR | O127: Margin | P127: USDm | R127: FY3
I128: #NAME? | J128: #NAME? | K128: #NAME? | L128: #NAME? | M128: #NAME? | N128: #NAME? | O128: #NAME? | P128: #NAME? | Q128: SGMS US Equity | R128: #NAME?
I129: #NAME? | J129: #NAME? | K129: #NAME? | L129: #NAME? | M129: #NAME? | N129: #NAME? | O129: #NAME? | P129: #NAME? | Q129: IGT US Equity | R129: #NAME?
I130: #NAME? | J130: #NAME? | K130: #NAME? | L130: #NAME? | M130: #NAME? | N130: #NAME? | O130: #NAME? | P130: #NAME? | Q130: AGI AU Equity | R130: #NAME?
I131: #NAME? | J131: #NAME? | K131: #NAME? | L131: #NAME? | M131: #NAME? | N131: #NAME? | O131: #NAME? | P131: #NAME? | Q131: EVRI US Equity | R131: #NAME?
I132: #NAME? | J132: #NAME? | K132: #NAME? | L132: #NAME? | M132: #NAME? | N132: #NAME? | O132: #NAME? | P132: #NAME? | Q132: AGS US Equity | R132: #NAME?
I133: MEDIAN | J133: #NAME? | K133: #NAME? | L133: #NAME? | M133: #NAME? | N133: #NAME? | O133: #NAME? | P133: #NAME?
I134: #NAME? | J134: #NAME? | K134: #NAME? | L134: #NAME? | M134: #NAME? | N134: #NAME? | O134: #NAME? | P134: #NAME? | Q134: ALL AU Equity | R134: #NAME?
I135: #NAME? | J135: #NAME? | K135: #NAME? | L135: #NAME? | M135: #NAME? | N135: #NAME? | O135: #NAME? | P135: 192080-KR

Sheet Annual
B1: TNE Model Summary | E1: 2012 | F1: 2013 | G1: 2014 | H1: 2015 | I1: 2016 | J1: 2017 | K1: 2018 | L1: 2019 | M1: 2020 | N1: 2021 | O1: 2022 | P1: 2023 | Q1: 2024 | R1: =Q1+1 -> 2025 | S1: 2026 | T1: 2027 | U1: 2028 | V1: 2029 | W1: 2030 | X1: 2031 | Y1: 2032 | Z1: 2033 | AA1: 2034 | AB1: 2035 | AD1: Earnings changes=> | AE1: 2025 | AF1: 2024 | AG1: 2026 | AH1: 2024
E2: Actual ----------> | S2: Forecast -----> | AF2: Forecast -----> | AG2: Forecast -----> | AH2: Forecast ----->
C3: Units | D3: Source | E3: FY12A | F3: FY13A | G3: FY14A | H3: FY15A | I3: FY16A | J3: FY17A | K3: FY18A | L3: FY19A | M3: FY20A | N3: FY21A | O3: FY22A | P3: FY23A | Q3: FY24A | R3: FY25A | S3: FY26E | T3: FY27E | U3: FY28E | V3: FY29E | W3: FY30E | X3: FY31E | Y3: FY32E | Z3: FY33E | AA3: FY34E | AB3: FY35E | AE3: FY25E | AF3: FY24E | AG3: FY26E | AH3: FY24E
B4: P &L
B5: Revenue | K5: *restated in FY19, with new revenue recognition
A6: Rev-SaaS fees | B6: SaaS fees | C6: AUDm | D6: AR | K6: 58.1 | L6: 81.5 | M6: 106.2 | N6: 151.1 | O6: 216.8 | P6: 316.2 | Q6: 407.4 | R6: 499.725 | S6: =INDEX(Segment!$A:$AR,MATCH(Annual!$A6,Segment!$A:$A,0),MATCH("1H"&RIGHT(Annual!S$1,2),Segment!$A$3:$AR$3,0))+INDEX(Segment!$A:$AR,MATCH(Annual!$A6,Segment!$A:$A,0),MATCH("2H"&RIGHT(Annual!S$1,2),Segment!$A$3:$AR$3,0)) -> 587.6793 | T6: =INDEX(Segment!$A:$AR,MATCH(Annual!$A6,Segment!$A:$A,0),MATCH("1H"&RIGHT(Annual!T$1,2),Segment!$A$3:$AR$3,0))+INDEX(Segment!$A:$AR,MATCH(Annual!$A6,Segment!$A:$A,0),MATCH("2H"&RIGHT(Annual!T$1,2),Segment!$A$3:$AR$3,0)) -> 695.66914 | U6: =INDEX(Segment!$A:$AR,MATCH(Annual!$A6,Segment!$A:$A,0),MATCH("1H"&RIGHT(Annual!U$1,2),Segment!$A$3:$AR$3,0))+INDEX(Segment!$A:$AR,MATCH(Annual!$A6,Segment!$A:$A,0),MATCH("2H"&RIGHT(Annual!U$1,2),Segment!$A$3:$AR$3,0)) -> 838.35305 | V6: =INDEX(Segment!$A:$AR,MATCH(Annual!$A6,Segment!$A:$A,0),MATCH("1H"&RIGHT(Annual!V$1,2),Segment!$A$3:$AR$3,0))+INDEX(Segment!$A:$AR,MATCH(Annual!$A6,Segment!$A:$A,0),MATCH("2H"&RIGHT(Annual!V$1,2),Segment!$A$3:$AR$3,0)) -> 1017.4705 | W6: =INDEX(Segment!$A:$AR,MATCH(Annual!$A6,Segment!$A:$A,0),MATCH("1H"&RIGHT(Annual!W$1,2),Segment!$A$3:$AR$3,0))+INDEX(Segment!$A:$AR,MATCH(Annual!$A6,Segment!$A:$A,0),MATCH("2H"&RIGHT(Annual!W$1,2),Segment!$A$3:$AR$3,0)) -> 1232.6543 | X6: =INDEX(Segment!$A:$AR,MATCH(Annual!$A6,Segment!$A:$A,0),MATCH("1H"&RIGHT(Annual!X$1,2),Segment!$A$3:$AR$3,0))+INDEX(Segment!$A:$AR,MATCH(Annual!$A6,Segment!$A:$A,0),MATCH("2H"&RIGHT(Annual!X$1,2),Segment!$A$3:$AR$3,0)) -> 1494.4905 | Y6: =INDEX(Segment!$A:$AR,MATCH(Annual!$A6,Segment!$A:$A,0),MATCH("1H"&RIGHT(Annual!Y$1,2),Segment!$A$3:$AR$3,0))+INDEX(Segment!$A:$AR,MATCH(Annual!$A6,Segment!$A:$A,0),MATCH("2H"&RIGHT(Annual!Y$1,2),Segment!$A$3:$AR$3,0)) -> 1813.5007 | Z6: =INDEX(Segment!$A:$AR,MATCH(Annual!$A6,Segment!$A:$A,0),MATCH("1H"&RIGHT(Annual!Z$1,2),Segment!$A$3:$AR$3,0))+INDEX(Segment!$A:$AR,MATCH(Annual!$A6,Segment!$A:$A,0),MATCH("2H"&RIGHT(Annual!Z$1,2),Segment!$A$3:$AR$3,0)) -> 2202.6851 | ... AB6: =INDEX(Segment!$A:$AR,MATCH(Annual!$A6,Segment!$A:$A,0),MATCH("1H"&RIGHT(Annual!AB$1,2),Segment!$A$3:$AR$3,0))+INDEX(Segment!$A:$AR,MATCH(Annual!$A6,Segment!$A:$A,0),MATCH("2H"&RIGHT(Annual!AB$1,2),Segment!$A$3:$AR$3,0)) -> 3259.7924 | AE6: 496.60116 | AF6: =IF(ISBLANK(AE6),"",INDEX($A6:$AB6,1,MATCH(AE$3,$A$3:$AB$3,0))-AE6) -> #N/A | AG6: 597.66026 | AH6: =IF(ISBLANK(AG6),"",INDEX($A6:$AB6,1,MATCH(AG$3,$A$3:$AB$3,0))-AG6) -> -9.9809589
A7: Rev-Annual licence fees | B7: Annual licence fees | C7: AUDm | D7: AR | K7: 103 | L7: 98.7 | M7: 101.1 | N7: 78 | O7: 69.2 | P7: 37 | Q7: 17.8 | R7: 7.211 | S7: =INDEX(Segment!$A:$AR,MATCH(Annual!$A7,Segment!$A:$A,0),MATCH("1H"&RIGHT(Annual!S$1,2),Segment!$A$3:$AR$3,0))+INDEX(Segment!$A:$AR,MATCH(Annual!$A7,Segment!$A:$A,0),MATCH("2H"&RIGHT(Annual!S$1,2),Segment!$A$3:$AR$3,0)) -> 7.211 | T7: =INDEX(Segment!$A:$AR,MATCH(Annual!$A7,Segment!$A:$A,0),MATCH("1H"&RIGHT(Annual!T$1,2),Segment!$A$3:$AR$3,0))+INDEX(Segment!$A:$AR,MATCH(Annual!$A7,Segment!$A:$A,0),MATCH("2H"&RIGHT(Annual!T$1,2),Segment!$A$3:$AR$3,0)) -> 7.211 | U7: =INDEX(Segment!$A:$AR,MATCH(Annual!$A7,Segment!$A:$A,0),MATCH("1H"&RIGHT(Annual!U$1,2),Segment!$A$3:$AR$3,0))+INDEX(Segment!$A:$AR,MATCH(Annual!$A7,Segment!$A:$A,0),MATCH("2H"&RIGHT(Annual!U$1,2),Segment!$A$3:$AR$3,0)) -> 7.211 | V7: =INDEX(Segment!$A:$AR,MATCH(Annual!$A7,Segment!$A:$A,0),MATCH("1H"&RIGHT(Annual!V$1,2),Segment!$A$3:$AR$3,0))+INDEX(Segment!$A:$AR,MATCH(Annual!$A7,Segment!$A:$A,0),MATCH("2H"&RIGHT(Annual!V$1,2),Segment!$A$3:$AR$3,0)) -> 7.211 | W7: =INDEX(Segment!$A:$AR,MATCH(Annual!$A7,Segment!$A:$A,0),MATCH("1H"&RIGHT(Annual!W$1,2),Segment!$A$3:$AR$3,0))+INDEX(Segment!$A:$AR,MATCH(Annual!$A7,Segment!$A:$A,0),MATCH("2H"&RIGHT(Annual!W$1,2),Segment!$A$3:$AR$3,0)) -> 7.211 | X7: =INDEX(Segment!$A:$AR,MATCH(Annual!$A7,Segment!$A:$A,0),MATCH("1H"&RIGHT(Annual!X$1,2),Segment!$A$3:$AR$3,0))+INDEX(Segment!$A:$AR,MATCH(Annual!$A7,Segment!$A:$A,0),MATCH("2H"&RIGHT(Annual!X$1,2),Segment!$A$3:$AR$3,0)) -> 7.211 | Y7: =INDEX(Segment!$A:$AR,MATCH(Annual!$A7,Segment!$A:$A,0),MATCH("1H"&RIGHT(Annual!Y$1,2),Segment!$A$3:$AR$3,0))+INDEX(Segment!$A:$AR,MATCH(Annual!$A7,Segment!$A:$A,0),MATCH("2H"&RIGHT(Annual!Y$1,2),Segment!$A$3:$AR$3,0)) -> 7.211 | Z7: =INDEX(Segment!$A:$AR,MATCH(Annual!$A7,Segment!$A:$A,0),MATCH("1H"&RIGHT(Annual!Z$1,2),Segment!$A$3:$AR$3,0))+INDEX(Segment!$A:$AR,MATCH(Annual!$A7,Segment!$A:$A,0),MATCH("2H"&RIGHT(Annual!Z$1,2),Segment!$A$3:$AR$3,0)) -> 7.211 | ... AB7: =INDEX(Segment!$A:$AR,MATCH(Annual!$A7,Segment!$A:$A,0),MATCH("1H"&RIGHT(Annual!AB$1,2),Segment!$A$3:$AR$3,0))+INDEX(Segment!$A:$AR,MATCH(Annual!$A7,Segment!$A:$A,0),MATCH("2H"&RIGHT(Annual!AB$1,2),Segment!$A$3:$AR$3,0)) -> 7.211 | AE7: 8.2 | AF7: =IF(ISBLANK(AE7),"",INDEX($A7:$AB7,1,MATCH(AE$3,$A$3:$AB$3,0))-AE7) -> #N/A | AG7: 8.2 | AH7: =IF(ISBLANK(AG7),"",INDEX($A7:$AB7,1,MATCH(AG$3,$A$3:$AB$3,0))-AG7) -> -0.989
A8: Rev-Consulting services | B8: Consulting services | C8: AUDm | D8: AR | K8: 63.2 | L8: 61.6 | M8: 62.5 | N8: 64.5 | O8: 72.7 | P8: 73.2 | Q8: 80.5 | R8: 91.566 | S8: =INDEX(Segment!$A:$AR,MATCH(Annual!$A8,Segment!$A:$A,0),MATCH("1H"&RIGHT(Annual!S$1,2),Segment!$A$3:$AR$3,0))+INDEX(Segment!$A:$AR,MATCH(Annual!$A8,Segment!$A:$A,0),MATCH("2H"&RIGHT(Annual!S$1,2),Segment!$A$3:$AR$3,0)) -> 86.9877 | T8: =INDEX(Segment!$A:$AR,MATCH(Annual!$A8,Segment!$A:$A,0),MATCH("1H"&RIGHT(Annual!T$1,2),Segment!$A$3:$AR$3,0))+INDEX(Segment!$A:$AR,MATCH(Annual!$A8,Segment!$A:$A,0),MATCH("2H"&RIGHT(Annual!T$1,2),Segment!$A$3:$AR$3,0)) -> 82.638315 | U8: =INDEX(Segment!$A:$AR,MATCH(Annual!$A8,Segment!$A:$A,0),MATCH("1H"&RIGHT(Annual!U$1,2),Segment!$A$3:$AR$3,0))+INDEX(Segment!$A:$AR,MATCH(Annual!$A8,Segment!$A:$A,0),MATCH("2H"&RIGHT(Annual!U$1,2),Segment!$A$3:$AR$3,0)) -> 78.506399 | V8: =INDEX(Segment!$A:$AR,MATCH(Annual!$A8,Segment!$A:$A,0),MATCH("1H"&RIGHT(Annual!V$1,2),Segment!$A$3:$AR$3,0))+INDEX(Segment!$A:$AR,MATCH(Annual!$A8,Segment!$A:$A,0),MATCH("2H"&RIGHT(Annual!V$1,2),Segment!$A$3:$AR$3,0)) -> 74.581079 | W8: =INDEX(Segment!$A:$AR,MATCH(Annual!$A8,Segment!$A:$A,0),MATCH("1H"&RIGHT(Annual!W$1,2),Segment!$A$3:$AR$3,0))+INDEX(Segment!$A:$AR,MATCH(Annual!$A8,Segment!$A:$A,0),MATCH("2H"&RIGHT(Annual!W$1,2),Segment!$A$3:$AR$3,0)) -> 70.852025 | X8: =INDEX(Segment!$A:$AR,MATCH(Annual!$A8,Segment!$A:$A,0),MATCH("1H"&RIGHT(Annual!X$1,2),Segment!$A$3:$AR$3,0))+INDEX(Segment!$A:$AR,MATCH(Annual!$A8,Segment!$A:$A,0),MATCH("2H"&RIGHT(Annual!X$1,2),Segment!$A$3:$AR$3,0)) -> 67.309424 | Y8: =INDEX(Segment!$A:$AR,MATCH(Annual!$A8,Segment!$A:$A,0),MATCH("1H"&RIGHT(Annual!Y$1,2),Segment!$A$3:$AR$3,0))+INDEX(Segment!$A:$AR,MATCH(Annual!$A8,Segment!$A:$A,0),MATCH("2H"&RIGHT(Annual!Y$1,2),Segment!$A$3:$AR$3,0)) -> 63.943953 | Z8: =INDEX(Segment!$A:$AR,MATCH(Annual!$A8,Segment!$A:$A,0),MATCH("1H"&RIGHT(Annual!Z$1,2),Segment!$A$3:$AR$3,0))+INDEX(Segment!$A:$AR,MATCH(Annual!$A8,Segment!$A:$A,0),MATCH("2H"&RIGHT(Annual!Z$1,2),Segment!$A$3:$AR$3,0)) -> 60.746755 | ... AB8: =INDEX(Segment!$A:$AR,MATCH(Annual!$A8,Segment!$A:$A,0),MATCH("1H"&RIGHT(Annual!AB$1,2),Segment!$A$3:$AR$3,0))+INDEX(Segment!$A:$AR,MATCH(Annual!$A8,Segment!$A:$A,0),MATCH("2H"&RIGHT(Annual!AB$1,2),Segment!$A$3:$AR$3,0)) -> 54.823947 | AE8: 89.01 | AF8: =IF(ISBLANK(AE8),"",INDEX($A8:$AB8,1,MATCH(AE$3,$A$3:$AB$3,0))-AE8) -> #N/A | AG8: 84.5595 | AH8: =IF(ISBLANK(AG8),"",INDEX($A8:$AB8,1,MATCH(AG$3,$A$3:$AB$3,0))-AG8) -> 2.4282
A9: Rev-Legacy licence services (initial fees) | B9: Legacy licence services (initial fees) | C9: AUDm | D9: AR | K9: 28.7 | L9: 43.2 | M9: 28.5 | N9: 17.7 | O9: 9.6 | P9: 3 | Q9: 0.8 | R9: 0 | S9: =INDEX(Segment!$A:$AR,MATCH(Annual!$A9,Segment!$A:$A,0),MATCH("1H"&RIGHT(Annual!S$1,2),Segment!$A$3:$AR$3,0))+INDEX(Segment!$A:$AR,MATCH(Annual!$A9,Segment!$A:$A,0),MATCH("2H"&RIGHT(Annual!S$1,2),Segment!$A$3:$AR$3,0)) -> 1.2 | T9: =INDEX(Segment!$A:$AR,MATCH(Annual!$A9,Segment!$A:$A,0),MATCH("1H"&RIGHT(Annual!T$1,2),Segment!$A$3:$AR$3,0))+INDEX(Segment!$A:$AR,MATCH(Annual!$A9,Segment!$A:$A,0),MATCH("2H"&RIGHT(Annual!T$1,2),Segment!$A$3:$AR$3,0)) -> 1.2 | U9: =INDEX(Segment!$A:$AR,MATCH(Annual!$A9,Segment!$A:$A,0),MATCH("1H"&RIGHT(Annual!U$1,2),Segment!$A$3:$AR$3,0))+INDEX(Segment!$A:$AR,MATCH(Annual!$A9,Segment!$A:$A,0),MATCH("2H"&RIGHT(Annual!U$1,2),Segment!$A$3:$AR$3,0)) -> 1.2 | V9: =INDEX(Segment!$A:$AR,MATCH(Annual!$A9,Segment!$A:$A,0),MATCH("1H"&RIGHT(Annual!V$1,2),Segment!$A$3:$AR$3,0))+INDEX(Segment!$A:$AR,MATCH(Annual!$A9,Segment!$A:$A,0),MATCH("2H"&RIGHT(Annual!V$1,2),Segment!$A$3:$AR$3,0)) -> 1.2 | W9: =INDEX(Segment!$A:$AR,MATCH(Annual!$A9,Segment!$A:$A,0),MATCH("1H"&RIGHT(Annual!W$1,2),Segment!$A$3:$AR$3,0))+INDEX(Segment!$A:$AR,MATCH(Annual!$A9,Segment!$A:$A,0),MATCH("2H"&RIGHT(Annual!W$1,2),Segment!$A$3:$AR$3,0)) -> 1.2 | X9: =INDEX(Segment!$A:$AR,MATCH(Annual!$A9,Segment!$A:$A,0),MATCH("1H"&RIGHT(Annual!X$1,2),Segment!$A$3:$AR$3,0))+INDEX(Segment!$A:$AR,MATCH(Annual!$A9,Segment!$A:$A,0),MATCH("2H"&RIGHT(Annual!X$1,2),Segment!$A$3:$AR$3,0)) -> 1.2 | Y9: =INDEX(Segment!$A:$AR,MATCH(Annual!$A9,Segment!$A:$A,0),MATCH("1H"&RIGHT(Annual!Y$1,2),Segment!$A$3:$AR$3,0))+INDEX(Segment!$A:$AR,MATCH(Annual!$A9,Segment!$A:$A,0),MATCH("2H"&RIGHT(Annual!Y$1,2),Segment!$A$3:$AR$3,0)) -> 1.2 | Z9: =INDEX(Segment!$A:$AR,MATCH(Annual!$A9,Segment!$A:$A,0),MATCH("1H"&RIGHT(Annual!Z$1,2),Segment!$A$3:$AR$3,0))+INDEX(Segment!$A:$AR,MATCH(Annual!$A9,Segment!$A:$A,0),MATCH("2H"&RIGHT(Annual!Z$1,2),Segment!$A$3:$AR$3,0)) -> 1.2 | ... AB9: =INDEX(Segment!$A:$AR,MATCH(Annual!$A9,Segment!$A:$A,0),MATCH("1H"&RIGHT(Annual!AB$1,2),Segment!$A$3:$AR$3,0))+INDEX(Segment!$A:$AR,MATCH(Annual!$A9,Segment!$A:$A,0),MATCH("2H"&RIGHT(Annual!AB$1,2),Segment!$A$3:$AR$3,0)) -> 1.2 | AE9: 0.6 | AF9: =IF(ISBLANK(AE9),"",INDEX($A9:$AB9,1,MATCH(AE$3,$A$3:$AB$3,0))-AE9) -> #N/A | AG9: 1.2 | AH9: =IF(ISBLANK(AG9),"",INDEX($A9:$AB9,1,MATCH(AG$3,$A$3:$AB$3,0))-AG9) -> 0
A10: Rev-Revenue from contracts with customers | B10: Revenue from contracts with customers | C10: AUDm | K10: 253 | L10: 285 | M10: 298.3 | N10: 311.3 | O10: 368.2 | P10: 429.4 | Q10: =SUM(Q6:Q9) -> 506.5 | R10: =SUM(R6:R9) -> 598.502 | S10: =INDEX(Segment!$A:$AR,MATCH(Annual!$A10,Segment!$A:$A,0),MATCH("1H"&RIGHT(Annual!S$1,2),Segment!$A$3:$AR$3,0))+INDEX(Segment!$A:$AR,MATCH(Annual!$A10,Segment!$A:$A,0),MATCH("2H"&RIGHT(Annual!S$1,2),Segment!$A$3:$AR$3,0)) -> 683.078 | T10: =INDEX(Segment!$A:$AR,MATCH(Annual!$A10,Segment!$A:$A,0),MATCH("1H"&RIGHT(Annual!T$1,2),Segment!$A$3:$AR$3,0))+INDEX(Segment!$A:$AR,MATCH(Annual!$A10,Segment!$A:$A,0),MATCH("2H"&RIGHT(Annual!T$1,2),Segment!$A$3:$AR$3,0)) -> 786.71846 | U10: =INDEX(Segment!$A:$AR,MATCH(Annual!$A10,Segment!$A:$A,0),MATCH("1H"&RIGHT(Annual!U$1,2),Segment!$A$3:$AR$3,0))+INDEX(Segment!$A:$AR,MATCH(Annual!$A10,Segment!$A:$A,0),MATCH("2H"&RIGHT(Annual!U$1,2),Segment!$A$3:$AR$3,0)) -> 925.27045 | V10: =INDEX(Segment!$A:$AR,MATCH(Annual!$A10,Segment!$A:$A,0),MATCH("1H"&RIGHT(Annual!V$1,2),Segment!$A$3:$AR$3,0))+INDEX(Segment!$A:$AR,MATCH(Annual!$A10,Segment!$A:$A,0),MATCH("2H"&RIGHT(Annual!V$1,2),Segment!$A$3:$AR$3,0)) -> 1100.4626 | W10: =INDEX(Segment!$A:$AR,MATCH(Annual!$A10,Segment!$A:$A,0),MATCH("1H"&RIGHT(Annual!W$1,2),Segment!$A$3:$AR$3,0))+INDEX(Segment!$A:$AR,MATCH(Annual!$A10,Segment!$A:$A,0),MATCH("2H"&RIGHT(Annual!W$1,2),Segment!$A$3:$AR$3,0)) -> 1311.9173 | X10: =INDEX(Segment!$A:$AR,MATCH(Annual!$A10,Segment!$A:$A,0),MATCH("1H"&RIGHT(Annual!X$1,2),Segment!$A$3:$AR$3,0))+INDEX(Segment!$A:$AR,MATCH(Annual!$A10,Segment!$A:$A,0),MATCH("2H"&RIGHT(Annual!X$1,2),Segment!$A$3:$AR$3,0)) -> 1570.2109 | Y10: =INDEX(Segment!$A:$AR,MATCH(Annual!$A10,Segment!$A:$A,0),MATCH("1H"&RIGHT(Annual!Y$1,2),Segment!$A$3:$AR$3,0))+INDEX(Segment!$A:$AR,MATCH(Annual!$A10,Segment!$A:$A,0),MATCH("2H"&RIGHT(Annual!Y$1,2),Segment!$A$3:$AR$3,0)) -> 1885.8557 | Z10: =INDEX(Segment!$A:$AR,MATCH(Annual!$A10,Segment!$A:$A,0),MATCH("1H"&RIGHT(Annual!Z$1,2),Segment!$A$3:$AR$3,0))+INDEX(Segment!$A:$AR,MATCH(Annual!$A10,Segment!$A:$A,0),MATCH("2H"&RIGHT(Annual!Z$1,2),Segment!$A$3:$AR$3,0)) -> 2271.8428 | ... AB10: =INDEX(Segment!$A:$AR,MATCH(Annual!$A10,Segment!$A:$A,0),MATCH("1H"&RIGHT(Annual!AB$1,2),Segment!$A$3:$AR$3,0))+INDEX(Segment!$A:$AR,MATCH(Annual!$A10,Segment!$A:$A,0),MATCH("2H"&RIGHT(Annual!AB$1,2),Segment!$A$3:$AR$3,0)) -> 3323.0273 | AE10: 594.41116 | AF10: =IF(ISBLANK(AE10),"",INDEX($A10:$AB10,1,MATCH(AE$3,$A$3:$AB$3,0))-AE10) -> #N/A | AG10: 691.61976 | AH10: =IF(ISBLANK(AG10),"",INDEX($A10:$AB10,1,MATCH(AG$3,$A$3:$AB$3,0))-AG10) -> -8.5417589
B11: Growth | C11: % YoY | K11: #DIV/0! | L11: 0.127 | M11: 0.047 | N11: 0.044 | O11: 0.183 | P11: 0.166 | Q11: =Q10/P10-1 -> 0.17955286 | R11: =R10/Q10-1 -> 0.18164265 | S11: =S10/R10-1 -> 0.14131281 | T11: =T10/S10-1 -> 0.15172565 | U11: =U10/T10-1 -> 0.17611382 | V11: =V10/U10-1 -> 0.18934156 | W11: =W10/V10-1 -> 0.19215078 | X11: =X10/W10-1 -> 0.19688249 | ... AB11: =AB10/AA10-1 -> 0.21090395 | AE11: 0.17356596 | AF11: =IF(ISBLANK(AE11),"",INDEX($A11:$AB11,1,MATCH(AE$3,$A$3:$AB$3,0))-AE11) -> #N/A | AG11: 0.16353765 | AH11: =IF(ISBLANK(AG11),"",INDEX($A11:$AB11,1,MATCH(AG$3,$A$3:$AB$3,0))-AG11) -> -0.022224836
AF12: =IF(ISBLANK(AE12),"",INDEX($A12:$AB12,1,MATCH(AE$3,$A$3:$AB$3,0))-AE12) | AH12: =IF(ISBLANK(AG12),"",INDEX($A12:$AB12,1,MATCH(AG$3,$A$3:$AB$3,0))-AG12)
B13: Traditional Consulting Model | AF13: =IF(ISBLANK(AE13),"",INDEX($A13:$AB13,1,MATCH(AE$3,$A$3:$AB$3,0))-AE13) | AH13: =IF(ISBLANK(AG13),"",INDEX($A13:$AB13,1,MATCH(AG$3,$A$3:$AB$3,0))-AG13)
B14: Revenue | AF14: =IF(ISBLANK(AE14),"",INDEX($A14:$AB14,1,MATCH(AE$3,$A$3:$AB$3,0))-AE14) | AH14: =IF(ISBLANK(AG14),"",INDEX($A14:$AB14,1,MATCH(AG$3,$A$3:$AB$3,0))-AG14)
A15: Rev-SaaS fees | B15: SaaS fees | C15: AUDm | D15: AR | K15: 58.1 | L15: 81.5 | M15: 106.2 | N15: 151.1 | O15: 216.8 | P15: 316.2 | Q15: =Q6 -> 407.4 | R15: =R6 -> 499.725 | AF15: =IF(ISBLANK(AE15),"",INDEX($A15:$AB15,1,MATCH(AE$3,$A$3:$AB$3,0))-AE15) | AH15: =IF(ISBLANK(AG15),"",INDEX($A15:$AB15,1,MATCH(AG$3,$A$3:$AB$3,0))-AG15)
B16: Growth from upgrades/implementations (Consulting:SaaS 1.6 ratio) | C16: AUDm | L16: 39.5 | M16: 38.5 | N16: 39.1 | O16: 40.3 | P16: =O22/1.6 -> 45.4375 | Q16: =P22/1.6 -> 45.75 | R16: =Q22/1.6 -> 50.3125 | AF16: =IF(ISBLANK(AE16),"",INDEX($A16:$AB16,1,MATCH(AE$3,$A$3:$AB$3,0))-AE16) | AH16: =IF(ISBLANK(AG16),"",INDEX($A16:$AB16,1,MATCH(AG$3,$A$3:$AB$3,0))-AG16)
B17: Saas Flip | L17: 4.3 | M17: -2.4 | N17: 23.1 | O17: 8.8 | P17: 32.2 | Q17: =-(Q7-P7) -> 19.2 | R17: =-(R7-Q7) -> 10.589 | AF17: =IF(ISBLANK(AE17),"",INDEX($A17:$AB17,1,MATCH(AE$3,$A$3:$AB$3,0))-AE17) | AH17: =IF(ISBLANK(AG17),"",INDEX($A17:$AB17,1,MATCH(AG$3,$A$3:$AB$3,0))-AG17)
B18: Other Growth | C18: AUDm | L18: -20.4 | M18: -11.4 | N18: -17.3 | O18: 16.6 | P18: 21.8 | Q18: =Q15-P15-Q16-Q17 -> 26.25 | R18: =R15-Q15-R16-R17 -> 31.4235 | AF18: =IF(ISBLANK(AE18),"",INDEX($A18:$AB18,1,MATCH(AE$3,$A$3:$AB$3,0))-AE18) | AH18: =IF(ISBLANK(AG18),"",INDEX($A18:$AB18,1,MATCH(AG$3,$A$3:$AB$3,0))-AG18)
B19: Other Growth % of pcp | C19: % | M19: -0.14 | N19: -0.16 | O19: 0.11 | P19: 0.1 | Q19: 0.08 | R19: 0.08 | AF19: =IF(ISBLANK(AE19),"",INDEX($A19:$AB19,1,MATCH(AE$3,$A$3:$AB$3,0))-AE19) | AH19: =IF(ISBLANK(AG19),"",INDEX($A19:$AB19,1,MATCH(AG$3,$A$3:$AB$3,0))-AG19)
AF20: =IF(ISBLANK(AE20),"",INDEX($A20:$AB20,1,MATCH(AE$3,$A$3:$AB$3,0))-AE20) | AH20: =IF(ISBLANK(AG20),"",INDEX($A20:$AB20,1,MATCH(AG$3,$A$3:$AB$3,0))-AG20)
B21: Annual license fees + Legacy | C21: AUDm | K21: 131.7 | L21: 141.9 | M21: 129.6 | N21: 95.7 | O21: 78.8 | P21: 40 | Q21: =Q7+Q9 -> 18.6 | R21: =R7+R9 -> 7.211 | AF21: =IF(ISBLANK(AE21),"",INDEX($A21:$AB21,1,MATCH(AE$3,$A$3:$AB$3,0))-AE21) | AH21: =IF(ISBLANK(AG21),"",INDEX($A21:$AB21,1,MATCH(AG$3,$A$3:$AB$3,0))-AG21)
A22: Rev-Consulting services | B22: Consulting services | C22: AUDm | D22: AR | K22: 63.2 | L22: 61.6 | M22: 62.5 | N22: 64.5 | O22: 72.7 | P22: 73.2 | Q22: =Q8 -> 80.5 | R22: =R8 -> 91.566 | AF22: =IF(ISBLANK(AE22),"",INDEX($A22:$AB22,1,MATCH(AE$3,$A$3:$AB$3,0))-AE22) | AH22: =IF(ISBLANK(AG22),"",INDEX($A22:$AB22,1,MATCH(AG$3,$A$3:$AB$3,0))-AG22)
B23: Growth | C23: % YoY | K23: #DIV/0! | L23: -0.025 | M23: 0.014 | N23: 0.032 | O23: 0.127 | P23: 0.007 | Q23: =Q22/P22-1 -> 0.099726776 | R23: =R22/Q22-1 -> 0.13746584 | AF23: =IF(ISBLANK(AE23),"",INDEX($A23:$AB23,1,MATCH(AE$3,$A$3:$AB$3,0))-AE23) | AH23: =IF(ISBLANK(AG23),"",INDEX($A23:$AB23,1,MATCH(AG$3,$A$3:$AB$3,0))-AG23)
B24: Total Revenue | C24: AUDm | K24: 253 | L24: 285 | M24: 298.3 | N24: 311.3 | O24: 368.2 | P24: 429.4 | Q24: =Q10 -> 506.5 | R24: =R10 -> 598.502 | AF24: =IF(ISBLANK(AE24),"",INDEX($A24:$AB24,1,MATCH(AE$3,$A$3:$AB$3,0))-AE24) | AH24: =IF(ISBLANK(AG24),"",INDEX($A24:$AB24,1,MATCH(AG$3,$A$3:$AB$3,0))-AG24)
AF25: =IF(ISBLANK(AE25),"",INDEX($A25:$AB25,1,MATCH(AE$3,$A$3:$AB$3,0))-AE25) | AH25: =IF(ISBLANK(AG25),"",INDEX($A25:$AB25,1,MATCH(AG$3,$A$3:$AB$3,0))-AG25)
A26: Rev-Other income exc interest | B26: Other income exc interest | C26: AUDm | K26: 0.8 | L26: 0.6 | M26: 0.4 | N26: 0.5 | O26: 0.7 | P26: 7.8 | Q26: 8.9 | R26: 11.526 | S26: =INDEX(Segment!$A:$AR,MATCH(Annual!$A26,Segment!$A:$A,0),MATCH("1H"&RIGHT(Annual!S$1,2),Segment!$A$3:$AR$3,0))+INDEX(Segment!$A:$AR,MATCH(Annual!$A26,Segment!$A:$A,0),MATCH("2H"&RIGHT(Annual!S$1,2),Segment!$A$3:$AR$3,0)) -> 11.526 | T26: =INDEX(Segment!$A:$AR,MATCH(Annual!$A26,Segment!$A:$A,0),MATCH("1H"&RIGHT(Annual!T$1,2),Segment!$A$3:$AR$3,0))+INDEX(Segment!$A:$AR,MATCH(Annual!$A26,Segment!$A:$A,0),MATCH("2H"&RIGHT(Annual!T$1,2),Segment!$A$3:$AR$3,0)) -> 11.526 | U26: =INDEX(Segment!$A:$AR,MATCH(Annual!$A26,Segment!$A:$A,0),MATCH("1H"&RIGHT(Annual!U$1,2),Segment!$A$3:$AR$3,0))+INDEX(Segment!$A:$AR,MATCH(Annual!$A26,Segment!$A:$A,0),MATCH("2H"&RIGHT(Annual!U$1,2),Segment!$A$3:$AR$3,0)) -> 11.526 | V26: =INDEX(Segment!$A:$AR,MATCH(Annual!$A26,Segment!$A:$A,0),MATCH("1H"&RIGHT(Annual!V$1,2),Segment!$A$3:$AR$3,0))+INDEX(Segment!$A:$AR,MATCH(Annual!$A26,Segment!$A:$A,0),MATCH("2H"&RIGHT(Annual!V$1,2),Segment!$A$3:$AR$3,0)) -> 11.526 | W26: =INDEX(Segment!$A:$AR,MATCH(Annual!$A26,Segment!$A:$A,0),MATCH("1H"&RIGHT(Annual!W$1,2),Segment!$A$3:$AR$3,0))+INDEX(Segment!$A:$AR,MATCH(Annual!$A26,Segment!$A:$A,0),MATCH("2H"&RIGHT(Annual!W$1,2),Segment!$A$3:$AR$3,0)) -> 11.526 | X26: =INDEX(Segment!$A:$AR,MATCH(Annual!$A26,Segment!$A:$A,0),MATCH("1H"&RIGHT(Annual!X$1,2),Segment!$A$3:$AR$3,0))+INDEX(Segment!$A:$AR,MATCH(Annual!$A26,Segment!$A:$A,0),MATCH("2H"&RIGHT(Annual!X$1,2),Segment!$A$3:$AR$3,0)) -> 11.526 | Y26: =INDEX(Segment!$A:$AR,MATCH(Annual!$A26,Segment!$A:$A,0),MATCH("1H"&RIGHT(Annual!Y$1,2),Segment!$A$3:$AR$3,0))+INDEX(Segment!$A:$AR,MATCH(Annual!$A26,Segment!$A:$A,0),MATCH("2H"&RIGHT(Annual!Y$1,2),Segment!$A$3:$AR$3,0)) -> 11.526 | Z26: =INDEX(Segment!$A:$AR,MATCH(Annual!$A26,Segment!$A:$A,0),MATCH("1H"&RIGHT(Annual!Z$1,2),Segment!$A$3:$AR$3,0))+INDEX(Segment!$A:$AR,MATCH(Annual!$A26,Segment!$A:$A,0),MATCH("2H"&RIGHT(Annual!Z$1,2),Segment!$A$3:$AR$3,0)) -> 11.526 | ... AB26: =INDEX(Segment!$A:$AR,MATCH(Annual!$A26,Segment!$A:$A,0),MATCH("1H"&RIGHT(Annual!AB$1,2),Segment!$A$3:$AR$3,0))+INDEX(Segment!$A:$AR,MATCH(Annual!$A26,Segment!$A:$A,0),MATCH("2H"&RIGHT(Annual!AB$1,2),Segment!$A$3:$AR$3,0)) -> 11.526 | AE26: 10.6 | AF26: =IF(ISBLANK(AE26),"",INDEX($A26:$AB26,1,MATCH(AE$3,$A$3:$AB$3,0))-AE26) -> #N/A | AG26: 10.6 | AH26: =IF(ISBLANK(AG26),"",INDEX($A26:$AB26,1,MATCH(AG$3,$A$3:$AB$3,0))-AG26) -> 0.926
A27: Rev-Total Revenue exc interest | B27: Total Revenue exc interest | C27: AUDm | D27: Preso | E27: 169.1 | F27: 180.6 | G27: 195.1 | H27: 218.7 | I27: 249 | J27: 273.3 | K27: 253.8 | L27: 285.6 | M27: 298.7 | N27: 311.8 | O27: 369 | P27: 437.2 | Q27: =Q10+Q26 -> 515.4 | R27: =R10+R26 -> 610.028 | S27: =S10+S26 -> 694.604 | T27: =T10+T26 -> 798.24446 | U27: =U10+U26 -> 936.79645 | V27: =V10+V26 -> 1111.9886 | W27: =W10+W26 -> 1323.4433 | X27: =X10+X26 -> 1581.7369 | ... AB27: =AB10+AB26 -> 3334.5533 | AE27: 605.01116 | AF27: =IF(ISBLANK(AE27),"",INDEX($A27:$AB27,1,MATCH(AE$3,$A$3:$AB$3,0))-AE27) -> #N/A | AG27: 702.21976 | AH27: =IF(ISBLANK(AG27),"",INDEX($A27:$AB27,1,MATCH(AG$3,$A$3:$AB$3,0))-AG27) -> -7.6157589
B28: Growth | C28: % YoY | F28: 0.068 | G28: 0.08 | H28: 0.121 | I28: 0.139 | J28: 0.097 | K28: -0.071 | L28: 0.126 | M28: 0.046 | N28: 0.044 | O28: 0.183 | P28: 0.185 | Q28: =Q27/P27-1 -> 0.17886551 | R28: =R27/Q27-1 -> 0.18360109 | S28: =S27/R27-1 -> 0.13864282 | T28: =T27/S27-1 -> 0.14920797 | U28: =U27/T27-1 -> 0.17357088 | V28: =V27/U27-1 -> 0.18701197 | W28: =W27/V27-1 -> 0.19015909 | X28: =X27/W27-1 -> 0.19516782 | ... AB28: =AB27/AA27-1 -> 0.21002184 | AE28: 0.1738672 | AF28: =IF(ISBLANK(AE28),"",INDEX($A28:$AB28,1,MATCH(AE$3,$A$3:$AB$3,0))-AE28) -> #N/A | AG28: 0.16067242 | AH28: =IF(ISBLANK(AG28),"",INDEX($A28:$AB28,1,MATCH(AG$3,$A$3:$AB$3,0))-AG28) -> -0.022029596
AF29: =IF(ISBLANK(AE29),"",INDEX($A29:$AB29,1,MATCH(AE$3,$A$3:$AB$3,0))-AE29) | AH29: =IF(ISBLANK(AG29),"",INDEX($A29:$AB29,1,MATCH(AG$3,$A$3:$AB$3,0))-AG29)
B30: Cost of Sales | AF30: =IF(ISBLANK(AE30),"",INDEX($A30:$AB30,1,MATCH(AE$3,$A$3:$AB$3,0))-AE30) | AH30: =IF(ISBLANK(AG30),"",INDEX($A30:$AB30,1,MATCH(AG$3,$A$3:$AB$3,0))-AG30)
A31: Costs-Variable costs | B31: Variable costs | C31: AUDm | D31: AR | K31: -24.5 | L31: -19.7 | M31: -19.1 | N31: -19.4 | O31: -20.7 | P31: -21 | Q31: -23.2 | R31: -23.03 | S31: =INDEX(Segment!$A:$AR,MATCH(Annual!$A31,Segment!$A:$A,0),MATCH("1H"&RIGHT(Annual!S$1,2),Segment!$A$3:$AR$3,0))+INDEX(Segment!$A:$AR,MATCH(Annual!$A31,Segment!$A:$A,0),MATCH("2H"&RIGHT(Annual!S$1,2),Segment!$A$3:$AR$3,0)) -> -26.237176 | T31: =INDEX(Segment!$A:$AR,MATCH(Annual!$A31,Segment!$A:$A,0),MATCH("1H"&RIGHT(Annual!T$1,2),Segment!$A$3:$AR$3,0))+INDEX(Segment!$A:$AR,MATCH(Annual!$A31,Segment!$A:$A,0),MATCH("2H"&RIGHT(Annual!T$1,2),Segment!$A$3:$AR$3,0)) -> -30.121113 | U31: =INDEX(Segment!$A:$AR,MATCH(Annual!$A31,Segment!$A:$A,0),MATCH("1H"&RIGHT(Annual!U$1,2),Segment!$A$3:$AR$3,0))+INDEX(Segment!$A:$AR,MATCH(Annual!$A31,Segment!$A:$A,0),MATCH("2H"&RIGHT(Annual!U$1,2),Segment!$A$3:$AR$3,0)) -> -35.296276 | V31: =INDEX(Segment!$A:$AR,MATCH(Annual!$A31,Segment!$A:$A,0),MATCH("1H"&RIGHT(Annual!V$1,2),Segment!$A$3:$AR$3,0))+INDEX(Segment!$A:$AR,MATCH(Annual!$A31,Segment!$A:$A,0),MATCH("2H"&RIGHT(Annual!V$1,2),Segment!$A$3:$AR$3,0)) -> -41.917711 | W31: =INDEX(Segment!$A:$AR,MATCH(Annual!$A31,Segment!$A:$A,0),MATCH("1H"&RIGHT(Annual!W$1,2),Segment!$A$3:$AR$3,0))+INDEX(Segment!$A:$AR,MATCH(Annual!$A31,Segment!$A:$A,0),MATCH("2H"&RIGHT(Annual!W$1,2),Segment!$A$3:$AR$3,0)) -> -49.890916 | X31: =INDEX(Segment!$A:$AR,MATCH(Annual!$A31,Segment!$A:$A,0),MATCH("1H"&RIGHT(Annual!X$1,2),Segment!$A$3:$AR$3,0))+INDEX(Segment!$A:$AR,MATCH(Annual!$A31,Segment!$A:$A,0),MATCH("2H"&RIGHT(Annual!X$1,2),Segment!$A$3:$AR$3,0)) -> -59.630427 | Y31: =INDEX(Segment!$A:$AR,MATCH(Annual!$A31,Segment!$A:$A,0),MATCH("1H"&RIGHT(Annual!Y$1,2),Segment!$A$3:$AR$3,0))+INDEX(Segment!$A:$AR,MATCH(Annual!$A31,Segment!$A:$A,0),MATCH("2H"&RIGHT(Annual!Y$1,2),Segment!$A$3:$AR$3,0)) -> -71.53278 | Z31: =INDEX(Segment!$A:$AR,MATCH(Annual!$A31,Segment!$A:$A,0),MATCH("1H"&RIGHT(Annual!Z$1,2),Segment!$A$3:$AR$3,0))+INDEX(Segment!$A:$AR,MATCH(Annual!$A31,Segment!$A:$A,0),MATCH("2H"&RIGHT(Annual!Z$1,2),Segment!$A$3:$AR$3,0)) -> -86.088034 | ... AB31: =INDEX(Segment!$A:$AR,MATCH(Annual!$A31,Segment!$A:$A,0),MATCH("1H"&RIGHT(Annual!AB$1,2),Segment!$A$3:$AR$3,0))+INDEX(Segment!$A:$AR,MATCH(Annual!$A31,Segment!$A:$A,0),MATCH("2H"&RIGHT(Annual!AB$1,2),Segment!$A$3:$AR$3,0)) -> -125.72947 | AE31: -27.106664 | AF31: =IF(ISBLANK(AE31),"",INDEX($A31:$AB31,1,MATCH(AE$3,$A$3:$AB$3,0))-AE31) -> #N/A | AG31: -31.461729 | AH31: =IF(ISBLANK(AG31),"",INDEX($A31:$AB31,1,MATCH(AG$3,$A$3:$AB$3,0))-AG31) -> 5.2245525
A32: Costs-Variable customer SaaS costs | B32: Variable customer SaaS costs | C32: AUDm | D32: AR | K32: -11.9 | L32: -17 | M32: -19.5 | N32: -21.9 | O32: -26.4 | P32: -34.9 | Q32: -38 | R32: -58.91 | S32: =INDEX(Segment!$A:$AR,MATCH(Annual!$A32,Segment!$A:$A,0),MATCH("1H"&RIGHT(Annual!S$1,2),Segment!$A$3:$AR$3,0))+INDEX(Segment!$A:$AR,MATCH(Annual!$A32,Segment!$A:$A,0),MATCH("2H"&RIGHT(Annual!S$1,2),Segment!$A$3:$AR$3,0)) -> -67.073374 | T32: =INDEX(Segment!$A:$AR,MATCH(Annual!$A32,Segment!$A:$A,0),MATCH("1H"&RIGHT(Annual!T$1,2),Segment!$A$3:$AR$3,0))+INDEX(Segment!$A:$AR,MATCH(Annual!$A32,Segment!$A:$A,0),MATCH("2H"&RIGHT(Annual!T$1,2),Segment!$A$3:$AR$3,0)) -> -77.090091 | U32: =INDEX(Segment!$A:$AR,MATCH(Annual!$A32,Segment!$A:$A,0),MATCH("1H"&RIGHT(Annual!U$1,2),Segment!$A$3:$AR$3,0))+INDEX(Segment!$A:$AR,MATCH(Annual!$A32,Segment!$A:$A,0),MATCH("2H"&RIGHT(Annual!U$1,2),Segment!$A$3:$AR$3,0)) -> -90.485856 | V32: =INDEX(Segment!$A:$AR,MATCH(Annual!$A32,Segment!$A:$A,0),MATCH("1H"&RIGHT(Annual!V$1,2),Segment!$A$3:$AR$3,0))+INDEX(Segment!$A:$AR,MATCH(Annual!$A32,Segment!$A:$A,0),MATCH("2H"&RIGHT(Annual!V$1,2),Segment!$A$3:$AR$3,0)) -> -107.40189 | W32: =INDEX(Segment!$A:$AR,MATCH(Annual!$A32,Segment!$A:$A,0),MATCH("1H"&RIGHT(Annual!W$1,2),Segment!$A$3:$AR$3,0))+INDEX(Segment!$A:$AR,MATCH(Annual!$A32,Segment!$A:$A,0),MATCH("2H"&RIGHT(Annual!W$1,2),Segment!$A$3:$AR$3,0)) -> -127.82472 | X32: =INDEX(Segment!$A:$AR,MATCH(Annual!$A32,Segment!$A:$A,0),MATCH("1H"&RIGHT(Annual!X$1,2),Segment!$A$3:$AR$3,0))+INDEX(Segment!$A:$AR,MATCH(Annual!$A32,Segment!$A:$A,0),MATCH("2H"&RIGHT(Annual!X$1,2),Segment!$A$3:$AR$3,0)) -> -152.7713 | Y32: =INDEX(Segment!$A:$AR,MATCH(Annual!$A32,Segment!$A:$A,0),MATCH("1H"&RIGHT(Annual!Y$1,2),Segment!$A$3:$AR$3,0))+INDEX(Segment!$A:$AR,MATCH(Annual!$A32,Segment!$A:$A,0),MATCH("2H"&RIGHT(Annual!Y$1,2),Segment!$A$3:$AR$3,0)) -> -183.25691 | Z32: =INDEX(Segment!$A:$AR,MATCH(Annual!$A32,Segment!$A:$A,0),MATCH("1H"&RIGHT(Annual!Z$1,2),Segment!$A$3:$AR$3,0))+INDEX(Segment!$A:$AR,MATCH(Annual!$A32,Segment!$A:$A,0),MATCH("2H"&RIGHT(Annual!Z$1,2),Segment!$A$3:$AR$3,0)) -> -220.53621 | ... AB32: =INDEX(Segment!$A:$AR,MATCH(Annual!$A32,Segment!$A:$A,0),MATCH("1H"&RIGHT(Annual!AB$1,2),Segment!$A$3:$AR$3,0))+INDEX(Segment!$A:$AR,MATCH(Annual!$A32,Segment!$A:$A,0),MATCH("2H"&RIGHT(Annual!AB$1,2),Segment!$A$3:$AR$3,0)) -> -322.06079 | AE32: -45.346885 | AF32: =IF(ISBLANK(AE32),"",INDEX($A32:$AB32,1,MATCH(AE$3,$A$3:$AB$3,0))-AE32) -> #N/A | AG32: -52.624196 | AH32: =IF(ISBLANK(AG32),"",INDEX($A32:$AB32,1,MATCH(AG$3,$A$3:$AB$3,0))-AG32) -> -14.449177
A33: Costs-Other | B33: Other | C33: AUDm | S33: =INDEX(Segment!$A:$AR,MATCH(Annual!$A33,Segment!$A:$A,0),MATCH("1H"&RIGHT(Annual!S$1,2),Segment!$A$3:$AR$3,0))+INDEX(Segment!$A:$AR,MATCH(Annual!$A33,Segment!$A:$A,0),MATCH("2H"&RIGHT(Annual!S$1,2),Segment!$A$3:$AR$3,0)) -> 0 | T33: =INDEX(Segment!$A:$AR,MATCH(Annual!$A33,Segment!$A:$A,0),MATCH("1H"&RIGHT(Annual!T$1,2),Segment!$A$3:$AR$3,0))+INDEX(Segment!$A:$AR,MATCH(Annual!$A33,Segment!$A:$A,0),MATCH("2H"&RIGHT(Annual!T$1,2),Segment!$A$3:$AR$3,0)) -> 0 | U33: =INDEX(Segment!$A:$AR,MATCH(Annual!$A33,Segment!$A:$A,0),MATCH("1H"&RIGHT(Annual!U$1,2),Segment!$A$3:$AR$3,0))+INDEX(Segment!$A:$AR,MATCH(Annual!$A33,Segment!$A:$A,0),MATCH("2H"&RIGHT(Annual!U$1,2),Segment!$A$3:$AR$3,0)) -> 0 | V33: =INDEX(Segment!$A:$AR,MATCH(Annual!$A33,Segment!$A:$A,0),MATCH("1H"&RIGHT(Annual!V$1,2),Segment!$A$3:$AR$3,0))+INDEX(Segment!$A:$AR,MATCH(Annual!$A33,Segment!$A:$A,0),MATCH("2H"&RIGHT(Annual!V$1,2),Segment!$A$3:$AR$3,0)) -> 0 | W33: =INDEX(Segment!$A:$AR,MATCH(Annual!$A33,Segment!$A:$A,0),MATCH("1H"&RIGHT(Annual!W$1,2),Segment!$A$3:$AR$3,0))+INDEX(Segment!$A:$AR,MATCH(Annual!$A33,Segment!$A:$A,0),MATCH("2H"&RIGHT(Annual!W$1,2),Segment!$A$3:$AR$3,0)) -> 0 | X33: =INDEX(Segment!$A:$AR,MATCH(Annual!$A33,Segment!$A:$A,0),MATCH("1H"&RIGHT(Annual!X$1,2),Segment!$A$3:$AR$3,0))+INDEX(Segment!$A:$AR,MATCH(Annual!$A33,Segment!$A:$A,0),MATCH("2H"&RIGHT(Annual!X$1,2),Segment!$A$3:$AR$3,0)) -> 0 | Y33: =INDEX(Segment!$A:$AR,MATCH(Annual!$A33,Segment!$A:$A,0),MATCH("1H"&RIGHT(Annual!Y$1,2),Segment!$A$3:$AR$3,0))+INDEX(Segment!$A:$AR,MATCH(Annual!$A33,Segment!$A:$A,0),MATCH("2H"&RIGHT(Annual!Y$1,2),Segment!$A$3:$AR$3,0)) -> 0 | Z33: =INDEX(Segment!$A:$AR,MATCH(Annual!$A33,Segment!$A:$A,0),MATCH("1H"&RIGHT(Annual!Z$1,2),Segment!$A$3:$AR$3,0))+INDEX(Segment!$A:$AR,MATCH(Annual!$A33,Segment!$A:$A,0),MATCH("2H"&RIGHT(Annual!Z$1,2),Segment!$A$3:$AR$3,0)) -> 0 | ... AB33: =INDEX(Segment!$A:$AR,MATCH(Annual!$A33,Segment!$A:$A,0),MATCH("1H"&RIGHT(Annual!AB$1,2),Segment!$A$3:$AR$3,0))+INDEX(Segment!$A:$AR,MATCH(Annual!$A33,Segment!$A:$A,0),MATCH("2H"&RIGHT(Annual!AB$1,2),Segment!$A$3:$AR$3,0)) -> 0 | AE33: 0 | AF33: =IF(ISBLANK(AE33),"",INDEX($A33:$AB33,1,MATCH(AE$3,$A$3:$AB$3,0))-AE33) -> #N/A | AG33: 0 | AH33: =IF(ISBLANK(AG33),"",INDEX($A33:$AB33,1,MATCH(AG$3,$A$3:$AB$3,0))-AG33) -> 0
B34: Cost of Sales | C34: AUDm | K34: -36.4 | L34: -36.7 | M34: -38.6 | N34: -41.4 | O34: -47.1 | P34: -55.9 | Q34: =SUM(Q31:Q33) -> -61.2 | R34: =SUM(R31:R33) -> -81.94 | S34: =SUM(S31:S33) -> -93.31055 | T34: =SUM(T31:T33) -> -107.2112 | U34: =SUM(U31:U33) -> -125.78213 | V34: =SUM(V31:V33) -> -149.3196 | W34: =SUM(W31:W33) -> -177.71563 | X34: =SUM(X31:X33) -> -212.40173 | ... AB34: =SUM(AB31:AB33) -> -447.79025 | AE34: -72.453549 | AF34: =IF(ISBLANK(AE34),"",INDEX($A34:$AB34,1,MATCH(AE$3,$A$3:$AB$3,0))-AE34) -> #N/A | AG34: -84.085925 | AH34: =IF(ISBLANK(AG34),"",INDEX($A34:$AB34,1,MATCH(AG$3,$A$3:$AB$3,0))-AG34) -> -9.2246249
AF35: =IF(ISBLANK(AE35),"",INDEX($A35:$AB35,1,MATCH(AE$3,$A$3:$AB$3,0))-AE35) | AH35: =IF(ISBLANK(AG35),"",INDEX($A35:$AB35,1,MATCH(AG$3,$A$3:$AB$3,0))-AG35)
A36: GP-Gross Profit | B36: Gross Profit | C36: AUDm | D36: Preso | K36: 217.4 | L36: 249 | M36: 260.1 | N36: 270.4 | O36: 321.9 | P36: 381.3 | Q36: =Q27+Q34 -> 454.2 | R36: =R27+R34 -> 528.088 | S36: =INDEX(Segment!$A:$AR,MATCH(Annual!$A36,Segment!$A:$A,0),MATCH("1H"&RIGHT(Annual!S$1,2),Segment!$A$3:$AR$3,0))+INDEX(Segment!$A:$AR,MATCH(Annual!$A36,Segment!$A:$A,0),MATCH("2H"&RIGHT(Annual!S$1,2),Segment!$A$3:$AR$3,0)) -> 601.29345 | T36: =INDEX(Segment!$A:$AR,MATCH(Annual!$A36,Segment!$A:$A,0),MATCH("1H"&RIGHT(Annual!T$1,2),Segment!$A$3:$AR$3,0))+INDEX(Segment!$A:$AR,MATCH(Annual!$A36,Segment!$A:$A,0),MATCH("2H"&RIGHT(Annual!T$1,2),Segment!$A$3:$AR$3,0)) -> 691.03325 | U36: =INDEX(Segment!$A:$AR,MATCH(Annual!$A36,Segment!$A:$A,0),MATCH("1H"&RIGHT(Annual!U$1,2),Segment!$A$3:$AR$3,0))+INDEX(Segment!$A:$AR,MATCH(Annual!$A36,Segment!$A:$A,0),MATCH("2H"&RIGHT(Annual!U$1,2),Segment!$A$3:$AR$3,0)) -> 811.01432 | V36: =INDEX(Segment!$A:$AR,MATCH(Annual!$A36,Segment!$A:$A,0),MATCH("1H"&RIGHT(Annual!V$1,2),Segment!$A$3:$AR$3,0))+INDEX(Segment!$A:$AR,MATCH(Annual!$A36,Segment!$A:$A,0),MATCH("2H"&RIGHT(Annual!V$1,2),Segment!$A$3:$AR$3,0)) -> 962.66899 | W36: =INDEX(Segment!$A:$AR,MATCH(Annual!$A36,Segment!$A:$A,0),MATCH("1H"&RIGHT(Annual!W$1,2),Segment!$A$3:$AR$3,0))+INDEX(Segment!$A:$AR,MATCH(Annual!$A36,Segment!$A:$A,0),MATCH("2H"&RIGHT(Annual!W$1,2),Segment!$A$3:$AR$3,0)) -> 1145.7277 | X36: =INDEX(Segment!$A:$AR,MATCH(Annual!$A36,Segment!$A:$A,0),MATCH("1H"&RIGHT(Annual!X$1,2),Segment!$A$3:$AR$3,0))+INDEX(Segment!$A:$AR,MATCH(Annual!$A36,Segment!$A:$A,0),MATCH("2H"&RIGHT(Annual!X$1,2),Segment!$A$3:$AR$3,0)) -> 1369.3352 | Y36: =INDEX(Segment!$A:$AR,MATCH(Annual!$A36,Segment!$A:$A,0),MATCH("1H"&RIGHT(Annual!Y$1,2),Segment!$A$3:$AR$3,0))+INDEX(Segment!$A:$AR,MATCH(Annual!$A36,Segment!$A:$A,0),MATCH("2H"&RIGHT(Annual!Y$1,2),Segment!$A$3:$AR$3,0)) -> 1642.592 | Z36: =INDEX(Segment!$A:$AR,MATCH(Annual!$A36,Segment!$A:$A,0),MATCH("1H"&RIGHT(Annual!Z$1,2),Segment!$A$3:$AR$3,0))+INDEX(Segment!$A:$AR,MATCH(Annual!$A36,Segment!$A:$A,0),MATCH("2H"&RIGHT(Annual!Z$1,2),Segment!$A$3:$AR$3,0)) -> 1976.7446 | ... AB36: =INDEX(Segment!$A:$AR,MATCH(Annual!$A36,Segment!$A:$A,0),MATCH("1H"&RIGHT(Annual!AB$1,2),Segment!$A$3:$AR$3,0))+INDEX(Segment!$A:$AR,MATCH(Annual!$A36,Segment!$A:$A,0),MATCH("2H"&RIGHT(Annual!AB$1,2),Segment!$A$3:$AR$3,0)) -> 2886.763 | AE36: 532.55761 | AF36: =IF(ISBLANK(AE36),"",INDEX($A36:$AB36,1,MATCH(AE$3,$A$3:$AB$3,0))-AE36) -> #N/A | AG36: 618.13384 | AH36: =IF(ISBLANK(AG36),"",INDEX($A36:$AB36,1,MATCH(AG$3,$A$3:$AB$3,0))-AG36) -> -16.840384
B37: Gross profit margin | C37: % | D37: #VALUE! | K37: 0.857 | L37: 0.872 | M37: 0.871 | N37: 0.867 | O37: 0.872 | P37: 0.872 | Q37: =Q36/Q$27 -> 0.88125728 | R37: =R36/R$27 -> 0.8656783 | S37: =S36/S27 -> 0.86566367 | T37: =T36/T27 -> 0.86569126 | U37: =U36/U27 -> 0.86573163 | V37: =V36/V27 -> 0.8657184 | W37: =W36/W27 -> 0.86571723 | X37: =X36/X27 -> 0.86571615 | Y37: =Y36/Y27 -> 0.86571511 | Z37: =Z36/Z27 -> 0.8657141 | ... AB37: =AB36/AB27 -> 0.86571207 | AE37: 0.88024428 | AF37: =IF(ISBLANK(AE37),"",INDEX($A37:$AB37,1,MATCH(AE$3,$A$3:$AB$3,0))-AE37) -> #N/A | AG37: 0.88025697 | AH37: =IF(ISBLANK(AG37),"",INDEX($A37:$AB37,1,MATCH(AG$3,$A$3:$AB$3,0))-AG37) -> -0.014593292
AF38: =IF(ISBLANK(AE38),"",INDEX($A38:$AB38,1,MATCH(AE$3,$A$3:$AB$3,0))-AE38) | AH38: =IF(ISBLANK(AG38),"",INDEX($A38:$AB38,1,MATCH(AG$3,$A$3:$AB$3,0))-AG38)
A39: Opex-Operating costs | B39: Operating costs | C39: AUDm | D39: Preso | K39: -133.7 | L39: -139.1 | M39: -126.8 | N39: -110.3 | O39: -127.9 | P39: -148.6 | Q39: =Q50-Q36-Q46 -> -180.1 | R39: =R50-R36-R46 -> -203.088 | S39: =INDEX(Segment!$A:$AR,MATCH(Annual!$A39,Segment!$A:$A,0),MATCH("1H"&RIGHT(Annual!S$1,2),Segment!$A$3:$AR$3,0))+INDEX(Segment!$A:$AR,MATCH(Annual!$A39,Segment!$A:$A,0),MATCH("2H"&RIGHT(Annual!S$1,2),Segment!$A$3:$AR$3,0)) -> -224.32787 | T39: =INDEX(Segment!$A:$AR,MATCH(Annual!$A39,Segment!$A:$A,0),MATCH("1H"&RIGHT(Annual!T$1,2),Segment!$A$3:$AR$3,0))+INDEX(Segment!$A:$AR,MATCH(Annual!$A39,Segment!$A:$A,0),MATCH("2H"&RIGHT(Annual!T$1,2),Segment!$A$3:$AR$3,0)) -> -249.75358 | U39: =INDEX(Segment!$A:$AR,MATCH(Annual!$A39,Segment!$A:$A,0),MATCH("1H"&RIGHT(Annual!U$1,2),Segment!$A$3:$AR$3,0))+INDEX(Segment!$A:$AR,MATCH(Annual!$A39,Segment!$A:$A,0),MATCH("2H"&RIGHT(Annual!U$1,2),Segment!$A$3:$AR$3,0)) -> -283.62681 | V39: =INDEX(Segment!$A:$AR,MATCH(Annual!$A39,Segment!$A:$A,0),MATCH("1H"&RIGHT(Annual!V$1,2),Segment!$A$3:$AR$3,0))+INDEX(Segment!$A:$AR,MATCH(Annual!$A39,Segment!$A:$A,0),MATCH("2H"&RIGHT(Annual!V$1,2),Segment!$A$3:$AR$3,0)) -> -331.15077 | W39: =INDEX(Segment!$A:$AR,MATCH(Annual!$A39,Segment!$A:$A,0),MATCH("1H"&RIGHT(Annual!W$1,2),Segment!$A$3:$AR$3,0))+INDEX(Segment!$A:$AR,MATCH(Annual!$A39,Segment!$A:$A,0),MATCH("2H"&RIGHT(Annual!W$1,2),Segment!$A$3:$AR$3,0)) -> -387.50935 | X39: =INDEX(Segment!$A:$AR,MATCH(Annual!$A39,Segment!$A:$A,0),MATCH("1H"&RIGHT(Annual!X$1,2),Segment!$A$3:$AR$3,0))+INDEX(Segment!$A:$AR,MATCH(Annual!$A39,Segment!$A:$A,0),MATCH("2H"&RIGHT(Annual!X$1,2),Segment!$A$3:$AR$3,0)) -> -455.23496 | Y39: =INDEX(Segment!$A:$AR,MATCH(Annual!$A39,Segment!$A:$A,0),MATCH("1H"&RIGHT(Annual!Y$1,2),Segment!$A$3:$AR$3,0))+INDEX(Segment!$A:$AR,MATCH(Annual!$A39,Segment!$A:$A,0),MATCH("2H"&RIGHT(Annual!Y$1,2),Segment!$A$3:$AR$3,0)) -> -536.59849 | Z39: =INDEX(Segment!$A:$AR,MATCH(Annual!$A39,Segment!$A:$A,0),MATCH("1H"&RIGHT(Annual!Z$1,2),Segment!$A$3:$AR$3,0))+INDEX(Segment!$A:$AR,MATCH(Annual!$A39,Segment!$A:$A,0),MATCH("2H"&RIGHT(Annual!Z$1,2),Segment!$A$3:$AR$3,0)) -> -634.34931 | ... AB39: =INDEX(Segment!$A:$AR,MATCH(Annual!$A39,Segment!$A:$A,0),MATCH("1H"&RIGHT(Annual!AB$1,2),Segment!$A$3:$AR$3,0))+INDEX(Segment!$A:$AR,MATCH(Annual!$A39,Segment!$A:$A,0),MATCH("2H"&RIGHT(Annual!AB$1,2),Segment!$A$3:$AR$3,0)) -> -893.0558 | AE39: -210.27387 | AF39: =IF(ISBLANK(AE39),"",INDEX($A39:$AB39,1,MATCH(AE$3,$A$3:$AB$3,0))-AE39) -> #N/A | AG39: -237.03649 | AH39: =IF(ISBLANK(AG39),"",INDEX($A39:$AB39,1,MATCH(AG$3,$A$3:$AB$3,0))-AG39) -> 12.708618
B40: % of sales | K40: -0.527 | L40: -0.487 | M40: -0.425 | N40: -0.354 | O40: -0.347 | P40: -0.34 | Q40: =Q39/Q$27 -> -0.34943733 | R40: =R39/R$27 -> -0.33291587 | S40: =S39/S$27 -> -0.32295793 | T40: =T39/T$27 -> -0.31287857 | U40: =U39/U$27 -> -0.30276247 | V40: =V39/V$27 -> -0.29780051 | W40: =W39/W$27 -> -0.29280388 | X40: =X39/X$27 -> -0.28780701 | ... AB40: =AB39/AB$27 -> -0.26781872 | AE40: -0.3475537 | AF40: =IF(ISBLANK(AE40),"",INDEX($A40:$AB40,1,MATCH(AE$3,$A$3:$AB$3,0))-AE40) -> #N/A | AG40: -0.33755314 | AH40: =IF(ISBLANK(AG40),"",INDEX($A40:$AB40,1,MATCH(AG$3,$A$3:$AB$3,0))-AG40) -> 0.014595215
AF41: =IF(ISBLANK(AE41),"",INDEX($A41:$AB41,1,MATCH(AE$3,$A$3:$AB$3,0))-AE41) | AH41: =IF(ISBLANK(AG41),"",INDEX($A41:$AB41,1,MATCH(AG$3,$A$3:$AB$3,0))-AG41)
A42: EBITDA-EBITDAR | B42: EBITDAR | C42: AUDm | D42: Preso | H42: 90.2 | I42: 102.4 | J42: 111.4 | K42: 83.6 | L42: 109.9 | M42: 133.2 | N42: 160.1 | O42: 194 | P42: 232.7 | Q42: =Q50-Q46 -> 274.1 | R42: =R50-R46 -> 325 | S42: =INDEX(Segment!$A:$AR,MATCH(Annual!$A42,Segment!$A:$A,0),MATCH("1H"&RIGHT(Annual!S$1,2),Segment!$A$3:$AR$3,0))+INDEX(Segment!$A:$AR,MATCH(Annual!$A42,Segment!$A:$A,0),MATCH("2H"&RIGHT(Annual!S$1,2),Segment!$A$3:$AR$3,0)) -> 376.96558 | T42: =INDEX(Segment!$A:$AR,MATCH(Annual!$A42,Segment!$A:$A,0),MATCH("1H"&RIGHT(Annual!T$1,2),Segment!$A$3:$AR$3,0))+INDEX(Segment!$A:$AR,MATCH(Annual!$A42,Segment!$A:$A,0),MATCH("2H"&RIGHT(Annual!T$1,2),Segment!$A$3:$AR$3,0)) -> 441.27967 | U42: =INDEX(Segment!$A:$AR,MATCH(Annual!$A42,Segment!$A:$A,0),MATCH("1H"&RIGHT(Annual!U$1,2),Segment!$A$3:$AR$3,0))+INDEX(Segment!$A:$AR,MATCH(Annual!$A42,Segment!$A:$A,0),MATCH("2H"&RIGHT(Annual!U$1,2),Segment!$A$3:$AR$3,0)) -> 527.38751 | V42: =INDEX(Segment!$A:$AR,MATCH(Annual!$A42,Segment!$A:$A,0),MATCH("1H"&RIGHT(Annual!V$1,2),Segment!$A$3:$AR$3,0))+INDEX(Segment!$A:$AR,MATCH(Annual!$A42,Segment!$A:$A,0),MATCH("2H"&RIGHT(Annual!V$1,2),Segment!$A$3:$AR$3,0)) -> 631.51822 | W42: =INDEX(Segment!$A:$AR,MATCH(Annual!$A42,Segment!$A:$A,0),MATCH("1H"&RIGHT(Annual!W$1,2),Segment!$A$3:$AR$3,0))+INDEX(Segment!$A:$AR,MATCH(Annual!$A42,Segment!$A:$A,0),MATCH("2H"&RIGHT(Annual!W$1,2),Segment!$A$3:$AR$3,0)) -> 758.21836 | X42: =INDEX(Segment!$A:$AR,MATCH(Annual!$A42,Segment!$A:$A,0),MATCH("1H"&RIGHT(Annual!X$1,2),Segment!$A$3:$AR$3,0))+INDEX(Segment!$A:$AR,MATCH(Annual!$A42,Segment!$A:$A,0),MATCH("2H"&RIGHT(Annual!X$1,2),Segment!$A$3:$AR$3,0)) -> 914.10021 | Y42: =INDEX(Segment!$A:$AR,MATCH(Annual!$A42,Segment!$A:$A,0),MATCH("1H"&RIGHT(Annual!Y$1,2),Segment!$A$3:$AR$3,0))+INDEX(Segment!$A:$AR,MATCH(Annual!$A42,Segment!$A:$A,0),MATCH("2H"&RIGHT(Annual!Y$1,2),Segment!$A$3:$AR$3,0)) -> 1105.9935 | Z42: =INDEX(Segment!$A:$AR,MATCH(Annual!$A42,Segment!$A:$A,0),MATCH("1H"&RIGHT(Annual!Z$1,2),Segment!$A$3:$AR$3,0))+INDEX(Segment!$A:$AR,MATCH(Annual!$A42,Segment!$A:$A,0),MATCH("2H"&RIGHT(Annual!Z$1,2),Segment!$A$3:$AR$3,0)) -> 1342.3953 | ... AB42: =INDEX(Segment!$A:$AR,MATCH(Annual!$A42,Segment!$A:$A,0),MATCH("1H"&RIGHT(Annual!AB$1,2),Segment!$A$3:$AR$3,0))+INDEX(Segment!$A:$AR,MATCH(Annual!$A42,Segment!$A:$A,0),MATCH("2H"&RIGHT(Annual!AB$1,2),Segment!$A$3:$AR$3,0)) -> 1993.7073 | AE42: 322.28374 | AF42: =IF(ISBLANK(AE42),"",INDEX($A42:$AB42,1,MATCH(AE$3,$A$3:$AB$3,0))-AE42) -> #N/A | AG42: 381.09735 | AH42: =IF(ISBLANK(AG42),"",INDEX($A42:$AB42,1,MATCH(AG$3,$A$3:$AB$3,0))-AG42) -> -4.131766
AF43: =IF(ISBLANK(AE43),"",INDEX($A43:$AB43,1,MATCH(AE$3,$A$3:$AB$3,0))-AE43) | AH43: =IF(ISBLANK(AG43),"",INDEX($A43:$AB43,1,MATCH(AG$3,$A$3:$AB$3,0))-AG43)
A44: Opex-R&D- total | B44: R&D- total | C44: AUDm | D44: AR | E44: -33.5 | F44: -35.6 | G44: -37.9 | H44: -41 | I44: -46 | J44: -49.9 | K44: -54 | L44: -60.1 | M44: -68.1 | N44: -77 | O44: -92.2 | P44: -112 | Q44: -128 | R44: =-69.3-84.4 -> -153.7 | S44: =INDEX(Segment!$A:$AR,MATCH(Annual!$A44,Segment!$A:$A,0),MATCH("1H"&RIGHT(Annual!S$1,2),Segment!$A$3:$AR$3,0))+INDEX(Segment!$A:$AR,MATCH(Annual!$A44,Segment!$A:$A,0),MATCH("2H"&RIGHT(Annual!S$1,2),Segment!$A$3:$AR$3,0)) -> -174.97971 | T44: =INDEX(Segment!$A:$AR,MATCH(Annual!$A44,Segment!$A:$A,0),MATCH("1H"&RIGHT(Annual!T$1,2),Segment!$A$3:$AR$3,0))+INDEX(Segment!$A:$AR,MATCH(Annual!$A44,Segment!$A:$A,0),MATCH("2H"&RIGHT(Annual!T$1,2),Segment!$A$3:$AR$3,0)) -> -201.15245 | U44: =INDEX(Segment!$A:$AR,MATCH(Annual!$A44,Segment!$A:$A,0),MATCH("1H"&RIGHT(Annual!U$1,2),Segment!$A$3:$AR$3,0))+INDEX(Segment!$A:$AR,MATCH(Annual!$A44,Segment!$A:$A,0),MATCH("2H"&RIGHT(Annual!U$1,2),Segment!$A$3:$AR$3,0)) -> -236.17718 | V44: =INDEX(Segment!$A:$AR,MATCH(Annual!$A44,Segment!$A:$A,0),MATCH("1H"&RIGHT(Annual!V$1,2),Segment!$A$3:$AR$3,0))+INDEX(Segment!$A:$AR,MATCH(Annual!$A44,Segment!$A:$A,0),MATCH("2H"&RIGHT(Annual!V$1,2),Segment!$A$3:$AR$3,0)) -> -280.30215 | W44: =INDEX(Segment!$A:$AR,MATCH(Annual!$A44,Segment!$A:$A,0),MATCH("1H"&RIGHT(Annual!W$1,2),Segment!$A$3:$AR$3,0))+INDEX(Segment!$A:$AR,MATCH(Annual!$A44,Segment!$A:$A,0),MATCH("2H"&RIGHT(Annual!W$1,2),Segment!$A$3:$AR$3,0)) -> -333.59963 | X44: =INDEX(Segment!$A:$AR,MATCH(Annual!$A44,Segment!$A:$A,0),MATCH("1H"&RIGHT(Annual!X$1,2),Segment!$A$3:$AR$3,0))+INDEX(Segment!$A:$AR,MATCH(Annual!$A44,Segment!$A:$A,0),MATCH("2H"&RIGHT(Annual!X$1,2),Segment!$A$3:$AR$3,0)) -> -398.70251 | Y44: =INDEX(Segment!$A:$AR,MATCH(Annual!$A44,Segment!$A:$A,0),MATCH("1H"&RIGHT(Annual!Y$1,2),Segment!$A$3:$AR$3,0))+INDEX(Segment!$A:$AR,MATCH(Annual!$A44,Segment!$A:$A,0),MATCH("2H"&RIGHT(Annual!Y$1,2),Segment!$A$3:$AR$3,0)) -> -478.26017 | Z44: =INDEX(Segment!$A:$AR,MATCH(Annual!$A44,Segment!$A:$A,0),MATCH("1H"&RIGHT(Annual!Z$1,2),Segment!$A$3:$AR$3,0))+INDEX(Segment!$A:$AR,MATCH(Annual!$A44,Segment!$A:$A,0),MATCH("2H"&RIGHT(Annual!Z$1,2),Segment!$A$3:$AR$3,0)) -> -575.54659 | ... AB44: =INDEX(Segment!$A:$AR,MATCH(Annual!$A44,Segment!$A:$A,0),MATCH("1H"&RIGHT(Annual!AB$1,2),Segment!$A$3:$AR$3,0))+INDEX(Segment!$A:$AR,MATCH(Annual!$A44,Segment!$A:$A,0),MATCH("2H"&RIGHT(Annual!AB$1,2),Segment!$A$3:$AR$3,0)) -> -840.48871 | AE44: -147.72032 | AF44: =IF(ISBLANK(AE44),"",INDEX($A44:$AB44,1,MATCH(AE$3,$A$3:$AB$3,0))-AE44) -> #N/A | AG44: -171.45846 | AH44: =IF(ISBLANK(AG44),"",INDEX($A44:$AB44,1,MATCH(AG$3,$A$3:$AB$3,0))-AG44) -> -3.5212559
A45: Opex-R&D- capitalisation | B45: R&D- capitalisation | C45: AUDm | D45: AR | K45: 26 | L45: 32.1 | M45: 37.1 | N45: 41.9 | O45: 50.1 | P45: 60.6 | Q45: 69.7 | R45: 84.4 | S45: =INDEX(Segment!$A:$AR,MATCH(Annual!$A45,Segment!$A:$A,0),MATCH("1H"&RIGHT(Annual!S$1,2),Segment!$A$3:$AR$3,0))+INDEX(Segment!$A:$AR,MATCH(Annual!$A45,Segment!$A:$A,0),MATCH("2H"&RIGHT(Annual!S$1,2),Segment!$A$3:$AR$3,0)) -> 96.080761 | T45: =INDEX(Segment!$A:$AR,MATCH(Annual!$A45,Segment!$A:$A,0),MATCH("1H"&RIGHT(Annual!T$1,2),Segment!$A$3:$AR$3,0))+INDEX(Segment!$A:$AR,MATCH(Annual!$A45,Segment!$A:$A,0),MATCH("2H"&RIGHT(Annual!T$1,2),Segment!$A$3:$AR$3,0)) -> 110.46164 | U45: =INDEX(Segment!$A:$AR,MATCH(Annual!$A45,Segment!$A:$A,0),MATCH("1H"&RIGHT(Annual!U$1,2),Segment!$A$3:$AR$3,0))+INDEX(Segment!$A:$AR,MATCH(Annual!$A45,Segment!$A:$A,0),MATCH("2H"&RIGHT(Annual!U$1,2),Segment!$A$3:$AR$3,0)) -> 129.7116 | V45: =INDEX(Segment!$A:$AR,MATCH(Annual!$A45,Segment!$A:$A,0),MATCH("1H"&RIGHT(Annual!V$1,2),Segment!$A$3:$AR$3,0))+INDEX(Segment!$A:$AR,MATCH(Annual!$A45,Segment!$A:$A,0),MATCH("2H"&RIGHT(Annual!V$1,2),Segment!$A$3:$AR$3,0)) -> 153.93926 | W45: =INDEX(Segment!$A:$AR,MATCH(Annual!$A45,Segment!$A:$A,0),MATCH("1H"&RIGHT(Annual!W$1,2),Segment!$A$3:$AR$3,0))+INDEX(Segment!$A:$AR,MATCH(Annual!$A45,Segment!$A:$A,0),MATCH("2H"&RIGHT(Annual!W$1,2),Segment!$A$3:$AR$3,0)) -> 183.20906 | X45: =INDEX(Segment!$A:$AR,MATCH(Annual!$A45,Segment!$A:$A,0),MATCH("1H"&RIGHT(Annual!X$1,2),Segment!$A$3:$AR$3,0))+INDEX(Segment!$A:$AR,MATCH(Annual!$A45,Segment!$A:$A,0),MATCH("2H"&RIGHT(Annual!X$1,2),Segment!$A$3:$AR$3,0)) -> 218.96207 | Y45: =INDEX(Segment!$A:$AR,MATCH(Annual!$A45,Segment!$A:$A,0),MATCH("1H"&RIGHT(Annual!Y$1,2),Segment!$A$3:$AR$3,0))+INDEX(Segment!$A:$AR,MATCH(Annual!$A45,Segment!$A:$A,0),MATCH("2H"&RIGHT(Annual!Y$1,2),Segment!$A$3:$AR$3,0)) -> 262.65321 | Z45: =INDEX(Segment!$A:$AR,MATCH(Annual!$A45,Segment!$A:$A,0),MATCH("1H"&RIGHT(Annual!Z$1,2),Segment!$A$3:$AR$3,0))+INDEX(Segment!$A:$AR,MATCH(Annual!$A45,Segment!$A:$A,0),MATCH("2H"&RIGHT(Annual!Z$1,2),Segment!$A$3:$AR$3,0)) -> 316.08044 | ... AB45: =INDEX(Segment!$A:$AR,MATCH(Annual!$A45,Segment!$A:$A,0),MATCH("1H"&RIGHT(Annual!AB$1,2),Segment!$A$3:$AR$3,0))+INDEX(Segment!$A:$AR,MATCH(Annual!$A45,Segment!$A:$A,0),MATCH("2H"&RIGHT(Annual!AB$1,2),Segment!$A$3:$AR$3,0)) -> 461.57925 | AE45: 82.412546 | AF45: =IF(ISBLANK(AE45),"",INDEX($A45:$AB45,1,MATCH(AE$3,$A$3:$AB$3,0))-AE45) -> #N/A | AG45: 95.657922 | AH45: =IF(ISBLANK(AG45),"",INDEX($A45:$AB45,1,MATCH(AG$3,$A$3:$AB$3,0))-AG45) -> 0.4228392
B46: R&D- net | J46: -49.9 | K46: -28.1 | L46: -28 | M46: -31 | N46: -35.1 | O46: -42.1 | P46: -51.4 | Q46: =SUM(Q44:Q45) -> -58.3 | R46: =SUM(R44:R45) -> -69.3 | S46: =SUM(S44:S45) -> -78.898953 | T46: =SUM(T44:T45) -> -90.690808 | U46: =SUM(U44:U45) -> -106.46558 | V46: =SUM(V44:V45) -> -126.36289 | W46: =SUM(W44:W45) -> -150.39057 | X46: =SUM(X44:X45) -> -179.74045 | ... AB46: =SUM(AB44:AB45) -> -378.90946 | AE46: -65.307771 | AF46: =IF(ISBLANK(AE46),"",INDEX($A46:$AB46,1,MATCH(AE$3,$A$3:$AB$3,0))-AE46) -> #N/A | AG46: -75.800536 | AH46: =IF(ISBLANK(AG46),"",INDEX($A46:$AB46,1,MATCH(AG$3,$A$3:$AB$3,0))-AG46) -> -3.0984167
B47: R&D % of sales | J47: 0.182 | K47: 0.213 | L47: 0.21 | M47: 0.228 | N47: 0.247 | O47: 0.25 | P47: 0.256 | Q47: =-Q44/Q$27 -> 0.2483508 | R47: =-R44/R$27 -> 0.25195565 | S47: =-S44/S$27 -> 0.25191291 | T47: =-T44/T$27 -> 0.25199355 | U47: =-U44/U$27 -> 0.25211152 | V47: =-V44/V$27 -> 0.25207287 | W47: =-W44/W$27 -> 0.25206944 | X47: =-X44/X$27 -> 0.25206627 | ... AB47: =-AB44/AB$27 -> 0.25205436 | AE47: 0.24416131 | AF47: =IF(ISBLANK(AE47),"",INDEX($A47:$AB47,1,MATCH(AE$3,$A$3:$AB$3,0))-AE47) -> #N/A | AG47: 0.24416638 | AH47: =IF(ISBLANK(AG47),"",INDEX($A47:$AB47,1,MATCH(AG$3,$A$3:$AB$3,0))-AG47) -> 0.0077465263
B48: R&D capitalisation % | C48: % | J48: 0 | K48: 0.48 | L48: 0.53 | M48: 0.54 | N48: 0.54 | O48: 0.54 | P48: 0.54 | Q48: =-Q45/Q44 -> 0.54453125 | R48: =-R45/R44 -> 0.54912167 | S48: =-S45/S44 -> 0.54909657 | T48: =-T45/T44 -> 0.54914391 | U48: =-U45/U44 -> 0.54921311 | V48: =-V45/V44 -> 0.54919044 | W48: =-W45/W44 -> 0.54918844 | X48: =-X45/X44 -> 0.54918657 | ... AB48: =-AB45/AB44 -> 0.54917959 | AE48: 0.55789581 | AF48: =IF(ISBLANK(AE48),"",INDEX($A48:$AB48,1,MATCH(AE$3,$A$3:$AB$3,0))-AE48) -> #N/A | AG48: 0.55790728 | AH48: =IF(ISBLANK(AG48),"",INDEX($A48:$AB48,1,MATCH(AG$3,$A$3:$AB$3,0))-AG48) -> -0.0088107075
AF49: =IF(ISBLANK(AE49),"",INDEX($A49:$AB49,1,MATCH(AE$3,$A$3:$AB$3,0))-AE49) | AH49: =IF(ISBLANK(AG49),"",INDEX($A49:$AB49,1,MATCH(AG$3,$A$3:$AB$3,0))-AG49)
A50: EBITDA-EBITDA | B50: EBITDA | C50: AUDm | D50: Preso | H50: 49.2 | I50: 56.4 | J50: 61.6 | K50: 55.6 | L50: 81.9 | M50: 102.3 | N50: 124.9 | O50: 151.9 | P50: 181.3 | Q50: 215.8 | R50: 255.7 | S50: =INDEX(Segment!$A:$AR,MATCH(Annual!$A50,Segment!$A:$A,0),MATCH("1H"&RIGHT(Annual!S$1,2),Segment!$A$3:$AR$3,0))+INDEX(Segment!$A:$AR,MATCH(Annual!$A50,Segment!$A:$A,0),MATCH("2H"&RIGHT(Annual!S$1,2),Segment!$A$3:$AR$3,0)) -> 298.06663 | T50: =INDEX(Segment!$A:$AR,MATCH(Annual!$A50,Segment!$A:$A,0),MATCH("1H"&RIGHT(Annual!T$1,2),Segment!$A$3:$AR$3,0))+INDEX(Segment!$A:$AR,MATCH(Annual!$A50,Segment!$A:$A,0),MATCH("2H"&RIGHT(Annual!T$1,2),Segment!$A$3:$AR$3,0)) -> 350.58886 | U50: =INDEX(Segment!$A:$AR,MATCH(Annual!$A50,Segment!$A:$A,0),MATCH("1H"&RIGHT(Annual!U$1,2),Segment!$A$3:$AR$3,0))+INDEX(Segment!$A:$AR,MATCH(Annual!$A50,Segment!$A:$A,0),MATCH("2H"&RIGHT(Annual!U$1,2),Segment!$A$3:$AR$3,0)) -> 420.92194 | V50: =INDEX(Segment!$A:$AR,MATCH(Annual!$A50,Segment!$A:$A,0),MATCH("1H"&RIGHT(Annual!V$1,2),Segment!$A$3:$AR$3,0))+INDEX(Segment!$A:$AR,MATCH(Annual!$A50,Segment!$A:$A,0),MATCH("2H"&RIGHT(Annual!V$1,2),Segment!$A$3:$AR$3,0)) -> 505.15533 | W50: =INDEX(Segment!$A:$AR,MATCH(Annual!$A50,Segment!$A:$A,0),MATCH("1H"&RIGHT(Annual!W$1,2),Segment!$A$3:$AR$3,0))+INDEX(Segment!$A:$AR,MATCH(Annual!$A50,Segment!$A:$A,0),MATCH("2H"&RIGHT(Annual!W$1,2),Segment!$A$3:$AR$3,0)) -> 607.82779 | X50: =INDEX(Segment!$A:$AR,MATCH(Annual!$A50,Segment!$A:$A,0),MATCH("1H"&RIGHT(Annual!X$1,2),Segment!$A$3:$AR$3,0))+INDEX(Segment!$A:$AR,MATCH(Annual!$A50,Segment!$A:$A,0),MATCH("2H"&RIGHT(Annual!X$1,2),Segment!$A$3:$AR$3,0)) -> 734.35976 | Y50: =INDEX(Segment!$A:$AR,MATCH(Annual!$A50,Segment!$A:$A,0),MATCH("1H"&RIGHT(Annual!Y$1,2),Segment!$A$3:$AR$3,0))+INDEX(Segment!$A:$AR,MATCH(Annual!$A50,Segment!$A:$A,0),MATCH("2H"&RIGHT(Annual!Y$1,2),Segment!$A$3:$AR$3,0)) -> 890.38654 | Z50: =INDEX(Segment!$A:$AR,MATCH(Annual!$A50,Segment!$A:$A,0),MATCH("1H"&RIGHT(Annual!Z$1,2),Segment!$A$3:$AR$3,0))+INDEX(Segment!$A:$AR,MATCH(Annual!$A50,Segment!$A:$A,0),MATCH("2H"&RIGHT(Annual!Z$1,2),Segment!$A$3:$AR$3,0)) -> 1082.9291 | ... AB50: =INDEX(Segment!$A:$AR,MATCH(Annual!$A50,Segment!$A:$A,0),MATCH("1H"&RIGHT(Annual!AB$1,2),Segment!$A$3:$AR$3,0))+INDEX(Segment!$A:$AR,MATCH(Annual!$A50,Segment!$A:$A,0),MATCH("2H"&RIGHT(Annual!AB$1,2),Segment!$A$3:$AR$3,0)) -> 1614.7978 | AE50: 256.97597 | AF50: =IF(ISBLANK(AE50),"",INDEX($A50:$AB50,1,MATCH(AE$3,$A$3:$AB$3,0))-AE50) -> #N/A | AG50: 305.29681 | AH50: =IF(ISBLANK(AG50),"",INDEX($A50:$AB50,1,MATCH(AG$3,$A$3:$AB$3,0))-AG50) -> -7.2301826
B51: Growth | C51: % YoY | H51: #DIV/0! | I51: 0.15 | J51: 0.09 | K51: -0.1 | L51: 0.47 | M51: 0.25 | N51: 0.22 | O51: 0.22 | P51: 0.19 | Q51: =Q50/P50-1 -> 0.19029233 | R51: =R50/Q50-1 -> 0.18489342 | S51: =S50/R50-1 -> 0.16568882 | T51: =T50/S50-1 -> 0.17620969 | U51: =U50/T50-1 -> 0.20061412 | V51: =V50/U50-1 -> 0.20011643 | W51: =W50/V50-1 -> 0.20324929 | X51: =X50/W50-1 -> 0.20817075 | ... AB51: =AB50/AA50-1 -> 0.22263788 | AE51: 0.19080616 | AF51: =IF(ISBLANK(AE51),"",INDEX($A51:$AB51,1,MATCH(AE$3,$A$3:$AB$3,0))-AE51) -> #N/A | AG51: 0.18803643 | AH51: =IF(ISBLANK(AG51),"",INDEX($A51:$AB51,1,MATCH(AG$3,$A$3:$AB$3,0))-AG51) -> -0.022347613
B52: Margin | C52: % | H52: 0.225 | I52: 0.226 | J52: 0.225 | K52: 0.219 | L52: 0.287 | M52: 0.342 | N52: 0.401 | O52: 0.412 | P52: 0.415 | Q52: =Q50/Q$27 -> 0.41870392 | R52: =R50/R$27 -> 0.41916109 | S52: =S50/S$27 -> 0.42911735 | T52: =T50/T$27 -> 0.43919987 | U52: =U50/U$27 -> 0.44932059 | V52: =V50/V$27 -> 0.45428103 | W52: =W50/W$27 -> 0.45927753 | X52: =X50/X$27 -> 0.46427428 | ... AB52: =AB50/AB$27 -> 0.4842621 | AE52: 0.42474584 | AF52: =IF(ISBLANK(AE52),"",INDEX($A52:$AB52,1,MATCH(AE$3,$A$3:$AB$3,0))-AE52) -> #N/A | AG52: 0.43475964 | AH52: =IF(ISBLANK(AG52),"",INDEX($A52:$AB52,1,MATCH(AG$3,$A$3:$AB$3,0))-AG52) -> -0.0056422911
AF53: =IF(ISBLANK(AE53),"",INDEX($A53:$AB53,1,MATCH(AE$3,$A$3:$AB$3,0))-AE53) | AH53: =IF(ISBLANK(AG53),"",INDEX($A53:$AB53,1,MATCH(AG$3,$A$3:$AB$3,0))-AG53)
B54: D&A | AF54: =IF(ISBLANK(AE54),"",INDEX($A54:$AB54,1,MATCH(AE$3,$A$3:$AB$3,0))-AE54) | AH54: =IF(ISBLANK(AG54),"",INDEX($A54:$AB54,1,MATCH(AG$3,$A$3:$AB$3,0))-AG54)
A55: D&A-Depreciation | B55: Depreciation | D55: AR | I55: 1.12 | K55: -3.9 | L55: -3.7 | M55: -3.9 | N55: -3.3 | O55: -2.6 | P55: -3 | Q55: -4.2 | R55: -4.696 | S55: =INDEX(Segment!$A:$AR,MATCH(Annual!$A55,Segment!$A:$A,0),MATCH("1H"&RIGHT(Annual!S$1,2),Segment!$A$3:$AR$3,0))+INDEX(Segment!$A:$AR,MATCH(Annual!$A55,Segment!$A:$A,0),MATCH("2H"&RIGHT(Annual!S$1,2),Segment!$A$3:$AR$3,0)) -> -5.3474387 | T55: =INDEX(Segment!$A:$AR,MATCH(Annual!$A55,Segment!$A:$A,0),MATCH("1H"&RIGHT(Annual!T$1,2),Segment!$A$3:$AR$3,0))+INDEX(Segment!$A:$AR,MATCH(Annual!$A55,Segment!$A:$A,0),MATCH("2H"&RIGHT(Annual!T$1,2),Segment!$A$3:$AR$3,0)) -> -6.1445126 | U55: =INDEX(Segment!$A:$AR,MATCH(Annual!$A55,Segment!$A:$A,0),MATCH("1H"&RIGHT(Annual!U$1,2),Segment!$A$3:$AR$3,0))+INDEX(Segment!$A:$AR,MATCH(Annual!$A55,Segment!$A:$A,0),MATCH("2H"&RIGHT(Annual!U$1,2),Segment!$A$3:$AR$3,0)) -> -7.2096363 | V55: =INDEX(Segment!$A:$AR,MATCH(Annual!$A55,Segment!$A:$A,0),MATCH("1H"&RIGHT(Annual!V$1,2),Segment!$A$3:$AR$3,0))+INDEX(Segment!$A:$AR,MATCH(Annual!$A55,Segment!$A:$A,0),MATCH("2H"&RIGHT(Annual!V$1,2),Segment!$A$3:$AR$3,0)) -> -8.5584632 | W55: =INDEX(Segment!$A:$AR,MATCH(Annual!$A55,Segment!$A:$A,0),MATCH("1H"&RIGHT(Annual!W$1,2),Segment!$A$3:$AR$3,0))+INDEX(Segment!$A:$AR,MATCH(Annual!$A55,Segment!$A:$A,0),MATCH("2H"&RIGHT(Annual!W$1,2),Segment!$A$3:$AR$3,0)) -> -10.185989 | X55: =INDEX(Segment!$A:$AR,MATCH(Annual!$A55,Segment!$A:$A,0),MATCH("1H"&RIGHT(Annual!X$1,2),Segment!$A$3:$AR$3,0))+INDEX(Segment!$A:$AR,MATCH(Annual!$A55,Segment!$A:$A,0),MATCH("2H"&RIGHT(Annual!X$1,2),Segment!$A$3:$AR$3,0)) -> -12.17403 | Y55: =INDEX(Segment!$A:$AR,MATCH(Annual!$A55,Segment!$A:$A,0),MATCH("1H"&RIGHT(Annual!Y$1,2),Segment!$A$3:$AR$3,0))+INDEX(Segment!$A:$AR,MATCH(Annual!$A55,Segment!$A:$A,0),MATCH("2H"&RIGHT(Annual!Y$1,2),Segment!$A$3:$AR$3,0)) -> -14.6035 | Z55: =INDEX(Segment!$A:$AR,MATCH(Annual!$A55,Segment!$A:$A,0),MATCH("1H"&RIGHT(Annual!Z$1,2),Segment!$A$3:$AR$3,0))+INDEX(Segment!$A:$AR,MATCH(Annual!$A55,Segment!$A:$A,0),MATCH("2H"&RIGHT(Annual!Z$1,2),Segment!$A$3:$AR$3,0)) -> -17.574396 | ... AB55: =INDEX(Segment!$A:$AR,MATCH(Annual!$A55,Segment!$A:$A,0),MATCH("1H"&RIGHT(Annual!AB$1,2),Segment!$A$3:$AR$3,0))+INDEX(Segment!$A:$AR,MATCH(Annual!$A55,Segment!$A:$A,0),MATCH("2H"&RIGHT(Annual!AB$1,2),Segment!$A$3:$AR$3,0)) -> -25.665291 | AE55: -4.9654439 | AF55: =IF(ISBLANK(AE55),"",INDEX($A55:$AB55,1,MATCH(AE$3,$A$3:$AB$3,0))-AE55) -> #N/A | AG55: -5.7633928 | AH55: =IF(ISBLANK(AG55),"",INDEX($A55:$AB55,1,MATCH(AG$3,$A$3:$AB$3,0))-AG55) -> 0.41595416
A56: D&A-R&D amortisation | B56: R&D amortisation | D56: AR | L56: -0.6 | M56: -6.1 | N56: -13.4 | O56: -23.4 | P56: -34.1 | Q56: -45.3 | R56: -53.143 | S56: =INDEX(Segment!$A:$AR,MATCH(Annual!$A56,Segment!$A:$A,0),MATCH("1H"&RIGHT(Annual!S$1,2),Segment!$A$3:$AR$3,0))+INDEX(Segment!$A:$AR,MATCH(Annual!$A56,Segment!$A:$A,0),MATCH("2H"&RIGHT(Annual!S$1,2),Segment!$A$3:$AR$3,0)) -> -60.835419 | T56: =INDEX(Segment!$A:$AR,MATCH(Annual!$A56,Segment!$A:$A,0),MATCH("1H"&RIGHT(Annual!T$1,2),Segment!$A$3:$AR$3,0))+INDEX(Segment!$A:$AR,MATCH(Annual!$A56,Segment!$A:$A,0),MATCH("2H"&RIGHT(Annual!T$1,2),Segment!$A$3:$AR$3,0)) -> -68.137056 | U56: =INDEX(Segment!$A:$AR,MATCH(Annual!$A56,Segment!$A:$A,0),MATCH("1H"&RIGHT(Annual!U$1,2),Segment!$A$3:$AR$3,0))+INDEX(Segment!$A:$AR,MATCH(Annual!$A56,Segment!$A:$A,0),MATCH("2H"&RIGHT(Annual!U$1,2),Segment!$A$3:$AR$3,0)) -> -76.972516 | V56: =INDEX(Segment!$A:$AR,MATCH(Annual!$A56,Segment!$A:$A,0),MATCH("1H"&RIGHT(Annual!V$1,2),Segment!$A$3:$AR$3,0))+INDEX(Segment!$A:$AR,MATCH(Annual!$A56,Segment!$A:$A,0),MATCH("2H"&RIGHT(Annual!V$1,2),Segment!$A$3:$AR$3,0)) -> -88.065022 | W56: =INDEX(Segment!$A:$AR,MATCH(Annual!$A56,Segment!$A:$A,0),MATCH("1H"&RIGHT(Annual!W$1,2),Segment!$A$3:$AR$3,0))+INDEX(Segment!$A:$AR,MATCH(Annual!$A56,Segment!$A:$A,0),MATCH("2H"&RIGHT(Annual!W$1,2),Segment!$A$3:$AR$3,0)) -> -101.85858 | X56: =INDEX(Segment!$A:$AR,MATCH(Annual!$A56,Segment!$A:$A,0),MATCH("1H"&RIGHT(Annual!X$1,2),Segment!$A$3:$AR$3,0))+INDEX(Segment!$A:$AR,MATCH(Annual!$A56,Segment!$A:$A,0),MATCH("2H"&RIGHT(Annual!X$1,2),Segment!$A$3:$AR$3,0)) -> -118.87575 | Y56: =INDEX(Segment!$A:$AR,MATCH(Annual!$A56,Segment!$A:$A,0),MATCH("1H"&RIGHT(Annual!Y$1,2),Segment!$A$3:$AR$3,0))+INDEX(Segment!$A:$AR,MATCH(Annual!$A56,Segment!$A:$A,0),MATCH("2H"&RIGHT(Annual!Y$1,2),Segment!$A$3:$AR$3,0)) -> -139.7995 | Z56: =INDEX(Segment!$A:$AR,MATCH(Annual!$A56,Segment!$A:$A,0),MATCH("1H"&RIGHT(Annual!Z$1,2),Segment!$A$3:$AR$3,0))+INDEX(Segment!$A:$AR,MATCH(Annual!$A56,Segment!$A:$A,0),MATCH("2H"&RIGHT(Annual!Z$1,2),Segment!$A$3:$AR$3,0)) -> -165.47449 | ... AB56: =INDEX(Segment!$A:$AR,MATCH(Annual!$A56,Segment!$A:$A,0),MATCH("1H"&RIGHT(Annual!AB$1,2),Segment!$A$3:$AR$3,0))+INDEX(Segment!$A:$AR,MATCH(Annual!$A56,Segment!$A:$A,0),MATCH("2H"&RIGHT(Annual!AB$1,2),Segment!$A$3:$AR$3,0)) -> -235.50409 | AE56: -51.78 | AF56: =IF(ISBLANK(AE56),"",INDEX($A56:$AB56,1,MATCH(AE$3,$A$3:$AB$3,0))-AE56) -> #N/A | AG56: -58.193331 | AH56: =IF(ISBLANK(AG56),"",INDEX($A56:$AB56,1,MATCH(AG$3,$A$3:$AB$3,0))-AG56) -> -2.6420885
A57: D&A-Other amortisation | B57: Other amortisation | K57: -1.2 | L57: -1.9 | M57: -8.6 | N57: -9.1 | O57: -12.1 | P57: -16.5 | Q57: =Q58-Q56-Q55 -> -19.3 | R57: =R58-R56-R55 -> -22.958 | S57: =INDEX(Segment!$A:$AR,MATCH(Annual!$A57,Segment!$A:$A,0),MATCH("1H"&RIGHT(Annual!S$1,2),Segment!$A$3:$AR$3,0))+INDEX(Segment!$A:$AR,MATCH(Annual!$A57,Segment!$A:$A,0),MATCH("2H"&RIGHT(Annual!S$1,2),Segment!$A$3:$AR$3,0)) -> -26.14314 | T57: =INDEX(Segment!$A:$AR,MATCH(Annual!$A57,Segment!$A:$A,0),MATCH("1H"&RIGHT(Annual!T$1,2),Segment!$A$3:$AR$3,0))+INDEX(Segment!$A:$AR,MATCH(Annual!$A57,Segment!$A:$A,0),MATCH("2H"&RIGHT(Annual!T$1,2),Segment!$A$3:$AR$3,0)) -> -30.039182 | U57: =INDEX(Segment!$A:$AR,MATCH(Annual!$A57,Segment!$A:$A,0),MATCH("1H"&RIGHT(Annual!U$1,2),Segment!$A$3:$AR$3,0))+INDEX(Segment!$A:$AR,MATCH(Annual!$A57,Segment!$A:$A,0),MATCH("2H"&RIGHT(Annual!U$1,2),Segment!$A$3:$AR$3,0)) -> -35.245 | V57: =INDEX(Segment!$A:$AR,MATCH(Annual!$A57,Segment!$A:$A,0),MATCH("1H"&RIGHT(Annual!V$1,2),Segment!$A$3:$AR$3,0))+INDEX(Segment!$A:$AR,MATCH(Annual!$A57,Segment!$A:$A,0),MATCH("2H"&RIGHT(Annual!V$1,2),Segment!$A$3:$AR$3,0)) -> -41.839391 | W57: =INDEX(Segment!$A:$AR,MATCH(Annual!$A57,Segment!$A:$A,0),MATCH("1H"&RIGHT(Annual!W$1,2),Segment!$A$3:$AR$3,0))+INDEX(Segment!$A:$AR,MATCH(Annual!$A57,Segment!$A:$A,0),MATCH("2H"&RIGHT(Annual!W$1,2),Segment!$A$3:$AR$3,0)) -> -49.795864 | X57: =INDEX(Segment!$A:$AR,MATCH(Annual!$A57,Segment!$A:$A,0),MATCH("1H"&RIGHT(Annual!X$1,2),Segment!$A$3:$AR$3,0))+INDEX(Segment!$A:$AR,MATCH(Annual!$A57,Segment!$A:$A,0),MATCH("2H"&RIGHT(Annual!X$1,2),Segment!$A$3:$AR$3,0)) -> -59.514783 | Y57: =INDEX(Segment!$A:$AR,MATCH(Annual!$A57,Segment!$A:$A,0),MATCH("1H"&RIGHT(Annual!Y$1,2),Segment!$A$3:$AR$3,0))+INDEX(Segment!$A:$AR,MATCH(Annual!$A57,Segment!$A:$A,0),MATCH("2H"&RIGHT(Annual!Y$1,2),Segment!$A$3:$AR$3,0)) -> -71.391726 | Z57: =INDEX(Segment!$A:$AR,MATCH(Annual!$A57,Segment!$A:$A,0),MATCH("1H"&RIGHT(Annual!Z$1,2),Segment!$A$3:$AR$3,0))+INDEX(Segment!$A:$AR,MATCH(Annual!$A57,Segment!$A:$A,0),MATCH("2H"&RIGHT(Annual!Z$1,2),Segment!$A$3:$AR$3,0)) -> -85.915545 | ... AB57: =INDEX(Segment!$A:$AR,MATCH(Annual!$A57,Segment!$A:$A,0),MATCH("1H"&RIGHT(Annual!AB$1,2),Segment!$A$3:$AR$3,0))+INDEX(Segment!$A:$AR,MATCH(Annual!$A57,Segment!$A:$A,0),MATCH("2H"&RIGHT(Annual!AB$1,2),Segment!$A$3:$AR$3,0)) -> -125.46955 | AE57: -23.004775 | AF57: =IF(ISBLANK(AE57),"",INDEX($A57:$AB57,1,MATCH(AE$3,$A$3:$AB$3,0))-AE57) -> #N/A | AG57: -26.700665 | AH57: =IF(ISBLANK(AG57),"",INDEX($A57:$AB57,1,MATCH(AG$3,$A$3:$AB$3,0))-AG57) -> 0.55752537
A58: D&A-D&A | B58: D&A | C58: AUDm | D58: AR | K58: -5.1 | L58: -6.1 | M58: -18.6 | N58: -25.8 | O58: -38.1 | P58: -53.5 | Q58: -68.8 | R58: -80.797 | S58: =INDEX(Segment!$A:$AR,MATCH(Annual!$A58,Segment!$A:$A,0),MATCH("1H"&RIGHT(Annual!S$1,2),Segment!$A$3:$AR$3,0))+INDEX(Segment!$A:$AR,MATCH(Annual!$A58,Segment!$A:$A,0),MATCH("2H"&RIGHT(Annual!S$1,2),Segment!$A$3:$AR$3,0)) -> -92.325998 | T58: =INDEX(Segment!$A:$AR,MATCH(Annual!$A58,Segment!$A:$A,0),MATCH("1H"&RIGHT(Annual!T$1,2),Segment!$A$3:$AR$3,0))+INDEX(Segment!$A:$AR,MATCH(Annual!$A58,Segment!$A:$A,0),MATCH("2H"&RIGHT(Annual!T$1,2),Segment!$A$3:$AR$3,0)) -> -104.32075 | U58: =INDEX(Segment!$A:$AR,MATCH(Annual!$A58,Segment!$A:$A,0),MATCH("1H"&RIGHT(Annual!U$1,2),Segment!$A$3:$AR$3,0))+INDEX(Segment!$A:$AR,MATCH(Annual!$A58,Segment!$A:$A,0),MATCH("2H"&RIGHT(Annual!U$1,2),Segment!$A$3:$AR$3,0)) -> -119.42715 | V58: =INDEX(Segment!$A:$AR,MATCH(Annual!$A58,Segment!$A:$A,0),MATCH("1H"&RIGHT(Annual!V$1,2),Segment!$A$3:$AR$3,0))+INDEX(Segment!$A:$AR,MATCH(Annual!$A58,Segment!$A:$A,0),MATCH("2H"&RIGHT(Annual!V$1,2),Segment!$A$3:$AR$3,0)) -> -138.46288 | W58: =INDEX(Segment!$A:$AR,MATCH(Annual!$A58,Segment!$A:$A,0),MATCH("1H"&RIGHT(Annual!W$1,2),Segment!$A$3:$AR$3,0))+INDEX(Segment!$A:$AR,MATCH(Annual!$A58,Segment!$A:$A,0),MATCH("2H"&RIGHT(Annual!W$1,2),Segment!$A$3:$AR$3,0)) -> -161.84044 | X58: =INDEX(Segment!$A:$AR,MATCH(Annual!$A58,Segment!$A:$A,0),MATCH("1H"&RIGHT(Annual!X$1,2),Segment!$A$3:$AR$3,0))+INDEX(Segment!$A:$AR,MATCH(Annual!$A58,Segment!$A:$A,0),MATCH("2H"&RIGHT(Annual!X$1,2),Segment!$A$3:$AR$3,0)) -> -190.56457 | Y58: =INDEX(Segment!$A:$AR,MATCH(Annual!$A58,Segment!$A:$A,0),MATCH("1H"&RIGHT(Annual!Y$1,2),Segment!$A$3:$AR$3,0))+INDEX(Segment!$A:$AR,MATCH(Annual!$A58,Segment!$A:$A,0),MATCH("2H"&RIGHT(Annual!Y$1,2),Segment!$A$3:$AR$3,0)) -> -225.79473 | Z58: =INDEX(Segment!$A:$AR,MATCH(Annual!$A58,Segment!$A:$A,0),MATCH("1H"&RIGHT(Annual!Z$1,2),Segment!$A$3:$AR$3,0))+INDEX(Segment!$A:$AR,MATCH(Annual!$A58,Segment!$A:$A,0),MATCH("2H"&RIGHT(Annual!Z$1,2),Segment!$A$3:$AR$3,0)) -> -268.96443 | ... AB58: =INDEX(Segment!$A:$AR,MATCH(Annual!$A58,Segment!$A:$A,0),MATCH("1H"&RIGHT(Annual!AB$1,2),Segment!$A$3:$AR$3,0))+INDEX(Segment!$A:$AR,MATCH(Annual!$A58,Segment!$A:$A,0),MATCH("2H"&RIGHT(Annual!AB$1,2),Segment!$A$3:$AR$3,0)) -> -386.63893 | AE58: -79.750219 | AF58: =IF(ISBLANK(AE58),"",INDEX($A58:$AB58,1,MATCH(AE$3,$A$3:$AB$3,0))-AE58) -> #N/A | AG58: -90.657389 | AH58: =IF(ISBLANK(AG58),"",INDEX($A58:$AB58,1,MATCH(AG$3,$A$3:$AB$3,0))-AG58) -> -1.668609
B59: D&A / Revenue | C59: % | K59: -0.02 | L59: -0.021 | M59: -0.062 | N59: -0.083 | O59: -0.103 | P59: -0.122 | Q59: =Q58/Q$27 -> -0.13348855 | R59: =R58/R$27 -> -0.13244802 | S59: =S58/S$27 -> -0.1329189 | T59: =T58/T$27 -> -0.13068772 | U59: =U58/U$27 -> -0.12748463 | V59: =V58/V$27 -> -0.12451825 | W59: =W58/W$27 -> -0.12228739 | X59: =X58/X$27 -> -0.12047804 | ... AB59: =AB58/AB$27 -> -0.11594924 | AE59: -0.13181611 | AF59: =IF(ISBLANK(AE59),"",INDEX($A59:$AB59,1,MATCH(AE$3,$A$3:$AB$3,0))-AE59) -> #N/A | AG59: -0.12910116 | AH59: =IF(ISBLANK(AG59),"",INDEX($A59:$AB59,1,MATCH(AG$3,$A$3:$AB$3,0))-AG59) -> -0.0038177326
AF60: =IF(ISBLANK(AE60),"",INDEX($A60:$AB60,1,MATCH(AE$3,$A$3:$AB$3,0))-AE60) | AH60: =IF(ISBLANK(AG60),"",INDEX($A60:$AB60,1,MATCH(AG$3,$A$3:$AB$3,0))-AG60)
B61: EBIT | AF61: =IF(ISBLANK(AE61),"",INDEX($A61:$AB61,1,MATCH(AE$3,$A$3:$AB$3,0))-AE61) | AH61: =IF(ISBLANK(AG61),"",INDEX($A61:$AB61,1,MATCH(AG$3,$A$3:$AB$3,0))-AG61)
A62: EBIT | B62: EBIT | C62: AUDm | H62: 49.2 | I62: 52.4 | J62: 57.3 | K62: 50.5 | L62: 75.8 | M62: 83.6 | N62: 99.1 | O62: 113.7 | P62: 127.8 | Q62: =Q50+Q58 -> 147 | R62: =R50+R58 -> 174.903 | S62: =INDEX(Segment!$A:$AR,MATCH(Annual!$A62,Segment!$A:$A,0),MATCH("1H"&RIGHT(Annual!S$1,2),Segment!$A$3:$AR$3,0))+INDEX(Segment!$A:$AR,MATCH(Annual!$A62,Segment!$A:$A,0),MATCH("2H"&RIGHT(Annual!S$1,2),Segment!$A$3:$AR$3,0)) -> 205.74063 | T62: =INDEX(Segment!$A:$AR,MATCH(Annual!$A62,Segment!$A:$A,0),MATCH("1H"&RIGHT(Annual!T$1,2),Segment!$A$3:$AR$3,0))+INDEX(Segment!$A:$AR,MATCH(Annual!$A62,Segment!$A:$A,0),MATCH("2H"&RIGHT(Annual!T$1,2),Segment!$A$3:$AR$3,0)) -> 246.26811 | U62: =INDEX(Segment!$A:$AR,MATCH(Annual!$A62,Segment!$A:$A,0),MATCH("1H"&RIGHT(Annual!U$1,2),Segment!$A$3:$AR$3,0))+INDEX(Segment!$A:$AR,MATCH(Annual!$A62,Segment!$A:$A,0),MATCH("2H"&RIGHT(Annual!U$1,2),Segment!$A$3:$AR$3,0)) -> 301.49478 | V62: =INDEX(Segment!$A:$AR,MATCH(Annual!$A62,Segment!$A:$A,0),MATCH("1H"&RIGHT(Annual!V$1,2),Segment!$A$3:$AR$3,0))+INDEX(Segment!$A:$AR,MATCH(Annual!$A62,Segment!$A:$A,0),MATCH("2H"&RIGHT(Annual!V$1,2),Segment!$A$3:$AR$3,0)) -> 366.69245 | W62: =INDEX(Segment!$A:$AR,MATCH(Annual!$A62,Segment!$A:$A,0),MATCH("1H"&RIGHT(Annual!W$1,2),Segment!$A$3:$AR$3,0))+INDEX(Segment!$A:$AR,MATCH(Annual!$A62,Segment!$A:$A,0),MATCH("2H"&RIGHT(Annual!W$1,2),Segment!$A$3:$AR$3,0)) -> 445.98736 | X62: =INDEX(Segment!$A:$AR,MATCH(Annual!$A62,Segment!$A:$A,0),MATCH("1H"&RIGHT(Annual!X$1,2),Segment!$A$3:$AR$3,0))+INDEX(Segment!$A:$AR,MATCH(Annual!$A62,Segment!$A:$A,0),MATCH("2H"&RIGHT(Annual!X$1,2),Segment!$A$3:$AR$3,0)) -> 543.79519 | Y62: =INDEX(Segment!$A:$AR,MATCH(Annual!$A62,Segment!$A:$A,0),MATCH("1H"&RIGHT(Annual!Y$1,2),Segment!$A$3:$AR$3,0))+INDEX(Segment!$A:$AR,MATCH(Annual!$A62,Segment!$A:$A,0),MATCH("2H"&RIGHT(Annual!Y$1,2),Segment!$A$3:$AR$3,0)) -> 664.59182 | Z62: =INDEX(Segment!$A:$AR,MATCH(Annual!$A62,Segment!$A:$A,0),MATCH("1H"&RIGHT(Annual!Z$1,2),Segment!$A$3:$AR$3,0))+INDEX(Segment!$A:$AR,MATCH(Annual!$A62,Segment!$A:$A,0),MATCH("2H"&RIGHT(Annual!Z$1,2),Segment!$A$3:$AR$3,0)) -> 813.9647 | ... AB62: =INDEX(Segment!$A:$AR,MATCH(Annual!$A62,Segment!$A:$A,0),MATCH("1H"&RIGHT(Annual!AB$1,2),Segment!$A$3:$AR$3,0))+INDEX(Segment!$A:$AR,MATCH(Annual!$A62,Segment!$A:$A,0),MATCH("2H"&RIGHT(Annual!AB$1,2),Segment!$A$3:$AR$3,0)) -> 1228.1589 | AE62: 177.22575 | AF62: =IF(ISBLANK(AE62),"",INDEX($A62:$AB62,1,MATCH(AE$3,$A$3:$AB$3,0))-AE62) -> #N/A | AG62: 214.63942 | AH62: =IF(ISBLANK(AG62),"",INDEX($A62:$AB62,1,MATCH(AG$3,$A$3:$AB$3,0))-AG62) -> -8.8987916
B63: Underlying EBIT Growth | C63: % YoY | I63: 0.07 | J63: 0.09 | K63: -0.12 | L63: 0.5 | M63: 0.1 | N63: 0.19 | O63: 0.15 | P63: 0.12 | Q63: =Q62/P62-1 -> 0.15023474 | R63: =R62/Q62-1 -> 0.18981633 | S63: =S62/R62-1 -> 0.17631277 | T63: =T62/S62-1 -> 0.19698334 | U63: =U62/T62-1 -> 0.22425426 | V63: =V62/U62-1 -> 0.21624809 | W63: =W62/V62-1 -> 0.21624361 | X63: =X62/W62-1 -> 0.2193063 | ... AB63: =AB62/AA62-1 -> 0.22950896 | AE63: 0.20561735 | AF63: =IF(ISBLANK(AE63),"",INDEX($A63:$AB63,1,MATCH(AE$3,$A$3:$AB$3,0))-AE63) -> #N/A | AG63: 0.21110744 | AH63: =IF(ISBLANK(AG63),"",INDEX($A63:$AB63,1,MATCH(AG$3,$A$3:$AB$3,0))-AG63) -> -0.034794668
B64: EBIT Margin | C64: % | H64: 0.225 | I64: 0.211 | J64: 0.21 | K64: 0.199 | L64: 0.265 | M64: 0.28 | N64: 0.318 | O64: 0.308 | P64: 0.292 | Q64: =Q62/Q$27 -> 0.28521537 | R64: =R62/R$27 -> 0.28671307 | S64: =S62/S$27 -> 0.29619846 | T64: =T62/T$27 -> 0.30851215 | U64: =U62/U$27 -> 0.32183596 | V64: =V62/V$27 -> 0.32976278 | W64: =W62/W$27 -> 0.33699014 | X64: =X62/X$27 -> 0.34379624 | ... AB64: =AB62/AB$27 -> 0.36831286 | AE64: 0.29292972 | AF64: =IF(ISBLANK(AE64),"",INDEX($A64:$AB64,1,MATCH(AE$3,$A$3:$AB$3,0))-AE64) -> #N/A | AG64: 0.30565848 | AH64: =IF(ISBLANK(AG64),"",INDEX($A64:$AB64,1,MATCH(AG$3,$A$3:$AB$3,0))-AG64) -> -0.0094600237
L65: 1.14 | AF65: =IF(ISBLANK(AE65),"",INDEX($A65:$AB65,1,MATCH(AE$3,$A$3:$AB$3,0))-AE65) | AH65: =IF(ISBLANK(AG65),"",INDEX($A65:$AB65,1,MATCH(AG$3,$A$3:$AB$3,0))-AG65)
B66: Interest | AF66: =IF(ISBLANK(AE66),"",INDEX($A66:$AB66,1,MATCH(AE$3,$A$3:$AB$3,0))-AE66) | AH66: =IF(ISBLANK(AG66),"",INDEX($A66:$AB66,1,MATCH(AG$3,$A$3:$AB$3,0))-AG66)
A67: Interest income | B67: Interest income | C67: AUDm | D67: AR | K67: 0.7 | L67: 0.6 | M67: 0.4 | N67: 0.2 | O67: 0.4 | P67: 4.1 | Q67: 8.4 | R67: 10.15 | S67: =R140*S70 -> 10.844506 | T67: =S140*T70 -> 11.779095 | U67: =T140*U70 -> 14.181529 | V67: =U140*V70 -> 16.854909 | W67: =V140*W70 -> 17.092204 | X67: =W140*X70 -> 17.351486 | Y67: =X140*Y70 -> 17.637414 | Z67: =Y140*Z70 -> 18.004718 | ... AB67: =AA140*AB70 -> 19.363597 | AE67: 9.327012 | AF67: =IF(ISBLANK(AE67),"",INDEX($A67:$AB67,1,MATCH(AE$3,$A$3:$AB$3,0))-AE67) -> #N/A | AG67: 10.671983 | AH67: =IF(ISBLANK(AG67),"",INDEX($A67:$AB67,1,MATCH(AG$3,$A$3:$AB$3,0))-AG67) -> 0.1725224
A68: Interest expense | B68: Interest expense | C68: AUDm | K68: -0.4 | L68: 0 | M68: -1.5 | N68: -1.5 | O68: -1.8 | P68: -2.1 | Q68: =Q69-Q67 -> -2.6 | R68: -3.511 | S68: =R68+S71*S212 -> -3.511 | T68: =S68+T71*T212 -> -3.511 | U68: =T68+U71*U212 -> -3.511 | V68: =U68+V71*V212 -> -3.511 | W68: =V68+W71*W212 -> -3.511 | X68: =W68+X71*X212 -> -3.511 | Y68: =X68+Y71*Y212 -> -3.511 | Z68: =Y68+Z71*Z212 -> -3.511 | ... AB68: =AA68+AB71*AB212 -> -3.511 | AE68: -2.6 | AF68: =IF(ISBLANK(AE68),"",INDEX($A68:$AB68,1,MATCH(AE$3,$A$3:$AB$3,0))-AE68) -> #N/A | AG68: -2.6 | AH68: =IF(ISBLANK(AG68),"",INDEX($A68:$AB68,1,MATCH(AG$3,$A$3:$AB$3,0))-AG68) -> -0.911
A69: Net Interest | B69: Net Interest | C69: AUDm | D69: Preso | K69: 0.3 | L69: 0.6 | M69: -1.1 | N69: -1.3 | O69: -1.4 | P69: 2 | Q69: 5.8 | R69: =SUM(R67:R68) -> 6.639 | S69: 8.8 | T69: 11.1 | U69: 13.7 | V69: 16.6 | W69: 16.8 | X69: 17 | Y69: 17.3 | Z69: 17.8 | AA69: 18.8 | AB69: 20.3 | AE69: 7.1 | AF69: =IF(ISBLANK(AE69),"",INDEX($A69:$AB69,1,MATCH(AE$3,$A$3:$AB$3,0))-AE69) -> #N/A | AG69: 8.8 | AH69: =IF(ISBLANK(AG69),"",INDEX($A69:$AB69,1,MATCH(AG$3,$A$3:$AB$3,0))-AG69) -> 0
B70: Interest income rate | K70: #DIV/0! | L70: #DIV/0! | M70: #DIV/0! | N70: #DIV/0! | O70: #DIV/0! | P70: #DIV/0! | Q70: =Q67/AVERAGE(P140:Q140) -> 0.033466135 | R70: =R67/AVERAGE(Q140:R140) -> 0.033927142 | S70: =R70 -> 0.033927142 | T70: =S70 -> 0.033927142 | U70: =T70 -> 0.033927142 | V70: =U70 -> 0.033927142 | W70: =V70 -> 0.033927142 | X70: =W70 -> 0.033927142 | Y70: =X70 -> 0.033927142 | Z70: =Y70 -> 0.033927142 | ... AB70: =AA70 -> 0.033927142 | AE70: 0.033466135 | AF70: =IF(ISBLANK(AE70),"",INDEX($A70:$AB70,1,MATCH(AE$3,$A$3:$AB$3,0))-AE70) -> #N/A | AG70: 0.033466135 | AH70: =IF(ISBLANK(AG70),"",INDEX($A70:$AB70,1,MATCH(AG$3,$A$3:$AB$3,0))-AG70) -> 0.00046100642
B71: Interest expense rate | K71: #DIV/0! | L71: #DIV/0! | M71: #DIV/0! | N71: #DIV/0! | O71: #DIV/0! | P71: #DIV/0! | Q71: =Q68/AVERAGE(P159:Q159) -> #DIV/0! | R71: =R68/AVERAGE(Q159:R159) -> #DIV/0! | S71: 0.06 | T71: 0.06 | U71: 0.06 | V71: 0.06 | W71: 0.06 | X71: 0.06 | Y71: 0.06 | Z71: 0.06 | AA71: 0.06 | AB71: 0.06 | AE71: 0.06 | AF71: =IF(ISBLANK(AE71),"",INDEX($A71:$AB71,1,MATCH(AE$3,$A$3:$AB$3,0))-AE71) -> #N/A | AG71: 0.06 | AH71: =IF(ISBLANK(AG71),"",INDEX($A71:$AB71,1,MATCH(AG$3,$A$3:$AB$3,0))-AG71) -> 0
AF72: =IF(ISBLANK(AE72),"",INDEX($A72:$AB72,1,MATCH(AE$3,$A$3:$AB$3,0))-AE72) | AH72: =IF(ISBLANK(AG72),"",INDEX($A72:$AB72,1,MATCH(AG$3,$A$3:$AB$3,0))-AG72)
B73: PBT | AF73: =IF(ISBLANK(AE73),"",INDEX($A73:$AB73,1,MATCH(AE$3,$A$3:$AB$3,0))-AE73) | AH73: =IF(ISBLANK(AG73),"",INDEX($A73:$AB73,1,MATCH(AG$3,$A$3:$AB$3,0))-AG73)
A74: PBTSoftware | B74: Software | N74: 63.4 | O74: 77.5 | P74: 97.8 | Q74: 132 | R74: 162.171 | AF74: =IF(ISBLANK(AE74),"",INDEX($A74:$AB74,1,MATCH(AE$3,$A$3:$AB$3,0))-AE74) | AH74: =IF(ISBLANK(AG74),"",INDEX($A74:$AB74,1,MATCH(AG$3,$A$3:$AB$3,0))-AG74)
A75: PBTConsulting | B75: Consulting | N75: 15.6 | O75: 16.9 | P75: 13.8 | Q75: 6.7 | R75: 8.782 | AF75: =IF(ISBLANK(AE75),"",INDEX($A75:$AB75,1,MATCH(AE$3,$A$3:$AB$3,0))-AE75) | AH75: =IF(ISBLANK(AG75),"",INDEX($A75:$AB75,1,MATCH(AG$3,$A$3:$AB$3,0))-AG75)
A76: PBTCorporate | B76: Corporate | N76: 18.8 | O76: 18 | P76: 18.3 | Q76: 14.2 | R76: 10.593 | AF76: =IF(ISBLANK(AE76),"",INDEX($A76:$AB76,1,MATCH(AE$3,$A$3:$AB$3,0))-AE76) | AH76: =IF(ISBLANK(AG76),"",INDEX($A76:$AB76,1,MATCH(AG$3,$A$3:$AB$3,0))-AG76)
A77: PBT | B77: PBT | C77: AUDm | E77: 30.3 | F77: 35.1 | G77: 40.2 | H77: 46.5 | I77: 53.2 | J77: 58 | K77: 50.8 | L77: 76.4 | M77: 82.5 | N77: 97.8 | O77: 112.3 | P77: 129.9 | Q77: =SUM(Q74:Q76) -> 152.9 | R77: =SUM(R74:R76) -> 181.546 | S77: =INDEX(Segment!$A:$AR,MATCH(Annual!$A77,Segment!$A:$A,0),MATCH("1H"&RIGHT(Annual!S$1,2),Segment!$A$3:$AR$3,0))+INDEX(Segment!$A:$AR,MATCH(Annual!$A77,Segment!$A:$A,0),MATCH("2H"&RIGHT(Annual!S$1,2),Segment!$A$3:$AR$3,0)) -> 214.54063 | T77: =INDEX(Segment!$A:$AR,MATCH(Annual!$A77,Segment!$A:$A,0),MATCH("1H"&RIGHT(Annual!T$1,2),Segment!$A$3:$AR$3,0))+INDEX(Segment!$A:$AR,MATCH(Annual!$A77,Segment!$A:$A,0),MATCH("2H"&RIGHT(Annual!T$1,2),Segment!$A$3:$AR$3,0)) -> 257.36811 | U77: =INDEX(Segment!$A:$AR,MATCH(Annual!$A77,Segment!$A:$A,0),MATCH("1H"&RIGHT(Annual!U$1,2),Segment!$A$3:$AR$3,0))+INDEX(Segment!$A:$AR,MATCH(Annual!$A77,Segment!$A:$A,0),MATCH("2H"&RIGHT(Annual!U$1,2),Segment!$A$3:$AR$3,0)) -> 315.19478 | V77: =INDEX(Segment!$A:$AR,MATCH(Annual!$A77,Segment!$A:$A,0),MATCH("1H"&RIGHT(Annual!V$1,2),Segment!$A$3:$AR$3,0))+INDEX(Segment!$A:$AR,MATCH(Annual!$A77,Segment!$A:$A,0),MATCH("2H"&RIGHT(Annual!V$1,2),Segment!$A$3:$AR$3,0)) -> 383.29245 | W77: =INDEX(Segment!$A:$AR,MATCH(Annual!$A77,Segment!$A:$A,0),MATCH("1H"&RIGHT(Annual!W$1,2),Segment!$A$3:$AR$3,0))+INDEX(Segment!$A:$AR,MATCH(Annual!$A77,Segment!$A:$A,0),MATCH("2H"&RIGHT(Annual!W$1,2),Segment!$A$3:$AR$3,0)) -> 462.78736 | X77: =INDEX(Segment!$A:$AR,MATCH(Annual!$A77,Segment!$A:$A,0),MATCH("1H"&RIGHT(Annual!X$1,2),Segment!$A$3:$AR$3,0))+INDEX(Segment!$A:$AR,MATCH(Annual!$A77,Segment!$A:$A,0),MATCH("2H"&RIGHT(Annual!X$1,2),Segment!$A$3:$AR$3,0)) -> 560.79519 | Y77: =INDEX(Segment!$A:$AR,MATCH(Annual!$A77,Segment!$A:$A,0),MATCH("1H"&RIGHT(Annual!Y$1,2),Segment!$A$3:$AR$3,0))+INDEX(Segment!$A:$AR,MATCH(Annual!$A77,Segment!$A:$A,0),MATCH("2H"&RIGHT(Annual!Y$1,2),Segment!$A$3:$AR$3,0)) -> 681.89182 | Z77: =INDEX(Segment!$A:$AR,MATCH(Annual!$A77,Segment!$A:$A,0),MATCH("1H"&RIGHT(Annual!Z$1,2),Segment!$A$3:$AR$3,0))+INDEX(Segment!$A:$AR,MATCH(Annual!$A77,Segment!$A:$A,0),MATCH("2H"&RIGHT(Annual!Z$1,2),Segment!$A$3:$AR$3,0)) -> 831.7647 | ... AB77: =INDEX(Segment!$A:$AR,MATCH(Annual!$A77,Segment!$A:$A,0),MATCH("1H"&RIGHT(Annual!AB$1,2),Segment!$A$3:$AR$3,0))+INDEX(Segment!$A:$AR,MATCH(Annual!$A77,Segment!$A:$A,0),MATCH("2H"&RIGHT(Annual!AB$1,2),Segment!$A$3:$AR$3,0)) -> 1248.4589 | AE77: 184.32575 | AF77: =IF(ISBLANK(AE77),"",INDEX($A77:$AB77,1,MATCH(AE$3,$A$3:$AB$3,0))-AE77) -> #N/A | AG77: 223.43942 | AH77: =IF(ISBLANK(AG77),"",INDEX($A77:$AB77,1,MATCH(AG$3,$A$3:$AB$3,0))-AG77) -> -8.8987916
B78: PBT Margin | C78: % | E78: 0.179 | F78: 0.194 | G78: 0.206 | H78: 0.213 | I78: 0.214 | J78: 0.212 | K78: 0.2 | L78: 0.267 | M78: 0.276 | N78: 0.314 | O78: 0.304 | P78: 0.297 | Q78: =Q77/Q27 -> 0.29666279 | R78: =R77/R27 -> 0.29760273 | S78: =S77/S27 -> 0.30886754 | T78: =T77/T27 -> 0.32241766 | U78: =U77/U27 -> 0.33646027 | V78: =V77/V27 -> 0.34469099 | W78: =W77/W27 -> 0.3496843 | X78: =X77/X27 -> 0.35454392 | ... AB78: =AB77/AB27 -> 0.37440063 | AE78: 0.30466504 | AF78: =IF(ISBLANK(AE78),"",INDEX($A78:$AB78,1,MATCH(AE$3,$A$3:$AB$3,0))-AE78) -> #N/A | AG78: 0.31819017 | AH78: =IF(ISBLANK(AG78),"",INDEX($A78:$AB78,1,MATCH(AG$3,$A$3:$AB$3,0))-AG78) -> -0.0093226241 | AI78: #DIV/0! | AJ78: #DIV/0!
B79: Growth | C79: % YoY | H79: 0.16 | I79: 0.15 | J79: 0.09 | K79: -0.12 | L79: 0.5 | M79: 0.08 | N79: 0.19 | O79: 0.15 | P79: 0.16 | Q79: =Q77/P77-1 -> 0.17705928 | R79: =R77/Q77-1 -> 0.18735121 | S79: =S77/R77-1 -> 0.18174255 | T79: =T77/S77-1 -> 0.19962408 | U79: =U77/T77-1 -> 0.22468469 | V79: =V77/U77-1 -> 0.21604948 | W79: =W77/V77-1 -> 0.20740012 | X79: =X77/W77-1 -> 0.21177726 | ... AB79: =AB77/AA77-1 -> 0.22674315 | AE79: 0.20553139 | AF79: =IF(ISBLANK(AE79),"",INDEX($A79:$AB79,1,MATCH(AE$3,$A$3:$AB$3,0))-AE79) -> #N/A | AG79: 0.21219865 | AH79: =IF(ISBLANK(AG79),"",INDEX($A79:$AB79,1,MATCH(AG$3,$A$3:$AB$3,0))-AG79) -> -0.030456096
J80: 1.913 | K80: 1.448 | L80: 1.899 | M80: 1.774 | N80: 1.838 | AF80: =IF(ISBLANK(AE80),"",INDEX($A80:$AB80,1,MATCH(AE$3,$A$3:$AB$3,0))-AE80) | AH80: =IF(ISBLANK(AG80),"",INDEX($A80:$AB80,1,MATCH(AG$3,$A$3:$AB$3,0))-AG80)
B81: Guidance at 1H low | P81: 0.1 | Q81: 0.12 | R81: 0.13 | AE81: 0.13 | AF81: =IF(ISBLANK(AE81),"",INDEX($A81:$AB81,1,MATCH(AE$3,$A$3:$AB$3,0))-AE81) -> #N/A | AH81: =IF(ISBLANK(AG81),"",INDEX($A81:$AB81,1,MATCH(AG$3,$A$3:$AB$3,0))-AG81)
B82: Guidance at 1H high | P82: 0.15 | Q82: 0.16 | R82: 0.17 | AE82: 0.17 | AF82: =IF(ISBLANK(AE82),"",INDEX($A82:$AB82,1,MATCH(AE$3,$A$3:$AB$3,0))-AE82) -> #N/A | AH82: =IF(ISBLANK(AG82),"",INDEX($A82:$AB82,1,MATCH(AG$3,$A$3:$AB$3,0))-AG82)
AF83: =IF(ISBLANK(AE83),"",INDEX($A83:$AB83,1,MATCH(AE$3,$A$3:$AB$3,0))-AE83) | AH83: =IF(ISBLANK(AG83),"",INDEX($A83:$AB83,1,MATCH(AG$3,$A$3:$AB$3,0))-AG83)
B84: Tax | AF84: =IF(ISBLANK(AE84),"",INDEX($A84:$AB84,1,MATCH(AE$3,$A$3:$AB$3,0))-AE84) | AH84: =IF(ISBLANK(AG84),"",INDEX($A84:$AB84,1,MATCH(AG$3,$A$3:$AB$3,0))-AG84)
A85: Tax expense | B85: Tax expense | C85: AUDm | D85: AR | E85: -6.7 | F85: -8.1 | G85: -9.2 | H85: -10.7 | I85: -11.9 | J85: -13.5 | K85: 0.2 | L85: -17.9 | M85: -19.5 | N85: -25.2 | O85: -23.5 | P85: -27 | Q85: -34.9 | R85: -43.901 | S85: =INDEX(Segment!$A:$AR,MATCH(Annual!$A85,Segment!$A:$A,0),MATCH("1H"&RIGHT(Annual!S$1,2),Segment!$A$3:$AR$3,0))+INDEX(Segment!$A:$AR,MATCH(Annual!$A85,Segment!$A:$A,0),MATCH("2H"&RIGHT(Annual!S$1,2),Segment!$A$3:$AR$3,0)) -> -51.908087 | T85: =INDEX(Segment!$A:$AR,MATCH(Annual!$A85,Segment!$A:$A,0),MATCH("1H"&RIGHT(Annual!T$1,2),Segment!$A$3:$AR$3,0))+INDEX(Segment!$A:$AR,MATCH(Annual!$A85,Segment!$A:$A,0),MATCH("2H"&RIGHT(Annual!T$1,2),Segment!$A$3:$AR$3,0)) -> -62.278744 | U85: =INDEX(Segment!$A:$AR,MATCH(Annual!$A85,Segment!$A:$A,0),MATCH("1H"&RIGHT(Annual!U$1,2),Segment!$A$3:$AR$3,0))+INDEX(Segment!$A:$AR,MATCH(Annual!$A85,Segment!$A:$A,0),MATCH("2H"&RIGHT(Annual!U$1,2),Segment!$A$3:$AR$3,0)) -> -76.290931 | V85: =INDEX(Segment!$A:$AR,MATCH(Annual!$A85,Segment!$A:$A,0),MATCH("1H"&RIGHT(Annual!V$1,2),Segment!$A$3:$AR$3,0))+INDEX(Segment!$A:$AR,MATCH(Annual!$A85,Segment!$A:$A,0),MATCH("2H"&RIGHT(Annual!V$1,2),Segment!$A$3:$AR$3,0)) -> -92.753105 | W85: =INDEX(Segment!$A:$AR,MATCH(Annual!$A85,Segment!$A:$A,0),MATCH("1H"&RIGHT(Annual!W$1,2),Segment!$A$3:$AR$3,0))+INDEX(Segment!$A:$AR,MATCH(Annual!$A85,Segment!$A:$A,0),MATCH("2H"&RIGHT(Annual!W$1,2),Segment!$A$3:$AR$3,0)) -> -111.9839 | X85: =INDEX(Segment!$A:$AR,MATCH(Annual!$A85,Segment!$A:$A,0),MATCH("1H"&RIGHT(Annual!X$1,2),Segment!$A$3:$AR$3,0))+INDEX(Segment!$A:$AR,MATCH(Annual!$A85,Segment!$A:$A,0),MATCH("2H"&RIGHT(Annual!X$1,2),Segment!$A$3:$AR$3,0)) -> -135.69287 | Y85: =INDEX(Segment!$A:$AR,MATCH(Annual!$A85,Segment!$A:$A,0),MATCH("1H"&RIGHT(Annual!Y$1,2),Segment!$A$3:$AR$3,0))+INDEX(Segment!$A:$AR,MATCH(Annual!$A85,Segment!$A:$A,0),MATCH("2H"&RIGHT(Annual!Y$1,2),Segment!$A$3:$AR$3,0)) -> -164.98653 | Z85: =INDEX(Segment!$A:$AR,MATCH(Annual!$A85,Segment!$A:$A,0),MATCH("1H"&RIGHT(Annual!Z$1,2),Segment!$A$3:$AR$3,0))+INDEX(Segment!$A:$AR,MATCH(Annual!$A85,Segment!$A:$A,0),MATCH("2H"&RIGHT(Annual!Z$1,2),Segment!$A$3:$AR$3,0)) -> -201.24022 | ... AB85: =INDEX(Segment!$A:$AR,MATCH(Annual!$A85,Segment!$A:$A,0),MATCH("1H"&RIGHT(Annual!AB$1,2),Segment!$A$3:$AR$3,0))+INDEX(Segment!$A:$AR,MATCH(Annual!$A85,Segment!$A:$A,0),MATCH("2H"&RIGHT(Annual!AB$1,2),Segment!$A$3:$AR$3,0)) -> -302.03135 | AE85: -42.560348 | AF85: =IF(ISBLANK(AE85),"",INDEX($A85:$AB85,1,MATCH(AE$3,$A$3:$AB$3,0))-AE85) -> #N/A | AG85: -51.614507 | AH85: =IF(ISBLANK(AG85),"",INDEX($A85:$AB85,1,MATCH(AG$3,$A$3:$AB$3,0))-AG85) -> -0.29357996
A86: Underlying Tax rate | B86: Underlying Tax rate | C86: % | E86: 0.222 | F86: 0.231 | G86: 0.23 | H86: 0.23 | I86: 0.224 | J86: 0.233 | K86: -0.004 | L86: 0.235 | M86: 0.237 | N86: 0.257 | O86: 0.209 | P86: 0.208 | Q86: =Q85/Q77 -> -0.22825376 | R86: =R85/R77 -> -0.2418175 | S86: =S85/S77 -> -0.24194991 | T86: =T85/T77 -> -0.24198314 | U86: =U85/U77 -> -0.24204376 | V86: =V85/V77 -> -0.24199043 | W86: =W85/W77 -> -0.24197701 | X86: =X85/X77 -> -0.2419651 | ... AB86: =AB85/AB77 -> -0.24192335 | AE86: -0.23089746 | AF86: =IF(ISBLANK(AE86),"",INDEX($A86:$AB86,1,MATCH(AE$3,$A$3:$AB$3,0))-AE86) -> #N/A | AG86: -0.231 | AH86: =IF(ISBLANK(AG86),"",INDEX($A86:$AB86,1,MATCH(AG$3,$A$3:$AB$3,0))-AG86) -> -0.010949911
AF87: =IF(ISBLANK(AE87),"",INDEX($A87:$AB87,1,MATCH(AE$3,$A$3:$AB$3,0))-AE87) | AH87: =IF(ISBLANK(AG87),"",INDEX($A87:$AB87,1,MATCH(AG$3,$A$3:$AB$3,0))-AG87)
B88: NPAT | AF88: =IF(ISBLANK(AE88),"",INDEX($A88:$AB88,1,MATCH(AE$3,$A$3:$AB$3,0))-AE88) | AH88: =IF(ISBLANK(AG88),"",INDEX($A88:$AB88,1,MATCH(AG$3,$A$3:$AB$3,0))-AG88)
A89: Statutory NPAT | B89: Statutory NPAT | C89: AUDm | D89: Preso | E89: 23.6 | F89: 27 | G89: 31 | H89: 35.8 | I89: 41.3 | J89: 44.5 | K89: 51 | L89: 58.5 | M89: 62.9 | N89: 72.7 | O89: 88.8 | P89: 102.9 | Q89: =Q77+Q85 -> 118 | R89: =R77+R85 -> 137.645 | S89: =INDEX(Segment!$A:$AR,MATCH(Annual!$A89,Segment!$A:$A,0),MATCH("1H"&RIGHT(Annual!S$1,2),Segment!$A$3:$AR$3,0))+INDEX(Segment!$A:$AR,MATCH(Annual!$A89,Segment!$A:$A,0),MATCH("2H"&RIGHT(Annual!S$1,2),Segment!$A$3:$AR$3,0)) -> 162.63255 | T89: =INDEX(Segment!$A:$AR,MATCH(Annual!$A89,Segment!$A:$A,0),MATCH("1H"&RIGHT(Annual!T$1,2),Segment!$A$3:$AR$3,0))+INDEX(Segment!$A:$AR,MATCH(Annual!$A89,Segment!$A:$A,0),MATCH("2H"&RIGHT(Annual!T$1,2),Segment!$A$3:$AR$3,0)) -> 195.08937 | U89: =INDEX(Segment!$A:$AR,MATCH(Annual!$A89,Segment!$A:$A,0),MATCH("1H"&RIGHT(Annual!U$1,2),Segment!$A$3:$AR$3,0))+INDEX(Segment!$A:$AR,MATCH(Annual!$A89,Segment!$A:$A,0),MATCH("2H"&RIGHT(Annual!U$1,2),Segment!$A$3:$AR$3,0)) -> 238.90385 | V89: =INDEX(Segment!$A:$AR,MATCH(Annual!$A89,Segment!$A:$A,0),MATCH("1H"&RIGHT(Annual!V$1,2),Segment!$A$3:$AR$3,0))+INDEX(Segment!$A:$AR,MATCH(Annual!$A89,Segment!$A:$A,0),MATCH("2H"&RIGHT(Annual!V$1,2),Segment!$A$3:$AR$3,0)) -> 290.53935 | W89: =INDEX(Segment!$A:$AR,MATCH(Annual!$A89,Segment!$A:$A,0),MATCH("1H"&RIGHT(Annual!W$1,2),Segment!$A$3:$AR$3,0))+INDEX(Segment!$A:$AR,MATCH(Annual!$A89,Segment!$A:$A,0),MATCH("2H"&RIGHT(Annual!W$1,2),Segment!$A$3:$AR$3,0)) -> 350.80345 | X89: =INDEX(Segment!$A:$AR,MATCH(Annual!$A89,Segment!$A:$A,0),MATCH("1H"&RIGHT(Annual!X$1,2),Segment!$A$3:$AR$3,0))+INDEX(Segment!$A:$AR,MATCH(Annual!$A89,Segment!$A:$A,0),MATCH("2H"&RIGHT(Annual!X$1,2),Segment!$A$3:$AR$3,0)) -> 425.10232 | Y89: =INDEX(Segment!$A:$AR,MATCH(Annual!$A89,Segment!$A:$A,0),MATCH("1H"&RIGHT(Annual!Y$1,2),Segment!$A$3:$AR$3,0))+INDEX(Segment!$A:$AR,MATCH(Annual!$A89,Segment!$A:$A,0),MATCH("2H"&RIGHT(Annual!Y$1,2),Segment!$A$3:$AR$3,0)) -> 516.90528 | Z89: =INDEX(Segment!$A:$AR,MATCH(Annual!$A89,Segment!$A:$A,0),MATCH("1H"&RIGHT(Annual!Z$1,2),Segment!$A$3:$AR$3,0))+INDEX(Segment!$A:$AR,MATCH(Annual!$A89,Segment!$A:$A,0),MATCH("2H"&RIGHT(Annual!Z$1,2),Segment!$A$3:$AR$3,0)) -> 630.52448 | ... AB89: =INDEX(Segment!$A:$AR,MATCH(Annual!$A89,Segment!$A:$A,0),MATCH("1H"&RIGHT(Annual!AB$1,2),Segment!$A$3:$AR$3,0))+INDEX(Segment!$A:$AR,MATCH(Annual!$A89,Segment!$A:$A,0),MATCH("2H"&RIGHT(Annual!AB$1,2),Segment!$A$3:$AR$3,0)) -> 946.4275 | AE89: 141.7654 | AF89: =IF(ISBLANK(AE89),"",INDEX($A89:$AB89,1,MATCH(AE$3,$A$3:$AB$3,0))-AE89) -> #N/A | AG89: 171.82492 | AH89: =IF(ISBLANK(AG89),"",INDEX($A89:$AB89,1,MATCH(AG$3,$A$3:$AB$3,0))-AG89) -> -9.1923716
A90: Significant items after tax | B90: Significant items after tax | E90: -5 | F90: -4 | G90: -3 | H90: -2 | I90: -1 | J90: 0 | K90: 0 | L90: 0 | M90: 0 | N90: 0 | O90: 0 | P90: 0 | Q90: 0 | R90: 0 | S90: 0 | T90: 0 | U90: 0 | V90: 0 | W90: 0 | X90: 0 | Y90: 0 | Z90: 0 | AA90: 0 | AB90: 0 | AE90: 0 | AF90: =IF(ISBLANK(AE90),"",INDEX($A90:$AB90,1,MATCH(AE$3,$A$3:$AB$3,0))-AE90) -> #N/A | AG90: 0 | AH90: =IF(ISBLANK(AG90),"",INDEX($A90:$AB90,1,MATCH(AG$3,$A$3:$AB$3,0))-AG90) -> 0
A91: Underlying NPAT | B91: Underlying NPAT | C91: AUDm | E91: 18.6 | F91: 23 | G91: 28 | H91: 33.8 | I91: 40.3 | J91: 44.5 | K91: 51 | L91: 58.5 | M91: 62.9 | N91: 72.7 | O91: 88.8 | P91: 102.9 | Q91: =Q89+Q90 -> 118 | R91: =R89+R90 -> 137.645 | S91: =INDEX(Segment!$A:$AR,MATCH(Annual!$A91,Segment!$A:$A,0),MATCH("1H"&RIGHT(Annual!S$1,2),Segment!$A$3:$AR$3,0))+INDEX(Segment!$A:$AR,MATCH(Annual!$A91,Segment!$A:$A,0),MATCH("2H"&RIGHT(Annual!S$1,2),Segment!$A$3:$AR$3,0)) -> 162.63255 | T91: =INDEX(Segment!$A:$AR,MATCH(Annual!$A91,Segment!$A:$A,0),MATCH("1H"&RIGHT(Annual!T$1,2),Segment!$A$3:$AR$3,0))+INDEX(Segment!$A:$AR,MATCH(Annual!$A91,Segment!$A:$A,0),MATCH("2H"&RIGHT(Annual!T$1,2),Segment!$A$3:$AR$3,0)) -> 195.08937 | U91: =INDEX(Segment!$A:$AR,MATCH(Annual!$A91,Segment!$A:$A,0),MATCH("1H"&RIGHT(Annual!U$1,2),Segment!$A$3:$AR$3,0))+INDEX(Segment!$A:$AR,MATCH(Annual!$A91,Segment!$A:$A,0),MATCH("2H"&RIGHT(Annual!U$1,2),Segment!$A$3:$AR$3,0)) -> 238.90385 | V91: =INDEX(Segment!$A:$AR,MATCH(Annual!$A91,Segment!$A:$A,0),MATCH("1H"&RIGHT(Annual!V$1,2),Segment!$A$3:$AR$3,0))+INDEX(Segment!$A:$AR,MATCH(Annual!$A91,Segment!$A:$A,0),MATCH("2H"&RIGHT(Annual!V$1,2),Segment!$A$3:$AR$3,0)) -> 290.53935 | W91: =INDEX(Segment!$A:$AR,MATCH(Annual!$A91,Segment!$A:$A,0),MATCH("1H"&RIGHT(Annual!W$1,2),Segment!$A$3:$AR$3,0))+INDEX(Segment!$A:$AR,MATCH(Annual!$A91,Segment!$A:$A,0),MATCH("2H"&RIGHT(Annual!W$1,2),Segment!$A$3:$AR$3,0)) -> 350.80345 | X91: =INDEX(Segment!$A:$AR,MATCH(Annual!$A91,Segment!$A:$A,0),MATCH("1H"&RIGHT(Annual!X$1,2),Segment!$A$3:$AR$3,0))+INDEX(Segment!$A:$AR,MATCH(Annual!$A91,Segment!$A:$A,0),MATCH("2H"&RIGHT(Annual!X$1,2),Segment!$A$3:$AR$3,0)) -> 425.10232 | Y91: =INDEX(Segment!$A:$AR,MATCH(Annual!$A91,Segment!$A:$A,0),MATCH("1H"&RIGHT(Annual!Y$1,2),Segment!$A$3:$AR$3,0))+INDEX(Segment!$A:$AR,MATCH(Annual!$A91,Segment!$A:$A,0),MATCH("2H"&RIGHT(Annual!Y$1,2),Segment!$A$3:$AR$3,0)) -> 516.90528 | Z91: =INDEX(Segment!$A:$AR,MATCH(Annual!$A91,Segment!$A:$A,0),MATCH("1H"&RIGHT(Annual!Z$1,2),Segment!$A$3:$AR$3,0))+INDEX(Segment!$A:$AR,MATCH(Annual!$A91,Segment!$A:$A,0),MATCH("2H"&RIGHT(Annual!Z$1,2),Segment!$A$3:$AR$3,0)) -> 630.52448 | ... AB91: =INDEX(Segment!$A:$AR,MATCH(Annual!$A91,Segment!$A:$A,0),MATCH("1H"&RIGHT(Annual!AB$1,2),Segment!$A$3:$AR$3,0))+INDEX(Segment!$A:$AR,MATCH(Annual!$A91,Segment!$A:$A,0),MATCH("2H"&RIGHT(Annual!AB$1,2),Segment!$A$3:$AR$3,0)) -> 946.4275 | AE91: 141.7654 | AF91: =IF(ISBLANK(AE91),"",INDEX($A91:$AB91,1,MATCH(AE$3,$A$3:$AB$3,0))-AE91) -> #N/A | AG91: 171.82492 | AH91: =IF(ISBLANK(AG91),"",INDEX($A91:$AB91,1,MATCH(AG$3,$A$3:$AB$3,0))-AG91) -> -9.1923716
B92: Underlying NPAT Growth | C92: % YoY | F92: 0.237 | G92: 0.217 | H92: 0.207 | I92: 0.192 | J92: 0.104 | K92: 0.146 | L92: 0.146 | M92: 0.077 | N92: 0.155 | O92: 0.222 | P92: 0.158 | Q92: =Q91/P91-1 -> 0.14674441 | R92: =R91/Q91-1 -> 0.16648305 | S92: =S91/R91-1 -> 0.18153617 | T92: =T91/S91-1 -> 0.1995715 | U92: =U91/T91-1 -> 0.22458675 | V92: =V91/U91-1 -> 0.21613505 | W92: =W91/V91-1 -> 0.20742149 | X92: =X91/W91-1 -> 0.21179629 | ... AB92: =AB91/AA91-1 -> 0.22675942 | AE92: 0.20140171 | AF92: =IF(ISBLANK(AE92),"",INDEX($A92:$AB92,1,MATCH(AE$3,$A$3:$AB$3,0))-AE92) -> #N/A | AG92: 0.21203704 | AH92: =IF(ISBLANK(AG92),"",INDEX($A92:$AB92,1,MATCH(AG$3,$A$3:$AB$3,0))-AG92) -> -0.030500869
B93: Underlying NPAT margin | C93: % | F93: 0.127 | G93: 0.143 | H93: 0.155 | I93: 0.162 | J93: 0.163 | K93: 0.201 | L93: 0.205 | M93: 0.211 | N93: 0.233 | O93: 0.241 | P93: 0.235 | Q93: =Q91/Q27 -> 0.22894839 | R93: =R91/R27 -> 0.22563718 | S93: =S91/S27 -> 0.23413707 | T93: =T91/T27 -> 0.24439802 | U93: =U91/U27 -> 0.25502216 | V93: =V91/V27 -> 0.26127907 | W93: =W91/W27 -> 0.26506874 | X93: =X91/X27 -> 0.26875666 | ... AB93: =AB91/AB27 -> 0.28382437 | AE93: 0.23431866 | AF93: =IF(ISBLANK(AE93),"",INDEX($A93:$AB93,1,MATCH(AE$3,$A$3:$AB$3,0))-AE93) -> #N/A | AG93: 0.24468824 | AH93: =IF(ISBLANK(AG93),"",INDEX($A93:$AB93,1,MATCH(AG$3,$A$3:$AB$3,0))-AG93) -> -0.01055117
AF94: =IF(ISBLANK(AE94),"",INDEX($A94:$AB94,1,MATCH(AE$3,$A$3:$AB$3,0))-AE94) | AH94: =IF(ISBLANK(AG94),"",INDEX($A94:$AB94,1,MATCH(AG$3,$A$3:$AB$3,0))-AG94)
B95: EPS | AF95: =IF(ISBLANK(AE95),"",INDEX($A95:$AB95,1,MATCH(AE$3,$A$3:$AB$3,0))-AE95) | AH95: =IF(ISBLANK(AG95),"",INDEX($A95:$AB95,1,MATCH(AG$3,$A$3:$AB$3,0))-AG95)
A96: =B96 -> YE Basic Shares Outstanding | B96: YE Basic Shares Outstanding | C96: #m | K96: 316.69 | L96: 317.83 | M96: 319.3 | N96: 321.65 | O96: 323.37 | P96: 324.67 | Q96: 326.08 | R96: 327.36854 | S96: =R96+S210/S103 -> 327.36854 | T96: =S96+T210/T103 -> 327.36854 | U96: =T96+U210/U103 -> 327.36854 | V96: =U96+V210/V103 -> 324.42736 | W96: =V96+W210/W103 -> 321.04501 | X96: =W96+X210/X103 -> 317.14795 | Y96: =X96+Y210/Y103 -> 312.66266 | Z96: =Y96+Z210/Z103 -> 307.5156 | ... AB96: =AA96+AB210/AB103 -> 294.79501 | AE96: 326.08 | AF96: =IF(ISBLANK(AE96),"",INDEX($A96:$AB96,1,MATCH(AE$3,$A$3:$AB$3,0))-AE96) -> #N/A | AG96: 326.08 | AH96: =IF(ISBLANK(AG96),"",INDEX($A96:$AB96,1,MATCH(AG$3,$A$3:$AB$3,0))-AG96) -> 1.288541
B97: Weighted Average Basic Shares Outstanding | C97: #m | K97: 315.8 | L97: 317.22 | M97: 318.66 | N97: 321.07 | O97: 322.95 | P97: 324.42 | Q97: 325.66 | R97: 326.72623 | S97: 326.08 | T97: 326.08 | U97: 326.08 | V97: 325.02 | W97: 322.76 | X97: 320.16 | Y97: 317.16 | Z97: 313.72 | AA97: 309.76 | AB97: 305.21 | AE97: 326.08 | AF97: =IF(ISBLANK(AE97),"",INDEX($A97:$AB97,1,MATCH(AE$3,$A$3:$AB$3,0))-AE97) -> #N/A | AG97: 326.08 | AH97: =IF(ISBLANK(AG97),"",INDEX($A97:$AB97,1,MATCH(AG$3,$A$3:$AB$3,0))-AG97) -> 0
B98: Dilution | C98: #m | J98: 0 | K98: 0.89 | L98: 2.28 | M98: 2.3 | N98: 1.67 | O98: 1.53 | P98: 1.58 | Q98: =Q99-Q97 -> 1.91 | R98: =R99-R97 -> 3.137279 | S98: 1.91 | T98: 1.91 | U98: 1.91 | V98: 1.91 | W98: 1.91 | X98: 1.91 | Y98: 1.91 | Z98: 1.91 | AA98: 1.91 | AB98: 1.91 | AE98: 1.91 | AF98: =IF(ISBLANK(AE98),"",INDEX($A98:$AB98,1,MATCH(AE$3,$A$3:$AB$3,0))-AE98) -> #N/A | AG98: 1.91 | AH98: =IF(ISBLANK(AG98),"",INDEX($A98:$AB98,1,MATCH(AG$3,$A$3:$AB$3,0))-AG98) -> 0
B99: Weighted Average Diluted Shares Outstanding | C99: #m | K99: 316.69 | L99: 319.5 | M99: 320.95 | N99: 322.74 | O99: 324.48 | P99: 326 | Q99: 327.57 | R99: 329.86351 | S99: 327.99 | T99: 327.99 | U99: 327.99 | V99: 326.94 | W99: 324.67 | X99: 322.07 | Y99: 319.08 | Z99: 315.64 | AA99: 311.68 | AB99: 307.13 | AE99: 327.99 | AF99: =IF(ISBLANK(AE99),"",INDEX($A99:$AB99,1,MATCH(AE$3,$A$3:$AB$3,0))-AE99) -> #N/A | AG99: 327.99 | AH99: =IF(ISBLANK(AG99),"",INDEX($A99:$AB99,1,MATCH(AG$3,$A$3:$AB$3,0))-AG99) -> 0
AF100: =IF(ISBLANK(AE100),"",INDEX($A100:$AB100,1,MATCH(AE$3,$A$3:$AB$3,0))-AE100) | AH100: =IF(ISBLANK(AG100),"",INDEX($A100:$AB100,1,MATCH(AG$3,$A$3:$AB$3,0))-AG100)
...

Sheet Segment
B1: Segments | C1: 2019 | D1: 2016 | E1: 2016 | F1: 2017 | G1: 2017 | H1: 2018 | I1: 2018 | J1: 2019 | K1: 2019 | L1: 2020 | M1: 2020 | N1: 2021 | O1: 2021 | P1: 2022 | Q1: 2022 | R1: 2023 | S1: 2023 | T1: 2024 | U1: 2024 | V1: 2025 | W1: =U1+1 -> 2025 | X1: 2026 | Y1: 2026 | Z1: 2027 | AA1: 2027 | AB1: 2028 | AC1: 2028 | AD1: 2029 | AE1: 2029 | AF1: 2030 | AG1: 2030 | AH1: 2031 | AI1: 2031 | AJ1: 2032 | AK1: 2032 | AL1: 2033 | AM1: 2033 | AN1: 2034 | AO1: 2034 | AP1: 2035 | AQ1: 2035 | AS1: Earnings changes=> | AT1: 2025 | AU1: 2024 | AV1: 2025 | AW1: 2024
D2: Actual ----------> | X2: Forecast -----> | AT2: Forecast -----> | AU2: Forecast -----> | AW2: Forecast -----> | AY2: Seasonality- 5yr averages
C3: Units | D3: 1H16 | E3: 2H16 | F3: 1H17 | G3: 2H17 | H3: 1H18 | I3: 2H18 | J3: 1H19 | K3: 2H19 | L3: 1H20 | M3: 2H20 | N3: 1H21 | O3: 2H21 | P3: 1H22 | Q3: 2H22 | R3: 1H23 | S3: 2H23 | T3: 1H24 | U3: 2H24 | V3: 1H25 | W3: ="2H"&RIGHT(W1,2) -> 2H25 | X3: 1H26 | Y3: 2H26 | Z3: 1H27 | AA3: 2H27 | AB3: 1H28 | AC3: 2H28 | AD3: 1H29 | AE3: 2H29 | AF3: 1H30 | AG3: 2H30 | AH3: 1H31 | AI3: 2H31 | AJ3: 1H32 | AK3: 2H32 | AL3: 1H33 | AM3: 2H33 | AN3: 1H34 | AO3: 2H34 | AP3: 1H35 | AQ3: 2H35 | AT3: 1H25 | AU3: FY24E | AV3: 2H25 | AW3: FY24E | AY3: 1H | AZ3: 2H
B4: P &L
B6: Revenue | BA6: #REF!
A7: Rev-SaaS fees | B7: SaaS fees | C7: AUDm | D7: AR | J7: 37.6 | K7: 43.9 | L7: 51.1 | M7: 55.1 | N7: 68.8 | O7: 82.2 | P7: 96.2 | Q7: 120.6 | R7: 145 | S7: 171.2 | T7: 193.9 | U7: =INDEX(Annual!$A:$AC,MATCH(Segment!$A7,Annual!$A:$A,0),MATCH(Segment!U$1,Annual!$A$1:$AC$1,0))-T7 -> 213.5 | V7: 239 | W7: =INDEX(Annual!$A:$AC,MATCH(Segment!$A7,Annual!$A:$A,0),MATCH(Segment!W$1,Annual!$A$1:$AC$1,0))-V7 -> 260.725 | X7: =V7*(1+W88) -> 281.90004 | Y7: =W7*(1+X88) -> 305.77926 | Z7: =X7*(1+Y88) -> 331.42832 | AA7: =Y7*(1+Z88) -> 364.24082 | AB7: =Z7*(1+AA88) -> 395.67694 | AC7: =AA7*(1+AB88) -> 442.67611 | AD7: =AB7*(1+AC88) -> 481.68012 | AE7: =AC7*(1+AD88) -> 535.79039 | ... AQ7: =AO7*(1+AP88) -> 1714.1896 | AT7: 237.5 | AU7: 1.5 | AV7: 251.5 | AW7: 6.1
A8: Rev-Annual licence fees | B8: Annual licence fees | C8: AUDm | D8: AR | J8: 50.8 | K8: 47.9 | L8: 50.5 | M8: 50.6 | N8: 41.4 | O8: 36.6 | P8: 39.1 | Q8: 30.1 | R8: 21.3 | S8: 15.7 | T8: 10.4 | U8: =INDEX(Annual!$A:$AC,MATCH(Segment!$A8,Annual!$A:$A,0),MATCH(Segment!U$1,Annual!$A$1:$AC$1,0))-T8 -> 7.4 | V8: 4.1 | W8: =INDEX(Annual!$A:$AC,MATCH(Segment!$A8,Annual!$A:$A,0),MATCH(Segment!W$1,Annual!$A$1:$AC$1,0))-V8 -> 3.111 | X8: =V8 -> 4.1 | Y8: =W8 -> 3.111 | Z8: =X8 -> 4.1 | AA8: =Y8 -> 3.111 | AB8: =Z8 -> 4.1 | AC8: =AA8 -> 3.111 | AD8: =AB8 -> 4.1 | AE8: =AC8 -> 3.111 | ... AQ8: =AO8 -> 3.111 | AT8: 7.4 | AU8: -3.3 | AV8: 7.4 | AW8: -3.3
A9: Rev-Consulting services | B9: Consulting services | C9: AUDm | D9: AR | J9: 29.2 | K9: 32.4 | L9: 30.2 | M9: 32.3 | N9: 30.4 | O9: 34.2 | P9: 34.1 | Q9: 38.5 | R9: 33.7 | S9: 39.4 | T9: 36.3 | U9: =INDEX(Annual!$A:$AC,MATCH(Segment!$A9,Annual!$A:$A,0),MATCH(Segment!U$1,Annual!$A$1:$AC$1,0))-T9 -> 44.2 | V9: 42.6 | W9: =INDEX(Annual!$A:$AC,MATCH(Segment!$A9,Annual!$A:$A,0),MATCH(Segment!W$1,Annual!$A$1:$AC$1,0))-V9 -> 48.966 | X9: =V9*0.95 -> 40.47 | Y9: =W9*0.95 -> 46.5177 | Z9: =X9*0.95 -> 38.4465 | AA9: =Y9*0.95 -> 44.191815 | AB9: =Z9*0.95 -> 36.524175 | AC9: =AA9*0.95 -> 41.982224 | AD9: =AB9*0.95 -> 34.697966 | AE9: =AC9*0.95 -> 39.883113 | ... AQ9: =AO9*0.95 -> 29.317753 | AT9: 31.9 | AU9: 10.7 | AV9: 39 | AW9: 7.5
A10: Rev-Legacy licence services (initial fees) | B10: Legacy licence services (initial fees) | C10: AUDm | D10: AR | J10: 11 | K10: 32.2 | L10: 6.2 | M10: 22.3 | N10: 3.8 | O10: 14 | P10: 2.5 | Q10: 7.1 | R10: 1 | S10: 2 | T10: 0.3 | U10: =INDEX(Annual!$A:$AC,MATCH(Segment!$A10,Annual!$A:$A,0),MATCH(Segment!U$1,Annual!$A$1:$AC$1,0))-T10 -> 0.5 | V10: 0 | W10: =INDEX(Annual!$A:$AC,MATCH(Segment!$A10,Annual!$A:$A,0),MATCH(Segment!W$1,Annual!$A$1:$AC$1,0))-V10 -> 0 | X10: 0.6 | Y10: 0.6 | Z10: 0.6 | AA10: 0.6 | AB10: 0.6 | AC10: 0.6 | AD10: 0.6 | AE10: 0.6 | AF10: 0.6 | AG10: 0.6 | AH10: 0.6 | AI10: 0.6 | AJ10: 0.6 | AK10: 0.6 | AL10: 0.6 | AM10: 0.6 | AN10: 0.6 | AO10: 0.6 | AP10: 0.6 | AQ10: 0.6 | AT10: 0.3 | AU10: -0.3 | AV10: 0.6 | AW10: 0
A11: Rev-Revenue from contracts with customers | B11: Revenue from contracts with customers | C11: AUDm | J11: 128.5 | K11: 156.5 | L11: 138 | M11: 160.3 | N11: 144.3 | O11: 167 | P11: 172 | Q11: 196.2 | R11: 201 | S11: 228.4 | T11: 240.8 | U11: =INDEX(Annual!$A:$AC,MATCH(Segment!$A11,Annual!$A:$A,0),MATCH(Segment!U$1,Annual!$A$1:$AC$1,0))-T11 -> 265.7 | V11: =SUM(V7:V10) -> 285.7 | W11: =INDEX(Annual!$A:$AC,MATCH(Segment!$A11,Annual!$A:$A,0),MATCH(Segment!W$1,Annual!$A$1:$AC$1,0))-V11 -> 312.802 | X11: =SUM(X7:X10) -> 327.07004 | Y11: =SUM(Y7:Y10) -> 356.00796 | Z11: =SUM(Z7:Z10) -> 374.57482 | AA11: =SUM(AA7:AA10) -> 412.14364 | AB11: =SUM(AB7:AB10) -> 436.90111 | AC11: =SUM(AC7:AC10) -> 488.36934 | AD11: =SUM(AD7:AD10) -> 521.07809 | AE11: =SUM(AE7:AE10) -> 579.38451 | ... AQ11: =SUM(AQ7:AQ10) -> 1747.2184 | AT11: 277.1 | AU11: 8.6 | AV11: 298.4 | AW11: 10.3
B12: Growth | C12: % YoY | J12: #DIV/0! | K12: #DIV/0! | L12: 0.074 | M12: 0.024 | N12: 0.046 | O12: 0.042 | P12: 0.192 | Q12: 0.175 | R12: 0.169 | S12: 0.164 | T12: 0.198 | U12: =U11/S11-1 -> 0.16330998 | V12: =V11/T11-1 -> 0.18646179 | W12: =W11/U11-1 -> 0.17727512 | X12: =X11/V11-1 -> 0.14480239 | Y12: =Y11/W11-1 -> 0.13812559 | Z12: =Z11/X11-1 -> 0.14524344 | AA12: =AA11/Y11-1 -> 0.15768096 | AB12: =AB11/Z11-1 -> 0.1663921 | ... AQ12: =AQ11/AO11-1 -> 0.21065643 | AT12: 0.151 | AU12: 0.036 | AV12: 0.123 | AW12: 0.039
A14: Rev-Other income exc interest | B14: Other income exc interest | C14: AUDm | J14: 0.3 | K14: 0.3 | L14: 0.2 | M14: 0.2 | N14: 0.2 | O14: 0.3 | P14: 0.4 | Q14: 0.4 | R14: 7.7 | S14: 0.1 | T14: 3.9 | U14: =INDEX(Annual!$A:$AC,MATCH(Segment!$A14,Annual!$A:$A,0),MATCH(Segment!U$1,Annual!$A$1:$AC$1,0))-T14 -> 5 | V14: 5.6 | W14: =INDEX(Annual!$A:$AC,MATCH(Segment!$A14,Annual!$A:$A,0),MATCH(Segment!W$1,Annual!$A$1:$AC$1,0))-V14 -> 5.926 | X14: =V14 -> 5.6 | Y14: =W14 -> 5.926 | Z14: =X14 -> 5.6 | AA14: =Y14 -> 5.926 | AB14: =Z14 -> 5.6 | AC14: =AA14 -> 5.926 | AD14: =AB14 -> 5.6 | AE14: =AC14 -> 5.926 | ... AQ14: =AO14 -> 5.926 | AT14: 3.9 | AU14: 1.7 | AV14: 4.9 | AW14: 0
B15: Total Revenue exc interest | C15: AUDm | D15: Preso | J15: 128.8 | K15: 156.8 | L15: 138.2 | M15: 160.5 | N15: 144.5 | O15: 167.3 | P15: 172.4 | Q15: 196.6 | R15: 208.7 | S15: 228.5 | T15: 244.7 | U15: =U11+U14 -> 270.7 | V15: =V11+V14 -> 291.3 | W15: =W11+W14 -> 318.728 | X15: =X11+X14 -> 332.67004 | Y15: =Y11+Y14 -> 361.93396 | Z15: =Z11+Z14 -> 380.17482 | AA15: =AA11+AA14 -> 418.06964 | AB15: =AB11+AB14 -> 442.50111 | ... AQ15: =AQ11+AQ14 -> 1753.1444 | AT15: 281 | AU15: 10.2 | AV15: 303.4 | AW15: 10.3
B16: Growth | C16: % YoY | J16: #DIV/0! | K16: #DIV/0! | L16: 0.072 | M16: 0.024 | N16: 0.046 | O16: 0.042 | P16: 0.193 | Q16: 0.176 | R16: 0.211 | S16: 0.162 | T16: 0.173 | U16: =U15/S15-1 -> 0.18468271 | V16: =V15/T15-1 -> 0.19043727 | W16: =W15/U15-1 -> 0.1774215 | X16: =X15/V15-1 -> 0.14201868 | Y16: =Y15/W15-1 -> 0.13555746 | Z16: =Z15/X15-1 -> 0.14279848 | AA16: =AA15/Y15-1 -> 0.15509923 | AB16: =AB15/Z15-1 -> 0.16394114 | ... AQ16: =AQ15/AO15-1 -> 0.20979498 | AT16: 0.148 | AU16: 0.042 | AV16: 0.121 | AW16: 0.038
B18: Cost of Sales
A19: Costs-Variable costs | B19: Variable costs | C19: AUDm | D19: AR | J19: -9.8 | K19: -9.9 | L19: -7.1 | M19: -12 | N19: -8.7 | O19: -10.7 | P19: -10.3 | Q19: -10.4 | R19: -11.5 | S19: -9.5 | T19: -11.2 | U19: =INDEX(Annual!$A:$AC,MATCH(Segment!$A19,Annual!$A:$A,0),MATCH(Segment!U$1,Annual!$A$1:$AC$1,0))-T19 -> -12 | V19: -13.2 | W19: =INDEX(Annual!$A:$AC,MATCH(Segment!$A19,Annual!$A:$A,0),MATCH(Segment!W$1,Annual!$A$1:$AC$1,0))-V19 -> -9.83 | X19: =X$22/V$22*V19 -> -15.074647 | Y19: =Y$22/W$22*W19 -> -11.16253 | Z19: =Z$22/X$22*X19 -> -17.227283 | AA19: =AA$22/Y$22*Y19 -> -12.89383 | AB19: =AB$22/Z$22*Z19 -> -20.051544 | AC19: =AC$22/AA$22*AA19 -> -15.244733 | AD19: =AD$22/AB$22*AB19 -> -23.865948 | AE19: =AE$22/AC$22*AC19 -> -18.051763 | ... AQ19: =AQ$22/AO$22*AO19 -> -54.069329 | AT19: -12.9 | AU19: -0.3 | AV19: -13.4 | AW19: -0.5
A20: Costs-Variable customer SaaS costs | B20: Variable customer SaaS costs | C20: AUDm | D20: AR | J20: -7.9 | K20: -9.1 | L20: -10.3 | M20: -9.2 | N20: -13.1 | O20: -8.8 | P20: -12.3 | Q20: -14.1 | R20: -17.4 | S20: -17.5 | T20: -22.6 | U20: =INDEX(Annual!$A:$AC,MATCH(Segment!$A20,Annual!$A:$A,0),MATCH(Segment!U$1,Annual!$A$1:$AC$1,0))-T20 -> -15.4 | V20: -27.5 | W20: =INDEX(Annual!$A:$AC,MATCH(Segment!$A20,Annual!$A:$A,0),MATCH(Segment!W$1,Annual!$A$1:$AC$1,0))-V20 -> -31.41 | X20: =X$22/V$22*V20 -> -31.405514 | Y20: =Y$22/W$22*W20 -> -35.66786 | Z20: =Z$22/X$22*X20 -> -35.890173 | AA20: =AA$22/Y$22*Y20 -> -41.199917 | AB20: =AB$22/Z$22*Z20 -> -41.774049 | AC20: =AC$22/AA$22*AA20 -> -48.711806 | AD20: =AD$22/AB$22*AB20 -> -49.720726 | AE20: =AE$22/AC$22*AC20 -> -57.681167 | ... AQ20: =AQ$22/AO$22*AO20 -> -172.76883 | AT20: -25.9 | AU20: -1.6 | AV20: -17.3 | AW20: -0.6
A21: Costs-Other | B21: Other | C21: AUDm | J21: 0 | K21: 0 | L21: 0 | M21: 0 | N21: 0 | O21: 0 | P21: 0 | Q21: 0 | R21: 0 | S21: 0 | T21: 0 | U21: =INDEX(Annual!$A:$AC,MATCH(Segment!$A21,Annual!$A:$A,0),MATCH(Segment!U$1,Annual!$A$1:$AC$1,0))-T21 -> 0 | V21: 0 | W21: =INDEX(Annual!$A:$AC,MATCH(Segment!$A21,Annual!$A:$A,0),MATCH(Segment!W$1,Annual!$A$1:$AC$1,0))-V21 -> 0 | X21: =X$22/V$22*V21 -> 0 | Y21: =Y$22/W$22*W21 -> 0 | Z21: =Z$22/X$22*X21 -> 0 | AA21: =AA$22/Y$22*Y21 -> 0 | AB21: =AB$22/Z$22*Z21 -> 0 | AC21: =AC$22/AA$22*AA21 -> 0 | AD21: =AD$22/AB$22*AB21 -> 0 | AE21: =AE$22/AC$22*AC21 -> 0 | ... AQ21: =AQ$22/AO$22*AO21 -> 0 | AT21: 0 | AU21: 0 | AV21: 0 | AW21: 0
B22: Cost of Sales | C22: AUDm | J22: -17.6 | K22: -19 | L22: -17.5 | M22: -21.2 | N22: -21.8 | O22: -19.5 | P22: -22.6 | Q22: -24.4 | R22: -29 | S22: -26.9 | T22: -33.8 | U22: =SUM(U19:U21) -> -27.4 | V22: =SUM(V19:V21) -> -40.7 | W22: =SUM(W19:W21) -> -41.24 | X22: =X24-X15 -> -46.48016 | Y22: =Y24-Y15 -> -46.83039 | Z22: =Z24-Z15 -> -53.117457 | AA22: =AA24-AA15 -> -54.093747 | AB22: =AB24-AB15 -> -61.825593 | AC22: =AC24-AC15 -> -63.956539 | AD22: =AD24-AD15 -> -73.586674 | AE22: =AE24-AE15 -> -75.73293 | ... AQ22: =AQ24-AQ15 -> -226.83816 | AT22: -38.8 | AU22: -1.9 | AV22: -30.7 | AW22: -1
A24: GP-Gross Profit | B24: Gross Profit | C24: AUDm | D24: Preso | J24: 111.2 | K24: 137.8 | L24: 120.7 | M24: 139.4 | N24: 122.7 | O24: 147.7 | P24: 149.7 | Q24: 172.2 | R24: 179.8 | S24: 201.6 | T24: 210.9 | U24: =INDEX(Annual!$A:$AC,MATCH(Segment!$A24,Annual!$A:$A,0),MATCH(Segment!U$1,Annual!$A$1:$AC$1,0))-T24 -> 243.3 | V24: =V15+V22 -> 250.6 | W24: =INDEX(Annual!$A:$AC,MATCH(Segment!$A24,Annual!$A:$A,0),MATCH(Segment!W$1,Annual!$A$1:$AC$1,0))-V24 -> 277.488 | X24: =X15*X25 -> 286.18988 | Y24: =Y15*Y25 -> 315.10357 | Z24: =Z15*Z25 -> 327.05736 | AA24: =AA15*AA25 -> 363.97589 | AB24: =AB15*AB25 -> 380.67552 | AC24: =AC15*AC25 -> 430.3388 | AD24: =AD15*AD25 -> 453.09142 | AE24: =AE15*AE25 -> 509.57758 | ... AQ24: =AQ15*AQ25 -> 1526.3062 | AT24: 242.2 | AU24: 8.4 | AV24: 272.7 | AW24: 9.2
B25: Gross profit margin | C25: % | D25: #VALUE! | J25: 0.863 | K25: 0.879 | L25: 0.874 | M25: 0.868 | N25: 0.849 | O25: 0.883 | P25: 0.869 | Q25: 0.876 | R25: 0.861 | S25: 0.882 | T25: 0.862 | U25: =U24/U15 -> 0.89878094 | V25: =V24/V15 -> 0.8602815 | W25: =W24/W15 -> 0.87061068 | X25: =V25 -> 0.8602815 | Y25: =W25 -> 0.87061068 | Z25: =X25 -> 0.8602815 | AA25: =Y25 -> 0.87061068 | AB25: =Z25 -> 0.8602815 | AC25: =AA25 -> 0.87061068 | AD25: =AB25 -> 0.8602815 | AE25: =AC25 -> 0.87061068 | ... AQ25: =AO25 -> 0.87061068 | AT25: 0.862 | AU25: -0.002 | AV25: 0.899 | AW25: 0
A27: Opex-Operating costs | B27: Operating costs | C27: AUDm | D27: Preso | J27: -70.6 | K27: -68.4 | L27: -71.4 | M27: -55.4 | N27: -56 | O27: -54.3 | P27: -69.2 | Q27: -58.8 | R27: -78.4 | S27: -70.2 | T27: -90.3 | U27: =INDEX(Annual!$A:$AC,MATCH(Segment!$A27,Annual!$A:$A,0),MATCH(Segment!U$1,Annual!$A$1:$AC$1,0))-T27 -> -89.8 | V27: =V30-V24 -> -101.5 | W27: =INDEX(Annual!$A:$AC,MATCH(Segment!$A27,Annual!$A:$A,0),MATCH(Segment!W$1,Annual!$A$1:$AC$1,0))-V27 -> -101.588 | X27: =X28*X15 -> -112.5882 | Y27: =Y28*Y15 -> -111.73967 | Z27: =Z28*Z15 -> -124.86387 | AA27: =AA28*AA15 -> -124.88971 | AB27: =AB28*AB15 -> -140.90919 | AC27: =AC28*AC15 -> -142.71762 | AD27: =AD28*AD15 -> -165.08095 | AE27: =AE28*AE15 -> -166.06983 | ... AQ27: =AQ28*AQ15 -> -444.82435 | AT27: -100.9 | AU27: -0.6 | AV27: -97.7 | AW27: -11.1
B28: % of sales | J28: -0.548 | K28: -0.436 | L28: -0.517 | M28: -0.345 | N28: -0.388 | O28: -0.325 | P28: -0.401 | Q28: -0.299 | R28: -0.376 | S28: -0.307 | T28: -0.369 | U28: =U27/U15 -> -0.33173255 | V28: =V27/V15 -> -0.34843804 | W28: =W27/W15 -> -0.31872945 | X28: =V28+1% -> -0.33843804 | Y28: =W28+1% -> -0.30872945 | Z28: =X28+1% -> -0.32843804 | AA28: =Y28+1% -> -0.29872945 | AB28: =Z28+1% -> -0.31843804 | AC28: =AA28+1% -> -0.28872945 | AD28: =AB28+0.5% -> -0.31343804 | AE28: =AC28+0.5% -> -0.28372945 | AF28: =AD28+0.5% -> -0.30843804 | AG28: =AE28+0.5% -> -0.27872945 | AH28: =AF28+0.5% -> -0.30343804 | AI28: =AG28+0.5% -> -0.27372945 | AJ28: =AH28+0.5% -> -0.29843804 | AK28: =AI28+0.5% -> -0.26872945 | ... AQ28: =AO28+0.5% -> -0.25372945 | AT28: -0.359 | AU28: 0.01 | AV28: -0.322 | AW28: -0.025
A30: EBITDA-EBITDAR | B30: EBITDAR | C30: AUDm | D30: Preso | J30: 40.6 | K30: 69.3 | L30: 49.3 | M30: 83.9 | N30: 66.7 | O30: 93.4 | P30: 80.6 | Q30: 113.4 | R30: 101.3 | S30: 131.4 | T30: 120.7 | U30: =INDEX(Annual!$A:$AC,MATCH(Segment!$A30,Annual!$A:$A,0),MATCH(Segment!U$1,Annual!$A$1:$AC$1,0))-T30 -> 153.4 | V30: =V38-V34 -> 149.1 | W30: =INDEX(Annual!$A:$AC,MATCH(Segment!$A30,Annual!$A:$A,0),MATCH(Segment!W$1,Annual!$A$1:$AC$1,0))-V30 -> 175.9 | X30: =X38-X34 -> 173.60169 | Y30: =Y38-Y34 -> 203.3639 | Z30: =Z38-Z34 -> 202.19349 | AA30: =AA38-AA34 -> 239.08618 | AB30: =AB38-AB34 -> 239.76633 | AC30: =AC38-AC34 -> 287.62118 | AD30: =AD38-AD34 -> 288.01047 | AE30: =AE38-AE34 -> 343.50775 | ... AQ30: =AQ38-AQ34 -> 1081.4818 | AT30: 141.4 | AU30: 7.7 | AV30: 175 | AW30: -1.9
A32: Opex-R&D- total | B32: R&D- total | C32: AUDm | D32: Preso | J32: -27.8 | K32: -32.3 | L32: -30.5 | M32: -37.6 | N32: -34.6 | O32: -42.4 | P32: -41.5 | Q32: -50.7 | R32: -49.4 | S32: -62.6 | T32: -59.9 | U32: =INDEX(Annual!$A:$AC,MATCH(Segment!$A32,Annual!$A:$A,0),MATCH(Segment!U$1,Annual!$A$1:$AC$1,0))-T32 -> -68.1 | V32: -68.8 | W32: =INDEX(Annual!$A:$AC,MATCH(Segment!$A32,Annual!$A:$A,0),MATCH(Segment!W$1,Annual!$A$1:$AC$1,0))-V32 -> -84.9 | X32: =-X35*X$15 -> -78.570885 | Y32: =-Y35*Y$15 -> -96.408829 | Z32: =-Z35*Z$15 -> -89.790689 | AA32: =-AA35*AA$15 -> -111.36176 | AB32: =-AB35*AB$15 -> -104.51108 | AC32: =-AC35*AC$15 -> -131.6661 | AD32: =-AD35*AD$15 -> -124.39222 | AE32: =-AE35*AE$15 -> -155.90994 | ... AQ32: =-AQ35*AQ$15 -> -466.98739 | AT32: -70.2 | AU32: 1.4 | AV32: -77.8 | AW32: -1.1
A33: Opex-R&D- capitalisation | B33: R&D- capitalisation | C33: AUDm | D33: AR | J33: 14 | K33: 18.1 | L33: 16 | M33: 21.1 | N33: 17.7 | O33: 24.2 | P33: 22.1 | Q33: 28 | R33: 25.7 | S33: 34.9 | T33: 30.6 | U33: =INDEX(Annual!$A:$AC,MATCH(Segment!$A33,Annual!$A:$A,0),MATCH(Segment!U$1,Annual!$A$1:$AC$1,0))-T33 -> 39.1 | V33: 37.1 | W33: =INDEX(Annual!$A:$AC,MATCH(Segment!$A33,Annual!$A:$A,0),MATCH(Segment!W$1,Annual!$A$1:$AC$1,0))-V33 -> 47.3 | X33: =-X36*X32 -> 42.368893 | Y33: =-Y36*Y32 -> 53.711868 | Z33: =-Z36*Z32 -> 48.419107 | AA33: =-AA36*AA32 -> 62.042537 | AB33: =-AB36*AB32 -> 56.35699 | AC33: =-AC36*AC32 -> 73.354614 | AD33: =-AD36*AD32 -> 67.077779 | AE33: =-AE36*AE32 -> 86.861484 | ... AQ33: =-AQ36*AQ32 -> 260.17083 | AT33: 35.8 | AU33: 1.3 | AV33: 44.8 | AW33: 0.6
B34: R&D- net | J34: -13.8 | K34: -14.2 | L34: -14.5 | M34: -16.5 | N34: -17 | O34: -18.2 | P34: -19.4 | Q34: -22.7 | R34: -23.7 | S34: -27.7 | T34: -29.4 | U34: =SUM(U32:U33) -> -29 | V34: =SUM(V32:V33) -> -31.7 | W34: =SUM(W32:W33) -> -37.6 | X34: =SUM(X32:X33) -> -36.201992 | Y34: =SUM(Y32:Y33) -> -42.696961 | Z34: =SUM(Z32:Z33) -> -41.371582 | AA34: =SUM(AA32:AA33) -> -49.319226 | AB34: =SUM(AB32:AB33) -> -48.154086 | ... AQ34: =SUM(AQ32:AQ33) -> -206.81656 | AT34: -34.4 | AU34: 2.7 | AV34: -33 | AW34: -0.5
B35: R&D % of sales | J35: 0.22 | K35: 0.21 | L35: 0.22 | M35: 0.23 | N35: 0.24 | O35: 0.25 | P35: 0.24 | Q35: 0.26 | R35: 0.24 | S35: 0.27 | T35: 0.24 | U35: =-U32/U$15 -> 0.25157 | V35: =-V32/V$15 -> 0.23618263 | W35: =-W32/W$15 -> 0.26637133 | X35: =V35 -> 0.23618263 | Y35: =W35 -> 0.26637133 | Z35: =X35 -> 0.23618263 | AA35: =Y35 -> 0.26637133 | AB35: =Z35 -> 0.23618263 | AC35: =AA35 -> 0.26637133 | AD35: =AB35 -> 0.23618263 | AE35: =AC35 -> 0.26637133 | ... AQ35: =AO35 -> 0.26637133 | AT35: 0.25 | AU35: -0.01 | AV35: 0.26 | AW35: -0.01
B36: R&D capitalisation % | C36: % | J36: 0.5 | K36: 0.56 | L36: 0.52 | M36: 0.56 | N36: 0.51 | O36: 0.57 | P36: 0.53 | Q36: 0.55 | R36: 0.52 | S36: 0.56 | T36: 0.51 | U36: =-U33/U32 -> 0.57415565 | V36: =-V33/V32 -> 0.53924419 | W36: =-W33/W32 -> 0.55712603 | X36: =V36 -> 0.53924419 | Y36: =W36 -> 0.55712603 | Z36: =X36 -> 0.53924419 | AA36: =Y36 -> 0.55712603 | AB36: =Z36 -> 0.53924419 | AC36: =AA36 -> 0.55712603 | AD36: =AB36 -> 0.53924419 | AE36: =AC36 -> 0.55712603 | ... AQ36: =AO36 -> 0.55712603 | AT36: 0.51 | AU36: 0.03 | AV36: 0.58 | AW36: 0
A38: EBITDA-EBITDA | B38: EBITDA | C38: AUDm | D38: Preso | J38: 26.8 | K38: 55.1 | L38: 34.8 | M38: 67.4 | N38: 49.7 | O38: 75.3 | P38: 61.2 | Q38: 90.7 | R38: 77.6 | S38: 103.7 | T38: 91.3 | U38: =INDEX(Annual!$A:$AC,MATCH(Segment!$A38,Annual!$A:$A,0),MATCH(Segment!U$1,Annual!$A$1:$AC$1,0))-T38 -> 124.5 | V38: 117.4 | W38: =INDEX(Annual!$A:$AC,MATCH(Segment!$A38,Annual!$A:$A,0),MATCH(Segment!W$1,Annual!$A$1:$AC$1,0))-V38 -> 138.3 | X38: =X24+X27+X34 -> 137.39969 | Y38: =Y24+Y27+Y34 -> 160.66694 | Z38: =Z24+Z27+Z34 -> 160.82191 | AA38: =AA24+AA27+AA34 -> 189.76695 | AB38: =AB24+AB27+AB34 -> 191.61225 | AC38: =AC24+AC27+AC34 -> 229.30969 | AD38: =AD24+AD27+AD34 -> 230.69603 | AE38: =AE24+AE27+AE34 -> 274.4593 | ... AQ38: =AQ24+AQ27+AQ34 -> 874.66528 | AT38: 107 | AU38: 10.4 | AV38: 142 | AW38: -2.4
B39: Growth | C39: % YoY | L39: 0.3 | M39: 0.22 | N39: 0.43 | O39: 0.12 | P39: 0.23 | Q39: 0.21 | R39: 0.27 | S39: 0.14 | T39: 0.18 | U39: =U38/S38-1 -> 0.20057859 | V39: =V38/T38-1 -> 0.28587076 | W39: =W38/U38-1 -> 0.11084337 | X39: =X38/V38-1 -> 0.17035514 | Y39: =Y38/W38-1 -> 0.16172767 | Z39: =Z38/X38-1 -> 0.17046774 | AA39: =AA38/Y38-1 -> 0.18112011 | AB39: =AB38/Z38-1 -> 0.19145611 | ... AQ39: =AQ38/AO38-1 -> 0.22204204 | AT39: 0.17 | AU39: 0.11 | AV39: 0.14 | AW39: -0.02
B40: Margin | C40: % | J40: 0.208 | K40: 0.352 | L40: 0.252 | M40: 0.42 | N40: 0.344 | O40: 0.45 | P40: 0.355 | Q40: 0.461 | R40: 0.372 | S40: 0.454 | T40: 0.373 | U40: =U38/U$15 -> 0.45991873 | V40: =V38/V$15 -> 0.40302094 | W40: =W38/W$15 -> 0.4339123 | X40: =X38/X$15 -> 0.41302094 | Y40: =Y38/Y$15 -> 0.4439123 | Z40: =Z38/Z$15 -> 0.42302094 | AA40: =AA38/AA$15 -> 0.4539123 | AB40: =AB38/AB$15 -> 0.43302094 | ... AQ40: =AQ38/AQ$15 -> 0.4989123 | AT40: 0.381 | AU40: 0.022 | AV40: 0.468 | AW40: -0.023
B41: Margin change | C41: % YoY | L41: 0.044 | M41: 0.068 | N41: 0.092 | O41: 0.03 | P41: 0.011 | Q41: 0.011 | R41: 0.017 | S41: -0.008 | T41: 0.001 | U41: =U40-S40 -> 0.0059187292 | V41: =V40-T40 -> 0.030020941 | W41: =W40-U40 -> -0.026006428 | X41: =X40-V40 -> 0.01 | Y41: =Y40-W40 -> 0.01 | Z41: =Z40-X40 -> 0.01 | AA41: =AA40-Y40 -> 0.01 | AB41: =AB40-Z40 -> 0.01 | ... AQ41: =AQ40-AO40 -> 0.005 | AT41: 0.008 | AU41: 0.022 | AV41: 0.008 | AW41: -0.023
B43: D&A
A44: D&A-Depreciation | B44: Depreciation | D44: AR | J44: -1.8 | K44: -1.9 | L44: -1.9 | M44: -2 | N44: -1.8 | O44: -1.5 | P44: -1.3 | Q44: -1.3 | R44: -1.4 | S44: -1.6 | T44: -1.9 | U44: =INDEX(Annual!$A:$AC,MATCH(Segment!$A44,Annual!$A:$A,0),MATCH(Segment!U$1,Annual!$A$1:$AC$1,0))-T44 -> -2.3 | V44: -2.3 | W44: =INDEX(Annual!$A:$AC,MATCH(Segment!$A44,Annual!$A:$A,0),MATCH(Segment!W$1,Annual!$A$1:$AC$1,0))-V44 -> -2.396 | X44: =X15/V15*V44 -> -2.626643 | Y44: =Y15/W15*W44 -> -2.7207957 | Z44: =Z15/X15*X44 -> -3.0017236 | AA44: =AA15/Y15*Y44 -> -3.142789 | AB44: =AB15/Z15*Z44 -> -3.4938296 | AC44: =AC15/AA15*AA44 -> -3.7158067 | AD44: =AD15/AB15*AB44 -> -4.1584607 | AE44: =AE15/AC15*AC44 -> -4.4000024 | ... AQ44: =AQ15/AO15*AO44 -> -13.179055 | AT44: -2.2 | AU44: -0.1 | AV44: -2.5 | AW44: -0.1
A45: D&A-R&D amortisation | B45: R&D amortisation | D45: AR | J45: 0 | K45: -0.6 | L45: -2.2 | M45: -3.9 | N45: -5.7 | O45: -7.8 | P45: -10.7 | Q45: -12.7 | R45: -16.1 | S45: -18 | T45: -21.4 | U45: =INDEX(Annual!$A:$AC,MATCH(Segment!$A45,Annual!$A:$A,0),MATCH(Segment!U$1,Annual!$A$1:$AC$1,0))-T45 -> -23.9 | V45: -25.3 | W45: =INDEX(Annual!$A:$AC,MATCH(Segment!$A45,Annual!$A:$A,0),MATCH(Segment!W$1,Annual!$A$1:$AC$1,0))-V45 -> -27.843 | X45: =W45-(W33+W45)/5/2 -> -29.7887 | Y45: =X45-(X33+X45)/5/2 -> -31.046719 | Z45: =Y45-(Y33+Y45)/5/2 -> -33.313234 | AA45: =Z45-(Z33+Z45)/5/2 -> -34.823821 | AB45: =AA45-(AA33+AA45)/5/2 -> -37.545693 | AC45: =AB45-(AB33+AB45)/5/2 -> -39.426823 | AD45: =AC45-(AC33+AC45)/5/2 -> -42.819602 | AE45: =AD45-(AD33+AD45)/5/2 -> -45.24542 | ... AQ45: =AP45-(AP33+AP45)/5/2 -> -122.15501 | AT45: -25.4 | AU45: 0.1 | AV45: -26.4 | AW45: 0
A46: D&A-Other amortisation | B46: Other amortisation | J46: -0.9 | K46: -0.9 | L46: -4.3 | M46: -4.3 | N46: -4.3 | O46: -4.8 | P46: -5.9 | Q46: -6.2 | R46: -8 | S46: -8.5 | T46: -9.2 | U46: =INDEX(Annual!$A:$AC,MATCH(Segment!$A46,Annual!$A:$A,0),MATCH(Segment!U$1,Annual!$A$1:$AC$1,0))-T46 -> -10.1 | V46: =V47-V45-V44 -> -11.3 | W46: =INDEX(Annual!$A:$AC,MATCH(Segment!$A46,Annual!$A:$A,0),MATCH(Segment!W$1,Annual!$A$1:$AC$1,0))-V46 -> -11.658 | X46: =X15/V15*V46 -> -12.904811 | Y46: =Y15/W15*W46 -> -13.238329 | Z46: =Z15/X15*X46 -> -14.747599 | AA46: =AA15/Y15*Y46 -> -15.291583 | AB46: =AB15/Z15*Z46 -> -17.165337 | AC46: =AC15/AA15*AA46 -> -18.079664 | AD46: =AD15/AB15*AB46 -> -20.430698 | AE46: =AE15/AC15*AC46 -> -21.408693 | ... AQ46: =AQ15/AO15*AO46 -> -64.124134 | AT46: -10.6 | AU46: -0.7 | AV46: -11.3 | AW46: -0.4
A47: D&A-D&A | B47: D&A | C47: AUDm | D47: AR | J47: -2.7 | K47: -3.4 | L47: -8.4 | M47: -10.2 | N47: -11.8 | O47: -14 | P47: -17.9 | Q47: -20.2 | R47: -25.5 | S47: -28 | T47: -32.6 | U47: =INDEX(Annual!$A:$AC,MATCH(Segment!$A47,Annual!$A:$A,0),MATCH(Segment!U$1,Annual!$A$1:$AC$1,0))-T47 -> -36.2 | V47: -38.9 | W47: =INDEX(Annual!$A:$AC,MATCH(Segment!$A47,Annual!$A:$A,0),MATCH(Segment!W$1,Annual!$A$1:$AC$1,0))-V47 -> -41.897 | X47: =SUM(X44:X46) -> -45.320154 | Y47: =SUM(Y44:Y46) -> -47.005844 | Z47: =SUM(Z44:Z46) -> -51.062556 | AA47: =SUM(AA44:AA46) -> -53.258194 | AB47: =SUM(AB44:AB46) -> -58.204859 | AC47: =SUM(AC44:AC46) -> -61.222293 | AD47: =SUM(AD44:AD46) -> -67.408761 | AE47: =SUM(AE44:AE46) -> -71.054115 | ... AQ47: =SUM(AQ44:AQ46) -> -199.4582 | AT47: -38.2 | AU47: -0.6 | AV47: -40.2 | AW47: -0.5
B48: D&A / Revenue | C48: % | J48: -0.021 | K48: -0.022 | L48: -0.061 | M48: -0.064 | N48: -0.082 | O48: -0.084 | P48: -0.104 | Q48: -0.103 | R48: -0.122 | S48: -0.123 | T48: -0.133 | U48: =U47/U$15 -> -0.13372737 | V48: =V47/V$15 -> -0.13353931 | W48: =W47/W$15 -> -0.13145064 | X48: =X47/X$15 -> -0.13623155 | Y48: =Y47/Y$15 -> -0.12987409 | Z48: =Z47/Z$15 -> -0.13431336 | AA48: =AA47/AA$15 -> -0.12739072 | AB48: =AB47/AB$15 -> -0.13153607 | ... AQ48: =AQ47/AQ$15 -> -0.11377169 | AT48: -0.136 | AU48: 0.003 | AV48: -0.133 | AW48: 0.003
B50: EBIT
A51: EBIT | B51: EBIT | C51: AUDm | J51: 24 | K51: 51.7 | L51: 26.4 | M51: 57.2 | N51: 37.9 | O51: 61.2 | P51: 43.3 | Q51: 70.5 | R51: 52.2 | S51: 75.7 | T51: 58.7 | U51: =INDEX(Annual!$A:$AC,MATCH(Segment!$A51,Annual!$A:$A,0),MATCH(Segment!U$1,Annual!$A$1:$AC$1,0))-T51 -> 88.3 | V51: =V38+V47 -> 78.5 | W51: =INDEX(Annual!$A:$AC,MATCH(Segment!$A51,Annual!$A:$A,0),MATCH(Segment!W$1,Annual!$A$1:$AC$1,0))-V51 -> 96.403 | X51: =X38+X47 -> 92.07954 | Y51: =Y38+Y47 -> 113.66109 | Z51: =Z38+Z47 -> 109.75935 | AA51: =AA38+AA47 -> 136.50876 | AB51: =AB38+AB47 -> 133.40739 | AC51: =AC38+AC47 -> 168.08739 | AD51: =AD38+AD47 -> 163.28727 | AE51: =AE38+AE47 -> 203.40518 | ... AQ51: =AQ38+AQ47 -> 675.20708 | AT51: 68.7 | AU51: 9.8 | AV51: 101.8 | AW51: -2.8
B52: Underlying EBIT Growth | C52: % YoY | J52: #DIV/0! | K52: #DIV/0! | L52: 0.1 | M52: 0.1 | N52: 0.43 | O52: 0.07 | P52: 0.14 | Q52: 0.15 | R52: 0.21 | S52: 0.07 | T52: 0.12 | U52: =U51/S51-1 -> 0.1664465 | V52: =V51/T51-1 -> 0.33730835 | W52: =W51/U51-1 -> 0.091766704 | X52: =X51/V51-1 -> 0.17298777 | Y52: =Y51/W51-1 -> 0.17902029 | Z52: =Z51/X51-1 -> 0.19200589 | AA52: =AA51/Y51-1 -> 0.2010157 | AB52: =AB51/Z51-1 -> 0.21545348 | ... AQ52: =AQ51/AO51-1 -> 0.22810829 | AT52: 0.17 | AU52: 0.17 | AV52: 0.15 | AW52: -0.03
B53: EBIT Margin | C53: % | J53: 0.187 | K53: 0.33 | L53: 0.191 | M53: 0.356 | N53: 0.262 | O53: 0.366 | P53: 0.251 | Q53: 0.358 | R53: 0.25 | S53: 0.331 | T53: 0.24 | U53: =U51/U$15 -> 0.32619136 | V53: =V51/V$15 -> 0.26948163 | W53: =W51/W$15 -> 0.30246166 | X53: =X51/X$15 -> 0.27678939 | Y53: =Y51/Y$15 -> 0.31403821 | Z53: =Z51/Z$15 -> 0.28870758 | AA53: =AA51/AA$15 -> 0.32652158 | AB53: =AB51/AB$15 -> 0.30148487 | ... AQ53: =AQ51/AQ$15 -> 0.38514061 | AT53: 0.245 | AU53: 0.025 | AV53: 0.336 | AW53: -0.02
B55: Interest
A56: Interest income | B56: Interest income | C56: AUDm | D56: AR | J56: 0.4 | K56: 0.2 | L56: 0.2 | M56: 0.1 | N56: 0.1 | O56: 0.1 | P56: 0.1 | Q56: 0.3 | R56: 1.6 | S56: 2.5 | T56: 3.8 | U56: =INDEX(Annual!$A:$AC,MATCH(Segment!$A56,Annual!$A:$A,0),MATCH(Segment!U$1,Annual!$A$1:$AC$1,0))-T56 -> 4.6 | V56: 5.2 | W56: =INDEX(Annual!$A:$AC,MATCH(Segment!$A56,Annual!$A:$A,0),MATCH(Segment!W$1,Annual!$A$1:$AC$1,0))-V56 -> 4.95 | X56: =INDEX(Annual!$A:$AC,MATCH(Segment!$A56,Annual!$A:$A,0),MATCH(Segment!X$1,Annual!$A$1:$AC$1,0))*0.5 -> 5.4222528 | Y56: =INDEX(Annual!$A:$AC,MATCH(Segment!$A56,Annual!$A:$A,0),MATCH(Segment!Y$1,Annual!$A$1:$AC$1,0))-X56 -> 5.4222528 | Z56: =INDEX(Annual!$A:$AC,MATCH(Segment!$A56,Annual!$A:$A,0),MATCH(Segment!Z$1,Annual!$A$1:$AC$1,0))*0.5 -> 5.8895476 | AA56: =INDEX(Annual!$A:$AC,MATCH(Segment!$A56,Annual!$A:$A,0),MATCH(Segment!AA$1,Annual!$A$1:$AC$1,0))-Z56 -> 5.8895476 | AB56: =INDEX(Annual!$A:$AC,MATCH(Segment!$A56,Annual!$A:$A,0),MATCH(Segment!AB$1,Annual!$A$1:$AC$1,0))*0.5 -> 7.0907646 | AC56: =INDEX(Annual!$A:$AC,MATCH(Segment!$A56,Annual!$A:$A,0),MATCH(Segment!AC$1,Annual!$A$1:$AC$1,0))-AB56 -> 7.0907646 | AD56: =INDEX(Annual!$A:$AC,MATCH(Segment!$A56,Annual!$A:$A,0),MATCH(Segment!AD$1,Annual!$A$1:$AC$1,0))*0.5 -> 8.4274547 | AE56: =INDEX(Annual!$A:$AC,MATCH(Segment!$A56,Annual!$A:$A,0),MATCH(Segment!AE$1,Annual!$A$1:$AC$1,0))-AD56 -> 8.4274547 | AF56: =INDEX(Annual!$A:$AC,MATCH(Segment!$A56,Annual!$A:$A,0),MATCH(Segment!AF$1,Annual!$A$1:$AC$1,0))*0.5 -> 8.5461018 | AG56: =INDEX(Annual!$A:$AC,MATCH(Segment!$A56,Annual!$A:$A,0),MATCH(Segment!AG$1,Annual!$A$1:$AC$1,0))-AF56 -> 8.5461018 | AH56: =INDEX(Annual!$A:$AC,MATCH(Segment!$A56,Annual!$A:$A,0),MATCH(Segment!AH$1,Annual!$A$1:$AC$1,0))*0.5 -> 8.6757429 | AI56: =INDEX(Annual!$A:$AC,MATCH(Segment!$A56,Annual!$A:$A,0),MATCH(Segment!AI$1,Annual!$A$1:$AC$1,0))-AH56 -> 8.6757429 | AJ56: =INDEX(Annual!$A:$AC,MATCH(Segment!$A56,Annual!$A:$A,0),MATCH(Segment!AJ$1,Annual!$A$1:$AC$1,0))*0.5 -> 8.8187069 | AK56: =INDEX(Annual!$A:$AC,MATCH(Segment!$A56,Annual!$A:$A,0),MATCH(Segment!AK$1,Annual!$A$1:$AC$1,0))-AJ56 -> 8.8187069 | AL56: =INDEX(Annual!$A:$AC,MATCH(Segment!$A56,Annual!$A:$A,0),MATCH(Segment!AL$1,Annual!$A$1:$AC$1,0))*0.5 -> 9.0023592 | AM56: =INDEX(Annual!$A:$AC,MATCH(Segment!$A56,Annual!$A:$A,0),MATCH(Segment!AM$1,Annual!$A$1:$AC$1,0))-AL56 -> 9.0023592 | AN56: =INDEX(Annual!$A:$AC,MATCH(Segment!$A56,Annual!$A:$A,0),MATCH(Segment!AN$1,Annual!$A$1:$AC$1,0))*0.5 -> 9.2760063 | AO56: =INDEX(Annual!$A:$AC,MATCH(Segment!$A56,Annual!$A:$A,0),MATCH(Segment!AO$1,Annual!$A$1:$AC$1,0))-AN56 -> 9.2760063 | AP56: =INDEX(Annual!$A:$AC,MATCH(Segment!$A56,Annual!$A:$A,0),MATCH(Segment!AP$1,Annual!$A$1:$AC$1,0))*0.5 -> 9.6817985 | AQ56: =INDEX(Annual!$A:$AC,MATCH(Segment!$A56,Annual!$A:$A,0),MATCH(Segment!AQ$1,Annual!$A$1:$AC$1,0))-AP56 -> 9.6817985 | AT56: 5.6 | AU56: -0.3 | AV56: 5.6 | AW56: 0.3
A57: Interest expense | B57: Interest expense | C57: AUDm | J57: 0 | K57: 0 | L57: -0.7 | M57: -0.8 | N57: -0.7 | O57: -0.8 | P57: -0.8 | Q57: -1 | R57: -1 | S57: -1.1 | T57: -1 | U57: =INDEX(Annual!$A:$AC,MATCH(Segment!$A57,Annual!$A:$A,0),MATCH(Segment!U$1,Annual!$A$1:$AC$1,0))-T57 -> -1.6 | V57: -1.9 | W57: =INDEX(Annual!$A:$AC,MATCH(Segment!$A57,Annual!$A:$A,0),MATCH(Segment!W$1,Annual!$A$1:$AC$1,0))-V57 -> -1.611 | X57: =INDEX(Annual!$A:$AC,MATCH(Segment!$A57,Annual!$A:$A,0),MATCH(Segment!X$1,Annual!$A$1:$AC$1,0))*0.5 -> -1.7555 | Y57: =INDEX(Annual!$A:$AC,MATCH(Segment!$A57,Annual!$A:$A,0),MATCH(Segment!Y$1,Annual!$A$1:$AC$1,0))-X57 -> -1.7555 | Z57: =INDEX(Annual!$A:$AC,MATCH(Segment!$A57,Annual!$A:$A,0),MATCH(Segment!Z$1,Annual!$A$1:$AC$1,0))*0.5 -> -1.7555 | AA57: =INDEX(Annual!$A:$AC,MATCH(Segment!$A57,Annual!$A:$A,0),MATCH(Segment!AA$1,Annual!$A$1:$AC$1,0))-Z57 -> -1.7555 | AB57: =INDEX(Annual!$A:$AC,MATCH(Segment!$A57,Annual!$A:$A,0),MATCH(Segment!AB$1,Annual!$A$1:$AC$1,0))*0.5 -> -1.7555 | AC57: =INDEX(Annual!$A:$AC,MATCH(Segment!$A57,Annual!$A:$A,0),MATCH(Segment!AC$1,Annual!$A$1:$AC$1,0))-AB57 -> -1.7555 | AD57: =INDEX(Annual!$A:$AC,MATCH(Segment!$A57,Annual!$A:$A,0),MATCH(Segment!AD$1,Annual!$A$1:$AC$1,0))*0.5 -> -1.7555 | AE57: =INDEX(Annual!$A:$AC,MATCH(Segment!$A57,Annual!$A:$A,0),MATCH(Segment!AE$1,Annual!$A$1:$AC$1,0))-AD57 -> -1.7555 | AF57: =INDEX(Annual!$A:$AC,MATCH(Segment!$A57,Annual!$A:$A,0),MATCH(Segment!AF$1,Annual!$A$1:$AC$1,0))*0.5 -> -1.7555 | AG57: =INDEX(Annual!$A:$AC,MATCH(Segment!$A57,Annual!$A:$A,0),MATCH(Segment!AG$1,Annual!$A$1:$AC$1,0))-AF57 -> -1.7555 | AH57: =INDEX(Annual!$A:$AC,MATCH(Segment!$A57,Annual!$A:$A,0),MATCH(Segment!AH$1,Annual!$A$1:$AC$1,0))*0.5 -> -1.7555 | AI57: =INDEX(Annual!$A:$AC,MATCH(Segment!$A57,Annual!$A:$A,0),MATCH(Segment!AI$1,Annual!$A$1:$AC$1,0))-AH57 -> -1.7555 | AJ57: =INDEX(Annual!$A:$AC,MATCH(Segment!$A57,Annual!$A:$A,0),MATCH(Segment!AJ$1,Annual!$A$1:$AC$1,0))*0.5 -> -1.7555 | AK57: =INDEX(Annual!$A:$AC,MATCH(Segment!$A57,Annual!$A:$A,0),MATCH(Segment!AK$1,Annual!$A$1:$AC$1,0))-AJ57 -> -1.7555 | AL57: =INDEX(Annual!$A:$AC,MATCH(Segment!$A57,Annual!$A:$A,0),MATCH(Segment!AL$1,Annual!$A$1:$AC$1,0))*0.5 -> -1.7555 | AM57: =INDEX(Annual!$A:$AC,MATCH(Segment!$A57,Annual!$A:$A,0),MATCH(Segment!AM$1,Annual!$A$1:$AC$1,0))-AL57 -> -1.7555 | AN57: =INDEX(Annual!$A:$AC,MATCH(Segment!$A57,Annual!$A:$A,0),MATCH(Segment!AN$1,Annual!$A$1:$AC$1,0))*0.5 -> -1.7555 | AO57: =INDEX(Annual!$A:$AC,MATCH(Segment!$A57,Annual!$A:$A,0),MATCH(Segment!AO$1,Annual!$A$1:$AC$1,0))-AN57 -> -1.7555 | AP57: =INDEX(Annual!$A:$AC,MATCH(Segment!$A57,Annual!$A:$A,0),MATCH(Segment!AP$1,Annual!$A$1:$AC$1,0))*0.5 -> -1.7555 | AQ57: =INDEX(Annual!$A:$AC,MATCH(Segment!$A57,Annual!$A:$A,0),MATCH(Segment!AQ$1,Annual!$A$1:$AC$1,0))-AP57 -> -1.7555 | AT57: -1 | AU57: -0.9 | AV57: -1 | AW57: -1.1
A58: Net Interest | B58: Net Interest | C58: AUDm | D58: Preso | J58: 0.4 | K58: 0.2 | L58: -0.5 | M58: -0.6 | N58: -0.6 | O58: -0.7 | P58: -0.7 | Q58: -0.7 | R58: 0.6 | S58: 1.4 | T58: 2.9 | U58: =INDEX(Annual!$A:$AC,MATCH(Segment!$A58,Annual!$A:$A,0),MATCH(Segment!U$1,Annual!$A$1:$AC$1,0))-T58 -> 2.9 | V58: 3.4 | W58: =INDEX(Annual!$A:$AC,MATCH(Segment!$A58,Annual!$A:$A,0),MATCH(Segment!W$1,Annual!$A$1:$AC$1,0))-V58 -> 3.239 | X58: =INDEX(Annual!$A:$AC,MATCH(Segment!$A58,Annual!$A:$A,0),MATCH(Segment!X$1,Annual!$A$1:$AC$1,0))*0.5 -> 4.4 | Y58: =INDEX(Annual!$A:$AC,MATCH(Segment!$A58,Annual!$A:$A,0),MATCH(Segment!Y$1,Annual!$A$1:$AC$1,0))-X58 -> 4.4 | Z58: =INDEX(Annual!$A:$AC,MATCH(Segment!$A58,Annual!$A:$A,0),MATCH(Segment!Z$1,Annual!$A$1:$AC$1,0))*0.5 -> 5.55 | AA58: =INDEX(Annual!$A:$AC,MATCH(Segment!$A58,Annual!$A:$A,0),MATCH(Segment!AA$1,Annual!$A$1:$AC$1,0))-Z58 -> 5.55 | AB58: =INDEX(Annual!$A:$AC,MATCH(Segment!$A58,Annual!$A:$A,0),MATCH(Segment!AB$1,Annual!$A$1:$AC$1,0))*0.5 -> 6.85 | AC58: =INDEX(Annual!$A:$AC,MATCH(Segment!$A58,Annual!$A:$A,0),MATCH(Segment!AC$1,Annual!$A$1:$AC$1,0))-AB58 -> 6.85 | AD58: =INDEX(Annual!$A:$AC,MATCH(Segment!$A58,Annual!$A:$A,0),MATCH(Segment!AD$1,Annual!$A$1:$AC$1,0))*0.5 -> 8.3 | AE58: =INDEX(Annual!$A:$AC,MATCH(Segment!$A58,Annual!$A:$A,0),MATCH(Segment!AE$1,Annual!$A$1:$AC$1,0))-AD58 -> 8.3 | AF58: =INDEX(Annual!$A:$AC,MATCH(Segment!$A58,Annual!$A:$A,0),MATCH(Segment!AF$1,Annual!$A$1:$AC$1,0))*0.5 -> 8.4 | AG58: =INDEX(Annual!$A:$AC,MATCH(Segment!$A58,Annual!$A:$A,0),MATCH(Segment!AG$1,Annual!$A$1:$AC$1,0))-AF58 -> 8.4 | AH58: =INDEX(Annual!$A:$AC,MATCH(Segment!$A58,Annual!$A:$A,0),MATCH(Segment!AH$1,Annual!$A$1:$AC$1,0))*0.5 -> 8.5 | AI58: =INDEX(Annual!$A:$AC,MATCH(Segment!$A58,Annual!$A:$A,0),MATCH(Segment!AI$1,Annual!$A$1:$AC$1,0))-AH58 -> 8.5 | AJ58: =INDEX(Annual!$A:$AC,MATCH(Segment!$A58,Annual!$A:$A,0),MATCH(Segment!AJ$1,Annual!$A$1:$AC$1,0))*0.5 -> 8.65 | AK58: =INDEX(Annual!$A:$AC,MATCH(Segment!$A58,Annual!$A:$A,0),MATCH(Segment!AK$1,Annual!$A$1:$AC$1,0))-AJ58 -> 8.65 | AL58: =INDEX(Annual!$A:$AC,MATCH(Segment!$A58,Annual!$A:$A,0),MATCH(Segment!AL$1,Annual!$A$1:$AC$1,0))*0.5 -> 8.9 | AM58: =INDEX(Annual!$A:$AC,MATCH(Segment!$A58,Annual!$A:$A,0),MATCH(Segment!AM$1,Annual!$A$1:$AC$1,0))-AL58 -> 8.9 | AN58: =INDEX(Annual!$A:$AC,MATCH(Segment!$A58,Annual!$A:$A,0),MATCH(Segment!AN$1,Annual!$A$1:$AC$1,0))*0.5 -> 9.4 | AO58: =INDEX(Annual!$A:$AC,MATCH(Segment!$A58,Annual!$A:$A,0),MATCH(Segment!AO$1,Annual!$A$1:$AC$1,0))-AN58 -> 9.4 | AP58: =INDEX(Annual!$A:$AC,MATCH(Segment!$A58,Annual!$A:$A,0),MATCH(Segment!AP$1,Annual!$A$1:$AC$1,0))*0.5 -> 10.15 | AQ58: =INDEX(Annual!$A:$AC,MATCH(Segment!$A58,Annual!$A:$A,0),MATCH(Segment!AQ$1,Annual!$A$1:$AC$1,0))-AP58 -> 10.15 | AT58: 4.6 | AU58: -1.2 | AV58: 4.6 | AW58: -0.8
B59: Interest expense rate
B61: PBT
A62: PBTSoftware | B62: Software | P62: 29.6 | Q62: 47.9 | R62: 37.2 | S62: 60.5 | T62: 47 | U62: =INDEX(Annual!$A:$AC,MATCH(Segment!$A62,Annual!$A:$A,0),MATCH(Segment!U$1,Annual!$A$1:$AC$1,0))-T62 -> 85 | V62: 68.6 | W62: =INDEX(Annual!$A:$AC,MATCH(Segment!$A62,Annual!$A:$A,0),MATCH(Segment!W$1,Annual!$A$1:$AC$1,0))-V62 -> 93.571
A63: PBTConsulting | B63: Consulting | P63: 6.7 | Q63: 10.1 | R63: 5 | S63: 8.8 | T63: 6.1 | U63: =INDEX(Annual!$A:$AC,MATCH(Segment!$A63,Annual!$A:$A,0),MATCH(Segment!U$1,Annual!$A$1:$AC$1,0))-T63 -> 0.6 | V63: 5.9 | W63: =INDEX(Annual!$A:$AC,MATCH(Segment!$A63,Annual!$A:$A,0),MATCH(Segment!W$1,Annual!$A$1:$AC$1,0))-V63 -> 2.882
A64: PBTCorporate | B64: Corporate | P64: 6.2 | Q64: 11.8 | R64: 10.5 | S64: 7.7 | T64: 8.5 | U64: =INDEX(Annual!$A:$AC,MATCH(Segment!$A64,Annual!$A:$A,0),MATCH(Segment!U$1,Annual!$A$1:$AC$1,0))-T64 -> 5.7 | V64: 7.4 | W64: =INDEX(Annual!$A:$AC,MATCH(Segment!$A64,Annual!$A:$A,0),MATCH(Segment!W$1,Annual!$A$1:$AC$1,0))-V64 -> 3.193
A65: PBT | B65: PBT | C65: AUDm | J65: 24.5 | K65: 51.9 | L65: 25.9 | M65: 56.5 | N65: 37.3 | O65: 60.6 | P65: 42.6 | Q65: 69.8 | R65: 52.7 | S65: 77.1 | T65: 61.5 | U65: =INDEX(Annual!$A:$AC,MATCH(Segment!$A65,Annual!$A:$A,0),MATCH(Segment!U$1,Annual!$A$1:$AC$1,0))-T65 -> 91.4 | V65: =SUM(V62:V64) -> 81.9 | W65: =INDEX(Annual!$A:$AC,MATCH(Segment!$A65,Annual!$A:$A,0),MATCH(Segment!W$1,Annual!$A$1:$AC$1,0))-V65 -> 99.646 | X65: =X51+X58 -> 96.47954 | Y65: =Y51+Y58 -> 118.06109 | Z65: =Z51+Z58 -> 115.30935 | AA65: =AA51+AA58 -> 142.05876 | AB65: =AB51+AB58 -> 140.25739 | AC65: =AC51+AC58 -> 174.93739 | AD65: =AD51+AD58 -> 171.58727 | AE65: =AE51+AE58 -> 211.70518 | ... AQ65: =AQ51+AQ58 -> 685.35708 | AT65: 73.3 | AU65: 8.6 | AV65: 106.4 | AW65: -3.6
B66: Growth | C66: % YoY | J66: #DIV/0! | K66: #DIV/0! | L66: 0.06 | M66: 0.089 | N66: 0.438 | O66: 0.071 | P66: 0.142 | Q66: 0.152 | R66: 0.239 | S66: 0.105 | T66: 0.166 | U66: =U65/S65-1 -> 0.18547341 | V66: =V65/T65-1 -> 0.33170732 | W66: =W65/U65-1 -> 0.090218818 | X66: =X65/V65-1 -> 0.17801636 | Y66: =Y65/W65-1 -> 0.18480514 | Z66: =Z65/X65-1 -> 0.19516898 | AA66: =AA65/Y65-1 -> 0.20326479 | AB66: =AB65/Z65-1 -> 0.21635743 | ... AQ66: =AQ65/AO65-1 -> 0.22561503 | AT66: 0.151 | AU66: 0.18 | AV66: 0.123 | AW66: 0.002
B67: PBT Margin | C67: % | J67: 0.19 | K67: 0.331 | L67: 0.188 | M67: 0.352 | N67: 0.258 | O67: 0.362 | P67: 0.247 | Q67: 0.355 | R67: 0.253 | S67: 0.337 | T67: 0.251 | U67: =U65/U$15 -> 0.33764315 | V67: =V65/V$15 -> 0.28115345 | W67: =W65/W$15 -> 0.31263648 | X67: =X65/X$15 -> 0.29001571 | Y67: =Y65/Y$15 -> 0.32619512 | Z67: =Z65/Z$15 -> 0.30330613 | AA67: =AA65/AA$15 -> 0.33979688 | AB67: =AB65/AB$15 -> 0.31696505 | ... AQ67: =AQ65/AQ$15 -> 0.39093021 | AT67: 0.261 | AU67: 0.02 | AV67: 0.351 | AW67: -0.023
B69: Tax
A70: Tax expense | B70: Tax expense | C70: AUDm | D70: AR | J70: -6.6 | K70: -11.4 | L70: -6.9 | M70: -12.6 | N70: -9.1 | O70: -16.1 | P70: -9.4 | Q70: -14.1 | R70: -11.5 | S70: -15.5 | T70: -13.5 | U70: =INDEX(Annual!$A:$AC,MATCH(Segment!$A70,Annual!$A:$A,0),MATCH(Segment!U$1,Annual!$A$1:$AC$1,0))-T70 -> -21.4 | V70: -18.9 | W70: =INDEX(Annual!$A:$AC,MATCH(Segment!$A70,Annual!$A:$A,0),MATCH(Segment!W$1,Annual!$A$1:$AC$1,0))-V70 -> -25.001 | X70: =-X65*X71 -> -22.286774 | Y70: =-Y65*Y71 -> -29.621313 | Z70: =-Z65*Z71 -> -26.636461 | AA70: =-AA65*AA71 -> -35.642283 | AB70: =-AB65*AB71 -> -32.399457 | AC70: =-AC65*AC71 -> -43.891474 | AD70: =-AD65*AD71 -> -39.63666 | AE70: =-AE65*AE71 -> -53.116445 | ... AQ70: =-AQ65*AQ71 -> -171.95484 | AT70: -16.7 | AU70: -2.2 | AV70: -24.3 | AW70: 0.5
A71: Underlying Tax rate | B71: Underlying Tax rate | C71: % | J71: 0.268 | K71: 0.219 | L71: 0.266 | M71: 0.224 | N71: 0.244 | O71: 0.265 | P71: 0.22 | Q71: 0.202 | R71: 0.217 | S71: 0.201 | T71: 0.22 | U71: =-U70/U65 -> 0.23413567 | V71: =-V70/V65 -> 0.23076923 | W71: =-W70/W65 -> 0.25089818 | X71: 0.231 | Y71: =W71 -> 0.25089818 | Z71: =X71 -> 0.231 | AA71: =Y71 -> 0.25089818 | AB71: =Z71 -> 0.231 | AC71: =AA71 -> 0.25089818 | AD71: =AB71 -> 0.231 | AE71: =AC71 -> 0.25089818 | AF71: =AD71 -> 0.231 | ... AQ71: =AO71 -> 0.25089818 | AT71: 0.228 | AU71: 0.003 | AV71: 0.228 | AW71: 0.003
B73: NPAT
A74: Statutory NPAT | B74: Statutory NPAT | C74: AUDm | D74: Preso | J74: 17.9 | K74: 40.5 | L74: 19.1 | M74: 43.9 | N74: 28.2 | O74: 44.5 | P74: 33.2 | Q74: 55.7 | R74: 41.3 | S74: 61.6 | T74: 48 | U74: =INDEX(Annual!$A:$AC,MATCH(Segment!$A74,Annual!$A:$A,0),MATCH(Segment!U$1,Annual!$A$1:$AC$1,0))-T74 -> 70 | V74: =V65+V70 -> 63 | W74: =INDEX(Annual!$A:$AC,MATCH(Segment!$A74,Annual!$A:$A,0),MATCH(Segment!W$1,Annual!$A$1:$AC$1,0))-V74 -> 74.645 | X74: =X65+X70 -> 74.192766 | Y74: =Y65+Y70 -> 88.43978 | Z74: =Z65+Z70 -> 88.672893 | AA74: =AA65+AA70 -> 106.41647 | AB74: =AB65+AB70 -> 107.85793 | AC74: =AC65+AC70 -> 131.04592 | AD74: =AD65+AD70 -> 131.95061 | AE74: =AE65+AE70 -> 158.58874 | ... AQ74: =AQ65+AQ70 -> 513.40224 | AT74: 56.6 | AU74: 6.4 | AV74: 82.1 | AW74: -3.1
A75: Significant items after tax | B75: Significant items after tax | J75: 0 | K75: 0 | L75: 0 | M75: 0 | N75: 0 | O75: 0 | P75: 0 | Q75: 0 | R75: 0 | S75: 0 | T75: 0 | U75: =INDEX(Annual!$A:$AC,MATCH(Segment!$A75,Annual!$A:$A,0),MATCH(Segment!U$1,Annual!$A$1:$AC$1,0))-T75 -> 0 | V75: 0 | W75: =INDEX(Annual!$A:$AC,MATCH(Segment!$A75,Annual!$A:$A,0),MATCH(Segment!W$1,Annual!$A$1:$AC$1,0))-V75 -> 0 | X75: 0 | Y75: 0 | Z75: 0 | AA75: 0 | AB75: 0 | AC75: 0 | AD75: 0 | AE75: 0 | AF75: 0 | AG75: 0 | AH75: 0 | AI75: 0 | AJ75: 0 | AK75: 0 | AL75: 0 | AM75: 0 | AN75: 0 | AO75: 0 | AP75: 0 | AQ75: 0 | AT75: 0 | AU75: 0 | AV75: 0 | AW75: 0
A76: Underlying NPAT | B76: Underlying NPAT | C76: AUDm | J76: 17.9 | K76: 40.5 | L76: 19.1 | M76: 43.9 | N76: 28.2 | O76: 44.5 | P76: 33.2 | Q76: 55.7 | R76: 41.3 | S76: 61.6 | T76: 48 | U76: =INDEX(Annual!$A:$AC,MATCH(Segment!$A76,Annual!$A:$A,0),MATCH(Segment!U$1,Annual!$A$1:$AC$1,0))-T76 -> 70 | V76: =V74+V75 -> 63 | W76: =INDEX(Annual!$A:$AC,MATCH(Segment!$A76,Annual!$A:$A,0),MATCH(Segment!W$1,Annual!$A$1:$AC$1,0))-V76 -> 74.645 | X76: =X74+X75 -> 74.192766 | Y76: =Y74+Y75 -> 88.43978 | Z76: =Z74+Z75 -> 88.672893 | AA76: =AA74+AA75 -> 106.41647 | AB76: =AB74+AB75 -> 107.85793 | AC76: =AC74+AC75 -> 131.04592 | AD76: =AD74+AD75 -> 131.95061 | AE76: =AE74+AE75 -> 158.58874 | ... AQ76: =AQ74+AQ75 -> 513.40224 | AT76: 56.6 | AU76: 6.4 | AV76: 82.1 | AW76: -3.1
B77: Underlying NPAT Growth | C77: % YoY | J77: #DIV/0! | K77: #DIV/0! | L77: 0.063 | M77: 0.083 | N77: 0.48 | O77: 0.014 | P77: 0.177 | Q77: 0.251 | R77: 0.244 | S77: 0.107 | T77: 0.163 | U77: =U76/S76-1 -> 0.13636364 | V77: =V76/T76-1 -> 0.3125 | W77: =W76/U76-1 -> 0.066357143 | X77: =X76/V76-1 -> 0.17766295 | Y77: =Y76/W76-1 -> 0.18480514 | Z77: =Z76/X76-1 -> 0.19516898 | AA77: =AA76/Y76-1 -> 0.20326479 | AB77: =AB76/Z76-1 -> 0.21635743 | ... AQ77: =AQ76/AO76-1 -> 0.22561503 | AT77: 0.179 | AU77: 0.134 | AV77: 0.173 | AW77: -0.044
B78: Underlying NPAT margin | C78: % | J78: 0.139 | K78: 0.259 | L78: 0.138 | M78: 0.273 | N78: 0.195 | O78: 0.266 | P78: 0.193 | Q78: 0.283 | R78: 0.198 | S78: 0.27 | T78: 0.196 | U78: =U76/U$15 -> 0.25858884 | V78: =V76/V$15 -> 0.21627188 | W78: =W76/W$15 -> 0.23419656 | X78: =X76/X$15 -> 0.22302208 | Y78: =Y76/Y$15 -> 0.24435336 | Z78: =Z76/Z$15 -> 0.23324241 | AA78: =AA76/AA$15 -> 0.25454246 | AB78: =AB76/AB$15 -> 0.24374613 | ... AQ78: =AQ76/AQ$15 -> 0.29284653 | AT78: 0.201 | AU78: 0.015 | AV78: 0.271 | AW78: -0.019
B80: Operating metrics
A82: KPIARR | B82: ARR
A83: KPISaaS ARR | B83: SaaS ARR | C83: AUDm | D83: Preso | H83: 59.3 | I83: 70 | J83: 82.7 | K83: 102 | L83: 110.2 | M83: 135 | N83: 155.8 | O83: 192 | P83: 225 | Q83: 274 | R83: 316.3 | S83: 384 | T83: 423.6 | U83: =INDEX(Annual!$A:$AC,MATCH(Segment!$A83,Annual!$A:$A,0),MATCH(Segment!U$1,Annual!$A$1:$AC$1,0)) -> 470.2 | V83: 511.1 | W83: =INDEX(Annual!$A:$AC,MATCH(Segment!$A83,Annual!$A:$A,0),MATCH(Segment!W$1,Annual!$A$1:$AC$1,0)) -> 554.6 | X83: =X85-X84 -> 599.42 | Y83: =Y85-Y84 -> 652.04015 | Z83: =Z85-Z84 -> 714.02238 | AA83: =AA85-AA84 -> 778.44057 | AB83: =AB85-AB84 -> 867.77932 | AC83: =AC85-AC84 -> 947.64014 | AD83: =AD85-AD84 -> 1050.3115 | AE83: =AE85-AE84 -> 1148.3851 | ... AQ83: =AQ85-AQ84 -> 3706.43 | AT83: 499 | AU83: 12.1 | AV83: 554.7 | AW83: 10.2
A84: KPIAnnual licence ARR | B84: Annual licence ARR | C84: AUDm | H84: -59.3 | I84: 103.5 | J84: 102 | K84: 100.8 | L84: 101.4 | M84: 87.4 | N84: 77.9 | O84: 65.2 | P84: 63.4 | Q84: 46.5 | R84: 34.3 | S84: 9 | T84: 0 | U84: =INDEX(Annual!$A:$AC,MATCH(Segment!$A84,Annual!$A:$A,0),MATCH(Segment!U$1,Annual!$A$1:$AC$1,0)) -> 0 | V84: 0 | W84: =INDEX(Annual!$A:$AC,MATCH(Segment!$A84,Annual!$A:$A,0),MATCH(Segment!W$1,Annual!$A$1:$AC$1,0)) -> 0 | X84: 0 | Y84: 0 | Z84: 0 | AA84: 0 | AB84: 0 | AC84: 0 | AD84: 0 | AE84: 0 | AF84: 0 | AG84: 0 | AH84: 0 | AI84: 0 | AJ84: 0 | AK84: 0 | AL84: 0 | AM84: 0 | AN84: 0 | AO84: 0 | AP84: 0 | AQ84: 0 | AT84: 0 | AU84: 0 | AV84: 0 | AW84: 0
A85: KPITotal ARR | B85: Total ARR | C85: AUDm | D85: Preso | I85: 174 | J85: 184.7 | K85: 202 | L85: 211.6 | M85: 222 | N85: 233.7 | O85: 257 | P85: 288.5 | Q85: 321 | R85: 350.6 | S85: 393 | T85: 423.6 | U85: =INDEX(Annual!$A:$AC,MATCH(Segment!$A85,Annual!$A:$A,0),MATCH(Segment!U$1,Annual!$A$1:$AC$1,0)) -> 470.2 | V85: 511.1 | W85: =INDEX(Annual!$A:$AC,MATCH(Segment!$A85,Annual!$A:$A,0),MATCH(Segment!W$1,Annual!$A$1:$AC$1,0)) -> 554.6 | X85: =X122 -> 599.42 | Y85: =Y122 -> 652.04015 | Z85: =Z122 -> 714.02238 | AA85: =AA122 -> 778.44057 | AB85: =AB122 -> 867.77932 | AC85: =AC122 -> 947.64014 | AD85: =AD122 -> 1050.3115 | AE85: =AE122 -> 1148.3851 | ... AQ85: =AQ122 -> 3706.43 | AT85: 499 | AU85: 12.1 | AV85: 554.7 | AW85: 10.2
B86: Growth | C86: % YoY | K86: 0.16 | L86: 0.15 | M86: 0.1 | N86: 0.1 | O86: 0.16 | P86: 0.23 | Q86: 0.25 | R86: 0.22 | S86: 0.23 | T86: 0.21 | U86: =U85/S85-1 -> 0.19643766 | V86: =V85/T85-1 -> 0.2065628 | W86: =W85/U85-1 -> 0.17949809 | X86: =X85/V85-1 -> 0.17280376 | Y86: =Y85/W85-1 -> 0.17569446 | Z86: =Z85/X85-1 -> 0.19118877 | AA86: =AA85/Y85-1 -> 0.19385373 | AB86: =AB85/Z85-1 -> 0.21533911 | ... AQ86: =AQ85/AO85-1 -> 0.21891436 | AT86: 0.18 | AU86: 0.03 | AV86: 0.18 | AW86: 0.02
B87: Growth exc SaaS-flip, assume 2x | C87: % YoY | K87: 0.15 | L87: 0.14 | M87: 0.03 | N87: -0.01 | O87: 0.06 | P87: 0.17 | Q87: 0.17 | R87: 0.11 | S87: 0.11 | T87: 0.11 | U87: =(U85+(U84-S84))/S85-1 -> 0.1735369 | V87: =(V85+(V84-T84))/T85-1 -> 0.2065628 | W87: =(W85+(W84-U84))/U85-1 -> 0.17949809 | X87: =(X85+(X84-V84))/V85-1 -> 0.17280376 | Y87: =(Y85+(Y84-W84))/W85-1 -> 0.17569446 | Z87: =(Z85+(Z84-X84))/X85-1 -> 0.19118877 | AA87: =(AA85+(AA84-Y84))/Y85-1 -> 0.19385373 | AB87: =(AB85+(AB84-Z84))/Z85-1 -> 0.21533911 | ... AQ87: =(AQ85+(AQ84-AO84))/AO85-1 -> 0.21891436 | AT87: 0.18 | AU87: 0.03 | AV87: 0.18 | AW87: 0.02
B88: SaaS ARR growth | C88: % YoY | K88: 0.44 | L88: 0.33 | M88: 0.32 | N88: 0.41 | O88: 0.43 | P88: 0.44 | Q88: 0.43 | R88: 0.41 | S88: 0.4 | T88: 0.34 | U88: =U83/S83-1 -> 0.22447917 | V88: =V83/T83-1 -> 0.2065628 | W88: =W83/U83-1 -> 0.17949809 | X88: =X83/V83-1 -> 0.17280376 | Y88: =Y83/W83-1 -> 0.17569446 | Z88: =Z83/X83-1 -> 0.19118877 | AA88: =AA83/Y83-1 -> 0.19385373 | AB88: =AB83/Z83-1 -> 0.21533911 | ... AQ88: =AQ83/AO83-1 -> 0.21891436 | AT88: 0.18 | AU88: 0.03 | AV88: 0.18 | AW88: 0.02
B89: Annual licence ARR growth | C89: % YoY | L89: -0.01 | M89: -0.13 | N89: -0.23 | O89: -0.25 | P89: -0.19 | Q89: -0.29 | R89: -0.46 | S89: -0.81 | T89: -1
A91: KPIUK ARR | B91: UK ARR | C91: AUDm | I91: 0 | K91: 0 | M91: 7.9 | O91: 9 | P91: 17.7 | Q91: 17.5 | R91: 21.2 | S91: 26.5 | T91: 28.8 | U91: =INDEX(Annual!$A:$AC,MATCH(Segment!$A91,Annual!$A:$A,0),MATCH(Segment!U$1,Annual!$A$1:$AC$1,0)) -> 34.7 | V91: 43.1 | W91: =INDEX(Annual!$A:$AC,MATCH(Segment!$A91,Annual!$A:$A,0),MATCH(Segment!W$1,Annual!$A$1:$AC$1,0)) -> 51.8
A92: KPIUK PBT | B92: UK Revenue | C92: AUDm | P92: NR | R92: NR | T92: NR | V92: NR
A93: KPIUK PBT | B93: UK PBT | C93: AUDm | P93: 2.3 | Q93: 2.4 | R93: 3 | S93: 3.7 | T93: 1 | U93: =INDEX(Annual!$A:$AC,MATCH(Segment!$A93,Annual!$A:$A,0),MATCH(Segment!U$1,Annual!$A$1:$AC$1,0))-T93 -> 1.9 | V93: 1.1 | W93: =INDEX(Annual!$A:$AC,MATCH(Segment!$A93,Annual!$A:$A,0),MATCH(Segment!W$1,Annual!$A$1:$AC$1,0))-V93 -> -1.1
A94: KPIUK margin (PBT) | B94: UK margin (PBT)
A96: KPINRR | B96: NRR | C96: % | D96: Target 115% | F96: 1.1 | G96: 1.13 | H96: 1.14 | I96: 1.1 | J96: 1.1 | K96: 1.14 | L96: 1.11 | M96: 1.07 | N96: 1.08 | O96: 1.12 | P96: 1.14 | Q96: 1.16 | R96: 1.19 | S96: 1.19 | T96: 1.17 | U96: =INDEX(Annual!$A:$AC,MATCH(Segment!$A96,Annual!$A:$A,0),MATCH(Segment!U$1,Annual!$A$1:$AC$1,0)) -> 1.17 | V96: 1.18 | W96: =INDEX(Annual!$A:$AC,MATCH(Segment!$A96,Annual!$A:$A,0),MATCH(Segment!W$1,Annual!$A$1:$AC$1,0)) -> 1.15
A97: KPIChurn | B97: Churn | C97: % | D97: Target 1% | I97: 0.01 | K97: 0.005 | M97: 0.008 | O97: 0.014 | P97: 0.001 | Q97: 0.006 | R97: 0.016 | S97: 0.01 | T97: 0.016 | U97: =INDEX(Annual!$A:$AC,MATCH(Segment!$A97,Annual!$A:$A,0),MATCH(Segment!U$1,Annual!$A$1:$AC$1,0))*2-T97 -> 0.01 | V97: 0.003 | W97: =INDEX(Annual!$A:$AC,MATCH(Segment!$A97,Annual!$A:$A,0),MATCH(Segment!W$1,Annual!$A$1:$AC$1,0))*2-V97 -> 0.021
B98: Customer/user growth | C98: % YoY | K98: 0.024 | L98: 0.035 | M98: 0.026 | N98: 0.025 | O98: 0.04 | P98: 0.094 | Q98: 0.085 | R98: 0.025 | S98: 0.035 | T98: 0.038 | U98: =(1+U86)/U96-1 -> 0.02259629 | V98: =(1+V86)/V96-1 -> 0.022510843 | W98: =(1+W86)/W96-1 -> 0.025650509
A100: KPIProducts per customer | B100: Products per customer | C100: # | D100: Preso | I100: 5.1 | J100: 5.5 | K100: 5.4 | L100: 5.6 | M100: 5.5 | N100: 5.8 | O100: 5.9 | P100: 6 | Q100: 6.2 | R100: 6.5 | S100: 6.7 | T100: 6.8 | U100: =INDEX(Annual!$A:$AC,MATCH(Segment!$A100,Annual!$A:$A,0),MATCH(Segment!U$1,Annual!$A$1:$AC$1,0)) -> NR | V100: 7 | W100: =INDEX(Annual!$A:$AC,MATCH(Segment!$A100,Annual!$A:$A,0),MATCH(Segment!W$1,Annual!$A$1:$AC$1,0)) -> NR | X100: 7.7 | Y100: #VALUE! | Z100: 8.5 | AA100: #VALUE! | AB100: 9.4 | AC100: #VALUE! | AD100: 10.3 | AE100: #VALUE! | AF100: 11.3 | AG100: #VALUE! | AH100: 12.5 | AI100: #VALUE! | AJ100: 13.7 | AK100: #VALUE! | AL100: 15.1 | AM100: #VALUE! | AN100: 16.6 | AO100: #VALUE! | AP100: 18.2 | AQ100: #VALUE! | AT100: 7.3 | AU100: -0.3 | AV100: #VALUE! | AW100: #VALUE!
A101: KPIProducts per customer inc T&S | B101: Products per customer inc T&S | I101: 0 | K101: 0 | M101: 0 | O101: 0 | P101: 5.4 | Q101: 5.5 | R101: 5.6 | S101: 0 | T101: NR | U101: =INDEX(Annual!$A:$AC,MATCH(Segment!$A101,Annual!$A:$A,0),MATCH(Segment!U$1,Annual!$A$1:$AC$1,0)) -> 0 | V101: NR | W101: =INDEX(Annual!$A:$AC,MATCH(Segment!$A101,Annual!$A:$A,0),MATCH(Segment!W$1,Annual!$A$1:$AC$1,0)) -> 0
A102: KPISaaS customers | B102: SaaS customers | C102: # | D102: Preso | H102: 280 | I102: 345 | J102: 389 | K102: 435 | L102: 475 | M102: 539 | N102: 576 | O102: 637 | P102: 714 | Q102: 810 | R102: 903 | S102: NR | T102: NR | U102: =INDEX(Annual!$A:$AC,MATCH(Segment!$A102,Annual!$A:$A,0),MATCH(Segment!U$1,Annual!$A$1:$AC$1,0)) -> NR | V102: NR | W102: =INDEX(Annual!$A:$AC,MATCH(Segment!$A102,Annual!$A:$A,0),MATCH(Segment!W$1,Annual!$A$1:$AC$1,0)) -> NR
A103: KPISaas ARR per customer | B103: Saas ARR per customer | C103: AUDm | H103: 0.21 | I103: 0.2 | J103: 0.21 | K103: 0.23 | L103: 0.23 | M103: 0.25 | N103: 0.27 | O103: 0.3 | P103: 0.32 | Q103: 0.34 | R103: 0.35 | T103: #VALUE! | V103: #VALUE!
B105: ARR
V106: =V107-T107 -> 14.3 | W106: =W107-U107 -> 17.1 | X106: =X107-V107 -> 19.395 | Y106: =Y107-W107 -> 23.31 | Z106: =Z107-X107 -> 24.998 | AA106: =AA107-Y107 -> 30.044 | AB106: =AB107-Z107 -> 30.62255 | AC106: =AC107-AA107 -> 36.8039
B107: UK ARR | H107: 4.9 | I107: 5.4 | J107: 5.9 | K107: 6.5 | L107: 7.2 | M107: 7.9 | N107: 8.5 | O107: 9 | P107: 17.7 | Q107: 17.5 | R107: 21.2 | S107: 26.5 | T107: 28.8 | U107: =U91 -> 34.7 | V107: =V91 -> 43.1 | W107: =W91 -> 51.8 | X107: =V107*(1+X108) -> 62.495 | Y107: =W107*(1+Y108) -> 75.11 | Z107: =X107*(1+Z108) -> 87.493 | AA107: =Y107*(1+AA108) -> 105.154 | AB107: =Z107*(1+AB108) -> 118.11555 | AC107: =AA107*(1+AC108) -> 141.9579 | AD107: =AB107*(1+AD108) -> 153.55022 | AE107: =AC107*(1+AE108) -> 184.54527 | ... AQ107: =AO107*(1+AQ108) -> 890.76477 | AT107: 38.9 | AU107: 4.2 | AV107: 46.8 | AW107: 5.2
B108: Growth | C108: % YoY | O108: 0.14 | Q108: 0.94 | R108: 0.2 | S108: 0.51 | T108: 0.36 | U108: =U107/S107-1 -> 0.30943396 | V108: =V107/T107-1 -> 0.49652778 | W108: =W107/U107-1 -> 0.49279539 | X108: 0.45 | Y108: 0.45 | Z108: 0.4 | AA108: 0.4 | AB108: 0.35 | AC108: 0.35 | AD108: 0.3 | AE108: 0.3 | AF108: 0.3 | AG108: 0.3 | AH108: 0.3 | AI108: 0.3 | AJ108: 0.3 | AK108: 0.3 | AL108: 0.3 | AM108: 0.3 | AN108: 0.3 | AO108: 0.3 | AP108: 0.3 | AQ108: 0.3 | AT108: 0.35 | AU108: 0.15 | AV108: 0.35 | AW108: 0.15
J109: 0.061 | K109: 0.096
B110: Non-UK ARR | H110: -4.9 | I110: 168.5 | J110: 178.8 | K110: 196 | L110: 204.4 | M110: 214 | N110: 225.3 | O110: 248.5 | P110: 270.8 | Q110: 303.2 | R110: 329.4 | S110: 366.4 | T110: 394.8 | U110: =U85-U107 -> 435.5 | V110: =V85-V107 -> 468 | W110: =W85-W107 -> 502.8 | X110: =V110*(1+X116)+X112+X113 -> 536.925 | Y110: =W110*(1+Y116)+Y112+Y113 -> 576.93015 | Z110: =X110*(1+Z116)+Z112+Z113 -> 626.52938 | AA110: =Y110*(1+AA116)+AA112+AA113 -> 673.28657 | AB110: =Z110*(1+AB116)+AB112+AB113 -> 749.66377 | AC110: =AA110*(1+AC116)+AC112+AC113 -> 805.68224 | AD110: =AB110*(1+AD116)+AD112+AD113 -> 896.7613 | AE110: =AC110*(1+AE116)+AE112+AE113 -> 963.83984 | ... AQ110: =AO110*(1+AQ116)+AQ112+AQ113 -> 2815.6652 | AT110: 460.1 | AU110: 7.9 | AV110: 507.8 | AW110: 4.9
B111: Growth | C111: % YoY | K111: 0.16 | L111: 0.14 | M111: 0.09 | N111: 0.1 | O111: 0.16 | P111: 0.2 | Q111: 0.22 | R111: 0.22 | S111: 0.21 | T111: 0.2 | U111: =U110/S110-1 -> 0.1885917 | V111: =V110/T110-1 -> 0.18541033 | W111: =W110/U110-1 -> 0.15453502 | X111: =X110/V110-1 -> 0.14727564 | Y111: =Y110/W110-1 -> 0.14743467 | Z111: =Z110/X110-1 -> 0.16688434 | AA111: =AA110/Y110-1 -> 0.16701574 | AB111: =AB110/Z110-1 -> 0.19653411 | ... AQ111: =AQ110/AO110-1 -> 0.19532753 | AT111: 0.17 | AU111: 0.02 | AV111: 0.17 | AW111: 0.01
B112: SaaS flip | C112: AUDm | K112: 2.7 | L112: 0.7 | M112: 13.5 | N112: 23.4 | O112: 22.2 | P112: 14.5 | Q112: 18.7 | R112: 29.1 | S112: 37.5 | T112: 34.3 | U112: =U84-S84 -> -9 | V112: =V84-T84 -> 0 | W112: =W84-U84 -> 0 | X112: =X84-V84 -> 0 | Y112: =Y84-W84 -> 0 | Z112: =Z84-X84 -> 0 | AA112: =AA84-Y84 -> 0 | AB112: =AB84-Z84 -> 0 | ... AQ112: =AQ84-AO84 -> 0 | AT112: 0 | AU112: 0 | AV112: 0 | AW112: 0
B113: SaaS Plus | R113: 0.4 | S113: -0.9 | T113: -2.5 | U113: =-(U9-S9) -> -4.8 | V113: =-(V9-T9) -> -6.3 | W113: =-(W9-U9) -> -4.766 | X113: =-(X9-V9)/4*2 -> 1.065 | Y113: =-(Y9-W9)/4*2 -> 1.22415 | Z113: =-(Z9-X9)/4*2 -> 1.01175 | AA113: =-(AA9-Y9)/4*2 -> 1.1629425 | AB113: =-(AB9-Z9)/4*2 -> 0.9611625 | AC113: =-(AC9-AA9)/4*2 -> 1.1047954 | AD113: =-(AD9-AB9)/4*2 -> 0.91310437 | AE113: =-(AE9-AC9)/4*2 -> 1.0495556 | ... AQ113: =-(AQ9-AO9)/4*2 -> 0.77151981 | AT113: 2.2 | AU113: -8.5 | AV113: 2.7 | AW113: -3.8
B115: SaaS flip pre FY24 /Saas + post FY24 | K115: 0.016 | L115: 0.004 | M115: 0.069 | N115: 0.115 | O115: 0.104 | P115: 0.065 | Q115: 0.075 | R115: 0.109 | S115: 0.121 | T115: 0.096 | U115: 0.011 | V115: =(V112+V113)/T110 -> -0.015957447 | W115: =(W112+W113)/U110 -> -0.010943743 | X115: =(X112+X113)/V110 -> 0.002275641 | Y115: =(Y112+Y113)/W110 -> 0.0024346659 | Z115: =(Z112+Z113)/X110 -> 0.0018843414 | AA115: =(AA112+AA113)/Y110 -> 0.0020157423 | AB115: =(AB112+AB113)/Z110 -> 0.001534106 | AC115: =(AC112+AC113)/AA110 -> 0.0016408992 | ... AQ115: =(AQ112+AQ113)/AO110 -> 0.00032753144 | AT115: 0.006 | AU115: -0.022 | AV115: 0.006 | AW115: -0.009
B116: Growth exc SaaS-flip @2x | C116: % YoY | K116: 0.147 | L116: 0.139 | M116: 0.024 | N116: -0.013 | O116: 0.058 | P116: 0.138 | Q116: 0.145 | R116: 0.109 | S116: 0.085 | T116: 0.102 | U116: 0.164 | V116: =((V$110-T$110)-(V112+V113))/T$110 -> 0.20136778 | W116: =((W$110-U$110)-(W112+W113))/U$110 -> 0.16547876 | X116: =SUM(X117:X120) -> 0.145 | Y116: =SUM(Y117:Y120) -> 0.145 | Z116: =SUM(Z117:Z120) -> 0.165 | AA116: =SUM(AA117:AA120) -> 0.165 | AB116: =SUM(AB117:AB120) -> 0.195 | AC116: =SUM(AC117:AC120) -> 0.195 | AD116: =SUM(AD117:AD120) -> 0.195 | AE116: =SUM(AE117:AE120) -> 0.195 | ... AQ116: =SUM(AQ117:AQ120) -> 0.195 | AT116: 0.16 | AU116: 0.042 | AV116: 0.16 | AW116: 0.02
B117: Price | C117: % YoY | X117: 0.05 | Y117: 0.05 | Z117: 0.06 | AA117: 0.06 | AB117: 0.08 | AC117: 0.08 | AD117: 0.08 | AE117: 0.08 | AF117: 0.08 | AG117: 0.08 | AH117: 0.08 | AI117: 0.08 | AJ117: 0.08 | AK117: 0.08 | AL117: 0.08 | AM117: 0.08 | AN117: 0.08 | AO117: 0.08 | AP117: 0.08 | AQ117: 0.08 | AT117: 0.04 | AU117: -0.04 | AV117: 0.04 | AW117: 0
B118: Customers (Logos) | C118: % YoY | X118: 0 | Y118: 0 | Z118: 0 | AA118: 0 | AB118: 0 | AC118: 0 | AD118: 0 | AE118: 0 | AF118: 0 | AG118: 0 | AH118: 0 | AI118: 0 | AJ118: 0 | AK118: 0 | AL118: 0 | AM118: 0 | AN118: 0 | AO118: 0 | AP118: 0 | AQ118: 0 | AT118: 0.02 | AU118: -0.02 | AV118: 0.02 | AW118: 0
B119: Users per customer (rateable properties, students) | C119: % YoY | X119: 0.015 | Y119: 0.015 | Z119: 0.015 | AA119: 0.015 | AB119: 0.015 | AC119: 0.015 | AD119: 0.015 | AE119: 0.015 | AF119: 0.015 | AG119: 0.015 | AH119: 0.015 | AI119: 0.015 | AJ119: 0.015 | AK119: 0.015 | AL119: 0.015 | AM119: 0.015 | AN119: 0.015 | AO119: 0.015 | AP119: 0.015 | AQ119: 0.015 | AT119: 0.02 | AU119: -0.02 | AV119: 0.02 | AW119: 0
B120: Products per customer | C120: % YoY | K120: 0.06 | L120: 0.02 | M120: 0.02 | N120: 0.04 | O120: 0.07 | P120: 0.03 | Q120: 0.05 | R120: 0.08 | S120: 0.08 | T120: 0.04 | U120: #VALUE! | V120: 0.04 | W120: #VALUE! | X120: 0.08 | Y120: 0.08 | Z120: 0.09 | AA120: 0.09 | AB120: 0.1 | AC120: 0.1 | AD120: 0.1 | AE120: 0.1 | AF120: 0.1 | AG120: 0.1 | AH120: 0.1 | AI120: 0.1 | AJ120: 0.1 | AK120: 0.1 | AL120: 0.1 | AM120: 0.1 | AN120: 0.1 | AO120: 0.1 | AP120: 0.1 | AQ120: 0.1 | AT120: 0.08 | AU120: -0.04 | AV120: 0.08 | AW120: 0.02
B122: Total ARR | I122: 173.9 | J122: 184.7 | K122: 202.5 | L122: 211.6 | M122: 221.9 | N122: 233.7 | O122: 257.5 | P122: 288.5 | Q122: 320.7 | R122: 350.6 | S122: 392.9 | T122: 423.6 | U122: =U107+U110 -> 470.2 | V122: =V107+V110 -> 511.1 | W122: =W107+W110 -> 554.6 | X122: =X107+X110 -> 599.42 | Y122: =Y107+Y110 -> 652.04015 | Z122: =Z107+Z110 -> 714.02238 | AA122: =AA107+AA110 -> 778.44057 | AB122: =AB107+AB110 -> 867.77932 | ... AQ122: =AQ107+AQ110 -> 3706.43 | AT122: 499 | AU122: 12.1 | AV122: 554.7 | AW122: 10.2
...
