Workbook

Sheet Model
B2: Item | C2: Source/notes | D2: Units | E2: FY-5 | F2: FY-4 | G2: FY-3 | H2: FY-2 | I2: FY-1 | J2: FY0 | K2: FY1 | L2: FY2 | M2: FY3 | N2: FY4 | O2: FY5 | P2: FY6 | Q2: FY7 | R2: FY8 | S2: FY9 | T2: FY10 | V2: Guidance | Y2: FY-2 | Z2: FY-2 | AA2: FY-1 | AB2: FY-1 | AC2: FY0 | AD2: FY0 | AE2: ="FY"&RIGHT(AC2,1)+1 -> FY1 | AF2: ="FY"&RIGHT(AD2,1)+1 -> FY1 | AG2: ="FY"&RIGHT(AE2,1)+1 -> FY2 | AH2: ="FY"&RIGHT(AF2,1)+1 -> FY2 | AI2: ="FY"&RIGHT(AG2,1)+1 -> FY3 | AJ2: ="FY"&RIGHT(AH2,1)+1 -> FY3 | AK2: ="FY"&RIGHT(AI2,1)+1 -> FY4 | AL2: ="FY"&RIGHT(AJ2,1)+1 -> FY4 | ... AX2: ="FY"&RIGHT(AV2,1)+1 -> FY10
B3: FY end | D3: June | E3: 2019 | F3: =E3+1 -> 2020 | G3: =F3+1 -> 2021 | H3: =G3+1 -> 2022 | I3: =H3+1 -> 2023 | J3: =I3+1 -> 2024 | K3: =J3+1 -> 2025 | L3: =K3+1 -> 2026 | M3: =L3+1 -> 2027 | ... T3: =S3+1 -> 2034 | V3: 2025 | W3: LT taget | Y3: ="1H"&RIGHT(INDEX($B$3:$T$3,1,MATCH(Y$2,$B$2:$T$2,0)),2) -> 1H22 | Z3: ="2H"&RIGHT(INDEX($B$3:$T$3,1,MATCH(Z$2,$B$2:$T$2,0)),2) -> 2H22 | AA3: ="1H"&RIGHT(INDEX($B$3:$T$3,1,MATCH(AA$2,$B$2:$T$2,0)),2) -> 1H23 | AB3: ="2H"&RIGHT(INDEX($B$3:$T$3,1,MATCH(AB$2,$B$2:$T$2,0)),2) -> 2H23 | AC3: ="1H"&RIGHT(INDEX($B$3:$T$3,1,MATCH(AC$2,$B$2:$T$2,0)),2) -> 1H24 | AD3: ="2H"&RIGHT(INDEX($B$3:$T$3,1,MATCH(AD$2,$B$2:$T$2,0)),2) -> 2H24 | AE3: ="1H"&RIGHT(INDEX($B$3:$T$3,1,MATCH(AE$2,$B$2:$T$2,0)),2) -> 1H25 | AF3: ="2H"&RIGHT(INDEX($B$3:$T$3,1,MATCH(AF$2,$B$2:$T$2,0)),2) -> 2H25 | AG3: ="1H"&RIGHT(INDEX($B$3:$T$3,1,MATCH(AG$2,$B$2:$T$2,0)),2) -> 1H26 | AH3: ="2H"&RIGHT(INDEX($B$3:$T$3,1,MATCH(AH$2,$B$2:$T$2,0)),2) -> 2H26 | AI3: ="1H"&RIGHT(INDEX($B$3:$T$3,1,MATCH(AI$2,$B$2:$T$2,0)),2) -> 1H27 | AJ3: ="2H"&RIGHT(INDEX($B$3:$T$3,1,MATCH(AJ$2,$B$2:$T$2,0)),2) -> 2H27 | AK3: ="1H"&RIGHT(INDEX($B$3:$T$3,1,MATCH(AK$2,$B$2:$T$2,0)),2) -> 1H28 | AL3: ="2H"&RIGHT(INDEX($B$3:$T$3,1,MATCH(AL$2,$B$2:$T$2,0)),2) -> 2H28 | AM3: ="1H"&RIGHT(INDEX($B$3:$T$3,1,MATCH(AM$2,$B$2:$T$2,0)),2) -> 1H29 | AN3: ="2H"&RIGHT(INDEX($B$3:$T$3,1,MATCH(AN$2,$B$2:$T$2,0)),2) -> 2H29 | AO3: ="1H"&RIGHT(INDEX($B$3:$T$3,1,MATCH(AO$2,$B$2:$T$2,0)),2) -> 1H30 | AP3: ="2H"&RIGHT(INDEX($B$3:$T$3,1,MATCH(AP$2,$B$2:$T$2,0)),2) -> 2H30 | AQ3: ="1H"&RIGHT(INDEX($B$3:$T$3,1,MATCH(AQ$2,$B$2:$T$2,0)),2) -> 1H31 | AR3: ="2H"&RIGHT(INDEX($B$3:$T$3,1,MATCH(AR$2,$B$2:$T$2,0)),2) -> 2H31 | AS3: ="1H"&RIGHT(INDEX($B$3:$T$3,1,MATCH(AS$2,$B$2:$T$2,0)),2) -> 1H32 | AT3: ="2H"&RIGHT(INDEX($B$3:$T$3,1,MATCH(AT$2,$B$2:$T$2,0)),2) -> 2H32 | AU3: ="1H"&RIGHT(INDEX($B$3:$T$3,1,MATCH(AU$2,$B$2:$T$2,0)),2) -> 1H33 | AV3: ="2H"&RIGHT(INDEX($B$3:$T$3,1,MATCH(AV$2,$B$2:$T$2,0)),2) -> 2H33 | AW3: ="1H"&RIGHT(INDEX($B$3:$T$3,1,MATCH(AW$2,$B$2:$T$2,0)),2) -> 1H34 | AX3: ="2H"&RIGHT(INDEX($B$3:$T$3,1,MATCH(AX$2,$B$2:$T$2,0)),2) -> 2H34
B4: Default units | D4: USDm
B5: Power equipment | E5: 6791.514 | F5: 8729.841 | G5: 11960.891 | H5: 12329.071 | I5: 12794.548 | J5: 13722.888 | K5: =SUMIF($Y$2:$AX$2,K$2,$Y5:$AX5) -> 14834.058 | L5: =SUMIF($Y$2:$AX$2,L$2,$Y5:$AX5) -> 16725.1 | M5: =SUMIF($Y$2:$AX$2,M$2,$Y5:$AX5) -> 18391.925 | N5: =SUMIF($Y$2:$AX$2,N$2,$Y5:$AX5) -> 20317.049 | O5: =SUMIF($Y$2:$AX$2,O$2,$Y5:$AX5) -> 22513.408 | P5: =SUMIF($Y$2:$AX$2,P$2,$Y5:$AX5) -> 24999.973 | Q5: =SUMIF($Y$2:$AX$2,Q$2,$Y5:$AX5) -> 27801.278 | R5: =SUMIF($Y$2:$AX$2,R$2,$Y5:$AX5) -> 30947.203 | ... T5: =SUMIF($Y$2:$AX$2,T$2,$Y5:$AX5) -> 38419.231 | Y5: 6561.632 | Z5: 5767.439 | AA5: 6450.231 | AB5: 6344.317 | AC5: 6884.453 | AD5: 6838.435 | AE5: 7425.059 | AF5: =AF30 -> 7408.9987 | AG5: =AG30 -> 8354.5477 | AH5: =AH30 -> 8370.5522 | AI5: =AI30 -> 9174.3134 | AJ5: =AJ30 -> 9217.6114 | AK5: =AK30 -> 10122.992 | AL5: =AL30 -> 10194.057 | AM5: =AM30 -> 11206.482 | ... AX5: =AX30 -> 19362.633
B6: Floor care | E6: 875.207 | F6: 1082.1 | G6: 1242.27 | H6: 924.846 | I6: 936.863 | J6: 898.728 | K6: =SUMIF($Y$2:$AX$2,K$2,$Y6:$AX6) -> 832.0977 | L6: =SUMIF($Y$2:$AX$2,L$2,$Y6:$AX6) -> 790.49281 | M6: =SUMIF($Y$2:$AX$2,M$2,$Y6:$AX6) -> 750.96817 | N6: =SUMIF($Y$2:$AX$2,N$2,$Y6:$AX6) -> 713.41977 | O6: =SUMIF($Y$2:$AX$2,O$2,$Y6:$AX6) -> 677.74878 | P6: =SUMIF($Y$2:$AX$2,P$2,$Y6:$AX6) -> 643.86134 | Q6: =SUMIF($Y$2:$AX$2,Q$2,$Y6:$AX6) -> 611.66827 | R6: =SUMIF($Y$2:$AX$2,R$2,$Y6:$AX6) -> 581.08486 | ... T6: =SUMIF($Y$2:$AX$2,T$2,$Y6:$AX6) -> 524.42908 | Y6: 471.974 | Z6: 452.872 | AA6: 429.233 | AB6: 507.63 | AC6: 427.535 | AD6: 471.193 | AE6: 408.024 | AF6: =AF33 -> 424.0737 | AG6: =AG33 -> 387.6228 | AH6: =AH33 -> 402.87002 | AI6: =AI33 -> 368.24166 | AJ6: =AJ33 -> 382.72651 | AK6: =AK33 -> 349.82958 | AL6: =AL33 -> 363.59019 | AM6: =AM33 -> 332.3381 | ... AX6: =AX33 -> 267.2722
K7: =SUMIF($Y$2:$AX$2,K$2,$Y7:$AX7) -> 0 | L7: =SUMIF($Y$2:$AX$2,L$2,$Y7:$AX7) -> 0 | M7: =SUMIF($Y$2:$AX$2,M$2,$Y7:$AX7) -> 0 | N7: =SUMIF($Y$2:$AX$2,N$2,$Y7:$AX7) -> 0 | O7: =SUMIF($Y$2:$AX$2,O$2,$Y7:$AX7) -> 0 | P7: =SUMIF($Y$2:$AX$2,P$2,$Y7:$AX7) -> 0 | Q7: =SUMIF($Y$2:$AX$2,Q$2,$Y7:$AX7) -> 0 | R7: =SUMIF($Y$2:$AX$2,R$2,$Y7:$AX7) -> 0 | ... T7: =SUMIF($Y$2:$AX$2,T$2,$Y7:$AX7) -> 0
K8: =SUMIF($Y$2:$AX$2,K$2,$Y8:$AX8) -> 0 | L8: =SUMIF($Y$2:$AX$2,L$2,$Y8:$AX8) -> 0 | M8: =SUMIF($Y$2:$AX$2,M$2,$Y8:$AX8) -> 0 | N8: =SUMIF($Y$2:$AX$2,N$2,$Y8:$AX8) -> 0 | O8: =SUMIF($Y$2:$AX$2,O$2,$Y8:$AX8) -> 0 | P8: =SUMIF($Y$2:$AX$2,P$2,$Y8:$AX8) -> 0 | Q8: =SUMIF($Y$2:$AX$2,Q$2,$Y8:$AX8) -> 0 | R8: =SUMIF($Y$2:$AX$2,R$2,$Y8:$AX8) -> 0 | ... T8: =SUMIF($Y$2:$AX$2,T$2,$Y8:$AX8) -> 0
B11: Other | E11: =E12-SUM(E5:E10) -> 0 | F11: =F12-SUM(F5:F10) -> 0 | G11: =G12-SUM(G5:G10) -> 0 | H11: =H12-SUM(H5:H10) -> 0 | I11: =I12-SUM(I5:I10) -> 0 | J11: =J12-SUM(J5:J10) -> 0 | K11: =SUMIF($Y$2:$AX$2,K$2,$Y11:$AX11) -> 0 | L11: =SUMIF($Y$2:$AX$2,L$2,$Y11:$AX11) -> 0 | M11: =SUMIF($Y$2:$AX$2,M$2,$Y11:$AX11) -> 0 | N11: =SUMIF($Y$2:$AX$2,N$2,$Y11:$AX11) -> 0 | O11: =SUMIF($Y$2:$AX$2,O$2,$Y11:$AX11) -> 0 | P11: =SUMIF($Y$2:$AX$2,P$2,$Y11:$AX11) -> 0 | Q11: =SUMIF($Y$2:$AX$2,Q$2,$Y11:$AX11) -> 0 | R11: =SUMIF($Y$2:$AX$2,R$2,$Y11:$AX11) -> 0 | ... T11: =SUMIF($Y$2:$AX$2,T$2,$Y11:$AX11) -> 0 | Y11: =Y12-SUM(Y5:Y10) -> 0 | Z11: =Z12-SUM(Z5:Z10) -> 0 | AA11: =AA12-SUM(AA5:AA10) -> 0 | AB11: =AB12-SUM(AB5:AB10) -> 0 | AC11: =AC12-SUM(AC5:AC10) -> 0 | AD11: =AD12-SUM(AD5:AD10) -> 0 | AE11: =AE12-SUM(AE5:AE10) -> 0
B12: Revenue | E12: 7666.721 | F12: 9811.941 | G12: 13203.161 | H12: 13253.917 | I12: 13731.411 | J12: 14621.616 | K12: =SUMIF($Y$2:$AX$2,K$2,$Y12:$AX12) -> 15666.155 | L12: =SUMIF($Y$2:$AX$2,L$2,$Y12:$AX12) -> 17515.593 | M12: =SUMIF($Y$2:$AX$2,M$2,$Y12:$AX12) -> 19142.893 | N12: =SUMIF($Y$2:$AX$2,N$2,$Y12:$AX12) -> 21030.469 | O12: =SUMIF($Y$2:$AX$2,O$2,$Y12:$AX12) -> 23191.157 | P12: =SUMIF($Y$2:$AX$2,P$2,$Y12:$AX12) -> 25643.835 | Q12: =SUMIF($Y$2:$AX$2,Q$2,$Y12:$AX12) -> 28412.947 | R12: =SUMIF($Y$2:$AX$2,R$2,$Y12:$AX12) -> 31528.288 | ... T12: =SUMIF($Y$2:$AX$2,T$2,$Y12:$AX12) -> 38943.66 | Y12: 7033.606 | Z12: 6220.311 | AA12: 6879.464 | AB12: 6851.947 | AC12: 7311.988 | AD12: 7309.628 | AE12: 7833.083 | AF12: =SUM(AF5:AF11) -> 7833.0724 | AG12: =SUM(AG5:AG11) -> 8742.1705 | AH12: =SUM(AH5:AH11) -> 8773.4222 | AI12: =SUM(AI5:AI11) -> 9542.5551 | AJ12: =SUM(AJ5:AJ11) -> 9600.3379 | AK12: =SUM(AK5:AK11) -> 10472.822 | AL12: =SUM(AL5:AL11) -> 10557.648 | AM12: =SUM(AM5:AM11) -> 11538.82 | ... AX12: =SUM(AX5:AX11) -> 19629.905
B13: Growth | F13: =F12/E12-1 -> 0.27980932 | G13: =G12/F12-1 -> 0.34562173 | H13: =H12/G12-1 -> 0.0038442309 | I13: =I12/H12-1 -> 0.036026633 | J13: =J12/I12-1 -> 0.064829827 | K13: =K12/J12-1 -> 0.071438024 | L13: =L12/K12-1 -> 0.11805305 | M13: =M12/L12-1 -> 0.092905803 | ... T13: =T12/S12-1 -> 0.11188219 | AA13: =AA12/Y12-1 -> -0.021915075 | AB13: =AB12/Z12-1 -> 0.10154412 | AC13: =AC12/AA12-1 -> 0.062871759 | AD13: =AD12/AB12-1 -> 0.066795759 | AE13: =AE12/AC12-1 -> 0.071265845 | AF13: =AF12/AD12-1 -> 0.071610259 | AG13: =AG12/AE12-1 -> 0.11605743 | AH13: =AH12/AF12-1 -> 0.12004867 | ... AX13: =AX12/AV12-1 -> 0.11250684
B14: =B5 -> Power equipment | F14: =F5/E5-1 -> 0.28540426 | G14: =G5/F5-1 -> 0.37011556 | H14: =H5/G5-1 -> 0.030781988 | I14: =I5/H5-1 -> 0.037754426 | J14: =J5/I5-1 -> 0.072557467 | K14: =K5/J5-1 -> 0.080971998 | L14: =L5/K5-1 -> 0.12747977 | M14: =M5/L5-1 -> 0.099660083 | ... T14: =T5/S5-1 -> 0.11447448 | AA14: =AA5/Y5-1 -> -0.016977636 | AB14: =AB5/Z5-1 -> 0.10002325 | AC14: =AC5/AA5-1 -> 0.067318829 | AD14: =AD5/AB5-1 -> 0.077883561 | AE14: =AE5/AC5-1 -> 0.078525629 | AF14: =AF5/AD5-1 -> 0.083434829 | AG14: =AG5/AE5-1 -> 0.12518267 | AH14: =AH5/AF5-1 -> 0.12978185 | ... AX14: =AX5/AV5-1 -> 0.11513994
B15: =B6 -> Floor care | F15: =F6/E6-1 -> 0.23639322 | G15: =G6/F6-1 -> 0.14801774 | H15: =H6/G6-1 -> -0.25551933 | I15: =I6/H6-1 -> 0.012993515 | J15: =J6/I6-1 -> -0.040704991 | K15: =K6/J6-1 -> -0.074138449 | L15: =L6/K6-1 -> -0.05 | M15: =M6/L6-1 -> -0.05 | ... T15: =T6/S6-1 -> -0.05 | AA15: =AA6/Y6-1 -> -0.090557954 | AB15: =AB6/Z6-1 -> 0.12091275 | AC15: =AC6/AA6-1 -> -0.0039558934 | AD15: =AD6/AB6-1 -> -0.071778658 | AE15: =AE6/AC6-1 -> -0.04563603 | AF15: =AF6/AD6-1 -> -0.1 | AG15: =AG6/AE6-1 -> -0.05 | AH15: =AH6/AF6-1 -> -0.05 | ... AX15: =AX6/AV6-1 -> -0.05
B16: =B7 -> 0 | F16: =F7/E7-1 -> #DIV/0! | G16: =G7/F7-1 -> #DIV/0! | H16: =H7/G7-1 -> #DIV/0! | I16: =I7/H7-1 -> #DIV/0! | J16: =J7/I7-1 -> #DIV/0! | K16: =K7/J7-1 -> #DIV/0! | L16: =L7/K7-1 -> #DIV/0! | M16: =M7/L7-1 -> #DIV/0! | ... T16: =T7/S7-1 -> #DIV/0! | AA16: =AA7/Y7-1 -> #DIV/0! | AB16: =AB7/Z7-1 -> #DIV/0! | AC16: =AC7/AA7-1 -> #DIV/0! | AD16: =AD7/AB7-1 -> #DIV/0! | AE16: =AE7/AC7-1 -> #DIV/0! | AF16: =AF7/AD7-1 -> #DIV/0! | AG16: =AG7/AE7-1 -> #DIV/0! | AH16: =AH7/AF7-1 -> #DIV/0! | ... AX16: =AX7/AV7-1 -> #DIV/0!
B17: =B8 -> 0 | F17: =F8/E8-1 -> #DIV/0! | G17: =G8/F8-1 -> #DIV/0! | H17: =H8/G8-1 -> #DIV/0! | I17: =I8/H8-1 -> #DIV/0! | J17: =J8/I8-1 -> #DIV/0! | K17: =K8/J8-1 -> #DIV/0! | L17: =L8/K8-1 -> #DIV/0! | M17: =M8/L8-1 -> #DIV/0! | ... T17: =T8/S8-1 -> #DIV/0! | AA17: =AA8/Y8-1 -> #DIV/0! | AB17: =AB8/Z8-1 -> #DIV/0! | AC17: =AC8/AA8-1 -> #DIV/0! | AD17: =AD8/AB8-1 -> #DIV/0! | AE17: =AE8/AC8-1 -> #DIV/0! | AF17: =AF8/AD8-1 -> #DIV/0! | AG17: =AG8/AE8-1 -> #DIV/0! | AH17: =AH8/AF8-1 -> #DIV/0! | ... AX17: =AX8/AV8-1 -> #DIV/0!
B18: =B9 -> 0 | F18: =F9/E9-1 -> #DIV/0! | G18: =G9/F9-1 -> #DIV/0! | H18: =H9/G9-1 -> #DIV/0! | I18: =I9/H9-1 -> #DIV/0! | J18: =J9/I9-1 -> #DIV/0! | K18: =K9/J9-1 -> #DIV/0! | L18: =L9/K9-1 -> #DIV/0! | M18: =M9/L9-1 -> #DIV/0! | ... T18: =T9/S9-1 -> #DIV/0! | AA18: =AA9/Y9-1 -> #DIV/0! | AB18: =AB9/Z9-1 -> #DIV/0! | AC18: =AC9/AA9-1 -> #DIV/0! | AD18: =AD9/AB9-1 -> #DIV/0! | AE18: =AE9/AC9-1 -> #DIV/0! | AF18: =AF9/AD9-1 -> #DIV/0! | AG18: =AG9/AE9-1 -> #DIV/0! | AH18: =AH9/AF9-1 -> #DIV/0! | ... AX18: =AX9/AV9-1 -> #DIV/0!
E19: =E6/E12 -> 0.11415663 | F19: =F6/F12 -> 0.11028399 | G19: =G6/G12 -> 0.094088832 | H19: =H6/H12 -> 0.06977907 | I19: =I6/I12 -> 0.06822773 | J19: =J6/J12 -> 0.061465709
B20: Workings- Revenue
B21: Share of Total revenue
B22: Milwaukee Tools | J22: =1-J24-J23 -> 0.69166667 | AD22: =$J22 -> 0.69166667 | AE22: =1-AE24-AE23 -> 0.7
B23: Ryobi | J23: =111/360-J24 -> 0.16388889 | AD23: =$J23 -> 0.16388889 | AE23: =108/360-AE24 -> 0.1875
B24: Other | J24: =52/360 -> 0.14444444 | AD24: =$J24 -> 0.14444444 | AE24: =40.5/360 -> 0.1125
B26: Revenue
B27: Milwaukee Tools | E27: =F27/(1+F37) -> 3871.4476 | F27: =G27/(1+G37) -> 4870.2811 | G27: =H27/(1+H37) -> 6720.9879 | H27: =I27/(1+I37) -> 8186.1633 | I27: =J27/(1+J37) -> 9062.0828 | J27: =J22*J$12 -> 10113.284 | AA27: =AC27/(1+AC37) -> 4410.5197 | AC27: =AE27/(1+AE37) -> 4895.6769 | AD27: =INDEX($B27:$T27,MATCH(AD$2,$B$2:$T$2,0))-AC27 -> 5217.6075 | AE27: =AE22*AE$12 -> 5483.1581 | AF27: =AD27*(1+AF37) -> 5843.7204 | AG27: =AE27*(1+AG37) -> 6360.4634 | AH27: =AF27*(1+AH37) -> 6778.7157 | AI27: =AG27*(1+AI37) -> 7123.719 | AJ27: =AH27*(1+AJ37) -> 7592.1616 | AK27: =AI27*(1+AK37) -> 7978.5653 | AL27: =AJ27*(1+AL37) -> 8503.221 | AM27: =AK27*(1+AM37) -> 8935.9931 | ... AX27: =AV27*(1+AX37) -> 16783.85
B28: Ryobi | I28: =J28/(1+J38) -> 2252.1808 | J28: =J23*J$12 -> 2396.3204 | AC28: =AE28/(1+AE38) -> 1347.434 | AD28: =INDEX($B28:$T28,MATCH(AD$2,$B$2:$T$2,0))-AC28 -> 1048.8864 | AE28: =AE23*AE$12 -> 1468.7031 | AF28: =AD28*(1+AF38) -> 1143.2862 | AG28: =AE28*(1+AG38) -> 1644.9474 | AH28: =AF28*(1+AH38) -> 1280.4805 | AI28: =AG28*(1+AI38) -> 1792.9927 | AJ28: =AH28*(1+AJ38) -> 1395.7238 | AK28: =AI28*(1+AK38) -> 1954.362 | AL28: =AJ28*(1+AL38) -> 1521.3389 | AM28: =AK28*(1+AM38) -> 2130.2546 | ... AX28: =AV28*(1+AX38) -> 2551.4376
B29: Other Power tools | I29: =I30-I28-I27 -> 1480.2844 | J29: =J30-J28-J27 -> 1213.2832 | AC29: =AC30-AC28-AC27 -> 641.34212 | AD29: =AD30-AD28-AD27 -> 571.94108 | AE29: =AE30-AE28-AE27 -> 473.19784 | AF29: =AD29*(1+AF39) -> 421.99206 | AG29: =AE29*(1+AG39) -> 349.13689 | AH29: =AF29*(1+AH39) -> 311.35602 | AI29: =AG29*(1+AI39) -> 257.6017 | AJ29: =AH29*(1+AJ39) -> 229.72605 | AK29: =AI29*(1+AK39) -> 190.06481 | AL29: =AJ29*(1+AL39) -> 169.49748 | AM29: =AK29*(1+AM39) -> 140.23444 | ... AX29: =AV29*(1+AX39) -> 27.345203
B30: Total Power Tools | I30: =I5 -> 12794.548 | J30: =J5 -> 13722.888 | Y30: =Y5 -> 6561.632 | Z30: =Z5 -> 5767.439 | AA30: =AA5 -> 6450.231 | AB30: =AB5 -> 6344.317 | AC30: =AC5 -> 6884.453 | AD30: =AD5 -> 6838.435 | AE30: =AE5 -> 7425.059 | AF30: =SUM(AF27:AF29) -> 7408.9987 | AG30: =SUM(AG27:AG29) -> 8354.5477 | AH30: =SUM(AH27:AH29) -> 8370.5522 | AI30: =SUM(AI27:AI29) -> 9174.3134 | AJ30: =SUM(AJ27:AJ29) -> 9217.6114 | AK30: =SUM(AK27:AK29) -> 10122.992 | AL30: =SUM(AL27:AL29) -> 10194.057 | AM30: =SUM(AM27:AM29) -> 11206.482 | ... AX30: =SUM(AX27:AX29) -> 19362.633
B31: Growth | AA31: =AA30/Y30-1 -> -0.016977636 | AB31: =AB30/Z30-1 -> 0.10002325 | AC31: =AC30/AA30-1 -> 0.067318829 | AD31: =AD30/AB30-1 -> 0.077883561 | AE31: =AE30/AC30-1 -> 0.078525629 | AF31: =AF30/AD30-1 -> 0.083434829 | AG31: =AG30/AE30-1 -> 0.12518267 | AH31: =AH30/AF30-1 -> 0.12978185 | ... AX31: =AX30/AV30-1 -> 0.11513994
B33: Floor care | Y33: =Y6 -> 471.974 | Z33: =Z6 -> 452.872 | AA33: =AA6 -> 429.233 | AB33: =AB6 -> 507.63 | AC33: =AC6 -> 427.535 | AD33: =AD6 -> 471.193 | AE33: =AE6 -> 408.024 | AF33: =AD33*(1+AF34) -> 424.0737 | AG33: =AE33*(1+AG34) -> 387.6228 | AH33: =AF33*(1+AH34) -> 402.87002 | AI33: =AG33*(1+AI34) -> 368.24166 | AJ33: =AH33*(1+AJ34) -> 382.72651 | AK33: =AI33*(1+AK34) -> 349.82958 | AL33: =AJ33*(1+AL34) -> 363.59019 | AM33: =AK33*(1+AM34) -> 332.3381 | ... AX33: =AV33*(1+AX34) -> 267.2722
B34: Growth | Z34: =Z33/X33-1 -> #DIV/0! | AA34: =AA33/Y33-1 -> -0.090557954 | AB34: =AB33/Z33-1 -> 0.12091275 | AC34: =AC33/AA33-1 -> -0.0039558934 | AD34: =AD33/AB33-1 -> -0.071778658 | AE34: =AE33/AC33-1 -> -0.04563603 | AF34: -0.1 | AG34: -0.05 | AH34: =AG34 -> -0.05 | AI34: =AH34 -> -0.05 | AJ34: =AI34 -> -0.05 | AK34: =AJ34 -> -0.05 | AL34: =AK34 -> -0.05 | AM34: =AL34 -> -0.05 | AN34: =AM34 -> -0.05 | AO34: =AN34 -> -0.05 | ... AX34: =AW34 -> -0.05
B36: Growth rates | AG36: Strong US 2026
B37: Milwaukee Tools | E37: 0.217 | F37: 0.258 | G37: 0.38 | H37: 0.218 | I37: 0.107 | J37: 0.116 | AC37: 0.11 | AE37: 0.12 | AF37: =AE37 -> 0.12 | AG37: 0.16 | AH37: 0.16 | AI37: 0.12 | AJ37: 0.12 | AK37: =AJ37 -> 0.12 | AL37: =AK37 -> 0.12 | AM37: =AL37 -> 0.12 | AN37: =AM37 -> 0.12 | AO37: =AN37 -> 0.12 | AP37: =AO37 -> 0.12 | AQ37: =AP37 -> 0.12 | AR37: =AQ37 -> 0.12 | ... AX37: =AW37 -> 0.12
B38: Ryobi | J38: 0.064 | AE38: 0.09 | AF38: =AE38 -> 0.09 | AG38: 0.12 | AH38: 0.12 | AI38: 0.09 | AJ38: 0.09 | AK38: =AJ38 -> 0.09 | AL38: =AK38 -> 0.09 | AM38: =AL38 -> 0.09 | AN38: =AM38 -> 0.09 | AO38: =AN38 -> 0.09 | AP38: =AO38 -> 0.09 | AQ38: =AP38 -> 0.09 | AR38: =AQ38 -> 0.09 | ... AX38: =AW38 -> 0.09
B39: Other Power tools | J39: =J29/I29-1 -> -0.18037154 | AE39: =AE29/AC29-1 -> -0.26217565 | AF39: =AE39 -> -0.26217565 | AG39: =AF39 -> -0.26217565 | AH39: =AG39 -> -0.26217565 | AI39: =AH39 -> -0.26217565 | AJ39: =AI39 -> -0.26217565 | AK39: =AJ39 -> -0.26217565 | AL39: =AK39 -> -0.26217565 | AM39: =AL39 -> -0.26217565 | ... AX39: =AW39 -> -0.26217565
B40: Other | J40: -0.14 | AE40: -0.19
K45: =SUMIF($Y$2:$AX$2,K$2,$Y45:$AX45) -> 0 | L45: =SUMIF($Y$2:$AX$2,L$2,$Y45:$AX45) -> 0 | M45: =SUMIF($Y$2:$AX$2,M$2,$Y45:$AX45) -> 0 | N45: =SUMIF($Y$2:$AX$2,N$2,$Y45:$AX45) -> 0 | O45: =SUMIF($Y$2:$AX$2,O$2,$Y45:$AX45) -> 0 | P45: =SUMIF($Y$2:$AX$2,P$2,$Y45:$AX45) -> 0 | Q45: =SUMIF($Y$2:$AX$2,Q$2,$Y45:$AX45) -> 0 | R45: =SUMIF($Y$2:$AX$2,R$2,$Y45:$AX45) -> 0 | ... T45: =SUMIF($Y$2:$AX$2,T$2,$Y45:$AX45) -> 0
K46: =SUMIF($Y$2:$AX$2,K$2,$Y46:$AX46) -> 0 | L46: =SUMIF($Y$2:$AX$2,L$2,$Y46:$AX46) -> 0 | M46: =SUMIF($Y$2:$AX$2,M$2,$Y46:$AX46) -> 0 | N46: =SUMIF($Y$2:$AX$2,N$2,$Y46:$AX46) -> 0 | O46: =SUMIF($Y$2:$AX$2,O$2,$Y46:$AX46) -> 0 | P46: =SUMIF($Y$2:$AX$2,P$2,$Y46:$AX46) -> 0 | Q46: =SUMIF($Y$2:$AX$2,Q$2,$Y46:$AX46) -> 0 | R46: =SUMIF($Y$2:$AX$2,R$2,$Y46:$AX46) -> 0 | ... T46: =SUMIF($Y$2:$AX$2,T$2,$Y46:$AX46) -> 0
B49: Other | E49: =E50-SUM(E45:E48) -> 2892.656 | F49: =F50-SUM(F45:F48) -> 3753.082 | G49: =G50-SUM(G45:G48) -> 5121.613 | H49: =H50-SUM(H45:H48) -> 5212.577 | I49: =I50-SUM(I45:I48) -> 5419.636 | J49: =J50-SUM(J45:J48) -> 5895.556 | K49: =SUMIF($Y$2:$AX$2,K$2,$Y49:$AX49) -> 3155.807 | L49: =SUMIF($Y$2:$AX$2,L$2,$Y49:$AX49) -> 0 | M49: =SUMIF($Y$2:$AX$2,M$2,$Y49:$AX49) -> 0 | N49: =SUMIF($Y$2:$AX$2,N$2,$Y49:$AX49) -> 0 | O49: =SUMIF($Y$2:$AX$2,O$2,$Y49:$AX49) -> 0 | P49: =SUMIF($Y$2:$AX$2,P$2,$Y49:$AX49) -> 0 | Q49: =SUMIF($Y$2:$AX$2,Q$2,$Y49:$AX49) -> 0 | R49: =SUMIF($Y$2:$AX$2,R$2,$Y49:$AX49) -> 0 | ... T49: =SUMIF($Y$2:$AX$2,T$2,$Y49:$AX49) -> 0 | Y49: =Y50-SUM(Y45:Y48) -> 2746.745 | Z49: =Z50-SUM(Z45:Z48) -> 2465.832 | AA49: =AA50-SUM(AA45:AA48) -> 2701.664 | AB49: =AB50-SUM(AB45:AB48) -> 2717.972 | AC49: =AC50-SUM(AC45:AC48) -> 2920.717 | AD49: =AD50-SUM(AD45:AD48) -> 2974.839 | AE49: =AE50-SUM(AE45:AE48) -> 3155.807
B50: Gross Profit | E50: 2892.656 | F50: 3753.082 | G50: 5121.613 | H50: 5212.577 | I50: 5419.636 | J50: 5895.556 | K50: =SUMIF($Y$2:$AX$2,K$2,$Y50:$AX50) -> 6375.0073 | L50: =SUMIF($Y$2:$AX$2,L$2,$Y50:$AX50) -> 7197.7852 | M50: =SUMIF($Y$2:$AX$2,M$2,$Y50:$AX50) -> 7943.1684 | N50: =SUMIF($Y$2:$AX$2,N$2,$Y50:$AX50) -> 8810.6092 | O50: =SUMIF($Y$2:$AX$2,O$2,$Y50:$AX50) -> 9808.664 | P50: =SUMIF($Y$2:$AX$2,P$2,$Y50:$AX50) -> 10948.674 | Q50: =SUMIF($Y$2:$AX$2,Q$2,$Y50:$AX50) -> 12244.68 | R50: =SUMIF($Y$2:$AX$2,R$2,$Y50:$AX50) -> 13713.444 | ... T50: =SUMIF($Y$2:$AX$2,T$2,$Y50:$AX50) -> 17250.542 | Y50: 2746.745 | Z50: 2465.832 | AA50: 2701.664 | AB50: 2717.972 | AC50: 2920.717 | AD50: 2974.839 | AE50: 3155.807 | AF50: =AF$12*AF51 -> 3219.2003 | AG50: =AG12*AG51 -> 3557.0305 | AH50: =AH12*AH51 -> 3640.7547 | AI50: =AI12*AI51 -> 3920.8627 | AJ50: =AJ12*AJ51 -> 4022.3057 | AK50: =AK12*AK51 -> 4344.9837 | AL50: =AL12*AL51 -> 4465.6255 | AM50: =AM12*AM51 -> 4833.4024 | AN50: =AN12*AN51 -> 4975.2616 | ... AX50: =AX12*AX51 -> 8774.0854
B51: Gross Margin | E51: =E50/E$12 -> 0.37730028 | F51: =F50/F$12 -> 0.38250148 | G51: =G50/G$12 -> 0.38790809 | H51: =H50/H$12 -> 0.39328577 | I51: =I50/I$12 -> 0.39468894 | J51: =J50/J$12 -> 0.40320824 | K51: =K50/K$12 -> 0.40692864 | L51: =L50/L$12 -> 0.41093586 | ... T51: =T50/T$12 -> 0.44296149 | Y51: =Y50/Y$12 -> 0.39051732 | Z51: =Z50/Z$12 -> 0.39641619 | AA51: =AA50/AA$12 -> 0.39271432 | AB51: =AB50/AB$12 -> 0.39667149 | AC51: =AC50/AC$12 -> 0.39944226 | AD51: =AD50/AD$12 -> 0.40697543 | AE51: =AE50/AE$12 -> 0.40288185 | AF51: =AD51+0.4% -> 0.41097543 | AG51: =AE51+0.4% -> 0.40688185 | AH51: =AF51+0.4% -> 0.41497543 | AI51: =AG51+0.4% -> 0.41088185 | AJ51: =AH51+0.4% -> 0.41897543 | AK51: =AI51+0.4% -> 0.41488185 | AL51: =AJ51+0.4% -> 0.42297543 | AM51: =AK51+0.4% -> 0.41888185 | ... AX51: =AV51+0.4% -> 0.44697543
B52: =B45 -> 0 | E52: =E45/E7 -> #DIV/0! | F52: =F45/F7 -> #DIV/0! | G52: =G45/G7 -> #DIV/0! | H52: =H45/H7 -> #DIV/0! | I52: =I45/I7 -> #DIV/0! | J52: =J45/J7 -> #DIV/0! | K52: =K45/K7 -> #DIV/0! | L52: =L45/L7 -> #DIV/0! | ... T52: =T45/T7 -> #DIV/0! | Y52: =Y45/Y7 -> #DIV/0! | Z52: =Z45/Z7 -> #DIV/0! | AA52: =AA45/AA7 -> #DIV/0! | AB52: =AB45/AB7 -> #DIV/0! | AC52: =AC45/AC7 -> #DIV/0! | AD52: =AD45/AD7 -> #DIV/0! | AE52: =AE45/AE7 -> #DIV/0!
B53: =B46 -> 0 | E53: =E46/E8 -> #DIV/0! | F53: =F46/F8 -> #DIV/0! | G53: =G46/G8 -> #DIV/0! | H53: =H46/H8 -> #DIV/0! | I53: =I46/I8 -> #DIV/0! | J53: =J46/J8 -> #DIV/0! | K53: =K46/K8 -> #DIV/0! | L53: =L46/L8 -> #DIV/0! | ... T53: =T46/T8 -> #DIV/0! | Y53: =Y46/Y8 -> #DIV/0! | Z53: =Z46/Z8 -> #DIV/0! | AA53: =AA46/AA8 -> #DIV/0! | AB53: =AB46/AB8 -> #DIV/0! | AC53: =AC46/AC8 -> #DIV/0! | AD53: =AD46/AD8 -> #DIV/0! | AE53: =AE46/AE8 -> #DIV/0!
B54: Other | E54: =E49/E11 -> #DIV/0! | F54: =F49/F11 -> #DIV/0! | G54: =G49/G11 -> #DIV/0! | H54: =H49/H11 -> #DIV/0! | I54: =I49/I11 -> #DIV/0! | J54: =J49/J11 -> #DIV/0! | K54: =K49/K11 -> #DIV/0! | L54: =L49/L11 -> #DIV/0! | ... T54: =T49/T11 -> #DIV/0! | Y54: =Y49/Y11 -> #DIV/0! | Z54: =Z49/Z11 -> #DIV/0! | AA54: =AA49/AA11 -> #DIV/0! | AB54: =AB49/AB11 -> #DIV/0! | AC54: =AC49/AC11 -> #DIV/0! | AD54: =AD49/AD11 -> #DIV/0! | AE54: =AE49/AE11 -> #DIV/0!
V55: =10/16 -> 0.625
K56: =SUMIF($Y$2:$AX$2,K$2,$Y56:$AX56) -> 0 | L56: =SUMIF($Y$2:$AX$2,L$2,$Y56:$AX56) -> 0 | M56: =SUMIF($Y$2:$AX$2,M$2,$Y56:$AX56) -> 0 | N56: =SUMIF($Y$2:$AX$2,N$2,$Y56:$AX56) -> 0 | O56: =SUMIF($Y$2:$AX$2,O$2,$Y56:$AX56) -> 0 | P56: =SUMIF($Y$2:$AX$2,P$2,$Y56:$AX56) -> 0 | Q56: =SUMIF($Y$2:$AX$2,Q$2,$Y56:$AX56) -> 0 | R56: =SUMIF($Y$2:$AX$2,R$2,$Y56:$AX56) -> 0 | ... T56: =SUMIF($Y$2:$AX$2,T$2,$Y56:$AX56) -> 0
K57: =SUMIF($Y$2:$AX$2,K$2,$Y57:$AX57) -> 0 | L57: =SUMIF($Y$2:$AX$2,L$2,$Y57:$AX57) -> 0 | M57: =SUMIF($Y$2:$AX$2,M$2,$Y57:$AX57) -> 0 | N57: =SUMIF($Y$2:$AX$2,N$2,$Y57:$AX57) -> 0 | O57: =SUMIF($Y$2:$AX$2,O$2,$Y57:$AX57) -> 0 | P57: =SUMIF($Y$2:$AX$2,P$2,$Y57:$AX57) -> 0 | Q57: =SUMIF($Y$2:$AX$2,Q$2,$Y57:$AX57) -> 0 | R57: =SUMIF($Y$2:$AX$2,R$2,$Y57:$AX57) -> 0 | ... T57: =SUMIF($Y$2:$AX$2,T$2,$Y57:$AX57) -> 0
K58: =SUMIF($Y$2:$AX$2,K$2,$Y58:$AX58) -> 0 | L58: =SUMIF($Y$2:$AX$2,L$2,$Y58:$AX58) -> 0 | M58: =SUMIF($Y$2:$AX$2,M$2,$Y58:$AX58) -> 0 | N58: =SUMIF($Y$2:$AX$2,N$2,$Y58:$AX58) -> 0 | O58: =SUMIF($Y$2:$AX$2,O$2,$Y58:$AX58) -> 0 | P58: =SUMIF($Y$2:$AX$2,P$2,$Y58:$AX58) -> 0 | Q58: =SUMIF($Y$2:$AX$2,Q$2,$Y58:$AX58) -> 0 | R58: =SUMIF($Y$2:$AX$2,R$2,$Y58:$AX58) -> 0 | ... T58: =SUMIF($Y$2:$AX$2,T$2,$Y58:$AX58) -> 0
B60: =$B$11 -> Other | E60: =E61-SUM(E56:E59) -> -1904.44 | F60: =F61-SUM(F56:F59) -> -2491.841 | G60: =G61-SUM(G56:G59) -> -3515.705 | H60: =H61-SUM(H56:H59) -> -3512.324 | I60: =I61-SUM(I56:I59) -> -3668.28 | J60: =J61-SUM(J56:J59) -> -3862.161 | Y60: =Y61-SUM(Y56:Y59) -> -1879.54 | Z60: =Z61-SUM(Z56:Z59) -> -1632.784 | AA60: =AA61-SUM(AA56:AA59) -> -1862.113 | AB60: =AB61-SUM(AB56:AB59) -> -1806.167 | AC60: =AC61-SUM(AC56:AC59) -> -1934.218 | AD60: =AD61-SUM(AD56:AD59) -> -1927.943 | AE60: =AE61-SUM(AE56:AE59) -> -2093.554
B61: Operating Costs | E61: =IF(ISBLANK(E50),E83-E12,E83-E50) -> -1904.44 | F61: =IF(ISBLANK(F50),F83-F12,F83-F50) -> -2491.841 | G61: =IF(ISBLANK(G50),G83-G12,G83-G50) -> -3515.705 | H61: =IF(ISBLANK(H50),H83-H12,H83-H50) -> -3512.324 | I61: =IF(ISBLANK(I50),I83-I12,I83-I50) -> -3668.28 | J61: =IF(ISBLANK(J50),J83-J12,J83-J50) -> -3862.161 | K61: =SUMIF($Y$2:$AX$2,K$2,$Y61:$AX61) -> -4159.5575 | L61: =SUMIF($Y$2:$AX$2,L$2,$Y61:$AX61) -> -4650.551 | M61: =SUMIF($Y$2:$AX$2,M$2,$Y61:$AX61) -> -5082.5726 | N61: =SUMIF($Y$2:$AX$2,N$2,$Y61:$AX61) -> -5583.6998 | O61: =SUMIF($Y$2:$AX$2,O$2,$Y61:$AX61) -> -6157.3387 | P61: =SUMIF($Y$2:$AX$2,P$2,$Y61:$AX61) -> -6808.4996 | Q61: =SUMIF($Y$2:$AX$2,Q$2,$Y61:$AX61) -> -7543.6715 | R61: =SUMIF($Y$2:$AX$2,R$2,$Y61:$AX61) -> -8370.7636 | ... T61: =SUMIF($Y$2:$AX$2,T$2,$Y61:$AX61) -> -10339.466 | Y61: =IF(ISBLANK(Y50),Y83-Y12,Y83-Y50) -> -1879.54 | Z61: =IF(ISBLANK(Z50),Z83-Z12,Z83-Z50) -> -1632.784 | AA61: =IF(ISBLANK(AA50),AA83-AA12,AA83-AA50) -> -1862.113 | AB61: =IF(ISBLANK(AB50),AB83-AB12,AB83-AB50) -> -1806.167 | AC61: =IF(ISBLANK(AC50),AC83-AC12,AC83-AC50) -> -1934.218 | AD61: =IF(ISBLANK(AD50),AD83-AD12,AD83-AD50) -> -1927.943 | AE61: =IF(ISBLANK(AE50),AE83-AE12,AE83-AE50) -> -2093.554 | AF61: =-AF$12*AF62 -> -2066.0035 | AG61: =-AG$12*AG62 -> -2336.5265 | AH61: =-AH$12*AH62 -> -2314.0245 | AI61: =-AI$12*AI62 -> -2550.4459 | AJ61: =-AJ$12*AJ62 -> -2532.1267 | AK61: =-AK$12*AK62 -> -2799.079 | AL61: =-AL$12*AL62 -> -2784.6209 | AM61: =-AM$12*AM62 -> -3083.9892 | ... AX61: =-AX$12*AX62 -> -5177.4644
B62: % of sales | E62: =-E61/E$12 -> 0.24840346 | F62: =-F61/F$12 -> 0.25396005 | G62: =-G61/G$12 -> 0.26627752 | H62: =-H61/H$12 -> 0.26500272 | I62: =-I61/I$12 -> 0.26714516 | J62: =-J61/J$12 -> 0.2641405 | K62: =-K61/K$12 -> 0.26551234 | L62: =-L61/L$12 -> 0.2655092 | ... T62: =-T61/T$12 -> 0.26549806 | Y62: =-Y61/Y$12 -> 0.26722282 | Z62: =-Z61/Z$12 -> 0.26249234 | AA62: =-AA61/AA$12 -> 0.27067705 | AB62: =-AB61/AB$12 -> 0.26359909 | AC62: =-AC61/AC$12 -> 0.26452697 | AD62: =-AD61/AD$12 -> 0.26375391 | AE62: =-AE61/AE$12 -> 0.26727075 | AF62: =AD62 -> 0.26375391 | AG62: =AE62 -> 0.26727075 | AH62: =AF62 -> 0.26375391 | AI62: =AG62 -> 0.26727075 | AJ62: =AH62 -> 0.26375391 | AK62: =AI62 -> 0.26727075 | AL62: =AJ62 -> 0.26375391 | AM62: =AK62 -> 0.26727075 | ... AX62: =AV62 -> 0.26375391
B64: Workings- Opex
B83: EBITDA | E83: 988.216 | F83: 1261.241 | G83: 1605.908 | H83: 1700.253 | I83: 1751.356 | J83: 2033.395 | K83: =SUMIF($Y$2:$AX$2,K$2,$Y83:$AX83) -> 2215.4498 | L83: =SUMIF($Y$2:$AX$2,L$2,$Y83:$AX83) -> 2547.2342 | M83: =SUMIF($Y$2:$AX$2,M$2,$Y83:$AX83) -> 2860.5958 | N83: =SUMIF($Y$2:$AX$2,N$2,$Y83:$AX83) -> 3226.9094 | O83: =SUMIF($Y$2:$AX$2,O$2,$Y83:$AX83) -> 3651.3253 | P83: =SUMIF($Y$2:$AX$2,P$2,$Y83:$AX83) -> 4140.1741 | Q83: =SUMIF($Y$2:$AX$2,Q$2,$Y83:$AX83) -> 4701.0089 | R83: =SUMIF($Y$2:$AX$2,R$2,$Y83:$AX83) -> 5342.6799 | ... T83: =SUMIF($Y$2:$AX$2,T$2,$Y83:$AX83) -> 6911.0756 | Y83: =Y95-Y87 -> 867.205 | Z83: =Z95-Z87 -> 833.048 | AA83: =AA95-AA87 -> 839.551 | AB83: =AB95-AB87 -> 911.805 | AC83: =AC95-AC87 -> 986.499 | AD83: =AD95-AD87 -> 1046.896 | AE83: =AE95-AE87 -> 1062.253 | AF83: =IF(ISBLANK(AF50),AF12+AF61,AF50+AF61) -> 1153.1968 | AG83: =IF(ISBLANK(AG50),AG12+AG61,AG50+AG61) -> 1220.504 | AH83: =IF(ISBLANK(AH50),AH12+AH61,AH50+AH61) -> 1326.7302 | AI83: =IF(ISBLANK(AI50),AI12+AI61,AI50+AI61) -> 1370.4168 | AJ83: =IF(ISBLANK(AJ50),AJ12+AJ61,AJ50+AJ61) -> 1490.179 | AK83: =IF(ISBLANK(AK50),AK12+AK61,AK50+AK61) -> 1545.9047 | AL83: =IF(ISBLANK(AL50),AL12+AL61,AL50+AL61) -> 1681.0046 | AM83: =IF(ISBLANK(AM50),AM12+AM61,AM50+AM61) -> 1749.4132 | ... AX83: =IF(ISBLANK(AX50),AX12+AX61,AX50+AX61) -> 3596.621
B84: Growth | F84: =F83/E83-1 -> 0.27628069 | G84: =G83/F83-1 -> 0.27327608 | H84: =H83/G83-1 -> 0.058748695 | I84: =I83/H83-1 -> 0.030056115 | J84: =J83/I83-1 -> 0.16104036 | K84: =K83/J83-1 -> 0.089532424 | L84: =L83/K83-1 -> 0.14975942 | M84: =M83/L83-1 -> 0.12302032 | ... T84: =T83/S83-1 -> 0.13754331 | AA84: =AA83/Y83-1 -> -0.031888654 | AB84: =AB83/Z83-1 -> 0.094540771 | AC84: =AC83/AA83-1 -> 0.17503165 | AD84: =AD83/AB83-1 -> 0.14815777 | AE84: =AE83/AC83-1 -> 0.076790752 | AF84: =AF83/AD83-1 -> 0.10153901 | AG84: =AG83/AE83-1 -> 0.14897679 | AH84: =AH83/AF83-1 -> 0.15048032 | ... AX84: =AX83/AV83-1 -> 0.1373366
B85: EBITDA margin | E85: =E83/E$12 -> 0.12889683 | F85: =F83/F$12 -> 0.12854144 | G85: =G83/G$12 -> 0.12163057 | H85: =H83/H$12 -> 0.12828306 | I85: =I83/I$12 -> 0.12754378 | J85: =J83/J$12 -> 0.13906773 | K85: =K83/K$12 -> 0.1414163 | L85: =L83/L$12 -> 0.14542667 | ... T85: =T83/T$12 -> 0.17746344 | Y85: =Y83/Y$12 -> 0.12329451 | Z85: =Z83/Z$12 -> 0.13392385 | AA85: =AA83/AA$12 -> 0.12203727 | AB85: =AB83/AB$12 -> 0.1330724 | AC85: =AC83/AC$12 -> 0.13491529 | AD85: =AD83/AD$12 -> 0.14322152 | AE85: =AE83/AE$12 -> 0.1356111 | AF85: =AF83/AF$12 -> 0.14722152 | ... AX85: =AX83/AX$12 -> 0.18322152
B87: D&A & Stock based Comp | E87: =E95-E83 -> -325.483 | F87: =F95-F83 -> -404.148 | G87: =G95-G83 -> -427.1 | H87: =H95-H83 -> -512.86 | I87: =I95-I83 -> -633.487 | J87: =J95-J83 -> -779.516 | K87: =SUMIF($Y$2:$AX$2,K$2,$Y87:$AX87) -> -799.50722 | L87: =SUMIF($Y$2:$AX$2,L$2,$Y87:$AX87) -> -894.05668 | M87: =SUMIF($Y$2:$AX$2,M$2,$Y87:$AX87) -> -977.24457 | N87: =SUMIF($Y$2:$AX$2,N$2,$Y87:$AX87) -> -1073.7181 | O87: =SUMIF($Y$2:$AX$2,O$2,$Y87:$AX87) -> -1184.1384 | P87: =SUMIF($Y$2:$AX$2,P$2,$Y87:$AX87) -> -1309.4741 | Q87: =SUMIF($Y$2:$AX$2,Q$2,$Y87:$AX87) -> -1450.9779 | R87: =SUMIF($Y$2:$AX$2,R$2,$Y87:$AX87) -> -1610.1754 | ... T87: =SUMIF($Y$2:$AX$2,T$2,$Y87:$AX87) -> -1989.1229 | Y87: =-57.696-115.39-69.175 -> -242.261 | Z87: =INDEX($B87:$T87,MATCH(Z$2,$B$2:$T$2,0))-Y87 -> -270.599 | AA87: =-76.747-129.727-80.902 -> -287.376 | AB87: =INDEX($B87:$T87,MATCH(AB$2,$B$2:$T$2,0))-AA87 -> -346.111 | AC87: =-136.857-142.561-88.436 -> -367.854 | AD87: =INDEX($B87:$T87,MATCH(AD$2,$B$2:$T$2,0))-AC87 -> -411.662 | AE87: =-138.093-136.866-83.407 -> -358.366 | AF87: =-AF88*AF12 -> -441.14122 | AG87: =-AG88*AG12 -> -399.95704 | AH87: =-AH88*AH12 -> -494.09964 | AI87: =-AI88*AI12 -> -436.57488 | AJ87: =-AJ88*AJ12 -> -540.66969 | AK87: =-AK88*AK12 -> -479.13487 | AL87: =-AL88*AL12 -> -594.58324 | AM87: =-AM88*AM12 -> -527.90464 | ... AX87: =-AX88*AX12 -> -1105.5126
B88: % of sales | E88: =-E87/E$12 -> 0.042454003 | F88: =-F87/F$12 -> 0.041189404 | G88: =-G87/G$12 -> 0.032348314 | H88: =-H87/H$12 -> 0.038694976 | I88: =-I87/I$12 -> 0.046134152 | J88: =-J87/J$12 -> 0.053312575 | K88: =-K87/K$12 -> 0.051034041 | L88: =-L87/L$12 -> 0.051043472 | ... T88: =-T87/T$12 -> 0.051076939 | X88: =-X87/X$12 -> #DIV/0! | Y88: =-Y87/Y$12 -> 0.034443357 | Z88: =-Z87/Z$12 -> 0.043502487 | AA88: =-AA87/AA$12 -> 0.041773022 | AB88: =-AB87/AB$12 -> 0.050512796 | AC88: =-AC87/AC$12 -> 0.050308343 | AD88: =-AD87/AD$12 -> 0.056317777 | AE88: =-AE87/AE$12 -> 0.045750313 | AF88: =AD88 -> 0.056317777 | AG88: =AE88 -> 0.045750313 | AH88: =AF88 -> 0.056317777 | AI88: =AG88 -> 0.045750313 | AJ88: =AH88 -> 0.056317777 | AK88: =AI88 -> 0.045750313 | AL88: =AJ88 -> 0.056317777 | AM88: =AK88 -> 0.045750313 | ... AX88: =AV88 -> 0.056317777
B95: EBIT | C95: 10Q | E95: 662.733 | F95: 857.093 | G95: 1178.808 | H95: 1187.393 | I95: 1117.869 | J95: 1253.879 | K95: =SUMIF($Y$2:$AX$2,K$2,$Y95:$AX95) -> 1415.9426 | L95: =SUMIF($Y$2:$AX$2,L$2,$Y95:$AX95) -> 1653.1776 | M95: =SUMIF($Y$2:$AX$2,M$2,$Y95:$AX95) -> 1883.3513 | N95: =SUMIF($Y$2:$AX$2,N$2,$Y95:$AX95) -> 2153.1913 | O95: =SUMIF($Y$2:$AX$2,O$2,$Y95:$AX95) -> 2467.187 | P95: =SUMIF($Y$2:$AX$2,P$2,$Y95:$AX95) -> 2830.7 | Q95: =SUMIF($Y$2:$AX$2,Q$2,$Y95:$AX95) -> 3250.0309 | R95: =SUMIF($Y$2:$AX$2,R$2,$Y95:$AX95) -> 3732.5045 | ... T95: =SUMIF($Y$2:$AX$2,T$2,$Y95:$AX95) -> 4921.9527 | Y95: 624.944 | Z95: 562.449 | AA95: 552.175 | AB95: 565.694 | AC95: 618.645 | AD95: 635.234 | AE95: 703.887 | AF95: =AF83+AF87 -> 712.05556 | AG95: =AG83+AG87 -> 820.547 | AH95: =AH83+AH87 -> 832.63057 | AI95: =AI83+AI87 -> 933.84194 | AJ95: =AJ83+AJ87 -> 949.50931 | AK95: =AK83+AK87 -> 1066.7699 | AL95: =AL83+AL87 -> 1086.4214 | AM95: =AM83+AM87 -> 1221.5086 | ... AX95: =AX83+AX87 -> 2491.1084
B96: EBIT margin | E96: =E95/E$12 -> 0.086442822 | F96: =F95/F$12 -> 0.087352034 | G96: =G95/G$12 -> 0.089282256 | H96: =H95/H$12 -> 0.089588082 | I96: =I95/I$12 -> 0.081409624 | J96: =J95/J$12 -> 0.085755159 | K96: =K95/K$12 -> 0.090382262 | L96: =L95/L$12 -> 0.094383193 | ... T96: =T95/T$12 -> 0.1263865 | W96: 0.1 | Y96: =Y95/Y$12 -> 0.088851153 | Z96: =Z95/Z$12 -> 0.090421363 | AA96: =AA95/AA$12 -> 0.080264247 | AB96: =AB95/AB$12 -> 0.082559599 | AC96: =AC95/AC$12 -> 0.08460695 | AD96: =AD95/AD$12 -> 0.086903738 | AE96: =AE95/AE$12 -> 0.089860787 | AF96: =AF95/AF$12 -> 0.090903738 | ... AX96: =AX95/AX$12 -> 0.12690374
B98: Net Interest | E98: =E101-E95 -> -1.447 | F98: =F101-F95 -> 4.161 | G98: =G101-G95 -> 3.012 | H98: =H101-H95 -> -30.496 | I98: =I101-I95 -> -62.253 | J98: =J101-J95 -> -37.485 | K98: =SUMIF($Y$2:$AX$2,K$2,$Y98:$AX98) -> -35.835422 | L98: =SUMIF($Y$2:$AX$2,L$2,$Y98:$AX98) -> -40.048049 | M98: =SUMIF($Y$2:$AX$2,M$2,$Y98:$AX98) -> -43.755252 | N98: =SUMIF($Y$2:$AX$2,N$2,$Y98:$AX98) -> -48.057529 | O98: =SUMIF($Y$2:$AX$2,O$2,$Y98:$AX98) -> -52.983592 | P98: =SUMIF($Y$2:$AX$2,P$2,$Y98:$AX98) -> -58.57604 | Q98: =SUMIF($Y$2:$AX$2,Q$2,$Y98:$AX98) -> -64.890242 | R98: =SUMIF($Y$2:$AX$2,R$2,$Y98:$AX98) -> -71.993813 | ... T98: =SUMIF($Y$2:$AX$2,T$2,$Y98:$AX98) -> -88.900803 | Y98: =Y101-Y95 -> -3.477 | Z98: =Z101-Z95 -> -27.019 | AA98: =AA101-AA95 -> -41.151 | AB98: =AB101-AB95 -> -21.102 | AC98: =AC101-AC95 -> -24.939 | AD98: =AD101-AD95 -> -12.546 | AE98: =AE101-AE95 -> -22.391 | AF98: =-AF99*AF12 -> -13.444422 | AG98: =-AG99*AG12 -> -24.989642 | AH98: =-AH99*AH12 -> -15.058407 | AI98: =-AI99*AI12 -> -27.277555 | AJ98: =-AJ99*AJ12 -> -16.477698 | AK98: =-AK99*AK12 -> -29.936738 | AL98: =-AL99*AL12 -> -18.120792 | AM98: =-AM99*AM12 -> -32.983913 | ... AX98: =-AX99*AX12 -> -33.69211
B99: % of sales | E99: =-E98/E$12 -> 0.00018873779 | F99: =-F98/F$12 -> -0.00042407511 | G99: =-G98/G$12 -> -0.00022812719 | H99: =-H98/H$12 -> 0.0023009047 | I99: =-I98/I$12 -> 0.00453362 | J99: =-J98/J$12 -> 0.0025636701 | K99: =-K98/K$12 -> 0.002287442 | L99: =-L98/L$12 -> 0.0022864227 | ... T99: =-T98/T$12 -> 0.0022828056 | Y99: =-Y98/Y$12 -> 0.00049434103 | Z99: =-Z98/Z$12 -> 0.0043436735 | AA99: =-AA98/AA$12 -> 0.005981716 | AB99: =-AB98/AB$12 -> 0.0030797086 | AC99: =-AC98/AC$12 -> 0.0034107003 | AD99: =-AD98/AD$12 -> 0.0017163664 | AE99: =-AE98/AE$12 -> 0.0028585169 | AF99: =AD99 -> 0.0017163664 | AG99: =AE99 -> 0.0028585169 | AH99: =AF99 -> 0.0017163664 | AI99: =AG99 -> 0.0028585169 | AJ99: =AH99 -> 0.0017163664 | AK99: =AI99 -> 0.0028585169 | AL99: =AJ99 -> 0.0017163664 | AM99: =AK99 -> 0.0028585169 | ... AX99: =AV99 -> 0.0017163664
B101: PBT | C101: 10Q | E101: 661.286 | F101: 861.254 | G101: 1181.82 | H101: 1156.897 | I101: 1055.616 | J101: 1216.394 | K101: =SUMIF($Y$2:$AX$2,K$2,$Y101:$AX101) -> 1380.1071 | L101: =SUMIF($Y$2:$AX$2,L$2,$Y101:$AX101) -> 1613.1295 | M101: =SUMIF($Y$2:$AX$2,M$2,$Y101:$AX101) -> 1839.596 | N101: =SUMIF($Y$2:$AX$2,N$2,$Y101:$AX101) -> 2105.1337 | O101: =SUMIF($Y$2:$AX$2,O$2,$Y101:$AX101) -> 2414.2034 | P101: =SUMIF($Y$2:$AX$2,P$2,$Y101:$AX101) -> 2772.124 | Q101: =SUMIF($Y$2:$AX$2,Q$2,$Y101:$AX101) -> 3185.1407 | R101: =SUMIF($Y$2:$AX$2,R$2,$Y101:$AX101) -> 3660.5107 | ... T101: =SUMIF($Y$2:$AX$2,T$2,$Y101:$AX101) -> 4833.0519 | Y101: 621.467 | Z101: 535.43 | AA101: 511.024 | AB101: 544.592 | AC101: 593.706 | AD101: 622.688 | AE101: 681.496 | AF101: =AF95+AF98 -> 698.61114 | AG101: =AG95+AG98 -> 795.55736 | AH101: =AH95+AH98 -> 817.57216 | AI101: =AI95+AI98 -> 906.56439 | AJ101: =AJ95+AJ98 -> 933.03161 | AK101: =AK95+AK98 -> 1036.8331 | AL101: =AL95+AL98 -> 1068.3006 | AM101: =AM95+AM98 -> 1188.5247 | ... AX101: =AX95+AX98 -> 2457.4163
B102: Income Tax | E102: =E104-E101 -> -46.386 | F102: =F104-F101 -> -60.494 | G102: =G104-G101 -> -82.822 | H102: =H104-H101 -> -79.747 | I102: =I104-I101 -> -79.276 | J102: =J104-J101 -> -94.714 | K102: =SUMIF($Y$2:$AX$2,K$2,$Y102:$AX102) -> -110.79381 | L102: =SUMIF($Y$2:$AX$2,L$2,$Y102:$AX102) -> -129.50517 | M102: =SUMIF($Y$2:$AX$2,M$2,$Y102:$AX102) -> -147.6894 | N102: =SUMIF($Y$2:$AX$2,N$2,$Y102:$AX102) -> -169.01039 | O102: =SUMIF($Y$2:$AX$2,O$2,$Y102:$AX102) -> -205.89742 | P102: =SUMIF($Y$2:$AX$2,P$2,$Y102:$AX102) -> -250.28589 | Q102: =SUMIF($Y$2:$AX$2,Q$2,$Y102:$AX102) -> -303.5038 | R102: =SUMIF($Y$2:$AX$2,R$2,$Y102:$AX102) -> -367.10555 | ... T102: =SUMIF($Y$2:$AX$2,T$2,$Y102:$AX102) -> -533.03396 | Y102: =Y104-Y101 -> -43.479 | Z102: =Z104-Z101 -> -36.268 | AA102: =AA104-AA101 -> -35.245 | AB102: =AB104-AB101 -> -44.031 | AC102: =AC104-AC101 -> -43.341 | AD102: =AD104-AD101 -> -51.373 | AE102: =AE104-AE101 -> -53.157 | AF102: =-AF103*AF101 -> -57.63681 | AG102: =-AG103*AG101 -> -62.053838 | AH102: =-AH103*AH101 -> -67.451332 | AI102: =-AI103*AI101 -> -70.712437 | AJ102: =-AJ103*AJ101 -> -76.976966 | AK102: =-AK103*AK101 -> -80.873458 | AL102: =-AL103*AL101 -> -88.136928 | AM102: =-AM103*AM101 -> -98.648093 | ... AX102: =-AX103*AX101 -> -276.46423
B103: Income tax rate | E103: =-E102/E101 -> 0.070145141 | F103: =-F102/F101 -> 0.070239442 | G103: =-G102/G101 -> 0.070080046 | H103: =-H102/H101 -> 0.068931806 | I103: =-I102/I101 -> 0.075099279 | J103: =-J102/J101 -> 0.077864573 | K103: =-K102/K101 -> 0.080279137 | L103: =-L102/L101 -> 0.080281941 | ... T103: =-T102/T101 -> 0.11028931 | Y103: =-Y102/Y101 -> 0.069961881 | Z103: =-Z102/Z101 -> 0.067736212 | AA103: =-AA102/AA101 -> 0.068969363 | AB103: =-AB102/AB101 -> 0.080851353 | AC103: =-AC102/AC101 -> 0.073000778 | AD103: =-AD102/AD101 -> 0.082501991 | AE103: =-AE102/AE101 -> 0.078000458 | AF103: =AD103 -> 0.082501991 | AG103: =AE103 -> 0.078000458 | AH103: =AF103 -> 0.082501991 | AI103: =AG103 -> 0.078000458 | AJ103: =AH103 -> 0.082501991 | AK103: =AI103 -> 0.078000458 | AL103: =AJ103 -> 0.082501991 | AM103: =AK103+0.5% -> 0.083000458 | AN103: =AL103+0.5% -> 0.087501991 | AO103: =AM103+0.5% -> 0.088000458 | AP103: =AN103+0.5% -> 0.092501991 | AQ103: =AO103+0.5% -> 0.093000458 | AR103: =AP103+0.5% -> 0.097501991 | AS103: =AQ103+0.5% -> 0.098000458 | AT103: =AR103+0.5% -> 0.10250199 | ... AX103: =AV103+0.5% -> 0.11250199
B104: NPAT | E104: 614.9 | F104: 800.76 | G104: 1098.998 | H104: 1077.15 | I104: 976.34 | J104: 1121.68 | K104: =SUMIF($Y$2:$AX$2,K$2,$Y104:$AX104) -> 1269.3133 | L104: =SUMIF($Y$2:$AX$2,L$2,$Y104:$AX104) -> 1483.6244 | M104: =SUMIF($Y$2:$AX$2,M$2,$Y104:$AX104) -> 1691.9066 | N104: =SUMIF($Y$2:$AX$2,N$2,$Y104:$AX104) -> 1936.1233 | O104: =SUMIF($Y$2:$AX$2,O$2,$Y104:$AX104) -> 2208.306 | P104: =SUMIF($Y$2:$AX$2,P$2,$Y104:$AX104) -> 2521.8381 | Q104: =SUMIF($Y$2:$AX$2,Q$2,$Y104:$AX104) -> 2881.6369 | R104: =SUMIF($Y$2:$AX$2,R$2,$Y104:$AX104) -> 3293.4051 | ... T104: =SUMIF($Y$2:$AX$2,T$2,$Y104:$AX104) -> 4300.0179 | Y104: 577.988 | Z104: 499.162 | AA104: 475.779 | AB104: 500.561 | AC104: 550.365 | AD104: 571.315 | AE104: 628.339 | AF104: =AF101+AF102 -> 640.97433 | AG104: =AG101+AG102 -> 733.50352 | AH104: =AH101+AH102 -> 750.12083 | AI104: =AI101+AI102 -> 835.85195 | AJ104: =AJ101+AJ102 -> 856.05465 | AK104: =AK101+AK102 -> 955.95966 | AL104: =AL101+AL102 -> 980.16368 | AM104: =AM101+AM102 -> 1089.8766 | ... AX104: =AX101+AX102 -> 2180.9521
B105: Growth | F105: =F104/E104-1 -> 0.30226053 | G105: =G104/F104-1 -> 0.37244368 | H105: =H104/G104-1 -> -0.019879927 | I105: =I104/H104-1 -> -0.093589565 | J105: =J104/I104-1 -> 0.14886208 | K105: =K104/J104-1 -> 0.13161804 | L105: =L104/K104-1 -> 0.16884013 | M105: =M104/L104-1 -> 0.14038745 | ... T105: =T104/S104-1 -> 0.14249745 | AA105: =AA104/Y104-1 -> -0.17683585 | AB105: =AB104/Z104-1 -> 0.0028026973 | AC105: =AC104/AA104-1 -> 0.15676606 | AD105: =AD104/AB104-1 -> 0.14134941 | AE105: =AE104/AC104-1 -> 0.14167689 | AF105: =AF104/AD104-1 -> 0.12192806 | AG105: =AG104/AE104-1 -> 0.16736908 | AH105: =AH104/AF104-1 -> 0.17028217 | ... AX105: =AX104/AV104-1 -> 0.14278881
B106: NPAT margin | G106: =G104/G12 -> 0.083237491 | H106: =H104/H12 -> 0.081270314 | I106: =I104/I12 -> 0.071102671 | J106: =J104/J12 -> 0.076713819 | K106: =K104/K12 -> 0.081022644 | L106: =L104/L12 -> 0.084703063 | M106: =M104/M12 -> 0.088383015 | N106: =N104/N12 -> 0.092062774 | ... T106: =T104/T12 -> 0.11041638
B108: EPS | E108: =E104/E112 -> 0.33600965 | F108: =F104/F112 -> 0.43694809 | G108: =G104/G112 -> 0.59907731 | H108: =H104/H112 -> 0.58667293 | I108: =I104/I112 -> 0.53172263 | J108: =J104/J112 -> 0.61077415 | K108: =K104/K112 -> 0.69116305 | L108: =L104/L112 -> 0.8078591 | ... T108: =T104/T112 -> 2.3414341
B109: DPS | E109: 0.12218205 | F109: 0.1737 | G109: 0.2381 | H109: 0.2381 | I109: 0.2484 | J109: 0.2909 | K109: =K108*K110 -> 0.33670758 | L109: =L108*L110 -> 0.40092496 | M109: =M108*M110 -> 0.46723329 | N109: =N108*N110 -> 0.54429039 | O109: =O108*O110 -> 0.63389025 | P109: =P108*P110 -> 0.73641245 | Q109: =Q108*Q110 -> 0.8585507 | R109: =R108*R110 -> 0.99758728 | ... T109: =T108*T110 -> 1.6390039
B110: Payout ratio | E110: =E109/E108 -> 0.36362661 | F110: =F109/F108 -> 0.39753006 | G110: =G109/G108 -> 0.39744453 | H110: =H109/H108 -> 0.40584794 | I110: =I109/I108 -> 0.46716086 | J110: =J109/J108 -> 0.4762808 | K110: =I110+2% -> 0.48716086 | L110: =J110+2% -> 0.4962808 | M110: =K110+2% -> 0.50716086 | N110: =L110+2% -> 0.5162808 | O110: =M110+2% -> 0.52716086 | P110: =N110+2% -> 0.5362808 | Q110: =O110+2% -> 0.54716086 | R110: =P110+2% -> 0.5562808 | S110: =Q110+2% -> 0.56716086 | T110: =$D$125 -> 0.7
B112: Weighted avg diluted shares | E112: 1830.0069 | F112: 1832.6204 | G112: 1834.4844 | H112: 1836.0315 | I112: 1836.1829 | J112: 1836.489 | K112: =J112 -> 1836.489 | L112: =K112 -> 1836.489 | M112: =L112 -> 1836.489 | N112: =M112 -> 1836.489 | O112: =N112 -> 1836.489 | P112: =O112 -> 1836.489 | Q112: =P112 -> 1836.489 | R112: =Q112 -> 1836.489 | ... T112: =S112 -> 1836.489
B113: Outstanding shares | E113: 1830.0069 | F113: 1832.6204 | G113: 1834.4844 | H113: 1836.0315 | I113: 1836.1829 | J113: 1836.489 | K113: =J113 -> 1836.489 | L113: =K113 -> 1836.489 | M113: =L113 -> 1836.489 | N113: =M113 -> 1836.489 | O113: =N113 -> 1836.489 | P113: =O113 -> 1836.489 | Q113: =P113 -> 1836.489 | R113: =Q113 -> 1836.489 | ... T113: =S113 -> 1836.489
B115: CFO | E115: 724.273 | F115: 1159.065 | G115: -100.9 | H115: 1233.103 | I115: 2103.875 | J115: 2267.646 | K115: =K116*(K83+K98+K102) -> 1758.4975 | L115: =L116*(L83+L98+L102) -> 2021.0289 | M115: =M116*(M83+M98+M102) -> 2268.7785 | N115: =N116*(N83+N98+N102) -> 2558.3652 | O115: =O116*(O83+O98+O102) -> 2883.5777 | P115: =P116*(P83+P98+P102) -> 3256.6154 | Q115: =Q116*(Q83+Q98+Q102) -> 3682.7226 | R115: =R116*(R83+R98+R102) -> 4168.0435 | ... T115: =T116*(T83+T98+T102) -> 5345.7697
B116: Conversion | E116: =(E115-E98-E102)/E83 -> 0.78131299 | F116: =(F115-F98-F102)/F83 -> 0.96365247 | G116: =(G115-G98-G102)/G83 -> -0.013132757 | H116: =(H115-H98-H102)/H83 -> 0.79008595 | I116: =(I115-I98-I102)/I83 -> 1.2820946 | J116: =(J115-J98-J102)/J83 -> 1.1802158 | K116: 0.85 | L116: 0.85 | M116: 0.85 | N116: 0.85 | O116: 0.85 | P116: 0.85 | Q116: 0.85 | R116: 0.85 | S116: 0.85 | T116: 0.85
B117: CFI ex acquisitions/sales | E117: -456.608 | F117: -458.928 | G117: -746.5 | H117: -580.99 | I117: -501.573 | J117: -291.503 | K117: =K87 -> -799.50722 | L117: =L87 -> -894.05668 | M117: =M87 -> -977.24457 | N117: =N87 -> -1073.7181 | O117: =O87 -> -1184.1384 | P117: =P87 -> -1309.4741 | Q117: =Q87 -> -1450.9779 | R117: =R87 -> -1610.1754 | ... T117: =T87 -> -1989.1229
B118: FCF before Divs/buybacks | E118: =E115+E117 -> 267.665 | F118: =F115+F117 -> 700.137 | G118: =G115+G117 -> -847.4 | H118: =H115+H117 -> 652.113 | I118: =I115+I117 -> 1602.302 | J118: =J115+J117 -> 1976.143 | K118: =K115+K117 -> 958.99025 | L118: =L115+L117 -> 1126.9722 | ... T118: =T115+T117 -> 3356.6468
B120: Net Debt | E120: 75.187 | F120: -208.442 | G120: 1406.586 | H120: 1722.019 | I120: 997.882 | J120: 41.153
B122: DDM Valuation
B123: Equity Beta | D123: 1
B124: Ke | D124: =4%+6%*D123 -> 0.1
B125: LT payout ratio | D125: 0.7
B126: ROE | D126: 0.2
B127: Terminal growth | D127: =D126*(1-D125) -> 0.06
B128: Discount | K128: =1/(1+0.1)^(K3-$J$3) -> 0.90909091 | L128: =1/(1+0.1)^(L3-$J$3) -> 0.82644628 | M128: =1/(1+0.1)^(M3-$J$3) -> 0.7513148 | N128: =1/(1+0.1)^(N3-$J$3) -> 0.68301346 | O128: =1/(1+0.1)^(O3-$J$3) -> 0.62092132 | P128: =1/(1+0.1)^(P3-$J$3) -> 0.56447393 | Q128: =1/(1+0.1)^(Q3-$J$3) -> 0.51315812 | R128: =1/(1+0.1)^(R3-$J$3) -> 0.46650738 | ... T128: =1/(1+0.1)^(T3-$J$3) -> 0.38554329
B129: DDM Value | D129: US$/sh | E129: =SUM(K129:T129) -> 20.94586 | K129: =K109*K128 -> 0.3060978 | L129: =L109*L128 -> 0.33134294 | M129: =M109*M128 -> 0.35103929 | N129: =N109*N128 -> 0.37175766 | O129: =O109*O128 -> 0.39359597 | P129: =P109*P128 -> 0.41568563 | Q129: =Q109*Q128 -> 0.44057226 | R129: =R109*R128 -> 0.46538183 | S129: =S109*S128 -> 0.49294536 | T129: =(T109+(T109*(1+D127))/($D$124-D127))*T128 -> 17.377441
B130: DDM Value | D130: HKD/sh | E130: =E129*7.8 -> 163.3777 | F130: =E130/E131-1 -> 0.6321449
B131: Last price | D131: HKD/sh | E131: 100.1
B132: Implied PE | K132: =$E$129/K108 -> 30.305236 | L132: =$E$129/L108 -> 25.927615 | M132: =$E$129/M108 -> 22.735794 | N132: =$E$129/N108 -> 19.86797 | O132: =$E$129/O108 -> 17.419163 | P132: =$E$129/P108 -> 15.253493 | Q132: =$E$129/Q108 -> 13.348955 | R132: =$E$129/R108 -> 11.67996 | ... T132: =$E$129/T108 -> 8.9457396
B133: Implied EV/EBITDA | K133: =($E$129*K$113+$J$120)/K$83 -> 17.381569 | L133: =($E$129*L$113+$J$120)/L$83 -> 15.117571 | M133: =($E$129*M$113+$J$120)/M$83 -> 13.461529 | N133: =($E$129*N$113+$J$120)/N$83 -> 11.933398 | O133: =($E$129*O$113+$J$120)/O$83 -> 10.546306 | P133: =($E$129*P$113+$J$120)/P$83 -> 9.3010565 | Q133: =($E$129*Q$113+$J$120)/Q$83 -> 8.1914318 | R133: =($E$129*R$113+$J$120)/R$83 -> 7.2076175 | ... T133: =($E$129*T$113+$J$120)/T$83 -> 5.5719248
B134: Implied EV/Sales | K134: =($E$129*K$113+$J$120)/K$12 -> 2.4580373 | L134: =($E$129*L$113+$J$120)/L$12 -> 2.1984979 | M134: =($E$129*M$113+$J$120)/M$12 -> 2.0116078 | N134: =($E$129*N$113+$J$120)/N$12 -> 1.8310573 | O134: =($E$129*O$113+$J$120)/O$12 -> 1.6604602 | P134: =($E$129*P$113+$J$120)/P$12 -> 1.5016472 | Q134: =($E$129*Q$113+$J$120)/Q$12 -> 1.3552974 | R134: =($E$129*R$113+$J$120)/R$12 -> 1.2213791 | ... T134: =($E$129*T$113+$J$120)/T$12 -> 0.98881291
F135: =4500/L12 -> 0.25691394
B136: Consensus | N136: MS | O136: MS | P136: MS | Q136: GS | R136: GS | S136: GS
B137: Revenue | K137: =AVERAGE(N137,Q137) -> 15449.482 | L137: =AVERAGE(O137,R137) -> 16622.368 | M137: =AVERAGE(P137,S137) -> 17998.838 | N137: 15515.322 | O137: 16768.365 | P137: 18158.117 | Q137: 15383.641 | R137: 16476.37 | S137: 17839.56 | AG137: =AG141 -> 8742.1705 | AH137: =AH141 -> 8773.4222 | AI137: =AI141 -> 9542.5551 | AJ137: =INDEX($E137:$T137,MATCH(AJ$2,$E$2:$T$2,0))-SUM(AG137:AI137) -> -9059.3095
B138: EBIT | K138: =AVERAGE(N138,Q138) -> 1372.5827 | L138: =AVERAGE(O138,R138) -> 1548.0335 | M138: =AVERAGE(P138,S138) -> 1733.6435 | N138: 1361.4523 | O138: 1491.1115 | P138: 1650.1593 | Q138: 1383.7131 | R138: 1604.9555 | S138: 1817.1277 | AG138: =AG142 -> 1220.504 | AH138: =AH142 -> 1326.7302 | AI138: =AI142 -> 1370.4168
B139: NPAT | K139: =AVERAGE(N139,Q139) -> 1240.5462 | L139: =AVERAGE(O139,R139) -> 1429.4038 | M139: =AVERAGE(P139,S139) -> 1630.4367 | N139: 1246.7616 | O139: 1472.8233 | P139: 1689.1166 | Q139: 1234.3308 | R139: 1385.9842 | S139: 1571.7568 | AG139: =AG143 -> 733.50352 | AH139: =AH143 -> 750.12083 | AI139: =AI143 -> 835.85195 | AJ139: =INDEX($E139:$T139,MATCH(AJ$2,$E$2:$T$2,0))-SUM(AG139:AI139) -> -689.03961
B140: PW forecast
B141: Revenue | K141: =K12 -> 15666.155 | L141: =L12 -> 17515.593 | M141: =M12 -> 19142.893 | AG141: =AG12 -> 8742.1705 | AH141: =AH12 -> 8773.4222 | AI141: =AI12 -> 9542.5551 | AJ141: =INDEX($E141:$T141,MATCH(AJ$2,$E$2:$T$2,0))-SUM(AG141:AI141) -> -7915.2549
B142: EBIT | K142: =K95 -> 1415.9426 | L142: =L95 -> 1653.1776 | M142: =M95 -> 1883.3513 | AG142: =AG83 -> 1220.504 | AH142: =AH83 -> 1326.7302 | AI142: =AI83 -> 1370.4168
B143: NPAT | K143: =K104 -> 1269.3133 | L143: =L104 -> 1483.6244 | M143: =M104 -> 1691.9066 | AG143: =AG104 -> 733.50352 | AH143: =AH104 -> 750.12083 | AI143: =AI104 -> 835.85195 | AJ143: =INDEX($E143:$T143,MATCH(AJ$2,$E$2:$T$2,0))-SUM(AG143:AI143) -> -627.56971
B144: PW vs Consensus
B145: Revenue | K145: =K141/K137-1 -> 0.014024668 | L145: =L141/L137-1 -> 0.053736337 | M145: =M141/M137-1 -> 0.063562694 | AJ145: =AJ141/AJ137-1 -> -0.12628497
B146: EBIT | K146: =K142/K138-1 -> 0.03159001 | L146: =L142/L138-1 -> 0.067921066 | M146: =M142/M138-1 -> 0.086354423 | AJ146: =AJ142/AJ138-1 -> #DIV/0!
...

Sheet Sheet1
F6: FY24
F7: FY24 | T7: 1H25

Sheet Sheet2
A1: Item | B1: =Model!J2 -> FY0 | C1: =Model!K2 -> FY1 | D1: =Model!L2 -> FY2 | E1: =Model!M2 -> FY3
A2: FY | B2: =Model!J3 -> 2024 | C2: =Model!K3 -> 2025 | D2: =Model!L3 -> 2026 | E2: =Model!M3 -> 2027
A3: Consensus
A4: Revenue | C4: =Model!K137 -> 15449.482 | D4: =Model!L137 -> 16622.368 | E4: =Model!M137 -> 17998.838
A5: EBIT | C5: =Model!K138 -> 1372.5827 | D5: =Model!L138 -> 1548.0335 | E5: =Model!M138 -> 1733.6435
A6: NPAT | C6: =Model!K139 -> 1240.5462 | D6: =Model!L139 -> 1429.4038 | E6: =Model!M139 -> 1630.4367
A7: PW forecast
A8: Revenue | C8: =Model!K141 -> 15666.155 | D8: =Model!L141 -> 17515.593 | E8: =Model!M141 -> 19142.893
A9: EBIT | C9: =Model!K142 -> 1415.9426 | D9: =Model!L142 -> 1653.1776 | E9: =Model!M142 -> 1883.3513
A10: NPAT | C10: =Model!K143 -> 1269.3133 | D10: =Model!L143 -> 1483.6244 | E10: =Model!M143 -> 1691.9066
A11: PW vs Consensus
A12: Revenue | C12: =Model!K145 -> 0.014024668 | D12: =Model!L145 -> 0.053736337 | E12: =Model!M145 -> 0.063562694
A13: EBIT | C13: =Model!K146 -> 0.03159001 | D13: =Model!L146 -> 0.067921066 | E13: =Model!M146 -> 0.086354423
A14: NPAT | C14: =Model!K147 -> 0.023189092 | D14: =Model!L147 -> 0.037932291 | E14: =Model!M147 -> 0.037701494
