Workbook
Name _Model_Path: "Z:\CONSUMER_STAPLES\Mixuebingcheng\model\Mixue Group final-2025 Oct.xlsx"
Name add_factors: DCF!$D$118:$H$118
Name AddToExplicitPeriods: DCF!$H$133
Name Calculate: DCF!$D$130
Name changes_in_e: #REF!
Name chk_1: #REF!
Name CoE: DCF!$H$119
Name Company_IMPLICATION: #REF!
Name cu107.DPSSymbol: "Rmb"
Name Dashboard: DCF!#REF!
Name DB: "WIREUK"
Name DB: "WIREJPPROD"
Name dcf_mixue: DCF!$B$37:$O$58
Name DCFTitle: DCF!$B$3
Name Discount_rates: DCF!$B$38
Name end_date: #REF!
Name End_of_period_assumptions: DCF!$D$139
Name End_of_period_diluted_shares: DCF!$C$50
Name EntireDCF: DCF!$B$6:$AD$56
Name ExplicitPeriodChk: DCF!$D$133
Name F.2014.12: #REF!
Name F.2015.12: #REF!
Name F.2016.12: #REF!
Name F.2017.12: #REF!
Name F.2018.12: #REF!
Name F.2019.12: #REF!
Name F.2020.12: #REF!
Name F.2021.12: #REF!
Name F.2022.12: #REF!
Name F.2023.12: #REF!
Name FadeToTerminalPeriod: DCF!$H$137
Name FCFF: DCF!$B$33
Name financial_forecast: #REF!
Name financials: #REF!
Name forecastchanges: #REF!
Name FY5Period: DCF!$R$6
Name I1.2014.06: #REF!
Name I1.2015.06: #REF!
Name I1.2016.06: #REF!
Name I1.2017.06: #REF!
Name I1.2018.06: #REF!
Name I1.2019.06: #REF!
Name I1.2020.06: #REF!
Name I1.2021.06: #REF!
Name I1.2022.06: #REF!
Name I1.2023.06: #REF!
Name I2.2014.12: #REF!
Name I2.2015.12: #REF!
Name I2.2016.12: #REF!
Name I2.2017.12: #REF!
Name I2.2018.12: #REF!
Name I2.2019.12: #REF!
Name I2.2020.12: #REF!
Name I2.2021.12: #REF!
Name I2.2022.12: #REF!
Name I2.2023.12: #REF!
Name Inputs___Assumptions: DCF!$B$105
Name Japan_stock_MSCI: #REF!
Name Key_items: DCF!$B$150
Name KeyitemsFY5: DCF!$R$149

Sheet VA-Disclaimer

Sheet DCF
A1: 1 | B1: =A1+1 -> 2 | C1: =B1+1 -> 3 | D1: =C1+1 -> 4 | E1: =D1+1 -> 5 | F1: =E1+1 -> 6 | G1: =F1+1 -> 7 | H1: =G1+1 -> 8 | J1: =H1+1 -> 9 | K1: =J1+1 -> 10 | L1: =K1+1 -> 11 | M1: =L1+1 -> 12 | N1: =M1+1 -> 13 | O1: =N1+1 -> 14 | P1: =O1+1 -> 15 | Q1: =P1+1 -> 16 | R1: 17 | AK1: [+] CAGR =>
B2: ab | G2: ="PT is " &H111&" "&ROUND(H57,2) -> PT is HKD 493.78 | M2: ="Price Target as of "&TEXT(H54, "dd mmm yyyy")&" is: " -> Price Target as of 13 Nov 2026 is: | Q2: =H111&" "&ROUND(H57,2) -> HKD 493.78 | AV2: =COLUMN() -> 48
B3: =$H$107&" DCF Valuation ("&$H$110&$H$113&" unless specified)" -> Mixue DCF Valuation (RMBk unless specified) | M3: Midpoint of offer price | Q3: 200 | R3: =PT/Q3-1 -> 1.4688875
M4: Stage One | S4: Stage Two | X4: Fade to Terminal period
B6: Periods counter | J6: =K6-1 -> -3 | K6: =L6-1 -> -2 | L6: =M6-1 -> -1 | M6: 0 | N6: =M6+1 -> 1 | O6: =N6+1 -> 2 | P6: =O6+1 -> 3 | Q6: =P6+1 -> 4 | R6: =Q6+1 -> 5 | S6: =R6+1 -> 6 | T6: =S6+1 -> 7 | U6: =T6+1 -> 8 | ... AB6: =AA6+1 -> 15 | AC6: Last Forecast | AD6: Terminal | AF6: Term. period | AH6: Stage 1 | AI6: Stage 2 | AJ6: Fade | AK6: Valuation Summary
B7: Periods end dates | J7: =EOMONTH($H$108,12*J6) -> 44561 | K7: =EOMONTH($H$108,12*K6) -> 44926 | L7: =EOMONTH($H$108,12*L6) -> 45291 | M7: =EOMONTH($H$108,12*M6) -> 45657 | N7: =EOMONTH($H$108,12*N6) -> 46022 | O7: =EOMONTH($H$108,12*O6) -> 46387 | P7: =EOMONTH($H$108,12*P6) -> 46752 | Q7: =EOMONTH($H$108,12*Q6) -> 47118 | ... AB7: =EOMONTH($H$108,12*AB6) -> 51135 | AC7: Period | AD7: Period | AF7: YoY growth | AH7: CAGR | AI7: CAGR | AJ7: CAGR | AK7: Assumptions
AH8: 5 | AI8: 5 | AJ8: 6 | AK8: Model forecasts
B9: Operating model
C10: Revenue | L10: =L153 -> 20302465 | M10: =M153 -> 24828874 | N10: =N153 -> 32189782 | O10: =O153 -> 35717844 | P10: =P153 -> 41517893 | Q10: =Q153 -> 47649032 | R10: =R153 -> 53780423 | S10: =R10*(1+S11) -> 60413837 | T10: =S10*(1+T11) -> 67543087 | U10: =T10*(1+U11) -> 75153252 | V10: =U10*(1+V11) -> 83219874 | W10: =V10*(1+W11) -> 91708301 | X10: =W10*(1+X11) -> 99962048 | Y10: =X10*(1+Y11) -> 1.0775909e+08 | Z10: =Y10*(1+Z11) -> 1.1487119e+08 | ... AD10: =AC10*(1+AD11) -> 1.3384245e+08 | AF10: =AD10/AC10-1 -> 0.03 | AH10: =(R10/ M10) ^ (1 /AH8) - 1 -> 0.16716818 | AI10: =(W10/ R10) ^ (1 /AI8) - 1 -> 0.11264568 | AJ10: =(AC10/ W10) ^ (1 /AJ8) - 1 -> 0.059801841
D11: YoY growth | L11: =IFERROR(L10/K10-1,"") | M11: =IFERROR(M10/L10-1,"") -> 0.22294874 | N11: =IFERROR(N10/M10-1,"") -> 0.29646564 | O11: =IFERROR(O10/N10-1,"") -> 0.10960191 | P11: =IFERROR(P10/O10-1,"") -> 0.16238522 | Q11: =IFERROR(Q10/P10-1,"") -> 0.14767462 | R11: =IFERROR(R10/Q10-1,"") -> 0.12867817 | S11: =R11-(R11-St2GR)/5 -> 0.12334254 | T11: =S11-(R11-St2GR)/5 -> 0.1180069 | U11: =T11-(R11-St2GR)/5 -> 0.11267127 | V11: =U11-(R11-St2GR)/5 -> 0.10733563 | W11: =V11-(R11-St2GR)/5 -> 0.102 | X11: =W11-(W11-PenGR)/6 -> 0.09 | Y11: =X11-(W11-PenGR)/6 -> 0.078 | Z11: =Y11-(W11-PenGR)/6 -> 0.066 | AA11: =Z11-(W11-PenGR)/6 -> 0.054 | AB11: =AA11-(W11-PenGR)/6 -> 0.042 | AC11: =AD11 -> 0.03 | AD11: =H140 -> 0.03
C12: EBITDA | L12: =L154 -> 4268960 | M12: =M154 -> 6035889 | N12: =N154 -> 7641476.9 | O12: =O154 -> 8690498.7 | P12: =P154 -> 10484220 | Q12: =Q154 -> 11878807 | R12: =R154 -> 13251088 | S12: =S13*S10 -> 15068052 | T12: =T13*T10 -> 17050269 | U12: =U13*U10 -> 19198422 | V12: =V13*V10 -> 21510547 | W12: =W13*W10 -> 23981721 | X12: =X13*X10 -> 24282448 | Y12: =Y13*Y10 -> 24173955 | Z12: =Z13*Z10 -> 23634747 | ... AD12: =AD13*AD10 -> 20076368 | AF12: =AD12/AC12-1 -> 0.03 | AH12: =(R12/ M12) ^ (1 /AH8) - 1 -> 0.17031308 | AI12: =(W12/ R12) ^ (1 /AI8) - 1 -> 0.12596726 | AJ12: =(AC12/ W12) ^ (1 /AJ8) - 1 -> -0.033961139
D13: EBITDA margin | L13: =IFERROR(L12/L10,"") -> 0.21026806 | M13: =IFERROR(M12/M10,"") -> 0.24309959 | N13: =IFERROR(N12/N10,"") -> 0.23738828 | O13: =IFERROR(O12/O10,"") -> 0.24330973 | P13: =IFERROR(P12/P10,"") -> 0.25252294 | Q13: =IFERROR(Q12/Q10,"") -> 0.24929798 | R13: =IFERROR(R12/R10,"") -> 0.24639241 | S13: =R13-(R13-St2EBITDAMargin)/5 -> 0.24941393 | T13: =S13-(R13-St2EBITDAMargin)/5 -> 0.25243545 | U13: =T13-(R13-St2EBITDAMargin)/5 -> 0.25545696 | V13: =U13-(R13-St2EBITDAMargin)/5 -> 0.25847848 | W13: =V13-(R13-St2EBITDAMargin)/5 -> 0.2615 | X13: =W13-(W13-PenEBITDAMargin)/6 -> 0.24291667 | Y13: =X13-(W13-PenEBITDAMargin)/6 -> 0.22433333 | Z13: =Y13-(W13-PenEBITDAMargin)/6 -> 0.20575 | AA13: =Z13-(W13-PenEBITDAMargin)/6 -> 0.18716667 | AB13: =AA13-(W13-PenEBITDAMargin)/6 -> 0.16858333 | AC13: =AD13 -> 0.15 | AD13: =H141 -> 0.15
C14: EBIT | L14: =L155 -> 4001184 | M14: =M155 -> 5616534 | N14: =N155 -> 6890556.7 | O14: =O155 -> 7663217.7 | P14: =P155 -> 8906197 | Q14: =Q155 -> 10229302 | R14: =R155 -> 11556678 | S14: =S12-S21 -> 13274731 | T14: =T12-T21 -> 15166092 | U14: =U12-U21 -> 17233834 | V14: =V12-V21 -> 19478443 | W14: =W12-W21 -> 21897441 | X14: =X12-X21 -> 22010583 | Y14: =Y12-Y21 -> 21724885 | Z14: =Z12-Z21 -> 21024038 | ... AD14: =AD12-AD21 -> 17034494 | AF14: =AD14/AC14-1 -> 0.03 | AH14: =(R14/ M14) ^ (1 /AH8) - 1 -> 0.15524188 | AI14: =(W14/ R14) ^ (1 /AI8) - 1 -> 0.13634988 | AJ14: =(AC14/ W14) ^ (1 /AJ8) - 1 -> -0.04570399
D15: EBIT margin | L15: =IFERROR(L14/L10,"") -> 0.19707873 | M15: =IFERROR(M14/M10,"") -> 0.22620977 | N15: =IFERROR(N14/N10,"") -> 0.21406037 | O15: =IFERROR(O14/O10,"") -> 0.21454872 | P15: =IFERROR(P14/P10,"") -> 0.21451467 | Q15: =IFERROR(Q14/Q10,"") -> 0.21468017 | R15: =IFERROR(R14/R10,"") -> 0.21488634 | S15: =IFERROR(S14/S10,"") -> 0.21972998 | ... AE15: =IFERROR(AE14/AE10,"") | AK15: =IFERROR(AK14/AK10,"") | AL15: =IFERROR(AL14/AL10,"") | AM15: =IFERROR(AM14/AM10,"") | AN15: =IFERROR(AN14/AN10,"") | AO15: =IFERROR(AO14/AO10,"") | AP15: =IFERROR(AP14/AP10,"") | AQ15: =IFERROR(BF8/BF6,"") | AR15: =IFERROR(AR14/AR10,"") | AS15: =IFERROR(AS14/AS10,"") | AT15: =IFERROR(AT14/AT10,"") | AU15: =IFERROR(AU14/AU10,"") | AV15: =IFERROR(AV14/AV10,"") | AW15: =IFERROR(AW14/AW10,"") | AX15: =IFERROR(AX14/AX10,"") | AY15: =IFERROR(AY14/AY10,"") | ... BE15: =IFERROR(BE14/BE10,"") | BF15: =IFERROR(BF14/#REF!,"") | BG15: =IFERROR(BG14/BG10,"") | BH15: =IFERROR(BH14/BH10,"") | BI15: =IFERROR(BI14/BI10,"") | BJ15: =IFERROR(BJ14/BJ10,"") | BK15: =IFERROR(BK14/BK10,"") | BL15: =IFERROR(BL14/BL10,"") | BM15: =IFERROR(BM14/BM10,"") | BN15: =IFERROR(BN14/BN10,"") | ... AFZ15: =IFERROR(AFZ14/AFZ10,"")
C16: (-) Tax expense (net of interest tax shield benefit) | L16: =L156 -> -957621 | M16: =M156 -> -1331218 | N16: =N156 -> -1571811.3 | O16: =O156 -> -1744940.8 | P16: =P156 -> -2025287.2 | Q16: =Q156 -> -2323072.5 | R16: =R156 -> -2621249.5 | S16: =-S17*S14 -> -3072482.9 | T16: =-T17*T14 -> -3580564.4 | U16: =-U17*U14 -> -4148644.7 | V16: =-V17*V14 -> -4779296.4 | W16: =-W17*W14 -> -5474360.3 | X16: =-X17*X14 -> -5502645.7 | Y16: =-Y17*Y14 -> -5431221.3 | Z16: =-Z17*Z14 -> -5256009.5 | ... AD16: =-AD17*AD14 -> -4258623.5 | AF16: =AD16/AC16-1 -> 0.03 | AH16: =(R16/ M16) ^ (1 /AH8) - 1 -> 0.14512221 | AI16: =(W16/ R16) ^ (1 /AI8) - 1 -> 0.15868398 | AJ16: =(AC16/ W16) ^ (1 /AJ8) - 1 -> -0.04570399
D17: Implied tax rate | L17: =IFERROR(-L16/L14,"") -> 0.23933441 | M17: =IFERROR(-M16/M14,"") -> 0.23701771 | N17: =IFERROR(-N16/N14,"") -> 0.22811093 | O17: =IFERROR(-O16/O14,"") -> 0.22770341 | P17: =IFERROR(-P16/P14,"") -> 0.22740203 | Q17: =IFERROR(-Q16/Q14,"") -> 0.2270998 | R17: =IFERROR(-R16/R14,"") -> 0.22681687 | S17: =R17-(R17-St2TaxRate)/5 -> 0.2314535 | T17: =S17-(R17-St2TaxRate)/5 -> 0.23609012 | U17: =T17-(R17-St2TaxRate)/5 -> 0.24072675 | V17: =U17-(R17-St2TaxRate)/5 -> 0.24536337 | W17: =V17-(R17-St2TaxRate)/5 -> 0.25 | X17: =W17-(W17-PenTaxRate)/6 -> 0.25 | Y17: =X17-(W17-PenTaxRate)/6 -> 0.25 | Z17: =Y17-(W17-PenTaxRate)/6 -> 0.25 | AA17: =Z17-(W17-PenTaxRate)/6 -> 0.25 | AB17: =AA17-(W17-PenTaxRate)/6 -> 0.25 | AC17: =AD17 -> 0.25 | AD17: =H142 -> 0.25
C18: NOPAT | L18: =L14+L16 -> 3043563 | M18: =M14+M16 -> 4285316 | N18: =N14+N16 -> 5318745.3 | O18: =O14+O16 -> 5918277 | P18: =P14+P16 -> 6880909.8 | Q18: =Q14+Q16 -> 7906229.9 | R18: =R14+R16 -> 8935428.5 | S18: =S14+S16 -> 10202248 | ... AD18: =AD14+AD16 -> 12775871 | AF18: =AD18/AC18-1 -> 0.03 | AH18: =(R18/ M18) ^ (1 /AH8) - 1 -> 0.15831453 | AI18: =(W18/ R18) ^ (1 /AI8) - 1 -> 0.12945218 | AJ18: =(AC18/ W18) ^ (1 /AJ8) - 1 -> -0.04570399
B20: Reinvestments
C21: (+) Depreciation and amortisation | L21: =L157 -> 267776 | M21: =M157 -> 419355 | N21: =N157 -> 750920.21 | O21: =O157 -> 1027281 | P21: =P157 -> 1578023.4 | Q21: =Q157 -> 1649505 | R21: =R157 -> 1694410 | S21: =-S24/S23 -> 1793321.1 | T21: =-T24/T23 -> 1884177.5 | U21: =-U24/U23 -> 1964587.8 | V21: =-V24/V23 -> 2032104.1 | W21: =-W24/W23 -> 2084279.6 | X21: =-X24/X23 -> 2271864.7 | Y21: =-Y24/Y23 -> 2449070.2 | Z21: =-Z24/Z23 -> 2610708.8 | ... AD21: =-AD24/AD23 -> 3041874 | AF21: =AD21/AC21-1 -> 0.03 | AH21: =(R21/ M21) ^ (1 /AH8) - 1 -> 0.32217011 | AI21: =(W21/ R21) ^ (1 /AI8) - 1 -> 0.042287416 | AJ21: =(AC21/ W21) ^ (1 /AJ8) - 1 -> 0.059801841
D22: D&A as a % of sales | L22: =IFERROR(L21/L10,"") -> 0.013189334 | M22: =IFERROR(M21/M10,"") -> 0.016889811 | N22: =IFERROR(N21/N10,"") -> 0.023327906 | O22: =IFERROR(O21/O10,"") -> 0.028761003 | P22: =IFERROR(P21/P10,"") -> 0.038008273 | Q22: =IFERROR(Q21/Q10,"") -> 0.034617806 | R22: =IFERROR(R21/R10,"") -> 0.031506074 | S22: =IFERROR(S21/S10,"") -> 0.029683946 | ... AD22: =IFERROR(AD21/AD10,"") -> 0.022727273
D23: Capex / Depreciation ratio | L23: =IFERROR(-L24/L21,"") -> 6.6693356 | M23: =IFERROR(-M24/M21,"") -> 3.5175615 | N23: =IFERROR(-N24/N21,"") -> 2.6299478 | O23: =IFERROR(-O24/O21,"") -> 1.8850826 | P23: =IFERROR(-P24/P21,"") -> 1.2389675 | Q23: =IFERROR(-Q24/Q21,"") -> 1.1462404 | R23: =IFERROR(-R24/R21,"") -> 1.0499185 | S23: =R23-(R23-St2CapDepr)/5 -> 1.0599348 | T23: =S23-(R23-St2CapDepr)/5 -> 1.0699511 | U23: =T23-(R23-St2CapDepr)/5 -> 1.0799674 | V23: =U23-(R23-St2CapDepr)/5 -> 1.0899837 | W23: =V23-(R23-St2CapDepr)/5 -> 1.1 | X23: =W23-(W23-PenCapDepr)/6 -> 1.1 | Y23: =X23-(W23-PenCapDepr)/6 -> 1.1 | Z23: =Y23-(W23-PenCapDepr)/6 -> 1.1 | AA23: =Z23-(W23-PenCapDepr)/6 -> 1.1 | AB23: =AA23-(W23-PenCapDepr)/6 -> 1.1 | AC23: =AD23 -> 1.1 | AD23: =H143 -> 1.1
C24: (-) Capex | L24: =L158 -> -1785888 | M24: =M158 -> -1475107 | N24: =N158 -> -1974880.9 | O24: =O158 -> -1936509.6 | P24: =P158 -> -1955119.7 | Q24: =Q158 -> -1890729.3 | R24: =R158 -> -1778992.3 | S24: =-S25*S10 -> -1900803.4 | T24: =-T25*T10 -> -2015977.8 | U24: =-U25*U10 -> -2121690.8 | V24: =-V25*V10 -> -2214960.3 | W24: =-W25*W10 -> -2292707.5 | X24: =-X25*X10 -> -2499051.2 | Y24: =-Y25*Y10 -> -2693977.2 | Z24: =-Z25*Z10 -> -2871779.7 | ... AD24: =-AD25*AD10 -> -3346061.3 | AF24: =AD24/AC24-1 -> 0.03 | AH24: =(R24/ M24) ^ (1 /AH8) - 1 -> 0.038173909 | AI24: =(W24/ R24) ^ (1 /AI8) - 1 -> 0.052046453 | AJ24: =(AC24/ W24) ^ (1 /AJ8) - 1 -> 0.059801841
D25: Capex as a % of sales | L25: =IFERROR(-L24/L10,"") -> 0.087964097 | M25: =IFERROR(-M24/M10,"") -> 0.05941095 | N25: =IFERROR(-N24/N10,"") -> 0.061351174 | O25: =IFERROR(-O24/O10,"") -> 0.054216866 | P25: =IFERROR(-P24/P10,"") -> 0.047091015 | Q25: =IFERROR(-Q24/Q10,"") -> 0.039680329 | R25: =IFERROR(-R24/R10,"") -> 0.033078809 | S25: =R25-(R25-St2Cap_Sales)/5 -> 0.031463047 | T25: =S25-(R25-St2Cap_Sales)/5 -> 0.029847285 | U25: =T25-(R25-St2Cap_Sales)/5 -> 0.028231524 | V25: =U25-(R25-St2Cap_Sales)/5 -> 0.026615762 | W25: =V25-(R25-St2Cap_Sales)/5 -> 0.025 | X25: =W25-(W25-PenCap_Sales)/6 -> 0.025 | Y25: =X25-(W25-PenCap_Sales)/6 -> 0.025 | Z25: =Y25-(W25-PenCap_Sales)/6 -> 0.025 | AA25: =Z25-(W25-PenCap_Sales)/6 -> 0.025 | AB25: =AA25-(W25-PenCap_Sales)/6 -> 0.025 | AC25: =AD25 -> 0.025 | AD25: =H144 -> 0.025
C26: Change in net working capital | L26: =L159 -> 630433 | M26: =M159 -> 928522 | N26: =N159 -> 625416.21 | O26: =O159 -> 304746.04 | P26: =P159 -> 482505.42 | Q26: =Q159 -> 527604.27 | R26: =R159 -> 550157.63 | S26: =(R10-S10)*S27+((R27-S27)*R10) -> 73002.879 | T26: =(S10-T10)*T27+((S27-T27)*S10) -> 9686.6385 | U26: =(T10-U10)*U27+((T27-U27)*T10) -> -64937.317 | V26: =(U10-V10)*V27+((U27-V27)*U10) -> -150896.56 | W26: =(V10-W10)*W27+((V27-W27)*V10) -> -247908.18 | X26: =(W10-X10)*X27+((W27-X27)*W10) -> 330149.88 | Y26: =(X10-Y10)*Y27+((X27-Y27)*X10) -> 311881.59 | Z26: =(Y10-Z10)*Z27+((Y27-Z27)*Y10) -> 284483.99 | ... AD26: =(AC10-AD10)*AD27+((AC27-AD27)*AC10) -> 155932.96 | AF26: =AD26/AC26-1 -> 0.03 | AH26: =(R26/ M26) ^ (1 /AH8) - 1 -> -0.099385389 | AI26: =(W26/ R26) ^ (1 /AI8) - 1 -> -1.8526303 | AJ26: =(AC26/ W26) ^ (1 /AJ8) - 1 -> #NUM!
D27: Working capital turnover (%) | L27: =IFERROR(L182/L10,"") -> -0.031052042 | M27: =IFERROR(M182/M10,"") -> -0.062787986 | N27: =IFERROR(N182/N10,"") -> -0.067859149 | O27: =IFERROR(O182/O10,"") -> -0.069688341 | P27: =IFERROR(P182/P10,"") -> -0.071574505 | Q27: =IFERROR(Q182/Q10,"") -> -0.073437524 | R27: =IFERROR(R182/R10,"") -> -0.07529477 | S27: =R27-(R27-St2WC)/5 -> -0.068235816 | T27: =S27-(R27-St2WC)/5 -> -0.061176862 | U27: =T27-(R27-St2WC)/5 -> -0.054117908 | V27: =U27-(R27-St2WC)/5 -> -0.047058954 | W27: =V27-(R27-St2WC)/5 -> -0.04 | X27: =W27-(W27-PenWC)/5 -> -0.04 | Y27: =X27-(W27-PenWC)/5 -> -0.04 | Z27: =Y27-(W27-PenWC)/5 -> -0.04 | AA27: =Z27-(W27-PenWC)/5 -> -0.04 | AB27: =AC27 -> -0.04 | AC27: =AD27 -> -0.04 | AD27: =H145 -> -0.04
C28: (-) Net acquisitions | L28: =L160 -> 0 | M28: =M160 -> 0 | N28: =N160 -> 0 | O28: =O160 -> 0 | P28: =P160 -> 0 | Q28: =Q160 -> 0 | R28: =R160 -> 0 | S28: 0 | T28: 0 | U28: 0 | V28: 0 | W28: 0 | X28: 0 | Y28: 0 | Z28: 0 | AA28: 0 | AB28: 0 | AC28: 0 | AD28: 0
C29: Reinvestments | L29: =L21+L24+L26+L28 -> -887679 | M29: =M21+M24+M26+M28 -> -127230 | N29: =N21+N24+N26+N28 -> -598544.5 | O29: =O21+O24+O26+O28 -> -604482.52 | P29: =P21+P24+P26+P28 -> 105409.11 | Q29: =Q21+Q24+Q26+Q28 -> 286379.98 | R29: =R21+R24+R26+R28 -> 465575.28 | S29: =S21+S24+S26+S28 -> -34479.415 | ... AD29: =AD21+AD24+AD26+AD28 -> -148254.44 | AF29: =AD29/AC29-1 -> 0.03 | AH29: =(R29/ M29) ^ (1 /AH8) - 1 -> -2.2962241 | AI29: =(W29/ R29) ^ (1 /AI8) - 1 -> -1.9959992 | AJ29: =(AC29/ W29) ^ (1 /AJ8) - 1 -> -0.17494873
D30: Reinvestment as a % of NOPAT | L30: =IFERROR(-L29/L18,"") -> 0.29165784 | M30: =IFERROR(-M29/M18,"") -> 0.029689759 | N30: =IFERROR(-N29/N18,"") -> 0.1125349 | O30: =IFERROR(-O29/O18,"") -> 0.10213826 | P30: =IFERROR(-P29/P18,"") -> -0.015319066 | Q30: =IFERROR(-Q29/Q18,"") -> -0.036222065 | R30: =IFERROR(-R29/R18,"") -> -0.052104416 | S30: =-IFERROR(S29/S18,"") -> 0.0033795899 | T30: =-IFERROR(T29/T18,"") -> 0.010540186 | U30: =-IFERROR(U29/U18,"") -> 0.016968824 | V30: =-IFERROR(V29/V18,"") -> 0.02270559 | W30: =-IFERROR(W29/W18,"") -> 0.027786269 | X30: =-IFERROR(X29/X18,"") -> -0.0062372064 | Y30: =-IFERROR(Y29/Y18,"") -> -0.0041104673 | Z30: =-IFERROR(Z29/Z18,"") -> -0.0014848471 | ... AD30: =-IFERROR(AD29/AD18,"") -> 0.011604253
C31: Other (items not captured elsewhere) | L31: =L161 -> 98178 | M31: =M161 -> 103567 | N31: =N161 -> 115268.45 | O31: =O161 -> 124088.61 | P31: =P161 -> 138588.73 | Q31: =Q161 -> 153916.58 | R31: =R161 -> 169245.06 | S31: =R31*(1+S32) -> 148880.07 | T31: =S31*(1+T32) -> 98224.178 | U31: =T31*(1+U32) -> 43202.51 | V31: =U31*(1+V32) -> 9501.0053 | W31: =V31*(1+W32) -> 0 | X31: =W31*(1+X32) -> 0 | Y31: =X31*(1+Y32) -> 0 | Z31: =Y31*(1+Z32) -> 0 | ... AD31: =AC31*(1+AD32) -> 0
D32: YoY growth | L32: =IFERROR(L31/K31-1,0) -> 0 | M32: =IFERROR(M31/L31-1,0) -> 0.054890084 | N32: =IFERROR(N31/M31-1,0) -> 0.1129844 | O32: =IFERROR(O31/N31-1,0) -> 0.076518366 | P32: =IFERROR(P31/O31-1,0) -> 0.11685299 | Q32: =IFERROR(Q31/P31-1,0) -> 0.11059952 | R32: =IFERROR(R31/Q31-1,0) -> 0.099589506 | S32: =R32-(R32-St2OtherItems)/5 -> -0.12032839 | T32: =S32-(R32-St2OtherItems)/5 -> -0.3402463 | U32: =T32-(R32-St2OtherItems)/5 -> -0.5601642 | V32: =U32-(R32-St2OtherItems)/5 -> -0.7800821 | W32: =V32-(R32-St2OtherItems)/5 -> -1 | X32: =W32-(W32-PenOtherItemsGR)/6 -> -0.82833333 | Y32: =X32-(W32-PenOtherItemsGR)/6 -> -0.65666667 | Z32: =Y32-(W32-PenOtherItemsGR)/6 -> -0.485 | AA32: =Z32-(W32-PenOtherItemsGR)/6 -> -0.31333333 | AB32: =AA32-(W32-PenOtherItemsGR)/6 -> -0.14166667 | AC32: =AD32 -> 0.03 | AD32: =H140 -> 0.03
B33: FCFF | L33: =L18+L29+L31 -> 2254062 | M33: =M18+M29+M31 -> 4261653 | N33: =N18+N29+N31 -> 4835469.3 | O33: =O18+O29+O31 -> 5437883.1 | P33: =P18+P29+P31 -> 7124907.6 | Q33: =Q18+Q29+Q31 -> 8346526.5 | R33: =R18+R29+R31 -> 9570248.8 | S33: =S18+S29+S31 -> 10316649 | ... AD33: =AD18+AD29+AD31 -> 12627616 | AF33: =AD33/AC33-1 -> 0.03 | AH33: =(R33/ M33) ^ (1 /AH8) - 1 -> 0.17562558 | AI33: =(W33/ R33) ^ (1 /AI8) - 1 -> 0.10779304 | AJ33: =(AC33/ W33) ^ (1 /AJ8) - 1 -> -0.043074868
C35: Terminal value | AD35: =AD33/(WACC-H140) -> 1.9900112e+08
M36: Value as at
B37: DCF Valuation (Rmb '000) | M37: =M7 -> 45657 | N37: =N7 -> 46022 | O37: =O7 -> 46387 | P37: =P7 -> 46752 | Q37: =Q7 -> 47118 | R37: =R7 -> 47483
B38: Terminal value discount factor | M38: =1/(1+WACC)^COLUMNS(N7:$AC$7) -> 0.23943375 | N38: =1/(1+WACC)^COLUMNS(O7:$AC$7) -> 0.26181003 | O38: =1/(1+WACC)^COLUMNS(P7:$AC$7) -> 0.28627748 | P38: =1/(1+WACC)^COLUMNS(Q7:$AC$7) -> 0.31303155 | Q38: =1/(1+WACC)^COLUMNS(R7:$AC$7) -> 0.34228591 | R38: =1/(1+WACC)^COLUMNS(S7:$AC$7) -> 0.37427424
B39: PV of visible period FCFs | M39: =IFERROR(NPV(WACC,N33:$AC$33),"n/a") -> 85439235 | N39: =IFERROR(NPV(WACC,O33:$AC$33),"n/a") -> 88588490 | O39: =IFERROR(NPV(WACC,P33:$AC$33),"n/a") -> 91429644 | P39: =IFERROR(NPV(WACC,Q33:$AC$33),"n/a") -> 92849294 | Q39: =IFERROR(NPV(WACC,R33:$AC$33),"n/a") -> 93179998 | R39: =IFERROR(NPV(WACC,S33:$AC$33),"n/a") -> 92317886
B40: PV of Terminal Value | M40: =IFERROR($AD$35*M38,"n/a") -> 47647584 | N40: =IFERROR($AD$35*N38,"n/a") -> 52100489 | O40: =IFERROR($AD$35*O38,"n/a") -> 56969541 | P40: =IFERROR($AD$35*P38,"n/a") -> 62293629 | Q40: =IFERROR($AD$35*Q38,"n/a") -> 68115280 | R40: =IFERROR($AD$35*R38,"n/a") -> 74480994
B41: =$H$107&" Enterprise Value" -> Mixue Enterprise Value | M41: =IFERROR(SUM(M39:M40),"n/a") -> 1.3308682e+08 | N41: =IFERROR(SUM(N39:N40),"n/a") -> 1.4068898e+08 | O41: =IFERROR(SUM(O39:O40),"n/a") -> 1.4839918e+08 | P41: =IFERROR(SUM(P39:P40),"n/a") -> 1.5514292e+08 | Q41: =IFERROR(SUM(Q39:Q40),"n/a") -> 1.6129528e+08 | R41: =IFERROR(SUM(R39:R40),"n/a") -> 1.6679888e+08
B42: (- /+) Net (debt) / cash (Incl. finance leases if appl.) | M42: =M172 -> 7525301 | N42: =N172 -> 15571506 | O42: =O172 -> 20962270 | P42: =P172 -> 28096079 | Q42: =Q172 -> 36527232 | R42: =R172 -> 46273501
B43: (+) Associates / JV value | M43: =M174 -> 0 | N43: =N174 -> 0 | O43: =O174 -> 0 | P43: =P174 -> 0 | Q43: =Q174 -> 0 | R43: =R174 -> 0
B44: (-) Non-controlling Interest / Minority Interest | M44: =M173 -> -105301 | N44: =N173 -> -143416.01 | O44: =O173 -> -186265.69 | P44: =P173 -> -236344.35 | Q44: =Q173 -> -294251.92 | R44: =R173 -> -360136
B45: Sum of other Items (if applicable) | M45: =SUM(M46:M48) -> 3594004 | N45: =SUM(N46:N48) -> 3805408.5 | O45: =SUM(O46:O48) -> 4029612.8 | P45: =SUM(P46:P48) -> 4267391.6 | Q45: =SUM(Q46:Q48) -> 4519567 | R45: =SUM(R46:R48) -> 4787010.5
C46: (+/-) Pension fund net asset / (liabilities) | M46: =M175 -> 0 | N46: =N175 -> 0 | O46: =O175 -> 0 | P46: =P175 -> 0 | Q46: =Q175 -> 0 | R46: =R175 -> 0
C47: (+/-) Other financial assets / (liabilities) | M47: =M176 -> 3498233 | N47: =N176 -> 3709637.5 | O47: =O176 -> 3933841.8 | P47: =P176 -> 4171620.6 | Q47: =Q176 -> 4423796 | R47: =R176 -> 4691239.5
C48: (+/-) Other items | M48: =M177 -> 95771 | N48: =N177 -> 95771 | O48: =O177 -> 95771 | P48: =P177 -> 95771 | Q48: =Q177 -> 95771 | R48: =R177 -> 95771
B49: =$H$107&" Equity Value (Rmb '000)" -> Mixue Equity Value (Rmb '000) | M49: =IFERROR(SUM(M41:M45),"n/a") -> 1.4410082e+08 | N49: =IFERROR(SUM(N41:N45),"n/a") -> 1.5992248e+08 | O49: =IFERROR(SUM(O41:O45),"n/a") -> 1.732048e+08 | Q49: =IFERROR(SUM(Q41:Q45),"n/a") -> 2.0204783e+08 | R49: =IFERROR(SUM(R41:R45),"n/a") -> 2.1749926e+08
C50: =C180 -> End of period diluted shares | G50: =$H$113 -> k | M50: =M180 -> 360000 | N50: =N180 -> 379619 | O50: =O180 -> 379619 | P50: =P180 -> 379619 | Q50: =Q180 -> 379619 | R50: =R180 -> 379619
B51: Value per share (end of period) | I51: =IFERROR(I49/I50," ") | J51: =IFERROR(J49/J50,"") | K51: =IFERROR(K49/K50,"") | L51: =IFERROR(L49/L50,"") | M51: =IFERROR(M49/M50,"") -> 400.28007 | N51: =IFERROR(N49/N50,"") -> 421.27101 | O51: =IFERROR(O49/O50,"") -> 456.25957 | P51: =IFERROR(P49/P50,"") -> 0 | Q51: =IFERROR(Q49/Q50,"") -> 532.23844 | R51: =IFERROR(R49/R50,"") -> 572.94091
B52: ="Valuation @ "&TEXT(H54, "dd mmm yyyy")&" (HK$ '000)" -> Valuation @ 13 Nov 2026 (HK$ '000) | N52: =IFERROR(H68*H112, "n/a") -> 1.8744732e+08 | O52: 0.94168555
B53: Time-weighted valuation | N53: 2025E | O53: 2026E
B54: Valuation date | H54: =H109 -> 46339 | M54: PS | N54: =$H$68/FS!R8 -> 5.325772 | O54: =$H$68/FS!S8 -> 4.7997142
B55: =MATCH(H109-1,M7:R7,1) -> 2 | C55: Mid-year adjustment factor (Stub) | H55: =IF(AND(MONTH(H109)=MONTH(H108),DAY(H109)=DAY(H108)),1,IF(AND((MONTH(H109)-MONTH(H108))<2,MOD(YEARFRAC(H108,H109,1),1)<0.01),0,IF(MOD(YEARFRAC(H108,H109,1),1)=0,1,MOD(YEARFRAC(H108,H109,1),1)))) -> 0.86678832 | M55: PE | N55: =$H$68/FS!R31 -> 31.291742 | O55: =$H$68/FS!S31 -> 27.834162
B56: ="Valuation @ reporting currency "&"("&H110&")" -> Valuation @ reporting currency (RMB) | H56: {=IF(H109=H108,M51,IFERROR((1-$H$55)*INDEX($M$51:$R$51,$B$55)+$H$55*INDEX($M$51:$R$51,$B$55+1),"n/a"))} -> 451.59868 | M56: EV/EBITDA | N56: =$H$63/FS!R63 -> 19.04948 | O56: =$H$63/FS!S63 -> 16.762299
B57: ="Valuation @ price currency "&"("&H111&")" -> Valuation @ price currency (HKD) | H57: =IFERROR(H56*H112, "n/a") -> 493.77749 | M57: PEG | N57: =N55/FS!AB31/100 -> 2.1396445 | O57: =O55/FS!AC31/100 -> 1.7128462
M58: PB | N58: =$H$68/FS!R114 -> 7.175868 | O58: =$H$68/FS!S114 -> 5.696935
B59: ="Valuation summary as of "&TEXT($H$54, "dd mmm yyyy") -> Valuation summary as of 13 Nov 2026
B60: =H110&" "&H113 -> RMB k
B61: =B39 -> PV of visible period FCFs | H61: {=IFERROR(IF($H$109=$H$108,M39,(1-$H$55)*INDEX($M39:$R39,$B$55)+$H$55*INDEX($M39:$R39,$B$55+1)),"n/a")} -> 91051169
B62: =B40 -> PV of Terminal Value | H62: {=IFERROR(IF(H109=H108,M40,(1-$H$55)*INDEX($M40:$R40,$B$55)+$H$55*INDEX($M40:$R40,$B$55+1)),"n/a")} -> 56320926
B63: ="Enterprise value "&"("&$B$60&")" -> Enterprise value (RMB k) | H63: {=IFERROR(IF(H109=H108,M41,(1-$H$55)*INDEX($M41:$R41,$B$55)+$H$55*INDEX($M41:$R41,$B$55+1)),"n/a")} -> 1.473721e+08
B64: (- /+) Net (debt) / cash | H64: {=IFERROR(IF($H$109=$H$108,M42,(1-$H$55)*INDEX($M42:$R42,$B$55)+$H$55*INDEX($M42:$R42,$B$55+1)),"n/a")} -> 20244157
B65: (+) Associates / JV | H65: {=IFERROR(IF($H$109=$H$108,M43,(1-$H$55)*INDEX($M43:$R43,$B$55)+$H$55*INDEX($M43:$R43,$B$55+1)),"n/a")} -> 0
B66: (-) Non-controlling Interest / Minority Interest | H66: {=IFERROR(IF($H$109=$H$108,M44,(1-$H$55)*INDEX($M44:$R44,$B$55)+$H$55*INDEX($M44:$R44,$B$55+1)),"n/a")} -> -180557.61
B67: (+/-) Sum of Other Items | H67: {=IFERROR(IF($H$109=$H$108,M45,(1-$H$55)*INDEX($M45:$R45,$B$55)+$H$55*INDEX($M45:$R45,$B$55+1)),"n/a")} -> 3999746.1
B68: ="Equity value "&"("&$B$60&")" -> Equity value (RMB k) | H68: {=IFERROR(IF(H109=H108,M49,(1-$H$55)*INDEX($M$49:$R$49,$B$55)+$H$55*INDEX($M$49:$R$49,$B$55+1)),"n/a")} -> 1.7143544e+08 | J68: =H68/H70*H71/1000000 -> 187.44732
B70: ="Price Target in "&H110 -> Price Target in RMB | H70: =OneYr_Fwd_Value -> 451.59868
B71: ="Price Target as of "&TEXT(H54, "dd mmm yyyy")&" in "&H111 -> Price Target as of 13 Nov 2026 in HKD | H71: =PT -> 493.77749
A73: =>
B76: Multiples analysis and Data table
B77: Multiples calculated as financial year-end valuation / metric from next financial year (1 year forward metric) NB: except P/BV | N77: =N$7 -> 46022 | O77: =O$7 -> 46387 | P77: =P$7 -> 46752 | Q77: =Q$7 -> 47118
B78: Implied 1Yr forward target P/E ratio | N78: =N49/O181 -> 26.399456 | O78: =O49/P181 -> 24.443002 | P78: =P49/Q181 -> 0 | Q78: =Q49/R181 -> 21.643965
B79: Implied 1Yr forward target EV/EBIT multiple | N79: =N41/O14 -> 18.358995 | O79: =O41/P14 -> 16.662464 | P79: =P41/Q14 -> 15.16652 | Q79: =Q41/R14 -> 13.95689
B80: Implied 1Yr forward target EV/EBITDA multiple | N80: =N41/O12 -> 16.188827 | O80: =O41/P12 -> 14.154527 | P80: =P41/Q12 -> 13.06048 | Q80: =Q41/R12 -> 12.172229
B81: Implied target P/BV multiple | N81: =N49/N184 -> 6.6939635 | O81: =O49/O184 -> 5.7557322 | P81: =P49/P184 -> 0 | Q81: =Q49/Q184 -> 4.4190116
B83: Returns analysis (year-end) | N83: =N7 -> 46022 | O83: =O7 -> 46387 | P83: =P7 -> 46752 | Q83: =Q7 -> 47118 | R83: =R7 -> 47483
B85: Return on equity (calculated) | G85: % | N85: =N86*N87*N88 -> 0.35747148 | O85: =O86*O87*O88 -> 0.25356445 | P85: =P86*P87*P88 -> 0.23547566 | Q85: =Q86*Q87*Q88 -> 0.21959716 | R85: =R86*R87*R88 -> 0.2041683
C86: Net profit margin | G86: % | N86: =N181/N153 -> 0.16725226 | O86: =O181/O153 -> 0.16960135 | P86: =P181/P153 -> 0.17067506 | Q86: =Q181/Q153 -> 0.17209077 | R86: =R181/R153 -> 0.17357739
C87: Asset Turnover | G87: x | N87: =N153/M183 -> 1.6271171 | O87: =O153/N183 -> 1.1874273 | P87: =P153/O183 -> 1.1231986 | Q87: =Q153/P183 -> 1.0511745 | R87: =R153/Q183 -> 0.97940496
C88: Financial Leverage | G88: x | N88: =IFERROR((M183/M184),"n/a") -> 1.3135621 | O88: =IFERROR((N183/N184),"n/a") -> 1.2590763 | P88: =IFERROR((O183/O184),"n/a") -> 1.2283423 | Q88: =IFERROR((P183/P184),"n/a") -> 1.2139319 | R88: =IFERROR((Q183/Q184),"n/a") -> 1.200972
M90: Equity value per share sensitivity
G91: Hardcode | M91: TGR | R91: WACC
G92: Table | M92: =PT -> 493.77749 | N92: =O92-$H$94 -> 0 | O92: =P92-$H$94 -> 0 | P92: =G94 -> 0 | Q92: =P92+$H$94 -> 0 | R92: =Q92+$H$94 -> 0
G93: Input | H93: Increment | M93: =M94-$H$95 -> 0 | N93: 577.78379 | O93: 577.78379 | P93: 577.78379 | Q93: 577.78379 | R93: 577.78379
D94: =IF(_xlfn.ISFORMULA((G94))=TRUE,1,0) -> 0 | E94: WACC | M94: =M95-$H$95 -> 0 | N94: 577.78379 | O94: 577.78379 | P94: 577.78379 | Q94: 577.78379 | R94: 577.78379
D95: =IF(_xlfn.ISFORMULA((G95))=TRUE,1,0) -> 0 | E95: TGR | M95: =M96-$H$95 -> 0 | N95: 577.78379 | O95: 577.78379 | P95: 577.78379 | Q95: 577.78379 | R95: 577.78379
M96: =G95 -> 0 | N96: 577.78379 | O96: 577.78379 | P96: 577.78379 | Q96: 577.78379 | R96: 577.78379
G97: Model | H97: Checks | M97: =M96+$H$95 -> 0 | N97: 577.78379 | O97: 577.78379 | P97: 577.78379 | Q97: 577.78379 | R97: 577.78379
G98: value | M98: =M97+$H$95 -> 0 | N98: 577.78379 | O98: 577.78379 | P98: 577.78379 | Q98: 577.78379 | R98: 577.78379
E99: =E94 -> WACC | G99: =WACC -> 0.093455 | H99: =G99-G94 -> 0.093455 | M99: =M98+$H$95 -> 0 | N99: 577.78379 | O99: 577.78379 | P99: 577.78379 | Q99: 577.78379 | R99: 577.78379
E100: =E95 -> TGR | G100: =H140 -> 0.03 | H100: =G100-G95 -> 0.03
E101: Data table consistency | H101: =IFERROR(M92-P96,"n/a") -> -84.006301
E102: Model values can be copy pasted into table input cells to ensure check passes
A104: =>
B105: Assumptions Please fill yellow coloured cells
C106: Set-up details
D107: Company name / ticker | H107: Mixue
D108: Last financial year end | H108: 45657
D109: Valuation date | H109: =TODAY()+365 -> 46339
D110: Reporting currency | H110: RMB
D111: Share price currency | H111: HKD
...

Sheet FS
A1: UBS Equity Research
A2: Mixue Group
A3: Unit: Thousand RMB
G4: 2021 | H4: 9M22 | I4: 2022 | J4: 9M23 | K4: 2023 | L4: 9M24 | M4: 2024H1 | N4: 2024H2 | O4: 2024 | P4: 2025H1 | Q4: 2025H2E | R4: 2025E | S4: 2026E | T4: 2027E | U4: 2028E | V4: 2029E | W4: 2030E | AA4: 24-26E | AB4: 25-27E | AC4: 26-28E | AF4: Consensus
A6: Income Statement
A8: Total revenue | G8: 10350986 | H8: 10543240 | I8: 13575577 | J8: 15393328 | K8: 20302465 | L8: 18659671 | M8: 10677054 | N8: =O8-M8 -> 14151820 | O8: 24828874 | P8: 14874809 | Q8: =Assumption!Q18 -> 17314973 | R8: =Assumption!R18 -> 32189782 | S8: =Assumption!S18 -> 35717844 | T8: =Assumption!T18 -> 41517893 | U8: =Assumption!U18 -> 47649032 | V8: =Assumption!V18 -> 53780423 | W8: =Assumption!W18 -> 57634735 | AA8: =(S8/O8)^0.5-1 -> 0.19940016 | AB8: =(T8/R8)^0.5-1 -> 0.13568695 | AC8: =(U8/S8)^0.5-1 -> 0.1550065 | AF8: 14701.517 | AG8: =P8/1000/AF8-1 -> 0.011787365
B9: YoY % | I9: =I8/G8-1 -> 0.31152501 | J9: =J8/H8-1 -> 0.46001874 | K9: =K8/I8-1 -> 0.49551397 | L9: =L8/J8-1 -> 0.21219213 | O9: =O8/K8-1 -> 0.22294874 | P9: =P8/M8-1 -> 0.39315667 | Q9: =Q8/N8-1 -> 0.22351563 | R9: =R8/O8-1 -> 0.29646564 | S9: =S8/R8-1 -> 0.10960191 | T9: =T8/S8-1 -> 0.16238522 | U9: =U8/T8-1 -> 0.14767462 | V9: =V8/U8-1 -> 0.12867817 | W9: =W8/V8-1 -> 0.07166756
B10: Cost of sales | G10: -7107124 | H10: -7572013 | I10: -9728740 | J10: -10817689 | K10: -14303498 | L10: -12619249 | M10: -7274359 | N10: =O10-M10 -> -9494308 | O10: -16768667 | P10: =-10168436 -> -10168436 | Q10: =Assumption!Q49 -> -11796915 | R10: =Assumption!R49 -> -22131087 | S10: =Assumption!S49 -> -24539254 | T10: =Assumption!T49 -> -28525480 | U10: =Assumption!U49 -> -32730083 | V10: =Assumption!V49 -> -36930643 | W10: =Assumption!W49 -> -39524015
A11: Gross profit | G11: =SUM(G8,G10) -> 3243862 | H11: =SUM(H8,H10) -> 2971227 | I11: =SUM(I8,I10) -> 3846837 | J11: =SUM(J8,J10) -> 4575639 | K11: =SUM(K8,K10) -> 5998967 | L11: =SUM(L8,L10) -> 6040422 | M11: =SUM(M8,M10) -> 3402695 | N11: =O11-M11 -> 4657512 | O11: =SUM(O8,O10) -> 8060207 | P11: =SUM(P8,P10) -> 4706373 | Q11: =SUM(Q8,Q10) -> 5518058.3 | R11: =SUM(R8,R10) -> 10058695 | S11: =SUM(S8,S10) -> 11178590 | T11: =SUM(T8,T10) -> 12992414 | U11: =SUM(U8,U10) -> 14918949 | V11: =SUM(V8,V10) -> 16849780 | W11: =SUM(W8,W10) -> 18110719 | AA11: =(S11/O11)^0.5-1 -> 0.17766132 | AB11: =(T11/R11)^0.5-1 -> 0.1365122 | AC11: =(U11/S11)^0.5-1 -> 0.15524903 | AF11: 4431.174 | AG11: =P11/1000/AF11-1 -> 0.0621052
B12: YoY % | I12: =I11/G11-1 -> 0.18588183 | J12: =J11/H11-1 -> 0.53998298 | K12: =K11/I11-1 -> 0.55945443 | L12: =L11/J11-1 -> 0.32012643 | O12: =O11/K11-1 -> 0.34359916 | P12: =P11/M11-1 -> 0.38313102 | Q12: =Q11/N11-1 -> 0.18476523 | R12: =R11/O11-1 -> 0.24794496 | S12: =S11/R11-1 -> 0.11133602 | T12: =T11/S11-1 -> 0.16225872 | U12: =U11/T11-1 -> 0.1482816 | V12: =V11/U11-1 -> 0.12942136 | W12: =W11/V11-1 -> 0.074834162
B13: Selling and distribution expenses | G13: -405766 | H13: -528184 | I13: -774431 | J13: -992934 | K13: -1318588 | L13: -1097090 | M13: -651491 | N13: =O13-M13 -> -947983 | O13: -1599474 | P13: -913679 | Q13: =Assumption!Q180 -> -1159984.1 | R13: =Assumption!R180 -> -2073663.1 | S13: =Assumption!S180 -> -2300940.5 | T13: =Assumption!T180 -> -2674579.2 | U13: =Assumption!U180 -> -3069546.7 | V13: =Assumption!V180 -> -3464530.4 | W13: =Assumption!W180 -> -3712824.8
B14: Administrative expenses | G14: -374665 | H14: -337176 | I14: -496506 | J14: -429811 | K14: -610622 | L14: -433470 | M14: =-279515 -> -279515 | N14: =O14-M14 -> -475600 | O14: -755115 | P14: -437650 | Q14: =Assumption!Q181 -> -541330.65 | R14: =Assumption!R181 -> -978980.65 | S14: =Assumption!S181 -> -1086278.8 | T14: =Assumption!T181 -> -1262674.4 | U14: =Assumption!U181 -> -1449139.4 | V14: =Assumption!V181 -> -1635612 | W14: =Assumption!W181 -> -1752832.3
B15: Research and development expenses | G15: -17151 | H15: -23852 | I15: -32304 | J15: -51343 | K15: -85000 | L15: -64805 | M15: =-40327 -> -40327 | N15: =O15-M15 -> -64543 | O15: -104870 | P15: -41037 | Q15: =Assumption!Q182 -> -94923.352 | R15: =Assumption!R182 -> -135960.35 | S15: =Assumption!S182 -> -150861.87 | T15: =Assumption!T182 -> -175359.6 | U15: =Assumption!U182 -> -201255.76 | V15: =Assumption!V182 -> -227152.99 | W15: =Assumption!W182 -> -243432.49
C16: In opex: equity-settled shared based payment | G16: -22554 | H16: -19377 | I16: -24981 | J16: -8687 | K16: -16427 | L16: -8007 | M16: -6521 | N16: =O16-M16 -> -9265 | O16: -15786 | P16: -9266 | Q16: =R16-P16 -> -11200.007 | R16: =O16/O8*R8 -> -20466.007 | S16: =R16/R8*S8 -> -22709.12 | T16: =S16/S8*T8 -> -26396.745 | U16: =T16/T8*U8 -> -30294.875 | V16: =U16/U8*V8 -> -34193.164 | W16: =V16/V8*W8 -> -36643.704
A17: Adj. EBIT | G17: =G23-G18-G16 -> 2468834 | H17: =H23-H18-H16 -> 2101392 | I17: =I23-I18-I16 -> 2568577 | J17: =J23-J18-J16 -> 3110238 | K17: =K23-K18-K16 -> 4001184 | L17: =L23-L18-L16 -> 4453064 | M17: =M23-M18-M16 -> 2437883 | N17: =O17-M17 -> 3178651 | O17: =O23-O18-O16 -> 5616534 | P17: =P23-P18-P16 -> 3322119 | Q17: =Q23-Q18-Q16 -> 3733020.2 | R17: =R23-R18-R16 -> 6890556.7 | S17: =S23-S18-S16 -> 7663217.7 | T17: =T23-T18-T16 -> 8906197 | U17: =U23-U18-U16 -> 10229302 | V17: =V23-V18-V16 -> 11556678 | W17: =W23-W18-W16 -> 12438273 | AA17: =(S17/O17)^0.5-1 -> 0.16807677 | AB17: =(T17/R17)^0.5-1 -> 0.13689144 | AC17: =(U17/S17)^0.5-1 -> 0.15536026
B18: Non-operating gains/(losses) | G18: =G19+G20+G21+G22 -> 80346 | H18: =H19+H20+H21+H22 -> 43419 | I18: =I19+I20+I21+I22 -> 79315 | J18: =J19+J20+J21+J22 -> 57360 | K18: =K19+K20+K21+K22 -> 130141 | L18: =L19+L20+L21+L22 -> 51628 | M18: =M19+M20+M21+M22 -> 74796 | N18: =O18-M18 -> 34390.999 | O18: =O19+O20+O21+O22 -> 109187 | P18: =P19+P20+P21 -> 86864.412 | Q18: =Q19+Q20+Q21+Q22 -> 27303.041 | R18: =R19+R20+R21 -> 115268.45 | S18: =S19+S20+S21 -> 124088.61 | T18: =T19+T20+T21 -> 138588.73 | U18: =U19+U20+U21 -> 153916.58 | V18: =V19+V20+V21 -> 169245.06 | W18: =W19+W20+W21 -> 178880.83
C19: Other income and gains (net) | G19: =Assumption!G213 -> 96960 | H19: =Assumption!H213 -> 47113 | I19: =Assumption!I213 -> 83593 | J19: =Assumption!J213 -> 112843 | K19: =Assumption!K213 -> 193831 | L19: =Assumption!L213 -> 58168 | M19: 80889 | N19: =O19-M19 -> 31642.999 | O19: =Assumption!O213 -> 112532 | P19: =158602-P25 -> 87965.412 | Q19: =R19-P19 -> 27303.041 | R19: =Assumption!R213 -> 115268.45 | S19: =Assumption!S213 -> 124088.61 | T19: =Assumption!T213 -> 138588.73 | U19: =Assumption!U213 -> 153916.58 | V19: =Assumption!V213 -> 169245.06 | W19: =Assumption!W213 -> 178880.83
C20: (Impairment)/reversal on financial assets | G20: -1787 | H20: -3473 | I20: -4098 | J20: 4480 | K20: 1638 | L20: -3524 | M20: -3077 | N20: =O20-M20 -> 2748 | O20: -329 | P20: -1101 | Q20: =Assumption!Q192 -> 0 | R20: =Assumption!R192 -> 0 | S20: =Assumption!S192 -> 0 | T20: =Assumption!T192 -> 0 | U20: =Assumption!U192 -> 0 | V20: =Assumption!V192 -> 0 | W20: =Assumption!W192 -> 0
C21: Impairment of PP&E | G21: -14827 | H21: 0 | I21: 0 | J21: -59999 | K21: -65524 | L21: 0 | M21: 0 | N21: =O21-M21 -> 0 | O21: 0 | P21: 0 | Q21: =Assumption!Q193 -> 0 | R21: =Assumption!R193 -> 0 | S21: =Assumption!S193 -> 0 | T21: =Assumption!T193 -> 0 | U21: =Assumption!U193 -> 0 | V21: =Assumption!V193 -> 0 | W21: =Assumption!W193 -> 0
C22: Share of (losses)/profits of an associate | G22: 0 | H22: -221 | I22: -180 | J22: 36 | K22: 196 | L22: -3016 | M22: -3016 | N22: =O22-M22 -> 0 | O22: -3016 | P22: -1154 | Q22: =Assumption!Q197 -> 0 | R22: =Assumption!R197 -> 0 | S22: =Assumption!S197 -> 0 | T22: =Assumption!T197 -> 0 | U22: =Assumption!U197 -> 0 | V22: =Assumption!V197 -> 0 | W22: =Assumption!W197 -> 0
A23: EBIT | G23: =G11+G13+G14+G15+G18 -> 2526626 | H23: =H11+H13+H14+H15+H18 -> 2125434 | I23: =I11+I13+I14+I15+I18 -> 2622911 | J23: =J11+J13+J14+J15+J18 -> 3158911 | K23: =K11+K13+K14+K15+K18 -> 4114898 | L23: =L11+L13+L14+L15+L18 -> 4496685 | M23: =M11+M13+M14+M15+M18 -> 2506158 | N23: =O23-M23 -> 3203777 | O23: =O11+O13+O14+O15+O18 -> 5709935 | P23: =P11+P13+P14+P15+P18+P22 -> 3399717.4 | Q23: =Q11+Q13+Q14+Q15+Q18+Q22 -> 3749123.2 | R23: =R11+R13+R14+R15+R18+R22 -> 6985359.1 | S23: =S11+S13+S14+S15+S18+S22 -> 7764597.2 | T23: =T11+T13+T14+T15+T18+T22 -> 9018389 | U23: =U11+U13+U14+U15+U18+U22 -> 10352924 | V23: =V11+V13+V14+V15+V18+V22 -> 11691730 | W23: =W11+W13+W14+W15+W18+W22 -> 12580511 | AA23: =(S23/O23)^0.5-1 -> 0.16612172 | AB23: =(T23/R23)^0.5-1 -> 0.1362401 | AC23: =(U23/S23)^0.5-1 -> 0.15470767
B24: YoY % | I24: =I23/G23-1 -> 0.038108133 | J24: =J23/H23-1 -> 0.48624281 | K24: =K23/I23-1 -> 0.56882868 | L24: =L23/J23-1 -> 0.42349215 | O24: =O23/K23-1 -> 0.38762492 | P24: =P23/M23-1 -> 0.35654552 | Q24: =Q23/N23-1 -> 0.17021979 | R24: =R23/O23-1 -> 0.22336929 | S24: =S23/R23-1 -> 0.11155305 | T24: =T23/S23-1 -> 0.16147544 | U24: =U23/T23-1 -> 0.14797933 | V24: =V23/U23-1 -> 0.12931667 | W24: =W23/V23-1 -> 0.076017895
B25: Interest income | G25: =Assumption!G207 -> 38221 | H25: =Assumption!H207 -> 32715 | I25: =Assumption!I207 -> 44322 | J25: =Assumption!J207 -> 36781 | K25: =Assumption!K207 -> 53801 | L25: =Assumption!L207 -> 77339 | M25: 0 | N25: =O25-M25 -> 107015 | O25: =Assumption!O207 -> 107015 | P25: =Assumption!P368 -> 70636.588 | Q25: =Assumption!Q207 -> 70636.588 | R25: =Assumption!R207 -> 141273.18 | S25: =Assumption!S207 -> 246072.76 | T25: =Assumption!T207 -> 342792.83 | U25: =Assumption!U207 -> 470880.28 | V25: =Assumption!V207 -> 622362.75 | W25: =Assumption!W207 -> 797577.14
B26: Finance costs | G26: -5973 | H26: -6980 | I26: -9190 | J26: -11037 | K26: -14697 | L26: -5479 | M26: -4405 | N26: =O26-M26 -> -1962 | O26: -6367 | P26: -2072 | Q26: =R26-P26 -> -949.25453 | R26: =-Assumption!R365 -> -3021.2545 | S26: =-Assumption!S365 -> -2158.697 | T26: =-Assumption!T365 -> -1589.8308 | U26: =-Assumption!U365 -> -1007.4837 | V26: =-Assumption!V365 -> -502.80054 | W26: =-Assumption!W365 -> -106.63015
A27: Profit before tax | G27: =G23+G26+G25 -> 2558874 | H27: =H23+H26+H25 -> 2151169 | I27: =I23+I26+I25 -> 2658043 | J27: =J23+J26+J25 -> 3184655 | K27: =K23+K26+K25 -> 4154002 | L27: =L23+L26+L25 -> 4568545 | M27: =M23+M26+M25 -> 2501753 | N27: =O27-M27 -> 3308830 | O27: =O23+O26+O25 -> 5810583 | P27: =P23+P26+P25 -> 3468282 | Q27: =Q23+Q26+Q25 -> 3818810.6 | R27: =R23+R26+R25 -> 7123611 | S27: =S23+S26+S25 -> 8008511.3 | T27: =T23+T26+T25 -> 9359592 | U27: =U23+U26+U25 -> 10822797 | V27: =V23+V26+V25 -> 12313590 | W27: =W23+W26+W25 -> 13377981
B28: YoY % | I28: =I27/G27-1 -> 0.038754937 | J28: =J27/H27-1 -> 0.48042994 | K28: =K27/I27-1 -> 0.56280466 | L28: =L27/J27-1 -> 0.43454943 | O28: =O27/K27-1 -> 0.39879157 | P28: =P27/M27-1 -> 0.3863407 | Q28: =Q27/N27-1 -> 0.15412716 | R28: =R27/O27-1 -> 0.22597182 | S28: =S27/R27-1 -> 0.12422075 | T28: =T27/S27-1 -> 0.1687056 | U28: =U27/T27-1 -> 0.15633213 | V28: =V27/U27-1 -> 0.13774562 | W28: =W27/V27-1 -> 0.08644037
B29: Income tax expense | G29: -646932 | H29: -527751 | I29: -644952 | J29: -731876 | K29: -967397 | L29: -1077573 | M29: -614854 | N29: =O29-M29 -> -741526 | O29: -1356380 | P29: -750068 | Q29: =R29-P29 -> -856306.28 | R29: =-R27*R52 -> -1606374.3 | S29: =-S27*S52 -> -1805919.3 | T29: =-T27*T52 -> -2110588 | U29: =-U27*U52 -> -2440540.7 | V29: =-V27*V52 -> -2776714.5 | W29: =-W27*W52 -> -3016734.7
B30: Non-controlling interests | G30: -1581 | H30: -6462 | I30: -16376 | J30: -51926 | K30: -49264 | L30: -4907 | M30: -2441 | N30: =O30-M30 -> -15258 | O30: -17699 | P30: -25330 | Q30: =R30-P30 -> -13290.657 | R30: =-Assumption!R385 -> -38620.657 | S30: =-Assumption!S385 -> -43418.144 | T30: =-Assumption!T385 -> -50743.028 | U30: =-Assumption!U385 -> -58675.794 | V30: =-Assumption!V385 -> -66758.127 | W30: =-Assumption!W385 -> -72528.724
A31: Profit attributable to common equity shareholders | G31: =G27+G29+G30 -> 1910361 | H31: =H27+H29+H30 -> 1616956 | I31: =I27+I29+I30 -> 1996715 | J31: =J27+J29+J30 -> 2400853 | K31: =K27+K29+K30 -> 3137341 | L31: =L27+L29+L30 -> 3486065 | M31: =M27+M29+M30 -> 1884458 | N31: =O31-M31 -> 2552046 | O31: =O27+O29+O30 -> 4436504 | P31: =P27+P29+P30 -> 2692884 | Q31: =Q27+Q29+Q30 -> 2949213.6 | R31: =R27+R29+R30 -> 5478616.1 | S31: =S27+S29+S30 -> 6159173.9 | T31: =T27+T29+T30 -> 7198261 | U31: =U27+U29+U30 -> 8323580.4 | V31: =V27+V29+V30 -> 9470117.2 | W31: =W27+W29+W30 -> 10288718 | AA31: =(S31/O31)^0.5-1 -> 0.17825907 | AB31: =(T31/R31)^0.5-1 -> 0.14624739 | AC31: =(U31/S31)^0.5-1 -> 0.1625024 | AF31: 2393.9252 | AG31: =P31/1000/AF31-1 -> 0.12488225
B32: YoY % | I32: =I31/G31-1 -> 0.045202975 | J32: =J31/H31-1 -> 0.48479798 | K32: =K31/I31-1 -> 0.57125128 | L32: =L31/J31-1 -> 0.45201101 | O32: =O31/K31-1 -> 0.41409684 | P32: =P31/M31-1 -> 0.42899656 | Q32: =Q31/N31-1 -> 0.15562715 | R32: =R31/O31-1 -> 0.23489488 | S32: =S31/R31-1 -> 0.12422075 | T32: =T31/S31-1 -> 0.1687056 | U32: =U31/T31-1 -> 0.15633213 | V32: =V31/U31-1 -> 0.13774562 | W32: =W31/V31-1 -> 0.08644037 | AA32: =(60/44)^0.5-1 -> 0.16774842
A34: Total shares outstanding (basic) | G34: =G111 -> 360000 | I34: =I111 -> 360000 | J34: =J111 -> 360000 | K34: =K111 -> 360000 | L34: =L111 -> 360000 | M34: =O34 -> 360000 | N34: =O34 -> 360000 | O34: =O111 -> 360000 | P34: =P111 -> 379619 | Q34: =Q111 -> 379619 | R34: =R111 -> 379619 | S34: =S111 -> 379619 | T34: =T111 -> 379619 | U34: =U111 -> 379619 | V34: =V111 -> 379619 | W34: =W111 -> 379619
A35: Total shares outstanding (diluted) | G35: =G34 -> 360000 | I35: =I34 -> 360000 | J35: =J34 -> 360000 | K35: =K34 -> 360000 | L35: =L34 -> 360000 | M35: =M34 -> 360000 | N35: =O35 -> 360000 | O35: =O34 -> 360000 | P35: =P34 -> 379619 | Q35: =Q34 -> 379619 | R35: =R34 -> 379619 | S35: =S34 -> 379619 | T35: =T34 -> 379619 | U35: =U34 -> 379619 | V35: =V34 -> 379619 | W35: =W34 -> 379619
A36: EPS (Basic) | G36: =G$31/G34 -> 5.3065583 | I36: =I$31/I34 -> 5.5464306 | J36: =J$31/J34 -> 6.6690361 | K36: =K$31/K34 -> 8.7148361 | L36: =L$31/L34 -> 9.6835139 | M36: =M$31/M34 -> 5.2346056 | N36: =N$31/N34 -> 7.0890167 | O36: =O$31/O34 -> 12.323622 | P36: =P$31/P34 -> 7.0936492 | ... W36: =W$31/W34 -> 27.102747 | AB36: =(T36/R36)^0.5-1 -> 0.14624739
A37: EPS (Diluted) | G37: =G$31/G35 -> 5.3065583 | I37: =I$31/I35 -> 5.5464306 | J37: =J$31/J35 -> 6.6690361 | K37: =K$31/K35 -> 8.7148361 | L37: =L$31/L35 -> 9.6835139 | M37: =M$31/M35 -> 5.2346056 | N37: =N$31/N35 -> 7.0890167 | O37: =O$31/O35 -> 12.323622 | P37: =P$31/P35 -> 7.0936492 | ... W37: =W$31/W35 -> 27.102747
A38: Dividends | G38: =-Assumption!G377 -> 404400 | I38: =-Assumption!I377 -> 104400 | J38: =-Assumption!J377 -> 100000 | K38: =-Assumption!K377 -> 100000 | L38: =-Assumption!L377 -> 0 | M38: 0 | N38: 0 | O38: =O31*O55 -> 0 | P38: 0 | Q38: =R38-P38 -> 0 | R38: =R31*R55 -> 0 | S38: =S31*S55 -> 0 | T38: =T31*T55 -> 0 | U38: =U31*U55 -> 0 | V38: =V31*V55 -> 0 | W38: =W31*W55 -> 0
A39: DPS | G39: =G38/G34 -> 1.1233333 | I39: =I38/I34 -> 0.29 | J39: =J38/J34 -> 0.27777778 | K39: =K38/K34 -> 0.27777778 | L39: =L38/L34 -> 0 | M39: =M38/M34 -> 0 | N39: =N38/N34 -> 0 | O39: =O38/O34 -> 0 | P39: =P38/P34 -> 0 | ... W39: =W38/W34 -> 0
A41: Key metrics:
A42: Gross margin | G42: =IFERROR(G11/G$8,"") -> 0.31338676 | H42: =IFERROR(H11/H$8,"") -> 0.28181347 | I42: =IFERROR(I11/I$8,"") -> 0.28336453 | J42: =IFERROR(J11/J$8,"") -> 0.2972482 | K42: =IFERROR(K11/K$8,"") -> 0.29547974 | L42: =IFERROR(L11/L$8,"") -> 0.32371535 | M42: =IFERROR(M11/M$8,"") -> 0.31869231 | N42: =IFERROR(N11/N$8,"") -> 0.32911046 | ... W42: =IFERROR(W11/W$8,"") -> 0.31423272 | AF42: =IFERROR(AF11/AF$8,"") -> 0.30140931 | AG42: =(P42-AF42)*100 -> 1.4989577
A43: Operating costs as % of revenue
B44: Selling and distribution expenses | G44: =IFERROR(-G13/G$8,"") -> 0.03920071 | H44: =IFERROR(-H13/H$8,"") -> 0.050096934 | I44: =IFERROR(-I13/I$8,"") -> 0.057045899 | J44: =IFERROR(-J13/J$8,"") -> 0.06450418 | K44: =IFERROR(-K13/K$8,"") -> 0.064947187 | L44: =IFERROR(-L13/L$8,"") -> 0.058794713 | M44: =IFERROR(-M13/M$8,"") -> 0.061017861 | N44: =IFERROR(-N13/N$8,"") -> 0.066986649 | ... W44: =IFERROR(-W13/W$8,"") -> 0.064419917
B45: Administrative expenses | G45: =IFERROR(-G14/G$8,"") -> 0.036196069 | H45: =IFERROR(-H14/H$8,"") -> 0.031980302 | I45: =IFERROR(-I14/I$8,"") -> 0.036573473 | J45: =IFERROR(-J14/J$8,"") -> 0.027921902 | K45: =IFERROR(-K14/K$8,"") -> 0.030076249 | L45: =IFERROR(-L14/L$8,"") -> 0.023230313 | M45: =IFERROR(-M14/M$8,"") -> 0.026179038 | N45: =IFERROR(-N14/N$8,"") -> 0.033606985 | ... W45: =IFERROR(-W14/W$8,"") -> 0.030412777
B46: Research and development expenses | G46: =IFERROR(-G15/G$8,"") -> 0.0016569436 | H46: =IFERROR(-H15/H$8,"") -> 0.0022623027 | I46: =IFERROR(-I15/I$8,"") -> 0.0023795674 | J46: =IFERROR(-J15/J$8,"") -> 0.0033354061 | K46: =IFERROR(-K15/K$8,"") -> 0.0041866837 | L46: =IFERROR(-L15/L$8,"") -> 0.003472998 | M46: =IFERROR(-M15/M$8,"") -> 0.0037769782 | N46: =IFERROR(-N15/N$8,"") -> 0.0045607561 | ... W46: =IFERROR(-W15/W$8,"") -> 0.0042237115
A47: Non-operating gains/(losses) as % of revenue | G47: =IFERROR(G18/G$8,"") -> 0.0077621591 | H47: =IFERROR(H18/H$8,"") -> 0.0041181838 | I47: =IFERROR(I18/I$8,"") -> 0.0058424773 | J47: =IFERROR(J18/J$8,"") -> 0.0037262897 | K47: =IFERROR(K18/K$8,"") -> 0.0064101083 | L47: =IFERROR(L18/L$8,"") -> 0.0027668226 | M47: =IFERROR(M18/M$8,"") -> 0.0070053031 | N47: =IFERROR(N18/N$8,"") -> 0.0024301467 | ... W47: =IFERROR(W18/W$8,"") -> 0.0031036984
A48: EBIT margin | G48: =IFERROR(G23/G$8,"") -> 0.2440952 | H48: =IFERROR(H23/H$8,"") -> 0.20159211 | I48: =IFERROR(I23/I$8,"") -> 0.19320807 | J48: =IFERROR(J23/J$8,"") -> 0.205213 | K48: =IFERROR(K23/K$8,"") -> 0.20267972 | L48: =IFERROR(L23/L$8,"") -> 0.24098415 | M48: =IFERROR(M23/M$8,"") -> 0.23472374 | N48: =IFERROR(N23/N$8,"") -> 0.22638622 | ... W48: =IFERROR(W23/W$8,"") -> 0.21828001
B49: Adj. EBIT margin | G49: =IFERROR(G17/G$8,"") -> 0.23851196 | H49: =IFERROR(H17/H$8,"") -> 0.19931179 | I49: =IFERROR(I17/I$8,"") -> 0.18920573 | J49: =IFERROR(J17/J$8,"") -> 0.20205104 | K49: =IFERROR(K17/K$8,"") -> 0.19707873 | L49: =IFERROR(L17/L$8,"") -> 0.23864644 | M49: =IFERROR(M17/M$8,"") -> 0.22832918 | N49: =IFERROR(N17/N$8,"") -> 0.22461076 | ... W49: =IFERROR(W17/W$8,"") -> 0.21581211
A50: EBITDA margin | G50: =IFERROR(G63/G$8,"") -> 0.25383331 | H50: =IFERROR(H63/H$8,"") -> 0.21431932 | I50: =IFERROR(I63/I$8,"") -> 0.20674444 | J50: =IFERROR(J63/J$8,"") -> 0.21766333 | K50: =IFERROR(K63/K$8,"") -> 0.21586906 | L50: =IFERROR(L63/L$8,"") -> 0.25696482 | M50: =IFERROR(M63/M$8,"") -> 0.23472374 | N50: =IFERROR(N63/N$8,"") -> 0.22638622 | ... W50: =IFERROR(W63/W$8,"") -> 0.24792632
B51: Adjusted EBITDA margin | G51: =G67/G8 -> 0.24825007 | H51: =H67/H8 -> 0.21203899 | I51: =I67/I8 -> 0.2027421 | J51: =J67/J8 -> 0.21450137 | K51: =K67/K8 -> 0.21026806 | L51: =L67/L8 -> 0.2546271 | M51: =M67/M8 -> 0.22832918 | N51: =N67/N8 -> 0.22461076 | ... W51: =W67/W8 -> 0.24545841
A52: Effective tax rate | G52: =-G29/G27 -> 0.25281901 | H52: =-H29/H27 -> 0.24533219 | I52: =-I29/I27 -> 0.24264167 | J52: =-J29/J27 -> 0.22981328 | K52: =-K29/K27 -> 0.23288313 | L52: =-L29/L27 -> 0.23586787 | M52: =-M29/M27 -> 0.24576927 | N52: =-N29/N27 -> 0.2241052 | ... Q52: =-Q29/Q27 -> 0.22423377 | R52: 0.2255 | S52: =R52 -> 0.2255 | T52: =S52 -> 0.2255 | U52: =T52 -> 0.2255 | V52: =U52 -> 0.2255 | W52: =V52 -> 0.2255
A53: Net margin | G53: =IFERROR(G31/G$8,"") -> 0.18455836 | H53: =IFERROR(H31/H$8,"") -> 0.15336424 | I53: =IFERROR(I31/I$8,"") -> 0.14708141 | J53: =IFERROR(J31/J$8,"") -> 0.15596712 | K53: =IFERROR(K31/K$8,"") -> 0.15453005 | L53: =IFERROR(L31/L$8,"") -> 0.1868235 | M53: =IFERROR(M31/M$8,"") -> 0.17649606 | N53: =IFERROR(N31/N$8,"") -> 0.18033341 | ... W53: =IFERROR(W31/W$8,"") -> 0.17851592
B54: Adjusted NPM | G54: =G68/G8 -> 0.17897512 | H54: =H68/H8 -> 0.15108392 | I54: =I68/I8 -> 0.14307908 | J54: =J68/J8 -> 0.15280516 | K54: =K68/K8 -> 0.14892906 | L54: =L68/L8 -> 0.18448578 | M54: =M68/M8 -> 0.17010151 | N54: =N68/N8 -> 0.17855795 | ... W54: =W68/W8 -> 0.17604801
A55: Dividend payout ratio | G55: =-Assumption!G377/Assumption!G376 -> 0.21168774 | I55: =-Assumption!I377/Assumption!I376 -> 0.05228588 | J55: =-Assumption!J377/Assumption!J376 -> 0.041651863 | K55: =-Assumption!K377/Assumption!K376 -> 0.031874125 | L55: =-Assumption!L377/Assumption!L376 -> 0 | M55: =-Assumption!M377/Assumption!M376 -> 0 | N55: =N38/N31 -> 0 | O55: =-Assumption!O377/Assumption!O376 -> 0 | P55: =-Assumption!P377/Assumption!P376 -> 0 | Q55: 0 | R55: 0 | S55: 0 | T55: =S55 -> 0 | U55: =T55 -> 0 | V55: =U55 -> 0 | W55: =V55 -> 0
A57: Non-GAAP measures:
A58: EBIT | G58: =G23 -> 2526626 | H58: =H23 -> 2125434 | I58: =I23 -> 2622911 | J58: =J23 -> 3158911 | K58: =K23 -> 4114898 | L58: =L23 -> 4496685 | M58: =M23 -> 2506158 | N58: =N23 -> 3203777 | ... W58: =W23 -> 12580511
A59: D&A | G59: =SUM(G60:G62) -> 100799 | H59: =SUM(H60:H62) -> 134186 | I59: =SUM(I60:I62) -> 183764 | J59: =SUM(J60:J62) -> 191652 | K59: =SUM(K60:K62) -> 267776 | L59: =SUM(L60:L62) -> 298194 | M59: =SUM(M60:M62) -> 0 | N59: =SUM(N60:N62) -> 0 | ... W59: =SUM(W60:W62) -> 1708656.9
B60: D&A for PP&E | G60: =Assumption!G307 -> 57239 | H60: =Assumption!H307 -> 79650 | I60: =Assumption!I307 -> 105310 | J60: =Assumption!J307 -> 110108 | K60: =Assumption!K307 -> 160504 | L60: =Assumption!L307 -> 220610 | M60: =Assumption!M307 -> 0 | N60: =Assumption!N307 -> 0 | ... W60: =Assumption!W307 -> 1621068.1
B61: D&A for intangible assets | G61: =Assumption!G308 -> 42363 | H61: =Assumption!H308 -> 52827 | I61: =Assumption!I308 -> 75782 | J61: =Assumption!J308 -> 78684 | K61: =Assumption!K308 -> 103472 | L61: =Assumption!L308 -> 74364 | M61: =Assumption!M308 -> 0 | N61: =Assumption!N308 -> 0 | ... W61: =Assumption!W308 -> 75792.456
B62: D&A for ROU assets | G62: =Assumption!G309 -> 1197 | H62: =Assumption!H309 -> 1709 | I62: =Assumption!I309 -> 2672 | J62: =Assumption!J309 -> 2860 | K62: =Assumption!K309 -> 3800 | L62: =Assumption!L309 -> 3220 | M62: =Assumption!M309 -> 0 | N62: =Assumption!N309 -> 0 | ... W62: =Assumption!W309 -> 11796.374
A63: EBITDA | G63: =SUM(G58:G59) -> 2627425 | H63: =SUM(H58:H59) -> 2259620 | I63: =SUM(I58:I59) -> 2806675 | J63: =SUM(J58:J59) -> 3350563 | K63: =SUM(K58:K59) -> 4382674 | L63: =SUM(L58:L59) -> 4794879 | M63: =SUM(M58:M59) -> 2506158 | N63: =SUM(N58:N59) -> 3203777 | ... W63: =SUM(W58:W59) -> 14289167 | AB63: =(S63/O63)^0.5-1 -> 0.19766607 | AC63: =(U63/K63)^0.2-1 -> 0.22322401
B64: Non-operating income/(losses) | G64: =-G18 -> -80346 | H64: =-H18 -> -43419 | I64: =-I18 -> -79315 | J64: =-J18 -> -57360 | K64: =-K18 -> -130141 | L64: =-L18 -> -51628 | M64: =-M18 -> -74796 | N64: =-N18 -> -34390.999 | ... W64: =-W18 -> -178880.83
B65: Lease expenses | G65: =Assumption!G363 -> 4800 | H65: =Assumption!H363 -> 0 | I65: =Assumption!I363 -> 5912 | J65: =Assumption!J363 -> 5976 | K65: =Assumption!K363 -> 7456 | L65: =Assumption!L363 -> 3239 | M65: =Assumption!M363 -> 0 | N65: =Assumption!N363 -> 0 | ... W65: =Assumption!W363 -> 106.63015
A66: Adjusted EBIT | G66: =G17 -> 2468834 | H66: =H17 -> 2101392 | I66: =I17 -> 2568577 | J66: =J17 -> 3110238 | K66: =K17 -> 4001184 | L66: =L17 -> 4453064 | M66: =M17 -> 2437883 | N66: =N17 -> 3178651 | ... W66: =W17 -> 12438273
A67: Adjusted EBITDA | G67: =G66+G59 -> 2569633 | H67: =H66+H59 -> 2235578 | I67: =I66+I59 -> 2752341 | J67: =J66+J59 -> 3301890 | K67: =K66+K59 -> 4268960 | L67: =L66+L59 -> 4751258 | M67: =M66+M59 -> 2437883 | N67: =N66+N59 -> 3178651 | ... W67: =W66+W59 -> 14146930
A68: Adjusted net income | G68: =G66+G26+G29+G30+G25 -> 1852569 | H68: =H66+H26+H29+H30+H25 -> 1592914 | I68: =I66+I26+I29+I30+I25 -> 1942381 | J68: =J66+J26+J29+J30+J25 -> 2352180 | K68: =K66+K26+K29+K30+K25 -> 3023627 | L68: =L66+L26+L29+L30+L25 -> 3442444 | M68: =M66+M26+M29+M30+M25 -> 1816183 | N68: =N66+N26+N29+N30+N25 -> 2526920 | ... W68: =W66+W26+W29+W30+W25 -> 10146480 | AB68: =(S68/O68)^0.5-1 -> 0.18101986 | AC68: =(U68/K68)^0.2-1 -> 0.22083421
R69: =+R31-R18 -> 5363347.6
A72: Balance Sheet
A74: Assets:
B75: Inventories | G75: 1251915 | I75: 1541156 | J75: 2374925 | K75: 2231714 | L75: 1839769 | O75: =2215352 -> 2215352 | P75: 2991706 | R75: =Assumption!R221 -> 2923795.2 | S75: =Assumption!S221 -> 3241944.3 | T75: =Assumption!T221 -> 3768575 | U75: =Assumption!U221 -> 4324056 | V75: =Assumption!V221 -> 4879002.8 | W75: =Assumption!W221 -> 5221619.9
B76: Trade receivables | G76: 2030 | I76: 15410 | J76: 28888 | K76: 28473 | L76: 21506 | O76: 25624 | P76: 34750 | R76: =Assumption!R227 -> 33220.636 | S76: =Assumption!S227 -> 36861.681 | T76: =Assumption!T227 -> 42847.473 | U76: =Assumption!U227 -> 49174.957 | V76: =Assumption!V227 -> 55502.7 | W76: =Assumption!W227 -> 59480.444
B77: Prepayments, receivables and other current assets | G77: 181892 | I77: 304539 | J77: 431517 | K77: 404428 | L77: 490867 | O77: 512505 | P77: 485200 | R77: =Assumption!R233 -> 664445.12 | S77: =Assumption!S233 -> 737269.58 | T77: =Assumption!T233 -> 856991.26 | U77: =Assumption!U233 -> 983547.11 | V77: =Assumption!V233 -> 1110108.2 | W77: =Assumption!W233 -> 1189666.9
B78: Short-term financial assets | G78: 900237 | I78: 1865676 | J78: 2574790 | K78: 746046 | L78: 2842603 | O78: 3491643 | P78: 5113517 | R78: =Assumption!R328 -> 3703047.5 | S78: =Assumption!S328 -> 3927251.8 | T78: =Assumption!T328 -> 4165030.6 | U78: =Assumption!U328 -> 4417206 | V78: =Assumption!V328 -> 4684649.5 | W78: =Assumption!W328 -> 4968285.7
B79: Restricted cash and time deposits | G79: 61865 | I79: 65146 | J79: 169906 | K79: 115620 | L79: 331759 | O79: 1315804 | P79: 1350469 | R79: =Assumption!R354 -> 1295944.4 | S79: =Assumption!S354 -> 3135145.7 | T79: =Assumption!T354 -> 4367429.5 | U79: =Assumption!U354 -> 5999356.8 | V79: =Assumption!V354 -> 7929353.4 | W79: =Assumption!W354 -> 10161712
B80: Cash and cash equivalents | G80: 2675827 | I80: 2764138 | J80: 3759213 | K80: 5621904 | L80: 5980396 | O80: 4335123 | P80: 8405472 | R80: =R206 -> 12374765 | S80: =S206 -> 15908900 | T80: =T206 -> 21792586 | U80: =U206 -> 28576352 | V80: =V206 -> 36380488 | W80: =W206 -> 44703291
A81: Total current assets | G81: =SUM(G75:G80) -> 5073766 | I81: =SUM(I75:I80) -> 6556065 | J81: =SUM(J75:J80) -> 9339239 | K81: =SUM(K75:K80) -> 9148185 | L81: =SUM(L75:L80) -> 11506900 | O81: =SUM(O75:O80) -> 11896051 | P81: =SUM(P75:P80) -> 18381114 | R81: =SUM(R75:R80) -> 20995218 | S81: =SUM(S75:S80) -> 26987373 | T81: =SUM(T75:T80) -> 34993460 | U81: =SUM(U75:U80) -> 44349692 | V81: =SUM(V75:V80) -> 55039105 | W81: =SUM(W75:W80) -> 66304056
B82: Property, plant, and equipment | G82: 1033497 | I82: 1701086 | J82: 3013946 | K82: 3390053 | L82: 5156514 | O82: 5317826 | P82: =17529+5382169 -> 5399698 | R82: =Assumption!R278 -> 6525581 | S82: =Assumption!S278 -> 7420332.4 | T82: =Assumption!T278 -> 7791349 | U82: =Assumption!U278 -> 8025089.4 | V82: =Assumption!V278 -> 8105340.3 | W82: =Assumption!W278 -> 8024286.9
B83: Right-of-use assets | G83: 166031 | I83: 445560 | J83: 439265 | K83: 426986 | L83: 378520 | O83: 382189 | P83: 393800 | R83: =Assumption!R292 -> 364490.47 | S83: =Assumption!S292 -> 352726.69 | T83: =Assumption!T292 -> 341342.58 | U83: =Assumption!U292 -> 333739.31 | V83: =Assumption!V292 -> 326305.4 | W83: =Assumption!W292 -> 319037.08
B84: Other intangible assets | G84: 9029 | I84: 20591 | J84: 23844 | K84: 25624 | L84: 27428 | O84: 41964 | P84: 41773 | R84: =Assumption!R285 -> 49444.938 | S84: =Assumption!S285 -> 58259.505 | T84: =Assumption!T285 -> 57883.902 | U84: =Assumption!U285 -> 57510.719 | V84: =Assumption!V285 -> 57139.943 | W84: =Assumption!W285 -> 56771.557
B85: Investment in joint ventures & associates | G85: 0 | I85: 2820 | J85: 2856 | K85: 3016 | L85: 0 | O85: 0 | P85: 103846 | R85: =Assumption!R199 -> 0 | S85: =Assumption!S199 -> 0 | T85: =Assumption!T199 -> 0 | U85: =Assumption!U199 -> 0 | V85: =Assumption!V199 -> 0 | W85: =Assumption!W199 -> 0
B86: Long-term financial assets | G86: 11400 | I86: 11400 | J86: 10480 | K86: 10460 | L86: 6590 | O86: 6590 | P86: 6590 | R86: =Assumption!R331 -> 6590 | S86: =Assumption!S331 -> 6590 | T86: =Assumption!T331 -> 6590 | U86: =Assumption!U331 -> 6590 | V86: =Assumption!V331 -> 6590 | W86: =Assumption!W331 -> 6590
B87: Deferred tax assets | G87: 23613 | I87: 41598 | J87: 117317 | K87: 111889 | L87: 112119 | O87: 76005 | P87: 106716 | R87: =O87 -> 76005 | S87: =R87 -> 76005 | T87: =S87 -> 76005 | U87: =T87 -> 76005 | V87: =U87 -> 76005 | W87: =V87 -> 76005
B88: Restricted cash and time deposits | K88: 300000 | L88: 1287420 | O88: 1966926 | P88: 2742349 | R88: =O88 -> 1966926 | S88: =R88 -> 1966926 | T88: =S88 -> 1966926 | U88: =T88 -> 1966926 | V88: =U88 -> 1966926 | W88: =V88 -> 1966926
B89: Other non-current assets | G89: 999047 | I89: 1166236 | J89: 1143308 | K89: 1177353 | L89: 144842 | O89: =95771 -> 95771 | P89: 117018 | R89: =O89 -> 95771 | S89: =R89 -> 95771 | T89: =S89 -> 95771 | U89: =T89 -> 95771 | V89: =U89 -> 95771 | W89: =V89 -> 95771
A90: Total non-current assets | G90: =SUM(G82:G89) -> 2242617 | I90: =SUM(I82:I89) -> 3389291 | J90: =SUM(J82:J89) -> 4751016 | K90: =SUM(K82:K89) -> 5445381 | L90: =SUM(L82:L89) -> 7113433 | O90: =SUM(O82:O89) -> 7887271 | P90: =SUM(P82:P89) -> 8911790 | R90: =SUM(R82:R89) -> 9084808.4 | S90: =SUM(S82:S89) -> 9976610.6 | T90: =SUM(T82:T89) -> 10335867 | U90: =SUM(U82:U89) -> 10561631 | V90: =SUM(V82:V89) -> 10634078 | W90: =SUM(W82:W89) -> 10545388
A91: Total assets | G91: =G90+G81 -> 7316383 | I91: =I90+I81 -> 9945356 | J91: =J90+J81 -> 14090255 | K91: =K90+K81 -> 14593566 | L91: =L90+L81 -> 18620333 | O91: =O90+O81 -> 19783322 | P91: =P90+P81 -> 27292904 | R91: =R90+R81 -> 30080026 | S91: =S90+S81 -> 36963984 | T91: =T90+T81 -> 45329328 | U91: =U90+U81 -> 54911324 | V91: =V90+V81 -> 65673182 | W91: =W90+W81 -> 76849443
A93: Liabilities:
B94: Trade payables | G94: 596681 | I94: 881806 | J94: 1607958 | K94: 1316780 | L94: 1604693 | O94: 1767263 | P94: 2507498 | R94: =Assumption!R239 -> 2393045.8 | S94: =Assumption!S239 -> 2720672.9 | T94: =Assumption!T239 -> 3240778.7 | U94: =Assumption!U239 -> 3808135 | V94: =Assumption!V239 -> 4398048.7 | W94: =Assumption!W239 -> 4815176.9
B95: Other payable and accruals | G95: 600753 | I95: 910196 | J95: 1405197 | K95: 1571615 | L95: 1762109 | O95: 2043625 | P95: 2077385 | R95: =Assumption!R245 -> 2697152 | S95: =Assumption!S245 -> 2990639.2 | T95: =Assumption!T245 -> 3476447.1 | U95: =Assumption!U245 -> 3988869 | V95: =Assumption!V245 -> 4500798.1 | W95: =Assumption!W245 -> 4816856.7
B96: Contract liabilities | G96: 305817 | I96: 198305 | J96: 297594 | K96: 259271 | L96: 410767 | O96: 359636 | P96: 535386 | R96: =Assumption!R252 -> 466255.72 | S96: =Assumption!S252 -> 517358.23 | T96: =Assumption!T252 -> 601369.56 | U96: =Assumption!U252 -> 690176.58 | V96: =Assumption!V252 -> 778987.24 | W96: =Assumption!W252 -> 834815.36
B97: Interest-bearing bank borrowings | G97: 30030 | I97: 140088 | J97: 290192 | K97: 259748 | L97: 4536 | O97: 0 | P97: 0 | R97: =Assumption!R337 -> 0 | S97: =Assumption!S337 -> 0 | T97: =Assumption!T337 -> 0 | U97: =Assumption!U337 -> 0 | V97: =Assumption!V337 -> 0 | W97: =Assumption!W337 -> 0
B98: Lease liabilities | G98: 50321 | I98: 78813 | J98: 77289 | K98: 72065 | L98: 50689 | O98: 52004 | P98: 63719 | R98: =Assumption!R345 -> 37157.041 | S98: =Assumption!S345 -> 27365.307 | T98: =Assumption!T345 -> 17341.531 | U98: =Assumption!U345 -> 8654.5636 | V98: =Assumption!V345 -> 1835.3947 | W98: =Assumption!W345 -> 543.36061
B99: Tax payable | G99: 122576 | I99: 129445 | J99: 347592 | K99: 254834 | L99: 456457 | O99: 294310 | P99: 506549 | R99: =O99 -> 294310 | S99: =R99 -> 294310 | T99: =S99 -> 294310 | U99: =T99 -> 294310 | V99: =U99 -> 294310 | W99: =V99 -> 294310
A100: Total current liabilities | G100: =SUM(G94:G99) -> 1706178 | I100: =SUM(I94:I99) -> 2338653 | J100: =SUM(J94:J99) -> 4025822 | K100: =SUM(K94:K99) -> 3734313 | L100: =SUM(L94:L99) -> 4289251 | O100: =SUM(O94:O99) -> 4516838 | P100: =SUM(P94:P99) -> 5690537 | R100: =SUM(R94:R99) -> 5887920.5 | S100: =SUM(S94:S99) -> 6550345.6 | T100: =SUM(T94:T99) -> 7630246.9 | U100: =SUM(U94:U99) -> 8790145.2 | V100: =SUM(V94:V99) -> 9973979.4 | W100: =SUM(W94:W99) -> 10761702
B101: Deferred revenue | G101: 2001 | I101: 58024 | J101: 116805 | K101: 122407 | L101: 124754 | O101: =134090 -> 134090 | P101: 141773 | R101: =Assumption!R263 -> 239237.75 | S101: =Assumption!S263 -> 265270.1 | T101: =Assumption!T263 -> 308361.33 | U101: =Assumption!U263 -> 353813.22 | V101: =Assumption!V263 -> 399221.4 | W101: =Assumption!W263 -> 427255.84
B102: Lease liabilities | G102: 62408 | I102: 62736 | J102: 62072 | K102: 54360 | L102: 37732 | O102: 40548 | P102: 47388 | R102: =Assumption!R346 -> 28971.689 | S102: =Assumption!S346 -> 21336.983 | T102: =Assumption!T346 -> 13521.353 | U102: =Assumption!U346 -> 6748.0433 | V102: =Assumption!V346 -> 1431.0742 | W102: =Assumption!W346 -> 423.6633
B103: Other payable and accruals | G103: 0 | I103: 0 | K103: 60408 | L103: 58323 | O103: 20712 | P103: 19945 | R103: =O103 -> 20712 | S103: =R103 -> 20712 | T103: =S103 -> 20712 | U103: =T103 -> 20712 | V103: =U103 -> 20712 | W103: =V103 -> 20712
B104: Deferred tax liabilities | G104: 2559 | I104: 81 | J104: 4903 | K104: 1638 | L104: 1654 | O104: 2492 | P104: 3446 | R104: =O104 -> 2492 | S104: =R104 -> 2492 | T104: =S104 -> 2492 | U104: =T104 -> 2492 | V104: =U104 -> 2492 | W104: =V104 -> 2492
B105: Other liabilities | G105: 0 | I105: 0 | K105: 0 | O105: 0 | P105: 5000
B106: Contract liabilities | G106: 527 | I106: 6595 | J106: 27011 | K106: 24975 | L106: 12413 | O106: 7822 | P106: 3351 | R106: =Assumption!R253 -> 10140.954 | S106: =Assumption!S253 -> 11252.422 | T106: =Assumption!T253 -> 13079.649 | U106: =Assumption!U253 -> 15011.181 | V106: =Assumption!V253 -> 16942.793 | W106: =Assumption!W253 -> 18157.041
A107: Total non-current liabilities | G107: =SUM(G101:G106) -> 67495 | I107: =SUM(I101:I106) -> 127436 | J107: =SUM(J101:J106) -> 210791 | K107: =SUM(K101:K106) -> 263788 | L107: =SUM(L101:L106) -> 234876 | O107: =SUM(O101:O106) -> 205664 | P107: =SUM(P101:P106) -> 220903 | R107: =SUM(R101:R106) -> 301554.39 | S107: =SUM(S101:S106) -> 321063.51 | T107: =SUM(T101:T106) -> 358166.33 | U107: =SUM(U101:U106) -> 398776.45 | V107: =SUM(V101:V106) -> 440799.27 | W107: =SUM(W101:W106) -> 469040.55
A108: Total liabilities | G108: =G107+G100 -> 1773673 | I108: =I107+I100 -> 2466089 | J108: =J107+J100 -> 4236613 | K108: =K107+K100 -> 3998101 | L108: =L107+L100 -> 4524127 | O108: =O107+O100 -> 4722502 | P108: =P107+P100 -> 5911440 | R108: =R107+R100 -> 6189474.9 | S108: =S107+S100 -> 6871409.1 | T108: =T107+T100 -> 7988413.2 | U108: =U107+U100 -> 9188921.6 | V108: =V107+V100 -> 10414779 | W108: =W107+W100 -> 11230743
A110: Shareholder's Equity:
...

Sheet Assumption
A1: UBS Equity Research
A2: Mixue Group
A3: Unit: Thousand RMB | I3: 2022 | J3: 9M23 | K3: 2023 | L3: 9M24 | M3: 2024H1 | N3: 2024H2 | O3: 2024 | P3: 2025H1 | Q3: 2025H2E | R3: 2025E | S3: 2026E | T3: 2027E
G4: 2021 | H4: 9M22 | I4: 2022 | J4: 9M23 | K4: 2023 | L4: 9M24 | M4: 2024H1 | N4: 2024H2 | O4: 2024 | P4: 2025H1 | Q4: 2025H2E | R4: 2025E | S4: 2026E | T4: 2027E | U4: 2028E | V4: 2029E | W4: 2030E
A6: Model Assumptions
A8: Revenues:
A10: Sales of goods & equipment | G10: =G12+G14 -> 10154604 | H10: =H12+H14 -> 10336970 | I10: =I12+I14 -> 13299430 | J10: =J12+J14 -> 15109557 | K10: =K12+K14 -> 19896747 | L10: =L12+L14 -> 18216311 | M10: =M12+M14 -> 10384198 | N10: =O10-M10 -> 13824631 | O10: =O12+O14 -> 24208829 | P10: =P12+P14 -> 14494688 | Q10: =R10-P10 -> 16857844 | R10: =R12+R14 -> 31352532 | S10: =S12+S14 -> 34787574 | T10: =T12+T14 -> 40436920 | U10: =U12+U14 -> 46406425 | V10: =V12+V14 -> 52375105 | W10: =W12+W14 -> 56115159
B11: YoY % | I11: =I10/G10-1 -> 0.3096946 | K11: =K10/I10-1 -> 0.49606013 | L11: =L10/J10-1 -> 0.20561516 | O11: =O10/K10-1 -> 0.21672296 | P11: =P10/M10-1 -> 0.39584087 | Q11: =Q10/N10-1 -> 0.21940643 | R11: =R10/O10-1 -> 0.29508668 | S11: =S10/R10-1 -> 0.10956186 | T11: =T10/S10-1 -> 0.16239553 | U11: =U10/T10-1 -> 0.14762512 | V11: =V10/U10-1 -> 0.12861753 | W11: =W10/V10-1 -> 0.071408994 | X11: =(U10/K10)^0.2-1 -> 0.18456585
B12: Sales of goods | G12: 9457660 | H12: 9776336 | I12: 12551043 | J12: 14504715 | K12: 19160210 | L12: 17595055 | M12: 9926304 | N12: =O12-M12 -> 13526153 | O12: 23452457 | P12: 13843184 | Q12: =R12-P12 -> 16647651 | R12: =R136*R91/10^3 -> 30490835 | S12: =S136*S91/10^3 -> 33878414 | T12: =T136*T91/10^3 -> 39366698 | U12: =U136*U91/10^3 -> 45253053 | V12: =V136*V91/10^3 -> 51178619 | W12: =W136*W91/10^3 -> 55339652
C13: YoY % | I13: =I12/G12-1 -> 0.32707699 | K13: =K12/I12-1 -> 0.52658309 | L13: =L12/J12-1 -> 0.21305762 | O13: =O12/K12-1 -> 0.22401879 | P13: =P12/M12-1 -> 0.39459601 | Q13: =Q12/N12-1 -> 0.23077503 | R13: =R12/O12-1 -> 0.30011262 | S13: =S12/R12-1 -> 0.11110154 | T13: =T12/S12-1 -> 0.16199942 | U13: =U12/T12-1 -> 0.14952628 | V13: =V12/U12-1 -> 0.13094288 | W13: =W12/V12-1 -> 0.08130413
B14: Sales of equipment | G14: 696944 | H14: 560634 | I14: 748387 | J14: 604842 | K14: 736537 | L14: 621256 | M14: 457894 | N14: =O14-M14 -> 298478 | O14: 756372 | P14: 651504 | Q14: =R14-P14 -> 210192.52 | R14: =R138*R75/10^3 -> 861696.52 | S14: =S138*S75/10^3 -> 909159.59 | T14: =T138*T75/10^3 -> 1070222.6 | U14: =U138*U75/10^3 -> 1153372 | V14: =V138*V75/10^3 -> 1196486.8 | W14: =W138*W75/10^3 -> 775507.35
C15: YoY % | I15: =I14/G14-1 -> 0.073812243 | K15: =K14/I14-1 -> -0.015834054 | L15: =L14/J14-1 -> 0.027137666 | O15: =O14/K14-1 -> 0.02693008 | P15: =P14/M14-1 -> 0.42282712 | Q15: =Q14/N14-1 -> -0.29578554 | R15: =R14/O14-1 -> 0.13924963 | S15: =S14/R14-1 -> 0.055080952 | T15: =T14/S14-1 -> 0.17715592 | U15: =U14/T14-1 -> 0.077693601 | V15: =V14/U14-1 -> 0.037381518 | W15: =W14/V14-1 -> -0.35184632
A16: Franchise and related services | G16: 196382 | H16: 206270 | I16: 276147 | J16: 283771 | K16: 405718 | L16: 443360 | M16: 292856 | N16: =O16-M16 -> 327189 | O16: 620045 | P16: 380121 | Q16: =R16-P16 -> 457129.08 | R16: =R27*R141 -> 837250.08 | S16: =S27*S141 -> 930269.85 | T16: =T27*T141 -> 1080973 | U16: =U27*U141 -> 1242606.9 | V16: =V27*V141 -> 1405317.4 | W16: =W27*W141 -> 1519575.5
B17: YoY % | I17: =I16/G16-1 -> 0.40617266 | K17: =K16/I16-1 -> 0.46921024 | O17: =O16/K16-1 -> 0.52826594 | P17: =P16/M16-1 -> 0.29797921 | Q17: =Q16/N16-1 -> 0.39714072 | R17: =R16/O16-1 -> 0.35030534 | S17: =S16/R16-1 -> 0.11110154 | T17: =T16/S16-1 -> 0.16199942 | U17: =U16/T16-1 -> 0.14952628 | V17: =V16/U16-1 -> 0.13094288 | W17: =W16/V16-1 -> 0.08130413
A18: Total revenue | G18: =G10+G16 -> 10350986 | H18: =H10+H16 -> 10543240 | I18: =I10+I16 -> 13575577 | J18: =J10+J16 -> 15393328 | K18: =K10+K16 -> 20302465 | L18: =L10+L16 -> 18659671 | M18: =M10+M16 -> 10677054 | N18: =O18-M18 -> 14151820 | O18: =O10+O16 -> 24828874 | P18: =P10+P16 -> 14874809 | Q18: =Q10+Q16 -> 17314973 | R18: =R10+R16 -> 32189782 | S18: =S10+S16 -> 35717844 | T18: =T10+T16 -> 41517893 | U18: =U10+U16 -> 47649032 | V18: =V10+V16 -> 53780423 | W18: =W10+W16 -> 57634735
B19: YoY % | I19: =I18/G18-1 -> 0.31152501 | K19: =K18/I18-1 -> 0.49551397 | O19: =O18/K18-1 -> 0.22294874 | R19: =R18/O18-1 -> 0.29646564 | S19: =S18/R18-1 -> 0.10960191 | T19: =T18/S18-1 -> 0.16238522 | U19: =U18/T18-1 -> 0.14767462 | V19: =V18/U18-1 -> 0.12867817 | W19: =W18/V18-1 -> 0.07166756
A21: GMV by region:
B22: In mainland China | G22: =G31*G27 -> 22689714 | I22: =I31*I27 -> 29477389 | K22: 44700000 | M22: =M27-M24 -> 23157668 | N22: =N27-N24 -> 32367369 | O22: =O27-O24 -> 55483722 | P22: =P27-P24 -> 32811843 | Q22: =R22-P22 -> 40205441 | R22: =R92*R109/1000 -> 73017284 | S22: =S92*S109/1000 -> 81540238 | T22: =T92*T109/1000 -> 94651198 | U22: =U92*U109/1000 -> 1.0801622e+08 | V22: =V92*V109/1000 -> 1.2085516e+08 | W22: =W92*W109/1000 -> 1.2879366e+08
C23: YoY % | I23: =I22/G22-1 -> 0.2991521 | K23: =K22/I22-1 -> 0.51641653 | O23: =O22/K22-1 -> 0.24124657 | P23: =P22/M22-1 -> 0.41688888 | Q23: =Q22/N22-1 -> 0.24215968 | R23: =R22/O22-1 -> 0.31601272 | S23: =S22/R22-1 -> 0.11672517 | T23: =T22/S22-1 -> 0.16079128 | U23: =U22/T22-1 -> 0.14120291 | V23: =V22/U22-1 -> 0.11886123 | W23: =W22/V22-1 -> 0.065686005 | X23: =(U22/K22)^0.2-1 -> 0.1929886
B24: Outside mainland China | G24: =G27-G22 -> 110286.42 | I24: =I27-I22 -> 1222610.9 | K24: 3142000 | M24: =K24/K27*M27 -> 1627771.7 | N24: =O24-M24 -> 1448013.5 | O24: =O93*O113/1000 -> 3075785.1 | P24: =P93*P113/1000 -> 1796117.2 | Q24: =R24-P24 -> 1413687.6 | R24: =R93*R113/1000 -> 3209804.8 | S24: =S93*S113/1000 -> 3155796.9 | T24: =T93*T113/1000 -> 3765546.5 | U24: =U93*U113/1000 -> 5116411.4 | V24: =V93*V113/1000 -> 7091382.9 | W24: =W93*W113/1000 -> 9555472.8
C25: YoY % | I25: =I24/G24-1 -> 10.085779 | K25: =K24/I24-1 -> 1.5699101 | O25: =O24/K24-1 -> -0.02107411 | P25: =P24/M24-1 -> 0.10342084 | Q25: =Q24/N24-1 -> -0.023705465 | R25: =R24/O24-1 -> 0.043572512 | S25: =S24/R24-1 -> -0.016825924 | T25: =T24/S24-1 -> 0.19321572 | U25: =U24/T24-1 -> 0.35874339 | V25: =V24/U24-1 -> 0.38600719 | W25: =W24/V24-1 -> 0.34747663 | X25: =(U24/K24)^0.2-1 -> 0.10243211
B26: Check | M26: =M22+M24 -> 24785440 | N26: =N22+N24 -> 33815382 | O26: =O22+O24 -> 58559507 | P26: =P22+P24 -> 34607960 | Q26: =Q22+Q24 -> 41619129 | R26: =R22+R24 -> 76227089 | S26: =S22+S24 -> 84696035 | T26: =T22+T24 -> 98416744 | ... W26: =W22+W24 -> 1.3834913e+08
B27: Total | G27: 22800000 | I27: 30700000 | K27: =K22+K24 -> 47842000 | L27: 44900000 | M27: =M12/M137 -> 24785440 | N27: =N12/N137 -> 33815382 | O27: =O12/O137 -> 58559507 | P27: =P12/P137 -> 34607960 | Q27: =R27-P27 -> 41619129 | R27: =R22+R24 -> 76227089 | S27: =S22+S24 -> 84696035 | T27: =T22+T24 -> 98416744 | U27: =U22+U24 -> 1.1313263e+08 | V27: =V22+V24 -> 1.2794655e+08 | W27: =W22+W24 -> 1.3834913e+08
A29: Revenue breakdown by GMV:
B30: In mainland China | G30: 10300917 | I30: 13034937 | J30: 14222007 | K30: 18815533 | L30: 17707309 | M30: =L30/L34*M18 -> 10132113 | N30: =O30-M30 -> 13392647 | O30: =O22/O27*O18 -> 23524760 | P30: =P22/P27*P18 -> 14102822 | Q30: =R30-P30 -> 16731498 | R30: =R22/R27*R18 -> 30834320 | S30: =S22/S27*S18 -> 34386987 | T30: =T22/T27*T18 -> 39929367 | U30: =U22/U27*U18 -> 45494110 | V30: =V22/V27*V18 -> 50799666 | W30: =W22/W27*W18 -> 53654029
C31: % of revenue | G31: =G30/G34 -> 0.99516288 | I31: =I30/I34 -> 0.96017554 | J31: =J30/J34 -> 0.92390723 | K31: =K30/K34 -> 0.92676101 | L31: =L30/L34 -> 0.94896148 | M31: =M30/M34 -> 0.94896148 | N31: =N30/N34 -> 0.94635509 | O31: =O30/O34 -> 0.9474759 | P31: =P30/P34 -> 0.94810104 | ... W31: =W30/W34 -> 0.93093218
B32: Outside mainland China | G32: 50069 | I32: 540640 | J32: 1171321 | K32: 1486932 | L32: 952362 | M32: =M18-M30 -> 544941.04 | N32: =O32-M32 -> 759173.12 | O32: =O18-O30 -> 1304114.2 | P32: =P18-P30 -> 771987.15 | Q32: =R32-P32 -> 583474.8 | R32: =R18-R30 -> 1355461.9 | S32: =S18-S30 -> 1330856.4 | T32: =T18-T30 -> 1588526 | U32: =U18-U30 -> 2154922.4 | V32: =V18-V30 -> 2980757.1 | W32: =W18-W30 -> 3980705.5 | X32: =(S32-O32)/(S18-O18) -> 0.0024559013 | Y32: =(T32/R32)^(0.5)-1 -> 0.082563794
C33: % of revenue | G33: =G32/G34 -> 0.0048371237 | I33: =I32/I34 -> 0.039824458 | J33: =J32/J34 -> 0.076092772 | K33: =K32/K34 -> 0.073238988 | L33: =L32/L34 -> 0.05103852 | M33: =M32/M34 -> 0.05103852 | N33: =N32/N34 -> 0.053644911 | O33: =O32/O34 -> 0.052524096 | P33: =P32/P34 -> 0.051898962 | ... W33: =W32/W34 -> 0.06906782
B34: Total | G34: =G30+G32 -> 10350986 | I34: =I30+I32 -> 13575577 | J34: =J30+J32 -> 15393328 | K34: =K30+K32 -> 20302465 | L34: =L30+L32 -> 18659671 | M34: =M30+M32 -> 10677054 | N34: =O34-M34 -> 14151820 | O34: =O30+O32 -> 24828874 | P34: =P30+P32 -> 14874809 | Q34: =R34-P34 -> 17314973 | R34: =R30+R32 -> 32189782 | S34: =S30+S32 -> 35717844 | T34: =T30+T32 -> 41517893 | U34: =U30+U32 -> 47649032 | V34: =V30+V32 -> 53780423 | W34: =W30+W32 -> 57634735 | Y34: =(T34/R34)^(0.5)-1 -> 0.13568695
A36: Freshly made beverages GMV (mn RMB) | G36: =360.5*1000 -> 360500 | I36: =421.3*1000 -> 421300 | K36: =517.5*1000 -> 517500 | O36: 627900 | P36: 627900 | Q36: =R36 -> 746400 | R36: 746400 | S36: 876200 | T36: 1016800 | U36: 1163400 | V36: 1163400 | W36: 1163400 | X36: =(U36/K36)^0.2-1 -> 0.175882
B37: Implied market share | G37: =G22/1000/G36 -> 0.062939566 | I37: =I22/1000/I36 -> 0.069967693 | K37: =K22/1000/K36 -> 0.086376812 | O37: =O22/1000/O36 -> 0.088363946 | P37: =P22/1000/P36 -> 0.052256478 | R37: =R22/1000/R36 -> 0.097825943 | S37: =S22/1000/S36 -> 0.093061217 | T37: =T22/1000/T36 -> 0.093087331 | U37: =U22/1000/U36 -> 0.0928453 | V37: =V22/1000/V36 -> 0.10388101 | W37: =W22/1000/W36 -> 0.11070454
A39: COGS:
A41: Sales of goods & equipment | G41: =SUM(G43,G45) -> -7051166 | H41: =SUM(H43,H45) -> -7529000 | I41: =SUM(I43,I45) -> -9668582 | J41: =SUM(J43,J45) -> -10762792 | K41: =SUM(K43,K45) -> -14210447 | L41: =SUM(L43,L45) -> -12541860 | M41: =SUM(M43,M45) -> -7217017.6 | N41: =O41-M41 -> -9430120.6 | O41: =SUM(O43,O45) -> -16647138 | P41: =SUM(P43,P45) -> -10268412 | Q41: =R41-P41 -> -11706570 | R41: =SUM(R43,R45) -> -21974981 | S41: =SUM(S43,S45) -> -24378317 | T41: =SUM(T43,T45) -> -28338471 | U41: =SUM(U43,U45) -> -32515112 | V41: =SUM(V43,V45) -> -36687523 | W41: =SUM(W43,W45) -> -39261129
B42: YoY % | I42: =I41/G41-1 -> 0.37120329 | K42: =K41/I41-1 -> 0.46975498 | L42: =L41/J41-1 -> 0.165298 | O42: =O41/K41-1 -> 0.17147186 | R42: =R41/O41-1 -> 0.32004558 | S42: =S41/R41-1 -> 0.10936691 | T42: =T41/S41-1 -> 0.16244577 | U42: =U41/T41-1 -> 0.14738412 | V42: =V41/U41-1 -> 0.1283222 | W42: =W41/V41-1 -> 0.07014935
B43: Sales of goods | G43: -6483793 | H43: -7068431 | I43: -9060836 | J43: -10295459 | K43: =K54-K12 -> -13642070 | L43: -12044122 | M43: =M54-M12 -> -6863666.2 | N43: =O43-M43 -> -9177814.4 | O43: =O54-O12 -> -16041481 | P43: =P54-P12 -> -9765653.6 | Q43: =-Q142*Q91/1000 -> -11528892 | R43: =P43+Q43 -> -21294546 | S43: =S91*S142/1000*-1 -> -23660402 | T43: =T91*T142/1000*-1 -> -27493374 | U43: =U91*U142/1000*-1 -> -31604356 | V43: =V91*V142/1000*-1 -> -35742721 | W43: =W91*W142/1000*-1 -> -38648752
C44: YoY % | I44: =I43/G43-1 -> 0.39745917 | K44: =K43/I43-1 -> 0.50560826 | L44: =L43/J43-1 -> 0.16984799 | O44: =O43/K43-1 -> 0.17588322 | R44: =R43/O43-1 -> 0.32746759 | S44: =S43/R43-1 -> 0.11110154 | T44: =T43/S43-1 -> 0.16199942 | U44: =U43/T43-1 -> 0.14952628 | V44: =V43/U43-1 -> 0.13094288 | W44: =W43/V43-1 -> 0.08130413
B45: Sales of equipment | G45: -567373 | H45: -460569 | I45: -607746 | J45: -467333 | K45: -568377 | L45: -497738 | M45: =M55-M14 -> -353351.45 | N45: =O45-M45 -> -252306.14 | O45: =O55-O14 -> -605657.59 | P45: =P55-P14 -> -502758.03 | Q45: =-Q75*Q144/1000 -> -177677.63 | R45: =P45+Q45 -> -680435.66 | S45: =S75*S144/1000*-1 -> -717914.7 | T45: =T75*T144/1000*-1 -> -845097.54 | U45: =U75*U144/1000*-1 -> -910756.22 | V45: =V75*V144/1000*-1 -> -944801.67 | W45: =W75*W144/1000*-1 -> -612376.68
C46: YoY % | I46: =I45/G45-1 -> 0.071157775 | K46: =K45/I45-1 -> -0.064778707 | L46: =L45/J45-1 -> 0.065060674 | O46: =O45/K45-1 -> 0.06559131 | R46: =R45/O45-1 -> 0.12346591 | S46: =S45/R45-1 -> 0.055080952 | T46: =T45/S45-1 -> 0.17715592 | U46: =U45/T45-1 -> 0.077693601 | V46: =V45/U45-1 -> 0.037381518 | W46: =W45/V45-1 -> -0.35184632
A47: Franchise and related services | G47: -55958 | H47: -43013 | I47: -60158 | J47: -54897 | K47: -82912 | L47: -77389 | M47: =M56-M16 -> -53592.648 | N47: =O47-M47 -> -67936.172 | O47: =O56-O16 -> -121528.82 | P47: =P56-P16 -> -65760.933 | Q47: =Q56-Q16 -> -90345.102 | R47: =P47+Q47 -> -156106.03 | S47: =S56-S16 -> -160936.68 | T47: =T56-T16 -> -187008.33 | U47: =U56-U16 -> -214970.99 | V47: =V56-V16 -> -243119.91 | W47: =W56-W16 -> -262886.57
B48: YoY % | I48: =I47/G47-1 -> 0.075056292 | K48: =K47/I47-1 -> 0.37823731 | L48: =L47/J47-1 -> 0.40971273 | O48: =O47/K47-1 -> 0.46575671 | R48: =R47/O47-1 -> 0.28451864 | S48: =S47/R47-1 -> 0.030944663 | T48: =T47/S47-1 -> 0.16199942 | U48: =U47/T47-1 -> 0.14952628 | V48: =V47/U47-1 -> 0.13094288 | W48: =W47/V47-1 -> 0.08130413
A49: Total cost of sales | G49: =G41+G47 -> -7107124 | H49: =H41+H47 -> -7572013 | I49: =I41+I47 -> -9728740 | J49: =J41+J47 -> -10817689 | K49: =K41+K47 -> -14293359 | L49: =L41+L47 -> -12619249 | M49: =M41+M47 -> -7270610.3 | N49: =O49-M49 -> -9498056.7 | O49: =O41+O47 -> -16768667 | P49: =P41+P47 -> -10334173 | Q49: =R49-P49 -> -11796915 | R49: =R41+R47 -> -22131087 | S49: =S41+S47 -> -24539254 | T49: =T41+T47 -> -28525480 | U49: =U41+U47 -> -32730083 | V49: =V41+V47 -> -36930643 | W49: =W41+W47 -> -39524015
A51: Gross profit:
A53: Sales of goods & equipment | G53: =G10+G41 -> 3103438 | H53: =H10+H41 -> 2807970 | I53: =I10+I41 -> 3630848 | J53: =J10+J41 -> 4346765 | K53: =K10+K41 -> 5686300.5 | L53: =L10+L41 -> 5674451 | M53: =M63*M10 -> 3167180.4 | N53: =O53-M53 -> 4394510.4 | O53: =O54+O55 -> 7561690.8 | P53: =P63*P10 -> 4391890.5 | Q53: =R53-P53 -> 4985660.2 | R53: =R10+R41 -> 9377550.7 | S53: =S10+S41 -> 10409257 | T53: =T10+T41 -> 12098449 | U53: =U10+U41 -> 13891314 | V53: =V10+V41 -> 15687583 | W53: =W10+W41 -> 16854030
B54: Sales of goods | G54: =G12+G43 -> 2973867 | H54: =H12+H43 -> 2707905 | I54: =I12+I43 -> 3490207 | J54: =J12+J43 -> 4209256 | K54: =K64*K12 -> 5518140.5 | L54: =L12+L43 -> 5550933 | M54: =M53-M55 -> 3062637.8 | N54: =O54-M54 -> 4348338.6 | O54: =O12*O64 -> 7410976.4 | P54: =P53-P56 -> 4077530.4 | Q54: =Q12+Q43 -> 5118759.4 | R54: =P54+Q54 -> 9196289.8 | S54: =S12+S43 -> 10218012 | T54: =T12+T43 -> 11873324 | U54: =U12+U43 -> 13648698 | V54: =V12+V43 -> 15435897 | W54: =W12+W43 -> 16690900
B55: Sales of equipment | G55: =G14+G45 -> 129571 | H55: =H14+H45 -> 100065 | I55: =I14+I45 -> 140641 | J55: =J14+J45 -> 137509 | K55: =K14+K45 -> 168160 | L55: =L14+L45 -> 123518 | M55: =M65*M14 -> 104542.55 | N55: =O55-M55 -> 46171.86 | O55: =O57-O54-O56 -> 150714.41 | P55: =P65*P14 -> 148745.97 | Q55: =Q45+Q14 -> 32514.891 | R55: =P55+Q55 -> 181260.86 | S55: =S14+S45 -> 191244.88 | T55: =T14+T45 -> 225125.05 | U55: =U14+U45 -> 242615.82 | V55: =V14+V45 -> 251685.17 | W55: =W14+W45 -> 163130.67
A56: Franchise and related services | G56: =G16+G47 -> 140424 | H56: =H16+H47 -> 163257 | I56: =I16+I47 -> 215989 | J56: =J16+J47 -> 228874 | K56: =K16+K47 -> 322806 | L56: =L16+L47 -> 365971 | M56: =M66*M16 -> 239263.35 | N56: =O56-M56 -> 259252.83 | O56: =O66*O16 -> 498516.18 | P56: =P66*P16 -> 314360.07 | Q56: =Q66*Q16 -> 366783.97 | R56: =P56+Q56 -> 681144.04 | S56: =S16*S66 -> 769333.16 | T56: =T16*T66 -> 893964.69 | U56: =U16*U66 -> 1027635.9 | V56: =V16*V66 -> 1162197.5 | W56: =W16*W66 -> 1256689
A57: Total gross profit | G57: =G53+G56 -> 3243862 | H57: =H53+H56 -> 2971227 | I57: =I53+I56 -> 3846837 | J57: =J53+J56 -> 4575639 | K57: =K53+K56 -> 6009106.5 | L57: =L53+L56 -> 6040422 | M57: =FS!M11 -> 3402695 | N57: =O57-M57 -> 4657512 | O57: =FS!O11 -> 8060207 | P57: =FS!P11 -> 4706373 | Q57: =R57-P57 -> 5352321.7 | R57: =R53+R56 -> 10058695 | S57: =S53+S56 -> 11178590 | T57: =T53+T56 -> 12992414 | U57: =U53+U56 -> 14918949 | V57: =V53+V56 -> 16849780 | W57: =W53+W56 -> 18110719
A58: Mainland China | G58: 3223345 | I58: 3614312 | J58: 4071554 | K58: 5402693 | L58: 5664364 | M58: =M30*M68 -> 3191615.6 | N58: =O58-M58 -> 4453931.4 | O58: =O30*O68 -> 7645546.9 | P58: =P30*P68 -> 4442388.9 | Q58: =R58-P58 -> 5116250.3 | R58: =R30*R68 -> 9558639.2 | S58: =S30*S68 -> 10763127 | T58: =T30*T68 -> 12497892 | U58: =U30*U68 -> 14239656 | V58: =V30*V68 -> 15900295 | W58: =W30*W68 -> 16793711
A59: Outside mainland China | G59: =G57-G58 -> 20517 | I59: =I57-I58 -> 232525 | J59: =J57-J58 -> 504085 | K59: =K57-K58 -> 606413.48 | L59: =L57-L58 -> 376058 | M59: =M57-M58 -> 211079.42 | N59: =O59-M59 -> 203580.63 | O59: =O57-O58 -> 414660.05 | P59: =P57-P58 -> 263984.12 | Q59: =R59-P59 -> 236071.4 | R59: =R57-R58 -> 500055.51 | S59: =S57-S58 -> 415462.84 | T59: =T57-T58 -> 494521.56 | U59: =U57-U58 -> 679293.01 | V59: =V57-V58 -> 949484.77 | W59: =W57-W58 -> 1317008.2 | X59: =(S59-O59)/(S57-O57) -> 0.00025743646
A61: Gross profit margin:
A63: Sales of goods & equipment | G63: =G53/G10 -> 0.30561881 | H63: =H53/H10 -> 0.27164343 | I63: =I53/I10 -> 0.27300779 | J63: =J53/J10 -> 0.28768315 | K63: =K53/K10 -> 0.28579046 | L63: =L53/L10 -> 0.31150385 | M63: 0.305 | N63: =N53/N10 -> 0.31787542 | O63: =O53/O10 -> 0.31235261 | P63: 0.303 | Q63: =Q53/Q10 -> 0.29574721 | R63: =R53/R10 -> 0.29910027 | S63: =S53/S10 -> 0.29922342 | T63: =T53/T10 -> 0.29919313 | U63: =U53/U10 -> 0.2993403 | V63: =V53/V10 -> 0.29952365 | W63: =W53/W10 -> 0.30034719
B64: Sales of goods | G64: =G54/G12 -> 0.31444004 | H64: =H54/H12 -> 0.27698567 | I64: =I54/I12 -> 0.27808103 | J64: =J54/J12 -> 0.29019915 | K64: 0.288 | L64: =L54/L12 -> 0.31548256 | M64: =M54/M12 -> 0.30853758 | N64: =N54/N12 -> 0.32147637 | O64: 0.316 | P64: =P54/P12 -> 0.29455148 | Q64: =Q54/Q12 -> 0.30747637 | R64: =R54/R12 -> 0.30160833 | S64: =S54/S12 -> 0.30160833 | T64: =T54/T12 -> 0.30160833 | U64: =U54/U12 -> 0.30160833 | V64: =V54/V12 -> 0.30160833 | W64: =W54/W12 -> 0.30160833
B65: Sales of equipment | G65: =G55/G14 -> 0.18591307 | H65: =H55/H14 -> 0.17848543 | I65: =I55/I14 -> 0.1879255 | J65: =J55/J14 -> 0.22734698 | K65: =K55/K14 -> 0.22831168 | L65: =L55/L14 -> 0.19881981 | M65: =K65 -> 0.22831168 | N65: =N55/N14 -> 0.154691 | O65: =O55/O14 -> 0.19925963 | P65: =M65 -> 0.22831168 | Q65: =Q55/Q14 -> 0.154691 | R65: =R55/R14 -> 0.21035348 | S65: =S55/S14 -> 0.21035348 | T65: =T55/T14 -> 0.21035348 | U65: =U55/U14 -> 0.21035348 | V65: =V55/V14 -> 0.21035348 | W65: =W55/W14 -> 0.21035348
A66: Franchise and related services | G66: =G56/G16 -> 0.71505535 | H66: =H56/H16 -> 0.79147234 | I66: =I56/I16 -> 0.78215226 | J66: =J56/J16 -> 0.80654471 | K66: =K56/K16 -> 0.79564131 | L66: =L56/L16 -> 0.82544885 | M66: 0.817 | N66: =N56/N16 -> 0.79236413 | O66: 0.804 | P66: 0.827 | Q66: =N66+1% -> 0.80236413 | R66: =P66 -> 0.827 | S66: =R66 -> 0.827 | T66: =S66 -> 0.827 | U66: =T66 -> 0.827 | V66: =U66 -> 0.827 | W66: =V66 -> 0.827
A67: Total gross profit | G67: =G57/G18 -> 0.31338676 | H67: =H57/H18 -> 0.28181347 | I67: =I57/I18 -> 0.28336453 | J67: =J57/J18 -> 0.2972482 | K67: =K57/K18 -> 0.29597916 | L67: =L57/L18 -> 0.32371535 | M67: =M57/M18 -> 0.31869231 | N67: =N57/N18 -> 0.32911046 | ... W67: =W57/W18 -> 0.31423272
A68: Mainland China | G68: =G58/G30 -> 0.31291826 | I68: =I58/I30 -> 0.27727882 | J68: =J58/J30 -> 0.28628547 | K68: =K58/K30 -> 0.28714005 | L68: =L58/L30 -> 0.31988847 | M68: 0.315 | N68: =N58/N30 -> 0.33256543 | O68: 0.325 | P68: 0.315 | Q68: =Q58/Q30 -> 0.30578555 | R68: 0.31 | S68: 0.313 | T68: =S68 -> 0.313 | U68: =T68 -> 0.313 | V68: =U68 -> 0.313 | W68: =V68 -> 0.313
A69: Outside mainland China | G69: =G59/G32 -> 0.40977451 | I69: =I59/I32 -> 0.43009211 | J69: =J59/J32 -> 0.43035598 | K69: =K59/K32 -> 0.40782866 | L69: =L59/L32 -> 0.39486876 | M69: =M59/M32 -> 0.38734359 | N69: =N59/N32 -> 0.26816101 | O69: =O59/O32 -> 0.317963 | P69: =P59/P32 -> 0.34195403 | ... W69: =W59/W32 -> 0.33084795 | X69: check
G70: =G69-G68 -> 0.096856254 | H70: =H69-H68 -> 0 | I70: =I69-I68 -> 0.15281329 | J70: =J69-J68 -> 0.14407051 | K70: =K69-K68 -> 0.12068861 | L70: =L69-L68 -> 0.074980287
A72: Store Counts:
A73: Franchised stores
A74: Beginning units | G74: 12509 | H74: 19954 | I74: 19954 | J74: 28929 | K74: =I78 -> 28929 | L74: =K78 -> 37516 | M74: =K78 -> 37516 | N74: =M78 -> 43197 | O74: =K78 -> 37516 | P74: =O78 -> 46462 | Q74: =P78 -> 52996 | R74: =O78 -> 46462 | S74: =R78 -> 54300 | T74: =S78 -> 62300 | U74: =T78 -> 71800 | V74: =U78 -> 81800 | W74: =V78 -> 91800
B75: New openings | G75: 8022 | H75: 7190 | I75: 9671 | J75: 8020 | K75: 9894 | L75: 9064 | M75: 6480 | N75: =O75-M75 -> 4075 | O75: 10555 | P75: 7721 | Q75: =R75-P75 -> 2491 | R75: =R78-R77-R76-R74 -> 10212 | S75: =S78-S77-S76-S74 -> 10774.487 | T75: =T78-T77-T76-T74 -> 12683.251 | U75: =U78-U77-U76-U74 -> 13668.658 | V75: =V78-V77-V76-V74 -> 14179.613 | W75: =W78-W77-W76-W74 -> 9190.5686
B76: Closed by company | G76: -371 | H76: -287 | I76: -432 | J76: -453 | K76: -666 | L76: -584 | M76: -500 | N76: =O76-M76 -> -250 | O76: -750 | P76: -550 | Q76: =P76 -> -550 | R76: =P76+Q76 -> -1100 | S76: =R76/R74*S74 -> -1285.5667 | T76: =S76/S74*T74 -> -1474.9688 | U76: =T76/T74*U74 -> -1699.8838 | V76: =U76/U74*V74 -> -1936.6364 | W76: =V76/V74*W74 -> -2173.389
B77: Closed by franchisee | G77: -206 | H77: -183 | I77: -264 | J77: -403 | K77: -641 | L77: -714 | M77: =-799-M76 -> -299 | N77: =O77-M77 -> -560 | O77: =-1609-O76 -> -859 | P77: =-1187-P76 -> -637 | Q77: =P77 -> -637 | R77: =P77+Q77 -> -1274 | S77: =R77/R74*S74 -> -1488.92 | T77: =S77/S74*T74 -> -1708.282 | U77: =T77/T74*U74 -> -1968.7745 | V77: =U77/U74*V74 -> -2242.9771 | W77: =V77/V74*W74 -> -2517.1796
A78: Ending units | G78: =SUM(G74:G77) -> 19954 | H78: =SUM(H74:H77) -> 26674 | I78: =SUM(I74:I77) -> 28929 | J78: =SUM(J74:J77) -> 36093 | K78: =SUM(K74:K77) -> 37516 | L78: =SUM(L74:L77) -> 45282 | M78: =SUM(M74:M77) -> 43197 | N78: =SUM(N74:N77) -> 46462 | ... P78: =SUM(P74:P77) -> 52996 | Q78: =Q88-Q89 -> 54300 | R78: =R88-R89 -> 54300 | S78: =S88-S89 -> 62300 | T78: =T88-T89 -> 71800 | U78: =U88-U89 -> 81800 | V78: =V88-V89 -> 91800 | W78: =W88-W89 -> 96300
B79: YoY % | I79: =I78/G78-1 -> 0.4497845 | K79: =K78/I78-1 -> 0.29683017 | O79: =O78/K78-1 -> 0.23845826 | R79: =R78/O78-1 -> 0.168697 | S79: =S78/R78-1 -> 0.14732965 | T79: =T78/S78-1 -> 0.15248796 | U79: =U78/T78-1 -> 0.13927577 | V79: =V78/U78-1 -> 0.12224939 | W79: =W78/V78-1 -> 0.049019608
P80: =P86-O86 -> 6697
A81: By store locations: | I81: =(I87-G87) -> 1525 | P81: =P87-O87 -> -162 | R81: =I86*18%*0.54 -> 2642.6736 | S81: =K86*18%*0.54 -> 3230.3448
B82: Tier-1 cities | G82: 782 | I82: 1190 | J82: 1444 | K82: 1513 | L82: 1942 | M82: 1812 | N82: =O82 -> 1983 | O82: 1983 | P82: 2356
B83: New tier-1 cities | G83: 4172 | I83: 5710 | J83: 6725 | K83: 6886 | L83: 7960 | M83: 7671 | N83: =O83 -> 8143 | O83: 8143 | P83: 8878
B84: Tier-2 cities | G84: 3187 | I84: 4739 | J84: 5714 | K84: 5955 | L84: 7446 | M84: 7033 | N84: =O84 -> 7600 | O84: 7600 | P84: 9243
B85: Tier-3 cities and below | G85: 11590 | I85: 15549 | J85: 18297 | K85: 18880 | L85: 23162 | M85: 22097 | N85: =O85 -> 23858 | O85: 23858 | P85: 27804
B86: Mainland China stores | G86: =SUM(G82:G85) -> 19731 | I86: =SUM(I82:I85) -> 27188 | J86: =SUM(J82:J85) -> 32180 | K86: =SUM(K82:K85) -> 33234 | L86: =SUM(L82:L85) -> 40510 | M86: =SUM(M82:M85) -> 38613 | N86: =SUM(N82:N85) -> 41584 | O86: =SUM(O82:O85) -> 41584 | P86: =SUM(P82:P85) -> 48281 | Q86: =R86 -> 49584 | R86: =O86+8000 -> 49584 | S86: =R86+8000 -> 57584 | T86: =S86+8000 -> 65584 | U86: =T86+8000 -> 73584 | V86: =U86+7000 -> 80584 | W86: =V86+1500 -> 82084 | Y86: =(T86/R86)^0.5-1 -> 0.15008032
B87: Stores outside mainland China | G87: 270 | I87: 1795 | J87: 3973 | K87: 4331 | L87: 4792 | M87: 4605 | N87: =O87 -> 4895 | O87: 4895 | P87: 4733 | Q87: =P87 -> 4733 | R87: =Q87 -> 4733 | S87: =R87 -> 4733 | T87: =S87+1500 -> 6233 | U87: =T87+2000 -> 8233 | V87: =U87+3000 -> 11233 | W87: =V87+3000 -> 14233 | Y87: =(T87/R87)^0.5-1 -> 0.14757297
B88: Total stores (At the end of period) | G88: =SUM(G86:G87) -> 20001 | I88: =SUM(I86:I87) -> 28983 | J88: =SUM(J86:J87) -> 36153 | K88: =SUM(K86:K87) -> 37565 | L88: =SUM(L86:L87) -> 45302 | M88: =SUM(M86:M87) -> 43218 | N88: =SUM(N86:N87) -> 46479 | O88: =SUM(O86:O87) -> 46479 | P88: =SUM(P86:P87) -> 53014 | ... W88: =SUM(W86:W87) -> 96317
B89: Self operated stores | G89: =G88-G78 -> 47 | I89: =I88-I78 -> 54 | J89: =J88-J78 -> 60 | K89: =K88-K78 -> 49 | L89: =L88-L78 -> 20 | M89: =M88-M78 -> 21 | N89: =N88-N78 -> 17 | O89: =O88-O78 -> 17 | P89: =O89 -> 17 | Q89: =P89 -> 17 | R89: =O89 -> 17 | S89: =R89 -> 17 | T89: =S89 -> 17 | U89: =T89 -> 17 | V89: =U89 -> 17 | W89: =V89 -> 17
B91: Avg. store counts | G91: =G74+(G75+G76+G77)*0.5 -> 16231.5 | H91: =H74+(H75+H76+H77)*0.5 -> 23314 | I91: =I74+(I75+I76+I77)*0.5 -> 24441.5 | J91: =J74+(J75+J76+J77)*0.5 -> 32511 | K91: =K74+(K75+K76+K77)*0.5 -> 33222.5 | L91: =L74+(L75+L76+L77)*0.5 -> 41399 | M91: =M74+(M75+M76+M77)*0.5 -> 40356.5 | N91: =AVERAGE(M88:N88) -> 44848.5 | O91: =O74+(O75+O76+O77)*0.5 -> 41989 | P91: =P74+(P75+P76+P77)*0.5 -> 49729 | Q91: =Q74+(Q75+Q76+Q77)*0.5 -> 53648 | R91: =R74+(R75+R76+R77)*0.5 -> 50381 | S91: =S74+(S75+S76+S77)*0.5 -> 58300 | T91: =T74+(T75+T76+T77)*0.5 -> 67050 | U91: =U74+(U75+U76+U77)*0.5 -> 76800 | V91: =V74+(V75+V76+V77)*0.5 -> 86800 | W91: =W74+(W75+W76+W77)*0.5 -> 94050
C92: Domestic | G92: =G91-G93 -> 16131.5 | I92: =AVERAGE(I86,G86) -> 23459.5 | J92: =AVERAGE(I86,J86) -> 29684 | K92: =AVERAGE(K86,I86) -> 30211 | L92: =AVERAGE(K86,L86) -> 36872 | M92: =K86+(M86-K86)*1/4 -> 34578.75 | N92: =AVERAGE(M86:N86) -> 40098.5 | O92: =AVERAGE(O86,K86) -> 37409 | P92: =O86+(P86-O86)/4 -> 43258.25 | Q92: =P86+(Q86-P86)/4 -> 48606.75 | R92: =AVERAGE(R86,O86) -> 45584 | S92: =AVERAGE(S86,R86) -> 53584 | T92: =AVERAGE(T86,S86) -> 61584 | U92: =AVERAGE(U86,T86) -> 69584 | V92: =AVERAGE(V86,U86) -> 77084 | W92: =AVERAGE(W86,V86) -> 81334
C93: Overseas | G93: 100 | I93: =AVERAGE(I87,G87) -> 1032.5 | J93: =AVERAGE(I87,J87) -> 2884 | K93: =AVERAGE(K87,I87) -> 3063 | L93: =AVERAGE(K87,L87) -> 4561.5 | M93: =K87+(M87-K87)/4 -> 4399.5 | N93: =AVERAGE(M87:N87) -> 4750 | O93: =AVERAGE(O87,K87) -> 4613 | P93: =O87+(P87-O87)/4 -> 4854.5 | Q93: =AVERAGE(P87:Q87) -> 4733 | R93: =AVERAGE(R87,O87) -> 4814 | S93: =AVERAGE(S87,R87) -> 4733 | T93: =AVERAGE(T87,S87) -> 5483 | U93: =AVERAGE(U87,T87) -> 7233 | V93: =AVERAGE(V87,U87) -> 9733 | W93: =AVERAGE(W87,V87) -> 12733
O94: =O86-K86 -> 8350 | R94: =R86-O86 -> 8000 | S94: =S86-R86 -> 8000
A95: Growth rate: | O95: =O87-K87 -> 564 | R95: =R87-O87 -> -162 | S95: =S87-R87 -> 0
B96: Tier-1 cities | I96: =I82/G82-1 -> 0.52173913 | J96: =J82/I82-1 -> 0.21344538 | K96: =K82/I82-1 -> 0.27142857 | L96: =L82/J82-1 -> 0.34487535 | O96: =O82/K82-1 -> 0.31064111 | P96: =P82/M82-1 -> 0.30022075
B97: New tier-1 cities | I97: =I83/G83-1 -> 0.36864813 | J97: =J83/I83-1 -> 0.17775832 | K97: =K83/I83-1 -> 0.20595447 | L97: =L83/J83-1 -> 0.18364312 | O97: =O83/K83-1 -> 0.18254429 | P97: =P83/M83-1 -> 0.15734585
B98: Tier-2 cities | I98: =I84/G84-1 -> 0.48697835 | J98: =J84/I84-1 -> 0.20573961 | K98: =K84/I84-1 -> 0.25659422 | L98: =L84/J84-1 -> 0.30311516 | O98: =O84/K84-1 -> 0.27623846 | P98: =P84/M84-1 -> 0.3142329
B99: Tier-3 cities and below | I99: =I85/G85-1 -> 0.34158758 | J99: =J85/I85-1 -> 0.17673162 | K99: =K85/I85-1 -> 0.214226 | L99: =L85/J85-1 -> 0.26589058 | O99: =O85/K85-1 -> 0.26366525 | P99: =P85/M85-1 -> 0.25827035
B100: China stores | I100: =I86/G86-1 -> 0.3779332 | J100: =J86/I86-1 -> 0.18361042 | K100: =K86/I86-1 -> 0.22237752 | L100: =L86/K86-1 -> 0.21893242 | O100: =O86/K86-1 -> 0.25124872 | P100: =P86/M86-1 -> 0.250382 | R100: =R86/O86-1 -> 0.19238169 | S100: =S86/R86-1 -> 0.16134237 | T100: =T86/S86-1 -> 0.13892748 | U100: =U86/T86-1 -> 0.12198097 | V100: =V86/U86-1 -> 0.095129376 | W100: =W86/V86-1 -> 0.018614117
B101: Overseas stores | I101: =I87/G87-1 -> 5.6481481 | J101: =J87/I87-1 -> 1.2133705 | K101: =K87/I87-1 -> 1.4128134 | L101: =L87/K87-1 -> 0.10644193 | O101: =O87/K87-1 -> 0.13022397 | P101: =P87/M87-1 -> 0.027795874 | R101: =R87/O87-1 -> -0.033094995 | S101: =S87/R87-1 -> 0 | T101: =T87/S87-1 -> 0.31692373 | U101: =U87/T87-1 -> 0.32087277 | V101: =V87/U87-1 -> 0.36438722 | W101: =W87/V87-1 -> 0.26707024
B102: Total stores | I102: =I88/G88-1 -> 0.44907755 | J102: =J88/I88-1 -> 0.2473864 | K102: =K88/I88-1 -> 0.29610461 | L102: =L88/K88-1 -> 0.205963 | O102: =O88/K88-1 -> 0.23729535 | P102: =P78/43218-1 -> 0.22624832 | R102: =R88/O88-1 -> 0.1686353 | S102: =S88/R88-1 -> 0.14728354 | T102: =T88/S88-1 -> 0.15244636 | U102: =U88/T88-1 -> 0.1392428 | V102: =V88/U88-1 -> 0.12222399 | W102: =W88/V88-1 -> 0.049010532
A105: Franchise store model
B107: Sales per store overall | G107: =G27/G91*1000 -> 1404676.1 | I107: =I27/I91*1000 -> 1256060.4 | K107: =K27/K91*1000 -> 1440048.2 | M107: =M27/M91*1000 -> 614162.28 | N107: =N27/N91*1000 -> 753991.38 | O107: =O27/O91*1000 -> 1394639.2 | P107: =P27/P91*1000 -> 695931.15 | Q107: =Q27/Q91*1000 -> 775781.55 | R107: =R27/R91*1000 -> 1513012.6 | S107: =S27/S91*1000 -> 1452762.2 | T107: =T27/T91*1000 -> 1467811.2 | ... W107: =W27/W91*1000 -> 1471016.8
C108: SSSG | I108: =I107/G107-1 -> -0.10580069 | K108: =K107/I107-1 -> 0.14648004 | O108: =O107/K107-1 -> -0.031532922 | P108: =P107/M107-1 -> 0.13313886 | Q108: =Q107/N107-1 -> 0.028899755 | R108: =R107/O107-1 -> 0.08487742 | S108: =S107/R107-1 -> -0.0398215 | T108: =T107/S107-1 -> 0.010358933 | U108: =U107/T107-1 -> 0.0035903246 | V108: =V107/U107-1 -> 0.00064992153 | W108: =W107/V107-1 -> -0.0020499893
B109: Sales per domestic store | G109: =G22/G92*1000 -> 1406547 | I109: =I22/I92*1000 -> 1256522.5 | K109: =K22/K92*1000 -> 1479593.5 | M109: =M22/M92*1000 -> 669708.08 | N109: =N22/N92*1000 -> 807196.5 | O109: =O22/O92*1000 -> 1483165.1 | P109: =P22/P92*1000 -> 758510.64 | Q109: =Q22/Q92*1000 -> 827157.56 | R109: =O109*(1+R110) -> 1601818.3 | S109: =R109*(1+S110) -> 1521727.3 | T109: =S109*(1+T110) -> 1536944.6 | U109: =T109*(1+U110) -> 1552314.1 | V109: =U109*(1+V110) -> 1567837.2 | W109: =V109*(1+W110) -> 1583515.6
C110: SSSG | I110: =I109/G109-1 -> -0.1066616 | K110: =K109/I109-1 -> 0.17753048 | O110: =O109/K109-1 -> 0.0024138606 | P110: =P109/M109-1 -> 0.1325989 | Q110: =Q109/N109-1 -> 0.024728872 | R110: =(1+R111)*(1+R112)-1 -> 0.08 | S110: =(1+S111)*(1+S112)-1 -> -0.05 | T110: =(1+T111)*(1+T112)-1 -> 0.01 | U110: =(1+U111)*(1+U112)-1 -> 0.01 | V110: =(1+V111)*(1+V112)-1 -> 0.01 | W110: =(1+W111)*(1+W112)-1 -> 0.01
D111: Cup volume | I111: -0.13 | K111: 0.16 | O111: =O110-O112 -> 0.0024138606 | P111: =P110-P112 -> 0.1325989 | Q111: =Q110-Q112 -> 0.024728872 | R111: 0.08 | S111: -0.05 | T111: 0.01 | U111: =T111 -> 0.01 | V111: =U111 -> 0.01 | W111: =V111 -> 0.01
D112: ASP | I112: =(1+I110)/(1+I111)-1 -> 0.026825746 | K112: =(1+K110)/(1+K111)-1 -> 0.015112487 | O112: 0 | P112: 0 | Q112: 0 | R112: 0 | S112: 0 | T112: =S112 -> 0 | U112: =T112 -> 0 | V112: =U112 -> 0 | W112: =V112 -> 0
B113: Sales per overseas store | G113: =G24/G93*1000 -> 1102864.2 | I113: =I24/I93*1000 -> 1184126.8 | K113: =K24/K93*1000 -> 1025791.7 | M113: =M24/M93*1000 -> 369990.15 | N113: =N24/N93*1000 -> 304844.94 | O113: =K113*(1+O114) -> 666764.61 | P113: =M113*(1+P114) -> 369990.15 | Q113: =Q24/Q93*1000 -> 298687.44 | R113: =O113*(1+R114) -> 666764.61 | S113: =R113*(1+S114) -> 666764.61 | T113: =S113*(1+T114) -> 686767.55 | U113: =T113*(1+U114) -> 707370.57 | V113: =U113*(1+V114) -> 728591.69 | W113: =V113*(1+W114) -> 750449.44
C114: SSSG | I114: =I113/G113-1 -> 0.073683178 | K114: =K113/I113-1 -> -0.13371461 | O114: =(1+O115)*(1+O116)-1 -> -0.35 | P114: =(1+P115)*(1+P116)-1 -> 0 | Q114: =Q113/N113-1 -> -0.020198808 | R114: =(1+R115)*(1+R116)-1 -> 0 | S114: =(1+S115)*(1+S116)-1 -> 0 | T114: =(1+T115)*(1+T116)-1 -> 0.03 | U114: =(1+U115)*(1+U116)-1 -> 0.03 | V114: =(1+V115)*(1+V116)-1 -> 0.03 | W114: =(1+W115)*(1+W116)-1 -> 0.03
D115: Cup volume | K115: 0.1 | O115: -0.35 | P115: 0 | Q115: =Q114-Q116 -> -0.020198808 | R115: 0 | S115: 0 | T115: 0.03 | U115: 0.03 | V115: 0.03 | W115: 0.03
D116: ASP | K116: =(1+K114)/(1+K115)-1 -> -0.21246782 | O116: 0 | P116: 0 | Q116: 0 | R116: 0 | S116: =R116 -> 0 | T116: =S116 -> 0 | U116: =T116 -> 0 | V116: =U116 -> 0 | W116: =V116 -> 0
B117: Operating costs:
...
