Workbook
Name A_ALL_WOW.AX: #REF!
Name Abnormals_PostTAX: #REF!
Name AEndDrinks_Sales: #REF!
Name Continuing_sales: #REF!
Name DCF_INF: #REF!
Name DPS: #REF!
Name E_ALL_COL.AX: '[1]COL.AX_Exchange_Sheet'!$A$1:$AN$471
Name E_ALL_WOW.AX: #REF!
Name EPS_Pre_Goodwill: #REF!
Name L_ALL_COL.AX: #REF!
Name L_ALL_WOW.AX: #REF!
Name NET_PROFIT: #REF!
Name NPAT_post_Abn: #REF!
Name Sales_Aust_FL: #REF!
Name Sales_NZ_FL: #REF!
Name TOTAL_SALES: #REF!
Name V_ALL_COL.AX: #REF!
Name V_ALL_WOW.AX: #REF!

Sheet Cover
B5: Woolworths Group (WOW.AX)
B6: Rating | C6: Buy
B7: Target Price/ Target price period/ Upside/downside to target price | C7: A$37/ 12 Month/ 16.5%
B8: M&A probability (1 = high, 3 = low) | C8: 3
B9: Market Cap (US$ mn) (price as of ______):
B10: Current shares outstanding (mn):
B11: Currency: | C11: AUD
B12: Current Publication Date: | C12: 46066
B13: Previous Publication Date:
B15: Team Contacts:
B16: Lead Analyst
B17: Peter Marks, peter.marks@gs.com, +61 2 9321 8846, Goldman Sachs Australia Pty Ltd
B18: Consumer Team
B19: James Leigh, james.leigh@gs.com, +61 2 , Goldman Sachs Australia Pty Ltd
B20: Consumer Team
B21: Rayanne Haidar, rayanne.haidar@gs.com +61 2 9321 8739, Goldman Sachs Australia Pty Ltd

Sheet Summary
D1: Woolworths Group (WOW.AX)
D6: Goldman Sachs | Woolworths Group | WOW-AU
D8: Price target | F8: =Valuation!E26 -> 37
D9: Current share price | F9: 31.75
D10: Upside / downside | F10: =F8/F9-1 -> 0.16535433
D11: Recommendation | F11: BUY
A13: Col C | B13: Col K | D13: P&L | E13: FY23 | F13: FY24 | G13: FY25 | H13: FY26E | I13: FY27E | J13: FY28E | L13: Balance sheet | M13: =E$13 -> FY23 | N13: =F$13 -> FY24 | O13: =G$13 -> FY25 | P13: =H$13 -> FY26E | Q13: =I$13 -> FY27E | R13: =J$13 -> FY28E
A14: - | B14: Cash | D14: Sales | L14: Cash | M14: =VLOOKUP($B14,BS!$1:$1048576,MATCH(Summary!M$13,CF!$3:$3,0),FALSE) -> 1135 | N14: =VLOOKUP($B14,BS!$1:$1048576,MATCH(Summary!N$13,CF!$3:$3,0),FALSE) -> 1298 | O14: =VLOOKUP($B14,BS!$1:$1048576,MATCH(Summary!O$13,CF!$3:$3,0),FALSE) -> 1275 | P14: =VLOOKUP($B14,BS!$1:$1048576,MATCH(Summary!P$13,CF!$3:$3,0),FALSE) -> 1379.0612 | Q14: =VLOOKUP($B14,BS!$1:$1048576,MATCH(Summary!Q$13,CF!$3:$3,0),FALSE) -> 1635.9805 | R14: =VLOOKUP($B14,BS!$1:$1048576,MATCH(Summary!R$13,CF!$3:$3,0),FALSE) -> 2028.8967
A15: Aus Food Sales | B15: TR | D15: Australian Food | E15: =VLOOKUP($A15,Model!$1:$1048576,MATCH(Summary!E$13,Model!$3:$3,0),FALSE) -> 48047 | F15: =VLOOKUP($A15,Model!$1:$1048576,MATCH(Summary!F$13,Model!$3:$3,0),FALSE) -> 50823 | G15: =VLOOKUP($A15,Model!$1:$1048576,MATCH(Summary!G$13,Model!$3:$3,0),FALSE) -> 51488 | H15: =VLOOKUP($A15,Model!$1:$1048576,MATCH(Summary!H$13,Model!$3:$3,0),FALSE) -> 53350.775 | I15: =VLOOKUP($A15,Model!$1:$1048576,MATCH(Summary!I$13,Model!$3:$3,0),FALSE) -> 55498.191 | J15: =VLOOKUP($A15,Model!$1:$1048576,MATCH(Summary!J$13,Model!$3:$3,0),FALSE) -> 57722.425 | L15: Trade receivables | M15: =VLOOKUP($B15,BS!$1:$1048576,MATCH(Summary!M$13,CF!$3:$3,0),FALSE) -> 1016 | N15: =VLOOKUP($B15,BS!$1:$1048576,MATCH(Summary!N$13,CF!$3:$3,0),FALSE) -> 1062 | O15: =VLOOKUP($B15,BS!$1:$1048576,MATCH(Summary!O$13,CF!$3:$3,0),FALSE) -> 1034 | P15: =VLOOKUP($B15,BS!$1:$1048576,MATCH(Summary!P$13,CF!$3:$3,0),FALSE) -> 1065.0715 | Q15: =VLOOKUP($B15,BS!$1:$1048576,MATCH(Summary!Q$13,CF!$3:$3,0),FALSE) -> 1107.6623 | R15: =VLOOKUP($B15,BS!$1:$1048576,MATCH(Summary!R$13,CF!$3:$3,0),FALSE) -> 1153.0636
A16: Aus B2B Sales | B16: Inventory | D16: Aus B2B | E16: =VLOOKUP($A16,Model!$1:$1048576,MATCH(Summary!E$13,Model!$3:$3,0),FALSE) -> 4324 | F16: =VLOOKUP($A16,Model!$1:$1048576,MATCH(Summary!F$13,Model!$3:$3,0),FALSE) -> 5594 | G16: =VLOOKUP($A16,Model!$1:$1048576,MATCH(Summary!G$13,Model!$3:$3,0),FALSE) -> 5743 | H16: =VLOOKUP($A16,Model!$1:$1048576,MATCH(Summary!H$13,Model!$3:$3,0),FALSE) -> 5944.005 | I16: =VLOOKUP($A16,Model!$1:$1048576,MATCH(Summary!I$13,Model!$3:$3,0),FALSE) -> 6241.2052 | J16: =VLOOKUP($A16,Model!$1:$1048576,MATCH(Summary!J$13,Model!$3:$3,0),FALSE) -> 6553.2655 | L16: Inventories | M16: =VLOOKUP($B16,BS!$1:$1048576,MATCH(Summary!M$13,CF!$3:$3,0),FALSE) -> 3698 | N16: =VLOOKUP($B16,BS!$1:$1048576,MATCH(Summary!N$13,CF!$3:$3,0),FALSE) -> 4187 | O16: =VLOOKUP($B16,BS!$1:$1048576,MATCH(Summary!O$13,CF!$3:$3,0),FALSE) -> 4169 | P16: =VLOOKUP($B16,BS!$1:$1048576,MATCH(Summary!P$13,CF!$3:$3,0),FALSE) -> 4294.2775 | Q16: =VLOOKUP($B16,BS!$1:$1048576,MATCH(Summary!Q$13,CF!$3:$3,0),FALSE) -> 4466.0003 | R16: =VLOOKUP($B16,BS!$1:$1048576,MATCH(Summary!R$13,CF!$3:$3,0),FALSE) -> 4649.0544
A17: NZ Supermarkets Sales | D17: NZ Supermarkets | E17: =VLOOKUP($A17,Model!$1:$1048576,MATCH(Summary!E$13,Model!$3:$3,0),FALSE) -> 7240 | F17: =VLOOKUP($A17,Model!$1:$1048576,MATCH(Summary!F$13,Model!$3:$3,0),FALSE) -> 7551 | G17: =VLOOKUP($A17,Model!$1:$1048576,MATCH(Summary!G$13,Model!$3:$3,0),FALSE) -> 7557 | H17: =VLOOKUP($A17,Model!$1:$1048576,MATCH(Summary!H$13,Model!$3:$3,0),FALSE) -> 7510.5624 | I17: =VLOOKUP($A17,Model!$1:$1048576,MATCH(Summary!I$13,Model!$3:$3,0),FALSE) -> 7748.9411 | J17: =VLOOKUP($A17,Model!$1:$1048576,MATCH(Summary!J$13,Model!$3:$3,0),FALSE) -> 8064.7313 | L17: Other current assets | M17: =M18-SUM(M14:M16) -> 526 | N17: =N18-SUM(N14:N16) -> 444 | O17: =O18-SUM(O14:O16) -> 513 | P17: =P18-SUM(P14:P16) -> 513 | Q17: =Q18-SUM(Q14:Q16) -> 513 | R17: =R18-SUM(R14:R16) -> 513
A18: W Living Sales | B18: CA | D18: W Living | E18: =VLOOKUP($A18,Model!$1:$1048576,MATCH(Summary!E$13,Model!$3:$3,0),FALSE) -> 4785 | F18: =VLOOKUP($A18,Model!$1:$1048576,MATCH(Summary!F$13,Model!$3:$3,0),FALSE) -> 5220 | G18: =VLOOKUP($A18,Model!$1:$1048576,MATCH(Summary!G$13,Model!$3:$3,0),FALSE) -> 5597 | H18: =VLOOKUP($A18,Model!$1:$1048576,MATCH(Summary!H$13,Model!$3:$3,0),FALSE) -> 5630.8058 | I18: =VLOOKUP($A18,Model!$1:$1048576,MATCH(Summary!I$13,Model!$3:$3,0),FALSE) -> 5785.0025 | J18: =VLOOKUP($A18,Model!$1:$1048576,MATCH(Summary!J$13,Model!$3:$3,0),FALSE) -> 5957.6171 | L18: Current assets | M18: =VLOOKUP($B18,BS!$1:$1048576,MATCH(Summary!M$13,CF!$3:$3,0),FALSE) -> 6375 | N18: =VLOOKUP($B18,BS!$1:$1048576,MATCH(Summary!N$13,CF!$3:$3,0),FALSE) -> 6991 | O18: =VLOOKUP($B18,BS!$1:$1048576,MATCH(Summary!O$13,CF!$3:$3,0),FALSE) -> 6991 | P18: =VLOOKUP($B18,BS!$1:$1048576,MATCH(Summary!P$13,CF!$3:$3,0),FALSE) -> 7251.4102 | Q18: =VLOOKUP($B18,BS!$1:$1048576,MATCH(Summary!Q$13,CF!$3:$3,0),FALSE) -> 7722.6432 | R18: =VLOOKUP($B18,BS!$1:$1048576,MATCH(Summary!R$13,CF!$3:$3,0),FALSE) -> 8344.0148
A19: Others Sales | B19: Fixed Assets | D19: Other | E19: =VLOOKUP($A19,Model!$1:$1048576,MATCH(Summary!E$13,Model!$3:$3,0),FALSE) -> -102 | F19: =VLOOKUP($A19,Model!$1:$1048576,MATCH(Summary!F$13,Model!$3:$3,0),FALSE) -> 226 | G19: =VLOOKUP($A19,Model!$1:$1048576,MATCH(Summary!G$13,Model!$3:$3,0),FALSE) -> 246 | H19: =VLOOKUP($A19,Model!$1:$1048576,MATCH(Summary!H$13,Model!$3:$3,0),FALSE) -> 270.6 | I19: =VLOOKUP($A19,Model!$1:$1048576,MATCH(Summary!I$13,Model!$3:$3,0),FALSE) -> 278.718 | J19: =VLOOKUP($A19,Model!$1:$1048576,MATCH(Summary!J$13,Model!$3:$3,0),FALSE) -> 287.07954 | L19: PPE | M19: =VLOOKUP($B19,BS!$1:$1048576,MATCH(Summary!M$13,CF!$3:$3,0),FALSE) -> 8881 | N19: =VLOOKUP($B19,BS!$1:$1048576,MATCH(Summary!N$13,CF!$3:$3,0),FALSE) -> 9678 | O19: =VLOOKUP($B19,BS!$1:$1048576,MATCH(Summary!O$13,CF!$3:$3,0),FALSE) -> 10172 | P19: =VLOOKUP($B19,BS!$1:$1048576,MATCH(Summary!P$13,CF!$3:$3,0),FALSE) -> 10552.43 | Q19: =VLOOKUP($B19,BS!$1:$1048576,MATCH(Summary!Q$13,CF!$3:$3,0),FALSE) -> 10873.593 | R19: =VLOOKUP($B19,BS!$1:$1048576,MATCH(Summary!R$13,CF!$3:$3,0),FALSE) -> 11133.753
A20: Elimination Sales | B20: ROU | D20: Eliminations | E20: =VLOOKUP($A20,Model!$1:$1048576,MATCH(Summary!E$13,Model!$3:$3,0),FALSE) -> 0 | F20: =VLOOKUP($A20,Model!$1:$1048576,MATCH(Summary!F$13,Model!$3:$3,0),FALSE) -> -1492 | G20: =VLOOKUP($A20,Model!$1:$1048576,MATCH(Summary!G$13,Model!$3:$3,0),FALSE) -> -1554 | H20: =VLOOKUP($A20,Model!$1:$1048576,MATCH(Summary!H$13,Model!$3:$3,0),FALSE) -> -1554 | I20: =VLOOKUP($A20,Model!$1:$1048576,MATCH(Summary!I$13,Model!$3:$3,0),FALSE) -> -1554 | J20: =VLOOKUP($A20,Model!$1:$1048576,MATCH(Summary!J$13,Model!$3:$3,0),FALSE) -> -1554 | L20: Lease assets | M20: =VLOOKUP($B20,BS!$1:$1048576,MATCH(Summary!M$13,CF!$3:$3,0),FALSE) -> 9467 | N20: =VLOOKUP($B20,BS!$1:$1048576,MATCH(Summary!N$13,CF!$3:$3,0),FALSE) -> 9604 | O20: =VLOOKUP($B20,BS!$1:$1048576,MATCH(Summary!O$13,CF!$3:$3,0),FALSE) -> 9162 | P20: =VLOOKUP($B20,BS!$1:$1048576,MATCH(Summary!P$13,CF!$3:$3,0),FALSE) -> 9190.45 | Q20: =VLOOKUP($B20,BS!$1:$1048576,MATCH(Summary!Q$13,CF!$3:$3,0),FALSE) -> 9233.3225 | R20: =VLOOKUP($B20,BS!$1:$1048576,MATCH(Summary!R$13,CF!$3:$3,0),FALSE) -> 9292.1186
A21: Total Sales | B21: Intangibles | D21: Total sales | E21: =VLOOKUP($A21,Model!$1:$1048576,MATCH(Summary!E$13,Model!$3:$3,0),FALSE) -> 64294 | F21: =VLOOKUP($A21,Model!$1:$1048576,MATCH(Summary!F$13,Model!$3:$3,0),FALSE) -> 67922 | G21: =VLOOKUP($A21,Model!$1:$1048576,MATCH(Summary!G$13,Model!$3:$3,0),FALSE) -> 69077 | H21: =VLOOKUP($A21,Model!$1:$1048576,MATCH(Summary!H$13,Model!$3:$3,0),FALSE) -> 71152.749 | I21: =VLOOKUP($A21,Model!$1:$1048576,MATCH(Summary!I$13,Model!$3:$3,0),FALSE) -> 73998.058 | J21: =VLOOKUP($A21,Model!$1:$1048576,MATCH(Summary!J$13,Model!$3:$3,0),FALSE) -> 77031.119 | L21: Intangibles | M21: =VLOOKUP($B21,BS!$1:$1048576,MATCH(Summary!M$13,CF!$3:$3,0),FALSE) -> 2189 | N21: =VLOOKUP($B21,BS!$1:$1048576,MATCH(Summary!N$13,CF!$3:$3,0),FALSE) -> 2407 | O21: =VLOOKUP($B21,BS!$1:$1048576,MATCH(Summary!O$13,CF!$3:$3,0),FALSE) -> 2241 | P21: =VLOOKUP($B21,BS!$1:$1048576,MATCH(Summary!P$13,CF!$3:$3,0),FALSE) -> 2241 | Q21: =VLOOKUP($B21,BS!$1:$1048576,MATCH(Summary!Q$13,CF!$3:$3,0),FALSE) -> 2241 | R21: =VLOOKUP($B21,BS!$1:$1048576,MATCH(Summary!R$13,CF!$3:$3,0),FALSE) -> 2241
A22: EBITDA | D22: EBITDA | E22: =VLOOKUP($A22,PL!$1:$1048576,MATCH(Summary!E$13,PL!$3:$3,0),FALSE) -> 5694 | F22: =VLOOKUP($A22,PL!$1:$1048576,MATCH(Summary!F$13,PL!$3:$3,0),FALSE) -> 6001 | G22: =VLOOKUP($A22,PL!$1:$1048576,MATCH(Summary!G$13,PL!$3:$3,0),FALSE) -> 5707 | H22: =VLOOKUP($A22,PL!$1:$1048576,MATCH(Summary!H$13,PL!$3:$3,0),FALSE) -> 6122.2555 | I22: =VLOOKUP($A22,PL!$1:$1048576,MATCH(Summary!I$13,PL!$3:$3,0),FALSE) -> 6587.8421 | J22: =VLOOKUP($A22,PL!$1:$1048576,MATCH(Summary!J$13,PL!$3:$3,0),FALSE) -> 7087.1762 | L22: Other non current assets | M22: =M23-SUM(M19:M21) -> 6736 | N22: =N23-SUM(N19:N21) -> 5256 | O22: =O23-SUM(O19:O21) -> 5263 | P22: =P23-SUM(P19:P21) -> 5263 | Q22: =Q23-SUM(Q19:Q21) -> 5263 | R22: =R23-SUM(R19:R21) -> 5263
A23: D&A | B23: NCA | D23: D&A | E23: =VLOOKUP($A23,PL!$1:$1048576,MATCH(Summary!E$13,PL!$3:$3,0),FALSE) -> -2578 | F23: =VLOOKUP($A23,PL!$1:$1048576,MATCH(Summary!F$13,PL!$3:$3,0),FALSE) -> -2778 | G23: =VLOOKUP($A23,PL!$1:$1048576,MATCH(Summary!G$13,PL!$3:$3,0),FALSE) -> -2953 | H23: =VLOOKUP($A23,PL!$1:$1048576,MATCH(Summary!H$13,PL!$3:$3,0),FALSE) -> -3071.12 | I23: =VLOOKUP($A23,PL!$1:$1048576,MATCH(Summary!I$13,PL!$3:$3,0),FALSE) -> -3193.9648 | J23: =VLOOKUP($A23,PL!$1:$1048576,MATCH(Summary!J$13,PL!$3:$3,0),FALSE) -> -3321.7234 | L23: Non-current assets | M23: =VLOOKUP($B23,BS!$1:$1048576,MATCH(Summary!M$13,CF!$3:$3,0),FALSE) -> 27273 | N23: =VLOOKUP($B23,BS!$1:$1048576,MATCH(Summary!N$13,CF!$3:$3,0),FALSE) -> 26945 | O23: =VLOOKUP($B23,BS!$1:$1048576,MATCH(Summary!O$13,CF!$3:$3,0),FALSE) -> 26838 | P23: =VLOOKUP($B23,BS!$1:$1048576,MATCH(Summary!P$13,CF!$3:$3,0),FALSE) -> 27246.88 | Q23: =VLOOKUP($B23,BS!$1:$1048576,MATCH(Summary!Q$13,CF!$3:$3,0),FALSE) -> 27610.915 | R23: =VLOOKUP($B23,BS!$1:$1048576,MATCH(Summary!R$13,CF!$3:$3,0),FALSE) -> 27929.872
B24: TP | D24: EBIT | L24: Trade payables | M24: =VLOOKUP($B24,BS!$1:$1048576,MATCH(Summary!M$13,CF!$3:$3,0),FALSE) -> 7623 | N24: =VLOOKUP($B24,BS!$1:$1048576,MATCH(Summary!N$13,CF!$3:$3,0),FALSE) -> 7762 | O24: =VLOOKUP($B24,BS!$1:$1048576,MATCH(Summary!O$13,CF!$3:$3,0),FALSE) -> 8083 | P24: =VLOOKUP($B24,BS!$1:$1048576,MATCH(Summary!P$13,CF!$3:$3,0),FALSE) -> 8325.8924 | Q24: =VLOOKUP($B24,BS!$1:$1048576,MATCH(Summary!Q$13,CF!$3:$3,0),FALSE) -> 8658.8344 | R24: =VLOOKUP($B24,BS!$1:$1048576,MATCH(Summary!R$13,CF!$3:$3,0),FALSE) -> 9013.746
A25: Aus Food EBIT | B25: C Borrowings | D25: Australian Food | E25: =VLOOKUP($A25,Model!$1:$1048576,MATCH(Summary!E$13,Model!$3:$3,0),FALSE) -> 2865 | F25: =VLOOKUP($A25,Model!$1:$1048576,MATCH(Summary!F$13,Model!$3:$3,0),FALSE) -> 3150 | G25: =VLOOKUP($A25,Model!$1:$1048576,MATCH(Summary!G$13,Model!$3:$3,0),FALSE) -> 2721 | H25: =VLOOKUP($A25,Model!$1:$1048576,MATCH(Summary!H$13,Model!$3:$3,0),FALSE) -> 2936.1146 | I25: =VLOOKUP($A25,Model!$1:$1048576,MATCH(Summary!I$13,Model!$3:$3,0),FALSE) -> 3240.4219 | J25: =VLOOKUP($A25,Model!$1:$1048576,MATCH(Summary!J$13,Model!$3:$3,0),FALSE) -> 3583.8158 | L25: Borrowings | M25: =VLOOKUP($B25,BS!$1:$1048576,MATCH(Summary!M$13,CF!$3:$3,0),FALSE) -> 466 | N25: =VLOOKUP($B25,BS!$1:$1048576,MATCH(Summary!N$13,CF!$3:$3,0),FALSE) -> 712 | O25: =VLOOKUP($B25,BS!$1:$1048576,MATCH(Summary!O$13,CF!$3:$3,0),FALSE) -> 244 | P25: =VLOOKUP($B25,BS!$1:$1048576,MATCH(Summary!P$13,CF!$3:$3,0),FALSE) -> 244 | Q25: =VLOOKUP($B25,BS!$1:$1048576,MATCH(Summary!Q$13,CF!$3:$3,0),FALSE) -> 244 | R25: =VLOOKUP($B25,BS!$1:$1048576,MATCH(Summary!R$13,CF!$3:$3,0),FALSE) -> 244
A26: Aus B2B EBIT | D26: Aus B2B | E26: =VLOOKUP($A26,Model!$1:$1048576,MATCH(Summary!E$13,Model!$3:$3,0),FALSE) -> 63 | F26: =VLOOKUP($A26,Model!$1:$1048576,MATCH(Summary!F$13,Model!$3:$3,0),FALSE) -> 122 | G26: =VLOOKUP($A26,Model!$1:$1048576,MATCH(Summary!G$13,Model!$3:$3,0),FALSE) -> 137 | H26: =VLOOKUP($A26,Model!$1:$1048576,MATCH(Summary!H$13,Model!$3:$3,0),FALSE) -> 147.739 | I26: =VLOOKUP($A26,Model!$1:$1048576,MATCH(Summary!I$13,Model!$3:$3,0),FALSE) -> 161.36716 | J26: =VLOOKUP($A26,Model!$1:$1048576,MATCH(Summary!J$13,Model!$3:$3,0),FALSE) -> 169.43552 | L26: Other current liabilities | M26: =M27-SUM(M24:M25) -> 3797 | N26: =N27-SUM(N24:N25) -> 4345 | O26: =O27-SUM(O24:O25) -> 3970 | P26: =P27-SUM(P24:P25) -> 3970 | Q26: =Q27-SUM(Q24:Q25) -> 3970 | R26: =R27-SUM(R24:R25) -> 3970
A27: NZ Supermarkets EBIT | B27: CL | D27: NZ Supermarkets | E27: =VLOOKUP($A27,Model!$1:$1048576,MATCH(Summary!E$13,Model!$3:$3,0),FALSE) -> 228 | F27: =VLOOKUP($A27,Model!$1:$1048576,MATCH(Summary!F$13,Model!$3:$3,0),FALSE) -> 100 | G27: =VLOOKUP($A27,Model!$1:$1048576,MATCH(Summary!G$13,Model!$3:$3,0),FALSE) -> 138 | H27: =VLOOKUP($A27,Model!$1:$1048576,MATCH(Summary!H$13,Model!$3:$3,0),FALSE) -> 157.72181 | I27: =VLOOKUP($A27,Model!$1:$1048576,MATCH(Summary!I$13,Model!$3:$3,0),FALSE) -> 178.22565 | J27: =VLOOKUP($A27,Model!$1:$1048576,MATCH(Summary!J$13,Model!$3:$3,0),FALSE) -> 201.61828 | L27: Current liabilities | M27: =VLOOKUP($B27,BS!$1:$1048576,MATCH(Summary!M$13,CF!$3:$3,0),FALSE) -> 11886 | N27: =VLOOKUP($B27,BS!$1:$1048576,MATCH(Summary!N$13,CF!$3:$3,0),FALSE) -> 12819 | O27: =VLOOKUP($B27,BS!$1:$1048576,MATCH(Summary!O$13,CF!$3:$3,0),FALSE) -> 12297 | P27: =VLOOKUP($B27,BS!$1:$1048576,MATCH(Summary!P$13,CF!$3:$3,0),FALSE) -> 12539.892 | Q27: =VLOOKUP($B27,BS!$1:$1048576,MATCH(Summary!Q$13,CF!$3:$3,0),FALSE) -> 12872.834 | R27: =VLOOKUP($B27,BS!$1:$1048576,MATCH(Summary!R$13,CF!$3:$3,0),FALSE) -> 13227.746
A28: W Living EBIT | B28: NC Lease | D28: W Living | E28: =VLOOKUP($A28,Model!$1:$1048576,MATCH(Summary!E$13,Model!$3:$3,0),FALSE) -> 145 | F28: =VLOOKUP($A28,Model!$1:$1048576,MATCH(Summary!F$13,Model!$3:$3,0),FALSE) -> -29 | G28: =VLOOKUP($A28,Model!$1:$1048576,MATCH(Summary!G$13,Model!$3:$3,0),FALSE) -> -31 | H28: =VLOOKUP($A28,Model!$1:$1048576,MATCH(Summary!H$13,Model!$3:$3,0),FALSE) -> 49.560103 | I28: =VLOOKUP($A28,Model!$1:$1048576,MATCH(Summary!I$13,Model!$3:$3,0),FALSE) -> 61.062615 | J28: =VLOOKUP($A28,Model!$1:$1048576,MATCH(Summary!J$13,Model!$3:$3,0),FALSE) -> 65.199165 | L28: Lease liabilities | M28: =VLOOKUP($B28,BS!$1:$1048576,MATCH(Summary!M$13,CF!$3:$3,0),FALSE) -> 10343 | N28: =VLOOKUP($B28,BS!$1:$1048576,MATCH(Summary!N$13,CF!$3:$3,0),FALSE) -> 10545 | O28: =VLOOKUP($B28,BS!$1:$1048576,MATCH(Summary!O$13,CF!$3:$3,0),FALSE) -> 10175 | P28: =VLOOKUP($B28,BS!$1:$1048576,MATCH(Summary!P$13,CF!$3:$3,0),FALSE) -> 10190.85 | Q28: =VLOOKUP($B28,BS!$1:$1048576,MATCH(Summary!Q$13,CF!$3:$3,0),FALSE) -> 10220.493 | R28: =VLOOKUP($B28,BS!$1:$1048576,MATCH(Summary!R$13,CF!$3:$3,0),FALSE) -> 10265.397
A29: Others EBIT | B29: NC Borrowings | D29: Other | E29: =VLOOKUP($A29,Model!$1:$1048576,MATCH(Summary!E$13,Model!$3:$3,0),FALSE) -> -185 | F29: =VLOOKUP($A29,Model!$1:$1048576,MATCH(Summary!F$13,Model!$3:$3,0),FALSE) -> -120 | G29: =VLOOKUP($A29,Model!$1:$1048576,MATCH(Summary!G$13,Model!$3:$3,0),FALSE) -> -211 | H29: =VLOOKUP($A29,Model!$1:$1048576,MATCH(Summary!H$13,Model!$3:$3,0),FALSE) -> -240 | I29: =VLOOKUP($A29,Model!$1:$1048576,MATCH(Summary!I$13,Model!$3:$3,0),FALSE) -> -247.2 | J29: =VLOOKUP($A29,Model!$1:$1048576,MATCH(Summary!J$13,Model!$3:$3,0),FALSE) -> -254.616 | L29: Borrowings | M29: =VLOOKUP($B29,BS!$1:$1048576,MATCH(Summary!M$13,CF!$3:$3,0),FALSE) -> 3289 | N29: =VLOOKUP($B29,BS!$1:$1048576,MATCH(Summary!N$13,CF!$3:$3,0),FALSE) -> 3866 | O29: =VLOOKUP($B29,BS!$1:$1048576,MATCH(Summary!O$13,CF!$3:$3,0),FALSE) -> 5267 | P29: =VLOOKUP($B29,BS!$1:$1048576,MATCH(Summary!P$13,CF!$3:$3,0),FALSE) -> 5267 | Q29: =VLOOKUP($B29,BS!$1:$1048576,MATCH(Summary!Q$13,CF!$3:$3,0),FALSE) -> 5267 | R29: =VLOOKUP($B29,BS!$1:$1048576,MATCH(Summary!R$13,CF!$3:$3,0),FALSE) -> 5267
A30: Total EBIT | D30: Total EBIT | E30: =VLOOKUP($A30,Model!$1:$1048576,MATCH(Summary!E$13,Model!$3:$3,0),FALSE) -> 3116 | F30: =VLOOKUP($A30,Model!$1:$1048576,MATCH(Summary!F$13,Model!$3:$3,0),FALSE) -> 3223 | G30: =VLOOKUP($A30,Model!$1:$1048576,MATCH(Summary!G$13,Model!$3:$3,0),FALSE) -> 2754 | H30: =VLOOKUP($A30,Model!$1:$1048576,MATCH(Summary!H$13,Model!$3:$3,0),FALSE) -> 3051.1355 | I30: =VLOOKUP($A30,Model!$1:$1048576,MATCH(Summary!I$13,Model!$3:$3,0),FALSE) -> 3393.8773 | J30: =VLOOKUP($A30,Model!$1:$1048576,MATCH(Summary!J$13,Model!$3:$3,0),FALSE) -> 3765.4528 | L30: Other non-current liabilities | M30: =M31-SUM(M28:M29) -> 1565 | N30: =N31-SUM(N28:N29) -> 1136 | O30: =O31-SUM(O28:O29) -> 1128 | P30: =P31-SUM(P28:P29) -> 1128 | Q30: =Q31-SUM(Q28:Q29) -> 1128 | R30: =R31-SUM(R28:R29) -> 1128
A31: Net Interest | B31: NCL | D31: Net interest | E31: =VLOOKUP($A31,PL!$1:$1048576,MATCH(Summary!E$13,PL!$3:$3,0),FALSE) -> -677 | F31: =VLOOKUP($A31,PL!$1:$1048576,MATCH(Summary!F$13,PL!$3:$3,0),FALSE) -> -740 | G31: =VLOOKUP($A31,PL!$1:$1048576,MATCH(Summary!G$13,PL!$3:$3,0),FALSE) -> -811 | H31: =VLOOKUP($A31,PL!$1:$1048576,MATCH(Summary!H$13,PL!$3:$3,0),FALSE) -> -815 | I31: =VLOOKUP($A31,PL!$1:$1048576,MATCH(Summary!I$13,PL!$3:$3,0),FALSE) -> -833.3 | J31: =VLOOKUP($A31,PL!$1:$1048576,MATCH(Summary!J$13,PL!$3:$3,0),FALSE) -> -852.149 | L31: Non-current liabilities | M31: =VLOOKUP($B31,BS!$1:$1048576,MATCH(Summary!M$13,CF!$3:$3,0),FALSE) -> 15197 | N31: =VLOOKUP($B31,BS!$1:$1048576,MATCH(Summary!N$13,CF!$3:$3,0),FALSE) -> 15547 | O31: =VLOOKUP($B31,BS!$1:$1048576,MATCH(Summary!O$13,CF!$3:$3,0),FALSE) -> 16570 | P31: =VLOOKUP($B31,BS!$1:$1048576,MATCH(Summary!P$13,CF!$3:$3,0),FALSE) -> 16585.85 | Q31: =VLOOKUP($B31,BS!$1:$1048576,MATCH(Summary!Q$13,CF!$3:$3,0),FALSE) -> 16615.493 | R31: =VLOOKUP($B31,BS!$1:$1048576,MATCH(Summary!R$13,CF!$3:$3,0),FALSE) -> 16660.397
A32: PBT | B32: Contributed Equity | D32: PBT | E32: =VLOOKUP($A32,PL!$1:$1048576,MATCH(Summary!E$13,PL!$3:$3,0),FALSE) -> 2439 | F32: =VLOOKUP($A32,PL!$1:$1048576,MATCH(Summary!F$13,PL!$3:$3,0),FALSE) -> 2483 | G32: =VLOOKUP($A32,PL!$1:$1048576,MATCH(Summary!G$13,PL!$3:$3,0),FALSE) -> 1943 | H32: =VLOOKUP($A32,PL!$1:$1048576,MATCH(Summary!H$13,PL!$3:$3,0),FALSE) -> 2236.1355 | I32: =VLOOKUP($A32,PL!$1:$1048576,MATCH(Summary!I$13,PL!$3:$3,0),FALSE) -> 2560.5773 | J32: =VLOOKUP($A32,PL!$1:$1048576,MATCH(Summary!J$13,PL!$3:$3,0),FALSE) -> 2913.3038 | L32: Contributed equity | M32: =VLOOKUP($B32,BS!$1:$1048576,MATCH(Summary!M$13,CF!$3:$3,0),FALSE) -> 5406 | N32: =VLOOKUP($B32,BS!$1:$1048576,MATCH(Summary!N$13,CF!$3:$3,0),FALSE) -> 5604 | O32: =VLOOKUP($B32,BS!$1:$1048576,MATCH(Summary!O$13,CF!$3:$3,0),FALSE) -> 5627 | P32: =VLOOKUP($B32,BS!$1:$1048576,MATCH(Summary!P$13,CF!$3:$3,0),FALSE) -> 5627 | Q32: =VLOOKUP($B32,BS!$1:$1048576,MATCH(Summary!Q$13,CF!$3:$3,0),FALSE) -> 5627 | R32: =VLOOKUP($B32,BS!$1:$1048576,MATCH(Summary!R$13,CF!$3:$3,0),FALSE) -> 5627
A33: Tax | B33: Reserves | D33: Tax | E33: =VLOOKUP($A33,PL!$1:$1048576,MATCH(Summary!E$13,PL!$3:$3,0),FALSE) -> -707 | F33: =VLOOKUP($A33,PL!$1:$1048576,MATCH(Summary!F$13,PL!$3:$3,0),FALSE) -> -763 | G33: =VLOOKUP($A33,PL!$1:$1048576,MATCH(Summary!G$13,PL!$3:$3,0),FALSE) -> -568 | H33: =VLOOKUP($A33,PL!$1:$1048576,MATCH(Summary!H$13,PL!$3:$3,0),FALSE) -> -664.13224 | I33: =VLOOKUP($A33,PL!$1:$1048576,MATCH(Summary!I$13,PL!$3:$3,0),FALSE) -> -760.49145 | J33: =VLOOKUP($A33,PL!$1:$1048576,MATCH(Summary!J$13,PL!$3:$3,0),FALSE) -> -865.25123 | L33: Reserves | M33: =VLOOKUP($B33,BS!$1:$1048576,MATCH(Summary!M$13,CF!$3:$3,0),FALSE) -> -7567 | N33: =VLOOKUP($B33,BS!$1:$1048576,MATCH(Summary!N$13,CF!$3:$3,0),FALSE) -> -7609 | O33: =VLOOKUP($B33,BS!$1:$1048576,MATCH(Summary!O$13,CF!$3:$3,0),FALSE) -> -7479 | P33: =VLOOKUP($B33,BS!$1:$1048576,MATCH(Summary!P$13,CF!$3:$3,0),FALSE) -> -7479 | Q33: =VLOOKUP($B33,BS!$1:$1048576,MATCH(Summary!Q$13,CF!$3:$3,0),FALSE) -> -7479 | R33: =VLOOKUP($B33,BS!$1:$1048576,MATCH(Summary!R$13,CF!$3:$3,0),FALSE) -> -7479
A34: Minorities | B34: Retained Profits | D34: Minority Interest | E34: =VLOOKUP($A34,PL!$1:$1048576,MATCH(Summary!E$13,PL!$3:$3,0),FALSE) -> -11 | F34: =VLOOKUP($A34,PL!$1:$1048576,MATCH(Summary!F$13,PL!$3:$3,0),FALSE) -> -9 | G34: =VLOOKUP($A34,PL!$1:$1048576,MATCH(Summary!G$13,PL!$3:$3,0),FALSE) -> 10 | H34: =VLOOKUP($A34,PL!$1:$1048576,MATCH(Summary!H$13,PL!$3:$3,0),FALSE) -> 10 | I34: =VLOOKUP($A34,PL!$1:$1048576,MATCH(Summary!I$13,PL!$3:$3,0),FALSE) -> 10 | J34: =VLOOKUP($A34,PL!$1:$1048576,MATCH(Summary!J$13,PL!$3:$3,0),FALSE) -> 10 | L34: Retained Profits | M34: =VLOOKUP($B34,BS!$1:$1048576,MATCH(Summary!M$13,CF!$3:$3,0),FALSE) -> 8586 | N34: =VLOOKUP($B34,BS!$1:$1048576,MATCH(Summary!N$13,CF!$3:$3,0),FALSE) -> 7413 | O34: =VLOOKUP($B34,BS!$1:$1048576,MATCH(Summary!O$13,CF!$3:$3,0),FALSE) -> 6712 | P34: =VLOOKUP($B34,BS!$1:$1048576,MATCH(Summary!P$13,CF!$3:$3,0),FALSE) -> 7132.5478 | Q34: =VLOOKUP($B34,BS!$1:$1048576,MATCH(Summary!Q$13,CF!$3:$3,0),FALSE) -> 7615.2315 | R34: =VLOOKUP($B34,BS!$1:$1048576,MATCH(Summary!R$13,CF!$3:$3,0),FALSE) -> 8165.7435
A35: NPAT | B35: Minorities | D35: NPAT | E35: =VLOOKUP($A35,PL!$1:$1048576,MATCH(Summary!E$13,PL!$3:$3,0),FALSE) -> 1721 | F35: =VLOOKUP($A35,PL!$1:$1048576,MATCH(Summary!F$13,PL!$3:$3,0),FALSE) -> 1711 | G35: =VLOOKUP($A35,PL!$1:$1048576,MATCH(Summary!G$13,PL!$3:$3,0),FALSE) -> 1385 | H35: =VLOOKUP($A35,PL!$1:$1048576,MATCH(Summary!H$13,PL!$3:$3,0),FALSE) -> 1582.0033 | I35: =VLOOKUP($A35,PL!$1:$1048576,MATCH(Summary!I$13,PL!$3:$3,0),FALSE) -> 1810.0858 | J35: =VLOOKUP($A35,PL!$1:$1048576,MATCH(Summary!J$13,PL!$3:$3,0),FALSE) -> 2058.0526 | L35: Minority Interests | M35: =VLOOKUP($B35,BS!$1:$1048576,MATCH(Summary!M$13,CF!$3:$3,0),FALSE) -> 140 | N35: =VLOOKUP($B35,BS!$1:$1048576,MATCH(Summary!N$13,CF!$3:$3,0),FALSE) -> 162 | O35: =VLOOKUP($B35,BS!$1:$1048576,MATCH(Summary!O$13,CF!$3:$3,0),FALSE) -> 102 | P35: =VLOOKUP($B35,BS!$1:$1048576,MATCH(Summary!P$13,CF!$3:$3,0),FALSE) -> 92 | Q35: =VLOOKUP($B35,BS!$1:$1048576,MATCH(Summary!Q$13,CF!$3:$3,0),FALSE) -> 82 | R35: =VLOOKUP($B35,BS!$1:$1048576,MATCH(Summary!R$13,CF!$3:$3,0),FALSE) -> 72
A36: Shares | B36: Total Equity | D36: Shares (m) | E36: =VLOOKUP($A36,PL!$1:$1048576,MATCH(Summary!E$13,PL!$3:$3,0),FALSE) -> 1223.1 | F36: =VLOOKUP($A36,PL!$1:$1048576,MATCH(Summary!F$13,PL!$3:$3,0),FALSE) -> 1225.7 | G36: =VLOOKUP($A36,PL!$1:$1048576,MATCH(Summary!G$13,PL!$3:$3,0),FALSE) -> 1228.7 | H36: =VLOOKUP($A36,PL!$1:$1048576,MATCH(Summary!H$13,PL!$3:$3,0),FALSE) -> 1230.7 | I36: =VLOOKUP($A36,PL!$1:$1048576,MATCH(Summary!I$13,PL!$3:$3,0),FALSE) -> 1232.7 | J36: =VLOOKUP($A36,PL!$1:$1048576,MATCH(Summary!J$13,PL!$3:$3,0),FALSE) -> 1234.7 | L36: Total Equity | M36: =VLOOKUP($B36,BS!$1:$1048576,MATCH(Summary!M$13,CF!$3:$3,0),FALSE) -> 6565 | N36: =VLOOKUP($B36,BS!$1:$1048576,MATCH(Summary!N$13,CF!$3:$3,0),FALSE) -> 5570 | O36: =VLOOKUP($B36,BS!$1:$1048576,MATCH(Summary!O$13,CF!$3:$3,0),FALSE) -> 4962 | P36: =VLOOKUP($B36,BS!$1:$1048576,MATCH(Summary!P$13,CF!$3:$3,0),FALSE) -> 5372.5478 | Q36: =VLOOKUP($B36,BS!$1:$1048576,MATCH(Summary!Q$13,CF!$3:$3,0),FALSE) -> 5845.2315 | R36: =VLOOKUP($B36,BS!$1:$1048576,MATCH(Summary!R$13,CF!$3:$3,0),FALSE) -> 6385.7435
A37: EPS | B37: Net Debt | D37: EPS | E37: =VLOOKUP($A37,PL!$1:$1048576,MATCH(Summary!E$13,PL!$3:$3,0),FALSE) -> 1.4070804 | F37: =VLOOKUP($A37,PL!$1:$1048576,MATCH(Summary!F$13,PL!$3:$3,0),FALSE) -> 1.395937 | G37: =VLOOKUP($A37,PL!$1:$1048576,MATCH(Summary!G$13,PL!$3:$3,0),FALSE) -> 1.1272076 | H37: =VLOOKUP($A37,PL!$1:$1048576,MATCH(Summary!H$13,PL!$3:$3,0),FALSE) -> 1.28545 | I37: =VLOOKUP($A37,PL!$1:$1048576,MATCH(Summary!I$13,PL!$3:$3,0),FALSE) -> 1.4683912 | J37: =VLOOKUP($A37,PL!$1:$1048576,MATCH(Summary!J$13,PL!$3:$3,0),FALSE) -> 1.6668442 | L37: Net debt ex leases | M37: =VLOOKUP($B37,BS!$1:$1048576,MATCH(Summary!M$13,CF!$3:$3,0),FALSE) -> 2620 | N37: =VLOOKUP($B37,BS!$1:$1048576,MATCH(Summary!N$13,CF!$3:$3,0),FALSE) -> 3280 | O37: =VLOOKUP($B37,BS!$1:$1048576,MATCH(Summary!O$13,CF!$3:$3,0),FALSE) -> 4236 | P37: =VLOOKUP($B37,BS!$1:$1048576,MATCH(Summary!P$13,CF!$3:$3,0),FALSE) -> 4131.9388 | Q37: =VLOOKUP($B37,BS!$1:$1048576,MATCH(Summary!Q$13,CF!$3:$3,0),FALSE) -> 3875.0195 | R37: =VLOOKUP($B37,BS!$1:$1048576,MATCH(Summary!R$13,CF!$3:$3,0),FALSE) -> 3482.1033
A38: DPS | D38: DPS total | E38: =VLOOKUP($A38,PL!$1:$1048576,MATCH(Summary!E$13,PL!$3:$3,0),FALSE) -> 1.04 | F38: =VLOOKUP($A38,PL!$1:$1048576,MATCH(Summary!F$13,PL!$3:$3,0),FALSE) -> 1.44 | G38: =VLOOKUP($A38,PL!$1:$1048576,MATCH(Summary!G$13,PL!$3:$3,0),FALSE) -> 0.84 | H38: =VLOOKUP($A38,PL!$1:$1048576,MATCH(Summary!H$13,PL!$3:$3,0),FALSE) -> 0.95123296 | I38: =VLOOKUP($A38,PL!$1:$1048576,MATCH(Summary!I$13,PL!$3:$3,0),FALSE) -> 1.0866095 | J38: =VLOOKUP($A38,PL!$1:$1048576,MATCH(Summary!J$13,PL!$3:$3,0),FALSE) -> 1.2334647 | L38: Divisional Key Metrics | M38: =E$13 -> FY23 | N38: =F$13 -> FY24 | O38: =G$13 -> FY25 | P38: =H$13 -> FY26E | Q38: =I$13 -> FY27E | R38: =J$13 -> FY28E
B39: Aus Food Comp | L39: Aus Food LFL Sales Growth | M39: =VLOOKUP($B39,Model!$1:$1048576,MATCH(Summary!M$13,CF!$3:$3,0),FALSE) -> 0.042 | N39: =VLOOKUP($B39,Model!$1:$1048576,MATCH(Summary!N$13,CF!$3:$3,0),FALSE) -> 0.028 | O39: =VLOOKUP($B39,Model!$1:$1048576,MATCH(Summary!O$13,CF!$3:$3,0),FALSE) -> 0.024 | P39: =VLOOKUP($B39,Model!$1:$1048576,MATCH(Summary!P$13,CF!$3:$3,0),FALSE) -> 0.02975 | Q39: =VLOOKUP($B39,Model!$1:$1048576,MATCH(Summary!Q$13,CF!$3:$3,0),FALSE) -> 0.035 | R39: =VLOOKUP($B39,Model!$1:$1048576,MATCH(Summary!R$13,CF!$3:$3,0),FALSE) -> 0.035
B40: Aus Food EBIT Margin | D40: Cash Flow | E40: FY23 | F40: FY24 | G40: FY25 | H40: FY26E | I40: FY27E | J40: FY28E | L40: Aus Food EBIT Margin | M40: =VLOOKUP($B40,Model!$1:$1048576,MATCH(Summary!M$13,CF!$3:$3,0),FALSE) -> 0.059629113 | N40: =VLOOKUP($B40,Model!$1:$1048576,MATCH(Summary!N$13,CF!$3:$3,0),FALSE) -> 0.061979812 | O40: =VLOOKUP($B40,Model!$1:$1048576,MATCH(Summary!O$13,CF!$3:$3,0),FALSE) -> 0.052847265 | P40: =VLOOKUP($B40,Model!$1:$1048576,MATCH(Summary!P$13,CF!$3:$3,0),FALSE) -> 0.05503415 | Q40: =VLOOKUP($B40,Model!$1:$1048576,MATCH(Summary!Q$13,CF!$3:$3,0),FALSE) -> 0.058387882 | R40: =VLOOKUP($B40,Model!$1:$1048576,MATCH(Summary!R$13,CF!$3:$3,0),FALSE) -> 0.062087063
A41: EBIT | B41: NZ LFL | D41: EBIT | E41: =VLOOKUP($A41,CF!$1:$1048576,MATCH(Summary!E$13,CF!$3:$3,0),FALSE) -> 3116 | F41: =VLOOKUP($A41,CF!$1:$1048576,MATCH(Summary!F$13,CF!$3:$3,0),FALSE) -> 3223 | G41: =VLOOKUP($A41,CF!$1:$1048576,MATCH(Summary!G$13,CF!$3:$3,0),FALSE) -> 2754 | H41: =VLOOKUP($A41,CF!$1:$1048576,MATCH(Summary!H$13,CF!$3:$3,0),FALSE) -> 3051.1355 | I41: =VLOOKUP($A41,CF!$1:$1048576,MATCH(Summary!I$13,CF!$3:$3,0),FALSE) -> 3393.8773 | J41: =VLOOKUP($A41,CF!$1:$1048576,MATCH(Summary!J$13,CF!$3:$3,0),FALSE) -> 3765.4528 | L41: NZ Food LFL Sales Growth | M41: =VLOOKUP($B41,Model!$1:$1048576,MATCH(Summary!M$13,CF!$3:$3,0),FALSE) -> 0.035 | N41: =VLOOKUP($B41,Model!$1:$1048576,MATCH(Summary!N$13,CF!$3:$3,0),FALSE) -> 0.018 | O41: =VLOOKUP($B41,Model!$1:$1048576,MATCH(Summary!O$13,CF!$3:$3,0),FALSE) -> 0.038 | P41: =VLOOKUP($B41,Model!$1:$1048576,MATCH(Summary!P$13,CF!$3:$3,0),FALSE) -> 0.03425 | Q41: =VLOOKUP($B41,Model!$1:$1048576,MATCH(Summary!Q$13,CF!$3:$3,0),FALSE) -> 0.035 | R41: =VLOOKUP($B41,Model!$1:$1048576,MATCH(Summary!R$13,CF!$3:$3,0),FALSE) -> 0.035
A42: D&A | B42: NZ Food EBIT Margin | D42: D&A | E42: =VLOOKUP($A42,CF!$1:$1048576,MATCH(Summary!E$13,CF!$3:$3,0),FALSE) -> 2578 | F42: =VLOOKUP($A42,CF!$1:$1048576,MATCH(Summary!F$13,CF!$3:$3,0),FALSE) -> 2778 | G42: =VLOOKUP($A42,CF!$1:$1048576,MATCH(Summary!G$13,CF!$3:$3,0),FALSE) -> 2953 | H42: =VLOOKUP($A42,CF!$1:$1048576,MATCH(Summary!H$13,CF!$3:$3,0),FALSE) -> 3071.12 | I42: =VLOOKUP($A42,CF!$1:$1048576,MATCH(Summary!I$13,CF!$3:$3,0),FALSE) -> 3193.9648 | J42: =VLOOKUP($A42,CF!$1:$1048576,MATCH(Summary!J$13,CF!$3:$3,0),FALSE) -> 3321.7234 | L42: NZ Food EBIT Margin | M42: =VLOOKUP($B42,Model!$1:$1048576,MATCH(Summary!M$13,CF!$3:$3,0),FALSE) -> 0.031471183 | N42: =VLOOKUP($B42,Model!$1:$1048576,MATCH(Summary!N$13,CF!$3:$3,0),FALSE) -> 0.013225569 | O42: =VLOOKUP($B42,Model!$1:$1048576,MATCH(Summary!O$13,CF!$3:$3,0),FALSE) -> 0.018102824 | P42: =VLOOKUP($B42,Model!$1:$1048576,MATCH(Summary!P$13,CF!$3:$3,0),FALSE) -> 0.021 | Q42: =VLOOKUP($B42,Model!$1:$1048576,MATCH(Summary!Q$13,CF!$3:$3,0),FALSE) -> 0.023 | R42: =VLOOKUP($B42,Model!$1:$1048576,MATCH(Summary!R$13,CF!$3:$3,0),FALSE) -> 0.025
A43: Net interest | D43: Net interest | E43: =VLOOKUP($A43,CF!$1:$1048576,MATCH(Summary!E$13,CF!$3:$3,0),FALSE) -> -677 | F43: =VLOOKUP($A43,CF!$1:$1048576,MATCH(Summary!F$13,CF!$3:$3,0),FALSE) -> -740 | G43: =VLOOKUP($A43,CF!$1:$1048576,MATCH(Summary!G$13,CF!$3:$3,0),FALSE) -> -811 | H43: =VLOOKUP($A43,CF!$1:$1048576,MATCH(Summary!H$13,CF!$3:$3,0),FALSE) -> -815 | I43: =VLOOKUP($A43,CF!$1:$1048576,MATCH(Summary!I$13,CF!$3:$3,0),FALSE) -> -833.3 | J43: =VLOOKUP($A43,CF!$1:$1048576,MATCH(Summary!J$13,CF!$3:$3,0),FALSE) -> -852.149 | L43: Group Key Metrics | M43: =E$13 -> FY23 | N43: =F$13 -> FY24 | O43: =G$13 -> FY25 | P43: =H$13 -> FY26E | Q43: =I$13 -> FY27E | R43: =J$13 -> FY28E
A44: Tax | B44: Total Sales Growth | D44: Tax | E44: =VLOOKUP($A44,CF!$1:$1048576,MATCH(Summary!E$13,CF!$3:$3,0),FALSE) -> -707 | F44: =VLOOKUP($A44,CF!$1:$1048576,MATCH(Summary!F$13,CF!$3:$3,0),FALSE) -> -763 | G44: =VLOOKUP($A44,CF!$1:$1048576,MATCH(Summary!G$13,CF!$3:$3,0),FALSE) -> -568 | H44: =VLOOKUP($A44,CF!$1:$1048576,MATCH(Summary!H$13,CF!$3:$3,0),FALSE) -> -664.13224 | I44: =VLOOKUP($A44,CF!$1:$1048576,MATCH(Summary!I$13,CF!$3:$3,0),FALSE) -> -760.49145 | J44: =VLOOKUP($A44,CF!$1:$1048576,MATCH(Summary!J$13,CF!$3:$3,0),FALSE) -> -865.25123 | L44: Sales Growth | M44: =VLOOKUP($B44,PL!$1:$1048576,MATCH(Summary!M$13,CF!$3:$3,0),FALSE) -> 0.056615557 | N44: =VLOOKUP($B44,PL!$1:$1048576,MATCH(Summary!N$13,CF!$3:$3,0),FALSE) -> 0.056428283 | O44: =VLOOKUP($B44,PL!$1:$1048576,MATCH(Summary!O$13,CF!$3:$3,0),FALSE) -> 0.0170048 | P44: =VLOOKUP($B44,PL!$1:$1048576,MATCH(Summary!P$13,CF!$3:$3,0),FALSE) -> 0.03004978 | Q44: =VLOOKUP($B44,PL!$1:$1048576,MATCH(Summary!Q$13,CF!$3:$3,0),FALSE) -> 0.039988751 | R44: =VLOOKUP($B44,PL!$1:$1048576,MATCH(Summary!R$13,CF!$3:$3,0),FALSE) -> 0.04098838
A45: Chg WC | B45: Total EBIT Growth | D45: Change in net working capital | E45: =VLOOKUP($A45,CF!$1:$1048576,MATCH(Summary!E$13,CF!$3:$3,0),FALSE) -> 544 | F45: =VLOOKUP($A45,CF!$1:$1048576,MATCH(Summary!F$13,CF!$3:$3,0),FALSE) -> -396 | G45: =VLOOKUP($A45,CF!$1:$1048576,MATCH(Summary!G$13,CF!$3:$3,0),FALSE) -> 367 | H45: =VLOOKUP($A45,CF!$1:$1048576,MATCH(Summary!H$13,CF!$3:$3,0),FALSE) -> 86.543366 | I45: =VLOOKUP($A45,CF!$1:$1048576,MATCH(Summary!I$13,CF!$3:$3,0),FALSE) -> 118.62836 | J45: =VLOOKUP($A45,CF!$1:$1048576,MATCH(Summary!J$13,CF!$3:$3,0),FALSE) -> 126.45619 | L45: EBIT Growth | M45: =VLOOKUP($B45,PL!$1:$1048576,MATCH(Summary!M$13,CF!$3:$3,0),FALSE) -> 0.15836431 | N45: =VLOOKUP($B45,PL!$1:$1048576,MATCH(Summary!N$13,CF!$3:$3,0),FALSE) -> 0.034338896 | O45: =VLOOKUP($B45,PL!$1:$1048576,MATCH(Summary!O$13,CF!$3:$3,0),FALSE) -> -0.1455166 | P45: =VLOOKUP($B45,PL!$1:$1048576,MATCH(Summary!P$13,CF!$3:$3,0),FALSE) -> 0.10789234 | Q45: =VLOOKUP($B45,PL!$1:$1048576,MATCH(Summary!Q$13,CF!$3:$3,0),FALSE) -> 0.11233254 | R45: =VLOOKUP($B45,PL!$1:$1048576,MATCH(Summary!R$13,CF!$3:$3,0),FALSE) -> 0.10948407
A46: Other | B46: NPAT Growth | D46: Other | E46: =VLOOKUP($A46,CF!$1:$1048576,MATCH(Summary!E$13,CF!$3:$3,0),FALSE) -> -100 | F46: =VLOOKUP($A46,CF!$1:$1048576,MATCH(Summary!F$13,CF!$3:$3,0),FALSE) -> 257 | G46: =VLOOKUP($A46,CF!$1:$1048576,MATCH(Summary!G$13,CF!$3:$3,0),FALSE) -> -145 | H46: =VLOOKUP($A46,CF!$1:$1048576,MATCH(Summary!H$13,CF!$3:$3,0),FALSE) -> 0 | I46: =VLOOKUP($A46,CF!$1:$1048576,MATCH(Summary!I$13,CF!$3:$3,0),FALSE) -> 0 | J46: =VLOOKUP($A46,CF!$1:$1048576,MATCH(Summary!J$13,CF!$3:$3,0),FALSE) -> 0 | L46: NPAT Growth | M46: =VLOOKUP($B46,PL!$1:$1048576,MATCH(Summary!M$13,CF!$3:$3,0),FALSE) -> 0.13672391 | N46: =VLOOKUP($B46,PL!$1:$1048576,MATCH(Summary!N$13,CF!$3:$3,0),FALSE) -> -0.0058105752 | O46: =VLOOKUP($B46,PL!$1:$1048576,MATCH(Summary!O$13,CF!$3:$3,0),FALSE) -> -0.19053185 | P46: =VLOOKUP($B46,PL!$1:$1048576,MATCH(Summary!P$13,CF!$3:$3,0),FALSE) -> 0.14224062 | Q46: =VLOOKUP($B46,PL!$1:$1048576,MATCH(Summary!Q$13,CF!$3:$3,0),FALSE) -> 0.14417327 | R46: =VLOOKUP($B46,PL!$1:$1048576,MATCH(Summary!R$13,CF!$3:$3,0),FALSE) -> 0.1369917
A47: OCF | B47: EPS Growth | D47: Operating cashflow | E47: =VLOOKUP($A47,CF!$1:$1048576,MATCH(Summary!E$13,CF!$3:$3,0),FALSE) -> 4754 | F47: =VLOOKUP($A47,CF!$1:$1048576,MATCH(Summary!F$13,CF!$3:$3,0),FALSE) -> 4359 | G47: =VLOOKUP($A47,CF!$1:$1048576,MATCH(Summary!G$13,CF!$3:$3,0),FALSE) -> 4550 | H47: =VLOOKUP($A47,CF!$1:$1048576,MATCH(Summary!H$13,CF!$3:$3,0),FALSE) -> 4729.6666 | I47: =VLOOKUP($A47,CF!$1:$1048576,MATCH(Summary!I$13,CF!$3:$3,0),FALSE) -> 5112.679 | J47: =VLOOKUP($A47,CF!$1:$1048576,MATCH(Summary!J$13,CF!$3:$3,0),FALSE) -> 5496.2322 | L47: EPS Growth | M47: =VLOOKUP($B47,PL!$1:$1048576,MATCH(Summary!M$13,CF!$3:$3,0),FALSE) -> 0.14341544 | N47: =VLOOKUP($B47,PL!$1:$1048576,MATCH(Summary!N$13,CF!$3:$3,0),FALSE) -> -0.0079194865 | O47: =VLOOKUP($B47,PL!$1:$1048576,MATCH(Summary!O$13,CF!$3:$3,0),FALSE) -> -0.19250825 | P47: =VLOOKUP($B47,PL!$1:$1048576,MATCH(Summary!P$13,CF!$3:$3,0),FALSE) -> 0.14038437 | Q47: =VLOOKUP($B47,PL!$1:$1048576,MATCH(Summary!Q$13,CF!$3:$3,0),FALSE) -> 0.1423169 | R47: =VLOOKUP($B47,PL!$1:$1048576,MATCH(Summary!R$13,CF!$3:$3,0),FALSE) -> 0.13514997
A48: Net capex | D48: Net capex | E48: =VLOOKUP($A48,CF!$1:$1048576,MATCH(Summary!E$13,CF!$3:$3,0),FALSE) -> -2158 | F48: =VLOOKUP($A48,CF!$1:$1048576,MATCH(Summary!F$13,CF!$3:$3,0),FALSE) -> -2206 | G48: =VLOOKUP($A48,CF!$1:$1048576,MATCH(Summary!G$13,CF!$3:$3,0),FALSE) -> -2230 | H48: =VLOOKUP($A48,CF!$1:$1048576,MATCH(Summary!H$13,CF!$3:$3,0),FALSE) -> -2180 | I48: =VLOOKUP($A48,CF!$1:$1048576,MATCH(Summary!I$13,CF!$3:$3,0),FALSE) -> -2180 | J48: =VLOOKUP($A48,CF!$1:$1048576,MATCH(Summary!J$13,CF!$3:$3,0),FALSE) -> -2180 | L48: RoE | M48: =E35/M36 -> 0.26214775 | N48: =F35/N36 -> 0.30718133 | O48: =G35/O36 -> 0.27912132 | P48: =H35/P36 -> 0.29446053 | Q48: =I35/Q36 -> 0.3096688 | R48: =J35/R36 -> 0.32228864
A49: Acquisitions | D49: Acquisitions | E49: =VLOOKUP($A49,CF!$1:$1048576,MATCH(Summary!E$13,CF!$3:$3,0),FALSE) -> -373 | F49: =VLOOKUP($A49,CF!$1:$1048576,MATCH(Summary!F$13,CF!$3:$3,0),FALSE) -> -487 | G49: =VLOOKUP($A49,CF!$1:$1048576,MATCH(Summary!G$13,CF!$3:$3,0),FALSE) -> -84 | H49: =VLOOKUP($A49,CF!$1:$1048576,MATCH(Summary!H$13,CF!$3:$3,0),FALSE) -> 0 | I49: =VLOOKUP($A49,CF!$1:$1048576,MATCH(Summary!I$13,CF!$3:$3,0),FALSE) -> 0 | J49: =VLOOKUP($A49,CF!$1:$1048576,MATCH(Summary!J$13,CF!$3:$3,0),FALSE) -> 0
A50: Proceeds from business sales | D50: Proceeds from business sales | E50: =VLOOKUP($A50,CF!$1:$1048576,MATCH(Summary!E$13,CF!$3:$3,0),FALSE) -> 659 | F50: =VLOOKUP($A50,CF!$1:$1048576,MATCH(Summary!F$13,CF!$3:$3,0),FALSE) -> 466 | G50: =VLOOKUP($A50,CF!$1:$1048576,MATCH(Summary!G$13,CF!$3:$3,0),FALSE) -> 408 | H50: =VLOOKUP($A50,CF!$1:$1048576,MATCH(Summary!H$13,CF!$3:$3,0),FALSE) -> 0 | I50: =VLOOKUP($A50,CF!$1:$1048576,MATCH(Summary!I$13,CF!$3:$3,0),FALSE) -> 0 | J50: =VLOOKUP($A50,CF!$1:$1048576,MATCH(Summary!J$13,CF!$3:$3,0),FALSE) -> 0 | L50: Valuation | M50: FY23 | N50: FY24 | O50: FY25 | P50: FY26E | Q50: FY27E | R50: FY28E
A51: Lease Repayment | D51: Lease repayments | E51: =VLOOKUP($A51,CF!$1:$1048576,MATCH(Summary!E$13,CF!$3:$3,0),FALSE) -> -1067 | F51: =VLOOKUP($A51,CF!$1:$1048576,MATCH(Summary!F$13,CF!$3:$3,0),FALSE) -> -1138 | G51: =VLOOKUP($A51,CF!$1:$1048576,MATCH(Summary!G$13,CF!$3:$3,0),FALSE) -> -1223 | H51: =VLOOKUP($A51,CF!$1:$1048576,MATCH(Summary!H$13,CF!$3:$3,0),FALSE) -> -1284.15 | I51: =VLOOKUP($A51,CF!$1:$1048576,MATCH(Summary!I$13,CF!$3:$3,0),FALSE) -> -1348.3575 | J51: =VLOOKUP($A51,CF!$1:$1048576,MATCH(Summary!J$13,CF!$3:$3,0),FALSE) -> -1415.7754 | L51: P/E | M51: =$F$9/E37 -> 22.564454 | N51: =$F$9/F37 -> 22.744579 | O51: =$F$9/G37 -> 28.166949 | P51: =$F$9/H37 -> 24.699523 | Q51: =$F$9/I37 -> 21.622303 | R51: =$F$9/J37 -> 19.047971
D52: FCF | E52: =SUM(E47:E51) -> 1815 | F52: =SUM(F47:F51) -> 994 | G52: =SUM(G47:G51) -> 1421 | H52: =SUM(H47:H51) -> 1265.5166 | I52: =SUM(I47:I51) -> 1584.3215 | J52: =SUM(J47:J51) -> 1900.4568 | L52: Div Yield | M52: =E38/$F$9 -> 0.032755906 | N52: =F38/$F$9 -> 0.045354331 | O52: =G38/$F$9 -> 0.026456693 | P52: =H38/$F$9 -> 0.029960093 | Q52: =I38/$F$9 -> 0.034223921 | R52: =J38/$F$9 -> 0.038849283
A53: Dividends paid | D53: Dividends paid | E53: =VLOOKUP($A53,CF!$1:$1048576,MATCH(Summary!E$13,CF!$3:$3,0),FALSE) -> -1026 | F53: =VLOOKUP($A53,CF!$1:$1048576,MATCH(Summary!F$13,CF!$3:$3,0),FALSE) -> -1172 | G53: =VLOOKUP($A53,CF!$1:$1048576,MATCH(Summary!G$13,CF!$3:$3,0),FALSE) -> -1661 | H53: =VLOOKUP($A53,CF!$1:$1048576,MATCH(Summary!H$13,CF!$3:$3,0),FALSE) -> -1161.4554 | I53: =VLOOKUP($A53,CF!$1:$1048576,MATCH(Summary!I$13,CF!$3:$3,0),FALSE) -> -1327.4022 | J53: =VLOOKUP($A53,CF!$1:$1048576,MATCH(Summary!J$13,CF!$3:$3,0),FALSE) -> -1507.5406 | L53: Payout Ratio | M53: =VLOOKUP($B54,PL!$1:$1048576,MATCH(Summary!M$13,PL!$3:$3,0),FALSE) -> 0.734043 | N53: =VLOOKUP($B54,PL!$1:$1048576,MATCH(Summary!N$13,PL!$3:$3,0),FALSE) -> 1.0265996 | O53: =VLOOKUP($B54,PL!$1:$1048576,MATCH(Summary!O$13,PL!$3:$3,0),FALSE) -> 0.7401704 | P53: =VLOOKUP($B54,PL!$1:$1048576,MATCH(Summary!P$13,PL!$3:$3,0),FALSE) -> 0.74 | Q53: =VLOOKUP($B54,PL!$1:$1048576,MATCH(Summary!Q$13,PL!$3:$3,0),FALSE) -> 0.74 | R53: =VLOOKUP($B54,PL!$1:$1048576,MATCH(Summary!R$13,PL!$3:$3,0),FALSE) -> 0.74
A54: Other financing | B54: Payout Ratio | D54: Other financing cashflows | E54: =VLOOKUP($A54,CF!$1:$1048576,MATCH(Summary!E$13,CF!$3:$3,0),FALSE) -> -115 | F54: =VLOOKUP($A54,CF!$1:$1048576,MATCH(Summary!F$13,CF!$3:$3,0),FALSE) -> -60 | G54: =VLOOKUP($A54,CF!$1:$1048576,MATCH(Summary!G$13,CF!$3:$3,0),FALSE) -> -450 | H54: =VLOOKUP($A54,CF!$1:$1048576,MATCH(Summary!H$13,CF!$3:$3,0),FALSE) -> -2.2737368e-13 | I54: =VLOOKUP($A54,CF!$1:$1048576,MATCH(Summary!I$13,CF!$3:$3,0),FALSE) -> 0 | J54: =VLOOKUP($A54,CF!$1:$1048576,MATCH(Summary!J$13,CF!$3:$3,0),FALSE) -> -2.2737368e-13 | L54: FCF Yield | M54: =(E52/VLOOKUP($B55,PL!$1:$1048576,MATCH(Summary!M$50,PL!$3:$3,0),FALSE))/$F$9 -> 0.047061294 | N54: =(F52/VLOOKUP($B55,PL!$1:$1048576,MATCH(Summary!N$50,PL!$3:$3,0),FALSE))/$F$9 -> 0.025665754 | O54: =(G52/VLOOKUP($B55,PL!$1:$1048576,MATCH(Summary!O$50,PL!$3:$3,0),FALSE))/$F$9 -> 0.036673144 | P54: =(H52/VLOOKUP($B55,PL!$1:$1048576,MATCH(Summary!P$50,PL!$3:$3,0),FALSE))/$F$9 -> 0.032644383 | Q54: =(I52/VLOOKUP($B55,PL!$1:$1048576,MATCH(Summary!Q$50,PL!$3:$3,0),FALSE))/$F$9 -> 0.040847978 | R54: =(J52/VLOOKUP($B55,PL!$1:$1048576,MATCH(Summary!R$50,PL!$3:$3,0),FALSE))/$F$9 -> 0.048974723
A55: Net Chg Cash | B55: Shares EOP | D55: FCF post financing | E55: =SUM(E52:E54) -> 674 | F55: =SUM(F52:F54) -> -238 | G55: =SUM(G52:G54) -> -690 | H55: =SUM(H52:H54) -> 104.06117 | I55: =SUM(I52:I54) -> 256.91934 | J55: =SUM(J52:J54) -> 392.91619
A56: Chg in Net Debt | D56: Change in net debt | E56: =VLOOKUP($A56,BS!$1:$1048576,MATCH(Summary!E$13,CF!$3:$3,0),FALSE) -> -640 | F56: =VLOOKUP($A56,BS!$1:$1048576,MATCH(Summary!F$13,CF!$3:$3,0),FALSE) -> 660 | G56: =VLOOKUP($A56,BS!$1:$1048576,MATCH(Summary!G$13,CF!$3:$3,0),FALSE) -> 956 | H56: =VLOOKUP($A56,BS!$1:$1048576,MATCH(Summary!H$13,CF!$3:$3,0),FALSE) -> -104.06117 | I56: =VLOOKUP($A56,BS!$1:$1048576,MATCH(Summary!I$13,CF!$3:$3,0),FALSE) -> -256.91934 | J56: =VLOOKUP($A56,BS!$1:$1048576,MATCH(Summary!J$13,CF!$3:$3,0),FALSE) -> -392.91619
D57: Note: FY24 includes 53 weeks vs. all other years include 52 weeks.

Sheet Model
B1: Woolworths Group (WOW.AX)
B2: A$M
C3: FY17 | D3: FY18 | E3: FY19 | F3: FY20 | G3: FY21 | H3: FY22 | I3: FY23 | J3: FY24 | K3: FY25 | L3: FY26E | M3: FY27E | N3: FY28E | O3: FY29E | P3: FY30E | R3: 1H17 | S3: 2H17 | T3: 1H18 | U3: 2H18 | V3: 1H19 | W3: 2H19 | X3: 1H20 | Y3: 2H20 | Z3: 1H21 | AA3: 2H21 | AB3: 1H22 | AC3: 2H22 | AD3: 1H23 | AE3: 2H23 | AF3: 1H24 | AG3: 2H24 | AH3: 1H25 | AI3: 2H25 | AJ3: 1H26E | AK3: 2H26E
B4: Model Summary
B6: Sales
A7: Aus Food Sales | B7: Australian Food | C7: =C30 -> 35836 | D7: =D30 -> 37589 | E7: =E30 -> 39635 | F7: =F30 -> 42151 | G7: =G30 -> 43746 | H7: =H30 -> 45740 | I7: =I30 -> 48047 | J7: =J30 -> 50823 | ... P7: =P30 -> 62411.748 | R7: =R30 -> 18712.6 | S7: =S30 -> 17123.4 | T7: =T30 -> 19436 | U7: =U30 -> 18153 | V7: =V30 -> 19928 | W7: =W30 -> 19707 | X7: =X30 -> 21200 | Y7: =Y30 -> 20951 | ... AK7: =AK30 -> 25732.964
A8: Aus B2B Sales | B8: Aus B2B | G8: =G317 -> 985 | H8: =H317 -> 3684 | I8: =I317 -> 4324 | J8: =J317 -> 5594 | K8: =K317 -> 5743 | L8: =L317 -> 5944.005 | M8: =M317 -> 6241.2052 | N8: =N317 -> 6553.2655 | ... P8: =P317 -> 7224.9752 | Z8: =Z317 -> 631 | AA8: =AA317 -> 354 | AB8: =AB317 -> 1979 | AC8: =AC317 -> 1705 | AD8: =AD317 -> 2433 | AE8: =AE317 -> 1891 | AF8: =AF317 -> 2828 | AG8: =AG317 -> 2766 | ... AK8: =AK317 -> 2842.725
B9: Endeavour drinks | C9: =C340 -> 7913 | D9: =D340 -> 8271 | E9: =E340 -> 8590 | F9: =F340 -> 9275 | G9: =G340 -> 10167 | R9: =R340 -> 4319.3 | S9: =S340 -> 3593.7 | T9: =T340 -> 4513 | U9: =U340 -> 3758 | V9: =V340 -> 4560 | W9: =W340 -> 4030 | X9: =X340 -> 4775 | Y9: =Y340 -> 4500 | ... AA9: =AA340 -> 4484
A10: NZ Supermarkets Sales | B10: NZ Supermarkets | C10: =C183 -> 5843 | D10: =D183 -> 5898 | E10: =E183 -> 6291 | F10: =F183 -> 6823 | G10: =G183 -> 6652 | H10: =H183 -> 7092 | I10: =I183 -> 7240 | J10: =J183 -> 7551 | ... P10: =P183 -> 8732.5841 | R10: =R183 -> 3068.9 | S10: =S183 -> 2774.1 | T10: =T183 -> 3060 | U10: =U183 -> 2838 | V10: =V183 -> 3143 | W10: =W183 -> 3148 | X10: =X183 -> 3367 | Y10: =Y183 -> 3456 | ... AD10: =AD183 -> 3703 | AE10: =I10-AD10 -> 3537 | AF10: =AF183 -> 3858 | AG10: =AG183 -> 3693 | AH10: =AH183 -> 3895 | AI10: =AI183 -> 3662 | AJ10: =AJ183 -> 3916.7475 | AK10: =AK183 -> 3593.8149
B11: Hotels | C11: =C345 -> 1553 | D11: =D345 -> 1612 | E11: =E345 -> 1671 | F11: =F345 -> 1320 | G11: =G345 -> 1417 | R11: =R345 -> 828.5 | S11: =S345 -> 724.5 | T11: =T345 -> 861 | U11: =U345 -> 751 | V11: =V345 -> 865 | W11: =W345 -> 806 | X11: =X345 -> 919 | Y11: =Y345 -> 401 | ... AA11: =AA345 -> 750
A12: W Living Sales | B12: W Living (prior to FY24, Big W) | C12: =C207 -> 3542 | D12: =D207 -> 3566 | E12: =E207 -> 3797 | F12: =F207 -> 4106 | G12: =G207 -> 4583 | H12: =H207 -> 4431 | I12: =I207 -> 4785 | J12: =J194 -> 5220 | K12: =K194 -> 5597 | L12: =L194 -> 5630.8058 | M12: =M194 -> 5785.0025 | N12: =N194 -> 5957.6171 | O12: =O194 -> 6134.7613 | P12: =P194 -> 6316.5493 | R12: =R207 -> 2050.3 | S12: =S207 -> 1547.7 | T12: =T207 -> 2037 | U12: =U207 -> 1529 | V12: =V207 -> 2091 | W12: =W207 -> 1706 | X12: =X207 -> 2149 | Y12: =Y207 -> 1957 | ... AE12: =AE207 -> 2077 | AF12: =AF194 -> 2656 | AG12: =AG194 -> 2564 | AH12: =AH194 -> 3061 | AI12: =AI194 -> 2536 | AJ12: =AJ194 -> 3088.372 | AK12: =AK194 -> 2542.4338
A13: Others Sales | B13: Others | G13: =G332 -> -233 | H13: =H332 -> -98 | I13: =I332 -> -102 | J13: =J332 -> 226 | K13: =K332 -> 246 | L13: =L332 -> 270.6 | M13: =M332 -> 278.718 | N13: =N332 -> 287.07954 | ... P13: =P332 -> 304.56268 | Z13: =Z332 -> -130 | AA13: =AA332 -> -103 | AB13: =AB332 -> -51 | AC13: =AC332 -> -47 | AD13: =AD332 -> -60 | AE13: =AE332 -> -42 | AF13: =AF332 -> 112 | AG13: =AG332 -> 114 | ... AK13: =AK332 -> 138.6
A14: Elimination Sales | B14: Elimination/Reclass/Unallocated | C14: 154 | D14: 239 | J14: -1492 | K14: =-411-391-375-377 -> -1554 | L14: =K14*1 -> -1554 | M14: =L14*1 -> -1554 | N14: =M14*1 -> -1554 | O14: =N14*1 -> -1554 | P14: =O14*1 -> -1554 | R14: 78.9 | S14: =C14-R14 -> 75.1 | U14: =D14-T14 -> 239 | AF14: -764 | AG14: =J14-AF14 -> -728 | AH14: =-411-391 -> -802 | AI14: =K14-AH14 -> -752 | AJ14: =AH14*1 -> -802 | AK14: =M14-AJ14 -> -752
A15: Total Sales | B15: Sales from Continuing Ops. | C15: =SUM(C7:C14) -> 54841 | D15: =SUM(D7:D14) -> 57175 | E15: =SUM(E7:E14) -> 59984 | F15: =SUM(F7:F14) -> 63675 | G15: =SUM(G7:G14) -> 67317 | H15: =SUM(H7:H14) -> 60849 | I15: =SUM(I7:I14) -> 64294 | J15: =SUM(J7:J14) -> 67922 | ... P15: =SUM(P7:P14) -> 83436.419 | R15: =SUM(R7:R14) -> 29058.5 | S15: =SUM(S7:S14) -> 25838.5 | T15: =SUM(T7:T14) -> 29907 | U15: =SUM(U7:U14) -> 27268 | V15: =SUM(V7:V14) -> 30587 | W15: =SUM(W7:W14) -> 29397 | X15: =SUM(X7:X14) -> 32410 | Y15: =SUM(Y7:Y14) -> 31265 | ... AK15: =SUM(AK7:AK14) -> 34098.538
B16: Growth % | D16: =D15/C15-1 -> 0.042559399 | E16: =E15/D15-1 -> 0.049129864 | F16: =F15/E15-1 -> 0.061533075 | G16: =G15/F15-1 -> 0.057196702 | H16: =H15/G15-1 -> -0.096082713 | I16: =I15/H15-1 -> 0.056615557 | J16: =J15/I15-1 -> 0.056428283 | K16: =K15/J15-1 -> 0.0170048 | ... P16: =P15/O15-1 -> 0.040666986 | T16: =T15/R15-1 -> 0.029199718 | U16: =U15/S15-1 -> 0.055324419 | V16: =V15/T15-1 -> 0.022737152 | W16: =W15/U15-1 -> 0.078076867 | X16: =X15/V15-1 -> 0.059600484 | Y16: =Y15/W15-1 -> 0.063543899 | Z16: =Z15/X15-1 -> 0.10721999 | AA16: =AA15/Y15-1 -> 0.0053414361 | ... AK16: =AK15/AI15-1 -> 0.0287066
B18: EBIT
A19: Aus Food EBIT | B19: Australian Food | C19: =C57 -> 1603.1 | D19: =D57 -> 1757 | E19: =E57 -> 1827 | F19: =F57 -> 2232 | G19: =G57 -> 2397 | H19: =H57 -> 2406 | I19: =I57 -> 2865 | J19: =J57 -> 3150 | ... P19: =P57 -> 3932.0914 | R19: =R57 -> 811.6 | S19: =S57 -> 791.5 | T19: =T57 -> 901 | U19: =U57 -> 856 | V19: =V57 -> 933 | W19: =W57 -> 894 | X19: =X57 -> 1177 | Y19: =Y57 -> 1055 | ... AK19: =AK57 -> 1461.4692
A20: Aus B2B EBIT | B20: Aus B2B | G20: =G320 -> 28 | H20: =H320 -> 56 | I20: =I320 -> 63 | J20: =J320 -> 122 | K20: =K320 -> 137 | L20: =L320 -> 147.739 | M20: =M320 -> 161.36716 | N20: =N320 -> 169.43552 | ... P20: =P320 -> 186.80266 | Z20: =Z320 -> 9 | AA20: =AA320 -> 19 | AB20: =AB320 -> 18 | AC20: =AC320 -> 38 | AD20: =AD320 -> 38 | AE20: =AE320 -> 25 | AF20: =AF320 -> 71 | AG20: =AG320 -> 51 | ... AK20: =AK320 -> 63.517725
B21: Endeavour drinks | C21: =C342 -> 503 | D21: =D342 -> 516 | E21: =E342 -> 504 | F21: =F342 -> 569 | R21: =R342 -> 302.3 | S21: =S342 -> 200.7 | T21: =T342 -> 309 | U21: =U342 -> 207 | V21: =V342 -> 294 | W21: =W342 -> 210 | X21: =X342 -> 338 | Y21: =Y342 -> 231
A22: NZ Supermarkets EBIT | B22: NZ Supermarkets | C22: =C190 -> 292 | D22: =D190 -> 262 | E22: =E190 -> 277 | F22: =F190 -> 358 | G22: =G190 -> 336 | H22: =H190 -> 296 | I22: =I190 -> 228 | J22: =J190 -> 100 | ... P22: =P190 -> 305.64044 | R22: =R190 -> 154.9 | S22: =S190 -> 137.1 | T22: =T190 -> 139 | U22: =U190 -> 123 | V22: =V190 -> 137 | W22: =W190 -> 140 | X22: =X190 -> 175 | Y22: =Y190 -> 183 | ... AD22: =AD190 -> 111 | AE22: =I22-AD22 -> 117 | AF22: =AF190 -> 65 | AG22: =AG190 -> 35 | AH22: =AH190 -> 73 | AI22: =AI190 -> 65 | AJ22: =AJ190 -> 86.168446 | AK22: =AK190 -> 71.553365
B23: Hotels | C23: =C347 -> 232.9 | D23: =D347 -> 259 | E23: =E347 -> 261 | F23: =F347 -> 172 | R23: =R347 -> 139.3 | S23: =S347 -> 93.6 | T23: =T347 -> 163 | U23: =U347 -> 96 | V23: =V347 -> 161 | W23: =W347 -> 100 | X23: =X347 -> 224 | Y23: =Y347 -> -52
A24: W Living EBIT | B24: W Living (prior to FY24 Big W) | C24: =C233 -> -150.5 | D24: =D233 -> -110 | E24: =E233 -> -85 | F24: =F233 -> 39 | G24: =G233 -> 172 | H24: =H233 -> 55 | I24: =I233 -> 145 | J24: =J201 -> -29 | K24: =K201 -> -31 | L24: =L201 -> 49.560103 | M24: =M201 -> 61.062615 | N24: =N201 -> 65.199165 | O24: =O201 -> 69.473629 | P24: =P201 -> 73.88997 | R24: =R233 -> 8.1 | S24: =S233 -> -158.6 | T24: =T233 -> -10 | U24: =U233 -> -100 | V24: =V233 -> -8 | W24: =W233 -> -77 | X24: =X233 -> 50 | Y24: =Y233 -> -11 | ... AE24: =AE233 -> 11 | AF24: =AF201 -> 15 | AG24: =AG201 -> -44 | AH24: =AH201 -> 33 | AI24: =AI201 -> -64 | AJ24: =AJ201 -> 42.74672 | AK24: =AK201 -> 6.8133826
A25: Others EBIT | B25: Others | C25: =C337 -> -154.3 | D25: =D337 -> -136 | E25: =E337 -> -62 | F25: =F337 -> -151 | G25: =G337 -> -169 | H25: =H337 -> -123 | I25: =I337 -> -185 | J25: =J337 -> -120 | ... P25: =P337 -> -270.12211 | R25: =R337 -> -79.6 | S25: =S337 -> 0 | T25: =T337 -> -72 | U25: =U337 -> -64 | V25: =V337 -> -98 | W25: =W337 -> 36 | X25: =X337 -> -71 | Y25: =Y337 -> -80 | ... AK25: =AK337 -> -120
A26: Total EBIT | B26: EBIT from Continuing Ops | C26: =SUM(C19:C25) -> 2326.2 | D26: =SUM(D19:D25) -> 2548 | E26: =SUM(E19:E25) -> 2722 | F26: =SUM(F19:F25) -> 3219 | G26: =SUM(G19:G25) -> 2764 | H26: =SUM(H19:H25) -> 2690 | I26: =SUM(I19:I25) -> 3116 | J26: =SUM(J19:J25) -> 3223 | ... P26: =SUM(P19:P25) -> 4228.3024 | R26: =SUM(R19:R25) -> 1336.6 | S26: =SUM(S19:S25) -> 1064.3 | T26: =SUM(T19:T25) -> 1430 | U26: =SUM(U19:U25) -> 1118 | V26: =SUM(V19:V25) -> 1419 | W26: =SUM(W19:W25) -> 1303 | X26: =SUM(X19:X25) -> 1893 | Y26: =SUM(Y19:Y25) -> 1326 | ... AK26: =SUM(AK19:AK25) -> 1483.3537
B27: Growth % | D27: =D26/C26-1 -> 0.095348637 | E27: =E26/D26-1 -> 0.068288854 | F27: =F26/E26-1 -> 0.18258633 | G27: =G26/F26-1 -> -0.14134824 | H27: =H26/G26-1 -> -0.026772793 | I27: =I26/H26-1 -> 0.15836431 | J27: =J26/I26-1 -> 0.034338896 | K27: =K26/J26-1 -> -0.1455166 | ... P27: =P26/O26-1 -> 0.059057127 | T27: =T26/R26-1 -> 0.069878797 | U27: =U26/S26-1 -> 0.050455699 | V27: =V26/T26-1 -> -0.0076923077 | W27: =W26/U26-1 -> 0.16547406 | X27: =X26/V26-1 -> 0.33403805 | Y27: =Y26/W26-1 -> 0.017651573 | Z27: =Z26/X26-1 -> -0.17908082 | AA27: =AA26/Y26-1 -> -0.087481146 | ... AK27: =AK26/AI26-1 -> 0.13841417
L28: =240/K30 -> 0.0046612803
B29: Australian Food | J29: =J3 -> FY24 | K29: =K3 -> FY25 | L29: =L3 -> FY26E | M29: =M3 -> FY27E | N29: =N3 -> FY28E | O29: =O3 -> FY29E | P29: =P3 -> FY30E
B30: Sales | C30: 35836 | D30: 37589 | E30: 39635 | F30: =42151 -> 42151 | G30: 43746 | H30: 45740 | I30: 48047 | J30: 50823 | K30: =13605+13069+13060+11754 -> 51488 | L30: =K30*(1+L31) -> 53350.775 | M30: =L30*(1+M31) -> 55498.191 | N30: =M30*(1+N31) -> 57722.425 | O30: =N30*(1+O31) -> 60026.057 | P30: =O30*(1+P31) -> 62411.748 | R30: 18712.6 | S30: =C30-R30 -> 17123.4 | T30: 19436 | U30: =D30-T30 -> 18153 | V30: 19928 | W30: =E30-V30 -> 19707 | X30: 21200 | Y30: =F30-X30 -> 20951 | Z30: 22988 | AA30: =G30-Z30 -> 20758 | AB30: 23780 | AC30: =H30-AB30 -> 21960 | AD30: 24385 | AE30: =I30-AD30 -> 23662 | AF30: 25945 | AG30: =J30-AF30 -> 24878 | AH30: =13605+13069 -> 26674 | AI30: =K30-AH30 -> 24814 | AJ30: =AH30*(1+AJ31) -> 27617.811 | AK30: =L30-AJ30 -> 25732.964
A31: Aus Food Growth | B31: Growth % | D31: =D30/C30-1 -> 0.04891729 | E31: =E30/D30-1 -> 0.054430818 | F31: =F30/E30-1 -> 0.063479248 | G31: =G30/F30-1 -> 0.037840146 | H31: =H30/G30-1 -> 0.04558131 | I31: =I30/H30-1 -> 0.050437254 | J31: =J30/I30-1 -> 0.05777676 | K31: =K30/J30-1 -> 0.013084627 | L31: =SUM(L33:L35) -> 0.036178827 | M31: =SUM(M33:M35) -> 0.040250883 | N31: =SUM(N33:N35) -> 0.040077594 | O31: =SUM(O33:O35) -> 0.039908778 | P31: =SUM(P33:P35) -> 0.039744265 | T31: =T30/R30-1 -> 0.038658444 | U31: =U30/S30-1 -> 0.060128246 | V31: =V30/T30-1 -> 0.025313851 | W31: =W30/U30-1 -> 0.085605685 | X31: =X30/V30-1 -> 0.063829787 | Y31: =Y30/W30-1 -> 0.063124778 | Z31: =Z30/X30-1 -> 0.084339623 | AA31: =AA30/Y30-1 -> -0.0092119708 | ... AI31: =AI30/AG30-1 -> -0.0025725541 | AJ31: =SUM(AJ33:AJ35) -> 0.035383199 | AK31: =AK30/AI30-1 -> 0.037034094
A32: Aus Food Growth ex Tobacco | B32: Growth ex Tobacco % | H32: 0.06 | I32: 0.063 | J32: 0.047 | K32: 0.044
A33: Aus Food Comp | B33: LFL Sales Growth % | C33: 0.036 | D33: 0.043 | E33: 0.031 | F33: 0.073 | G33: 0.042 | H33: 0.035 | I33: 0.042 | J33: 0.028 | K33: 0.024 | L33: =VLOOKUP($A33,Quarterly!$1:$1048576,MATCH(Model!L$3,Quarterly!$3:$3,0),FALSE) -> 0.02975 | M33: 0.035 | N33: 0.035 | O33: 0.035 | P33: 0.035 | R33: 0.019 | T33: 0.049 | U33: =VLOOKUP($A33,Quarterly!$1:$1048576,MATCH(Model!U$3,Quarterly!$3:$3,0),FALSE) -> 0.0355 | V33: 0.023 | W33: =VLOOKUP($A33,Quarterly!$1:$1048576,MATCH(Model!W$3,Quarterly!$3:$3,0),FALSE) -> 0.039 | X33: 0.051 | Y33: =VLOOKUP($A33,Quarterly!$1:$1048576,MATCH(Model!Y$3,Quarterly!$3:$3,0),FALSE) -> 0.096 | Z33: 0.095 | AA33: =VLOOKUP($A33,Quarterly!$1:$1048576,MATCH(Model!AA$3,Quarterly!$3:$3,0),FALSE) -> -0.01 | AB33: 0.023 | AC33: =VLOOKUP($A33,Quarterly!$1:$1048576,MATCH(Model!AC$3,Quarterly!$3:$3,0),FALSE) -> 0.048 | AD33: 0.018 | AE33: =VLOOKUP($A33,Quarterly!$1:$1048576,MATCH(Model!AE$3,Quarterly!$3:$3,0),FALSE) -> 0.066 | AF33: 0.046 | AG33: =VLOOKUP($A33,Quarterly!$1:$1048576,MATCH(Model!AG$3,Quarterly!$3:$3,0),FALSE) -> 0.012 | AH33: 0.017120428 | AI33: =VLOOKUP($A33,Quarterly!$1:$1048576,MATCH(Model!AI$3,Quarterly!$3:$3,0),FALSE) -> 0.0295 | AJ33: =VLOOKUP($A33,Quarterly!$1:$1048576,MATCH(Model!AJ$3,Quarterly!$3:$3,0),FALSE) -> 0.0295 | AK33: =VLOOKUP($A33,Quarterly!$1:$1048576,MATCH(Model!AK$3,Quarterly!$3:$3,0),FALSE) -> 0.03
B34: Store Growth % | D34: =D76/C76-1 -> 0.01002004 | E34: =E76/D76-1 -> 0.015873016 | F34: =F76/E76-1 -> 0.026367188 | G34: =G76/F76-1 -> 0.02188392 | H34: =H76/G76-1 -> 0.010242086 | I34: =I76/H76-1 -> 0.0092165899 | J34: =J76/I76-1 -> 0.014611872 | K34: =K76/J76-1 -> 0.0054005401 | ... P34: =P76/O76-1 -> 0.012744265 | T34: =T76/R76-1 -> 0.012048193 | U34: =U76/S76-1 -> 0.010050251 | V34: =V76/T76-1 -> 0.0099206349 | W34: =W76/U76-1 -> 0.018905473 | X34: =X76/V76-1 -> 0.020628684 | Y34: =Y76/W76-1 -> 0.02734375 | Z34: =Z76/X76-1 -> 0.024061598 | AA34: =AA76/Y76-1 -> 0.019961977 | ... AK34: =AK76/AI76-1 -> 0.013428827
B35: Other | D35: =D31-SUM(D33:D34) -> -0.0041027502 | E35: =E31-SUM(E33:E34) -> 0.0075578017 | F35: =F31-SUM(F33:F34) -> -0.035887939 | G35: =G31-SUM(G33:G34) -> -0.026043774 | H35: =H31-SUM(H33:H34) -> 0.00033922463 | I35: =I31-SUM(I33:I34) -> -0.00077933582 | J35: =J31-SUM(J33:J34) -> 0.015164888 | K35: =K31-SUM(K33:K34) -> -0.016315913 | L35: -0.007 | M35: -0.008 | N35: -0.008 | O35: -0.008 | P35: -0.008 | T35: =T31-SUM(T33:T34) -> -0.022389749 | U35: =U31-SUM(U33:U34) -> 0.014577994 | V35: =V31-SUM(V33:V34) -> -0.0076067843 | W35: =W31-SUM(W33:W34) -> 0.027700212 | X35: =X31-SUM(X33:X34) -> -0.0077988965 | Y35: =Y31-SUM(Y33:Y34) -> -0.060218972 | Z35: =Z31-SUM(Z33:Z34) -> -0.034721975 | AA35: =AA31-SUM(AA33:AA34) -> -0.019173948 | ... AI35: =AI31-SUM(AI33:AI34) -> -0.037473094 | AJ35: -0.004 | AK35: =AK31-SUM(AK33:AK34) -> -0.0063947329
A37: Aus Food GP | B37: Gross Profit | C37: =C39*C30 -> 10059.165 | D37: =D39*D30 -> 10938.399 | E37: =E39*E30 -> 11375.245 | F37: =F39*F30 -> 12308.092 | G37: =G39*G30 -> 11723.928 | H37: =H39*H30 -> 12532.76 | I37: =I39*I30 -> 13501.207 | J37: =J39*J30 -> 14687.847 | ... P37: =P39*P30 -> 17912.172 | R37: =R39*R30 -> 5217.0729 | S37: =C37-R37 -> 4842.0923 | T37: =T39*T30 -> 5597.568 | U37: =D37-T37 -> 5340.831 | V37: =V39*V30 -> 5719.336 | W37: =E37-V37 -> 5655.909 | X37: =X39*X30 -> 6169.2 | Y37: =F37-X37 -> 6138.892 | Z37: =Z39*Z30 -> 6114.808 | AA37: =G37-Z37 -> 5609.12 | AB37: =AB39*AB30 -> 6468.16 | AC37: =H37-AB37 -> 6064.6 | AD37: =AD39*AD30 -> 6803.415 | AE37: =I37-AD37 -> 6697.792 | AF37: =AF39*AF30 -> 7498.105 | AG37: =J37-AF37 -> 7189.742 | AH37: =AH39*AH30 -> 7628.764 | AI37: =K37-AH37 -> 7096.804 | AJ37: =AJ39*AJ30 -> 7898.6941 | AK37: =L37-AJ37 -> 7359.6277
B38: Growth % | D38: =D37/C37-1 -> 0.087406239 | E38: =E37/D37-1 -> 0.039936923 | F38: =F37/E37-1 -> 0.082006761 | G38: =G37/F37-1 -> -0.047461784 | H38: =H37/G37-1 -> 0.068989847 | I38: =I37/H37-1 -> 0.077273242 | J38: =J37/I37-1 -> 0.087891401 | K38: =K37/J37-1 -> 0.0025681776 | ... P38: =P37/O37-1 -> 0.039744265 | T38: =T37/R37-1 -> 0.072932683 | U38: =U37/S37-1 -> 0.10300065 | V38: =V37/T37-1 -> 0.021753733 | W38: =W37/U37-1 -> 0.05899419 | X38: =X37/V37-1 -> 0.078656683 | Y38: =Y37/W37-1 -> 0.085394408 | Z38: =Z37/X37-1 -> -0.0088167023 | AA38: =AA37/Y37-1 -> -0.086297658 | ... AI38: =AI37/AG37-1 -> -0.012926472 | AJ38: =AJ37/AI37-1 -> 0.11299313 | AK38: =AK37/AI37-1 -> 0.037034094
A39: Aus Food GPM | B39: Gross Margin | C39: 0.2807 | D39: 0.291 | E39: 0.287 | F39: 0.292 | G39: 0.268 | H39: 0.274 | I39: 0.281 | J39: 0.289 | K39: 0.286 | L39: =K39+L40 -> 0.286 | M39: =L39+M40 -> 0.286 | N39: =M39+N40 -> 0.287 | O39: =N39+O40 -> 0.287 | P39: =O39+P40 -> 0.287 | R39: 0.2788 | S39: =S37/S30 -> 0.28277634 | T39: 0.288 | U39: =U37/U30 -> 0.29421203 | V39: 0.287 | W39: =W37/W30 -> 0.287 | X39: 0.291 | Y39: =Y37/Y30 -> 0.29301188 | Z39: 0.266 | AA39: =AA37/AA30 -> 0.27021486 | AB39: 0.272 | AC39: =AC37/AC30 -> 0.27616576 | AD39: 0.279 | AE39: =AE37/AE30 -> 0.28306111 | AF39: 0.289 | AG39: =AG37/AG30 -> 0.289 | AH39: 0.286 | AI39: =AI37/AI30 -> 0.286 | AJ39: =AH39+AJ40 -> 0.286 | AK39: =AK37/AK30 -> 0.286
B40: Change YoY % | C40: 0.007 | D40: 0.0063 | E40: -0.0024 | F40: 0.0047 | G40: 0.0021 | H40: 0.0074 | I40: 0.0076 | J40: 0.0076 | K40: -0.0025 | L40: 0 | M40: 0 | N40: 0.001 | O40: 0 | P40: 0 | R40: =50&" bp" -> 50 bp | T40: 0.0055 | U40: =U39-S39 -> 0.011435695 | V40: 0.0002 | W40: =W39-U39 -> -0.0072120311 | X40: 0.0038 | Y40: =Y39-W39 -> 0.0060118849 | Z40: 0.0011 | AA40: =AA39-Y39 -> -0.022797028 | AB40: 0.0079 | AC40: =AC39-AA39 -> 0.005950899 | AD40: 0.0048 | AE40: =AE39-AC39 -> 0.0068953547 | AF40: 0.0096 | AG40: =AG39-AE39 -> 0.0059388894 | AH40: -0.0032 | AI40: =AI39-AG39 -> -0.003 | AJ40: 0 | AK40: =AK39-AI39 -> 0
L41: =100/L30 -> 0.001874387
B42: CODB | G42: =G47-G37 -> -7783.928 | H42: =H47-H37 -> -8488.76 | I42: =I47-I37 -> -8850.207 | J42: =J47-J37 -> -9642.847 | K42: =K47-K37 -> -9959.568 | L42: =K42*(1+L43) -> -10208.557 | M42: =L42*(1+M43) -> -10412.728 | N42: =M42*(1+N43) -> -10652.221 | O42: =N42*(1+O43) -> -11025.049 | P42: =O42*(1+P43) -> -11410.926 | R42: =R47-R37 -> -4169.0729 | S42: =S47-S37 -> -3668.9923 | T42: =T47-T37 -> -4355.568 | U42: =U47-U37 -> -4152.831 | V42: =V47-V37 -> -4406.336 | W42: =W47-W37 -> -4385.909 | X42: =X47-X37 -> -4240.2 | Y42: =Y47-Y37 -> -4360.892 | ... AI42: =AI47-AI37 -> -4747.804 | AJ42: =AH42*(1+AJ43) -> -5346.7487 | AK42: =L42-AJ42 -> -4861.8085
B43: Growth % | H43: =H42/G42-1 -> 0.090549656 | I43: =I42/H42-1 -> 0.042579482 | J43: =J42/I42-1 -> 0.089561747 | K43: =K42/J42-1 -> 0.032845175 | L43: 0.025 | M43: 0.02 | N43: 0.023 | O43: 0.035 | P43: 0.035 | T43: =T42/R42-1 -> 0.044732996 | U43: =U42/S42-1 -> 0.13187236 | V43: =V42/T42-1 -> 0.011655885 | W43: =W42/U42-1 -> 0.056125087 | X43: =X42/V42-1 -> -0.037703888 | Y43: =Y42/W42-1 -> -0.0057039487 | Z43: =Z42/X42-1 -> -0.050561766 | AA43: =AA42/Y42-1 -> -0.13822218 | ... AI43: =AI42/AG42-1 -> 0.010011611 | AJ43: 0.0259 | AK43: =AK42/AI42-1 -> 0.024012051
B44: % of Sales | G44: =G42/G30 -> -0.17793462 | H44: =H42/H30 -> -0.18558723 | I44: =I42/I30 -> -0.18419895 | J44: =J42/J30 -> -0.18973392 | K44: =K42/K30 -> -0.19343474 | L44: =L42/L30 -> -0.19134787 | M44: =M42/M30 -> -0.18762284 | N44: =N42/N30 -> -0.18454216 | ... P44: =P42/P30 -> -0.18283297 | R44: =R42/R30 -> -0.22279496 | S44: =S42/S30 -> -0.21426775 | T44: =T42/T30 -> -0.22409796 | U44: =U42/U30 -> -0.2287683 | V44: =V42/V30 -> -0.22111281 | W44: =W42/W30 -> -0.22255589 | X44: =X42/X30 -> -0.20000943 | Y44: =Y42/Y30 -> -0.2081472 | ... AK44: =AK42/AK30 -> -0.18893309
B45: Change YoY % | H45: =H44-G44 -> -0.0076526096 | I45: =I44-H44 -> 0.0013882812 | J45: =J44-I44 -> -0.0055349687 | K45: =K44-J44 -> -0.0037008224 | L45: =L44-K44 -> 0.0020868729 | M45: =M44-L44 -> 0.0037250277 | N45: =N44-M44 -> 0.0030806804 | O45: =O44-N44 -> 0.0008711115 | P45: =P44-O44 -> 0.00083807545 | T45: =T44-S44 -> -0.0098302167 | U45: =U44-T44 -> -0.0046703402 | V45: =V44-U44 -> 0.0076554967 | W45: =W44-V44 -> -0.0014430877 | X45: =X44-W44 -> 0.02254646 | Y45: =Y44-X44 -> -0.0081377666 | Z45: =Z44-Y44 -> 0.0330207 | AA45: =AA44-Z44 -> -0.0059179158 | ... AK45: =AK44-AJ44 -> 0.0046647476
B47: EBITDA | C47: 2221.1 | D47: 2430 | E47: 2583 | F47: 3707 | G47: 3940 | H47: 4044 | I47: 4651 | J47: 5045 | K47: 4766 | L47: =L37+L42 -> 5049.7646 | M47: =M37+M42 -> 5459.7544 | N47: =N37+N42 -> 5914.115 | O47: =O37+O42 -> 6202.4294 | P47: =P37+P42 -> 6501.2462 | R47: 1048 | S47: =C47-R47 -> 1173.1 | T47: 1242 | U47: =D47-T47 -> 1188 | V47: 1313 | W47: 1270 | X47: 1929 | Y47: =F47-X47 -> 1778 | Z47: 2089 | AA47: =G47-Z47 -> 1851 | AB47: 2047 | AC47: =H47-AB47 -> 1997 | AD47: 2317 | AE47: =I47-AD47 -> 2334 | AF47: 2556 | AG47: =J47-AF47 -> 2489 | AH47: 2417 | AI47: =K47-AH47 -> 2349 | AJ47: =AJ37+AJ42 -> 2551.9454 | AK47: =L47-AJ47 -> 2497.8192
B48: Growth % | D48: =D47/C47-1 -> 0.094052497 | E48: =E47/D47-1 -> 0.062962963 | F48: =F47/E47-1 -> 0.43515292 | G48: =G47/F47-1 -> 0.06285406 | H48: =H47/G47-1 -> 0.026395939 | I48: =I47/H47-1 -> 0.15009891 | J48: =J47/I47-1 -> 0.084712965 | K48: =K47/J47-1 -> -0.055302279 | ... P48: =P47/O47-1 -> 0.048177373 | T48: =T47/R47-1 -> 0.1851145 | U48: =U47/S47-1 -> 0.012701389 | V48: =V47/T47-1 -> 0.057165862 | W48: =W47/U47-1 -> 0.069023569 | X48: =X47/V47-1 -> 0.46915461 | Y48: =Y47/W47-1 -> 0.4 | Z48: =Z47/X47-1 -> 0.082944531 | AA48: =AA47/Y47-1 -> 0.041057368 | ... AK48: =AK47/AI47-1 -> 0.063354277
B49: EBITDA Margin | C49: =C47/C30 -> 0.061979574 | D49: =D47/D30 -> 0.064646572 | E49: =E47/E30 -> 0.065169673 | F49: =F47/F30 -> 0.087945719 | G49: =G47/G30 -> 0.090065377 | H49: =H47/H30 -> 0.088412768 | I49: =I47/I30 -> 0.096801049 | J49: =J47/J30 -> 0.09926608 | ... P49: =P47/P30 -> 0.10416703 | R49: =R47/R30 -> 0.056005045 | S49: =S47/S30 -> 0.068508591 | T49: =T47/T30 -> 0.063902037 | U49: =U47/U30 -> 0.065443728 | V49: =V47/V30 -> 0.065887194 | W49: =W47/W30 -> 0.064444106 | X49: =X47/X30 -> 0.090990566 | Y49: =Y47/Y30 -> 0.084864684 | ... AK49: =AK47/AK30 -> 0.097066906
B50: Change YoY % | D50: =D49-C49 -> 0.0026669985 | E50: =E49-D49 -> 0.00052310113 | F50: =F49-E49 -> 0.022776046 | G50: =G49-F49 -> 0.0021196584 | H50: =H49-G49 -> -0.0016526096 | I50: =I49-H49 -> 0.0083882812 | J50: =J49-I49 -> 0.0024650313 | K50: =K49-J49 -> -0.0067008224 | ... P50: =P49-O49 -> 0.00083807545 | T50: =T49-R49 -> 0.0078969927 | U50: =U49-S49 -> -0.0030648623 | V50: =V49-T49 -> 0.0019851564 | W50: =W49-U49 -> -0.00099962215 | X50: =X49-V49 -> 0.025103372 | Y50: =Y49-W49 -> 0.020420578 | Z50: =Z49-X49 -> -0.00011706682 | AA50: =AA49-Y49 -> 0.004305756 | ... AK50: =AK49-AI49 -> 0.0024026035
B52: D&A | C52: =C57-C47 -> -618 | D52: =D57-D47 -> -673 | E52: =E57-E47 -> -756 | F52: =F57-F47 -> -1475 | G52: =G57-G47 -> -1543 | H52: =H57-H47 -> -1638 | I52: -1786 | J52: -1896 | K52: -2013 | L52: =K52*(1+L53) -> -2113.65 | M52: =L52*(1+M53) -> -2219.3325 | N52: =M52*(1+N53) -> -2330.2991 | O52: =N52*(1+O53) -> -2446.8141 | P52: =O52*(1+P53) -> -2569.1548 | R52: =R57-R47 -> -236.4 | S52: =S57-S47 -> -381.6 | T52: =T57-T47 -> -341 | U52: =U57-U47 -> -332 | V52: =V57-V47 -> -380 | W52: =W57-W47 -> -376 | X52: =X57-X47 -> -752 | Y52: =Y57-Y47 -> -723 | Z52: =Z57-Z47 -> -772 | AA52: =G52-Z52 -> -771 | AB52: =AB57-AB47 -> -830 | AC52: =H52-AB52 -> -808 | AD52: =AD57-AD47 -> -878 | AE52: =I52-AD52 -> -908 | AF52: -961 | AG52: =J52-AF52 -> -935 | AH52: -1026 | AI52: =K52-AH52 -> -987 | AJ52: =AH52*(1+AJ53) -> -1077.3 | AK52: =L52-AJ52 -> -1036.35
B53: Growth % | D53: =D52/C52-1 -> 0.088996764 | E53: =E52/D52-1 -> 0.12332838 | F53: =F52/E52-1 -> 0.9510582 | G53: =G52/F52-1 -> 0.046101695 | H53: =H52/G52-1 -> 0.061568373 | I53: =I52/H52-1 -> 0.09035409 | J53: =J52/I52-1 -> 0.061590146 | K53: =K52/J52-1 -> 0.061708861 | L53: 0.05 | M53: 0.05 | N53: 0.05 | O53: 0.05 | P53: 0.05 | T53: =T52/R52-1 -> 0.44247039 | U53: =U52/S52-1 -> -0.12997904 | V53: =V52/T52-1 -> 0.1143695 | W53: =W52/U52-1 -> 0.13253012 | X53: =X52/V52-1 -> 0.97894737 | Y53: =Y52/W52-1 -> 0.92287234 | Z53: =Z52/X52-1 -> 0.026595745 | AA53: =AA52/Y52-1 -> 0.066390041 | ... AI53: =AI52/AG52-1 -> 0.055614973 | AJ53: 0.05 | AK53: =AK52/AI52-1 -> 0.05
B54: % of Sales | C54: =C52/C30 -> -0.017245228 | D54: =D52/D30 -> -0.017904174 | E54: =E52/E30 -> -0.019074051 | F54: =F52/F30 -> -0.034993239 | G54: =G52/G30 -> -0.035271796 | H54: =H52/H30 -> -0.035811106 | I54: =I52/I30 -> -0.037171936 | J54: =J52/J30 -> -0.037305944 | ... P54: =P52/P30 -> -0.041164602 | R54: =R52/R30 -> -0.012633199 | S54: =S52/S30 -> -0.022285294 | T54: =T52/T30 -> -0.017544762 | U54: =U52/U30 -> -0.018288988 | V54: =V52/V30 -> -0.019068647 | W54: =W52/W30 -> -0.019079515 | X54: =X52/X30 -> -0.035471698 | Y54: =Y52/Y30 -> -0.034509093 | ... AK54: =AK52/AK30 -> -0.040273246
B55: Change YoY % | D55: =D54-C54 -> -0.00065894583 | E55: =E54-D54 -> -0.0011698766 | F55: =F54-E54 -> -0.015919188 | G55: =G54-F54 -> -0.00027855768 | H55: =H54-G54 -> -0.00053930997 | I55: =I54-H54 -> -0.0013608296 | J55: =J54-I54 -> -0.00013400835 | K55: =K54-J54 -> -0.0017905443 | ... P55: =P54-O54 -> -0.00040206976 | T55: =T54-R54 -> -0.0049115633 | U55: =U54-S54 -> 0.0039963058 | V55: =V54-T54 -> -0.0015238848 | W55: =W54-U54 -> -0.00079052685 | X55: =X54-V54 -> -0.016403051 | Y55: =Y54-W54 -> -0.015429578 | Z55: =Z54-X54 -> 0.0018889593 | AA55: =AA54-Y54 -> -0.0026332139 | ... AK55: =AK54-AI54 -> -0.00049731344
B57: EBIT | C57: 1603.1 | D57: 1757 | E57: 1827 | F57: 2232 | G57: 2397 | H57: 2406 | I57: 2865 | J57: 3150 | K57: 2721 | L57: =L47+L52 -> 2936.1146 | M57: =M47+M52 -> 3240.4219 | N57: =N47+N52 -> 3583.8158 | O57: =O47+O52 -> 3755.6154 | P57: =P47+P52 -> 3932.0914 | R57: 811.6 | S57: =C57-R57 -> 791.5 | T57: 901 | U57: =D57-T57 -> 856 | V57: 933 | W57: =E57-V57 -> 894 | X57: 1177 | Y57: =F57-X57 -> 1055 | Z57: 1317 | AA57: =G57-Z57 -> 1080 | AB57: 1217 | AC57: =H57-AB57 -> 1189 | AD57: 1439 | AE57: =I57-AD57 -> 1426 | AF57: 1595 | AG57: =J57-AF57 -> 1555 | AH57: 1373 | AI57: =K57-AH57 -> 1348 | AJ57: =AJ47+AJ52 -> 1474.6454 | AK57: =L57-AJ57 -> 1461.4692
B58: Growth % | D58: =D57/C57-1 -> 0.096001497 | E58: =E57/D57-1 -> 0.039840637 | F58: =F57/E57-1 -> 0.22167488 | G58: =G57/F57-1 -> 0.073924731 | H58: =H57/G57-1 -> 0.0037546934 | I58: =I57/H57-1 -> 0.19077307 | J58: =J57/I57-1 -> 0.09947644 | K58: =K57/J57-1 -> -0.13619048 | ... P58: =P57/O57-1 -> 0.046989916 | T58: =T57/R57-1 -> 0.11015278 | U58: =U57/S57-1 -> 0.08149084 | V58: =V57/T57-1 -> 0.035516093 | W58: =W57/U57-1 -> 0.044392523 | X58: =X57/V57-1 -> 0.26152197 | Y58: =Y57/W57-1 -> 0.18008949 | Z58: =Z57/X57-1 -> 0.11894647 | AA58: =AA57/Y57-1 -> 0.023696682 | ... AK58: =AK57/AI57-1 -> 0.084175962
A59: Aus Food EBIT Margin | B59: EBIT Margin | C59: =C57/C30 -> 0.044734345 | D59: =D57/D30 -> 0.046742398 | E59: =E57/E30 -> 0.046095623 | F59: =F57/F30 -> 0.05295248 | G59: =G57/G30 -> 0.054793581 | H59: =H57/H30 -> 0.052601662 | I59: =I57/I30 -> 0.059629113 | J59: =J57/J30 -> 0.061979812 | ... P59: =P57/P30 -> 0.063002424 | R59: =R57/R30 -> 0.043371846 | S59: =S57/S30 -> 0.046223297 | T59: =T57/T30 -> 0.046357275 | U59: =U57/U30 -> 0.04715474 | V59: =V57/V30 -> 0.046818547 | W59: =W57/W30 -> 0.045364591 | X59: =X57/X30 -> 0.055518868 | Y59: =Y57/Y30 -> 0.050355592 | ... AK59: =AK57/AK30 -> 0.05679366
B60: Change YoY % | D60: =D59-C59 -> 0.0020080527 | E60: =E59-D59 -> -0.00064677549 | F60: =F59-E59 -> 0.0068568578 | G60: =G59-F59 -> 0.0018411008 | H60: =H59-G59 -> -0.0021919196 | I60: =I59-H59 -> 0.0070274516 | J60: =J59-I59 -> 0.0023506991 | K60: =K59-J59 -> -0.0091325469 | ... P60: =P59-O59 -> 0.00043600569 | T60: =T59-R59 -> 0.0029854295 | U60: =U59-S59 -> 0.00093144349 | V60: =V59-T59 -> 0.00046127161 | W60: =W59-U59 -> -0.001790149 | X60: =X59-V59 -> 0.0087003212 | Y60: =Y59-W59 -> 0.0049910004 | Z60: =Z59-X59 -> 0.0017718925 | AA60: =AA59-Y59 -> 0.0016725421 | ... AK60: =AK59-AI59 -> 0.0024694877
B62: AASB16 adjustment | C62: =C65-C57 -> 0 | D62: =D65-D57 -> 0 | E62: =E65-E57 -> 0 | F62: =F65-F57 -> -311 | G62: =F62*(1+G34+3%) -> -327.1359 | H62: =G62*(1+H34+3%) -> -340.30053 | I62: =H62*(1+I34+3%) -> -353.64596 | J62: =I62*(1+J34+3%) -> -369.42276 | K62: =J62*(1+K34+3%) -> -382.50053 | L62: =K62*(1+L34+3%) -> -399.11208 | M62: =L62*(1+M34+3%) -> -416.37403 | N62: =M62*(1+N34+3%) -> -434.31042 | ... P62: =O62*(1+P34+3%) -> -472.307 | R62: =R65-R57 -> 0 | S62: =S65-S57 -> 0 | T62: =T65-T57 -> 0 | U62: =U65-U57 -> 0 | V62: =V65-V57 -> 0 | W62: =W65-W57 -> 0 | X62: =X65-X57 -> -159 | Y62: =Y65-Y57 -> -152 | Z62: =X62*(1+Z81+3%) -> -167.4444 | AA62: =G62-Z62 -> -159.6915 | AB62: =Z62*(1+AB81+3%) -> -175.12414 | AC62: =H62-AB62 -> -165.17639 | AD62: =AB62*(1+AD81+3%) -> -183.3493 | AE62: =I62-AD62 -> -170.29666 | AF62: =AD62*(1+AF81+3%) -> -190.52291 | AG62: =J62-AF62 -> -178.89986 | AH62: =AF62*(1+AH81+3%) -> -197.83152 | AI62: =K62-AH62 -> -184.66901 | AJ62: =AH62*(1+AJ81+3%) -> -203.76647 | AK62: =L62-AJ62 -> -195.34561
B63: margin impact | F63: =-F62/F30 -> 0.0073782354 | G63: =F63 -> 0.0073782354 | H63: =-H62/H30 -> 0.0074398892 | I63: =-I62/I30 -> 0.007360417 | J63: =-J62/J30 -> 0.0072688107 | K63: =-K62/K30 -> 0.0074289258 | L63: =-L62/L30 -> 0.0074809049 | M63: =-M62/M30 -> 0.0075024793 | N63: =-N62/N30 -> 0.0075241194 | O63: =-O62/O30 -> 0.0075458255 | P63: =-P62/P30 -> 0.0075675977 | X63: =-X62/X30 -> 0.0075 | Y63: =-Y62/Y30 -> 0.0072550236 | Z63: =-Z62/Z30 -> 0.0072839918 | AA63: =-AA62/AA30 -> 0.0076930097 | AB63: =-AB62/AB30 -> 0.0073643458 | AC63: =-AC62/AC30 -> 0.0075216934 | AD63: =-AD62/AD30 -> 0.0075189377 | AE63: =-AE62/AE30 -> 0.0071970527 | ... AK63: =-AK62/AK30 -> 0.0075912595
B65: EBIT pre AASB16 | C65: =C57 -> 1603.1 | D65: =D57 -> 1757 | E65: =E57 -> 1827 | F65: 1921 | G65: =G62+G57 -> 2069.8641 | H65: =H62+H57 -> 2065.6995 | I65: =I62+I57 -> 2511.354 | J65: =J62+J57 -> 2780.5772 | K65: =K62+K57 -> 2338.4995 | L65: =L62+L57 -> 2537.0025 | M65: =M62+M57 -> 2824.0478 | N65: =N62+N57 -> 3149.5054 | ... P65: =P62+P57 -> 3459.7844 | R65: =R57 -> 811.6 | S65: =S57 -> 791.5 | T65: =T57 -> 901 | U65: =U57 -> 856 | V65: =V57 -> 933 | W65: =W57 -> 894 | X65: 1018 | Y65: =F65-X65 -> 903 | Z65: =Z62+Z57 -> 1149.5556 | AA65: =AA62+AA57 -> 920.3085 | AB65: =AB62+AB57 -> 1041.8759 | AC65: =AC62+AC57 -> 1023.8236 | AD65: =AD62+AD57 -> 1255.6507 | AE65: =AE62+AE57 -> 1255.7033 | AF65: =AF62+AF57 -> 1404.4771 | AG65: =AG62+AG57 -> 1376.1001 | ... AK65: =AK62+AK57 -> 1266.1236
B66: Growth % | D66: =D65/C65-1 -> 0.096001497 | E66: =E65/D65-1 -> 0.039840637 | F66: =F65/E65-1 -> 0.051450465 | G66: =G65/F65-1 -> 0.077493025 | H66: =H65/G65-1 -> -0.0020120311 | I66: =I65/H65-1 -> 0.21574028 | J66: =J65/I65-1 -> 0.1072024 | K66: =K65/J65-1 -> -0.15898777 | ... P66: =P65/O65-1 -> 0.047572188 | T66: =T65/R65-1 -> 0.11015278 | U66: =U65/S65-1 -> 0.08149084 | V66: =V65/T65-1 -> 0.035516093 | W66: =W65/U65-1 -> 0.044392523 | X66: =X65/V65-1 -> 0.091103966 | Y66: =Y65/W65-1 -> 0.010067114 | Z66: =Z65/X65-1 -> 0.12922947 | AA66: =AA65/Y65-1 -> 0.019167779 | ... AK66: =AK65/AI65-1 -> 0.088360573
A67: Aus Food EBIT Margin AASB16 | B67: EBIT pre AASB16 Margin | C67: =C65/C30 -> 0.044734345 | D67: =D65/D30 -> 0.046742398 | E67: =E65/E30 -> 0.046095623 | F67: =F65/F30 -> 0.045574245 | G67: =G65/G30 -> 0.047315505 | H67: =H65/H30 -> 0.045161772 | I67: =I65/I30 -> 0.052268696 | J67: =J65/J30 -> 0.054711002 | ... P67: =P65/P30 -> 0.055434826 | R67: =R65/R30 -> 0.043371846 | S67: =S65/S30 -> 0.046223297 | T67: =T65/T30 -> 0.046357275 | U67: =U65/U30 -> 0.04715474 | V67: =V65/V30 -> 0.046818547 | W67: =W65/W30 -> 0.045364591 | X67: =X65/X30 -> 0.048018868 | Y67: =Y65/Y30 -> 0.043100568 | ... AK67: =AK65/AK30 -> 0.0492024
B68: Change YoY % | D68: =D67-C67 -> 0.0020080527 | E68: =E67-D67 -> -0.00064677549 | F68: =F67-E67 -> -0.00052137758 | G68: =G67-F67 -> 0.0017412605 | H68: =H67-G67 -> -0.002153733 | I68: =I67-H67 -> 0.0071069237 | J68: =J67-I67 -> 0.0024423055 | K68: =K67-J67 -> -0.009292662 | ... P68: =P67-O67 -> 0.00041423354 | T68: =T67-R67 -> 0.0029854295 | U68: =U67-S67 -> 0.00093144349 | V68: =V67-T67 -> 0.00046127161 | W68: =W67-U67 -> -0.001790149 | X68: =X67-V67 -> 0.0012003212 | Y68: =Y67-W67 -> -0.0022640233 | Z68: =Z67-X67 -> 0.0019879007 | AA68: =AA67-Y67 -> 0.001234556 | ... AK68: =AK67-AI67 -> 0.0023203578
B70: Funds employed | F70: 9161 | G70: 9401 | H70: 10082 | I70: 9647 | J70: 9883 | K70: 10223 | Z70: 9069 | AB70: 9458 | AD70: 9871 | AF70: 9460 | AH70: 10255
B71: ROFE % | F71: 0.25 | G71: 0.264 | H71: 0.251 | I71: 0.29 | J71: 0.322 | K71: 0.272 | Z71: 0.265 | AB71: 0.248 | AD71: 0.269 | AF71: 0.318 | AH71: 0.291
B73: Store Numbers and Trading Area
B74: Net New Stores
B75: Australian Supermarkets | C75: 3 | D75: 10 | E75: 16 | F75: 27 | G75: 23 | H75: 11 | I75: 10 | J75: 16 | K75: 6 | L75: 15 | M75: 15 | N75: 15 | O75: 15 | P75: 15 | R75: 4 | S75: =C75-R75 -> -1 | T75: 13 | U75: =D75-T75 -> -3 | V75: 10 | W75: =E75-V75 -> 6 | X75: 14 | Y75: =F75-X75 -> 13 | Z75: 14 | AA75: =G75-Z75 -> 9 | AB75: 9 | AC75: =H75-AB75 -> 2 | AD75: 8 | AE75: =I75-AD75 -> 2 | AF75: 9 | AG75: =J75-AF75 -> 7 | AH75: 2 | AI75: =K75-AH75 -> 4 | AJ75: 7 | AK75: =L75-AJ75 -> 8
B76: Ending Stores | C76: 998 | D76: 1008 | E76: 1024 | F76: 1051 | G76: 1074 | H76: 1085 | I76: 1095 | J76: 1111 | K76: 1117 | L76: =L75+K76 -> 1132 | M76: =M75+L76 -> 1147 | N76: =N75+M76 -> 1162 | O76: =O75+N76 -> 1177 | P76: =P75+O76 -> 1192 | R76: 996 | S76: =R76+S75 -> 995 | T76: 1008 | U76: =T76+U75 -> 1005 | V76: 1018 | W76: =V76+W75 -> 1024 | X76: 1039 | Y76: =X76+Y75 -> 1052 | Z76: 1064 | AA76: =Z76+AA75 -> 1073 | AB76: 1083 | AC76: =AB76+AC75 -> 1085 | AD76: 1093 | AE76: =AD76+AE75 -> 1095 | AF76: 1104 | AG76: =AF76+AG75 -> 1111 | AH76: 1113 | AI76: =AH76+AI75 -> 1117 | AJ76: =AI76+AJ75 -> 1124 | AK76: =AJ76+AK75 -> 1132
B77: o/w Metro | G77: 78 | H77: 90 | I77: 93 | J77: 105 | K77: 105 | Z77: 70 | AA77: 78 | AB77: 82 | AC77: 90 | AD77: 90 | AE77: 93 | AF77: 103 | AG77: 105 | AH77: 106
B80: Trading Area | C80: 2252.709 | D80: 2281.866 | E80: =2330.718 -> 2330.718 | F80: 2382.764 | G80: 2435.065 | H80: 2460.633 | I80: 2491.102 | J80: 2531.657 | K80: 2549.069 | R80: 2250.028 | S80: =AVERAGE(R80,C80) -> 2251.3685 | T80: 2283.289 | U80: =AVERAGE(T80,D80) -> 2282.5775 | V80: 2308.944 | W80: =AVERAGE(V80,E80) -> 2319.831 | X80: 2357.52 | Y80: =AVERAGE(X80,F80) -> 2370.142 | Z80: 2412.001 | AA80: =AVERAGE(Z80,G80) -> 2423.533 | AB80: 2450.266 | AC80: =AVERAGE(AB80,H80) -> 2455.4495 | AD80: 2491.841 | AE80: =AVERAGE(AD80,I80) -> 2491.4715 | AF80: 2514.58 | AG80: =AVERAGE(AF80,J80) -> 2523.1185 | AH80: 2535.604 | AI80: =AVERAGE(AH80,K80) -> 2542.3365
B81: Growth % | D81: =D80/C80-1 -> 0.012943083 | E81: =E80/D80-1 -> 0.021408794 | F81: =F80/E80-1 -> 0.022330458 | G81: =G80/F80-1 -> 0.021949719 | H81: =H80/G80-1 -> 0.010499925 | I81: =I80/H80-1 -> 0.012382586 | J81: =J80/I80-1 -> 0.016279944 | K81: =K80/J80-1 -> 0.0068777089 | T81: =T80/R80-1 -> 0.014782483 | U81: =U80/S80-1 -> 0.013862235 | V81: =V80/T80-1 -> 0.011235985 | W81: =W80/U80-1 -> 0.016320804 | X81: =X80/V80-1 -> 0.021038189 | Y81: =Y80/W80-1 -> 0.021687356 | Z81: =Z80/X80-1 -> 0.023109454 | AA81: =AA80/Y80-1 -> 0.022526498 | ... AI81: =AI80/AG80-1 -> 0.0076167647
B83: Sales Per Sqm | C83: =C30/C80 -> 15.907958 | D83: =D30/D80 -> 16.472922 | E83: =E30/E80 -> 17.005489 | F83: =F30/F80 -> 17.68996 | G83: =G30/G80 -> 17.965024 | H83: =H30/H80 -> 18.588713 | I83: =I30/I80 -> 19.287448 | J83: =J30/J80 -> 20.074994 | K83: =K30/K80 -> 20.198747 | R83: =R30/R80 -> 8.3166076 | S83: =S30/S80 -> 7.605774 | T83: =T30/T80 -> 8.5122821 | U83: =U30/U80 -> 7.9528515 | V83: =V30/V80 -> 8.6307853 | W83: =W30/W80 -> 8.4950154 | X83: =X30/X80 -> 8.9925006 | Y83: =Y30/Y80 -> 8.8395548 | ... AI83: =AI30/AI80 -> 9.760313
B84: Growth % | D84: =D83/C83-1 -> 0.035514539 | E84: =E83/D83-1 -> 0.032329879 | F84: =F83/E83-1 -> 0.04024999 | G84: =G83/F83-1 -> 0.015549128 | H84: =H83/G83-1 -> 0.034716861 | I84: =I83/H83-1 -> 0.037589216 | J84: =J83/I83-1 -> 0.040832073 | K84: =K83/J83-1 -> 0.0061645203 | T84: =T83/R83-1 -> 0.023528157 | U84: =U83/S83-1 -> 0.045633429 | V84: =V83/T83-1 -> 0.013921445 | W84: =W83/U83-1 -> 0.068172255 | X84: =X83/V83-1 -> 0.04190989 | Y84: =Y83/W83-1 -> 0.04055783 | Z84: =Z83/X83-1 -> 0.059847134 | AA84: =AA83/Y83-1 -> -0.031039263 | ... AI84: =AI83/AG83-1 -> -0.010112296
B86: Area per store | C86: =(C80*1000)/C76 -> 2257.2234 | D86: =(D80*1000)/D76 -> 2263.756 | E86: =(E80*1000)/E76 -> 2276.0918 | F86: =(F80*1000)/F76 -> 2267.1399 | G86: =(G80*1000)/G76 -> 2267.2858 | H86: =(H80*1000)/H76 -> 2267.8645 | I86: =(I80*1000)/I76 -> 2274.979 | J86: =(J80*1000)/J76 -> 2278.7192 | K86: =(K80*1000)/K76 -> 2282.0671 | R86: =(R80*1000)/R76 -> 2259.0643 | S86: =(S80*1000)/S76 -> 2262.6819 | T86: =(T80*1000)/T76 -> 2265.1677 | U86: =(U80*1000)/U76 -> 2271.2214 | V86: =(V80*1000)/V76 -> 2268.1179 | W86: =(W80*1000)/W76 -> 2265.46 | X86: =(X80*1000)/X76 -> 2269.0279 | Y86: =(Y80*1000)/Y76 -> 2252.9867 | ... AI86: =(AI80*1000)/AI76 -> 2276.0398
B87: Growth % | D87: =D86/C86-1 -> 0.0028940447 | E87: =E86/D86-1 -> 0.005449282 | F87: =F86/E86-1 -> -0.0039330268 | G87: =G86/F86-1 -> 6.4389722e-05 | H87: =H86/G86-1 -> 0.00025522535 | I87: =I86/H86-1 -> 0.003137083 | J87: =J86/I86-1 -> 0.0016440488 | K87: =K86/J86-1 -> 0.0014692342 | T87: =T86/R86-1 -> 0.0027017389 | U87: =U86/S86-1 -> 0.0037740539 | V87: =V86/T86-1 -> 0.0013024287 | W87: =W86/U86-1 -> -0.0025367109 | X87: =X86/V86-1 -> 0.00040122838 | Y87: =Y86/W86-1 -> -0.0055058439 | Z87: =Z86/X86-1 -> -0.00092977189 | AA87: =AA86/Y86-1 -> 0.0025143302 | ... AI87: =AI86/AG86-1 -> 0.0022043202
B89: Store locations
B90: NSW & ACT | C90: 312 | D90: 317 | E90: 324 | F90: 334 | G90: 343 | H90: 346 | I90: 349 | J90: 358 | K90: 357 | R90: 308 | AD90: 348 | AF90: 353 | AH90: 359
B91: QLD | C91: 234 | D91: 334 | E91: 237 | F91: 242 | G91: 250 | H91: 253 | I91: 256 | J91: 260 | K91: 262 | R91: 234 | AD91: 254 | AF91: 259 | AH91: 261
B92: VIC | C92: 244 | D92: 249 | E92: 253 | F92: 265 | G92: 268 | H92: 270 | I92: 273 | J92: 274 | K92: 278 | R92: 243 | AD92: 274 | AF92: 274 | AH92: 273
B93: SA & NT | C93: 80 | D93: 79 | E93: 78 | F93: 78 | G93: 78 | H93: 79 | I93: 79 | J93: 79 | K93: 79 | R93: 83 | AD93: 79 | AF93: 79 | AH93: 79
B94: WA | C94: 94 | D94: 98 | E94: 101 | F94: 101 | G94: 104 | H94: 106 | I94: 107 | J94: 109 | K94: 110 | R94: 96 | AD94: 107 | AF94: 108 | AH94: 110
B95: TAS | C95: 31 | D95: 31 | E95: 31 | F95: 31 | G95: 31 | H95: 31 | I95: 31 | J95: 31 | K95: 31 | R95: 32 | AD95: 31 | AF95: 31 | AH95: 31
B96: Mini Woolies (not included in sqm) | E96: 2 | F96: 2 | G96: 3 | H96: 13 | I96: 41 | J96: 66 | K96: 32 | AF96: 52 | AH96: 86
A97: Total Aus Stores | B97: Total | C97: =SUM(C90:C95) -> 995 | D97: =SUM(D90:D95) -> 1108 | E97: =SUM(E90:E95) -> 1024 | F97: =SUM(F90:F95) -> 1051 | G97: =SUM(G90:G95) -> 1074 | H97: =SUM(H90:H95) -> 1085 | I97: =SUM(I90:I95) -> 1095 | J97: =SUM(J90:J95) -> 1111 | K97: =SUM(K90:K95) -> 1117 | R97: =SUM(R90:R95) -> 996 | AD97: =SUM(AD90:AD95) -> 1093 | AF97: =SUM(AF90:AF95) -> 1104 | AH97: =SUM(AH90:AH95) -> 1113
B99: Refurbishments | C99: 72 | D99: =80+54-11 -> 123 | E99: 68 | F99: 69 | G99: 65 | H99: 58 | I99: 39 | J99: 48 | K99: 63 | R99: 26 | T99: 37 | V99: 43 | X99: 36 | Z99: 35 | AB99: 27 | AD99: 23 | AF99: 23 | AH99: 30
B102: eCom (Woolies X)
B103: Online sales | D103: 1100 | E103: =395+368+346+335 -> 1444 | F103: 2017 | G103: 3286 | H103: 4937 | I103: 5079 | J103: 6226 | K103: 7309 | L103: =K103*(1+L104) -> 8259.17 | M103: =L103*(1+M104) -> 9085.087 | N103: =M103*(1+N104) -> 9993.5957 | O103: =N103*(1+O104) -> 10992.955 | P103: =O103*(1+P104) -> 12092.251 | T103: =D103-U103 -> 543 | U103: =277+280 -> 557 | V103: =355+343 -> 698 | W103: =E103-V103 -> 746 | X103: =462+480 -> 942 | Y103: =F103-X103 -> 1075 | Z103: 1697 | AA103: =G103-Z103 -> 1589 | AB103: 2547 | AC103: =H103-AB103 -> 2390 | AD103: 2356 | AE103: =I103-AD103 -> 2723 | AF103: 3113 | AG103: =J103-AF103 -> 3113 | AH103: 3735 | AI103: =K103-AH103 -> 3574 | AJ103: =AH103*(1+AJ104) -> 3921.75 | AK103: =L103-AJ103 -> 4337.42
B104: Growth % | E104: =E103/D103-1 -> 0.31272727 | F104: =F103/E103-1 -> 0.3968144 | G104: =G103/F103-1 -> 0.62915221 | H104: =H103/G103-1 -> 0.50243457 | I104: =I103/H103-1 -> 0.028762406 | J104: =J103/I103-1 -> 0.22583186 | K104: =K103/J103-1 -> 0.17394796 | L104: 0.13 | M104: 0.1 | N104: 0.1 | O104: 0.1 | P104: 0.1 | V104: =V103/T103-1 -> 0.2854512 | W104: =W103/U103-1 -> 0.33931777 | X104: =X103/V103-1 -> 0.3495702 | Y104: =Y103/W103-1 -> 0.44101877 | Z104: =Z103/X103-1 -> 0.8014862 | AA104: =AA103/Y103-1 -> 0.47813953 | AB104: =AB103/Z103-1 -> 0.50088391 | AC104: =AC103/AA103-1 -> 0.50409062 | ... AI104: =AI103/AG103-1 -> 0.14808866 | AJ104: 0.05 | AK104: =AK103/AI103-1 -> 0.21360381
B105: Online Penetration | D105: =D103/D30 -> 0.02926388 | E105: =E103/E30 -> 0.036432446 | F105: =F103/F30 -> 0.047851771 | G105: =G103/G30 -> 0.075115439 | H105: =H103/H30 -> 0.10793616 | I105: =I103/I30 -> 0.10570899 | J105: =J103/J30 -> 0.12250359 | K105: =K103/K30 -> 0.14195541 | ... P105: =P103/P30 -> 0.19374959 | T105: =T103/T30 -> 0.027937847 | U105: =U103/U30 -> 0.030683634 | V105: =V103/V30 -> 0.035026094 | W105: =W103/W30 -> 0.037854569 | X105: =X103/X30 -> 0.044433962 | Y105: =Y103/Y30 -> 0.0513102 | Z105: =Z103/Z30 -> 0.073821124 | AA105: =AA103/AA30 -> 0.0765488 | ... AK105: =AK103/AK30 -> 0.16855501
B106: Change YoY % | E106: =E105-D105 -> 0.0071685657 | F106: =F105-E105 -> 0.011419325 | G106: =G105-F105 -> 0.027263668 | H106: =H105-G105 -> 0.032820722 | I106: =I105-H105 -> -0.0022271676 | J106: =J105-I105 -> 0.016794598 | K106: =K105-J105 -> 0.019451816 | L106: =L105-K105 -> 0.012853402 | ... P106: =P105-O105 -> 0.010613204 | V106: =V105-T105 -> 0.0070882466 | W106: =W105-U105 -> 0.0071709359 | X106: =X105-V105 -> 0.0094078683 | Y106: =Y105-W105 -> 0.013455631 | Z106: =Z105-X105 -> 0.029387162 | AA106: =AA105-Y105 -> 0.0252386 | AB106: =AB105-Z105 -> 0.033285688 | AC106: =AC105-AA105 -> 0.032285444 | ... AK106: =AK105-AI105 -> 0.024523415
B107: Online Contribution to LFL | E107: =(E103-D103)/D30 -> 0.0091516135 | F107: =(F103-E103)/E30 -> 0.014456919 | G107: =(G103-F103)/F30 -> 0.030106047 | H107: =(H103-G103)/G30 -> 0.037740593 | I107: =(I103-H103)/H30 -> 0.0031045037 | J107: =(J103-I103)/I30 -> 0.023872458 | K107: =(K103-J103)/J30 -> 0.02130925 | L107: =(L103-K103)/K30 -> 0.018454203 | ... P107: =(P103-O103)/O30 -> 0.018313639
B109: EBIT | H109: 93 | I109: 89 | J109: 201 | K109: 207 | L109: =L103*L111 -> 242.16917 | M109: =M103*M111 -> 275.47117 | N109: =N103*N111 -> 313.01189 | O109: =O103*O111 -> 355.30603 | P109: =P103*P111 -> 402.92888 | AB109: 71 | AC109: =H109-AB109 -> 22 | AD109: 34 | AE109: =I109-AD109 -> 55 | AF109: 89 | AG109: =J109-AF109 -> 112 | AH109: 97 | AI109: =K109-AH109 -> 110 | AJ109: =AJ103*AJ111 -> 105.77175 | AK109: =L109-AJ109 -> 136.39742
B110: Growth % | I110: =I109/H109-1 -> -0.043010753 | J110: =J109/I109-1 -> 1.258427 | K110: =K109/J109-1 -> 0.029850746 | L110: =L109/K109-1 -> 0.16989937 | M110: =M109/L109-1 -> 0.13751546 | N110: =N109/M109-1 -> 0.13627819 | O110: =O109/N109-1 -> 0.13511993 | P110: =P109/O109-1 -> 0.13403334 | AD110: =AD109/AB109-1 -> -0.52112676 | AE110: =AE109/AC109-1 -> 1.5 | AF110: =AF109/AD109-1 -> 1.6176471 | AG110: =AG109/AE109-1 -> 1.0363636 | AH110: =AH109/AF109-1 -> 0.08988764 | AI110: =AI109/AG109-1 -> -0.017857143 | AJ110: =AJ109/AH109-1 -> 0.090430412 | AK110: =AK109/AI109-1 -> 0.23997655
B111: EBIT Margin | H111: =H109/H103 -> 0.018837351 | I111: =I109/I103 -> 0.017523134 | J111: =J109/J103 -> 0.03228397 | K111: =K109/K103 -> 0.028321248 | L111: =K111+L112 -> 0.029321248 | M111: =L111+M112 -> 0.030321248 | N111: =M111+N112 -> 0.031321248 | O111: =N111+O112 -> 0.032321248 | P111: =O111+P112 -> 0.033321248 | AB111: =AB109/AB103 -> 0.027875932 | AC111: =AC109/AC103 -> 0.0092050209 | AD111: =AD109/AD103 -> 0.014431239 | AE111: =AE109/AE103 -> 0.020198311 | AF111: =AF109/AF103 -> 0.028589785 | AG111: =AG109/AG103 -> 0.035978156 | AH111: =AH109/AH103 -> 0.025970549 | AI111: =AI109/AI103 -> 0.03077784 | AJ111: =AH111+AJ112 -> 0.026970549 | AK111: =AK109/AK103 -> 0.031446671
B112: Change YoY % | I112: =I111-H111 -> -0.0013142161 | J112: =J111-I111 -> 0.014760836 | K112: =K111-J111 -> -0.0039627227 | L112: 0.001 | M112: 0.001 | N112: 0.001 | O112: 0.001 | P112: 0.001 | AD112: =AD111-AB111 -> -0.013444693 | AE112: =AE111-AC111 -> 0.01099329 | AF112: =AF111-AD111 -> 0.014158545 | AG112: =AG111-AE111 -> 0.015779845 | AH112: =AH111-AF111 -> -0.0026192359 | AI112: =AI111-AG111 -> -0.0052003162 | AJ112: 0.001 | AK112: =AK111-AI111 -> 0.00066883111
B114: NZ Food
B116: NZ$
B117: Sales | C117: 6232 | D117: 6396 | E117: 6712 | F117: 7192 | G117: 7146 | H117: 7563 | I117: 7912 | J117: 8166 | K117: 8286 | L117: =K117*(1+L118) -> 8486.9355 | M117: =L117*(1+M118) -> 8833.7929 | N117: =M117*(1+N118) -> 9193.7937 | O117: =N117*(1+O118) -> 9567.4138 | P117: =O117*(1+P118) -> 9955.1458 | R117: 3227 | S117: =C117-R117 -> 3005 | T117: 3337 | U117: =D117-T117 -> 3059 | V117: 3401 | W117: =E117-V117 -> 3311 | X117: 3564 | Y117: =F117-X117 -> 3628 | Z117: 3717 | AA117: =G117-Z117 -> 3429 | AB117: 4027 | AC117: =H117-AB117 -> 3536 | AD117: 4079 | AE117: =I117-AD117 -> 3833 | AF117: 4172 | AG117: =J117-AF117 -> 3994 | AH117: 4285 | AI117: =K117-AH117 -> 4001 | AJ117: =AH117*(1+AJ118) -> 4386.7572 | AK117: =L117-AJ117 -> 4100.1783
A118: NZ Growth | B118: Growth % | D118: =D117/C117-1 -> 0.026315789 | E118: =E117/D117-1 -> 0.049405879 | F118: =F117/E117-1 -> 0.071513707 | G118: =G117/F117-1 -> -0.0063959956 | H118: =H117/G117-1 -> 0.058354324 | I118: =I117/H117-1 -> 0.046145709 | J118: =J117/I117-1 -> 0.032103134 | K118: =K117/J117-1 -> 0.014695077 | L118: =SUM(L119:L121) -> 0.02425 | M118: =SUM(M119:M121) -> 0.040869565 | N118: =SUM(N119:N121) -> 0.040752688 | O118: =SUM(O119:O121) -> 0.040638298 | P118: =SUM(P119:P121) -> 0.040526316 | T118: =T117/R117-1 -> 0.034087388 | U118: =U117/S117-1 -> 0.01797005 | V118: =V117/T117-1 -> 0.019178903 | W118: =W117/U117-1 -> 0.082379863 | X118: =X117/V117-1 -> 0.04792708 | Y118: =Y117/W117-1 -> 0.095741468 | Z118: =Z117/X117-1 -> 0.042929293 | AA118: =AA117/Y117-1 -> -0.054851158 | ... AI118: =AI117/AG117-1 -> 0.0017526289 | AJ118: =SUM(AJ119:AJ121) -> 0.023747312 | AK118: =AK117/AI117-1 -> 0.02478837
A119: NZ LFL | B119: LFL Sales Growth % | C119: 0.012 | D119: 0.034 | E119: 0.034 | F119: 0.089 | G119: -0.013 | H119: 0.05 | I119: 0.035 | J119: 0.018 | K119: 0.038 | L119: =VLOOKUP($A119,Quarterly!$1:$1048576,MATCH(Model!L$3,Quarterly!$3:$3,0),FALSE) -> 0.03425 | M119: 0.035 | N119: 0.035 | O119: 0.035 | P119: 0.035 | R119: 0 | S119: 0.024886522 | T119: 0.03 | U119: =VLOOKUP($A119,Quarterly!$1:$1048576,MATCH(Model!U$3,Quarterly!$3:$3,0),FALSE) -> 0.0375 | V119: 0.032 | W119: =VLOOKUP($A119,Quarterly!$1:$1048576,MATCH(Model!W$3,Quarterly!$3:$3,0),FALSE) -> 0.0365 | X119: 0.047 | Y119: =VLOOKUP($A119,Quarterly!$1:$1048576,MATCH(Model!Y$3,Quarterly!$3:$3,0),FALSE) -> 0.1365 | Z119: 0.033 | AA119: =VLOOKUP($A119,Quarterly!$1:$1048576,MATCH(Model!AA$3,Quarterly!$3:$3,0),FALSE) -> -0.0585 | AB119: 0.07 | AC119: =VLOOKUP($A119,Quarterly!$1:$1048576,MATCH(Model!AC$3,Quarterly!$3:$3,0),FALSE) -> 0.0225 | AD119: 0.003 | AE119: =VLOOKUP($A119,Quarterly!$1:$1048576,MATCH(Model!AE$3,Quarterly!$3:$3,0),FALSE) -> 0.07 | AF119: 0.025 | AG119: =VLOOKUP($A119,Quarterly!$1:$1048576,MATCH(Model!AG$3,Quarterly!$3:$3,0),FALSE) -> 0.013 | AH119: 0.033 | AI119: =VLOOKUP($A119,Quarterly!$1:$1048576,MATCH(Model!AI$3,Quarterly!$3:$3,0),FALSE) -> 0.0435 | AJ119: =VLOOKUP($A119,Quarterly!$1:$1048576,MATCH(Model!AJ$3,Quarterly!$3:$3,0),FALSE) -> 0.0385 | AK119: =VLOOKUP($A119,Quarterly!$1:$1048576,MATCH(Model!AK$3,Quarterly!$3:$3,0),FALSE) -> 0.03
B120: Store Growth % | D120: =D162/C162-1 -> -0.016304348 | E120: =E162/D162-1 -> -0.0055248619 | F120: =F162/E162-1 -> 0.011111111 | G120: =G162/F162-1 -> 0.010989011 | H120: =H162/G162-1 -> 0.032608696 | I120: =I162/H162-1 -> 0.0052631579 | J120: =J162/I162-1 -> -0.015706806 | K120: =K162/J162-1 -> -0.021276596 | ... P120: =P162/O162-1 -> 0.010526316 | T120: =T162/R162-1 -> 0.0054644809 | U120: =U162/S162-1 -> -0.016304348 | V120: =V162/T162-1 -> -0.02173913 | W120: =W162/U162-1 -> -0.0055248619 | X120: =X162/V162-1 -> 0.011111111 | Y120: =Y162/W162-1 -> 0.011111111 | Z120: =Z162/X162-1 -> -0.0054945055 | AA120: =AA162/Y162-1 -> 0.0054945055 | ... AK120: =AK162/AI162-1 -> 0
B121: Other | D121: =D118-SUM(D119:D120) -> 0.0086201373 | E121: =E118-SUM(E119:E120) -> 0.020930741 | F121: =F118-SUM(F119:F120) -> -0.028597404 | G121: =G118-SUM(G119:G120) -> -0.0043850065 | H121: =H118-SUM(H119:H120) -> -0.024254372 | I121: =I118-SUM(I119:I120) -> 0.0058825515 | J121: =J118-SUM(J119:J120) -> 0.029809941 | K121: =K118-SUM(K119:K120) -> -0.0020283271 | L121: -0.01 | M121: -0.005 | N121: -0.005 | O121: -0.005 | P121: -0.005 | T121: =T118-SUM(T119:T120) -> -0.0013770932 | U121: =U118-SUM(U119:U120) -> -0.0032256023 | V121: =V118-SUM(V119:V120) -> 0.0089180336 | W121: =W118-SUM(W119:W120) -> 0.051404725 | X121: =X118-SUM(X119:X120) -> -0.010184031 | Y121: =Y118-SUM(Y119:Y120) -> -0.051869643 | Z121: =Z118-SUM(Z119:Z120) -> 0.015423798 | AA121: =AA118-SUM(AA119:AA120) -> -0.0018456632 | ... AI121: =AI118-SUM(AI119:AI120) -> -0.020470775 | AJ121: -0.004 | AK121: =AK118-SUM(AK119:AK120) -> -0.0052116299
...

Sheet PL
B1: Woolworths Group (WOW.AX)
B2: A$M
C3: =Model!C3 -> FY17 | D3: =Model!D3 -> FY18 | E3: =Model!E3 -> FY19 | F3: =Model!F3 -> FY20 | G3: =Model!G3 -> FY21 | H3: =Model!H3 -> FY22 | I3: =Model!I3 -> FY23 | J3: =Model!J3 -> FY24 | K3: =Model!K3 -> FY25 | L3: FY26E | M3: FY27E | N3: FY28E | O3: FY29E | P3: FY30E | R3: =Model!R3 -> 1H17 | S3: =Model!S3 -> 2H17 | T3: =Model!T3 -> 1H18 | U3: =Model!U3 -> 2H18 | V3: =Model!V3 -> 1H19 | W3: =Model!W3 -> 2H19 | X3: =Model!X3 -> 1H20 | Y3: =Model!Y3 -> 2H20 | ... AI3: =Model!AI3 -> 2H25 | AJ3: 1H26E | AK3: 2H26E
B4: P&L
A5: Total Sales | B5: Sales | C5: =VLOOKUP($A$5,Model!1:1048576,MATCH(PL!C3,Model!3:3,0),FALSE) -> 54841 | D5: =VLOOKUP($A$5,Model!1:1048576,MATCH(PL!D3,Model!3:3,0),FALSE) -> 57175 | E5: =VLOOKUP($A$5,Model!1:1048576,MATCH(PL!E3,Model!3:3,0),FALSE) -> 59984 | F5: =VLOOKUP($A$5,Model!1:1048576,MATCH(PL!F3,Model!3:3,0),FALSE) -> 63675 | G5: =VLOOKUP($A$5,Model!1:1048576,MATCH(PL!G3,Model!3:3,0),FALSE) -> 67317 | H5: =VLOOKUP($A$5,Model!1:1048576,MATCH(PL!H3,Model!3:3,0),FALSE) -> 60849 | I5: =VLOOKUP($A$5,Model!1:1048576,MATCH(PL!I3,Model!3:3,0),FALSE) -> 64294 | J5: =VLOOKUP($A$5,Model!1:1048576,MATCH(PL!J3,Model!3:3,0),FALSE) -> 67922 | ... P5: =VLOOKUP($A$5,Model!1:1048576,MATCH(PL!P3,Model!3:3,0),FALSE) -> 83436.419 | R5: =VLOOKUP($A$5,Model!1:1048576,MATCH(PL!R3,Model!3:3,0),FALSE) -> 29058.5 | S5: =VLOOKUP($A$5,Model!1:1048576,MATCH(PL!S3,Model!3:3,0),FALSE) -> 25838.5 | T5: =VLOOKUP($A$5,Model!1:1048576,MATCH(PL!T3,Model!3:3,0),FALSE) -> 29907 | U5: =VLOOKUP($A$5,Model!1:1048576,MATCH(PL!U3,Model!3:3,0),FALSE) -> 27268 | V5: =VLOOKUP($A$5,Model!1:1048576,MATCH(PL!V3,Model!3:3,0),FALSE) -> 30587 | W5: =VLOOKUP($A$5,Model!1:1048576,MATCH(PL!W3,Model!3:3,0),FALSE) -> 29397 | X5: =VLOOKUP($A$5,Model!1:1048576,MATCH(PL!X3,Model!3:3,0),FALSE) -> 32410 | Y5: =VLOOKUP($A$5,Model!1:1048576,MATCH(PL!Y3,Model!3:3,0),FALSE) -> 31265 | ... AK5: =VLOOKUP($A$5,Model!1:1048576,MATCH(PL!AK3,Model!3:3,0),FALSE) -> 34098.538
A6: Total Sales Growth | B6: Growth % | D6: =D5/C5-1 -> 0.042559399 | E6: =E5/D5-1 -> 0.049129864 | F6: =F5/E5-1 -> 0.061533075 | G6: =G5/F5-1 -> 0.057196702 | H6: =H5/G5-1 -> -0.096082713 | I6: =I5/H5-1 -> 0.056615557 | J6: =J5/I5-1 -> 0.056428283 | K6: =K5/J5-1 -> 0.0170048 | ... P6: =P5/O5-1 -> 0.040666986 | T6: =T5/R5-1 -> 0.029199718 | U6: =U5/S5-1 -> 0.055324419 | V6: =V5/T5-1 -> 0.022737152 | W6: =W5/U5-1 -> 0.078076867 | X6: =X5/V5-1 -> 0.059600484 | Y6: =Y5/W5-1 -> 0.063543899 | Z6: =Z5/X5-1 -> 0.10721999 | AA6: =AA5/Y5-1 -> 0.0053414361 | ... AK6: =AK5/AI5-1 -> 0.0287066
B8: Cost of Goods Sold | C8: =C9-C5 -> -38912.1 | D8: =D9-D5 -> -40466 | E8: =E9-E5 -> -42542 | F8: =F9-F5 -> -45105 | G8: =G9-G5 -> -49276.044 | H8: =H9-H5 -> -44906.562 | I8: -47118 | J8: -49370 | K8: -50262 | L8: =L9-L5 -> -52761.259 | M8: =M9-M5 -> -54862.321 | N8: =N9-N5 -> -57050.224 | O8: =O9-O5 -> -59376.258 | P8: =P9-P5 -> -61787.904 | R8: -20660.593 | S8: =C8-R8 -> -18251.506 | T8: =T9-T5 -> -21186 | U8: =U9-U5 -> -19280 | V8: =V9-V5 -> -21682 | W8: =W9-W5 -> -20860 | X8: =X9-X5 -> -22825 | Y8: =Y9-Y5 -> -22280 | Z8: =Z9-Z5 -> -26339.59 | AA8: =G8-Z8 -> -22936.454 | AB8: =AB9-AB5 -> -22491 | AC8: =H8-AB8 -> -22415.562 | AD8: =AD9-AD5 -> -23288 | AE8: =AE9-AE5 -> -23802 | AF8: -25154 | AG8: =AG9-AG5 -> -24216 | AH8: -26154 | AI8: =AI9-AI5 -> -24108 | AJ8: =AJ9-AJ5 -> -27473.263 | AK8: =L8-AJ8 -> -25287.995
A9: Gross Profit | B9: Gross Profit Reported | C9: 15928.9 | D9: 16709 | E9: 17442 | F9: 18570 | G9: =G5*G10 -> 18040.956 | H9: =H5*H10 -> 15942.438 | I9: 17204 | J9: 18552 | K9: 18815 | L9: =Model!L37+Model!L123/Model!L181+Model!L213 -> 18391.49 | M9: =Model!M37+Model!M123/Model!M181+Model!M213 -> 19135.737 | N9: =Model!N37+Model!N123/Model!N181+Model!N213 -> 19980.894 | O9: =Model!O37+Model!O123/Model!O181+Model!O213 -> 20799.649 | P9: =Model!P37+Model!P123/Model!P181+Model!P213 -> 21648.515 | R9: 8397.9065 | S9: =C9-R9 -> 7530.9935 | T9: 8721 | U9: =D9-T9 -> 7988 | V9: 8905 | W9: =E9-V9 -> 8537 | X9: 9585 | Y9: =F9-X9 -> 8985 | Z9: =Z5*Z10 -> 9545.41 | AA9: =G9-Z9 -> 8495.546 | AB9: 9403 | AC9: =H9-AB9 -> 6539.438 | AD9: 9881 | AE9: =I9-AD9 -> 7323 | AF9: =AF5+AF8 -> 9481 | AG9: =J9-AF9 -> 9071 | AH9: =AH5+AH8 -> 9776 | AI9: =K9-AH9 -> 9039 | AJ9: =Model!AJ37+Model!AJ123/Model!AJ181+Model!AJ213 -> 9580.9476 | AK9: =L9-AJ9 -> 8810.5423
B10: Gross Margin | C10: =C9/C5 -> 0.29045605 | D10: =D9/D5 -> 0.29224311 | E10: =E9/E5 -> 0.29077754 | F10: =F9/F5 -> 0.29163722 | G10: 0.268 | H10: 0.262 | I10: =I9/I5 -> 0.26758329 | J10: =J9/J5 -> 0.27313683 | K10: =K9/K5 -> 0.2723772 | T10: =T9/T5 -> 0.29160397 | U10: =U9/U5 -> 0.29294411 | V10: =V9/V5 -> 0.29113676 | W10: =W9/W5 -> 0.29040378 | X10: =X9/X5 -> 0.29574205 | Y10: =Y9/Y5 -> 0.28738206 | Z10: 0.266 | AA10: =AA9/AA5 -> 0.27028334 | AB10: =AB9/AB5 -> 0.29482034 | AC10: =AC9/AC5 -> 0.22584832 | AD10: =AD9/AD5 -> 0.29789864 | AE10: =AE9/AE5 -> 0.23527711 | AF10: =AF9/AF5 -> 0.27374044 | AG10: =AG9/AG5 -> 0.27250879 | AH10: =AH9/AH5 -> 0.27208461 | AI10: =AI9/AI5 -> 0.27269436
B11: Change YoY % | D11: =D10-C10 -> 0.0017870676 | E11: =E10-D10 -> -0.0014655726 | F11: =F10-E10 -> 0.00085967958 | G11: =G10-F10 -> -0.02363722 | H11: =H10-G10 -> -0.006 | I11: =I10-H10 -> 0.0055832893 | J11: =J10-I10 -> 0.0055535442 | K11: =K10-J10 -> -0.00075963117 | V11: =V10-T10 -> -0.00046721487 | W11: =W10-U10 -> -0.0025403276 | X11: =X10-V10 -> 0.0046052975 | Y11: =Y10-W10 -> -0.0030217261 | Z11: =Z10-X10 -> -0.029742055 | AA11: =AA10-Y10 -> -0.017098715 | AB11: =AB10-Z10 -> 0.028820342 | AC11: =AC10-AA10 -> -0.044435025 | ... AI11: =AI10-AG10 -> 0.00018557427
B13: Branch & Administration Expenses
B14: Employee Expenses | H14: 8557 | I14: 8762 | J14: 9519 | K14: 9993 | AD14: 5144 | AE14: =I14-AD14 -> 3618 | AF14: 4811 | AG14: =J14-AF14 -> 4708 | AH14: 5181 | AI14: =K14-AH14 -> 4812
B15: D&A | H15: 2132 | I15: 2309 | J15: 2452 | K15: 2574 | AD15: 1287 | AE15: =I15-AD15 -> 1022 | AF15: 1233 | AG15: =J15-AF15 -> 1219 | AH15: 1317 | AI15: =K15-AH15 -> 1257
B16: Occupancy Expenses | H16: 624 | I16: 611 | J16: 706 | K16: 750 | AD16: 321 | AE16: =I16-AD16 -> 290 | AF16: 367 | AG16: =J16-AF16 -> 339 | AH16: 385 | AI16: =K16-AH16 -> 365
B17: Contract Labour & Consultancy | H17: 745 | I17: 832 | J17: 825 | K17: 759 | AD17: 733 | AE17: =I17-AD17 -> 99 | AF17: 437 | AG17: =J17-AF17 -> 388 | AH17: 408 | AI17: =K17-AH17 -> 351
B18: Other | H18: =H19-SUM(H14:H17) -> 1519 | I18: =I19-SUM(I14:I17) -> 1940 | J18: =J19-SUM(J14:J17) -> 3744 | K18: =K19-SUM(K14:K17) -> 2827 | AD18: =AD19-SUM(AD14:AD17) -> 960 | AE18: =I18-AD18 -> 980 | AF18: =AF19-SUM(AF14:AF17) -> 2809 | AG18: =J18-AF18 -> 935 | AH18: =AH19-SUM(AH14:AH17) -> 1169 | AI18: =K18-AH18 -> 1658
B19: Total | H19: 13577 | I19: 14454 | J19: 17246 | K19: 16903 | AD19: 8445 | AE19: =I19-AD19 -> 6009 | AF19: 9657 | AG19: =J19-AF19 -> 7589 | AH19: 8460 | AI19: =K19-AH19 -> 8443
A21: EBITDA | B21: EBITDA Normalised | C21: =C28-C26 -> 3363.8 | D21: =D28-D26 -> 3651 | E21: =E28-E26 -> 3944 | F21: =F28-F26 -> 5187 | G21: =G28-G26 -> 4843 | H21: =H28-H26 -> 5051 | I21: =I28-I26 -> 5694 | J21: =J28-J26 -> 6001 | ... P21: =P28-P26 -> 7821.0784 | R21: =R28-R26 -> 1861.4 | S21: =S28-S26 -> 1577.1 | T21: =T28-T26 -> 1993 | U21: =U28-U26 -> 1658 | V21: =V28-V26 -> 2030 | W21: =W28-W26 -> 1914 | X21: =X28-X26 -> 3141 | Y21: =Y28-Y26 -> 2046 | ... AK21: =AK28-AK26 -> 2974.2237
B22: Growth % | D22: =D21/C21-1 -> 0.08537963 | E22: =E21/D21-1 -> 0.080251986 | F22: =F21/E21-1 -> 0.31516227 | G22: =G21/F21-1 -> -0.066319645 | H22: =H21/G21-1 -> 0.042948586 | I22: =I21/H21-1 -> 0.12730152 | J22: =J21/I21-1 -> 0.053916403 | K22: =K21/J21-1 -> -0.048991835 | ... P22: =P21/O21-1 -> 0.050216836 | T22: =T21/R21-1 -> 0.070699474 | U22: =U21/S21-1 -> 0.051296684 | V22: =V21/T21-1 -> 0.018564977 | W22: =W21/U21-1 -> 0.1544029 | X22: =X21/V21-1 -> 0.54729064 | Y22: =Y21/W21-1 -> 0.068965517 | Z22: =Z21/X21-1 -> -0.16905444 | AA22: =AA21/Y21-1 -> 0.091397849 | ... AK22: =AK21/AI21-1 -> 0.081142737
B24: Lease D&A | F24: -1158 | G24: -945 | H24: -1039 | I24: -1066 | J24: -1151 | K24: -1211 | L24: =K24*1.05 -> -1271.55 | M24: =L24*1.05 -> -1335.1275 | N24: =M24*1.05 -> -1401.8839 | O24: =N24*1.05 -> -1471.9781 | P24: =O24*1.05 -> -1545.577
A25: D&A ex leases | B25: Non Lease D&A | F25: =F26-F24 -> -810 | G25: =G26-G24 -> -1134 | H25: =H26-H24 -> -1322 | I25: =I26-I24 -> -1512 | J25: =J26-J24 -> -1627 | K25: =K26-K24 -> -1742 | L25: =L26-L24 -> -1799.57 | M25: =M26-M24 -> -1858.8373 | ... P25: =P26-P24 -> -2047.199
A26: D&A | B26: D&A | C26: -1037.6 | D26: -1103 | E26: -1222 | F26: -1968 | G26: -2079 | H26: -2361 | I26: -2578 | J26: -2778 | K26: -2953 | L26: =K26*1.04 -> -3071.12 | M26: =L26*1.04 -> -3193.9648 | N26: =M26*1.04 -> -3321.7234 | O26: =N26*1.04 -> -3454.5923 | P26: =O26*1.04 -> -3592.776 | R26: -524.8 | S26: =C26-R26 -> -512.8 | T26: -563 | U26: =D26-T26 -> -540 | V26: -611 | W26: =E26-V26 -> -611 | X26: -1248 | Y26: =F26-X26 -> -720 | Z26: -1056 | AA26: =G26-Z26 -> -1023 | AB26: -1214 | AC26: =H26-AB26 -> -1147 | AD26: -1287 | AE26: =I26-AD26 -> -1291 | AF26: -1387 | AG26: =J26-AF26 -> -1391 | AH26: -1505 | AI26: =K26-AH26 -> -1448 | AJ26: =AH26*1.05 -> -1580.25 | AK26: =L26-AJ26 -> -1490.87
A28: Total EBIT | B28: EBIT Normalised | C28: =VLOOKUP($A$28,Model!1:1048576,MATCH(PL!C3,Model!3:3,0),FALSE) -> 2326.2 | D28: =VLOOKUP($A$28,Model!1:1048576,MATCH(PL!D3,Model!3:3,0),FALSE) -> 2548 | E28: =VLOOKUP($A$28,Model!1:1048576,MATCH(PL!E3,Model!3:3,0),FALSE) -> 2722 | F28: =VLOOKUP($A$28,Model!1:1048576,MATCH(PL!F3,Model!3:3,0),FALSE) -> 3219 | G28: =VLOOKUP($A$28,Model!1:1048576,MATCH(PL!G3,Model!3:3,0),FALSE) -> 2764 | H28: =VLOOKUP($A$28,Model!1:1048576,MATCH(PL!H3,Model!3:3,0),FALSE) -> 2690 | I28: =VLOOKUP($A$28,Model!1:1048576,MATCH(PL!I3,Model!3:3,0),FALSE) -> 3116 | J28: =VLOOKUP($A$28,Model!1:1048576,MATCH(PL!J3,Model!3:3,0),FALSE) -> 3223 | ... P28: =VLOOKUP($A$28,Model!1:1048576,MATCH(PL!P3,Model!3:3,0),FALSE) -> 4228.3024 | R28: =VLOOKUP($A$28,Model!1:1048576,MATCH(PL!R3,Model!3:3,0),FALSE) -> 1336.6 | S28: =VLOOKUP($A$28,Model!1:1048576,MATCH(PL!S3,Model!3:3,0),FALSE) -> 1064.3 | T28: =VLOOKUP($A$28,Model!1:1048576,MATCH(PL!T3,Model!3:3,0),FALSE) -> 1430 | U28: =VLOOKUP($A$28,Model!1:1048576,MATCH(PL!U3,Model!3:3,0),FALSE) -> 1118 | V28: =VLOOKUP($A$28,Model!1:1048576,MATCH(PL!V3,Model!3:3,0),FALSE) -> 1419 | W28: =VLOOKUP($A$28,Model!1:1048576,MATCH(PL!W3,Model!3:3,0),FALSE) -> 1303 | X28: =VLOOKUP($A$28,Model!1:1048576,MATCH(PL!X3,Model!3:3,0),FALSE) -> 1893 | Y28: =VLOOKUP($A$28,Model!1:1048576,MATCH(PL!Y3,Model!3:3,0),FALSE) -> 1326 | ... AK28: =VLOOKUP($A$28,Model!1:1048576,MATCH(PL!AK3,Model!3:3,0),FALSE) -> 1483.3537
A29: Total EBIT Growth | B29: Growth % | D29: =D28/C28-1 -> 0.095348637 | E29: =E28/D28-1 -> 0.068288854 | F29: =F28/E28-1 -> 0.18258633 | G29: =G28/F28-1 -> -0.14134824 | H29: =H28/G28-1 -> -0.026772793 | I29: =I28/H28-1 -> 0.15836431 | J29: =J28/I28-1 -> 0.034338896 | K29: =K28/J28-1 -> -0.1455166 | ... P29: =P28/O28-1 -> 0.059057127 | T29: =T28/R28-1 -> 0.069878797 | U29: =U28/S28-1 -> 0.050455699 | V29: =V28/T28-1 -> -0.0076923077 | W29: =W28/U28-1 -> 0.16547406 | X29: =X28/V28-1 -> 0.33403805 | Y29: =Y28/W28-1 -> 0.017651573 | Z29: =Z28/X28-1 -> -0.17908082 | AA29: =AA28/Y28-1 -> -0.087481146 | ... AK29: =AK28/AI28-1 -> 0.13841417
B31: Significant Items | C31: =C28-C33 -> -79 | D31: =D28-D33 -> 41.5 | E31: =E28-E33 -> -7.8 | F31: =F28-F33 -> 932.8 | G31: =G28-G33 -> -283.8 | H31: =H28-H33 -> -1 | I31: =I28-I33 -> 117 | J31: =J28-J33 -> 1607 | K31: =K28-K33 -> 569 | L31: 0 | M31: 0 | N31: 0 | O31: 0 | P31: 0 | R31: =R28-R33 -> 41.1 | S31: =S28-S33 -> -45.4 | T31: =T28-T33 -> -30.5 | U31: =U28-U33 -> 72 | V31: =V28-V33 -> -97.8 | W31: =W28-W33 -> 90 | X31: =X28-X33 -> 337.7 | Y31: =Y28-Y33 -> 595.1 | ... AI31: =AI28-AI33 -> 569 | AJ31: 0 | AK31: =L31-AJ31 -> 0
B33: EBIT Statutory | C33: 2405.2 | D33: 2506.5 | E33: 2729.8 | F33: 2286.2 | G33: 3047.8 | H33: 2691 | I33: 2999 | J33: 1616 | K33: 2185 | L33: =L28+L31 -> 3051.1355 | M33: =M28+M31 -> 3393.8773 | N33: =N28+N31 -> 3765.4528 | O33: =O28+O31 -> 3992.5159 | P33: =P28+P31 -> 4228.3024 | R33: 1295.5 | S33: =C33-R33 -> 1109.7 | T33: 1460.5 | U33: =D33-T33 -> 1046 | V33: 1516.8 | W33: =E33-V33 -> 1213 | X33: 1555.3 | Y33: =F33-X33 -> 730.9 | Z33: 1554 | AA33: =G33-Z33 -> 1493.8 | AB33: 1237 | AC33: =H33-AB33 -> 1454 | AD33: 1561 | AE33: =I33-AD33 -> 1438 | AF33: -22 | AG33: =J33-AF33 -> 1638 | AH33: 1451 | AI33: =K33-AH33 -> 734 | AJ33: =AJ28+AJ31 -> 1567.7818 | AK33: =AK28+AK31 -> 1483.3537
B35: Least Interest | F35: -701 | G35: -528 | H35: -542 | I35: -542 | J35: -570 | K35: -597 | L35: -610 | M35: =L35*1.03 -> -628.3 | N35: =M35*1.03 -> -647.149 | O35: =N35*1.03 -> -666.56347 | P35: =O35*1.03 -> -686.56037 | X35: -414 | Y35: =F35-X35 -> -287 | Z35: -407 | AA35: =G35-Z35 -> -121 | AB35: -322 | AC35: =H35-AB35 -> -220 | AD35: -320 | AE35: =I35-AD35 -> -222 | AF35: =AF37-AF36 -> -291 | AG35: =J35-AF35 -> -279 | AH35: =AH37-AH36 -> -311 | AI35: =K35-AH35 -> -286
B36: Non-Lease Interest | F36: =F37-F35 -> -142 | G36: =G37-G35 -> -85 | H36: =H37-H35 -> -58 | I36: =I37-I35 -> -135 | J36: =J37-J35 -> -170 | K36: =K37-K35 -> -214 | L36: -205 | M36: -205 | N36: -205 | O36: -205 | P36: -205 | X36: =X37-X35 -> -26 | Y36: =Y37-Y35 -> -116 | Z36: =Z37-Z35 -> 76 | AA36: =AA37-AA35 -> -161 | AB36: =AB37-AB35 -> 16.873101 | AC36: =AC37-AC35 -> -74.873101 | AD36: =AD37-AD35 -> -26 | AE36: =AE37-AE35 -> -109 | AF36: -67 | AG36: =AG37-AG35 -> -103 | AH36: -105 | AI36: =AI37-AI35 -> -109
A37: Net Interest | B37: Net Interest Income / (Expense) | C37: -193.6 | D37: -154 | E37: -126 | F37: -843 | G37: -613 | H37: -600 | I37: -677 | J37: -740 | K37: -811 | L37: =SUM(L35:L36) -> -815 | M37: =SUM(M35:M36) -> -833.3 | N37: =SUM(N35:N36) -> -852.149 | O37: =SUM(O35:O36) -> -871.56347 | P37: =SUM(P35:P36) -> -891.56037 | R37: -113.5 | S37: =C37-R37 -> -80.1 | T37: -82 | U37: =D37-T37 -> -72 | V37: -71 | W37: =E37-V37 -> -55 | X37: -440 | Y37: =F37-X37 -> -403 | Z37: -331 | AA37: =G37-Z37 -> -282 | AB37: -305.1269 | AC37: =H37-AB37 -> -294.8731 | AD37: -346 | AE37: =I37-AD37 -> -331 | AF37: -358 | AG37: =J37-AF37 -> -382 | AH37: -416 | AI37: =K37-AH37 -> -395 | AJ37: -410 | AK37: =L37-AJ37 -> -405
A39: PBT | B39: PBT Normalised | C39: =C28+C37 -> 2132.6 | D39: =D28+D37 -> 2394 | E39: =E28+E37 -> 2596 | F39: =F28+F37 -> 2376 | G39: =G28+G37 -> 2151 | H39: =H28+H37 -> 2090 | I39: =I28+I37 -> 2439 | J39: =J28+J37 -> 2483 | ... P39: =P28+P37 -> 3336.742 | R39: =R28+R37 -> 1223.1 | S39: =S28+S37 -> 984.2 | T39: =T28+T37 -> 1348 | U39: =U28+U37 -> 1046 | V39: =V28+V37 -> 1348 | W39: =W28+W37 -> 1248 | X39: =X28+X37 -> 1453 | Y39: =Y28+Y37 -> 923 | ... AJ39: =AJ28+AJ37 -> 1157.7818 | AK39: =L39-AJ39 -> 1078.3537
A40: PBT Growth | B40: Growth % | D40: =D39/C39-1 -> 0.12257338 | E40: =E39/D39-1 -> 0.084377611 | F40: =F39/E39-1 -> -0.084745763 | G40: =G39/F39-1 -> -0.09469697 | H40: =H39/G39-1 -> -0.028358903 | I40: =I39/H39-1 -> 0.16698565 | J40: =J39/I39-1 -> 0.01804018 | K40: =K39/J39-1 -> -0.21747886 | ... P40: =P39/O39-1 -> 0.069142232 | T40: =T39/R39-1 -> 0.10211757 | U40: =U39/S39-1 -> 0.062792115 | V40: =V39/T39-1 -> 0 | W40: =W39/U39-1 -> 0.19311663 | X40: =X39/V39-1 -> 0.077893175 | Y40: =Y39/W39-1 -> -0.26041667 | Z40: =Z39/X39-1 -> -0.15829319 | AA40: =AA39/Y39-1 -> 0.0054171181 | ... AK40: =AK39/AI39-1 -> 0.18761417
A42: Tax | B42: Income Tax Normalised | C42: -650.4 | D42: -718 | E42: -779 | F42: -730 | G42: -647 | H42: -566 | I42: -707 | J42: -763 | K42: -568 | L42: =L60 -> -664.13224 | M42: =M60 -> -760.49145 | N42: =N60 -> -865.25123 | O42: =O60 -> -926.92286 | P42: =P60 -> -991.01237 | R42: -368.3 | S42: =C42-R42 -> -282.1 | T42: -404 | U42: =D42-T42 -> -314 | V42: -404 | W42: =E42-V42 -> -375 | X42: -429.3 | Y42: =F42-X42 -> -300.7 | Z42: -372 | AA42: =G42-Z42 -> -275 | AB42: -279 | AC42: =H42-AB42 -> -287 | AD42: -380 | AE42: =I42-AD42 -> -327 | AF42: -397 | AG42: =J42-AF42 -> -366 | AH42: -294 | AI42: =K42-AH42 -> -274 | AJ42: =AJ60 -> -341.54564 | AK42: =AK60 -> -322.5866
A44: Minorities | B44: Minority Interest | C44: -59.9 | D44: -71 | E44: -66 | F44: -44 | G44: 0 | H44: -10 | I44: -11 | J44: -9 | K44: 10 | L44: =K44 -> 10 | M44: =L44 -> 10 | N44: =M44 -> 10 | O44: =N44 -> 10 | P44: =O44 -> 10 | R44: 33.8 | S44: =C44-R44 -> -93.7 | T44: -42 | U44: =D44-T44 -> -29 | V44: -42 | W44: =E44-V44 -> -24 | X44: -45 | Y44: =F44-X44 -> 1 | Z44: -1 | AA44: =G44-Z44 -> 1 | AB44: -3 | AC44: =H44-AB44 -> -7 | AD44: -4 | AE44: =I44-AD44 -> -7 | AF44: -8 | AG44: =J44-AF44 -> -1 | AH44: -2 | AI44: =K44-AH44 -> 12 | AJ44: -1 | AK44: =L44-AJ44 -> 11
A46: NPAT | B46: NPAT Normalised | C46: =C44+C42+C39 -> 1422.3 | D46: =D44+D42+D39 -> 1605 | E46: =E44+E42+E39 -> 1751 | F46: =F44+F42+F39 -> 1602 | G46: =G44+G42+G39 -> 1504 | H46: =H44+H42+H39 -> 1514 | I46: =I44+I42+I39 -> 1721 | J46: =J44+J42+J39 -> 1711 | ... P46: =P44+P42+P39 -> 2355.7296 | R46: =R44+R42+R39 -> 888.6 | S46: =S44+S42+S39 -> 608.4 | T46: =T44+T42+T39 -> 902 | U46: =U44+U42+U39 -> 703 | V46: =V44+V42+V39 -> 902 | W46: =W44+W42+W39 -> 849 | X46: =X44+X42+X39 -> 978.7 | Y46: =Y44+Y42+Y39 -> 623.3 | ... AK46: =AK44+AK42+AK39 -> 766.76707
A47: NPAT Growth | B47: Growth % | D47: =D46/C46-1 -> 0.12845391 | E47: =E46/D46-1 -> 0.090965732 | F47: =F46/E46-1 -> -0.085094232 | G47: =G46/F46-1 -> -0.061173533 | H47: =H46/G46-1 -> 0.0066489362 | I47: =I46/H46-1 -> 0.13672391 | J47: =J46/I46-1 -> -0.0058105752 | K47: =K46/J46-1 -> -0.19053185 | ... P47: =P46/O46-1 -> 0.068828523 | T47: =T46/R46-1 -> 0.015079901 | U47: =U46/S46-1 -> 0.15548981 | V47: =V46/T46-1 -> 0 | W47: =W46/U46-1 -> 0.20768137 | X47: =X46/V46-1 -> 0.085033259 | Y47: =Y46/W46-1 -> -0.26584217 | Z47: =Z46/X46-1 -> -0.13150097 | AA47: =AA46/Y46-1 -> 0.049253971 | ... AK47: =AK46/AI46-1 -> 0.18694592
B49: Significant Items | C49: =C46-C51 -> -111.2 | D49: =D46-D51 -> -119 | E49: =E46-E51 -> -941 | F49: =F46-F51 -> 437 | G49: =G46-G51 -> -570 | H49: =H46-H51 -> -6420 | I49: =I46-I51 -> 103 | J49: =J46-J51 -> 1603 | K49: =K46-K51 -> 422 | L49: =L31+L61 -> 0 | M49: =M31+M61 -> 0 | N49: =N31+N61 -> 0 | O49: =O31+O61 -> 0 | P49: =P31+P61 -> 0 | R49: =R46-R51 -> 102.9 | S49: =S46-S51 -> -139.4 | T49: =T46-T51 -> -124.14636 | U49: =U46-U51 -> 5.1463572 | V49: =V46-V51 -> -136.6 | W49: =W46-W51 -> -804.4 | X49: =X46-X51 -> 91.7 | Y49: =Y46-Y51 -> 345.3 | ... AI49: =AI46-AI51 -> 422 | AJ49: 0 | AK49: =L49-AJ49 -> 0
B51: NPAT Statutory | C51: 1533.5 | D51: 1724 | E51: 2692 | F51: 1165 | G51: 2074 | H51: 7934 | I51: 1618 | J51: 108 | K51: 963 | L51: =L46+L49 -> 1582.0033 | M51: =M46+M49 -> 1810.0858 | N51: =N46+N49 -> 2058.0526 | O51: =O46+O49 -> 2204.0295 | P51: =P46+P49 -> 2355.7296 | R51: 785.7 | S51: =C51-R51 -> 747.8 | T51: 1026.1464 | U51: =D51-T51 -> 697.85364 | V51: 1038.6 | W51: =E51-V51 -> 1653.4 | X51: 887 | Y51: =F51-X51 -> 278 | Z51: 1135 | AA51: =G51-Z51 -> 939 | AB51: 794.8731 | AC51: =H51-AB51 -> 7139.1269 | AD51: 845 | AE51: =I51-AD51 -> 773 | AF51: -781 | AG51: =J51-AF51 -> 889 | AH51: 739 | AI51: =K51-AH51 -> 224 | AJ51: =L51-AI51 -> 1358.0033 | AK51: =M51-AJ51 -> 452.08258
B52: Growth % | D52: =D51/C51-1 -> 0.12422563 | E52: =E51/D51-1 -> 0.56148492 | F52: =F51/E51-1 -> -0.56723626 | G52: =G51/F51-1 -> 0.78025751 | H52: =H51/G51-1 -> 2.8254581 | I52: =I51/H51-1 -> -0.79606756 | J52: =J51/I51-1 -> -0.93325093 | K52: =K51/J51-1 -> 7.9166667 | T52: =T51/R51-1 -> 0.3060282 | U52: =U51/S51-1 -> -0.066791063 | V52: =V51/T51-1 -> 0.012136322 | W52: =W51/U51-1 -> 1.3692647 | X52: =X51/V51-1 -> -0.14596572 | Y52: =Y51/W51-1 -> -0.83186162 | Z52: =Z51/X51-1 -> 0.27959414 | AA52: =AA51/Y51-1 -> 2.3776978 | ... AK52: =AK51/AI51-1 -> 1.0182258
A54: Shares | B54: Shares (Diluted) | C54: =C76 -> 1287.3 | D54: =D76 -> 1303.9 | E54: =E76 -> 1313.7 | F54: =F76 -> 1265.4 | G54: =G76 -> 1262.6 | H54: =H76 -> 1230.3 | I54: =I76 -> 1223.1 | J54: =J76 -> 1225.7 | ... P54: =P76 -> 1238.7 | R54: =R76 -> 1282.1 | S54: =S76 -> 1287.3 | T54: =T76 -> 1299.6 | U54: =U76 -> 1303.9 | V54: =V76 -> 1313.4 | W54: =W76 -> 1313.7 | X54: =X76 -> 1268 | Y54: =Y76 -> 1265.4 | ... AK54: =AK76 -> 1230.7
A56: EPS | B56: EPS Normalised | C56: =C46/C54 -> 1.1048707 | D56: =D46/D54 -> 1.2309226 | E56: =E46/E54 -> 1.3328766 | F56: =F46/F54 -> 1.2660028 | G56: =G46/G54 -> 1.1911928 | H56: =H46/H54 -> 1.2305942 | I56: =I46/I54 -> 1.4070804 | J56: =J46/J54 -> 1.395937 | ... P56: =P46/P54 -> 1.9017758 | R56: =R46/R54 -> 0.69308166 | S56: =S46/S54 -> 0.47261711 | T56: =T46/T54 -> 0.69405971 | U56: =U46/U54 -> 0.53915178 | V56: =V46/V54 -> 0.68676717 | W56: =W46/W54 -> 0.64626627 | X56: =X46/X54 -> 0.77184543 | Y56: =Y46/Y54 -> 0.49257152 | ... AK56: =AK46/AK54 -> 0.62303329
A57: EPS Growth | B57: Growth % | D57: =D56/C56-1 -> 0.11408752 | E57: =E56/D56-1 -> 0.082827295 | F57: =F56/E56-1 -> -0.050172509 | G57: =G56/F56-1 -> -0.059091548 | H57: =H56/G56-1 -> 0.033077255 | I57: =I56/H56-1 -> 0.14341544 | J57: =J56/I56-1 -> -0.0079194865 | K57: =K56/J56-1 -> -0.19250825 | ... P57: =P56/O56-1 -> 0.067102797 | T57: =T56/R56-1 -> 0.0014111581 | U57: =U56/S56-1 -> 0.14077923 | V57: =V56/T56-1 -> -0.010507081 | W57: =W56/U56-1 -> 0.19867225 | X57: =X56/V56-1 -> 0.12388224 | Y57: =Y56/W56-1 -> -0.23781955 | Z57: =Z56/X56-1 -> -0.12889039 | AA57: =AA56/Y56-1 -> 0.051580845 | ... AK57: =AK56/AI56-1 -> 0.18501703
B59: Tax Modelling
B60: Tax Normalised | C60: =C42 -> -650.4 | D60: =D42 -> -718 | E60: =E42 -> -779 | F60: =F42 -> -730 | G60: =G42 -> -647 | H60: =H42 -> -566 | I60: =I42 -> -707 | J60: =J42 -> -763 | K60: =K42 -> -568 | L60: =L70*-L65 -> -664.13224 | M60: =M70*-M65 -> -760.49145 | N60: =N70*-N65 -> -865.25123 | O60: =O70*-O65 -> -926.92286 | P60: =P70*-P65 -> -991.01237 | R60: =R42 -> -368.3 | S60: =S42 -> -282.1 | T60: =T42 -> -404 | U60: =U42 -> -314 | V60: =V42 -> -404 | W60: =W42 -> -375 | X60: =X42 -> -429.3 | Y60: =Y42 -> -300.7 | ... AI60: =AI42 -> -274 | AJ60: =AJ70*-AJ65 -> -341.54564 | AK60: =L60-AJ60 -> -322.5866
B61: Significant Items | C61: =C62-C60 -> 0 | D61: =D62-D60 -> 0 | E61: =E62-E60 -> 111 | F61: =F62-F60 -> 154 | G61: =G62-G60 -> 43 | H61: =H62-H60 -> 32 | I61: =I62-I60 -> 14 | J61: =J62-J60 -> 4 | K61: =K62-K60 -> 147 | L61: =L71*-L66 -> 0 | M61: =M71*-M66 -> 0 | N61: =N71*-N66 -> 0 | O61: =O71*-O66 -> 0 | P61: =P71*-P66 -> 0 | R61: =R62-R60 -> 0 | S61: =S62-S60 -> -107.9 | T61: =T62-T60 -> 0 | U61: =U62-U60 -> -76 | V61: =V62-V60 -> -8 | W61: =W62-W60 -> -15 | X61: =X62-X60 -> 39.3 | Y61: =Y62-Y60 -> -89.3 | ... AI61: =AI62-AI60 -> 147 | AJ61: =AJ71*-AJ66 -> 0 | AK61: =L61-AJ61 -> 0
B62: Tax Statutory | C62: -650.4 | D62: -718 | E62: -668 | F62: -576 | G62: -604 | H62: -534 | I62: -693 | J62: -759 | K62: -421 | L62: =L60+L61 -> -664.13224 | M62: =M60+M61 -> -760.49145 | N62: =N60+N61 -> -865.25123 | O62: =O60+O61 -> -926.92286 | P62: =P60+P61 -> -991.01237 | R62: -368.3 | S62: -390 | T62: -404 | U62: -390 | V62: -412 | W62: -390 | X62: -390 | Y62: -390 | Z62: -505 | AA62: =G62-Z62 -> -99 | AB62: -253 | AC62: =H62-AB62 -> -281 | AD62: -366 | AE62: =I62-AD62 -> -327 | AF62: -393 | AG62: =J62-AF62 -> -366 | AH62: -294 | AI62: =K62-AH62 -> -127 | AJ62: =AJ60+AJ61 -> -341.54564 | AK62: =L62-AJ62 -> -322.5866
B64: Tax Rates
B65: Tax Normalised | C65: =-C60/C70 -> 0.30497984 | D65: =-D60/D70 -> 0.29991646 | E65: =-E60/E70 -> 0.30007704 | F65: =-F60/F70 -> 0.30723906 | G65: =-G60/G70 -> 0.30079033 | H65: =-H60/H70 -> 0.2708134 | I65: =-I60/I70 -> 0.2898729 | J65: =-J60/J70 -> 0.30728957 | K65: =-K60/K70 -> 0.29233145 | L65: 0.297 | M65: 0.297 | N65: 0.297 | O65: 0.297 | P65: 0.297 | R65: =-R60/R70 -> 0.3011201 | S65: =-S60/S70 -> 0.28662873 | T65: =-T60/T70 -> 0.29970326 | U65: =-U60/U70 -> 0.3001912 | V65: =-V60/V70 -> 0.29970326 | W65: =-W60/W70 -> 0.30048077 | X65: =-X60/X70 -> 0.29545767 | Y65: =-Y60/Y70 -> 0.32578548 | ... AI65: =-AI60/AI70 -> 0.30176211 | AJ65: 0.295 | AK65: =-AK60/AK70 -> 0.29914731
B66: Significant items | C66: =-C61/C71 -> 0 | D66: =-D61/D71 -> 0 | E66: =-E61/E71 -> 0.10693642 | F66: =-F61/F71 -> 0.10709318 | G66: =-G61/G71 -> 0.078899083 | H66: =-H61/H71 -> 0.060037523 | I66: =-I61/I71 -> 0.017283951 | J66: =-J61/J71 -> 0.0016906171 | K66: =-K61/K71 -> 0.14848485 | L66: 0.297 | M66: 0.297 | N66: 0.297 | O66: 0.297 | P66: 0.297 | R66: =-R61/R71 -> 0 | S66: =-S61/S71 -> -0.14310345 | T66: =-T61/T71 -> #DIV/0! | U66: =-U61/U71 -> -0.10584958 | V66: =-V61/V71 -> 0.30769231 | W66: =-W61/W71 -> -0.014097744 | X66: =-X61/X71 -> 0.3 | Y66: =-Y61/Y71 -> -0.068324407 | ... AI66: =-AI61/AI71 -> 0.2112069 | AJ66: 0.3
B67: Tax Statutory | C67: =-C62/C72 -> 0.45867419 | D67: =-D62/D72 -> 0.42840095 | E67: =-E62/E72 -> 0.42875481 | F67: =-F62/F72 -> 0.61407249 | G67: =-G62/G72 -> 0.37608966 | H67: =-H62/H72 -> 0.34296724 | I67: =-I62/I72 -> 0.42541436 | J67: =-J62/J72 -> 6.4871795 | ... P67: =-P62/P72 -> 0.297 | R67: =-R62/R72 -> 0.31006904 | S67: =-S62/S72 -> 1.694179 | T67: =-T62/T72 -> 0.29970326 | U67: =-U62/U72 -> 1.1890244 | V67: =-V62/V72 -> 0.29985444 | W67: =-W62/W72 -> 2.1195652 | X67: =-X62/X72 -> 0.29500756 | Y67: =-Y62/Y72 -> -1.015625 | ... AK67: =-AK62/AK72 -> 0.29914731
B69: PBT
B70: PBT Normalised | C70: =C39 -> 2132.6 | D70: =D39 -> 2394 | E70: =E39 -> 2596 | F70: =F39 -> 2376 | G70: =G39 -> 2151 | H70: =H39 -> 2090 | I70: =I39 -> 2439 | J70: =J39 -> 2483 | ... P70: =P39 -> 3336.742 | R70: =R39 -> 1223.1 | S70: =S39 -> 984.2 | T70: =T39 -> 1348 | U70: =U39 -> 1046 | V70: =V39 -> 1348 | W70: =W39 -> 1248 | X70: =X39 -> 1453 | Y70: =Y39 -> 923 | ... AJ70: =AJ39 -> 1157.7818 | AK70: =L70-AJ70 -> 1078.3537
B71: Significant items | C71: =C72-C70 -> -714.6 | D71: =D72-D70 -> -718 | E71: =E72-E70 -> -1038 | F71: =F72-F70 -> -1438 | G71: =G72-G70 -> -545 | H71: =H72-H70 -> -533 | I71: =I72-I70 -> -810 | J71: =J72-J70 -> -2366 | K71: =K72-K70 -> -990 | L71: =L31 -> 0 | M71: =M31 -> 0 | N71: =N31 -> 0 | O71: =O31 -> 0 | P71: =P31 -> 0 | R71: =R72-R70 -> -35.3 | S71: =S72-S70 -> -754 | T71: =T72-T70 -> 0 | U71: =U72-U70 -> -718 | V71: =V72-V70 -> 26 | W71: =W72-W70 -> -1064 | X71: =X72-X70 -> -131 | Y71: =Y72-Y70 -> -1307 | ... AB71: =AB72-AB70 -> -144.8731 | AC71: =H71-AB71 -> -388.1269 | AD71: =AD72-AD70 -> -76 | AE71: =AE72-AE70 -> -734 | AF71: =AF72-AF70 -> -1714 | AG71: =AG72-AG70 -> -652 | AH71: =AH72-AH70 -> -294 | AI71: =AI72-AI70 -> -696 | AJ71: =AJ31 -> 0 | AK71: =L71-AJ71 -> 0
B72: PBT statutory | C72: 1418 | D72: 1676 | E72: 1558 | F72: 938 | G72: 1606 | H72: 1557 | I72: 1629 | J72: 117 | K72: 953 | L72: =L70+L71 -> 2236.1355 | M72: =M70+M71 -> 2560.5773 | N72: =N70+N71 -> 2913.3038 | O72: =O70+O71 -> 3120.9524 | P72: =P70+P71 -> 3336.742 | R72: 1187.8 | S72: =C72-R72 -> 230.2 | T72: 1348 | U72: =D72-T72 -> 328 | V72: 1374 | W72: =E72-V72 -> 184 | X72: 1322 | Y72: =F72-X72 -> -384 | Z72: 1680 | AA72: =G72-Z72 -> -74 | AB72: 932 | AC72: =H72-AB72 -> 625 | AD72: 1215 | AE72: =I72-AD72 -> 414 | AF72: -380 | AG72: =J72-AF72 -> 497 | AH72: 741 | AI72: =K72-AH72 -> 212 | AJ72: =AJ70+AJ71 -> 1157.7818 | AK72: =L72-AJ72 -> 1078.3537
A74: Shares EOP | B74: Period End Shares | C74: 1294.4 | D74: 1313.3 | E74: 1258.7 | F74: 1263.0919 | G74: 1267.6524 | H74: 1213.9 | I74: 1214.7 | J74: 1219.8 | K74: 1220.4 | L74: =K74+(K74-J74) -> 1221 | M74: =L74+(L74-K74) -> 1221.6 | N74: =M74+(M74-L74) -> 1222.2 | O74: =N74+(N74-M74) -> 1222.8 | P74: =O74+(O74-N74) -> 1223.4 | R74: 1288.2 | S74: =C74 -> 1294.4 | T74: 1304.8 | U74: =D74 -> 1313.3 | V74: 1261.2 | W74: =E74 -> 1258.7 | X74: 1261.2103 | Y74: =F74 -> 1263.0919 | Z74: 1263.9 | AA74: =G74 -> 1267.6524 | AB74: 1212 | AC74: =H74 -> 1213.9 | AD74: 1215.2 | AE74: =I74 -> 1214.7 | AF74: 1221.1 | AG74: =J74 -> 1219.8 | AH74: 1221.1 | AI74: =K74 -> 1220.4 | AJ74: =AVERAGE(K74:L74) -> 1220.7 | AK74: =L74 -> 1221
B75: Weighted Average Basic | C75: 1283.9 | D75: 1300.5 | E75: 1305.7 | F75: 1257.9 | G75: 1256.9 | H75: 1221.5 | I75: 1214.3 | J75: 1219.8 | K75: 1220.8 | L75: =K75+(K75-J75) -> 1221.8 | M75: =L75+(L75-K75) -> 1222.8 | N75: =M75+(M75-L75) -> 1223.8 | O75: =N75+(N75-M75) -> 1224.8 | P75: =O75+(O75-N75) -> 1225.8 | R75: 1282.1 | S75: =C75 -> 1283.9 | T75: =(T74+C74)*0.5 -> 1299.6 | U75: =D75 -> 1300.5 | V75: 1310 | W75: =E75 -> 1305.7 | X75: 1260 | Y75: =F75 -> 1257.9 | Z75: 1264.2 | AA75: =G75 -> 1256.9 | AB75: =H75 -> 1221.5 | AC75: =H75 -> 1221.5 | AD75: 1236.8 | AE75: =I75 -> 1214.3 | AF75: 1218.7 | AG75: =J75 -> 1219.8 | AH75: 1220.7 | AI75: =K75 -> 1220.8 | AJ75: =AVERAGE(K75:L75) -> 1221.3 | AK75: =L75 -> 1221.8
A76: Shares Diluted | B76: Weighted Average Diluted | C76: 1287.3 | D76: 1303.9 | E76: 1313.7 | F76: 1265.4 | G76: 1262.6 | H76: 1230.3 | I76: 1223.1 | J76: 1225.7 | K76: 1228.7 | L76: =K76+2 -> 1230.7 | M76: =L76+2 -> 1232.7 | N76: =M76+2 -> 1234.7 | O76: =N76+2 -> 1236.7 | P76: =O76+2 -> 1238.7 | R76: 1282.1 | S76: =C76 -> 1287.3 | T76: =T75 -> 1299.6 | U76: =D76 -> 1303.9 | V76: 1313.4 | W76: =E76 -> 1313.7 | X76: 1268 | Y76: =F76 -> 1265.4 | Z76: 1264.2 | AA76: =G76 -> 1262.6 | AB76: =H76 -> 1230.3 | AC76: =H76 -> 1230.3 | AD76: 1243.5 | AE76: =I76 -> 1223.1 | AF76: 1218.7 | AG76: =J76 -> 1225.7 | AH76: 1227.1 | AI76: =K76 -> 1228.7 | AJ76: =AVERAGE(K76:L76) -> 1229.7 | AK76: =L76 -> 1230.7
B78: Ordinary Dividend | C78: 0.84 | D78: 0.93 | E78: 1.02 | F78: 0.94 | G78: 1.08 | H78: 0.92 | I78: 1.04 | J78: 1.04 | K78: 0.84 | L78: =L81*L56 -> 0.95123296 | M78: =M81*M56 -> 1.0866095 | N78: =N81*N56 -> 1.2334647 | O78: =O81*O56 -> 1.3188177 | P78: =P81*P56 -> 1.4073141 | R78: 0.34 | S78: =C78-R78 -> 0.5 | T78: 0.43 | U78: =D78-T78 -> 0.5 | V78: 0.45 | W78: =E78-V78 -> 0.57 | X78: 0.46 | Y78: =F78-X78 -> 0.48 | Z78: 0.53 | AA78: =G78-Z78 -> 0.55 | AB78: 0.39 | AC78: =H78-AB78 -> 0.53 | AD78: 0.46 | AE78: =I78-AD78 -> 0.58 | AF78: 0.47 | AG78: =J78-AF78 -> 0.57 | AH78: 0.39 | AI78: =K78-AH78 -> 0.45 | AJ78: =AJ81*AJ56 -> 0.42722403 | AK78: =L78-AJ78 -> 0.52400893
B79: Special Dividend | C79: 0 | D79: 0.1 | E79: 0 | F79: 0 | G79: 0 | H79: 0 | I79: 0 | J79: 0.4 | K79: 0 | L79: 0 | M79: 0 | N79: 0 | O79: 0 | P79: 0 | R79: 0 | S79: =C79-R79 -> 0 | T79: 0 | U79: =D79-T79 -> 0.1 | V79: 0 | W79: =E79-V79 -> 0 | X79: 0 | Y79: =F79-X79 -> 0 | Z79: 0 | AA79: =G79-Z79 -> 0 | AB79: 0 | AC79: =H79-AB79 -> 0 | AD79: 0 | AE79: =I79-AD79 -> 0 | AF79: 0 | AG79: =J79-AF79 -> 0.4 | AH79: 0 | AI79: =K79-AH79 -> 0 | AJ79: 0 | AK79: =L79-AJ79 -> 0
A80: DPS | B80: Total Dividend Per Share | C80: =SUM(C78:C79) -> 0.84 | D80: =SUM(D78:D79) -> 1.03 | E80: =SUM(E78:E79) -> 1.02 | F80: =SUM(F78:F79) -> 0.94 | G80: =SUM(G78:G79) -> 1.08 | H80: =SUM(H78:H79) -> 0.92 | I80: =SUM(I78:I79) -> 1.04 | J80: =SUM(J78:J79) -> 1.44 | ... P80: =SUM(P78:P79) -> 1.4073141 | R80: =SUM(R78:R79) -> 0.34 | S80: =C80-R80 -> 0.5 | T80: =SUM(T78:T79) -> 0.43 | U80: =D80-T80 -> 0.6 | V80: =SUM(V78:V79) -> 0.45 | W80: =E80-V80 -> 0.57 | X80: =SUM(X78:X79) -> 0.46 | Y80: =F80-X80 -> 0.48 | Z80: =SUM(Z78:Z79) -> 0.53 | AA80: =G80-Z80 -> 0.55 | AB80: =SUM(AB78:AB79) -> 0.39 | AC80: =H80-AB80 -> 0.53 | AD80: =SUM(AD78:AD79) -> 0.46 | AE80: =I80-AD80 -> 0.58 | AF80: =SUM(AF78:AF79) -> 0.47 | AG80: =J80-AF80 -> 0.97 | AH80: =SUM(AH78:AH79) -> 0.39 | AI80: =K80-AH80 -> 0.45 | AJ80: =SUM(AJ78:AJ79) -> 0.42722403 | AK80: =L80-AJ80 -> 0.52400893
A81: Payout Ratio | B81: Payout Ratio % | C81: =(C80*C74)/C46 -> 0.76446319 | D81: =(D80*D74)/D46 -> 0.84280312 | E81: =(E80*E74)/E46 -> 0.7332233 | F81: =(F80*F74)/F46 -> 0.74114009 | G81: =(G80*G74)/G46 -> 0.91028232 | H81: =(H80*H74)/H46 -> 0.73764069 | I81: =(I80*I74)/I46 -> 0.734043 | J81: =(J80*J74)/J46 -> 1.0265996 | K81: =(K80*K74)/K46 -> 0.7401704 | L81: 0.74 | M81: 0.74 | N81: 0.74 | O81: 0.74 | P81: 0.74 | R81: =(R80*R74)/R46 -> 0.49289669 | S81: =(S80*S74)/S46 -> 1.0637738 | T81: =(T80*T74)/T46 -> 0.62202217 | U81: =(U80*U74)/U46 -> 1.1208819 | V81: =(V80*V74)/V46 -> 0.62920177 | W81: =(W80*W74)/W46 -> 0.8450636 | X81: =(X80*X74)/X46 -> 0.59278303 | Y81: =(Y80*Y74)/Y46 -> 0.97270035 | ... AI81: =(AI80*AI74)/AI46 -> 0.85012384 | AJ81: =AH81 -> 0.64442355 | AK81: =(AK80*AK74)/AK46 -> 0.8344319
B83: Franking | C83: 1 | D83: 1 | E83: 1 | F83: 1 | G83: 1 | H83: 1 | I83: 1 | J83: 1 | K83: 1 | L83: =K83 -> 1 | M83: =L83 -> 1 | N83: =M83 -> 1 | O83: =N83 -> 1 | P83: =O83 -> 1 | R83: 1 | S83: 1 | T83: 1 | U83: 1 | V83: 1 | W83: =E83 -> 1 | X83: 1 | Y83: =F83 -> 1 | Z83: 1 | AA83: =G83 -> 1 | AB83: 1 | AC83: =H83 -> 1 | AD83: 1 | AE83: =I83 -> 1 | AF83: 1 | AG83: =J83 -> 1 | AH83: 1 | AI83: =K83 -> 1
B84: Franking Rate | C84: 0.3 | D84: 0.3 | E84: 0.3 | F84: 0.3 | G84: 0.3 | H84: 0.3 | I84: 0.3 | J84: 0.3 | K84: 0.3 | L84: =K84 -> 0.3 | M84: =L84 -> 0.3 | N84: =M84 -> 0.3 | O84: =N84 -> 0.3 | P84: =O84 -> 0.3 | R84: 0.3 | S84: 0.3 | T84: 0.3 | U84: 0.3 | V84: 0.3 | W84: =E84 -> 0.3 | X84: 0.3 | Y84: =F84 -> 0.3 | Z84: 0.3 | AA84: =G84 -> 0.3 | AB84: 0.3 | AC84: =H84 -> 0.3 | AD84: 0.3 | AE84: =I84 -> 0.3 | AF84: 0.3 | AG84: =J84 -> 0.3 | AH84: 0.3 | AI84: =K84 -> 0.3
B85: Franking Credits | C85: 2577.2 | D85: 2610 | E85: 1953 | F85: 1546 | G85: 1740 | H85: 981 | I85: 1240 | J85: 1550 | K85: 1509

Sheet CF
B1: Woolworths Group (WOW.AX)
B2: A$M
C3: =Model!C3 -> FY17 | D3: =Model!D3 -> FY18 | E3: =Model!E3 -> FY19 | F3: =Model!F3 -> FY20 | G3: =Model!G3 -> FY21 | H3: =Model!H3 -> FY22 | I3: =Model!I3 -> FY23 | J3: =Model!J3 -> FY24 | K3: =Model!K3 -> FY25 | L3: FY26E | M3: FY27E | N3: FY28E | O3: FY29E | P3: FY30E | R3: =Model!R3 -> 1H17 | S3: =Model!S3 -> 2H17 | T3: =Model!T3 -> 1H18 | U3: =Model!U3 -> 2H18 | V3: =Model!V3 -> 1H19 | W3: =Model!W3 -> 2H19 | X3: =Model!X3 -> 1H20 | Y3: =Model!Y3 -> 2H20 | ... AI3: =Model!AI3 -> 2H25
B4: CFS
B5: Operating cash flow
A6: EBIT | B6: EBIT | C6: =PL!C28 -> 2326.2 | D6: =PL!D28 -> 2548 | E6: =PL!E28 -> 2722 | F6: =PL!F28 -> 3219 | G6: =PL!G28 -> 2764 | H6: =PL!H28 -> 2690 | I6: =PL!I28 -> 3116 | J6: =PL!J28 -> 3223 | ... P6: =PL!P28 -> 4228.3024 | R6: =PL!R28 -> 1336.6 | S6: =PL!S28 -> 1064.3 | T6: =PL!T28 -> 1430 | U6: =PL!U28 -> 1118 | V6: =PL!V28 -> 1419 | W6: =PL!W28 -> 1303 | X6: =PL!X28 -> 1893 | Y6: =PL!Y28 -> 1326 | ... AI6: =PL!AI28 -> 1303
A7: D&A | B7: Depreciation and Amortisation | C7: =-PL!C26 -> 1037.6 | D7: =-PL!D26 -> 1103 | E7: =-PL!E26 -> 1222 | F7: =-PL!F26 -> 1968 | G7: =-PL!G26 -> 2079 | H7: =-PL!H26 -> 2361 | I7: =-PL!I26 -> 2578 | J7: =-PL!J26 -> 2778 | ... P7: =-PL!P26 -> 3592.776 | R7: =-PL!R26 -> 524.8 | S7: =-PL!S26 -> 512.8 | T7: =-PL!T26 -> 563 | U7: =-PL!U26 -> 540 | V7: =-PL!V26 -> 611 | W7: =-PL!W26 -> 611 | X7: =-PL!X26 -> 1248 | Y7: =-PL!Y26 -> 720 | ... AI7: =-PL!AI26 -> 1448
A8: Chg WC | B8: Change in Net Working Capital | D8: =BS!D66 -> 38.9 | E8: =BS!E66 -> -25 | F8: =BS!F66 -> 412 | G8: =BS!G66 -> 2017 | H8: =BS!H66 -> -321 | I8: =BS!I66 -> 544 | J8: =BS!J66 -> -396 | K8: =BS!K66 -> 367 | ... P8: =BS!P66 -> 135.93926 | T8: =BS!T66 -> 5.8020809 | U8: =BS!U66 -> 33.097919 | V8: =BS!V66 -> 1077.2649 | W8: =BS!W66 -> -1102.2649 | X8: =BS!X66 -> 304.22963 | Y8: =BS!Y66 -> 107.77037 | Z8: =BS!Z66 -> -2038 | AA8: =BS!AA66 -> 4055 | ... AI8: =BS!AI66 -> 269
A9: Tax | B9: Tax Paid | C9: =PL!C42 -> -650.4 | D9: =PL!D42 -> -718 | E9: =PL!E42 -> -779 | F9: =PL!F42 -> -730 | G9: =PL!G42 -> -647 | H9: =PL!H42 -> -566 | I9: =PL!I42 -> -707 | J9: =PL!J42 -> -763 | ... P9: =PL!P42 -> -991.01237 | R9: =PL!R42 -> -368.3 | S9: =PL!S42 -> -282.1 | T9: =PL!T42 -> -404 | U9: =PL!U42 -> -314 | V9: =PL!V42 -> -404 | W9: =PL!W42 -> -375 | X9: =PL!X42 -> -429.3 | Y9: =PL!Y42 -> -300.7 | ... AI9: =PL!AI42 -> -274
A10: Net interest | B10: Net interest | C10: =PL!C37 -> -193.6 | D10: =PL!D37 -> -154 | E10: =PL!E37 -> -126 | F10: =PL!F37 -> -843 | G10: =PL!G37 -> -613 | H10: =PL!H37 -> -600 | I10: =PL!I37 -> -677 | J10: =PL!J37 -> -740 | ... P10: =PL!P37 -> -891.56037 | R10: =PL!R37 -> -113.5 | S10: =PL!S37 -> -80.1 | T10: =PL!T37 -> -82 | U10: =PL!U37 -> -72 | V10: =PL!V37 -> -71 | W10: =PL!W37 -> -55 | X10: =PL!X37 -> -440 | Y10: =PL!Y37 -> -403 | ... AI10: =PL!AI37 -> -395
A11: Other | B11: Other | C11: =C12-SUM(C6:C10) -> 602.2 | D11: =D12-SUM(D6:D10) -> 112.1 | E11: =E12-SUM(E6:E10) -> -66 | F11: =F12-SUM(F6:F10) -> 535 | G11: =G12-SUM(G6:G10) -> -976 | H11: =H12-SUM(H6:H10) -> -186 | I11: =I12-SUM(I6:I10) -> -100 | J11: =J12-SUM(J6:J10) -> 257 | K11: =K12-SUM(K6:K10) -> -145 | L11: 0 | M11: 0 | N11: 0 | O11: 0 | P11: 0 | R11: =R12-SUM(R6:R10) -> 816.1 | S11: =S12-SUM(S6:S10) -> -288.6 | T11: =T12-SUM(T6:T10) -> 462.19792 | U11: =U12-SUM(U6:U10) -> -350.09792 | V11: =V12-SUM(V6:V10) -> -617.2649 | W11: =W12-SUM(W6:W10) -> 551.2649 | X11: =X12-SUM(X6:X10) -> -514.92963 | Y11: =Y12-SUM(Y6:Y10) -> 1049.9296 | ... AI11: =AI12-SUM(AI6:AI10) -> 300
A12: OCF | B12: Net Operating Cash Flow | C12: =C20 -> 3122 | D12: =D20 -> 2930 | E12: =E20 -> 2948 | F12: =F20 -> 4561 | G12: =G20 -> 4624 | H12: =H20 -> 3378 | I12: =I20 -> 4754 | J12: =J20 -> 4359 | K12: =K20 -> 4550 | L12: =SUM(L6:L11) -> 4729.6666 | M12: =SUM(M6:M11) -> 5112.679 | N12: =SUM(N6:N11) -> 5496.2322 | O12: =SUM(O6:O11) -> 5779.7363 | P12: =SUM(P6:P11) -> 6074.4449 | R12: =R20 -> 2195.7 | S12: =C12-R12 -> 926.3 | T12: =T20 -> 1975 | U12: =D12-T12 -> 955 | V12: =V20 -> 2015 | W12: =E12-V12 -> 933 | X12: =X20 -> 2061 | Y12: =F12-X12 -> 2500 | Z12: =Z20 -> 2880 | AA12: =G12-Z12 -> 1744 | AB12: =AB20 -> 1731 | AC12: =H12-AB12 -> 1647 | AD12: =AD20 -> 2149 | AE12: =I12-AD12 -> 2605 | AF12: =AF20 -> 2582 | AG12: =J12-AF12 -> 1777 | AH12: =AH20 -> 1899 | AI12: =K12-AH12 -> 2651
B13: Reported Operating Cash Flow Items
B14: Receipts from customers | C14: 65498.9 | D14: 66899 | E14: 68998 | F14: 68898 | G14: 72688 | H14: 64538 | I14: 68275 | J14: 72155 | K14: 73510 | R14: 35014.2 | S14: =C14-R14 -> 30484.7 | T14: 35298 | U14: =D14-T14 -> 31601 | V14: 35909 | W14: =E14-V14 -> 33089 | X14: 35105 | Y14: =F14-X14 -> 33793 | Z14: 38659 | AA14: =G14-Z14 -> 34029 | AB14: 33811 | AC14: =H14-AB14 -> 30727 | AD14: 35210 | AE14: =I14-AD14 -> 33065 | AF14: 36841 | AG14: =J14-AF14 -> 35314 | AH14: 38157 | AI14: =K14-AH14 -> 35353
B15: Payments to suppliers | C15: -61474.8 | D15: -63124 | E15: -65140 | F15: -62831 | G15: -66526 | H15: -59721 | I15: -62259 | J15: -66292 | K15: -67336 | R15: -32256.6 | S15: =C15-R15 -> -29218.2 | T15: -32892 | U15: =D15-T15 -> -30232 | V15: -33422 | W15: =E15-V15 -> -31718 | X15: -32154 | Y15: =F15-X15 -> -30677 | Z15: -34886 | AA15: =G15-Z15 -> -31640 | AB15: -31235 | AC15: =H15-AB15 -> -28486 | AD15: -32335 | AE15: =I15-AD15 -> -29924 | AF15: -33435 | AG15: =J15-AF15 -> -32857 | AH15: -35138 | AI15: =K15-AH15 -> -32198
B16: Payments for interest component of leases | F16: -701 | G16: -687 | H16: -542 | I16: -542 | J16: -570 | K16: -597 | S16: =C16-R16 -> 0 | U16: =D16-T16 -> 0 | W16: =E16-V16 -> 0 | X16: -414 | Y16: =F16-X16 -> -287 | Z16: -407 | AA16: =G16-Z16 -> -280 | AB16: -322 | AC16: =H16-AB16 -> -220 | AD16: -320 | AE16: =I16-AD16 -> -222 | AF16: -333 | AG16: =J16-AF16 -> -237 | AH16: -356 | AI16: =K16-AH16 -> -241
B17: Net finance costs | C17: -234 | D17: -184 | E17: -166 | F17: -155 | G17: -113 | H17: -59 | I17: -133 | J17: -160 | K17: -226 | R17: -132.5 | S17: =C17-R17 -> -101.5 | T17: -95 | U17: =D17-T17 -> -89 | V17: -86 | W17: =E17-V17 -> -80 | X17: -91 | Y17: =F17-X17 -> -64 | Z17: -67 | AA17: =G17-Z17 -> -46 | AB17: -13 | AC17: =H17-AB17 -> -46 | AD17: -52 | AE17: =I17-AD17 -> -81 | AF17: -67 | AG17: =J17-AF17 -> -93 | AH17: -105 | AI17: =K17-AH17 -> -121
B18: Income tax paid | C18: -668.1 | D18: -661 | E18: -744 | F18: -650 | G18: -738 | H18: -838 | I18: -587 | J18: -774 | K18: -801 | R18: -429.4 | S18: =C18-R18 -> -238.7 | T18: -336 | U18: =D18-T18 -> -325 | V18: -386 | W18: =E18-V18 -> -358 | X18: -385 | Y18: =F18-X18 -> -265 | Z18: -419 | AA18: =G18-Z18 -> -319 | AB18: -510 | AC18: =H18-AB18 -> -328 | AD18: -354 | AE18: =I18-AD18 -> -233 | AF18: -424 | AG18: =J18-AF18 -> -350 | AH18: -659 | AI18: =K18-AH18 -> -142
B19: Other
B20: Total Operating Cash Flow | C20: =SUM(C13:C19) -> 3122 | D20: =SUM(D13:D19) -> 2930 | E20: =SUM(E13:E19) -> 2948 | F20: =SUM(F13:F19) -> 4561 | G20: =SUM(G13:G19) -> 4624 | H20: =SUM(H13:H19) -> 3378 | I20: =SUM(I13:I19) -> 4754 | J20: =SUM(J13:J19) -> 4359 | K20: =SUM(K13:K19) -> 4550 | L20: =L12 -> 4729.6666 | M20: =M12 -> 5112.679 | N20: =N12 -> 5496.2322 | O20: =O12 -> 5779.7363 | P20: =P12 -> 6074.4449 | R20: =SUM(R13:R19) -> 2195.7 | S20: =C20-R20 -> 926.3 | T20: =SUM(T13:T19) -> 1975 | U20: =D20-T20 -> 955 | V20: =SUM(V13:V19) -> 2015 | W20: =E20-V20 -> 933 | X20: =SUM(X13:X19) -> 2061 | Y20: =F20-X20 -> 2500 | Z20: =SUM(Z13:Z19) -> 2880 | AA20: =G20-Z20 -> 1744 | AB20: =SUM(AB13:AB19) -> 1731 | AC20: =H20-AB20 -> 1647 | AD20: =SUM(AD13:AD19) -> 2149 | AE20: =I20-AD20 -> 2605 | AF20: =SUM(AF13:AF19) -> 2582 | AG20: =J20-AF20 -> 1777 | AH20: =SUM(AH13:AH19) -> 1899 | AI20: =K20-AH20 -> 2651
A21: Proceeds PPE | B21: Proceeds from sale of PPE | C21: 279.8 | D21: 85 | E21: 177 | F21: 261 | G21: 389 | H21: 332 | I21: 361 | J21: 342 | K21: 298 | L21: =-Model!L365 -> 250 | M21: =-Model!M365 -> 250 | N21: =-Model!N365 -> 250 | O21: =-Model!O365 -> 250 | P21: =-Model!P365 -> 250 | R21: 167.2 | S21: =C21-R21 -> 112.6 | T21: 35 | U21: =D21-T21 -> 50 | V21: 115 | W21: =E21-V21 -> 62 | X21: 158 | Y21: =F21-X21 -> 103 | Z21: 298 | AA21: =G21-Z21 -> 91 | AB21: 228 | AC21: =H21-AB21 -> 104 | AD21: 134 | AE21: =I21-AD21 -> 227 | AF21: 124 | AG21: =J21-AF21 -> 218 | AH21: 142 | AI21: =K21-AH21 -> 156
A22: Capex | B22: Payments for PPE & Intangibles | C22: =-253.2-1633.6-23 -> -1909.8 | D22: =-1848 -> -1848 | E22: -1991 | F22: -2149 | G22: -2389 | H22: -2416 | I22: -2519 | J22: -2548 | K22: -2528 | L22: =-Model!L374 -> -2430 | M22: =-Model!M374 -> -2430 | N22: =-Model!N374 -> -2430 | O22: =-Model!O374 -> -2430 | P22: =-Model!P374 -> -2430 | R22: =-88.7-646.1-19.6 -> -754.4 | S22: =C22-R22 -> -1155.4 | T22: =-106-765-5 -> -876 | U22: =D22-T22 -> -972 | V22: -1002 | W22: =E22-V22 -> -989 | X22: -888 | Y22: =F22-X22 -> -1261 | Z22: -1005 | AA22: =G22-Z22 -> -1384 | AB22: -1144 | AC22: =H22-AB22 -> -1272 | AD22: -1274 | AE22: =I22-AD22 -> -1245 | AF22: -1315 | AG22: =J22-AF22 -> -1233 | AH22: -1218 | AI22: =K22-AH22 -> -1310
A23: Proceeds from business sales | B23: Proceeds from sale of businesses | C23: 200.7 | D23: 287 | E23: 1682 | F23: 34 | G23: 19 | H23: 53 | I23: 659 | J23: 466 | K23: 408 | R23: =2.8+197.9 -> 200.7 | S23: =C23-R23 -> 0 | T23: 272 | U23: =D23-T23 -> 15 | W23: =E23-V23 -> 1682 | X23: 18 | Y23: =F23-X23 -> 16 | Z23: 19 | AA23: =G23-Z23 -> 0 | AB23: 53 | AC23: =H23-AB23 -> 0 | AD23: 659 | AE23: =I23-AD23 -> 0 | AG23: =J23-AF23 -> 466 | AH23: 408 | AI23: =K23-AH23 -> 0
A24: Acquisitions | B24: Payments for purchase of businesses | C24: -5.6 | D24: -38 | E24: -80 | F24: -91 | G24: -209 | H24: -425 | I24: -373 | J24: -487 | K24: -84 | R24: -1.6 | S24: =C24-R24 -> -4 | T24: -38 | U24: =D24-T24 -> 0 | V24: -26 | W24: =E24-V24 -> -54 | X24: -47 | Y24: =F24-X24 -> -44 | Z24: -28 | AA24: =G24-Z24 -> -181 | AB24: -396 | AC24: =H24-AB24 -> -29 | AD24: -365 | AE24: =I24-AD24 -> -8 | AF24: -8 | AG24: =J24-AF24 -> -479 | AI24: =K24-AH24 -> -84
B25: Payments for purchase of reinvestment | G25: -35 | H25: -32 | I25: -30 | J25: -86 | K25: -12 | R25: 0 | S25: =C25-R25 -> 0 | U25: =D25-T25 -> 0 | W25: =E25-V25 -> 0 | Y25: =F25-X25 -> 0 | AA25: =G25-Z25 -> -35 | AB25: -23 | AC25: =H25-AB25 -> -9 | AD25: -13 | AE25: =I25-AD25 -> -17 | AF25: -2 | AG25: =J25-AF25 -> -84 | AI25: =K25-AH25 -> -12
B26: Advances to non-related parties | E26: -38 | F26: -4 | G26: 12 | H26: -20 | I26: 15 | K26: -8 | S26: =C26-R26 -> 0 | U26: =D26-T26 -> 0 | W26: =E26-V26 -> -38 | X26: -4 | Y26: =F26-X26 -> 0 | AA26: =G26-Z26 -> 12 | AB26: -17 | AC26: =H26-AB26 -> -3 | AE26: =I26-AD26 -> 15 | AG26: =J26-AF26 -> 0 | AH26: -10 | AI26: =K26-AH26 -> 2
B27: Dividends received | C27: 3.5 | D27: 4 | E27: 4 | F27: 4 | G27: 13 | H27: 51 | I27: 43 | J27: 36 | R27: 1.7 | S27: =C27-R27 -> 1.8 | T27: 2 | U27: =D27-T27 -> 2 | V27: 2 | W27: =E27-V27 -> 2 | X27: 2 | Y27: =F27-X27 -> 2 | Z27: 6 | AA27: =G27-Z27 -> 7 | AB27: 19 | AC27: =H27-AB27 -> 32 | AD27: 20 | AE27: =I27-AD27 -> 23 | AF27: 12 | AG27: =J27-AF27 -> 24 | AI27: =K27-AH27 -> 0
B28: Total Investing Cash Flow | C28: =SUM(C21:C27) -> -1431.4 | D28: =SUM(D21:D27) -> -1510 | E28: =SUM(E21:E27) -> -246 | F28: =SUM(F21:F27) -> -1945 | G28: =SUM(G21:G27) -> -2200 | H28: =SUM(H21:H27) -> -2457 | I28: =SUM(I21:I27) -> -1844 | J28: =SUM(J21:J27) -> -2277 | ... P28: =SUM(P21:P27) -> -2180 | R28: =SUM(R21:R27) -> -386.4 | S28: =C28-R28 -> -1045 | T28: =SUM(T21:T27) -> -605 | U28: =D28-T28 -> -905 | V28: =SUM(V21:V27) -> -911 | W28: =E28-V28 -> 665 | X28: =SUM(X21:X27) -> -761 | Y28: =F28-X28 -> -1184 | Z28: =SUM(Z21:Z27) -> -710 | AA28: =G28-Z28 -> -1490 | AB28: =SUM(AB21:AB27) -> -1280 | AC28: =H28-AB28 -> -1177 | AD28: =SUM(AD21:AD27) -> -839 | AE28: =I28-AD28 -> -1005 | AF28: =SUM(AF21:AF27) -> -1189 | AG28: =J28-AF28 -> -1088 | AH28: =SUM(AH21:AH27) -> -678 | AI28: =K28-AH28 -> -1248
A30: Lease Repayment | B30: Lease repayment | F30: -1066 | G30: -1158 | H30: -1019 | I30: -1067 | J30: -1138 | K30: -1223 | L30: =K30*1.05 -> -1284.15 | M30: =L30*1.05 -> -1348.3575 | N30: =M30*1.05 -> -1415.7754 | O30: =N30*1.05 -> -1486.5641 | P30: =O30*1.05 -> -1560.8924 | S30: =C30-R30 -> 0 | U30: =D30-T30 -> 0 | W30: =E30-V30 -> 0 | X30: -602 | Y30: =F30-X30 -> -464 | Z30: -618 | AA30: =G30-Z30 -> -540 | AB30: -554 | AC30: =H30-AB30 -> -465 | AD30: -580 | AE30: =I30-AD30 -> -487 | AF30: -652 | AG30: =J30-AF30 -> -486 | AH30: -674 | AI30: =K30-AH30 -> -549
B31: Proceeds from borrowings | C31: 184.1 | D31: 4 | E31: 665 | F31: 1500 | G31: 971 | H31: 2513 | I31: 351 | J31: 1215 | K31: 2686 | S31: =C31-R31 -> 184.1 | U31: =D31-T31 -> 4 | W31: =E31-V31 -> 665 | X31: 8 | Y31: =F31-X31 -> 1492 | AA31: =G31-Z31 -> 971 | AB31: 1988 | AC31: =H31-AB31 -> 525 | AD31: 775 | AE31: =I31-AD31 -> -424 | AF31: 784 | AG31: =J31-AF31 -> 431 | AH31: 2093 | AI31: =K31-AH31 -> 593
B32: Repayment of borrowings | C32: -1406.5 | D32: -284 | E32: -503 | F32: -745 | G32: -1525 | H32: -969 | I32: -952 | J32: -764 | K32: -2001 | R32: -1112.5 | S32: =C32-R32 -> -294 | T32: -165 | U32: =D32-T32 -> -119 | V32: -49 | W32: =E32-V32 -> -454 | X32: -86 | Y32: =F32-X32 -> -659 | Z32: -956 | AA32: =G32-Z32 -> -569 | AB32: -969 | AC32: =H32-AB32 -> 0 | AD32: -925 | AE32: =I32-AD32 -> -27 | AF32: -351 | AG32: =J32-AF32 -> -413 | AH32: -1043 | AI32: =K32-AH32 -> -958
A33: Dividends paid | B33: Dividends paid | C33: -540.9 | D33: -724 | E33: -1267 | F33: -1133 | G33: -1104 | H33: -1007 | I33: -1026 | J33: -1172 | K33: -1661 | L33: =-PL!L74*PL!L80 -> -1161.4554 | M33: =-PL!M74*PL!M80 -> -1327.4022 | N33: =-PL!N74*PL!N80 -> -1507.5406 | O33: =-PL!O74*PL!O80 -> -1612.6503 | P33: =-PL!P74*PL!P80 -> -1721.708 | R33: -265.6 | S33: =C33-R33 -> -275.3 | T33: -390 | U33: =D33-T33 -> -334 | V33: -674 | W33: =E33-V33 -> -593 | X33: -623 | Y33: =F33-X33 -> -510 | Z33: -522 | AA33: =G33-Z33 -> -582 | AB33: -603 | AC33: =H33-AB33 -> -404 | AD33: -549 | AE33: =I33-AD33 -> -477 | AF33: -598 | AG33: =J33-AF33 -> -574 | AH33: -1185 | AI33: =K33-AH33 -> -476
B34: Dividends paid to non-controlling interests | C34: -21.5 | D34: -56 | E34: -51 | F34: -66 | G34: -50 | H34: -5 | I34: -5 | J34: -16 | K34: -3 | R34: -4.7 | S34: =C34-R34 -> -16.8 | T34: -26 | U34: =D34-T34 -> -30 | V34: -29 | W34: =E34-V34 -> -22 | X34: -25 | Y34: =F34-X34 -> -41 | Z34: -2 | AA34: =G34-Z34 -> -48 | AB34: -5 | AC34: =H34-AB34 -> 0 | AD34: -5 | AE34: =I34-AD34 -> 0 | AF34: -15 | AG34: =J34-AF34 -> -1 | AH34: -3 | AI34: =K34-AH34 -> 0
B35: Payments for purchase of additional equity | K35: -422 | S35: =C35-R35 -> 0 | U35: =D35-T35 -> 0 | W35: =E35-V35 -> 0 | Y35: =F35-X35 -> 0 | AA35: =G35-Z35 -> 0 | AC35: =H35-AB35 -> 0 | AE35: =I35-AD35 -> 0 | AG35: =J35-AF35 -> 0 | AH35: -420 | AI35: =K35-AH35 -> -2
B36: Payments for shares held in trust | E36: -60 | F36: -102 | G36: -177 | H36: -125 | I36: -110 | J36: -44 | K36: -25 | S36: =C36-R36 -> 0 | U36: =D36-T36 -> 0 | W36: =E36-V36 -> -60 | X36: -1 | Y36: =F36-X36 -> -101 | Z36: -1 | AA36: =G36-Z36 -> -176 | AB36: -25 | AC36: =H36-AB36 -> -100 | AD36: -1 | AE36: =I36-AD36 -> -109 | AF36: -1 | AG36: =J36-AF36 -> -43 | AH36: -1 | AI36: =K36-AH36 -> -24
B37: Other | C37: 55.5 | E37: -1701 | H37: =1712-437-2000 -> -725 | R37: 55.5 | AB37: =1712-437-2000 -> -725
B38: Total Financing Cash Flow | C38: =SUM(C31:C37) -> -1729.3 | D38: =SUM(D31:D37) -> -1060 | E38: =SUM(E31:E37) -> -2917 | F38: =SUM(F30:F37) -> -1612 | G38: =SUM(G30:G37) -> -3043 | H38: =SUM(H30:H37) -> -1337 | I38: =SUM(I30:I37) -> -2809 | J38: =SUM(J30:J37) -> -1919 | K38: =SUM(K30:K37) -> -2649 | L38: =SUM(L30:L37) -> -2445.6054 | M38: =SUM(M30:M37) -> -2675.7597 | ... P38: =SUM(P30:P37) -> -3282.6004 | R38: =SUM(R31:R37) -> -1327.3 | S38: =C38-R38 -> -402 | T38: =SUM(T31:T37) -> -581 | U38: =D38-T38 -> -479 | V38: =SUM(V31:V37) -> -752 | W38: =E38-V38 -> -2165 | X38: =SUM(X30:X37) -> -1329 | Y38: =F38-X38 -> -283 | Z38: =SUM(Z30:Z37) -> -2099 | AA38: =G38-Z38 -> -944 | AB38: =SUM(AB30:AB37) -> -893 | AC38: =H38-AB38 -> -444 | AD38: =SUM(AD30:AD37) -> -1285 | AE38: =I38-AD38 -> -1524 | AF38: =SUM(AF30:AF37) -> -833 | AG38: =J38-AF38 -> -1086 | AH38: =SUM(AH30:AH37) -> -1233 | AI38: =K38-AH38 -> -1416
B40: Cash at Beginning | C40: 956 | D40: =C43 -> 917 | E40: =D43 -> 1277 | F40: =E43 -> 1066 | G40: =F43 -> 2068 | H40: =G43 -> 1446 | I40: =H43 -> 1032 | J40: =I43 -> 1135 | K40: =J43 -> 1298 | ... P40: =O43 -> 2529.4185 | R40: 956 | S40: =C40-R40 -> 0 | T40: =C43 -> 917 | U40: =D40-T40 -> 0 | V40: =D43 -> 1277 | W40: =E40-V40 -> 0 | X40: =E43 -> 1066 | Y40: =F40-X40 -> 0 | Z40: =F43 -> 2068 | AA40: =G40-Z40 -> 0 | AB40: =G43 -> 1446 | AC40: =H40-AB40 -> 0 | AD40: =H43 -> 1032 | AE40: =I40-AD40 -> 0 | AF40: =I43 -> 1135 | AG40: =J40-AF40 -> 0 | AH40: =J43 -> 1298 | AI40: =K40-AH40 -> 0
A41: Net Chg Cash | B41: Net Increase in Cash | C41: =C38+C28+C20 -> -38.7 | D41: =D38+D28+D20 -> 360 | E41: =E38+E28+E20 -> -215 | F41: =F38+F28+F20 -> 1004 | G41: =G38+G28+G20 -> -619 | H41: =H38+H28+H20 -> -416 | I41: =I38+I28+I20 -> 101 | J41: =J38+J28+J20 -> 163 | ... P41: =P38+P28+P20 -> 611.84453 | R41: =R38+R28+R20 -> 482 | S41: =C41-R41 -> -520.7 | T41: =T38+T28+T20 -> 789 | U41: =D41-T41 -> -429 | V41: =V38+V28+V20 -> 352 | W41: =E41-V41 -> -567 | X41: =X38+X28+X20 -> -29 | Y41: =F41-X41 -> 1033 | Z41: =Z38+Z28+Z20 -> 71 | AA41: =G41-Z41 -> -690 | AB41: =AB38+AB28+AB20 -> -442 | AC41: =H41-AB41 -> 26 | AD41: =AD38+AD28+AD20 -> 25 | AE41: =I41-AD41 -> 76 | AF41: =AF38+AF28+AF20 -> 560 | AG41: =J41-AF41 -> -397 | AH41: =AH38+AH28+AH20 -> -12 | AI41: =K41-AH41 -> -13
B42: FX Impact | C42: -0.6 | D42: 0 | E42: 4 | F42: -2 | G42: -3 | H42: 2 | I42: 2 | J42: 0 | K42: 2 | L42: 0 | M42: 0 | N42: 0 | O42: 0 | P42: 0 | R42: 0.2 | S42: =C42-R42 -> -0.8 | T42: -3 | U42: =D42-T42 -> 3 | V42: 4 | W42: =E42-V42 -> 0 | X42: 0 | Y42: =F42-X42 -> -2 | Z42: -4 | AA42: =G42-Z42 -> 1 | AB42: 2 | AC42: =H42-AB42 -> 0 | AD42: 2 | AE42: =I42-AD42 -> 0 | AF42: 1 | AG42: =J42-AF42 -> -1 | AH42: 3 | AI42: =K42-AH42 -> -1
B43: Cash at Ending | C43: 917 | D43: =D40+D41+D42 -> 1277 | E43: =E40+E41+E42 -> 1066 | F43: =F40+F41+F42 -> 2068 | G43: =G40+G41+G42 -> 1446 | H43: =H40+H41+H42 -> 1032 | I43: =I40+I41+I42 -> 1135 | J43: =J40+J41+J42 -> 1298 | K43: =K40+K41+K42 -> 1275 | ... P43: =P40+P41+P42 -> 3141.2631 | R43: =R40+R41+R42 -> 1438.2 | S43: =C43-R43 -> -521.2 | T43: =T40+T41+T42 -> 1703 | U43: =D43-T43 -> -426 | V43: =V40+V41+V42 -> 1633 | W43: =E43-V43 -> -567 | X43: =X40+X41+X42 -> 1037 | Y43: =F43-X43 -> 1031 | Z43: =Z40+Z41+Z42 -> 2135 | AA43: =G43-Z43 -> -689 | AB43: =AB40+AB41+AB42 -> 1006 | AC43: =H43-AB43 -> 26 | AD43: =AD40+AD41+AD42 -> 1059 | AE43: =I43-AD43 -> 76 | AF43: =AF40+AF41+AF42 -> 1696 | AG43: =J43-AF43 -> -398 | AH43: =AH40+AH41+AH42 -> 1289 | AI43: =K43-AH43 -> -14
A45: Net capex | B45: Net Capex | C45: =C21+C22 -> -1630 | D45: =D21+D22 -> -1763 | E45: =E21+E22 -> -1814 | F45: =F21+F22 -> -1888 | G45: =G21+G22 -> -2000 | H45: =H21+H22 -> -2084 | I45: =I21+I22 -> -2158 | J45: =J21+J22 -> -2206 | ... P45: =P21+P22 -> -2180
A47: Other financing | B47: Other financing cashflows | C47: =C38-C30-C33-C31-C32 -> 34 | D47: =D38-D30-D33-D31-D32 -> -56 | E47: =E38-E30-E33-E31-E32 -> -1812 | F47: =F38-F30-F33-F31-F32 -> -168 | G47: =G38-G30-G33-G31-G32 -> -227 | H47: =H38-H30-H33-H31-H32 -> -855 | I47: =I38-I30-I33-I31-I32 -> -115 | J47: =J38-J30-J33-J31-J32 -> -60 | ... P47: =P38-P30-P33-P31-P32 -> -2.2737368e-13

Sheet BS
B1: Woolworths Group (WOW.AX)
B2: A$M
C3: =Model!C3 -> FY17 | D3: =Model!D3 -> FY18 | E3: =Model!E3 -> FY19 | F3: =Model!F3 -> FY20 | G3: =Model!G3 -> FY21 | H3: =Model!H3 -> FY22 | I3: =Model!I3 -> FY23 | J3: =Model!J3 -> FY24 | K3: =Model!K3 -> FY25 | L3: FY26E | M3: FY27E | N3: FY28E | O3: FY29E | P3: FY30E | R3: =Model!R3 -> 1H17 | S3: =Model!S3 -> 2H17 | T3: =Model!T3 -> 1H18 | U3: =Model!U3 -> 2H18 | V3: =Model!V3 -> 1H19 | W3: =Model!W3 -> 2H19 | X3: =Model!X3 -> 1H20 | Y3: =Model!Y3 -> 2H20 | ... AI3: =Model!AI3 -> 2H25
B4: BS
B5: Assets
A6: Cash | B6: Cash Deposits | C6: 909.4 | D6: 1273 | E6: 1066 | F6: 2068 | G6: 1009 | H6: 1032 | I6: 1135 | J6: 1298 | K6: 1275 | L6: =CF!L43 -> 1379.0612 | M6: =CF!M43 -> 1635.9805 | N6: =CF!N43 -> 2028.8967 | O6: =CF!O43 -> 2529.4185 | P6: =CF!P43 -> 3141.2631 | R6: 1421.3 | T6: 1688 | V6: 1618 | X6: 1037 | Z6: 2135 | AB6: 1006 | AD6: 1059 | AF6: 1696 | AH6: 1289
A7: TR | B7: Current Receivables | C7: 744.7 | D7: 801 | E7: 682 | F7: 740 | G7: 649 | H7: 1044 | I7: 1016 | J7: 1062 | K7: 1034 | L7: =L53 -> 1065.0715 | M7: =M53 -> 1107.6623 | N7: =N53 -> 1153.0636 | O7: =O53 -> 1200.1374 | P7: =P53 -> 1248.9433 | R7: 737.3 | T7: 837 | V7: 821 | X7: 811 | Z7: 853 | AB7: 1077 | AD7: 1211 | AF7: 996 | AH7: 1085
A8: Inventory | B8: Inventory | C8: 4080.4 | D8: 4233 | E8: 4280 | F8: 4434 | G8: 3132 | H8: 3593 | I8: 3698 | J8: 4187 | K8: 4169 | L8: =L57 -> 4294.2775 | M8: =M57 -> 4466.0003 | N8: =N57 -> 4649.0544 | O8: =O57 -> 4838.8517 | P8: =P57 -> 5035.6332 | R8: 4449.2 | T8: 4558 | V8: 4752 | X8: 4621 | Z8: 4808 | AB8: 3554 | AD8: 3944 | AF8: 3999 | AH8: 4470
A9: Other CA | B9: Other Current Assets | C9: 1259.7 | D9: =53+821 -> 874 | E9: =45+225 -> 270 | F9: =534+16+333 -> 883 | G9: =19+18 -> 37 | H9: =106+48 -> 154 | I9: =225+51 -> 276 | J9: =23+221 -> 244 | K9: =52+261 -> 313 | L9: =K9 -> 313 | M9: =L9 -> 313 | N9: =M9 -> 313 | O9: =N9 -> 313 | P9: =O9 -> 313 | R9: 1392.9 | T9: =741+16 -> 757 | V9: =843+54 -> 897 | X9: =294+198 -> 492 | Z9: =157+9 -> 166 | AB9: =34+48 -> 82 | AD9: =55+42 -> 97 | AF9: =251+22 -> 273 | AH9: =308+91+61 -> 460
B10: Assets held for sale or distribution | G10: 10959 | H10: 287 | I10: 250 | J10: 200 | K10: 200 | L10: =K10 -> 200 | M10: =L10 -> 200 | N10: =M10 -> 200 | O10: =N10 -> 200 | P10: =O10 -> 200 | Z10: 178 | AB10: 166 | AD10: 209 | AF10: 352 | AH10: 80
A11: CA | B11: Total Current Assets | C11: =SUM(C6:C10) -> 6994.2 | D11: =SUM(D6:D10) -> 7181 | E11: =SUM(E6:E10) -> 6298 | F11: =SUM(F6:F10) -> 8125 | G11: =SUM(G6:G10) -> 15786 | H11: =SUM(H6:H10) -> 6110 | I11: =SUM(I6:I10) -> 6375 | J11: =SUM(J6:J10) -> 6991 | ... P11: =SUM(P6:P10) -> 9938.8396 | R11: =SUM(R6:R10) -> 8000.7 | T11: =SUM(T6:T10) -> 7840 | V11: =SUM(V6:V10) -> 8088 | X11: =SUM(X6:X10) -> 6961 | Z11: =SUM(Z6:Z10) -> 8140 | AB11: =SUM(AB6:AB10) -> 5885 | AD11: =SUM(AD6:AD10) -> 6520 | AF11: =SUM(AF6:AF10) -> 7316 | AH11: =SUM(AH6:AH10) -> 7384
B13: Non Current Recievables | C13: 72.1 | D13: 93 | E13: 145 | F13: 154 | G13: 133 | H13: 159 | I13: 132 | J13: 129 | K13: 146 | L13: =K13 -> 146 | M13: =L13 -> 146 | N13: =M13 -> 146 | O13: =N13 -> 146 | P13: =O13 -> 146 | R13: 132.5 | T13: 73 | V13: 107 | X13: 204 | Z13: 162 | AB13: 151 | AD13: 147 | AF13: 126 | AH13: 145
A14: Fixed Assets | B14: Fixed Assets | C14: 8437.5 | D14: 9026 | E14: 9519 | F14: 8742 | G14: 7477 | H14: 8231 | I14: 8881 | J14: 9678 | K14: 10172 | L14: =K14-CF!L22-CF!L21+PL!L25 -> 10552.43 | M14: =L14-CF!M22-CF!M21+PL!M25 -> 10873.593 | N14: =M14-CF!N22-CF!N21+PL!N25 -> 11133.753 | O14: =N14-CF!O22-CF!O21+PL!O25 -> 11331.139 | P14: =O14-CF!P22-CF!P21+PL!P25 -> 11463.94 | R14: 7888.2 | T14: 8635 | V14: 9335 | X14: 9583 | Z14: 8960 | AB14: 7822 | AD14: 8705 | AF14: 9136 | AH14: 9953
A15: ROU | B15: Right of Use Assets | F15: 12062 | G15: 9553 | H15: 9995 | I15: 9467 | J15: 9604 | K15: 9162 | L15: =K15+PL!L24+L74 -> 9190.45 | M15: =L15+PL!M24+M74 -> 9233.3225 | N15: =M15+PL!N24+N74 -> 9292.1186 | O15: =N15+PL!O24+O74 -> 9368.4614 | P15: =O15+PL!P24+P74 -> 9464.1044 | X15: 11993 | Z15: 12759 | AB15: 10178 | AD15: 9696 | AF15: 9432 | AH15: 9505
B16: Goodwill | C16: 4216.4 | D16: 4155 | E16: 4217 | F16: 4196 | G16: 2881 | H16: 3198 | I16: 3504 | J16: 2466 | K16: 2468 | L16: =K16 -> 2468 | M16: =L16 -> 2468 | N16: =M16 -> 2468 | O16: =N16 -> 2468 | P16: =O16 -> 2468 | R16: 3637.3 | T16: =C16 -> 4216.4 | V16: =D16 -> 4155 | X16: =E16 -> 4217 | Z16: =7740-Z17 -> 4219 | AB16: =5309-AB17 -> 3519 | AD16: =5708-AD17 -> 3628 | AF16: =4198-AF17 -> 2009 | AH16: =J16 -> 2466
A17: Intangibles | B17: Intangible Assets | C17: 2316.4 | D17: =6465-D16 -> 2310 | E17: =6526-E16 -> 2309 | F17: =7717-F16 -> 3521 | G17: =4671-G16 -> 1790 | H17: =5278-3198 -> 2080 | I17: 2189 | J17: 2407 | K17: 2241 | L17: =K17-CF!L23-CF!L24-CF!L25 -> 2241 | M17: =L17-CF!M23-CF!M24-CF!M25 -> 2241 | N17: =M17-CF!N23-CF!N24-CF!N25 -> 2241 | O17: =N17-CF!O23-CF!O24-CF!O25 -> 2241 | P17: =O17-CF!P23-CF!P24-CF!P25 -> 2241 | R17: 2314.9 | T17: =6426-T16 -> 2209.6 | V17: =6522-V16 -> 2367 | X17: =6540-X16 -> 2323 | Z17: =F17 -> 3521 | AB17: =G17 -> 1790 | AD17: =H17 -> 2080 | AF17: =I17 -> 2189 | AH17: =4827-AH16 -> 2361
B18: Deferred Tax Asset | F18: 1327 | G18: 1371 | H18: 1337 | I18: 1123 | J18: 1647 | K18: 1853 | L18: =K18 -> 1853 | M18: =L18 -> 1853 | N18: =M18 -> 1853 | O18: =N18 -> 1853 | P18: =O18 -> 1853 | Z18: 1358 | AB18: 1341 | AD18: 1437 | AF18: 1586 | AH18: 1609
B19: Equity Accounted Investments | G19: 30 | H19: 1691 | I19: 1478 | J19: 78 | K19: 77 | L19: =K19 -> 77 | M19: =L19 -> 77 | N19: =M19 -> 77 | O19: =N19 -> 77 | P19: =O19 -> 77 | Z19: 72 | AB19: 1683 | AD19: =1102 -> 1102 | AF19: 69 | AH19: 79
A20: Other NCA | B20: Other Non Current Assets | C20: 879.2 | D20: =522+271 -> 793 | E20: =692+311 -> 1003 | F20: =168+177 -> 345 | G20: =105+110 -> 215 | H20: =95+377 -> 472 | I20: =359+140 -> 499 | J20: =600+336 -> 936 | K20: =383+336 -> 719 | L20: =K20 -> 719 | M20: =L20 -> 719 | N20: =M20 -> 719 | O20: =N20 -> 719 | P20: =O20 -> 719 | R20: 1681.9 | T20: =366+443 -> 809 | V20: =622+215 -> 837 | X20: =368+1002+61 -> 1431 | Z20: =117+176 -> 293 | AB20: =372+82 -> 454 | AD20: =368+89 -> 457 | AF20: =999+345 -> 1344 | AH20: =272+314 -> 586
A21: NCA | B21: Total Non-Current Assets | C21: =SUM(C13:C20) -> 15921.6 | D21: =SUM(D13:D20) -> 16377 | E21: =SUM(E13:E20) -> 17193 | F21: =SUM(F13:F20) -> 30347 | G21: =SUM(G13:G20) -> 23450 | H21: =SUM(H13:H20) -> 27163 | I21: =SUM(I13:I20) -> 27273 | J21: =SUM(J13:J20) -> 26945 | ... P21: =SUM(P13:P20) -> 28432.044 | R21: =SUM(R13:R20) -> 15654.8 | T21: =SUM(T13:T20) -> 15943 | V21: =SUM(V13:V20) -> 16801 | X21: =SUM(X13:X20) -> 29751 | Z21: =SUM(Z13:Z20) -> 31344 | AB21: =SUM(AB13:AB20) -> 26938 | AD21: =SUM(AD13:AD20) -> 27252 | AF21: =SUM(AF13:AF20) -> 25891 | AH21: =SUM(AH13:AH20) -> 26704
B23: Total Assets | C23: =C21+C11 -> 22915.8 | D23: =D21+D11 -> 23558 | E23: =E21+E11 -> 23491 | F23: =F21+F11 -> 38472 | G23: =G21+G11 -> 39236 | H23: =H21+H11 -> 33273 | I23: =I21+I11 -> 33648 | J23: =J21+J11 -> 33936 | ... P23: =P21+P11 -> 38370.884 | R23: =R21+R11 -> 23655.5 | T23: =T21+T11 -> 23783 | V23: =V21+V11 -> 24889 | X23: =X21+X11 -> 36712 | Z23: =Z21+Z11 -> 39484 | AB23: =AB21+AB11 -> 32823 | AD23: =AD21+AD11 -> 33772 | AF23: =AF21+AF11 -> 33207 | AH23: =AH21+AH11 -> 34088
B25: Liabilities
A26: TP | B26: Trade Payables | C26: 5068.2 | D26: 5316 | E26: 5219 | F26: 5843 | G26: 6467 | H26: 7002 | I26: 7623 | J26: 7762 | K26: 8083 | L26: =L61 -> 8325.8924 | M26: =M61 -> 8658.8344 | N26: =N61 -> 9013.746 | O26: =O61 -> 9381.7313 | P26: =P61 -> 9763.2581 | R26: 5772.4881 | T26: =C26/SUM(C26:C27)*7525 -> 5705.2979 | V26: =D26/D30*V30 -> 4884.7351 | X26: =E26/SUM(E26:E27)*7149 -> 5588.7704 | Z26: 8530 | AB26: 7153 | AD26: 7535 | AF26: 8096 | AH26: 8115
B27: Other Current Creditors | C27: 1616.5 | D27: 1644 | E27: 1457 | F27: 1665 | R27: 1619.8119 | T27: =7525-T26 -> 1819.7021 | V27: 2841.2649 | X27: =7149-X26 -> 1560.2296
B28: Current lease liabilities | F28: 1560 | G28: 1495 | H28: 1572 | I28: 1637 | J28: 1599 | K28: 1699 | L28: =K28 -> 1699 | M28: =L28 -> 1699 | N28: =M28 -> 1699 | O28: =N28 -> 1699 | P28: =O28 -> 1699 | X28: 1676 | Z28: 1852 | AB28: 1561 | AD28: 1478 | AF28: 1629 | AH28: 1563
B29: Bank Overdraft
A30: C Borrowings | B30: Current Debt | C30: 253.5 | D30: 604 | E30: 274 | F30: 2027 | G30: 119 | H30: 354 | I30: 466 | J30: 712 | K30: 244 | L30: =K30 -> 244 | M30: =L30 -> 244 | N30: =M30 -> 244 | O30: =N30 -> 244 | P30: =O30 -> 244 | R30: 589 | T30: 88 | V30: 555 | X30: 1419 | Z30: 721 | AB30: 409 | AD30: 525 | AF30: 596 | AH30: 423
B31: Provisions | C31: 1470.6 | D31: 1451 | E31: 1528 | F31: 1881 | G31: 1518 | H31: 1680 | I31: 1640 | J31: 1706 | K31: 1791 | L31: =K31 -> 1791 | M31: =L31 -> 1791 | N31: =M31 -> 1791 | O31: =N31 -> 1791 | P31: =O31 -> 1791 | Z31: 1818 | AB31: 1713 | AD31: 1686 | AF31: 1709 | AH31: 1695
B32: Other Current Liabilities | C32: 415.4 | D32: =110+50+21 -> 181 | E32: =84+58+0 -> 142 | F32: =131+84 -> 215 | G32: =252+165+7870+5231 -> 13518 | H32: =12+21+109 -> 142 | I32: =21+269+230 -> 520 | J32: =10+303+689+38 -> 1040 | K32: =11+127+342 -> 480 | L32: =K32 -> 480 | M32: =L32 -> 480 | N32: =M32 -> 480 | O32: =N32 -> 480 | P32: =O32 -> 480 | R32: 1977.5 | T32: =1475+72+21+175 -> 1743 | V32: =117+60+1352+207 -> 1736 | X32: =1748+101+59 -> 1908 | Z32: =256+126 -> 382 | AB32: =32+172 -> 204 | AD32: =101+163+11+15 -> 290 | AF32: =13+263+243 -> 519 | AH32: =13+8+287 -> 308
A33: CL | B33: Total Current liabilities | C33: =SUM(C26:C32) -> 8824.2 | D33: =SUM(D26:D32) -> 9196 | E33: =SUM(E26:E32) -> 8620 | F33: =SUM(F26:F32) -> 13191 | G33: =SUM(G26:G32) -> 23117 | H33: =SUM(H26:H32) -> 10750 | I33: =SUM(I26:I32) -> 11886 | J33: =SUM(J26:J32) -> 12819 | ... P33: =SUM(P26:P32) -> 13977.258 | R33: =SUM(R26:R32) -> 9958.8 | T33: =SUM(T26:T32) -> 9356 | V33: =SUM(V26:V32) -> 10017 | X33: =SUM(X26:X32) -> 12152 | Z33: =SUM(Z26:Z32) -> 13303 | AB33: =SUM(AB26:AB32) -> 11040 | AD33: =SUM(AD26:AD32) -> 11514 | AF33: =SUM(AF26:AF32) -> 12549 | AH33: =SUM(AH26:AH32) -> 12104
A35: NC Borrowings | B35: Non Current Debt | C35: 2777 | D35: 2199 | E35: 2855 | F35: 1904 | G35: 2753 | H35: 3938 | I35: 3289 | J35: 3866 | K35: 5267 | L35: =K35+CF!L31+CF!L32 -> 5267 | M35: =L35+CF!M31+CF!M32 -> 5267 | N35: =M35+CF!N31+CF!N32 -> 5267 | O35: =N35+CF!O31+CF!O32 -> 5267 | P35: =O35+CF!P31+CF!P32 -> 5267 | R35: 2671.6 | T35: 2709 | V35: 2316 | X35: 1602 | Z35: 1905 | AB35: 3509 | AD35: 3640 | AF35: 3636 | AH35: 5258
A36: NC Lease | B36: Non-Current Lease Liabilities | F36: 13168 | G36: 10521 | H36: 10899 | I36: 10343 | J36: 10545 | K36: 10175 | L36: =K36+CF!L30+L74 -> 10190.85 | M36: =L36+CF!M30+M74 -> 10220.493 | N36: =M36+CF!N30+N74 -> 10265.397 | O36: =N36+CF!O30+O74 -> 10327.154 | P36: =O36+CF!P30+P74 -> 10407.481 | X36: 12707 | Z36: 13534 | AB36: 10992 | AD36: 10624 | AF36: 10206 | AH36: 10378
B37: Provisions | C37: 1010.9 | D37: 942 | E37: 986 | F37: 918 | G37: 804 | H37: 846 | I37: 857 | J37: 894 | K37: 963 | L37: =K37 -> 963 | M37: =L37 -> 963 | N37: =M37 -> 963 | O37: =N37 -> 963 | P37: =O37 -> 963 | Z37: 824 | AB37: 837 | AD37: 832 | AF37: 852 | AH37: 954
B38: Other Non-Current Liabilities | C38: 427.6 | D38: =61+311 -> 372 | E38: =24+337 -> 361 | F38: =3+204+52 -> 259 | G38: =251+0+51 -> 302 | H38: =690+46 -> 736 | I38: =669+39 -> 708 | J38: =83+33+126 -> 242 | K38: =46+61+58 -> 165 | L38: =K38 -> 165 | M38: =L38 -> 165 | N38: =M38 -> 165 | O38: =N38 -> 165 | P38: =O38 -> 165 | R38: 1663.3 | T38: =316+937+105 -> 1358 | V38: =39+932+321 -> 1292 | X38: =11+753+83 -> 847 | Z38: =185+51 -> 236 | AB38: =698+55 -> 753 | AD38: =741+47 -> 788 | AF38: =33+647+53 -> 733 | AH38: =78+62+28 -> 168
A39: NCL | B39: Total Non-Current liabilities | C39: =SUM(C35:C38) -> 4215.5 | D39: =SUM(D35:D38) -> 3513 | E39: =SUM(E35:E38) -> 4202 | F39: =SUM(F35:F38) -> 16249 | G39: =SUM(G35:G38) -> 14380 | H39: =SUM(H35:H38) -> 16419 | I39: =SUM(I35:I38) -> 15197 | J39: =SUM(J35:J38) -> 15547 | ... P39: =SUM(P35:P38) -> 16802.481 | R39: =SUM(R35:R38) -> 4334.9 | T39: =SUM(T35:T38) -> 4067 | V39: =SUM(V35:V38) -> 3608 | X39: =SUM(X35:X38) -> 15156 | Z39: =SUM(Z35:Z38) -> 16499 | AB39: =SUM(AB35:AB38) -> 16091 | AD39: =SUM(AD35:AD38) -> 15884 | AF39: =SUM(AF35:AF38) -> 15427 | AH39: =SUM(AH35:AH38) -> 16758
B41: Total Liabilities | C41: =C39+C33 -> 13039.7 | D41: =D39+D33 -> 12709 | E41: =E39+E33 -> 12822 | F41: =F39+F33 -> 29440 | G41: =G39+G33 -> 37497 | H41: =H39+H33 -> 27169 | I41: =I39+I33 -> 27083 | J41: =J39+J33 -> 28366 | ... P41: =P39+P33 -> 30779.74 | R41: =R39+R33 -> 14293.7 | T41: =T39+T33 -> 13423 | V41: =V39+V33 -> 13625 | X41: =X39+X33 -> 27308 | Z41: =Z39+Z33 -> 29802 | AB41: =AB39+AB33 -> 27131 | AD41: =AD39+AD33 -> 27398 | AF41: =AF39+AF33 -> 27976 | AH41: =AH39+AH33 -> 28862
A43: Contributed Equity | B43: Contributed equity | C43: 5615 | D43: 6055 | E43: 5828 | F43: 6022 | G43: 5253 | H43: 5207 | I43: 5406 | J43: 5604 | K43: 5627 | L43: =K43+CF!L35 -> 5627 | M43: =L43+CF!M35 -> 5627 | N43: =M43+CF!N35 -> 5627 | O43: =N43+CF!O35 -> 5627 | P43: =O43+CF!P35 -> 5627 | R43: 5495.5 | T43: 5881 | V43: 6169 | X43: 6049 | Z43: 6226 | AB43: 5230 | AD43: 5428 | AF43: 5645 | AH43: 5649
A44: Reserves | B44: Reserves | C44: 113.8 | D44: 353 | E44: 490 | F44: 391 | G44: -6989 | H44: -7400 | I44: -7567 | J44: -7609 | K44: -7479 | L44: =K44 -> -7479 | M44: =L44 -> -7479 | N44: =M44 -> -7479 | O44: =N44 -> -7479 | P44: =O44 -> -7479 | R44: 241.4 | T44: -11 | V44: 447 | X44: 399 | Z44: 271 | AB44: -7438 | AD44: -7560 | AF44: -7646 | AH44: -7487
A45: Retained Profits | B45: Retained Profits | C45: 3797.2 | D45: 4073 | E45: 3968 | F45: 2329 | G45: 3115 | H45: 8173 | I45: 8586 | J45: 7413 | K45: 6712 | L45: =K45+PL!L51+CF!L33 -> 7132.5478 | M45: =L45+PL!M51+CF!M33 -> 7615.2315 | N45: =M45+PL!N51+CF!N33 -> 8165.7435 | O45: =N45+PL!O51+CF!O33 -> 8757.1227 | P45: =O45+PL!P51+CF!P33 -> 9391.1443 | R45: 3425.3 | T45: 4121 | V45: 4267 | X45: 2625 | Z45: 2858 | AB45: 7774 | AD45: 8375 | AF45: 7098 | AH45: 6967
B47: Shareholders Equity | C47: =SUM(C43:C45) -> 9526 | D47: =SUM(D43:D45) -> 10481 | E47: =SUM(E43:E45) -> 10286 | F47: =SUM(F43:F45) -> 8742 | G47: =SUM(G43:G45) -> 1379 | H47: =SUM(H43:H45) -> 5980 | I47: =SUM(I43:I45) -> 6425 | J47: =SUM(J43:J45) -> 5408 | ... P47: =SUM(P43:P45) -> 7539.1443 | R47: =SUM(R43:R45) -> 9162.2 | T47: =SUM(T43:T45) -> 9991 | V47: =SUM(V43:V45) -> 10883 | X47: =SUM(X43:X45) -> 9073 | Z47: =SUM(Z43:Z45) -> 9355 | AB47: =SUM(AB43:AB45) -> 5566 | AD47: =SUM(AD43:AD45) -> 6243 | AF47: =SUM(AF43:AF45) -> 5097 | AH47: =SUM(AH43:AH45) -> 5129
A48: Minorities | B48: Minority Interests | C48: 350.1 | D48: 368 | E48: 383 | F48: 290 | G48: 360 | H48: 124 | I48: 140 | J48: 162 | K48: 102 | L48: =K48-PL!L44 -> 92 | M48: =L48-PL!M44 -> 82 | N48: =M48-PL!N44 -> 72 | O48: =N48-PL!O44 -> 62 | P48: =O48-PL!P44 -> 52 | R48: 199.6 | T48: 369 | V48: 381 | X48: 331 | Z48: 327 | AB48: 126 | AD48: 131 | AF48: 134 | AH48: 97
A49: Total Equity | B49: Total Equity | C49: =SUM(C47:C48) -> 9876.1 | D49: =SUM(D47:D48) -> 10849 | E49: =SUM(E47:E48) -> 10669 | F49: =SUM(F47:F48) -> 9032 | G49: =SUM(G47:G48) -> 1739 | H49: =SUM(H47:H48) -> 6104 | I49: =SUM(I47:I48) -> 6565 | J49: =SUM(J47:J48) -> 5570 | ... P49: =SUM(P47:P48) -> 7591.1443 | R49: =SUM(R47:R48) -> 9361.8 | T49: =SUM(T47:T48) -> 10360 | V49: =SUM(V47:V48) -> 11264 | X49: =SUM(X47:X48) -> 9404 | Z49: =SUM(Z47:Z48) -> 9682 | AB49: =SUM(AB47:AB48) -> 5692 | AD49: =SUM(AD47:AD48) -> 6374 | AF49: =SUM(AF47:AF48) -> 5231 | AH49: =SUM(AH47:AH48) -> 5226
B50: Check | C50: =C23-C41-C49 -> 0 | D50: =D23-D41-D49 -> 0 | E50: =E23-E41-E49 -> 0 | F50: =F23-F41-F49 -> 0 | G50: =G23-G41-G49 -> 0 | H50: =H23-H41-H49 -> 0 | I50: =I23-I41-I49 -> 0 | J50: =J23-J41-J49 -> 0 | ... P50: =P23-P41-P49 -> 0 | R50: =R23-R41-R49 -> 0 | T50: =T23-T41-T49 -> 0 | V50: =V23-V41-V49 -> 0 | X50: =X23-X41-X49 -> 0 | Z50: =Z23-Z41-Z49 -> 0 | AB50: =AB23-AB41-AB49 -> 0 | AD50: =AD23-AD41-AD49 -> 0 | AF50: =AF23-AF41-AF49 -> 0 | AH50: =AH23-AH41-AH49 -> 0
B52: Balance Sheet Metrics
B53: Receivables | C53: =C7 -> 744.7 | D53: =D7 -> 801 | E53: =E7 -> 682 | F53: =F7 -> 740 | G53: =G7 -> 649 | H53: =H7 -> 1044 | I53: =I7 -> 1016 | J53: =J7 -> 1062 | K53: =K7 -> 1034 | L53: =L54*Model!L15 -> 1065.0715 | M53: =M54*Model!M15 -> 1107.6623 | N53: =N54*Model!N15 -> 1153.0636 | O53: =O54*Model!O15 -> 1200.1374 | P53: =P54*Model!P15 -> 1248.9433
B54: % of Sales | C54: =(C53)/Model!C15 -> 0.013579256 | D54: =(D53)/Model!D15 -> 0.01400962 | E54: =(E53)/Model!E15 -> 0.011369699 | F54: =(F53)/Model!F15 -> 0.011621516 | G54: =(G53)/Model!G15 -> 0.0096409525 | H54: =(H53)/Model!H15 -> 0.017157225 | I54: =(I53)/Model!I15 -> 0.015802408 | J54: =(J53)/Model!J15 -> 0.015635582 | K54: =(K53)/Model!K15 -> 0.014968803 | L54: =K54 -> 0.014968803 | M54: =L54 -> 0.014968803 | N54: =M54 -> 0.014968803 | O54: =N54 -> 0.014968803 | P54: =O54 -> 0.014968803 | R54: =(R7+R13)/Model!R15 -> 0.029932722 | T54: =(T7+T13)/Model!T15 -> 0.030427659 | V54: =(V7+V13)/Model!V15 -> 0.030339687 | X54: =(X7+X13)/Model!X15 -> 0.031317495 | Z54: =(Z7+Z13)/Model!Z15 -> 0.028284799 | AB54: =(AB7+AB13)/Model!AB15 -> 0.03850254 | AD54: =(AD7+AD13)/Model!AD15 -> 0.040941843 | AF54: =(AF7+AF13)/Model!AF15 -> 0.032394976 | AH54: =(AH7+AH13)/Model!AH15 -> 0.034233231
B55: Receivables Days | C55: =C53/Model!C15*365 -> 4.9564286 | D55: =D53/Model!D15*365 -> 5.1135111 | E55: =E53/Model!E15*365 -> 4.14994 | F55: =F53/Model!F15*365 -> 4.2418532 | G55: =G53/Model!G15*365 -> 3.5189477 | H55: =H53/Model!H15*365 -> 6.2623872 | I55: =I53/Model!I15*365 -> 5.7678788 | J55: =J53/Model!J15*365 -> 5.7069874 | K55: =K53/Model!K15*365 -> 5.4636131 | L55: =(L7+L13)/Model!L15*365 -> 6.2125652 | M55: =(M7+M13)/Model!M15*365 -> 6.1837671 | N55: =(N7+N13)/Model!N15*365 -> 6.1554114 | O55: =(O7+O13)/Model!O15*365 -> 6.1282766 | P55: =(P7+P13)/Model!P15*365 -> 6.102303 | R55: =(R7+R13)/Model!R15*365 -> 10.925444 | T55: =(T7+T13)/Model!T15*365 -> 11.106096 | V55: =(V7+V13)/Model!V15*365 -> 11.073986 | X55: =(X7+X13)/Model!X15*365 -> 11.430886 | Z55: =(Z7+Z13)/Model!Z15*365 -> 10.323952 | AB55: =(AB7+AB13)/Model!AB15*365 -> 14.053427 | AD55: =(AD7+AD13)/Model!AD15*365 -> 14.943773 | AF55: =(AF7+AF13)/Model!AF15*365 -> 11.824166 | AH55: =(AH7+AH13)/Model!AH15*365 -> 12.495129
B57: Inventory | C57: =C8 -> 4080.4 | D57: =D8 -> 4233 | E57: =E8 -> 4280 | F57: =F8 -> 4434 | G57: =G8 -> 3132 | H57: =H8 -> 3593 | I57: =I8 -> 3698 | J57: =J8 -> 4187 | K57: =K8 -> 4169 | L57: =L58*Model!L15 -> 4294.2775 | M57: =M58*Model!M15 -> 4466.0003 | N57: =N58*Model!N15 -> 4649.0544 | O57: =O58*Model!O15 -> 4838.8517 | P57: =P58*Model!P15 -> 5035.6332
B58: % of Sales | C58: =C57/Model!C15 -> 0.074404187 | D58: =D57/Model!D15 -> 0.074035855 | E58: =E57/Model!E15 -> 0.071352361 | F58: =F57/Model!F15 -> 0.069634865 | G58: =G57/Model!G15 -> 0.046526138 | H58: =H57/Model!H15 -> 0.059047807 | I58: =I57/Model!I15 -> 0.057517031 | J58: =J57/Model!J15 -> 0.061644239 | K58: =K57/Model!K15 -> 0.060352939 | L58: =K58 -> 0.060352939 | M58: =L58 -> 0.060352939 | N58: =M58 -> 0.060352939 | O58: =N58 -> 0.060352939 | P58: =O58 -> 0.060352939 | R58: =R8/Model!R15 -> 0.15311183 | T58: =T8/Model!T15 -> 0.15240579 | V58: =V8/Model!V15 -> 0.15536012 | X58: =X8/Model!X15 -> 0.14257945 | Z58: =Z8/Model!Z15 -> 0.13398356 | AB58: =AB8/Model!AB15 -> 0.11143162 | AD58: =AD8/Model!AD15 -> 0.11890621 | AF58: =AF8/Model!AF15 -> 0.11546124 | AH58: =AH8/Model!AH15 -> 0.12440857
B59: Inventory Days | C59: =C57/PL!C5*365 -> 27.157528 | D59: =D57/PL!D5*365 -> 27.023087 | E59: =E57/PL!E5*365 -> 26.043612 | F59: =F57/PL!F5*365 -> 25.416726 | G59: =G57/PL!G5*365 -> 16.98204 | H59: =H57/PL!H5*365 -> 21.55245 | I59: =I57/PL!I5*365 -> 20.993716 | J59: =J57/PL!J5*365 -> 22.500147 | ... P59: =P57/PL!P5*365 -> 22.028823 | R59: =R8/PL!R5*365 -> 55.885817 | T59: =T8/PL!T5*365 -> 55.628114 | V59: =V8/PL!V5*365 -> 56.706444 | X59: =X8/PL!X5*365 -> 52.0415 | Z59: =Z8/PL!Z5*365 -> 48.903999 | AB59: =AB8/PL!AB5*365 -> 40.67254 | AD59: =AD8/PL!AD5*365 -> 43.400766 | AF59: =AF8/PL!AF5*365 -> 42.143352 | AH59: =AH8/PL!AH5*365 -> 45.409129
B61: Payables | C61: =C26 -> 5068.2 | D61: =D26 -> 5316 | E61: =E26 -> 5219 | F61: =F26 -> 5843 | G61: =G26 -> 6467 | H61: =H26 -> 7002 | I61: =I26 -> 7623 | J61: =J26 -> 7762 | K61: =K26 -> 8083 | L61: =L62*Model!L15 -> 8325.8924 | M61: =M62*Model!M15 -> 8658.8344 | N61: =N62*Model!N15 -> 9013.746 | O61: =O62*Model!O15 -> 9381.7313 | P61: =P62*Model!P15 -> 9763.2581
B62: % of Sales | C62: =C26/Model!C15 -> 0.092416258 | D62: =D26/Model!D15 -> 0.0929777 | E62: =E26/Model!E15 -> 0.087006535 | F62: =F26/Model!F15 -> 0.091762858 | G62: =G26/Model!G15 -> 0.096067858 | H62: =H26/Model!H15 -> 0.11507173 | I62: =I26/Model!I15 -> 0.11856472 | J62: =J26/Model!J15 -> 0.11427814 | K62: =K26/Model!K15 -> 0.11701435 | L62: =K62 -> 0.11701435 | M62: =L62 -> 0.11701435 | N62: =M62 -> 0.11701435 | O62: =N62 -> 0.11701435 | P62: =O62 -> 0.11701435 | R62: =R26/Model!R15 -> 0.19865059 | T62: =T26/Model!T15 -> 0.19076798 | V62: =V26/Model!V15 -> 0.15969971 | X62: =X26/Model!X15 -> 0.17243969 | Z62: =Z26/Model!Z15 -> 0.23770378 | AB62: =AB26/Model!AB15 -> 0.22427416 | AD62: =AD26/Model!AD15 -> 0.22716995 | AF62: =AF26/Model!AF15 -> 0.23375198 | AH62: =AH26/Model!AH15 -> 0.22585583
B63: Payables Days | C63: =C61/PL!C5*365 -> 33.731934 | D63: =D61/PL!D5*365 -> 33.936861 | E63: =E61/PL!E5*365 -> 31.757385 | F63: =F61/PL!F5*365 -> 33.493443 | G63: =G61/PL!G5*365 -> 35.064768 | H63: =H61/PL!H5*365 -> 42.001183 | I63: =I61/PL!I5*365 -> 43.276122 | J63: =J61/PL!J5*365 -> 41.711522 | ... P63: =P61/PL!P5*365 -> 42.710236 | R63: =R26/PL!R5*365 -> 72.507464 | T63: =T26/PL!T5*365 -> 69.630312 | V63: =V26/PL!V5*365 -> 58.290395 | X63: =X26/PL!X5*365 -> 62.940487 | Z63: =Z26/PL!Z5*365 -> 86.761878 | AB63: =AB26/PL!AB5*365 -> 81.860068 | AD63: =AD26/PL!AD5*365 -> 82.917031 | AF63: =AF26/PL!AF5*365 -> 85.319475 | AH63: =AH26/PL!AH5*365 -> 82.437378
B65: Net Working Capital | C65: =C53+C57-C61 -> -243.1 | D65: =D53+D57-D61 -> -282 | E65: =E53+E57-E61 -> -257 | F65: =F53+F57-F61 -> -669 | G65: =G53+G57-G61 -> -2686 | H65: =H53+H57-H61 -> -2365 | I65: =I53+I57-I61 -> -2909 | J65: =J53+J57-J61 -> -2513 | ... P65: =P53+P57-P61 -> -3478.6816 | R65: =R7+R13+R8-R26 -> -453.48808 | T65: =T7+T13+T8-T26 -> -237.29792 | V65: =V7+V13+V8-V26 -> 795.2649 | X65: =X7+X13+X8-X26 -> 47.229629 | Z65: =Z7+Z13+Z8-Z26 -> -2707 | AB65: =AB7+AB13+AB8-AB26 -> -2371 | AD65: =AD7+AD13+AD8-AD26 -> -2233 | AF65: =AF7+AF13+AF8-AF26 -> -2975 | AH65: =AH7+AH13+AH8-AH26 -> -2415
A66: Chg in NWC | B66: Change in Net Working Capital | D66: =-(D65-C65) -> 38.9 | E66: =-(E65-D65) -> -25 | F66: =-(F65-E65) -> 412 | G66: =-(G65-F65) -> 2017 | H66: =-(H65-G65) -> -321 | I66: =-(I65-H65) -> 544 | J66: =-(J65-I65) -> -396 | K66: =-(K65-J65) -> 367 | ... P66: =-(P65-O65) -> 135.93926 | T66: =T65-C65 -> 5.8020809 | U66: =D66-T66 -> 33.097919 | V66: =V65-D65 -> 1077.2649 | W66: =E66-V66 -> -1102.2649 | X66: =X65-E65 -> 304.22963 | Y66: =F66-X66 -> 107.77037 | Z66: =Z65-F65 -> -2038 | AA66: =G66-Z66 -> 4055 | AB66: =AB65-G65 -> 315 | AC66: =H66-AB66 -> -636 | AD66: =AD65-H65 -> 132 | AE66: =I66-AD66 -> 412 | AF66: =AF65-I65 -> -66 | AG66: =J66-AF66 -> -330 | AH66: =AH65-J65 -> 98 | AI66: =K66-AH66 -> 269
B67: Change YoY % | D67: =D65/C65-1 -> 0.16001645 | E67: =E65/D65-1 -> -0.088652482 | F67: =F65/E65-1 -> 1.6031128 | G67: =G65/F65-1 -> 3.0149477 | H67: =H65/G65-1 -> -0.11950856 | I67: =I65/H65-1 -> 0.23002114 | J67: =J65/I65-1 -> -0.13612925 | K67: =K65/J65-1 -> 0.14604059 | ... P67: =P65/O65-1 -> 0.040666986
B69: Cash | C69: =C6 -> 909.4 | D69: =D6 -> 1273 | E69: =E6 -> 1066 | F69: =F6 -> 2068 | G69: =G6 -> 1009 | H69: =H6 -> 1032 | I69: =I6 -> 1135 | J69: =J6 -> 1298 | ... P69: =P6 -> 3141.2631 | R69: =R6 -> 1421.3 | T69: =T6 -> 1688 | V69: =V6 -> 1618 | X69: =X6 -> 1037 | Z69: =Z6 -> 2135 | AB69: =AB6 -> 1006 | AD69: =AD6 -> 1059 | AF69: =AF6 -> 1696 | AH69: =AH6 -> 1289
B70: Borrowings | C70: =C30+C35 -> 3030.5 | D70: =D30+D35 -> 2803 | E70: =E30+E35 -> 3129 | F70: =F30+F35 -> 3931 | G70: =G30+G35 -> 2872 | H70: =H30+H35 -> 4292 | I70: =I30+I35 -> 3755 | J70: =J30+J35 -> 4578 | ... P70: =P30+P35 -> 5511 | R70: =R30+R35 -> 3260.6 | T70: =T30+T35 -> 2797 | V70: =V30+V35 -> 2871 | X70: =X30+X35 -> 3021 | Z70: =Z30+Z35 -> 2626 | AB70: =AB30+AB35 -> 3918 | AD70: =AD30+AD35 -> 4165 | AF70: =AF30+AF35 -> 4232 | AH70: =AH30+AH35 -> 5681
A71: Net Debt | B71: Net Debt | C71: =C70-C69 -> 2121.1 | D71: =D70-D69 -> 1530 | E71: =E70-E69 -> 2063 | F71: =F70-F69 -> 1863 | G71: =G70-G69 -> 1863 | H71: =H70-H69 -> 3260 | I71: =I70-I69 -> 2620 | J71: =J70-J69 -> 3280 | ... P71: =P70-P69 -> 2369.7369 | R71: =R70-R69 -> 1839.3 | T71: =T70-T69 -> 1109 | V71: =V70-V69 -> 1253 | X71: =X70-X69 -> 1984 | Z71: =Z70-Z69 -> 491 | AB71: =AB70-AB69 -> 2912 | AD71: =AD70-AD69 -> 3106 | AF71: =AF70-AF69 -> 2536 | AH71: =AH70-AH69 -> 4392
A72: Chg in Net Debt | B72: Change in Net Debt | D72: =D71-C71 -> -591.1 | E72: =E71-D71 -> 533 | F72: =F71-E71 -> -200 | G72: =G71-F71 -> 0 | H72: =H71-G71 -> 1397 | I72: =I71-H71 -> -640 | J72: =J71-I71 -> 660 | K72: =K71-J71 -> 956 | ... P72: =P71-O71 -> -611.84453 | T72: =T71-C71 -> -1012.1 | U72: =D72-T72 -> 421 | V72: =V71-D71 -> -277 | W72: =E72-V72 -> 810 | X72: =X71-E71 -> -79 | Y72: =F72-X72 -> -121 | Z72: =Z71-F71 -> -1372 | AA72: =G72-Z72 -> 1372 | AB72: =AB71-G71 -> 1049 | AC72: =H72-AB72 -> 348 | AD72: =AD71-H71 -> -154 | AE72: =I72-AD72 -> -486 | AF72: =AF71-I71 -> -84 | AG72: =J72-AF72 -> 744 | AH72: =AH71-J71 -> 1112 | AI72: =K72-AH72 -> -156
B74: Lease Modelling Adjustment | L74: 1300 | M74: =L74*1.06 -> 1378 | N74: =M74*1.06 -> 1460.68 | O74: =N74*1.06 -> 1548.3208 | P74: =O74*1.06 -> 1641.22

Sheet Quarterly
B1: Woolworths Group (WOW.AX)
B2: A$M
B3: Quarterly Sales | C3: 1Q17 | D3: 2Q17 | E3: 3Q17 | F3: 4Q17 | G3: 1Q18 | H3: 2Q18 | I3: 3Q18 | J3: 4Q18 | K3: 1Q19 | L3: 2Q19 | M3: 3Q19 | N3: 4Q19 | O3: 1Q20 | P3: 2Q20 | Q3: 3Q20 | R3: 4Q20 | S3: 1Q21 | T3: 2Q21 | U3: 3Q21 | V3: 4Q21 | W3: 1Q22 | X3: 2Q22 | Y3: 3Q22 | Z3: 4Q22 | AA3: 1Q23 | AB3: 2Q23 | AC3: 3Q23 | AD3: 4Q23 | AE3: 1Q24 | AF3: 2Q24 | AG3: 3Q24 | AH3: 4Q24 | AI3: 1Q25 | AJ3: 2Q25 | AK3: 3Q25 | AL3: 4Q25 | AM3: 1Q26 | AN3: 2Q26E | AO3: 3Q26E | AP3: 4Q26E | AV3: 1H17 | AW3: 2H17 | AX3: 1H18 | AY3: 2H18 | AZ3: 1H19 | BA3: 2H19 | BB3: 1H20 | BC3: 2H20 | BD3: 1H21 | BE3: 2H21 | BF3: 1H22 | BG3: 2H22 | BH3: 1H23 | BI3: 2H23 | BJ3: 1H24 | BK3: 2H24 | BL3: 1H25 | BM3: 2H25 | BN3: 1H26E | BO3: 2H26E | BR3: FY17 | BS3: FY18 | BT3: FY19 | BU3: FY20 | BV3: FY21 | BW3: FY22 | BX3: FY23 | BY3: FY24 | BZ3: FY25 | CA3: FY26E
B4: Weeks in period | C4: 14 | D4: 13 | E4: 13 | F4: 12 | G4: 14 | H4: 13 | I4: 13 | J4: 12 | K4: 14 | L4: 13 | M4: 13 | N4: 12 | O4: 14 | P4: 13 | Q4: 13 | R4: 12 | S4: 14 | T4: 13 | U4: 13 | V4: 12 | W4: 14 | X4: 13 | Y4: 13 | Z4: 12 | AA4: 14 | AB4: 13 | AC4: 13 | AD4: 12 | AE4: 14 | AF4: 13 | AG4: 13 | AH4: 13 | AI4: 14 | AJ4: 13 | AK4: 13 | AL4: 12 | AM4: 14 | AN4: 13 | AO4: 13 | AP4: 12 | AQ4: 14 | AR4: 13 | AS4: 13 | AT4: 12 | AV4: =D4+C4 -> 27 | AW4: =F4+E4 -> 25 | AX4: =H4+G4 -> 27 | AY4: =J4+I4 -> 25 | AZ4: =L4+K4 -> 27 | BA4: =N4+M4 -> 25 | BB4: =P4+O4 -> 27 | BC4: =R4+Q4 -> 25 | BD4: =T4+S4 -> 27 | BE4: =V4+U4 -> 25 | BF4: =X4+W4 -> 27 | BG4: =Z4+Y4 -> 25 | BH4: =AB4+AA4 -> 27 | BI4: =AD4+AC4 -> 25 | BJ4: =AF4+AE4 -> 27 | BK4: =AH4+AG4 -> 26 | BL4: =AI4+AJ4 -> 27 | BM4: =AK4+AL4 -> 25 | BN4: =AM4+AN4 -> 27 | BO4: =AO4+AP4 -> 25
B5: Sales from Continuing Ops.
A6: Aus Food Sales | B6: Australian Food | C6: 9202 | D6: 9392 | E6: 9276 | F6: 8252 | G6: 9634 | H6: 9752 | I6: 9571 | J6: 8529 | K6: 9870 | L6: 10022 | M6: 10017 | N6: 9659 | O6: 10663 | P6: 10537 | Q6: 11171 | R6: 9780 | S6: 11808 | T6: 11180 | U6: 10778 | V6: 9500.3643 | W6: 12271 | X6: 11648 | Y6: 11432 | Z6: 10389 | AA6: 12204 | AB6: 12356 | AC6: 12300 | AD6: 11187 | AE6: 13102 | AF6: 12843 | AG6: 12597 | AH6: 12281 | AI6: 13605 | AJ6: 13069 | AK6: 13060 | AL6: 11754 | AM6: 13887 | AN6: =BN6-AM6 -> 13730.811 | AO6: =AK6*(1+AO24) -> 13517.1 | AP6: =BO6-AO6 -> 12215.864 | AV6: =VLOOKUP($A6,Model!$1:$1048576,MATCH(Quarterly!AV$3,Model!$3:$3,0),FALSE) -> 18712.6 | AW6: =VLOOKUP($A6,Model!$1:$1048576,MATCH(Quarterly!AW$3,Model!$3:$3,0),FALSE) -> 17123.4 | AX6: =VLOOKUP($A6,Model!$1:$1048576,MATCH(Quarterly!AX$3,Model!$3:$3,0),FALSE) -> 19436 | AY6: =VLOOKUP($A6,Model!$1:$1048576,MATCH(Quarterly!AY$3,Model!$3:$3,0),FALSE) -> 18153 | AZ6: =VLOOKUP($A6,Model!$1:$1048576,MATCH(Quarterly!AZ$3,Model!$3:$3,0),FALSE) -> 19928 | BA6: =VLOOKUP($A6,Model!$1:$1048576,MATCH(Quarterly!BA$3,Model!$3:$3,0),FALSE) -> 19707 | BB6: =VLOOKUP($A6,Model!$1:$1048576,MATCH(Quarterly!BB$3,Model!$3:$3,0),FALSE) -> 21200 | BC6: =VLOOKUP($A6,Model!$1:$1048576,MATCH(Quarterly!BC$3,Model!$3:$3,0),FALSE) -> 20951 | ... BO6: =VLOOKUP($A6,Model!$1:$1048576,MATCH(Quarterly!BO$3,Model!$3:$3,0),FALSE) -> 25732.964 | BR6: =VLOOKUP($A6,Model!$1:$1048576,MATCH(Quarterly!BR$3,Model!$3:$3,0),FALSE) -> 35836 | BS6: =VLOOKUP($A6,Model!$1:$1048576,MATCH(Quarterly!BS$3,Model!$3:$3,0),FALSE) -> 37589 | BT6: =VLOOKUP($A6,Model!$1:$1048576,MATCH(Quarterly!BT$3,Model!$3:$3,0),FALSE) -> 39635 | BU6: =VLOOKUP($A6,Model!$1:$1048576,MATCH(Quarterly!BU$3,Model!$3:$3,0),FALSE) -> 42151 | BV6: =VLOOKUP($A6,Model!$1:$1048576,MATCH(Quarterly!BV$3,Model!$3:$3,0),FALSE) -> 43746 | BW6: =VLOOKUP($A6,Model!$1:$1048576,MATCH(Quarterly!BW$3,Model!$3:$3,0),FALSE) -> 45740 | BX6: =VLOOKUP($A6,Model!$1:$1048576,MATCH(Quarterly!BX$3,Model!$3:$3,0),FALSE) -> 48047 | BY6: =VLOOKUP($A6,Model!$1:$1048576,MATCH(Quarterly!BY$3,Model!$3:$3,0),FALSE) -> 50823 | ... CA6: =VLOOKUP($A6,Model!$1:$1048576,MATCH(Quarterly!CA$3,Model!$3:$3,0),FALSE) -> 53350.775
A7: Aus B2B Sales | B7: Aus B2B | S7: 321 | T7: 310 | U7: 314 | V7: 229.63567 | W7: 952 | X7: 1027 | Y7: 995 | Z7: 710 | AA7: 1199 | AB7: 1059 | AC7: 1159 | AD7: 907 | AE7: 1378 | AF7: 1450 | AG7: 1352 | AH7: 1414 | AI7: 1473 | AJ7: 1509 | AK7: 1438 | AL7: 1323 | AM7: 1565 | AN7: =BN7-AM7 -> 1536.28 | AO7: =AK7*(1+AO25) -> 1466.76 | AP7: =BO7-AO7 -> 1375.965 | BD7: =VLOOKUP($A7,Model!$1:$1048576,MATCH(Quarterly!BD$3,Model!$3:$3,0),FALSE) -> 631 | BE7: =VLOOKUP($A7,Model!$1:$1048576,MATCH(Quarterly!BE$3,Model!$3:$3,0),FALSE) -> 354 | BF7: =VLOOKUP($A7,Model!$1:$1048576,MATCH(Quarterly!BF$3,Model!$3:$3,0),FALSE) -> 1979 | BG7: =VLOOKUP($A7,Model!$1:$1048576,MATCH(Quarterly!BG$3,Model!$3:$3,0),FALSE) -> 1705 | BH7: =VLOOKUP($A7,Model!$1:$1048576,MATCH(Quarterly!BH$3,Model!$3:$3,0),FALSE) -> 2433 | BI7: =VLOOKUP($A7,Model!$1:$1048576,MATCH(Quarterly!BI$3,Model!$3:$3,0),FALSE) -> 1891 | BJ7: =VLOOKUP($A7,Model!$1:$1048576,MATCH(Quarterly!BJ$3,Model!$3:$3,0),FALSE) -> 2828 | BK7: =VLOOKUP($A7,Model!$1:$1048576,MATCH(Quarterly!BK$3,Model!$3:$3,0),FALSE) -> 2766 | ... BO7: =VLOOKUP($A7,Model!$1:$1048576,MATCH(Quarterly!BO$3,Model!$3:$3,0),FALSE) -> 2842.725 | BV7: =VLOOKUP($A7,Model!$1:$1048576,MATCH(Quarterly!BV$3,Model!$3:$3,0),FALSE) -> 985 | BW7: =VLOOKUP($A7,Model!$1:$1048576,MATCH(Quarterly!BW$3,Model!$3:$3,0),FALSE) -> 3684 | BX7: =VLOOKUP($A7,Model!$1:$1048576,MATCH(Quarterly!BX$3,Model!$3:$3,0),FALSE) -> 4324 | BY7: =VLOOKUP($A7,Model!$1:$1048576,MATCH(Quarterly!BY$3,Model!$3:$3,0),FALSE) -> 5594 | BZ7: =VLOOKUP($A7,Model!$1:$1048576,MATCH(Quarterly!BZ$3,Model!$3:$3,0),FALSE) -> 5743 | CA7: =VLOOKUP($A7,Model!$1:$1048576,MATCH(Quarterly!CA$3,Model!$3:$3,0),FALSE) -> 5944.005
A8: NZ Supermarkets Sales | B8: NZ Supermarkets AUD | C8: 1502 | D8: 1556 | E8: 1492 | F8: 1316 | G8: 1508 | H8: 1542 | I8: 1509 | J8: 1732 | K8: 1537 | L8: 1606 | M8: 1616 | N8: 1989 | O8: 1660 | P8: 1707 | Q8: 1856 | R8: 1600 | S8: 1738 | T8: 1727 | U8: 1667 | V8: 1520.4418 | W8: 1962 | X8: 1846.2728 | Y8: 1736 | Z8: 1518 | AA8: 1802 | AB8: 1901 | AC8: 1858 | AD8: 1679 | AE8: 1906 | AF8: 1952 | AG8: 1884 | AH8: 1809 | AI8: 1933 | AJ8: 1962 | AK8: 1918 | AL8: 1744 | AM8: 1980 | AN8: =BN8-AM8 -> 1936.7475 | AO8: =AO84/AO88 -> 1896.9913 | AP8: =BO8-AO8 -> 1696.8236 | AV8: =VLOOKUP($A8,Model!$1:$1048576,MATCH(Quarterly!AV$3,Model!$3:$3,0),FALSE) -> 3068.9 | AW8: =VLOOKUP($A8,Model!$1:$1048576,MATCH(Quarterly!AW$3,Model!$3:$3,0),FALSE) -> 2774.1 | AX8: =VLOOKUP($A8,Model!$1:$1048576,MATCH(Quarterly!AX$3,Model!$3:$3,0),FALSE) -> 3060 | AY8: =VLOOKUP($A8,Model!$1:$1048576,MATCH(Quarterly!AY$3,Model!$3:$3,0),FALSE) -> 2838 | AZ8: =VLOOKUP($A8,Model!$1:$1048576,MATCH(Quarterly!AZ$3,Model!$3:$3,0),FALSE) -> 3143 | BA8: =VLOOKUP($A8,Model!$1:$1048576,MATCH(Quarterly!BA$3,Model!$3:$3,0),FALSE) -> 3148 | BB8: =VLOOKUP($A8,Model!$1:$1048576,MATCH(Quarterly!BB$3,Model!$3:$3,0),FALSE) -> 3367 | BC8: =VLOOKUP($A8,Model!$1:$1048576,MATCH(Quarterly!BC$3,Model!$3:$3,0),FALSE) -> 3456 | ... BO8: =VLOOKUP($A8,Model!$1:$1048576,MATCH(Quarterly!BO$3,Model!$3:$3,0),FALSE) -> 3593.8149 | BR8: =VLOOKUP($A8,Model!$1:$1048576,MATCH(Quarterly!BR$3,Model!$3:$3,0),FALSE) -> 5843 | BS8: =VLOOKUP($A8,Model!$1:$1048576,MATCH(Quarterly!BS$3,Model!$3:$3,0),FALSE) -> 5898 | BT8: =VLOOKUP($A8,Model!$1:$1048576,MATCH(Quarterly!BT$3,Model!$3:$3,0),FALSE) -> 6291 | BU8: =VLOOKUP($A8,Model!$1:$1048576,MATCH(Quarterly!BU$3,Model!$3:$3,0),FALSE) -> 6823 | BV8: =VLOOKUP($A8,Model!$1:$1048576,MATCH(Quarterly!BV$3,Model!$3:$3,0),FALSE) -> 6652 | BW8: =VLOOKUP($A8,Model!$1:$1048576,MATCH(Quarterly!BW$3,Model!$3:$3,0),FALSE) -> 7092 | BX8: =VLOOKUP($A8,Model!$1:$1048576,MATCH(Quarterly!BX$3,Model!$3:$3,0),FALSE) -> 7240 | BY8: =VLOOKUP($A8,Model!$1:$1048576,MATCH(Quarterly!BY$3,Model!$3:$3,0),FALSE) -> 7551 | ... CA8: =VLOOKUP($A8,Model!$1:$1048576,MATCH(Quarterly!CA$3,Model!$3:$3,0),FALSE) -> 7510.5624
A9: W Living Sales | B9: W Living (prior to FY24 Big W) | C9: 868 | D9: 1170 | E9: 757 | F9: 780 | G9: 890 | H9: 1147 | I9: 770 | J9: 759 | K9: 902 | L9: 1189 | M9: 791 | N9: 915 | O9: 926 | P9: 1223 | Q9: 866 | R9: 1091 | S9: 1115 | T9: 1466 | U9: 1024 | V9: 978 | W9: 920 | X9: 1428 | Y9: 989 | Z9: 1094 | AA9: 1197 | AB9: 1511 | AC9: 1046 | AD9: 1031 | AE9: 1160 | AF9: 1496 | AG9: 1253 | AH9: 1311 | AI9: 1346 | AJ9: 1715 | AK9: 1210 | AL9: 1326 | AM9: 1390 | AN9: =BN9-AM9 -> 1698.372 | AO9: =AO126 -> 1244.14 | AP9: =BO9-AO9 -> 1298.2938 | AV9: =VLOOKUP($A9,Model!$1:$1048576,MATCH(Quarterly!AV$3,Model!$3:$3,0),FALSE) -> 2050.3 | AW9: =VLOOKUP($A9,Model!$1:$1048576,MATCH(Quarterly!AW$3,Model!$3:$3,0),FALSE) -> 1547.7 | AX9: =VLOOKUP($A9,Model!$1:$1048576,MATCH(Quarterly!AX$3,Model!$3:$3,0),FALSE) -> 2037 | AY9: =VLOOKUP($A9,Model!$1:$1048576,MATCH(Quarterly!AY$3,Model!$3:$3,0),FALSE) -> 1529 | AZ9: =VLOOKUP($A9,Model!$1:$1048576,MATCH(Quarterly!AZ$3,Model!$3:$3,0),FALSE) -> 2091 | BA9: =VLOOKUP($A9,Model!$1:$1048576,MATCH(Quarterly!BA$3,Model!$3:$3,0),FALSE) -> 1706 | BB9: =VLOOKUP($A9,Model!$1:$1048576,MATCH(Quarterly!BB$3,Model!$3:$3,0),FALSE) -> 2149 | BC9: =VLOOKUP($A9,Model!$1:$1048576,MATCH(Quarterly!BC$3,Model!$3:$3,0),FALSE) -> 1957 | ... BO9: =VLOOKUP($A9,Model!$1:$1048576,MATCH(Quarterly!BO$3,Model!$3:$3,0),FALSE) -> 2542.4338 | BR9: =VLOOKUP($A9,Model!$1:$1048576,MATCH(Quarterly!BR$3,Model!$3:$3,0),FALSE) -> 3542 | BS9: =VLOOKUP($A9,Model!$1:$1048576,MATCH(Quarterly!BS$3,Model!$3:$3,0),FALSE) -> 3566 | BT9: =VLOOKUP($A9,Model!$1:$1048576,MATCH(Quarterly!BT$3,Model!$3:$3,0),FALSE) -> 3797 | BU9: =VLOOKUP($A9,Model!$1:$1048576,MATCH(Quarterly!BU$3,Model!$3:$3,0),FALSE) -> 4106 | BV9: =VLOOKUP($A9,Model!$1:$1048576,MATCH(Quarterly!BV$3,Model!$3:$3,0),FALSE) -> 4583 | BW9: =VLOOKUP($A9,Model!$1:$1048576,MATCH(Quarterly!BW$3,Model!$3:$3,0),FALSE) -> 4431 | BX9: =VLOOKUP($A9,Model!$1:$1048576,MATCH(Quarterly!BX$3,Model!$3:$3,0),FALSE) -> 4785 | BY9: =VLOOKUP($A9,Model!$1:$1048576,MATCH(Quarterly!BY$3,Model!$3:$3,0),FALSE) -> 5220 | ... CA9: =VLOOKUP($A9,Model!$1:$1048576,MATCH(Quarterly!CA$3,Model!$3:$3,0),FALSE) -> 5630.8058
A10: Others Sales | B10: Others | U10: -51.5 | V10: -51.5 | W10: 52 | Y10: -29 | Z10: -18 | AA10: -36.428571 | AB10: -23.571429 | AC10: -25 | AD10: -17 | AE10: 54 | AF10: 58 | AG10: 57 | AH10: 57 | AI10: 58 | AJ10: 62 | AK10: 59 | AL10: 67 | AM10: 66 | AN10: =BN10-AM10 -> 66 | AO10: =AJ10*(1+AK28) -> 64.175439 | AP10: =BO10-AO10 -> 74.424561 | BD10: =VLOOKUP($A10,Model!$1:$1048576,MATCH(Quarterly!BD$3,Model!$3:$3,0),FALSE) -> -130 | BE10: =VLOOKUP($A10,Model!$1:$1048576,MATCH(Quarterly!BE$3,Model!$3:$3,0),FALSE) -> -103 | BF10: =VLOOKUP($A10,Model!$1:$1048576,MATCH(Quarterly!BF$3,Model!$3:$3,0),FALSE) -> -51 | BG10: =VLOOKUP($A10,Model!$1:$1048576,MATCH(Quarterly!BG$3,Model!$3:$3,0),FALSE) -> -47 | BH10: =VLOOKUP($A10,Model!$1:$1048576,MATCH(Quarterly!BH$3,Model!$3:$3,0),FALSE) -> -60 | BI10: =VLOOKUP($A10,Model!$1:$1048576,MATCH(Quarterly!BI$3,Model!$3:$3,0),FALSE) -> -42 | BJ10: =VLOOKUP($A10,Model!$1:$1048576,MATCH(Quarterly!BJ$3,Model!$3:$3,0),FALSE) -> 112 | BK10: =VLOOKUP($A10,Model!$1:$1048576,MATCH(Quarterly!BK$3,Model!$3:$3,0),FALSE) -> 114 | ... BO10: =VLOOKUP($A10,Model!$1:$1048576,MATCH(Quarterly!BO$3,Model!$3:$3,0),FALSE) -> 138.6 | BV10: =VLOOKUP($A10,Model!$1:$1048576,MATCH(Quarterly!BV$3,Model!$3:$3,0),FALSE) -> -233 | BW10: =VLOOKUP($A10,Model!$1:$1048576,MATCH(Quarterly!BW$3,Model!$3:$3,0),FALSE) -> -98 | BX10: =VLOOKUP($A10,Model!$1:$1048576,MATCH(Quarterly!BX$3,Model!$3:$3,0),FALSE) -> -102 | BY10: =VLOOKUP($A10,Model!$1:$1048576,MATCH(Quarterly!BY$3,Model!$3:$3,0),FALSE) -> 226 | BZ10: =VLOOKUP($A10,Model!$1:$1048576,MATCH(Quarterly!BZ$3,Model!$3:$3,0),FALSE) -> 246 | CA10: =VLOOKUP($A10,Model!$1:$1048576,MATCH(Quarterly!CA$3,Model!$3:$3,0),FALSE) -> 270.6
A11: Elimination Sales | B11: Elimination/Reclass/Unallocated | S11: -74 | W11: -87 | AE11: -376 | AF11: -388 | AG11: -371 | AH11: -357 | AI11: -411 | AJ11: -391 | AK11: -375 | AL11: -377 | AM11: -405 | AN11: =BN11-AM11 -> -397 | AO11: =AK11*(1+AO29) -> -375 | AP11: =BO11-AO11 -> -377 | AV11: =VLOOKUP($A11,Model!$1:$1048576,MATCH(Quarterly!AV$3,Model!$3:$3,0),FALSE) -> 78.9 | AW11: =VLOOKUP($A11,Model!$1:$1048576,MATCH(Quarterly!AW$3,Model!$3:$3,0),FALSE) -> 75.1 | AY11: =VLOOKUP($A11,Model!$1:$1048576,MATCH(Quarterly!AY$3,Model!$3:$3,0),FALSE) -> 239 | BJ11: =VLOOKUP($A11,Model!$1:$1048576,MATCH(Quarterly!BJ$3,Model!$3:$3,0),FALSE) -> -764 | BK11: =VLOOKUP($A11,Model!$1:$1048576,MATCH(Quarterly!BK$3,Model!$3:$3,0),FALSE) -> -728 | BL11: =VLOOKUP($A11,Model!$1:$1048576,MATCH(Quarterly!BL$3,Model!$3:$3,0),FALSE) -> -802 | BM11: =VLOOKUP($A11,Model!$1:$1048576,MATCH(Quarterly!BM$3,Model!$3:$3,0),FALSE) -> -752 | BN11: =VLOOKUP($A11,Model!$1:$1048576,MATCH(Quarterly!BN$3,Model!$3:$3,0),FALSE) -> -802 | BO11: =VLOOKUP($A11,Model!$1:$1048576,MATCH(Quarterly!BO$3,Model!$3:$3,0),FALSE) -> -752 | BR11: =VLOOKUP($A11,Model!$1:$1048576,MATCH(Quarterly!BR$3,Model!$3:$3,0),FALSE) -> 154 | BS11: =VLOOKUP($A11,Model!$1:$1048576,MATCH(Quarterly!BS$3,Model!$3:$3,0),FALSE) -> 239 | BY11: =VLOOKUP($A11,Model!$1:$1048576,MATCH(Quarterly!BY$3,Model!$3:$3,0),FALSE) -> -1492 | BZ11: =VLOOKUP($A11,Model!$1:$1048576,MATCH(Quarterly!BZ$3,Model!$3:$3,0),FALSE) -> -1554 | CA11: =VLOOKUP($A11,Model!$1:$1048576,MATCH(Quarterly!CA$3,Model!$3:$3,0),FALSE) -> -1554
A12: Total Sales | B12: Sales from Continuing Ops. | C12: 14007 | D12: 14910 | E12: 13811 | F12: 12454 | G12: 14520 | H12: 15335 | I12: 14244 | J12: 12736 | K12: 14853 | L12: 15734 | M12: 14898 | N12: 14499 | O12: 15903 | P12: 16507 | Q12: 16495 | R12: 14770 | S12: =SUM(S6:S11) -> 14908 | T12: =SUM(T6:T11) -> 14683 | U12: =SUM(U6:U11) -> 13731.5 | V12: =SUM(V6:V11) -> 12176.942 | W12: =SUM(W6:W11) -> 16070 | X12: =SUM(X6:X11) -> 15949.273 | Y12: =SUM(Y6:Y11) -> 15123 | Z12: =SUM(Z6:Z11) -> 13693 | ... AM12: =SUM(AM6:AM11) -> 18483 | AN12: =BN12-AM12 -> 18571.211 | AO12: =SUM(AO6:AO11) -> 17814.167 | AP12: =BO12-AO12 -> 16284.371 | AV12: =VLOOKUP($A12,Model!$1:$1048576,MATCH(Quarterly!AV$3,Model!$3:$3,0),FALSE) -> 29058.5 | AW12: =VLOOKUP($A12,Model!$1:$1048576,MATCH(Quarterly!AW$3,Model!$3:$3,0),FALSE) -> 25838.5 | AX12: =VLOOKUP($A12,Model!$1:$1048576,MATCH(Quarterly!AX$3,Model!$3:$3,0),FALSE) -> 29907 | AY12: =VLOOKUP($A12,Model!$1:$1048576,MATCH(Quarterly!AY$3,Model!$3:$3,0),FALSE) -> 27268 | AZ12: =VLOOKUP($A12,Model!$1:$1048576,MATCH(Quarterly!AZ$3,Model!$3:$3,0),FALSE) -> 30587 | BA12: =VLOOKUP($A12,Model!$1:$1048576,MATCH(Quarterly!BA$3,Model!$3:$3,0),FALSE) -> 29397 | BB12: =VLOOKUP($A12,Model!$1:$1048576,MATCH(Quarterly!BB$3,Model!$3:$3,0),FALSE) -> 32410 | BC12: =VLOOKUP($A12,Model!$1:$1048576,MATCH(Quarterly!BC$3,Model!$3:$3,0),FALSE) -> 31265 | ... BO12: =VLOOKUP($A12,Model!$1:$1048576,MATCH(Quarterly!BO$3,Model!$3:$3,0),FALSE) -> 34098.538 | BR12: =VLOOKUP($A12,Model!$1:$1048576,MATCH(Quarterly!BR$3,Model!$3:$3,0),FALSE) -> 54841 | BS12: =VLOOKUP($A12,Model!$1:$1048576,MATCH(Quarterly!BS$3,Model!$3:$3,0),FALSE) -> 57175 | BT12: =VLOOKUP($A12,Model!$1:$1048576,MATCH(Quarterly!BT$3,Model!$3:$3,0),FALSE) -> 59984 | BU12: =VLOOKUP($A12,Model!$1:$1048576,MATCH(Quarterly!BU$3,Model!$3:$3,0),FALSE) -> 63675 | BV12: =VLOOKUP($A12,Model!$1:$1048576,MATCH(Quarterly!BV$3,Model!$3:$3,0),FALSE) -> 67317 | BW12: =VLOOKUP($A12,Model!$1:$1048576,MATCH(Quarterly!BW$3,Model!$3:$3,0),FALSE) -> 60849 | BX12: =VLOOKUP($A12,Model!$1:$1048576,MATCH(Quarterly!BX$3,Model!$3:$3,0),FALSE) -> 64294 | BY12: =VLOOKUP($A12,Model!$1:$1048576,MATCH(Quarterly!BY$3,Model!$3:$3,0),FALSE) -> 67922 | ... CA12: =VLOOKUP($A12,Model!$1:$1048576,MATCH(Quarterly!CA$3,Model!$3:$3,0),FALSE) -> 71152.749
B14: Total Growth % (reported, adjusted)
A15: Aus Food Growth | B15: Australian Food | C15: 0.017 | D15: 0.04 | E15: 0.056 | F15: 0.072 | G15: 0.047 | H15: 0.051 | I15: 0.042 | J15: 0.031 | K15: 0.019 | L15: 0.028 | M15: 0.047 | N15: 0.044 | O15: 0.078 | P15: 0.049 | Q15: 0.113 | R15: 0.093 | S15: 0.129 | T15: 0.083 | U15: -0.007 | V15: 0.012 | W15: 0.039 | X15: 0.029 | Y15: 0.054 | Z15: 0.06 | AA15: -0.004 | AB15: 0.059 | AC15: 0.078 | AD15: 0.075 | AE15: 0.064 | AF15: 0.045 | AG15: 0.015 | AH15: 0.022 | AI15: 0.038 | AJ15: 0.017 | AK15: 0.036 | AL15: 0.034 | AM15: 0.021 | BS15: =BS6/BR6-1 -> 0.04891729 | BT15: =BT6/BS6-1 -> 0.054430818 | BU15: =BU6/BT6-1 -> 0.063479248 | BV15: =BV6/BU6-1 -> 0.037840146 | BW15: =BW6/BV6-1 -> 0.04558131 | BX15: =BX6/BW6-1 -> 0.050437254 | BY15: =BY6/BX6-1 -> 0.05777676 | BZ15: =BZ6/BY6-1 -> 0.013084627 | CA15: =CA6/BZ6-1 -> 0.036178827
B16: Aus B2B | W16: 1.964 | X16: 2.31 | Y16: 2.173 | Z16: 2.564 | AA16: 0.256 | AB16: 0.202 | AC16: 0.149 | AD16: 0.091 | AE16: 0.015 | AF16: 0.041 | AG16: 0.032 | AH16: 0.089 | AI16: 0.069 | AJ16: 0.041 | AK16: 0.063 | AL16: -0.009 | AM16: 0.062 | BW16: =BW7/BV7-1 -> 2.7401015 | BX16: =BX7/BW7-1 -> 0.17372421 | BY16: =BY7/BX7-1 -> 0.29370953 | BZ16: =BZ7/BY7-1 -> 0.026635681 | CA16: =CA7/BZ7-1 -> 0.035
A17: NZ Growth | B17: NZ Supermarkets AUD | C17: 0.081 | D17: 0.04 | E17: 0.044 | F17: 0.046 | G17: 0.004 | H17: -0.006 | I17: 0.022 | J17: 0.019 | K17: 0.012 | L17: 0.041 | M17: 0.062 | N17: 0.049 | O17: 0.08 | P17: 0.062 | Q17: 0.148 | R17: 0.13 | S17: 0.047 | T17: 0.012 | U17: 0.102 | V17: -0.05 | W17: 0.12888377 | X17: 0.086 | Y17: 0.042 | Z17: -0.001 | AA17: -0.081 | AB17: 0.013 | AC17: 0.07 | AD17: 0.106 | AE17: 0.058 | AF17: 0.028 | AG17: 0.014 | AH17: -0.004 | AI17: 0.014 | AJ17: 0.004 | AK17: 0.018 | AL17: 0.043 | AM17: 0.032 | BS17: =BS8/BR8-1 -> 0.0094129728 | BT17: =BT8/BS8-1 -> 0.066632757 | BU17: =BU8/BT8-1 -> 0.084565252 | BV17: =BV8/BU8-1 -> -0.025062289 | BW17: =BW8/BV8-1 -> 0.06614552 | BX17: =BX8/BW8-1 -> 0.020868584 | BY17: =BY8/BX8-1 -> 0.042955801 | BZ17: =BZ8/BY8-1 -> 0.00079459674 | CA17: =CA8/BZ8-1 -> -0.0061449796
B18: W Living (prior to FY24 Big W) | C18: -0.055 | D18: -0.068 | E18: -0.061 | F18: -0.044 | G18: 0.025 | H18: -0.001 | I18: -0.013 | J18: 0.017 | K18: 0.013 | L18: 0.037 | M18: 0.056 | N18: 0.069 | O18: 0.026 | P18: 0.029 | Q18: 0.095 | R18: 0.308 | S18: 0.204 | T18: 0.198 | U18: 0.183 | V18: -0.104 | W18: -0.17488789 | X18: -0.026 | Y18: -0.035 | Z18: 0.119 | AA18: 0.301 | AB18: 0.058 | AC18: 0.057 | AD18: -0.057 | AE18: -0.055 | AF18: -0.031 | AG18: -0.041 | AH18: -0.031 | AI18: 0.17 | AJ18: 0.153 | AK18: -0.027 | AL18: 0.099 | AM18: 0.033 | BS18: =BS9/BR9-1 -> 0.0067758329 | BT18: =BT9/BS9-1 -> 0.064778463 | BU18: =BU9/BT9-1 -> 0.081380037 | BV18: =BV9/BU9-1 -> 0.11617146 | BW18: =BW9/BV9-1 -> -0.033166048 | BX18: =BX9/BW9-1 -> 0.079891672 | BY18: =BY9/BX9-1 -> 0.090909091 | BZ18: =BZ9/BY9-1 -> 0.072222222 | CA18: =CA9/BZ9-1 -> 0.0060399834
B19: Others | AI19: 0.058 | AJ19: 0.072 | AK19: 0.053 | AL19: 0.087 | AM19: 0.138 | BW19: =BW10/BV10-1 -> -0.57939914 | BX19: =BX10/BW10-1 -> 0.040816327 | BY19: =BY10/BX10-1 -> -3.2156863 | BZ19: =BZ10/BY10-1 -> 0.088495575 | CA19: =CA10/BZ10-1 -> 0.1
B20: Elimination/Reclass/Unallocated | AI20: 0.093 | AJ20: 0.015 | AK20: 0.016 | AL20: 0.045 | AM20: -0.015 | BS20: =BS11/BR11-1 -> 0.55194805 | BT20: =BT11/BS11-1 -> -1 | BZ20: =BZ11/BY11-1 -> 0.04155496 | CA20: =CA11/BZ11-1 -> 0
B21: Sales from Continuing Ops. % | C21: 0.022 | D21: 0.031 | E21: 0.044 | F21: 0.057 | G21: 0.037 | H21: 0.039 | I21: 0.034 | J21: 0.027 | K21: 0.019 | L21: 0.026 | M21: 0.051 | N21: 0.042 | O21: 0.071 | P21: 0.049 | Q21: 0.107 | R21: 0.102 | S21: 0.124 | T21: 0.085 | U21: -0.008 | V21: -0.004 | W21: 0.077944728 | X21: 0.082 | Y21: 0.097 | Z21: 0.115 | AA21: 0.018 | AB21: 0.062 | AC21: 0.08 | AD21: 0.069 | AE21: 0.053 | AF21: 0.036 | AG21: 0.028 | AH21: 0.069 | AI21: 0.045 | AJ21: 0.029 | AK21: 0.032 | AL21: 0.035 | AM21: 0.027 | BS21: =BS12/BR12-1 -> 0.042559399 | BT21: =BT12/BS12-1 -> 0.049129864 | BU21: =BU12/BT12-1 -> 0.061533075 | BV21: =BV12/BU12-1 -> 0.057196702 | BW21: =BW12/BV12-1 -> -0.096082713 | BX21: =BX12/BW12-1 -> 0.056615557 | BY21: =BY12/BX12-1 -> 0.056428283 | BZ21: =BZ12/BY12-1 -> 0.0170048 | CA21: =CA12/BZ12-1 -> 0.03004978
AN22: =220/AJ6 -> 0.016833729
B23: Total Growth % (calculated) | AJ23: =240/AF6 -> 0.018687223 | AN23: =240/AJ6 -> 0.018364068
B24: Australian Food | G24: =G6/C6-1 -> 0.046946316 | H24: =H6/D6-1 -> 0.038330494 | I24: =I6/E6-1 -> 0.031802501 | J24: =J6/F6-1 -> 0.03356762 | K24: =K6/G6-1 -> 0.024496575 | L24: =L6/H6-1 -> 0.027686628 | M24: =M6/I6-1 -> 0.046599101 | N24: =N6/J6-1 -> 0.13248915 | ... AN24: =AN6/AJ6-1 -> 0.050639792 | AO24: =AO33+AO38 -> 0.035 | AP24: =AP6/AL6-1 -> 0.039294199 | AW24: =AW6/AV6-1 -> -0.084926734 | AX24: =AX6/AW6-1 -> 0.13505495 | AY24: =AY6/AX6-1 -> -0.066011525 | AZ24: =AZ6/AY6-1 -> 0.097779981 | BA24: =BA6/AZ6-1 -> -0.011089924 | BB24: =BB6/BA6-1 -> 0.075759882 | BC24: =BC6/BB6-1 -> -0.011745283 | BD24: =BD6/BC6-1 -> 0.097226863 | ... BL24: =BL6/BK6-1 -> 0.072192298 | BM24: =BM6/BK6-1 -> -0.0025725541 | BN24: =BN6/BL6-1 -> 0.035383199 | BO24: =BO6/BM6-1 -> 0.037034094 | BS24: =BS6/BR6-1 -> 0.04891729 | BT24: =BT6/BS6-1 -> 0.054430818 | BU24: =BU6/BT6-1 -> 0.063479248 | BV24: =BV6/BU6-1 -> 0.037840146 | BW24: =BW6/BV6-1 -> 0.04558131 | BX24: =BX6/BW6-1 -> 0.050437254 | BY24: =BY6/BX6-1 -> 0.05777676 | BZ24: =BZ6/BY6-1 -> 0.013084627 | CA24: =CA6/BZ6-1 -> 0.036178827
B25: Aus B2B | Y25: =Y7/U7-1 -> 2.1687898 | Z25: =Z7/V7-1 -> 2.0918541 | AA25: =AA7/W7-1 -> 0.25945378 | AB25: =AB7/X7-1 -> 0.031158715 | AC25: =AC7/Y7-1 -> 0.16482412 | AD25: =AD7/Z7-1 -> 0.27746479 | AE25: =AE7/AA7-1 -> 0.14929108 | AF25: =AF7/AB7-1 -> 0.36921624 | ... AN25: =AN7/AJ7-1 -> 0.018078197 | AO25: 0.02 | AP25: =AP7/AL7-1 -> 0.040034014 | BE25: =BE7/BD7-1 -> -0.43898574 | BF25: =BF7/BE7-1 -> 4.5903955 | BG25: =BG7/BF7-1 -> -0.13845376 | BH25: =BH7/BG7-1 -> 0.42697947 | BI25: =BI7/BH7-1 -> -0.22277024 | BJ25: =BJ7/BI7-1 -> 0.49550502 | BK25: =BK7/BJ7-1 -> -0.021923621 | BL25: =BL7/BK7-1 -> 0.078091106 | BM25: =BM7/BK7-1 -> -0.0018076645 | BN25: =BN7/BL7-1 -> 0.04 | BO25: =BO7/BM7-1 -> 0.029599783 | BW25: =BW7/BV7-1 -> 2.7401015 | BX25: =BX7/BW7-1 -> 0.17372421 | BY25: =BY7/BX7-1 -> 0.29370953 | BZ25: =BZ7/BY7-1 -> 0.026635681 | CA25: =CA7/BZ7-1 -> 0.035
B26: NZ Supermarkets AUD | G26: =G8/C8-1 -> 0.0039946738 | H26: =H8/D8-1 -> -0.0089974293 | I26: =I8/E8-1 -> 0.011394102 | J26: =J8/F8-1 -> 0.31610942 | K26: =K8/G8-1 -> 0.019230769 | L26: =L8/H8-1 -> 0.04150454 | M26: =M8/I8-1 -> 0.070907886 | N26: =N8/J8-1 -> 0.14838337 | ... AP26: =AP8/AL8-1 -> -0.027050713 | AW26: =AW8/AV8-1 -> -0.096060478 | AX26: =AX8/AW8-1 -> 0.10306045 | AY26: =AY8/AX8-1 -> -0.07254902 | AZ26: =AZ8/AY8-1 -> 0.10747005 | BA26: =BA8/AZ8-1 -> 0.0015908368 | BB26: =BB8/BA8-1 -> 0.06956798 | BC26: =BC8/BB8-1 -> 0.026433026 | BD26: =BD8/BC8-1 -> 0.0026041667 | ... BL26: =BL8/BK8-1 -> 0.054698077 | BM26: =BM8/BK8-1 -> -0.0083942594 | BN26: =BN8/BL8-1 -> 0.0055834475 | BO26: =BO8/BM8-1 -> -0.018619645 | BS26: =BS8/BR8-1 -> 0.0094129728 | BT26: =BT8/BS8-1 -> 0.066632757 | BU26: =BU8/BT8-1 -> 0.084565252 | BV26: =BV8/BU8-1 -> -0.025062289 | BW26: =BW8/BV8-1 -> 0.06614552 | BX26: =BX8/BW8-1 -> 0.020868584 | BY26: =BY8/BX8-1 -> 0.042955801 | BZ26: =BZ8/BY8-1 -> 0.00079459674 | CA26: =CA8/BZ8-1 -> -0.0061449796
B27: W Living (prior to FY24 Big W) | G27: =G9/C9-1 -> 0.025345622 | H27: =H9/D9-1 -> -0.01965812 | I27: =I9/E9-1 -> 0.017173052 | J27: =J9/F9-1 -> -0.026923077 | K27: =K9/G9-1 -> 0.013483146 | L27: =L9/H9-1 -> 0.036617262 | M27: =M9/I9-1 -> 0.027272727 | N27: =N9/J9-1 -> 0.2055336 | ... AP27: =AP9/AL9-1 -> -0.02089458 | AW27: =AW9/AV9-1 -> -0.24513486 | AX27: =AX9/AW9-1 -> 0.31614654 | AY27: =AY9/AX9-1 -> -0.24938635 | AZ27: =AZ9/AY9-1 -> 0.3675605 | BA27: =BA9/AZ9-1 -> -0.18412243 | BB27: =BB9/BA9-1 -> 0.25967175 | BC27: =BC9/BB9-1 -> -0.089343881 | BD27: =BD9/BC9-1 -> 0.31885539 | ... BL27: =BL9/BK9-1 -> 0.19383775 | BM27: =BM9/BK9-1 -> -0.010920437 | BN27: =BN9/BL9-1 -> 0.0089421758 | BO27: =BO9/BM9-1 -> 0.0025369823 | BS27: =BS9/BR9-1 -> 0.0067758329 | BT27: =BT9/BS9-1 -> 0.064778463 | BU27: =BU9/BT9-1 -> 0.081380037 | BV27: =BV9/BU9-1 -> 0.11617146 | BW27: =BW9/BV9-1 -> -0.033166048 | BX27: =BX9/BW9-1 -> 0.079891672 | BY27: =BY9/BX9-1 -> 0.090909091 | BZ27: =BZ9/BY9-1 -> 0.072222222 | CA27: =CA9/BZ9-1 -> 0.0060399834
B28: Others | AI28: =AI10/AE10-1 -> 0.074074074 | AJ28: =AJ10/AF10-1 -> 0.068965517 | AK28: =AK10/AG10-1 -> 0.035087719 | AL28: =AL10/AH10-1 -> 0.1754386 | AM28: =AM10/AI10-1 -> 0.13793103 | AN28: =AN10/AJ10-1 -> 0.064516129 | AO28: 0.1 | AP28: =AP10/AL10-1 -> 0.11081435 | BE28: =BE10/BD10-1 -> -0.20769231 | BF28: =BF10/BE10-1 -> -0.50485437 | BG28: =BG10/BF10-1 -> -0.078431373 | BH28: =BH10/BG10-1 -> 0.27659574 | BI28: =BI10/BH10-1 -> -0.3 | BJ28: =BJ10/BI10-1 -> -3.6666667 | BK28: =BK10/BJ10-1 -> 0.017857143 | BL28: =BL10/BK10-1 -> 0.052631579 | BM28: =BM10/BK10-1 -> 0.10526316 | BN28: =BN10/BL10-1 -> 0.1 | BO28: =BO10/BM10-1 -> 0.1 | BZ28: =BZ10/BY10-1 -> 0.088495575 | CA28: =CA10/BZ10-1 -> 0.1
B29: Elimination/Reclass/Unallocated | AI29: =AI11/AE11-1 -> 0.093085106 | AJ29: =AJ11/AF11-1 -> 0.0077319588 | AK29: =AK11/AG11-1 -> 0.010781671 | AL29: =AL11/AH11-1 -> 0.056022409 | AM29: =AM11/AI11-1 -> -0.01459854 | AN29: =AN11/AJ11-1 -> 0.015345269 | AO29: 0 | AP29: =AP11/AL11-1 -> 0 | BK29: =BK11/BJ11-1 -> -0.047120419 | BL29: =BL11/BK11-1 -> 0.10164835 | BM29: =BM11/BK11-1 -> 0.032967033 | BN29: =BN11/BL11-1 -> 0 | BO29: =BO11/BM11-1 -> 0 | BZ29: =BZ11/BY11-1 -> 0.04155496 | CA29: =CA11/BZ11-1 -> 0
B30: Sales from Continuing Ops. % | Y30: =Y12/U12-1 -> 0.10133634 | Z30: =Z12/V12-1 -> 0.12450238 | AA30: =AA12/W12-1 -> 0.018392746 | AB30: =AB12/X12-1 -> 0.053554525 | AC30: =AC12/Y12-1 -> 0.080341202 | AD30: =AD12/Z12-1 -> 0.079894837 | AE30: =AE12/AA12-1 -> 0.052453321 | AF30: =AF12/AB12-1 -> 0.036157587 | ... AP30: =AP12/AL12-1 -> 0.028248464 | AW30: =AW12/AV12-1 -> -0.11081095 | AX30: =AX12/AW12-1 -> 0.15745883 | AY30: =AY12/AX12-1 -> -0.088240211 | AZ30: =AZ12/AY12-1 -> 0.12171776 | BA30: =BA12/AZ12-1 -> -0.038905417 | BB30: =BB12/BA12-1 -> 0.10249345 | BC30: =BC12/BB12-1 -> -0.035328602 | BD30: =BD12/BC12-1 -> 0.14776907 | ... BL30: =BL12/BK12-1 -> 0.079400367 | BM30: =BM12/BK12-1 -> -0.0042058461 | BN30: =BN12/BL12-1 -> 0.031288922 | BO30: =BO12/BM12-1 -> 0.0287066 | BS30: =BS12/BR12-1 -> 0.042559399 | BT30: =BT12/BS12-1 -> 0.049129864 | BU30: =BU12/BT12-1 -> 0.061533075 | BV30: =BV12/BU12-1 -> 0.057196702 | BW30: =BW12/BV12-1 -> -0.096082713 | BX30: =BX12/BW12-1 -> 0.056615557 | BY30: =BY12/BX12-1 -> 0.056428283 | BZ30: =BZ12/BY12-1 -> 0.0170048 | CA30: =CA12/BZ12-1 -> 0.03004978
B32: LFL Sales Growth %
A33: Aus Food Comp | B33: Australian Food | C33: 0.007 | D33: 0.031 | E33: 0.045 | F33: 0.064 | G33: 0.049 | H33: 0.05 | I33: 0.04 | J33: 0.031 | K33: 0.018 | L33: 0.027 | M33: 0.042 | N33: 0.036 | O33: 0.066 | P33: 0.038 | Q33: 0.103 | R33: 0.089 | S33: 0.115 | T33: 0.071 | U33: -0.021 | V33: 0.001 | W33: 0.027 | X33: 0.019 | Y33: 0.044 | Z33: 0.052 | AA33: -0.009 | AB33: 0.051 | AC33: 0.068 | AD33: 0.064 | AE33: 0.055 | AF33: 0.038 | AG33: 0.011 | AH33: 0.013 | AI33: 0.023 | AJ33: 0.011 | AK33: 0.03 | AL33: 0.029 | AM33: 0.016 | AN33: 0.043 | AO33: 0.03 | AP33: 0.03 | AV33: =AVERAGE(C33:D33) -> 0.019 | AW33: =AVERAGE(E33:F33) -> 0.0545 | AX33: =AVERAGE(G33:H33) -> 0.0495 | AY33: =AVERAGE(I33:J33) -> 0.0355 | AZ33: =AVERAGE(K33:L33) -> 0.0225 | BA33: =AVERAGE(M33:N33) -> 0.039 | BB33: =AVERAGE(O33:P33) -> 0.052 | BC33: =AVERAGE(Q33:R33) -> 0.096 | BD33: =AVERAGE(S33:T33) -> 0.093 | BE33: =AVERAGE(U33:V33) -> -0.01 | BF33: =AVERAGE(W33:X33) -> 0.023 | BG33: =AVERAGE(Y33:Z33) -> 0.048 | BH33: =AVERAGE(AA33:AB33) -> 0.021 | BI33: =AVERAGE(AC33:AD33) -> 0.066 | BJ33: =AVERAGE(AE33:AF33) -> 0.0465 | BK33: =AVERAGE(AG33:AH33) -> 0.012 | BL33: =AVERAGE(AI33:AJ33) -> 0.017 | BM33: =AVERAGE(AK33:AL33) -> 0.0295 | BN33: =AVERAGE(AM33:AN33) -> 0.0295 | BO33: =AVERAGE(AO33:AP33) -> 0.03 | CA33: =AVERAGE(AM33:AP33) -> 0.02975
A34: NZ LFL | B34: NZ Supermarkets (NZD) | C34: -0.007 | D34: 0.005 | E34: 0.021 | F34: 0.03 | G34: 0.027 | H34: 0.033 | I34: 0.038 | J34: 0.037 | K34: 0.04 | L34: 0.024 | M34: 0.038 | N34: 0.035 | O34: 0.048 | P34: 0.045 | Q34: 0.134 | R34: 0.139 | S34: 0.058 | T34: 0.008 | U34: -0.075 | V34: -0.042 | W34: 0.09 | X34: 0.06 | Y34: 0.031 | Z34: 0.014 | AA34: -0.033 | AB34: 0.04 | AC34: 0.068 | AD34: 0.072 | AE34: 0.026 | AF34: 0.025 | AG34: 0.015 | AH34: 0.011 | AI34: 0.034 | AJ34: 0.032 | AK34: 0.038 | AL34: 0.049 | AM34: 0.037 | AN34: 0.04 | AO34: 0.035 | AP34: 0.025 | AV34: =AVERAGE(C34:D34) -> -0.001 | AW34: =AVERAGE(E34:F34) -> 0.0255 | AX34: =AVERAGE(G34:H34) -> 0.03 | AY34: =AVERAGE(I34:J34) -> 0.0375 | AZ34: =AVERAGE(K34:L34) -> 0.032 | BA34: =AVERAGE(M34:N34) -> 0.0365 | BB34: =AVERAGE(O34:P34) -> 0.0465 | BC34: =AVERAGE(Q34:R34) -> 0.1365 | BD34: =AVERAGE(S34:T34) -> 0.033 | BE34: =AVERAGE(U34:V34) -> -0.0585 | BF34: =AVERAGE(W34:X34) -> 0.075 | BG34: =AVERAGE(Y34:Z34) -> 0.0225 | BH34: =AVERAGE(AA34:AB34) -> 0.0035 | BI34: =AVERAGE(AC34:AD34) -> 0.07 | BJ34: =AVERAGE(AE34:AF34) -> 0.0255 | BK34: =AVERAGE(AG34:AH34) -> 0.013 | BL34: =AVERAGE(AI34:AJ34) -> 0.033 | BM34: =AVERAGE(AK34:AL34) -> 0.0435 | BN34: =AVERAGE(AM34:AN34) -> 0.0385 | BO34: =AVERAGE(AO34:AP34) -> 0.03 | CA34: =AVERAGE(AM34:AP34) -> 0.03425
A35: Big W LFL | B35: Big W only | C35: -0.057 | D35: -0.067 | E35: -0.057 | F35: -0.039 | G35: 0.029 | H35: 0.001 | I35: -0.012 | J35: -0.023 | K35: 0.022 | L35: 0.05 | M35: 0.074 | N35: 0.072 | O35: 0.044 | P35: 0.032 | Q35: 0.099 | R35: 0.305 | S35: 0.223 | T35: 0.21 | U35: 0.2 | V35: -0.094 | W35: -0.168 | X35: -0.018 | Y35: -0.034 | Z35: 0.119 | AA35: 0.299 | AB35: 0.056 | AC35: 0.055 | AD35: -0.059 | AE35: -0.056 | AF35: -0.031 | AG35: -0.051 | AH35: -0.021 | AI35: -0.007 | AJ35: -0.003 | AK35: 0.011 | AL35: 0.024 | AM35: 0.006 | AN35: 0.01 | AO35: 0.01 | AP35: 0.01 | AV35: =AVERAGE(C35:D35) -> -0.062 | AW35: =AVERAGE(E35:F35) -> -0.048 | AX35: =AVERAGE(G35:H35) -> 0.015 | AY35: =AVERAGE(I35:J35) -> -0.0175 | AZ35: =AVERAGE(K35:L35) -> 0.036 | BA35: =AVERAGE(M35:N35) -> 0.073 | BB35: =AVERAGE(O35:P35) -> 0.038 | BC35: =AVERAGE(Q35:R35) -> 0.202 | BD35: =AVERAGE(S35:T35) -> 0.2165 | BE35: =AVERAGE(U35:V35) -> 0.053 | BF35: =AVERAGE(W35:X35) -> -0.093 | BG35: =AVERAGE(Y35:Z35) -> 0.0425 | BH35: =AVERAGE(AA35:AB35) -> 0.1775 | BI35: =AVERAGE(AC35:AD35) -> -0.002 | BJ35: =AVERAGE(AE35:AF35) -> -0.0435 | BK35: =AVERAGE(AG35:AH35) -> -0.036 | BL35: =AVERAGE(AI35:AJ35) -> -0.005 | BM35: =AVERAGE(AK35:AL35) -> 0.0175 | BN35: =AVERAGE(AM35:AN35) -> 0.008 | BO35: =AVERAGE(AO35:AP35) -> 0.01 | CA35: =AVERAGE(AM35:AP35) -> 0.009
B37: Other Growth (space/timing/fx) %
