Workbook

Sheet Value
B2: Valuation | C2: XYZ
I3: DDM | J3: Units
C4: Current Price (ASX)= | D4: =G4 -> 96.82 | F4: XYZ.AX | G4: 96.82 | I4: Risk Free Rate | J4: % | K4: 0.04
C5: Shares Outstanding = | D5: #VALUE! | F5: XYZ.N | G5: 62.75 | I5: Beta | J5: x | K5: 1.2
C6: AS51 Index | I6: Market Premium | J6: % | K6: 0.06
C7: TARGET Relative Forward PE | I7: Ke | J7: % | K7: =K4+K5*K6 -> 0.112
C8: TARGET Forward PE | I8: ROE | J8: % p.a. | K8: 0.3
C9: PE Price Target = | I9: LT Payout Ratio | J9: % p.a. | K9: 0.8
I10: LT growth rate | J10: % p.a. | K10: =(1-K9)*K8 -> 0.06
J11: Dividend Discount Model (Common shares, USD/sh) | K11: =Annual!D249 -> 116.18855 | L11: =K11/G5-1 -> 0.85161029
J12: Dividend Discount Model (Common shares, AUD/sh) | K12: =K11*G4/G5 -> 179.27291 | L12: =K12/G4-1 -> 0.85161029 | M12: =K11/K12 -> 0.64810989
B14: Notes | C14: Units
B15: Actual Values | C15: 1000 | D15: (hard coded)
B16: Formula | C16: 1000
B17: Manual entry (assumption) | C17: 1000 | D17: (usually from guidance given by management)
C19: Actual ---> | E19: Forecast ----->
C20: 2023 | D20: 2024 | E20: 2025 | F20: 2026 | G20: 2027 | J20: Actual ---> | L20: Forecast -----> | Q20: Actual ---> | S20: Forecast ----->
B21: PE | J21: 2023 | K21: 2024 | L21: 2025 | M21: 2026 | N21: 2027 | Q21: 2023 | R21: 2024 | S21: 2025 | T21: 2026 | U21: 2027
B22: Consensus | I22: NPAT(USDm) | P22: EBITDA (USDm)
B23: Blackwattle | C23: =$G$5/C29 -> 34.185223 | D23: =$G$5/D29 -> 18.653824 | E23: =$G$5/E29 -> 26.792326 | F23: =$G$5/F29 -> 18.679391 | G23: =$G$5/G29 -> 14.326722 | I23: Consensus | P23: Consensus
B24: Difference | H24: Adjusted NPAT (non-GAAP, pre-NCI) | I24: Blackwattle | J24: =INDEX(Annual!$A:$AA,MATCH($H24,Annual!$A:$A,0),MATCH(Value!J$21,Annual!$A$1:$AA$1,0))/1000 -> 1127.088 | K24: =INDEX(Annual!$A:$AA,MATCH($H24,Annual!$A:$A,0),MATCH(Value!K$21,Annual!$A$1:$AA$1,0))/1000 -> 2140.766 | L24: =INDEX(Annual!$A:$AA,MATCH($H24,Annual!$A:$A,0),MATCH(Value!L$21,Annual!$A$1:$AA$1,0))/1000 -> 1496.7819 | M24: =INDEX(Annual!$A:$AA,MATCH($H24,Annual!$A:$A,0),MATCH(Value!M$21,Annual!$A$1:$AA$1,0))/1000 -> 2146.8724 | N24: =INDEX(Annual!$A:$AA,MATCH($H24,Annual!$A:$A,0),MATCH(Value!N$21,Annual!$A$1:$AA$1,0))/1000 -> 2772.9032 | O24: UEBITDA-Adjusted EBITDA (Non-GAAP, as guided to) | P24: Blackwattle | Q24: =INDEX(Annual!$A:$AA,MATCH(Value!$O24,Annual!$A:$A,0),MATCH(Value!Q$21,Annual!$A$1:$AA$1,0))/1000 -> 1792.42 | R24: =INDEX(Annual!$A:$AA,MATCH(Value!$O24,Annual!$A:$A,0),MATCH(Value!R$21,Annual!$A$1:$AA$1,0))/1000 -> 3029.031 | S24: =INDEX(Annual!$A:$AA,MATCH(Value!$O24,Annual!$A:$A,0),MATCH(Value!S$21,Annual!$A$1:$AA$1,0))/1000 -> 3492.6452 | T24: =INDEX(Annual!$A:$AA,MATCH(Value!$O24,Annual!$A:$A,0),MATCH(Value!T$21,Annual!$A$1:$AA$1,0))/1000 -> 4660.1531 | U24: =INDEX(Annual!$A:$AA,MATCH(Value!$O24,Annual!$A:$A,0),MATCH(Value!U$21,Annual!$A$1:$AA$1,0))/1000 -> 5742.0905
I25: Difference | P25: Difference
B26: EPS (UScps)
A27: YE Basic Shares Outstanding | B27: Shares Outstanding | C27: =INDEX(Annual!$A:$AA,MATCH($A27,Annual!$A:$A,0),MATCH(C$20,Annual!$A$1:$AA$1,0)) -> 615.82 | D27: =INDEX(Annual!$A:$AA,MATCH($A27,Annual!$A:$A,0),MATCH(D$20,Annual!$A$1:$AA$1,0)) -> 619.68 | E27: =INDEX(Annual!$A:$AA,MATCH($A27,Annual!$A:$A,0),MATCH(E$20,Annual!$A$1:$AA$1,0)) -> 619.68 | F27: =INDEX(Annual!$A:$AA,MATCH($A27,Annual!$A:$A,0),MATCH(F$20,Annual!$A$1:$AA$1,0)) -> 619.68 | G27: =INDEX(Annual!$A:$AA,MATCH($A27,Annual!$A:$A,0),MATCH(G$20,Annual!$A$1:$AA$1,0)) -> 607.70686 | I27: Gross Profit | P27: Revenue (USDm)
B28: Consensus | H28: Gross profit/(loss) | I28: Consensus | O28: Visible Alpha | P28: Consensus
A29: EPS | B29: Blackwattle | C29: =INDEX(Annual!$A:$AA,MATCH($A29,Annual!$A:$A,0),MATCH(C$20,Annual!$A$1:$AA$1,0)) -> 1.8355884 | D29: =INDEX(Annual!$A:$AA,MATCH($A29,Annual!$A:$A,0),MATCH(D$20,Annual!$A$1:$AA$1,0)) -> 3.3639215 | E29: =INDEX(Annual!$A:$AA,MATCH($A29,Annual!$A:$A,0),MATCH(E$20,Annual!$A$1:$AA$1,0)) -> 2.3420885 | F29: =INDEX(Annual!$A:$AA,MATCH($A29,Annual!$A:$A,0),MATCH(F$20,Annual!$A$1:$AA$1,0)) -> 3.3593171 | G29: =INDEX(Annual!$A:$AA,MATCH($A29,Annual!$A:$A,0),MATCH(G$20,Annual!$A$1:$AA$1,0)) -> 4.3799274 | H29: GP-Total Gross Profit | I29: Blackwattle | J29: =INDEX(Annual!$A:$AA,MATCH($H29,Annual!$A:$A,0),MATCH(Value!J$21,Annual!$A$1:$AA$1,0))/1000 -> 7504.886 | K29: =INDEX(Annual!$A:$AA,MATCH($H29,Annual!$A:$A,0),MATCH(Value!K$21,Annual!$A$1:$AA$1,0))/1000 -> 8889.036 | L29: =INDEX(Annual!$A:$AA,MATCH($H29,Annual!$A:$A,0),MATCH(Value!L$21,Annual!$A$1:$AA$1,0))/1000 -> 10321.979 | M29: =INDEX(Annual!$A:$AA,MATCH($H29,Annual!$A:$A,0),MATCH(Value!M$21,Annual!$A$1:$AA$1,0))/1000 -> 12472.487 | N29: =INDEX(Annual!$A:$AA,MATCH($H29,Annual!$A:$A,0),MATCH(Value!N$21,Annual!$A$1:$AA$1,0))/1000 -> 14624.993 | O29: RevTotal Revenue | P29: Blackwattle | Q29: =INDEX(Annual!$A:$AA,MATCH(Value!$O29,Annual!$A:$A,0),MATCH(Value!Q$21,Annual!$A$1:$AA$1,0))/1000 -> 21915.623 | R29: =INDEX(Annual!$A:$AA,MATCH(Value!$O29,Annual!$A:$A,0),MATCH(Value!R$21,Annual!$A$1:$AA$1,0))/1000 -> 24121.053 | S29: =INDEX(Annual!$A:$AA,MATCH(Value!$O29,Annual!$A:$A,0),MATCH(Value!S$21,Annual!$A$1:$AA$1,0))/1000 -> 23989.907 | T29: =INDEX(Annual!$A:$AA,MATCH(Value!$O29,Annual!$A:$A,0),MATCH(Value!T$21,Annual!$A$1:$AA$1,0))/1000 -> 27383.528 | U29: =INDEX(Annual!$A:$AA,MATCH(Value!$O29,Annual!$A:$A,0),MATCH(Value!U$21,Annual!$A$1:$AA$1,0))/1000 -> 31112.66
B30: Difference | I30: Difference | P30: Difference
B32: DPS (UScps) | I32: Adj Operating Income (USDm) | J32: FY-2023 | K32: FY-2024 | L32: FY-2025E | M32: FY-2026E | N32: FY-2027E | O32: Visible Alpha | P32: EV / EBITDA
B33: Consensus | H33: Operating income/(loss), Operating | I33: Consensus | O33: Net debt | P33: Consensus
A34: Dividends | B34: Blackwattle | C34: =INDEX(Annual!$A:$AA,MATCH($A34,Annual!$A:$A,0),MATCH(C$20,Annual!$A$1:$AA$1,0)) -> 0 | D34: =INDEX(Annual!$A:$AA,MATCH($A34,Annual!$A:$A,0),MATCH(D$20,Annual!$A$1:$AA$1,0)) -> 0 | E34: =INDEX(Annual!$A:$AA,MATCH($A34,Annual!$A:$A,0),MATCH(E$20,Annual!$A$1:$AA$1,0)) -> 0 | F34: =INDEX(Annual!$A:$AA,MATCH($A34,Annual!$A:$A,0),MATCH(F$20,Annual!$A$1:$AA$1,0)) -> 0 | G34: =INDEX(Annual!$A:$AA,MATCH($A34,Annual!$A:$A,0),MATCH(G$20,Annual!$A$1:$AA$1,0)) -> 0 | H34: EBITAdjusted Operating Income, EBITA (non-GAAP, as guided to) | I34: Blackwattle | J34: =INDEX(Annual!$A:$AA,MATCH($H34,Annual!$A:$A,0),MATCH(Value!J$21,Annual!$A$1:$AA$1,0))/1000 -> 351.351 | K34: =INDEX(Annual!$A:$AA,MATCH($H34,Annual!$A:$A,0),MATCH(Value!K$21,Annual!$A$1:$AA$1,0))/1000 -> 1608.79 | L34: =INDEX(Annual!$A:$AA,MATCH($H34,Annual!$A:$A,0),MATCH(Value!L$21,Annual!$A$1:$AA$1,0))/1000 -> 2101.7236 | M34: =INDEX(Annual!$A:$AA,MATCH($H34,Annual!$A:$A,0),MATCH(Value!M$21,Annual!$A$1:$AA$1,0))/1000 -> 3048.705 | N34: =INDEX(Annual!$A:$AA,MATCH($H34,Annual!$A:$A,0),MATCH(Value!N$21,Annual!$A$1:$AA$1,0))/1000 -> 3888.2195 | O34: Net debt | P34: Blackwattle | Q34: =(INDEX(Annual!$A:$AA,MATCH(Value!$O34,Annual!$A:$A,0),MATCH(Value!Q$21,Annual!$A$1:$AA$1,0))/1000+C27*$G$5)/Q24 -> 20.594743 | R34: =(INDEX(Annual!$A:$AA,MATCH(Value!$O34,Annual!$A:$A,0),MATCH(Value!R$21,Annual!$A$1:$AA$1,0))/1000+D27*$G$5)/R24 -> 11.723943 | S34: =(INDEX(Annual!$A:$AA,MATCH(Value!$O34,Annual!$A:$A,0),MATCH(Value!S$21,Annual!$A$1:$AA$1,0))/1000+E27*$G$5)/S24 -> 9.7708398 | T34: =(INDEX(Annual!$A:$AA,MATCH(Value!$O34,Annual!$A:$A,0),MATCH(Value!T$21,Annual!$A$1:$AA$1,0))/1000+F27*$G$5)/T24 -> 7.1964628 | U34: =(INDEX(Annual!$A:$AA,MATCH(Value!$O34,Annual!$A:$A,0),MATCH(Value!U$21,Annual!$A$1:$AA$1,0))/1000+G27*$G$5)/U24 -> 5.7067189
B35: Dividend Yield | I35: Difference | P35: Difference
J38: PE | L38: EV/EBITDA | N38: EV/Sales | O38: EBITDA Growth | P38: EBITDA margin | Q38: EBITDA margin | R38: Revenue Growth | S38: EBIT margin | T38: Rule of 40 | U38: Market Cap | V38: Dividend Yield | W38: Stock
J39: FY1 | K39: FY2 | L39: FY1 | M39: FY2 | N39: NTM | O39: FY0-3 CAGR | P39: FY1 | Q39: FY3 | R39: FY0-3 CAGR | S39: FY3 | T39: FY3 | U39: AUDm | V39: NTM | W39: Code
I40: Block Inc | J40: 27.9x | K40: 19.9x | L40: 12.5x | M40: 10.2x | N40: 1.6x | O40: 0.203 | P40: #VALUE! | Q40: #VALUE! | R40: #VALUE! | S40: #VALUE! | T40: #VALUE! | U40: 66828 | V40: 0 | W40: XYZ
I41: Zip Co Ltd | J41: 58.9x | K41: 38.4x | L41: 39.8x | M41: 29.7x | N41: 5.9x | O41: 0.431 | P41: #VALUE! | Q41: #VALUE! | R41: #VALUE! | S41: #VALUE! | T41: #VALUE! | U41: 5835 | V41: 0 | W41: ZIP.AX
I43: US fintech neobanks
I44: Chime Financial Inc | J44: NULL | K44: NULL | L44: 93.9x | M44: 30.8x | N44: 3.1x | O44: #VALUE! | P44: #VALUE! | Q44: #VALUE! | R44: #VALUE! | S44: #VALUE! | T44: #VALUE! | U44: 13198 | V44: 0 | W44: CHYM.O
I45: SoFi Technologies Inc | J45: 85.0x | K45: 48.3x | L45: 34.4x | M45: 23.7x | N45: 8.3x | O45: 0.411 | P45: #VALUE! | Q45: #VALUE! | R45: #VALUE! | S45: #VALUE! | T45: #VALUE! | U45: 47406 | V45: 0 | W45: SOFI.O
I46: eToro Group Ltd | J46: 19.9x | K46: 18.1x | L46: 2.9x | M46: 2.6x | N46: 1.0x | O46: #VALUE! | P46: #VALUE! | Q46: #VALUE! | R46: #VALUE! | S46: #VALUE! | T46: #VALUE! | U46: 3017 | V46: 0 | W46: ETOR.O
I47: Robinhood Markets Inc | J47: 69.5x | K47: 55.0x | L47: 44.2x | M47: 34.6x | N47: 21.1x | O47: 0.341 | P47: #VALUE! | Q47: #VALUE! | R47: #VALUE! | S47: #VALUE! | T47: #VALUE! | U47: 153790 | V47: 0 | W47: HOOD.O
I49: Aus Tech/SaaS
I50: Objective Corporation Ltd | J50: 53.1x | K50: 46.9x | L50: 35.2x | M50: 30.3x | N50: 13.2x | O50: 0.14 | P50: #VALUE! | Q50: #VALUE! | R50: #VALUE! | S50: #VALUE! | T50: #VALUE! | U50: 1940 | V50: 0.012 | W50: OCL.AX
I51: TechnologyOne Ltd | J51: 89.5x | K51: 75.0x | L51: 48.0x | M51: 40.5x | N51: 18.0x | O51: 0.191 | P51: #VALUE! | Q51: #VALUE! | R51: #VALUE! | S51: #VALUE! | T51: #VALUE! | U51: 12460 | V51: 0.008 | W51: TNE.AX
I52: Pro Medicus Ltd | J52: 200.3x | K52: 149.3x | L52: 136.8x | M52: 102.9x | N52: 100.1x | O52: 0.328 | P52: #VALUE! | Q52: #VALUE! | R52: #VALUE! | S52: #VALUE! | T52: #VALUE! | U52: 30928 | V52: 0.003 | W52: PME.AX
I53: Readytech Holdings Ltd | J53: 29.6x | K53: 17.9x | L53: 7.2x | M53: 6.2x | N53: 2.2x | O53: 0.121 | P53: #VALUE! | Q53: #VALUE! | R53: #VALUE! | S53: #VALUE! | T53: #VALUE! | U53: 266 | V53: 0 | W53: RDY.AX
I54: RPMGlobal Holdings Ltd | J54: 67.8x | K54: 52.5x | L54: 43.3x | M54: 32.5x | N54: 10.5x | O54: 0.403 | P54: #VALUE! | Q54: #VALUE! | R54: #VALUE! | S54: #VALUE! | T54: #VALUE! | U54: 1026 | V54: 0 | W54: RUL.AX
I55: WiseTech Global Ltd | J55: 77.2x | K55: 57.0x | L55: 36.2x | M55: 27.4x | N55: 14.4x | O55: 0.332 | P55: #VALUE! | Q55: #VALUE! | R55: #VALUE! | S55: #VALUE! | T55: #VALUE! | U55: 31766 | V55: 0.003 | W55: WTC.AX
I56: Siteminder Ltd | J56: 1059.6x | K56: 102.9x | L56: 57.6x | M56: 34.3x | N56: 6.4x | O56: 0.802 | P56: #VALUE! | Q56: #VALUE! | R56: #VALUE! | S56: #VALUE! | T56: #VALUE! | U56: 1950 | V56: 0 | W56: SDR.AX
I57: Xero Ltd | J57: 90.9x | K57: 71.7x | L57: 37.5x | M57: 29.5x | N57: 10.1x | O57: 0.245 | P57: #VALUE! | Q57: #VALUE! | R57: #VALUE! | S57: #VALUE! | T57: #VALUE! | U57: 26822 | V57: #VALUE! | W57: XRO.AX
I58: Megaport Ltd | J58: NULL | K58: NULL | L58: 48.8x | M58: 35.5x | N58: 8.4x | O58: 0.167 | P58: #VALUE! | Q58: #VALUE! | R58: #VALUE! | S58: #VALUE! | T58: #VALUE! | U58: 2409 | V58: 0 | W58: MP1.AX
I59: Life360 Inc | J59: 130.0x | K59: 85.3x | L59: 97.2x | M59: 65.8x | N59: 13.5x | O59: 0.576 | P59: #VALUE! | Q59: #VALUE! | R59: #VALUE! | S59: #VALUE! | T59: #VALUE! | U59: 11541 | V59: 0 | W59: 360.AX
I60: Siteminder Ltd | J60: 1059.6x | K60: 102.9x | L60: 57.6x | M60: 34.3x | N60: 6.4x | O60: 0.802 | P60: #VALUE! | Q60: #VALUE! | R60: #VALUE! | S60: #VALUE! | T60: #VALUE! | U60: 1950 | V60: 0 | W60: SDR.AX
I61: MEDIAN | J61: 90.2x | K61: 73.4x | L61: 48.0x | M61: 34.3x | N61: 10.5x | O61: 0.328 | P61: #VALUE! | Q61: #VALUE! | R61: #VALUE! | S61: #VALUE! | T61: #VALUE! | U61: 2409 | V61: #VALUE!
I63: Global Payments/Fintech
I64: PayPal Holdings Inc | J64: 12.7x | K64: 11.5x | L64: 9.3x | M64: 8.7x | N64: 1.9x | O64: 0.065 | P64: #VALUE! | Q64: #VALUE! | R64: #VALUE! | S64: #VALUE! | T64: #VALUE! | U64: 96142 | V64: 0 | W64: PYPL.O
I65: Global Payments Inc | J65: 7.0x | K65: 6.2x | L65: 7.8x | M65: 7.3x | N65: 3.7x | O65: 0.037 | P65: #VALUE! | Q65: #VALUE! | R65: #VALUE! | S65: #VALUE! | T65: #VALUE! | U65: 31152 | V65: 0.012 | W65: GPN.N
I66: Shopify Inc | J66: 99.5x | K66: 79.0x | L66: 95.0x | M66: 71.7x | N66: 13.8x | O66: 0.332 | P66: #VALUE! | Q66: #VALUE! | R66: #VALUE! | S66: #VALUE! | T66: #VALUE! | U66: 280345 | V66: 0 | W66: SHOP.K
I67: Affirm Holdings Inc | J67: 102.0x | K67: 55.2x | L67: 31.3x | M67: 25.6x | N67: 7.9x | O67: 0.285 | P67: #VALUE! | Q67: #VALUE! | R67: #VALUE! | S67: #VALUE! | T67: #VALUE! | U67: 40703 | V67: 0 | W67: AFRM.O
I68: Capital One Financial Corp | J68: 12.8x | K68: 11.4x | L68: NULL | M68: NULL | N68: 3.3x | O68: #VALUE! | P68: #VALUE! | Q68: #VALUE! | R68: #VALUE! | S68: #VALUE! | T68: #VALUE! | U68: 215277 | V68: 0.011 | W68: COF.N
I69: Toast Inc | J69: 82.0x | K69: 50.8x | L69: 37.3x | M69: 27.6x | N69: 3.1x | O69: 0.431 | P69: #VALUE! | Q69: #VALUE! | R69: #VALUE! | S69: #VALUE! | T69: #VALUE! | U69: 35040 | V69: 0 | W69: TOST.K
I70: Lightspeed Commerce Inc | J70: 27.7x | K70: 17.0x | L70: 17.2x | M70: 12.6x | N70: 0.9x | O70: 0.351 | P70: #VALUE! | Q70: #VALUE! | R70: #VALUE! | S70: #VALUE! | T70: #VALUE! | U70: 2465 | V70: 0 | W70: LSPD.TO
I71: Fiserv Inc | J71: 13.2x | K71: 11.3x | L71: 9.8x | M71: 9.0x | N71: 4.5x | O71: 0.096 | P71: #VALUE! | Q71: #VALUE! | R71: #VALUE! | S71: #VALUE! | T71: #VALUE! | U71: 109847 | V71: 0 | W71: FI.N
I72: MEDIAN | J72: 20.4x | K72: 14.2x | L72: 17.2x | M72: 12.6x | N72: 3.5x | O72: #VALUE! | P72: #VALUE! | Q72: #VALUE! | R72: #VALUE! | S72: #VALUE! | T72: #VALUE! | U72: 68422 | V72: 0
I74: US banks
I75: Morgan Stanley | J75: 17.6x | K75: 16.3x | L75: NULL | M75: NULL | N75: 8.5x | O75: #VALUE! | P75: #VALUE! | Q75: #VALUE! | R75: #VALUE! | S75: #VALUE! | T75: #VALUE! | U75: 375585 | V75: 0.026 | W75: MS.N
I76: JPMorgan Chase & Co | J76: 15.7x | K76: 15.1x | L76: NULL | M76: NULL | N76: 8.4x | O76: #VALUE! | P76: #VALUE! | Q76: #VALUE! | R76: #VALUE! | S76: #VALUE! | T76: #VALUE! | U76: 1269637 | V76: 0.018 | W76: JPM.N
I77: MEDIAN | J77: 16.6x | K77: 15.7x | L77: #NUM! | M77: #NUM! | N77: 8.5x | O77: #VALUE! | P77: #VALUE! | Q77: #VALUE! | R77: #VALUE! | S77: #VALUE! | T77: #VALUE! | U77: 822611 | V77: 0.022

Sheet Annual
B1: XYZ Model Summary | E1: 2014 | F1: 2015 | G1: 2016 | H1: 2017 | I1: 2018 | J1: 2019 | K1: 2020 | L1: 2021 | M1: 2022 | N1: 2023 | O1: 2024 | P1: 2025 | Q1: 2026 | R1: 2027 | S1: 2028 | T1: 2029 | U1: 2030 | V1: 2031 | W1: 2032 | X1: 2033 | Y1: 2034 | Z1: 2035 | AB1: Earnings changes=>
E2: Actual ----------> | P2: Forecast -----> | AC2: Forecast ----->
C3: Units | E3: FY14A | F3: FY15A | G3: FY16A | H3: FY17A | I3: FY18A | J3: FY19A | K3: FY20A | L3: FY21A | M3: FY22A | N3: FY23A | O3: FY24A | P3: FY25E | Q3: FY26E | R3: FY27E | S3: FY28E | T3: FY29E | U3: FY30E | V3: FY31E | W3: FY32E | X3: FY33E | Y3: FY34E | Z3: FY35E | AC3: FY25E | AE3: FY26E
B4: P &L | I4: Dec-YE | J4: Dec-YE | K4: Dec-YE | L4: Dec-YE | M4: Dec-YE | N4: Dec-YE | O4: Dec-YE | P4: Dec-YE | Q4: Dec-YE | R4: Dec-YE | S4: Dec-YE | T4: Dec-YE | U4: Dec-YE | V4: Dec-YE | W4: Dec-YE | X4: Dec-YE | Y4: Dec-YE | Z4: Dec-YE | AC4: Dec-YE | AE4: Dec-YE
B6: Revenue (GAAP, as per guidance) | N6: 0 | O6: 0
A7: RevSquare | B7: Square | J7: 3461988 | K7: 3529192 | L7: 5193347 | M7: 6294138 | N7: 7033383 | O7: =INDEX(Qrtly!$A:$BH,MATCH(Annual!$A7,Qrtly!$A:$A,0),MATCH("1Q"&RIGHT(Annual!O$1,2),Qrtly!$A$3:$BH$3,0))+INDEX(Qrtly!$A:$BH,MATCH(Annual!$A7,Qrtly!$A:$A,0),MATCH("2Q"&RIGHT(Annual!O$1,2),Qrtly!$A$3:$BH$3,0))+INDEX(Qrtly!$A:$BH,MATCH(Annual!$A7,Qrtly!$A:$A,0),MATCH("3Q"&RIGHT(Annual!O$1,2),Qrtly!$A$3:$BH$3,0))+INDEX(Qrtly!$A:$BH,MATCH(Annual!$A7,Qrtly!$A:$A,0),MATCH("4Q"&RIGHT(Annual!O$1,2),Qrtly!$A$3:$BH$3,0)) -> 7681656 | P7: =INDEX(Qrtly!$A:$BH,MATCH(Annual!$A7,Qrtly!$A:$A,0),MATCH("1Q"&RIGHT(Annual!P$1,2),Qrtly!$A$3:$BH$3,0))+INDEX(Qrtly!$A:$BH,MATCH(Annual!$A7,Qrtly!$A:$A,0),MATCH("2Q"&RIGHT(Annual!P$1,2),Qrtly!$A$3:$BH$3,0))+INDEX(Qrtly!$A:$BH,MATCH(Annual!$A7,Qrtly!$A:$A,0),MATCH("3Q"&RIGHT(Annual!P$1,2),Qrtly!$A$3:$BH$3,0))+INDEX(Qrtly!$A:$BH,MATCH(Annual!$A7,Qrtly!$A:$A,0),MATCH("4Q"&RIGHT(Annual!P$1,2),Qrtly!$A$3:$BH$3,0)) -> 8477414.6 | Q7: =INDEX(Qrtly!$A:$BH,MATCH(Annual!$A7,Qrtly!$A:$A,0),MATCH("1Q"&RIGHT(Annual!Q$1,2),Qrtly!$A$3:$BH$3,0))+INDEX(Qrtly!$A:$BH,MATCH(Annual!$A7,Qrtly!$A:$A,0),MATCH("2Q"&RIGHT(Annual!Q$1,2),Qrtly!$A$3:$BH$3,0))+INDEX(Qrtly!$A:$BH,MATCH(Annual!$A7,Qrtly!$A:$A,0),MATCH("3Q"&RIGHT(Annual!Q$1,2),Qrtly!$A$3:$BH$3,0))+INDEX(Qrtly!$A:$BH,MATCH(Annual!$A7,Qrtly!$A:$A,0),MATCH("4Q"&RIGHT(Annual!Q$1,2),Qrtly!$A$3:$BH$3,0)) -> 9638032.8 | R7: =INDEX(Qrtly!$A:$BH,MATCH(Annual!$A7,Qrtly!$A:$A,0),MATCH("1Q"&RIGHT(Annual!R$1,2),Qrtly!$A$3:$BH$3,0))+INDEX(Qrtly!$A:$BH,MATCH(Annual!$A7,Qrtly!$A:$A,0),MATCH("2Q"&RIGHT(Annual!R$1,2),Qrtly!$A$3:$BH$3,0))+INDEX(Qrtly!$A:$BH,MATCH(Annual!$A7,Qrtly!$A:$A,0),MATCH("3Q"&RIGHT(Annual!R$1,2),Qrtly!$A$3:$BH$3,0))+INDEX(Qrtly!$A:$BH,MATCH(Annual!$A7,Qrtly!$A:$A,0),MATCH("4Q"&RIGHT(Annual!R$1,2),Qrtly!$A$3:$BH$3,0)) -> 10908141 | S7: =INDEX(Qrtly!$A:$BH,MATCH(Annual!$A7,Qrtly!$A:$A,0),MATCH("1Q"&RIGHT(Annual!S$1,2),Qrtly!$A$3:$BH$3,0))+INDEX(Qrtly!$A:$BH,MATCH(Annual!$A7,Qrtly!$A:$A,0),MATCH("2Q"&RIGHT(Annual!S$1,2),Qrtly!$A$3:$BH$3,0))+INDEX(Qrtly!$A:$BH,MATCH(Annual!$A7,Qrtly!$A:$A,0),MATCH("3Q"&RIGHT(Annual!S$1,2),Qrtly!$A$3:$BH$3,0))+INDEX(Qrtly!$A:$BH,MATCH(Annual!$A7,Qrtly!$A:$A,0),MATCH("4Q"&RIGHT(Annual!S$1,2),Qrtly!$A$3:$BH$3,0)) -> 12360525 | T7: =INDEX(Qrtly!$A:$BH,MATCH(Annual!$A7,Qrtly!$A:$A,0),MATCH("1Q"&RIGHT(Annual!T$1,2),Qrtly!$A$3:$BH$3,0))+INDEX(Qrtly!$A:$BH,MATCH(Annual!$A7,Qrtly!$A:$A,0),MATCH("2Q"&RIGHT(Annual!T$1,2),Qrtly!$A$3:$BH$3,0))+INDEX(Qrtly!$A:$BH,MATCH(Annual!$A7,Qrtly!$A:$A,0),MATCH("3Q"&RIGHT(Annual!T$1,2),Qrtly!$A$3:$BH$3,0))+INDEX(Qrtly!$A:$BH,MATCH(Annual!$A7,Qrtly!$A:$A,0),MATCH("4Q"&RIGHT(Annual!T$1,2),Qrtly!$A$3:$BH$3,0)) -> 13761987 | U7: =INDEX(Qrtly!$A:$BH,MATCH(Annual!$A7,Qrtly!$A:$A,0),MATCH("1Q"&RIGHT(Annual!U$1,2),Qrtly!$A$3:$BH$3,0))+INDEX(Qrtly!$A:$BH,MATCH(Annual!$A7,Qrtly!$A:$A,0),MATCH("2Q"&RIGHT(Annual!U$1,2),Qrtly!$A$3:$BH$3,0))+INDEX(Qrtly!$A:$BH,MATCH(Annual!$A7,Qrtly!$A:$A,0),MATCH("3Q"&RIGHT(Annual!U$1,2),Qrtly!$A$3:$BH$3,0))+INDEX(Qrtly!$A:$BH,MATCH(Annual!$A7,Qrtly!$A:$A,0),MATCH("4Q"&RIGHT(Annual!U$1,2),Qrtly!$A$3:$BH$3,0)) -> 15346426 | V7: =INDEX(Qrtly!$A:$BH,MATCH(Annual!$A7,Qrtly!$A:$A,0),MATCH("1Q"&RIGHT(Annual!V$1,2),Qrtly!$A$3:$BH$3,0))+INDEX(Qrtly!$A:$BH,MATCH(Annual!$A7,Qrtly!$A:$A,0),MATCH("2Q"&RIGHT(Annual!V$1,2),Qrtly!$A$3:$BH$3,0))+INDEX(Qrtly!$A:$BH,MATCH(Annual!$A7,Qrtly!$A:$A,0),MATCH("3Q"&RIGHT(Annual!V$1,2),Qrtly!$A$3:$BH$3,0))+INDEX(Qrtly!$A:$BH,MATCH(Annual!$A7,Qrtly!$A:$A,0),MATCH("4Q"&RIGHT(Annual!V$1,2),Qrtly!$A$3:$BH$3,0)) -> 17141516 | ... Z7: =INDEX(Qrtly!$A:$BH,MATCH(Annual!$A7,Qrtly!$A:$A,0),MATCH("1Q"&RIGHT(Annual!Z$1,2),Qrtly!$A$3:$BH$3,0))+INDEX(Qrtly!$A:$BH,MATCH(Annual!$A7,Qrtly!$A:$A,0),MATCH("2Q"&RIGHT(Annual!Z$1,2),Qrtly!$A$3:$BH$3,0))+INDEX(Qrtly!$A:$BH,MATCH(Annual!$A7,Qrtly!$A:$A,0),MATCH("3Q"&RIGHT(Annual!Z$1,2),Qrtly!$A$3:$BH$3,0))+INDEX(Qrtly!$A:$BH,MATCH(Annual!$A7,Qrtly!$A:$A,0),MATCH("4Q"&RIGHT(Annual!Z$1,2),Qrtly!$A$3:$BH$3,0)) -> 27165836 | AC7: 8438950 | AD7: =IF(ISBLANK(AC7),"",INDEX($A7:$AA7,1,MATCH(AC$3,$A$3:$AA$3,0))-AC7) -> 38464.596 | AE7: 9453980.2 | AF7: =IF(ISBLANK(AE7),"",INDEX($A7:$AA7,1,MATCH(AE$3,$A$3:$AA$3,0))-AE7) -> 184052.69
A8: RevCash App | B8: Cash App | J8: 1105599 | K8: 5968386 | L8: 12315498 | M8: 11031802 | N8: 14681687 | O8: =INDEX(Qrtly!$A:$BH,MATCH(Annual!$A8,Qrtly!$A:$A,0),MATCH("1Q"&RIGHT(Annual!O$1,2),Qrtly!$A$3:$BH$3,0))+INDEX(Qrtly!$A:$BH,MATCH(Annual!$A8,Qrtly!$A:$A,0),MATCH("2Q"&RIGHT(Annual!O$1,2),Qrtly!$A$3:$BH$3,0))+INDEX(Qrtly!$A:$BH,MATCH(Annual!$A8,Qrtly!$A:$A,0),MATCH("3Q"&RIGHT(Annual!O$1,2),Qrtly!$A$3:$BH$3,0))+INDEX(Qrtly!$A:$BH,MATCH(Annual!$A8,Qrtly!$A:$A,0),MATCH("4Q"&RIGHT(Annual!O$1,2),Qrtly!$A$3:$BH$3,0)) -> 16247880 | P8: =INDEX(Qrtly!$A:$BH,MATCH(Annual!$A8,Qrtly!$A:$A,0),MATCH("1Q"&RIGHT(Annual!P$1,2),Qrtly!$A$3:$BH$3,0))+INDEX(Qrtly!$A:$BH,MATCH(Annual!$A8,Qrtly!$A:$A,0),MATCH("2Q"&RIGHT(Annual!P$1,2),Qrtly!$A$3:$BH$3,0))+INDEX(Qrtly!$A:$BH,MATCH(Annual!$A8,Qrtly!$A:$A,0),MATCH("3Q"&RIGHT(Annual!P$1,2),Qrtly!$A$3:$BH$3,0))+INDEX(Qrtly!$A:$BH,MATCH(Annual!$A8,Qrtly!$A:$A,0),MATCH("4Q"&RIGHT(Annual!P$1,2),Qrtly!$A$3:$BH$3,0)) -> 15266139 | Q8: =INDEX(Qrtly!$A:$BH,MATCH(Annual!$A8,Qrtly!$A:$A,0),MATCH("1Q"&RIGHT(Annual!Q$1,2),Qrtly!$A$3:$BH$3,0))+INDEX(Qrtly!$A:$BH,MATCH(Annual!$A8,Qrtly!$A:$A,0),MATCH("2Q"&RIGHT(Annual!Q$1,2),Qrtly!$A$3:$BH$3,0))+INDEX(Qrtly!$A:$BH,MATCH(Annual!$A8,Qrtly!$A:$A,0),MATCH("3Q"&RIGHT(Annual!Q$1,2),Qrtly!$A$3:$BH$3,0))+INDEX(Qrtly!$A:$BH,MATCH(Annual!$A8,Qrtly!$A:$A,0),MATCH("4Q"&RIGHT(Annual!Q$1,2),Qrtly!$A$3:$BH$3,0)) -> 17382453 | R8: =INDEX(Qrtly!$A:$BH,MATCH(Annual!$A8,Qrtly!$A:$A,0),MATCH("1Q"&RIGHT(Annual!R$1,2),Qrtly!$A$3:$BH$3,0))+INDEX(Qrtly!$A:$BH,MATCH(Annual!$A8,Qrtly!$A:$A,0),MATCH("2Q"&RIGHT(Annual!R$1,2),Qrtly!$A$3:$BH$3,0))+INDEX(Qrtly!$A:$BH,MATCH(Annual!$A8,Qrtly!$A:$A,0),MATCH("3Q"&RIGHT(Annual!R$1,2),Qrtly!$A$3:$BH$3,0))+INDEX(Qrtly!$A:$BH,MATCH(Annual!$A8,Qrtly!$A:$A,0),MATCH("4Q"&RIGHT(Annual!R$1,2),Qrtly!$A$3:$BH$3,0)) -> 19768868 | S8: =INDEX(Qrtly!$A:$BH,MATCH(Annual!$A8,Qrtly!$A:$A,0),MATCH("1Q"&RIGHT(Annual!S$1,2),Qrtly!$A$3:$BH$3,0))+INDEX(Qrtly!$A:$BH,MATCH(Annual!$A8,Qrtly!$A:$A,0),MATCH("2Q"&RIGHT(Annual!S$1,2),Qrtly!$A$3:$BH$3,0))+INDEX(Qrtly!$A:$BH,MATCH(Annual!$A8,Qrtly!$A:$A,0),MATCH("3Q"&RIGHT(Annual!S$1,2),Qrtly!$A$3:$BH$3,0))+INDEX(Qrtly!$A:$BH,MATCH(Annual!$A8,Qrtly!$A:$A,0),MATCH("4Q"&RIGHT(Annual!S$1,2),Qrtly!$A$3:$BH$3,0)) -> 22486290 | T8: =INDEX(Qrtly!$A:$BH,MATCH(Annual!$A8,Qrtly!$A:$A,0),MATCH("1Q"&RIGHT(Annual!T$1,2),Qrtly!$A$3:$BH$3,0))+INDEX(Qrtly!$A:$BH,MATCH(Annual!$A8,Qrtly!$A:$A,0),MATCH("2Q"&RIGHT(Annual!T$1,2),Qrtly!$A$3:$BH$3,0))+INDEX(Qrtly!$A:$BH,MATCH(Annual!$A8,Qrtly!$A:$A,0),MATCH("3Q"&RIGHT(Annual!T$1,2),Qrtly!$A$3:$BH$3,0))+INDEX(Qrtly!$A:$BH,MATCH(Annual!$A8,Qrtly!$A:$A,0),MATCH("4Q"&RIGHT(Annual!T$1,2),Qrtly!$A$3:$BH$3,0)) -> 25581080 | U8: =INDEX(Qrtly!$A:$BH,MATCH(Annual!$A8,Qrtly!$A:$A,0),MATCH("1Q"&RIGHT(Annual!U$1,2),Qrtly!$A$3:$BH$3,0))+INDEX(Qrtly!$A:$BH,MATCH(Annual!$A8,Qrtly!$A:$A,0),MATCH("2Q"&RIGHT(Annual!U$1,2),Qrtly!$A$3:$BH$3,0))+INDEX(Qrtly!$A:$BH,MATCH(Annual!$A8,Qrtly!$A:$A,0),MATCH("3Q"&RIGHT(Annual!U$1,2),Qrtly!$A$3:$BH$3,0))+INDEX(Qrtly!$A:$BH,MATCH(Annual!$A8,Qrtly!$A:$A,0),MATCH("4Q"&RIGHT(Annual!U$1,2),Qrtly!$A$3:$BH$3,0)) -> 29106153 | V8: =INDEX(Qrtly!$A:$BH,MATCH(Annual!$A8,Qrtly!$A:$A,0),MATCH("1Q"&RIGHT(Annual!V$1,2),Qrtly!$A$3:$BH$3,0))+INDEX(Qrtly!$A:$BH,MATCH(Annual!$A8,Qrtly!$A:$A,0),MATCH("2Q"&RIGHT(Annual!V$1,2),Qrtly!$A$3:$BH$3,0))+INDEX(Qrtly!$A:$BH,MATCH(Annual!$A8,Qrtly!$A:$A,0),MATCH("3Q"&RIGHT(Annual!V$1,2),Qrtly!$A$3:$BH$3,0))+INDEX(Qrtly!$A:$BH,MATCH(Annual!$A8,Qrtly!$A:$A,0),MATCH("4Q"&RIGHT(Annual!V$1,2),Qrtly!$A$3:$BH$3,0)) -> 33121913 | ... Z8: =INDEX(Qrtly!$A:$BH,MATCH(Annual!$A8,Qrtly!$A:$A,0),MATCH("1Q"&RIGHT(Annual!Z$1,2),Qrtly!$A$3:$BH$3,0))+INDEX(Qrtly!$A:$BH,MATCH(Annual!$A8,Qrtly!$A:$A,0),MATCH("2Q"&RIGHT(Annual!Z$1,2),Qrtly!$A$3:$BH$3,0))+INDEX(Qrtly!$A:$BH,MATCH(Annual!$A8,Qrtly!$A:$A,0),MATCH("3Q"&RIGHT(Annual!Z$1,2),Qrtly!$A$3:$BH$3,0))+INDEX(Qrtly!$A:$BH,MATCH(Annual!$A8,Qrtly!$A:$A,0),MATCH("4Q"&RIGHT(Annual!Z$1,2),Qrtly!$A$3:$BH$3,0)) -> 55626213 | AC8: 17223573 | AD8: =IF(ISBLANK(AC8),"",INDEX($A8:$AA8,1,MATCH(AC$3,$A$3:$AA$3,0))-AC8) -> -1957433.9 | AE8: 20980789 | AF8: =IF(ISBLANK(AE8),"",INDEX($A8:$AA8,1,MATCH(AE$3,$A$3:$AA$3,0))-AE8) -> -3598336.1
A9: RevCorporate & Other | B9: Corporate & Other | J9: 145913 | K9: 0 | L9: 152358 | M9: 205647 | N9: 200554 | O9: =INDEX(Qrtly!$A:$BH,MATCH(Annual!$A9,Qrtly!$A:$A,0),MATCH("1Q"&RIGHT(Annual!O$1,2),Qrtly!$A$3:$BH$3,0))+INDEX(Qrtly!$A:$BH,MATCH(Annual!$A9,Qrtly!$A:$A,0),MATCH("2Q"&RIGHT(Annual!O$1,2),Qrtly!$A$3:$BH$3,0))+INDEX(Qrtly!$A:$BH,MATCH(Annual!$A9,Qrtly!$A:$A,0),MATCH("3Q"&RIGHT(Annual!O$1,2),Qrtly!$A$3:$BH$3,0))+INDEX(Qrtly!$A:$BH,MATCH(Annual!$A9,Qrtly!$A:$A,0),MATCH("4Q"&RIGHT(Annual!O$1,2),Qrtly!$A$3:$BH$3,0)) -> 191517 | P9: =INDEX(Qrtly!$A:$BH,MATCH(Annual!$A9,Qrtly!$A:$A,0),MATCH("1Q"&RIGHT(Annual!P$1,2),Qrtly!$A$3:$BH$3,0))+INDEX(Qrtly!$A:$BH,MATCH(Annual!$A9,Qrtly!$A:$A,0),MATCH("2Q"&RIGHT(Annual!P$1,2),Qrtly!$A$3:$BH$3,0))+INDEX(Qrtly!$A:$BH,MATCH(Annual!$A9,Qrtly!$A:$A,0),MATCH("3Q"&RIGHT(Annual!P$1,2),Qrtly!$A$3:$BH$3,0))+INDEX(Qrtly!$A:$BH,MATCH(Annual!$A9,Qrtly!$A:$A,0),MATCH("4Q"&RIGHT(Annual!P$1,2),Qrtly!$A$3:$BH$3,0)) -> 246353 | Q9: =INDEX(Qrtly!$A:$BH,MATCH(Annual!$A9,Qrtly!$A:$A,0),MATCH("1Q"&RIGHT(Annual!Q$1,2),Qrtly!$A$3:$BH$3,0))+INDEX(Qrtly!$A:$BH,MATCH(Annual!$A9,Qrtly!$A:$A,0),MATCH("2Q"&RIGHT(Annual!Q$1,2),Qrtly!$A$3:$BH$3,0))+INDEX(Qrtly!$A:$BH,MATCH(Annual!$A9,Qrtly!$A:$A,0),MATCH("3Q"&RIGHT(Annual!Q$1,2),Qrtly!$A$3:$BH$3,0))+INDEX(Qrtly!$A:$BH,MATCH(Annual!$A9,Qrtly!$A:$A,0),MATCH("4Q"&RIGHT(Annual!Q$1,2),Qrtly!$A$3:$BH$3,0)) -> 363042.6 | R9: =INDEX(Qrtly!$A:$BH,MATCH(Annual!$A9,Qrtly!$A:$A,0),MATCH("1Q"&RIGHT(Annual!R$1,2),Qrtly!$A$3:$BH$3,0))+INDEX(Qrtly!$A:$BH,MATCH(Annual!$A9,Qrtly!$A:$A,0),MATCH("2Q"&RIGHT(Annual!R$1,2),Qrtly!$A$3:$BH$3,0))+INDEX(Qrtly!$A:$BH,MATCH(Annual!$A9,Qrtly!$A:$A,0),MATCH("3Q"&RIGHT(Annual!R$1,2),Qrtly!$A$3:$BH$3,0))+INDEX(Qrtly!$A:$BH,MATCH(Annual!$A9,Qrtly!$A:$A,0),MATCH("4Q"&RIGHT(Annual!R$1,2),Qrtly!$A$3:$BH$3,0)) -> 435651.12 | S9: =INDEX(Qrtly!$A:$BH,MATCH(Annual!$A9,Qrtly!$A:$A,0),MATCH("1Q"&RIGHT(Annual!S$1,2),Qrtly!$A$3:$BH$3,0))+INDEX(Qrtly!$A:$BH,MATCH(Annual!$A9,Qrtly!$A:$A,0),MATCH("2Q"&RIGHT(Annual!S$1,2),Qrtly!$A$3:$BH$3,0))+INDEX(Qrtly!$A:$BH,MATCH(Annual!$A9,Qrtly!$A:$A,0),MATCH("3Q"&RIGHT(Annual!S$1,2),Qrtly!$A$3:$BH$3,0))+INDEX(Qrtly!$A:$BH,MATCH(Annual!$A9,Qrtly!$A:$A,0),MATCH("4Q"&RIGHT(Annual!S$1,2),Qrtly!$A$3:$BH$3,0)) -> 503800.78 | T9: =INDEX(Qrtly!$A:$BH,MATCH(Annual!$A9,Qrtly!$A:$A,0),MATCH("1Q"&RIGHT(Annual!T$1,2),Qrtly!$A$3:$BH$3,0))+INDEX(Qrtly!$A:$BH,MATCH(Annual!$A9,Qrtly!$A:$A,0),MATCH("2Q"&RIGHT(Annual!T$1,2),Qrtly!$A$3:$BH$3,0))+INDEX(Qrtly!$A:$BH,MATCH(Annual!$A9,Qrtly!$A:$A,0),MATCH("3Q"&RIGHT(Annual!T$1,2),Qrtly!$A$3:$BH$3,0))+INDEX(Qrtly!$A:$BH,MATCH(Annual!$A9,Qrtly!$A:$A,0),MATCH("4Q"&RIGHT(Annual!T$1,2),Qrtly!$A$3:$BH$3,0)) -> 528990.81 | U9: =INDEX(Qrtly!$A:$BH,MATCH(Annual!$A9,Qrtly!$A:$A,0),MATCH("1Q"&RIGHT(Annual!U$1,2),Qrtly!$A$3:$BH$3,0))+INDEX(Qrtly!$A:$BH,MATCH(Annual!$A9,Qrtly!$A:$A,0),MATCH("2Q"&RIGHT(Annual!U$1,2),Qrtly!$A$3:$BH$3,0))+INDEX(Qrtly!$A:$BH,MATCH(Annual!$A9,Qrtly!$A:$A,0),MATCH("3Q"&RIGHT(Annual!U$1,2),Qrtly!$A$3:$BH$3,0))+INDEX(Qrtly!$A:$BH,MATCH(Annual!$A9,Qrtly!$A:$A,0),MATCH("4Q"&RIGHT(Annual!U$1,2),Qrtly!$A$3:$BH$3,0)) -> 555440.36 | V9: =INDEX(Qrtly!$A:$BH,MATCH(Annual!$A9,Qrtly!$A:$A,0),MATCH("1Q"&RIGHT(Annual!V$1,2),Qrtly!$A$3:$BH$3,0))+INDEX(Qrtly!$A:$BH,MATCH(Annual!$A9,Qrtly!$A:$A,0),MATCH("2Q"&RIGHT(Annual!V$1,2),Qrtly!$A$3:$BH$3,0))+INDEX(Qrtly!$A:$BH,MATCH(Annual!$A9,Qrtly!$A:$A,0),MATCH("3Q"&RIGHT(Annual!V$1,2),Qrtly!$A$3:$BH$3,0))+INDEX(Qrtly!$A:$BH,MATCH(Annual!$A9,Qrtly!$A:$A,0),MATCH("4Q"&RIGHT(Annual!V$1,2),Qrtly!$A$3:$BH$3,0)) -> 583212.37 | ... Z9: =INDEX(Qrtly!$A:$BH,MATCH(Annual!$A9,Qrtly!$A:$A,0),MATCH("1Q"&RIGHT(Annual!Z$1,2),Qrtly!$A$3:$BH$3,0))+INDEX(Qrtly!$A:$BH,MATCH(Annual!$A9,Qrtly!$A:$A,0),MATCH("2Q"&RIGHT(Annual!Z$1,2),Qrtly!$A$3:$BH$3,0))+INDEX(Qrtly!$A:$BH,MATCH(Annual!$A9,Qrtly!$A:$A,0),MATCH("3Q"&RIGHT(Annual!Z$1,2),Qrtly!$A$3:$BH$3,0))+INDEX(Qrtly!$A:$BH,MATCH(Annual!$A9,Qrtly!$A:$A,0),MATCH("4Q"&RIGHT(Annual!Z$1,2),Qrtly!$A$3:$BH$3,0)) -> 708898.28 | AC9: 258464 | AD9: =IF(ISBLANK(AC9),"",INDEX($A9:$AA9,1,MATCH(AC$3,$A$3:$AA$3,0))-AC9) -> -12111 | AE9: 377575.8 | AF9: =IF(ISBLANK(AE9),"",INDEX($A9:$AA9,1,MATCH(AE$3,$A$3:$AA$3,0))-AE9) -> -14533.2
A10: RevTotal Revenue | B10: Total Revenue | C10: USDk | F10: 1267118 | G10: 1708721 | H10: 2214253 | I10: 3298177 | J10: 4713500 | K10: 9497578 | L10: 17661203 | M10: 17531587 | N10: 21915623 | O10: =INDEX(Qrtly!$A:$BH,MATCH(Annual!$A10,Qrtly!$A:$A,0),MATCH("1Q"&RIGHT(Annual!O$1,2),Qrtly!$A$3:$BH$3,0))+INDEX(Qrtly!$A:$BH,MATCH(Annual!$A10,Qrtly!$A:$A,0),MATCH("2Q"&RIGHT(Annual!O$1,2),Qrtly!$A$3:$BH$3,0))+INDEX(Qrtly!$A:$BH,MATCH(Annual!$A10,Qrtly!$A:$A,0),MATCH("3Q"&RIGHT(Annual!O$1,2),Qrtly!$A$3:$BH$3,0))+INDEX(Qrtly!$A:$BH,MATCH(Annual!$A10,Qrtly!$A:$A,0),MATCH("4Q"&RIGHT(Annual!O$1,2),Qrtly!$A$3:$BH$3,0)) -> 24121053 | P10: =INDEX(Qrtly!$A:$BH,MATCH(Annual!$A10,Qrtly!$A:$A,0),MATCH("1Q"&RIGHT(Annual!P$1,2),Qrtly!$A$3:$BH$3,0))+INDEX(Qrtly!$A:$BH,MATCH(Annual!$A10,Qrtly!$A:$A,0),MATCH("2Q"&RIGHT(Annual!P$1,2),Qrtly!$A$3:$BH$3,0))+INDEX(Qrtly!$A:$BH,MATCH(Annual!$A10,Qrtly!$A:$A,0),MATCH("3Q"&RIGHT(Annual!P$1,2),Qrtly!$A$3:$BH$3,0))+INDEX(Qrtly!$A:$BH,MATCH(Annual!$A10,Qrtly!$A:$A,0),MATCH("4Q"&RIGHT(Annual!P$1,2),Qrtly!$A$3:$BH$3,0)) -> 23989907 | Q10: =INDEX(Qrtly!$A:$BH,MATCH(Annual!$A10,Qrtly!$A:$A,0),MATCH("1Q"&RIGHT(Annual!Q$1,2),Qrtly!$A$3:$BH$3,0))+INDEX(Qrtly!$A:$BH,MATCH(Annual!$A10,Qrtly!$A:$A,0),MATCH("2Q"&RIGHT(Annual!Q$1,2),Qrtly!$A$3:$BH$3,0))+INDEX(Qrtly!$A:$BH,MATCH(Annual!$A10,Qrtly!$A:$A,0),MATCH("3Q"&RIGHT(Annual!Q$1,2),Qrtly!$A$3:$BH$3,0))+INDEX(Qrtly!$A:$BH,MATCH(Annual!$A10,Qrtly!$A:$A,0),MATCH("4Q"&RIGHT(Annual!Q$1,2),Qrtly!$A$3:$BH$3,0)) -> 27383528 | R10: =INDEX(Qrtly!$A:$BH,MATCH(Annual!$A10,Qrtly!$A:$A,0),MATCH("1Q"&RIGHT(Annual!R$1,2),Qrtly!$A$3:$BH$3,0))+INDEX(Qrtly!$A:$BH,MATCH(Annual!$A10,Qrtly!$A:$A,0),MATCH("2Q"&RIGHT(Annual!R$1,2),Qrtly!$A$3:$BH$3,0))+INDEX(Qrtly!$A:$BH,MATCH(Annual!$A10,Qrtly!$A:$A,0),MATCH("3Q"&RIGHT(Annual!R$1,2),Qrtly!$A$3:$BH$3,0))+INDEX(Qrtly!$A:$BH,MATCH(Annual!$A10,Qrtly!$A:$A,0),MATCH("4Q"&RIGHT(Annual!R$1,2),Qrtly!$A$3:$BH$3,0)) -> 31112660 | S10: =INDEX(Qrtly!$A:$BH,MATCH(Annual!$A10,Qrtly!$A:$A,0),MATCH("1Q"&RIGHT(Annual!S$1,2),Qrtly!$A$3:$BH$3,0))+INDEX(Qrtly!$A:$BH,MATCH(Annual!$A10,Qrtly!$A:$A,0),MATCH("2Q"&RIGHT(Annual!S$1,2),Qrtly!$A$3:$BH$3,0))+INDEX(Qrtly!$A:$BH,MATCH(Annual!$A10,Qrtly!$A:$A,0),MATCH("3Q"&RIGHT(Annual!S$1,2),Qrtly!$A$3:$BH$3,0))+INDEX(Qrtly!$A:$BH,MATCH(Annual!$A10,Qrtly!$A:$A,0),MATCH("4Q"&RIGHT(Annual!S$1,2),Qrtly!$A$3:$BH$3,0)) -> 35350615 | T10: =INDEX(Qrtly!$A:$BH,MATCH(Annual!$A10,Qrtly!$A:$A,0),MATCH("1Q"&RIGHT(Annual!T$1,2),Qrtly!$A$3:$BH$3,0))+INDEX(Qrtly!$A:$BH,MATCH(Annual!$A10,Qrtly!$A:$A,0),MATCH("2Q"&RIGHT(Annual!T$1,2),Qrtly!$A$3:$BH$3,0))+INDEX(Qrtly!$A:$BH,MATCH(Annual!$A10,Qrtly!$A:$A,0),MATCH("3Q"&RIGHT(Annual!T$1,2),Qrtly!$A$3:$BH$3,0))+INDEX(Qrtly!$A:$BH,MATCH(Annual!$A10,Qrtly!$A:$A,0),MATCH("4Q"&RIGHT(Annual!T$1,2),Qrtly!$A$3:$BH$3,0)) -> 39872057 | U10: =INDEX(Qrtly!$A:$BH,MATCH(Annual!$A10,Qrtly!$A:$A,0),MATCH("1Q"&RIGHT(Annual!U$1,2),Qrtly!$A$3:$BH$3,0))+INDEX(Qrtly!$A:$BH,MATCH(Annual!$A10,Qrtly!$A:$A,0),MATCH("2Q"&RIGHT(Annual!U$1,2),Qrtly!$A$3:$BH$3,0))+INDEX(Qrtly!$A:$BH,MATCH(Annual!$A10,Qrtly!$A:$A,0),MATCH("3Q"&RIGHT(Annual!U$1,2),Qrtly!$A$3:$BH$3,0))+INDEX(Qrtly!$A:$BH,MATCH(Annual!$A10,Qrtly!$A:$A,0),MATCH("4Q"&RIGHT(Annual!U$1,2),Qrtly!$A$3:$BH$3,0)) -> 45008020 | V10: =INDEX(Qrtly!$A:$BH,MATCH(Annual!$A10,Qrtly!$A:$A,0),MATCH("1Q"&RIGHT(Annual!V$1,2),Qrtly!$A$3:$BH$3,0))+INDEX(Qrtly!$A:$BH,MATCH(Annual!$A10,Qrtly!$A:$A,0),MATCH("2Q"&RIGHT(Annual!V$1,2),Qrtly!$A$3:$BH$3,0))+INDEX(Qrtly!$A:$BH,MATCH(Annual!$A10,Qrtly!$A:$A,0),MATCH("3Q"&RIGHT(Annual!V$1,2),Qrtly!$A$3:$BH$3,0))+INDEX(Qrtly!$A:$BH,MATCH(Annual!$A10,Qrtly!$A:$A,0),MATCH("4Q"&RIGHT(Annual!V$1,2),Qrtly!$A$3:$BH$3,0)) -> 50846642 | ... Z10: =INDEX(Qrtly!$A:$BH,MATCH(Annual!$A10,Qrtly!$A:$A,0),MATCH("1Q"&RIGHT(Annual!Z$1,2),Qrtly!$A$3:$BH$3,0))+INDEX(Qrtly!$A:$BH,MATCH(Annual!$A10,Qrtly!$A:$A,0),MATCH("2Q"&RIGHT(Annual!Z$1,2),Qrtly!$A$3:$BH$3,0))+INDEX(Qrtly!$A:$BH,MATCH(Annual!$A10,Qrtly!$A:$A,0),MATCH("3Q"&RIGHT(Annual!Z$1,2),Qrtly!$A$3:$BH$3,0))+INDEX(Qrtly!$A:$BH,MATCH(Annual!$A10,Qrtly!$A:$A,0),MATCH("4Q"&RIGHT(Annual!Z$1,2),Qrtly!$A$3:$BH$3,0)) -> 83500947 | AC10: 25920987 | AD10: =IF(ISBLANK(AC10),"",INDEX($A10:$AA10,1,MATCH(AC$3,$A$3:$AA$3,0))-AC10) -> -1931080.3 | AE10: 30812345 | AF10: =IF(ISBLANK(AE10),"",INDEX($A10:$AA10,1,MATCH(AE$3,$A$3:$AA$3,0))-AE10) -> -3428816.6
B11: Growth | C11: % YoY | I11: 0.49 | J11: 0.429 | K11: 1.015 | L11: 0.86 | M11: -0.007 | N11: 0.25 | O11: =O10/N10-1 -> 0.10063278 | P11: =P10/O10-1 -> -0.0054370058 | Q11: =Q10/P10-1 -> 0.14146038 | R11: =R10/Q10-1 -> 0.13618158 | S11: =S10/R10-1 -> 0.1362132 | T11: =T10/S10-1 -> 0.12790279 | U11: =U10/T10-1 -> 0.12881107 | V11: =V10/U10-1 -> 0.12972403 | ... Z11: =Z10/Y10-1 -> 0.13342026 | AC11: 0.074620871 | AD11: =IF(ISBLANK(AC11),"",INDEX($A11:$AA11,1,MATCH(AC$3,$A$3:$AA$3,0))-AC11) -> -0.080057877 | AE11: 0.1887026 | AF11: =IF(ISBLANK(AE11),"",INDEX($A11:$AA11,1,MATCH(AE$3,$A$3:$AA$3,0))-AE11) -> -0.04724222
B12: Initial Guidance | C12: USDk | G12: 610000 | H12: 2120000 | I12: 2850000 | J12: 4380000 | K12: 5930000 | AD12: =IF(ISBLANK(AC12),"",INDEX($A12:$AA12,1,MATCH(AC$3,$A$3:$AA$3,0))-AC12) | AF12: =IF(ISBLANK(AE12),"",INDEX($A12:$AA12,1,MATCH(AE$3,$A$3:$AA$3,0))-AE12)
B13: vs guidance | G13: 1.8 | H13: 0.04 | I13: 0.16 | J13: 0.08 | K13: 0.6 | AD13: =IF(ISBLANK(AC13),"",INDEX($A13:$AA13,1,MATCH(AC$3,$A$3:$AA$3,0))-AC13) | AF13: =IF(ISBLANK(AE13),"",INDEX($A13:$AA13,1,MATCH(AE$3,$A$3:$AA$3,0))-AE13)
AD14: =IF(ISBLANK(AC14),"",INDEX($A14:$AA14,1,MATCH(AC$3,$A$3:$AA$3,0))-AC14) | AF14: =IF(ISBLANK(AE14),"",INDEX($A14:$AA14,1,MATCH(AE$3,$A$3:$AA$3,0))-AE14)
B15: Gross Profit (GAAP) | AD15: =IF(ISBLANK(AC15),"",INDEX($A15:$AA15,1,MATCH(AC$3,$A$3:$AA$3,0))-AC15) | AF15: =IF(ISBLANK(AE15),"",INDEX($A15:$AA15,1,MATCH(AE$3,$A$3:$AA$3,0))-AE15)
A16: GP-Square | B16: Square | J16: 1390427 | K16: 1507831 | L16: 2316670 | M16: 2706902 | N16: 3128649 | O16: =INDEX(Qrtly!$A:$BH,MATCH(Annual!$A16,Qrtly!$A:$A,0),MATCH("1Q"&RIGHT(Annual!O$1,2),Qrtly!$A$3:$BH$3,0))+INDEX(Qrtly!$A:$BH,MATCH(Annual!$A16,Qrtly!$A:$A,0),MATCH("2Q"&RIGHT(Annual!O$1,2),Qrtly!$A$3:$BH$3,0))+INDEX(Qrtly!$A:$BH,MATCH(Annual!$A16,Qrtly!$A:$A,0),MATCH("3Q"&RIGHT(Annual!O$1,2),Qrtly!$A$3:$BH$3,0))+INDEX(Qrtly!$A:$BH,MATCH(Annual!$A16,Qrtly!$A:$A,0),MATCH("4Q"&RIGHT(Annual!O$1,2),Qrtly!$A$3:$BH$3,0)) -> 3598912 | P16: =INDEX(Qrtly!$A:$BH,MATCH(Annual!$A16,Qrtly!$A:$A,0),MATCH("1Q"&RIGHT(Annual!P$1,2),Qrtly!$A$3:$BH$3,0))+INDEX(Qrtly!$A:$BH,MATCH(Annual!$A16,Qrtly!$A:$A,0),MATCH("2Q"&RIGHT(Annual!P$1,2),Qrtly!$A$3:$BH$3,0))+INDEX(Qrtly!$A:$BH,MATCH(Annual!$A16,Qrtly!$A:$A,0),MATCH("3Q"&RIGHT(Annual!P$1,2),Qrtly!$A$3:$BH$3,0))+INDEX(Qrtly!$A:$BH,MATCH(Annual!$A16,Qrtly!$A:$A,0),MATCH("4Q"&RIGHT(Annual!P$1,2),Qrtly!$A$3:$BH$3,0)) -> 3964136.9 | Q16: =INDEX(Qrtly!$A:$BH,MATCH(Annual!$A16,Qrtly!$A:$A,0),MATCH("1Q"&RIGHT(Annual!Q$1,2),Qrtly!$A$3:$BH$3,0))+INDEX(Qrtly!$A:$BH,MATCH(Annual!$A16,Qrtly!$A:$A,0),MATCH("2Q"&RIGHT(Annual!Q$1,2),Qrtly!$A$3:$BH$3,0))+INDEX(Qrtly!$A:$BH,MATCH(Annual!$A16,Qrtly!$A:$A,0),MATCH("3Q"&RIGHT(Annual!Q$1,2),Qrtly!$A$3:$BH$3,0))+INDEX(Qrtly!$A:$BH,MATCH(Annual!$A16,Qrtly!$A:$A,0),MATCH("4Q"&RIGHT(Annual!Q$1,2),Qrtly!$A$3:$BH$3,0)) -> 4503213.6 | R16: =INDEX(Qrtly!$A:$BH,MATCH(Annual!$A16,Qrtly!$A:$A,0),MATCH("1Q"&RIGHT(Annual!R$1,2),Qrtly!$A$3:$BH$3,0))+INDEX(Qrtly!$A:$BH,MATCH(Annual!$A16,Qrtly!$A:$A,0),MATCH("2Q"&RIGHT(Annual!R$1,2),Qrtly!$A$3:$BH$3,0))+INDEX(Qrtly!$A:$BH,MATCH(Annual!$A16,Qrtly!$A:$A,0),MATCH("3Q"&RIGHT(Annual!R$1,2),Qrtly!$A$3:$BH$3,0))+INDEX(Qrtly!$A:$BH,MATCH(Annual!$A16,Qrtly!$A:$A,0),MATCH("4Q"&RIGHT(Annual!R$1,2),Qrtly!$A$3:$BH$3,0)) -> 5161113.4 | S16: =INDEX(Qrtly!$A:$BH,MATCH(Annual!$A16,Qrtly!$A:$A,0),MATCH("1Q"&RIGHT(Annual!S$1,2),Qrtly!$A$3:$BH$3,0))+INDEX(Qrtly!$A:$BH,MATCH(Annual!$A16,Qrtly!$A:$A,0),MATCH("2Q"&RIGHT(Annual!S$1,2),Qrtly!$A$3:$BH$3,0))+INDEX(Qrtly!$A:$BH,MATCH(Annual!$A16,Qrtly!$A:$A,0),MATCH("3Q"&RIGHT(Annual!S$1,2),Qrtly!$A$3:$BH$3,0))+INDEX(Qrtly!$A:$BH,MATCH(Annual!$A16,Qrtly!$A:$A,0),MATCH("4Q"&RIGHT(Annual!S$1,2),Qrtly!$A$3:$BH$3,0)) -> 5927203.9 | T16: =INDEX(Qrtly!$A:$BH,MATCH(Annual!$A16,Qrtly!$A:$A,0),MATCH("1Q"&RIGHT(Annual!T$1,2),Qrtly!$A$3:$BH$3,0))+INDEX(Qrtly!$A:$BH,MATCH(Annual!$A16,Qrtly!$A:$A,0),MATCH("2Q"&RIGHT(Annual!T$1,2),Qrtly!$A$3:$BH$3,0))+INDEX(Qrtly!$A:$BH,MATCH(Annual!$A16,Qrtly!$A:$A,0),MATCH("3Q"&RIGHT(Annual!T$1,2),Qrtly!$A$3:$BH$3,0))+INDEX(Qrtly!$A:$BH,MATCH(Annual!$A16,Qrtly!$A:$A,0),MATCH("4Q"&RIGHT(Annual!T$1,2),Qrtly!$A$3:$BH$3,0)) -> 6711355.8 | U16: =INDEX(Qrtly!$A:$BH,MATCH(Annual!$A16,Qrtly!$A:$A,0),MATCH("1Q"&RIGHT(Annual!U$1,2),Qrtly!$A$3:$BH$3,0))+INDEX(Qrtly!$A:$BH,MATCH(Annual!$A16,Qrtly!$A:$A,0),MATCH("2Q"&RIGHT(Annual!U$1,2),Qrtly!$A$3:$BH$3,0))+INDEX(Qrtly!$A:$BH,MATCH(Annual!$A16,Qrtly!$A:$A,0),MATCH("3Q"&RIGHT(Annual!U$1,2),Qrtly!$A$3:$BH$3,0))+INDEX(Qrtly!$A:$BH,MATCH(Annual!$A16,Qrtly!$A:$A,0),MATCH("4Q"&RIGHT(Annual!U$1,2),Qrtly!$A$3:$BH$3,0)) -> 7612981.9 | V16: =INDEX(Qrtly!$A:$BH,MATCH(Annual!$A16,Qrtly!$A:$A,0),MATCH("1Q"&RIGHT(Annual!V$1,2),Qrtly!$A$3:$BH$3,0))+INDEX(Qrtly!$A:$BH,MATCH(Annual!$A16,Qrtly!$A:$A,0),MATCH("2Q"&RIGHT(Annual!V$1,2),Qrtly!$A$3:$BH$3,0))+INDEX(Qrtly!$A:$BH,MATCH(Annual!$A16,Qrtly!$A:$A,0),MATCH("3Q"&RIGHT(Annual!V$1,2),Qrtly!$A$3:$BH$3,0))+INDEX(Qrtly!$A:$BH,MATCH(Annual!$A16,Qrtly!$A:$A,0),MATCH("4Q"&RIGHT(Annual!V$1,2),Qrtly!$A$3:$BH$3,0)) -> 8651724.8 | ... Z16: =INDEX(Qrtly!$A:$BH,MATCH(Annual!$A16,Qrtly!$A:$A,0),MATCH("1Q"&RIGHT(Annual!Z$1,2),Qrtly!$A$3:$BH$3,0))+INDEX(Qrtly!$A:$BH,MATCH(Annual!$A16,Qrtly!$A:$A,0),MATCH("2Q"&RIGHT(Annual!Z$1,2),Qrtly!$A$3:$BH$3,0))+INDEX(Qrtly!$A:$BH,MATCH(Annual!$A16,Qrtly!$A:$A,0),MATCH("3Q"&RIGHT(Annual!Z$1,2),Qrtly!$A$3:$BH$3,0))+INDEX(Qrtly!$A:$BH,MATCH(Annual!$A16,Qrtly!$A:$A,0),MATCH("4Q"&RIGHT(Annual!Z$1,2),Qrtly!$A$3:$BH$3,0)) -> 14710033 | AA16: -0.01 | AB16: -0.01 | AC16: 3991241.3 | AD16: =IF(ISBLANK(AC16),"",INDEX($A16:$AA16,1,MATCH(AC$3,$A$3:$AA$3,0))-AC16) -> -27104.401 | AE16: 4525935.8 | AF16: =IF(ISBLANK(AE16),"",INDEX($A16:$AA16,1,MATCH(AE$3,$A$3:$AA$3,0))-AE16) -> -22722.236
A17: GP-Cash App | B17: Cash App | J17: 457668 | K17: 1225578 | L17: 2070847 | M17: 3245042 | N17: 4323463 | O17: =INDEX(Qrtly!$A:$BH,MATCH(Annual!$A17,Qrtly!$A:$A,0),MATCH("1Q"&RIGHT(Annual!O$1,2),Qrtly!$A$3:$BH$3,0))+INDEX(Qrtly!$A:$BH,MATCH(Annual!$A17,Qrtly!$A:$A,0),MATCH("2Q"&RIGHT(Annual!O$1,2),Qrtly!$A$3:$BH$3,0))+INDEX(Qrtly!$A:$BH,MATCH(Annual!$A17,Qrtly!$A:$A,0),MATCH("3Q"&RIGHT(Annual!O$1,2),Qrtly!$A$3:$BH$3,0))+INDEX(Qrtly!$A:$BH,MATCH(Annual!$A17,Qrtly!$A:$A,0),MATCH("4Q"&RIGHT(Annual!O$1,2),Qrtly!$A$3:$BH$3,0)) -> 5239011 | P17: =INDEX(Qrtly!$A:$BH,MATCH(Annual!$A17,Qrtly!$A:$A,0),MATCH("1Q"&RIGHT(Annual!P$1,2),Qrtly!$A$3:$BH$3,0))+INDEX(Qrtly!$A:$BH,MATCH(Annual!$A17,Qrtly!$A:$A,0),MATCH("2Q"&RIGHT(Annual!P$1,2),Qrtly!$A$3:$BH$3,0))+INDEX(Qrtly!$A:$BH,MATCH(Annual!$A17,Qrtly!$A:$A,0),MATCH("3Q"&RIGHT(Annual!P$1,2),Qrtly!$A$3:$BH$3,0))+INDEX(Qrtly!$A:$BH,MATCH(Annual!$A17,Qrtly!$A:$A,0),MATCH("4Q"&RIGHT(Annual!P$1,2),Qrtly!$A$3:$BH$3,0)) -> 6284206.9 | Q17: =INDEX(Qrtly!$A:$BH,MATCH(Annual!$A17,Qrtly!$A:$A,0),MATCH("1Q"&RIGHT(Annual!Q$1,2),Qrtly!$A$3:$BH$3,0))+INDEX(Qrtly!$A:$BH,MATCH(Annual!$A17,Qrtly!$A:$A,0),MATCH("2Q"&RIGHT(Annual!Q$1,2),Qrtly!$A$3:$BH$3,0))+INDEX(Qrtly!$A:$BH,MATCH(Annual!$A17,Qrtly!$A:$A,0),MATCH("3Q"&RIGHT(Annual!Q$1,2),Qrtly!$A$3:$BH$3,0))+INDEX(Qrtly!$A:$BH,MATCH(Annual!$A17,Qrtly!$A:$A,0),MATCH("4Q"&RIGHT(Annual!Q$1,2),Qrtly!$A$3:$BH$3,0)) -> 7825132.4 | R17: =INDEX(Qrtly!$A:$BH,MATCH(Annual!$A17,Qrtly!$A:$A,0),MATCH("1Q"&RIGHT(Annual!R$1,2),Qrtly!$A$3:$BH$3,0))+INDEX(Qrtly!$A:$BH,MATCH(Annual!$A17,Qrtly!$A:$A,0),MATCH("2Q"&RIGHT(Annual!R$1,2),Qrtly!$A$3:$BH$3,0))+INDEX(Qrtly!$A:$BH,MATCH(Annual!$A17,Qrtly!$A:$A,0),MATCH("3Q"&RIGHT(Annual!R$1,2),Qrtly!$A$3:$BH$3,0))+INDEX(Qrtly!$A:$BH,MATCH(Annual!$A17,Qrtly!$A:$A,0),MATCH("4Q"&RIGHT(Annual!R$1,2),Qrtly!$A$3:$BH$3,0)) -> 9281980.2 | S17: =INDEX(Qrtly!$A:$BH,MATCH(Annual!$A17,Qrtly!$A:$A,0),MATCH("1Q"&RIGHT(Annual!S$1,2),Qrtly!$A$3:$BH$3,0))+INDEX(Qrtly!$A:$BH,MATCH(Annual!$A17,Qrtly!$A:$A,0),MATCH("2Q"&RIGHT(Annual!S$1,2),Qrtly!$A$3:$BH$3,0))+INDEX(Qrtly!$A:$BH,MATCH(Annual!$A17,Qrtly!$A:$A,0),MATCH("3Q"&RIGHT(Annual!S$1,2),Qrtly!$A$3:$BH$3,0))+INDEX(Qrtly!$A:$BH,MATCH(Annual!$A17,Qrtly!$A:$A,0),MATCH("4Q"&RIGHT(Annual!S$1,2),Qrtly!$A$3:$BH$3,0)) -> 10803008 | T17: =INDEX(Qrtly!$A:$BH,MATCH(Annual!$A17,Qrtly!$A:$A,0),MATCH("1Q"&RIGHT(Annual!T$1,2),Qrtly!$A$3:$BH$3,0))+INDEX(Qrtly!$A:$BH,MATCH(Annual!$A17,Qrtly!$A:$A,0),MATCH("2Q"&RIGHT(Annual!T$1,2),Qrtly!$A$3:$BH$3,0))+INDEX(Qrtly!$A:$BH,MATCH(Annual!$A17,Qrtly!$A:$A,0),MATCH("3Q"&RIGHT(Annual!T$1,2),Qrtly!$A$3:$BH$3,0))+INDEX(Qrtly!$A:$BH,MATCH(Annual!$A17,Qrtly!$A:$A,0),MATCH("4Q"&RIGHT(Annual!T$1,2),Qrtly!$A$3:$BH$3,0)) -> 12453690 | U17: =INDEX(Qrtly!$A:$BH,MATCH(Annual!$A17,Qrtly!$A:$A,0),MATCH("1Q"&RIGHT(Annual!U$1,2),Qrtly!$A$3:$BH$3,0))+INDEX(Qrtly!$A:$BH,MATCH(Annual!$A17,Qrtly!$A:$A,0),MATCH("2Q"&RIGHT(Annual!U$1,2),Qrtly!$A$3:$BH$3,0))+INDEX(Qrtly!$A:$BH,MATCH(Annual!$A17,Qrtly!$A:$A,0),MATCH("3Q"&RIGHT(Annual!U$1,2),Qrtly!$A$3:$BH$3,0))+INDEX(Qrtly!$A:$BH,MATCH(Annual!$A17,Qrtly!$A:$A,0),MATCH("4Q"&RIGHT(Annual!U$1,2),Qrtly!$A$3:$BH$3,0)) -> 14382454 | V17: =INDEX(Qrtly!$A:$BH,MATCH(Annual!$A17,Qrtly!$A:$A,0),MATCH("1Q"&RIGHT(Annual!V$1,2),Qrtly!$A$3:$BH$3,0))+INDEX(Qrtly!$A:$BH,MATCH(Annual!$A17,Qrtly!$A:$A,0),MATCH("2Q"&RIGHT(Annual!V$1,2),Qrtly!$A$3:$BH$3,0))+INDEX(Qrtly!$A:$BH,MATCH(Annual!$A17,Qrtly!$A:$A,0),MATCH("3Q"&RIGHT(Annual!V$1,2),Qrtly!$A$3:$BH$3,0))+INDEX(Qrtly!$A:$BH,MATCH(Annual!$A17,Qrtly!$A:$A,0),MATCH("4Q"&RIGHT(Annual!V$1,2),Qrtly!$A$3:$BH$3,0)) -> 16641613 | ... Z17: =INDEX(Qrtly!$A:$BH,MATCH(Annual!$A17,Qrtly!$A:$A,0),MATCH("1Q"&RIGHT(Annual!Z$1,2),Qrtly!$A$3:$BH$3,0))+INDEX(Qrtly!$A:$BH,MATCH(Annual!$A17,Qrtly!$A:$A,0),MATCH("2Q"&RIGHT(Annual!Z$1,2),Qrtly!$A$3:$BH$3,0))+INDEX(Qrtly!$A:$BH,MATCH(Annual!$A17,Qrtly!$A:$A,0),MATCH("3Q"&RIGHT(Annual!Z$1,2),Qrtly!$A$3:$BH$3,0))+INDEX(Qrtly!$A:$BH,MATCH(Annual!$A17,Qrtly!$A:$A,0),MATCH("4Q"&RIGHT(Annual!Z$1,2),Qrtly!$A$3:$BH$3,0)) -> 30464680 | AA17: 0.03 | AB17: 0.08 | AC17: 6143549.1 | AD17: =IF(ISBLANK(AC17),"",INDEX($A17:$AA17,1,MATCH(AC$3,$A$3:$AA$3,0))-AC17) -> 140657.78 | AE17: 7660639.7 | AF17: =IF(ISBLANK(AE17),"",INDEX($A17:$AA17,1,MATCH(AE$3,$A$3:$AA$3,0))-AE17) -> 164492.67
A18: GP-Corporate & Other | B18: Corporate & Other | J18: 41590 | K18: 0 | L18: 32305 | M18: 39949 | N18: 52775 | O18: =INDEX(Qrtly!$A:$BH,MATCH(Annual!$A18,Qrtly!$A:$A,0),MATCH("1Q"&RIGHT(Annual!O$1,2),Qrtly!$A$3:$BH$3,0))+INDEX(Qrtly!$A:$BH,MATCH(Annual!$A18,Qrtly!$A:$A,0),MATCH("2Q"&RIGHT(Annual!O$1,2),Qrtly!$A$3:$BH$3,0))+INDEX(Qrtly!$A:$BH,MATCH(Annual!$A18,Qrtly!$A:$A,0),MATCH("3Q"&RIGHT(Annual!O$1,2),Qrtly!$A$3:$BH$3,0))+INDEX(Qrtly!$A:$BH,MATCH(Annual!$A18,Qrtly!$A:$A,0),MATCH("4Q"&RIGHT(Annual!O$1,2),Qrtly!$A$3:$BH$3,0)) -> 51113 | P18: =INDEX(Qrtly!$A:$BH,MATCH(Annual!$A18,Qrtly!$A:$A,0),MATCH("1Q"&RIGHT(Annual!P$1,2),Qrtly!$A$3:$BH$3,0))+INDEX(Qrtly!$A:$BH,MATCH(Annual!$A18,Qrtly!$A:$A,0),MATCH("2Q"&RIGHT(Annual!P$1,2),Qrtly!$A$3:$BH$3,0))+INDEX(Qrtly!$A:$BH,MATCH(Annual!$A18,Qrtly!$A:$A,0),MATCH("3Q"&RIGHT(Annual!P$1,2),Qrtly!$A$3:$BH$3,0))+INDEX(Qrtly!$A:$BH,MATCH(Annual!$A18,Qrtly!$A:$A,0),MATCH("4Q"&RIGHT(Annual!P$1,2),Qrtly!$A$3:$BH$3,0)) -> 73635 | Q18: =INDEX(Qrtly!$A:$BH,MATCH(Annual!$A18,Qrtly!$A:$A,0),MATCH("1Q"&RIGHT(Annual!Q$1,2),Qrtly!$A$3:$BH$3,0))+INDEX(Qrtly!$A:$BH,MATCH(Annual!$A18,Qrtly!$A:$A,0),MATCH("2Q"&RIGHT(Annual!Q$1,2),Qrtly!$A$3:$BH$3,0))+INDEX(Qrtly!$A:$BH,MATCH(Annual!$A18,Qrtly!$A:$A,0),MATCH("3Q"&RIGHT(Annual!Q$1,2),Qrtly!$A$3:$BH$3,0))+INDEX(Qrtly!$A:$BH,MATCH(Annual!$A18,Qrtly!$A:$A,0),MATCH("4Q"&RIGHT(Annual!Q$1,2),Qrtly!$A$3:$BH$3,0)) -> 144141 | R18: =INDEX(Qrtly!$A:$BH,MATCH(Annual!$A18,Qrtly!$A:$A,0),MATCH("1Q"&RIGHT(Annual!R$1,2),Qrtly!$A$3:$BH$3,0))+INDEX(Qrtly!$A:$BH,MATCH(Annual!$A18,Qrtly!$A:$A,0),MATCH("2Q"&RIGHT(Annual!R$1,2),Qrtly!$A$3:$BH$3,0))+INDEX(Qrtly!$A:$BH,MATCH(Annual!$A18,Qrtly!$A:$A,0),MATCH("3Q"&RIGHT(Annual!R$1,2),Qrtly!$A$3:$BH$3,0))+INDEX(Qrtly!$A:$BH,MATCH(Annual!$A18,Qrtly!$A:$A,0),MATCH("4Q"&RIGHT(Annual!R$1,2),Qrtly!$A$3:$BH$3,0)) -> 181899 | S18: =INDEX(Qrtly!$A:$BH,MATCH(Annual!$A18,Qrtly!$A:$A,0),MATCH("1Q"&RIGHT(Annual!S$1,2),Qrtly!$A$3:$BH$3,0))+INDEX(Qrtly!$A:$BH,MATCH(Annual!$A18,Qrtly!$A:$A,0),MATCH("2Q"&RIGHT(Annual!S$1,2),Qrtly!$A$3:$BH$3,0))+INDEX(Qrtly!$A:$BH,MATCH(Annual!$A18,Qrtly!$A:$A,0),MATCH("3Q"&RIGHT(Annual!S$1,2),Qrtly!$A$3:$BH$3,0))+INDEX(Qrtly!$A:$BH,MATCH(Annual!$A18,Qrtly!$A:$A,0),MATCH("4Q"&RIGHT(Annual!S$1,2),Qrtly!$A$3:$BH$3,0)) -> 217156 | T18: =INDEX(Qrtly!$A:$BH,MATCH(Annual!$A18,Qrtly!$A:$A,0),MATCH("1Q"&RIGHT(Annual!T$1,2),Qrtly!$A$3:$BH$3,0))+INDEX(Qrtly!$A:$BH,MATCH(Annual!$A18,Qrtly!$A:$A,0),MATCH("2Q"&RIGHT(Annual!T$1,2),Qrtly!$A$3:$BH$3,0))+INDEX(Qrtly!$A:$BH,MATCH(Annual!$A18,Qrtly!$A:$A,0),MATCH("3Q"&RIGHT(Annual!T$1,2),Qrtly!$A$3:$BH$3,0))+INDEX(Qrtly!$A:$BH,MATCH(Annual!$A18,Qrtly!$A:$A,0),MATCH("4Q"&RIGHT(Annual!T$1,2),Qrtly!$A$3:$BH$3,0)) -> 228013 | U18: =INDEX(Qrtly!$A:$BH,MATCH(Annual!$A18,Qrtly!$A:$A,0),MATCH("1Q"&RIGHT(Annual!U$1,2),Qrtly!$A$3:$BH$3,0))+INDEX(Qrtly!$A:$BH,MATCH(Annual!$A18,Qrtly!$A:$A,0),MATCH("2Q"&RIGHT(Annual!U$1,2),Qrtly!$A$3:$BH$3,0))+INDEX(Qrtly!$A:$BH,MATCH(Annual!$A18,Qrtly!$A:$A,0),MATCH("3Q"&RIGHT(Annual!U$1,2),Qrtly!$A$3:$BH$3,0))+INDEX(Qrtly!$A:$BH,MATCH(Annual!$A18,Qrtly!$A:$A,0),MATCH("4Q"&RIGHT(Annual!U$1,2),Qrtly!$A$3:$BH$3,0)) -> 239415 | V18: =INDEX(Qrtly!$A:$BH,MATCH(Annual!$A18,Qrtly!$A:$A,0),MATCH("1Q"&RIGHT(Annual!V$1,2),Qrtly!$A$3:$BH$3,0))+INDEX(Qrtly!$A:$BH,MATCH(Annual!$A18,Qrtly!$A:$A,0),MATCH("2Q"&RIGHT(Annual!V$1,2),Qrtly!$A$3:$BH$3,0))+INDEX(Qrtly!$A:$BH,MATCH(Annual!$A18,Qrtly!$A:$A,0),MATCH("3Q"&RIGHT(Annual!V$1,2),Qrtly!$A$3:$BH$3,0))+INDEX(Qrtly!$A:$BH,MATCH(Annual!$A18,Qrtly!$A:$A,0),MATCH("4Q"&RIGHT(Annual!V$1,2),Qrtly!$A$3:$BH$3,0)) -> 251385 | ... Z18: =INDEX(Qrtly!$A:$BH,MATCH(Annual!$A18,Qrtly!$A:$A,0),MATCH("1Q"&RIGHT(Annual!Z$1,2),Qrtly!$A$3:$BH$3,0))+INDEX(Qrtly!$A:$BH,MATCH(Annual!$A18,Qrtly!$A:$A,0),MATCH("2Q"&RIGHT(Annual!Z$1,2),Qrtly!$A$3:$BH$3,0))+INDEX(Qrtly!$A:$BH,MATCH(Annual!$A18,Qrtly!$A:$A,0),MATCH("3Q"&RIGHT(Annual!Z$1,2),Qrtly!$A$3:$BH$3,0))+INDEX(Qrtly!$A:$BH,MATCH(Annual!$A18,Qrtly!$A:$A,0),MATCH("4Q"&RIGHT(Annual!Z$1,2),Qrtly!$A$3:$BH$3,0)) -> 305559 | AA18: -0.04 | AB18: -0.02 | AC18: 85633 | AD18: =IF(ISBLANK(AC18),"",INDEX($A18:$AA18,1,MATCH(AC$3,$A$3:$AA$3,0))-AC18) -> -11998 | AE18: 144141 | AF18: =IF(ISBLANK(AE18),"",INDEX($A18:$AA18,1,MATCH(AE$3,$A$3:$AA$3,0))-AE18) -> 0
A19: GP-Total Gross Profit | B19: Total Gross Profit | C19: USDk | F19: 370030 | G19: 576038 | H19: 839306 | I19: 1303700 | J19: 1889685 | K19: 2733409 | L19: 4419822 | M19: 5991892 | N19: 7504886 | O19: =INDEX(Qrtly!$A:$BH,MATCH(Annual!$A19,Qrtly!$A:$A,0),MATCH("1Q"&RIGHT(Annual!O$1,2),Qrtly!$A$3:$BH$3,0))+INDEX(Qrtly!$A:$BH,MATCH(Annual!$A19,Qrtly!$A:$A,0),MATCH("2Q"&RIGHT(Annual!O$1,2),Qrtly!$A$3:$BH$3,0))+INDEX(Qrtly!$A:$BH,MATCH(Annual!$A19,Qrtly!$A:$A,0),MATCH("3Q"&RIGHT(Annual!O$1,2),Qrtly!$A$3:$BH$3,0))+INDEX(Qrtly!$A:$BH,MATCH(Annual!$A19,Qrtly!$A:$A,0),MATCH("4Q"&RIGHT(Annual!O$1,2),Qrtly!$A$3:$BH$3,0)) -> 8889036 | P19: =INDEX(Qrtly!$A:$BH,MATCH(Annual!$A19,Qrtly!$A:$A,0),MATCH("1Q"&RIGHT(Annual!P$1,2),Qrtly!$A$3:$BH$3,0))+INDEX(Qrtly!$A:$BH,MATCH(Annual!$A19,Qrtly!$A:$A,0),MATCH("2Q"&RIGHT(Annual!P$1,2),Qrtly!$A$3:$BH$3,0))+INDEX(Qrtly!$A:$BH,MATCH(Annual!$A19,Qrtly!$A:$A,0),MATCH("3Q"&RIGHT(Annual!P$1,2),Qrtly!$A$3:$BH$3,0))+INDEX(Qrtly!$A:$BH,MATCH(Annual!$A19,Qrtly!$A:$A,0),MATCH("4Q"&RIGHT(Annual!P$1,2),Qrtly!$A$3:$BH$3,0)) -> 10321979 | Q19: =INDEX(Qrtly!$A:$BH,MATCH(Annual!$A19,Qrtly!$A:$A,0),MATCH("1Q"&RIGHT(Annual!Q$1,2),Qrtly!$A$3:$BH$3,0))+INDEX(Qrtly!$A:$BH,MATCH(Annual!$A19,Qrtly!$A:$A,0),MATCH("2Q"&RIGHT(Annual!Q$1,2),Qrtly!$A$3:$BH$3,0))+INDEX(Qrtly!$A:$BH,MATCH(Annual!$A19,Qrtly!$A:$A,0),MATCH("3Q"&RIGHT(Annual!Q$1,2),Qrtly!$A$3:$BH$3,0))+INDEX(Qrtly!$A:$BH,MATCH(Annual!$A19,Qrtly!$A:$A,0),MATCH("4Q"&RIGHT(Annual!Q$1,2),Qrtly!$A$3:$BH$3,0)) -> 12472487 | R19: =INDEX(Qrtly!$A:$BH,MATCH(Annual!$A19,Qrtly!$A:$A,0),MATCH("1Q"&RIGHT(Annual!R$1,2),Qrtly!$A$3:$BH$3,0))+INDEX(Qrtly!$A:$BH,MATCH(Annual!$A19,Qrtly!$A:$A,0),MATCH("2Q"&RIGHT(Annual!R$1,2),Qrtly!$A$3:$BH$3,0))+INDEX(Qrtly!$A:$BH,MATCH(Annual!$A19,Qrtly!$A:$A,0),MATCH("3Q"&RIGHT(Annual!R$1,2),Qrtly!$A$3:$BH$3,0))+INDEX(Qrtly!$A:$BH,MATCH(Annual!$A19,Qrtly!$A:$A,0),MATCH("4Q"&RIGHT(Annual!R$1,2),Qrtly!$A$3:$BH$3,0)) -> 14624993 | S19: =INDEX(Qrtly!$A:$BH,MATCH(Annual!$A19,Qrtly!$A:$A,0),MATCH("1Q"&RIGHT(Annual!S$1,2),Qrtly!$A$3:$BH$3,0))+INDEX(Qrtly!$A:$BH,MATCH(Annual!$A19,Qrtly!$A:$A,0),MATCH("2Q"&RIGHT(Annual!S$1,2),Qrtly!$A$3:$BH$3,0))+INDEX(Qrtly!$A:$BH,MATCH(Annual!$A19,Qrtly!$A:$A,0),MATCH("3Q"&RIGHT(Annual!S$1,2),Qrtly!$A$3:$BH$3,0))+INDEX(Qrtly!$A:$BH,MATCH(Annual!$A19,Qrtly!$A:$A,0),MATCH("4Q"&RIGHT(Annual!S$1,2),Qrtly!$A$3:$BH$3,0)) -> 16947368 | T19: =INDEX(Qrtly!$A:$BH,MATCH(Annual!$A19,Qrtly!$A:$A,0),MATCH("1Q"&RIGHT(Annual!T$1,2),Qrtly!$A$3:$BH$3,0))+INDEX(Qrtly!$A:$BH,MATCH(Annual!$A19,Qrtly!$A:$A,0),MATCH("2Q"&RIGHT(Annual!T$1,2),Qrtly!$A$3:$BH$3,0))+INDEX(Qrtly!$A:$BH,MATCH(Annual!$A19,Qrtly!$A:$A,0),MATCH("3Q"&RIGHT(Annual!T$1,2),Qrtly!$A$3:$BH$3,0))+INDEX(Qrtly!$A:$BH,MATCH(Annual!$A19,Qrtly!$A:$A,0),MATCH("4Q"&RIGHT(Annual!T$1,2),Qrtly!$A$3:$BH$3,0)) -> 19393059 | U19: =INDEX(Qrtly!$A:$BH,MATCH(Annual!$A19,Qrtly!$A:$A,0),MATCH("1Q"&RIGHT(Annual!U$1,2),Qrtly!$A$3:$BH$3,0))+INDEX(Qrtly!$A:$BH,MATCH(Annual!$A19,Qrtly!$A:$A,0),MATCH("2Q"&RIGHT(Annual!U$1,2),Qrtly!$A$3:$BH$3,0))+INDEX(Qrtly!$A:$BH,MATCH(Annual!$A19,Qrtly!$A:$A,0),MATCH("3Q"&RIGHT(Annual!U$1,2),Qrtly!$A$3:$BH$3,0))+INDEX(Qrtly!$A:$BH,MATCH(Annual!$A19,Qrtly!$A:$A,0),MATCH("4Q"&RIGHT(Annual!U$1,2),Qrtly!$A$3:$BH$3,0)) -> 22234851 | V19: =INDEX(Qrtly!$A:$BH,MATCH(Annual!$A19,Qrtly!$A:$A,0),MATCH("1Q"&RIGHT(Annual!V$1,2),Qrtly!$A$3:$BH$3,0))+INDEX(Qrtly!$A:$BH,MATCH(Annual!$A19,Qrtly!$A:$A,0),MATCH("2Q"&RIGHT(Annual!V$1,2),Qrtly!$A$3:$BH$3,0))+INDEX(Qrtly!$A:$BH,MATCH(Annual!$A19,Qrtly!$A:$A,0),MATCH("3Q"&RIGHT(Annual!V$1,2),Qrtly!$A$3:$BH$3,0))+INDEX(Qrtly!$A:$BH,MATCH(Annual!$A19,Qrtly!$A:$A,0),MATCH("4Q"&RIGHT(Annual!V$1,2),Qrtly!$A$3:$BH$3,0)) -> 25544723 | ... Z19: =INDEX(Qrtly!$A:$BH,MATCH(Annual!$A19,Qrtly!$A:$A,0),MATCH("1Q"&RIGHT(Annual!Z$1,2),Qrtly!$A$3:$BH$3,0))+INDEX(Qrtly!$A:$BH,MATCH(Annual!$A19,Qrtly!$A:$A,0),MATCH("2Q"&RIGHT(Annual!Z$1,2),Qrtly!$A$3:$BH$3,0))+INDEX(Qrtly!$A:$BH,MATCH(Annual!$A19,Qrtly!$A:$A,0),MATCH("3Q"&RIGHT(Annual!Z$1,2),Qrtly!$A$3:$BH$3,0))+INDEX(Qrtly!$A:$BH,MATCH(Annual!$A19,Qrtly!$A:$A,0),MATCH("4Q"&RIGHT(Annual!Z$1,2),Qrtly!$A$3:$BH$3,0)) -> 45480272 | AA19: 0.01 | AB19: 0.04 | AC19: 10220423 | AD19: =IF(ISBLANK(AC19),"",INDEX($A19:$AA19,1,MATCH(AC$3,$A$3:$AA$3,0))-AC19) -> 101555.38 | AE19: 12330717 | AF19: =IF(ISBLANK(AE19),"",INDEX($A19:$AA19,1,MATCH(AE$3,$A$3:$AA$3,0))-AE19) -> 141770.43
B20: Growth | C20: % YoY | I20: 0.553 | J20: 0.449 | K20: 0.446 | L20: 0.617 | M20: 0.356 | N20: 0.253 | O20: =O19/N19-1 -> 0.18443318 | P20: =P19/O19-1 -> 0.1612034 | Q20: =Q19/P19-1 -> 0.20834263 | R20: =R19/Q19-1 -> 0.17258031 | S20: =S19/R19-1 -> 0.158795 | T20: =T19/S19-1 -> 0.14431092 | U20: =U19/T19-1 -> 0.1465366 | V20: =V19/U19-1 -> 0.14885963 | ... Z20: =Z19/Y19-1 -> 0.15907227 | AC20: 0.14977861 | AD20: =IF(ISBLANK(AC20),"",INDEX($A20:$AA20,1,MATCH(AC$3,$A$3:$AA$3,0))-AC20) -> 0.011424791 | AE20: 0.20647805 | AF20: =IF(ISBLANK(AE20),"",INDEX($A20:$AA20,1,MATCH(AE$3,$A$3:$AA$3,0))-AE20) -> 0.0018645746
B21: Initial Guidance | C21: USDk | K21: 2457500 | M21: NR | N21: NR | O21: 8650000 | P21: 10220000 | AC21: 10220000 | AD21: =IF(ISBLANK(AC21),"",INDEX($A21:$AA21,1,MATCH(AC$3,$A$3:$AA$3,0))-AC21) -> 0 | AF21: =IF(ISBLANK(AE21),"",INDEX($A21:$AA21,1,MATCH(AE$3,$A$3:$AA$3,0))-AE21)
B22: Latest Guidance | P22: 10243000 | R22: 10243000 | AC22: 10170000 | AD22: =IF(ISBLANK(AC22),"",INDEX($A22:$AA22,1,MATCH(AC$3,$A$3:$AA$3,0))-AC22) -> 73000 | AF22: =IF(ISBLANK(AE22),"",INDEX($A22:$AA22,1,MATCH(AE$3,$A$3:$AA$3,0))-AE22)
B23: vs guidance | K23: 0.11 | O23: 0.03 | P23: 0 | R23: =R22/P22-1 -> 0 | AA23: 0.6 | AC23: 0 | AD23: =IF(ISBLANK(AC23),"",INDEX($A23:$AA23,1,MATCH(AC$3,$A$3:$AA$3,0))-AC23) -> 0 | AF23: =IF(ISBLANK(AE23),"",INDEX($A23:$AA23,1,MATCH(AE$3,$A$3:$AA$3,0))-AE23)
P24: 0.14 | AC24: 0.14 | AD24: =IF(ISBLANK(AC24),"",INDEX($A24:$AA24,1,MATCH(AC$3,$A$3:$AA$3,0))-AC24) -> 0 | AF24: =IF(ISBLANK(AE24),"",INDEX($A24:$AA24,1,MATCH(AE$3,$A$3:$AA$3,0))-AE24)
B25: Operating Expenses (Non- GAAP) | AD25: =IF(ISBLANK(AC25),"",INDEX($A25:$AA25,1,MATCH(AC$3,$A$3:$AA$3,0))-AC25) | AF25: =IF(ISBLANK(AE25),"",INDEX($A25:$AA25,1,MATCH(AE$3,$A$3:$AA$3,0))-AE25)
A26: Opex-Non-GAAP product development | B26: Non-GAAP product development | F26: 133553 | G26: 163943 | H26: 206623 | I26: 319845 | J26: 417018 | K26: 546019 | L26: 859594 | M26: 1311170 | N26: =INDEX(Qrtly!$A:$BH,MATCH(Annual!$A26,Qrtly!$A:$A,0),MATCH("1Q"&RIGHT(Annual!N$1,2),Qrtly!$A$3:$BH$3,0))+INDEX(Qrtly!$A:$BH,MATCH(Annual!$A26,Qrtly!$A:$A,0),MATCH("2Q"&RIGHT(Annual!N$1,2),Qrtly!$A$3:$BH$3,0))+INDEX(Qrtly!$A:$BH,MATCH(Annual!$A26,Qrtly!$A:$A,0),MATCH("3Q"&RIGHT(Annual!N$1,2),Qrtly!$A$3:$BH$3,0))+INDEX(Qrtly!$A:$BH,MATCH(Annual!$A26,Qrtly!$A:$A,0),MATCH("4Q"&RIGHT(Annual!N$1,2),Qrtly!$A$3:$BH$3,0)) -> 1668712 | O26: =INDEX(Qrtly!$A:$BH,MATCH(Annual!$A26,Qrtly!$A:$A,0),MATCH("1Q"&RIGHT(Annual!O$1,2),Qrtly!$A$3:$BH$3,0))+INDEX(Qrtly!$A:$BH,MATCH(Annual!$A26,Qrtly!$A:$A,0),MATCH("2Q"&RIGHT(Annual!O$1,2),Qrtly!$A$3:$BH$3,0))+INDEX(Qrtly!$A:$BH,MATCH(Annual!$A26,Qrtly!$A:$A,0),MATCH("3Q"&RIGHT(Annual!O$1,2),Qrtly!$A$3:$BH$3,0))+INDEX(Qrtly!$A:$BH,MATCH(Annual!$A26,Qrtly!$A:$A,0),MATCH("4Q"&RIGHT(Annual!O$1,2),Qrtly!$A$3:$BH$3,0)) -> 2849128 | P26: =INDEX(Qrtly!$A:$BH,MATCH(Annual!$A26,Qrtly!$A:$A,0),MATCH("1Q"&RIGHT(Annual!P$1,2),Qrtly!$A$3:$BH$3,0))+INDEX(Qrtly!$A:$BH,MATCH(Annual!$A26,Qrtly!$A:$A,0),MATCH("2Q"&RIGHT(Annual!P$1,2),Qrtly!$A$3:$BH$3,0))+INDEX(Qrtly!$A:$BH,MATCH(Annual!$A26,Qrtly!$A:$A,0),MATCH("3Q"&RIGHT(Annual!P$1,2),Qrtly!$A$3:$BH$3,0))+INDEX(Qrtly!$A:$BH,MATCH(Annual!$A26,Qrtly!$A:$A,0),MATCH("4Q"&RIGHT(Annual!P$1,2),Qrtly!$A$3:$BH$3,0)) -> 2883152.2 | Q26: =INDEX(Qrtly!$A:$BH,MATCH(Annual!$A26,Qrtly!$A:$A,0),MATCH("1Q"&RIGHT(Annual!Q$1,2),Qrtly!$A$3:$BH$3,0))+INDEX(Qrtly!$A:$BH,MATCH(Annual!$A26,Qrtly!$A:$A,0),MATCH("2Q"&RIGHT(Annual!Q$1,2),Qrtly!$A$3:$BH$3,0))+INDEX(Qrtly!$A:$BH,MATCH(Annual!$A26,Qrtly!$A:$A,0),MATCH("3Q"&RIGHT(Annual!Q$1,2),Qrtly!$A$3:$BH$3,0))+INDEX(Qrtly!$A:$BH,MATCH(Annual!$A26,Qrtly!$A:$A,0),MATCH("4Q"&RIGHT(Annual!Q$1,2),Qrtly!$A$3:$BH$3,0)) -> 2940815.3 | R26: =INDEX(Qrtly!$A:$BH,MATCH(Annual!$A26,Qrtly!$A:$A,0),MATCH("1Q"&RIGHT(Annual!R$1,2),Qrtly!$A$3:$BH$3,0))+INDEX(Qrtly!$A:$BH,MATCH(Annual!$A26,Qrtly!$A:$A,0),MATCH("2Q"&RIGHT(Annual!R$1,2),Qrtly!$A$3:$BH$3,0))+INDEX(Qrtly!$A:$BH,MATCH(Annual!$A26,Qrtly!$A:$A,0),MATCH("3Q"&RIGHT(Annual!R$1,2),Qrtly!$A$3:$BH$3,0))+INDEX(Qrtly!$A:$BH,MATCH(Annual!$A26,Qrtly!$A:$A,0),MATCH("4Q"&RIGHT(Annual!R$1,2),Qrtly!$A$3:$BH$3,0)) -> 3058447.9 | S26: =INDEX(Qrtly!$A:$BH,MATCH(Annual!$A26,Qrtly!$A:$A,0),MATCH("1Q"&RIGHT(Annual!S$1,2),Qrtly!$A$3:$BH$3,0))+INDEX(Qrtly!$A:$BH,MATCH(Annual!$A26,Qrtly!$A:$A,0),MATCH("2Q"&RIGHT(Annual!S$1,2),Qrtly!$A$3:$BH$3,0))+INDEX(Qrtly!$A:$BH,MATCH(Annual!$A26,Qrtly!$A:$A,0),MATCH("3Q"&RIGHT(Annual!S$1,2),Qrtly!$A$3:$BH$3,0))+INDEX(Qrtly!$A:$BH,MATCH(Annual!$A26,Qrtly!$A:$A,0),MATCH("4Q"&RIGHT(Annual!S$1,2),Qrtly!$A$3:$BH$3,0)) -> 3180785.8 | T26: =INDEX(Qrtly!$A:$BH,MATCH(Annual!$A26,Qrtly!$A:$A,0),MATCH("1Q"&RIGHT(Annual!T$1,2),Qrtly!$A$3:$BH$3,0))+INDEX(Qrtly!$A:$BH,MATCH(Annual!$A26,Qrtly!$A:$A,0),MATCH("2Q"&RIGHT(Annual!T$1,2),Qrtly!$A$3:$BH$3,0))+INDEX(Qrtly!$A:$BH,MATCH(Annual!$A26,Qrtly!$A:$A,0),MATCH("3Q"&RIGHT(Annual!T$1,2),Qrtly!$A$3:$BH$3,0))+INDEX(Qrtly!$A:$BH,MATCH(Annual!$A26,Qrtly!$A:$A,0),MATCH("4Q"&RIGHT(Annual!T$1,2),Qrtly!$A$3:$BH$3,0)) -> 3308017.2 | U26: =INDEX(Qrtly!$A:$BH,MATCH(Annual!$A26,Qrtly!$A:$A,0),MATCH("1Q"&RIGHT(Annual!U$1,2),Qrtly!$A$3:$BH$3,0))+INDEX(Qrtly!$A:$BH,MATCH(Annual!$A26,Qrtly!$A:$A,0),MATCH("2Q"&RIGHT(Annual!U$1,2),Qrtly!$A$3:$BH$3,0))+INDEX(Qrtly!$A:$BH,MATCH(Annual!$A26,Qrtly!$A:$A,0),MATCH("3Q"&RIGHT(Annual!U$1,2),Qrtly!$A$3:$BH$3,0))+INDEX(Qrtly!$A:$BH,MATCH(Annual!$A26,Qrtly!$A:$A,0),MATCH("4Q"&RIGHT(Annual!U$1,2),Qrtly!$A$3:$BH$3,0)) -> 3440337.9 | ... Z26: =INDEX(Qrtly!$A:$BH,MATCH(Annual!$A26,Qrtly!$A:$A,0),MATCH("1Q"&RIGHT(Annual!Z$1,2),Qrtly!$A$3:$BH$3,0))+INDEX(Qrtly!$A:$BH,MATCH(Annual!$A26,Qrtly!$A:$A,0),MATCH("2Q"&RIGHT(Annual!Z$1,2),Qrtly!$A$3:$BH$3,0))+INDEX(Qrtly!$A:$BH,MATCH(Annual!$A26,Qrtly!$A:$A,0),MATCH("3Q"&RIGHT(Annual!Z$1,2),Qrtly!$A$3:$BH$3,0))+INDEX(Qrtly!$A:$BH,MATCH(Annual!$A26,Qrtly!$A:$A,0),MATCH("4Q"&RIGHT(Annual!Z$1,2),Qrtly!$A$3:$BH$3,0)) -> 4185697.1 | AC26: 2897119.9 | AD26: =IF(ISBLANK(AC26),"",INDEX($A26:$AA26,1,MATCH(AC$3,$A$3:$AA$3,0))-AC26) -> -13967.66 | AE26: 2955062.3 | AF26: =IF(ISBLANK(AE26),"",INDEX($A26:$AA26,1,MATCH(AE$3,$A$3:$AA$3,0))-AE26) -> -14247.013
A27: Opex-Non-GAAP sales and marketing | B27: Non-GAAP sales and marketing | F27: 138195 | G27: 159651 | H27: 234029 | I27: 383708 | J27: 593439 | K27: 1068893 | L27: 1554977 | M27: 1946279 | N27: =INDEX(Qrtly!$A:$BH,MATCH(Annual!$A27,Qrtly!$A:$A,0),MATCH("1Q"&RIGHT(Annual!N$1,2),Qrtly!$A$3:$BH$3,0))+INDEX(Qrtly!$A:$BH,MATCH(Annual!$A27,Qrtly!$A:$A,0),MATCH("2Q"&RIGHT(Annual!N$1,2),Qrtly!$A$3:$BH$3,0))+INDEX(Qrtly!$A:$BH,MATCH(Annual!$A27,Qrtly!$A:$A,0),MATCH("3Q"&RIGHT(Annual!N$1,2),Qrtly!$A$3:$BH$3,0))+INDEX(Qrtly!$A:$BH,MATCH(Annual!$A27,Qrtly!$A:$A,0),MATCH("4Q"&RIGHT(Annual!N$1,2),Qrtly!$A$3:$BH$3,0)) -> 1879759 | O27: =INDEX(Qrtly!$A:$BH,MATCH(Annual!$A27,Qrtly!$A:$A,0),MATCH("1Q"&RIGHT(Annual!O$1,2),Qrtly!$A$3:$BH$3,0))+INDEX(Qrtly!$A:$BH,MATCH(Annual!$A27,Qrtly!$A:$A,0),MATCH("2Q"&RIGHT(Annual!O$1,2),Qrtly!$A$3:$BH$3,0))+INDEX(Qrtly!$A:$BH,MATCH(Annual!$A27,Qrtly!$A:$A,0),MATCH("3Q"&RIGHT(Annual!O$1,2),Qrtly!$A$3:$BH$3,0))+INDEX(Qrtly!$A:$BH,MATCH(Annual!$A27,Qrtly!$A:$A,0),MATCH("4Q"&RIGHT(Annual!O$1,2),Qrtly!$A$3:$BH$3,0)) -> 1983062 | P27: =INDEX(Qrtly!$A:$BH,MATCH(Annual!$A27,Qrtly!$A:$A,0),MATCH("1Q"&RIGHT(Annual!P$1,2),Qrtly!$A$3:$BH$3,0))+INDEX(Qrtly!$A:$BH,MATCH(Annual!$A27,Qrtly!$A:$A,0),MATCH("2Q"&RIGHT(Annual!P$1,2),Qrtly!$A$3:$BH$3,0))+INDEX(Qrtly!$A:$BH,MATCH(Annual!$A27,Qrtly!$A:$A,0),MATCH("3Q"&RIGHT(Annual!P$1,2),Qrtly!$A$3:$BH$3,0))+INDEX(Qrtly!$A:$BH,MATCH(Annual!$A27,Qrtly!$A:$A,0),MATCH("4Q"&RIGHT(Annual!P$1,2),Qrtly!$A$3:$BH$3,0)) -> 2250471.5 | Q27: =INDEX(Qrtly!$A:$BH,MATCH(Annual!$A27,Qrtly!$A:$A,0),MATCH("1Q"&RIGHT(Annual!Q$1,2),Qrtly!$A$3:$BH$3,0))+INDEX(Qrtly!$A:$BH,MATCH(Annual!$A27,Qrtly!$A:$A,0),MATCH("2Q"&RIGHT(Annual!Q$1,2),Qrtly!$A$3:$BH$3,0))+INDEX(Qrtly!$A:$BH,MATCH(Annual!$A27,Qrtly!$A:$A,0),MATCH("3Q"&RIGHT(Annual!Q$1,2),Qrtly!$A$3:$BH$3,0))+INDEX(Qrtly!$A:$BH,MATCH(Annual!$A27,Qrtly!$A:$A,0),MATCH("4Q"&RIGHT(Annual!Q$1,2),Qrtly!$A$3:$BH$3,0)) -> 2602673.9 | R27: =INDEX(Qrtly!$A:$BH,MATCH(Annual!$A27,Qrtly!$A:$A,0),MATCH("1Q"&RIGHT(Annual!R$1,2),Qrtly!$A$3:$BH$3,0))+INDEX(Qrtly!$A:$BH,MATCH(Annual!$A27,Qrtly!$A:$A,0),MATCH("2Q"&RIGHT(Annual!R$1,2),Qrtly!$A$3:$BH$3,0))+INDEX(Qrtly!$A:$BH,MATCH(Annual!$A27,Qrtly!$A:$A,0),MATCH("3Q"&RIGHT(Annual!R$1,2),Qrtly!$A$3:$BH$3,0))+INDEX(Qrtly!$A:$BH,MATCH(Annual!$A27,Qrtly!$A:$A,0),MATCH("4Q"&RIGHT(Annual!R$1,2),Qrtly!$A$3:$BH$3,0)) -> 2957089.4 | S27: =INDEX(Qrtly!$A:$BH,MATCH(Annual!$A27,Qrtly!$A:$A,0),MATCH("1Q"&RIGHT(Annual!S$1,2),Qrtly!$A$3:$BH$3,0))+INDEX(Qrtly!$A:$BH,MATCH(Annual!$A27,Qrtly!$A:$A,0),MATCH("2Q"&RIGHT(Annual!S$1,2),Qrtly!$A$3:$BH$3,0))+INDEX(Qrtly!$A:$BH,MATCH(Annual!$A27,Qrtly!$A:$A,0),MATCH("3Q"&RIGHT(Annual!S$1,2),Qrtly!$A$3:$BH$3,0))+INDEX(Qrtly!$A:$BH,MATCH(Annual!$A27,Qrtly!$A:$A,0),MATCH("4Q"&RIGHT(Annual!S$1,2),Qrtly!$A$3:$BH$3,0)) -> 3359755 | T27: =INDEX(Qrtly!$A:$BH,MATCH(Annual!$A27,Qrtly!$A:$A,0),MATCH("1Q"&RIGHT(Annual!T$1,2),Qrtly!$A$3:$BH$3,0))+INDEX(Qrtly!$A:$BH,MATCH(Annual!$A27,Qrtly!$A:$A,0),MATCH("2Q"&RIGHT(Annual!T$1,2),Qrtly!$A$3:$BH$3,0))+INDEX(Qrtly!$A:$BH,MATCH(Annual!$A27,Qrtly!$A:$A,0),MATCH("3Q"&RIGHT(Annual!T$1,2),Qrtly!$A$3:$BH$3,0))+INDEX(Qrtly!$A:$BH,MATCH(Annual!$A27,Qrtly!$A:$A,0),MATCH("4Q"&RIGHT(Annual!T$1,2),Qrtly!$A$3:$BH$3,0)) -> 3789370.4 | U27: =INDEX(Qrtly!$A:$BH,MATCH(Annual!$A27,Qrtly!$A:$A,0),MATCH("1Q"&RIGHT(Annual!U$1,2),Qrtly!$A$3:$BH$3,0))+INDEX(Qrtly!$A:$BH,MATCH(Annual!$A27,Qrtly!$A:$A,0),MATCH("2Q"&RIGHT(Annual!U$1,2),Qrtly!$A$3:$BH$3,0))+INDEX(Qrtly!$A:$BH,MATCH(Annual!$A27,Qrtly!$A:$A,0),MATCH("3Q"&RIGHT(Annual!U$1,2),Qrtly!$A$3:$BH$3,0))+INDEX(Qrtly!$A:$BH,MATCH(Annual!$A27,Qrtly!$A:$A,0),MATCH("4Q"&RIGHT(Annual!U$1,2),Qrtly!$A$3:$BH$3,0)) -> 4277366 | ... Z27: =INDEX(Qrtly!$A:$BH,MATCH(Annual!$A27,Qrtly!$A:$A,0),MATCH("1Q"&RIGHT(Annual!Z$1,2),Qrtly!$A$3:$BH$3,0))+INDEX(Qrtly!$A:$BH,MATCH(Annual!$A27,Qrtly!$A:$A,0),MATCH("2Q"&RIGHT(Annual!Z$1,2),Qrtly!$A$3:$BH$3,0))+INDEX(Qrtly!$A:$BH,MATCH(Annual!$A27,Qrtly!$A:$A,0),MATCH("3Q"&RIGHT(Annual!Z$1,2),Qrtly!$A$3:$BH$3,0))+INDEX(Qrtly!$A:$BH,MATCH(Annual!$A27,Qrtly!$A:$A,0),MATCH("4Q"&RIGHT(Annual!Z$1,2),Qrtly!$A$3:$BH$3,0)) -> 7934586.1 | AC27: 2253781.2 | AD27: =IF(ISBLANK(AC27),"",INDEX($A27:$AA27,1,MATCH(AC$3,$A$3:$AA$3,0))-AC27) -> -3309.7814 | AE27: 2679045.8 | AF27: =IF(ISBLANK(AE27),"",INDEX($A27:$AA27,1,MATCH(AE$3,$A$3:$AA$3,0))-AE27) -> -76371.856
A28: Opex-Non-GAAP general and administrative | B28: Non-GAAP general and administrative | F28: 115365 | G28: 157389 | H28: 199439 | I28: 274625 | J28: 354645 | K28: 483417 | L28: 815338 | M28: 1219727 | N28: =INDEX(Qrtly!$A:$BH,MATCH(Annual!$A28,Qrtly!$A:$A,0),MATCH("1Q"&RIGHT(Annual!N$1,2),Qrtly!$A$3:$BH$3,0))+INDEX(Qrtly!$A:$BH,MATCH(Annual!$A28,Qrtly!$A:$A,0),MATCH("2Q"&RIGHT(Annual!N$1,2),Qrtly!$A$3:$BH$3,0))+INDEX(Qrtly!$A:$BH,MATCH(Annual!$A28,Qrtly!$A:$A,0),MATCH("3Q"&RIGHT(Annual!N$1,2),Qrtly!$A$3:$BH$3,0))+INDEX(Qrtly!$A:$BH,MATCH(Annual!$A28,Qrtly!$A:$A,0),MATCH("4Q"&RIGHT(Annual!N$1,2),Qrtly!$A$3:$BH$3,0)) -> 1533602 | O28: =INDEX(Qrtly!$A:$BH,MATCH(Annual!$A28,Qrtly!$A:$A,0),MATCH("1Q"&RIGHT(Annual!O$1,2),Qrtly!$A$3:$BH$3,0))+INDEX(Qrtly!$A:$BH,MATCH(Annual!$A28,Qrtly!$A:$A,0),MATCH("2Q"&RIGHT(Annual!O$1,2),Qrtly!$A$3:$BH$3,0))+INDEX(Qrtly!$A:$BH,MATCH(Annual!$A28,Qrtly!$A:$A,0),MATCH("3Q"&RIGHT(Annual!O$1,2),Qrtly!$A$3:$BH$3,0))+INDEX(Qrtly!$A:$BH,MATCH(Annual!$A28,Qrtly!$A:$A,0),MATCH("4Q"&RIGHT(Annual!O$1,2),Qrtly!$A$3:$BH$3,0)) -> 1722199 | P28: =INDEX(Qrtly!$A:$BH,MATCH(Annual!$A28,Qrtly!$A:$A,0),MATCH("1Q"&RIGHT(Annual!P$1,2),Qrtly!$A$3:$BH$3,0))+INDEX(Qrtly!$A:$BH,MATCH(Annual!$A28,Qrtly!$A:$A,0),MATCH("2Q"&RIGHT(Annual!P$1,2),Qrtly!$A$3:$BH$3,0))+INDEX(Qrtly!$A:$BH,MATCH(Annual!$A28,Qrtly!$A:$A,0),MATCH("3Q"&RIGHT(Annual!P$1,2),Qrtly!$A$3:$BH$3,0))+INDEX(Qrtly!$A:$BH,MATCH(Annual!$A28,Qrtly!$A:$A,0),MATCH("4Q"&RIGHT(Annual!P$1,2),Qrtly!$A$3:$BH$3,0)) -> 1914707.1 | Q28: =INDEX(Qrtly!$A:$BH,MATCH(Annual!$A28,Qrtly!$A:$A,0),MATCH("1Q"&RIGHT(Annual!Q$1,2),Qrtly!$A$3:$BH$3,0))+INDEX(Qrtly!$A:$BH,MATCH(Annual!$A28,Qrtly!$A:$A,0),MATCH("2Q"&RIGHT(Annual!Q$1,2),Qrtly!$A$3:$BH$3,0))+INDEX(Qrtly!$A:$BH,MATCH(Annual!$A28,Qrtly!$A:$A,0),MATCH("3Q"&RIGHT(Annual!Q$1,2),Qrtly!$A$3:$BH$3,0))+INDEX(Qrtly!$A:$BH,MATCH(Annual!$A28,Qrtly!$A:$A,0),MATCH("4Q"&RIGHT(Annual!Q$1,2),Qrtly!$A$3:$BH$3,0)) -> 1915139 | R28: =INDEX(Qrtly!$A:$BH,MATCH(Annual!$A28,Qrtly!$A:$A,0),MATCH("1Q"&RIGHT(Annual!R$1,2),Qrtly!$A$3:$BH$3,0))+INDEX(Qrtly!$A:$BH,MATCH(Annual!$A28,Qrtly!$A:$A,0),MATCH("2Q"&RIGHT(Annual!R$1,2),Qrtly!$A$3:$BH$3,0))+INDEX(Qrtly!$A:$BH,MATCH(Annual!$A28,Qrtly!$A:$A,0),MATCH("3Q"&RIGHT(Annual!R$1,2),Qrtly!$A$3:$BH$3,0))+INDEX(Qrtly!$A:$BH,MATCH(Annual!$A28,Qrtly!$A:$A,0),MATCH("4Q"&RIGHT(Annual!R$1,2),Qrtly!$A$3:$BH$3,0)) -> 1991744.6 | S28: =INDEX(Qrtly!$A:$BH,MATCH(Annual!$A28,Qrtly!$A:$A,0),MATCH("1Q"&RIGHT(Annual!S$1,2),Qrtly!$A$3:$BH$3,0))+INDEX(Qrtly!$A:$BH,MATCH(Annual!$A28,Qrtly!$A:$A,0),MATCH("2Q"&RIGHT(Annual!S$1,2),Qrtly!$A$3:$BH$3,0))+INDEX(Qrtly!$A:$BH,MATCH(Annual!$A28,Qrtly!$A:$A,0),MATCH("3Q"&RIGHT(Annual!S$1,2),Qrtly!$A$3:$BH$3,0))+INDEX(Qrtly!$A:$BH,MATCH(Annual!$A28,Qrtly!$A:$A,0),MATCH("4Q"&RIGHT(Annual!S$1,2),Qrtly!$A$3:$BH$3,0)) -> 2071414.3 | T28: =INDEX(Qrtly!$A:$BH,MATCH(Annual!$A28,Qrtly!$A:$A,0),MATCH("1Q"&RIGHT(Annual!T$1,2),Qrtly!$A$3:$BH$3,0))+INDEX(Qrtly!$A:$BH,MATCH(Annual!$A28,Qrtly!$A:$A,0),MATCH("2Q"&RIGHT(Annual!T$1,2),Qrtly!$A$3:$BH$3,0))+INDEX(Qrtly!$A:$BH,MATCH(Annual!$A28,Qrtly!$A:$A,0),MATCH("3Q"&RIGHT(Annual!T$1,2),Qrtly!$A$3:$BH$3,0))+INDEX(Qrtly!$A:$BH,MATCH(Annual!$A28,Qrtly!$A:$A,0),MATCH("4Q"&RIGHT(Annual!T$1,2),Qrtly!$A$3:$BH$3,0)) -> 2154270.9 | U28: =INDEX(Qrtly!$A:$BH,MATCH(Annual!$A28,Qrtly!$A:$A,0),MATCH("1Q"&RIGHT(Annual!U$1,2),Qrtly!$A$3:$BH$3,0))+INDEX(Qrtly!$A:$BH,MATCH(Annual!$A28,Qrtly!$A:$A,0),MATCH("2Q"&RIGHT(Annual!U$1,2),Qrtly!$A$3:$BH$3,0))+INDEX(Qrtly!$A:$BH,MATCH(Annual!$A28,Qrtly!$A:$A,0),MATCH("3Q"&RIGHT(Annual!U$1,2),Qrtly!$A$3:$BH$3,0))+INDEX(Qrtly!$A:$BH,MATCH(Annual!$A28,Qrtly!$A:$A,0),MATCH("4Q"&RIGHT(Annual!U$1,2),Qrtly!$A$3:$BH$3,0)) -> 2240441.8 | ... Z28: =INDEX(Qrtly!$A:$BH,MATCH(Annual!$A28,Qrtly!$A:$A,0),MATCH("1Q"&RIGHT(Annual!Z$1,2),Qrtly!$A$3:$BH$3,0))+INDEX(Qrtly!$A:$BH,MATCH(Annual!$A28,Qrtly!$A:$A,0),MATCH("2Q"&RIGHT(Annual!Z$1,2),Qrtly!$A$3:$BH$3,0))+INDEX(Qrtly!$A:$BH,MATCH(Annual!$A28,Qrtly!$A:$A,0),MATCH("3Q"&RIGHT(Annual!Z$1,2),Qrtly!$A$3:$BH$3,0))+INDEX(Qrtly!$A:$BH,MATCH(Annual!$A28,Qrtly!$A:$A,0),MATCH("4Q"&RIGHT(Annual!Z$1,2),Qrtly!$A$3:$BH$3,0)) -> 2725840 | AC28: 1811129.3 | AD28: =IF(ISBLANK(AC28),"",INDEX($A28:$AA28,1,MATCH(AC$3,$A$3:$AA$3,0))-AC28) -> 103577.74 | AE28: 1847351.9 | AF28: =IF(ISBLANK(AE28),"",INDEX($A28:$AA28,1,MATCH(AE$3,$A$3:$AA$3,0))-AE28) -> 67787.076
A29: Opex- GAAP Transaction, loan, and consumer receivable losses | B29: GAAP Transaction, loan, and consumer receivable losses | F29: 54009 | G29: 51235 | H29: 67018 | I29: 88077 | J29: 126959 | K29: 177670 | L29: 187991 | M29: 550683 | N29: =INDEX(Qrtly!$A:$BH,MATCH(Annual!$A29,Qrtly!$A:$A,0),MATCH("1Q"&RIGHT(Annual!N$1,2),Qrtly!$A$3:$BH$3,0))+INDEX(Qrtly!$A:$BH,MATCH(Annual!$A29,Qrtly!$A:$A,0),MATCH("2Q"&RIGHT(Annual!N$1,2),Qrtly!$A$3:$BH$3,0))+INDEX(Qrtly!$A:$BH,MATCH(Annual!$A29,Qrtly!$A:$A,0),MATCH("3Q"&RIGHT(Annual!N$1,2),Qrtly!$A$3:$BH$3,0))+INDEX(Qrtly!$A:$BH,MATCH(Annual!$A29,Qrtly!$A:$A,0),MATCH("4Q"&RIGHT(Annual!N$1,2),Qrtly!$A$3:$BH$3,0)) -> 660663 | O29: =INDEX(Qrtly!$A:$BH,MATCH(Annual!$A29,Qrtly!$A:$A,0),MATCH("1Q"&RIGHT(Annual!O$1,2),Qrtly!$A$3:$BH$3,0))+INDEX(Qrtly!$A:$BH,MATCH(Annual!$A29,Qrtly!$A:$A,0),MATCH("2Q"&RIGHT(Annual!O$1,2),Qrtly!$A$3:$BH$3,0))+INDEX(Qrtly!$A:$BH,MATCH(Annual!$A29,Qrtly!$A:$A,0),MATCH("3Q"&RIGHT(Annual!O$1,2),Qrtly!$A$3:$BH$3,0))+INDEX(Qrtly!$A:$BH,MATCH(Annual!$A29,Qrtly!$A:$A,0),MATCH("4Q"&RIGHT(Annual!O$1,2),Qrtly!$A$3:$BH$3,0)) -> 794221 | P29: =INDEX(Qrtly!$A:$BH,MATCH(Annual!$A29,Qrtly!$A:$A,0),MATCH("1Q"&RIGHT(Annual!P$1,2),Qrtly!$A$3:$BH$3,0))+INDEX(Qrtly!$A:$BH,MATCH(Annual!$A29,Qrtly!$A:$A,0),MATCH("2Q"&RIGHT(Annual!P$1,2),Qrtly!$A$3:$BH$3,0))+INDEX(Qrtly!$A:$BH,MATCH(Annual!$A29,Qrtly!$A:$A,0),MATCH("3Q"&RIGHT(Annual!P$1,2),Qrtly!$A$3:$BH$3,0))+INDEX(Qrtly!$A:$BH,MATCH(Annual!$A29,Qrtly!$A:$A,0),MATCH("4Q"&RIGHT(Annual!P$1,2),Qrtly!$A$3:$BH$3,0)) -> 1267546.4 | Q29: =INDEX(Qrtly!$A:$BH,MATCH(Annual!$A29,Qrtly!$A:$A,0),MATCH("1Q"&RIGHT(Annual!Q$1,2),Qrtly!$A$3:$BH$3,0))+INDEX(Qrtly!$A:$BH,MATCH(Annual!$A29,Qrtly!$A:$A,0),MATCH("2Q"&RIGHT(Annual!Q$1,2),Qrtly!$A$3:$BH$3,0))+INDEX(Qrtly!$A:$BH,MATCH(Annual!$A29,Qrtly!$A:$A,0),MATCH("3Q"&RIGHT(Annual!Q$1,2),Qrtly!$A$3:$BH$3,0))+INDEX(Qrtly!$A:$BH,MATCH(Annual!$A29,Qrtly!$A:$A,0),MATCH("4Q"&RIGHT(Annual!Q$1,2),Qrtly!$A$3:$BH$3,0)) -> 2058356.6 | R29: =INDEX(Qrtly!$A:$BH,MATCH(Annual!$A29,Qrtly!$A:$A,0),MATCH("1Q"&RIGHT(Annual!R$1,2),Qrtly!$A$3:$BH$3,0))+INDEX(Qrtly!$A:$BH,MATCH(Annual!$A29,Qrtly!$A:$A,0),MATCH("2Q"&RIGHT(Annual!R$1,2),Qrtly!$A$3:$BH$3,0))+INDEX(Qrtly!$A:$BH,MATCH(Annual!$A29,Qrtly!$A:$A,0),MATCH("3Q"&RIGHT(Annual!R$1,2),Qrtly!$A$3:$BH$3,0))+INDEX(Qrtly!$A:$BH,MATCH(Annual!$A29,Qrtly!$A:$A,0),MATCH("4Q"&RIGHT(Annual!R$1,2),Qrtly!$A$3:$BH$3,0)) -> 2813522.2 | S29: =INDEX(Qrtly!$A:$BH,MATCH(Annual!$A29,Qrtly!$A:$A,0),MATCH("1Q"&RIGHT(Annual!S$1,2),Qrtly!$A$3:$BH$3,0))+INDEX(Qrtly!$A:$BH,MATCH(Annual!$A29,Qrtly!$A:$A,0),MATCH("2Q"&RIGHT(Annual!S$1,2),Qrtly!$A$3:$BH$3,0))+INDEX(Qrtly!$A:$BH,MATCH(Annual!$A29,Qrtly!$A:$A,0),MATCH("3Q"&RIGHT(Annual!S$1,2),Qrtly!$A$3:$BH$3,0))+INDEX(Qrtly!$A:$BH,MATCH(Annual!$A29,Qrtly!$A:$A,0),MATCH("4Q"&RIGHT(Annual!S$1,2),Qrtly!$A$3:$BH$3,0)) -> 3657277.2 | T29: =INDEX(Qrtly!$A:$BH,MATCH(Annual!$A29,Qrtly!$A:$A,0),MATCH("1Q"&RIGHT(Annual!T$1,2),Qrtly!$A$3:$BH$3,0))+INDEX(Qrtly!$A:$BH,MATCH(Annual!$A29,Qrtly!$A:$A,0),MATCH("2Q"&RIGHT(Annual!T$1,2),Qrtly!$A$3:$BH$3,0))+INDEX(Qrtly!$A:$BH,MATCH(Annual!$A29,Qrtly!$A:$A,0),MATCH("3Q"&RIGHT(Annual!T$1,2),Qrtly!$A$3:$BH$3,0))+INDEX(Qrtly!$A:$BH,MATCH(Annual!$A29,Qrtly!$A:$A,0),MATCH("4Q"&RIGHT(Annual!T$1,2),Qrtly!$A$3:$BH$3,0)) -> 4590687.4 | U29: =INDEX(Qrtly!$A:$BH,MATCH(Annual!$A29,Qrtly!$A:$A,0),MATCH("1Q"&RIGHT(Annual!U$1,2),Qrtly!$A$3:$BH$3,0))+INDEX(Qrtly!$A:$BH,MATCH(Annual!$A29,Qrtly!$A:$A,0),MATCH("2Q"&RIGHT(Annual!U$1,2),Qrtly!$A$3:$BH$3,0))+INDEX(Qrtly!$A:$BH,MATCH(Annual!$A29,Qrtly!$A:$A,0),MATCH("3Q"&RIGHT(Annual!U$1,2),Qrtly!$A$3:$BH$3,0))+INDEX(Qrtly!$A:$BH,MATCH(Annual!$A29,Qrtly!$A:$A,0),MATCH("4Q"&RIGHT(Annual!U$1,2),Qrtly!$A$3:$BH$3,0)) -> 5706436 | ... Z29: =INDEX(Qrtly!$A:$BH,MATCH(Annual!$A29,Qrtly!$A:$A,0),MATCH("1Q"&RIGHT(Annual!Z$1,2),Qrtly!$A$3:$BH$3,0))+INDEX(Qrtly!$A:$BH,MATCH(Annual!$A29,Qrtly!$A:$A,0),MATCH("2Q"&RIGHT(Annual!Z$1,2),Qrtly!$A$3:$BH$3,0))+INDEX(Qrtly!$A:$BH,MATCH(Annual!$A29,Qrtly!$A:$A,0),MATCH("3Q"&RIGHT(Annual!Z$1,2),Qrtly!$A$3:$BH$3,0))+INDEX(Qrtly!$A:$BH,MATCH(Annual!$A29,Qrtly!$A:$A,0),MATCH("4Q"&RIGHT(Annual!Z$1,2),Qrtly!$A$3:$BH$3,0)) -> 15389295 | AC29: 1220085.6 | AD29: =IF(ISBLANK(AC29),"",INDEX($A29:$AA29,1,MATCH(AC$3,$A$3:$AA$3,0))-AC29) -> 47460.8 | AE29: 1905021.2 | AF29: =IF(ISBLANK(AE29),"",INDEX($A29:$AA29,1,MATCH(AE$3,$A$3:$AA$3,0))-AE29) -> 153335.48
A30: Opex-Other | B30: Other | F30: -29977 | G30: -1067 | H30: -6812 | I30: -19078 | J30: -19229 | K30: -16661 | L30: -11734 | M30: -26931 | N30: =INDEX(Qrtly!$A:$BH,MATCH(Annual!$A30,Qrtly!$A:$A,0),MATCH("1Q"&RIGHT(Annual!N$1,2),Qrtly!$A$3:$BH$3,0))+INDEX(Qrtly!$A:$BH,MATCH(Annual!$A30,Qrtly!$A:$A,0),MATCH("2Q"&RIGHT(Annual!N$1,2),Qrtly!$A$3:$BH$3,0))+INDEX(Qrtly!$A:$BH,MATCH(Annual!$A30,Qrtly!$A:$A,0),MATCH("3Q"&RIGHT(Annual!N$1,2),Qrtly!$A$3:$BH$3,0))+INDEX(Qrtly!$A:$BH,MATCH(Annual!$A30,Qrtly!$A:$A,0),MATCH("4Q"&RIGHT(Annual!N$1,2),Qrtly!$A$3:$BH$3,0)) -> -30270 | O30: =INDEX(Qrtly!$A:$BH,MATCH(Annual!$A30,Qrtly!$A:$A,0),MATCH("1Q"&RIGHT(Annual!O$1,2),Qrtly!$A$3:$BH$3,0))+INDEX(Qrtly!$A:$BH,MATCH(Annual!$A30,Qrtly!$A:$A,0),MATCH("2Q"&RIGHT(Annual!O$1,2),Qrtly!$A$3:$BH$3,0))+INDEX(Qrtly!$A:$BH,MATCH(Annual!$A30,Qrtly!$A:$A,0),MATCH("3Q"&RIGHT(Annual!O$1,2),Qrtly!$A$3:$BH$3,0))+INDEX(Qrtly!$A:$BH,MATCH(Annual!$A30,Qrtly!$A:$A,0),MATCH("4Q"&RIGHT(Annual!O$1,2),Qrtly!$A$3:$BH$3,0)) -> -224473 | P30: =INDEX(Qrtly!$A:$BH,MATCH(Annual!$A30,Qrtly!$A:$A,0),MATCH("1Q"&RIGHT(Annual!P$1,2),Qrtly!$A$3:$BH$3,0))+INDEX(Qrtly!$A:$BH,MATCH(Annual!$A30,Qrtly!$A:$A,0),MATCH("2Q"&RIGHT(Annual!P$1,2),Qrtly!$A$3:$BH$3,0))+INDEX(Qrtly!$A:$BH,MATCH(Annual!$A30,Qrtly!$A:$A,0),MATCH("3Q"&RIGHT(Annual!P$1,2),Qrtly!$A$3:$BH$3,0))+INDEX(Qrtly!$A:$BH,MATCH(Annual!$A30,Qrtly!$A:$A,0),MATCH("4Q"&RIGHT(Annual!P$1,2),Qrtly!$A$3:$BH$3,0)) -> -269125.56 | Q30: =INDEX(Qrtly!$A:$BH,MATCH(Annual!$A30,Qrtly!$A:$A,0),MATCH("1Q"&RIGHT(Annual!Q$1,2),Qrtly!$A$3:$BH$3,0))+INDEX(Qrtly!$A:$BH,MATCH(Annual!$A30,Qrtly!$A:$A,0),MATCH("2Q"&RIGHT(Annual!Q$1,2),Qrtly!$A$3:$BH$3,0))+INDEX(Qrtly!$A:$BH,MATCH(Annual!$A30,Qrtly!$A:$A,0),MATCH("3Q"&RIGHT(Annual!Q$1,2),Qrtly!$A$3:$BH$3,0))+INDEX(Qrtly!$A:$BH,MATCH(Annual!$A30,Qrtly!$A:$A,0),MATCH("4Q"&RIGHT(Annual!Q$1,2),Qrtly!$A$3:$BH$3,0)) -> -307406.82 | R30: =INDEX(Qrtly!$A:$BH,MATCH(Annual!$A30,Qrtly!$A:$A,0),MATCH("1Q"&RIGHT(Annual!R$1,2),Qrtly!$A$3:$BH$3,0))+INDEX(Qrtly!$A:$BH,MATCH(Annual!$A30,Qrtly!$A:$A,0),MATCH("2Q"&RIGHT(Annual!R$1,2),Qrtly!$A$3:$BH$3,0))+INDEX(Qrtly!$A:$BH,MATCH(Annual!$A30,Qrtly!$A:$A,0),MATCH("3Q"&RIGHT(Annual!R$1,2),Qrtly!$A$3:$BH$3,0))+INDEX(Qrtly!$A:$BH,MATCH(Annual!$A30,Qrtly!$A:$A,0),MATCH("4Q"&RIGHT(Annual!R$1,2),Qrtly!$A$3:$BH$3,0)) -> -349257.78 | S30: =INDEX(Qrtly!$A:$BH,MATCH(Annual!$A30,Qrtly!$A:$A,0),MATCH("1Q"&RIGHT(Annual!S$1,2),Qrtly!$A$3:$BH$3,0))+INDEX(Qrtly!$A:$BH,MATCH(Annual!$A30,Qrtly!$A:$A,0),MATCH("2Q"&RIGHT(Annual!S$1,2),Qrtly!$A$3:$BH$3,0))+INDEX(Qrtly!$A:$BH,MATCH(Annual!$A30,Qrtly!$A:$A,0),MATCH("3Q"&RIGHT(Annual!S$1,2),Qrtly!$A$3:$BH$3,0))+INDEX(Qrtly!$A:$BH,MATCH(Annual!$A30,Qrtly!$A:$A,0),MATCH("4Q"&RIGHT(Annual!S$1,2),Qrtly!$A$3:$BH$3,0)) -> -396857.03 | T30: =INDEX(Qrtly!$A:$BH,MATCH(Annual!$A30,Qrtly!$A:$A,0),MATCH("1Q"&RIGHT(Annual!T$1,2),Qrtly!$A$3:$BH$3,0))+INDEX(Qrtly!$A:$BH,MATCH(Annual!$A30,Qrtly!$A:$A,0),MATCH("2Q"&RIGHT(Annual!T$1,2),Qrtly!$A$3:$BH$3,0))+INDEX(Qrtly!$A:$BH,MATCH(Annual!$A30,Qrtly!$A:$A,0),MATCH("3Q"&RIGHT(Annual!T$1,2),Qrtly!$A$3:$BH$3,0))+INDEX(Qrtly!$A:$BH,MATCH(Annual!$A30,Qrtly!$A:$A,0),MATCH("4Q"&RIGHT(Annual!T$1,2),Qrtly!$A$3:$BH$3,0)) -> -447593.94 | U30: =INDEX(Qrtly!$A:$BH,MATCH(Annual!$A30,Qrtly!$A:$A,0),MATCH("1Q"&RIGHT(Annual!U$1,2),Qrtly!$A$3:$BH$3,0))+INDEX(Qrtly!$A:$BH,MATCH(Annual!$A30,Qrtly!$A:$A,0),MATCH("2Q"&RIGHT(Annual!U$1,2),Qrtly!$A$3:$BH$3,0))+INDEX(Qrtly!$A:$BH,MATCH(Annual!$A30,Qrtly!$A:$A,0),MATCH("3Q"&RIGHT(Annual!U$1,2),Qrtly!$A$3:$BH$3,0))+INDEX(Qrtly!$A:$BH,MATCH(Annual!$A30,Qrtly!$A:$A,0),MATCH("4Q"&RIGHT(Annual!U$1,2),Qrtly!$A$3:$BH$3,0)) -> -505223.82 | ... Z30: =INDEX(Qrtly!$A:$BH,MATCH(Annual!$A30,Qrtly!$A:$A,0),MATCH("1Q"&RIGHT(Annual!Z$1,2),Qrtly!$A$3:$BH$3,0))+INDEX(Qrtly!$A:$BH,MATCH(Annual!$A30,Qrtly!$A:$A,0),MATCH("2Q"&RIGHT(Annual!Z$1,2),Qrtly!$A$3:$BH$3,0))+INDEX(Qrtly!$A:$BH,MATCH(Annual!$A30,Qrtly!$A:$A,0),MATCH("3Q"&RIGHT(Annual!Z$1,2),Qrtly!$A$3:$BH$3,0))+INDEX(Qrtly!$A:$BH,MATCH(Annual!$A30,Qrtly!$A:$A,0),MATCH("4Q"&RIGHT(Annual!Z$1,2),Qrtly!$A$3:$BH$3,0)) -> -937080.5 | AC30: -264181.26 | AD30: =IF(ISBLANK(AC30),"",INDEX($A30:$AA30,1,MATCH(AC$3,$A$3:$AA$3,0))-AC30) -> -4944.2958 | AE30: -314005.16 | AF30: =IF(ISBLANK(AE30),"",INDEX($A30:$AA30,1,MATCH(AE$3,$A$3:$AA$3,0))-AE30) -> 6598.3445
A31: Opex-Total Operating Expenses (Non-GAAP) | B31: Total Operating Expenses (Non-GAAP) | C31: USDk | F31: 411145 | G31: 531151 | H31: 700297 | I31: 1047177 | J31: 1472832 | K31: 2259338 | L31: 3406166 | M31: 5000928 | N31: =INDEX(Qrtly!$A:$BH,MATCH(Annual!$A31,Qrtly!$A:$A,0),MATCH("1Q"&RIGHT(Annual!N$1,2),Qrtly!$A$3:$BH$3,0))+INDEX(Qrtly!$A:$BH,MATCH(Annual!$A31,Qrtly!$A:$A,0),MATCH("2Q"&RIGHT(Annual!N$1,2),Qrtly!$A$3:$BH$3,0))+INDEX(Qrtly!$A:$BH,MATCH(Annual!$A31,Qrtly!$A:$A,0),MATCH("3Q"&RIGHT(Annual!N$1,2),Qrtly!$A$3:$BH$3,0))+INDEX(Qrtly!$A:$BH,MATCH(Annual!$A31,Qrtly!$A:$A,0),MATCH("4Q"&RIGHT(Annual!N$1,2),Qrtly!$A$3:$BH$3,0)) -> 5712466 | O31: =INDEX(Qrtly!$A:$BH,MATCH(Annual!$A31,Qrtly!$A:$A,0),MATCH("1Q"&RIGHT(Annual!O$1,2),Qrtly!$A$3:$BH$3,0))+INDEX(Qrtly!$A:$BH,MATCH(Annual!$A31,Qrtly!$A:$A,0),MATCH("2Q"&RIGHT(Annual!O$1,2),Qrtly!$A$3:$BH$3,0))+INDEX(Qrtly!$A:$BH,MATCH(Annual!$A31,Qrtly!$A:$A,0),MATCH("3Q"&RIGHT(Annual!O$1,2),Qrtly!$A$3:$BH$3,0))+INDEX(Qrtly!$A:$BH,MATCH(Annual!$A31,Qrtly!$A:$A,0),MATCH("4Q"&RIGHT(Annual!O$1,2),Qrtly!$A$3:$BH$3,0)) -> 5860005 | P31: =INDEX(Qrtly!$A:$BH,MATCH(Annual!$A31,Qrtly!$A:$A,0),MATCH("1Q"&RIGHT(Annual!P$1,2),Qrtly!$A$3:$BH$3,0))+INDEX(Qrtly!$A:$BH,MATCH(Annual!$A31,Qrtly!$A:$A,0),MATCH("2Q"&RIGHT(Annual!P$1,2),Qrtly!$A$3:$BH$3,0))+INDEX(Qrtly!$A:$BH,MATCH(Annual!$A31,Qrtly!$A:$A,0),MATCH("3Q"&RIGHT(Annual!P$1,2),Qrtly!$A$3:$BH$3,0))+INDEX(Qrtly!$A:$BH,MATCH(Annual!$A31,Qrtly!$A:$A,0),MATCH("4Q"&RIGHT(Annual!P$1,2),Qrtly!$A$3:$BH$3,0)) -> 6829333.6 | Q31: =INDEX(Qrtly!$A:$BH,MATCH(Annual!$A31,Qrtly!$A:$A,0),MATCH("1Q"&RIGHT(Annual!Q$1,2),Qrtly!$A$3:$BH$3,0))+INDEX(Qrtly!$A:$BH,MATCH(Annual!$A31,Qrtly!$A:$A,0),MATCH("2Q"&RIGHT(Annual!Q$1,2),Qrtly!$A$3:$BH$3,0))+INDEX(Qrtly!$A:$BH,MATCH(Annual!$A31,Qrtly!$A:$A,0),MATCH("3Q"&RIGHT(Annual!Q$1,2),Qrtly!$A$3:$BH$3,0))+INDEX(Qrtly!$A:$BH,MATCH(Annual!$A31,Qrtly!$A:$A,0),MATCH("4Q"&RIGHT(Annual!Q$1,2),Qrtly!$A$3:$BH$3,0)) -> 7812333.9 | R31: =INDEX(Qrtly!$A:$BH,MATCH(Annual!$A31,Qrtly!$A:$A,0),MATCH("1Q"&RIGHT(Annual!R$1,2),Qrtly!$A$3:$BH$3,0))+INDEX(Qrtly!$A:$BH,MATCH(Annual!$A31,Qrtly!$A:$A,0),MATCH("2Q"&RIGHT(Annual!R$1,2),Qrtly!$A$3:$BH$3,0))+INDEX(Qrtly!$A:$BH,MATCH(Annual!$A31,Qrtly!$A:$A,0),MATCH("3Q"&RIGHT(Annual!R$1,2),Qrtly!$A$3:$BH$3,0))+INDEX(Qrtly!$A:$BH,MATCH(Annual!$A31,Qrtly!$A:$A,0),MATCH("4Q"&RIGHT(Annual!R$1,2),Qrtly!$A$3:$BH$3,0)) -> 8882902.1 | S31: =INDEX(Qrtly!$A:$BH,MATCH(Annual!$A31,Qrtly!$A:$A,0),MATCH("1Q"&RIGHT(Annual!S$1,2),Qrtly!$A$3:$BH$3,0))+INDEX(Qrtly!$A:$BH,MATCH(Annual!$A31,Qrtly!$A:$A,0),MATCH("2Q"&RIGHT(Annual!S$1,2),Qrtly!$A$3:$BH$3,0))+INDEX(Qrtly!$A:$BH,MATCH(Annual!$A31,Qrtly!$A:$A,0),MATCH("3Q"&RIGHT(Annual!S$1,2),Qrtly!$A$3:$BH$3,0))+INDEX(Qrtly!$A:$BH,MATCH(Annual!$A31,Qrtly!$A:$A,0),MATCH("4Q"&RIGHT(Annual!S$1,2),Qrtly!$A$3:$BH$3,0)) -> 10070665 | T31: =INDEX(Qrtly!$A:$BH,MATCH(Annual!$A31,Qrtly!$A:$A,0),MATCH("1Q"&RIGHT(Annual!T$1,2),Qrtly!$A$3:$BH$3,0))+INDEX(Qrtly!$A:$BH,MATCH(Annual!$A31,Qrtly!$A:$A,0),MATCH("2Q"&RIGHT(Annual!T$1,2),Qrtly!$A$3:$BH$3,0))+INDEX(Qrtly!$A:$BH,MATCH(Annual!$A31,Qrtly!$A:$A,0),MATCH("3Q"&RIGHT(Annual!T$1,2),Qrtly!$A$3:$BH$3,0))+INDEX(Qrtly!$A:$BH,MATCH(Annual!$A31,Qrtly!$A:$A,0),MATCH("4Q"&RIGHT(Annual!T$1,2),Qrtly!$A$3:$BH$3,0)) -> 11361963 | U31: =INDEX(Qrtly!$A:$BH,MATCH(Annual!$A31,Qrtly!$A:$A,0),MATCH("1Q"&RIGHT(Annual!U$1,2),Qrtly!$A$3:$BH$3,0))+INDEX(Qrtly!$A:$BH,MATCH(Annual!$A31,Qrtly!$A:$A,0),MATCH("2Q"&RIGHT(Annual!U$1,2),Qrtly!$A$3:$BH$3,0))+INDEX(Qrtly!$A:$BH,MATCH(Annual!$A31,Qrtly!$A:$A,0),MATCH("3Q"&RIGHT(Annual!U$1,2),Qrtly!$A$3:$BH$3,0))+INDEX(Qrtly!$A:$BH,MATCH(Annual!$A31,Qrtly!$A:$A,0),MATCH("4Q"&RIGHT(Annual!U$1,2),Qrtly!$A$3:$BH$3,0)) -> 12858873 | ... Z31: =INDEX(Qrtly!$A:$BH,MATCH(Annual!$A31,Qrtly!$A:$A,0),MATCH("1Q"&RIGHT(Annual!Z$1,2),Qrtly!$A$3:$BH$3,0))+INDEX(Qrtly!$A:$BH,MATCH(Annual!$A31,Qrtly!$A:$A,0),MATCH("2Q"&RIGHT(Annual!Z$1,2),Qrtly!$A$3:$BH$3,0))+INDEX(Qrtly!$A:$BH,MATCH(Annual!$A31,Qrtly!$A:$A,0),MATCH("3Q"&RIGHT(Annual!Z$1,2),Qrtly!$A$3:$BH$3,0))+INDEX(Qrtly!$A:$BH,MATCH(Annual!$A31,Qrtly!$A:$A,0),MATCH("4Q"&RIGHT(Annual!Z$1,2),Qrtly!$A$3:$BH$3,0)) -> 24856751 | AC31: 6721466.8 | AD31: =IF(ISBLANK(AC31),"",INDEX($A31:$AA31,1,MATCH(AC$3,$A$3:$AA$3,0))-AC31) -> 107866.8 | AE31: 7697815 | AF31: =IF(ISBLANK(AE31),"",INDEX($A31:$AA31,1,MATCH(AE$3,$A$3:$AA$3,0))-AE31) -> 114518.89
B32: % of GP | C32: % | F32: =F31/F19 -> 1.1111126 | G32: =G31/G19 -> 0.92207632 | H32: =H31/H19 -> 0.83437626 | I32: =I31/I19 -> 0.80323464 | J32: =J31/J19 -> 0.77940609 | K32: =K31/K19 -> 0.82656419 | L32: =L31/L19 -> 0.77065683 | M32: =M31/M19 -> 0.83461584 | ... Z32: =Z31/Z19 -> 0.54653918 | AC32: 0.65765052 | AD32: =IF(ISBLANK(AC32),"",INDEX($A32:$AA32,1,MATCH(AC$3,$A$3:$AA$3,0))-AC32) -> 0.0039797462 | AE32: 0.62427962 | AF32: =IF(ISBLANK(AE32),"",INDEX($A32:$AA32,1,MATCH(AE$3,$A$3:$AA$3,0))-AE32) -> 0.0020857507
AD33: =IF(ISBLANK(AC33),"",INDEX($A33:$AA33,1,MATCH(AC$3,$A$3:$AA$3,0))-AC33) | AF33: =IF(ISBLANK(AE33),"",INDEX($A33:$AA33,1,MATCH(AE$3,$A$3:$AA$3,0))-AE33)
B34: EBITDA | AD34: =IF(ISBLANK(AC34),"",INDEX($A34:$AA34,1,MATCH(AC$3,$A$3:$AA$3,0))-AC34) | AF34: =IF(ISBLANK(AE34),"",INDEX($A34:$AA34,1,MATCH(AE$3,$A$3:$AA$3,0))-AE34)
A35: UEBITDA-Adjusted EBITDA (Non-GAAP, as guided to) | B35: Adjusted EBITDA (Non-GAAP, as guided to) | C35: USDk | F35: -41115 | G35: 44887 | H35: 139009 | I35: 256523 | J35: 416853 | K35: 474071 | L35: 1013656 | M35: 990964 | N35: 1792420 | O35: =INDEX(Qrtly!$A:$BH,MATCH(Annual!$A35,Qrtly!$A:$A,0),MATCH("1Q"&RIGHT(Annual!O$1,2),Qrtly!$A$3:$BH$3,0))+INDEX(Qrtly!$A:$BH,MATCH(Annual!$A35,Qrtly!$A:$A,0),MATCH("2Q"&RIGHT(Annual!O$1,2),Qrtly!$A$3:$BH$3,0))+INDEX(Qrtly!$A:$BH,MATCH(Annual!$A35,Qrtly!$A:$A,0),MATCH("3Q"&RIGHT(Annual!O$1,2),Qrtly!$A$3:$BH$3,0))+INDEX(Qrtly!$A:$BH,MATCH(Annual!$A35,Qrtly!$A:$A,0),MATCH("4Q"&RIGHT(Annual!O$1,2),Qrtly!$A$3:$BH$3,0)) -> 3029031 | P35: =INDEX(Qrtly!$A:$BH,MATCH(Annual!$A35,Qrtly!$A:$A,0),MATCH("1Q"&RIGHT(Annual!P$1,2),Qrtly!$A$3:$BH$3,0))+INDEX(Qrtly!$A:$BH,MATCH(Annual!$A35,Qrtly!$A:$A,0),MATCH("2Q"&RIGHT(Annual!P$1,2),Qrtly!$A$3:$BH$3,0))+INDEX(Qrtly!$A:$BH,MATCH(Annual!$A35,Qrtly!$A:$A,0),MATCH("3Q"&RIGHT(Annual!P$1,2),Qrtly!$A$3:$BH$3,0))+INDEX(Qrtly!$A:$BH,MATCH(Annual!$A35,Qrtly!$A:$A,0),MATCH("4Q"&RIGHT(Annual!P$1,2),Qrtly!$A$3:$BH$3,0)) -> 3492645.2 | Q35: =INDEX(Qrtly!$A:$BH,MATCH(Annual!$A35,Qrtly!$A:$A,0),MATCH("1Q"&RIGHT(Annual!Q$1,2),Qrtly!$A$3:$BH$3,0))+INDEX(Qrtly!$A:$BH,MATCH(Annual!$A35,Qrtly!$A:$A,0),MATCH("2Q"&RIGHT(Annual!Q$1,2),Qrtly!$A$3:$BH$3,0))+INDEX(Qrtly!$A:$BH,MATCH(Annual!$A35,Qrtly!$A:$A,0),MATCH("3Q"&RIGHT(Annual!Q$1,2),Qrtly!$A$3:$BH$3,0))+INDEX(Qrtly!$A:$BH,MATCH(Annual!$A35,Qrtly!$A:$A,0),MATCH("4Q"&RIGHT(Annual!Q$1,2),Qrtly!$A$3:$BH$3,0)) -> 4660153.1 | R35: =INDEX(Qrtly!$A:$BH,MATCH(Annual!$A35,Qrtly!$A:$A,0),MATCH("1Q"&RIGHT(Annual!R$1,2),Qrtly!$A$3:$BH$3,0))+INDEX(Qrtly!$A:$BH,MATCH(Annual!$A35,Qrtly!$A:$A,0),MATCH("2Q"&RIGHT(Annual!R$1,2),Qrtly!$A$3:$BH$3,0))+INDEX(Qrtly!$A:$BH,MATCH(Annual!$A35,Qrtly!$A:$A,0),MATCH("3Q"&RIGHT(Annual!R$1,2),Qrtly!$A$3:$BH$3,0))+INDEX(Qrtly!$A:$BH,MATCH(Annual!$A35,Qrtly!$A:$A,0),MATCH("4Q"&RIGHT(Annual!R$1,2),Qrtly!$A$3:$BH$3,0)) -> 5742090.5 | S35: =INDEX(Qrtly!$A:$BH,MATCH(Annual!$A35,Qrtly!$A:$A,0),MATCH("1Q"&RIGHT(Annual!S$1,2),Qrtly!$A$3:$BH$3,0))+INDEX(Qrtly!$A:$BH,MATCH(Annual!$A35,Qrtly!$A:$A,0),MATCH("2Q"&RIGHT(Annual!S$1,2),Qrtly!$A$3:$BH$3,0))+INDEX(Qrtly!$A:$BH,MATCH(Annual!$A35,Qrtly!$A:$A,0),MATCH("3Q"&RIGHT(Annual!S$1,2),Qrtly!$A$3:$BH$3,0))+INDEX(Qrtly!$A:$BH,MATCH(Annual!$A35,Qrtly!$A:$A,0),MATCH("4Q"&RIGHT(Annual!S$1,2),Qrtly!$A$3:$BH$3,0)) -> 6876703.5 | T35: =INDEX(Qrtly!$A:$BH,MATCH(Annual!$A35,Qrtly!$A:$A,0),MATCH("1Q"&RIGHT(Annual!T$1,2),Qrtly!$A$3:$BH$3,0))+INDEX(Qrtly!$A:$BH,MATCH(Annual!$A35,Qrtly!$A:$A,0),MATCH("2Q"&RIGHT(Annual!T$1,2),Qrtly!$A$3:$BH$3,0))+INDEX(Qrtly!$A:$BH,MATCH(Annual!$A35,Qrtly!$A:$A,0),MATCH("3Q"&RIGHT(Annual!T$1,2),Qrtly!$A$3:$BH$3,0))+INDEX(Qrtly!$A:$BH,MATCH(Annual!$A35,Qrtly!$A:$A,0),MATCH("4Q"&RIGHT(Annual!T$1,2),Qrtly!$A$3:$BH$3,0)) -> 8031095.5 | U35: =INDEX(Qrtly!$A:$BH,MATCH(Annual!$A35,Qrtly!$A:$A,0),MATCH("1Q"&RIGHT(Annual!U$1,2),Qrtly!$A$3:$BH$3,0))+INDEX(Qrtly!$A:$BH,MATCH(Annual!$A35,Qrtly!$A:$A,0),MATCH("2Q"&RIGHT(Annual!U$1,2),Qrtly!$A$3:$BH$3,0))+INDEX(Qrtly!$A:$BH,MATCH(Annual!$A35,Qrtly!$A:$A,0),MATCH("3Q"&RIGHT(Annual!U$1,2),Qrtly!$A$3:$BH$3,0))+INDEX(Qrtly!$A:$BH,MATCH(Annual!$A35,Qrtly!$A:$A,0),MATCH("4Q"&RIGHT(Annual!U$1,2),Qrtly!$A$3:$BH$3,0)) -> 9375978.3 | V35: =INDEX(Qrtly!$A:$BH,MATCH(Annual!$A35,Qrtly!$A:$A,0),MATCH("1Q"&RIGHT(Annual!V$1,2),Qrtly!$A$3:$BH$3,0))+INDEX(Qrtly!$A:$BH,MATCH(Annual!$A35,Qrtly!$A:$A,0),MATCH("2Q"&RIGHT(Annual!V$1,2),Qrtly!$A$3:$BH$3,0))+INDEX(Qrtly!$A:$BH,MATCH(Annual!$A35,Qrtly!$A:$A,0),MATCH("3Q"&RIGHT(Annual!V$1,2),Qrtly!$A$3:$BH$3,0))+INDEX(Qrtly!$A:$BH,MATCH(Annual!$A35,Qrtly!$A:$A,0),MATCH("4Q"&RIGHT(Annual!V$1,2),Qrtly!$A$3:$BH$3,0)) -> 10948942 | ... Z35: =INDEX(Qrtly!$A:$BH,MATCH(Annual!$A35,Qrtly!$A:$A,0),MATCH("1Q"&RIGHT(Annual!Z$1,2),Qrtly!$A$3:$BH$3,0))+INDEX(Qrtly!$A:$BH,MATCH(Annual!$A35,Qrtly!$A:$A,0),MATCH("2Q"&RIGHT(Annual!Z$1,2),Qrtly!$A$3:$BH$3,0))+INDEX(Qrtly!$A:$BH,MATCH(Annual!$A35,Qrtly!$A:$A,0),MATCH("3Q"&RIGHT(Annual!Z$1,2),Qrtly!$A$3:$BH$3,0))+INDEX(Qrtly!$A:$BH,MATCH(Annual!$A35,Qrtly!$A:$A,0),MATCH("4Q"&RIGHT(Annual!Z$1,2),Qrtly!$A$3:$BH$3,0)) -> 20623522 | AA35: 0.01 | AB35: 0.02 | AC35: 3498956.6 | AD35: =IF(ISBLANK(AC35),"",INDEX($A35:$AA35,1,MATCH(AC$3,$A$3:$AA$3,0))-AC35) -> -6311.4256 | AE35: 4632901.5 | AF35: =IF(ISBLANK(AE35),"",INDEX($A35:$AA35,1,MATCH(AE$3,$A$3:$AA$3,0))-AE35) -> 27251.543
B36: Growth | C36: % YoY | F36: #DIV/0! | G36: -2.09 | H36: 2.1 | I36: 0.85 | J36: 0.63 | K36: 0.14 | L36: 1.14 | M36: -0.02 | N36: 0.81 | O36: =O35/N$35-1 -> 0.6899114 | P36: =P35/O35-1 -> 0.15305693 | Q36: =Q35/P35-1 -> 0.33427613 | R36: =R35/Q35-1 -> 0.23216779 | S36: =S35/R35-1 -> 0.1975958 | T36: =T35/S35-1 -> 0.16786996 | U36: =U35/T35-1 -> 0.16745945 | V36: =V35/U35-1 -> 0.16776528 | W36: =W35/V35-1 -> 0.1687157 | ... Z36: =Z35/Y35-1 -> 0.17480865 | AC36: 0.15514057 | AD36: =IF(ISBLANK(AC36),"",INDEX($A36:$AA36,1,MATCH(AC$3,$A$3:$AA$3,0))-AC36) -> -0.0020836451 | AE36: 0.32408088 | AF36: =IF(ISBLANK(AE36),"",INDEX($A36:$AA36,1,MATCH(AE$3,$A$3:$AA$3,0))-AE36) -> 0.010195247
B37: Margin | C37: % | F37: -0.032 | G37: 0.026 | H37: 0.063 | I37: 0.078 | J37: 0.088 | K37: 0.05 | L37: 0.057 | M37: 0.057 | N37: 0.082 | O37: =O35/O$10 -> 0.12557623 | P37: =P35/P10 -> 0.14558811 | Q37: =Q35/Q10 -> 0.17018089 | R37: =R35/R10 -> 0.18455801 | S37: =S35/S10 -> 0.19452854 | T37: =T35/T10 -> 0.20142165 | U37: =U35/U10 -> 0.20831795 | V37: =V35/V10 -> 0.21533265 | W37: =W35/W10 -> 0.22258393 | ... Z37: =Z35/Z10 -> 0.24698548 | AC37: 0.13498547 | AD37: =IF(ISBLANK(AC37),"",INDEX($A37:$AA37,1,MATCH(AC$3,$A$3:$AA$3,0))-AC37) -> 0.01060264 | AE37: 0.15035862 | AF37: =IF(ISBLANK(AE37),"",INDEX($A37:$AA37,1,MATCH(AE$3,$A$3:$AA$3,0))-AE37) -> 0.019822269
B38: Margin of GP | F38: -0.111 | G38: 0.078 | H38: 0.166 | I38: 0.197 | J38: 0.221 | K38: 0.173 | L38: 0.229 | M38: 0.165 | N38: 0.239 | O38: =O35/O$19 -> 0.34076035 | P38: =P35/P19 -> 0.33836973 | Q38: =Q35/Q19 -> 0.37363463 | R38: =R35/R19 -> 0.39262177 | S38: =S35/S19 -> 0.40576822 | T38: =T35/T19 -> 0.41412217 | U38: =U35/U19 -> 0.42167938 | V38: =V35/V19 -> 0.42861854 | W38: =W35/W19 -> 0.43511038 | ... Z38: =Z35/Z19 -> 0.45346082 | AC38: 0.34234948 | AD38: =IF(ISBLANK(AC38),"",INDEX($A38:$AA38,1,MATCH(AC$3,$A$3:$AA$3,0))-AC38) -> -0.0039797462 | AE38: 0.37572038 | AF38: =IF(ISBLANK(AE38),"",INDEX($A38:$AA38,1,MATCH(AE$3,$A$3:$AA$3,0))-AE38) -> -0.0020857507
B39: Initial Guidance | G39: 9000 | H39: 105000 | I39: 245000 | J39: 410000 | K39: 510000 | M39: NR | N39: 1300000 | O39: 2400000 | AD39: =IF(ISBLANK(AC39),"",INDEX($A39:$AA39,1,MATCH(AC$3,$A$3:$AA$3,0))-AC39) | AF39: =IF(ISBLANK(AE39),"",INDEX($A39:$AA39,1,MATCH(AE$3,$A$3:$AA$3,0))-AE39)
B40: vs guidance | G40: 3.99 | H40: 0.32 | I40: 0.05 | J40: 0.02 | K40: -0.07 | N40: 0.38 | O40: 0.26 | AD40: =IF(ISBLANK(AC40),"",INDEX($A40:$AA40,1,MATCH(AC$3,$A$3:$AA$3,0))-AC40) | AF40: =IF(ISBLANK(AE40),"",INDEX($A40:$AA40,1,MATCH(AE$3,$A$3:$AA$3,0))-AE40)
AD41: =IF(ISBLANK(AC41),"",INDEX($A41:$AA41,1,MATCH(AC$3,$A$3:$AA$3,0))-AC41) | AF41: =IF(ISBLANK(AE41),"",INDEX($A41:$AA41,1,MATCH(AE$3,$A$3:$AA$3,0))-AE41)
B42: D&A | AD42: =IF(ISBLANK(AC42),"",INDEX($A42:$AA42,1,MATCH(AC$3,$A$3:$AA$3,0))-AC42) | AF42: =IF(ISBLANK(AE42),"",INDEX($A42:$AA42,1,MATCH(AE$3,$A$3:$AA$3,0))-AE42)
A43: D&A-D&A | B43: D&A | C43: USDk | F43: 27626 | G43: 37745 | H43: 37279 | I43: 60961 | J43: 75598 | K43: 84212 | L43: 134756 | M43: 340523 | N43: 408560 | O43: =INDEX(Qrtly!$A:$BH,MATCH(Annual!$A43,Qrtly!$A:$A,0),MATCH("1Q"&RIGHT(Annual!O$1,2),Qrtly!$A$3:$BH$3,0))+INDEX(Qrtly!$A:$BH,MATCH(Annual!$A43,Qrtly!$A:$A,0),MATCH("2Q"&RIGHT(Annual!O$1,2),Qrtly!$A$3:$BH$3,0))+INDEX(Qrtly!$A:$BH,MATCH(Annual!$A43,Qrtly!$A:$A,0),MATCH("3Q"&RIGHT(Annual!O$1,2),Qrtly!$A$3:$BH$3,0))+INDEX(Qrtly!$A:$BH,MATCH(Annual!$A43,Qrtly!$A:$A,0),MATCH("4Q"&RIGHT(Annual!O$1,2),Qrtly!$A$3:$BH$3,0)) -> 376127 | P43: =INDEX(Qrtly!$A:$BH,MATCH(Annual!$A43,Qrtly!$A:$A,0),MATCH("1Q"&RIGHT(Annual!P$1,2),Qrtly!$A$3:$BH$3,0))+INDEX(Qrtly!$A:$BH,MATCH(Annual!$A43,Qrtly!$A:$A,0),MATCH("2Q"&RIGHT(Annual!P$1,2),Qrtly!$A$3:$BH$3,0))+INDEX(Qrtly!$A:$BH,MATCH(Annual!$A43,Qrtly!$A:$A,0),MATCH("3Q"&RIGHT(Annual!P$1,2),Qrtly!$A$3:$BH$3,0))+INDEX(Qrtly!$A:$BH,MATCH(Annual!$A43,Qrtly!$A:$A,0),MATCH("4Q"&RIGHT(Annual!P$1,2),Qrtly!$A$3:$BH$3,0)) -> 364194.53 | Q43: =INDEX(Qrtly!$A:$BH,MATCH(Annual!$A43,Qrtly!$A:$A,0),MATCH("1Q"&RIGHT(Annual!Q$1,2),Qrtly!$A$3:$BH$3,0))+INDEX(Qrtly!$A:$BH,MATCH(Annual!$A43,Qrtly!$A:$A,0),MATCH("2Q"&RIGHT(Annual!Q$1,2),Qrtly!$A$3:$BH$3,0))+INDEX(Qrtly!$A:$BH,MATCH(Annual!$A43,Qrtly!$A:$A,0),MATCH("3Q"&RIGHT(Annual!Q$1,2),Qrtly!$A$3:$BH$3,0))+INDEX(Qrtly!$A:$BH,MATCH(Annual!$A43,Qrtly!$A:$A,0),MATCH("4Q"&RIGHT(Annual!Q$1,2),Qrtly!$A$3:$BH$3,0)) -> 410752.92 | R43: =INDEX(Qrtly!$A:$BH,MATCH(Annual!$A43,Qrtly!$A:$A,0),MATCH("1Q"&RIGHT(Annual!R$1,2),Qrtly!$A$3:$BH$3,0))+INDEX(Qrtly!$A:$BH,MATCH(Annual!$A43,Qrtly!$A:$A,0),MATCH("2Q"&RIGHT(Annual!R$1,2),Qrtly!$A$3:$BH$3,0))+INDEX(Qrtly!$A:$BH,MATCH(Annual!$A43,Qrtly!$A:$A,0),MATCH("3Q"&RIGHT(Annual!R$1,2),Qrtly!$A$3:$BH$3,0))+INDEX(Qrtly!$A:$BH,MATCH(Annual!$A43,Qrtly!$A:$A,0),MATCH("4Q"&RIGHT(Annual!R$1,2),Qrtly!$A$3:$BH$3,0)) -> 466689.9 | S43: =INDEX(Qrtly!$A:$BH,MATCH(Annual!$A43,Qrtly!$A:$A,0),MATCH("1Q"&RIGHT(Annual!S$1,2),Qrtly!$A$3:$BH$3,0))+INDEX(Qrtly!$A:$BH,MATCH(Annual!$A43,Qrtly!$A:$A,0),MATCH("2Q"&RIGHT(Annual!S$1,2),Qrtly!$A$3:$BH$3,0))+INDEX(Qrtly!$A:$BH,MATCH(Annual!$A43,Qrtly!$A:$A,0),MATCH("3Q"&RIGHT(Annual!S$1,2),Qrtly!$A$3:$BH$3,0))+INDEX(Qrtly!$A:$BH,MATCH(Annual!$A43,Qrtly!$A:$A,0),MATCH("4Q"&RIGHT(Annual!S$1,2),Qrtly!$A$3:$BH$3,0)) -> 530259.23 | T43: =INDEX(Qrtly!$A:$BH,MATCH(Annual!$A43,Qrtly!$A:$A,0),MATCH("1Q"&RIGHT(Annual!T$1,2),Qrtly!$A$3:$BH$3,0))+INDEX(Qrtly!$A:$BH,MATCH(Annual!$A43,Qrtly!$A:$A,0),MATCH("2Q"&RIGHT(Annual!T$1,2),Qrtly!$A$3:$BH$3,0))+INDEX(Qrtly!$A:$BH,MATCH(Annual!$A43,Qrtly!$A:$A,0),MATCH("3Q"&RIGHT(Annual!T$1,2),Qrtly!$A$3:$BH$3,0))+INDEX(Qrtly!$A:$BH,MATCH(Annual!$A43,Qrtly!$A:$A,0),MATCH("4Q"&RIGHT(Annual!T$1,2),Qrtly!$A$3:$BH$3,0)) -> 598080.86 | U43: =INDEX(Qrtly!$A:$BH,MATCH(Annual!$A43,Qrtly!$A:$A,0),MATCH("1Q"&RIGHT(Annual!U$1,2),Qrtly!$A$3:$BH$3,0))+INDEX(Qrtly!$A:$BH,MATCH(Annual!$A43,Qrtly!$A:$A,0),MATCH("2Q"&RIGHT(Annual!U$1,2),Qrtly!$A$3:$BH$3,0))+INDEX(Qrtly!$A:$BH,MATCH(Annual!$A43,Qrtly!$A:$A,0),MATCH("3Q"&RIGHT(Annual!U$1,2),Qrtly!$A$3:$BH$3,0))+INDEX(Qrtly!$A:$BH,MATCH(Annual!$A43,Qrtly!$A:$A,0),MATCH("4Q"&RIGHT(Annual!U$1,2),Qrtly!$A$3:$BH$3,0)) -> 675120.3 | V43: =INDEX(Qrtly!$A:$BH,MATCH(Annual!$A43,Qrtly!$A:$A,0),MATCH("1Q"&RIGHT(Annual!V$1,2),Qrtly!$A$3:$BH$3,0))+INDEX(Qrtly!$A:$BH,MATCH(Annual!$A43,Qrtly!$A:$A,0),MATCH("2Q"&RIGHT(Annual!V$1,2),Qrtly!$A$3:$BH$3,0))+INDEX(Qrtly!$A:$BH,MATCH(Annual!$A43,Qrtly!$A:$A,0),MATCH("3Q"&RIGHT(Annual!V$1,2),Qrtly!$A$3:$BH$3,0))+INDEX(Qrtly!$A:$BH,MATCH(Annual!$A43,Qrtly!$A:$A,0),MATCH("4Q"&RIGHT(Annual!V$1,2),Qrtly!$A$3:$BH$3,0)) -> 762699.63 | ... Z43: =INDEX(Qrtly!$A:$BH,MATCH(Annual!$A43,Qrtly!$A:$A,0),MATCH("1Q"&RIGHT(Annual!Z$1,2),Qrtly!$A$3:$BH$3,0))+INDEX(Qrtly!$A:$BH,MATCH(Annual!$A43,Qrtly!$A:$A,0),MATCH("2Q"&RIGHT(Annual!Z$1,2),Qrtly!$A$3:$BH$3,0))+INDEX(Qrtly!$A:$BH,MATCH(Annual!$A43,Qrtly!$A:$A,0),MATCH("3Q"&RIGHT(Annual!Z$1,2),Qrtly!$A$3:$BH$3,0))+INDEX(Qrtly!$A:$BH,MATCH(Annual!$A43,Qrtly!$A:$A,0),MATCH("4Q"&RIGHT(Annual!Z$1,2),Qrtly!$A$3:$BH$3,0)) -> 1252514.2 | AC43: 392766.01 | AD43: =IF(ISBLANK(AC43),"",INDEX($A43:$AA43,1,MATCH(AC$3,$A$3:$AA$3,0))-AC43) -> -28571.484 | AE43: 462185.17 | AF43: =IF(ISBLANK(AE43),"",INDEX($A43:$AA43,1,MATCH(AE$3,$A$3:$AA$3,0))-AE43) -> -51432.249
B44: D&A / Revenue | C44: % | F44: 0.022 | G44: 0.022 | H44: 0.017 | I44: 0.018 | J44: 0.016 | K44: 0.009 | L44: 0.008 | M44: 0.019 | N44: 0.019 | O44: =O43/O10 -> 0.015593308 | P44: =P43/P10 -> 0.015181156 | Q44: =Q43/Q10 -> 0.015 | R44: =R43/R10 -> 0.015 | S44: =S43/S10 -> 0.015 | T44: =T43/T10 -> 0.015 | U44: =U43/U10 -> 0.015 | V44: =V43/V10 -> 0.015 | ... Z44: =Z43/Z10 -> 0.015 | AC44: 0.015152433 | AD44: =IF(ISBLANK(AC44),"",INDEX($A44:$AA44,1,MATCH(AC$3,$A$3:$AA$3,0))-AC44) -> 2.8723734e-05 | AE44: 0.015 | AF44: =IF(ISBLANK(AE44),"",INDEX($A44:$AA44,1,MATCH(AE$3,$A$3:$AA$3,0))-AE44) -> 0
AD45: =IF(ISBLANK(AC45),"",INDEX($A45:$AA45,1,MATCH(AC$3,$A$3:$AA$3,0))-AC45) | AF45: =IF(ISBLANK(AE45),"",INDEX($A45:$AA45,1,MATCH(AE$3,$A$3:$AA$3,0))-AE45)
B46: EBIT (Non-GAAP) | AD46: =IF(ISBLANK(AC46),"",INDEX($A46:$AA46,1,MATCH(AC$3,$A$3:$AA$3,0))-AC46) | AF46: =IF(ISBLANK(AE46),"",INDEX($A46:$AA46,1,MATCH(AE$3,$A$3:$AA$3,0))-AE46)
A47: EBITShare-based payments | B47: Share-based payments | F47: 82292 | G47: 138786 | H47: 155759 | I47: 216784 | J47: 297708 | K47: 397132 | L47: 607632 | M47: 1068795 | N47: 1275496 | O47: =INDEX(Qrtly!$A:$BH,MATCH(Annual!$A47,Qrtly!$A:$A,0),MATCH("1Q"&RIGHT(Annual!O$1,2),Qrtly!$A$3:$BH$3,0))+INDEX(Qrtly!$A:$BH,MATCH(Annual!$A47,Qrtly!$A:$A,0),MATCH("2Q"&RIGHT(Annual!O$1,2),Qrtly!$A$3:$BH$3,0))+INDEX(Qrtly!$A:$BH,MATCH(Annual!$A47,Qrtly!$A:$A,0),MATCH("3Q"&RIGHT(Annual!O$1,2),Qrtly!$A$3:$BH$3,0))+INDEX(Qrtly!$A:$BH,MATCH(Annual!$A47,Qrtly!$A:$A,0),MATCH("4Q"&RIGHT(Annual!O$1,2),Qrtly!$A$3:$BH$3,0)) -> 1264132 | P47: =INDEX(Qrtly!$A:$BH,MATCH(Annual!$A47,Qrtly!$A:$A,0),MATCH("1Q"&RIGHT(Annual!P$1,2),Qrtly!$A$3:$BH$3,0))+INDEX(Qrtly!$A:$BH,MATCH(Annual!$A47,Qrtly!$A:$A,0),MATCH("2Q"&RIGHT(Annual!P$1,2),Qrtly!$A$3:$BH$3,0))+INDEX(Qrtly!$A:$BH,MATCH(Annual!$A47,Qrtly!$A:$A,0),MATCH("3Q"&RIGHT(Annual!P$1,2),Qrtly!$A$3:$BH$3,0))+INDEX(Qrtly!$A:$BH,MATCH(Annual!$A47,Qrtly!$A:$A,0),MATCH("4Q"&RIGHT(Annual!P$1,2),Qrtly!$A$3:$BH$3,0)) -> 1217418 | Q47: =INDEX(Qrtly!$A:$BH,MATCH(Annual!$A47,Qrtly!$A:$A,0),MATCH("1Q"&RIGHT(Annual!Q$1,2),Qrtly!$A$3:$BH$3,0))+INDEX(Qrtly!$A:$BH,MATCH(Annual!$A47,Qrtly!$A:$A,0),MATCH("2Q"&RIGHT(Annual!Q$1,2),Qrtly!$A$3:$BH$3,0))+INDEX(Qrtly!$A:$BH,MATCH(Annual!$A47,Qrtly!$A:$A,0),MATCH("3Q"&RIGHT(Annual!Q$1,2),Qrtly!$A$3:$BH$3,0))+INDEX(Qrtly!$A:$BH,MATCH(Annual!$A47,Qrtly!$A:$A,0),MATCH("4Q"&RIGHT(Annual!Q$1,2),Qrtly!$A$3:$BH$3,0)) -> 1397244.1 | R47: =INDEX(Qrtly!$A:$BH,MATCH(Annual!$A47,Qrtly!$A:$A,0),MATCH("1Q"&RIGHT(Annual!R$1,2),Qrtly!$A$3:$BH$3,0))+INDEX(Qrtly!$A:$BH,MATCH(Annual!$A47,Qrtly!$A:$A,0),MATCH("2Q"&RIGHT(Annual!R$1,2),Qrtly!$A$3:$BH$3,0))+INDEX(Qrtly!$A:$BH,MATCH(Annual!$A47,Qrtly!$A:$A,0),MATCH("3Q"&RIGHT(Annual!R$1,2),Qrtly!$A$3:$BH$3,0))+INDEX(Qrtly!$A:$BH,MATCH(Annual!$A47,Qrtly!$A:$A,0),MATCH("4Q"&RIGHT(Annual!R$1,2),Qrtly!$A$3:$BH$3,0)) -> 1588644.1 | S47: =INDEX(Qrtly!$A:$BH,MATCH(Annual!$A47,Qrtly!$A:$A,0),MATCH("1Q"&RIGHT(Annual!S$1,2),Qrtly!$A$3:$BH$3,0))+INDEX(Qrtly!$A:$BH,MATCH(Annual!$A47,Qrtly!$A:$A,0),MATCH("2Q"&RIGHT(Annual!S$1,2),Qrtly!$A$3:$BH$3,0))+INDEX(Qrtly!$A:$BH,MATCH(Annual!$A47,Qrtly!$A:$A,0),MATCH("3Q"&RIGHT(Annual!S$1,2),Qrtly!$A$3:$BH$3,0))+INDEX(Qrtly!$A:$BH,MATCH(Annual!$A47,Qrtly!$A:$A,0),MATCH("4Q"&RIGHT(Annual!S$1,2),Qrtly!$A$3:$BH$3,0)) -> 1801710.4 | T47: =INDEX(Qrtly!$A:$BH,MATCH(Annual!$A47,Qrtly!$A:$A,0),MATCH("1Q"&RIGHT(Annual!T$1,2),Qrtly!$A$3:$BH$3,0))+INDEX(Qrtly!$A:$BH,MATCH(Annual!$A47,Qrtly!$A:$A,0),MATCH("2Q"&RIGHT(Annual!T$1,2),Qrtly!$A$3:$BH$3,0))+INDEX(Qrtly!$A:$BH,MATCH(Annual!$A47,Qrtly!$A:$A,0),MATCH("3Q"&RIGHT(Annual!T$1,2),Qrtly!$A$3:$BH$3,0))+INDEX(Qrtly!$A:$BH,MATCH(Annual!$A47,Qrtly!$A:$A,0),MATCH("4Q"&RIGHT(Annual!T$1,2),Qrtly!$A$3:$BH$3,0)) -> 2032788.8 | U47: =INDEX(Qrtly!$A:$BH,MATCH(Annual!$A47,Qrtly!$A:$A,0),MATCH("1Q"&RIGHT(Annual!U$1,2),Qrtly!$A$3:$BH$3,0))+INDEX(Qrtly!$A:$BH,MATCH(Annual!$A47,Qrtly!$A:$A,0),MATCH("2Q"&RIGHT(Annual!U$1,2),Qrtly!$A$3:$BH$3,0))+INDEX(Qrtly!$A:$BH,MATCH(Annual!$A47,Qrtly!$A:$A,0),MATCH("3Q"&RIGHT(Annual!U$1,2),Qrtly!$A$3:$BH$3,0))+INDEX(Qrtly!$A:$BH,MATCH(Annual!$A47,Qrtly!$A:$A,0),MATCH("4Q"&RIGHT(Annual!U$1,2),Qrtly!$A$3:$BH$3,0)) -> 2300484.8 | V47: =INDEX(Qrtly!$A:$BH,MATCH(Annual!$A47,Qrtly!$A:$A,0),MATCH("1Q"&RIGHT(Annual!V$1,2),Qrtly!$A$3:$BH$3,0))+INDEX(Qrtly!$A:$BH,MATCH(Annual!$A47,Qrtly!$A:$A,0),MATCH("2Q"&RIGHT(Annual!V$1,2),Qrtly!$A$3:$BH$3,0))+INDEX(Qrtly!$A:$BH,MATCH(Annual!$A47,Qrtly!$A:$A,0),MATCH("3Q"&RIGHT(Annual!V$1,2),Qrtly!$A$3:$BH$3,0))+INDEX(Qrtly!$A:$BH,MATCH(Annual!$A47,Qrtly!$A:$A,0),MATCH("4Q"&RIGHT(Annual!V$1,2),Qrtly!$A$3:$BH$3,0)) -> 2610897.3 | ... Z47: =INDEX(Qrtly!$A:$BH,MATCH(Annual!$A47,Qrtly!$A:$A,0),MATCH("1Q"&RIGHT(Annual!Z$1,2),Qrtly!$A$3:$BH$3,0))+INDEX(Qrtly!$A:$BH,MATCH(Annual!$A47,Qrtly!$A:$A,0),MATCH("2Q"&RIGHT(Annual!Z$1,2),Qrtly!$A$3:$BH$3,0))+INDEX(Qrtly!$A:$BH,MATCH(Annual!$A47,Qrtly!$A:$A,0),MATCH("3Q"&RIGHT(Annual!Z$1,2),Qrtly!$A$3:$BH$3,0))+INDEX(Qrtly!$A:$BH,MATCH(Annual!$A47,Qrtly!$A:$A,0),MATCH("4Q"&RIGHT(Annual!Z$1,2),Qrtly!$A$3:$BH$3,0)) -> 4441586.7 | AC47: 1196468 | AD47: =IF(ISBLANK(AC47),"",INDEX($A47:$AA47,1,MATCH(AC$3,$A$3:$AA$3,0))-AC47) -> 20950 | AE47: 1374661 | AF47: =IF(ISBLANK(AE47),"",INDEX($A47:$AA47,1,MATCH(AE$3,$A$3:$AA$3,0))-AE47) -> 22583.138
A48: EBITAmortization of acquired intangible assets | B48: Amortization of acquired intangible assets | F48: 0 | G48: 0 | H48: 0 | I48: 0 | J48: 0 | K48: 0 | L48: 0 | M48: -208952 | N48: -246873 | O48: =INDEX(Qrtly!$A:$BH,MATCH(Annual!$A48,Qrtly!$A:$A,0),MATCH("1Q"&RIGHT(Annual!O$1,2),Qrtly!$A$3:$BH$3,0))+INDEX(Qrtly!$A:$BH,MATCH(Annual!$A48,Qrtly!$A:$A,0),MATCH("2Q"&RIGHT(Annual!O$1,2),Qrtly!$A$3:$BH$3,0))+INDEX(Qrtly!$A:$BH,MATCH(Annual!$A48,Qrtly!$A:$A,0),MATCH("3Q"&RIGHT(Annual!O$1,2),Qrtly!$A$3:$BH$3,0))+INDEX(Qrtly!$A:$BH,MATCH(Annual!$A48,Qrtly!$A:$A,0),MATCH("4Q"&RIGHT(Annual!O$1,2),Qrtly!$A$3:$BH$3,0)) -> -223072 | P48: =INDEX(Qrtly!$A:$BH,MATCH(Annual!$A48,Qrtly!$A:$A,0),MATCH("1Q"&RIGHT(Annual!P$1,2),Qrtly!$A$3:$BH$3,0))+INDEX(Qrtly!$A:$BH,MATCH(Annual!$A48,Qrtly!$A:$A,0),MATCH("2Q"&RIGHT(Annual!P$1,2),Qrtly!$A$3:$BH$3,0))+INDEX(Qrtly!$A:$BH,MATCH(Annual!$A48,Qrtly!$A:$A,0),MATCH("3Q"&RIGHT(Annual!P$1,2),Qrtly!$A$3:$BH$3,0))+INDEX(Qrtly!$A:$BH,MATCH(Annual!$A48,Qrtly!$A:$A,0),MATCH("4Q"&RIGHT(Annual!P$1,2),Qrtly!$A$3:$BH$3,0)) -> -193510 | Q48: =INDEX(Qrtly!$A:$BH,MATCH(Annual!$A48,Qrtly!$A:$A,0),MATCH("1Q"&RIGHT(Annual!Q$1,2),Qrtly!$A$3:$BH$3,0))+INDEX(Qrtly!$A:$BH,MATCH(Annual!$A48,Qrtly!$A:$A,0),MATCH("2Q"&RIGHT(Annual!Q$1,2),Qrtly!$A$3:$BH$3,0))+INDEX(Qrtly!$A:$BH,MATCH(Annual!$A48,Qrtly!$A:$A,0),MATCH("3Q"&RIGHT(Annual!Q$1,2),Qrtly!$A$3:$BH$3,0))+INDEX(Qrtly!$A:$BH,MATCH(Annual!$A48,Qrtly!$A:$A,0),MATCH("4Q"&RIGHT(Annual!Q$1,2),Qrtly!$A$3:$BH$3,0)) -> -198626 | R48: =INDEX(Qrtly!$A:$BH,MATCH(Annual!$A48,Qrtly!$A:$A,0),MATCH("1Q"&RIGHT(Annual!R$1,2),Qrtly!$A$3:$BH$3,0))+INDEX(Qrtly!$A:$BH,MATCH(Annual!$A48,Qrtly!$A:$A,0),MATCH("2Q"&RIGHT(Annual!R$1,2),Qrtly!$A$3:$BH$3,0))+INDEX(Qrtly!$A:$BH,MATCH(Annual!$A48,Qrtly!$A:$A,0),MATCH("3Q"&RIGHT(Annual!R$1,2),Qrtly!$A$3:$BH$3,0))+INDEX(Qrtly!$A:$BH,MATCH(Annual!$A48,Qrtly!$A:$A,0),MATCH("4Q"&RIGHT(Annual!R$1,2),Qrtly!$A$3:$BH$3,0)) -> -203592 | S48: =INDEX(Qrtly!$A:$BH,MATCH(Annual!$A48,Qrtly!$A:$A,0),MATCH("1Q"&RIGHT(Annual!S$1,2),Qrtly!$A$3:$BH$3,0))+INDEX(Qrtly!$A:$BH,MATCH(Annual!$A48,Qrtly!$A:$A,0),MATCH("2Q"&RIGHT(Annual!S$1,2),Qrtly!$A$3:$BH$3,0))+INDEX(Qrtly!$A:$BH,MATCH(Annual!$A48,Qrtly!$A:$A,0),MATCH("3Q"&RIGHT(Annual!S$1,2),Qrtly!$A$3:$BH$3,0))+INDEX(Qrtly!$A:$BH,MATCH(Annual!$A48,Qrtly!$A:$A,0),MATCH("4Q"&RIGHT(Annual!S$1,2),Qrtly!$A$3:$BH$3,0)) -> -208681 | T48: =INDEX(Qrtly!$A:$BH,MATCH(Annual!$A48,Qrtly!$A:$A,0),MATCH("1Q"&RIGHT(Annual!T$1,2),Qrtly!$A$3:$BH$3,0))+INDEX(Qrtly!$A:$BH,MATCH(Annual!$A48,Qrtly!$A:$A,0),MATCH("2Q"&RIGHT(Annual!T$1,2),Qrtly!$A$3:$BH$3,0))+INDEX(Qrtly!$A:$BH,MATCH(Annual!$A48,Qrtly!$A:$A,0),MATCH("3Q"&RIGHT(Annual!T$1,2),Qrtly!$A$3:$BH$3,0))+INDEX(Qrtly!$A:$BH,MATCH(Annual!$A48,Qrtly!$A:$A,0),MATCH("4Q"&RIGHT(Annual!T$1,2),Qrtly!$A$3:$BH$3,0)) -> -213900 | U48: =INDEX(Qrtly!$A:$BH,MATCH(Annual!$A48,Qrtly!$A:$A,0),MATCH("1Q"&RIGHT(Annual!U$1,2),Qrtly!$A$3:$BH$3,0))+INDEX(Qrtly!$A:$BH,MATCH(Annual!$A48,Qrtly!$A:$A,0),MATCH("2Q"&RIGHT(Annual!U$1,2),Qrtly!$A$3:$BH$3,0))+INDEX(Qrtly!$A:$BH,MATCH(Annual!$A48,Qrtly!$A:$A,0),MATCH("3Q"&RIGHT(Annual!U$1,2),Qrtly!$A$3:$BH$3,0))+INDEX(Qrtly!$A:$BH,MATCH(Annual!$A48,Qrtly!$A:$A,0),MATCH("4Q"&RIGHT(Annual!U$1,2),Qrtly!$A$3:$BH$3,0)) -> -219246 | V48: =INDEX(Qrtly!$A:$BH,MATCH(Annual!$A48,Qrtly!$A:$A,0),MATCH("1Q"&RIGHT(Annual!V$1,2),Qrtly!$A$3:$BH$3,0))+INDEX(Qrtly!$A:$BH,MATCH(Annual!$A48,Qrtly!$A:$A,0),MATCH("2Q"&RIGHT(Annual!V$1,2),Qrtly!$A$3:$BH$3,0))+INDEX(Qrtly!$A:$BH,MATCH(Annual!$A48,Qrtly!$A:$A,0),MATCH("3Q"&RIGHT(Annual!V$1,2),Qrtly!$A$3:$BH$3,0))+INDEX(Qrtly!$A:$BH,MATCH(Annual!$A48,Qrtly!$A:$A,0),MATCH("4Q"&RIGHT(Annual!V$1,2),Qrtly!$A$3:$BH$3,0)) -> -224727 | ... Z48: =INDEX(Qrtly!$A:$BH,MATCH(Annual!$A48,Qrtly!$A:$A,0),MATCH("1Q"&RIGHT(Annual!Z$1,2),Qrtly!$A$3:$BH$3,0))+INDEX(Qrtly!$A:$BH,MATCH(Annual!$A48,Qrtly!$A:$A,0),MATCH("2Q"&RIGHT(Annual!Z$1,2),Qrtly!$A$3:$BH$3,0))+INDEX(Qrtly!$A:$BH,MATCH(Annual!$A48,Qrtly!$A:$A,0),MATCH("3Q"&RIGHT(Annual!Z$1,2),Qrtly!$A$3:$BH$3,0))+INDEX(Qrtly!$A:$BH,MATCH(Annual!$A48,Qrtly!$A:$A,0),MATCH("4Q"&RIGHT(Annual!Z$1,2),Qrtly!$A$3:$BH$3,0)) -> -248057 | AC48: -194114 | AD48: =IF(ISBLANK(AC48),"",INDEX($A48:$AA48,1,MATCH(AC$3,$A$3:$AA$3,0))-AC48) -> 604 | AE48: -198626 | AF48: =IF(ISBLANK(AE48),"",INDEX($A48:$AA48,1,MATCH(AE$3,$A$3:$AA$3,0))-AE48) -> 0
A49: EBITOther | B49: Other | F49: 0 | G49: 0 | H49: 0 | I49: 0 | J49: 0 | K49: 0 | L49: 0 | M49: -63994 | N49: 3886 | O49: =INDEX(Qrtly!$A:$BH,MATCH(Annual!$A49,Qrtly!$A:$A,0),MATCH("1Q"&RIGHT(Annual!O$1,2),Qrtly!$A$3:$BH$3,0))+INDEX(Qrtly!$A:$BH,MATCH(Annual!$A49,Qrtly!$A:$A,0),MATCH("2Q"&RIGHT(Annual!O$1,2),Qrtly!$A$3:$BH$3,0))+INDEX(Qrtly!$A:$BH,MATCH(Annual!$A49,Qrtly!$A:$A,0),MATCH("3Q"&RIGHT(Annual!O$1,2),Qrtly!$A$3:$BH$3,0))+INDEX(Qrtly!$A:$BH,MATCH(Annual!$A49,Qrtly!$A:$A,0),MATCH("4Q"&RIGHT(Annual!O$1,2),Qrtly!$A$3:$BH$3,0)) -> 3054 | P49: =INDEX(Qrtly!$A:$BH,MATCH(Annual!$A49,Qrtly!$A:$A,0),MATCH("1Q"&RIGHT(Annual!P$1,2),Qrtly!$A$3:$BH$3,0))+INDEX(Qrtly!$A:$BH,MATCH(Annual!$A49,Qrtly!$A:$A,0),MATCH("2Q"&RIGHT(Annual!P$1,2),Qrtly!$A$3:$BH$3,0))+INDEX(Qrtly!$A:$BH,MATCH(Annual!$A49,Qrtly!$A:$A,0),MATCH("3Q"&RIGHT(Annual!P$1,2),Qrtly!$A$3:$BH$3,0))+INDEX(Qrtly!$A:$BH,MATCH(Annual!$A49,Qrtly!$A:$A,0),MATCH("4Q"&RIGHT(Annual!P$1,2),Qrtly!$A$3:$BH$3,0)) -> 2819 | Q49: =INDEX(Qrtly!$A:$BH,MATCH(Annual!$A49,Qrtly!$A:$A,0),MATCH("1Q"&RIGHT(Annual!Q$1,2),Qrtly!$A$3:$BH$3,0))+INDEX(Qrtly!$A:$BH,MATCH(Annual!$A49,Qrtly!$A:$A,0),MATCH("2Q"&RIGHT(Annual!Q$1,2),Qrtly!$A$3:$BH$3,0))+INDEX(Qrtly!$A:$BH,MATCH(Annual!$A49,Qrtly!$A:$A,0),MATCH("3Q"&RIGHT(Annual!Q$1,2),Qrtly!$A$3:$BH$3,0))+INDEX(Qrtly!$A:$BH,MATCH(Annual!$A49,Qrtly!$A:$A,0),MATCH("4Q"&RIGHT(Annual!Q$1,2),Qrtly!$A$3:$BH$3,0)) -> 2077 | R49: =INDEX(Qrtly!$A:$BH,MATCH(Annual!$A49,Qrtly!$A:$A,0),MATCH("1Q"&RIGHT(Annual!R$1,2),Qrtly!$A$3:$BH$3,0))+INDEX(Qrtly!$A:$BH,MATCH(Annual!$A49,Qrtly!$A:$A,0),MATCH("2Q"&RIGHT(Annual!R$1,2),Qrtly!$A$3:$BH$3,0))+INDEX(Qrtly!$A:$BH,MATCH(Annual!$A49,Qrtly!$A:$A,0),MATCH("3Q"&RIGHT(Annual!R$1,2),Qrtly!$A$3:$BH$3,0))+INDEX(Qrtly!$A:$BH,MATCH(Annual!$A49,Qrtly!$A:$A,0),MATCH("4Q"&RIGHT(Annual!R$1,2),Qrtly!$A$3:$BH$3,0)) -> 2129 | S49: =INDEX(Qrtly!$A:$BH,MATCH(Annual!$A49,Qrtly!$A:$A,0),MATCH("1Q"&RIGHT(Annual!S$1,2),Qrtly!$A$3:$BH$3,0))+INDEX(Qrtly!$A:$BH,MATCH(Annual!$A49,Qrtly!$A:$A,0),MATCH("2Q"&RIGHT(Annual!S$1,2),Qrtly!$A$3:$BH$3,0))+INDEX(Qrtly!$A:$BH,MATCH(Annual!$A49,Qrtly!$A:$A,0),MATCH("3Q"&RIGHT(Annual!S$1,2),Qrtly!$A$3:$BH$3,0))+INDEX(Qrtly!$A:$BH,MATCH(Annual!$A49,Qrtly!$A:$A,0),MATCH("4Q"&RIGHT(Annual!S$1,2),Qrtly!$A$3:$BH$3,0)) -> 2182 | T49: =INDEX(Qrtly!$A:$BH,MATCH(Annual!$A49,Qrtly!$A:$A,0),MATCH("1Q"&RIGHT(Annual!T$1,2),Qrtly!$A$3:$BH$3,0))+INDEX(Qrtly!$A:$BH,MATCH(Annual!$A49,Qrtly!$A:$A,0),MATCH("2Q"&RIGHT(Annual!T$1,2),Qrtly!$A$3:$BH$3,0))+INDEX(Qrtly!$A:$BH,MATCH(Annual!$A49,Qrtly!$A:$A,0),MATCH("3Q"&RIGHT(Annual!T$1,2),Qrtly!$A$3:$BH$3,0))+INDEX(Qrtly!$A:$BH,MATCH(Annual!$A49,Qrtly!$A:$A,0),MATCH("4Q"&RIGHT(Annual!T$1,2),Qrtly!$A$3:$BH$3,0)) -> 2236 | U49: =INDEX(Qrtly!$A:$BH,MATCH(Annual!$A49,Qrtly!$A:$A,0),MATCH("1Q"&RIGHT(Annual!U$1,2),Qrtly!$A$3:$BH$3,0))+INDEX(Qrtly!$A:$BH,MATCH(Annual!$A49,Qrtly!$A:$A,0),MATCH("2Q"&RIGHT(Annual!U$1,2),Qrtly!$A$3:$BH$3,0))+INDEX(Qrtly!$A:$BH,MATCH(Annual!$A49,Qrtly!$A:$A,0),MATCH("3Q"&RIGHT(Annual!U$1,2),Qrtly!$A$3:$BH$3,0))+INDEX(Qrtly!$A:$BH,MATCH(Annual!$A49,Qrtly!$A:$A,0),MATCH("4Q"&RIGHT(Annual!U$1,2),Qrtly!$A$3:$BH$3,0)) -> 2292 | V49: =INDEX(Qrtly!$A:$BH,MATCH(Annual!$A49,Qrtly!$A:$A,0),MATCH("1Q"&RIGHT(Annual!V$1,2),Qrtly!$A$3:$BH$3,0))+INDEX(Qrtly!$A:$BH,MATCH(Annual!$A49,Qrtly!$A:$A,0),MATCH("2Q"&RIGHT(Annual!V$1,2),Qrtly!$A$3:$BH$3,0))+INDEX(Qrtly!$A:$BH,MATCH(Annual!$A49,Qrtly!$A:$A,0),MATCH("3Q"&RIGHT(Annual!V$1,2),Qrtly!$A$3:$BH$3,0))+INDEX(Qrtly!$A:$BH,MATCH(Annual!$A49,Qrtly!$A:$A,0),MATCH("4Q"&RIGHT(Annual!V$1,2),Qrtly!$A$3:$BH$3,0)) -> 2350 | ... Z49: =INDEX(Qrtly!$A:$BH,MATCH(Annual!$A49,Qrtly!$A:$A,0),MATCH("1Q"&RIGHT(Annual!Z$1,2),Qrtly!$A$3:$BH$3,0))+INDEX(Qrtly!$A:$BH,MATCH(Annual!$A49,Qrtly!$A:$A,0),MATCH("2Q"&RIGHT(Annual!Z$1,2),Qrtly!$A$3:$BH$3,0))+INDEX(Qrtly!$A:$BH,MATCH(Annual!$A49,Qrtly!$A:$A,0),MATCH("3Q"&RIGHT(Annual!Z$1,2),Qrtly!$A$3:$BH$3,0))+INDEX(Qrtly!$A:$BH,MATCH(Annual!$A49,Qrtly!$A:$A,0),MATCH("4Q"&RIGHT(Annual!Z$1,2),Qrtly!$A$3:$BH$3,0)) -> 2592 | AC49: 2701 | AD49: =IF(ISBLANK(AC49),"",INDEX($A49:$AA49,1,MATCH(AC$3,$A$3:$AA$3,0))-AC49) -> 118 | AE49: 2077 | AF49: =IF(ISBLANK(AE49),"",INDEX($A49:$AA49,1,MATCH(AE$3,$A$3:$AA$3,0))-AE49) -> 0
A50: EBITAdjusted Operating Income, EBITA (non-GAAP, as guided to) | B50: Adjusted Operating Income, EBITA (non-GAAP, as guided to) | C50: USDk | F50: -151033 | G50: -131644 | H50: -54029 | I50: -21222 | J50: 43547 | K50: -7273 | L50: 271268 | M50: -145408 | N50: 351351 | O50: =INDEX(Qrtly!$A:$BH,MATCH(Annual!$A50,Qrtly!$A:$A,0),MATCH("1Q"&RIGHT(Annual!O$1,2),Qrtly!$A$3:$BH$3,0))+INDEX(Qrtly!$A:$BH,MATCH(Annual!$A50,Qrtly!$A:$A,0),MATCH("2Q"&RIGHT(Annual!O$1,2),Qrtly!$A$3:$BH$3,0))+INDEX(Qrtly!$A:$BH,MATCH(Annual!$A50,Qrtly!$A:$A,0),MATCH("3Q"&RIGHT(Annual!O$1,2),Qrtly!$A$3:$BH$3,0))+INDEX(Qrtly!$A:$BH,MATCH(Annual!$A50,Qrtly!$A:$A,0),MATCH("4Q"&RIGHT(Annual!O$1,2),Qrtly!$A$3:$BH$3,0)) -> 1608790 | P50: =INDEX(Qrtly!$A:$BH,MATCH(Annual!$A50,Qrtly!$A:$A,0),MATCH("1Q"&RIGHT(Annual!P$1,2),Qrtly!$A$3:$BH$3,0))+INDEX(Qrtly!$A:$BH,MATCH(Annual!$A50,Qrtly!$A:$A,0),MATCH("2Q"&RIGHT(Annual!P$1,2),Qrtly!$A$3:$BH$3,0))+INDEX(Qrtly!$A:$BH,MATCH(Annual!$A50,Qrtly!$A:$A,0),MATCH("3Q"&RIGHT(Annual!P$1,2),Qrtly!$A$3:$BH$3,0))+INDEX(Qrtly!$A:$BH,MATCH(Annual!$A50,Qrtly!$A:$A,0),MATCH("4Q"&RIGHT(Annual!P$1,2),Qrtly!$A$3:$BH$3,0)) -> 2101723.6 | Q50: =INDEX(Qrtly!$A:$BH,MATCH(Annual!$A50,Qrtly!$A:$A,0),MATCH("1Q"&RIGHT(Annual!Q$1,2),Qrtly!$A$3:$BH$3,0))+INDEX(Qrtly!$A:$BH,MATCH(Annual!$A50,Qrtly!$A:$A,0),MATCH("2Q"&RIGHT(Annual!Q$1,2),Qrtly!$A$3:$BH$3,0))+INDEX(Qrtly!$A:$BH,MATCH(Annual!$A50,Qrtly!$A:$A,0),MATCH("3Q"&RIGHT(Annual!Q$1,2),Qrtly!$A$3:$BH$3,0))+INDEX(Qrtly!$A:$BH,MATCH(Annual!$A50,Qrtly!$A:$A,0),MATCH("4Q"&RIGHT(Annual!Q$1,2),Qrtly!$A$3:$BH$3,0)) -> 3048705 | R50: =INDEX(Qrtly!$A:$BH,MATCH(Annual!$A50,Qrtly!$A:$A,0),MATCH("1Q"&RIGHT(Annual!R$1,2),Qrtly!$A$3:$BH$3,0))+INDEX(Qrtly!$A:$BH,MATCH(Annual!$A50,Qrtly!$A:$A,0),MATCH("2Q"&RIGHT(Annual!R$1,2),Qrtly!$A$3:$BH$3,0))+INDEX(Qrtly!$A:$BH,MATCH(Annual!$A50,Qrtly!$A:$A,0),MATCH("3Q"&RIGHT(Annual!R$1,2),Qrtly!$A$3:$BH$3,0))+INDEX(Qrtly!$A:$BH,MATCH(Annual!$A50,Qrtly!$A:$A,0),MATCH("4Q"&RIGHT(Annual!R$1,2),Qrtly!$A$3:$BH$3,0)) -> 3888219.5 | S50: =INDEX(Qrtly!$A:$BH,MATCH(Annual!$A50,Qrtly!$A:$A,0),MATCH("1Q"&RIGHT(Annual!S$1,2),Qrtly!$A$3:$BH$3,0))+INDEX(Qrtly!$A:$BH,MATCH(Annual!$A50,Qrtly!$A:$A,0),MATCH("2Q"&RIGHT(Annual!S$1,2),Qrtly!$A$3:$BH$3,0))+INDEX(Qrtly!$A:$BH,MATCH(Annual!$A50,Qrtly!$A:$A,0),MATCH("3Q"&RIGHT(Annual!S$1,2),Qrtly!$A$3:$BH$3,0))+INDEX(Qrtly!$A:$BH,MATCH(Annual!$A50,Qrtly!$A:$A,0),MATCH("4Q"&RIGHT(Annual!S$1,2),Qrtly!$A$3:$BH$3,0)) -> 4751232.9 | T50: =INDEX(Qrtly!$A:$BH,MATCH(Annual!$A50,Qrtly!$A:$A,0),MATCH("1Q"&RIGHT(Annual!T$1,2),Qrtly!$A$3:$BH$3,0))+INDEX(Qrtly!$A:$BH,MATCH(Annual!$A50,Qrtly!$A:$A,0),MATCH("2Q"&RIGHT(Annual!T$1,2),Qrtly!$A$3:$BH$3,0))+INDEX(Qrtly!$A:$BH,MATCH(Annual!$A50,Qrtly!$A:$A,0),MATCH("3Q"&RIGHT(Annual!T$1,2),Qrtly!$A$3:$BH$3,0))+INDEX(Qrtly!$A:$BH,MATCH(Annual!$A50,Qrtly!$A:$A,0),MATCH("4Q"&RIGHT(Annual!T$1,2),Qrtly!$A$3:$BH$3,0)) -> 5611889.8 | U50: =INDEX(Qrtly!$A:$BH,MATCH(Annual!$A50,Qrtly!$A:$A,0),MATCH("1Q"&RIGHT(Annual!U$1,2),Qrtly!$A$3:$BH$3,0))+INDEX(Qrtly!$A:$BH,MATCH(Annual!$A50,Qrtly!$A:$A,0),MATCH("2Q"&RIGHT(Annual!U$1,2),Qrtly!$A$3:$BH$3,0))+INDEX(Qrtly!$A:$BH,MATCH(Annual!$A50,Qrtly!$A:$A,0),MATCH("3Q"&RIGHT(Annual!U$1,2),Qrtly!$A$3:$BH$3,0))+INDEX(Qrtly!$A:$BH,MATCH(Annual!$A50,Qrtly!$A:$A,0),MATCH("4Q"&RIGHT(Annual!U$1,2),Qrtly!$A$3:$BH$3,0)) -> 6617327.2 | V50: =INDEX(Qrtly!$A:$BH,MATCH(Annual!$A50,Qrtly!$A:$A,0),MATCH("1Q"&RIGHT(Annual!V$1,2),Qrtly!$A$3:$BH$3,0))+INDEX(Qrtly!$A:$BH,MATCH(Annual!$A50,Qrtly!$A:$A,0),MATCH("2Q"&RIGHT(Annual!V$1,2),Qrtly!$A$3:$BH$3,0))+INDEX(Qrtly!$A:$BH,MATCH(Annual!$A50,Qrtly!$A:$A,0),MATCH("3Q"&RIGHT(Annual!V$1,2),Qrtly!$A$3:$BH$3,0))+INDEX(Qrtly!$A:$BH,MATCH(Annual!$A50,Qrtly!$A:$A,0),MATCH("4Q"&RIGHT(Annual!V$1,2),Qrtly!$A$3:$BH$3,0)) -> 7797722 | ... Z50: =INDEX(Qrtly!$A:$BH,MATCH(Annual!$A50,Qrtly!$A:$A,0),MATCH("1Q"&RIGHT(Annual!Z$1,2),Qrtly!$A$3:$BH$3,0))+INDEX(Qrtly!$A:$BH,MATCH(Annual!$A50,Qrtly!$A:$A,0),MATCH("2Q"&RIGHT(Annual!Z$1,2),Qrtly!$A$3:$BH$3,0))+INDEX(Qrtly!$A:$BH,MATCH(Annual!$A50,Qrtly!$A:$A,0),MATCH("3Q"&RIGHT(Annual!Z$1,2),Qrtly!$A$3:$BH$3,0))+INDEX(Qrtly!$A:$BH,MATCH(Annual!$A50,Qrtly!$A:$A,0),MATCH("4Q"&RIGHT(Annual!Z$1,2),Qrtly!$A$3:$BH$3,0)) -> 15174886 | AA50: 0.03 | AB50: 0.03 | AC50: 2101135.6 | AD50: =IF(ISBLANK(AC50),"",INDEX($A50:$AA50,1,MATCH(AC$3,$A$3:$AA$3,0))-AC50) -> 588.05878 | AE50: 2992604.4 | AF50: =IF(ISBLANK(AE50),"",INDEX($A50:$AA50,1,MATCH(AE$3,$A$3:$AA$3,0))-AE50) -> 56100.655
B51: Growth | C51: % YoY | G51: -0.13 | H51: -0.59 | I51: -0.61 | J51: -3.05 | K51: -1.17 | L51: -38.3 | M51: -1.54 | N51: -3.42 | O51: =O50/N$35-1 -> -0.10244809 | P51: =P50/O$35-1 -> -0.30613993 | Q51: =Q50/P$35-1 -> -0.12710714 | R51: =R50/Q$35-1 -> -0.16564554 | S51: =S50/R$35-1 -> -0.17256044 | T51: =T50/S$35-1 -> -0.18392733 | U51: =U50/T$35-1 -> -0.17603679 | V51: =V50/U$35-1 -> -0.16832978 | ... Z51: =Z50/Y$35-1 -> -0.13557018 | AC51: -0.30633408 | AD51: =IF(ISBLANK(AC51),"",INDEX($A51:$AA51,1,MATCH(AC$3,$A$3:$AA$3,0))-AC51) -> 0.00019414089 | AE51: -0.14471521 | AF51: =IF(ISBLANK(AE51),"",INDEX($A51:$AA51,1,MATCH(AE$3,$A$3:$AA$3,0))-AE51) -> 0.017608064
B52: EBIT Margin | C52: % | F52: -0.119 | G52: -0.077 | H52: -0.024 | I52: -0.006 | J52: 0.009 | K52: -0.001 | L52: 0.015 | M52: -0.008 | N52: 0.016 | O52: =O50/O$10 -> 0.066696508 | P52: =P50/P$10 -> 0.087608663 | Q52: =Q50/Q$10 -> 0.11133354 | R52: =R50/R$10 -> 0.12497226 | S52: =S50/S$10 -> 0.13440312 | T52: =T50/T$10 -> 0.14074743 | U52: =U50/U$10 -> 0.14702551 | V52: =V50/V$10 -> 0.15335766 | ... Z52: =Z50/Z$10 -> 0.1817331 | AC52: 0.081059243 | AD52: =IF(ISBLANK(AC52),"",INDEX($A52:$AA52,1,MATCH(AC$3,$A$3:$AA$3,0))-AC52) -> 0.0065494196 | AE52: 0.097123552 | AF52: =IF(ISBLANK(AE52),"",INDEX($A52:$AA52,1,MATCH(AE$3,$A$3:$AA$3,0))-AE52) -> 0.014209984
B53: Margin of GP | C53: % | F53: -0.408 | G53: -0.229 | H53: -0.064 | I53: -0.016 | J53: 0.023 | K53: -0.003 | L53: 0.061 | M53: -0.024 | N53: 0.047 | O53: =O50/O$19 -> 0.18098588 | P53: =P50/P$19 -> 0.20361635 | Q53: =Q50/Q$19 -> 0.24443441 | R53: =R50/R$19 -> 0.2658613 | S53: =S50/S$19 -> 0.28035225 | T53: =T50/T$19 -> 0.28937621 | U53: =U50/U$19 -> 0.29761059 | V53: =V50/V$19 -> 0.30525764 | ... Z53: =Z50/Z$19 -> 0.33365864 | AC53: 0.20558205 | AD53: =IF(ISBLANK(AC53),"",INDEX($A53:$AA53,1,MATCH(AC$3,$A$3:$AA$3,0))-AC53) -> -0.001965699 | AE53: 0.24269509 | AF53: =IF(ISBLANK(AE53),"",INDEX($A53:$AA53,1,MATCH(AE$3,$A$3:$AA$3,0))-AE53) -> 0.0017393216
B54: Initial Guidance | K54: NR | M54: NR | N54: -150000 | O54: 875000 | P54: 2100000 | AC54: 2100000 | AD54: =IF(ISBLANK(AC54),"",INDEX($A54:$AA54,1,MATCH(AC$3,$A$3:$AA$3,0))-AC54) -> 0 | AF54: =IF(ISBLANK(AE54),"",INDEX($A54:$AA54,1,MATCH(AE$3,$A$3:$AA$3,0))-AE54)
B55: Latest Guidance | O55: 1560000 | P55: 2056000 | R55: 2056000 | AC55: 2030000 | AD55: =IF(ISBLANK(AC55),"",INDEX($A55:$AA55,1,MATCH(AC$3,$A$3:$AA$3,0))-AC55) -> 26000 | AF55: =IF(ISBLANK(AE55),"",INDEX($A55:$AA55,1,MATCH(AE$3,$A$3:$AA$3,0))-AE55)
B56: vs guidance | M56: #VALUE! | N56: -3.34 | O56: 0.84 | P56: 0 | R56: =R55/P55-1 -> 0 | AC56: 0 | AD56: =IF(ISBLANK(AC56),"",INDEX($A56:$AA56,1,MATCH(AC$3,$A$3:$AA$3,0))-AC56) -> 0 | AF56: =IF(ISBLANK(AE56),"",INDEX($A56:$AA56,1,MATCH(AE$3,$A$3:$AA$3,0))-AE56)
AD57: =IF(ISBLANK(AC57),"",INDEX($A57:$AA57,1,MATCH(AC$3,$A$3:$AA$3,0))-AC57) | AF57: =IF(ISBLANK(AE57),"",INDEX($A57:$AA57,1,MATCH(AE$3,$A$3:$AA$3,0))-AE57)
B58: Rule of 40 | N58: =N53+N20 -> 0.3 | O58: =O53+O20 -> 0.36541906 | P58: =P53+P20 -> 0.36481975 | Q58: =Q53+Q20 -> 0.45277704 | R58: =R53+R20 -> 0.4384416 | S58: =S53+S20 -> 0.43914725 | T58: =T53+T20 -> 0.43368712 | U58: =U53+U20 -> 0.44414718 | ... Z58: =Z53+Z20 -> 0.49273091 | AC58: 0.35536066 | AD58: =IF(ISBLANK(AC58),"",INDEX($A58:$AA58,1,MATCH(AC$3,$A$3:$AA$3,0))-AC58) -> 0.0094590918 | AE58: 0.44917315 | AF58: =IF(ISBLANK(AE58),"",INDEX($A58:$AA58,1,MATCH(AE$3,$A$3:$AA$3,0))-AE58) -> 0.0036038962
AD59: =IF(ISBLANK(AC59),"",INDEX($A59:$AA59,1,MATCH(AC$3,$A$3:$AA$3,0))-AC59) | AF59: =IF(ISBLANK(AE59),"",INDEX($A59:$AA59,1,MATCH(AE$3,$A$3:$AA$3,0))-AE59)
B60: Interest | AD60: =IF(ISBLANK(AC60),"",INDEX($A60:$AA60,1,MATCH(AC$3,$A$3:$AA$3,0))-AC60) | AF60: =IF(ISBLANK(AE60),"",INDEX($A60:$AA60,1,MATCH(AE$3,$A$3:$AA$3,0))-AE60)
A61: Interest income | B61: Interest income | P61: =P64 -> 120582 | Q61: =Q64 -> 182803.82 | R61: =R64 -> 187373.91 | S61: =S64 -> 192058.26 | T61: =T64 -> 196859.72 | U61: =U64 -> 201781.21 | V61: =V64 -> 206825.74 | W61: =W64 -> 211996.39 | ... Z61: =Z64 -> 228296.92 | AC61: 88744.935 | AD61: =IF(ISBLANK(AC61),"",INDEX($A61:$AA61,1,MATCH(AC$3,$A$3:$AA$3,0))-AC61) -> 31837.065 | AE61: 97419.241 | AF61: =IF(ISBLANK(AE61),"",INDEX($A61:$AA61,1,MATCH(AE$3,$A$3:$AA$3,0))-AE61) -> 85384.578
A62: Interest on lease liabilities | B62: Interest on lease liabilities | P62: 0 | Q62: 0 | R62: 0 | S62: 0 | T62: 0 | U62: 0 | V62: 0 | W62: 0 | X62: 0 | Y62: 0 | Z62: 0 | AC62: 0 | AD62: =IF(ISBLANK(AC62),"",INDEX($A62:$AA62,1,MATCH(AC$3,$A$3:$AA$3,0))-AC62) -> 0 | AE62: 0 | AF62: =IF(ISBLANK(AE62),"",INDEX($A62:$AA62,1,MATCH(AE$3,$A$3:$AA$3,0))-AE62) -> 0
A63: Interest expense | B63: Interest expense | P63: 0 | Q63: 0 | R63: 0 | S63: 0 | T63: 0 | U63: 0 | V63: 0 | W63: 0 | X63: 0 | Y63: 0 | Z63: 0 | AC63: 0 | AD63: =IF(ISBLANK(AC63),"",INDEX($A63:$AA63,1,MATCH(AC$3,$A$3:$AA$3,0))-AC63) -> 0 | AE63: 0 | AF63: =IF(ISBLANK(AE63),"",INDEX($A63:$AA63,1,MATCH(AE$3,$A$3:$AA$3,0))-AE63) -> 0
A64: Net Interest | B64: Net Interest | C64: USDk | F64: 1163 | G64: -533 | H64: 10053 | I64: 17982 | J64: 21516 | K64: 56943 | L64: 33124 | M64: 36228 | N64: -47221 | O64: =INDEX(Qrtly!$A:$BH,MATCH(Annual!$A64,Qrtly!$A:$A,0),MATCH("1Q"&RIGHT(Annual!O$1,2),Qrtly!$A$3:$BH$3,0))+INDEX(Qrtly!$A:$BH,MATCH(Annual!$A64,Qrtly!$A:$A,0),MATCH("2Q"&RIGHT(Annual!O$1,2),Qrtly!$A$3:$BH$3,0))+INDEX(Qrtly!$A:$BH,MATCH(Annual!$A64,Qrtly!$A:$A,0),MATCH("3Q"&RIGHT(Annual!O$1,2),Qrtly!$A$3:$BH$3,0))+INDEX(Qrtly!$A:$BH,MATCH(Annual!$A64,Qrtly!$A:$A,0),MATCH("4Q"&RIGHT(Annual!O$1,2),Qrtly!$A$3:$BH$3,0)) -> 9302 | P64: =INDEX(Qrtly!$A:$BH,MATCH(Annual!$A64,Qrtly!$A:$A,0),MATCH("1Q"&RIGHT(Annual!P$1,2),Qrtly!$A$3:$BH$3,0))+INDEX(Qrtly!$A:$BH,MATCH(Annual!$A64,Qrtly!$A:$A,0),MATCH("2Q"&RIGHT(Annual!P$1,2),Qrtly!$A$3:$BH$3,0))+INDEX(Qrtly!$A:$BH,MATCH(Annual!$A64,Qrtly!$A:$A,0),MATCH("3Q"&RIGHT(Annual!P$1,2),Qrtly!$A$3:$BH$3,0))+INDEX(Qrtly!$A:$BH,MATCH(Annual!$A64,Qrtly!$A:$A,0),MATCH("4Q"&RIGHT(Annual!P$1,2),Qrtly!$A$3:$BH$3,0)) -> 120582 | Q64: =INDEX(Qrtly!$A:$BH,MATCH(Annual!$A64,Qrtly!$A:$A,0),MATCH("1Q"&RIGHT(Annual!Q$1,2),Qrtly!$A$3:$BH$3,0))+INDEX(Qrtly!$A:$BH,MATCH(Annual!$A64,Qrtly!$A:$A,0),MATCH("2Q"&RIGHT(Annual!Q$1,2),Qrtly!$A$3:$BH$3,0))+INDEX(Qrtly!$A:$BH,MATCH(Annual!$A64,Qrtly!$A:$A,0),MATCH("3Q"&RIGHT(Annual!Q$1,2),Qrtly!$A$3:$BH$3,0))+INDEX(Qrtly!$A:$BH,MATCH(Annual!$A64,Qrtly!$A:$A,0),MATCH("4Q"&RIGHT(Annual!Q$1,2),Qrtly!$A$3:$BH$3,0)) -> 182803.82 | R64: =INDEX(Qrtly!$A:$BH,MATCH(Annual!$A64,Qrtly!$A:$A,0),MATCH("1Q"&RIGHT(Annual!R$1,2),Qrtly!$A$3:$BH$3,0))+INDEX(Qrtly!$A:$BH,MATCH(Annual!$A64,Qrtly!$A:$A,0),MATCH("2Q"&RIGHT(Annual!R$1,2),Qrtly!$A$3:$BH$3,0))+INDEX(Qrtly!$A:$BH,MATCH(Annual!$A64,Qrtly!$A:$A,0),MATCH("3Q"&RIGHT(Annual!R$1,2),Qrtly!$A$3:$BH$3,0))+INDEX(Qrtly!$A:$BH,MATCH(Annual!$A64,Qrtly!$A:$A,0),MATCH("4Q"&RIGHT(Annual!R$1,2),Qrtly!$A$3:$BH$3,0)) -> 187373.91 | S64: =INDEX(Qrtly!$A:$BH,MATCH(Annual!$A64,Qrtly!$A:$A,0),MATCH("1Q"&RIGHT(Annual!S$1,2),Qrtly!$A$3:$BH$3,0))+INDEX(Qrtly!$A:$BH,MATCH(Annual!$A64,Qrtly!$A:$A,0),MATCH("2Q"&RIGHT(Annual!S$1,2),Qrtly!$A$3:$BH$3,0))+INDEX(Qrtly!$A:$BH,MATCH(Annual!$A64,Qrtly!$A:$A,0),MATCH("3Q"&RIGHT(Annual!S$1,2),Qrtly!$A$3:$BH$3,0))+INDEX(Qrtly!$A:$BH,MATCH(Annual!$A64,Qrtly!$A:$A,0),MATCH("4Q"&RIGHT(Annual!S$1,2),Qrtly!$A$3:$BH$3,0)) -> 192058.26 | T64: =INDEX(Qrtly!$A:$BH,MATCH(Annual!$A64,Qrtly!$A:$A,0),MATCH("1Q"&RIGHT(Annual!T$1,2),Qrtly!$A$3:$BH$3,0))+INDEX(Qrtly!$A:$BH,MATCH(Annual!$A64,Qrtly!$A:$A,0),MATCH("2Q"&RIGHT(Annual!T$1,2),Qrtly!$A$3:$BH$3,0))+INDEX(Qrtly!$A:$BH,MATCH(Annual!$A64,Qrtly!$A:$A,0),MATCH("3Q"&RIGHT(Annual!T$1,2),Qrtly!$A$3:$BH$3,0))+INDEX(Qrtly!$A:$BH,MATCH(Annual!$A64,Qrtly!$A:$A,0),MATCH("4Q"&RIGHT(Annual!T$1,2),Qrtly!$A$3:$BH$3,0)) -> 196859.72 | U64: =INDEX(Qrtly!$A:$BH,MATCH(Annual!$A64,Qrtly!$A:$A,0),MATCH("1Q"&RIGHT(Annual!U$1,2),Qrtly!$A$3:$BH$3,0))+INDEX(Qrtly!$A:$BH,MATCH(Annual!$A64,Qrtly!$A:$A,0),MATCH("2Q"&RIGHT(Annual!U$1,2),Qrtly!$A$3:$BH$3,0))+INDEX(Qrtly!$A:$BH,MATCH(Annual!$A64,Qrtly!$A:$A,0),MATCH("3Q"&RIGHT(Annual!U$1,2),Qrtly!$A$3:$BH$3,0))+INDEX(Qrtly!$A:$BH,MATCH(Annual!$A64,Qrtly!$A:$A,0),MATCH("4Q"&RIGHT(Annual!U$1,2),Qrtly!$A$3:$BH$3,0)) -> 201781.21 | V64: =INDEX(Qrtly!$A:$BH,MATCH(Annual!$A64,Qrtly!$A:$A,0),MATCH("1Q"&RIGHT(Annual!V$1,2),Qrtly!$A$3:$BH$3,0))+INDEX(Qrtly!$A:$BH,MATCH(Annual!$A64,Qrtly!$A:$A,0),MATCH("2Q"&RIGHT(Annual!V$1,2),Qrtly!$A$3:$BH$3,0))+INDEX(Qrtly!$A:$BH,MATCH(Annual!$A64,Qrtly!$A:$A,0),MATCH("3Q"&RIGHT(Annual!V$1,2),Qrtly!$A$3:$BH$3,0))+INDEX(Qrtly!$A:$BH,MATCH(Annual!$A64,Qrtly!$A:$A,0),MATCH("4Q"&RIGHT(Annual!V$1,2),Qrtly!$A$3:$BH$3,0)) -> 206825.74 | ... Z64: =INDEX(Qrtly!$A:$BH,MATCH(Annual!$A64,Qrtly!$A:$A,0),MATCH("1Q"&RIGHT(Annual!Z$1,2),Qrtly!$A$3:$BH$3,0))+INDEX(Qrtly!$A:$BH,MATCH(Annual!$A64,Qrtly!$A:$A,0),MATCH("2Q"&RIGHT(Annual!Z$1,2),Qrtly!$A$3:$BH$3,0))+INDEX(Qrtly!$A:$BH,MATCH(Annual!$A64,Qrtly!$A:$A,0),MATCH("3Q"&RIGHT(Annual!Z$1,2),Qrtly!$A$3:$BH$3,0))+INDEX(Qrtly!$A:$BH,MATCH(Annual!$A64,Qrtly!$A:$A,0),MATCH("4Q"&RIGHT(Annual!Z$1,2),Qrtly!$A$3:$BH$3,0)) -> 228296.92 | AC64: 88744.935 | AD64: =IF(ISBLANK(AC64),"",INDEX($A64:$AA64,1,MATCH(AC$3,$A$3:$AA$3,0))-AC64) -> 31837.065 | AE64: 97419.241 | AF64: =IF(ISBLANK(AE64),"",INDEX($A64:$AA64,1,MATCH(AE$3,$A$3:$AA$3,0))-AE64) -> 85384.578
B65: Interest income rate | L65: #DIV/0! | M65: 0 | N65: 0 | O65: =O61/AVERAGE(N144:O144) -> 0 | P65: =P61/AVERAGE(O144:P144) -> 0.013147141 | Q65: =Q61/AVERAGE(P144:Q144) -> 0.017993367 | R65: =R61/AVERAGE(Q144:R144) -> 0.017908849 | S65: =S61/AVERAGE(R144:S144) -> 0.018062537 | T65: =T61/AVERAGE(S144:T144) -> 0.01771926 | U65: =U61/AVERAGE(T144:U144) -> 0.016946903 | V65: =V61/AVERAGE(U144:V144) -> 0.015821242 | ... Z65: =Z61/AVERAGE(Y144:Z144) -> 0.011917493 | AC65: 0.0099511687 | AD65: =IF(ISBLANK(AC65),"",INDEX($A65:$AA65,1,MATCH(AC$3,$A$3:$AA$3,0))-AC65) -> 0.0031959726 | AE65: 0.010099452 | AF65: =IF(ISBLANK(AE65),"",INDEX($A65:$AA65,1,MATCH(AE$3,$A$3:$AA$3,0))-AE65) -> 0.0078939153
B66: Interest expense rate | L66: #DIV/0! | M66: 0 | N66: 0 | O66: =O63/AVERAGE(N166:O166) -> 0 | P66: =P63/AVERAGE(O166:P166) -> 0 | Q66: =Q63/AVERAGE(P166:Q166) -> 0 | R66: =R63/AVERAGE(Q166:R166) -> 0 | S66: =S63/AVERAGE(R166:S166) -> 0 | T66: =T63/AVERAGE(S166:T166) -> 0 | U66: =U63/AVERAGE(T166:U166) -> 0 | V66: =V63/AVERAGE(U166:V166) -> 0 | ... Z66: =Z63/AVERAGE(Y166:Z166) -> 0 | AC66: 0 | AD66: =IF(ISBLANK(AC66),"",INDEX($A66:$AA66,1,MATCH(AC$3,$A$3:$AA$3,0))-AC66) -> 0 | AE66: 0 | AF66: =IF(ISBLANK(AE66),"",INDEX($A66:$AA66,1,MATCH(AE$3,$A$3:$AA$3,0))-AE66) -> 0
AD67: =IF(ISBLANK(AC67),"",INDEX($A67:$AA67,1,MATCH(AC$3,$A$3:$AA$3,0))-AC67) | AF67: =IF(ISBLANK(AE67),"",INDEX($A67:$AA67,1,MATCH(AE$3,$A$3:$AA$3,0))-AE67)
B68: PBT | AD68: =IF(ISBLANK(AC68),"",INDEX($A68:$AA68,1,MATCH(AC$3,$A$3:$AA$3,0))-AC68) | AF68: =IF(ISBLANK(AE68),"",INDEX($A68:$AA68,1,MATCH(AE$3,$A$3:$AA$3,0))-AE68)
A69: PBTAdd back Share-based comp | B69: Add back Share-based comp | F69: 82292 | G69: 138786 | H69: 155759 | I69: 216784 | J69: 297708 | K69: 397132 | L69: 607632 | M69: 1068795 | N69: 1275496 | O69: =INDEX(Qrtly!$A:$BH,MATCH(Annual!$A69,Qrtly!$A:$A,0),MATCH("1Q"&RIGHT(Annual!O$1,2),Qrtly!$A$3:$BH$3,0))+INDEX(Qrtly!$A:$BH,MATCH(Annual!$A69,Qrtly!$A:$A,0),MATCH("2Q"&RIGHT(Annual!O$1,2),Qrtly!$A$3:$BH$3,0))+INDEX(Qrtly!$A:$BH,MATCH(Annual!$A69,Qrtly!$A:$A,0),MATCH("3Q"&RIGHT(Annual!O$1,2),Qrtly!$A$3:$BH$3,0))+INDEX(Qrtly!$A:$BH,MATCH(Annual!$A69,Qrtly!$A:$A,0),MATCH("4Q"&RIGHT(Annual!O$1,2),Qrtly!$A$3:$BH$3,0)) -> 1264132 | P69: =INDEX(Qrtly!$A:$BH,MATCH(Annual!$A69,Qrtly!$A:$A,0),MATCH("1Q"&RIGHT(Annual!P$1,2),Qrtly!$A$3:$BH$3,0))+INDEX(Qrtly!$A:$BH,MATCH(Annual!$A69,Qrtly!$A:$A,0),MATCH("2Q"&RIGHT(Annual!P$1,2),Qrtly!$A$3:$BH$3,0))+INDEX(Qrtly!$A:$BH,MATCH(Annual!$A69,Qrtly!$A:$A,0),MATCH("3Q"&RIGHT(Annual!P$1,2),Qrtly!$A$3:$BH$3,0))+INDEX(Qrtly!$A:$BH,MATCH(Annual!$A69,Qrtly!$A:$A,0),MATCH("4Q"&RIGHT(Annual!P$1,2),Qrtly!$A$3:$BH$3,0)) -> 0 | Q69: =INDEX(Qrtly!$A:$BH,MATCH(Annual!$A69,Qrtly!$A:$A,0),MATCH("1Q"&RIGHT(Annual!Q$1,2),Qrtly!$A$3:$BH$3,0))+INDEX(Qrtly!$A:$BH,MATCH(Annual!$A69,Qrtly!$A:$A,0),MATCH("2Q"&RIGHT(Annual!Q$1,2),Qrtly!$A$3:$BH$3,0))+INDEX(Qrtly!$A:$BH,MATCH(Annual!$A69,Qrtly!$A:$A,0),MATCH("3Q"&RIGHT(Annual!Q$1,2),Qrtly!$A$3:$BH$3,0))+INDEX(Qrtly!$A:$BH,MATCH(Annual!$A69,Qrtly!$A:$A,0),MATCH("4Q"&RIGHT(Annual!Q$1,2),Qrtly!$A$3:$BH$3,0)) -> 0 | R69: =INDEX(Qrtly!$A:$BH,MATCH(Annual!$A69,Qrtly!$A:$A,0),MATCH("1Q"&RIGHT(Annual!R$1,2),Qrtly!$A$3:$BH$3,0))+INDEX(Qrtly!$A:$BH,MATCH(Annual!$A69,Qrtly!$A:$A,0),MATCH("2Q"&RIGHT(Annual!R$1,2),Qrtly!$A$3:$BH$3,0))+INDEX(Qrtly!$A:$BH,MATCH(Annual!$A69,Qrtly!$A:$A,0),MATCH("3Q"&RIGHT(Annual!R$1,2),Qrtly!$A$3:$BH$3,0))+INDEX(Qrtly!$A:$BH,MATCH(Annual!$A69,Qrtly!$A:$A,0),MATCH("4Q"&RIGHT(Annual!R$1,2),Qrtly!$A$3:$BH$3,0)) -> 0 | S69: =INDEX(Qrtly!$A:$BH,MATCH(Annual!$A69,Qrtly!$A:$A,0),MATCH("1Q"&RIGHT(Annual!S$1,2),Qrtly!$A$3:$BH$3,0))+INDEX(Qrtly!$A:$BH,MATCH(Annual!$A69,Qrtly!$A:$A,0),MATCH("2Q"&RIGHT(Annual!S$1,2),Qrtly!$A$3:$BH$3,0))+INDEX(Qrtly!$A:$BH,MATCH(Annual!$A69,Qrtly!$A:$A,0),MATCH("3Q"&RIGHT(Annual!S$1,2),Qrtly!$A$3:$BH$3,0))+INDEX(Qrtly!$A:$BH,MATCH(Annual!$A69,Qrtly!$A:$A,0),MATCH("4Q"&RIGHT(Annual!S$1,2),Qrtly!$A$3:$BH$3,0)) -> 0 | T69: =INDEX(Qrtly!$A:$BH,MATCH(Annual!$A69,Qrtly!$A:$A,0),MATCH("1Q"&RIGHT(Annual!T$1,2),Qrtly!$A$3:$BH$3,0))+INDEX(Qrtly!$A:$BH,MATCH(Annual!$A69,Qrtly!$A:$A,0),MATCH("2Q"&RIGHT(Annual!T$1,2),Qrtly!$A$3:$BH$3,0))+INDEX(Qrtly!$A:$BH,MATCH(Annual!$A69,Qrtly!$A:$A,0),MATCH("3Q"&RIGHT(Annual!T$1,2),Qrtly!$A$3:$BH$3,0))+INDEX(Qrtly!$A:$BH,MATCH(Annual!$A69,Qrtly!$A:$A,0),MATCH("4Q"&RIGHT(Annual!T$1,2),Qrtly!$A$3:$BH$3,0)) -> 0 | U69: =INDEX(Qrtly!$A:$BH,MATCH(Annual!$A69,Qrtly!$A:$A,0),MATCH("1Q"&RIGHT(Annual!U$1,2),Qrtly!$A$3:$BH$3,0))+INDEX(Qrtly!$A:$BH,MATCH(Annual!$A69,Qrtly!$A:$A,0),MATCH("2Q"&RIGHT(Annual!U$1,2),Qrtly!$A$3:$BH$3,0))+INDEX(Qrtly!$A:$BH,MATCH(Annual!$A69,Qrtly!$A:$A,0),MATCH("3Q"&RIGHT(Annual!U$1,2),Qrtly!$A$3:$BH$3,0))+INDEX(Qrtly!$A:$BH,MATCH(Annual!$A69,Qrtly!$A:$A,0),MATCH("4Q"&RIGHT(Annual!U$1,2),Qrtly!$A$3:$BH$3,0)) -> 0 | V69: =INDEX(Qrtly!$A:$BH,MATCH(Annual!$A69,Qrtly!$A:$A,0),MATCH("1Q"&RIGHT(Annual!V$1,2),Qrtly!$A$3:$BH$3,0))+INDEX(Qrtly!$A:$BH,MATCH(Annual!$A69,Qrtly!$A:$A,0),MATCH("2Q"&RIGHT(Annual!V$1,2),Qrtly!$A$3:$BH$3,0))+INDEX(Qrtly!$A:$BH,MATCH(Annual!$A69,Qrtly!$A:$A,0),MATCH("3Q"&RIGHT(Annual!V$1,2),Qrtly!$A$3:$BH$3,0))+INDEX(Qrtly!$A:$BH,MATCH(Annual!$A69,Qrtly!$A:$A,0),MATCH("4Q"&RIGHT(Annual!V$1,2),Qrtly!$A$3:$BH$3,0)) -> 0 | ... Z69: =INDEX(Qrtly!$A:$BH,MATCH(Annual!$A69,Qrtly!$A:$A,0),MATCH("1Q"&RIGHT(Annual!Z$1,2),Qrtly!$A$3:$BH$3,0))+INDEX(Qrtly!$A:$BH,MATCH(Annual!$A69,Qrtly!$A:$A,0),MATCH("2Q"&RIGHT(Annual!Z$1,2),Qrtly!$A$3:$BH$3,0))+INDEX(Qrtly!$A:$BH,MATCH(Annual!$A69,Qrtly!$A:$A,0),MATCH("3Q"&RIGHT(Annual!Z$1,2),Qrtly!$A$3:$BH$3,0))+INDEX(Qrtly!$A:$BH,MATCH(Annual!$A69,Qrtly!$A:$A,0),MATCH("4Q"&RIGHT(Annual!Z$1,2),Qrtly!$A$3:$BH$3,0)) -> 0 | AC69: 0 | AD69: =IF(ISBLANK(AC69),"",INDEX($A69:$AA69,1,MATCH(AC$3,$A$3:$AA$3,0))-AC69) -> 0 | AE69: 0 | AF69: =IF(ISBLANK(AE69),"",INDEX($A69:$AA69,1,MATCH(AE$3,$A$3:$AA$3,0))-AE69) -> 0
A70: PBTOther income (expense), net | B70: Other income (expense), net | F70: -106167 | G70: 9260 | H70: 23433 | I70: 49114 | J70: 66192 | K70: 90297 | L70: 44326 | M70: -26846 | N70: 27704 | O70: =INDEX(Qrtly!$A:$BH,MATCH(Annual!$A70,Qrtly!$A:$A,0),MATCH("1Q"&RIGHT(Annual!O$1,2),Qrtly!$A$3:$BH$3,0))+INDEX(Qrtly!$A:$BH,MATCH(Annual!$A70,Qrtly!$A:$A,0),MATCH("2Q"&RIGHT(Annual!O$1,2),Qrtly!$A$3:$BH$3,0))+INDEX(Qrtly!$A:$BH,MATCH(Annual!$A70,Qrtly!$A:$A,0),MATCH("3Q"&RIGHT(Annual!O$1,2),Qrtly!$A$3:$BH$3,0))+INDEX(Qrtly!$A:$BH,MATCH(Annual!$A70,Qrtly!$A:$A,0),MATCH("4Q"&RIGHT(Annual!O$1,2),Qrtly!$A$3:$BH$3,0)) -> 38433 | P70: =INDEX(Qrtly!$A:$BH,MATCH(Annual!$A70,Qrtly!$A:$A,0),MATCH("1Q"&RIGHT(Annual!P$1,2),Qrtly!$A$3:$BH$3,0))+INDEX(Qrtly!$A:$BH,MATCH(Annual!$A70,Qrtly!$A:$A,0),MATCH("2Q"&RIGHT(Annual!P$1,2),Qrtly!$A$3:$BH$3,0))+INDEX(Qrtly!$A:$BH,MATCH(Annual!$A70,Qrtly!$A:$A,0),MATCH("3Q"&RIGHT(Annual!P$1,2),Qrtly!$A$3:$BH$3,0))+INDEX(Qrtly!$A:$BH,MATCH(Annual!$A70,Qrtly!$A:$A,0),MATCH("4Q"&RIGHT(Annual!P$1,2),Qrtly!$A$3:$BH$3,0)) -> 1638.25 | Q70: =INDEX(Qrtly!$A:$BH,MATCH(Annual!$A70,Qrtly!$A:$A,0),MATCH("1Q"&RIGHT(Annual!Q$1,2),Qrtly!$A$3:$BH$3,0))+INDEX(Qrtly!$A:$BH,MATCH(Annual!$A70,Qrtly!$A:$A,0),MATCH("2Q"&RIGHT(Annual!Q$1,2),Qrtly!$A$3:$BH$3,0))+INDEX(Qrtly!$A:$BH,MATCH(Annual!$A70,Qrtly!$A:$A,0),MATCH("3Q"&RIGHT(Annual!Q$1,2),Qrtly!$A$3:$BH$3,0))+INDEX(Qrtly!$A:$BH,MATCH(Annual!$A70,Qrtly!$A:$A,0),MATCH("4Q"&RIGHT(Annual!Q$1,2),Qrtly!$A$3:$BH$3,0)) -> -3404.6787 | R70: =INDEX(Qrtly!$A:$BH,MATCH(Annual!$A70,Qrtly!$A:$A,0),MATCH("1Q"&RIGHT(Annual!R$1,2),Qrtly!$A$3:$BH$3,0))+INDEX(Qrtly!$A:$BH,MATCH(Annual!$A70,Qrtly!$A:$A,0),MATCH("2Q"&RIGHT(Annual!R$1,2),Qrtly!$A$3:$BH$3,0))+INDEX(Qrtly!$A:$BH,MATCH(Annual!$A70,Qrtly!$A:$A,0),MATCH("3Q"&RIGHT(Annual!R$1,2),Qrtly!$A$3:$BH$3,0))+INDEX(Qrtly!$A:$BH,MATCH(Annual!$A70,Qrtly!$A:$A,0),MATCH("4Q"&RIGHT(Annual!R$1,2),Qrtly!$A$3:$BH$3,0)) -> -3641.2859 | S70: =INDEX(Qrtly!$A:$BH,MATCH(Annual!$A70,Qrtly!$A:$A,0),MATCH("1Q"&RIGHT(Annual!S$1,2),Qrtly!$A$3:$BH$3,0))+INDEX(Qrtly!$A:$BH,MATCH(Annual!$A70,Qrtly!$A:$A,0),MATCH("2Q"&RIGHT(Annual!S$1,2),Qrtly!$A$3:$BH$3,0))+INDEX(Qrtly!$A:$BH,MATCH(Annual!$A70,Qrtly!$A:$A,0),MATCH("3Q"&RIGHT(Annual!S$1,2),Qrtly!$A$3:$BH$3,0))+INDEX(Qrtly!$A:$BH,MATCH(Annual!$A70,Qrtly!$A:$A,0),MATCH("4Q"&RIGHT(Annual!S$1,2),Qrtly!$A$3:$BH$3,0)) -> -3586.9955 | T70: =INDEX(Qrtly!$A:$BH,MATCH(Annual!$A70,Qrtly!$A:$A,0),MATCH("1Q"&RIGHT(Annual!T$1,2),Qrtly!$A$3:$BH$3,0))+INDEX(Qrtly!$A:$BH,MATCH(Annual!$A70,Qrtly!$A:$A,0),MATCH("2Q"&RIGHT(Annual!T$1,2),Qrtly!$A$3:$BH$3,0))+INDEX(Qrtly!$A:$BH,MATCH(Annual!$A70,Qrtly!$A:$A,0),MATCH("3Q"&RIGHT(Annual!T$1,2),Qrtly!$A$3:$BH$3,0))+INDEX(Qrtly!$A:$BH,MATCH(Annual!$A70,Qrtly!$A:$A,0),MATCH("4Q"&RIGHT(Annual!T$1,2),Qrtly!$A$3:$BH$3,0)) -> -3566.0938 | U70: =INDEX(Qrtly!$A:$BH,MATCH(Annual!$A70,Qrtly!$A:$A,0),MATCH("1Q"&RIGHT(Annual!U$1,2),Qrtly!$A$3:$BH$3,0))+INDEX(Qrtly!$A:$BH,MATCH(Annual!$A70,Qrtly!$A:$A,0),MATCH("2Q"&RIGHT(Annual!U$1,2),Qrtly!$A$3:$BH$3,0))+INDEX(Qrtly!$A:$BH,MATCH(Annual!$A70,Qrtly!$A:$A,0),MATCH("3Q"&RIGHT(Annual!U$1,2),Qrtly!$A$3:$BH$3,0))+INDEX(Qrtly!$A:$BH,MATCH(Annual!$A70,Qrtly!$A:$A,0),MATCH("4Q"&RIGHT(Annual!U$1,2),Qrtly!$A$3:$BH$3,0)) -> -3561.6093 | V70: =INDEX(Qrtly!$A:$BH,MATCH(Annual!$A70,Qrtly!$A:$A,0),MATCH("1Q"&RIGHT(Annual!V$1,2),Qrtly!$A$3:$BH$3,0))+INDEX(Qrtly!$A:$BH,MATCH(Annual!$A70,Qrtly!$A:$A,0),MATCH("2Q"&RIGHT(Annual!V$1,2),Qrtly!$A$3:$BH$3,0))+INDEX(Qrtly!$A:$BH,MATCH(Annual!$A70,Qrtly!$A:$A,0),MATCH("3Q"&RIGHT(Annual!V$1,2),Qrtly!$A$3:$BH$3,0))+INDEX(Qrtly!$A:$BH,MATCH(Annual!$A70,Qrtly!$A:$A,0),MATCH("4Q"&RIGHT(Annual!V$1,2),Qrtly!$A$3:$BH$3,0)) -> -3560.8873 | ... Z70: =INDEX(Qrtly!$A:$BH,MATCH(Annual!$A70,Qrtly!$A:$A,0),MATCH("1Q"&RIGHT(Annual!Z$1,2),Qrtly!$A$3:$BH$3,0))+INDEX(Qrtly!$A:$BH,MATCH(Annual!$A70,Qrtly!$A:$A,0),MATCH("2Q"&RIGHT(Annual!Z$1,2),Qrtly!$A$3:$BH$3,0))+INDEX(Qrtly!$A:$BH,MATCH(Annual!$A70,Qrtly!$A:$A,0),MATCH("3Q"&RIGHT(Annual!Z$1,2),Qrtly!$A$3:$BH$3,0))+INDEX(Qrtly!$A:$BH,MATCH(Annual!$A70,Qrtly!$A:$A,0),MATCH("4Q"&RIGHT(Annual!Z$1,2),Qrtly!$A$3:$BH$3,0)) -> -3560.7998 | AC70: -17495.812 | AD70: =IF(ISBLANK(AC70),"",INDEX($A70:$AA70,1,MATCH(AC$3,$A$3:$AA$3,0))-AC70) -> 19134.062 | AE70: -22119.073 | AF70: =IF(ISBLANK(AE70),"",INDEX($A70:$AA70,1,MATCH(AE$3,$A$3:$AA$3,0))-AE70) -> 18714.395
A71: PBTPBT (non-GAAP) | B71: PBT (non-GAAP) | C71: USDk | F71: -176071 | G71: 16935 | H71: 115110 | I71: 226694 | J71: 385931 | K71: 423213 | L71: 890102 | M71: 860313 | N71: 1701772 | O71: =INDEX(Qrtly!$A:$BH,MATCH(Annual!$A71,Qrtly!$A:$A,0),MATCH("1Q"&RIGHT(Annual!O$1,2),Qrtly!$A$3:$BH$3,0))+INDEX(Qrtly!$A:$BH,MATCH(Annual!$A71,Qrtly!$A:$A,0),MATCH("2Q"&RIGHT(Annual!O$1,2),Qrtly!$A$3:$BH$3,0))+INDEX(Qrtly!$A:$BH,MATCH(Annual!$A71,Qrtly!$A:$A,0),MATCH("3Q"&RIGHT(Annual!O$1,2),Qrtly!$A$3:$BH$3,0))+INDEX(Qrtly!$A:$BH,MATCH(Annual!$A71,Qrtly!$A:$A,0),MATCH("4Q"&RIGHT(Annual!O$1,2),Qrtly!$A$3:$BH$3,0)) -> 2902053 | P71: =INDEX(Qrtly!$A:$BH,MATCH(Annual!$A71,Qrtly!$A:$A,0),MATCH("1Q"&RIGHT(Annual!P$1,2),Qrtly!$A$3:$BH$3,0))+INDEX(Qrtly!$A:$BH,MATCH(Annual!$A71,Qrtly!$A:$A,0),MATCH("2Q"&RIGHT(Annual!P$1,2),Qrtly!$A$3:$BH$3,0))+INDEX(Qrtly!$A:$BH,MATCH(Annual!$A71,Qrtly!$A:$A,0),MATCH("3Q"&RIGHT(Annual!P$1,2),Qrtly!$A$3:$BH$3,0))+INDEX(Qrtly!$A:$BH,MATCH(Annual!$A71,Qrtly!$A:$A,0),MATCH("4Q"&RIGHT(Annual!P$1,2),Qrtly!$A$3:$BH$3,0)) -> 1982779.9 | Q71: =INDEX(Qrtly!$A:$BH,MATCH(Annual!$A71,Qrtly!$A:$A,0),MATCH("1Q"&RIGHT(Annual!Q$1,2),Qrtly!$A$3:$BH$3,0))+INDEX(Qrtly!$A:$BH,MATCH(Annual!$A71,Qrtly!$A:$A,0),MATCH("2Q"&RIGHT(Annual!Q$1,2),Qrtly!$A$3:$BH$3,0))+INDEX(Qrtly!$A:$BH,MATCH(Annual!$A71,Qrtly!$A:$A,0),MATCH("3Q"&RIGHT(Annual!Q$1,2),Qrtly!$A$3:$BH$3,0))+INDEX(Qrtly!$A:$BH,MATCH(Annual!$A71,Qrtly!$A:$A,0),MATCH("4Q"&RIGHT(Annual!Q$1,2),Qrtly!$A$3:$BH$3,0)) -> 2862496.5 | R71: =INDEX(Qrtly!$A:$BH,MATCH(Annual!$A71,Qrtly!$A:$A,0),MATCH("1Q"&RIGHT(Annual!R$1,2),Qrtly!$A$3:$BH$3,0))+INDEX(Qrtly!$A:$BH,MATCH(Annual!$A71,Qrtly!$A:$A,0),MATCH("2Q"&RIGHT(Annual!R$1,2),Qrtly!$A$3:$BH$3,0))+INDEX(Qrtly!$A:$BH,MATCH(Annual!$A71,Qrtly!$A:$A,0),MATCH("3Q"&RIGHT(Annual!R$1,2),Qrtly!$A$3:$BH$3,0))+INDEX(Qrtly!$A:$BH,MATCH(Annual!$A71,Qrtly!$A:$A,0),MATCH("4Q"&RIGHT(Annual!R$1,2),Qrtly!$A$3:$BH$3,0)) -> 3697204.3 | S71: =INDEX(Qrtly!$A:$BH,MATCH(Annual!$A71,Qrtly!$A:$A,0),MATCH("1Q"&RIGHT(Annual!S$1,2),Qrtly!$A$3:$BH$3,0))+INDEX(Qrtly!$A:$BH,MATCH(Annual!$A71,Qrtly!$A:$A,0),MATCH("2Q"&RIGHT(Annual!S$1,2),Qrtly!$A$3:$BH$3,0))+INDEX(Qrtly!$A:$BH,MATCH(Annual!$A71,Qrtly!$A:$A,0),MATCH("3Q"&RIGHT(Annual!S$1,2),Qrtly!$A$3:$BH$3,0))+INDEX(Qrtly!$A:$BH,MATCH(Annual!$A71,Qrtly!$A:$A,0),MATCH("4Q"&RIGHT(Annual!S$1,2),Qrtly!$A$3:$BH$3,0)) -> 4555587.6 | T71: =INDEX(Qrtly!$A:$BH,MATCH(Annual!$A71,Qrtly!$A:$A,0),MATCH("1Q"&RIGHT(Annual!T$1,2),Qrtly!$A$3:$BH$3,0))+INDEX(Qrtly!$A:$BH,MATCH(Annual!$A71,Qrtly!$A:$A,0),MATCH("2Q"&RIGHT(Annual!T$1,2),Qrtly!$A$3:$BH$3,0))+INDEX(Qrtly!$A:$BH,MATCH(Annual!$A71,Qrtly!$A:$A,0),MATCH("3Q"&RIGHT(Annual!T$1,2),Qrtly!$A$3:$BH$3,0))+INDEX(Qrtly!$A:$BH,MATCH(Annual!$A71,Qrtly!$A:$A,0),MATCH("4Q"&RIGHT(Annual!T$1,2),Qrtly!$A$3:$BH$3,0)) -> 5411464 | U71: =INDEX(Qrtly!$A:$BH,MATCH(Annual!$A71,Qrtly!$A:$A,0),MATCH("1Q"&RIGHT(Annual!U$1,2),Qrtly!$A$3:$BH$3,0))+INDEX(Qrtly!$A:$BH,MATCH(Annual!$A71,Qrtly!$A:$A,0),MATCH("2Q"&RIGHT(Annual!U$1,2),Qrtly!$A$3:$BH$3,0))+INDEX(Qrtly!$A:$BH,MATCH(Annual!$A71,Qrtly!$A:$A,0),MATCH("3Q"&RIGHT(Annual!U$1,2),Qrtly!$A$3:$BH$3,0))+INDEX(Qrtly!$A:$BH,MATCH(Annual!$A71,Qrtly!$A:$A,0),MATCH("4Q"&RIGHT(Annual!U$1,2),Qrtly!$A$3:$BH$3,0)) -> 6411984.4 | V71: =INDEX(Qrtly!$A:$BH,MATCH(Annual!$A71,Qrtly!$A:$A,0),MATCH("1Q"&RIGHT(Annual!V$1,2),Qrtly!$A$3:$BH$3,0))+INDEX(Qrtly!$A:$BH,MATCH(Annual!$A71,Qrtly!$A:$A,0),MATCH("2Q"&RIGHT(Annual!V$1,2),Qrtly!$A$3:$BH$3,0))+INDEX(Qrtly!$A:$BH,MATCH(Annual!$A71,Qrtly!$A:$A,0),MATCH("3Q"&RIGHT(Annual!V$1,2),Qrtly!$A$3:$BH$3,0))+INDEX(Qrtly!$A:$BH,MATCH(Annual!$A71,Qrtly!$A:$A,0),MATCH("4Q"&RIGHT(Annual!V$1,2),Qrtly!$A$3:$BH$3,0)) -> 7587335.3 | ... Z71: =INDEX(Qrtly!$A:$BH,MATCH(Annual!$A71,Qrtly!$A:$A,0),MATCH("1Q"&RIGHT(Annual!Z$1,2),Qrtly!$A$3:$BH$3,0))+INDEX(Qrtly!$A:$BH,MATCH(Annual!$A71,Qrtly!$A:$A,0),MATCH("2Q"&RIGHT(Annual!Z$1,2),Qrtly!$A$3:$BH$3,0))+INDEX(Qrtly!$A:$BH,MATCH(Annual!$A71,Qrtly!$A:$A,0),MATCH("3Q"&RIGHT(Annual!Z$1,2),Qrtly!$A$3:$BH$3,0))+INDEX(Qrtly!$A:$BH,MATCH(Annual!$A71,Qrtly!$A:$A,0),MATCH("4Q"&RIGHT(Annual!Z$1,2),Qrtly!$A$3:$BH$3,0)) -> 14943028 | AC71: 1994894.8 | AD71: =IF(ISBLANK(AC71),"",INDEX($A71:$AA71,1,MATCH(AC$3,$A$3:$AA$3,0))-AC71) -> -12114.943 | AE71: 2873066.1 | AF71: =IF(ISBLANK(AE71),"",INDEX($A71:$AA71,1,MATCH(AE$3,$A$3:$AA$3,0))-AE71) -> -10569.528
AD72: =IF(ISBLANK(AC72),"",INDEX($A72:$AA72,1,MATCH(AC$3,$A$3:$AA$3,0))-AC72) | AF72: =IF(ISBLANK(AE72),"",INDEX($A72:$AA72,1,MATCH(AE$3,$A$3:$AA$3,0))-AE72)
B73: Tax | AD73: =IF(ISBLANK(AC73),"",INDEX($A73:$AA73,1,MATCH(AC$3,$A$3:$AA$3,0))-AC73) | AF73: =IF(ISBLANK(AE73),"",INDEX($A73:$AA73,1,MATCH(AE$3,$A$3:$AA$3,0))-AE73)
A74: TaxProvision (benefit) for income taxes | B74: Provision (benefit) for income taxes | F74: 3746 | G74: 1917 | H74: 149 | I74: 2326 | J74: 2767 | K74: 2862 | L74: -1364 | M74: -12312 | N74: -8019 | O74: =INDEX(Qrtly!$A:$BH,MATCH(Annual!$A74,Qrtly!$A:$A,0),MATCH("1Q"&RIGHT(Annual!O$1,2),Qrtly!$A$3:$BH$3,0))+INDEX(Qrtly!$A:$BH,MATCH(Annual!$A74,Qrtly!$A:$A,0),MATCH("2Q"&RIGHT(Annual!O$1,2),Qrtly!$A$3:$BH$3,0))+INDEX(Qrtly!$A:$BH,MATCH(Annual!$A74,Qrtly!$A:$A,0),MATCH("3Q"&RIGHT(Annual!O$1,2),Qrtly!$A$3:$BH$3,0))+INDEX(Qrtly!$A:$BH,MATCH(Annual!$A74,Qrtly!$A:$A,0),MATCH("4Q"&RIGHT(Annual!O$1,2),Qrtly!$A$3:$BH$3,0)) -> -1509343 | P74: =INDEX(Qrtly!$A:$BH,MATCH(Annual!$A74,Qrtly!$A:$A,0),MATCH("1Q"&RIGHT(Annual!P$1,2),Qrtly!$A$3:$BH$3,0))+INDEX(Qrtly!$A:$BH,MATCH(Annual!$A74,Qrtly!$A:$A,0),MATCH("2Q"&RIGHT(Annual!P$1,2),Qrtly!$A$3:$BH$3,0))+INDEX(Qrtly!$A:$BH,MATCH(Annual!$A74,Qrtly!$A:$A,0),MATCH("3Q"&RIGHT(Annual!P$1,2),Qrtly!$A$3:$BH$3,0))+INDEX(Qrtly!$A:$BH,MATCH(Annual!$A74,Qrtly!$A:$A,0),MATCH("4Q"&RIGHT(Annual!P$1,2),Qrtly!$A$3:$BH$3,0)) -> 299304 | Q74: =INDEX(Qrtly!$A:$BH,MATCH(Annual!$A74,Qrtly!$A:$A,0),MATCH("1Q"&RIGHT(Annual!Q$1,2),Qrtly!$A$3:$BH$3,0))+INDEX(Qrtly!$A:$BH,MATCH(Annual!$A74,Qrtly!$A:$A,0),MATCH("2Q"&RIGHT(Annual!Q$1,2),Qrtly!$A$3:$BH$3,0))+INDEX(Qrtly!$A:$BH,MATCH(Annual!$A74,Qrtly!$A:$A,0),MATCH("3Q"&RIGHT(Annual!Q$1,2),Qrtly!$A$3:$BH$3,0))+INDEX(Qrtly!$A:$BH,MATCH(Annual!$A74,Qrtly!$A:$A,0),MATCH("4Q"&RIGHT(Annual!Q$1,2),Qrtly!$A$3:$BH$3,0)) -> 0 | R74: =INDEX(Qrtly!$A:$BH,MATCH(Annual!$A74,Qrtly!$A:$A,0),MATCH("1Q"&RIGHT(Annual!R$1,2),Qrtly!$A$3:$BH$3,0))+INDEX(Qrtly!$A:$BH,MATCH(Annual!$A74,Qrtly!$A:$A,0),MATCH("2Q"&RIGHT(Annual!R$1,2),Qrtly!$A$3:$BH$3,0))+INDEX(Qrtly!$A:$BH,MATCH(Annual!$A74,Qrtly!$A:$A,0),MATCH("3Q"&RIGHT(Annual!R$1,2),Qrtly!$A$3:$BH$3,0))+INDEX(Qrtly!$A:$BH,MATCH(Annual!$A74,Qrtly!$A:$A,0),MATCH("4Q"&RIGHT(Annual!R$1,2),Qrtly!$A$3:$BH$3,0)) -> 0 | S74: =INDEX(Qrtly!$A:$BH,MATCH(Annual!$A74,Qrtly!$A:$A,0),MATCH("1Q"&RIGHT(Annual!S$1,2),Qrtly!$A$3:$BH$3,0))+INDEX(Qrtly!$A:$BH,MATCH(Annual!$A74,Qrtly!$A:$A,0),MATCH("2Q"&RIGHT(Annual!S$1,2),Qrtly!$A$3:$BH$3,0))+INDEX(Qrtly!$A:$BH,MATCH(Annual!$A74,Qrtly!$A:$A,0),MATCH("3Q"&RIGHT(Annual!S$1,2),Qrtly!$A$3:$BH$3,0))+INDEX(Qrtly!$A:$BH,MATCH(Annual!$A74,Qrtly!$A:$A,0),MATCH("4Q"&RIGHT(Annual!S$1,2),Qrtly!$A$3:$BH$3,0)) -> 0 | T74: =INDEX(Qrtly!$A:$BH,MATCH(Annual!$A74,Qrtly!$A:$A,0),MATCH("1Q"&RIGHT(Annual!T$1,2),Qrtly!$A$3:$BH$3,0))+INDEX(Qrtly!$A:$BH,MATCH(Annual!$A74,Qrtly!$A:$A,0),MATCH("2Q"&RIGHT(Annual!T$1,2),Qrtly!$A$3:$BH$3,0))+INDEX(Qrtly!$A:$BH,MATCH(Annual!$A74,Qrtly!$A:$A,0),MATCH("3Q"&RIGHT(Annual!T$1,2),Qrtly!$A$3:$BH$3,0))+INDEX(Qrtly!$A:$BH,MATCH(Annual!$A74,Qrtly!$A:$A,0),MATCH("4Q"&RIGHT(Annual!T$1,2),Qrtly!$A$3:$BH$3,0)) -> 0 | U74: =INDEX(Qrtly!$A:$BH,MATCH(Annual!$A74,Qrtly!$A:$A,0),MATCH("1Q"&RIGHT(Annual!U$1,2),Qrtly!$A$3:$BH$3,0))+INDEX(Qrtly!$A:$BH,MATCH(Annual!$A74,Qrtly!$A:$A,0),MATCH("2Q"&RIGHT(Annual!U$1,2),Qrtly!$A$3:$BH$3,0))+INDEX(Qrtly!$A:$BH,MATCH(Annual!$A74,Qrtly!$A:$A,0),MATCH("3Q"&RIGHT(Annual!U$1,2),Qrtly!$A$3:$BH$3,0))+INDEX(Qrtly!$A:$BH,MATCH(Annual!$A74,Qrtly!$A:$A,0),MATCH("4Q"&RIGHT(Annual!U$1,2),Qrtly!$A$3:$BH$3,0)) -> 0 | V74: =INDEX(Qrtly!$A:$BH,MATCH(Annual!$A74,Qrtly!$A:$A,0),MATCH("1Q"&RIGHT(Annual!V$1,2),Qrtly!$A$3:$BH$3,0))+INDEX(Qrtly!$A:$BH,MATCH(Annual!$A74,Qrtly!$A:$A,0),MATCH("2Q"&RIGHT(Annual!V$1,2),Qrtly!$A$3:$BH$3,0))+INDEX(Qrtly!$A:$BH,MATCH(Annual!$A74,Qrtly!$A:$A,0),MATCH("3Q"&RIGHT(Annual!V$1,2),Qrtly!$A$3:$BH$3,0))+INDEX(Qrtly!$A:$BH,MATCH(Annual!$A74,Qrtly!$A:$A,0),MATCH("4Q"&RIGHT(Annual!V$1,2),Qrtly!$A$3:$BH$3,0)) -> 0 | ... Z74: =INDEX(Qrtly!$A:$BH,MATCH(Annual!$A74,Qrtly!$A:$A,0),MATCH("1Q"&RIGHT(Annual!Z$1,2),Qrtly!$A$3:$BH$3,0))+INDEX(Qrtly!$A:$BH,MATCH(Annual!$A74,Qrtly!$A:$A,0),MATCH("2Q"&RIGHT(Annual!Z$1,2),Qrtly!$A$3:$BH$3,0))+INDEX(Qrtly!$A:$BH,MATCH(Annual!$A74,Qrtly!$A:$A,0),MATCH("3Q"&RIGHT(Annual!Z$1,2),Qrtly!$A$3:$BH$3,0))+INDEX(Qrtly!$A:$BH,MATCH(Annual!$A74,Qrtly!$A:$A,0),MATCH("4Q"&RIGHT(Annual!Z$1,2),Qrtly!$A$3:$BH$3,0)) -> 0 | AC74: 159376 | AD74: =IF(ISBLANK(AC74),"",INDEX($A74:$AA74,1,MATCH(AC$3,$A$3:$AA$3,0))-AC74) -> 139928 | AE74: 0 | AF74: =IF(ISBLANK(AE74),"",INDEX($A74:$AA74,1,MATCH(AE$3,$A$3:$AA$3,0))-AE74) -> 0
A75: TaxTax effect of non-GAAP net income adjustments | B75: Tax effect of non-GAAP net income adjustments | F75: 0 | G75: 0 | H75: 0 | I75: 0 | J75: 0 | K75: 0 | L75: 0 | M75: -264523 | N75: -582703 | O75: =INDEX(Qrtly!$A:$BH,MATCH(Annual!$A75,Qrtly!$A:$A,0),MATCH("1Q"&RIGHT(Annual!O$1,2),Qrtly!$A$3:$BH$3,0))+INDEX(Qrtly!$A:$BH,MATCH(Annual!$A75,Qrtly!$A:$A,0),MATCH("2Q"&RIGHT(Annual!O$1,2),Qrtly!$A$3:$BH$3,0))+INDEX(Qrtly!$A:$BH,MATCH(Annual!$A75,Qrtly!$A:$A,0),MATCH("3Q"&RIGHT(Annual!O$1,2),Qrtly!$A$3:$BH$3,0))+INDEX(Qrtly!$A:$BH,MATCH(Annual!$A75,Qrtly!$A:$A,0),MATCH("4Q"&RIGHT(Annual!O$1,2),Qrtly!$A$3:$BH$3,0)) -> -2270630 | P75: =INDEX(Qrtly!$A:$BH,MATCH(Annual!$A75,Qrtly!$A:$A,0),MATCH("1Q"&RIGHT(Annual!P$1,2),Qrtly!$A$3:$BH$3,0))+INDEX(Qrtly!$A:$BH,MATCH(Annual!$A75,Qrtly!$A:$A,0),MATCH("2Q"&RIGHT(Annual!P$1,2),Qrtly!$A$3:$BH$3,0))+INDEX(Qrtly!$A:$BH,MATCH(Annual!$A75,Qrtly!$A:$A,0),MATCH("3Q"&RIGHT(Annual!P$1,2),Qrtly!$A$3:$BH$3,0))+INDEX(Qrtly!$A:$BH,MATCH(Annual!$A75,Qrtly!$A:$A,0),MATCH("4Q"&RIGHT(Annual!P$1,2),Qrtly!$A$3:$BH$3,0)) -> -46409 | Q75: =INDEX(Qrtly!$A:$BH,MATCH(Annual!$A75,Qrtly!$A:$A,0),MATCH("1Q"&RIGHT(Annual!Q$1,2),Qrtly!$A$3:$BH$3,0))+INDEX(Qrtly!$A:$BH,MATCH(Annual!$A75,Qrtly!$A:$A,0),MATCH("2Q"&RIGHT(Annual!Q$1,2),Qrtly!$A$3:$BH$3,0))+INDEX(Qrtly!$A:$BH,MATCH(Annual!$A75,Qrtly!$A:$A,0),MATCH("3Q"&RIGHT(Annual!Q$1,2),Qrtly!$A$3:$BH$3,0))+INDEX(Qrtly!$A:$BH,MATCH(Annual!$A75,Qrtly!$A:$A,0),MATCH("4Q"&RIGHT(Annual!Q$1,2),Qrtly!$A$3:$BH$3,0)) -> 0 | R75: =INDEX(Qrtly!$A:$BH,MATCH(Annual!$A75,Qrtly!$A:$A,0),MATCH("1Q"&RIGHT(Annual!R$1,2),Qrtly!$A$3:$BH$3,0))+INDEX(Qrtly!$A:$BH,MATCH(Annual!$A75,Qrtly!$A:$A,0),MATCH("2Q"&RIGHT(Annual!R$1,2),Qrtly!$A$3:$BH$3,0))+INDEX(Qrtly!$A:$BH,MATCH(Annual!$A75,Qrtly!$A:$A,0),MATCH("3Q"&RIGHT(Annual!R$1,2),Qrtly!$A$3:$BH$3,0))+INDEX(Qrtly!$A:$BH,MATCH(Annual!$A75,Qrtly!$A:$A,0),MATCH("4Q"&RIGHT(Annual!R$1,2),Qrtly!$A$3:$BH$3,0)) -> 0 | S75: =INDEX(Qrtly!$A:$BH,MATCH(Annual!$A75,Qrtly!$A:$A,0),MATCH("1Q"&RIGHT(Annual!S$1,2),Qrtly!$A$3:$BH$3,0))+INDEX(Qrtly!$A:$BH,MATCH(Annual!$A75,Qrtly!$A:$A,0),MATCH("2Q"&RIGHT(Annual!S$1,2),Qrtly!$A$3:$BH$3,0))+INDEX(Qrtly!$A:$BH,MATCH(Annual!$A75,Qrtly!$A:$A,0),MATCH("3Q"&RIGHT(Annual!S$1,2),Qrtly!$A$3:$BH$3,0))+INDEX(Qrtly!$A:$BH,MATCH(Annual!$A75,Qrtly!$A:$A,0),MATCH("4Q"&RIGHT(Annual!S$1,2),Qrtly!$A$3:$BH$3,0)) -> 0 | T75: =INDEX(Qrtly!$A:$BH,MATCH(Annual!$A75,Qrtly!$A:$A,0),MATCH("1Q"&RIGHT(Annual!T$1,2),Qrtly!$A$3:$BH$3,0))+INDEX(Qrtly!$A:$BH,MATCH(Annual!$A75,Qrtly!$A:$A,0),MATCH("2Q"&RIGHT(Annual!T$1,2),Qrtly!$A$3:$BH$3,0))+INDEX(Qrtly!$A:$BH,MATCH(Annual!$A75,Qrtly!$A:$A,0),MATCH("3Q"&RIGHT(Annual!T$1,2),Qrtly!$A$3:$BH$3,0))+INDEX(Qrtly!$A:$BH,MATCH(Annual!$A75,Qrtly!$A:$A,0),MATCH("4Q"&RIGHT(Annual!T$1,2),Qrtly!$A$3:$BH$3,0)) -> 0 | U75: =INDEX(Qrtly!$A:$BH,MATCH(Annual!$A75,Qrtly!$A:$A,0),MATCH("1Q"&RIGHT(Annual!U$1,2),Qrtly!$A$3:$BH$3,0))+INDEX(Qrtly!$A:$BH,MATCH(Annual!$A75,Qrtly!$A:$A,0),MATCH("2Q"&RIGHT(Annual!U$1,2),Qrtly!$A$3:$BH$3,0))+INDEX(Qrtly!$A:$BH,MATCH(Annual!$A75,Qrtly!$A:$A,0),MATCH("3Q"&RIGHT(Annual!U$1,2),Qrtly!$A$3:$BH$3,0))+INDEX(Qrtly!$A:$BH,MATCH(Annual!$A75,Qrtly!$A:$A,0),MATCH("4Q"&RIGHT(Annual!U$1,2),Qrtly!$A$3:$BH$3,0)) -> 0 | V75: =INDEX(Qrtly!$A:$BH,MATCH(Annual!$A75,Qrtly!$A:$A,0),MATCH("1Q"&RIGHT(Annual!V$1,2),Qrtly!$A$3:$BH$3,0))+INDEX(Qrtly!$A:$BH,MATCH(Annual!$A75,Qrtly!$A:$A,0),MATCH("2Q"&RIGHT(Annual!V$1,2),Qrtly!$A$3:$BH$3,0))+INDEX(Qrtly!$A:$BH,MATCH(Annual!$A75,Qrtly!$A:$A,0),MATCH("3Q"&RIGHT(Annual!V$1,2),Qrtly!$A$3:$BH$3,0))+INDEX(Qrtly!$A:$BH,MATCH(Annual!$A75,Qrtly!$A:$A,0),MATCH("4Q"&RIGHT(Annual!V$1,2),Qrtly!$A$3:$BH$3,0)) -> 0 | ... Z75: =INDEX(Qrtly!$A:$BH,MATCH(Annual!$A75,Qrtly!$A:$A,0),MATCH("1Q"&RIGHT(Annual!Z$1,2),Qrtly!$A$3:$BH$3,0))+INDEX(Qrtly!$A:$BH,MATCH(Annual!$A75,Qrtly!$A:$A,0),MATCH("2Q"&RIGHT(Annual!Z$1,2),Qrtly!$A$3:$BH$3,0))+INDEX(Qrtly!$A:$BH,MATCH(Annual!$A75,Qrtly!$A:$A,0),MATCH("3Q"&RIGHT(Annual!Z$1,2),Qrtly!$A$3:$BH$3,0))+INDEX(Qrtly!$A:$BH,MATCH(Annual!$A75,Qrtly!$A:$A,0),MATCH("4Q"&RIGHT(Annual!Z$1,2),Qrtly!$A$3:$BH$3,0)) -> 0 | AC75: -77433 | AD75: =IF(ISBLANK(AC75),"",INDEX($A75:$AA75,1,MATCH(AC$3,$A$3:$AA$3,0))-AC75) -> 31024 | AE75: 0 | AF75: =IF(ISBLANK(AE75),"",INDEX($A75:$AA75,1,MATCH(AE$3,$A$3:$AA$3,0))-AE75) -> 0
A76: TaxTax expense | B76: Tax expense | C76: USDk | F76: 3746 | G76: 1917 | H76: 149 | I76: 2326 | J76: 2767 | K76: 2862 | L76: -1364 | M76: 252211 | N76: 574684 | O76: =INDEX(Qrtly!$A:$BH,MATCH(Annual!$A76,Qrtly!$A:$A,0),MATCH("1Q"&RIGHT(Annual!O$1,2),Qrtly!$A$3:$BH$3,0))+INDEX(Qrtly!$A:$BH,MATCH(Annual!$A76,Qrtly!$A:$A,0),MATCH("2Q"&RIGHT(Annual!O$1,2),Qrtly!$A$3:$BH$3,0))+INDEX(Qrtly!$A:$BH,MATCH(Annual!$A76,Qrtly!$A:$A,0),MATCH("3Q"&RIGHT(Annual!O$1,2),Qrtly!$A$3:$BH$3,0))+INDEX(Qrtly!$A:$BH,MATCH(Annual!$A76,Qrtly!$A:$A,0),MATCH("4Q"&RIGHT(Annual!O$1,2),Qrtly!$A$3:$BH$3,0)) -> 761287 | P76: =INDEX(Qrtly!$A:$BH,MATCH(Annual!$A76,Qrtly!$A:$A,0),MATCH("1Q"&RIGHT(Annual!P$1,2),Qrtly!$A$3:$BH$3,0))+INDEX(Qrtly!$A:$BH,MATCH(Annual!$A76,Qrtly!$A:$A,0),MATCH("2Q"&RIGHT(Annual!P$1,2),Qrtly!$A$3:$BH$3,0))+INDEX(Qrtly!$A:$BH,MATCH(Annual!$A76,Qrtly!$A:$A,0),MATCH("3Q"&RIGHT(Annual!P$1,2),Qrtly!$A$3:$BH$3,0))+INDEX(Qrtly!$A:$BH,MATCH(Annual!$A76,Qrtly!$A:$A,0),MATCH("4Q"&RIGHT(Annual!P$1,2),Qrtly!$A$3:$BH$3,0)) -> 485997.97 | Q76: =INDEX(Qrtly!$A:$BH,MATCH(Annual!$A76,Qrtly!$A:$A,0),MATCH("1Q"&RIGHT(Annual!Q$1,2),Qrtly!$A$3:$BH$3,0))+INDEX(Qrtly!$A:$BH,MATCH(Annual!$A76,Qrtly!$A:$A,0),MATCH("2Q"&RIGHT(Annual!Q$1,2),Qrtly!$A$3:$BH$3,0))+INDEX(Qrtly!$A:$BH,MATCH(Annual!$A76,Qrtly!$A:$A,0),MATCH("3Q"&RIGHT(Annual!Q$1,2),Qrtly!$A$3:$BH$3,0))+INDEX(Qrtly!$A:$BH,MATCH(Annual!$A76,Qrtly!$A:$A,0),MATCH("4Q"&RIGHT(Annual!Q$1,2),Qrtly!$A$3:$BH$3,0)) -> 715624.13 | R76: =INDEX(Qrtly!$A:$BH,MATCH(Annual!$A76,Qrtly!$A:$A,0),MATCH("1Q"&RIGHT(Annual!R$1,2),Qrtly!$A$3:$BH$3,0))+INDEX(Qrtly!$A:$BH,MATCH(Annual!$A76,Qrtly!$A:$A,0),MATCH("2Q"&RIGHT(Annual!R$1,2),Qrtly!$A$3:$BH$3,0))+INDEX(Qrtly!$A:$BH,MATCH(Annual!$A76,Qrtly!$A:$A,0),MATCH("3Q"&RIGHT(Annual!R$1,2),Qrtly!$A$3:$BH$3,0))+INDEX(Qrtly!$A:$BH,MATCH(Annual!$A76,Qrtly!$A:$A,0),MATCH("4Q"&RIGHT(Annual!R$1,2),Qrtly!$A$3:$BH$3,0)) -> 924301.08 | S76: =INDEX(Qrtly!$A:$BH,MATCH(Annual!$A76,Qrtly!$A:$A,0),MATCH("1Q"&RIGHT(Annual!S$1,2),Qrtly!$A$3:$BH$3,0))+INDEX(Qrtly!$A:$BH,MATCH(Annual!$A76,Qrtly!$A:$A,0),MATCH("2Q"&RIGHT(Annual!S$1,2),Qrtly!$A$3:$BH$3,0))+INDEX(Qrtly!$A:$BH,MATCH(Annual!$A76,Qrtly!$A:$A,0),MATCH("3Q"&RIGHT(Annual!S$1,2),Qrtly!$A$3:$BH$3,0))+INDEX(Qrtly!$A:$BH,MATCH(Annual!$A76,Qrtly!$A:$A,0),MATCH("4Q"&RIGHT(Annual!S$1,2),Qrtly!$A$3:$BH$3,0)) -> 1138896.9 | T76: =INDEX(Qrtly!$A:$BH,MATCH(Annual!$A76,Qrtly!$A:$A,0),MATCH("1Q"&RIGHT(Annual!T$1,2),Qrtly!$A$3:$BH$3,0))+INDEX(Qrtly!$A:$BH,MATCH(Annual!$A76,Qrtly!$A:$A,0),MATCH("2Q"&RIGHT(Annual!T$1,2),Qrtly!$A$3:$BH$3,0))+INDEX(Qrtly!$A:$BH,MATCH(Annual!$A76,Qrtly!$A:$A,0),MATCH("3Q"&RIGHT(Annual!T$1,2),Qrtly!$A$3:$BH$3,0))+INDEX(Qrtly!$A:$BH,MATCH(Annual!$A76,Qrtly!$A:$A,0),MATCH("4Q"&RIGHT(Annual!T$1,2),Qrtly!$A$3:$BH$3,0)) -> 1352866 | U76: =INDEX(Qrtly!$A:$BH,MATCH(Annual!$A76,Qrtly!$A:$A,0),MATCH("1Q"&RIGHT(Annual!U$1,2),Qrtly!$A$3:$BH$3,0))+INDEX(Qrtly!$A:$BH,MATCH(Annual!$A76,Qrtly!$A:$A,0),MATCH("2Q"&RIGHT(Annual!U$1,2),Qrtly!$A$3:$BH$3,0))+INDEX(Qrtly!$A:$BH,MATCH(Annual!$A76,Qrtly!$A:$A,0),MATCH("3Q"&RIGHT(Annual!U$1,2),Qrtly!$A$3:$BH$3,0))+INDEX(Qrtly!$A:$BH,MATCH(Annual!$A76,Qrtly!$A:$A,0),MATCH("4Q"&RIGHT(Annual!U$1,2),Qrtly!$A$3:$BH$3,0)) -> 1602996.1 | V76: =INDEX(Qrtly!$A:$BH,MATCH(Annual!$A76,Qrtly!$A:$A,0),MATCH("1Q"&RIGHT(Annual!V$1,2),Qrtly!$A$3:$BH$3,0))+INDEX(Qrtly!$A:$BH,MATCH(Annual!$A76,Qrtly!$A:$A,0),MATCH("2Q"&RIGHT(Annual!V$1,2),Qrtly!$A$3:$BH$3,0))+INDEX(Qrtly!$A:$BH,MATCH(Annual!$A76,Qrtly!$A:$A,0),MATCH("3Q"&RIGHT(Annual!V$1,2),Qrtly!$A$3:$BH$3,0))+INDEX(Qrtly!$A:$BH,MATCH(Annual!$A76,Qrtly!$A:$A,0),MATCH("4Q"&RIGHT(Annual!V$1,2),Qrtly!$A$3:$BH$3,0)) -> 1896833.8 | ... Z76: =INDEX(Qrtly!$A:$BH,MATCH(Annual!$A76,Qrtly!$A:$A,0),MATCH("1Q"&RIGHT(Annual!Z$1,2),Qrtly!$A$3:$BH$3,0))+INDEX(Qrtly!$A:$BH,MATCH(Annual!$A76,Qrtly!$A:$A,0),MATCH("2Q"&RIGHT(Annual!Z$1,2),Qrtly!$A$3:$BH$3,0))+INDEX(Qrtly!$A:$BH,MATCH(Annual!$A76,Qrtly!$A:$A,0),MATCH("3Q"&RIGHT(Annual!Z$1,2),Qrtly!$A$3:$BH$3,0))+INDEX(Qrtly!$A:$BH,MATCH(Annual!$A76,Qrtly!$A:$A,0),MATCH("4Q"&RIGHT(Annual!Z$1,2),Qrtly!$A$3:$BH$3,0)) -> 3735757.1 | AC76: 448340.53 | AD76: =IF(ISBLANK(AC76),"",INDEX($A76:$AA76,1,MATCH(AC$3,$A$3:$AA$3,0))-AC76) -> 37657.449 | AE76: 632074.53 | AF76: =IF(ISBLANK(AE76),"",INDEX($A76:$AA76,1,MATCH(AE$3,$A$3:$AA$3,0))-AE76) -> 83549.6
A77: Underlying Tax rate | B77: Underlying Tax rate | C77: % | F77: -0.021 | G77: 0.113 | H77: 0.001 | I77: 0.01 | J77: 0.007 | K77: 0.007 | L77: -0.002 | M77: 0.293 | N77: 0.338 | O77: =O76/O71 -> 0.26232705 | P77: =P76/P71 -> 0.24510939 | Q77: =Q76/Q71 -> 0.25 | R77: =R76/R71 -> 0.25 | S77: =S76/S71 -> 0.25 | T77: =T76/T71 -> 0.25 | U77: =U76/U71 -> 0.25 | V77: =V76/V71 -> 0.25 | ... Z77: =Z76/Z71 -> 0.25 | AC77: 0.22474394 | AD77: =IF(ISBLANK(AC77),"",INDEX($A77:$AA77,1,MATCH(AC$3,$A$3:$AA$3,0))-AC77) -> 0.020365452 | AE77: 0.22 | AF77: =IF(ISBLANK(AE77),"",INDEX($A77:$AA77,1,MATCH(AE$3,$A$3:$AA$3,0))-AE77) -> 0.03
AD78: =IF(ISBLANK(AC78),"",INDEX($A78:$AA78,1,MATCH(AC$3,$A$3:$AA$3,0))-AC78) | AF78: =IF(ISBLANK(AE78),"",INDEX($A78:$AA78,1,MATCH(AE$3,$A$3:$AA$3,0))-AE78)
A79: Adjusted NPAT (non-GAAP, pre-NCI) | B79: Adjusted NPAT (non-GAAP, pre-NCI) | C79: USDk | F79: -179817 | G79: 15018 | H79: 114961 | I79: 224368 | J79: 383164 | K79: 420351 | L79: 891466 | M79: 608102 | N79: 1127088 | O79: =INDEX(Qrtly!$A:$BH,MATCH(Annual!$A79,Qrtly!$A:$A,0),MATCH("1Q"&RIGHT(Annual!O$1,2),Qrtly!$A$3:$BH$3,0))+INDEX(Qrtly!$A:$BH,MATCH(Annual!$A79,Qrtly!$A:$A,0),MATCH("2Q"&RIGHT(Annual!O$1,2),Qrtly!$A$3:$BH$3,0))+INDEX(Qrtly!$A:$BH,MATCH(Annual!$A79,Qrtly!$A:$A,0),MATCH("3Q"&RIGHT(Annual!O$1,2),Qrtly!$A$3:$BH$3,0))+INDEX(Qrtly!$A:$BH,MATCH(Annual!$A79,Qrtly!$A:$A,0),MATCH("4Q"&RIGHT(Annual!O$1,2),Qrtly!$A$3:$BH$3,0)) -> 2140766 | P79: =INDEX(Qrtly!$A:$BH,MATCH(Annual!$A79,Qrtly!$A:$A,0),MATCH("1Q"&RIGHT(Annual!P$1,2),Qrtly!$A$3:$BH$3,0))+INDEX(Qrtly!$A:$BH,MATCH(Annual!$A79,Qrtly!$A:$A,0),MATCH("2Q"&RIGHT(Annual!P$1,2),Qrtly!$A$3:$BH$3,0))+INDEX(Qrtly!$A:$BH,MATCH(Annual!$A79,Qrtly!$A:$A,0),MATCH("3Q"&RIGHT(Annual!P$1,2),Qrtly!$A$3:$BH$3,0))+INDEX(Qrtly!$A:$BH,MATCH(Annual!$A79,Qrtly!$A:$A,0),MATCH("4Q"&RIGHT(Annual!P$1,2),Qrtly!$A$3:$BH$3,0)) -> 1496781.9 | Q79: =INDEX(Qrtly!$A:$BH,MATCH(Annual!$A79,Qrtly!$A:$A,0),MATCH("1Q"&RIGHT(Annual!Q$1,2),Qrtly!$A$3:$BH$3,0))+INDEX(Qrtly!$A:$BH,MATCH(Annual!$A79,Qrtly!$A:$A,0),MATCH("2Q"&RIGHT(Annual!Q$1,2),Qrtly!$A$3:$BH$3,0))+INDEX(Qrtly!$A:$BH,MATCH(Annual!$A79,Qrtly!$A:$A,0),MATCH("3Q"&RIGHT(Annual!Q$1,2),Qrtly!$A$3:$BH$3,0))+INDEX(Qrtly!$A:$BH,MATCH(Annual!$A79,Qrtly!$A:$A,0),MATCH("4Q"&RIGHT(Annual!Q$1,2),Qrtly!$A$3:$BH$3,0)) -> 2146872.4 | R79: =INDEX(Qrtly!$A:$BH,MATCH(Annual!$A79,Qrtly!$A:$A,0),MATCH("1Q"&RIGHT(Annual!R$1,2),Qrtly!$A$3:$BH$3,0))+INDEX(Qrtly!$A:$BH,MATCH(Annual!$A79,Qrtly!$A:$A,0),MATCH("2Q"&RIGHT(Annual!R$1,2),Qrtly!$A$3:$BH$3,0))+INDEX(Qrtly!$A:$BH,MATCH(Annual!$A79,Qrtly!$A:$A,0),MATCH("3Q"&RIGHT(Annual!R$1,2),Qrtly!$A$3:$BH$3,0))+INDEX(Qrtly!$A:$BH,MATCH(Annual!$A79,Qrtly!$A:$A,0),MATCH("4Q"&RIGHT(Annual!R$1,2),Qrtly!$A$3:$BH$3,0)) -> 2772903.2 | S79: =INDEX(Qrtly!$A:$BH,MATCH(Annual!$A79,Qrtly!$A:$A,0),MATCH("1Q"&RIGHT(Annual!S$1,2),Qrtly!$A$3:$BH$3,0))+INDEX(Qrtly!$A:$BH,MATCH(Annual!$A79,Qrtly!$A:$A,0),MATCH("2Q"&RIGHT(Annual!S$1,2),Qrtly!$A$3:$BH$3,0))+INDEX(Qrtly!$A:$BH,MATCH(Annual!$A79,Qrtly!$A:$A,0),MATCH("3Q"&RIGHT(Annual!S$1,2),Qrtly!$A$3:$BH$3,0))+INDEX(Qrtly!$A:$BH,MATCH(Annual!$A79,Qrtly!$A:$A,0),MATCH("4Q"&RIGHT(Annual!S$1,2),Qrtly!$A$3:$BH$3,0)) -> 3416690.7 | T79: =INDEX(Qrtly!$A:$BH,MATCH(Annual!$A79,Qrtly!$A:$A,0),MATCH("1Q"&RIGHT(Annual!T$1,2),Qrtly!$A$3:$BH$3,0))+INDEX(Qrtly!$A:$BH,MATCH(Annual!$A79,Qrtly!$A:$A,0),MATCH("2Q"&RIGHT(Annual!T$1,2),Qrtly!$A$3:$BH$3,0))+INDEX(Qrtly!$A:$BH,MATCH(Annual!$A79,Qrtly!$A:$A,0),MATCH("3Q"&RIGHT(Annual!T$1,2),Qrtly!$A$3:$BH$3,0))+INDEX(Qrtly!$A:$BH,MATCH(Annual!$A79,Qrtly!$A:$A,0),MATCH("4Q"&RIGHT(Annual!T$1,2),Qrtly!$A$3:$BH$3,0)) -> 4058598 | U79: =INDEX(Qrtly!$A:$BH,MATCH(Annual!$A79,Qrtly!$A:$A,0),MATCH("1Q"&RIGHT(Annual!U$1,2),Qrtly!$A$3:$BH$3,0))+INDEX(Qrtly!$A:$BH,MATCH(Annual!$A79,Qrtly!$A:$A,0),MATCH("2Q"&RIGHT(Annual!U$1,2),Qrtly!$A$3:$BH$3,0))+INDEX(Qrtly!$A:$BH,MATCH(Annual!$A79,Qrtly!$A:$A,0),MATCH("3Q"&RIGHT(Annual!U$1,2),Qrtly!$A$3:$BH$3,0))+INDEX(Qrtly!$A:$BH,MATCH(Annual!$A79,Qrtly!$A:$A,0),MATCH("4Q"&RIGHT(Annual!U$1,2),Qrtly!$A$3:$BH$3,0)) -> 4808988.3 | V79: =INDEX(Qrtly!$A:$BH,MATCH(Annual!$A79,Qrtly!$A:$A,0),MATCH("1Q"&RIGHT(Annual!V$1,2),Qrtly!$A$3:$BH$3,0))+INDEX(Qrtly!$A:$BH,MATCH(Annual!$A79,Qrtly!$A:$A,0),MATCH("2Q"&RIGHT(Annual!V$1,2),Qrtly!$A$3:$BH$3,0))+INDEX(Qrtly!$A:$BH,MATCH(Annual!$A79,Qrtly!$A:$A,0),MATCH("3Q"&RIGHT(Annual!V$1,2),Qrtly!$A$3:$BH$3,0))+INDEX(Qrtly!$A:$BH,MATCH(Annual!$A79,Qrtly!$A:$A,0),MATCH("4Q"&RIGHT(Annual!V$1,2),Qrtly!$A$3:$BH$3,0)) -> 5690501.5 | ... Z79: =INDEX(Qrtly!$A:$BH,MATCH(Annual!$A79,Qrtly!$A:$A,0),MATCH("1Q"&RIGHT(Annual!Z$1,2),Qrtly!$A$3:$BH$3,0))+INDEX(Qrtly!$A:$BH,MATCH(Annual!$A79,Qrtly!$A:$A,0),MATCH("2Q"&RIGHT(Annual!Z$1,2),Qrtly!$A$3:$BH$3,0))+INDEX(Qrtly!$A:$BH,MATCH(Annual!$A79,Qrtly!$A:$A,0),MATCH("3Q"&RIGHT(Annual!Z$1,2),Qrtly!$A$3:$BH$3,0))+INDEX(Qrtly!$A:$BH,MATCH(Annual!$A79,Qrtly!$A:$A,0),MATCH("4Q"&RIGHT(Annual!Z$1,2),Qrtly!$A$3:$BH$3,0)) -> 11207271 | AB79: -0.01 | AC79: 1546554.3 | AD79: =IF(ISBLANK(AC79),"",INDEX($A79:$AA79,1,MATCH(AC$3,$A$3:$AA$3,0))-AC79) -> -49772.393 | AE79: 2240991.5 | AF79: =IF(ISBLANK(AE79),"",INDEX($A79:$AA79,1,MATCH(AE$3,$A$3:$AA$3,0))-AE79) -> -94119.128
AD80: =IF(ISBLANK(AC80),"",INDEX($A80:$AA80,1,MATCH(AC$3,$A$3:$AA$3,0))-AC80) | AF80: =IF(ISBLANK(AE80),"",INDEX($A80:$AA80,1,MATCH(AE$3,$A$3:$AA$3,0))-AE80)
A81: NPATAdjustments | B81: Adjustments | F81: 0 | G81: 186608 | H81: 177774 | I81: 262821 | J81: 7718 | K81: 207246 | L81: 725184 | M81: 1148849 | N81: 1117316 | O81: =INDEX(Qrtly!$A:$BH,MATCH(Annual!$A81,Qrtly!$A:$A,0),MATCH("1Q"&RIGHT(Annual!O$1,2),Qrtly!$A$3:$BH$3,0))+INDEX(Qrtly!$A:$BH,MATCH(Annual!$A81,Qrtly!$A:$A,0),MATCH("2Q"&RIGHT(Annual!O$1,2),Qrtly!$A$3:$BH$3,0))+INDEX(Qrtly!$A:$BH,MATCH(Annual!$A81,Qrtly!$A:$A,0),MATCH("3Q"&RIGHT(Annual!O$1,2),Qrtly!$A$3:$BH$3,0))+INDEX(Qrtly!$A:$BH,MATCH(Annual!$A81,Qrtly!$A:$A,0),MATCH("4Q"&RIGHT(Annual!O$1,2),Qrtly!$A$3:$BH$3,0)) -> -756281 | P81: =INDEX(Qrtly!$A:$BH,MATCH(Annual!$A81,Qrtly!$A:$A,0),MATCH("1Q"&RIGHT(Annual!P$1,2),Qrtly!$A$3:$BH$3,0))+INDEX(Qrtly!$A:$BH,MATCH(Annual!$A81,Qrtly!$A:$A,0),MATCH("2Q"&RIGHT(Annual!P$1,2),Qrtly!$A$3:$BH$3,0))+INDEX(Qrtly!$A:$BH,MATCH(Annual!$A81,Qrtly!$A:$A,0),MATCH("3Q"&RIGHT(Annual!P$1,2),Qrtly!$A$3:$BH$3,0))+INDEX(Qrtly!$A:$BH,MATCH(Annual!$A81,Qrtly!$A:$A,0),MATCH("4Q"&RIGHT(Annual!P$1,2),Qrtly!$A$3:$BH$3,0)) -> 144949 | Q81: =INDEX(Qrtly!$A:$BH,MATCH(Annual!$A81,Qrtly!$A:$A,0),MATCH("1Q"&RIGHT(Annual!Q$1,2),Qrtly!$A$3:$BH$3,0))+INDEX(Qrtly!$A:$BH,MATCH(Annual!$A81,Qrtly!$A:$A,0),MATCH("2Q"&RIGHT(Annual!Q$1,2),Qrtly!$A$3:$BH$3,0))+INDEX(Qrtly!$A:$BH,MATCH(Annual!$A81,Qrtly!$A:$A,0),MATCH("3Q"&RIGHT(Annual!Q$1,2),Qrtly!$A$3:$BH$3,0))+INDEX(Qrtly!$A:$BH,MATCH(Annual!$A81,Qrtly!$A:$A,0),MATCH("4Q"&RIGHT(Annual!Q$1,2),Qrtly!$A$3:$BH$3,0)) -> 1198618.1 | R81: =INDEX(Qrtly!$A:$BH,MATCH(Annual!$A81,Qrtly!$A:$A,0),MATCH("1Q"&RIGHT(Annual!R$1,2),Qrtly!$A$3:$BH$3,0))+INDEX(Qrtly!$A:$BH,MATCH(Annual!$A81,Qrtly!$A:$A,0),MATCH("2Q"&RIGHT(Annual!R$1,2),Qrtly!$A$3:$BH$3,0))+INDEX(Qrtly!$A:$BH,MATCH(Annual!$A81,Qrtly!$A:$A,0),MATCH("3Q"&RIGHT(Annual!R$1,2),Qrtly!$A$3:$BH$3,0))+INDEX(Qrtly!$A:$BH,MATCH(Annual!$A81,Qrtly!$A:$A,0),MATCH("4Q"&RIGHT(Annual!R$1,2),Qrtly!$A$3:$BH$3,0)) -> 1385052.1 | S81: =INDEX(Qrtly!$A:$BH,MATCH(Annual!$A81,Qrtly!$A:$A,0),MATCH("1Q"&RIGHT(Annual!S$1,2),Qrtly!$A$3:$BH$3,0))+INDEX(Qrtly!$A:$BH,MATCH(Annual!$A81,Qrtly!$A:$A,0),MATCH("2Q"&RIGHT(Annual!S$1,2),Qrtly!$A$3:$BH$3,0))+INDEX(Qrtly!$A:$BH,MATCH(Annual!$A81,Qrtly!$A:$A,0),MATCH("3Q"&RIGHT(Annual!S$1,2),Qrtly!$A$3:$BH$3,0))+INDEX(Qrtly!$A:$BH,MATCH(Annual!$A81,Qrtly!$A:$A,0),MATCH("4Q"&RIGHT(Annual!S$1,2),Qrtly!$A$3:$BH$3,0)) -> 1593029.4 | T81: =INDEX(Qrtly!$A:$BH,MATCH(Annual!$A81,Qrtly!$A:$A,0),MATCH("1Q"&RIGHT(Annual!T$1,2),Qrtly!$A$3:$BH$3,0))+INDEX(Qrtly!$A:$BH,MATCH(Annual!$A81,Qrtly!$A:$A,0),MATCH("2Q"&RIGHT(Annual!T$1,2),Qrtly!$A$3:$BH$3,0))+INDEX(Qrtly!$A:$BH,MATCH(Annual!$A81,Qrtly!$A:$A,0),MATCH("3Q"&RIGHT(Annual!T$1,2),Qrtly!$A$3:$BH$3,0))+INDEX(Qrtly!$A:$BH,MATCH(Annual!$A81,Qrtly!$A:$A,0),MATCH("4Q"&RIGHT(Annual!T$1,2),Qrtly!$A$3:$BH$3,0)) -> 1818888.8 | U81: =INDEX(Qrtly!$A:$BH,MATCH(Annual!$A81,Qrtly!$A:$A,0),MATCH("1Q"&RIGHT(Annual!U$1,2),Qrtly!$A$3:$BH$3,0))+INDEX(Qrtly!$A:$BH,MATCH(Annual!$A81,Qrtly!$A:$A,0),MATCH("2Q"&RIGHT(Annual!U$1,2),Qrtly!$A$3:$BH$3,0))+INDEX(Qrtly!$A:$BH,MATCH(Annual!$A81,Qrtly!$A:$A,0),MATCH("3Q"&RIGHT(Annual!U$1,2),Qrtly!$A$3:$BH$3,0))+INDEX(Qrtly!$A:$BH,MATCH(Annual!$A81,Qrtly!$A:$A,0),MATCH("4Q"&RIGHT(Annual!U$1,2),Qrtly!$A$3:$BH$3,0)) -> 2081238.8 | V81: =INDEX(Qrtly!$A:$BH,MATCH(Annual!$A81,Qrtly!$A:$A,0),MATCH("1Q"&RIGHT(Annual!V$1,2),Qrtly!$A$3:$BH$3,0))+INDEX(Qrtly!$A:$BH,MATCH(Annual!$A81,Qrtly!$A:$A,0),MATCH("2Q"&RIGHT(Annual!V$1,2),Qrtly!$A$3:$BH$3,0))+INDEX(Qrtly!$A:$BH,MATCH(Annual!$A81,Qrtly!$A:$A,0),MATCH("3Q"&RIGHT(Annual!V$1,2),Qrtly!$A$3:$BH$3,0))+INDEX(Qrtly!$A:$BH,MATCH(Annual!$A81,Qrtly!$A:$A,0),MATCH("4Q"&RIGHT(Annual!V$1,2),Qrtly!$A$3:$BH$3,0)) -> 2386170.3 | ... Z81: =INDEX(Qrtly!$A:$BH,MATCH(Annual!$A81,Qrtly!$A:$A,0),MATCH("1Q"&RIGHT(Annual!Z$1,2),Qrtly!$A$3:$BH$3,0))+INDEX(Qrtly!$A:$BH,MATCH(Annual!$A81,Qrtly!$A:$A,0),MATCH("2Q"&RIGHT(Annual!Z$1,2),Qrtly!$A$3:$BH$3,0))+INDEX(Qrtly!$A:$BH,MATCH(Annual!$A81,Qrtly!$A:$A,0),MATCH("3Q"&RIGHT(Annual!Z$1,2),Qrtly!$A$3:$BH$3,0))+INDEX(Qrtly!$A:$BH,MATCH(Annual!$A81,Qrtly!$A:$A,0),MATCH("4Q"&RIGHT(Annual!Z$1,2),Qrtly!$A$3:$BH$3,0)) -> 4193529.7 | AC81: 508209 | AD81: =IF(ISBLANK(AC81),"",INDEX($A81:$AA81,1,MATCH(AC$3,$A$3:$AA$3,0))-AC81) -> -363260 | AE81: 1176035 | AF81: =IF(ISBLANK(AE81),"",INDEX($A81:$AA81,1,MATCH(AE$3,$A$3:$AA$3,0))-AE81) -> 22583.138
A82: NPATNPAT (GAAP) | B82: NPAT (GAAP) | C82: USDk | F82: -179817 | G82: -171590 | H82: -62813 | I82: -38453 | J82: 375446 | K82: 213105 | L82: 158824 | M82: -553005 | N82: -21124 | O82: =INDEX(Qrtly!$A:$BH,MATCH(Annual!$A82,Qrtly!$A:$A,0),MATCH("1Q"&RIGHT(Annual!O$1,2),Qrtly!$A$3:$BH$3,0))+INDEX(Qrtly!$A:$BH,MATCH(Annual!$A82,Qrtly!$A:$A,0),MATCH("2Q"&RIGHT(Annual!O$1,2),Qrtly!$A$3:$BH$3,0))+INDEX(Qrtly!$A:$BH,MATCH(Annual!$A82,Qrtly!$A:$A,0),MATCH("3Q"&RIGHT(Annual!O$1,2),Qrtly!$A$3:$BH$3,0))+INDEX(Qrtly!$A:$BH,MATCH(Annual!$A82,Qrtly!$A:$A,0),MATCH("4Q"&RIGHT(Annual!O$1,2),Qrtly!$A$3:$BH$3,0)) -> 2866497 | P82: =INDEX(Qrtly!$A:$BH,MATCH(Annual!$A82,Qrtly!$A:$A,0),MATCH("1Q"&RIGHT(Annual!P$1,2),Qrtly!$A$3:$BH$3,0))+INDEX(Qrtly!$A:$BH,MATCH(Annual!$A82,Qrtly!$A:$A,0),MATCH("2Q"&RIGHT(Annual!P$1,2),Qrtly!$A$3:$BH$3,0))+INDEX(Qrtly!$A:$BH,MATCH(Annual!$A82,Qrtly!$A:$A,0),MATCH("3Q"&RIGHT(Annual!P$1,2),Qrtly!$A$3:$BH$3,0))+INDEX(Qrtly!$A:$BH,MATCH(Annual!$A82,Qrtly!$A:$A,0),MATCH("4Q"&RIGHT(Annual!P$1,2),Qrtly!$A$3:$BH$3,0)) -> 1350682.9 | Q82: =INDEX(Qrtly!$A:$BH,MATCH(Annual!$A82,Qrtly!$A:$A,0),MATCH("1Q"&RIGHT(Annual!Q$1,2),Qrtly!$A$3:$BH$3,0))+INDEX(Qrtly!$A:$BH,MATCH(Annual!$A82,Qrtly!$A:$A,0),MATCH("2Q"&RIGHT(Annual!Q$1,2),Qrtly!$A$3:$BH$3,0))+INDEX(Qrtly!$A:$BH,MATCH(Annual!$A82,Qrtly!$A:$A,0),MATCH("3Q"&RIGHT(Annual!Q$1,2),Qrtly!$A$3:$BH$3,0))+INDEX(Qrtly!$A:$BH,MATCH(Annual!$A82,Qrtly!$A:$A,0),MATCH("4Q"&RIGHT(Annual!Q$1,2),Qrtly!$A$3:$BH$3,0)) -> 948254.27 | R82: =INDEX(Qrtly!$A:$BH,MATCH(Annual!$A82,Qrtly!$A:$A,0),MATCH("1Q"&RIGHT(Annual!R$1,2),Qrtly!$A$3:$BH$3,0))+INDEX(Qrtly!$A:$BH,MATCH(Annual!$A82,Qrtly!$A:$A,0),MATCH("2Q"&RIGHT(Annual!R$1,2),Qrtly!$A$3:$BH$3,0))+INDEX(Qrtly!$A:$BH,MATCH(Annual!$A82,Qrtly!$A:$A,0),MATCH("3Q"&RIGHT(Annual!R$1,2),Qrtly!$A$3:$BH$3,0))+INDEX(Qrtly!$A:$BH,MATCH(Annual!$A82,Qrtly!$A:$A,0),MATCH("4Q"&RIGHT(Annual!R$1,2),Qrtly!$A$3:$BH$3,0)) -> 1387851.1 | S82: =INDEX(Qrtly!$A:$BH,MATCH(Annual!$A82,Qrtly!$A:$A,0),MATCH("1Q"&RIGHT(Annual!S$1,2),Qrtly!$A$3:$BH$3,0))+INDEX(Qrtly!$A:$BH,MATCH(Annual!$A82,Qrtly!$A:$A,0),MATCH("2Q"&RIGHT(Annual!S$1,2),Qrtly!$A$3:$BH$3,0))+INDEX(Qrtly!$A:$BH,MATCH(Annual!$A82,Qrtly!$A:$A,0),MATCH("3Q"&RIGHT(Annual!S$1,2),Qrtly!$A$3:$BH$3,0))+INDEX(Qrtly!$A:$BH,MATCH(Annual!$A82,Qrtly!$A:$A,0),MATCH("4Q"&RIGHT(Annual!S$1,2),Qrtly!$A$3:$BH$3,0)) -> 1823661.3 | T82: =INDEX(Qrtly!$A:$BH,MATCH(Annual!$A82,Qrtly!$A:$A,0),MATCH("1Q"&RIGHT(Annual!T$1,2),Qrtly!$A$3:$BH$3,0))+INDEX(Qrtly!$A:$BH,MATCH(Annual!$A82,Qrtly!$A:$A,0),MATCH("2Q"&RIGHT(Annual!T$1,2),Qrtly!$A$3:$BH$3,0))+INDEX(Qrtly!$A:$BH,MATCH(Annual!$A82,Qrtly!$A:$A,0),MATCH("3Q"&RIGHT(Annual!T$1,2),Qrtly!$A$3:$BH$3,0))+INDEX(Qrtly!$A:$BH,MATCH(Annual!$A82,Qrtly!$A:$A,0),MATCH("4Q"&RIGHT(Annual!T$1,2),Qrtly!$A$3:$BH$3,0)) -> 2239709.1 | U82: =INDEX(Qrtly!$A:$BH,MATCH(Annual!$A82,Qrtly!$A:$A,0),MATCH("1Q"&RIGHT(Annual!U$1,2),Qrtly!$A$3:$BH$3,0))+INDEX(Qrtly!$A:$BH,MATCH(Annual!$A82,Qrtly!$A:$A,0),MATCH("2Q"&RIGHT(Annual!U$1,2),Qrtly!$A$3:$BH$3,0))+INDEX(Qrtly!$A:$BH,MATCH(Annual!$A82,Qrtly!$A:$A,0),MATCH("3Q"&RIGHT(Annual!U$1,2),Qrtly!$A$3:$BH$3,0))+INDEX(Qrtly!$A:$BH,MATCH(Annual!$A82,Qrtly!$A:$A,0),MATCH("4Q"&RIGHT(Annual!U$1,2),Qrtly!$A$3:$BH$3,0)) -> 2727749.4 | V82: =INDEX(Qrtly!$A:$BH,MATCH(Annual!$A82,Qrtly!$A:$A,0),MATCH("1Q"&RIGHT(Annual!V$1,2),Qrtly!$A$3:$BH$3,0))+INDEX(Qrtly!$A:$BH,MATCH(Annual!$A82,Qrtly!$A:$A,0),MATCH("2Q"&RIGHT(Annual!V$1,2),Qrtly!$A$3:$BH$3,0))+INDEX(Qrtly!$A:$BH,MATCH(Annual!$A82,Qrtly!$A:$A,0),MATCH("3Q"&RIGHT(Annual!V$1,2),Qrtly!$A$3:$BH$3,0))+INDEX(Qrtly!$A:$BH,MATCH(Annual!$A82,Qrtly!$A:$A,0),MATCH("4Q"&RIGHT(Annual!V$1,2),Qrtly!$A$3:$BH$3,0)) -> 3304331.2 | ... Z82: =INDEX(Qrtly!$A:$BH,MATCH(Annual!$A82,Qrtly!$A:$A,0),MATCH("1Q"&RIGHT(Annual!Z$1,2),Qrtly!$A$3:$BH$3,0))+INDEX(Qrtly!$A:$BH,MATCH(Annual!$A82,Qrtly!$A:$A,0),MATCH("2Q"&RIGHT(Annual!Z$1,2),Qrtly!$A$3:$BH$3,0))+INDEX(Qrtly!$A:$BH,MATCH(Annual!$A82,Qrtly!$A:$A,0),MATCH("3Q"&RIGHT(Annual!Z$1,2),Qrtly!$A$3:$BH$3,0))+INDEX(Qrtly!$A:$BH,MATCH(Annual!$A82,Qrtly!$A:$A,0),MATCH("4Q"&RIGHT(Annual!Z$1,2),Qrtly!$A$3:$BH$3,0)) -> 7013741.5 | AC82: 1037195.3 | AD82: =IF(ISBLANK(AC82),"",INDEX($A82:$AA82,1,MATCH(AC$3,$A$3:$AA$3,0))-AC82) -> 313487.61 | AE82: 1064956.5 | AF82: =IF(ISBLANK(AE82),"",INDEX($A82:$AA82,1,MATCH(AE$3,$A$3:$AA$3,0))-AE82) -> -116702.27
A83: NPATNCI | B83: NCI | F83: 0 | G83: 0 | H83: 0 | I83: 0 | J83: 0 | K83: 0 | L83: -7458 | M83: -12258 | N83: -30896 | O83: =INDEX(Qrtly!$A:$BH,MATCH(Annual!$A83,Qrtly!$A:$A,0),MATCH("1Q"&RIGHT(Annual!O$1,2),Qrtly!$A$3:$BH$3,0))+INDEX(Qrtly!$A:$BH,MATCH(Annual!$A83,Qrtly!$A:$A,0),MATCH("2Q"&RIGHT(Annual!O$1,2),Qrtly!$A$3:$BH$3,0))+INDEX(Qrtly!$A:$BH,MATCH(Annual!$A83,Qrtly!$A:$A,0),MATCH("3Q"&RIGHT(Annual!O$1,2),Qrtly!$A$3:$BH$3,0))+INDEX(Qrtly!$A:$BH,MATCH(Annual!$A83,Qrtly!$A:$A,0),MATCH("4Q"&RIGHT(Annual!O$1,2),Qrtly!$A$3:$BH$3,0)) -> -30550 | P83: =INDEX(Qrtly!$A:$BH,MATCH(Annual!$A83,Qrtly!$A:$A,0),MATCH("1Q"&RIGHT(Annual!P$1,2),Qrtly!$A$3:$BH$3,0))+INDEX(Qrtly!$A:$BH,MATCH(Annual!$A83,Qrtly!$A:$A,0),MATCH("2Q"&RIGHT(Annual!P$1,2),Qrtly!$A$3:$BH$3,0))+INDEX(Qrtly!$A:$BH,MATCH(Annual!$A83,Qrtly!$A:$A,0),MATCH("3Q"&RIGHT(Annual!P$1,2),Qrtly!$A$3:$BH$3,0))+INDEX(Qrtly!$A:$BH,MATCH(Annual!$A83,Qrtly!$A:$A,0),MATCH("4Q"&RIGHT(Annual!P$1,2),Qrtly!$A$3:$BH$3,0)) -> -6862.75 | Q83: =INDEX(Qrtly!$A:$BH,MATCH(Annual!$A83,Qrtly!$A:$A,0),MATCH("1Q"&RIGHT(Annual!Q$1,2),Qrtly!$A$3:$BH$3,0))+INDEX(Qrtly!$A:$BH,MATCH(Annual!$A83,Qrtly!$A:$A,0),MATCH("2Q"&RIGHT(Annual!Q$1,2),Qrtly!$A$3:$BH$3,0))+INDEX(Qrtly!$A:$BH,MATCH(Annual!$A83,Qrtly!$A:$A,0),MATCH("3Q"&RIGHT(Annual!Q$1,2),Qrtly!$A$3:$BH$3,0))+INDEX(Qrtly!$A:$BH,MATCH(Annual!$A83,Qrtly!$A:$A,0),MATCH("4Q"&RIGHT(Annual!Q$1,2),Qrtly!$A$3:$BH$3,0)) -> -8739.667 | R83: =INDEX(Qrtly!$A:$BH,MATCH(Annual!$A83,Qrtly!$A:$A,0),MATCH("1Q"&RIGHT(Annual!R$1,2),Qrtly!$A$3:$BH$3,0))+INDEX(Qrtly!$A:$BH,MATCH(Annual!$A83,Qrtly!$A:$A,0),MATCH("2Q"&RIGHT(Annual!R$1,2),Qrtly!$A$3:$BH$3,0))+INDEX(Qrtly!$A:$BH,MATCH(Annual!$A83,Qrtly!$A:$A,0),MATCH("3Q"&RIGHT(Annual!R$1,2),Qrtly!$A$3:$BH$3,0))+INDEX(Qrtly!$A:$BH,MATCH(Annual!$A83,Qrtly!$A:$A,0),MATCH("4Q"&RIGHT(Annual!R$1,2),Qrtly!$A$3:$BH$3,0)) -> -9344.9253 | S83: =INDEX(Qrtly!$A:$BH,MATCH(Annual!$A83,Qrtly!$A:$A,0),MATCH("1Q"&RIGHT(Annual!S$1,2),Qrtly!$A$3:$BH$3,0))+INDEX(Qrtly!$A:$BH,MATCH(Annual!$A83,Qrtly!$A:$A,0),MATCH("2Q"&RIGHT(Annual!S$1,2),Qrtly!$A$3:$BH$3,0))+INDEX(Qrtly!$A:$BH,MATCH(Annual!$A83,Qrtly!$A:$A,0),MATCH("3Q"&RIGHT(Annual!S$1,2),Qrtly!$A$3:$BH$3,0))+INDEX(Qrtly!$A:$BH,MATCH(Annual!$A83,Qrtly!$A:$A,0),MATCH("4Q"&RIGHT(Annual!S$1,2),Qrtly!$A$3:$BH$3,0)) -> -9488.9582 | T83: =INDEX(Qrtly!$A:$BH,MATCH(Annual!$A83,Qrtly!$A:$A,0),MATCH("1Q"&RIGHT(Annual!T$1,2),Qrtly!$A$3:$BH$3,0))+INDEX(Qrtly!$A:$BH,MATCH(Annual!$A83,Qrtly!$A:$A,0),MATCH("2Q"&RIGHT(Annual!T$1,2),Qrtly!$A$3:$BH$3,0))+INDEX(Qrtly!$A:$BH,MATCH(Annual!$A83,Qrtly!$A:$A,0),MATCH("3Q"&RIGHT(Annual!T$1,2),Qrtly!$A$3:$BH$3,0))+INDEX(Qrtly!$A:$BH,MATCH(Annual!$A83,Qrtly!$A:$A,0),MATCH("4Q"&RIGHT(Annual!T$1,2),Qrtly!$A$3:$BH$3,0)) -> -9517.3097 | U83: =INDEX(Qrtly!$A:$BH,MATCH(Annual!$A83,Qrtly!$A:$A,0),MATCH("1Q"&RIGHT(Annual!U$1,2),Qrtly!$A$3:$BH$3,0))+INDEX(Qrtly!$A:$BH,MATCH(Annual!$A83,Qrtly!$A:$A,0),MATCH("2Q"&RIGHT(Annual!U$1,2),Qrtly!$A$3:$BH$3,0))+INDEX(Qrtly!$A:$BH,MATCH(Annual!$A83,Qrtly!$A:$A,0),MATCH("3Q"&RIGHT(Annual!U$1,2),Qrtly!$A$3:$BH$3,0))+INDEX(Qrtly!$A:$BH,MATCH(Annual!$A83,Qrtly!$A:$A,0),MATCH("4Q"&RIGHT(Annual!U$1,2),Qrtly!$A$3:$BH$3,0)) -> -9522.0612 | V83: =INDEX(Qrtly!$A:$BH,MATCH(Annual!$A83,Qrtly!$A:$A,0),MATCH("1Q"&RIGHT(Annual!V$1,2),Qrtly!$A$3:$BH$3,0))+INDEX(Qrtly!$A:$BH,MATCH(Annual!$A83,Qrtly!$A:$A,0),MATCH("2Q"&RIGHT(Annual!V$1,2),Qrtly!$A$3:$BH$3,0))+INDEX(Qrtly!$A:$BH,MATCH(Annual!$A83,Qrtly!$A:$A,0),MATCH("3Q"&RIGHT(Annual!V$1,2),Qrtly!$A$3:$BH$3,0))+INDEX(Qrtly!$A:$BH,MATCH(Annual!$A83,Qrtly!$A:$A,0),MATCH("4Q"&RIGHT(Annual!V$1,2),Qrtly!$A$3:$BH$3,0)) -> -9522.7277 | ... Z83: =INDEX(Qrtly!$A:$BH,MATCH(Annual!$A83,Qrtly!$A:$A,0),MATCH("1Q"&RIGHT(Annual!Z$1,2),Qrtly!$A$3:$BH$3,0))+INDEX(Qrtly!$A:$BH,MATCH(Annual!$A83,Qrtly!$A:$A,0),MATCH("2Q"&RIGHT(Annual!Z$1,2),Qrtly!$A$3:$BH$3,0))+INDEX(Qrtly!$A:$BH,MATCH(Annual!$A83,Qrtly!$A:$A,0),MATCH("3Q"&RIGHT(Annual!Z$1,2),Qrtly!$A$3:$BH$3,0))+INDEX(Qrtly!$A:$BH,MATCH(Annual!$A83,Qrtly!$A:$A,0),MATCH("4Q"&RIGHT(Annual!Z$1,2),Qrtly!$A$3:$BH$3,0)) -> -9522.8001 | AC83: -14818.688 | AD83: =IF(ISBLANK(AC83),"",INDEX($A83:$AA83,1,MATCH(AC$3,$A$3:$AA$3,0))-AC83) -> 7955.9375 | AE83: -18616.218 | AF83: =IF(ISBLANK(AE83),"",INDEX($A83:$AA83,1,MATCH(AE$3,$A$3:$AA$3,0))-AE83) -> 9876.5505
A84: NPATNPAT post NCI (GAAP) | B84: NPAT post NCI (GAAP) | C84: USDk | F84: -179817 | G84: -171590 | H84: -62813 | I84: -38453 | J84: 375446 | K84: 213105 | L84: 166282 | M84: -540747 | N84: 9772 | O84: =INDEX(Qrtly!$A:$BH,MATCH(Annual!$A84,Qrtly!$A:$A,0),MATCH("1Q"&RIGHT(Annual!O$1,2),Qrtly!$A$3:$BH$3,0))+INDEX(Qrtly!$A:$BH,MATCH(Annual!$A84,Qrtly!$A:$A,0),MATCH("2Q"&RIGHT(Annual!O$1,2),Qrtly!$A$3:$BH$3,0))+INDEX(Qrtly!$A:$BH,MATCH(Annual!$A84,Qrtly!$A:$A,0),MATCH("3Q"&RIGHT(Annual!O$1,2),Qrtly!$A$3:$BH$3,0))+INDEX(Qrtly!$A:$BH,MATCH(Annual!$A84,Qrtly!$A:$A,0),MATCH("4Q"&RIGHT(Annual!O$1,2),Qrtly!$A$3:$BH$3,0)) -> 2897047 | P84: =INDEX(Qrtly!$A:$BH,MATCH(Annual!$A84,Qrtly!$A:$A,0),MATCH("1Q"&RIGHT(Annual!P$1,2),Qrtly!$A$3:$BH$3,0))+INDEX(Qrtly!$A:$BH,MATCH(Annual!$A84,Qrtly!$A:$A,0),MATCH("2Q"&RIGHT(Annual!P$1,2),Qrtly!$A$3:$BH$3,0))+INDEX(Qrtly!$A:$BH,MATCH(Annual!$A84,Qrtly!$A:$A,0),MATCH("3Q"&RIGHT(Annual!P$1,2),Qrtly!$A$3:$BH$3,0))+INDEX(Qrtly!$A:$BH,MATCH(Annual!$A84,Qrtly!$A:$A,0),MATCH("4Q"&RIGHT(Annual!P$1,2),Qrtly!$A$3:$BH$3,0)) -> 1346260.2 | Q84: =INDEX(Qrtly!$A:$BH,MATCH(Annual!$A84,Qrtly!$A:$A,0),MATCH("1Q"&RIGHT(Annual!Q$1,2),Qrtly!$A$3:$BH$3,0))+INDEX(Qrtly!$A:$BH,MATCH(Annual!$A84,Qrtly!$A:$A,0),MATCH("2Q"&RIGHT(Annual!Q$1,2),Qrtly!$A$3:$BH$3,0))+INDEX(Qrtly!$A:$BH,MATCH(Annual!$A84,Qrtly!$A:$A,0),MATCH("3Q"&RIGHT(Annual!Q$1,2),Qrtly!$A$3:$BH$3,0))+INDEX(Qrtly!$A:$BH,MATCH(Annual!$A84,Qrtly!$A:$A,0),MATCH("4Q"&RIGHT(Annual!Q$1,2),Qrtly!$A$3:$BH$3,0)) -> 939514.61 | R84: =INDEX(Qrtly!$A:$BH,MATCH(Annual!$A84,Qrtly!$A:$A,0),MATCH("1Q"&RIGHT(Annual!R$1,2),Qrtly!$A$3:$BH$3,0))+INDEX(Qrtly!$A:$BH,MATCH(Annual!$A84,Qrtly!$A:$A,0),MATCH("2Q"&RIGHT(Annual!R$1,2),Qrtly!$A$3:$BH$3,0))+INDEX(Qrtly!$A:$BH,MATCH(Annual!$A84,Qrtly!$A:$A,0),MATCH("3Q"&RIGHT(Annual!R$1,2),Qrtly!$A$3:$BH$3,0))+INDEX(Qrtly!$A:$BH,MATCH(Annual!$A84,Qrtly!$A:$A,0),MATCH("4Q"&RIGHT(Annual!R$1,2),Qrtly!$A$3:$BH$3,0)) -> 1378506.2 | S84: =INDEX(Qrtly!$A:$BH,MATCH(Annual!$A84,Qrtly!$A:$A,0),MATCH("1Q"&RIGHT(Annual!S$1,2),Qrtly!$A$3:$BH$3,0))+INDEX(Qrtly!$A:$BH,MATCH(Annual!$A84,Qrtly!$A:$A,0),MATCH("2Q"&RIGHT(Annual!S$1,2),Qrtly!$A$3:$BH$3,0))+INDEX(Qrtly!$A:$BH,MATCH(Annual!$A84,Qrtly!$A:$A,0),MATCH("3Q"&RIGHT(Annual!S$1,2),Qrtly!$A$3:$BH$3,0))+INDEX(Qrtly!$A:$BH,MATCH(Annual!$A84,Qrtly!$A:$A,0),MATCH("4Q"&RIGHT(Annual!S$1,2),Qrtly!$A$3:$BH$3,0)) -> 1814172.3 | T84: =INDEX(Qrtly!$A:$BH,MATCH(Annual!$A84,Qrtly!$A:$A,0),MATCH("1Q"&RIGHT(Annual!T$1,2),Qrtly!$A$3:$BH$3,0))+INDEX(Qrtly!$A:$BH,MATCH(Annual!$A84,Qrtly!$A:$A,0),MATCH("2Q"&RIGHT(Annual!T$1,2),Qrtly!$A$3:$BH$3,0))+INDEX(Qrtly!$A:$BH,MATCH(Annual!$A84,Qrtly!$A:$A,0),MATCH("3Q"&RIGHT(Annual!T$1,2),Qrtly!$A$3:$BH$3,0))+INDEX(Qrtly!$A:$BH,MATCH(Annual!$A84,Qrtly!$A:$A,0),MATCH("4Q"&RIGHT(Annual!T$1,2),Qrtly!$A$3:$BH$3,0)) -> 2230191.8 | U84: =INDEX(Qrtly!$A:$BH,MATCH(Annual!$A84,Qrtly!$A:$A,0),MATCH("1Q"&RIGHT(Annual!U$1,2),Qrtly!$A$3:$BH$3,0))+INDEX(Qrtly!$A:$BH,MATCH(Annual!$A84,Qrtly!$A:$A,0),MATCH("2Q"&RIGHT(Annual!U$1,2),Qrtly!$A$3:$BH$3,0))+INDEX(Qrtly!$A:$BH,MATCH(Annual!$A84,Qrtly!$A:$A,0),MATCH("3Q"&RIGHT(Annual!U$1,2),Qrtly!$A$3:$BH$3,0))+INDEX(Qrtly!$A:$BH,MATCH(Annual!$A84,Qrtly!$A:$A,0),MATCH("4Q"&RIGHT(Annual!U$1,2),Qrtly!$A$3:$BH$3,0)) -> 2718227.4 | V84: =INDEX(Qrtly!$A:$BH,MATCH(Annual!$A84,Qrtly!$A:$A,0),MATCH("1Q"&RIGHT(Annual!V$1,2),Qrtly!$A$3:$BH$3,0))+INDEX(Qrtly!$A:$BH,MATCH(Annual!$A84,Qrtly!$A:$A,0),MATCH("2Q"&RIGHT(Annual!V$1,2),Qrtly!$A$3:$BH$3,0))+INDEX(Qrtly!$A:$BH,MATCH(Annual!$A84,Qrtly!$A:$A,0),MATCH("3Q"&RIGHT(Annual!V$1,2),Qrtly!$A$3:$BH$3,0))+INDEX(Qrtly!$A:$BH,MATCH(Annual!$A84,Qrtly!$A:$A,0),MATCH("4Q"&RIGHT(Annual!V$1,2),Qrtly!$A$3:$BH$3,0)) -> 3294808.5 | ... Z84: =INDEX(Qrtly!$A:$BH,MATCH(Annual!$A84,Qrtly!$A:$A,0),MATCH("1Q"&RIGHT(Annual!Z$1,2),Qrtly!$A$3:$BH$3,0))+INDEX(Qrtly!$A:$BH,MATCH(Annual!$A84,Qrtly!$A:$A,0),MATCH("2Q"&RIGHT(Annual!Z$1,2),Qrtly!$A$3:$BH$3,0))+INDEX(Qrtly!$A:$BH,MATCH(Annual!$A84,Qrtly!$A:$A,0),MATCH("3Q"&RIGHT(Annual!Z$1,2),Qrtly!$A$3:$BH$3,0))+INDEX(Qrtly!$A:$BH,MATCH(Annual!$A84,Qrtly!$A:$A,0),MATCH("4Q"&RIGHT(Annual!Z$1,2),Qrtly!$A$3:$BH$3,0)) -> 7004218.7 | AC84: 1024924.6 | AD84: =IF(ISBLANK(AC84),"",INDEX($A84:$AA84,1,MATCH(AC$3,$A$3:$AA$3,0))-AC84) -> 321335.54 | AE84: 1046340.3 | AF84: =IF(ISBLANK(AE84),"",INDEX($A84:$AA84,1,MATCH(AE$3,$A$3:$AA$3,0))-AE84) -> -106825.72
O85: =O87*75 -> 46476 | P85: =P87*75 -> 46476 | AC85: 46476 | AD85: =IF(ISBLANK(AC85),"",INDEX($A85:$AA85,1,MATCH(AC$3,$A$3:$AA$3,0))-AC85) -> 0 | AF85: =IF(ISBLANK(AE85),"",INDEX($A85:$AA85,1,MATCH(AE$3,$A$3:$AA$3,0))-AE85)
B86: EPS | P86: =P87/O87 -> 1 | AC86: 1 | AD86: =IF(ISBLANK(AC86),"",INDEX($A86:$AA86,1,MATCH(AC$3,$A$3:$AA$3,0))-AC86) -> 0 | AF86: =IF(ISBLANK(AE86),"",INDEX($A86:$AA86,1,MATCH(AE$3,$A$3:$AA$3,0))-AE86)
A87: YE Basic Shares Outstanding | B87: YE Basic Shares Outstanding | C87: #m | M87: 600.06 | N87: 615.82 | O87: 619.68 | P87: =O87+(P211+P47)/P94/1000 -> 619.68 | Q87: =P87+(Q211+Q47)/Q94/1000 -> 619.68 | R87: =Q87+(R211+R47)/R94/1000 -> 607.70686 | S87: =R87+(S211+S47)/S94/1000 -> 595.73371 | T87: =S87+(T211+T47)/T94/1000 -> 583.76057 | U87: =T87+(U211+U47)/U94/1000 -> 571.78742 | V87: =U87+(V211+V47)/V94/1000 -> 559.81428 | W87: =V87+(W211+W47)/W94/1000 -> 547.84113 | ... Z87: =Y87+(Z211+Z47)/Z94/1000 -> 511.9217 | AC87: 619.68 | AD87: =IF(ISBLANK(AC87),"",INDEX($A87:$AA87,1,MATCH(AC$3,$A$3:$AA$3,0))-AC87) -> 0 | AE87: 619.68 | AF87: =IF(ISBLANK(AE87),"",INDEX($A87:$AA87,1,MATCH(AE$3,$A$3:$AA$3,0))-AE87) -> 0
B88: Weighted Average Basic Shares Outstanding | C88: #m | L88: 458.43 | M88: 578.95 | N88: 608.86 | O88: 616.99 | P88: =AVERAGE(O87:P87) -> 619.68 | Q88: =AVERAGE(P87:Q87) -> 619.68 | R88: =AVERAGE(Q87:R87) -> 613.69343 | S88: =AVERAGE(R87:S87) -> 601.72028 | T88: =AVERAGE(S87:T87) -> 589.74714 | U88: =AVERAGE(T87:U87) -> 577.774 | V88: =AVERAGE(U87:V87) -> 565.80085 | W88: =AVERAGE(V87:W87) -> 553.82771 | ... Z88: =AVERAGE(Y87:Z87) -> 517.90827 | AC88: 619.68 | AD88: =IF(ISBLANK(AC88),"",INDEX($A88:$AA88,1,MATCH(AC$3,$A$3:$AA$3,0))-AC88) -> 0 | AE88: 619.68 | AF88: =IF(ISBLANK(AE88),"",INDEX($A88:$AA88,1,MATCH(AE$3,$A$3:$AA$3,0))-AE88) -> 0
B89: Dilution | C89: #m | L89: 43.35 | M89: 0 | N89: 5.17 | O89: 19.4 | P89: 19.4 | Q89: 19.4 | R89: 19.4 | S89: 19.4 | T89: 19.4 | U89: 19.4 | V89: 19.4 | W89: 19.4 | X89: 19.4 | Y89: 19.4 | Z89: 19.4 | AC89: 19.4 | AD89: =IF(ISBLANK(AC89),"",INDEX($A89:$AA89,1,MATCH(AC$3,$A$3:$AA$3,0))-AC89) -> 0 | AE89: 19.4 | AF89: =IF(ISBLANK(AE89),"",INDEX($A89:$AA89,1,MATCH(AE$3,$A$3:$AA$3,0))-AE89) -> 0
A90: Weighted Average Diluted Shares Outstanding | B90: Weighted Average Diluted Shares Outstanding | C90: #m | L90: 501.78 | M90: 578.95 | N90: 614.02 | O90: 636.39 | P90: =P88+P89 -> 639.08 | Q90: =Q88+Q89 -> 639.08 | R90: =R88+R89 -> 633.09343 | S90: =S88+S89 -> 621.12028 | T90: =T88+T89 -> 609.14714 | U90: =U88+U89 -> 597.174 | V90: =V88+V89 -> 585.20085 | W90: =W88+W89 -> 573.22771 | ... Z90: =Z88+Z89 -> 537.30827 | AC90: 639.08 | AD90: =IF(ISBLANK(AC90),"",INDEX($A90:$AA90,1,MATCH(AC$3,$A$3:$AA$3,0))-AC90) -> 0 | AE90: 639.08 | AF90: =IF(ISBLANK(AE90),"",INDEX($A90:$AA90,1,MATCH(AE$3,$A$3:$AA$3,0))-AE90) -> 0
AD91: =IF(ISBLANK(AC91),"",INDEX($A91:$AA91,1,MATCH(AC$3,$A$3:$AA$3,0))-AC91) | AF91: =IF(ISBLANK(AE91),"",INDEX($A91:$AA91,1,MATCH(AE$3,$A$3:$AA$3,0))-AE91)
A92: EPS | B92: Underlying EPS | C92: USDps | L92: =L79/L90/1000 -> 1.7766073 | M92: =M79/M90/1000 -> 1.0503532 | N92: =N79/N90/1000 -> 1.8355884 | O92: =O79/O90/1000 -> 3.3639215 | P92: =P79/P90/1000 -> 2.3420885 | Q92: =Q79/Q90/1000 -> 3.3593171 | R92: =R79/R90/1000 -> 4.3799274 | S92: =S79/S90/1000 -> 5.5008519 | ... Z92: =Z79/Z90/1000 -> 20.858177 | AC92: 2.4199698 | AD92: =IF(ISBLANK(AC92),"",INDEX($A92:$AA92,1,MATCH(AC$3,$A$3:$AA$3,0))-AC92) -> -0.077881318 | AE92: 3.50659 | AF92: =IF(ISBLANK(AE92),"",INDEX($A92:$AA92,1,MATCH(AE$3,$A$3:$AA$3,0))-AE92) -> -0.14727284
B93: EPS Growth | C93: % YoY | L93: #DIV/0! | M93: -0.41 | N93: 0.75 | O93: =O92/N92-1 -> 0.83261207 | P93: =P92/O92-1 -> -0.30376244 | Q93: =Q92/P92-1 -> 0.43432545 | R93: =R92/Q92-1 -> 0.30381479 | S93: =S92/R92-1 -> 0.25592309 | T93: =T92/S92-1 -> 0.21122234 | U93: =U92/T92-1 -> 0.20864568 | V93: =V92/U92-1 -> 0.20751564 | ... Z93: =Z92/Y92-1 -> 0.21363694 | AC93: -0.28061049 | AD93: =IF(ISBLANK(AC93),"",INDEX($A93:$AA93,1,MATCH(AC$3,$A$3:$AA$3,0))-AC93) -> -0.023151943 | AE93: 0.44902219 | AF93: =IF(ISBLANK(AE93),"",INDEX($A93:$AA93,1,MATCH(AE$3,$A$3:$AA$3,0))-AE93) -> -0.014696748
B94: Average Share Price | C94: USDps | L94: =Value!$G$5 -> 62.75 | M94: =Value!$G$5 -> 62.75 | N94: =Value!$G$5 -> 62.75 | O94: =Value!$G$5 -> 62.75 | P94: =O94*1.1 -> 69.025 | Q94: =P94*1.1 -> 75.9275 | R94: =Q94*1.1 -> 83.52025 | S94: =R94*1.1 -> 91.872275 | T94: =S94*1.1 -> 101.0595 | U94: =T94*1.1 -> 111.16545 | V94: =U94*1.1 -> 122.282 | W94: =V94*1.1 -> 134.5102 | ... Z94: =Y94*1.1 -> 179.03307 | AC94: 79.86 | AD94: =IF(ISBLANK(AC94),"",INDEX($A94:$AA94,1,MATCH(AC$3,$A$3:$AA$3,0))-AC94) -> -10.835 | AE94: 87.846 | AF94: =IF(ISBLANK(AE94),"",INDEX($A94:$AA94,1,MATCH(AE$3,$A$3:$AA$3,0))-AE94) -> -11.9185
B95: PE multiple | C95: x | L95: =L94/L92 -> 35.32013 | M95: =M94/M92 -> 59.741807 | N95: =N94/N92 -> 34.185223 | O95: =O94/O92 -> 18.653824 | P95: =P94/P92 -> 29.471559 | Q95: =Q94/Q92 -> 22.602064 | R95: =R94/R92 -> 19.068866 | S95: =S94/S92 -> 16.701463 | ... Z95: =Z94/Z92 -> 8.5833518 | AC95: 33.000411 | AD95: =IF(ISBLANK(AC95),"",INDEX($A95:$AA95,1,MATCH(AC$3,$A$3:$AA$3,0))-AC95) -> -3.5288523 | AE95: 25.051688 | AF95: =IF(ISBLANK(AE95),"",INDEX($A95:$AA95,1,MATCH(AE$3,$A$3:$AA$3,0))-AE95) -> -2.4496248
AD96: =IF(ISBLANK(AC96),"",INDEX($A96:$AA96,1,MATCH(AC$3,$A$3:$AA$3,0))-AC96) | AF96: =IF(ISBLANK(AE96),"",INDEX($A96:$AA96,1,MATCH(AE$3,$A$3:$AA$3,0))-AE96)
B97: Dividends | AD97: =IF(ISBLANK(AC97),"",INDEX($A97:$AA97,1,MATCH(AC$3,$A$3:$AA$3,0))-AC97) | AF97: =IF(ISBLANK(AE97),"",INDEX($A97:$AA97,1,MATCH(AE$3,$A$3:$AA$3,0))-AE97)
A98: Dividends | B98: Dividends | C98: USDps | J98: 0 | K98: 0 | L98: 0 | M98: 0 | N98: 0 | O98: 0 | P98: =P92*P100 -> 0 | Q98: =Q92*Q100 -> 0 | R98: =R92*R100 -> 0 | S98: =S92*S100 -> 0 | T98: =T92*T100 -> 0 | U98: =U92*U100 -> 0 | V98: =V92*V100 -> 0 | W98: =W92*W100 -> 0 | ... Z98: =Z92*Z100 -> 16.686542 | AC98: 0 | AD98: =IF(ISBLANK(AC98),"",INDEX($A98:$AA98,1,MATCH(AC$3,$A$3:$AA$3,0))-AC98) -> 0 | AE98: 0 | AF98: =IF(ISBLANK(AE98),"",INDEX($A98:$AA98,1,MATCH(AE$3,$A$3:$AA$3,0))-AE98) -> 0
B99: Dividends | C99: USDk | J99: 0 | K99: 0 | L99: 0 | M99: 0 | N99: 0 | O99: 0 | P99: =P98*P87*1000 -> 0 | Q99: =Q98*Q87*1000 -> 0 | R99: =R98*R87*1000 -> 0 | S99: =S98*S87*1000 -> 0 | T99: =T98*T87*1000 -> 0 | U99: =U98*U87*1000 -> 0 | V99: =V98*V87*1000 -> 0 | W99: =W98*W87*1000 -> 0 | ... Z99: =Z98*Z87*1000 -> 8542202.9 | AC99: 0 | AD99: =IF(ISBLANK(AC99),"",INDEX($A99:$AA99,1,MATCH(AC$3,$A$3:$AA$3,0))-AC99) -> 0 | AE99: 0 | AF99: =IF(ISBLANK(AE99),"",INDEX($A99:$AA99,1,MATCH(AE$3,$A$3:$AA$3,0))-AE99) -> 0
B100: Payout Ratio | C100: % | J100: #DIV/0! | K100: #DIV/0! | L100: 0 | M100: 0 | N100: 0 | O100: 0 | P100: 0 | Q100: 0 | R100: 0 | S100: 0 | T100: 0 | U100: 0 | V100: 0 | W100: 0 | X100: 0 | Y100: 0 | Z100: =Value!$K$9 -> 0.8 | AC100: 0 | AD100: =IF(ISBLANK(AC100),"",INDEX($A100:$AA100,1,MATCH(AC$3,$A$3:$AA$3,0))-AC100) -> 0 | AE100: 0 | AF100: =IF(ISBLANK(AE100),"",INDEX($A100:$AA100,1,MATCH(AE$3,$A$3:$AA$3,0))-AE100) -> 0
B101: Dividend Yield | C101: % | J101: #VALUE! | K101: #VALUE! | L101: #VALUE! | M101: #VALUE! | N101: #VALUE! | O101: #VALUE! | P101: #VALUE! | Q101: #VALUE! | R101: #VALUE! | S101: #VALUE! | T101: #VALUE! | U101: #VALUE! | V101: #VALUE! | W101: #VALUE! | X101: #VALUE! | Y101: #VALUE! | Z101: #VALUE! | AC101: #VALUE! | AD101: =IF(ISBLANK(AC101),"",INDEX($A101:$AA101,1,MATCH(AC$3,$A$3:$AA$3,0))-AC101) -> #VALUE! | AE101: #VALUE! | AF101: =IF(ISBLANK(AE101),"",INDEX($A101:$AA101,1,MATCH(AE$3,$A$3:$AA$3,0))-AE101) -> #VALUE!
...

Sheet Qrtly
B1: Segments | D1: 2022 | E1: 2022 | F1: 2022 | G1: 2022 | H1: 2023 | I1: 2023 | J1: 2023 | K1: 2023 | L1: 2024 | M1: 2024 | N1: 2024 | O1: 2024 | P1: 2025 | Q1: 2025 | R1: 2025 | S1: 2025 | T1: 2026 | U1: 2026 | V1: 2026 | W1: 2026 | X1: 2027 | Y1: 2027 | Z1: 2027 | AA1: 2027 | AB1: 2028 | AC1: 2028 | AD1: 2028 | AE1: 2028 | AF1: 2029 | AG1: 2029 | AH1: 2029 | AI1: 2029 | AJ1: 2030 | AK1: 2030 | AL1: 2030 | AM1: 2030 | AN1: 2031 | AO1: 2031 | AP1: 2031 | AQ1: 2031 | AR1: 2032 | AS1: 2032 | AT1: 2032 | AU1: 2032 | AV1: 2033 | AW1: 2033 | AX1: 2033 | AY1: 2033 | AZ1: 2034 | BA1: 2034 | BB1: 2034 | BC1: 2034 | BD1: 2035 | BE1: 2035 | BF1: 2035 | BG1: 2035 | BN1: 2025 | BP1: 2025
S2: Forecast -----> | BI2: Seasonality- 5yr averages | BN2: Forecast ----->
C3: Units | D3: 1Q22 | E3: 2Q22 | F3: 3Q22 | G3: 4Q22 | H3: 1Q23 | I3: 2Q23 | J3: 3Q23 | K3: 4Q23 | L3: 1Q24 | M3: 2Q24 | N3: 3Q24 | O3: 4Q24 | P3: 1Q25 | Q3: 2Q25 | R3: 3Q25 | S3: 4Q25 | T3: 1Q26 | U3: 2Q26 | V3: 3Q26 | W3: 4Q26 | X3: 1Q27 | Y3: 2Q27 | Z3: 3Q27 | AA3: 4Q27 | AB3: 1Q28 | AC3: 2Q28 | AD3: 3Q28 | AE3: 4Q28 | AF3: 1Q29 | AG3: 2Q29 | AH3: 3Q29 | AI3: 4Q29 | AJ3: 1Q30 | AK3: 2Q30 | AL3: 3Q30 | AM3: 4Q30 | AN3: 1Q31 | AO3: 2Q31 | AP3: 3Q31 | AQ3: 4Q31 | AR3: 1Q32 | AS3: 2Q32 | AT3: 3Q32 | AU3: 4Q32 | AV3: 1Q33 | AW3: 2Q33 | AX3: 3Q33 | AY3: 4Q33 | AZ3: 1Q34 | BA3: 2Q34 | BB3: 3Q34 | BC3: 4Q34 | BD3: 1Q35 | BE3: 2Q35 | BF3: 3Q35 | BG3: 4Q35 | BI3: 1Q | BJ3: 2Q | BK3: 3Q | BL3: 4Q | BN3: 3Q25 | BP3: 4Q25
D4: 1H22 | E4: 1H22 | F4: 2H22 | G4: 2H22 | H4: 1H23 | I4: 1H23 | J4: 2H23 | K4: 2H23 | L4: 1H24 | M4: 1H24 | N4: 2H24 | O4: 2H24 | P4: 1H25 | Q4: 1H25 | R4: 1H25 | S4: 2H25 | T4: 1H26 | U4: 1H26 | V4: 2H26 | W4: 2H26 | X4: 1H27 | Y4: 1H27 | Z4: 2H27 | AA4: 2H27 | AB4: 1H28 | AC4: 1H28 | AD4: 2H28 | AE4: 2H28 | AF4: 1H29 | AG4: 1H29 | AH4: 2H29 | AI4: 2H29 | AJ4: 1H30 | AK4: 1H30 | AL4: 2H30 | AM4: 2H30 | AN4: 1H31 | AO4: 1H31 | AP4: 2H31 | AQ4: 2H31 | AR4: 1H32 | AS4: 1H32 | AT4: 2H32 | AU4: 2H32 | AV4: 1H33 | AW4: 1H33 | AX4: 2H33 | AY4: 2H33 | AZ4: 1H34 | BA4: 1H34 | BB4: 2H34 | BC4: 2H34 | BD4: 1H35 | BE4: 1H35 | BF4: 2H35 | BG4: 2H35 | BN4: 2H25 | BP4: 2H25
B5: P &L
B6: Revenue (GAAP, as per guidance)
A7: RevSquare | B7: Square | D7: 1378822 | E7: 1621463 | F7: 1669556 | G7: 1624298 | H7: 1555376 | I7: 1811713 | J7: 1853382 | K7: 1812912 | L7: 1730037 | M7: 1979490 | N7: 2001737 | O7: 1970392 | P7: 1852161 | Q7: 2166275 | R7: =R139 -> 2240846 | S7: =S139 -> 2218132.6 | T7: =T139 -> 2096505.8 | U7: =U139 -> 2461866.2 | V7: =V139 -> 2552542.2 | W7: =W139 -> 2527118.7 | X7: =X139 -> 2371569.4 | Y7: =Y139 -> 2784453.9 | ... BG7: =BG139 -> 7163164.3 | BN7: 2212027 | BO7: =IF(ISBLANK(BN7),"",INDEX($A7:$BH7,1,MATCH(BN$3,$A$3:$BH$3,0))-BN7) -> 28819.012 | BP7: 2208487 | BQ7: =IF(ISBLANK(BP7),"",INDEX($A7:$BH7,1,MATCH(BP$3,$A$3:$BH$3,0))-BP7) -> 9645.5837
A8: RevCash App | B8: Cash App | D8: 2527225 | E8: 2726196 | F8: 2789851 | G8: 2988531 | H8: 3384163 | I8: 3673166 | J8: 3713928 | K8: 3910430 | L8: 4172904 | M8: 4128827 | N8: 3929573 | O8: 4016576 | P8: 3879014 | Q8: 3844928 | R8: =R186 -> 3799501 | S8: =S186 -> 3742696.1 | T8: =T186 -> 4349897.8 | U8: =U186 -> 4460787.8 | V8: =V186 -> 4318080.9 | W8: =W186 -> 4253686.1 | X8: =X186 -> 4951468.5 | Y8: =Y186 -> 5074041.8 | ... BG8: =BG186 -> 13550000 | BN8: 4682108.5 | BO8: =IF(ISBLANK(BN8),"",INDEX($A8:$BH8,1,MATCH(BN$3,$A$3:$BH$3,0))-BN8) -> -882607.47 | BP8: 4817522.5 | BQ8: =IF(ISBLANK(BP8),"",INDEX($A8:$BH8,1,MATCH(BP$3,$A$3:$BH$3,0))-BP8) -> -1074826.4
A9: RevCorporate & Other | B9: Corporate & Other | D9: 54598 | E9: 56841 | F9: 56135 | G9: 38073 | H9: 50592 | I9: 50079 | J9: 50183 | K9: 49700 | L9: 54187 | M9: 47246 | N9: 44491 | O9: 45593 | P9: 40621 | Q9: 43254 | R9: =R10-R7-R8 -> 74605 | S9: 87873 | T9: 82652 | U9: 85417 | V9: =R9*1.2 -> 89526 | W9: =S9*1.2 -> 105447.6 | X9: =T9*1.2 -> 99182.4 | Y9: =U9*1.2 -> 102500.4 | Z9: =V9*1.2 -> 107431.2 | AA9: =W9*1.2 -> 126537.12 | AB9: =X9*1.2 -> 119018.88 | AC9: =Y9*1.2 -> 123000.48 | AD9: =Z9*1.2 -> 128917.44 | AE9: =AA9*1.05 -> 132863.98 | AF9: =AB9*1.05 -> 124969.82 | AG9: =AC9*1.05 -> 129150.5 | AH9: =AD9*1.05 -> 135363.31 | AI9: =AE9*1.05 -> 139507.17 | AJ9: =AF9*1.05 -> 131218.32 | AK9: =AG9*1.05 -> 135608.03 | AL9: =AH9*1.05 -> 142131.48 | ... BG9: =BC9*1.05 -> 186952.96 | BN9: 86716 | BO9: =IF(ISBLANK(BN9),"",INDEX($A9:$BH9,1,MATCH(BN$3,$A$3:$BH$3,0))-BN9) -> -12111 | BP9: 87873 | BQ9: =IF(ISBLANK(BP9),"",INDEX($A9:$BH9,1,MATCH(BP$3,$A$3:$BH$3,0))-BP9) -> 0
A10: RevTotal Revenue | B10: Total Revenue | C10: USDk | D10: 3960645 | E10: 4404499 | F10: 4515541 | G10: 4650902 | H10: 4990131 | I10: 5534957 | J10: 5617493 | K10: 5773042 | L10: 5957128 | M10: 6155563 | N10: 5975801 | O10: 6032561 | P10: 5771796 | Q10: 6054457 | R10: 6114952 | S10: =SUM(S7:S9) -> 6048701.7 | T10: =SUM(T7:T9) -> 6529055.6 | U10: =SUM(U7:U9) -> 7008071 | V10: =SUM(V7:V9) -> 6960149.1 | W10: =SUM(W7:W9) -> 6886252.5 | X10: =SUM(X7:X9) -> 7422220.3 | Y10: =SUM(Y7:Y9) -> 7960996 | Z10: =SUM(Z7:Z9) -> 7905629.3 | ... BG10: =SUM(BG7:BG9) -> 20900117 | BN10: 6980851.5 | BO10: =IF(ISBLANK(BN10),"",INDEX($A10:$BH10,1,MATCH(BN$3,$A$3:$BH$3,0))-BN10) -> -865899.46 | BP10: 7113882.5 | BQ10: =IF(ISBLANK(BP10),"",INDEX($A10:$BH10,1,MATCH(BP$3,$A$3:$BH$3,0))-BP10) -> -1065180.8
B11: Growth | C11: % YoY | G11: 0.14 | H11: 0.26 | I11: 0.257 | J11: 0.244 | K11: 0.241 | L11: 0.194 | M11: 0.112 | N11: 0.064 | O11: 0.045 | P11: -0.031 | Q11: =Q10/M10-1 -> -0.016425143 | R11: =R10/N10-1 -> 0.023285749 | S11: =S10/O10-1 -> 0.0026755959 | T11: =T10/P10-1 -> 0.13119999 | U11: =U10/Q10-1 -> 0.15750611 | V11: =V10/R10-1 -> 0.1382181 | W11: =W10/S10-1 -> 0.13846786 | X11: =X10/T10-1 -> 0.13679847 | ... BG11: =BG10/BC10-1 -> 0.13302115 | BN11: 0.16818673 | BO11: =IF(ISBLANK(BN11),"",INDEX($A11:$BH11,1,MATCH(BN$3,$A$3:$BH$3,0))-BN11) -> -0.14490099 | BP11: 0.17924751 | BQ11: =IF(ISBLANK(BP11),"",INDEX($A11:$BH11,1,MATCH(BP$3,$A$3:$BH$3,0))-BP11) -> -0.17657191
BO12: =IF(ISBLANK(BN12),"",INDEX($A12:$BH12,1,MATCH(BN$3,$A$3:$BH$3,0))-BN12) | BQ12: =IF(ISBLANK(BP12),"",INDEX($A12:$BH12,1,MATCH(BP$3,$A$3:$BH$3,0))-BP12)
B13: Gross Profit (GAAP) | BO13: =IF(ISBLANK(BN13),"",INDEX($A13:$BH13,1,MATCH(BN$3,$A$3:$BH$3,0))-BN13) | BQ13: =IF(ISBLANK(BP13),"",INDEX($A13:$BH13,1,MATCH(BP$3,$A$3:$BH$3,0))-BP13)
A14: GP-Square | B14: Square | D14: 615081 | E14: 680615 | F14: 708103 | G14: 703103 | H14: 691561 | I14: 804033 | J14: 805338 | K14: 827717 | L14: 820272 | M14: 922584 | N14: 932356 | O14: 923700 | P14: 897899 | Q14: 1026811 | R14: =R154 -> 1017660 | S14: =S154 -> 1021766.9 | T14: =T154 -> 1000056.6 | U14: =U154 -> 1148978 | V14: =V154 -> 1177498.3 | W14: =W154 -> 1176680.6 | X14: =X154 -> 1144621.2 | Y14: =Y154 -> 1314541.8 | ... BG14: =BG154 -> 3880171.9 | BN14: 1031672.8 | BO14: =IF(ISBLANK(BN14),"",INDEX($A14:$BH14,1,MATCH(BN$3,$A$3:$BH$3,0))-BN14) -> -14012.768 | BP14: 1034858.5 | BQ14: =IF(ISBLANK(BP14),"",INDEX($A14:$BH14,1,MATCH(BP$3,$A$3:$BH$3,0))-BP14) -> -13091.633
A15: GP-Cash App | B15: Cash App | D15: 669800 | E15: 779717 | F15: 849335 | G15: 946190 | H15: 1009954 | I15: 1052285 | J15: 1077490 | K15: 1183734 | L15: 1258527 | M15: 1298944 | N15: 1305943 | O15: 1375597 | P15: 1379951 | Q15: 1500500 | R15: =R197 -> 1623953 | S15: =S197 -> 1779802.9 | T15: =T197 -> 1853208.2 | U15: =U197 -> 1923627.1 | V15: =V197 -> 1931327.4 | W15: =W197 -> 2116969.7 | X15: =X197 -> 2195868.9 | Y15: =Y197 -> 2281007.4 | ... BG15: =BG197 -> 8514019.1 | BN15: 1561340 | BO15: =IF(ISBLANK(BN15),"",INDEX($A15:$BH15,1,MATCH(BN$3,$A$3:$BH$3,0))-BN15) -> 62612.95 | BP15: 1701758.1 | BQ15: =IF(ISBLANK(BP15),"",INDEX($A15:$BH15,1,MATCH(BP$3,$A$3:$BH$3,0))-BP15) -> 78044.828
A16: GP-Corporate & Other | B16: Corporate & Other | D16: 10080 | E16: 9316 | F16: 9651 | G16: 10902 | H16: 13069 | I16: 9783 | J16: 15622 | K16: 14301 | L16: 15674 | M16: 11952 | N16: 11386 | O16: 12101 | P16: 11753 | Q16: 9219 | R16: =R17-R14-R15 -> 19957 | S16: 32706 | T16: 32341 | U16: 29680 | V16: 40627 | W16: 41493 | X16: 40606 | Y16: 38222 | Z16: 51033 | AA16: 52038 | AB16: 50524 | AC16: 48472 | AD16: 63520 | AE16: 54640 | AF16: 53050 | AG16: 50895 | AH16: 66696 | AI16: 57372 | AJ16: 55703 | AK16: 53440 | AL16: 70031 | AM16: 60241 | AN16: 58488 | AO16: 56112 | AP16: 73532 | AQ16: 63253 | AR16: 61412 | AS16: 58918 | AT16: 77209 | AU16: 66415 | AV16: 64483 | AW16: 61863 | AX16: 81069 | AY16: 69736 | AZ16: 67707 | BA16: 64957 | BB16: 85123 | BC16: 73223 | BD16: 71092 | BE16: 68204 | BF16: 89379 | BG16: 76884 | BN16: 31955 | BO16: =IF(ISBLANK(BN16),"",INDEX($A16:$BH16,1,MATCH(BN$3,$A$3:$BH$3,0))-BN16) -> -11998 | BP16: 32706 | BQ16: =IF(ISBLANK(BP16),"",INDEX($A16:$BH16,1,MATCH(BP$3,$A$3:$BH$3,0))-BP16) -> 0
A17: GP-Total Gross Profit | B17: Total Gross Profit | C17: USDk | D17: 1294960 | E17: 1469648 | F17: 1567089 | G17: 1660195 | H17: 1714584 | I17: 1866101 | J17: 1898449 | K17: 2025752 | L17: 2094473 | M17: 2233480 | N17: 2249685 | O17: 2311398 | P17: 2289603 | Q17: 2536530 | R17: 2661570 | S17: =SUM(S14:S16) -> 2834275.8 | T17: =SUM(T14:T16) -> 2885605.8 | U17: =SUM(U14:U16) -> 3102285.1 | V17: =SUM(V14:V16) -> 3149452.8 | W17: =SUM(W14:W16) -> 3335143.4 | X17: =SUM(X14:X16) -> 3381096 | Y17: =SUM(Y14:Y16) -> 3633771.3 | Z17: =SUM(Z14:Z16) -> 3691117.2 | ... BG17: =SUM(BG14:BG16) -> 12471075 | BI17: 981660 | BJ17: 1107884 | BK17: 1178649 | BL17: 1239746 | BN17: 2624967.8 | BO17: =IF(ISBLANK(BN17),"",INDEX($A17:$BH17,1,MATCH(BN$3,$A$3:$BH$3,0))-BN17) -> 36602.182 | BP17: 2769322.6 | BQ17: =IF(ISBLANK(BP17),"",INDEX($A17:$BH17,1,MATCH(BP$3,$A$3:$BH$3,0))-BP17) -> 64953.195
B18: Growth | C18: % YoY | D18: 0.344 | E18: 0.288 | F18: 0.383 | G18: 0.405 | H18: 0.324 | I18: 0.27 | J18: 0.211 | K18: 0.22 | L18: 0.222 | M18: 0.197 | N18: 0.185 | O18: 0.141 | P18: 0.093 | Q18: =Q17/M17-1 -> 0.13568512 | R18: =R17/N17-1 -> 0.18308563 | S18: =S17/O17-1 -> 0.22621712 | T18: =T17/P17-1 -> 0.26030836 | U18: =U17/Q17-1 -> 0.22304292 | V18: =V17/R17-1 -> 0.18330638 | W18: =W17/S17-1 -> 0.176718 | X18: =X17/T17-1 -> 0.17171099 | ... BG18: =BG17/BC17-1 -> 0.16446243 | BN18: 0.16681572 | BO18: =IF(ISBLANK(BN18),"",INDEX($A18:$BH18,1,MATCH(BN$3,$A$3:$BH$3,0))-BN18) -> 0.016269914 | BP18: 0.19811586 | BQ18: =IF(ISBLANK(BP18),"",INDEX($A18:$BH18,1,MATCH(BP$3,$A$3:$BH$3,0))-BP18) -> 0.02810126
B19: GP Margin | C19: % Mgn | D19: 0.327 | E19: 0.334 | F19: 0.347 | G19: 0.357 | H19: 0.344 | I19: 0.337 | J19: 0.338 | K19: 0.351 | L19: 0.352 | M19: 0.363 | N19: 0.376 | O19: 0.383 | P19: 0.397 | Q19: =Q17/Q$10 -> 0.41895252 | R19: =R17/R$10 -> 0.43525607 | S19: =S17/S$10 -> 0.46857589 | T19: =T17/T$10 -> 0.44196374 | U19: =U17/U$10 -> 0.44267318 | V19: =V17/V$10 -> 0.45249789 | W19: =W17/W$10 -> 0.48431907 | X19: =X17/X$10 -> 0.45553701 | ... BG19: =BG17/BG$10 -> 0.5966988 | BN19: 0.37602402 | BO19: =IF(ISBLANK(BN19),"",INDEX($A19:$BH19,1,MATCH(BN$3,$A$3:$BH$3,0))-BN19) -> 0.059232055 | BP19: 0.38928427 | BQ19: =IF(ISBLANK(BP19),"",INDEX($A19:$BH19,1,MATCH(BP$3,$A$3:$BH$3,0))-BP19) -> 0.079291618
B20: Guidance | P20: 2320000 | Q20: 2450000 | R20: 2600000 | S20: 2755000 | BN20: 2600000 | BO20: =IF(ISBLANK(BN20),"",INDEX($A20:$BH20,1,MATCH(BN$3,$A$3:$BH$3,0))-BN20) -> 0 | BP20: 2743867 | BQ20: =IF(ISBLANK(BP20),"",INDEX($A20:$BH20,1,MATCH(BP$3,$A$3:$BH$3,0))-BP20) -> 11133
T21: =SUM(T23:T26)/SUM(P23:P26)-1 -> 0.21849251 | U21: =SUM(U23:U26)/SUM(Q23:Q26)-1 -> 0.15879335 | V21: =SUM(V23:V26)/SUM(R23:R26)-1 -> 0.087883982 | W21: =SUM(W23:W26)/SUM(S23:S26)-1 -> 0.12673971 | X21: =SUM(X23:X26)/SUM(T23:T26)-1 -> 0.13684165 | Y21: =SUM(Y23:Y26)/SUM(U23:U26)-1 -> 0.13658034 | AU21: =AU15/AQ15-1 -> 0.16565282 | AV21: =AV15/AR15-1 -> 0.15717563 | AW21: =AW15/AS15-1 -> 0.16038724 | AX21: =AX15/AT15-1 -> 0.16050308 | AY21: =AY15/AU15-1 -> 0.16837325 | AZ21: =AZ15/AV15-1 -> 0.15951206 | BA21: =BA15/AW15-1 -> 0.16288524 | BB21: =BB15/AX15-1 -> 0.16300716 | ... BG21: =BG15/BC15-1 -> 0.17409899 | BO21: =IF(ISBLANK(BN21),"",INDEX($A21:$BH21,1,MATCH(BN$3,$A$3:$BH$3,0))-BN21) | BQ21: =IF(ISBLANK(BP21),"",INDEX($A21:$BH21,1,MATCH(BP$3,$A$3:$BH$3,0))-BP21)
B22: Operating Expenses (Non- GAAP) | L22: Changed reporting of share based comp from 1Q25 | BO22: =IF(ISBLANK(BN22),"",INDEX($A22:$BH22,1,MATCH(BN$3,$A$3:$BH$3,0))-BN22) | BQ22: =IF(ISBLANK(BP22),"",INDEX($A22:$BH22,1,MATCH(BP$3,$A$3:$BH$3,0))-BP22)
A23: Opex-Non-GAAP product development | B23: Non-GAAP product development | D23: 286317 | E23: 311956 | F23: 331250 | G23: 381647 | H23: 398219 | I23: 429444 | J23: 430462 | K23: 410587 | L23: 716070 | M23: 713163 | N23: 710983 | O23: 708912 | P23: 723539 | Q23: 725288 | R23: 711235 | S23: =O23*(1+S33) -> 723090.24 | T23: =P23*(1+T33) -> 738009.78 | U23: =Q23*(1+U33) -> 739793.76 | V23: =R23*(1+V33) -> 725459.7 | W23: =S23*(1+W33) -> 737552.04 | X23: =T23*(1+X33) -> 767530.17 | Y23: =U23*(1+Y33) -> 769385.51 | Z23: =V23*(1+Z33) -> 754478.09 | ... BG23: =BC23*(1+BG33) -> 1049766.5 | BN23: 725202.66 | BO23: =IF(ISBLANK(BN23),"",INDEX($A23:$BH23,1,MATCH(BN$3,$A$3:$BH$3,0))-BN23) -> -13967.66 | BP23: 723090.24 | BQ23: =IF(ISBLANK(BP23),"",INDEX($A23:$BH23,1,MATCH(BP$3,$A$3:$BH$3,0))-BP23) -> 0
A24: Opex-Non-GAAP sales and marketing | B24: Non-GAAP sales and marketing | D24: 478395 | E24: 504176 | F24: 455951 | G24: 507757 | H24: 465188 | I24: 502847 | J24: 441733 | K24: 469991 | L24: 442807 | M24: 507562 | N24: 511755 | O24: 520938 | P24: 491910 | Q24: 549731 | R24: 599333 | S24: =O24*(1+S34) -> 609497.46 | T24: =P24*(1+T34) -> 590292 | U24: =Q24*(1+U34) -> 636316.99 | V24: =R24*(1+V34) -> 682171.67 | W24: =S24*(1+W34) -> 693893.27 | X24: =T24*(1+X34) -> 671043.04 | Y24: =U24*(1+Y34) -> 722840.43 | Z24: =V24*(1+Z34) -> 774839.2 | ... BG24: =BC24*(1+BG34) -> 2106000.4 | BN24: 597825.4 | BO24: =IF(ISBLANK(BN24),"",INDEX($A24:$BH24,1,MATCH(BN$3,$A$3:$BH$3,0))-BN24) -> 1507.5976 | BP24: 614314.84 | BQ24: =IF(ISBLANK(BP24),"",INDEX($A24:$BH24,1,MATCH(BP$3,$A$3:$BH$3,0))-BP24) -> -4817.3789
A25: Opex-Non-GAAP general and administrative | B25: Non-GAAP general and administrative | D25: 251616 | E25: 312949 | F25: 311972 | G25: 343190 | H25: 362301 | I25: 377456 | J25: 378961 | K25: 414884 | L25: 423630 | M25: 439414 | N25: 408553 | O25: 450602 | P25: 452870 | Q25: 449237 | R25: 543974 | S25: =O25*(1+S35) -> 468626.08 | T25: =P25*(1+T35) -> 470984.8 | U25: =Q25*(1+U35) -> 467206.48 | V25: =R25*(1+V35) -> 489576.6 | W25: =S25*(1+W35) -> 487371.12 | X25: =T25*(1+X35) -> 489824.19 | Y25: =U25*(1+Y35) -> 485894.74 | Z25: =V25*(1+Z35) -> 509159.66 | ... BG25: =BC25*(1+BG35) -> 693681.08 | BN25: 449408.3 | BO25: =IF(ISBLANK(BN25),"",INDEX($A25:$BH25,1,MATCH(BN$3,$A$3:$BH$3,0))-BN25) -> 94565.7 | BP25: 459614.04 | BQ25: =IF(ISBLANK(BP25),"",INDEX($A25:$BH25,1,MATCH(BP$3,$A$3:$BH$3,0))-BP25) -> 9012.04
A26: Opex- GAAP Transaction, loan, and consumer receivable losses | B26: GAAP Transaction, loan, and consumer receivable losses | D26: 91150 | E26: 156697 | F26: 147586 | G26: 155250 | H26: 127896 | I26: 179771 | J26: 177338 | K26: 175658 | L26: 165729 | M26: 191812 | N26: 192062 | O26: 244618 | P26: 169689 | Q26: 294090 | R26: 363455 | S26: =O26*(1+S36) -> 440312.4 | T26: =S26 -> 440312.4 | U26: =(U196-Q196)*0.75/0.05*0.03+Q26*(1+U11) -> 495528.68 | V26: =(V196-R196)*0.75/0.05*0.03+R26*(1+V11) -> 515715.44 | W26: =(W196-S196)*0.75/0.05*0.03+S26*(1+W11) -> 606800.13 | X26: =(X196-T196)*0.75/0.05*0.03+T26*(1+X11) -> 617672 | Y26: =(Y196-U196)*0.75/0.05*0.03+U26*(1+Y11) -> 680165.61 | Z26: =(Z196-V196)*0.75/0.05*0.03+V26*(1+Z11) -> 704012.65 | AA26: =(AA196-W196)*0.75/0.05*0.03+W26*(1+AA11) -> 811671.9 | AB26: =(AB196-X196)*0.75/0.05*0.03+X26*(1+AB11) -> 829383.07 | ... BG26: =(BG196-BC196)*0.75/0.05*0.03+BC26*(1+BG11) -> 4136221 | BI26: 90316 | BJ26: 108053 | BK26: 104535 | BL26: 113460 | BN26: 364917.8 | BO26: =IF(ISBLANK(BN26),"",INDEX($A26:$BH26,1,MATCH(BN$3,$A$3:$BH$3,0))-BN26) -> -1462.8 | BP26: 391388.8 | BQ26: =IF(ISBLANK(BP26),"",INDEX($A26:$BH26,1,MATCH(BP$3,$A$3:$BH$3,0))-BP26) -> 48923.6
B27: Share-based payments | L27: -304358 | M27: -320187 | N27: -324055 | O27: -315532 | P27: -304730 | Q27: -297246 | R27: -307721 | S27: =R27 -> -307721 | T27: =SUM(T23:T26)/SUM(P23:P26)*P27 -> -371311.22 | U27: =SUM(U23:U26)/SUM(Q23:Q26)*Q27 -> -344446.69 | V27: =SUM(V23:V26)/SUM(R23:R26)*R27 -> -334764.75 | W27: =SUM(W23:W26)/SUM(S23:S26)*S27 -> -346721.47 | X27: =SUM(X23:X26)/SUM(T23:T26)*T27 -> -422122.06 | Y27: =SUM(Y23:Y26)/SUM(U23:U26)*U27 -> -391491.33 | Z27: =SUM(Z23:Z26)/SUM(V23:V26)*V27 -> -380488.18 | AA27: =SUM(AA23:AA26)/SUM(W23:W26)*W27 -> -394542.55 | ... BG27: =SUM(BG23:BG26)/SUM(BC23:BC26)*BC27 -> -1096287.9 | BN27: -297246 | BO27: =IF(ISBLANK(BN27),"",INDEX($A27:$BH27,1,MATCH(BN$3,$A$3:$BH$3,0))-BN27) -> -10475 | BP27: -297246 | BQ27: =IF(ISBLANK(BP27),"",INDEX($A27:$BH27,1,MATCH(BP$3,$A$3:$BH$3,0))-BP27) -> -10475
A28: Opex-Other | B28: Other | D28: -7879 | E28: -3472 | F28: -7030 | G28: -8550 | H28: -7387 | I28: -7819 | J28: -7533 | K28: -7531 | L28: -54479 | M28: -57760 | N28: -57085 | O28: -55149 | P28: -56469 | Q28: -75992 | R28: =R29-SUM(R23:R27) -> -81368 | S28: =O28*(1+S11) -> -55296.556 | T28: =P28*(1+T11) -> -63877.732 | U28: =Q28*(1+U11) -> -87961.204 | V28: =R28*(1+V11) -> -92614.531 | W28: =S28*(1+W11) -> -62953.352 | X28: =T28*(1+X11) -> -72616.108 | Y28: =U28*(1+Y11) -> -99921.762 | Z28: =V28*(1+Z11) -> -105195.47 | ... BG28: =BC28*(1+BG11) -> -191066.54 | BN28: -66685.94 | BO28: =IF(ISBLANK(BN28),"",INDEX($A28:$BH28,1,MATCH(BN$3,$A$3:$BH$3,0))-BN28) -> -14682.06 | BP28: -65034.321 | BQ28: =IF(ISBLANK(BP28),"",INDEX($A28:$BH28,1,MATCH(BP$3,$A$3:$BH$3,0))-BP28) -> 9737.7644
A29: Opex-Total Operating Expenses (Non-GAAP) | B29: Total Operating Expenses (Non-GAAP) | D29: 1099599 | E29: 1282306 | F29: 1239729 | G29: 1379294 | H29: 1346217 | I29: 1481699 | J29: 1420961 | K29: 1463589 | L29: 1389399 | M29: 1474004 | N29: 1442213 | O29: 1554389 | P29: =P17-P42 -> 1476809 | Q29: =Q17-Q42 -> 1645108 | R29: =R17-R42 -> 1828908 | S29: =SUM(S23:S28) -> 1878508.6 | T29: =SUM(T23:T28) -> 1804410 | U29: =SUM(U23:U28) -> 1906438 | V29: =SUM(V23:V28) -> 1985544.1 | W29: =SUM(W23:W28) -> 2115941.7 | X29: =SUM(X23:X28) -> 2051331.2 | Y29: =SUM(Y23:Y28) -> 2166873.2 | Z29: =SUM(Z23:Z28) -> 2256806 | ... BG29: =SUM(BG23:BG28) -> 6698314.6 | BN29: 1773422.2 | BO29: =IF(ISBLANK(BN29),"",INDEX($A29:$BH29,1,MATCH(BN$3,$A$3:$BH$3,0))-BN29) -> 55485.777 | BP29: 1826127.6 | BQ29: =IF(ISBLANK(BP29),"",INDEX($A29:$BH29,1,MATCH(BP$3,$A$3:$BH$3,0))-BP29) -> 52381.026
B30: % of GP | C30: % | D30: =D29/D$17 -> 0.84913743 | E30: =E29/E$17 -> 0.87252594 | F30: =F29/F$17 -> 0.79110312 | G30: =G29/G$17 -> 0.83080241 | H30: =H29/H$17 -> 0.78515663 | I30: =I29/I$17 -> 0.79400793 | J30: =J29/J$17 -> 0.74848521 | K30: =K29/K$17 -> 0.7224917 | ... BG30: =BG29/BG$17 -> 0.53710804 | BN30: 0.6755977 | BO30: =IF(ISBLANK(BN30),"",INDEX($A30:$BH30,1,MATCH(BN$3,$A$3:$BH$3,0))-BN30) -> 0.011556122 | BP30: 0.6594131 | BQ30: =IF(ISBLANK(BP30),"",INDEX($A30:$BH30,1,MATCH(BP$3,$A$3:$BH$3,0))-BP30) -> 0.0033694808
BO31: =IF(ISBLANK(BN31),"",INDEX($A31:$BH31,1,MATCH(BN$3,$A$3:$BH$3,0))-BN31) | BQ31: =IF(ISBLANK(BP31),"",INDEX($A31:$BH31,1,MATCH(BP$3,$A$3:$BH$3,0))-BP31)
B32: Operating Expenses growth | BO32: =IF(ISBLANK(BN32),"",INDEX($A32:$BH32,1,MATCH(BN$3,$A$3:$BH$3,0))-BN32) | BQ32: =IF(ISBLANK(BP32),"",INDEX($A32:$BH32,1,MATCH(BP$3,$A$3:$BH$3,0))-BP32)
B33: Non-GAAP product development | C33: % YoY | D33: 0.41 | E33: 0.541 | F33: 0.536 | G33: 0.601 | H33: 0.391 | I33: 0.377 | J33: 0.3 | K33: 0.076 | L33: 0.159 | M33: 0.033 | N33: 0.028 | O33: 0.087 | P33: 0.01 | Q33: =Q23/M23-1 -> 0.017001723 | R33: =R23/N23-1 -> 0.00035443885 | S33: 0.02 | T33: 0.02 | U33: 0.02 | V33: 0.02 | W33: 0.02 | X33: 0.04 | Y33: 0.04 | Z33: 0.04 | AA33: 0.04 | AB33: 0.04 | AC33: 0.04 | AD33: 0.04 | AE33: 0.04 | AF33: 0.04 | AG33: 0.04 | AH33: 0.04 | AI33: 0.04 | AJ33: 0.04 | AK33: 0.04 | AL33: 0.04 | AM33: 0.04 | AN33: 0.04 | AO33: 0.04 | AP33: 0.04 | AQ33: 0.04 | AR33: 0.04 | AS33: 0.04 | AT33: 0.04 | AU33: 0.04 | AV33: 0.04 | AW33: 0.04 | AX33: 0.04 | AY33: 0.04 | AZ33: 0.04 | BA33: 0.04 | BB33: 0.04 | BC33: 0.04 | BD33: 0.04 | BE33: 0.04 | BF33: 0.04 | BG33: 0.04 | BH33: 0.045 | BN33: 0.02 | BO33: =IF(ISBLANK(BN33),"",INDEX($A33:$BH33,1,MATCH(BN$3,$A$3:$BH$3,0))-BN33) -> -0.019645561 | BP33: 0.02 | BQ33: =IF(ISBLANK(BP33),"",INDEX($A33:$BH33,1,MATCH(BP$3,$A$3:$BH$3,0))-BP33) -> 0
B34: Non-GAAP sales and marketing | C34: % YoY | D34: 0.418 | E34: 0.41 | F34: 0.16 | G34: 0.087 | H34: -0.028 | I34: -0.003 | J34: -0.031 | K34: -0.074 | L34: -0.115 | M34: -0.057 | N34: 0.077 | O34: 0.036 | P34: 0.111 | Q34: =Q24/M24-1 -> 0.083081476 | R34: =R24/N24-1 -> 0.17113267 | S34: 0.17 | T34: 0.2 | U34: =U11 -> 0.15750611 | V34: =V11 -> 0.1382181 | W34: =W11 -> 0.13846786 | X34: =X11 -> 0.13679847 | Y34: =Y11 -> 0.13597537 | Z34: =Z11 -> 0.13584194 | AA34: =AA11 -> 0.13614981 | AB34: =AB11 -> 0.13740374 | ... BG34: =BG11 -> 0.13302115 | BN34: 0.16818673 | BO34: =IF(ISBLANK(BN34),"",INDEX($A34:$BH34,1,MATCH(BN$3,$A$3:$BH$3,0))-BN34) -> 0.0029459362 | BP34: 0.17924751 | BQ34: =IF(ISBLANK(BP34),"",INDEX($A34:$BH34,1,MATCH(BP$3,$A$3:$BH$3,0))-BP34) -> -0.0092475091
B35: Non-GAAP general and administrative | C35: % YoY | D35: 0.48 | E35: 0.791 | F35: 0.353 | G35: 0.43 | H35: 0.44 | I35: 0.206 | J35: 0.215 | K35: 0.209 | L35: -0.013 | M35: -0.017 | N35: -0.107 | O35: -0.08 | P35: 0.069 | Q35: =Q25/M25-1 -> 0.022354772 | R35: =R25/N25-1 -> 0.33146495 | S35: 0.04 | T35: 0.04 | U35: 0.04 | V35: -0.1 | W35: 0.04 | X35: 0.04 | Y35: 0.04 | Z35: 0.04 | AA35: 0.04 | AB35: 0.04 | AC35: 0.04 | AD35: 0.04 | AE35: 0.04 | AF35: 0.04 | AG35: 0.04 | AH35: 0.04 | AI35: 0.04 | AJ35: 0.04 | AK35: 0.04 | AL35: 0.04 | AM35: 0.04 | AN35: 0.04 | AO35: 0.04 | AP35: 0.04 | AQ35: 0.04 | AR35: 0.04 | AS35: 0.04 | AT35: 0.04 | AU35: 0.04 | AV35: 0.04 | AW35: 0.04 | AX35: 0.04 | AY35: 0.04 | AZ35: 0.04 | BA35: 0.04 | BB35: 0.04 | BC35: 0.04 | BD35: 0.04 | BE35: 0.04 | BF35: 0.04 | BG35: 0.04 | BN35: 0.1 | BO35: =IF(ISBLANK(BN35),"",INDEX($A35:$BH35,1,MATCH(BN$3,$A$3:$BH$3,0))-BN35) -> 0.23146495 | BP35: 0.02 | BQ35: =IF(ISBLANK(BP35),"",INDEX($A35:$BH35,1,MATCH(BP$3,$A$3:$BH$3,0))-BP35) -> 0.02
B36: GAAP Transaction, loan, and consumer receivable losses | D36: 3.469 | E36: 2.253 | F36: 1.369 | G36: 1.718 | H36: 0.403 | I36: 0.147 | J36: 0.202 | K36: 0.131 | L36: 0.296 | M36: 0.067 | N36: 0.083 | O36: 0.393 | P36: 0.024 | Q36: =Q26/M26-1 -> 0.53322003 | R36: =R26/N26-1 -> 0.89238371 | S36: 0.8 | T36: =T26/P26-1 -> 1.5948199 | U36: =U26/Q26-1 -> 0.6849559 | V36: =V26/R26-1 -> 0.41892514 | W36: =W26/S26-1 -> 0.37811274 | X36: =X26/T26-1 -> 0.402804 | Y36: =Y26/U26-1 -> 0.37260593 | Z36: =Z26/V26-1 -> 0.36511843 | AA36: =AA26/W26-1 -> 0.33762645 | ... BG36: =BG26/BC26-1 -> 0.20349025 | BN36: 0.9 | BO36: =IF(ISBLANK(BN36),"",INDEX($A36:$BH36,1,MATCH(BN$3,$A$3:$BH$3,0))-BN36) -> -0.0076162906 | BP36: 0.6 | BQ36: =IF(ISBLANK(BP36),"",INDEX($A36:$BH36,1,MATCH(BP$3,$A$3:$BH$3,0))-BP36) -> 0.2
