Workbook

Sheet Value
B2: DCF Valuation
B4: Current Share Price (NZD) | C4: 7.91
B5: Shares Outstanding (#m) | C5: =Annual!G79 -> 146.53
B6: Market Cap (NZDm) | C6: =C4*C5 -> 1159.0523
B7: Net Debt (NZDm) | C7: =Annual!F131 -> 232.3
B8: Market EV (NZDm) | C8: =C6+C7 -> 1391.3523
B9: Valuation Date | C9: 46022
B11: WACC Inputs
B12: Risk-free Rate | C12: 0.04
B13: Equity Risk Premium | C13: 0.06
B14: Beta | C14: 1
B15: Cost of Equity | C15: =C12+C13*C14 -> 0.1
B16: Pre-tax Cost of Debt | C16: 0.06
B17: Tax Rate | C17: 0.28
B18: After-tax Cost of Debt | C18: =C16*(1-C17) -> 0.0432
B19: Debt Weight (D/(D+E)) | C19: 0.3
B20: WACC | C20: =C15*(1-C19)+C18*C19 -> 0.08296
B21: Terminal Growth Rate | C21: 0.025
B22: Stub Period | C22: =(Annual!G4-C9)/365.25 -> 0.49555099
B24: FCF Projection | D24: FY26E | E24: FY27E | F24: FY28E | G24: FY29E | H24: FY30E | I24: FY31E | J24: FY32E | K24: FY33E | L24: FY34E | M24: FY35E
B25: EBITDA | C25: NZDm | D25: =Annual!G38 -> 134.80708 | E25: =Annual!H38 -> 157.62309 | F25: =Annual!I38 -> 172.77767 | G25: =Annual!J38 -> 188.93631 | H25: =Annual!K38 -> 206.15894 | I25: =Annual!L38 -> 224.50898 | J25: =Annual!M38 -> 244.05344 | K25: =Annual!N38 -> 264.86321 | ... M25: =Annual!P38 -> 310.58269
B26: less D&A | C26: NZDm | D26: =Annual!G50 -> -52.837036 | E26: =Annual!H50 -> -54.612869 | F26: =Annual!I50 -> -55.881845 | G26: =Annual!J50 -> -57.216272 | H26: =Annual!K50 -> -58.620468 | I26: =Annual!L50 -> -60.098911 | J26: =Annual!M50 -> -61.656251 | K26: =Annual!N50 -> -63.297335 | ... M26: =Annual!P50 -> -66.8512
B27: EBIT | C27: NZDm | D27: =Annual!G54 -> 81.970047 | E27: =Annual!H54 -> 103.01022 | F27: =Annual!I54 -> 116.89583 | G27: =Annual!J54 -> 131.72004 | H27: =Annual!K54 -> 147.53848 | I27: =Annual!L54 -> 164.41007 | J27: =Annual!M54 -> 182.39719 | K27: =Annual!N54 -> 201.56588 | ... M27: =Annual!P54 -> 243.73149
B28: less Tax on EBIT | C28: NZDm | D28: =-D27*$C$17 -> -22.951613 | E28: =-E27*$C$17 -> -28.842861 | F28: =-F27*$C$17 -> -32.730832 | G28: =-G27*$C$17 -> -36.88161 | H28: =-H27*$C$17 -> -41.310773 | I28: =-I27*$C$17 -> -46.034819 | J28: =-J27*$C$17 -> -51.071213 | K28: =-K27*$C$17 -> -56.438446 | ... M28: =-M27*$C$17 -> -68.244818
B29: NOPAT | C29: NZDm | D29: =D27+D28 -> 59.018434 | E29: =E27+E28 -> 74.167356 | F29: =F27+F28 -> 84.164997 | G29: =G27+G28 -> 94.838426 | H29: =H27+H28 -> 106.2277 | I29: =I27+I28 -> 118.37525 | J29: =J27+J28 -> 131.32598 | K29: =K27+K28 -> 145.12743 | ... M29: =M27+M28 -> 175.48667
B30: plus D&A | C30: NZDm | D30: =-D26 -> 52.837036 | E30: =-E26 -> 54.612869 | F30: =-F26 -> 55.881845 | G30: =-G26 -> 57.216272 | H30: =-H26 -> 58.620468 | I30: =-I26 -> 60.098911 | J30: =-J26 -> 61.656251 | K30: =-K26 -> 63.297335 | ... M30: =-M26 -> 66.8512
B31: less Capex | C31: NZDm | D31: =Annual!G160+Annual!G162 -> -24.161453 | E31: =Annual!H160+Annual!H162 -> -26.252216 | F31: =Annual!I160+Annual!I162 -> -27.715777 | G31: =Annual!J160+Annual!J162 -> -29.260932 | H31: =Annual!K160+Annual!K162 -> -30.892228 | I31: =Annual!L160+Annual!L162 -> -32.61447 | J31: =Annual!M160+Annual!M162 -> -34.432727 | K31: =Annual!N160+Annual!N162 -> -36.352351 | ... M31: =Annual!P160+Annual!P162 -> -40.518624
B32: less WC Change | C32: NZDm | D32: =Annual!G149 -> -43.177045 | E32: =Annual!H149 -> -31.54794 | F32: =Annual!I149 -> -22.083968 | G32: =Annual!J149 -> -23.315149 | H32: =Annual!K149 -> -24.614969 | I32: =Annual!L149 -> -25.987253 | J32: =Annual!M149 -> -27.436043 | K32: =Annual!N149 -> -28.965602 | ... M32: =Annual!P149 -> -32.285294
B33: FCFF | C33: NZDm | D33: =D29+D30+D31+D32 -> 44.516971 | E33: =E29+E30+E31+E32 -> 70.980068 | F33: =F29+F30+F31+F32 -> 90.247097 | G33: =G29+G30+G31+G32 -> 99.478618 | H33: =H29+H30+H31+H32 -> 109.34097 | I33: =I29+I30+I31+I32 -> 119.87244 | J33: =J29+J30+J31+J32 -> 131.11346 | K33: =K29+K30+K31+K32 -> 143.10681 | ... M33: =M29+M30+M31+M32 -> 169.53396
B34: Normalised FCFF (capex=D&A) | C34: NZDm | M34: =M29+M32 -> 143.20138
B35: Terminal Value | M35: =M34*(1+$C$21)/($C$20-$C$21) -> 2532.4606
B37: Discount Factor | D37: =1/(1+$C$20)^($C$22+0) -> 0.9612753 | E37: =1/(1+$C$20)^($C$22+1) -> 0.88763694 | F37: =1/(1+$C$20)^($C$22+2) -> 0.81963963 | G37: =1/(1+$C$20)^($C$22+3) -> 0.75685125 | H37: =1/(1+$C$20)^($C$22+4) -> 0.69887277 | I37: =1/(1+$C$20)^($C$22+5) -> 0.64533572 | J37: =1/(1+$C$20)^($C$22+6) -> 0.59589987 | K37: =1/(1+$C$20)^($C$22+7) -> 0.55025104 | L37: =1/(1+$C$20)^($C$22+8) -> 0.50809914 | M37: =1/(1+$C$20)^($C$22+9) -> 0.46917627
B38: PV of FCFF | D38: =D33*D37 -> 42.793065 | E38: =E33*E37 -> 63.004531 | F38: =F33*F37 -> 73.970098 | G38: =G33*G37 -> 75.290517 | H38: =H33*H37 -> 76.415429 | I38: =I33*I37 -> 77.357964 | J38: =J33*J37 -> 78.130492 | K38: =K33*K37 -> 78.744673 | ... M38: =M33*M37 -> 79.54131
B39: PV of Terminal Value | M39: =M35*M37 -> 1188.1704
B41: Sum of PV of FCFs | C41: =SUM(D38:M38) -> 724.45957
B42: PV of Terminal Value | C42: =M39 -> 1188.1704
B43: Enterprise Value | C43: =C41+C42 -> 1912.63
B45: less Net Debt | C45: =-C7 -> -232.3
B46: less Lease Liabilities | C46: =-Annual!F127 -> -295.3
B47: Equity Value | C47: =C43+C45+C46 -> 1385.03
B48: Per Share Value (NZD) | C48: =C47/C5 -> 9.452194
B49: Upside / Downside | C49: =IF(C4=0,"",C48/C4-1) -> 0.19496764
B52: EV/EBITDA Sum-of-the-Parts
B54: Segment | C54: FY27E EBITDA | D54: Multiple | E54: Implied EV
B55: Steel | C55: =Annual!H35 -> 92.617551 | D55: 8 | E55: =C55*D55 -> 740.9404
B56: Metals | C56: =Annual!H36 -> 89.042348 | D56: 7 | E56: =C56*D56 -> 623.29644
B57: Corporate | C57: =Annual!H37 -> -24.036813 | D57: =IF((C55+C56)=0,"",(C55*D55+C56*D56)/(C55+C56)) -> 7.5098404 | E57: =C57*D57 -> -180.51263
B59: Group EV | E59: =SUM(E55:E57) -> 1183.7242
B60: less Net Debt | E60: =-C7 -> -232.3
B61: less Lease Liabilities | E61: =-Annual!F127 -> -295.3
B62: Equity Value | E62: =E59+E60+E61 -> 656.12421
B63: Per Share Value (NZD) | E63: =E62/C5 -> 4.4777466
B64: Upside / Downside | E64: =IF(C4=0,"",E63/C4-1) -> -0.4339132
B66: Implied Group EV/EBITDA | E66: =IF(Annual!H38=0,"",E59/Annual!H38) -> 7.5098404

Sheet Annual
D1: 2023 | E1: 2024 | F1: 2025 | G1: 2026 | H1: 2027 | I1: 2028 | J1: 2029 | K1: 2030 | L1: 2031 | M1: 2032 | N1: 2033 | O1: 2034 | P1: 2035
B2: VSL Model Summary | D2: Actual ----------> | G2: Forecast ----->
B3: Vulcan Steel (VSL.NZ) | C3: Units | D3: FY23A | E3: FY24A | F3: FY25A | G3: FY26E | H3: FY27E | I3: FY28E | J3: FY29E | K3: FY30E | L3: FY31E | M3: FY32E | N3: FY33E | O3: FY34E | P3: FY35E
D4: 45107 | E4: 45473 | F4: 45838 | G4: 46203 | H4: 46568 | I4: 46934 | J4: 47299 | K4: 47664 | L4: 48029 | M4: 48395 | N4: 48760 | O4: 49125 | P4: 49490
B5: P&L
B6: Revenue
A7: Rev-Steel Revenue | B7: Steel Revenue | C7: NZDm | D7: 596.3 | E7: 471.3 | F7: 409.7 | G7: =INDEX('HY & Segments'!$A:$AG,MATCH($A7,'HY & Segments'!$A:$A,0),MATCH("1H"&RIGHT(G$1,2),'HY & Segments'!$3:$3,0))+INDEX('HY & Segments'!$A:$AG,MATCH($A7,'HY & Segments'!$A:$A,0),MATCH("2H"&RIGHT(G$1,2),'HY & Segments'!$3:$3,0)) -> 533.03528 | H7: =INDEX('HY & Segments'!$A:$AG,MATCH($A7,'HY & Segments'!$A:$A,0),MATCH("1H"&RIGHT(H$1,2),'HY & Segments'!$3:$3,0))+INDEX('HY & Segments'!$A:$AG,MATCH($A7,'HY & Segments'!$A:$A,0),MATCH("2H"&RIGHT(H$1,2),'HY & Segments'!$3:$3,0)) -> 595.85812 | I7: =INDEX('HY & Segments'!$A:$AG,MATCH($A7,'HY & Segments'!$A:$A,0),MATCH("1H"&RIGHT(I$1,2),'HY & Segments'!$3:$3,0))+INDEX('HY & Segments'!$A:$AG,MATCH($A7,'HY & Segments'!$A:$A,0),MATCH("2H"&RIGHT(I$1,2),'HY & Segments'!$3:$3,0)) -> 629.07721 | J7: =INDEX('HY & Segments'!$A:$AG,MATCH($A7,'HY & Segments'!$A:$A,0),MATCH("1H"&RIGHT(J$1,2),'HY & Segments'!$3:$3,0))+INDEX('HY & Segments'!$A:$AG,MATCH($A7,'HY & Segments'!$A:$A,0),MATCH("2H"&RIGHT(J$1,2),'HY & Segments'!$3:$3,0)) -> 664.14826 | K7: =INDEX('HY & Segments'!$A:$AG,MATCH($A7,'HY & Segments'!$A:$A,0),MATCH("1H"&RIGHT(K$1,2),'HY & Segments'!$3:$3,0))+INDEX('HY & Segments'!$A:$AG,MATCH($A7,'HY & Segments'!$A:$A,0),MATCH("2H"&RIGHT(K$1,2),'HY & Segments'!$3:$3,0)) -> 701.17453 | L7: =INDEX('HY & Segments'!$A:$AG,MATCH($A7,'HY & Segments'!$A:$A,0),MATCH("1H"&RIGHT(L$1,2),'HY & Segments'!$3:$3,0))+INDEX('HY & Segments'!$A:$AG,MATCH($A7,'HY & Segments'!$A:$A,0),MATCH("2H"&RIGHT(L$1,2),'HY & Segments'!$3:$3,0)) -> 740.26501 | M7: =INDEX('HY & Segments'!$A:$AG,MATCH($A7,'HY & Segments'!$A:$A,0),MATCH("1H"&RIGHT(M$1,2),'HY & Segments'!$3:$3,0))+INDEX('HY & Segments'!$A:$AG,MATCH($A7,'HY & Segments'!$A:$A,0),MATCH("2H"&RIGHT(M$1,2),'HY & Segments'!$3:$3,0)) -> 781.53478 | N7: =INDEX('HY & Segments'!$A:$AG,MATCH($A7,'HY & Segments'!$A:$A,0),MATCH("1H"&RIGHT(N$1,2),'HY & Segments'!$3:$3,0))+INDEX('HY & Segments'!$A:$AG,MATCH($A7,'HY & Segments'!$A:$A,0),MATCH("2H"&RIGHT(N$1,2),'HY & Segments'!$3:$3,0)) -> 825.10535 | ... P7: =INDEX('HY & Segments'!$A:$AG,MATCH($A7,'HY & Segments'!$A:$A,0),MATCH("1H"&RIGHT(P$1,2),'HY & Segments'!$3:$3,0))+INDEX('HY & Segments'!$A:$AG,MATCH($A7,'HY & Segments'!$A:$A,0),MATCH("2H"&RIGHT(P$1,2),'HY & Segments'!$3:$3,0)) -> 919.66907
A8: Rev-Metals Revenue | B8: Metals Revenue | C8: NZDm | D8: 648.6 | E8: 593 | F8: 538.4 | G8: =INDEX('HY & Segments'!$A:$AG,MATCH($A8,'HY & Segments'!$A:$A,0),MATCH("1H"&RIGHT(G$1,2),'HY & Segments'!$3:$3,0))+INDEX('HY & Segments'!$A:$AG,MATCH($A8,'HY & Segments'!$A:$A,0),MATCH("2H"&RIGHT(G$1,2),'HY & Segments'!$3:$3,0)) -> 542.43297 | H8: =INDEX('HY & Segments'!$A:$AG,MATCH($A8,'HY & Segments'!$A:$A,0),MATCH("1H"&RIGHT(H$1,2),'HY & Segments'!$3:$3,0))+INDEX('HY & Segments'!$A:$AG,MATCH($A8,'HY & Segments'!$A:$A,0),MATCH("2H"&RIGHT(H$1,2),'HY & Segments'!$3:$3,0)) -> 572.67361 | I8: =INDEX('HY & Segments'!$A:$AG,MATCH($A8,'HY & Segments'!$A:$A,0),MATCH("1H"&RIGHT(I$1,2),'HY & Segments'!$3:$3,0))+INDEX('HY & Segments'!$A:$AG,MATCH($A8,'HY & Segments'!$A:$A,0),MATCH("2H"&RIGHT(I$1,2),'HY & Segments'!$3:$3,0)) -> 604.60017 | J8: =INDEX('HY & Segments'!$A:$AG,MATCH($A8,'HY & Segments'!$A:$A,0),MATCH("1H"&RIGHT(J$1,2),'HY & Segments'!$3:$3,0))+INDEX('HY & Segments'!$A:$AG,MATCH($A8,'HY & Segments'!$A:$A,0),MATCH("2H"&RIGHT(J$1,2),'HY & Segments'!$3:$3,0)) -> 638.30663 | K8: =INDEX('HY & Segments'!$A:$AG,MATCH($A8,'HY & Segments'!$A:$A,0),MATCH("1H"&RIGHT(K$1,2),'HY & Segments'!$3:$3,0))+INDEX('HY & Segments'!$A:$AG,MATCH($A8,'HY & Segments'!$A:$A,0),MATCH("2H"&RIGHT(K$1,2),'HY & Segments'!$3:$3,0)) -> 673.89222 | L8: =INDEX('HY & Segments'!$A:$AG,MATCH($A8,'HY & Segments'!$A:$A,0),MATCH("1H"&RIGHT(L$1,2),'HY & Segments'!$3:$3,0))+INDEX('HY & Segments'!$A:$AG,MATCH($A8,'HY & Segments'!$A:$A,0),MATCH("2H"&RIGHT(L$1,2),'HY & Segments'!$3:$3,0)) -> 711.46171 | M8: =INDEX('HY & Segments'!$A:$AG,MATCH($A8,'HY & Segments'!$A:$A,0),MATCH("1H"&RIGHT(M$1,2),'HY & Segments'!$3:$3,0))+INDEX('HY & Segments'!$A:$AG,MATCH($A8,'HY & Segments'!$A:$A,0),MATCH("2H"&RIGHT(M$1,2),'HY & Segments'!$3:$3,0)) -> 751.1257 | N8: =INDEX('HY & Segments'!$A:$AG,MATCH($A8,'HY & Segments'!$A:$A,0),MATCH("1H"&RIGHT(N$1,2),'HY & Segments'!$3:$3,0))+INDEX('HY & Segments'!$A:$AG,MATCH($A8,'HY & Segments'!$A:$A,0),MATCH("2H"&RIGHT(N$1,2),'HY & Segments'!$3:$3,0)) -> 793.00096 | ... P8: =INDEX('HY & Segments'!$A:$AG,MATCH($A8,'HY & Segments'!$A:$A,0),MATCH("1H"&RIGHT(P$1,2),'HY & Segments'!$3:$3,0))+INDEX('HY & Segments'!$A:$AG,MATCH($A8,'HY & Segments'!$A:$A,0),MATCH("2H"&RIGHT(P$1,2),'HY & Segments'!$3:$3,0)) -> 883.88526
A9: Rev-Total Revenue | B9: Total Revenue | C9: NZDm | D9: =D7+D8 -> 1244.9 | E9: =E7+E8 -> 1064.3 | F9: =F7+F8 -> 948.1 | G9: =G7+G8 -> 1075.4683 | H9: =H7+H8 -> 1168.5317 | I9: =I7+I8 -> 1233.6774 | J9: =J7+J8 -> 1302.4549 | K9: =K7+K8 -> 1375.0668 | ... P9: =P7+P8 -> 1803.5543
B10: Revenue Growth | C10: % YoY | E10: =IF(D9=0,"",E9/D9-1) -> -0.14507189 | F10: =IF(E9=0,"",F9/E9-1) -> -0.10917974 | G10: =IF(F9=0,"",G9/F9-1) -> 0.13434053 | H10: =IF(G9=0,"",H9/G9-1) -> 0.086532986 | I10: =IF(H9=0,"",I9/H9-1) -> 0.05575 | J10: =IF(I9=0,"",J9/I9-1) -> 0.05575 | K10: =IF(J9=0,"",K9/J9-1) -> 0.05575 | L10: =IF(K9=0,"",L9/K9-1) -> 0.05575 | ... P10: =IF(O9=0,"",P9/O9-1) -> 0.05575
B12: COGS
A13: COGS-Steel COGS | B13: Steel COGS | C13: NZDm | D13: -410.2544 | E13: -327.6 | F13: -290.5 | G13: =INDEX('HY & Segments'!$A:$AG,MATCH($A13,'HY & Segments'!$A:$A,0),MATCH("1H"&RIGHT(G$1,2),'HY & Segments'!$3:$3,0))+INDEX('HY & Segments'!$A:$AG,MATCH($A13,'HY & Segments'!$A:$A,0),MATCH("2H"&RIGHT(G$1,2),'HY & Segments'!$3:$3,0)) -> -374.71591 | H13: =INDEX('HY & Segments'!$A:$AG,MATCH($A13,'HY & Segments'!$A:$A,0),MATCH("1H"&RIGHT(H$1,2),'HY & Segments'!$3:$3,0))+INDEX('HY & Segments'!$A:$AG,MATCH($A13,'HY & Segments'!$A:$A,0),MATCH("2H"&RIGHT(H$1,2),'HY & Segments'!$3:$3,0)) -> -418.81371 | I13: =INDEX('HY & Segments'!$A:$AG,MATCH($A13,'HY & Segments'!$A:$A,0),MATCH("1H"&RIGHT(I$1,2),'HY & Segments'!$3:$3,0))+INDEX('HY & Segments'!$A:$AG,MATCH($A13,'HY & Segments'!$A:$A,0),MATCH("2H"&RIGHT(I$1,2),'HY & Segments'!$3:$3,0)) -> -442.16257 | J13: =INDEX('HY & Segments'!$A:$AG,MATCH($A13,'HY & Segments'!$A:$A,0),MATCH("1H"&RIGHT(J$1,2),'HY & Segments'!$3:$3,0))+INDEX('HY & Segments'!$A:$AG,MATCH($A13,'HY & Segments'!$A:$A,0),MATCH("2H"&RIGHT(J$1,2),'HY & Segments'!$3:$3,0)) -> -466.81314 | K13: =INDEX('HY & Segments'!$A:$AG,MATCH($A13,'HY & Segments'!$A:$A,0),MATCH("1H"&RIGHT(K$1,2),'HY & Segments'!$3:$3,0))+INDEX('HY & Segments'!$A:$AG,MATCH($A13,'HY & Segments'!$A:$A,0),MATCH("2H"&RIGHT(K$1,2),'HY & Segments'!$3:$3,0)) -> -492.83797 | L13: =INDEX('HY & Segments'!$A:$AG,MATCH($A13,'HY & Segments'!$A:$A,0),MATCH("1H"&RIGHT(L$1,2),'HY & Segments'!$3:$3,0))+INDEX('HY & Segments'!$A:$AG,MATCH($A13,'HY & Segments'!$A:$A,0),MATCH("2H"&RIGHT(L$1,2),'HY & Segments'!$3:$3,0)) -> -520.31369 | M13: =INDEX('HY & Segments'!$A:$AG,MATCH($A13,'HY & Segments'!$A:$A,0),MATCH("1H"&RIGHT(M$1,2),'HY & Segments'!$3:$3,0))+INDEX('HY & Segments'!$A:$AG,MATCH($A13,'HY & Segments'!$A:$A,0),MATCH("2H"&RIGHT(M$1,2),'HY & Segments'!$3:$3,0)) -> -549.32117 | N13: =INDEX('HY & Segments'!$A:$AG,MATCH($A13,'HY & Segments'!$A:$A,0),MATCH("1H"&RIGHT(N$1,2),'HY & Segments'!$3:$3,0))+INDEX('HY & Segments'!$A:$AG,MATCH($A13,'HY & Segments'!$A:$A,0),MATCH("2H"&RIGHT(N$1,2),'HY & Segments'!$3:$3,0)) -> -579.94583 | ... P13: =INDEX('HY & Segments'!$A:$AG,MATCH($A13,'HY & Segments'!$A:$A,0),MATCH("1H"&RIGHT(P$1,2),'HY & Segments'!$3:$3,0))+INDEX('HY & Segments'!$A:$AG,MATCH($A13,'HY & Segments'!$A:$A,0),MATCH("2H"&RIGHT(P$1,2),'HY & Segments'!$3:$3,0)) -> -646.4123
A14: COGS-Metals COGS | B14: Metals COGS | C14: NZDm | D14: -391.1058 | E14: -375.4 | F14: -332.7 | G14: =INDEX('HY & Segments'!$A:$AG,MATCH($A14,'HY & Segments'!$A:$A,0),MATCH("1H"&RIGHT(G$1,2),'HY & Segments'!$3:$3,0))+INDEX('HY & Segments'!$A:$AG,MATCH($A14,'HY & Segments'!$A:$A,0),MATCH("2H"&RIGHT(G$1,2),'HY & Segments'!$3:$3,0)) -> -341.93503 | H14: =INDEX('HY & Segments'!$A:$AG,MATCH($A14,'HY & Segments'!$A:$A,0),MATCH("1H"&RIGHT(H$1,2),'HY & Segments'!$3:$3,0))+INDEX('HY & Segments'!$A:$AG,MATCH($A14,'HY & Segments'!$A:$A,0),MATCH("2H"&RIGHT(H$1,2),'HY & Segments'!$3:$3,0)) -> -360.99791 | I14: =INDEX('HY & Segments'!$A:$AG,MATCH($A14,'HY & Segments'!$A:$A,0),MATCH("1H"&RIGHT(I$1,2),'HY & Segments'!$3:$3,0))+INDEX('HY & Segments'!$A:$AG,MATCH($A14,'HY & Segments'!$A:$A,0),MATCH("2H"&RIGHT(I$1,2),'HY & Segments'!$3:$3,0)) -> -381.12354 | J14: =INDEX('HY & Segments'!$A:$AG,MATCH($A14,'HY & Segments'!$A:$A,0),MATCH("1H"&RIGHT(J$1,2),'HY & Segments'!$3:$3,0))+INDEX('HY & Segments'!$A:$AG,MATCH($A14,'HY & Segments'!$A:$A,0),MATCH("2H"&RIGHT(J$1,2),'HY & Segments'!$3:$3,0)) -> -402.37118 | K14: =INDEX('HY & Segments'!$A:$AG,MATCH($A14,'HY & Segments'!$A:$A,0),MATCH("1H"&RIGHT(K$1,2),'HY & Segments'!$3:$3,0))+INDEX('HY & Segments'!$A:$AG,MATCH($A14,'HY & Segments'!$A:$A,0),MATCH("2H"&RIGHT(K$1,2),'HY & Segments'!$3:$3,0)) -> -424.80337 | L14: =INDEX('HY & Segments'!$A:$AG,MATCH($A14,'HY & Segments'!$A:$A,0),MATCH("1H"&RIGHT(L$1,2),'HY & Segments'!$3:$3,0))+INDEX('HY & Segments'!$A:$AG,MATCH($A14,'HY & Segments'!$A:$A,0),MATCH("2H"&RIGHT(L$1,2),'HY & Segments'!$3:$3,0)) -> -448.48616 | M14: =INDEX('HY & Segments'!$A:$AG,MATCH($A14,'HY & Segments'!$A:$A,0),MATCH("1H"&RIGHT(M$1,2),'HY & Segments'!$3:$3,0))+INDEX('HY & Segments'!$A:$AG,MATCH($A14,'HY & Segments'!$A:$A,0),MATCH("2H"&RIGHT(M$1,2),'HY & Segments'!$3:$3,0)) -> -473.48926 | N14: =INDEX('HY & Segments'!$A:$AG,MATCH($A14,'HY & Segments'!$A:$A,0),MATCH("1H"&RIGHT(N$1,2),'HY & Segments'!$3:$3,0))+INDEX('HY & Segments'!$A:$AG,MATCH($A14,'HY & Segments'!$A:$A,0),MATCH("2H"&RIGHT(N$1,2),'HY & Segments'!$3:$3,0)) -> -499.88629 | ... P14: =INDEX('HY & Segments'!$A:$AG,MATCH($A14,'HY & Segments'!$A:$A,0),MATCH("1H"&RIGHT(P$1,2),'HY & Segments'!$3:$3,0))+INDEX('HY & Segments'!$A:$AG,MATCH($A14,'HY & Segments'!$A:$A,0),MATCH("2H"&RIGHT(P$1,2),'HY & Segments'!$3:$3,0)) -> -557.17729
A15: COGS-Other COGS | B15: Other COGS | C15: NZDm | D15: 0 | E15: 0 | F15: 0 | G15: =INDEX('HY & Segments'!$A:$AG,MATCH($A15,'HY & Segments'!$A:$A,0),MATCH("1H"&RIGHT(G$1,2),'HY & Segments'!$3:$3,0))+INDEX('HY & Segments'!$A:$AG,MATCH($A15,'HY & Segments'!$A:$A,0),MATCH("2H"&RIGHT(G$1,2),'HY & Segments'!$3:$3,0)) -> 0 | H15: =INDEX('HY & Segments'!$A:$AG,MATCH($A15,'HY & Segments'!$A:$A,0),MATCH("1H"&RIGHT(H$1,2),'HY & Segments'!$3:$3,0))+INDEX('HY & Segments'!$A:$AG,MATCH($A15,'HY & Segments'!$A:$A,0),MATCH("2H"&RIGHT(H$1,2),'HY & Segments'!$3:$3,0)) -> 0 | I15: =INDEX('HY & Segments'!$A:$AG,MATCH($A15,'HY & Segments'!$A:$A,0),MATCH("1H"&RIGHT(I$1,2),'HY & Segments'!$3:$3,0))+INDEX('HY & Segments'!$A:$AG,MATCH($A15,'HY & Segments'!$A:$A,0),MATCH("2H"&RIGHT(I$1,2),'HY & Segments'!$3:$3,0)) -> 0 | J15: =INDEX('HY & Segments'!$A:$AG,MATCH($A15,'HY & Segments'!$A:$A,0),MATCH("1H"&RIGHT(J$1,2),'HY & Segments'!$3:$3,0))+INDEX('HY & Segments'!$A:$AG,MATCH($A15,'HY & Segments'!$A:$A,0),MATCH("2H"&RIGHT(J$1,2),'HY & Segments'!$3:$3,0)) -> 0 | K15: =INDEX('HY & Segments'!$A:$AG,MATCH($A15,'HY & Segments'!$A:$A,0),MATCH("1H"&RIGHT(K$1,2),'HY & Segments'!$3:$3,0))+INDEX('HY & Segments'!$A:$AG,MATCH($A15,'HY & Segments'!$A:$A,0),MATCH("2H"&RIGHT(K$1,2),'HY & Segments'!$3:$3,0)) -> 0 | L15: =INDEX('HY & Segments'!$A:$AG,MATCH($A15,'HY & Segments'!$A:$A,0),MATCH("1H"&RIGHT(L$1,2),'HY & Segments'!$3:$3,0))+INDEX('HY & Segments'!$A:$AG,MATCH($A15,'HY & Segments'!$A:$A,0),MATCH("2H"&RIGHT(L$1,2),'HY & Segments'!$3:$3,0)) -> 0 | M15: =INDEX('HY & Segments'!$A:$AG,MATCH($A15,'HY & Segments'!$A:$A,0),MATCH("1H"&RIGHT(M$1,2),'HY & Segments'!$3:$3,0))+INDEX('HY & Segments'!$A:$AG,MATCH($A15,'HY & Segments'!$A:$A,0),MATCH("2H"&RIGHT(M$1,2),'HY & Segments'!$3:$3,0)) -> 0 | N15: =INDEX('HY & Segments'!$A:$AG,MATCH($A15,'HY & Segments'!$A:$A,0),MATCH("1H"&RIGHT(N$1,2),'HY & Segments'!$3:$3,0))+INDEX('HY & Segments'!$A:$AG,MATCH($A15,'HY & Segments'!$A:$A,0),MATCH("2H"&RIGHT(N$1,2),'HY & Segments'!$3:$3,0)) -> 0 | ... P15: =INDEX('HY & Segments'!$A:$AG,MATCH($A15,'HY & Segments'!$A:$A,0),MATCH("1H"&RIGHT(P$1,2),'HY & Segments'!$3:$3,0))+INDEX('HY & Segments'!$A:$AG,MATCH($A15,'HY & Segments'!$A:$A,0),MATCH("2H"&RIGHT(P$1,2),'HY & Segments'!$3:$3,0)) -> 0
A16: COGS-Total COGS | B16: Total COGS | C16: NZDm | D16: =SUM(D13:D15) -> -801.3602 | E16: =SUM(E13:E15) -> -703 | F16: =SUM(F13:F15) -> -623.2 | G16: =SUM(G13:G15) -> -716.65094 | H16: =SUM(H13:H15) -> -779.81162 | I16: =SUM(I13:I15) -> -823.28612 | J16: =SUM(J13:J15) -> -869.18432 | K16: =SUM(K13:K15) -> -917.64134 | ... P16: =SUM(P13:P15) -> -1203.5896
B18: Gross Profit
A19: GP-Steel GP | B19: Steel GP | C19: NZDm | D19: =D7+D13 -> 186.0456 | E19: =E7+E13 -> 143.7 | F19: =F7+F13 -> 119.2 | G19: =INDEX('HY & Segments'!$A:$AG,MATCH($A19,'HY & Segments'!$A:$A,0),MATCH("1H"&RIGHT(G$1,2),'HY & Segments'!$3:$3,0))+INDEX('HY & Segments'!$A:$AG,MATCH($A19,'HY & Segments'!$A:$A,0),MATCH("2H"&RIGHT(G$1,2),'HY & Segments'!$3:$3,0)) -> 158.31937 | H19: =INDEX('HY & Segments'!$A:$AG,MATCH($A19,'HY & Segments'!$A:$A,0),MATCH("1H"&RIGHT(H$1,2),'HY & Segments'!$3:$3,0))+INDEX('HY & Segments'!$A:$AG,MATCH($A19,'HY & Segments'!$A:$A,0),MATCH("2H"&RIGHT(H$1,2),'HY & Segments'!$3:$3,0)) -> 177.04441 | I19: =INDEX('HY & Segments'!$A:$AG,MATCH($A19,'HY & Segments'!$A:$A,0),MATCH("1H"&RIGHT(I$1,2),'HY & Segments'!$3:$3,0))+INDEX('HY & Segments'!$A:$AG,MATCH($A19,'HY & Segments'!$A:$A,0),MATCH("2H"&RIGHT(I$1,2),'HY & Segments'!$3:$3,0)) -> 186.91464 | J19: =INDEX('HY & Segments'!$A:$AG,MATCH($A19,'HY & Segments'!$A:$A,0),MATCH("1H"&RIGHT(J$1,2),'HY & Segments'!$3:$3,0))+INDEX('HY & Segments'!$A:$AG,MATCH($A19,'HY & Segments'!$A:$A,0),MATCH("2H"&RIGHT(J$1,2),'HY & Segments'!$3:$3,0)) -> 197.33513 | K19: =INDEX('HY & Segments'!$A:$AG,MATCH($A19,'HY & Segments'!$A:$A,0),MATCH("1H"&RIGHT(K$1,2),'HY & Segments'!$3:$3,0))+INDEX('HY & Segments'!$A:$AG,MATCH($A19,'HY & Segments'!$A:$A,0),MATCH("2H"&RIGHT(K$1,2),'HY & Segments'!$3:$3,0)) -> 208.33656 | L19: =INDEX('HY & Segments'!$A:$AG,MATCH($A19,'HY & Segments'!$A:$A,0),MATCH("1H"&RIGHT(L$1,2),'HY & Segments'!$3:$3,0))+INDEX('HY & Segments'!$A:$AG,MATCH($A19,'HY & Segments'!$A:$A,0),MATCH("2H"&RIGHT(L$1,2),'HY & Segments'!$3:$3,0)) -> 219.95132 | M19: =INDEX('HY & Segments'!$A:$AG,MATCH($A19,'HY & Segments'!$A:$A,0),MATCH("1H"&RIGHT(M$1,2),'HY & Segments'!$3:$3,0))+INDEX('HY & Segments'!$A:$AG,MATCH($A19,'HY & Segments'!$A:$A,0),MATCH("2H"&RIGHT(M$1,2),'HY & Segments'!$3:$3,0)) -> 232.21361 | N19: =INDEX('HY & Segments'!$A:$AG,MATCH($A19,'HY & Segments'!$A:$A,0),MATCH("1H"&RIGHT(N$1,2),'HY & Segments'!$3:$3,0))+INDEX('HY & Segments'!$A:$AG,MATCH($A19,'HY & Segments'!$A:$A,0),MATCH("2H"&RIGHT(N$1,2),'HY & Segments'!$3:$3,0)) -> 245.15952 | ... P19: =INDEX('HY & Segments'!$A:$AG,MATCH($A19,'HY & Segments'!$A:$A,0),MATCH("1H"&RIGHT(P$1,2),'HY & Segments'!$3:$3,0))+INDEX('HY & Segments'!$A:$AG,MATCH($A19,'HY & Segments'!$A:$A,0),MATCH("2H"&RIGHT(P$1,2),'HY & Segments'!$3:$3,0)) -> 273.25678
A20: GP-Metals GP | B20: Metals GP | C20: NZDm | D20: =D8+D14 -> 257.4942 | E20: =E8+E14 -> 217.6 | F20: =F8+F14 -> 205.7 | G20: =INDEX('HY & Segments'!$A:$AG,MATCH($A20,'HY & Segments'!$A:$A,0),MATCH("1H"&RIGHT(G$1,2),'HY & Segments'!$3:$3,0))+INDEX('HY & Segments'!$A:$AG,MATCH($A20,'HY & Segments'!$A:$A,0),MATCH("2H"&RIGHT(G$1,2),'HY & Segments'!$3:$3,0)) -> 200.49794 | H20: =INDEX('HY & Segments'!$A:$AG,MATCH($A20,'HY & Segments'!$A:$A,0),MATCH("1H"&RIGHT(H$1,2),'HY & Segments'!$3:$3,0))+INDEX('HY & Segments'!$A:$AG,MATCH($A20,'HY & Segments'!$A:$A,0),MATCH("2H"&RIGHT(H$1,2),'HY & Segments'!$3:$3,0)) -> 211.67571 | I20: =INDEX('HY & Segments'!$A:$AG,MATCH($A20,'HY & Segments'!$A:$A,0),MATCH("1H"&RIGHT(I$1,2),'HY & Segments'!$3:$3,0))+INDEX('HY & Segments'!$A:$AG,MATCH($A20,'HY & Segments'!$A:$A,0),MATCH("2H"&RIGHT(I$1,2),'HY & Segments'!$3:$3,0)) -> 223.47663 | J20: =INDEX('HY & Segments'!$A:$AG,MATCH($A20,'HY & Segments'!$A:$A,0),MATCH("1H"&RIGHT(J$1,2),'HY & Segments'!$3:$3,0))+INDEX('HY & Segments'!$A:$AG,MATCH($A20,'HY & Segments'!$A:$A,0),MATCH("2H"&RIGHT(J$1,2),'HY & Segments'!$3:$3,0)) -> 235.93545 | K20: =INDEX('HY & Segments'!$A:$AG,MATCH($A20,'HY & Segments'!$A:$A,0),MATCH("1H"&RIGHT(K$1,2),'HY & Segments'!$3:$3,0))+INDEX('HY & Segments'!$A:$AG,MATCH($A20,'HY & Segments'!$A:$A,0),MATCH("2H"&RIGHT(K$1,2),'HY & Segments'!$3:$3,0)) -> 249.08885 | L20: =INDEX('HY & Segments'!$A:$AG,MATCH($A20,'HY & Segments'!$A:$A,0),MATCH("1H"&RIGHT(L$1,2),'HY & Segments'!$3:$3,0))+INDEX('HY & Segments'!$A:$AG,MATCH($A20,'HY & Segments'!$A:$A,0),MATCH("2H"&RIGHT(L$1,2),'HY & Segments'!$3:$3,0)) -> 262.97555 | M20: =INDEX('HY & Segments'!$A:$AG,MATCH($A20,'HY & Segments'!$A:$A,0),MATCH("1H"&RIGHT(M$1,2),'HY & Segments'!$3:$3,0))+INDEX('HY & Segments'!$A:$AG,MATCH($A20,'HY & Segments'!$A:$A,0),MATCH("2H"&RIGHT(M$1,2),'HY & Segments'!$3:$3,0)) -> 277.63644 | N20: =INDEX('HY & Segments'!$A:$AG,MATCH($A20,'HY & Segments'!$A:$A,0),MATCH("1H"&RIGHT(N$1,2),'HY & Segments'!$3:$3,0))+INDEX('HY & Segments'!$A:$AG,MATCH($A20,'HY & Segments'!$A:$A,0),MATCH("2H"&RIGHT(N$1,2),'HY & Segments'!$3:$3,0)) -> 293.11467 | ... P20: =INDEX('HY & Segments'!$A:$AG,MATCH($A20,'HY & Segments'!$A:$A,0),MATCH("1H"&RIGHT(P$1,2),'HY & Segments'!$3:$3,0))+INDEX('HY & Segments'!$A:$AG,MATCH($A20,'HY & Segments'!$A:$A,0),MATCH("2H"&RIGHT(P$1,2),'HY & Segments'!$3:$3,0)) -> 326.70798
A21: GP-Corporate GP | B21: Corporate/Elim | C21: NZDm | D21: =D22-D19-D20 -> 0 | E21: =E22-E19-E20 -> 0 | F21: =F22-F19-F20 -> 0 | G21: =INDEX('HY & Segments'!$A:$AG,MATCH($A21,'HY & Segments'!$A:$A,0),MATCH("1H"&RIGHT(G$1,2),'HY & Segments'!$3:$3,0))+INDEX('HY & Segments'!$A:$AG,MATCH($A21,'HY & Segments'!$A:$A,0),MATCH("2H"&RIGHT(G$1,2),'HY & Segments'!$3:$3,0)) -> 0 | H21: =INDEX('HY & Segments'!$A:$AG,MATCH($A21,'HY & Segments'!$A:$A,0),MATCH("1H"&RIGHT(H$1,2),'HY & Segments'!$3:$3,0))+INDEX('HY & Segments'!$A:$AG,MATCH($A21,'HY & Segments'!$A:$A,0),MATCH("2H"&RIGHT(H$1,2),'HY & Segments'!$3:$3,0)) -> 0 | I21: =INDEX('HY & Segments'!$A:$AG,MATCH($A21,'HY & Segments'!$A:$A,0),MATCH("1H"&RIGHT(I$1,2),'HY & Segments'!$3:$3,0))+INDEX('HY & Segments'!$A:$AG,MATCH($A21,'HY & Segments'!$A:$A,0),MATCH("2H"&RIGHT(I$1,2),'HY & Segments'!$3:$3,0)) -> 0 | J21: =INDEX('HY & Segments'!$A:$AG,MATCH($A21,'HY & Segments'!$A:$A,0),MATCH("1H"&RIGHT(J$1,2),'HY & Segments'!$3:$3,0))+INDEX('HY & Segments'!$A:$AG,MATCH($A21,'HY & Segments'!$A:$A,0),MATCH("2H"&RIGHT(J$1,2),'HY & Segments'!$3:$3,0)) -> 0 | K21: =INDEX('HY & Segments'!$A:$AG,MATCH($A21,'HY & Segments'!$A:$A,0),MATCH("1H"&RIGHT(K$1,2),'HY & Segments'!$3:$3,0))+INDEX('HY & Segments'!$A:$AG,MATCH($A21,'HY & Segments'!$A:$A,0),MATCH("2H"&RIGHT(K$1,2),'HY & Segments'!$3:$3,0)) -> 0 | L21: =INDEX('HY & Segments'!$A:$AG,MATCH($A21,'HY & Segments'!$A:$A,0),MATCH("1H"&RIGHT(L$1,2),'HY & Segments'!$3:$3,0))+INDEX('HY & Segments'!$A:$AG,MATCH($A21,'HY & Segments'!$A:$A,0),MATCH("2H"&RIGHT(L$1,2),'HY & Segments'!$3:$3,0)) -> 0 | M21: =INDEX('HY & Segments'!$A:$AG,MATCH($A21,'HY & Segments'!$A:$A,0),MATCH("1H"&RIGHT(M$1,2),'HY & Segments'!$3:$3,0))+INDEX('HY & Segments'!$A:$AG,MATCH($A21,'HY & Segments'!$A:$A,0),MATCH("2H"&RIGHT(M$1,2),'HY & Segments'!$3:$3,0)) -> 0 | N21: =INDEX('HY & Segments'!$A:$AG,MATCH($A21,'HY & Segments'!$A:$A,0),MATCH("1H"&RIGHT(N$1,2),'HY & Segments'!$3:$3,0))+INDEX('HY & Segments'!$A:$AG,MATCH($A21,'HY & Segments'!$A:$A,0),MATCH("2H"&RIGHT(N$1,2),'HY & Segments'!$3:$3,0)) -> 0 | ... P21: =INDEX('HY & Segments'!$A:$AG,MATCH($A21,'HY & Segments'!$A:$A,0),MATCH("1H"&RIGHT(P$1,2),'HY & Segments'!$3:$3,0))+INDEX('HY & Segments'!$A:$AG,MATCH($A21,'HY & Segments'!$A:$A,0),MATCH("2H"&RIGHT(P$1,2),'HY & Segments'!$3:$3,0)) -> 0
A22: GP-Gross Profit | B22: Gross Profit | C22: NZDm | D22: =D9+D16 -> 443.5398 | E22: =E9+E16 -> 361.3 | F22: =F9+F16 -> 324.9 | G22: =G9+G16 -> 358.81732 | H22: =H9+H16 -> 388.72012 | I22: =I9+I16 -> 410.39126 | J22: =J9+J16 -> 433.27057 | K22: =K9+K16 -> 457.42541 | ... P22: =P9+P16 -> 599.96475
B23: GP Growth | C23: % YoY | E23: =IF(D22=0,"",E22/D22-1) -> -0.18541696 | F23: =IF(E22=0,"",F22/E22-1) -> -0.1007473 | G23: =IF(F22=0,"",G22/F22-1) -> 0.1043931 | H23: =IF(G22=0,"",H22/G22-1) -> 0.083337105 | I23: =IF(H22=0,"",I22/H22-1) -> 0.05575 | J23: =IF(I22=0,"",J22/I22-1) -> 0.05575 | K23: =IF(J22=0,"",K22/J22-1) -> 0.05575 | L23: =IF(K22=0,"",L22/K22-1) -> 0.05575 | ... P23: =IF(O22=0,"",P22/O22-1) -> 0.05575
B24: GP Margin | C24: % | D24: =IF(D9=0,"",D22/D9) -> 0.35628548 | E24: =IF(E9=0,"",E22/E9) -> 0.33947195 | F24: =IF(F9=0,"",F22/F9) -> 0.34268537 | G24: =IF(G9=0,"",G22/G9) -> 0.33363822 | H24: =IF(H9=0,"",H22/H9) -> 0.33265688 | I24: =IF(I9=0,"",I22/I9) -> 0.33265688 | J24: =IF(J9=0,"",J22/J9) -> 0.33265688 | K24: =IF(K9=0,"",K22/K9) -> 0.33265688 | ... P24: =IF(P9=0,"",P22/P9) -> 0.33265688
B26: Operating Expenses
A27: OPEX-Employee Benefits | B27: Employee Benefits | C27: NZDm | D27: -142.2 | E27: -139.3 | F27: -146.4 | G27: =INDEX('HY & Segments'!$A:$AG,MATCH($A27,'HY & Segments'!$A:$A,0),MATCH("1H"&RIGHT(G$1,2),'HY & Segments'!$3:$3,0))+INDEX('HY & Segments'!$A:$AG,MATCH($A27,'HY & Segments'!$A:$A,0),MATCH("2H"&RIGHT(G$1,2),'HY & Segments'!$3:$3,0)) -> -164.17509 | H27: =INDEX('HY & Segments'!$A:$AG,MATCH($A27,'HY & Segments'!$A:$A,0),MATCH("1H"&RIGHT(H$1,2),'HY & Segments'!$3:$3,0))+INDEX('HY & Segments'!$A:$AG,MATCH($A27,'HY & Segments'!$A:$A,0),MATCH("2H"&RIGHT(H$1,2),'HY & Segments'!$3:$3,0)) -> -169.40565 | I27: =INDEX('HY & Segments'!$A:$AG,MATCH($A27,'HY & Segments'!$A:$A,0),MATCH("1H"&RIGHT(I$1,2),'HY & Segments'!$3:$3,0))+INDEX('HY & Segments'!$A:$AG,MATCH($A27,'HY & Segments'!$A:$A,0),MATCH("2H"&RIGHT(I$1,2),'HY & Segments'!$3:$3,0)) -> -174.18104 | J27: =INDEX('HY & Segments'!$A:$AG,MATCH($A27,'HY & Segments'!$A:$A,0),MATCH("1H"&RIGHT(J$1,2),'HY & Segments'!$3:$3,0))+INDEX('HY & Segments'!$A:$AG,MATCH($A27,'HY & Segments'!$A:$A,0),MATCH("2H"&RIGHT(J$1,2),'HY & Segments'!$3:$3,0)) -> -179.10592 | K27: =INDEX('HY & Segments'!$A:$AG,MATCH($A27,'HY & Segments'!$A:$A,0),MATCH("1H"&RIGHT(K$1,2),'HY & Segments'!$3:$3,0))+INDEX('HY & Segments'!$A:$AG,MATCH($A27,'HY & Segments'!$A:$A,0),MATCH("2H"&RIGHT(K$1,2),'HY & Segments'!$3:$3,0)) -> -184.18573 | L27: =INDEX('HY & Segments'!$A:$AG,MATCH($A27,'HY & Segments'!$A:$A,0),MATCH("1H"&RIGHT(L$1,2),'HY & Segments'!$3:$3,0))+INDEX('HY & Segments'!$A:$AG,MATCH($A27,'HY & Segments'!$A:$A,0),MATCH("2H"&RIGHT(L$1,2),'HY & Segments'!$3:$3,0)) -> -189.4261 | M27: =INDEX('HY & Segments'!$A:$AG,MATCH($A27,'HY & Segments'!$A:$A,0),MATCH("1H"&RIGHT(M$1,2),'HY & Segments'!$3:$3,0))+INDEX('HY & Segments'!$A:$AG,MATCH($A27,'HY & Segments'!$A:$A,0),MATCH("2H"&RIGHT(M$1,2),'HY & Segments'!$3:$3,0)) -> -194.83293 | N27: =INDEX('HY & Segments'!$A:$AG,MATCH($A27,'HY & Segments'!$A:$A,0),MATCH("1H"&RIGHT(N$1,2),'HY & Segments'!$3:$3,0))+INDEX('HY & Segments'!$A:$AG,MATCH($A27,'HY & Segments'!$A:$A,0),MATCH("2H"&RIGHT(N$1,2),'HY & Segments'!$3:$3,0)) -> -200.41234 | ... P27: =INDEX('HY & Segments'!$A:$AG,MATCH($A27,'HY & Segments'!$A:$A,0),MATCH("1H"&RIGHT(P$1,2),'HY & Segments'!$3:$3,0))+INDEX('HY & Segments'!$A:$AG,MATCH($A27,'HY & Segments'!$A:$A,0),MATCH("2H"&RIGHT(P$1,2),'HY & Segments'!$3:$3,0)) -> -212.11481
A28: OPEX-Selling & Distribution | B28: Selling & Distribution | C28: NZDm | D28: -26.7 | E28: -27.5 | F28: -22.5 | G28: =INDEX('HY & Segments'!$A:$AG,MATCH($A28,'HY & Segments'!$A:$A,0),MATCH("1H"&RIGHT(G$1,2),'HY & Segments'!$3:$3,0))+INDEX('HY & Segments'!$A:$AG,MATCH($A28,'HY & Segments'!$A:$A,0),MATCH("2H"&RIGHT(G$1,2),'HY & Segments'!$3:$3,0)) -> -23.64729 | H28: =INDEX('HY & Segments'!$A:$AG,MATCH($A28,'HY & Segments'!$A:$A,0),MATCH("1H"&RIGHT(H$1,2),'HY & Segments'!$3:$3,0))+INDEX('HY & Segments'!$A:$AG,MATCH($A28,'HY & Segments'!$A:$A,0),MATCH("2H"&RIGHT(H$1,2),'HY & Segments'!$3:$3,0)) -> -24.397053 | I28: =INDEX('HY & Segments'!$A:$AG,MATCH($A28,'HY & Segments'!$A:$A,0),MATCH("1H"&RIGHT(I$1,2),'HY & Segments'!$3:$3,0))+INDEX('HY & Segments'!$A:$AG,MATCH($A28,'HY & Segments'!$A:$A,0),MATCH("2H"&RIGHT(I$1,2),'HY & Segments'!$3:$3,0)) -> -25.084442 | J28: =INDEX('HY & Segments'!$A:$AG,MATCH($A28,'HY & Segments'!$A:$A,0),MATCH("1H"&RIGHT(J$1,2),'HY & Segments'!$3:$3,0))+INDEX('HY & Segments'!$A:$AG,MATCH($A28,'HY & Segments'!$A:$A,0),MATCH("2H"&RIGHT(J$1,2),'HY & Segments'!$3:$3,0)) -> -25.793334 | K28: =INDEX('HY & Segments'!$A:$AG,MATCH($A28,'HY & Segments'!$A:$A,0),MATCH("1H"&RIGHT(K$1,2),'HY & Segments'!$3:$3,0))+INDEX('HY & Segments'!$A:$AG,MATCH($A28,'HY & Segments'!$A:$A,0),MATCH("2H"&RIGHT(K$1,2),'HY & Segments'!$3:$3,0)) -> -26.524508 | L28: =INDEX('HY & Segments'!$A:$AG,MATCH($A28,'HY & Segments'!$A:$A,0),MATCH("1H"&RIGHT(L$1,2),'HY & Segments'!$3:$3,0))+INDEX('HY & Segments'!$A:$AG,MATCH($A28,'HY & Segments'!$A:$A,0),MATCH("2H"&RIGHT(L$1,2),'HY & Segments'!$3:$3,0)) -> -27.278775 | M28: =INDEX('HY & Segments'!$A:$AG,MATCH($A28,'HY & Segments'!$A:$A,0),MATCH("1H"&RIGHT(M$1,2),'HY & Segments'!$3:$3,0))+INDEX('HY & Segments'!$A:$AG,MATCH($A28,'HY & Segments'!$A:$A,0),MATCH("2H"&RIGHT(M$1,2),'HY & Segments'!$3:$3,0)) -> -28.056981 | N28: =INDEX('HY & Segments'!$A:$AG,MATCH($A28,'HY & Segments'!$A:$A,0),MATCH("1H"&RIGHT(N$1,2),'HY & Segments'!$3:$3,0))+INDEX('HY & Segments'!$A:$AG,MATCH($A28,'HY & Segments'!$A:$A,0),MATCH("2H"&RIGHT(N$1,2),'HY & Segments'!$3:$3,0)) -> -28.860007 | ... P28: =INDEX('HY & Segments'!$A:$AG,MATCH($A28,'HY & Segments'!$A:$A,0),MATCH("1H"&RIGHT(P$1,2),'HY & Segments'!$3:$3,0))+INDEX('HY & Segments'!$A:$AG,MATCH($A28,'HY & Segments'!$A:$A,0),MATCH("2H"&RIGHT(P$1,2),'HY & Segments'!$3:$3,0)) -> -30.544237
A29: OPEX-Occupancy Costs | B29: Occupancy Costs | C29: NZDm | D29: -11 | E29: -12.8 | F29: -14.2 | G29: =INDEX('HY & Segments'!$A:$AG,MATCH($A29,'HY & Segments'!$A:$A,0),MATCH("1H"&RIGHT(G$1,2),'HY & Segments'!$3:$3,0))+INDEX('HY & Segments'!$A:$AG,MATCH($A29,'HY & Segments'!$A:$A,0),MATCH("2H"&RIGHT(G$1,2),'HY & Segments'!$3:$3,0)) -> -15.58725 | H29: =INDEX('HY & Segments'!$A:$AG,MATCH($A29,'HY & Segments'!$A:$A,0),MATCH("1H"&RIGHT(H$1,2),'HY & Segments'!$3:$3,0))+INDEX('HY & Segments'!$A:$AG,MATCH($A29,'HY & Segments'!$A:$A,0),MATCH("2H"&RIGHT(H$1,2),'HY & Segments'!$3:$3,0)) -> -16.082928 | I29: =INDEX('HY & Segments'!$A:$AG,MATCH($A29,'HY & Segments'!$A:$A,0),MATCH("1H"&RIGHT(I$1,2),'HY & Segments'!$3:$3,0))+INDEX('HY & Segments'!$A:$AG,MATCH($A29,'HY & Segments'!$A:$A,0),MATCH("2H"&RIGHT(I$1,2),'HY & Segments'!$3:$3,0)) -> -16.536204 | J29: =INDEX('HY & Segments'!$A:$AG,MATCH($A29,'HY & Segments'!$A:$A,0),MATCH("1H"&RIGHT(J$1,2),'HY & Segments'!$3:$3,0))+INDEX('HY & Segments'!$A:$AG,MATCH($A29,'HY & Segments'!$A:$A,0),MATCH("2H"&RIGHT(J$1,2),'HY & Segments'!$3:$3,0)) -> -17.003666 | K29: =INDEX('HY & Segments'!$A:$AG,MATCH($A29,'HY & Segments'!$A:$A,0),MATCH("1H"&RIGHT(K$1,2),'HY & Segments'!$3:$3,0))+INDEX('HY & Segments'!$A:$AG,MATCH($A29,'HY & Segments'!$A:$A,0),MATCH("2H"&RIGHT(K$1,2),'HY & Segments'!$3:$3,0)) -> -17.485828 | L29: =INDEX('HY & Segments'!$A:$AG,MATCH($A29,'HY & Segments'!$A:$A,0),MATCH("1H"&RIGHT(L$1,2),'HY & Segments'!$3:$3,0))+INDEX('HY & Segments'!$A:$AG,MATCH($A29,'HY & Segments'!$A:$A,0),MATCH("2H"&RIGHT(L$1,2),'HY & Segments'!$3:$3,0)) -> -17.983226 | M29: =INDEX('HY & Segments'!$A:$AG,MATCH($A29,'HY & Segments'!$A:$A,0),MATCH("1H"&RIGHT(M$1,2),'HY & Segments'!$3:$3,0))+INDEX('HY & Segments'!$A:$AG,MATCH($A29,'HY & Segments'!$A:$A,0),MATCH("2H"&RIGHT(M$1,2),'HY & Segments'!$3:$3,0)) -> -18.496418 | N29: =INDEX('HY & Segments'!$A:$AG,MATCH($A29,'HY & Segments'!$A:$A,0),MATCH("1H"&RIGHT(N$1,2),'HY & Segments'!$3:$3,0))+INDEX('HY & Segments'!$A:$AG,MATCH($A29,'HY & Segments'!$A:$A,0),MATCH("2H"&RIGHT(N$1,2),'HY & Segments'!$3:$3,0)) -> -19.025986 | ... P29: =INDEX('HY & Segments'!$A:$AG,MATCH($A29,'HY & Segments'!$A:$A,0),MATCH("1H"&RIGHT(P$1,2),'HY & Segments'!$3:$3,0))+INDEX('HY & Segments'!$A:$AG,MATCH($A29,'HY & Segments'!$A:$A,0),MATCH("2H"&RIGHT(P$1,2),'HY & Segments'!$3:$3,0)) -> -20.136705
A30: OPEX-General & Admin | B30: General & Admin | C30: NZDm | D30: -45.5 | E30: -34.2 | F30: -29.4 | G30: =INDEX('HY & Segments'!$A:$AG,MATCH($A30,'HY & Segments'!$A:$A,0),MATCH("1H"&RIGHT(G$1,2),'HY & Segments'!$3:$3,0))+INDEX('HY & Segments'!$A:$AG,MATCH($A30,'HY & Segments'!$A:$A,0),MATCH("2H"&RIGHT(G$1,2),'HY & Segments'!$3:$3,0)) -> -20.5298 | H30: =INDEX('HY & Segments'!$A:$AG,MATCH($A30,'HY & Segments'!$A:$A,0),MATCH("1H"&RIGHT(H$1,2),'HY & Segments'!$3:$3,0))+INDEX('HY & Segments'!$A:$AG,MATCH($A30,'HY & Segments'!$A:$A,0),MATCH("2H"&RIGHT(H$1,2),'HY & Segments'!$3:$3,0)) -> -21.211395 | I30: =INDEX('HY & Segments'!$A:$AG,MATCH($A30,'HY & Segments'!$A:$A,0),MATCH("1H"&RIGHT(I$1,2),'HY & Segments'!$3:$3,0))+INDEX('HY & Segments'!$A:$AG,MATCH($A30,'HY & Segments'!$A:$A,0),MATCH("2H"&RIGHT(I$1,2),'HY & Segments'!$3:$3,0)) -> -21.811905 | J30: =INDEX('HY & Segments'!$A:$AG,MATCH($A30,'HY & Segments'!$A:$A,0),MATCH("1H"&RIGHT(J$1,2),'HY & Segments'!$3:$3,0))+INDEX('HY & Segments'!$A:$AG,MATCH($A30,'HY & Segments'!$A:$A,0),MATCH("2H"&RIGHT(J$1,2),'HY & Segments'!$3:$3,0)) -> -22.431341 | K30: =INDEX('HY & Segments'!$A:$AG,MATCH($A30,'HY & Segments'!$A:$A,0),MATCH("1H"&RIGHT(K$1,2),'HY & Segments'!$3:$3,0))+INDEX('HY & Segments'!$A:$AG,MATCH($A30,'HY & Segments'!$A:$A,0),MATCH("2H"&RIGHT(K$1,2),'HY & Segments'!$3:$3,0)) -> -23.070398 | L30: =INDEX('HY & Segments'!$A:$AG,MATCH($A30,'HY & Segments'!$A:$A,0),MATCH("1H"&RIGHT(L$1,2),'HY & Segments'!$3:$3,0))+INDEX('HY & Segments'!$A:$AG,MATCH($A30,'HY & Segments'!$A:$A,0),MATCH("2H"&RIGHT(L$1,2),'HY & Segments'!$3:$3,0)) -> -23.729794 | M30: =INDEX('HY & Segments'!$A:$AG,MATCH($A30,'HY & Segments'!$A:$A,0),MATCH("1H"&RIGHT(M$1,2),'HY & Segments'!$3:$3,0))+INDEX('HY & Segments'!$A:$AG,MATCH($A30,'HY & Segments'!$A:$A,0),MATCH("2H"&RIGHT(M$1,2),'HY & Segments'!$3:$3,0)) -> -24.410282 | N30: =INDEX('HY & Segments'!$A:$AG,MATCH($A30,'HY & Segments'!$A:$A,0),MATCH("1H"&RIGHT(N$1,2),'HY & Segments'!$3:$3,0))+INDEX('HY & Segments'!$A:$AG,MATCH($A30,'HY & Segments'!$A:$A,0),MATCH("2H"&RIGHT(N$1,2),'HY & Segments'!$3:$3,0)) -> -25.112646 | ... P30: =INDEX('HY & Segments'!$A:$AG,MATCH($A30,'HY & Segments'!$A:$A,0),MATCH("1H"&RIGHT(P$1,2),'HY & Segments'!$3:$3,0))+INDEX('HY & Segments'!$A:$AG,MATCH($A30,'HY & Segments'!$A:$A,0),MATCH("2H"&RIGHT(P$1,2),'HY & Segments'!$3:$3,0)) -> -26.58631
A31: OPEX-Total OpEx | B31: Total Operating Expenses | C31: NZDm | D31: =SUM(D27:D30) -> -225.4 | E31: =SUM(E27:E30) -> -213.8 | F31: =SUM(F27:F30) -> -212.5 | G31: =SUM(G27:G30) -> -223.93944 | H31: =SUM(H27:H30) -> -231.09703 | I31: =SUM(I27:I30) -> -237.61359 | J31: =SUM(J27:J30) -> -244.33427 | K31: =SUM(K27:K30) -> -251.26646 | ... P31: =SUM(P27:P30) -> -289.38206
B32: OpEx Growth | C32: % YoY | E32: =IF(D31=0,"",E31/D31-1) -> -0.051464064 | F32: =IF(E31=0,"",F31/E31-1) -> -0.006080449 | G32: =IF(F31=0,"",G31/F31-1) -> 0.053832637 | H32: =IF(G31=0,"",H31/G31-1) -> 0.031962188 | I32: =IF(H31=0,"",I31/H31-1) -> 0.028198362 | J32: =IF(I31=0,"",J31/I31-1) -> 0.028284066 | K32: =IF(J31=0,"",K31/J31-1) -> 0.028371784 | L32: =IF(K31=0,"",L31/K31-1) -> 0.028461551 | ... P32: =IF(O31=0,"",P31/O31-1) -> 0.028841728
B34: EBITDA
A35: EBITDA-Steel EBITDA | B35: Steel EBITDA | C35: NZDm | D35: 113.2 | E35: 68.8 | F35: 44.1 | G35: =INDEX('HY & Segments'!$A:$AG,MATCH($A35,'HY & Segments'!$A:$A,0),MATCH("1H"&RIGHT(G$1,2),'HY & Segments'!$3:$3,0))+INDEX('HY & Segments'!$A:$AG,MATCH($A35,'HY & Segments'!$A:$A,0),MATCH("2H"&RIGHT(G$1,2),'HY & Segments'!$3:$3,0)) -> 75.951706 | H35: =INDEX('HY & Segments'!$A:$AG,MATCH($A35,'HY & Segments'!$A:$A,0),MATCH("1H"&RIGHT(H$1,2),'HY & Segments'!$3:$3,0))+INDEX('HY & Segments'!$A:$AG,MATCH($A35,'HY & Segments'!$A:$A,0),MATCH("2H"&RIGHT(H$1,2),'HY & Segments'!$3:$3,0)) -> 92.617551 | I35: =INDEX('HY & Segments'!$A:$AG,MATCH($A35,'HY & Segments'!$A:$A,0),MATCH("1H"&RIGHT(I$1,2),'HY & Segments'!$3:$3,0))+INDEX('HY & Segments'!$A:$AG,MATCH($A35,'HY & Segments'!$A:$A,0),MATCH("2H"&RIGHT(I$1,2),'HY & Segments'!$3:$3,0)) -> 100.3771 | J35: =INDEX('HY & Segments'!$A:$AG,MATCH($A35,'HY & Segments'!$A:$A,0),MATCH("1H"&RIGHT(J$1,2),'HY & Segments'!$3:$3,0))+INDEX('HY & Segments'!$A:$AG,MATCH($A35,'HY & Segments'!$A:$A,0),MATCH("2H"&RIGHT(J$1,2),'HY & Segments'!$3:$3,0)) -> 108.63416 | K35: =INDEX('HY & Segments'!$A:$AG,MATCH($A35,'HY & Segments'!$A:$A,0),MATCH("1H"&RIGHT(K$1,2),'HY & Segments'!$3:$3,0))+INDEX('HY & Segments'!$A:$AG,MATCH($A35,'HY & Segments'!$A:$A,0),MATCH("2H"&RIGHT(K$1,2),'HY & Segments'!$3:$3,0)) -> 117.41807 | L35: =INDEX('HY & Segments'!$A:$AG,MATCH($A35,'HY & Segments'!$A:$A,0),MATCH("1H"&RIGHT(L$1,2),'HY & Segments'!$3:$3,0))+INDEX('HY & Segments'!$A:$AG,MATCH($A35,'HY & Segments'!$A:$A,0),MATCH("2H"&RIGHT(L$1,2),'HY & Segments'!$3:$3,0)) -> 126.75987 | M35: =INDEX('HY & Segments'!$A:$AG,MATCH($A35,'HY & Segments'!$A:$A,0),MATCH("1H"&RIGHT(M$1,2),'HY & Segments'!$3:$3,0))+INDEX('HY & Segments'!$A:$AG,MATCH($A35,'HY & Segments'!$A:$A,0),MATCH("2H"&RIGHT(M$1,2),'HY & Segments'!$3:$3,0)) -> 136.69237 | N35: =INDEX('HY & Segments'!$A:$AG,MATCH($A35,'HY & Segments'!$A:$A,0),MATCH("1H"&RIGHT(N$1,2),'HY & Segments'!$3:$3,0))+INDEX('HY & Segments'!$A:$AG,MATCH($A35,'HY & Segments'!$A:$A,0),MATCH("2H"&RIGHT(N$1,2),'HY & Segments'!$3:$3,0)) -> 147.25025 | ... P35: =INDEX('HY & Segments'!$A:$AG,MATCH($A35,'HY & Segments'!$A:$A,0),MATCH("1H"&RIGHT(P$1,2),'HY & Segments'!$3:$3,0))+INDEX('HY & Segments'!$A:$AG,MATCH($A35,'HY & Segments'!$A:$A,0),MATCH("2H"&RIGHT(P$1,2),'HY & Segments'!$3:$3,0)) -> 170.39085
A36: EBITDA-Metals EBITDA | B36: Metals EBITDA | C36: NZDm | D36: 131 | E36: 99.5 | F36: 84.9 | G36: =INDEX('HY & Segments'!$A:$AG,MATCH($A36,'HY & Segments'!$A:$A,0),MATCH("1H"&RIGHT(G$1,2),'HY & Segments'!$3:$3,0))+INDEX('HY & Segments'!$A:$AG,MATCH($A36,'HY & Segments'!$A:$A,0),MATCH("2H"&RIGHT(G$1,2),'HY & Segments'!$3:$3,0)) -> 80.855645 | H36: =INDEX('HY & Segments'!$A:$AG,MATCH($A36,'HY & Segments'!$A:$A,0),MATCH("1H"&RIGHT(H$1,2),'HY & Segments'!$3:$3,0))+INDEX('HY & Segments'!$A:$AG,MATCH($A36,'HY & Segments'!$A:$A,0),MATCH("2H"&RIGHT(H$1,2),'HY & Segments'!$3:$3,0)) -> 89.042348 | I36: =INDEX('HY & Segments'!$A:$AG,MATCH($A36,'HY & Segments'!$A:$A,0),MATCH("1H"&RIGHT(I$1,2),'HY & Segments'!$3:$3,0))+INDEX('HY & Segments'!$A:$AG,MATCH($A36,'HY & Segments'!$A:$A,0),MATCH("2H"&RIGHT(I$1,2),'HY & Segments'!$3:$3,0)) -> 97.777435 | J36: =INDEX('HY & Segments'!$A:$AG,MATCH($A36,'HY & Segments'!$A:$A,0),MATCH("1H"&RIGHT(J$1,2),'HY & Segments'!$3:$3,0))+INDEX('HY & Segments'!$A:$AG,MATCH($A36,'HY & Segments'!$A:$A,0),MATCH("2H"&RIGHT(J$1,2),'HY & Segments'!$3:$3,0)) -> 107.09378 | K36: =INDEX('HY & Segments'!$A:$AG,MATCH($A36,'HY & Segments'!$A:$A,0),MATCH("1H"&RIGHT(K$1,2),'HY & Segments'!$3:$3,0))+INDEX('HY & Segments'!$A:$AG,MATCH($A36,'HY & Segments'!$A:$A,0),MATCH("2H"&RIGHT(K$1,2),'HY & Segments'!$3:$3,0)) -> 117.02614 | L36: =INDEX('HY & Segments'!$A:$AG,MATCH($A36,'HY & Segments'!$A:$A,0),MATCH("1H"&RIGHT(L$1,2),'HY & Segments'!$3:$3,0))+INDEX('HY & Segments'!$A:$AG,MATCH($A36,'HY & Segments'!$A:$A,0),MATCH("2H"&RIGHT(L$1,2),'HY & Segments'!$3:$3,0)) -> 127.61127 | M36: =INDEX('HY & Segments'!$A:$AG,MATCH($A36,'HY & Segments'!$A:$A,0),MATCH("1H"&RIGHT(M$1,2),'HY & Segments'!$3:$3,0))+INDEX('HY & Segments'!$A:$AG,MATCH($A36,'HY & Segments'!$A:$A,0),MATCH("2H"&RIGHT(M$1,2),'HY & Segments'!$3:$3,0)) -> 138.88805 | N36: =INDEX('HY & Segments'!$A:$AG,MATCH($A36,'HY & Segments'!$A:$A,0),MATCH("1H"&RIGHT(N$1,2),'HY & Segments'!$3:$3,0))+INDEX('HY & Segments'!$A:$AG,MATCH($A36,'HY & Segments'!$A:$A,0),MATCH("2H"&RIGHT(N$1,2),'HY & Segments'!$3:$3,0)) -> 150.89757 | ... P36: =INDEX('HY & Segments'!$A:$AG,MATCH($A36,'HY & Segments'!$A:$A,0),MATCH("1H"&RIGHT(P$1,2),'HY & Segments'!$3:$3,0))+INDEX('HY & Segments'!$A:$AG,MATCH($A36,'HY & Segments'!$A:$A,0),MATCH("2H"&RIGHT(P$1,2),'HY & Segments'!$3:$3,0)) -> 177.29114
A37: EBITDA-Corporate EBITDA | B37: Corporate EBITDA | C37: NZDm | D37: -25.3 | E37: -20.7 | F37: -17 | G37: =INDEX('HY & Segments'!$A:$AG,MATCH($A37,'HY & Segments'!$A:$A,0),MATCH("1H"&RIGHT(G$1,2),'HY & Segments'!$3:$3,0))+INDEX('HY & Segments'!$A:$AG,MATCH($A37,'HY & Segments'!$A:$A,0),MATCH("2H"&RIGHT(G$1,2),'HY & Segments'!$3:$3,0)) -> -22.000268 | H37: =INDEX('HY & Segments'!$A:$AG,MATCH($A37,'HY & Segments'!$A:$A,0),MATCH("1H"&RIGHT(H$1,2),'HY & Segments'!$3:$3,0))+INDEX('HY & Segments'!$A:$AG,MATCH($A37,'HY & Segments'!$A:$A,0),MATCH("2H"&RIGHT(H$1,2),'HY & Segments'!$3:$3,0)) -> -24.036813 | I37: =INDEX('HY & Segments'!$A:$AG,MATCH($A37,'HY & Segments'!$A:$A,0),MATCH("1H"&RIGHT(I$1,2),'HY & Segments'!$3:$3,0))+INDEX('HY & Segments'!$A:$AG,MATCH($A37,'HY & Segments'!$A:$A,0),MATCH("2H"&RIGHT(I$1,2),'HY & Segments'!$3:$3,0)) -> -25.376865 | J37: =INDEX('HY & Segments'!$A:$AG,MATCH($A37,'HY & Segments'!$A:$A,0),MATCH("1H"&RIGHT(J$1,2),'HY & Segments'!$3:$3,0))+INDEX('HY & Segments'!$A:$AG,MATCH($A37,'HY & Segments'!$A:$A,0),MATCH("2H"&RIGHT(J$1,2),'HY & Segments'!$3:$3,0)) -> -26.791626 | K37: =INDEX('HY & Segments'!$A:$AG,MATCH($A37,'HY & Segments'!$A:$A,0),MATCH("1H"&RIGHT(K$1,2),'HY & Segments'!$3:$3,0))+INDEX('HY & Segments'!$A:$AG,MATCH($A37,'HY & Segments'!$A:$A,0),MATCH("2H"&RIGHT(K$1,2),'HY & Segments'!$3:$3,0)) -> -28.285259 | L37: =INDEX('HY & Segments'!$A:$AG,MATCH($A37,'HY & Segments'!$A:$A,0),MATCH("1H"&RIGHT(L$1,2),'HY & Segments'!$3:$3,0))+INDEX('HY & Segments'!$A:$AG,MATCH($A37,'HY & Segments'!$A:$A,0),MATCH("2H"&RIGHT(L$1,2),'HY & Segments'!$3:$3,0)) -> -29.862162 | M37: =INDEX('HY & Segments'!$A:$AG,MATCH($A37,'HY & Segments'!$A:$A,0),MATCH("1H"&RIGHT(M$1,2),'HY & Segments'!$3:$3,0))+INDEX('HY & Segments'!$A:$AG,MATCH($A37,'HY & Segments'!$A:$A,0),MATCH("2H"&RIGHT(M$1,2),'HY & Segments'!$3:$3,0)) -> -31.526978 | N37: =INDEX('HY & Segments'!$A:$AG,MATCH($A37,'HY & Segments'!$A:$A,0),MATCH("1H"&RIGHT(N$1,2),'HY & Segments'!$3:$3,0))+INDEX('HY & Segments'!$A:$AG,MATCH($A37,'HY & Segments'!$A:$A,0),MATCH("2H"&RIGHT(N$1,2),'HY & Segments'!$3:$3,0)) -> -33.284607 | ... P37: =INDEX('HY & Segments'!$A:$AG,MATCH($A37,'HY & Segments'!$A:$A,0),MATCH("1H"&RIGHT(P$1,2),'HY & Segments'!$3:$3,0))+INDEX('HY & Segments'!$A:$AG,MATCH($A37,'HY & Segments'!$A:$A,0),MATCH("2H"&RIGHT(P$1,2),'HY & Segments'!$3:$3,0)) -> -37.099291
A38: EBITDA-Underlying EBITDA | B38: Underlying EBITDA | C38: NZDm | D38: =SUM(D35:D37) -> 218.9 | E38: =SUM(E35:E37) -> 147.6 | F38: =SUM(F35:F37) -> 112 | G38: =SUM(G35:G37) -> 134.80708 | H38: =SUM(H35:H37) -> 157.62309 | I38: =SUM(I35:I37) -> 172.77767 | J38: =SUM(J35:J37) -> 188.93631 | K38: =SUM(K35:K37) -> 206.15894 | ... P38: =SUM(P35:P37) -> 310.58269
B39: EBITDA Growth | C39: % YoY | E39: =IF(D38=0,"",E38/D38-1) -> -0.32571951 | F39: =IF(E38=0,"",F38/E38-1) -> -0.24119241 | G39: =IF(F38=0,"",G38/F38-1) -> 0.20363467 | H39: =IF(G38=0,"",H38/G38-1) -> 0.16924928 | I39: =IF(H38=0,"",I38/H38-1) -> 0.096144474 | J39: =IF(I38=0,"",J38/I38-1) -> 0.0935227 | K39: =IF(J38=0,"",K38/J38-1) -> 0.091155774 | L39: =IF(K38=0,"",L38/K38-1) -> 0.089009154 | ... P39: =IF(O38=0,"",P38/O38-1) -> 0.082119806
B40: EBITDA Margin | C40: % | D40: =IF(D9=0,"",D38/D9) -> 0.17583742 | E40: =IF(E9=0,"",E38/E9) -> 0.1386827 | F40: =IF(F9=0,"",F38/F9) -> 0.118131 | G40: =IF(G9=0,"",G38/G9) -> 0.12534734 | H40: =IF(H9=0,"",H38/H9) -> 0.13488986 | I40: =IF(I9=0,"",I38/I9) -> 0.14005094 | J40: =IF(J9=0,"",J38/J9) -> 0.14506169 | K40: =IF(K9=0,"",K38/K9) -> 0.1499265 | ... P40: =IF(P9=0,"",P38/P9) -> 0.1722059
B42: Statutory EBITDA Adjustments
A43: Stat-SBP | B43: Share-based payments | C43: NZDm | D43: 0 | E43: 0 | F43: 0 | G43: =0 -> 0 | H43: =0 -> 0 | I43: =0 -> 0 | J43: =0 -> 0 | K43: =0 -> 0 | L43: =0 -> 0 | M43: =0 -> 0 | N43: =0 -> 0 | ... P43: =0 -> 0
A44: Stat-Significant Items | B44: Significant items | C44: NZDm | D44: -10.2 | E44: 0 | F44: -3.1 | G44: =INDEX('HY & Segments'!$A:$AG,MATCH($A44,'HY & Segments'!$A:$A,0),MATCH("1H"&RIGHT(G$1,2),'HY & Segments'!$3:$3,0))+INDEX('HY & Segments'!$A:$AG,MATCH($A44,'HY & Segments'!$A:$A,0),MATCH("2H"&RIGHT(G$1,2),'HY & Segments'!$3:$3,0)) -> -1 | H44: =INDEX('HY & Segments'!$A:$AG,MATCH($A44,'HY & Segments'!$A:$A,0),MATCH("1H"&RIGHT(H$1,2),'HY & Segments'!$3:$3,0))+INDEX('HY & Segments'!$A:$AG,MATCH($A44,'HY & Segments'!$A:$A,0),MATCH("2H"&RIGHT(H$1,2),'HY & Segments'!$3:$3,0)) -> 0 | I44: =INDEX('HY & Segments'!$A:$AG,MATCH($A44,'HY & Segments'!$A:$A,0),MATCH("1H"&RIGHT(I$1,2),'HY & Segments'!$3:$3,0))+INDEX('HY & Segments'!$A:$AG,MATCH($A44,'HY & Segments'!$A:$A,0),MATCH("2H"&RIGHT(I$1,2),'HY & Segments'!$3:$3,0)) -> 0 | J44: =INDEX('HY & Segments'!$A:$AG,MATCH($A44,'HY & Segments'!$A:$A,0),MATCH("1H"&RIGHT(J$1,2),'HY & Segments'!$3:$3,0))+INDEX('HY & Segments'!$A:$AG,MATCH($A44,'HY & Segments'!$A:$A,0),MATCH("2H"&RIGHT(J$1,2),'HY & Segments'!$3:$3,0)) -> 0 | K44: =INDEX('HY & Segments'!$A:$AG,MATCH($A44,'HY & Segments'!$A:$A,0),MATCH("1H"&RIGHT(K$1,2),'HY & Segments'!$3:$3,0))+INDEX('HY & Segments'!$A:$AG,MATCH($A44,'HY & Segments'!$A:$A,0),MATCH("2H"&RIGHT(K$1,2),'HY & Segments'!$3:$3,0)) -> 0 | L44: =INDEX('HY & Segments'!$A:$AG,MATCH($A44,'HY & Segments'!$A:$A,0),MATCH("1H"&RIGHT(L$1,2),'HY & Segments'!$3:$3,0))+INDEX('HY & Segments'!$A:$AG,MATCH($A44,'HY & Segments'!$A:$A,0),MATCH("2H"&RIGHT(L$1,2),'HY & Segments'!$3:$3,0)) -> 0 | M44: =INDEX('HY & Segments'!$A:$AG,MATCH($A44,'HY & Segments'!$A:$A,0),MATCH("1H"&RIGHT(M$1,2),'HY & Segments'!$3:$3,0))+INDEX('HY & Segments'!$A:$AG,MATCH($A44,'HY & Segments'!$A:$A,0),MATCH("2H"&RIGHT(M$1,2),'HY & Segments'!$3:$3,0)) -> 0 | N44: =INDEX('HY & Segments'!$A:$AG,MATCH($A44,'HY & Segments'!$A:$A,0),MATCH("1H"&RIGHT(N$1,2),'HY & Segments'!$3:$3,0))+INDEX('HY & Segments'!$A:$AG,MATCH($A44,'HY & Segments'!$A:$A,0),MATCH("2H"&RIGHT(N$1,2),'HY & Segments'!$3:$3,0)) -> 0 | ... P44: =INDEX('HY & Segments'!$A:$AG,MATCH($A44,'HY & Segments'!$A:$A,0),MATCH("1H"&RIGHT(P$1,2),'HY & Segments'!$3:$3,0))+INDEX('HY & Segments'!$A:$AG,MATCH($A44,'HY & Segments'!$A:$A,0),MATCH("2H"&RIGHT(P$1,2),'HY & Segments'!$3:$3,0)) -> 0
A45: Stat-Statutory EBITDA | B45: Statutory EBITDA | C45: NZDm | D45: =D38+D43+D44 -> 208.7 | E45: =E38+E43+E44 -> 147.6 | F45: =F38+F43+F44 -> 108.9 | G45: =G38+G43+G44 -> 133.80708 | H45: =H38+H43+H44 -> 157.62309 | I45: =I38+I43+I44 -> 172.77767 | J45: =J38+J43+J44 -> 188.93631 | K45: =K38+K43+K44 -> 206.15894 | ... P45: =P38+P43+P44 -> 310.58269
B47: D&A
A48: DA-Depreciation PPE | B48: Depreciation PPE & Intangibles | C48: NZDm | D48: -15.1 | E48: -18.2 | F48: -18.2 | G48: =INDEX('HY & Segments'!$A:$AG,MATCH($A48,'HY & Segments'!$A:$A,0),MATCH("1H"&RIGHT(G$1,2),'HY & Segments'!$3:$3,0))+INDEX('HY & Segments'!$A:$AG,MATCH($A48,'HY & Segments'!$A:$A,0),MATCH("2H"&RIGHT(G$1,2),'HY & Segments'!$3:$3,0)) -> -20.498992 | H48: =INDEX('HY & Segments'!$A:$AG,MATCH($A48,'HY & Segments'!$A:$A,0),MATCH("1H"&RIGHT(H$1,2),'HY & Segments'!$3:$3,0))+INDEX('HY & Segments'!$A:$AG,MATCH($A48,'HY & Segments'!$A:$A,0),MATCH("2H"&RIGHT(H$1,2),'HY & Segments'!$3:$3,0)) -> -22.241604 | I48: =INDEX('HY & Segments'!$A:$AG,MATCH($A48,'HY & Segments'!$A:$A,0),MATCH("1H"&RIGHT(I$1,2),'HY & Segments'!$3:$3,0))+INDEX('HY & Segments'!$A:$AG,MATCH($A48,'HY & Segments'!$A:$A,0),MATCH("2H"&RIGHT(I$1,2),'HY & Segments'!$3:$3,0)) -> -23.481573 | J48: =INDEX('HY & Segments'!$A:$AG,MATCH($A48,'HY & Segments'!$A:$A,0),MATCH("1H"&RIGHT(J$1,2),'HY & Segments'!$3:$3,0))+INDEX('HY & Segments'!$A:$AG,MATCH($A48,'HY & Segments'!$A:$A,0),MATCH("2H"&RIGHT(J$1,2),'HY & Segments'!$3:$3,0)) -> -24.790671 | K48: =INDEX('HY & Segments'!$A:$AG,MATCH($A48,'HY & Segments'!$A:$A,0),MATCH("1H"&RIGHT(K$1,2),'HY & Segments'!$3:$3,0))+INDEX('HY & Segments'!$A:$AG,MATCH($A48,'HY & Segments'!$A:$A,0),MATCH("2H"&RIGHT(K$1,2),'HY & Segments'!$3:$3,0)) -> -26.172751 | L48: =INDEX('HY & Segments'!$A:$AG,MATCH($A48,'HY & Segments'!$A:$A,0),MATCH("1H"&RIGHT(L$1,2),'HY & Segments'!$3:$3,0))+INDEX('HY & Segments'!$A:$AG,MATCH($A48,'HY & Segments'!$A:$A,0),MATCH("2H"&RIGHT(L$1,2),'HY & Segments'!$3:$3,0)) -> -27.631882 | M48: =INDEX('HY & Segments'!$A:$AG,MATCH($A48,'HY & Segments'!$A:$A,0),MATCH("1H"&RIGHT(M$1,2),'HY & Segments'!$3:$3,0))+INDEX('HY & Segments'!$A:$AG,MATCH($A48,'HY & Segments'!$A:$A,0),MATCH("2H"&RIGHT(M$1,2),'HY & Segments'!$3:$3,0)) -> -29.172359 | N48: =INDEX('HY & Segments'!$A:$AG,MATCH($A48,'HY & Segments'!$A:$A,0),MATCH("1H"&RIGHT(N$1,2),'HY & Segments'!$3:$3,0))+INDEX('HY & Segments'!$A:$AG,MATCH($A48,'HY & Segments'!$A:$A,0),MATCH("2H"&RIGHT(N$1,2),'HY & Segments'!$3:$3,0)) -> -30.798718 | ... P48: =INDEX('HY & Segments'!$A:$AG,MATCH($A48,'HY & Segments'!$A:$A,0),MATCH("1H"&RIGHT(P$1,2),'HY & Segments'!$3:$3,0))+INDEX('HY & Segments'!$A:$AG,MATCH($A48,'HY & Segments'!$A:$A,0),MATCH("2H"&RIGHT(P$1,2),'HY & Segments'!$3:$3,0)) -> -34.3285
A49: DA-ROU Amortisation | B49: ROU Asset Amortisation | C49: NZDm | D49: -29.4 | E49: -30.4 | F49: -32.3 | G49: =-F115/G52 -> -32.338045 | H49: =-G115/H52 -> -32.371265 | I49: =-H115/I52 -> -32.400272 | J49: =-I115/J52 -> -32.425601 | K49: =-J115/K52 -> -32.447717 | L49: =-K115/L52 -> -32.467029 | M49: =-L115/M52 -> -32.483892 | N49: =-M115/N52 -> -32.498616 | ... P49: =-O115/P52 -> -32.5227
A50: DA-Total DA | B50: Total D&A | C50: NZDm | D50: =D48+D49 -> -44.5 | E50: =E48+E49 -> -48.6 | F50: =F48+F49 -> -50.5 | G50: =G48+G49 -> -52.837036 | H50: =H48+H49 -> -54.612869 | I50: =I48+I49 -> -55.881845 | J50: =J48+J49 -> -57.216272 | K50: =K48+K49 -> -58.620468 | ... P50: =P48+P49 -> -66.8512
B51: D&A / Revenue | C51: % | D51: =IF(D9=0,"",D50/D9) -> -0.035745843 | E51: =IF(E9=0,"",E50/E9) -> -0.045663817 | F51: =IF(F9=0,"",F50/F9) -> -0.053264424 | G51: =IF(G9=0,"",G50/G9) -> -0.049129332 | H51: =IF(H9=0,"",H50/H9) -> -0.046736316 | I51: =IF(I9=0,"",I50/I9) -> -0.045296969 | J51: =IF(J9=0,"",J50/J9) -> -0.043929561 | K51: =IF(K9=0,"",K50/K9) -> -0.042630998 | ... P51: =IF(P9=0,"",P50/P9) -> -0.037066363
B52: Avg Lease Life | C52: years | E52: =D115/(-E49) -> 8.5657895 | F52: =E115/(-F49) -> 7.8854489 | G52: =F52 -> 7.8854489 | H52: =G52 -> 7.8854489 | I52: =H52 -> 7.8854489 | J52: =I52 -> 7.8854489 | K52: =J52 -> 7.8854489 | L52: =K52 -> 7.8854489 | M52: =L52 -> 7.8854489 | N52: =M52 -> 7.8854489 | ... P52: =O52 -> 7.8854489
B53: EBIT
A54: EBIT-Underlying EBIT | B54: Underlying EBIT | C54: NZDm | D54: =D38+D50 -> 174.4 | E54: =E38+E50 -> 99 | F54: =F38+F50 -> 61.5 | G54: =G38+G50 -> 81.970047 | H54: =H38+H50 -> 103.01022 | I54: =I38+I50 -> 116.89583 | J54: =J38+J50 -> 131.72004 | K54: =K38+K50 -> 147.53848 | ... P54: =P38+P50 -> 243.73149
B55: EBIT Growth | C55: % YoY | E55: =IF(D54=0,"",E54/D54-1) -> -0.43233945 | F55: =IF(E54=0,"",F54/E54-1) -> -0.37878788 | G55: =IF(F54=0,"",G54/F54-1) -> 0.33284629 | H55: =IF(G54=0,"",H54/G54-1) -> 0.2566812 | I55: =IF(H54=0,"",I54/H54-1) -> 0.1347984 | J55: =IF(I54=0,"",J54/I54-1) -> 0.12681554 | K55: =IF(J54=0,"",K54/J54-1) -> 0.12009136 | L55: =IF(K54=0,"",L54/K54-1) -> 0.11435383 | ... P55: =IF(O54=0,"",P54/O54-1) -> 0.097958838
B56: EBIT Margin | C56: % | D56: =IF(D9=0,"",D54/D9) -> 0.14009157 | E56: =IF(E9=0,"",E54/E9) -> 0.093018886 | F56: =IF(F9=0,"",F54/F9) -> 0.064866575 | G56: =IF(G9=0,"",G54/G9) -> 0.076218007 | H56: =IF(H9=0,"",H54/H9) -> 0.088153547 | I56: =IF(I9=0,"",I54/I9) -> 0.09475397 | J56: =IF(J9=0,"",J54/J9) -> 0.10113213 | K56: =IF(K9=0,"",K54/K9) -> 0.1072955 | ... P56: =IF(P9=0,"",P54/P9) -> 0.13513953
B58: Interest
A59: Int-Interest Income | B59: Interest Income | C59: NZDm | D59: 0.1 | E59: 0.3 | F59: 0.2 | G59: =INDEX('HY & Segments'!$A:$AG,MATCH($A59,'HY & Segments'!$A:$A,0),MATCH("1H"&RIGHT(G$1,2),'HY & Segments'!$3:$3,0))+INDEX('HY & Segments'!$A:$AG,MATCH($A59,'HY & Segments'!$A:$A,0),MATCH("2H"&RIGHT(G$1,2),'HY & Segments'!$3:$3,0)) -> 0.14439834 | H59: =INDEX('HY & Segments'!$A:$AG,MATCH($A59,'HY & Segments'!$A:$A,0),MATCH("1H"&RIGHT(H$1,2),'HY & Segments'!$3:$3,0))+INDEX('HY & Segments'!$A:$AG,MATCH($A59,'HY & Segments'!$A:$A,0),MATCH("2H"&RIGHT(H$1,2),'HY & Segments'!$3:$3,0)) -> 0.20760601 | I59: =INDEX('HY & Segments'!$A:$AG,MATCH($A59,'HY & Segments'!$A:$A,0),MATCH("1H"&RIGHT(I$1,2),'HY & Segments'!$3:$3,0))+INDEX('HY & Segments'!$A:$AG,MATCH($A59,'HY & Segments'!$A:$A,0),MATCH("2H"&RIGHT(I$1,2),'HY & Segments'!$3:$3,0)) -> 0.18006629 | J59: =INDEX('HY & Segments'!$A:$AG,MATCH($A59,'HY & Segments'!$A:$A,0),MATCH("1H"&RIGHT(J$1,2),'HY & Segments'!$3:$3,0))+INDEX('HY & Segments'!$A:$AG,MATCH($A59,'HY & Segments'!$A:$A,0),MATCH("2H"&RIGHT(J$1,2),'HY & Segments'!$3:$3,0)) -> 0.28665576 | K59: =INDEX('HY & Segments'!$A:$AG,MATCH($A59,'HY & Segments'!$A:$A,0),MATCH("1H"&RIGHT(K$1,2),'HY & Segments'!$3:$3,0))+INDEX('HY & Segments'!$A:$AG,MATCH($A59,'HY & Segments'!$A:$A,0),MATCH("2H"&RIGHT(K$1,2),'HY & Segments'!$3:$3,0)) -> 0.44172681 | L59: =INDEX('HY & Segments'!$A:$AG,MATCH($A59,'HY & Segments'!$A:$A,0),MATCH("1H"&RIGHT(L$1,2),'HY & Segments'!$3:$3,0))+INDEX('HY & Segments'!$A:$AG,MATCH($A59,'HY & Segments'!$A:$A,0),MATCH("2H"&RIGHT(L$1,2),'HY & Segments'!$3:$3,0)) -> 0.64781544 | M59: =INDEX('HY & Segments'!$A:$AG,MATCH($A59,'HY & Segments'!$A:$A,0),MATCH("1H"&RIGHT(M$1,2),'HY & Segments'!$3:$3,0))+INDEX('HY & Segments'!$A:$AG,MATCH($A59,'HY & Segments'!$A:$A,0),MATCH("2H"&RIGHT(M$1,2),'HY & Segments'!$3:$3,0)) -> 0.90772235 | N59: =INDEX('HY & Segments'!$A:$AG,MATCH($A59,'HY & Segments'!$A:$A,0),MATCH("1H"&RIGHT(N$1,2),'HY & Segments'!$3:$3,0))+INDEX('HY & Segments'!$A:$AG,MATCH($A59,'HY & Segments'!$A:$A,0),MATCH("2H"&RIGHT(N$1,2),'HY & Segments'!$3:$3,0)) -> 1.2245144 | ... P59: =INDEX('HY & Segments'!$A:$AG,MATCH($A59,'HY & Segments'!$A:$A,0),MATCH("1H"&RIGHT(P$1,2),'HY & Segments'!$3:$3,0))+INDEX('HY & Segments'!$A:$AG,MATCH($A59,'HY & Segments'!$A:$A,0),MATCH("2H"&RIGHT(P$1,2),'HY & Segments'!$3:$3,0)) -> 2.0423753
A60: Int-Lease Interest | B60: Interest on Lease Liabilities | C60: NZDm | D60: -16.4 | E60: -17 | F60: -18 | G60: =INDEX('HY & Segments'!$A:$AG,MATCH($A60,'HY & Segments'!$A:$A,0),MATCH("1H"&RIGHT(G$1,2),'HY & Segments'!$3:$3,0))+INDEX('HY & Segments'!$A:$AG,MATCH($A60,'HY & Segments'!$A:$A,0),MATCH("2H"&RIGHT(G$1,2),'HY & Segments'!$3:$3,0)) -> -18.0133 | H60: =INDEX('HY & Segments'!$A:$AG,MATCH($A60,'HY & Segments'!$A:$A,0),MATCH("1H"&RIGHT(H$1,2),'HY & Segments'!$3:$3,0))+INDEX('HY & Segments'!$A:$AG,MATCH($A60,'HY & Segments'!$A:$A,0),MATCH("2H"&RIGHT(H$1,2),'HY & Segments'!$3:$3,0)) -> -17.717528 | I60: =INDEX('HY & Segments'!$A:$AG,MATCH($A60,'HY & Segments'!$A:$A,0),MATCH("1H"&RIGHT(I$1,2),'HY & Segments'!$3:$3,0))+INDEX('HY & Segments'!$A:$AG,MATCH($A60,'HY & Segments'!$A:$A,0),MATCH("2H"&RIGHT(I$1,2),'HY & Segments'!$3:$3,0)) -> -17.459264 | J60: =INDEX('HY & Segments'!$A:$AG,MATCH($A60,'HY & Segments'!$A:$A,0),MATCH("1H"&RIGHT(J$1,2),'HY & Segments'!$3:$3,0))+INDEX('HY & Segments'!$A:$AG,MATCH($A60,'HY & Segments'!$A:$A,0),MATCH("2H"&RIGHT(J$1,2),'HY & Segments'!$3:$3,0)) -> -17.233753 | K60: =INDEX('HY & Segments'!$A:$AG,MATCH($A60,'HY & Segments'!$A:$A,0),MATCH("1H"&RIGHT(K$1,2),'HY & Segments'!$3:$3,0))+INDEX('HY & Segments'!$A:$AG,MATCH($A60,'HY & Segments'!$A:$A,0),MATCH("2H"&RIGHT(K$1,2),'HY & Segments'!$3:$3,0)) -> -17.036839 | L60: =INDEX('HY & Segments'!$A:$AG,MATCH($A60,'HY & Segments'!$A:$A,0),MATCH("1H"&RIGHT(L$1,2),'HY & Segments'!$3:$3,0))+INDEX('HY & Segments'!$A:$AG,MATCH($A60,'HY & Segments'!$A:$A,0),MATCH("2H"&RIGHT(L$1,2),'HY & Segments'!$3:$3,0)) -> -16.864898 | M60: =INDEX('HY & Segments'!$A:$AG,MATCH($A60,'HY & Segments'!$A:$A,0),MATCH("1H"&RIGHT(M$1,2),'HY & Segments'!$3:$3,0))+INDEX('HY & Segments'!$A:$AG,MATCH($A60,'HY & Segments'!$A:$A,0),MATCH("2H"&RIGHT(M$1,2),'HY & Segments'!$3:$3,0)) -> -16.714761 | N60: =INDEX('HY & Segments'!$A:$AG,MATCH($A60,'HY & Segments'!$A:$A,0),MATCH("1H"&RIGHT(N$1,2),'HY & Segments'!$3:$3,0))+INDEX('HY & Segments'!$A:$AG,MATCH($A60,'HY & Segments'!$A:$A,0),MATCH("2H"&RIGHT(N$1,2),'HY & Segments'!$3:$3,0)) -> -16.583665 | ... P60: =INDEX('HY & Segments'!$A:$AG,MATCH($A60,'HY & Segments'!$A:$A,0),MATCH("1H"&RIGHT(P$1,2),'HY & Segments'!$3:$3,0))+INDEX('HY & Segments'!$A:$AG,MATCH($A60,'HY & Segments'!$A:$A,0),MATCH("2H"&RIGHT(P$1,2),'HY & Segments'!$3:$3,0)) -> -16.369238
A61: Int-Bank Interest | B61: Bank Interest Expense | C61: NZDm | D61: -22.2 | E61: -23.4 | F61: -18.3 | G61: =INDEX('HY & Segments'!$A:$AG,MATCH($A61,'HY & Segments'!$A:$A,0),MATCH("1H"&RIGHT(G$1,2),'HY & Segments'!$3:$3,0))+INDEX('HY & Segments'!$A:$AG,MATCH($A61,'HY & Segments'!$A:$A,0),MATCH("2H"&RIGHT(G$1,2),'HY & Segments'!$3:$3,0)) -> -17.738705 | H61: =INDEX('HY & Segments'!$A:$AG,MATCH($A61,'HY & Segments'!$A:$A,0),MATCH("1H"&RIGHT(H$1,2),'HY & Segments'!$3:$3,0))+INDEX('HY & Segments'!$A:$AG,MATCH($A61,'HY & Segments'!$A:$A,0),MATCH("2H"&RIGHT(H$1,2),'HY & Segments'!$3:$3,0)) -> -19.111151 | I61: =INDEX('HY & Segments'!$A:$AG,MATCH($A61,'HY & Segments'!$A:$A,0),MATCH("1H"&RIGHT(I$1,2),'HY & Segments'!$3:$3,0))+INDEX('HY & Segments'!$A:$AG,MATCH($A61,'HY & Segments'!$A:$A,0),MATCH("2H"&RIGHT(I$1,2),'HY & Segments'!$3:$3,0)) -> -19.650242 | J61: =INDEX('HY & Segments'!$A:$AG,MATCH($A61,'HY & Segments'!$A:$A,0),MATCH("1H"&RIGHT(J$1,2),'HY & Segments'!$3:$3,0))+INDEX('HY & Segments'!$A:$AG,MATCH($A61,'HY & Segments'!$A:$A,0),MATCH("2H"&RIGHT(J$1,2),'HY & Segments'!$3:$3,0)) -> -20.219387 | K61: =INDEX('HY & Segments'!$A:$AG,MATCH($A61,'HY & Segments'!$A:$A,0),MATCH("1H"&RIGHT(K$1,2),'HY & Segments'!$3:$3,0))+INDEX('HY & Segments'!$A:$AG,MATCH($A61,'HY & Segments'!$A:$A,0),MATCH("2H"&RIGHT(K$1,2),'HY & Segments'!$3:$3,0)) -> -20.820262 | L61: =INDEX('HY & Segments'!$A:$AG,MATCH($A61,'HY & Segments'!$A:$A,0),MATCH("1H"&RIGHT(L$1,2),'HY & Segments'!$3:$3,0))+INDEX('HY & Segments'!$A:$AG,MATCH($A61,'HY & Segments'!$A:$A,0),MATCH("2H"&RIGHT(L$1,2),'HY & Segments'!$3:$3,0)) -> -21.454636 | M61: =INDEX('HY & Segments'!$A:$AG,MATCH($A61,'HY & Segments'!$A:$A,0),MATCH("1H"&RIGHT(M$1,2),'HY & Segments'!$3:$3,0))+INDEX('HY & Segments'!$A:$AG,MATCH($A61,'HY & Segments'!$A:$A,0),MATCH("2H"&RIGHT(M$1,2),'HY & Segments'!$3:$3,0)) -> -22.124376 | N61: =INDEX('HY & Segments'!$A:$AG,MATCH($A61,'HY & Segments'!$A:$A,0),MATCH("1H"&RIGHT(N$1,2),'HY & Segments'!$3:$3,0))+INDEX('HY & Segments'!$A:$AG,MATCH($A61,'HY & Segments'!$A:$A,0),MATCH("2H"&RIGHT(N$1,2),'HY & Segments'!$3:$3,0)) -> -22.831454 | ... P61: =INDEX('HY & Segments'!$A:$AG,MATCH($A61,'HY & Segments'!$A:$A,0),MATCH("1H"&RIGHT(P$1,2),'HY & Segments'!$3:$3,0))+INDEX('HY & Segments'!$A:$AG,MATCH($A61,'HY & Segments'!$A:$A,0),MATCH("2H"&RIGHT(P$1,2),'HY & Segments'!$3:$3,0)) -> -24.366066
A62: Int-Net Finance Costs | B62: Net Finance Costs | C62: NZDm | D62: =SUM(D59:D61) -> -38.5 | E62: =SUM(E59:E61) -> -40.1 | F62: =SUM(F59:F61) -> -36.1 | G62: =SUM(G59:G61) -> -35.607606 | H62: =SUM(H59:H61) -> -36.621073 | I62: =SUM(I59:I61) -> -36.92944 | J62: =SUM(J59:J61) -> -37.166484 | K62: =SUM(K59:K61) -> -37.415375 | ... P62: =SUM(P59:P61) -> -38.692929
B63: Interest Income Rate | C63: % | E63: =IF(D110=0,"",E59/D110) -> 0.014778325 | F63: =IF(E110=0,"",F59/E110) -> 0.0082987552 | G63: =IF(F110=0,"",G59/F110) -> 0.0082987552 | H63: =IF(G110=0,"",H59/G110) -> 0.0082987552 | I63: =IF(H110=0,"",I59/H110) -> 0.0082987552 | J63: =IF(I110=0,"",J59/I110) -> 0.0082987552 | K63: =IF(J110=0,"",K59/J110) -> 0.0082987552 | L63: =IF(K110=0,"",L59/K110) -> 0.0082987552 | ... P63: =IF(O110=0,"",P59/O110) -> 0.0082987552
B64: Lease Interest Rate | C64: % | E64: =-E60/((D127+E127)/2) -> 0.05862069 | F64: =-F60/((E127+F127)/2) -> 0.06147541 | G64: =F64 -> 0.06147541 | H64: =G64 -> 0.06147541 | I64: =H64 -> 0.06147541 | J64: =I64 -> 0.06147541 | K64: =J64 -> 0.06147541 | L64: =K64 -> 0.06147541 | M64: =L64 -> 0.06147541 | N64: =M64 -> 0.06147541 | ... P64: =O64 -> 0.06147541
B65: Bank Interest Rate | C65: % | E65: =IF((D128+E128)=0,"",-E61/((D128+E128)/2)) -> 0.070919836 | F65: =IF((E128+F128)=0,"",-F61/((E128+F128)/2)) -> 0.066593886 | G65: =IF((F128+G128)=0,"",-G61/((F128+G128)/2)) -> 0.066593886 | H65: =IF((G128+H128)=0,"",-H61/((G128+H128)/2)) -> 0.066593886 | I65: =IF((H128+I128)=0,"",-I61/((H128+I128)/2)) -> 0.066593886 | J65: =IF((I128+J128)=0,"",-J61/((I128+J128)/2)) -> 0.066593886 | K65: =IF((J128+K128)=0,"",-K61/((J128+K128)/2)) -> 0.066593886 | L65: =IF((K128+L128)=0,"",-L61/((K128+L128)/2)) -> 0.066593886 | ... P65: =IF((O128+P128)=0,"",-P61/((O128+P128)/2)) -> 0.066593886
B67: PBT, Tax, NPAT
A68: PBT-PBT | B68: PBT | C68: NZDm | D68: =D54+D62 -> 135.9 | E68: =E54+E62 -> 58.9 | F68: =F54+F62 -> 25.4 | G68: =G54+G62 -> 46.36244 | H68: =H54+H62 -> 66.389143 | I68: =I54+I62 -> 79.966389 | J68: =J54+J62 -> 94.553553 | K68: =K54+K62 -> 110.1231 | ... P68: =P54+P62 -> 205.03856
A69: Tax-Tax Expense | B69: Tax Expense | C69: NZDm | D69: -37 | E69: -18.9 | F69: -7.6 | G69: =INDEX('HY & Segments'!$A:$AG,MATCH($A69,'HY & Segments'!$A:$A,0),MATCH("1H"&RIGHT(G$1,2),'HY & Segments'!$3:$3,0))+INDEX('HY & Segments'!$A:$AG,MATCH($A69,'HY & Segments'!$A:$A,0),MATCH("2H"&RIGHT(G$1,2),'HY & Segments'!$3:$3,0)) -> -10.846525 | H69: =INDEX('HY & Segments'!$A:$AG,MATCH($A69,'HY & Segments'!$A:$A,0),MATCH("1H"&RIGHT(H$1,2),'HY & Segments'!$3:$3,0))+INDEX('HY & Segments'!$A:$AG,MATCH($A69,'HY & Segments'!$A:$A,0),MATCH("2H"&RIGHT(H$1,2),'HY & Segments'!$3:$3,0)) -> -15.339241 | I69: =INDEX('HY & Segments'!$A:$AG,MATCH($A69,'HY & Segments'!$A:$A,0),MATCH("1H"&RIGHT(I$1,2),'HY & Segments'!$3:$3,0))+INDEX('HY & Segments'!$A:$AG,MATCH($A69,'HY & Segments'!$A:$A,0),MATCH("2H"&RIGHT(I$1,2),'HY & Segments'!$3:$3,0)) -> -18.34194 | J69: =INDEX('HY & Segments'!$A:$AG,MATCH($A69,'HY & Segments'!$A:$A,0),MATCH("1H"&RIGHT(J$1,2),'HY & Segments'!$3:$3,0))+INDEX('HY & Segments'!$A:$AG,MATCH($A69,'HY & Segments'!$A:$A,0),MATCH("2H"&RIGHT(J$1,2),'HY & Segments'!$3:$3,0)) -> -21.577686 | K69: =INDEX('HY & Segments'!$A:$AG,MATCH($A69,'HY & Segments'!$A:$A,0),MATCH("1H"&RIGHT(K$1,2),'HY & Segments'!$3:$3,0))+INDEX('HY & Segments'!$A:$AG,MATCH($A69,'HY & Segments'!$A:$A,0),MATCH("2H"&RIGHT(K$1,2),'HY & Segments'!$3:$3,0)) -> -25.037463 | L69: =INDEX('HY & Segments'!$A:$AG,MATCH($A69,'HY & Segments'!$A:$A,0),MATCH("1H"&RIGHT(L$1,2),'HY & Segments'!$3:$3,0))+INDEX('HY & Segments'!$A:$AG,MATCH($A69,'HY & Segments'!$A:$A,0),MATCH("2H"&RIGHT(L$1,2),'HY & Segments'!$3:$3,0)) -> -28.73618 | M69: =INDEX('HY & Segments'!$A:$AG,MATCH($A69,'HY & Segments'!$A:$A,0),MATCH("1H"&RIGHT(M$1,2),'HY & Segments'!$3:$3,0))+INDEX('HY & Segments'!$A:$AG,MATCH($A69,'HY & Segments'!$A:$A,0),MATCH("2H"&RIGHT(M$1,2),'HY & Segments'!$3:$3,0)) -> -32.689463 | N69: =INDEX('HY & Segments'!$A:$AG,MATCH($A69,'HY & Segments'!$A:$A,0),MATCH("1H"&RIGHT(N$1,2),'HY & Segments'!$3:$3,0))+INDEX('HY & Segments'!$A:$AG,MATCH($A69,'HY & Segments'!$A:$A,0),MATCH("2H"&RIGHT(N$1,2),'HY & Segments'!$3:$3,0)) -> -36.913712 | ... P69: =INDEX('HY & Segments'!$A:$AG,MATCH($A69,'HY & Segments'!$A:$A,0),MATCH("1H"&RIGHT(P$1,2),'HY & Segments'!$3:$3,0))+INDEX('HY & Segments'!$A:$AG,MATCH($A69,'HY & Segments'!$A:$A,0),MATCH("2H"&RIGHT(P$1,2),'HY & Segments'!$3:$3,0)) -> -46.244941
B70: Underlying Tax Rate | C70: % | D70: =IF(D68=0,"",-D69/D68) -> 0.27225901 | E70: =IF(E68=0,"",-E69/E68) -> 0.32088285 | F70: =IF(F68=0,"",-F69/F68) -> 0.2992126 | G70: =IF(G68=0,"",-G69/G68) -> 0.23395069 | H70: =IF(H68=0,"",-H69/H68) -> 0.23105044 | I70: =IF(I68=0,"",-I69/I68) -> 0.22937062 | J70: =IF(J68=0,"",-J69/J68) -> 0.22820598 | K70: =IF(K68=0,"",-K69/K68) -> 0.22735886 | ... P70: =IF(P68=0,"",-P69/P68) -> 0.22554265
A71: NPAT-NCI | B71: Non-controlling Interests | C71: NZDm | D71: 0 | E71: 0 | F71: 0 | G71: =INDEX('HY & Segments'!$A:$AG,MATCH($A71,'HY & Segments'!$A:$A,0),MATCH("1H"&RIGHT(G$1,2),'HY & Segments'!$3:$3,0))+INDEX('HY & Segments'!$A:$AG,MATCH($A71,'HY & Segments'!$A:$A,0),MATCH("2H"&RIGHT(G$1,2),'HY & Segments'!$3:$3,0)) -> -0.8 | H71: =INDEX('HY & Segments'!$A:$AG,MATCH($A71,'HY & Segments'!$A:$A,0),MATCH("1H"&RIGHT(H$1,2),'HY & Segments'!$3:$3,0))+INDEX('HY & Segments'!$A:$AG,MATCH($A71,'HY & Segments'!$A:$A,0),MATCH("2H"&RIGHT(H$1,2),'HY & Segments'!$3:$3,0)) -> -0.98862754 | I71: =INDEX('HY & Segments'!$A:$AG,MATCH($A71,'HY & Segments'!$A:$A,0),MATCH("1H"&RIGHT(I$1,2),'HY & Segments'!$3:$3,0))+INDEX('HY & Segments'!$A:$AG,MATCH($A71,'HY & Segments'!$A:$A,0),MATCH("2H"&RIGHT(I$1,2),'HY & Segments'!$3:$3,0)) -> -1.0716526 | J71: =INDEX('HY & Segments'!$A:$AG,MATCH($A71,'HY & Segments'!$A:$A,0),MATCH("1H"&RIGHT(J$1,2),'HY & Segments'!$3:$3,0))+INDEX('HY & Segments'!$A:$AG,MATCH($A71,'HY & Segments'!$A:$A,0),MATCH("2H"&RIGHT(J$1,2),'HY & Segments'!$3:$3,0)) -> -1.160004 | K71: =INDEX('HY & Segments'!$A:$AG,MATCH($A71,'HY & Segments'!$A:$A,0),MATCH("1H"&RIGHT(K$1,2),'HY & Segments'!$3:$3,0))+INDEX('HY & Segments'!$A:$AG,MATCH($A71,'HY & Segments'!$A:$A,0),MATCH("2H"&RIGHT(K$1,2),'HY & Segments'!$3:$3,0)) -> -1.2539962 | L71: =INDEX('HY & Segments'!$A:$AG,MATCH($A71,'HY & Segments'!$A:$A,0),MATCH("1H"&RIGHT(L$1,2),'HY & Segments'!$3:$3,0))+INDEX('HY & Segments'!$A:$AG,MATCH($A71,'HY & Segments'!$A:$A,0),MATCH("2H"&RIGHT(L$1,2),'HY & Segments'!$3:$3,0)) -> -1.3539615 | M71: =INDEX('HY & Segments'!$A:$AG,MATCH($A71,'HY & Segments'!$A:$A,0),MATCH("1H"&RIGHT(M$1,2),'HY & Segments'!$3:$3,0))+INDEX('HY & Segments'!$A:$AG,MATCH($A71,'HY & Segments'!$A:$A,0),MATCH("2H"&RIGHT(M$1,2),'HY & Segments'!$3:$3,0)) -> -1.4602512 | N71: =INDEX('HY & Segments'!$A:$AG,MATCH($A71,'HY & Segments'!$A:$A,0),MATCH("1H"&RIGHT(N$1,2),'HY & Segments'!$3:$3,0))+INDEX('HY & Segments'!$A:$AG,MATCH($A71,'HY & Segments'!$A:$A,0),MATCH("2H"&RIGHT(N$1,2),'HY & Segments'!$3:$3,0)) -> -1.5732368 | ... P71: =INDEX('HY & Segments'!$A:$AG,MATCH($A71,'HY & Segments'!$A:$A,0),MATCH("1H"&RIGHT(P$1,2),'HY & Segments'!$3:$3,0))+INDEX('HY & Segments'!$A:$AG,MATCH($A71,'HY & Segments'!$A:$A,0),MATCH("2H"&RIGHT(P$1,2),'HY & Segments'!$3:$3,0)) -> -1.8208878
A72: NPAT-Underlying NPAT | B72: Underlying NPAT | C72: NZDm | D72: =D68+D69+D71 -> 98.9 | E72: =E68+E69+E71 -> 40 | F72: =F68+F69+F71 -> 17.8 | G72: =G68+G69+G71 -> 34.715916 | H72: =H68+H69+H71 -> 50.061275 | I72: =I68+I69+I71 -> 60.552796 | J72: =J68+J69+J71 -> 71.815863 | K72: =K68+K69+K71 -> 83.831642 | ... P72: =P68+P69+P71 -> 156.97273
A73: NPAT-Sig Items AT | B73: Significant Items After Tax | C73: NZDm | D73: -7.2 | E73: 0 | F73: -2.2 | G73: =INDEX('HY & Segments'!$A:$AG,MATCH($A73,'HY & Segments'!$A:$A,0),MATCH("1H"&RIGHT(G$1,2),'HY & Segments'!$3:$3,0))+INDEX('HY & Segments'!$A:$AG,MATCH($A73,'HY & Segments'!$A:$A,0),MATCH("2H"&RIGHT(G$1,2),'HY & Segments'!$3:$3,0)) -> -0.7 | H73: =INDEX('HY & Segments'!$A:$AG,MATCH($A73,'HY & Segments'!$A:$A,0),MATCH("1H"&RIGHT(H$1,2),'HY & Segments'!$3:$3,0))+INDEX('HY & Segments'!$A:$AG,MATCH($A73,'HY & Segments'!$A:$A,0),MATCH("2H"&RIGHT(H$1,2),'HY & Segments'!$3:$3,0)) -> 0 | I73: =INDEX('HY & Segments'!$A:$AG,MATCH($A73,'HY & Segments'!$A:$A,0),MATCH("1H"&RIGHT(I$1,2),'HY & Segments'!$3:$3,0))+INDEX('HY & Segments'!$A:$AG,MATCH($A73,'HY & Segments'!$A:$A,0),MATCH("2H"&RIGHT(I$1,2),'HY & Segments'!$3:$3,0)) -> 0 | J73: =INDEX('HY & Segments'!$A:$AG,MATCH($A73,'HY & Segments'!$A:$A,0),MATCH("1H"&RIGHT(J$1,2),'HY & Segments'!$3:$3,0))+INDEX('HY & Segments'!$A:$AG,MATCH($A73,'HY & Segments'!$A:$A,0),MATCH("2H"&RIGHT(J$1,2),'HY & Segments'!$3:$3,0)) -> 0 | K73: =INDEX('HY & Segments'!$A:$AG,MATCH($A73,'HY & Segments'!$A:$A,0),MATCH("1H"&RIGHT(K$1,2),'HY & Segments'!$3:$3,0))+INDEX('HY & Segments'!$A:$AG,MATCH($A73,'HY & Segments'!$A:$A,0),MATCH("2H"&RIGHT(K$1,2),'HY & Segments'!$3:$3,0)) -> 0 | L73: =INDEX('HY & Segments'!$A:$AG,MATCH($A73,'HY & Segments'!$A:$A,0),MATCH("1H"&RIGHT(L$1,2),'HY & Segments'!$3:$3,0))+INDEX('HY & Segments'!$A:$AG,MATCH($A73,'HY & Segments'!$A:$A,0),MATCH("2H"&RIGHT(L$1,2),'HY & Segments'!$3:$3,0)) -> 0 | M73: =INDEX('HY & Segments'!$A:$AG,MATCH($A73,'HY & Segments'!$A:$A,0),MATCH("1H"&RIGHT(M$1,2),'HY & Segments'!$3:$3,0))+INDEX('HY & Segments'!$A:$AG,MATCH($A73,'HY & Segments'!$A:$A,0),MATCH("2H"&RIGHT(M$1,2),'HY & Segments'!$3:$3,0)) -> 0 | N73: =INDEX('HY & Segments'!$A:$AG,MATCH($A73,'HY & Segments'!$A:$A,0),MATCH("1H"&RIGHT(N$1,2),'HY & Segments'!$3:$3,0))+INDEX('HY & Segments'!$A:$AG,MATCH($A73,'HY & Segments'!$A:$A,0),MATCH("2H"&RIGHT(N$1,2),'HY & Segments'!$3:$3,0)) -> 0 | ... P73: =INDEX('HY & Segments'!$A:$AG,MATCH($A73,'HY & Segments'!$A:$A,0),MATCH("1H"&RIGHT(P$1,2),'HY & Segments'!$3:$3,0))+INDEX('HY & Segments'!$A:$AG,MATCH($A73,'HY & Segments'!$A:$A,0),MATCH("2H"&RIGHT(P$1,2),'HY & Segments'!$3:$3,0)) -> 0
A74: NPAT-Statutory NPAT | B74: Statutory NPAT | C74: NZDm | D74: =D72+D73 -> 91.7 | E74: =E72+E73 -> 40 | F74: =F72+F73 -> 15.6 | G74: =G72+G73 -> 34.015916 | H74: =H72+H73 -> 50.061275 | I74: =I72+I73 -> 60.552796 | J74: =J72+J73 -> 71.815863 | K74: =K72+K73 -> 83.831642 | ... P74: =P72+P73 -> 156.97273
B75: NPAT Growth | C75: % YoY | E75: =IF(D72=0,"",E72/D72-1) -> -0.59555106 | F75: =IF(E72=0,"",F72/E72-1) -> -0.555 | G75: =IF(F72=0,"",G72/F72-1) -> 0.95033234 | H75: =IF(G72=0,"",H72/G72-1) -> 0.44202663 | I75: =IF(H72=0,"",I72/H72-1) -> 0.20957359 | J75: =IF(I72=0,"",J72/I72-1) -> 0.18600408 | K75: =IF(J72=0,"",K72/J72-1) -> 0.16731372 | L75: =IF(K72=0,"",L72/K72-1) -> 0.15288456 | ... P75: =IF(O72=0,"",P72/O72-1) -> 0.11787289
B76: NPAT Margin | C76: % | D76: =IF(D9=0,"",D72/D9) -> 0.079444132 | E76: =IF(E9=0,"",E72/E9) -> 0.037583388 | F76: =IF(F9=0,"",F72/F9) -> 0.018774391 | G76: =IF(G9=0,"",G72/G9) -> 0.032279814 | H76: =IF(H9=0,"",H72/H9) -> 0.042841177 | I76: =IF(I9=0,"",I72/I9) -> 0.04908317 | J76: =IF(J9=0,"",J72/J9) -> 0.055138849 | K76: =IF(K9=0,"",K72/K9) -> 0.060965507 | ... P76: =IF(P9=0,"",P72/P9) -> 0.087035212
B78: EPS & Dividends
A79: EPS-YE Shares | B79: YE Basic Shares Outstanding | C79: #m | D79: 131.409 | E79: 131.409 | F79: 131.785 | G79: 146.53 | H79: =G79+IF(Value!$C$4=0,0,H170/Value!$C$4) -> 146.53 | I79: =H79+IF(Value!$C$4=0,0,I170/Value!$C$4) -> 146.53 | J79: =I79+IF(Value!$C$4=0,0,J170/Value!$C$4) -> 146.53 | K79: =J79+IF(Value!$C$4=0,0,K170/Value!$C$4) -> 146.53 | L79: =K79+IF(Value!$C$4=0,0,L170/Value!$C$4) -> 146.53 | M79: =L79+IF(Value!$C$4=0,0,M170/Value!$C$4) -> 146.53 | N79: =M79+IF(Value!$C$4=0,0,N170/Value!$C$4) -> 146.53 | O79: =N79+IF(Value!$C$4=0,0,O170/Value!$C$4) -> 146.53 | P79: =O79+IF(Value!$C$4=0,0,P170/Value!$C$4) -> 146.53
A80: EPS-WASO Basic | B80: WASO Basic | C80: #m | D80: 131.409 | E80: 131.409 | F80: 131.695 | G80: =IF(G79=0,"",AVERAGE(F79,G79)) -> 139.1575 | H80: =IF(H79=0,"",AVERAGE(G79,H79)) -> 146.53 | I80: =IF(I79=0,"",AVERAGE(H79,I79)) -> 146.53 | J80: =IF(J79=0,"",AVERAGE(I79,J79)) -> 146.53 | K80: =IF(K79=0,"",AVERAGE(J79,K79)) -> 146.53 | L80: =IF(L79=0,"",AVERAGE(K79,L79)) -> 146.53 | M80: =IF(M79=0,"",AVERAGE(L79,M79)) -> 146.53 | N80: =IF(N79=0,"",AVERAGE(M79,N79)) -> 146.53 | ... P80: =IF(P79=0,"",AVERAGE(O79,P79)) -> 146.53
A81: EPS-Dilution | B81: Dilution | C81: #m | D81: =D82-D80 -> 0 | E81: =E82-E80 -> 0 | F81: =F82-F80 -> 0 | G81: =F81 -> 0 | H81: =G81 -> 0 | I81: =H81 -> 0 | J81: =I81 -> 0 | K81: =J81 -> 0 | L81: =K81 -> 0 | M81: =L81 -> 0 | N81: =M81 -> 0 | ... P81: =O81 -> 0
A82: EPS-WASO Diluted | B82: WASO Diluted | C82: #m | D82: 131.409 | E82: 131.409 | F82: 131.695 | G82: =G80+G81 -> 139.1575 | H82: =H80+H81 -> 146.53 | I82: =I80+I81 -> 146.53 | J82: =J80+J81 -> 146.53 | K82: =K80+K81 -> 146.53 | L82: =L80+L81 -> 146.53 | M82: =M80+M81 -> 146.53 | N82: =N80+N81 -> 146.53 | ... P82: =P80+P81 -> 146.53
A84: EPS-Underlying EPS | B84: Underlying EPS | C84: NZDps | D84: =IF(D82=0,"",D72/D82) -> 0.75261207 | E84: =IF(E82=0,"",E72/E82) -> 0.30439315 | F84: =IF(F82=0,"",F72/F82) -> 0.13516079 | G84: =IF(G82=0,"",G72/G82) -> 0.24947211 | H84: =IF(H82=0,"",H72/H82) -> 0.34164523 | I84: =IF(I82=0,"",I72/I82) -> 0.41324504 | J84: =IF(J82=0,"",J72/J82) -> 0.4901103 | K84: =IF(K82=0,"",K72/K82) -> 0.57211248 | ... P84: =IF(P82=0,"",P72/P82) -> 1.0712669
A85: EPS-Statutory EPS | B85: Statutory EPS | C85: NZDps | D85: =IF(D82=0,"",D74/D82) -> 0.69782131 | E85: =IF(E82=0,"",E74/E82) -> 0.30439315 | F85: =IF(F82=0,"",F74/F82) -> 0.11845552 | G85: =IF(G82=0,"",G74/G82) -> 0.24444184 | H85: =IF(H82=0,"",H74/H82) -> 0.34164523 | I85: =IF(I82=0,"",I74/I82) -> 0.41324504 | J85: =IF(J82=0,"",J74/J82) -> 0.4901103 | K85: =IF(K82=0,"",K74/K82) -> 0.57211248 | ... P85: =IF(P82=0,"",P74/P82) -> 1.0712669
B86: EPS Growth | C86: % YoY | E86: =IF(D84=0,"",E84/D84-1) -> -0.59555106 | F86: =IF(E84=0,"",F84/E84-1) -> -0.5559664 | G86: =IF(F84=0,"",G84/F84-1) -> 0.84574326 | H86: =IF(G84=0,"",H84/G84-1) -> 0.36947261 | I86: =IF(H84=0,"",I84/H84-1) -> 0.20957359 | J86: =IF(I84=0,"",J84/I84-1) -> 0.18600408 | K86: =IF(J84=0,"",K84/J84-1) -> 0.16731372 | L86: =IF(K84=0,"",L84/K84-1) -> 0.15288456 | ... P86: =IF(O84=0,"",P84/O84-1) -> 0.11787289
A88: Div-DPS | B88: DPS | C88: NZDps | D88: 0.55 | E88: 0.24 | F88: 0.06 | G88: =G90*G84 -> 0.1107446 | H88: =H90*H84 -> 0.15166169 | I88: =I90*I84 -> 0.18344597 | J88: =J90*J84 -> 0.21756767 | K88: =K90*K84 -> 0.25396973 | L88: =L90*L84 -> 0.29279778 | M88: =M90*M84 -> 0.33420484 | N88: =N90*N84 -> 0.37835182 | ... P88: =P90*P84 -> 0.47555222
A89: Div-Total Dividends | B89: Total Dividends | C89: NZDm | D89: =D88*D80 -> 72.27495 | E89: =E88*E80 -> 31.53816 | F89: =F88*F80 -> 7.9017 | G89: =G88*G80 -> 15.410941 | H89: =H88*H80 -> 22.222987 | I89: =I88*I80 -> 26.880339 | J89: =J88*J80 -> 31.880191 | K89: =K88*K80 -> 37.214185 | ... P89: =P88*P80 -> 69.682666
B90: Payout Ratio | C90: % | D90: =IF(D84=0,"",D88/D84) -> 0.73078817 | E90: =IF(E84=0,"",E88/E84) -> 0.788454 | F90: =IF(F84=0,"",F88/F84) -> 0.44391573 | G90: =F90 -> 0.44391573 | H90: =G90 -> 0.44391573 | I90: =H90 -> 0.44391573 | J90: =I90 -> 0.44391573 | K90: =J90 -> 0.44391573 | L90: =K90 -> 0.44391573 | M90: =L90 -> 0.44391573 | N90: =M90 -> 0.44391573 | ... P90: =O90 -> 0.44391573
B91: Dividend Yield | C91: % | D91: =IF(Value!$C$4=0,"",D88/Value!$C$4) -> 0.069532238 | E91: =IF(Value!$C$4=0,"",E88/Value!$C$4) -> 0.03034134 | F91: =IF(Value!$C$4=0,"",F88/Value!$C$4) -> 0.007585335 | G91: =IF(Value!$C$4=0,"",G88/Value!$C$4) -> 0.014000581 | H91: =IF(Value!$C$4=0,"",H88/Value!$C$4) -> 0.019173412 | I91: =IF(Value!$C$4=0,"",I88/Value!$C$4) -> 0.023191653 | J91: =IF(Value!$C$4=0,"",J88/Value!$C$4) -> 0.027505395 | K91: =IF(Value!$C$4=0,"",K88/Value!$C$4) -> 0.032107425 | ... P91: =IF(Value!$C$4=0,"",P88/Value!$C$4) -> 0.060120381
B92: Dividend Growth | C92: % YoY | E92: =IF(D88=0,"",E88/D88-1) -> -0.56363636 | F92: =IF(E88=0,"",F88/E88-1) -> -0.75 | G92: =IF(F88=0,"",G88/F88-1) -> 0.84574326 | H92: =IF(G88=0,"",H88/G88-1) -> 0.36947261 | I92: =IF(H88=0,"",I88/H88-1) -> 0.20957359 | J92: =IF(I88=0,"",J88/I88-1) -> 0.18600408 | K92: =IF(J88=0,"",K88/J88-1) -> 0.16731372 | L92: =IF(K88=0,"",L88/K88-1) -> 0.15288456 | ... P92: =IF(O88=0,"",P88/O88-1) -> 0.11787289
B94: Operating Metrics
A95: KPI-Steel Volume | B95: Steel Volume | C95: 000t | D95: 182.8 | E95: 162 | F95: 152.7 | G95: =INDEX('HY & Segments'!$A:$AG,MATCH($A95,'HY & Segments'!$A:$A,0),MATCH("1H"&RIGHT(G$1,2),'HY & Segments'!$3:$3,0))+INDEX('HY & Segments'!$A:$AG,MATCH($A95,'HY & Segments'!$A:$A,0),MATCH("2H"&RIGHT(G$1,2),'HY & Segments'!$3:$3,0)) -> 189.268 | H95: =INDEX('HY & Segments'!$A:$AG,MATCH($A95,'HY & Segments'!$A:$A,0),MATCH("1H"&RIGHT(H$1,2),'HY & Segments'!$3:$3,0))+INDEX('HY & Segments'!$A:$AG,MATCH($A95,'HY & Segments'!$A:$A,0),MATCH("2H"&RIGHT(H$1,2),'HY & Segments'!$3:$3,0)) -> 205.94604 | I95: =INDEX('HY & Segments'!$A:$AG,MATCH($A95,'HY & Segments'!$A:$A,0),MATCH("1H"&RIGHT(I$1,2),'HY & Segments'!$3:$3,0))+INDEX('HY & Segments'!$A:$AG,MATCH($A95,'HY & Segments'!$A:$A,0),MATCH("2H"&RIGHT(I$1,2),'HY & Segments'!$3:$3,0)) -> 212.12442 | J95: =INDEX('HY & Segments'!$A:$AG,MATCH($A95,'HY & Segments'!$A:$A,0),MATCH("1H"&RIGHT(J$1,2),'HY & Segments'!$3:$3,0))+INDEX('HY & Segments'!$A:$AG,MATCH($A95,'HY & Segments'!$A:$A,0),MATCH("2H"&RIGHT(J$1,2),'HY & Segments'!$3:$3,0)) -> 218.48815 | K95: =INDEX('HY & Segments'!$A:$AG,MATCH($A95,'HY & Segments'!$A:$A,0),MATCH("1H"&RIGHT(K$1,2),'HY & Segments'!$3:$3,0))+INDEX('HY & Segments'!$A:$AG,MATCH($A95,'HY & Segments'!$A:$A,0),MATCH("2H"&RIGHT(K$1,2),'HY & Segments'!$3:$3,0)) -> 225.0428 | L95: =INDEX('HY & Segments'!$A:$AG,MATCH($A95,'HY & Segments'!$A:$A,0),MATCH("1H"&RIGHT(L$1,2),'HY & Segments'!$3:$3,0))+INDEX('HY & Segments'!$A:$AG,MATCH($A95,'HY & Segments'!$A:$A,0),MATCH("2H"&RIGHT(L$1,2),'HY & Segments'!$3:$3,0)) -> 231.79408 | M95: =INDEX('HY & Segments'!$A:$AG,MATCH($A95,'HY & Segments'!$A:$A,0),MATCH("1H"&RIGHT(M$1,2),'HY & Segments'!$3:$3,0))+INDEX('HY & Segments'!$A:$AG,MATCH($A95,'HY & Segments'!$A:$A,0),MATCH("2H"&RIGHT(M$1,2),'HY & Segments'!$3:$3,0)) -> 238.7479 | N95: =INDEX('HY & Segments'!$A:$AG,MATCH($A95,'HY & Segments'!$A:$A,0),MATCH("1H"&RIGHT(N$1,2),'HY & Segments'!$3:$3,0))+INDEX('HY & Segments'!$A:$AG,MATCH($A95,'HY & Segments'!$A:$A,0),MATCH("2H"&RIGHT(N$1,2),'HY & Segments'!$3:$3,0)) -> 245.91034 | ... P95: =INDEX('HY & Segments'!$A:$AG,MATCH($A95,'HY & Segments'!$A:$A,0),MATCH("1H"&RIGHT(P$1,2),'HY & Segments'!$3:$3,0))+INDEX('HY & Segments'!$A:$AG,MATCH($A95,'HY & Segments'!$A:$A,0),MATCH("2H"&RIGHT(P$1,2),'HY & Segments'!$3:$3,0)) -> 260.88628
A96: KPI-Metals Volume | B96: Metals Volume | C96: 000t | D96: 68.6 | E96: 66.5 | F96: 61.1 | G96: =INDEX('HY & Segments'!$A:$AG,MATCH($A96,'HY & Segments'!$A:$A,0),MATCH("1H"&RIGHT(G$1,2),'HY & Segments'!$3:$3,0))+INDEX('HY & Segments'!$A:$AG,MATCH($A96,'HY & Segments'!$A:$A,0),MATCH("2H"&RIGHT(G$1,2),'HY & Segments'!$3:$3,0)) -> 61.367 | H96: =INDEX('HY & Segments'!$A:$AG,MATCH($A96,'HY & Segments'!$A:$A,0),MATCH("1H"&RIGHT(H$1,2),'HY & Segments'!$3:$3,0))+INDEX('HY & Segments'!$A:$AG,MATCH($A96,'HY & Segments'!$A:$A,0),MATCH("2H"&RIGHT(H$1,2),'HY & Segments'!$3:$3,0)) -> 63.20801 | I96: =INDEX('HY & Segments'!$A:$AG,MATCH($A96,'HY & Segments'!$A:$A,0),MATCH("1H"&RIGHT(I$1,2),'HY & Segments'!$3:$3,0))+INDEX('HY & Segments'!$A:$AG,MATCH($A96,'HY & Segments'!$A:$A,0),MATCH("2H"&RIGHT(I$1,2),'HY & Segments'!$3:$3,0)) -> 65.10425 | J96: =INDEX('HY & Segments'!$A:$AG,MATCH($A96,'HY & Segments'!$A:$A,0),MATCH("1H"&RIGHT(J$1,2),'HY & Segments'!$3:$3,0))+INDEX('HY & Segments'!$A:$AG,MATCH($A96,'HY & Segments'!$A:$A,0),MATCH("2H"&RIGHT(J$1,2),'HY & Segments'!$3:$3,0)) -> 67.057378 | K96: =INDEX('HY & Segments'!$A:$AG,MATCH($A96,'HY & Segments'!$A:$A,0),MATCH("1H"&RIGHT(K$1,2),'HY & Segments'!$3:$3,0))+INDEX('HY & Segments'!$A:$AG,MATCH($A96,'HY & Segments'!$A:$A,0),MATCH("2H"&RIGHT(K$1,2),'HY & Segments'!$3:$3,0)) -> 69.069099 | L96: =INDEX('HY & Segments'!$A:$AG,MATCH($A96,'HY & Segments'!$A:$A,0),MATCH("1H"&RIGHT(L$1,2),'HY & Segments'!$3:$3,0))+INDEX('HY & Segments'!$A:$AG,MATCH($A96,'HY & Segments'!$A:$A,0),MATCH("2H"&RIGHT(L$1,2),'HY & Segments'!$3:$3,0)) -> 71.141172 | M96: =INDEX('HY & Segments'!$A:$AG,MATCH($A96,'HY & Segments'!$A:$A,0),MATCH("1H"&RIGHT(M$1,2),'HY & Segments'!$3:$3,0))+INDEX('HY & Segments'!$A:$AG,MATCH($A96,'HY & Segments'!$A:$A,0),MATCH("2H"&RIGHT(M$1,2),'HY & Segments'!$3:$3,0)) -> 73.275407 | N96: =INDEX('HY & Segments'!$A:$AG,MATCH($A96,'HY & Segments'!$A:$A,0),MATCH("1H"&RIGHT(N$1,2),'HY & Segments'!$3:$3,0))+INDEX('HY & Segments'!$A:$AG,MATCH($A96,'HY & Segments'!$A:$A,0),MATCH("2H"&RIGHT(N$1,2),'HY & Segments'!$3:$3,0)) -> 75.473669 | ... P96: =INDEX('HY & Segments'!$A:$AG,MATCH($A96,'HY & Segments'!$A:$A,0),MATCH("1H"&RIGHT(P$1,2),'HY & Segments'!$3:$3,0))+INDEX('HY & Segments'!$A:$AG,MATCH($A96,'HY & Segments'!$A:$A,0),MATCH("2H"&RIGHT(P$1,2),'HY & Segments'!$3:$3,0)) -> 80.070016
A97: KPI-Total Volume | B97: Total Volume | C97: 000t | D97: =D95+D96 -> 251.4 | E97: =E95+E96 -> 228.5 | F97: =F95+F96 -> 213.8 | G97: =G95+G96 -> 250.635 | H97: =H95+H96 -> 269.15405 | I97: =I95+I96 -> 277.22867 | J97: =J95+J96 -> 285.54553 | K97: =K95+K96 -> 294.1119 | ... P97: =P95+P96 -> 340.9563
A98: KPI-Steel Rev/t | B98: Steel Revenue / Tonne | C98: NZD | D98: =IF(D95=0,"",D7/D95*1000) -> 3262.035 | E98: =IF(E95=0,"",E7/E95*1000) -> 2909.2593 | F98: =IF(F95=0,"",F7/F95*1000) -> 2683.0386 | G98: =IF(G95=0,"",G7/G95*1000) -> 2816.299 | H98: =IF(H95=0,"",H7/H95*1000) -> 2893.273 | I98: =IF(I95=0,"",I7/I95*1000) -> 2965.6048 | J98: =IF(J95=0,"",J7/J95*1000) -> 3039.745 | K98: =IF(K95=0,"",K7/K95*1000) -> 3115.7386 | ... P98: =IF(P95=0,"",P7/P95*1000) -> 3525.1722
A99: KPI-Metals Rev/t | B99: Metals Revenue / Tonne | C99: NZD | D99: =IF(D96=0,"",D8/D96*1000) -> 9454.8105 | E99: =IF(E96=0,"",E8/E96*1000) -> 8917.2932 | F99: =IF(F96=0,"",F8/F96*1000) -> 8811.784 | G99: =IF(G96=0,"",G8/G96*1000) -> 8839.164 | H99: =IF(H96=0,"",H8/H96*1000) -> 9060.1431 | I99: =IF(I96=0,"",I8/I96*1000) -> 9286.6466 | J99: =IF(J96=0,"",J8/J96*1000) -> 9518.8128 | K99: =IF(K96=0,"",K8/K96*1000) -> 9756.7831 | ... P99: =IF(P96=0,"",P8/P96*1000) -> 11038.905
A100: KPI-Steel GP/t | B100: Steel GP / Tonne | C100: NZD | D100: =IF(D95=0,"",D19/D95*1000) -> 1017.7549 | E100: =IF(E95=0,"",E19/E95*1000) -> 887.03704 | F100: =IF(F95=0,"",F19/F95*1000) -> 780.61559 | G100: =IF(G95=0,"",G19/G95*1000) -> 836.48252 | H100: =IF(H95=0,"",H19/H95*1000) -> 859.66406 | I100: =IF(I95=0,"",I19/I95*1000) -> 881.15567 | J100: =IF(J95=0,"",J19/J95*1000) -> 903.18456 | K100: =IF(K95=0,"",K19/K95*1000) -> 925.76417 | ... P100: =IF(P95=0,"",P19/P95*1000) -> 1047.4172
A101: KPI-Metals GP/t | B101: Metals GP / Tonne | C101: NZD | D101: =IF(D96=0,"",D20/D96*1000) -> 3753.5598 | E101: =IF(E96=0,"",E20/E96*1000) -> 3272.1805 | F101: =IF(F96=0,"",F20/F96*1000) -> 3366.6121 | G101: =IF(G96=0,"",G20/G96*1000) -> 3267.1948 | H101: =IF(H96=0,"",H20/H96*1000) -> 3348.8747 | I101: =IF(I96=0,"",I20/I96*1000) -> 3432.5966 | J101: =IF(J96=0,"",J20/J96*1000) -> 3518.4115 | K101: =IF(K96=0,"",K20/K96*1000) -> 3606.3718 | ... P101: =IF(P96=0,"",P20/P96*1000) -> 4080.2786
A102: KPI-Customers | B102: Active Customers | C102: # | D102: 12108 | F102: 21727
A103: KPI-Headcount | B103: Headcount | C103: # | D103: 1361 | E103: 1326 | F103: 1344
A104: KPI-DIFOT | B104: DIFOT | C104: % | F104: 0.98
B105: Revenue per Employee | C105: NZDm | D105: =IF(D103=0,"",D9/D103) -> 0.91469508 | E105: =IF(E103=0,"",E9/E103) -> 0.80263952 | F105: =IF(F103=0,"",F9/F103) -> 0.70543155
B106: EBITDA per Employee | C106: NZDm | D106: =IF(D103=0,"",D38/D103) -> 0.16083762 | E106: =IF(E103=0,"",E38/E103) -> 0.11131222 | F106: =IF(F103=0,"",F38/F103) -> 0.083333333
B108: Balance Sheet
B109: Assets
A110: BS-Cash | B110: Cash | C110: NZDm | D110: 20.3 | E110: 24.1 | F110: 17.4 | G110: =F110+G177 -> 25.016524 | H110: =G110+H177 -> 21.697988 | I110: =H110+I177 -> 34.542019 | J110: =I110+J177 -> 53.22808 | K110: =J110+K177 -> 78.061761 | L110: =K110+L177 -> 109.38054 | M110: =L110+M177 -> 147.55399 | N110: =M110+N177 -> 192.98416 | ... P110: =O110+P177 -> 307.38924
A111: BS-Trade Receivables | B111: Trade Receivables | C111: NZDm | D111: 170.7 | E111: 144.8 | F111: 130.8 | G111: =G9*G118 -> 148.37174 | H111: =H9*H118 -> 161.21079 | I111: =I9*I118 -> 170.19829 | J111: =J9*J118 -> 179.68685 | K111: =K9*K118 -> 189.70439 | L111: =L9*L118 -> 200.28041 | M111: =M9*M118 -> 211.44604 | N111: =N9*N118 -> 223.23416 | ... P111: =P9*P118 -> 248.81859
A112: BS-Inventories | B112: Inventories | C112: NZDm | D112: 437.7 | E112: 360.6 | F112: 333.9 | G112: =G9*G119 -> 378.7563 | H112: =H9*H119 -> 411.53122 | I112: =I9*I119 -> 434.47408 | J112: =J9*J119 -> 458.69601 | K112: =K9*K119 -> 484.26831 | L112: =L9*L119 -> 511.26627 | M112: =M9*M119 -> 539.76937 | N112: =N9*N119 -> 569.86151 | ... P112: =P9*P119 -> 635.17223
A113: BS-PPE | B113: Property, Plant & Equipment | C113: NZDm | D113: 86.8 | E113: 95.7 | F113: 95.7 | G113: =F113-G160+G48 -> 99.362462 | H113: =G113-H160+H48 -> 103.37307 | I113: =H113-I160+I48 -> 107.60728 | J113: =I113-J160+J48 -> 112.07754 | K113: =J113-K160+K48 -> 116.79702 | L113: =K113-L160+L48 -> 121.7796 | M113: =L113-M160+M48 -> 127.03997 | N113: =M113-N160+N48 -> 132.5936 | ... P113: =O113-P160+P48 -> 144.64698
...

Sheet HY & Segments
D1: 2023 | E1: 2023 | F1: 2024 | G1: 2024 | H1: 2025 | I1: 2025 | J1: 2026 | K1: 2026 | L1: 2027 | M1: 2027 | N1: 2028 | O1: 2028 | P1: 2029 | Q1: 2029 | R1: 2030 | S1: 2030 | T1: 2031 | U1: 2031 | V1: 2032 | W1: 2032 | X1: 2033 | Y1: 2033 | Z1: 2034 | AA1: 2034 | AB1: 2035 | AC1: 2035
B2: VSL Segments (Half-Year) | D2: Actual ----------> | K2: Forecast ----->
B3: Vulcan Steel (VSL.NZ) | C3: Units | D3: 1H23 | E3: 2H23 | F3: 1H24 | G3: 2H24 | H3: 1H25 | I3: 2H25 | J3: 1H26 | K3: 2H26 | L3: 1H27 | M3: 2H27 | N3: 1H28 | O3: 2H28 | P3: 1H29 | Q3: 2H29 | R3: 1H30 | S3: 2H30 | T3: 1H31 | U3: 2H31 | V3: 1H32 | W3: 2H32 | X3: 1H33 | Y3: 2H33 | Z3: 1H34 | AA3: 2H34 | AB3: 1H35 | AC3: 2H35
D4: 44926 | E4: 45107 | F4: 45291 | G4: 45473 | H4: 45657 | I4: 45838 | J4: 46022 | K4: 46203 | L4: 46387 | M4: 46568 | N4: 46752 | O4: 46934 | P4: 47118 | Q4: 47299 | R4: 47483 | S4: 47664 | T4: 47848 | U4: 48029 | V4: 48213 | W4: 48395 | X4: 48579 | Y4: 48760 | Z4: 48944 | AA4: 49125 | AB4: 49309 | AC4: 49490
B5: P&L
B6: Revenue
A7: Rev-Steel Revenue | B7: Steel Revenue | C7: NZDm | D7: 316.5 | E7: =INDEX(Annual!$A:$R,MATCH($A7,Annual!$A:$A,0),MATCH(E$1,Annual!$A$1:$R$1,0))-D7 -> 279.8 | F7: 252.3 | G7: =INDEX(Annual!$A:$R,MATCH($A7,Annual!$A:$A,0),MATCH(G$1,Annual!$A$1:$R$1,0))-F7 -> 219 | H7: 209.9 | I7: =INDEX(Annual!$A:$R,MATCH($A7,Annual!$A:$A,0),MATCH(I$1,Annual!$A$1:$R$1,0))-H7 -> 199.8 | J7: 262.5 | K7: =K97 -> 270.53528 | L7: =L97 -> 310.2405 | M7: =M97 -> 285.61762 | N7: =N97 -> 327.53641 | O7: =O97 -> 301.5408 | P7: =P97 -> 345.79656 | Q7: =Q97 -> 318.3517 | R7: =R97 -> 365.07472 | ... AC7: =AC97 -> 440.83261
A8: Rev-Metals Revenue | B8: Metals Revenue | C8: NZDm | D8: 321.4 | E8: =INDEX(Annual!$A:$R,MATCH($A8,Annual!$A:$A,0),MATCH(E$1,Annual!$A$1:$R$1,0))-D8 -> 327.2 | F8: 311.7 | G8: =INDEX(Annual!$A:$R,MATCH($A8,Annual!$A:$A,0),MATCH(G$1,Annual!$A$1:$R$1,0))-F8 -> 281.3 | H8: 283.1 | I8: =INDEX(Annual!$A:$R,MATCH($A8,Annual!$A:$A,0),MATCH(I$1,Annual!$A$1:$R$1,0))-H8 -> 255.3 | J8: 272.9 | K8: =K110 -> 269.53297 | L8: =L110 -> 288.11417 | M8: =M110 -> 284.55944 | N8: =N110 -> 304.17654 | O8: =O110 -> 300.42363 | P8: =P110 -> 321.13438 | Q8: =Q110 -> 317.17224 | R8: =R110 -> 339.03762 | ... AC8: =AC110 -> 439.19938
A9: Rev-Total Revenue | B9: Total Revenue | C9: NZDm | D9: =D7+D8 -> 637.9 | E9: =E7+E8 -> 607 | F9: =F7+F8 -> 564 | G9: =G7+G8 -> 500.3 | H9: =H7+H8 -> 493 | I9: =I7+I8 -> 455.1 | J9: =J7+J8 -> 535.4 | K9: =K7+K8 -> 540.06825 | ... AC9: =AC7+AC8 -> 880.03199
B10: Revenue Growth (YoY) | C10: % YoY | F10: =IF(D9=0,"",F9/D9-1) -> -0.11584888 | G10: =IF(E9=0,"",G9/E9-1) -> -0.17578254 | H10: =IF(F9=0,"",H9/F9-1) -> -0.12588652 | I10: =IF(G9=0,"",I9/G9-1) -> -0.090345793 | J10: =IF(H9=0,"",J9/H9-1) -> 0.086004057 | K10: =IF(I9=0,"",K9/I9-1) -> 0.18670238 | L10: =IF(J9=0,"",L9/J9-1) -> 0.11758437 | M10: =IF(K9=0,"",M9/K9-1) -> 0.05575 | ... AC10: =IF(AA9=0,"",AC9/AA9-1) -> 0.05575
B12: COGS
A13: COGS-Steel COGS | B13: Steel COGS | C13: NZDm | D13: =-D7*(1-Inputs!D6) -> -214.587 | E13: =INDEX(Annual!$A:$R,MATCH($A13,Annual!$A:$A,0),MATCH(E$1,Annual!$A$1:$R$1,0))-D13 -> -195.6674 | F13: =-F7*(1-Inputs!E6) -> -162.9858 | G13: =INDEX(Annual!$A:$R,MATCH($A13,Annual!$A:$A,0),MATCH(G$1,Annual!$A$1:$R$1,0))-F13 -> -164.6142 | H13: =-H7*(1-Inputs!F6) -> -149.6587 | I13: =INDEX(Annual!$A:$R,MATCH($A13,Annual!$A:$A,0),MATCH(I$1,Annual!$A$1:$R$1,0))-H13 -> -140.8413 | J13: =-J7*(1-Inputs!G6) -> -184.0125 | K13: =-K7*(1-K98) -> -190.70341 | L13: =-L7*(1-L98) -> -217.47859 | M13: =-M7*(1-M98) -> -201.33512 | N13: =-N7*(1-N98) -> -229.60302 | O13: =-O7*(1-O98) -> -212.55955 | P13: =-P7*(1-P98) -> -242.40339 | Q13: =-Q7*(1-Q98) -> -224.40975 | R13: =-R7*(1-R98) -> -255.91738 | ... AC13: =-AC7*(1-AC98) -> -310.74794
A14: COGS-Metals COGS | B14: Metals COGS | C14: NZDm | D14: =-D8*(1-Inputs!D7) -> -194.1256 | E14: =INDEX(Annual!$A:$R,MATCH($A14,Annual!$A:$A,0),MATCH(E$1,Annual!$A$1:$R$1,0))-D14 -> -196.9802 | F14: =-F8*(1-Inputs!E7) -> -201.3582 | G14: =INDEX(Annual!$A:$R,MATCH($A14,Annual!$A:$A,0),MATCH(G$1,Annual!$A$1:$R$1,0))-F14 -> -174.0418 | H14: =-H8*(1-Inputs!F7) -> -169.86 | I14: =INDEX(Annual!$A:$R,MATCH($A14,Annual!$A:$A,0),MATCH(I$1,Annual!$A$1:$R$1,0))-H14 -> -162.84 | J14: =-J8*(1-Inputs!G7) -> -170.0167 | K14: =-K8*(1-K111) -> -171.91833 | L14: =-L8*(1-L111) -> -179.49513 | M14: =-M8*(1-M111) -> -181.50278 | N14: =-N8*(1-N111) -> -189.50198 | O14: =-O8*(1-O111) -> -191.62156 | P14: =-P8*(1-P111) -> -200.06672 | Q14: =-Q8*(1-Q111) -> -202.30446 | R14: =-R8*(1-R111) -> -211.22044 | ... AC14: =-AC8*(1-AC111) -> -280.13798
A15: COGS-Other COGS | B15: Other COGS | C15: NZDm | D15: 0 | E15: =INDEX(Annual!$A:$R,MATCH($A15,Annual!$A:$A,0),MATCH(E$1,Annual!$A$1:$R$1,0))-D15 -> 0 | F15: 0 | G15: =INDEX(Annual!$A:$R,MATCH($A15,Annual!$A:$A,0),MATCH(G$1,Annual!$A$1:$R$1,0))-F15 -> 0 | H15: 0 | I15: =INDEX(Annual!$A:$R,MATCH($A15,Annual!$A:$A,0),MATCH(I$1,Annual!$A$1:$R$1,0))-H15 -> 0 | J15: 0 | K15: =0 -> 0 | L15: =0 -> 0 | M15: =0 -> 0 | N15: =0 -> 0 | O15: =0 -> 0 | P15: =0 -> 0 | Q15: =0 -> 0 | R15: =0 -> 0 | ... AC15: =0 -> 0
A16: COGS-Total COGS | B16: Total COGS | C16: NZDm | D16: =SUM(D13:D15) -> -408.7126 | E16: =SUM(E13:E15) -> -392.6476 | F16: =SUM(F13:F15) -> -364.344 | G16: =SUM(G13:G15) -> -338.656 | H16: =SUM(H13:H15) -> -319.5187 | I16: =SUM(I13:I15) -> -303.6813 | J16: =SUM(J13:J15) -> -354.0292 | K16: =SUM(K13:K15) -> -362.62174 | ... AC16: =SUM(AC13:AC15) -> -590.88592
B18: Gross Profit
A19: GP-Steel GP | B19: Steel GP | C19: NZDm | D19: =D7+D13 -> 101.913 | E19: =E7+E13 -> 84.1326 | F19: =F7+F13 -> 89.3142 | G19: =G7+G13 -> 54.3858 | H19: =H7+H13 -> 60.2413 | I19: =I7+I13 -> 58.9587 | J19: =J7+J13 -> 78.4875 | K19: =K7+K13 -> 79.831874 | ... AC19: =AC7+AC13 -> 130.08467
A20: GP-Metals GP | B20: Metals GP | C20: NZDm | D20: =D8+D14 -> 127.2744 | E20: =E8+E14 -> 130.2198 | F20: =F8+F14 -> 110.3418 | G20: =G8+G14 -> 107.2582 | H20: =H8+H14 -> 113.24 | I20: =I8+I14 -> 92.46 | J20: =J8+J14 -> 102.8833 | K20: =K8+K14 -> 97.614645 | ... AC20: =AC8+AC14 -> 159.0614
A21: GP-Corporate GP | B21: Corporate/Elim | C21: NZDm | D21: =D22-D19-D20 -> 0 | E21: =E22-E19-E20 -> 0 | F21: =F22-F19-F20 -> 0 | G21: =G22-G19-G20 -> 0 | H21: =H22-H19-H20 -> 0 | I21: =I22-I19-I20 -> 0 | J21: =J22-J19-J20 -> 0 | K21: =K22-K19-K20 -> 0 | ... AC21: =AC22-AC19-AC20 -> 0
A22: GP-Gross Profit | B22: Gross Profit | C22: NZDm | D22: =D9+D16 -> 229.1874 | E22: =E9+E16 -> 214.3524 | F22: =F9+F16 -> 199.656 | G22: =G9+G16 -> 161.644 | H22: =H9+H16 -> 173.4813 | I22: =I9+I16 -> 151.4187 | J22: =J9+J16 -> 181.3708 | K22: =K9+K16 -> 177.44652 | ... AC22: =AC9+AC16 -> 289.14607
B23: GP Growth (YoY) | C23: % YoY | F23: =IF(D22=0,"",F22/D22-1) -> -0.12885263 | G23: =IF(E22=0,"",G22/E22-1) -> -0.24589601 | H23: =IF(F22=0,"",H22/F22-1) -> -0.13109899 | I23: =IF(G22=0,"",I22/G22-1) -> -0.063258148 | J23: =IF(H22=0,"",J22/H22-1) -> 0.045477524 | K23: =IF(I22=0,"",K22/I22-1) -> 0.17189303 | L23: =IF(J22=0,"",L22/J22-1) -> 0.11032731 | M23: =IF(K22=0,"",M22/K22-1) -> 0.05575 | ... AC23: =IF(AA22=0,"",AC22/AA22-1) -> 0.05575
B24: GP Margin | C24: % | D24: =IF(D9=0,"",D22/D9) -> 0.35928421 | E24: =IF(E9=0,"",E22/E9) -> 0.3531341 | F24: =IF(F9=0,"",F22/F9) -> 0.354 | G24: =IF(G9=0,"",G22/G9) -> 0.32309414 | H24: =IF(H9=0,"",H22/H9) -> 0.35188905 | I24: =IF(I9=0,"",I22/I9) -> 0.33271523 | J24: =IF(J9=0,"",J22/J9) -> 0.33875756 | K24: =IF(K9=0,"",K22/K9) -> 0.32856314 | ... AC24: =IF(AC9=0,"",AC22/AC9) -> 0.32856314
B25: Steel GP Margin | C25: % | D25: =IF(D7=0,"",D19/D7) -> 0.322 | E25: =IF(E7=0,"",E19/E7) -> 0.30068835 | F25: =IF(F7=0,"",F19/F7) -> 0.354 | G25: =IF(G7=0,"",G19/G7) -> 0.24833699 | H25: =IF(H7=0,"",H19/H7) -> 0.287 | I25: =IF(I7=0,"",I19/I7) -> 0.29508859 | J25: =IF(J7=0,"",J19/J7) -> 0.299 | K25: =IF(K7=0,"",K19/K7) -> 0.29508859 | ... AC25: =IF(AC7=0,"",AC19/AC7) -> 0.29508859
B26: Metals GP Margin | C26: % | D26: =IF(D8=0,"",D20/D8) -> 0.396 | E26: =IF(E8=0,"",E20/E8) -> 0.39798227 | F26: =IF(F8=0,"",F20/F8) -> 0.354 | G26: =IF(G8=0,"",G20/G8) -> 0.3812947 | H26: =IF(H8=0,"",H20/H8) -> 0.4 | I26: =IF(I8=0,"",I20/I8) -> 0.36216216 | J26: =IF(J8=0,"",J20/J8) -> 0.377 | K26: =IF(K8=0,"",K20/K8) -> 0.36216216 | ... AC26: =IF(AC8=0,"",AC20/AC8) -> 0.36216216
B28: Operating Expenses
A29: OPEX-Employee Benefits | B29: Employee Benefits | C29: NZDm | D29: -70.7 | E29: =INDEX(Annual!$A:$R,MATCH($A29,Annual!$A:$A,0),MATCH(E$1,Annual!$A$1:$R$1,0))-D29 -> -71.5 | F29: -71.5 | G29: =INDEX(Annual!$A:$R,MATCH($A29,Annual!$A:$A,0),MATCH(G$1,Annual!$A$1:$R$1,0))-F29 -> -67.8 | H29: -73.9 | I29: =INDEX(Annual!$A:$R,MATCH($A29,Annual!$A:$A,0),MATCH(I$1,Annual!$A$1:$R$1,0))-H29 -> -72.5 | J29: -88.7 | K29: =IF(I33=0,0,K33*I29/I33) -> -75.475094 | L29: =IF(J33=0,0,L33*J29/J33) -> -91.836994 | M29: =IF(K33=0,0,M33*K29/K33) -> -77.56866 | N29: =IF(L33=0,0,N33*L29/L33) -> -94.45495 | O29: =IF(M33=0,0,O33*M29/M33) -> -79.726087 | P29: =IF(N33=0,0,P33*N29/N33) -> -97.156309 | Q29: =IF(O33=0,0,Q33*O29/O33) -> -81.949615 | R29: =IF(P33=0,0,R33*P29/P33) -> -99.944156 | ... AC29: =IF(AA33=0,0,AC33*AA29/AA33) -> -96.816409
A30: OPEX-Selling & Distribution | B30: Selling & Distribution | C30: NZDm | D30: -13.3 | E30: =INDEX(Annual!$A:$R,MATCH($A30,Annual!$A:$A,0),MATCH(E$1,Annual!$A$1:$R$1,0))-D30 -> -13.4 | F30: -15 | G30: =INDEX(Annual!$A:$R,MATCH($A30,Annual!$A:$A,0),MATCH(G$1,Annual!$A$1:$R$1,0))-F30 -> -12.5 | H30: -11.6 | I30: =INDEX(Annual!$A:$R,MATCH($A30,Annual!$A:$A,0),MATCH(I$1,Annual!$A$1:$R$1,0))-H30 -> -10.9 | J30: -12.3 | K30: =IF(I33=0,0,K33*I30/I33) -> -11.34729 | L30: =IF(J33=0,0,L33*J30/J33) -> -12.735006 | M30: =IF(K33=0,0,M33*K30/K33) -> -11.662047 | N30: =IF(L33=0,0,N33*L30/L33) -> -13.098037 | O30: =IF(M33=0,0,O33*M30/M33) -> -11.986405 | P30: =IF(N33=0,0,P33*N30/N33) -> -13.472634 | Q30: =IF(O33=0,0,Q33*O30/O33) -> -12.320701 | R30: =IF(P33=0,0,R33*P30/P33) -> -13.859223 | ... AC30: =IF(AA33=0,0,AC33*AA30/AA33) -> -14.555846
A31: OPEX-Occupancy Costs | B31: Occupancy Costs | C31: NZDm | D31: -4.9 | E31: =INDEX(Annual!$A:$R,MATCH($A31,Annual!$A:$A,0),MATCH(E$1,Annual!$A$1:$R$1,0))-D31 -> -6.1 | F31: -7 | G31: =INDEX(Annual!$A:$R,MATCH($A31,Annual!$A:$A,0),MATCH(G$1,Annual!$A$1:$R$1,0))-F31 -> -5.8 | H31: -7.2 | I31: =INDEX(Annual!$A:$R,MATCH($A31,Annual!$A:$A,0),MATCH(I$1,Annual!$A$1:$R$1,0))-H31 -> -7 | J31: -8.3 | K31: =IF(I33=0,0,K33*I31/I33) -> -7.2872505 | L31: =IF(J33=0,0,L33*J31/J33) -> -8.5935406 | M31: =IF(K33=0,0,M33*K31/K33) -> -7.4893878 | N31: =IF(L33=0,0,N33*L31/L33) -> -8.8385128 | O31: =IF(M33=0,0,O33*M31/M33) -> -7.6976911 | P31: =IF(N33=0,0,P33*N31/N33) -> -9.0912894 | Q31: =IF(O33=0,0,Q33*O31/O33) -> -7.9123766 | R31: =IF(P33=0,0,R33*P31/P33) -> -9.3521589 | ... AC31: =IF(AA33=0,0,AC33*AA31/AA33) -> -9.3477912
A32: OPEX-General & Admin | B32: General & Admin | C32: NZDm | D32: -25.1 | E32: =INDEX(Annual!$A:$R,MATCH($A32,Annual!$A:$A,0),MATCH(E$1,Annual!$A$1:$R$1,0))-D32 -> -20.4 | F32: -24.5 | G32: =INDEX(Annual!$A:$R,MATCH($A32,Annual!$A:$A,0),MATCH(G$1,Annual!$A$1:$R$1,0))-F32 -> -9.7 | H32: -23.8 | I32: =INDEX(Annual!$A:$R,MATCH($A32,Annual!$A:$A,0),MATCH(I$1,Annual!$A$1:$R$1,0))-H32 -> -5.6 | J32: -14.7 | K32: =IF(I33=0,0,K33*I32/I33) -> -5.8298004 | L32: =IF(J33=0,0,L33*J32/J33) -> -15.219885 | M32: =IF(K33=0,0,M33*K32/K33) -> -5.9915103 | N32: =IF(L33=0,0,N33*L32/L33) -> -15.653752 | O32: =IF(M33=0,0,O33*M32/M33) -> -6.1581529 | P32: =IF(N33=0,0,P33*N32/N33) -> -16.10144 | Q32: =IF(O33=0,0,Q33*O32/O33) -> -6.3299013 | R32: =IF(P33=0,0,R33*P32/P33) -> -16.563462 | ... AC32: =IF(AA33=0,0,AC33*AA32/AA33) -> -7.478233
A33: OPEX-Total OpEx | B33: Total Operating Expenses | C33: NZDm | D33: =SUM(D29:D32) -> -114 | E33: =SUM(E29:E32) -> -111.4 | F33: =SUM(F29:F32) -> -118 | G33: =SUM(G29:G32) -> -95.8 | H33: =SUM(H29:H32) -> -116.5 | I33: =SUM(I29:I32) -> -96 | J33: =SUM(J29:J32) -> -124 | K33: =K42-K22 -> -99.939435 | L33: =L42-L22 -> -128.38543 | M33: =M42-M22 -> -102.7116 | N33: =N42-N22 -> -132.04525 | O33: =O42-O22 -> -105.56834 | P33: =P42-P22 -> -135.82167 | Q33: =Q42-Q22 -> -108.51259 | R33: =R42-R22 -> -139.719 | ... AC33: =AC42-AC22 -> -128.19828
B34: OpEx Growth (YoY) | C34: % YoY | F34: =IF(D33=0,"",F33/D33-1) -> 0.035087719 | G34: =IF(E33=0,"",G33/E33-1) -> -0.14003591 | H34: =IF(F33=0,"",H33/F33-1) -> -0.012711864 | I34: =IF(G33=0,"",I33/G33-1) -> 0.0020876827 | J34: =IF(H33=0,"",J33/H33-1) -> 0.064377682 | K34: =IF(I33=0,"",K33/I33-1) -> 0.041035785 | L34: =IF(J33=0,"",L33/J33-1) -> 0.035366333 | M34: =IF(K33=0,"",M33/K33-1) -> 0.027738491 | ... AC34: =IF(AA33=0,"",AC33/AA33-1) -> 0.028388535
B35: Cost-to-Income Ratio | C35: % | D35: =IF(D22=0,"",-D33/D22) -> 0.49740954 | E35: =IF(E22=0,"",-E33/E22) -> 0.51970493 | F35: =IF(F22=0,"",-F33/F22) -> 0.59101655 | G35: =IF(G22=0,"",-G33/G22) -> 0.59266041 | H35: =IF(H22=0,"",-H33/H22) -> 0.67154212 | I35: =IF(I22=0,"",-I33/I22) -> 0.63400359 | J35: =IF(J22=0,"",-J33/J22) -> 0.68368227 | K35: =IF(K22=0,"",-K33/K22) -> 0.56320877 | ... AC35: =IF(AC22=0,"",-AC33/AC22) -> 0.44336857
B37: EBITDA
A38: EBITDA-Steel EBITDA | B38: Steel EBITDA | C38: NZDm | D38: 64.3 | E38: =INDEX(Annual!$A:$R,MATCH($A38,Annual!$A:$A,0),MATCH(E$1,Annual!$A$1:$R$1,0))-D38 -> 48.9 | F38: 37.8 | G38: =INDEX(Annual!$A:$R,MATCH($A38,Annual!$A:$A,0),MATCH(G$1,Annual!$A$1:$R$1,0))-F38 -> 31 | H38: 22 | I38: =INDEX(Annual!$A:$R,MATCH($A38,Annual!$A:$A,0),MATCH(I$1,Annual!$A$1:$R$1,0))-H38 -> 22.1 | J38: 33.9 | K38: =K103 -> 42.051706 | L38: =L103 -> 47.059722 | M38: =M103 -> 45.557829 | N38: =N103 -> 51.088644 | O38: =O103 -> 49.288461 | P38: =P103 -> 55.377311 | Q38: =Q103 -> 53.256846 | R38: =R103 -> 59.941084 | ... AC38: =AC103 -> 82.902422
A39: EBITDA-Metals EBITDA | B39: Metals EBITDA | C39: NZDm | D39: 66.6 | E39: =INDEX(Annual!$A:$R,MATCH($A39,Annual!$A:$A,0),MATCH(E$1,Annual!$A$1:$R$1,0))-D39 -> 64.4 | F39: 53 | G39: =INDEX(Annual!$A:$R,MATCH($A39,Annual!$A:$A,0),MATCH(G$1,Annual!$A$1:$R$1,0))-F39 -> 46.5 | H39: 44.4 | I39: =INDEX(Annual!$A:$R,MATCH($A39,Annual!$A:$A,0),MATCH(I$1,Annual!$A$1:$R$1,0))-H39 -> 40.5 | J39: 36.5 | K39: =K116 -> 44.355645 | L39: =L116 -> 40.576161 | M39: =M116 -> 48.466186 | N39: =N116 -> 44.930601 | O39: =O116 -> 52.846833 | P39: =P116 -> 49.580109 | Q39: =Q116 -> 57.513668 | R39: =R116 -> 54.542442 | ... AC39: =AC116 -> 92.548203
A40: EBITDA-Corporate EBITDA | B40: Corporate EBITDA | C40: NZDm | D40: -15.7 | E40: =INDEX(Annual!$A:$R,MATCH($A40,Annual!$A:$A,0),MATCH(E$1,Annual!$A$1:$R$1,0))-D40 -> -9.6 | F40: -8.9 | G40: =INDEX(Annual!$A:$R,MATCH($A40,Annual!$A:$A,0),MATCH(G$1,Annual!$A$1:$R$1,0))-F40 -> -11.8 | H40: -9.5 | I40: =INDEX(Annual!$A:$R,MATCH($A40,Annual!$A:$A,0),MATCH(I$1,Annual!$A$1:$R$1,0))-H40 -> -7.5 | J40: -13.1 | K40: =-K9*K41 -> -8.9002679 | L40: =-L9*L41 -> -14.640355 | M40: =-M9*M41 -> -9.3964578 | N40: =-N9*N41 -> -15.456555 | O40: =-O9*O41 -> -9.9203103 | P40: =-P9*P41 -> -16.318258 | Q40: =-Q9*Q41 -> -10.473368 | R40: =-R9*R41 -> -17.228001 | ... AC40: =-AC9*AC41 -> -14.502834
B41: Corp EBITDA / Revenue | C41: % | D41: =IF(D9=0,"",-D40/D9) -> 0.024612008 | E41: =IF(E9=0,"",-E40/E9) -> 0.015815486 | F41: =IF(F9=0,"",-F40/F9) -> 0.015780142 | G41: =IF(G9=0,"",-G40/G9) -> 0.023585848 | H41: =IF(H9=0,"",-H40/H9) -> 0.019269777 | I41: =IF(I9=0,"",-I40/I9) -> 0.016479895 | J41: =IF(J9=0,"",-J40/J9) -> 0.024467688 | K41: =I41 -> 0.016479895 | L41: =J41 -> 0.024467688 | M41: =K41 -> 0.016479895 | N41: =L41 -> 0.024467688 | O41: =M41 -> 0.016479895 | P41: =N41 -> 0.024467688 | Q41: =O41 -> 0.016479895 | R41: =P41 -> 0.024467688 | ... AC41: =AA41 -> 0.016479895
A42: EBITDA-Underlying EBITDA | B42: Underlying EBITDA | C42: NZDm | D42: =SUM(D38:D40) -> 115.2 | E42: =SUM(E38:E40) -> 103.7 | F42: =SUM(F38:F40) -> 81.9 | G42: =SUM(G38:G40) -> 65.7 | H42: =SUM(H38:H40) -> 56.9 | I42: =SUM(I38:I40) -> 55.1 | J42: =SUM(J38:J40) -> 57.3 | K42: =SUM(K38:K40) -> 77.507083 | ... AC42: =SUM(AC38:AC40) -> 160.94779
B43: EBITDA Growth (YoY) | C43: % YoY | F43: =IF(D42=0,"",F42/D42-1) -> -0.2890625 | G43: =IF(E42=0,"",G42/E42-1) -> -0.36644166 | H43: =IF(F42=0,"",H42/F42-1) -> -0.30525031 | I43: =IF(G42=0,"",I42/G42-1) -> -0.16133942 | J43: =IF(H42=0,"",J42/H42-1) -> 0.007029877 | K43: =IF(I42=0,"",K42/I42-1) -> 0.40666213 | L43: =IF(J42=0,"",L42/J42-1) -> 0.27391846 | M43: =IF(K42=0,"",M42/K42-1) -> 0.091868691 | ... AC43: =IF(AA42=0,"",AC42/AA42-1) -> 0.078608253
B44: EBITDA Margin | C44: % | D44: =IF(D9=0,"",D42/D9) -> 0.18059257 | E44: =IF(E9=0,"",E42/E9) -> 0.1708402 | F44: =IF(F9=0,"",F42/F9) -> 0.14521277 | G44: =IF(G9=0,"",G42/G9) -> 0.13132121 | H44: =IF(H9=0,"",H42/H9) -> 0.11541582 | I44: =IF(I9=0,"",I42/I9) -> 0.12107229 | J44: =IF(J9=0,"",J42/J9) -> 0.10702279 | K44: =IF(K9=0,"",K42/K9) -> 0.1435135 | ... AC44: =IF(AC9=0,"",AC42/AC9) -> 0.18288857
B45: Steel EBITDA Margin | C45: % | D45: =IF(D7=0,"",D38/D7) -> 0.20315956 | E45: =IF(E7=0,"",E38/E7) -> 0.17476769 | F45: =IF(F7=0,"",F38/F7) -> 0.14982164 | G45: =IF(G7=0,"",G38/G7) -> 0.14155251 | H45: =IF(H7=0,"",H38/H7) -> 0.10481182 | I45: =IF(I7=0,"",I38/I7) -> 0.11061061 | J45: =IF(J7=0,"",J38/J7) -> 0.12914286 | K45: =IF(K7=0,"",K38/K7) -> 0.1554389 | ... AC45: =IF(AC7=0,"",AC38/AC7) -> 0.18805873
B46: Metals EBITDA Margin | C46: % | D46: =IF(D8=0,"",D39/D8) -> 0.20721842 | E46: =IF(E8=0,"",E39/E8) -> 0.19682152 | F46: =IF(F8=0,"",F39/F8) -> 0.17003529 | G46: =IF(G8=0,"",G39/G8) -> 0.16530395 | H46: =IF(H8=0,"",H39/H8) -> 0.15683504 | I46: =IF(I8=0,"",I39/I8) -> 0.1586369 | J46: =IF(J8=0,"",J39/J8) -> 0.13374863 | K46: =IF(K8=0,"",K39/K8) -> 0.16456482 | ... AC46: =IF(AC8=0,"",AC39/AC8) -> 0.21072025
A48: Stat-Significant Items | B48: Significant Items | C48: NZDm | D48: 0 | E48: =INDEX(Annual!$A:$R,MATCH($A48,Annual!$A:$A,0),MATCH(E$1,Annual!$A$1:$R$1,0))-D48 -> -10.2 | F48: 0 | G48: =INDEX(Annual!$A:$R,MATCH($A48,Annual!$A:$A,0),MATCH(G$1,Annual!$A$1:$R$1,0))-F48 -> 0 | H48: 0 | I48: =INDEX(Annual!$A:$R,MATCH($A48,Annual!$A:$A,0),MATCH(I$1,Annual!$A$1:$R$1,0))-H48 -> -3.1 | J48: -1 | K48: =0 -> 0 | L48: =0 -> 0 | M48: =0 -> 0 | N48: =0 -> 0 | O48: =0 -> 0 | P48: =0 -> 0 | Q48: =0 -> 0 | R48: =0 -> 0 | ... AC48: =0 -> 0
A49: Stat-Statutory EBITDA | B49: Statutory EBITDA | C49: NZDm | D49: =D42+D48 -> 115.2 | E49: =E42+E48 -> 93.5 | F49: =F42+F48 -> 81.9 | G49: =G42+G48 -> 65.7 | H49: =H42+H48 -> 56.9 | I49: =I42+I48 -> 52 | J49: =J42+J48 -> 56.3 | K49: =K42+K48 -> 77.507083 | ... AC49: =AC42+AC48 -> 160.94779
B51: D&A
A52: DA-Depreciation PPE | B52: Depreciation PPE & Intangibles | C52: NZDm | D52: =Inputs!D10 -> -6.7 | E52: =INDEX(Annual!$A:$R,MATCH($A52,Annual!$A:$A,0),MATCH(E$1,Annual!$A$1:$R$1,0))-D52 -> -8.4 | F52: =Inputs!E10 -> -7.8 | G52: =INDEX(Annual!$A:$R,MATCH($A52,Annual!$A:$A,0),MATCH(G$1,Annual!$A$1:$R$1,0))-F52 -> -10.4 | H52: =Inputs!F10 -> -9.1 | I52: =INDEX(Annual!$A:$R,MATCH($A52,Annual!$A:$A,0),MATCH(I$1,Annual!$A$1:$R$1,0))-H52 -> -9.1 | J52: =Inputs!G10 -> -9.7 | K52: =IF(I54=0,0,K54*I52/I54) -> -10.798992 | L52: =IF(J54=0,0,L54*J52/J54) -> -10.840568 | M52: =IF(K54=0,0,M54*K52/K54) -> -11.401035 | N52: =IF(L54=0,0,N54*L52/L54) -> -11.44493 | O52: =IF(M54=0,0,O54*M52/M54) -> -12.036643 | P52: =IF(N54=0,0,P54*N52/N54) -> -12.082985 | Q52: =IF(O54=0,0,Q54*O52/O54) -> -12.707686 | R52: =IF(P54=0,0,R54*P52/P54) -> -12.756611 | ... AC52: =IF(AA54=0,0,AC54*AA52/AA54) -> -17.596772
A53: DA-ROU Amortisation | B53: ROU Asset Amortisation | C53: NZDm | D53: -14.3 | E53: =INDEX(Annual!$A:$R,MATCH($A53,Annual!$A:$A,0),MATCH(E$1,Annual!$A$1:$R$1,0))-D53 -> -15.1 | F53: -14.9 | G53: =INDEX(Annual!$A:$R,MATCH($A53,Annual!$A:$A,0),MATCH(G$1,Annual!$A$1:$R$1,0))-F53 -> -15.5 | H53: -15.8 | I53: =INDEX(Annual!$A:$R,MATCH($A53,Annual!$A:$A,0),MATCH(I$1,Annual!$A$1:$R$1,0))-H53 -> -16.5 | J53: -17.8 | K53: =K54-K52 -> -19.580589 | L53: =L54-L52 -> -19.893002 | M53: =M54-M52 -> -20.672207 | N53: =N54-N52 -> -21.002037 | O53: =O54-O52 -> -21.824683 | P53: =P54-P52 -> -22.1729 | Q53: =Q54-Q52 -> -23.041409 | R53: =R54-R52 -> -23.409039 | ... AC53: =AC54-AC52 -> -31.906236
A54: DA-Total DA | B54: Total D&A | C54: NZDm | D54: =D52+D53 -> -21 | E54: =E52+E53 -> -23.5 | F54: =F52+F53 -> -22.7 | G54: =G52+G53 -> -25.9 | H54: =H52+H53 -> -24.9 | I54: =I52+I53 -> -25.6 | J54: =J52+J53 -> -27.5 | K54: =-K9*K55 -> -30.379581 | L54: =-L9*L55 -> -30.73357 | M54: =-M9*M55 -> -32.073243 | N54: =-N9*N55 -> -32.446967 | O54: =-O9*O55 -> -33.861326 | P54: =-P9*P55 -> -34.255885 | Q54: =-Q9*Q55 -> -35.749095 | R54: =-R9*R55 -> -36.165651 | ... AC54: =-AC9*AC55 -> -49.503008
B55: D&A / Revenue | C55: % | D55: =IF(D9=0,"",-D54/D9) -> 0.03292052 | E55: =IF(E9=0,"",-E54/E9) -> 0.038714992 | F55: =IF(F9=0,"",-F54/F9) -> 0.040248227 | G55: =IF(G9=0,"",-G54/G9) -> 0.051768939 | H55: =IF(H9=0,"",-H54/H9) -> 0.050507099 | I55: =IF(I9=0,"",-I54/I9) -> 0.056251373 | J55: =IF(J9=0,"",-J54/J9) -> 0.051363467 | K55: =I55 -> 0.056251373 | L55: =J55 -> 0.051363467 | M55: =K55 -> 0.056251373 | N55: =L55 -> 0.051363467 | O55: =M55 -> 0.056251373 | P55: =N55 -> 0.051363467 | Q55: =O55 -> 0.056251373 | R55: =P55 -> 0.051363467 | ... AC55: =AA55 -> 0.056251373
B57: EBIT
A58: EBIT-Underlying EBIT | B58: Underlying EBIT | C58: NZDm | D58: =D42+D54 -> 94.2 | E58: =E42+E54 -> 80.2 | F58: =F42+F54 -> 59.2 | G58: =G42+G54 -> 39.8 | H58: =H42+H54 -> 32 | I58: =I42+I54 -> 29.5 | J58: =J42+J54 -> 29.8 | K58: =K42+K54 -> 47.127502 | ... AC58: =AC42+AC54 -> 111.44478
B59: EBIT Growth (YoY) | C59: % YoY | F59: =IF(D58=0,"",F58/D58-1) -> -0.37154989 | G59: =IF(E58=0,"",G58/E58-1) -> -0.50374065 | H59: =IF(F58=0,"",H58/F58-1) -> -0.45945946 | I59: =IF(G58=0,"",I58/G58-1) -> -0.25879397 | J59: =IF(H58=0,"",J58/H58-1) -> -0.06875 | K59: =IF(I58=0,"",K58/I58-1) -> 0.59754245 | L59: =IF(J58=0,"",L58/J58-1) -> 0.4181865 | M59: =IF(K58=0,"",M58/K58-1) -> 0.11515171 | ... AC59: =IF(AA58=0,"",AC58/AA58-1) -> 0.0890823
B60: EBIT Margin | C60: % | D60: =IF(D9=0,"",D58/D9) -> 0.14767205 | E60: =IF(E9=0,"",E58/E9) -> 0.13212521 | F60: =IF(F9=0,"",F58/F9) -> 0.10496454 | G60: =IF(G9=0,"",G58/G9) -> 0.079552269 | H60: =IF(H9=0,"",H58/H9) -> 0.064908722 | I60: =IF(I9=0,"",I58/I9) -> 0.064820918 | J60: =IF(J9=0,"",J58/J9) -> 0.05565932 | K60: =IF(K9=0,"",K58/K9) -> 0.087262123 | ... AC60: =IF(AC9=0,"",AC58/AC9) -> 0.12663719
B62: Interest
A63: Int-Interest Income | B63: Interest Income | C63: NZDm | D63: 0 | E63: =INDEX(Annual!$A:$R,MATCH($A63,Annual!$A:$A,0),MATCH(E$1,Annual!$A$1:$R$1,0))-D63 -> 0.1 | F63: 0.2 | G63: =INDEX(Annual!$A:$R,MATCH($A63,Annual!$A:$A,0),MATCH(G$1,Annual!$A$1:$R$1,0))-F63 -> 0.1 | H63: 0.1 | I63: =INDEX(Annual!$A:$R,MATCH($A63,Annual!$A:$A,0),MATCH(I$1,Annual!$A$1:$R$1,0))-H63 -> 0.1 | J63: 1.2 | K63: =INDEX(Annual!$110:$110,MATCH(K$1-1,Annual!$1:$1,0))*K67-J63 -> -1.0556017 | L63: =INDEX(Annual!$110:$110,MATCH(L$1-1,Annual!$1:$1,0))*L67/2 -> 0.10380301 | M63: =INDEX(Annual!$110:$110,MATCH(M$1-1,Annual!$1:$1,0))*M67-L63 -> 0.10380301 | N63: =INDEX(Annual!$110:$110,MATCH(N$1-1,Annual!$1:$1,0))*N67/2 -> 0.090033145 | O63: =INDEX(Annual!$110:$110,MATCH(O$1-1,Annual!$1:$1,0))*O67-N63 -> 0.090033145 | P63: =INDEX(Annual!$110:$110,MATCH(P$1-1,Annual!$1:$1,0))*P67/2 -> 0.14332788 | Q63: =INDEX(Annual!$110:$110,MATCH(Q$1-1,Annual!$1:$1,0))*Q67-P63 -> 0.14332788 | R63: =INDEX(Annual!$110:$110,MATCH(R$1-1,Annual!$1:$1,0))*R67/2 -> 0.2208634 | S63: =INDEX(Annual!$110:$110,MATCH(S$1-1,Annual!$1:$1,0))*S67-R63 -> 0.2208634 | T63: =INDEX(Annual!$110:$110,MATCH(T$1-1,Annual!$1:$1,0))*T67/2 -> 0.32390772 | U63: =INDEX(Annual!$110:$110,MATCH(U$1-1,Annual!$1:$1,0))*U67-T63 -> 0.32390772 | V63: =INDEX(Annual!$110:$110,MATCH(V$1-1,Annual!$1:$1,0))*V67/2 -> 0.45386117 | W63: =INDEX(Annual!$110:$110,MATCH(W$1-1,Annual!$1:$1,0))*W67-V63 -> 0.45386117 | X63: =INDEX(Annual!$110:$110,MATCH(X$1-1,Annual!$1:$1,0))*X67/2 -> 0.61225722 | Y63: =INDEX(Annual!$110:$110,MATCH(Y$1-1,Annual!$1:$1,0))*Y67-X63 -> 0.61225722 | Z63: =INDEX(Annual!$110:$110,MATCH(Z$1-1,Annual!$1:$1,0))*Z67/2 -> 0.80076416 | AA63: =INDEX(Annual!$110:$110,MATCH(AA$1-1,Annual!$1:$1,0))*AA67-Z63 -> 0.80076416 | AB63: =INDEX(Annual!$110:$110,MATCH(AB$1-1,Annual!$1:$1,0))*AB67/2 -> 1.0211876 | AC63: =INDEX(Annual!$110:$110,MATCH(AC$1-1,Annual!$1:$1,0))*AC67-AB63 -> 1.0211876
A64: Int-Lease Interest | B64: Interest on Lease Liabilities | C64: NZDm | D64: =Inputs!D13 -> -8 | E64: =INDEX(Annual!$A:$R,MATCH($A64,Annual!$A:$A,0),MATCH(E$1,Annual!$A$1:$R$1,0))-D64 -> -8.4 | F64: =Inputs!E13 -> -8.3 | G64: =INDEX(Annual!$A:$R,MATCH($A64,Annual!$A:$A,0),MATCH(G$1,Annual!$A$1:$R$1,0))-F64 -> -8.7 | H64: =Inputs!F13 -> -8.5 | I64: =INDEX(Annual!$A:$R,MATCH($A64,Annual!$A:$A,0),MATCH(I$1,Annual!$A$1:$R$1,0))-H64 -> -9.5 | J64: =Inputs!G13 -> -10.4 | K64: =-INDEX(Annual!$127:$127,MATCH(K$1-1,Annual!$1:$1,0))*K68-J64 -> -7.6133 | L64: =-INDEX(Annual!$127:$127,MATCH(L$1-1,Annual!$1:$1,0))*L68/2 -> -8.8587639 | M64: =-INDEX(Annual!$127:$127,MATCH(M$1-1,Annual!$1:$1,0))*M68-L64 -> -8.8587639 | N64: =-INDEX(Annual!$127:$127,MATCH(N$1-1,Annual!$1:$1,0))*N68/2 -> -8.7296321 | O64: =-INDEX(Annual!$127:$127,MATCH(O$1-1,Annual!$1:$1,0))*O68-N64 -> -8.7296321 | P64: =-INDEX(Annual!$127:$127,MATCH(P$1-1,Annual!$1:$1,0))*P68/2 -> -8.6168763 | Q64: =-INDEX(Annual!$127:$127,MATCH(Q$1-1,Annual!$1:$1,0))*Q68-P64 -> -8.6168763 | R64: =-INDEX(Annual!$127:$127,MATCH(R$1-1,Annual!$1:$1,0))*R68/2 -> -8.5184197 | S64: =-INDEX(Annual!$127:$127,MATCH(S$1-1,Annual!$1:$1,0))*S68-R64 -> -8.5184197 | T64: =-INDEX(Annual!$127:$127,MATCH(T$1-1,Annual!$1:$1,0))*T68/2 -> -8.432449 | U64: =-INDEX(Annual!$127:$127,MATCH(U$1-1,Annual!$1:$1,0))*U68-T64 -> -8.432449 | V64: =-INDEX(Annual!$127:$127,MATCH(V$1-1,Annual!$1:$1,0))*V68/2 -> -8.3573807 | W64: =-INDEX(Annual!$127:$127,MATCH(W$1-1,Annual!$1:$1,0))*W68-V64 -> -8.3573807 | X64: =-INDEX(Annual!$127:$127,MATCH(X$1-1,Annual!$1:$1,0))*X68/2 -> -8.2918323 | Y64: =-INDEX(Annual!$127:$127,MATCH(Y$1-1,Annual!$1:$1,0))*Y68-X64 -> -8.2918323 | Z64: =-INDEX(Annual!$127:$127,MATCH(Z$1-1,Annual!$1:$1,0))*Z68/2 -> -8.2345964 | AA64: =-INDEX(Annual!$127:$127,MATCH(AA$1-1,Annual!$1:$1,0))*AA68-Z64 -> -8.2345964 | AB64: =-INDEX(Annual!$127:$127,MATCH(AB$1-1,Annual!$1:$1,0))*AB68/2 -> -8.184619 | AC64: =-INDEX(Annual!$127:$127,MATCH(AC$1-1,Annual!$1:$1,0))*AC68-AB64 -> -8.184619
A65: Int-Bank Interest | B65: Bank Interest Expense | C65: NZDm | D65: =Inputs!D14 -> -9.3 | E65: =INDEX(Annual!$A:$R,MATCH($A65,Annual!$A:$A,0),MATCH(E$1,Annual!$A$1:$R$1,0))-D65 -> -12.9 | F65: =Inputs!E14 -> -12.4 | G65: =INDEX(Annual!$A:$R,MATCH($A65,Annual!$A:$A,0),MATCH(G$1,Annual!$A$1:$R$1,0))-F65 -> -11 | H65: =Inputs!F14 -> -9.8 | I65: =INDEX(Annual!$A:$R,MATCH($A65,Annual!$A:$A,0),MATCH(I$1,Annual!$A$1:$R$1,0))-H65 -> -8.5 | J65: =Inputs!G14 -> -7.3 | K65: =-((INDEX(Annual!$128:$128,MATCH(K$1-1,Annual!$1:$1,0))+INDEX(Annual!$128:$128,MATCH(K$1,Annual!$1:$1,0)))/2)*K69-J65 -> -10.438705 | L65: =-((INDEX(Annual!$128:$128,MATCH(L$1-1,Annual!$1:$1,0))+INDEX(Annual!$128:$128,MATCH(L$1,Annual!$1:$1,0)))/2)*L69/2 -> -9.5555757 | M65: =-((INDEX(Annual!$128:$128,MATCH(M$1-1,Annual!$1:$1,0))+INDEX(Annual!$128:$128,MATCH(M$1,Annual!$1:$1,0)))/2)*M69-L65 -> -9.5555757 | N65: =-((INDEX(Annual!$128:$128,MATCH(N$1-1,Annual!$1:$1,0))+INDEX(Annual!$128:$128,MATCH(N$1,Annual!$1:$1,0)))/2)*N69/2 -> -9.8251211 | O65: =-((INDEX(Annual!$128:$128,MATCH(O$1-1,Annual!$1:$1,0))+INDEX(Annual!$128:$128,MATCH(O$1,Annual!$1:$1,0)))/2)*O69-N65 -> -9.8251211 | P65: =-((INDEX(Annual!$128:$128,MATCH(P$1-1,Annual!$1:$1,0))+INDEX(Annual!$128:$128,MATCH(P$1,Annual!$1:$1,0)))/2)*P69/2 -> -10.109694 | Q65: =-((INDEX(Annual!$128:$128,MATCH(Q$1-1,Annual!$1:$1,0))+INDEX(Annual!$128:$128,MATCH(Q$1,Annual!$1:$1,0)))/2)*Q69-P65 -> -10.109694 | R65: =-((INDEX(Annual!$128:$128,MATCH(R$1-1,Annual!$1:$1,0))+INDEX(Annual!$128:$128,MATCH(R$1,Annual!$1:$1,0)))/2)*R69/2 -> -10.410131 | S65: =-((INDEX(Annual!$128:$128,MATCH(S$1-1,Annual!$1:$1,0))+INDEX(Annual!$128:$128,MATCH(S$1,Annual!$1:$1,0)))/2)*S69-R65 -> -10.410131 | T65: =-((INDEX(Annual!$128:$128,MATCH(T$1-1,Annual!$1:$1,0))+INDEX(Annual!$128:$128,MATCH(T$1,Annual!$1:$1,0)))/2)*T69/2 -> -10.727318 | U65: =-((INDEX(Annual!$128:$128,MATCH(U$1-1,Annual!$1:$1,0))+INDEX(Annual!$128:$128,MATCH(U$1,Annual!$1:$1,0)))/2)*U69-T65 -> -10.727318 | V65: =-((INDEX(Annual!$128:$128,MATCH(V$1-1,Annual!$1:$1,0))+INDEX(Annual!$128:$128,MATCH(V$1,Annual!$1:$1,0)))/2)*V69/2 -> -11.062188 | W65: =-((INDEX(Annual!$128:$128,MATCH(W$1-1,Annual!$1:$1,0))+INDEX(Annual!$128:$128,MATCH(W$1,Annual!$1:$1,0)))/2)*W69-V65 -> -11.062188 | X65: =-((INDEX(Annual!$128:$128,MATCH(X$1-1,Annual!$1:$1,0))+INDEX(Annual!$128:$128,MATCH(X$1,Annual!$1:$1,0)))/2)*X69/2 -> -11.415727 | Y65: =-((INDEX(Annual!$128:$128,MATCH(Y$1-1,Annual!$1:$1,0))+INDEX(Annual!$128:$128,MATCH(Y$1,Annual!$1:$1,0)))/2)*Y69-X65 -> -11.415727 | Z65: =-((INDEX(Annual!$128:$128,MATCH(Z$1-1,Annual!$1:$1,0))+INDEX(Annual!$128:$128,MATCH(Z$1,Annual!$1:$1,0)))/2)*Z69/2 -> -11.788976 | AA65: =-((INDEX(Annual!$128:$128,MATCH(AA$1-1,Annual!$1:$1,0))+INDEX(Annual!$128:$128,MATCH(AA$1,Annual!$1:$1,0)))/2)*AA69-Z65 -> -11.788976 | AB65: =-((INDEX(Annual!$128:$128,MATCH(AB$1-1,Annual!$1:$1,0))+INDEX(Annual!$128:$128,MATCH(AB$1,Annual!$1:$1,0)))/2)*AB69/2 -> -12.183033 | AC65: =-((INDEX(Annual!$128:$128,MATCH(AC$1-1,Annual!$1:$1,0))+INDEX(Annual!$128:$128,MATCH(AC$1,Annual!$1:$1,0)))/2)*AC69-AB65 -> -12.183033
A66: Int-Net Finance Costs | B66: Net Finance Costs | C66: NZDm | D66: =SUM(D63:D65) -> -17.3 | E66: =SUM(E63:E65) -> -21.2 | F66: =SUM(F63:F65) -> -20.5 | G66: =SUM(G63:G65) -> -19.6 | H66: =SUM(H63:H65) -> -18.2 | I66: =SUM(I63:I65) -> -17.9 | J66: =SUM(J63:J65) -> -16.5 | K66: =SUM(K63:K65) -> -19.107606 | ... AC66: =SUM(AC63:AC65) -> -19.346464
B67: Interest Income Rate | C67: % | D67: =IFERROR(IF(INDEX(Annual!$110:$110,MATCH(D$1-1,Annual!$1:$1,0))=0,"",INDEX(Annual!$59:$59,MATCH(D$1,Annual!$1:$1,0))/INDEX(Annual!$110:$110,MATCH(D$1-1,Annual!$1:$1,0))),"") | E67: =IFERROR(IF(INDEX(Annual!$110:$110,MATCH(E$1-1,Annual!$1:$1,0))=0,"",INDEX(Annual!$59:$59,MATCH(E$1,Annual!$1:$1,0))/INDEX(Annual!$110:$110,MATCH(E$1-1,Annual!$1:$1,0))),"") | F67: =IFERROR(IF(INDEX(Annual!$110:$110,MATCH(F$1-1,Annual!$1:$1,0))=0,"",INDEX(Annual!$59:$59,MATCH(F$1,Annual!$1:$1,0))/INDEX(Annual!$110:$110,MATCH(F$1-1,Annual!$1:$1,0))),"") -> 0.014778325 | G67: =IFERROR(IF(INDEX(Annual!$110:$110,MATCH(G$1-1,Annual!$1:$1,0))=0,"",INDEX(Annual!$59:$59,MATCH(G$1,Annual!$1:$1,0))/INDEX(Annual!$110:$110,MATCH(G$1-1,Annual!$1:$1,0))),"") -> 0.014778325 | H67: =IFERROR(IF(INDEX(Annual!$110:$110,MATCH(H$1-1,Annual!$1:$1,0))=0,"",INDEX(Annual!$59:$59,MATCH(H$1,Annual!$1:$1,0))/INDEX(Annual!$110:$110,MATCH(H$1-1,Annual!$1:$1,0))),"") -> 0.0082987552 | I67: =IFERROR(IF(INDEX(Annual!$110:$110,MATCH(I$1-1,Annual!$1:$1,0))=0,"",INDEX(Annual!$59:$59,MATCH(I$1,Annual!$1:$1,0))/INDEX(Annual!$110:$110,MATCH(I$1-1,Annual!$1:$1,0))),"") -> 0.0082987552 | J67: =IFERROR(IF(INDEX(Annual!$110:$110,MATCH(J$1-1,Annual!$1:$1,0))=0,"",INDEX(Annual!$59:$59,MATCH(J$1,Annual!$1:$1,0))/INDEX(Annual!$110:$110,MATCH(J$1-1,Annual!$1:$1,0))),"") -> 0.0082987552 | K67: =I67 -> 0.0082987552 | L67: =J67 -> 0.0082987552 | M67: =K67 -> 0.0082987552 | N67: =L67 -> 0.0082987552 | O67: =M67 -> 0.0082987552 | P67: =N67 -> 0.0082987552 | Q67: =O67 -> 0.0082987552 | R67: =P67 -> 0.0082987552 | ... AC67: =AA67 -> 0.0082987552
B68: Lease Interest Rate | C68: % | I68: 0.061 | J68: 0.061 | K68: =I68 -> 0.061 | L68: =J68 -> 0.061 | M68: =K68 -> 0.061 | N68: =L68 -> 0.061 | O68: =M68 -> 0.061 | P68: =N68 -> 0.061 | Q68: =O68 -> 0.061 | R68: =P68 -> 0.061 | ... AC68: =AA68 -> 0.061
B69: Bank Interest Rate | C69: % | D69: =IFERROR(IF((INDEX(Annual!$128:$128,MATCH(D$1-1,Annual!$1:$1,0))+INDEX(Annual!$128:$128,MATCH(D$1,Annual!$1:$1,0)))=0,"",-INDEX(Annual!$61:$61,MATCH(D$1,Annual!$1:$1,0))/((INDEX(Annual!$128:$128,MATCH(D$1-1,Annual!$1:$1,0))+INDEX(Annual!$128:$128,MATCH(D$1,Annual!$1:$1,0)))/2)),"") | E69: =IFERROR(IF((INDEX(Annual!$128:$128,MATCH(E$1-1,Annual!$1:$1,0))+INDEX(Annual!$128:$128,MATCH(E$1,Annual!$1:$1,0)))=0,"",-INDEX(Annual!$61:$61,MATCH(E$1,Annual!$1:$1,0))/((INDEX(Annual!$128:$128,MATCH(E$1-1,Annual!$1:$1,0))+INDEX(Annual!$128:$128,MATCH(E$1,Annual!$1:$1,0)))/2)),"") | F69: =IFERROR(IF((INDEX(Annual!$128:$128,MATCH(F$1-1,Annual!$1:$1,0))+INDEX(Annual!$128:$128,MATCH(F$1,Annual!$1:$1,0)))=0,"",-INDEX(Annual!$61:$61,MATCH(F$1,Annual!$1:$1,0))/((INDEX(Annual!$128:$128,MATCH(F$1-1,Annual!$1:$1,0))+INDEX(Annual!$128:$128,MATCH(F$1,Annual!$1:$1,0)))/2)),"") -> 0.070919836 | G69: =IFERROR(IF((INDEX(Annual!$128:$128,MATCH(G$1-1,Annual!$1:$1,0))+INDEX(Annual!$128:$128,MATCH(G$1,Annual!$1:$1,0)))=0,"",-INDEX(Annual!$61:$61,MATCH(G$1,Annual!$1:$1,0))/((INDEX(Annual!$128:$128,MATCH(G$1-1,Annual!$1:$1,0))+INDEX(Annual!$128:$128,MATCH(G$1,Annual!$1:$1,0)))/2)),"") -> 0.070919836 | H69: =IFERROR(IF((INDEX(Annual!$128:$128,MATCH(H$1-1,Annual!$1:$1,0))+INDEX(Annual!$128:$128,MATCH(H$1,Annual!$1:$1,0)))=0,"",-INDEX(Annual!$61:$61,MATCH(H$1,Annual!$1:$1,0))/((INDEX(Annual!$128:$128,MATCH(H$1-1,Annual!$1:$1,0))+INDEX(Annual!$128:$128,MATCH(H$1,Annual!$1:$1,0)))/2)),"") -> 0.066593886 | I69: =IFERROR(IF((INDEX(Annual!$128:$128,MATCH(I$1-1,Annual!$1:$1,0))+INDEX(Annual!$128:$128,MATCH(I$1,Annual!$1:$1,0)))=0,"",-INDEX(Annual!$61:$61,MATCH(I$1,Annual!$1:$1,0))/((INDEX(Annual!$128:$128,MATCH(I$1-1,Annual!$1:$1,0))+INDEX(Annual!$128:$128,MATCH(I$1,Annual!$1:$1,0)))/2)),"") -> 0.066593886 | J69: =IFERROR(IF((INDEX(Annual!$128:$128,MATCH(J$1-1,Annual!$1:$1,0))+INDEX(Annual!$128:$128,MATCH(J$1,Annual!$1:$1,0)))=0,"",-INDEX(Annual!$61:$61,MATCH(J$1,Annual!$1:$1,0))/((INDEX(Annual!$128:$128,MATCH(J$1-1,Annual!$1:$1,0))+INDEX(Annual!$128:$128,MATCH(J$1,Annual!$1:$1,0)))/2)),"") -> 0.066593886 | K69: =I69 -> 0.066593886 | L69: =J69 -> 0.066593886 | M69: =K69 -> 0.066593886 | N69: =L69 -> 0.066593886 | O69: =M69 -> 0.066593886 | P69: =N69 -> 0.066593886 | Q69: =O69 -> 0.066593886 | R69: =P69 -> 0.066593886 | ... AC69: =AA69 -> 0.066593886
A71: PBT-PBT | B71: PBT | C71: NZDm | D71: =D58+D66 -> 76.9 | E71: =E58+E66 -> 59 | F71: =F58+F66 -> 38.7 | G71: =G58+G66 -> 20.2 | H71: =H58+H66 -> 13.8 | I71: =I58+I66 -> 11.6 | J71: =J58+J66 -> 13.3 | K71: =K58+K66 -> 28.019896 | ... AC71: =AC58+AC66 -> 92.098318
A72: Tax-Tax Expense | B72: Tax Expense | C72: NZDm | D72: -22.4 | E72: =INDEX(Annual!$A:$R,MATCH($A72,Annual!$A:$A,0),MATCH(E$1,Annual!$A$1:$R$1,0))-D72 -> -14.6 | F72: -12.4 | G72: =INDEX(Annual!$A:$R,MATCH($A72,Annual!$A:$A,0),MATCH(G$1,Annual!$A$1:$R$1,0))-F72 -> -6.5 | H72: -4.6 | I72: =INDEX(Annual!$A:$R,MATCH($A72,Annual!$A:$A,0),MATCH(I$1,Annual!$A$1:$R$1,0))-H72 -> -3 | J72: -3.6 | K72: =-K71*K73 -> -7.2465248 | L72: =-L71*L73 -> -6.4830914 | M72: =-M71*M73 -> -8.8561495 | N72: =-N71*N73 -> -8.0258353 | O72: =-O71*O73 -> -10.316105 | P72: =-P71*P73 -> -9.6902349 | Q72: =-Q71*Q73 -> -11.887451 | R72: =-R71*R73 -> -11.47187 | ... AC72: =-AC71*AC73 -> -23.81853
B73: Tax Rate | C73: % | D73: =IF(D71=0,"",-D72/D71) -> 0.29128739 | E73: =IF(E71=0,"",-E72/E71) -> 0.24745763 | F73: =IF(F71=0,"",-F72/F71) -> 0.32041344 | G73: =IF(G71=0,"",-G72/G71) -> 0.32178218 | H73: =IF(H71=0,"",-H72/H71) -> 0.33333333 | I73: =IF(I71=0,"",-I72/I71) -> 0.25862069 | J73: =IF(J71=0,"",-J72/J71) -> 0.27067669 | K73: =I73 -> 0.25862069 | L73: =J73 -> 0.27067669 | M73: =K73 -> 0.25862069 | N73: =L73 -> 0.27067669 | O73: =M73 -> 0.25862069 | P73: =N73 -> 0.27067669 | Q73: =O73 -> 0.25862069 | R73: =P73 -> 0.27067669 | ... AC73: =AA73 -> 0.25862069
A74: NPAT-NCI | B74: Non-controlling Interests | C74: NZDm | D74: 0 | E74: =INDEX(Annual!$A:$R,MATCH($A74,Annual!$A:$A,0),MATCH(E$1,Annual!$A$1:$R$1,0))-D74 -> 0 | F74: 0 | G74: =INDEX(Annual!$A:$R,MATCH($A74,Annual!$A:$A,0),MATCH(G$1,Annual!$A$1:$R$1,0))-F74 -> 0 | H74: 0 | I74: =INDEX(Annual!$A:$R,MATCH($A74,Annual!$A:$A,0),MATCH(I$1,Annual!$A$1:$R$1,0))-H74 -> 0 | J74: -0.4 | K74: =J74 -> -0.4 | L74: =L38/J38*J74 -> -0.55527695 | M74: =M38/K38*K74 -> -0.43335059 | N74: =N38/L38*L74 -> -0.60281585 | O74: =O38/M38*M74 -> -0.46883674 | P74: =P38/N38*N74 -> -0.6534196 | Q74: =Q38/O38*O74 -> -0.50658441 | R74: =R38/P38*P74 -> -0.70726943 | S74: =S38/Q38*Q74 -> -0.54672676 | ... AC74: =AC38/AA38*AA74 -> -0.78857606
A75: NPAT-Underlying NPAT | B75: Underlying NPAT | C75: NZDm | D75: =D71+D72+D74 -> 54.5 | E75: =E71+E72+E74 -> 44.4 | F75: =F71+F72+F74 -> 26.3 | G75: =G71+G72+G74 -> 13.7 | H75: =H71+H72+H74 -> 9.2 | I75: =I71+I72+I74 -> 8.6 | J75: =J71+J72+J74 -> 9.3 | K75: =K71+K72+K74 -> 20.373371 | ... AC75: =AC71+AC72+AC74 -> 67.491211
A76: NPAT-Sig Items AT | B76: Significant Items After Tax | C76: NZDm | D76: 0 | E76: =INDEX(Annual!$A:$R,MATCH($A76,Annual!$A:$A,0),MATCH(E$1,Annual!$A$1:$R$1,0))-D76 -> -7.2 | F76: 0 | G76: =INDEX(Annual!$A:$R,MATCH($A76,Annual!$A:$A,0),MATCH(G$1,Annual!$A$1:$R$1,0))-F76 -> 0 | H76: 0 | I76: =INDEX(Annual!$A:$R,MATCH($A76,Annual!$A:$A,0),MATCH(I$1,Annual!$A$1:$R$1,0))-H76 -> -2.2 | J76: -0.7 | K76: =0 -> 0 | L76: =0 -> 0 | M76: =0 -> 0 | N76: =0 -> 0 | O76: =0 -> 0 | P76: =0 -> 0 | Q76: =0 -> 0 | R76: =0 -> 0 | ... AC76: =0 -> 0
A77: NPAT-Statutory NPAT | B77: Statutory NPAT | C77: NZDm | D77: =D75+D76 -> 54.5 | E77: =E75+E76 -> 37.2 | F77: =F75+F76 -> 26.3 | G77: =G75+G76 -> 13.7 | H77: =H75+H76 -> 9.2 | I77: =I75+I76 -> 6.4 | J77: =J75+J76 -> 8.6 | K77: =K75+K76 -> 20.373371 | ... AC77: =AC75+AC76 -> 67.491211
B78: NPAT Growth (YoY) | C78: % YoY | F78: =IF(D75=0,"",F75/D75-1) -> -0.51743119 | G78: =IF(E75=0,"",G75/E75-1) -> -0.69144144 | H78: =IF(F75=0,"",H75/F75-1) -> -0.65019011 | I78: =IF(G75=0,"",I75/G75-1) -> -0.37226277 | J78: =IF(H75=0,"",J75/H75-1) -> 0.010869565 | K78: =IF(I75=0,"",K75/I75-1) -> 1.3689966 | L78: =IF(J75=0,"",L75/J75-1) -> 0.81860781 | M78: =IF(K75=0,"",M75/K75-1) -> 0.22484777 | ... AC78: =IF(AA75=0,"",AC75/AA75-1) -> 0.10861082
B80: Operating Metrics
A81: KPI-Steel Volume | B81: Steel Volume | C81: 000t | D81: 94.5 | E81: =INDEX(Annual!$A:$R,MATCH($A81,Annual!$A:$A,0),MATCH(E$1,Annual!$A$1:$R$1,0))-D81 -> 88.3 | F81: 84.5 | G81: =INDEX(Annual!$A:$R,MATCH($A81,Annual!$A:$A,0),MATCH(G$1,Annual!$A$1:$R$1,0))-F81 -> 77.5 | H81: 77.1 | I81: =INDEX(Annual!$A:$R,MATCH($A81,Annual!$A:$A,0),MATCH(I$1,Annual!$A$1:$R$1,0))-H81 -> 75.6 | J81: 89.4 | K81: =K93 -> 99.868 | L81: =L93 -> 103.082 | M81: =M93 -> 102.86404 | N81: =N93 -> 106.17446 | O81: =O93 -> 105.94996 | P81: =P93 -> 109.35969 | Q81: =Q93 -> 109.12846 | R81: =R93 -> 112.64048 | ... AC81: =AC93 -> 130.30509
A82: KPI-Metals Volume | B82: Metals Volume | C82: 000t | D82: 32.9 | E82: =INDEX(Annual!$A:$R,MATCH($A82,Annual!$A:$A,0),MATCH(E$1,Annual!$A$1:$R$1,0))-D82 -> 35.7 | F82: 34.6 | G82: =INDEX(Annual!$A:$R,MATCH($A82,Annual!$A:$A,0),MATCH(G$1,Annual!$A$1:$R$1,0))-F82 -> 31.9 | H82: 32.2 | I82: =INDEX(Annual!$A:$R,MATCH($A82,Annual!$A:$A,0),MATCH(I$1,Annual!$A$1:$R$1,0))-H82 -> 28.9 | J82: 31.6 | K82: =K106 -> 29.767 | L82: =L106 -> 32.548 | M82: =M106 -> 30.66001 | N82: =N106 -> 33.52444 | O82: =O106 -> 31.57981 | P82: =P106 -> 34.530173 | Q82: =Q106 -> 32.527205 | R82: =R106 -> 35.566078 | ... AC82: =AC106 -> 38.839183
A83: KPI-Total Volume | B83: Total Volume | C83: 000t | D83: =D81+D82 -> 127.4 | E83: =E81+E82 -> 124 | F83: =F81+F82 -> 119.1 | G83: =G81+G82 -> 109.4 | H83: =H81+H82 -> 109.3 | I83: =I81+I82 -> 104.5 | J83: =J81+J82 -> 121 | K83: =K81+K82 -> 129.635 | ... AC83: =AC81+AC82 -> 169.14427
A84: KPI-Steel Rev/t | B84: Steel Revenue / Tonne | C84: NZD | D84: =IF(D81=0,"",D7/D81*1000) -> 3349.2063 | E84: =IF(E81=0,"",E7/E81*1000) -> 3168.7429 | F84: =IF(F81=0,"",F7/F81*1000) -> 2985.7988 | G84: =IF(G81=0,"",G7/G81*1000) -> 2825.8065 | H84: =IF(H81=0,"",H7/H81*1000) -> 2722.4384 | I84: =IF(I81=0,"",I7/I81*1000) -> 2642.8571 | J84: =IF(J81=0,"",J7/J81*1000) -> 2936.2416 | K84: =IF(K81=0,"",K7/K81*1000) -> 2708.9286 | ... AC84: =IF(AC81=0,"",AC7/AC81*1000) -> 3383.0806
A85: KPI-Metals Rev/t | B85: Metals Revenue / Tonne | C85: NZD | D85: =IF(D82=0,"",D8/D82*1000) -> 9768.997 | E85: =IF(E82=0,"",E8/E82*1000) -> 9165.2661 | F85: =IF(F82=0,"",F8/F82*1000) -> 9008.6705 | G85: =IF(G82=0,"",G8/G82*1000) -> 8818.1818 | H85: =IF(H82=0,"",H8/H82*1000) -> 8791.9255 | I85: =IF(I82=0,"",I8/I82*1000) -> 8833.91 | J85: =IF(J82=0,"",J8/J82*1000) -> 8636.0759 | K85: =IF(K82=0,"",K8/K82*1000) -> 9054.7578 | ... AC85: =IF(AC82=0,"",AC8/AC82*1000) -> 11308.152
A86: KPI-Steel GP/t | B86: Steel GP / Tonne | C86: NZD | D86: =IF(D81=0,"",D19/D81*1000) -> 1078.4444 | E86: =IF(E81=0,"",E19/E81*1000) -> 952.80408 | F86: =IF(F81=0,"",F19/F81*1000) -> 1056.9728 | G86: =IF(G81=0,"",G19/G81*1000) -> 701.75226 | H86: =IF(H81=0,"",H19/H81*1000) -> 781.33982 | I86: =IF(I81=0,"",I19/I81*1000) -> 779.87698 | J86: =IF(J81=0,"",J19/J81*1000) -> 877.93624 | K86: =IF(K81=0,"",K19/K81*1000) -> 799.37391 | ... AC86: =IF(AC81=0,"",AC19/AC81*1000) -> 998.30847
A87: KPI-Metals GP/t | B87: Metals GP / Tonne | C87: NZD | D87: =IF(D82=0,"",D20/D82*1000) -> 3868.5228 | E87: =IF(E82=0,"",E20/E82*1000) -> 3647.6134 | F87: =IF(F82=0,"",F20/F82*1000) -> 3189.0694 | G87: =IF(G82=0,"",G20/G82*1000) -> 3362.326 | H87: =IF(H82=0,"",H20/H82*1000) -> 3516.7702 | I87: =IF(I82=0,"",I20/I82*1000) -> 3199.308 | J87: =IF(J82=0,"",J20/J82*1000) -> 3255.8006 | K87: =IF(K82=0,"",K20/K82*1000) -> 3279.2907 | ... AC87: =IF(AC82=0,"",AC20/AC82*1000) -> 4095.3847
A88: KPI-Customers | B88: Active Customers | C88: # | D88: 11941 | E88: =INDEX(Annual!$A:$R,MATCH($A88,Annual!$A:$A,0),MATCH(E$1,Annual!$A$1:$R$1,0)) -> 12108 | F88: 12646 | G88: =INDEX(Annual!$A:$R,MATCH($A88,Annual!$A:$A,0),MATCH(G$1,Annual!$A$1:$R$1,0)) -> 0 | H88: 22612 | I88: =INDEX(Annual!$A:$R,MATCH($A88,Annual!$A:$A,0),MATCH(I$1,Annual!$A$1:$R$1,0)) -> 21727 | J88: 25456
A89: KPI-Headcount | B89: Headcount | C89: # | D89: 1440 | E89: =INDEX(Annual!$A:$R,MATCH($A89,Annual!$A:$A,0),MATCH(E$1,Annual!$A$1:$R$1,0)) -> 1361 | F89: 1283 | G89: =INDEX(Annual!$A:$R,MATCH($A89,Annual!$A:$A,0),MATCH(G$1,Annual!$A$1:$R$1,0)) -> 1326 | H89: 1307 | I89: =INDEX(Annual!$A:$R,MATCH($A89,Annual!$A:$A,0),MATCH(I$1,Annual!$A$1:$R$1,0)) -> 1344 | J89: 1648
A90: KPI-DIFOT | B90: DIFOT | C90: % | J90: 0.98
B92: Segment Forecast - Steel
B93: Volume | C93: 000t | D93: =D81 -> 94.5 | E93: =E81 -> 88.3 | F93: =F81 -> 84.5 | G93: =G81 -> 77.5 | H93: =H81 -> 77.1 | I93: =I81 -> 75.6 | J93: =J81 -> 89.4 | K93: =I93*(1+K94)+22 -> 99.868 | L93: =J93*(1+L94)+11 -> 103.082 | M93: =K93*(1+M94) -> 102.86404 | N93: =L93*(1+N94) -> 106.17446 | O93: =M93*(1+O94) -> 105.94996 | P93: =N93*(1+P94) -> 109.35969 | Q93: =O93*(1+Q94) -> 109.12846 | R93: =P93*(1+R94) -> 112.64048 | S93: =Q93*(1+S94) -> 112.40231 | T93: =R93*(1+T94) -> 116.0197 | ... AC93: =AA93*(1+AC94) -> 130.30509
B94: Volume Growth | C94: % YoY | F94: =IF(D93=0,"",F93/D93-1) -> -0.10582011 | G94: =IF(E93=0,"",G93/E93-1) -> -0.12231031 | H94: =IF(F93=0,"",H93/F93-1) -> -0.087573964 | I94: =IF(G93=0,"",I93/G93-1) -> -0.024516129 | J94: =IF(H93=0,"",J93/H93-1) -> 0.15953307 | K94: 0.03 | L94: 0.03 | M94: 0.03 | N94: 0.03 | O94: 0.03 | P94: 0.03 | Q94: 0.03 | R94: 0.03 | S94: 0.03 | T94: 0.03 | U94: 0.03 | V94: 0.03 | W94: 0.03 | X94: 0.03 | Y94: 0.03 | Z94: 0.03 | AA94: 0.03 | AB94: 0.03 | AC94: 0.03
B95: Revenue / Tonne | C95: NZD | D95: =IF(D93=0,"",D7/D93*1000) -> 3349.2063 | E95: =IF(E93=0,"",E7/E93*1000) -> 3168.7429 | F95: =IF(F93=0,"",F7/F93*1000) -> 2985.7988 | G95: =IF(G93=0,"",G7/G93*1000) -> 2825.8065 | H95: =IF(H93=0,"",H7/H93*1000) -> 2722.4384 | I95: =IF(I93=0,"",I7/I93*1000) -> 2642.8571 | J95: =IF(J93=0,"",J7/J93*1000) -> 2936.2416 | K95: =I95*(1+K96) -> 2708.9286 | L95: =J95*(1+L96) -> 3009.6477 | M95: =K95*(1+M96) -> 2776.6518 | N95: =L95*(1+N96) -> 3084.8888 | O95: =M95*(1+O96) -> 2846.0681 | P95: =N95*(1+P96) -> 3162.0111 | Q95: =O95*(1+Q96) -> 2917.2198 | R95: =P95*(1+R96) -> 3241.0613 | ... AC95: =AA95*(1+AC96) -> 3383.0806
B96: Rev/Tonne Growth | C96: % YoY | F96: =IF(D95=0,"",F95/D95-1) -> -0.10850557 | G96: =IF(E95=0,"",G95/E95-1) -> -0.10822477 | H96: =IF(F95=0,"",H95/F95-1) -> -0.088204344 | I96: =IF(G95=0,"",I95/G95-1) -> -0.064742335 | J96: =IF(H95=0,"",J95/H95-1) -> 0.078533722 | K96: 0.025 | L96: 0.025 | M96: 0.025 | N96: 0.025 | O96: 0.025 | P96: 0.025 | Q96: 0.025 | R96: 0.025 | S96: 0.025 | T96: 0.025 | U96: 0.025 | V96: 0.025 | W96: 0.025 | X96: 0.025 | Y96: 0.025 | Z96: 0.025 | AA96: 0.025 | AB96: 0.025 | AC96: 0.025
B97: Revenue | C97: NZDm | D97: =D7 -> 316.5 | E97: =E7 -> 279.8 | F97: =F7 -> 252.3 | G97: =G7 -> 219 | H97: =H7 -> 209.9 | I97: =I7 -> 199.8 | J97: =J7 -> 262.5 | K97: =K93*K95/1000 -> 270.53528 | L97: =L93*L95/1000 -> 310.2405 | M97: =M93*M95/1000 -> 285.61762 | N97: =N93*N95/1000 -> 327.53641 | O97: =O93*O95/1000 -> 301.5408 | P97: =P93*P95/1000 -> 345.79656 | Q97: =Q93*Q95/1000 -> 318.3517 | R97: =R93*R95/1000 -> 365.07472 | ... AC97: =AC93*AC95/1000 -> 440.83261
B98: GP Margin | C98: % | D98: =IF(D7=0,"",D19/D7) -> 0.322 | E98: =IF(E7=0,"",E19/E7) -> 0.30068835 | F98: =IF(F7=0,"",F19/F7) -> 0.354 | G98: =IF(G7=0,"",G19/G7) -> 0.24833699 | H98: =IF(H7=0,"",H19/H7) -> 0.287 | I98: =IF(I7=0,"",I19/I7) -> 0.29508859 | J98: =IF(J7=0,"",J19/J7) -> 0.299 | K98: =I98 -> 0.29508859 | L98: =J98 -> 0.299 | M98: =K98 -> 0.29508859 | N98: =L98 -> 0.299 | O98: =M98 -> 0.29508859 | P98: =N98 -> 0.299 | Q98: =O98 -> 0.29508859 | R98: =P98 -> 0.299 | ... AC98: =AA98 -> 0.29508859
B99: Gross Profit | C99: NZDm | D99: =D19 -> 101.913 | E99: =E19 -> 84.1326 | F99: =F19 -> 89.3142 | G99: =G19 -> 54.3858 | H99: =H19 -> 60.2413 | I99: =I19 -> 58.9587 | J99: =J19 -> 78.4875 | K99: =K97*K98 -> 79.831874 | L99: =L97*L98 -> 92.761909 | M99: =M97*M98 -> 84.2825 | N99: =N97*N98 -> 97.933386 | O99: =O97*O98 -> 88.98125 | P99: =P97*P98 -> 103.39317 | Q99: =Q97*Q98 -> 93.941955 | R99: =R97*R98 -> 109.15734 | ... AC99: =AC97*AC98 -> 130.08467
B100: Opex | C100: NZDm | D100: =D38-D19 -> -37.613 | E100: =E38-E19 -> -35.2326 | F100: =F38-F19 -> -51.5142 | G100: =G38-G19 -> -23.3858 | H100: =H38-H19 -> -38.2413 | I100: =I38-I19 -> -36.8587 | J100: =J38-J19 -> -44.5875 | K100: =I100*(1+K101) -> -37.780167 | L100: =J100*(1+L101) -> -45.702187 | M100: =K100*(1+M101) -> -38.724672 | N100: =L100*(1+N101) -> -46.844742 | O100: =M100*(1+O101) -> -39.692788 | P100: =N100*(1+P101) -> -48.015861 | Q100: =O100*(1+Q101) -> -40.685108 | R100: =P100*(1+R101) -> -49.216257 | ... AC100: =AA100*(1+AC101) -> -47.182252
B101: Opex Growth | C101: % YoY | F101: =IF(D102=0,"",F102/D102-1) -> 0.53166605 | G101: =IF(E102=0,"",G102/E102-1) -> -0.243748 | H101: =IF(F102=0,"",H102/F102-1) -> -0.18640547 | I101: =IF(G102=0,"",I102/G102-1) -> 0.61572591 | J101: =IF(H102=0,"",J102/H102-1) -> 0.0055353293 | K101: 0.025 | L101: 0.025 | M101: 0.025 | N101: 0.025 | O101: 0.025 | P101: 0.025 | Q101: 0.025 | R101: 0.025 | S101: 0.025 | T101: 0.025 | U101: 0.025 | V101: 0.025 | W101: 0.025 | X101: 0.025 | Y101: 0.025 | Z101: 0.025 | AA101: 0.025 | AB101: 0.025 | AC101: 0.025
B102: Opex per Tonne | C102: NZD | D102: =IF(D93=0,"",-D100/D93*1000) -> 398.02116 | E102: =IF(E93=0,"",-E100/E93*1000) -> 399.01019 | F102: =IF(F93=0,"",-F100/F93*1000) -> 609.6355 | G102: =IF(G93=0,"",-G100/G93*1000) -> 301.75226 | H102: =IF(H93=0,"",-H100/H93*1000) -> 495.99611 | I102: =IF(I93=0,"",-I100/I93*1000) -> 487.54894 | J102: =IF(J93=0,"",-J100/J93*1000) -> 498.74161 | K102: =IF(K93=0,"",-K100/K93*1000) -> 378.30103 | ... AC102: =IF(AC93=0,"",-AC100/AC93*1000) -> 362.09064
B103: Segment EBITDA | C103: NZDm | D103: =D38 -> 64.3 | E103: =E38 -> 48.9 | F103: =F38 -> 37.8 | G103: =G38 -> 31 | H103: =H38 -> 22 | I103: =I38 -> 22.1 | J103: =J38 -> 33.9 | K103: =K99+K100 -> 42.051706 | L103: =L99+L100 -> 47.059722 | M103: =M99+M100 -> 45.557829 | N103: =N99+N100 -> 51.088644 | O103: =O99+O100 -> 49.288461 | P103: =P99+P100 -> 55.377311 | Q103: =Q99+Q100 -> 53.256846 | R103: =R99+R100 -> 59.941084 | ... AC103: =AC99+AC100 -> 82.902422
B105: Segment Forecast - Metals
B106: Volume | C106: 000t | D106: =D82 -> 32.9 | E106: =E82 -> 35.7 | F106: =F82 -> 34.6 | G106: =G82 -> 31.9 | H106: =H82 -> 32.2 | I106: =I82 -> 28.9 | J106: =J82 -> 31.6 | K106: =I106*(1+K107) -> 29.767 | L106: =J106*(1+L107) -> 32.548 | M106: =K106*(1+M107) -> 30.66001 | N106: =L106*(1+N107) -> 33.52444 | O106: =M106*(1+O107) -> 31.57981 | P106: =N106*(1+P107) -> 34.530173 | Q106: =O106*(1+Q107) -> 32.527205 | R106: =P106*(1+R107) -> 35.566078 | ... AC106: =AA106*(1+AC107) -> 38.839183
B107: Volume Growth | C107: % YoY | F107: =IF(D106=0,"",F106/D106-1) -> 0.051671733 | G107: =IF(E106=0,"",G106/E106-1) -> -0.10644258 | H107: =IF(F106=0,"",H106/F106-1) -> -0.069364162 | I107: =IF(G106=0,"",I106/G106-1) -> -0.094043887 | J107: =IF(H106=0,"",J106/H106-1) -> -0.01863354 | K107: 0.03 | L107: 0.03 | M107: 0.03 | N107: 0.03 | O107: 0.03 | P107: 0.03 | Q107: 0.03 | R107: 0.03 | S107: 0.03 | T107: 0.03 | U107: 0.03 | V107: 0.03 | W107: 0.03 | X107: 0.03 | Y107: 0.03 | Z107: 0.03 | AA107: 0.03 | AB107: 0.03 | AC107: 0.03
B108: Revenue / Tonne | C108: NZD | D108: =IF(D106=0,"",D8/D106*1000) -> 9768.997 | E108: =IF(E106=0,"",E8/E106*1000) -> 9165.2661 | F108: =IF(F106=0,"",F8/F106*1000) -> 9008.6705 | G108: =IF(G106=0,"",G8/G106*1000) -> 8818.1818 | H108: =IF(H106=0,"",H8/H106*1000) -> 8791.9255 | I108: =IF(I106=0,"",I8/I106*1000) -> 8833.91 | J108: =IF(J106=0,"",J8/J106*1000) -> 8636.0759 | K108: =I108*(1+K109) -> 9054.7578 | L108: =J108*(1+L109) -> 8851.9778 | M108: =K108*(1+M109) -> 9281.1267 | N108: =L108*(1+N109) -> 9073.2773 | O108: =M108*(1+O109) -> 9513.1549 | P108: =N108*(1+P109) -> 9300.1092 | Q108: =O108*(1+Q109) -> 9750.9838 | R108: =P108*(1+R109) -> 9532.612 | ... AC108: =AA108*(1+AC109) -> 11308.152
B109: Rev/Tonne Growth | C109: % YoY | F109: =IF(D108=0,"",F108/D108-1) -> -0.077830553 | G109: =IF(E108=0,"",G108/E108-1) -> -0.037869527 | H109: =IF(F108=0,"",H108/F108-1) -> -0.024059605 | I109: =IF(G108=0,"",I108/G108-1) -> 0.0017836122 | J109: =IF(H108=0,"",J108/H108-1) -> -0.017726437 | K109: 0.025 | L109: 0.025 | M109: 0.025 | N109: 0.025 | O109: 0.025 | P109: 0.025 | Q109: 0.025 | R109: 0.025 | S109: 0.025 | T109: 0.025 | U109: 0.025 | V109: 0.025 | W109: 0.025 | X109: 0.025 | Y109: 0.025 | Z109: 0.025 | AA109: 0.025 | AB109: 0.025 | AC109: 0.025
B110: Revenue | C110: NZDm | D110: =D8 -> 321.4 | E110: =E8 -> 327.2 | F110: =F8 -> 311.7 | G110: =G8 -> 281.3 | H110: =H8 -> 283.1 | I110: =I8 -> 255.3 | J110: =J8 -> 272.9 | K110: =K106*K108/1000 -> 269.53297 | L110: =L106*L108/1000 -> 288.11417 | M110: =M106*M108/1000 -> 284.55944 | N110: =N106*N108/1000 -> 304.17654 | O110: =O106*O108/1000 -> 300.42363 | P110: =P106*P108/1000 -> 321.13438 | Q110: =Q106*Q108/1000 -> 317.17224 | R110: =R106*R108/1000 -> 339.03762 | ... AC110: =AC106*AC108/1000 -> 439.19938
B111: GP Margin | C111: % | D111: =IF(D8=0,"",D20/D8) -> 0.396 | E111: =IF(E8=0,"",E20/E8) -> 0.39798227 | F111: =IF(F8=0,"",F20/F8) -> 0.354 | G111: =IF(G8=0,"",G20/G8) -> 0.3812947 | H111: =IF(H8=0,"",H20/H8) -> 0.4 | I111: =IF(I8=0,"",I20/I8) -> 0.36216216 | J111: =IF(J8=0,"",J20/J8) -> 0.377 | K111: =I111 -> 0.36216216 | L111: =J111 -> 0.377 | M111: =K111 -> 0.36216216 | N111: =L111 -> 0.377 | O111: =M111 -> 0.36216216 | P111: =N111 -> 0.377 | Q111: =O111 -> 0.36216216 | R111: =P111 -> 0.377 | ... AC111: =AA111 -> 0.36216216
B112: Gross Profit | C112: NZDm | D112: =D20 -> 127.2744 | E112: =E20 -> 130.2198 | F112: =F20 -> 110.3418 | G112: =G20 -> 107.2582 | H112: =H20 -> 113.24 | I112: =I20 -> 92.46 | J112: =J20 -> 102.8833 | K112: =K110*K111 -> 97.614645 | L112: =L110*L111 -> 108.61904 | M112: =M110*M111 -> 103.05666 | N112: =N110*N111 -> 114.67456 | O112: =O110*O111 -> 108.80207 | P112: =P110*P111 -> 121.06766 | Q112: =Q110*Q111 -> 114.86779 | R112: =R110*R111 -> 127.81718 | ... AC112: =AC110*AC111 -> 159.0614
...

Sheet Inputs
B2: VSL — Inputs (Presentation-Only Items)
B3: Item | C3: Unit | D3: 1H23 | E3: 1H24 | F3: 1H25 | G3: 1H26
B5: Segment Gross Margins
B6: Steel GP Margin | C6: % | D6: 0.322 | E6: 0.354 | F6: 0.287 | G6: 0.299
B7: Metals GP Margin | C7: % | D7: 0.396 | E7: 0.354 | F7: 0.4 | G7: 0.377
B9: D&A Split
B10: Depreciation PPE & Intangibles | C10: NZDm | D10: -6.7 | E10: -7.8 | F10: -9.1 | G10: -9.7
B12: Interest Split
B13: Interest on Lease Liabilities | C13: NZDm | D13: -8 | E13: -8.3 | F13: -8.5 | G13: -10.4
B14: Bank Interest Expense | C14: NZDm | D14: -9.3 | E14: -12.4 | F14: -9.8 | G14: -7.3

Sheet Charts
A1: Group EBITDA Movement from FY24 to FY25 (NZ$m)
A2: Category | B2: Value | C2: Type | D2: Running | E2: Base | F2: Total | G2: Increase | H2: Decrease
A3: FY24 (statutory) | B3: =Annual!E45 -> 147.6 | C3: 1 | D3: =B3 -> 147.6 | E3: =IF(C3=1,0,IF(B3>=0,D3-B3,D3)) -> 0 | F3: =IF(C3=1,B3,0) -> 147.6 | G3: =IF(AND(C3=0,B3>0),B3,0) -> 0 | H3: =IF(AND(C3=0,B3<0),-B3,0) -> 0
A4: Significant Items | B4: =-Annual!E44 -> 0 | C4: 0 | D4: =IF(C4=1,B4,D3+B4) -> 147.6 | E4: =IF(C4=1,0,IF(B4>=0,D4-B4,D4)) -> 147.6 | F4: =IF(C4=1,B4,0) -> 0 | G4: =IF(AND(C4=0,B4>0),B4,0) -> 0 | H4: =IF(AND(C4=0,B4<0),-B4,0) -> 0
A5: FY24 (adjusted) | B5: =Annual!E38 -> 147.6 | C5: 1 | D5: =IF(C5=1,B5,D4+B5) -> 147.6 | E5: =IF(C5=1,0,IF(B5>=0,D5-B5,D5)) -> 0 | F5: =IF(C5=1,B5,0) -> 147.6 | G5: =IF(AND(C5=0,B5>0),B5,0) -> 0 | H5: =IF(AND(C5=0,B5<0),-B5,0) -> 0
A6: Volume (000t) | B6: =B15+B24 -> -25.919219 | C6: 0 | D6: =IF(C6=1,B6,D5+B6) -> 121.68078 | E6: =IF(C6=1,0,IF(B6>=0,D6-B6,D6)) -> 121.68078 | F6: =IF(C6=1,B6,0) -> 0 | G6: =IF(AND(C6=0,B6>0),B6,0) -> 0 | H6: =IF(AND(C6=0,B6<0),-B6,0) -> 25.919219
A7: Gross Margin (NZ$/t) | B7: =(Annual!F22-Annual!E22)-B6 -> -10.480781 | C7: 0 | D7: =IF(C7=1,B7,D6+B7) -> 111.2 | E7: =IF(C7=1,0,IF(B7>=0,D7-B7,D7)) -> 111.2 | F7: =IF(C7=1,B7,0) -> 0 | G7: =IF(AND(C7=0,B7>0),B7,0) -> 0 | H7: =IF(AND(C7=0,B7<0),-B7,0) -> 10.480781
A8: OPEX (NZ$m) | B8: =(Annual!F38-Annual!E38)-(Annual!F22-Annual!E22) -> 0.8 | C8: 0 | D8: =IF(C8=1,B8,D7+B8) -> 112 | E8: =IF(C8=1,0,IF(B8>=0,D8-B8,D8)) -> 111.2 | F8: =IF(C8=1,B8,0) -> 0 | G8: =IF(AND(C8=0,B8>0),B8,0) -> 0.8 | H8: =IF(AND(C8=0,B8<0),-B8,0) -> 0
A9: FY25 (adjusted) | B9: =Annual!F38 -> 112 | C9: 1 | D9: =IF(C9=1,B9,D8+B9) -> 112 | E9: =IF(C9=1,0,IF(B9>=0,D9-B9,D9)) -> 0 | F9: =IF(C9=1,B9,0) -> 112 | G9: =IF(AND(C9=0,B9>0),B9,0) -> 0 | H9: =IF(AND(C9=0,B9<0),-B9,0) -> 0
A12: Steel EBITDA Movement from FY24 to FY25 (NZ$m)
A13: Category | B13: Value | C13: Type | D13: Running | E13: Base | F13: Total | G13: Increase | H13: Decrease
A14: FY24 Steel EBITDA | B14: =Annual!E35 -> 68.8 | C14: 1 | D14: =B14 -> 68.8 | E14: =IF(C14=1,0,IF(B14>=0,D14-B14,D14)) -> 0 | F14: =IF(C14=1,B14,0) -> 68.8 | G14: =IF(AND(C14=0,B14>0),B14,0) -> 0 | H14: =IF(AND(C14=0,B14<0),-B14,0) -> 0
A15: Volume (000t) | B15: =(Annual!F95-Annual!E95)*Annual!E19/Annual!E95 -> -8.2494444 | C15: 0 | D15: =IF(C15=1,B15,D14+B15) -> 60.550556 | E15: =IF(C15=1,0,IF(B15>=0,D15-B15,D15)) -> 60.550556 | F15: =IF(C15=1,B15,0) -> 0 | G15: =IF(AND(C15=0,B15>0),B15,0) -> 0 | H15: =IF(AND(C15=0,B15<0),-B15,0) -> 8.2494444
A16: Gross Margin (NZ$/t) | B16: =(Annual!F19-Annual!E19)-B15 -> -16.250556 | C16: 0 | D16: =IF(C16=1,B16,D15+B16) -> 44.3 | E16: =IF(C16=1,0,IF(B16>=0,D16-B16,D16)) -> 44.3 | F16: =IF(C16=1,B16,0) -> 0 | G16: =IF(AND(C16=0,B16>0),B16,0) -> 0 | H16: =IF(AND(C16=0,B16<0),-B16,0) -> 16.250556
A17: OPEX (NZ$m) | B17: =(Annual!F35-Annual!E35)-(Annual!F19-Annual!E19) -> -0.2 | C17: 0 | D17: =IF(C17=1,B17,D16+B17) -> 44.1 | E17: =IF(C17=1,0,IF(B17>=0,D17-B17,D17)) -> 44.1 | F17: =IF(C17=1,B17,0) -> 0 | G17: =IF(AND(C17=0,B17>0),B17,0) -> 0 | H17: =IF(AND(C17=0,B17<0),-B17,0) -> 0.2
A18: FY25 Steel EBITDA | B18: =Annual!F35 -> 44.1 | C18: 1 | D18: =IF(C18=1,B18,D17+B18) -> 44.1 | E18: =IF(C18=1,0,IF(B18>=0,D18-B18,D18)) -> 0 | F18: =IF(C18=1,B18,0) -> 44.1 | G18: =IF(AND(C18=0,B18>0),B18,0) -> 0 | H18: =IF(AND(C18=0,B18<0),-B18,0) -> 0
A21: Metals EBITDA Movement from FY24 to FY25 (NZ$m)
A22: Category | B22: Value | C22: Type | D22: Running | E22: Base | F22: Total | G22: Increase | H22: Decrease
A23: FY24 Metals EBITDA | B23: =Annual!E36 -> 99.5 | C23: 1 | D23: =B23 -> 99.5 | E23: =IF(C23=1,0,IF(B23>=0,D23-B23,D23)) -> 0 | F23: =IF(C23=1,B23,0) -> 99.5 | G23: =IF(AND(C23=0,B23>0),B23,0) -> 0 | H23: =IF(AND(C23=0,B23<0),-B23,0) -> 0
A24: Volume (000t) | B24: =(Annual!F96-Annual!E96)*Annual!E20/Annual!E96 -> -17.669774 | C24: 0 | D24: =IF(C24=1,B24,D23+B24) -> 81.830226 | E24: =IF(C24=1,0,IF(B24>=0,D24-B24,D24)) -> 81.830226 | F24: =IF(C24=1,B24,0) -> 0 | G24: =IF(AND(C24=0,B24>0),B24,0) -> 0 | H24: =IF(AND(C24=0,B24<0),-B24,0) -> 17.669774
A25: Gross Margin (NZ$/t) | B25: =(Annual!F20-Annual!E20)-B24 -> 5.7697744 | C25: 0 | D25: =IF(C25=1,B25,D24+B25) -> 87.6 | E25: =IF(C25=1,0,IF(B25>=0,D25-B25,D25)) -> 81.830226 | F25: =IF(C25=1,B25,0) -> 0 | G25: =IF(AND(C25=0,B25>0),B25,0) -> 5.7697744 | H25: =IF(AND(C25=0,B25<0),-B25,0) -> 0
A26: OPEX (NZ$m) | B26: =(Annual!F36-Annual!E36)-(Annual!F20-Annual!E20) -> -2.7 | C26: 0 | D26: =IF(C26=1,B26,D25+B26) -> 84.9 | E26: =IF(C26=1,0,IF(B26>=0,D26-B26,D26)) -> 84.9 | F26: =IF(C26=1,B26,0) -> 0 | G26: =IF(AND(C26=0,B26>0),B26,0) -> 0 | H26: =IF(AND(C26=0,B26<0),-B26,0) -> 2.7
A27: FY25 Metals EBITDA | B27: =Annual!F36 -> 84.9 | C27: 1 | D27: =IF(C27=1,B27,D26+B27) -> 84.9 | E27: =IF(C27=1,0,IF(B27>=0,D27-B27,D27)) -> 0 | F27: =IF(C27=1,B27,0) -> 84.9 | G27: =IF(AND(C27=0,B27>0),B27,0) -> 0 | H27: =IF(AND(C27=0,B27<0),-B27,0) -> 0
A30: FY25 Earnings and Cashflow (CF) Movements (NZ$m)
A31: Category | B31: Value | C31: Type | D31: Running | E31: Base | F31: Total | G31: Increase | H31: Decrease
A32: Adjusted EBITDA | B32: =Annual!F38 -> 112 | C32: 1 | D32: =B32 -> 112 | E32: =IF(C32=1,0,IF(B32>=0,D32-B32,D32)) -> 0 | F32: =IF(C32=1,B32,0) -> 112 | G32: =IF(AND(C32=0,B32>0),B32,0) -> 0 | H32: =IF(AND(C32=0,B32<0),-B32,0) -> 0
A33: Lease interest | B33: =Annual!F154 -> -18 | C33: 0 | D33: =IF(C33=1,B33,D32+B33) -> 94 | E33: =IF(C33=1,0,IF(B33>=0,D33-B33,D33)) -> 94 | F33: =IF(C33=1,B33,0) -> 0 | G33: =IF(AND(C33=0,B33>0),B33,0) -> 0 | H33: =IF(AND(C33=0,B33<0),-B33,0) -> 18
A34: Interest Paid | B34: =Annual!F153 -> -23.9 | C34: 0 | D34: =IF(C34=1,B34,D33+B34) -> 70.1 | E34: =IF(C34=1,0,IF(B34>=0,D34-B34,D34)) -> 70.1 | F34: =IF(C34=1,B34,0) -> 0 | G34: =IF(AND(C34=0,B34>0),B34,0) -> 0 | H34: =IF(AND(C34=0,B34<0),-B34,0) -> 23.9
A35: Tax paid | B35: =Annual!F155 -> -7.5 | C35: 0 | D35: =IF(C35=1,B35,D34+B35) -> 62.6 | E35: =IF(C35=1,0,IF(B35>=0,D35-B35,D35)) -> 62.6 | F35: =IF(C35=1,B35,0) -> 0 | G35: =IF(AND(C35=0,B35>0),B35,0) -> 0 | H35: =IF(AND(C35=0,B35<0),-B35,0) -> 7.5
A36: CF pre W/Capital | B36: =SUM(B32:B35) -> 62.6 | C36: 1 | D36: =IF(C36=1,B36,D35+B36) -> 62.6 | E36: =IF(C36=1,0,IF(B36>=0,D36-B36,D36)) -> 0 | F36: =IF(C36=1,B36,0) -> 62.6 | G36: =IF(AND(C36=0,B36>0),B36,0) -> 0 | H36: =IF(AND(C36=0,B36<0),-B36,0) -> 0
A37: W/Cap/Other | B37: =Annual!F156-B36 -> 42.4 | C37: 0 | D37: =IF(C37=1,B37,D36+B37) -> 105 | E37: =IF(C37=1,0,IF(B37>=0,D37-B37,D37)) -> 62.6 | F37: =IF(C37=1,B37,0) -> 0 | G37: =IF(AND(C37=0,B37>0),B37,0) -> 42.4 | H37: =IF(AND(C37=0,B37<0),-B37,0) -> 0
A38: Operating CF | B38: =Annual!F156 -> 105 | C38: 1 | D38: =IF(C38=1,B38,D37+B38) -> 105 | E38: =IF(C38=1,0,IF(B38>=0,D38-B38,D38)) -> 0 | F38: =IF(C38=1,B38,0) -> 105 | G38: =IF(AND(C38=0,B38>0),B38,0) -> 0 | H38: =IF(AND(C38=0,B38<0),-B38,0) -> 0
A39: Net Capex | B39: =Annual!F160+Annual!F162+Annual!F164 -> -17.2 | C39: 0 | D39: =IF(C39=1,B39,D38+B39) -> 87.8 | E39: =IF(C39=1,0,IF(B39>=0,D39-B39,D39)) -> 87.8 | F39: =IF(C39=1,B39,0) -> 0 | G39: =IF(AND(C39=0,B39>0),B39,0) -> 0 | H39: =IF(AND(C39=0,B39<0),-B39,0) -> 17.2
A40: Lease payments | B40: =Annual!F171 -> -26.7 | C40: 0 | D40: =IF(C40=1,B40,D39+B40) -> 61.1 | E40: =IF(C40=1,0,IF(B40>=0,D40-B40,D40)) -> 61.1 | F40: =IF(C40=1,B40,0) -> 0 | G40: =IF(AND(C40=0,B40>0),B40,0) -> 0 | H40: =IF(AND(C40=0,B40<0),-B40,0) -> 26.7
A41: Free cash flow | B41: =B38+B39+B40 -> 61.1 | C41: 1 | D41: =IF(C41=1,B41,D40+B41) -> 61.1 | E41: =IF(C41=1,0,IF(B41>=0,D41-B41,D41)) -> 0 | F41: =IF(C41=1,B41,0) -> 61.1 | G41: =IF(AND(C41=0,B41>0),B41,0) -> 0 | H41: =IF(AND(C41=0,B41<0),-B41,0) -> 0
A44: Movement in Working Capital (excl tax, NZ$m)
A45: Category | B45: Value | C45: Type | D45: Running | E45: Base | F45: Total | G45: Increase | H45: Decrease
A46: Jun 24 | B46: =Annual!E120 -> 361.3 | C46: 1 | D46: =B46 -> 361.3 | E46: =IF(C46=1,0,IF(B46>=0,D46-B46,D46)) -> 0 | F46: =IF(C46=1,B46,0) -> 361.3 | G46: =IF(AND(C46=0,B46>0),B46,0) -> 0 | H46: =IF(AND(C46=0,B46<0),-B46,0) -> 0
A47: Inventory | B47: =Annual!F112-Annual!E112 -> -26.7 | C47: 0 | D47: =IF(C47=1,B47,D46+B47) -> 334.6 | E47: =IF(C47=1,0,IF(B47>=0,D47-B47,D47)) -> 334.6 | F47: =IF(C47=1,B47,0) -> 0 | G47: =IF(AND(C47=0,B47>0),B47,0) -> 0 | H47: =IF(AND(C47=0,B47<0),-B47,0) -> 26.7
A48: Debtors | B48: =Annual!F111-Annual!E111 -> -14 | C48: 0 | D48: =IF(C48=1,B48,D47+B48) -> 320.6 | E48: =IF(C48=1,0,IF(B48>=0,D48-B48,D48)) -> 320.6 | F48: =IF(C48=1,B48,0) -> 0 | G48: =IF(AND(C48=0,B48>0),B48,0) -> 0 | H48: =IF(AND(C48=0,B48<0),-B48,0) -> 14
A49: Creditors | B49: =-(Annual!F125-Annual!E125) -> 0.8 | C49: 0 | D49: =IF(C49=1,B49,D48+B49) -> 321.4 | E49: =IF(C49=1,0,IF(B49>=0,D49-B49,D49)) -> 320.6 | F49: =IF(C49=1,B49,0) -> 0 | G49: =IF(AND(C49=0,B49>0),B49,0) -> 0.8 | H49: =IF(AND(C49=0,B49<0),-B49,0) -> 0
A50: Jun 25 | B50: =Annual!F120 -> 321.4 | C50: 1 | D50: =IF(C50=1,B50,D49+B50) -> 321.4 | E50: =IF(C50=1,0,IF(B50>=0,D50-B50,D50)) -> 0 | F50: =IF(C50=1,B50,0) -> 321.4 | G50: =IF(AND(C50=0,B50>0),B50,0) -> 0 | H50: =IF(AND(C50=0,B50<0),-B50,0) -> 0
A52: Revenue Movement from FY24 to FY25 (NZ$m)
A53: Category | B53: Value | C53: Type | D53: Running | E53: Base | F53: Total | G53: Increase | H53: Decrease
A54: FY24 Revenue | B54: =Annual!E9 -> 1064.3 | C54: 1 | D54: =B54 -> 1064.3 | E54: =IF(C54=1,0,IF(B54>=0,D54-B54,D54)) -> 0 | F54: =IF(C54=1,B54,0) -> 1064.3 | G54: =IF(AND(C54=0,B54>0),B54,0) -> 0 | H54: =IF(AND(C54=0,B54<0),-B54,0) -> 0
A55: Steel Volume (000t) | B55: =((Annual!F95-Annual!E95)*Annual!E98)/1000 -> -27.056111 | C55: 0 | D55: =IF(C55=1,B55,D54+B55) -> 1037.2439 | E55: =IF(C55=1,0,IF(B55>=0,D55-B55,D55)) -> 1037.2439 | F55: =IF(C55=1,B55,0) -> 0 | G55: =IF(AND(C55=0,B55>0),B55,0) -> 0 | H55: =IF(AND(C55=0,B55<0),-B55,0) -> 27.056111
A56: Steel Price (NZ$/t) | B56: =((Annual!F98-Annual!E98)*Annual!F95)/1000 -> -34.543889 | C56: 0 | D56: =IF(C56=1,B56,D55+B56) -> 1002.7 | E56: =IF(C56=1,0,IF(B56>=0,D56-B56,D56)) -> 1002.7 | F56: =IF(C56=1,B56,0) -> 0 | G56: =IF(AND(C56=0,B56>0),B56,0) -> 0 | H56: =IF(AND(C56=0,B56<0),-B56,0) -> 34.543889
A57: Metals Volume (000t) | B57: =((Annual!F96-Annual!E96)*Annual!E99)/1000 -> -48.153383 | C57: 0 | D57: =IF(C57=1,B57,D56+B57) -> 954.54662 | E57: =IF(C57=1,0,IF(B57>=0,D57-B57,D57)) -> 954.54662 | F57: =IF(C57=1,B57,0) -> 0 | G57: =IF(AND(C57=0,B57>0),B57,0) -> 0 | H57: =IF(AND(C57=0,B57<0),-B57,0) -> 48.153383
A58: Metals Price (NZ$/t) | B58: =((Annual!F99-Annual!E99)*Annual!F96)/1000 -> -6.4466165 | C58: 0 | D58: =IF(C58=1,B58,D57+B58) -> 948.1 | E58: =IF(C58=1,0,IF(B58>=0,D58-B58,D58)) -> 948.1 | F58: =IF(C58=1,B58,0) -> 0 | G58: =IF(AND(C58=0,B58>0),B58,0) -> 0 | H58: =IF(AND(C58=0,B58<0),-B58,0) -> 6.4466165
A59: FY25 Revenue | B59: =Annual!F9 -> 948.1 | C59: 1 | D59: =IF(C59=1,B59,D58+B59) -> 948.1 | E59: =IF(C59=1,0,IF(B59>=0,D59-B59,D59)) -> 0 | F59: =IF(C59=1,B59,0) -> 948.1 | G59: =IF(AND(C59=0,B59>0),B59,0) -> 0 | H59: =IF(AND(C59=0,B59<0),-B59,0) -> 0
