Workbook

Sheet Value
B2: DCF Valuation
B4: Current Share Price (A$) | C4: 7.91
B5: Shares Outstanding (#m) | C5: =INDEX(Annual!$D:$P,MATCH("EPS-YE Shares",Annual!$A:$A,0),MATCH($D$24,Annual!$D$3:$P$3,0)-1)
B6: Market Cap (A$m) | C6: =C4*C5
B7: Net Debt (A$m) | C7: =INDEX(Annual!$D:$P,MATCH("BS-Total Banking Debt",Annual!$A:$A,0),MATCH($D$24,Annual!$D$3:$P$3,0)-1)-INDEX(Annual!$D:$P,MATCH("BS-Cash",Annual!$A:$A,0),MATCH($D$24,Annual!$D$3:$P$3,0)-1)
B8: Market EV (A$m) | C8: =C6+C7
B9: Valuation Date | C9: 46022
B11: WACC Inputs
B12: Risk-free Rate | C12: 0.04
B13: Equity Risk Premium | C13: 0.06
B14: Beta | C14: 1
B15: Cost of Equity | C15: =C12+C13*C14
B16: Pre-tax Cost of Debt | C16: 0.06
B17: Tax Rate | C17: 0.3
B18: After-tax Cost of Debt | C18: =C16*(1-C17)
B19: Debt Weight (D/(D+E)) | C19: 0.3
B20: WACC | C20: =C15*(1-C19)+C18*C19
B21: Terminal Growth Rate | C21: 0.025
B22: Stub Period | C22: =(INDEX(Annual!$D:$P,4,MATCH($D$24,Annual!$D$3:$P$3,0))-C9)/365.25
B24: FCF Projection | D24: FY26E | E24: FY27E | F24: FY28E | G24: FY29E | H24: FY30E | I24: FY31E | J24: FY32E | K24: FY33E | L24: FY34E | M24: FY35E
B25: EBITDA | C25: A$m | D25: =INDEX(Annual!$D:$P,MATCH("EBITDA-Statutory EBITDA",Annual!$A:$A,0),MATCH(D$24,Annual!$D$3:$P$3,0)) | E25: =INDEX(Annual!$D:$P,MATCH("EBITDA-Statutory EBITDA",Annual!$A:$A,0),MATCH(E$24,Annual!$D$3:$P$3,0)) | F25: =INDEX(Annual!$D:$P,MATCH("EBITDA-Statutory EBITDA",Annual!$A:$A,0),MATCH(F$24,Annual!$D$3:$P$3,0)) | G25: =INDEX(Annual!$D:$P,MATCH("EBITDA-Statutory EBITDA",Annual!$A:$A,0),MATCH(G$24,Annual!$D$3:$P$3,0)) | H25: =INDEX(Annual!$D:$P,MATCH("EBITDA-Statutory EBITDA",Annual!$A:$A,0),MATCH(H$24,Annual!$D$3:$P$3,0)) | I25: =INDEX(Annual!$D:$P,MATCH("EBITDA-Statutory EBITDA",Annual!$A:$A,0),MATCH(I$24,Annual!$D$3:$P$3,0)) | J25: =INDEX(Annual!$D:$P,MATCH("EBITDA-Statutory EBITDA",Annual!$A:$A,0),MATCH(J$24,Annual!$D$3:$P$3,0)) | K25: =INDEX(Annual!$D:$P,MATCH("EBITDA-Statutory EBITDA",Annual!$A:$A,0),MATCH(K$24,Annual!$D$3:$P$3,0)) | ... M25: =INDEX(Annual!$D:$P,MATCH("EBITDA-Statutory EBITDA",Annual!$A:$A,0),MATCH(M$24,Annual!$D$3:$P$3,0))
B26: less D&A | C26: A$m | D26: =INDEX(Annual!$D:$P,MATCH("DA-Total DA",Annual!$A:$A,0),MATCH(D$24,Annual!$D$3:$P$3,0)) | E26: =INDEX(Annual!$D:$P,MATCH("DA-Total DA",Annual!$A:$A,0),MATCH(E$24,Annual!$D$3:$P$3,0)) | F26: =INDEX(Annual!$D:$P,MATCH("DA-Total DA",Annual!$A:$A,0),MATCH(F$24,Annual!$D$3:$P$3,0)) | G26: =INDEX(Annual!$D:$P,MATCH("DA-Total DA",Annual!$A:$A,0),MATCH(G$24,Annual!$D$3:$P$3,0)) | H26: =INDEX(Annual!$D:$P,MATCH("DA-Total DA",Annual!$A:$A,0),MATCH(H$24,Annual!$D$3:$P$3,0)) | I26: =INDEX(Annual!$D:$P,MATCH("DA-Total DA",Annual!$A:$A,0),MATCH(I$24,Annual!$D$3:$P$3,0)) | J26: =INDEX(Annual!$D:$P,MATCH("DA-Total DA",Annual!$A:$A,0),MATCH(J$24,Annual!$D$3:$P$3,0)) | K26: =INDEX(Annual!$D:$P,MATCH("DA-Total DA",Annual!$A:$A,0),MATCH(K$24,Annual!$D$3:$P$3,0)) | ... M26: =INDEX(Annual!$D:$P,MATCH("DA-Total DA",Annual!$A:$A,0),MATCH(M$24,Annual!$D$3:$P$3,0))
B27: EBIT | C27: A$m | D27: =INDEX(Annual!$D:$P,MATCH("EBIT-EBIT",Annual!$A:$A,0),MATCH(D$24,Annual!$D$3:$P$3,0)) | E27: =INDEX(Annual!$D:$P,MATCH("EBIT-EBIT",Annual!$A:$A,0),MATCH(E$24,Annual!$D$3:$P$3,0)) | F27: =INDEX(Annual!$D:$P,MATCH("EBIT-EBIT",Annual!$A:$A,0),MATCH(F$24,Annual!$D$3:$P$3,0)) | G27: =INDEX(Annual!$D:$P,MATCH("EBIT-EBIT",Annual!$A:$A,0),MATCH(G$24,Annual!$D$3:$P$3,0)) | H27: =INDEX(Annual!$D:$P,MATCH("EBIT-EBIT",Annual!$A:$A,0),MATCH(H$24,Annual!$D$3:$P$3,0)) | I27: =INDEX(Annual!$D:$P,MATCH("EBIT-EBIT",Annual!$A:$A,0),MATCH(I$24,Annual!$D$3:$P$3,0)) | J27: =INDEX(Annual!$D:$P,MATCH("EBIT-EBIT",Annual!$A:$A,0),MATCH(J$24,Annual!$D$3:$P$3,0)) | K27: =INDEX(Annual!$D:$P,MATCH("EBIT-EBIT",Annual!$A:$A,0),MATCH(K$24,Annual!$D$3:$P$3,0)) | ... M27: =INDEX(Annual!$D:$P,MATCH("EBIT-EBIT",Annual!$A:$A,0),MATCH(M$24,Annual!$D$3:$P$3,0))
B28: less Tax on EBIT | C28: A$m | D28: =-D27*$C$17 | E28: =-E27*$C$17 | F28: =-F27*$C$17 | G28: =-G27*$C$17 | H28: =-H27*$C$17 | I28: =-I27*$C$17 | J28: =-J27*$C$17 | K28: =-K27*$C$17 | ... M28: =-M27*$C$17
B29: NOPAT | C29: A$m | D29: =D27+D28 | E29: =E27+E28 | F29: =F27+F28 | G29: =G27+G28 | H29: =H27+H28 | I29: =I27+I28 | J29: =J27+J28 | K29: =K27+K28 | ... M29: =M27+M28
B30: plus D&A | C30: A$m | D30: =-D26 | E30: =-E26 | F30: =-F26 | G30: =-G26 | H30: =-H26 | I30: =-I26 | J30: =-J26 | K30: =-K26 | ... M30: =-M26
B31: less Capex | C31: A$m | D31: =INDEX(Annual!$D:$P,MATCH("CF-Capex PPE",Annual!$A:$A,0),MATCH(D$24,Annual!$D$3:$P$3,0))+INDEX(Annual!$D:$P,MATCH("CF-Capex Intang",Annual!$A:$A,0),MATCH(D$24,Annual!$D$3:$P$3,0)) | E31: =INDEX(Annual!$D:$P,MATCH("CF-Capex PPE",Annual!$A:$A,0),MATCH(E$24,Annual!$D$3:$P$3,0))+INDEX(Annual!$D:$P,MATCH("CF-Capex Intang",Annual!$A:$A,0),MATCH(E$24,Annual!$D$3:$P$3,0)) | F31: =INDEX(Annual!$D:$P,MATCH("CF-Capex PPE",Annual!$A:$A,0),MATCH(F$24,Annual!$D$3:$P$3,0))+INDEX(Annual!$D:$P,MATCH("CF-Capex Intang",Annual!$A:$A,0),MATCH(F$24,Annual!$D$3:$P$3,0)) | G31: =INDEX(Annual!$D:$P,MATCH("CF-Capex PPE",Annual!$A:$A,0),MATCH(G$24,Annual!$D$3:$P$3,0))+INDEX(Annual!$D:$P,MATCH("CF-Capex Intang",Annual!$A:$A,0),MATCH(G$24,Annual!$D$3:$P$3,0)) | H31: =INDEX(Annual!$D:$P,MATCH("CF-Capex PPE",Annual!$A:$A,0),MATCH(H$24,Annual!$D$3:$P$3,0))+INDEX(Annual!$D:$P,MATCH("CF-Capex Intang",Annual!$A:$A,0),MATCH(H$24,Annual!$D$3:$P$3,0)) | I31: =INDEX(Annual!$D:$P,MATCH("CF-Capex PPE",Annual!$A:$A,0),MATCH(I$24,Annual!$D$3:$P$3,0))+INDEX(Annual!$D:$P,MATCH("CF-Capex Intang",Annual!$A:$A,0),MATCH(I$24,Annual!$D$3:$P$3,0)) | J31: =INDEX(Annual!$D:$P,MATCH("CF-Capex PPE",Annual!$A:$A,0),MATCH(J$24,Annual!$D$3:$P$3,0))+INDEX(Annual!$D:$P,MATCH("CF-Capex Intang",Annual!$A:$A,0),MATCH(J$24,Annual!$D$3:$P$3,0)) | K31: =INDEX(Annual!$D:$P,MATCH("CF-Capex PPE",Annual!$A:$A,0),MATCH(K$24,Annual!$D$3:$P$3,0))+INDEX(Annual!$D:$P,MATCH("CF-Capex Intang",Annual!$A:$A,0),MATCH(K$24,Annual!$D$3:$P$3,0)) | ... M31: =INDEX(Annual!$D:$P,MATCH("CF-Capex PPE",Annual!$A:$A,0),MATCH(M$24,Annual!$D$3:$P$3,0))+INDEX(Annual!$D:$P,MATCH("CF-Capex Intang",Annual!$A:$A,0),MATCH(M$24,Annual!$D$3:$P$3,0))
B32: less WC Change | C32: A$m | D32: =INDEX(Annual!$D:$P,MATCH("CF-WC Change",Annual!$A:$A,0),MATCH(D$24,Annual!$D$3:$P$3,0)) | E32: =INDEX(Annual!$D:$P,MATCH("CF-WC Change",Annual!$A:$A,0),MATCH(E$24,Annual!$D$3:$P$3,0)) | F32: =INDEX(Annual!$D:$P,MATCH("CF-WC Change",Annual!$A:$A,0),MATCH(F$24,Annual!$D$3:$P$3,0)) | G32: =INDEX(Annual!$D:$P,MATCH("CF-WC Change",Annual!$A:$A,0),MATCH(G$24,Annual!$D$3:$P$3,0)) | H32: =INDEX(Annual!$D:$P,MATCH("CF-WC Change",Annual!$A:$A,0),MATCH(H$24,Annual!$D$3:$P$3,0)) | I32: =INDEX(Annual!$D:$P,MATCH("CF-WC Change",Annual!$A:$A,0),MATCH(I$24,Annual!$D$3:$P$3,0)) | J32: =INDEX(Annual!$D:$P,MATCH("CF-WC Change",Annual!$A:$A,0),MATCH(J$24,Annual!$D$3:$P$3,0)) | K32: =INDEX(Annual!$D:$P,MATCH("CF-WC Change",Annual!$A:$A,0),MATCH(K$24,Annual!$D$3:$P$3,0)) | ... M32: =INDEX(Annual!$D:$P,MATCH("CF-WC Change",Annual!$A:$A,0),MATCH(M$24,Annual!$D$3:$P$3,0))
B33: FCFF | C33: A$m | D33: =D29+D30+D31+D32 | E33: =E29+E30+E31+E32 | F33: =F29+F30+F31+F32 | G33: =G29+G30+G31+G32 | H33: =H29+H30+H31+H32 | I33: =I29+I30+I31+I32 | J33: =J29+J30+J31+J32 | K33: =K29+K30+K31+K32 | ... M33: =M29+M30+M31+M32
B34: Normalised FCFF (capex=D&A) | C34: A$m | M34: =M29+M32
B35: Terminal Value | M35: =M34*(1+$C$21)/($C$20-$C$21)
B37: Discount Factor | D37: =1/(1+$C$20)^($C$22+0) | E37: =1/(1+$C$20)^($C$22+1) | F37: =1/(1+$C$20)^($C$22+2) | G37: =1/(1+$C$20)^($C$22+3) | H37: =1/(1+$C$20)^($C$22+4) | I37: =1/(1+$C$20)^($C$22+5) | J37: =1/(1+$C$20)^($C$22+6) | K37: =1/(1+$C$20)^($C$22+7) | L37: =1/(1+$C$20)^($C$22+8) | M37: =1/(1+$C$20)^($C$22+9)
B38: PV of FCFF | D38: =D33*D37 | E38: =E33*E37 | F38: =F33*F37 | G38: =G33*G37 | H38: =H33*H37 | I38: =I33*I37 | J38: =J33*J37 | K38: =K33*K37 | ... M38: =M33*M37
B39: PV of Terminal Value | M39: =M35*M37
B41: Sum of PV of FCFs | C41: =SUM(D38:M38)
B42: PV of Terminal Value | C42: =M39
B43: Enterprise Value | C43: =C41+C42
B45: less Net Debt | C45: =-C7
B46: less Lease Liabilities | C46: =-INDEX(Annual!$D:$P,MATCH("BS-Lease Liabilities",Annual!$A:$A,0),MATCH($D$24,Annual!$D$3:$P$3,0)-1)
B47: Equity Value | C47: =C43+C45+C46
B48: Per Share Value (A$) | C48: =C47/C5
B49: Upside / Downside | C49: =IF(C4=0,"",C48/C4-1)
B52: EV/EBITDA SOTP
B54: Select FY: | C54: FY27E
B56: Segment | C56: =$C$54&" EBITDA" | D56: Multiple | E56: Implied EV
B57: Australia | C57: =INDEX(Annual!$D:$P,MATCH("SegEBITDA-Australia",Annual!$A:$A,0),MATCH($C$54,Annual!$D$3:$P$3,0)) | D57: 25 | E57: =C57*D57
B58: US | C58: =INDEX(Annual!$D:$P,MATCH("SegEBITDA-US",Annual!$A:$A,0),MATCH($C$54,Annual!$D$3:$P$3,0)) | D58: 15 | E58: =C58*D58
B59: Corporate | C59: =INDEX(Annual!$D:$P,MATCH("EBITDA-Statutory EBITDA",Annual!$A:$A,0),MATCH($C$54,Annual!$D$3:$P$3,0))-C57-C58 | D59: =IF((C57+C58)=0,"",(C57*D57+C58*D58)/(C57+C58)) | E59: =C59*D59
B61: Group EV | C61: =SUM(E57:E59) | E61: =SUM(E57:E59)
B62: less Net Debt | C62: =-C7 | E62: =-C7
B63: less Lease Liabilities | C63: =-INDEX(Annual!$D:$P,MATCH("BS-Lease Liabilities",Annual!$A:$A,0),MATCH($D$24,Annual!$D$3:$P$3,0)-1) | E63: =-INDEX(Annual!$D:$P,MATCH("BS-Lease Liabilities",Annual!$A:$A,0),MATCH($D$24,Annual!$D$3:$P$3,0)-1)
B64: Equity Value | C64: =C61+C62+C63 | E64: =E61+E62+E63
B65: Per Share Value (A$) | C65: =C64/C5 | E65: =E64/C5
B66: Upside / Downside | C66: =IF(C4=0,"",C65/C4-1) | E66: =IF(C4=0,"",E65/C4-1)
B68: Implied Group EV/EBITDA | C68: =IF(C59+C57+C58=0,"",C61/(C57+C58+C59)) | E68: =IF(INDEX(Annual!$D:$P,MATCH("EBITDA-Statutory EBITDA",Annual!$A:$A,0),MATCH($C$54,Annual!$D$3:$P$3,0))=0,"",E61/INDEX(Annual!$D:$P,MATCH("EBITDA-Statutory EBITDA",Annual!$A:$A,0),MATCH($C$54,Annual!$D$3:$P$3,0)))

Sheet Annual
D1: 2023 | E1: 2024 | F1: 2025 | G1: 2026 | H1: 2027 | I1: 2028 | J1: 2029 | K1: 2030 | L1: 2031 | M1: 2032 | N1: 2033 | O1: 2034 | P1: 2035
B2: GYG Model Summary | D2: Actual ----------> | G2: Forecast ----->
B3: Guzman y Gomez (GYG.AX) | C3: Units | D3: FY23A | E3: FY24A | F3: FY25A | G3: FY26E | H3: FY27E | I3: FY28E | J3: FY29E | K3: FY30E | L3: FY31E | M3: FY32E | N3: FY33E | O3: FY34E | P3: FY35E
D4: 45107 | E4: 45473 | F4: 45838 | G4: 46203 | H4: 46568 | I4: 46934 | J4: 47299 | K4: 47664 | L4: 48029 | M4: 48395 | N4: 48760 | O4: 49125 | P4: 49490
B5: P&L
B6: Revenue
A7: Rev-Corp Restaurant Sales Aus | B7: Corp Restaurant Sales - Australia | C7: A$m | D7: 211.975 | E7: 278.877 | F7: 359.722 | G7: =INDEX('HY & Segments'!$A:$AG,MATCH($A7,'HY & Segments'!$A:$A,0),MATCH("1H"&RIGHT(G$1,2),'HY & Segments'!$3:$3,0))+INDEX('HY & Segments'!$A:$AG,MATCH($A7,'HY & Segments'!$A:$A,0),MATCH("2H"&RIGHT(G$1,2),'HY & Segments'!$3:$3,0)) | H7: =INDEX('HY & Segments'!$A:$AG,MATCH($A7,'HY & Segments'!$A:$A,0),MATCH("1H"&RIGHT(H$1,2),'HY & Segments'!$3:$3,0))+INDEX('HY & Segments'!$A:$AG,MATCH($A7,'HY & Segments'!$A:$A,0),MATCH("2H"&RIGHT(H$1,2),'HY & Segments'!$3:$3,0)) | I7: =INDEX('HY & Segments'!$A:$AG,MATCH($A7,'HY & Segments'!$A:$A,0),MATCH("1H"&RIGHT(I$1,2),'HY & Segments'!$3:$3,0))+INDEX('HY & Segments'!$A:$AG,MATCH($A7,'HY & Segments'!$A:$A,0),MATCH("2H"&RIGHT(I$1,2),'HY & Segments'!$3:$3,0)) | J7: =INDEX('HY & Segments'!$A:$AG,MATCH($A7,'HY & Segments'!$A:$A,0),MATCH("1H"&RIGHT(J$1,2),'HY & Segments'!$3:$3,0))+INDEX('HY & Segments'!$A:$AG,MATCH($A7,'HY & Segments'!$A:$A,0),MATCH("2H"&RIGHT(J$1,2),'HY & Segments'!$3:$3,0)) | K7: =INDEX('HY & Segments'!$A:$AG,MATCH($A7,'HY & Segments'!$A:$A,0),MATCH("1H"&RIGHT(K$1,2),'HY & Segments'!$3:$3,0))+INDEX('HY & Segments'!$A:$AG,MATCH($A7,'HY & Segments'!$A:$A,0),MATCH("2H"&RIGHT(K$1,2),'HY & Segments'!$3:$3,0)) | L7: =INDEX('HY & Segments'!$A:$AG,MATCH($A7,'HY & Segments'!$A:$A,0),MATCH("1H"&RIGHT(L$1,2),'HY & Segments'!$3:$3,0))+INDEX('HY & Segments'!$A:$AG,MATCH($A7,'HY & Segments'!$A:$A,0),MATCH("2H"&RIGHT(L$1,2),'HY & Segments'!$3:$3,0)) | M7: =INDEX('HY & Segments'!$A:$AG,MATCH($A7,'HY & Segments'!$A:$A,0),MATCH("1H"&RIGHT(M$1,2),'HY & Segments'!$3:$3,0))+INDEX('HY & Segments'!$A:$AG,MATCH($A7,'HY & Segments'!$A:$A,0),MATCH("2H"&RIGHT(M$1,2),'HY & Segments'!$3:$3,0)) | N7: =INDEX('HY & Segments'!$A:$AG,MATCH($A7,'HY & Segments'!$A:$A,0),MATCH("1H"&RIGHT(N$1,2),'HY & Segments'!$3:$3,0))+INDEX('HY & Segments'!$A:$AG,MATCH($A7,'HY & Segments'!$A:$A,0),MATCH("2H"&RIGHT(N$1,2),'HY & Segments'!$3:$3,0)) | ... P7: =INDEX('HY & Segments'!$A:$AG,MATCH($A7,'HY & Segments'!$A:$A,0),MATCH("1H"&RIGHT(P$1,2),'HY & Segments'!$3:$3,0))+INDEX('HY & Segments'!$A:$AG,MATCH($A7,'HY & Segments'!$A:$A,0),MATCH("2H"&RIGHT(P$1,2),'HY & Segments'!$3:$3,0))
A8: Rev-Corp Restaurant Sales US | B8: Corp Restaurant Sales - US | C8: A$m | D8: 5.959 | E8: 10.834 | F8: 8.869 | G8: =INDEX('HY & Segments'!$A:$AG,MATCH($A8,'HY & Segments'!$A:$A,0),MATCH("1H"&RIGHT(G$1,2),'HY & Segments'!$3:$3,0))+INDEX('HY & Segments'!$A:$AG,MATCH($A8,'HY & Segments'!$A:$A,0),MATCH("2H"&RIGHT(G$1,2),'HY & Segments'!$3:$3,0)) | H8: =INDEX('HY & Segments'!$A:$AG,MATCH($A8,'HY & Segments'!$A:$A,0),MATCH("1H"&RIGHT(H$1,2),'HY & Segments'!$3:$3,0))+INDEX('HY & Segments'!$A:$AG,MATCH($A8,'HY & Segments'!$A:$A,0),MATCH("2H"&RIGHT(H$1,2),'HY & Segments'!$3:$3,0)) | I8: =INDEX('HY & Segments'!$A:$AG,MATCH($A8,'HY & Segments'!$A:$A,0),MATCH("1H"&RIGHT(I$1,2),'HY & Segments'!$3:$3,0))+INDEX('HY & Segments'!$A:$AG,MATCH($A8,'HY & Segments'!$A:$A,0),MATCH("2H"&RIGHT(I$1,2),'HY & Segments'!$3:$3,0)) | J8: =INDEX('HY & Segments'!$A:$AG,MATCH($A8,'HY & Segments'!$A:$A,0),MATCH("1H"&RIGHT(J$1,2),'HY & Segments'!$3:$3,0))+INDEX('HY & Segments'!$A:$AG,MATCH($A8,'HY & Segments'!$A:$A,0),MATCH("2H"&RIGHT(J$1,2),'HY & Segments'!$3:$3,0)) | K8: =INDEX('HY & Segments'!$A:$AG,MATCH($A8,'HY & Segments'!$A:$A,0),MATCH("1H"&RIGHT(K$1,2),'HY & Segments'!$3:$3,0))+INDEX('HY & Segments'!$A:$AG,MATCH($A8,'HY & Segments'!$A:$A,0),MATCH("2H"&RIGHT(K$1,2),'HY & Segments'!$3:$3,0)) | L8: =INDEX('HY & Segments'!$A:$AG,MATCH($A8,'HY & Segments'!$A:$A,0),MATCH("1H"&RIGHT(L$1,2),'HY & Segments'!$3:$3,0))+INDEX('HY & Segments'!$A:$AG,MATCH($A8,'HY & Segments'!$A:$A,0),MATCH("2H"&RIGHT(L$1,2),'HY & Segments'!$3:$3,0)) | M8: =INDEX('HY & Segments'!$A:$AG,MATCH($A8,'HY & Segments'!$A:$A,0),MATCH("1H"&RIGHT(M$1,2),'HY & Segments'!$3:$3,0))+INDEX('HY & Segments'!$A:$AG,MATCH($A8,'HY & Segments'!$A:$A,0),MATCH("2H"&RIGHT(M$1,2),'HY & Segments'!$3:$3,0)) | N8: =INDEX('HY & Segments'!$A:$AG,MATCH($A8,'HY & Segments'!$A:$A,0),MATCH("1H"&RIGHT(N$1,2),'HY & Segments'!$3:$3,0))+INDEX('HY & Segments'!$A:$AG,MATCH($A8,'HY & Segments'!$A:$A,0),MATCH("2H"&RIGHT(N$1,2),'HY & Segments'!$3:$3,0)) | ... P8: =INDEX('HY & Segments'!$A:$AG,MATCH($A8,'HY & Segments'!$A:$A,0),MATCH("1H"&RIGHT(P$1,2),'HY & Segments'!$3:$3,0))+INDEX('HY & Segments'!$A:$AG,MATCH($A8,'HY & Segments'!$A:$A,0),MATCH("2H"&RIGHT(P$1,2),'HY & Segments'!$3:$3,0))
A9: Rev-Total Corp Restaurant Sales | B9: Total Corp Restaurant Sales | C9: A$m | D9: 217.934 | E9: 289.711 | F9: 368.591 | G9: =G7+G8 | H9: =H7+H8 | I9: =I7+I8 | J9: =J7+J8 | K9: =K7+K8 | L9: =L7+L8 | M9: =M7+M8 | N9: =N7+N8 | ... P9: =P7+P8
A10: Rev-Franchise Royalty Revenue | B10: Franchise Royalty Revenue | C10: A$m | D10: 40.51 | E10: 51.858 | F10: 66.761 | G10: =INDEX('HY & Segments'!$A:$AG,MATCH($A10,'HY & Segments'!$A:$A,0),MATCH("1H"&RIGHT(G$1,2),'HY & Segments'!$3:$3,0))+INDEX('HY & Segments'!$A:$AG,MATCH($A10,'HY & Segments'!$A:$A,0),MATCH("2H"&RIGHT(G$1,2),'HY & Segments'!$3:$3,0)) | H10: =INDEX('HY & Segments'!$A:$AG,MATCH($A10,'HY & Segments'!$A:$A,0),MATCH("1H"&RIGHT(H$1,2),'HY & Segments'!$3:$3,0))+INDEX('HY & Segments'!$A:$AG,MATCH($A10,'HY & Segments'!$A:$A,0),MATCH("2H"&RIGHT(H$1,2),'HY & Segments'!$3:$3,0)) | I10: =INDEX('HY & Segments'!$A:$AG,MATCH($A10,'HY & Segments'!$A:$A,0),MATCH("1H"&RIGHT(I$1,2),'HY & Segments'!$3:$3,0))+INDEX('HY & Segments'!$A:$AG,MATCH($A10,'HY & Segments'!$A:$A,0),MATCH("2H"&RIGHT(I$1,2),'HY & Segments'!$3:$3,0)) | J10: =INDEX('HY & Segments'!$A:$AG,MATCH($A10,'HY & Segments'!$A:$A,0),MATCH("1H"&RIGHT(J$1,2),'HY & Segments'!$3:$3,0))+INDEX('HY & Segments'!$A:$AG,MATCH($A10,'HY & Segments'!$A:$A,0),MATCH("2H"&RIGHT(J$1,2),'HY & Segments'!$3:$3,0)) | K10: =INDEX('HY & Segments'!$A:$AG,MATCH($A10,'HY & Segments'!$A:$A,0),MATCH("1H"&RIGHT(K$1,2),'HY & Segments'!$3:$3,0))+INDEX('HY & Segments'!$A:$AG,MATCH($A10,'HY & Segments'!$A:$A,0),MATCH("2H"&RIGHT(K$1,2),'HY & Segments'!$3:$3,0)) | L10: =INDEX('HY & Segments'!$A:$AG,MATCH($A10,'HY & Segments'!$A:$A,0),MATCH("1H"&RIGHT(L$1,2),'HY & Segments'!$3:$3,0))+INDEX('HY & Segments'!$A:$AG,MATCH($A10,'HY & Segments'!$A:$A,0),MATCH("2H"&RIGHT(L$1,2),'HY & Segments'!$3:$3,0)) | M10: =INDEX('HY & Segments'!$A:$AG,MATCH($A10,'HY & Segments'!$A:$A,0),MATCH("1H"&RIGHT(M$1,2),'HY & Segments'!$3:$3,0))+INDEX('HY & Segments'!$A:$AG,MATCH($A10,'HY & Segments'!$A:$A,0),MATCH("2H"&RIGHT(M$1,2),'HY & Segments'!$3:$3,0)) | N10: =INDEX('HY & Segments'!$A:$AG,MATCH($A10,'HY & Segments'!$A:$A,0),MATCH("1H"&RIGHT(N$1,2),'HY & Segments'!$3:$3,0))+INDEX('HY & Segments'!$A:$AG,MATCH($A10,'HY & Segments'!$A:$A,0),MATCH("2H"&RIGHT(N$1,2),'HY & Segments'!$3:$3,0)) | ... P10: =INDEX('HY & Segments'!$A:$AG,MATCH($A10,'HY & Segments'!$A:$A,0),MATCH("1H"&RIGHT(P$1,2),'HY & Segments'!$3:$3,0))+INDEX('HY & Segments'!$A:$AG,MATCH($A10,'HY & Segments'!$A:$A,0),MATCH("2H"&RIGHT(P$1,2),'HY & Segments'!$3:$3,0))
A11: Rev-Franchise Fee Revenue | B11: Franchise Fee Revenue | C11: A$m | D11: 0.6 | E11: 0.645 | F11: 0.63 | G11: =INDEX('HY & Segments'!$A:$AG,MATCH($A11,'HY & Segments'!$A:$A,0),MATCH("1H"&RIGHT(G$1,2),'HY & Segments'!$3:$3,0))+INDEX('HY & Segments'!$A:$AG,MATCH($A11,'HY & Segments'!$A:$A,0),MATCH("2H"&RIGHT(G$1,2),'HY & Segments'!$3:$3,0)) | H11: =INDEX('HY & Segments'!$A:$AG,MATCH($A11,'HY & Segments'!$A:$A,0),MATCH("1H"&RIGHT(H$1,2),'HY & Segments'!$3:$3,0))+INDEX('HY & Segments'!$A:$AG,MATCH($A11,'HY & Segments'!$A:$A,0),MATCH("2H"&RIGHT(H$1,2),'HY & Segments'!$3:$3,0)) | I11: =INDEX('HY & Segments'!$A:$AG,MATCH($A11,'HY & Segments'!$A:$A,0),MATCH("1H"&RIGHT(I$1,2),'HY & Segments'!$3:$3,0))+INDEX('HY & Segments'!$A:$AG,MATCH($A11,'HY & Segments'!$A:$A,0),MATCH("2H"&RIGHT(I$1,2),'HY & Segments'!$3:$3,0)) | J11: =INDEX('HY & Segments'!$A:$AG,MATCH($A11,'HY & Segments'!$A:$A,0),MATCH("1H"&RIGHT(J$1,2),'HY & Segments'!$3:$3,0))+INDEX('HY & Segments'!$A:$AG,MATCH($A11,'HY & Segments'!$A:$A,0),MATCH("2H"&RIGHT(J$1,2),'HY & Segments'!$3:$3,0)) | K11: =INDEX('HY & Segments'!$A:$AG,MATCH($A11,'HY & Segments'!$A:$A,0),MATCH("1H"&RIGHT(K$1,2),'HY & Segments'!$3:$3,0))+INDEX('HY & Segments'!$A:$AG,MATCH($A11,'HY & Segments'!$A:$A,0),MATCH("2H"&RIGHT(K$1,2),'HY & Segments'!$3:$3,0)) | L11: =INDEX('HY & Segments'!$A:$AG,MATCH($A11,'HY & Segments'!$A:$A,0),MATCH("1H"&RIGHT(L$1,2),'HY & Segments'!$3:$3,0))+INDEX('HY & Segments'!$A:$AG,MATCH($A11,'HY & Segments'!$A:$A,0),MATCH("2H"&RIGHT(L$1,2),'HY & Segments'!$3:$3,0)) | M11: =INDEX('HY & Segments'!$A:$AG,MATCH($A11,'HY & Segments'!$A:$A,0),MATCH("1H"&RIGHT(M$1,2),'HY & Segments'!$3:$3,0))+INDEX('HY & Segments'!$A:$AG,MATCH($A11,'HY & Segments'!$A:$A,0),MATCH("2H"&RIGHT(M$1,2),'HY & Segments'!$3:$3,0)) | N11: =INDEX('HY & Segments'!$A:$AG,MATCH($A11,'HY & Segments'!$A:$A,0),MATCH("1H"&RIGHT(N$1,2),'HY & Segments'!$3:$3,0))+INDEX('HY & Segments'!$A:$AG,MATCH($A11,'HY & Segments'!$A:$A,0),MATCH("2H"&RIGHT(N$1,2),'HY & Segments'!$3:$3,0)) | ... P11: =INDEX('HY & Segments'!$A:$AG,MATCH($A11,'HY & Segments'!$A:$A,0),MATCH("1H"&RIGHT(P$1,2),'HY & Segments'!$3:$3,0))+INDEX('HY & Segments'!$A:$AG,MATCH($A11,'HY & Segments'!$A:$A,0),MATCH("2H"&RIGHT(P$1,2),'HY & Segments'!$3:$3,0))
A12: Rev-Total Revenue | B12: Total Revenue | C12: A$m | D12: 259.044 | E12: 342.214 | F12: 435.982 | G12: =SUM(G9:G11) | H12: =SUM(H9:H11) | I12: =SUM(I9:I11) | J12: =SUM(J9:J11) | K12: =SUM(K9:K11) | L12: =SUM(L9:L11) | M12: =SUM(M9:M11) | N12: =SUM(N9:N11) | ... P12: =SUM(P9:P11)
B13: Revenue Growth | C13: % YoY | E13: =IF(D12=0,"",E12/D12-1) | F13: =IF(E12=0,"",F12/E12-1) | G13: =IF(F12=0,"",G12/F12-1) | H13: =IF(G12=0,"",H12/G12-1) | I13: =IF(H12=0,"",I12/H12-1) | J13: =IF(I12=0,"",J12/I12-1) | K13: =IF(J12=0,"",K12/J12-1) | L13: =IF(K12=0,"",L12/K12-1) | ... P13: =IF(O12=0,"",P12/O12-1)
B15: Other Revenue
A16: OthRev-Marketing Levy | B16: Marketing Levy Revenue | C16: A$m | D16: 13.252 | E16: 16.382 | F16: 19.688 | G16: =INDEX('HY & Segments'!$A:$AG,MATCH($A16,'HY & Segments'!$A:$A,0),MATCH("1H"&RIGHT(G$1,2),'HY & Segments'!$3:$3,0))+INDEX('HY & Segments'!$A:$AG,MATCH($A16,'HY & Segments'!$A:$A,0),MATCH("2H"&RIGHT(G$1,2),'HY & Segments'!$3:$3,0)) | H16: =INDEX('HY & Segments'!$A:$AG,MATCH($A16,'HY & Segments'!$A:$A,0),MATCH("1H"&RIGHT(H$1,2),'HY & Segments'!$3:$3,0))+INDEX('HY & Segments'!$A:$AG,MATCH($A16,'HY & Segments'!$A:$A,0),MATCH("2H"&RIGHT(H$1,2),'HY & Segments'!$3:$3,0)) | I16: =INDEX('HY & Segments'!$A:$AG,MATCH($A16,'HY & Segments'!$A:$A,0),MATCH("1H"&RIGHT(I$1,2),'HY & Segments'!$3:$3,0))+INDEX('HY & Segments'!$A:$AG,MATCH($A16,'HY & Segments'!$A:$A,0),MATCH("2H"&RIGHT(I$1,2),'HY & Segments'!$3:$3,0)) | J16: =INDEX('HY & Segments'!$A:$AG,MATCH($A16,'HY & Segments'!$A:$A,0),MATCH("1H"&RIGHT(J$1,2),'HY & Segments'!$3:$3,0))+INDEX('HY & Segments'!$A:$AG,MATCH($A16,'HY & Segments'!$A:$A,0),MATCH("2H"&RIGHT(J$1,2),'HY & Segments'!$3:$3,0)) | K16: =INDEX('HY & Segments'!$A:$AG,MATCH($A16,'HY & Segments'!$A:$A,0),MATCH("1H"&RIGHT(K$1,2),'HY & Segments'!$3:$3,0))+INDEX('HY & Segments'!$A:$AG,MATCH($A16,'HY & Segments'!$A:$A,0),MATCH("2H"&RIGHT(K$1,2),'HY & Segments'!$3:$3,0)) | L16: =INDEX('HY & Segments'!$A:$AG,MATCH($A16,'HY & Segments'!$A:$A,0),MATCH("1H"&RIGHT(L$1,2),'HY & Segments'!$3:$3,0))+INDEX('HY & Segments'!$A:$AG,MATCH($A16,'HY & Segments'!$A:$A,0),MATCH("2H"&RIGHT(L$1,2),'HY & Segments'!$3:$3,0)) | M16: =INDEX('HY & Segments'!$A:$AG,MATCH($A16,'HY & Segments'!$A:$A,0),MATCH("1H"&RIGHT(M$1,2),'HY & Segments'!$3:$3,0))+INDEX('HY & Segments'!$A:$AG,MATCH($A16,'HY & Segments'!$A:$A,0),MATCH("2H"&RIGHT(M$1,2),'HY & Segments'!$3:$3,0)) | N16: =INDEX('HY & Segments'!$A:$AG,MATCH($A16,'HY & Segments'!$A:$A,0),MATCH("1H"&RIGHT(N$1,2),'HY & Segments'!$3:$3,0))+INDEX('HY & Segments'!$A:$AG,MATCH($A16,'HY & Segments'!$A:$A,0),MATCH("2H"&RIGHT(N$1,2),'HY & Segments'!$3:$3,0)) | ... P16: =INDEX('HY & Segments'!$A:$AG,MATCH($A16,'HY & Segments'!$A:$A,0),MATCH("1H"&RIGHT(P$1,2),'HY & Segments'!$3:$3,0))+INDEX('HY & Segments'!$A:$AG,MATCH($A16,'HY & Segments'!$A:$A,0),MATCH("2H"&RIGHT(P$1,2),'HY & Segments'!$3:$3,0))
A17: OthRev-Other Franchise Revenue | B17: Other Franchise Revenue | C17: A$m | D17: 1.813 | E17: 6.164 | F17: 8.942 | G17: =INDEX('HY & Segments'!$A:$AG,MATCH($A17,'HY & Segments'!$A:$A,0),MATCH("1H"&RIGHT(G$1,2),'HY & Segments'!$3:$3,0))+INDEX('HY & Segments'!$A:$AG,MATCH($A17,'HY & Segments'!$A:$A,0),MATCH("2H"&RIGHT(G$1,2),'HY & Segments'!$3:$3,0)) | H17: =INDEX('HY & Segments'!$A:$AG,MATCH($A17,'HY & Segments'!$A:$A,0),MATCH("1H"&RIGHT(H$1,2),'HY & Segments'!$3:$3,0))+INDEX('HY & Segments'!$A:$AG,MATCH($A17,'HY & Segments'!$A:$A,0),MATCH("2H"&RIGHT(H$1,2),'HY & Segments'!$3:$3,0)) | I17: =INDEX('HY & Segments'!$A:$AG,MATCH($A17,'HY & Segments'!$A:$A,0),MATCH("1H"&RIGHT(I$1,2),'HY & Segments'!$3:$3,0))+INDEX('HY & Segments'!$A:$AG,MATCH($A17,'HY & Segments'!$A:$A,0),MATCH("2H"&RIGHT(I$1,2),'HY & Segments'!$3:$3,0)) | J17: =INDEX('HY & Segments'!$A:$AG,MATCH($A17,'HY & Segments'!$A:$A,0),MATCH("1H"&RIGHT(J$1,2),'HY & Segments'!$3:$3,0))+INDEX('HY & Segments'!$A:$AG,MATCH($A17,'HY & Segments'!$A:$A,0),MATCH("2H"&RIGHT(J$1,2),'HY & Segments'!$3:$3,0)) | K17: =INDEX('HY & Segments'!$A:$AG,MATCH($A17,'HY & Segments'!$A:$A,0),MATCH("1H"&RIGHT(K$1,2),'HY & Segments'!$3:$3,0))+INDEX('HY & Segments'!$A:$AG,MATCH($A17,'HY & Segments'!$A:$A,0),MATCH("2H"&RIGHT(K$1,2),'HY & Segments'!$3:$3,0)) | L17: =INDEX('HY & Segments'!$A:$AG,MATCH($A17,'HY & Segments'!$A:$A,0),MATCH("1H"&RIGHT(L$1,2),'HY & Segments'!$3:$3,0))+INDEX('HY & Segments'!$A:$AG,MATCH($A17,'HY & Segments'!$A:$A,0),MATCH("2H"&RIGHT(L$1,2),'HY & Segments'!$3:$3,0)) | M17: =INDEX('HY & Segments'!$A:$AG,MATCH($A17,'HY & Segments'!$A:$A,0),MATCH("1H"&RIGHT(M$1,2),'HY & Segments'!$3:$3,0))+INDEX('HY & Segments'!$A:$AG,MATCH($A17,'HY & Segments'!$A:$A,0),MATCH("2H"&RIGHT(M$1,2),'HY & Segments'!$3:$3,0)) | N17: =INDEX('HY & Segments'!$A:$AG,MATCH($A17,'HY & Segments'!$A:$A,0),MATCH("1H"&RIGHT(N$1,2),'HY & Segments'!$3:$3,0))+INDEX('HY & Segments'!$A:$AG,MATCH($A17,'HY & Segments'!$A:$A,0),MATCH("2H"&RIGHT(N$1,2),'HY & Segments'!$3:$3,0)) | ... P17: =INDEX('HY & Segments'!$A:$AG,MATCH($A17,'HY & Segments'!$A:$A,0),MATCH("1H"&RIGHT(P$1,2),'HY & Segments'!$3:$3,0))+INDEX('HY & Segments'!$A:$AG,MATCH($A17,'HY & Segments'!$A:$A,0),MATCH("2H"&RIGHT(P$1,2),'HY & Segments'!$3:$3,0))
A18: OthRev-Other Income | B18: Other Income | C18: A$m | D18: 2.66 | E18: 0.228 | F18: 3.394 | G18: =INDEX('HY & Segments'!$A:$AG,MATCH($A18,'HY & Segments'!$A:$A,0),MATCH("1H"&RIGHT(G$1,2),'HY & Segments'!$3:$3,0))+INDEX('HY & Segments'!$A:$AG,MATCH($A18,'HY & Segments'!$A:$A,0),MATCH("2H"&RIGHT(G$1,2),'HY & Segments'!$3:$3,0)) | H18: =INDEX('HY & Segments'!$A:$AG,MATCH($A18,'HY & Segments'!$A:$A,0),MATCH("1H"&RIGHT(H$1,2),'HY & Segments'!$3:$3,0))+INDEX('HY & Segments'!$A:$AG,MATCH($A18,'HY & Segments'!$A:$A,0),MATCH("2H"&RIGHT(H$1,2),'HY & Segments'!$3:$3,0)) | I18: =INDEX('HY & Segments'!$A:$AG,MATCH($A18,'HY & Segments'!$A:$A,0),MATCH("1H"&RIGHT(I$1,2),'HY & Segments'!$3:$3,0))+INDEX('HY & Segments'!$A:$AG,MATCH($A18,'HY & Segments'!$A:$A,0),MATCH("2H"&RIGHT(I$1,2),'HY & Segments'!$3:$3,0)) | J18: =INDEX('HY & Segments'!$A:$AG,MATCH($A18,'HY & Segments'!$A:$A,0),MATCH("1H"&RIGHT(J$1,2),'HY & Segments'!$3:$3,0))+INDEX('HY & Segments'!$A:$AG,MATCH($A18,'HY & Segments'!$A:$A,0),MATCH("2H"&RIGHT(J$1,2),'HY & Segments'!$3:$3,0)) | K18: =INDEX('HY & Segments'!$A:$AG,MATCH($A18,'HY & Segments'!$A:$A,0),MATCH("1H"&RIGHT(K$1,2),'HY & Segments'!$3:$3,0))+INDEX('HY & Segments'!$A:$AG,MATCH($A18,'HY & Segments'!$A:$A,0),MATCH("2H"&RIGHT(K$1,2),'HY & Segments'!$3:$3,0)) | L18: =INDEX('HY & Segments'!$A:$AG,MATCH($A18,'HY & Segments'!$A:$A,0),MATCH("1H"&RIGHT(L$1,2),'HY & Segments'!$3:$3,0))+INDEX('HY & Segments'!$A:$AG,MATCH($A18,'HY & Segments'!$A:$A,0),MATCH("2H"&RIGHT(L$1,2),'HY & Segments'!$3:$3,0)) | M18: =INDEX('HY & Segments'!$A:$AG,MATCH($A18,'HY & Segments'!$A:$A,0),MATCH("1H"&RIGHT(M$1,2),'HY & Segments'!$3:$3,0))+INDEX('HY & Segments'!$A:$AG,MATCH($A18,'HY & Segments'!$A:$A,0),MATCH("2H"&RIGHT(M$1,2),'HY & Segments'!$3:$3,0)) | N18: =INDEX('HY & Segments'!$A:$AG,MATCH($A18,'HY & Segments'!$A:$A,0),MATCH("1H"&RIGHT(N$1,2),'HY & Segments'!$3:$3,0))+INDEX('HY & Segments'!$A:$AG,MATCH($A18,'HY & Segments'!$A:$A,0),MATCH("2H"&RIGHT(N$1,2),'HY & Segments'!$3:$3,0)) | ... P18: =INDEX('HY & Segments'!$A:$AG,MATCH($A18,'HY & Segments'!$A:$A,0),MATCH("1H"&RIGHT(P$1,2),'HY & Segments'!$3:$3,0))+INDEX('HY & Segments'!$A:$AG,MATCH($A18,'HY & Segments'!$A:$A,0),MATCH("2H"&RIGHT(P$1,2),'HY & Segments'!$3:$3,0))
A19: OthRev-Total Other Revenue | B19: Total Other Revenue & Income | C19: A$m | D19: 17.725 | E19: 22.774 | F19: 32.024 | G19: =SUM(G16:G18) | H19: =SUM(H16:H18) | I19: =SUM(I16:I18) | J19: =SUM(J16:J18) | K19: =SUM(K16:K18) | L19: =SUM(L16:L18) | M19: =SUM(M16:M18) | N19: =SUM(N16:N18) | ... P19: =SUM(P16:P18)
B21: Total Revenue & Other Income | C21: A$m | D21: =D12+D19 | E21: =E12+E19 | F21: =F12+F19 | G21: =G12+G19 | H21: =H12+H19 | I21: =I12+I19 | J21: =J12+J19 | K21: =K12+K19 | ... P21: =P12+P19
B23: Segment EBITDA Bridge
A24: SegEBITDA-Australia | B24: Australia Segment EBITDA | C24: A$m | D24: 33.306 | E24: 47.536 | F24: 66.029 | G24: =INDEX('HY & Segments'!$A:$AG,MATCH($A24,'HY & Segments'!$A:$A,0),MATCH("1H"&RIGHT(G$1,2),'HY & Segments'!$3:$3,0))+INDEX('HY & Segments'!$A:$AG,MATCH($A24,'HY & Segments'!$A:$A,0),MATCH("2H"&RIGHT(G$1,2),'HY & Segments'!$3:$3,0)) | H24: =INDEX('HY & Segments'!$A:$AG,MATCH($A24,'HY & Segments'!$A:$A,0),MATCH("1H"&RIGHT(H$1,2),'HY & Segments'!$3:$3,0))+INDEX('HY & Segments'!$A:$AG,MATCH($A24,'HY & Segments'!$A:$A,0),MATCH("2H"&RIGHT(H$1,2),'HY & Segments'!$3:$3,0)) | I24: =INDEX('HY & Segments'!$A:$AG,MATCH($A24,'HY & Segments'!$A:$A,0),MATCH("1H"&RIGHT(I$1,2),'HY & Segments'!$3:$3,0))+INDEX('HY & Segments'!$A:$AG,MATCH($A24,'HY & Segments'!$A:$A,0),MATCH("2H"&RIGHT(I$1,2),'HY & Segments'!$3:$3,0)) | J24: =INDEX('HY & Segments'!$A:$AG,MATCH($A24,'HY & Segments'!$A:$A,0),MATCH("1H"&RIGHT(J$1,2),'HY & Segments'!$3:$3,0))+INDEX('HY & Segments'!$A:$AG,MATCH($A24,'HY & Segments'!$A:$A,0),MATCH("2H"&RIGHT(J$1,2),'HY & Segments'!$3:$3,0)) | K24: =INDEX('HY & Segments'!$A:$AG,MATCH($A24,'HY & Segments'!$A:$A,0),MATCH("1H"&RIGHT(K$1,2),'HY & Segments'!$3:$3,0))+INDEX('HY & Segments'!$A:$AG,MATCH($A24,'HY & Segments'!$A:$A,0),MATCH("2H"&RIGHT(K$1,2),'HY & Segments'!$3:$3,0)) | L24: =INDEX('HY & Segments'!$A:$AG,MATCH($A24,'HY & Segments'!$A:$A,0),MATCH("1H"&RIGHT(L$1,2),'HY & Segments'!$3:$3,0))+INDEX('HY & Segments'!$A:$AG,MATCH($A24,'HY & Segments'!$A:$A,0),MATCH("2H"&RIGHT(L$1,2),'HY & Segments'!$3:$3,0)) | M24: =INDEX('HY & Segments'!$A:$AG,MATCH($A24,'HY & Segments'!$A:$A,0),MATCH("1H"&RIGHT(M$1,2),'HY & Segments'!$3:$3,0))+INDEX('HY & Segments'!$A:$AG,MATCH($A24,'HY & Segments'!$A:$A,0),MATCH("2H"&RIGHT(M$1,2),'HY & Segments'!$3:$3,0)) | N24: =INDEX('HY & Segments'!$A:$AG,MATCH($A24,'HY & Segments'!$A:$A,0),MATCH("1H"&RIGHT(N$1,2),'HY & Segments'!$3:$3,0))+INDEX('HY & Segments'!$A:$AG,MATCH($A24,'HY & Segments'!$A:$A,0),MATCH("2H"&RIGHT(N$1,2),'HY & Segments'!$3:$3,0)) | ... P24: =INDEX('HY & Segments'!$A:$AG,MATCH($A24,'HY & Segments'!$A:$A,0),MATCH("1H"&RIGHT(P$1,2),'HY & Segments'!$3:$3,0))+INDEX('HY & Segments'!$A:$AG,MATCH($A24,'HY & Segments'!$A:$A,0),MATCH("2H"&RIGHT(P$1,2),'HY & Segments'!$3:$3,0))
A25: SegEBITDA-US | B25: US Segment EBITDA | C25: A$m | D25: -4.296 | E25: -6.544 | F25: -13.223 | G25: =INDEX('HY & Segments'!$A:$AG,MATCH($A25,'HY & Segments'!$A:$A,0),MATCH("1H"&RIGHT(G$1,2),'HY & Segments'!$3:$3,0))+INDEX('HY & Segments'!$A:$AG,MATCH($A25,'HY & Segments'!$A:$A,0),MATCH("2H"&RIGHT(G$1,2),'HY & Segments'!$3:$3,0)) | H25: =INDEX('HY & Segments'!$A:$AG,MATCH($A25,'HY & Segments'!$A:$A,0),MATCH("1H"&RIGHT(H$1,2),'HY & Segments'!$3:$3,0))+INDEX('HY & Segments'!$A:$AG,MATCH($A25,'HY & Segments'!$A:$A,0),MATCH("2H"&RIGHT(H$1,2),'HY & Segments'!$3:$3,0)) | I25: =INDEX('HY & Segments'!$A:$AG,MATCH($A25,'HY & Segments'!$A:$A,0),MATCH("1H"&RIGHT(I$1,2),'HY & Segments'!$3:$3,0))+INDEX('HY & Segments'!$A:$AG,MATCH($A25,'HY & Segments'!$A:$A,0),MATCH("2H"&RIGHT(I$1,2),'HY & Segments'!$3:$3,0)) | J25: =INDEX('HY & Segments'!$A:$AG,MATCH($A25,'HY & Segments'!$A:$A,0),MATCH("1H"&RIGHT(J$1,2),'HY & Segments'!$3:$3,0))+INDEX('HY & Segments'!$A:$AG,MATCH($A25,'HY & Segments'!$A:$A,0),MATCH("2H"&RIGHT(J$1,2),'HY & Segments'!$3:$3,0)) | K25: =INDEX('HY & Segments'!$A:$AG,MATCH($A25,'HY & Segments'!$A:$A,0),MATCH("1H"&RIGHT(K$1,2),'HY & Segments'!$3:$3,0))+INDEX('HY & Segments'!$A:$AG,MATCH($A25,'HY & Segments'!$A:$A,0),MATCH("2H"&RIGHT(K$1,2),'HY & Segments'!$3:$3,0)) | L25: =INDEX('HY & Segments'!$A:$AG,MATCH($A25,'HY & Segments'!$A:$A,0),MATCH("1H"&RIGHT(L$1,2),'HY & Segments'!$3:$3,0))+INDEX('HY & Segments'!$A:$AG,MATCH($A25,'HY & Segments'!$A:$A,0),MATCH("2H"&RIGHT(L$1,2),'HY & Segments'!$3:$3,0)) | M25: =INDEX('HY & Segments'!$A:$AG,MATCH($A25,'HY & Segments'!$A:$A,0),MATCH("1H"&RIGHT(M$1,2),'HY & Segments'!$3:$3,0))+INDEX('HY & Segments'!$A:$AG,MATCH($A25,'HY & Segments'!$A:$A,0),MATCH("2H"&RIGHT(M$1,2),'HY & Segments'!$3:$3,0)) | N25: =INDEX('HY & Segments'!$A:$AG,MATCH($A25,'HY & Segments'!$A:$A,0),MATCH("1H"&RIGHT(N$1,2),'HY & Segments'!$3:$3,0))+INDEX('HY & Segments'!$A:$AG,MATCH($A25,'HY & Segments'!$A:$A,0),MATCH("2H"&RIGHT(N$1,2),'HY & Segments'!$3:$3,0)) | ... P25: =INDEX('HY & Segments'!$A:$AG,MATCH($A25,'HY & Segments'!$A:$A,0),MATCH("1H"&RIGHT(P$1,2),'HY & Segments'!$3:$3,0))+INDEX('HY & Segments'!$A:$AG,MATCH($A25,'HY & Segments'!$A:$A,0),MATCH("2H"&RIGHT(P$1,2),'HY & Segments'!$3:$3,0))
A26: SegEBITDA-Total Segment EBITDA | B26: Total Segment Underlying EBITDA | C26: A$m | D26: 29.01 | E26: 40.992 | F26: 52.806 | G26: =G24+G25 | H26: =H24+H25 | I26: =I24+I25 | J26: =J24+J25 | K26: =K24+K25 | L26: =L24+L25 | M26: =M24+M25 | N26: =N24+N25 | ... P26: =P24+P25
A27: Bridge-Cash Rent | B27: Cash Rent Addback | C27: A$m | D27: 11.213 | E27: 17.084 | F27: 18.473 | G27: =INDEX('HY & Segments'!$A:$AG,MATCH($A27,'HY & Segments'!$A:$A,0),MATCH("1H"&RIGHT(G$1,2),'HY & Segments'!$3:$3,0))+INDEX('HY & Segments'!$A:$AG,MATCH($A27,'HY & Segments'!$A:$A,0),MATCH("2H"&RIGHT(G$1,2),'HY & Segments'!$3:$3,0)) | H27: =INDEX('HY & Segments'!$A:$AG,MATCH($A27,'HY & Segments'!$A:$A,0),MATCH("1H"&RIGHT(H$1,2),'HY & Segments'!$3:$3,0))+INDEX('HY & Segments'!$A:$AG,MATCH($A27,'HY & Segments'!$A:$A,0),MATCH("2H"&RIGHT(H$1,2),'HY & Segments'!$3:$3,0)) | I27: =INDEX('HY & Segments'!$A:$AG,MATCH($A27,'HY & Segments'!$A:$A,0),MATCH("1H"&RIGHT(I$1,2),'HY & Segments'!$3:$3,0))+INDEX('HY & Segments'!$A:$AG,MATCH($A27,'HY & Segments'!$A:$A,0),MATCH("2H"&RIGHT(I$1,2),'HY & Segments'!$3:$3,0)) | J27: =INDEX('HY & Segments'!$A:$AG,MATCH($A27,'HY & Segments'!$A:$A,0),MATCH("1H"&RIGHT(J$1,2),'HY & Segments'!$3:$3,0))+INDEX('HY & Segments'!$A:$AG,MATCH($A27,'HY & Segments'!$A:$A,0),MATCH("2H"&RIGHT(J$1,2),'HY & Segments'!$3:$3,0)) | K27: =INDEX('HY & Segments'!$A:$AG,MATCH($A27,'HY & Segments'!$A:$A,0),MATCH("1H"&RIGHT(K$1,2),'HY & Segments'!$3:$3,0))+INDEX('HY & Segments'!$A:$AG,MATCH($A27,'HY & Segments'!$A:$A,0),MATCH("2H"&RIGHT(K$1,2),'HY & Segments'!$3:$3,0)) | L27: =INDEX('HY & Segments'!$A:$AG,MATCH($A27,'HY & Segments'!$A:$A,0),MATCH("1H"&RIGHT(L$1,2),'HY & Segments'!$3:$3,0))+INDEX('HY & Segments'!$A:$AG,MATCH($A27,'HY & Segments'!$A:$A,0),MATCH("2H"&RIGHT(L$1,2),'HY & Segments'!$3:$3,0)) | M27: =INDEX('HY & Segments'!$A:$AG,MATCH($A27,'HY & Segments'!$A:$A,0),MATCH("1H"&RIGHT(M$1,2),'HY & Segments'!$3:$3,0))+INDEX('HY & Segments'!$A:$AG,MATCH($A27,'HY & Segments'!$A:$A,0),MATCH("2H"&RIGHT(M$1,2),'HY & Segments'!$3:$3,0)) | N27: =INDEX('HY & Segments'!$A:$AG,MATCH($A27,'HY & Segments'!$A:$A,0),MATCH("1H"&RIGHT(N$1,2),'HY & Segments'!$3:$3,0))+INDEX('HY & Segments'!$A:$AG,MATCH($A27,'HY & Segments'!$A:$A,0),MATCH("2H"&RIGHT(N$1,2),'HY & Segments'!$3:$3,0)) | ... P27: =INDEX('HY & Segments'!$A:$AG,MATCH($A27,'HY & Segments'!$A:$A,0),MATCH("1H"&RIGHT(P$1,2),'HY & Segments'!$3:$3,0))+INDEX('HY & Segments'!$A:$AG,MATCH($A27,'HY & Segments'!$A:$A,0),MATCH("2H"&RIGHT(P$1,2),'HY & Segments'!$3:$3,0))
A28: Bridge-SBP | B28: Share-Based Payments | C28: A$m | D28: -4.24 | E28: -11.142 | F28: -9.018 | G28: =INDEX('HY & Segments'!$A:$AG,MATCH($A28,'HY & Segments'!$A:$A,0),MATCH("1H"&RIGHT(G$1,2),'HY & Segments'!$3:$3,0))+INDEX('HY & Segments'!$A:$AG,MATCH($A28,'HY & Segments'!$A:$A,0),MATCH("2H"&RIGHT(G$1,2),'HY & Segments'!$3:$3,0)) | H28: =INDEX('HY & Segments'!$A:$AG,MATCH($A28,'HY & Segments'!$A:$A,0),MATCH("1H"&RIGHT(H$1,2),'HY & Segments'!$3:$3,0))+INDEX('HY & Segments'!$A:$AG,MATCH($A28,'HY & Segments'!$A:$A,0),MATCH("2H"&RIGHT(H$1,2),'HY & Segments'!$3:$3,0)) | I28: =INDEX('HY & Segments'!$A:$AG,MATCH($A28,'HY & Segments'!$A:$A,0),MATCH("1H"&RIGHT(I$1,2),'HY & Segments'!$3:$3,0))+INDEX('HY & Segments'!$A:$AG,MATCH($A28,'HY & Segments'!$A:$A,0),MATCH("2H"&RIGHT(I$1,2),'HY & Segments'!$3:$3,0)) | J28: =INDEX('HY & Segments'!$A:$AG,MATCH($A28,'HY & Segments'!$A:$A,0),MATCH("1H"&RIGHT(J$1,2),'HY & Segments'!$3:$3,0))+INDEX('HY & Segments'!$A:$AG,MATCH($A28,'HY & Segments'!$A:$A,0),MATCH("2H"&RIGHT(J$1,2),'HY & Segments'!$3:$3,0)) | K28: =INDEX('HY & Segments'!$A:$AG,MATCH($A28,'HY & Segments'!$A:$A,0),MATCH("1H"&RIGHT(K$1,2),'HY & Segments'!$3:$3,0))+INDEX('HY & Segments'!$A:$AG,MATCH($A28,'HY & Segments'!$A:$A,0),MATCH("2H"&RIGHT(K$1,2),'HY & Segments'!$3:$3,0)) | L28: =INDEX('HY & Segments'!$A:$AG,MATCH($A28,'HY & Segments'!$A:$A,0),MATCH("1H"&RIGHT(L$1,2),'HY & Segments'!$3:$3,0))+INDEX('HY & Segments'!$A:$AG,MATCH($A28,'HY & Segments'!$A:$A,0),MATCH("2H"&RIGHT(L$1,2),'HY & Segments'!$3:$3,0)) | M28: =INDEX('HY & Segments'!$A:$AG,MATCH($A28,'HY & Segments'!$A:$A,0),MATCH("1H"&RIGHT(M$1,2),'HY & Segments'!$3:$3,0))+INDEX('HY & Segments'!$A:$AG,MATCH($A28,'HY & Segments'!$A:$A,0),MATCH("2H"&RIGHT(M$1,2),'HY & Segments'!$3:$3,0)) | N28: =INDEX('HY & Segments'!$A:$AG,MATCH($A28,'HY & Segments'!$A:$A,0),MATCH("1H"&RIGHT(N$1,2),'HY & Segments'!$3:$3,0))+INDEX('HY & Segments'!$A:$AG,MATCH($A28,'HY & Segments'!$A:$A,0),MATCH("2H"&RIGHT(N$1,2),'HY & Segments'!$3:$3,0)) | ... P28: =INDEX('HY & Segments'!$A:$AG,MATCH($A28,'HY & Segments'!$A:$A,0),MATCH("1H"&RIGHT(P$1,2),'HY & Segments'!$3:$3,0))+INDEX('HY & Segments'!$A:$AG,MATCH($A28,'HY & Segments'!$A:$A,0),MATCH("2H"&RIGHT(P$1,2),'HY & Segments'!$3:$3,0))
A29: Bridge-Other | B29: Other Income/(Costs) | C29: A$m | D29: -6.362 | E29: -19.661 | F29: 2.858 | G29: =INDEX('HY & Segments'!$A:$AG,MATCH($A29,'HY & Segments'!$A:$A,0),MATCH("1H"&RIGHT(G$1,2),'HY & Segments'!$3:$3,0))+INDEX('HY & Segments'!$A:$AG,MATCH($A29,'HY & Segments'!$A:$A,0),MATCH("2H"&RIGHT(G$1,2),'HY & Segments'!$3:$3,0)) | H29: =INDEX('HY & Segments'!$A:$AG,MATCH($A29,'HY & Segments'!$A:$A,0),MATCH("1H"&RIGHT(H$1,2),'HY & Segments'!$3:$3,0))+INDEX('HY & Segments'!$A:$AG,MATCH($A29,'HY & Segments'!$A:$A,0),MATCH("2H"&RIGHT(H$1,2),'HY & Segments'!$3:$3,0)) | I29: =INDEX('HY & Segments'!$A:$AG,MATCH($A29,'HY & Segments'!$A:$A,0),MATCH("1H"&RIGHT(I$1,2),'HY & Segments'!$3:$3,0))+INDEX('HY & Segments'!$A:$AG,MATCH($A29,'HY & Segments'!$A:$A,0),MATCH("2H"&RIGHT(I$1,2),'HY & Segments'!$3:$3,0)) | J29: =INDEX('HY & Segments'!$A:$AG,MATCH($A29,'HY & Segments'!$A:$A,0),MATCH("1H"&RIGHT(J$1,2),'HY & Segments'!$3:$3,0))+INDEX('HY & Segments'!$A:$AG,MATCH($A29,'HY & Segments'!$A:$A,0),MATCH("2H"&RIGHT(J$1,2),'HY & Segments'!$3:$3,0)) | K29: =INDEX('HY & Segments'!$A:$AG,MATCH($A29,'HY & Segments'!$A:$A,0),MATCH("1H"&RIGHT(K$1,2),'HY & Segments'!$3:$3,0))+INDEX('HY & Segments'!$A:$AG,MATCH($A29,'HY & Segments'!$A:$A,0),MATCH("2H"&RIGHT(K$1,2),'HY & Segments'!$3:$3,0)) | L29: =INDEX('HY & Segments'!$A:$AG,MATCH($A29,'HY & Segments'!$A:$A,0),MATCH("1H"&RIGHT(L$1,2),'HY & Segments'!$3:$3,0))+INDEX('HY & Segments'!$A:$AG,MATCH($A29,'HY & Segments'!$A:$A,0),MATCH("2H"&RIGHT(L$1,2),'HY & Segments'!$3:$3,0)) | M29: =INDEX('HY & Segments'!$A:$AG,MATCH($A29,'HY & Segments'!$A:$A,0),MATCH("1H"&RIGHT(M$1,2),'HY & Segments'!$3:$3,0))+INDEX('HY & Segments'!$A:$AG,MATCH($A29,'HY & Segments'!$A:$A,0),MATCH("2H"&RIGHT(M$1,2),'HY & Segments'!$3:$3,0)) | N29: =INDEX('HY & Segments'!$A:$AG,MATCH($A29,'HY & Segments'!$A:$A,0),MATCH("1H"&RIGHT(N$1,2),'HY & Segments'!$3:$3,0))+INDEX('HY & Segments'!$A:$AG,MATCH($A29,'HY & Segments'!$A:$A,0),MATCH("2H"&RIGHT(N$1,2),'HY & Segments'!$3:$3,0)) | ... P29: =INDEX('HY & Segments'!$A:$AG,MATCH($A29,'HY & Segments'!$A:$A,0),MATCH("1H"&RIGHT(P$1,2),'HY & Segments'!$3:$3,0))+INDEX('HY & Segments'!$A:$AG,MATCH($A29,'HY & Segments'!$A:$A,0),MATCH("2H"&RIGHT(P$1,2),'HY & Segments'!$3:$3,0))
A30: EBITDA-Statutory EBITDA | B30: EBITDA | C30: A$m | D30: 29.621 | E30: 27.273 | F30: 65.119 | G30: =SUM(G26:G29) | H30: =SUM(H26:H29) | I30: =SUM(I26:I29) | J30: =SUM(J26:J29) | K30: =SUM(K26:K29) | L30: =SUM(L26:L29) | M30: =SUM(M26:M29) | N30: =SUM(N26:N29) | ... P30: =SUM(P26:P29)
B31: EBITDA Margin | C31: % | D31: =IF(D21=0,"",D30/D21) | E31: =IF(E21=0,"",E30/E21) | F31: =IF(F21=0,"",F30/F21) | G31: =IF(G21=0,"",G30/G21) | H31: =IF(H21=0,"",H30/H21) | I31: =IF(I21=0,"",I30/I21) | J31: =IF(J21=0,"",J30/J21) | K31: =IF(K21=0,"",K30/K21) | ... P31: =IF(P21=0,"",P30/P21)
B33: Expenses (Memo)
A34: Exp-Food & Packaging | B34: Cost of Food & Packaging | C34: A$m | D34: -70.428 | E34: -87.58 | F34: -113.948 | G34: =INDEX('HY & Segments'!$A:$AG,MATCH($A34,'HY & Segments'!$A:$A,0),MATCH("1H"&RIGHT(G$1,2),'HY & Segments'!$3:$3,0))+INDEX('HY & Segments'!$A:$AG,MATCH($A34,'HY & Segments'!$A:$A,0),MATCH("2H"&RIGHT(G$1,2),'HY & Segments'!$3:$3,0)) | H34: =INDEX('HY & Segments'!$A:$AG,MATCH($A34,'HY & Segments'!$A:$A,0),MATCH("1H"&RIGHT(H$1,2),'HY & Segments'!$3:$3,0))+INDEX('HY & Segments'!$A:$AG,MATCH($A34,'HY & Segments'!$A:$A,0),MATCH("2H"&RIGHT(H$1,2),'HY & Segments'!$3:$3,0)) | I34: =INDEX('HY & Segments'!$A:$AG,MATCH($A34,'HY & Segments'!$A:$A,0),MATCH("1H"&RIGHT(I$1,2),'HY & Segments'!$3:$3,0))+INDEX('HY & Segments'!$A:$AG,MATCH($A34,'HY & Segments'!$A:$A,0),MATCH("2H"&RIGHT(I$1,2),'HY & Segments'!$3:$3,0)) | J34: =INDEX('HY & Segments'!$A:$AG,MATCH($A34,'HY & Segments'!$A:$A,0),MATCH("1H"&RIGHT(J$1,2),'HY & Segments'!$3:$3,0))+INDEX('HY & Segments'!$A:$AG,MATCH($A34,'HY & Segments'!$A:$A,0),MATCH("2H"&RIGHT(J$1,2),'HY & Segments'!$3:$3,0)) | K34: =INDEX('HY & Segments'!$A:$AG,MATCH($A34,'HY & Segments'!$A:$A,0),MATCH("1H"&RIGHT(K$1,2),'HY & Segments'!$3:$3,0))+INDEX('HY & Segments'!$A:$AG,MATCH($A34,'HY & Segments'!$A:$A,0),MATCH("2H"&RIGHT(K$1,2),'HY & Segments'!$3:$3,0)) | L34: =INDEX('HY & Segments'!$A:$AG,MATCH($A34,'HY & Segments'!$A:$A,0),MATCH("1H"&RIGHT(L$1,2),'HY & Segments'!$3:$3,0))+INDEX('HY & Segments'!$A:$AG,MATCH($A34,'HY & Segments'!$A:$A,0),MATCH("2H"&RIGHT(L$1,2),'HY & Segments'!$3:$3,0)) | M34: =INDEX('HY & Segments'!$A:$AG,MATCH($A34,'HY & Segments'!$A:$A,0),MATCH("1H"&RIGHT(M$1,2),'HY & Segments'!$3:$3,0))+INDEX('HY & Segments'!$A:$AG,MATCH($A34,'HY & Segments'!$A:$A,0),MATCH("2H"&RIGHT(M$1,2),'HY & Segments'!$3:$3,0)) | N34: =INDEX('HY & Segments'!$A:$AG,MATCH($A34,'HY & Segments'!$A:$A,0),MATCH("1H"&RIGHT(N$1,2),'HY & Segments'!$3:$3,0))+INDEX('HY & Segments'!$A:$AG,MATCH($A34,'HY & Segments'!$A:$A,0),MATCH("2H"&RIGHT(N$1,2),'HY & Segments'!$3:$3,0)) | ... P34: =INDEX('HY & Segments'!$A:$AG,MATCH($A34,'HY & Segments'!$A:$A,0),MATCH("1H"&RIGHT(P$1,2),'HY & Segments'!$3:$3,0))+INDEX('HY & Segments'!$A:$AG,MATCH($A34,'HY & Segments'!$A:$A,0),MATCH("2H"&RIGHT(P$1,2),'HY & Segments'!$3:$3,0))
A35: Exp-Employee Benefits | B35: Employee Benefit Expenses | C35: A$m | D35: -113.725 | E35: -153.733 | F35: -184.656 | G35: =INDEX('HY & Segments'!$A:$AG,MATCH($A35,'HY & Segments'!$A:$A,0),MATCH("1H"&RIGHT(G$1,2),'HY & Segments'!$3:$3,0))+INDEX('HY & Segments'!$A:$AG,MATCH($A35,'HY & Segments'!$A:$A,0),MATCH("2H"&RIGHT(G$1,2),'HY & Segments'!$3:$3,0)) | H35: =INDEX('HY & Segments'!$A:$AG,MATCH($A35,'HY & Segments'!$A:$A,0),MATCH("1H"&RIGHT(H$1,2),'HY & Segments'!$3:$3,0))+INDEX('HY & Segments'!$A:$AG,MATCH($A35,'HY & Segments'!$A:$A,0),MATCH("2H"&RIGHT(H$1,2),'HY & Segments'!$3:$3,0)) | I35: =INDEX('HY & Segments'!$A:$AG,MATCH($A35,'HY & Segments'!$A:$A,0),MATCH("1H"&RIGHT(I$1,2),'HY & Segments'!$3:$3,0))+INDEX('HY & Segments'!$A:$AG,MATCH($A35,'HY & Segments'!$A:$A,0),MATCH("2H"&RIGHT(I$1,2),'HY & Segments'!$3:$3,0)) | J35: =INDEX('HY & Segments'!$A:$AG,MATCH($A35,'HY & Segments'!$A:$A,0),MATCH("1H"&RIGHT(J$1,2),'HY & Segments'!$3:$3,0))+INDEX('HY & Segments'!$A:$AG,MATCH($A35,'HY & Segments'!$A:$A,0),MATCH("2H"&RIGHT(J$1,2),'HY & Segments'!$3:$3,0)) | K35: =INDEX('HY & Segments'!$A:$AG,MATCH($A35,'HY & Segments'!$A:$A,0),MATCH("1H"&RIGHT(K$1,2),'HY & Segments'!$3:$3,0))+INDEX('HY & Segments'!$A:$AG,MATCH($A35,'HY & Segments'!$A:$A,0),MATCH("2H"&RIGHT(K$1,2),'HY & Segments'!$3:$3,0)) | L35: =INDEX('HY & Segments'!$A:$AG,MATCH($A35,'HY & Segments'!$A:$A,0),MATCH("1H"&RIGHT(L$1,2),'HY & Segments'!$3:$3,0))+INDEX('HY & Segments'!$A:$AG,MATCH($A35,'HY & Segments'!$A:$A,0),MATCH("2H"&RIGHT(L$1,2),'HY & Segments'!$3:$3,0)) | M35: =INDEX('HY & Segments'!$A:$AG,MATCH($A35,'HY & Segments'!$A:$A,0),MATCH("1H"&RIGHT(M$1,2),'HY & Segments'!$3:$3,0))+INDEX('HY & Segments'!$A:$AG,MATCH($A35,'HY & Segments'!$A:$A,0),MATCH("2H"&RIGHT(M$1,2),'HY & Segments'!$3:$3,0)) | N35: =INDEX('HY & Segments'!$A:$AG,MATCH($A35,'HY & Segments'!$A:$A,0),MATCH("1H"&RIGHT(N$1,2),'HY & Segments'!$3:$3,0))+INDEX('HY & Segments'!$A:$AG,MATCH($A35,'HY & Segments'!$A:$A,0),MATCH("2H"&RIGHT(N$1,2),'HY & Segments'!$3:$3,0)) | ... P35: =INDEX('HY & Segments'!$A:$AG,MATCH($A35,'HY & Segments'!$A:$A,0),MATCH("1H"&RIGHT(P$1,2),'HY & Segments'!$3:$3,0))+INDEX('HY & Segments'!$A:$AG,MATCH($A35,'HY & Segments'!$A:$A,0),MATCH("2H"&RIGHT(P$1,2),'HY & Segments'!$3:$3,0))
A36: Exp-Admin | B36: Administrative Expenses | C36: A$m | D36: -35.282 | E36: -60.595 | F36: -53.615 | G36: =INDEX('HY & Segments'!$A:$AG,MATCH($A36,'HY & Segments'!$A:$A,0),MATCH("1H"&RIGHT(G$1,2),'HY & Segments'!$3:$3,0))+INDEX('HY & Segments'!$A:$AG,MATCH($A36,'HY & Segments'!$A:$A,0),MATCH("2H"&RIGHT(G$1,2),'HY & Segments'!$3:$3,0)) | H36: =INDEX('HY & Segments'!$A:$AG,MATCH($A36,'HY & Segments'!$A:$A,0),MATCH("1H"&RIGHT(H$1,2),'HY & Segments'!$3:$3,0))+INDEX('HY & Segments'!$A:$AG,MATCH($A36,'HY & Segments'!$A:$A,0),MATCH("2H"&RIGHT(H$1,2),'HY & Segments'!$3:$3,0)) | I36: =INDEX('HY & Segments'!$A:$AG,MATCH($A36,'HY & Segments'!$A:$A,0),MATCH("1H"&RIGHT(I$1,2),'HY & Segments'!$3:$3,0))+INDEX('HY & Segments'!$A:$AG,MATCH($A36,'HY & Segments'!$A:$A,0),MATCH("2H"&RIGHT(I$1,2),'HY & Segments'!$3:$3,0)) | J36: =INDEX('HY & Segments'!$A:$AG,MATCH($A36,'HY & Segments'!$A:$A,0),MATCH("1H"&RIGHT(J$1,2),'HY & Segments'!$3:$3,0))+INDEX('HY & Segments'!$A:$AG,MATCH($A36,'HY & Segments'!$A:$A,0),MATCH("2H"&RIGHT(J$1,2),'HY & Segments'!$3:$3,0)) | K36: =INDEX('HY & Segments'!$A:$AG,MATCH($A36,'HY & Segments'!$A:$A,0),MATCH("1H"&RIGHT(K$1,2),'HY & Segments'!$3:$3,0))+INDEX('HY & Segments'!$A:$AG,MATCH($A36,'HY & Segments'!$A:$A,0),MATCH("2H"&RIGHT(K$1,2),'HY & Segments'!$3:$3,0)) | L36: =INDEX('HY & Segments'!$A:$AG,MATCH($A36,'HY & Segments'!$A:$A,0),MATCH("1H"&RIGHT(L$1,2),'HY & Segments'!$3:$3,0))+INDEX('HY & Segments'!$A:$AG,MATCH($A36,'HY & Segments'!$A:$A,0),MATCH("2H"&RIGHT(L$1,2),'HY & Segments'!$3:$3,0)) | M36: =INDEX('HY & Segments'!$A:$AG,MATCH($A36,'HY & Segments'!$A:$A,0),MATCH("1H"&RIGHT(M$1,2),'HY & Segments'!$3:$3,0))+INDEX('HY & Segments'!$A:$AG,MATCH($A36,'HY & Segments'!$A:$A,0),MATCH("2H"&RIGHT(M$1,2),'HY & Segments'!$3:$3,0)) | N36: =INDEX('HY & Segments'!$A:$AG,MATCH($A36,'HY & Segments'!$A:$A,0),MATCH("1H"&RIGHT(N$1,2),'HY & Segments'!$3:$3,0))+INDEX('HY & Segments'!$A:$AG,MATCH($A36,'HY & Segments'!$A:$A,0),MATCH("2H"&RIGHT(N$1,2),'HY & Segments'!$3:$3,0)) | ... P36: =INDEX('HY & Segments'!$A:$AG,MATCH($A36,'HY & Segments'!$A:$A,0),MATCH("1H"&RIGHT(P$1,2),'HY & Segments'!$3:$3,0))+INDEX('HY & Segments'!$A:$AG,MATCH($A36,'HY & Segments'!$A:$A,0),MATCH("2H"&RIGHT(P$1,2),'HY & Segments'!$3:$3,0))
A37: Exp-Marketing | B37: Marketing Expenses | C37: A$m | D37: -13.718 | E37: -17.938 | F37: -21.287 | G37: =INDEX('HY & Segments'!$A:$AG,MATCH($A37,'HY & Segments'!$A:$A,0),MATCH("1H"&RIGHT(G$1,2),'HY & Segments'!$3:$3,0))+INDEX('HY & Segments'!$A:$AG,MATCH($A37,'HY & Segments'!$A:$A,0),MATCH("2H"&RIGHT(G$1,2),'HY & Segments'!$3:$3,0)) | H37: =INDEX('HY & Segments'!$A:$AG,MATCH($A37,'HY & Segments'!$A:$A,0),MATCH("1H"&RIGHT(H$1,2),'HY & Segments'!$3:$3,0))+INDEX('HY & Segments'!$A:$AG,MATCH($A37,'HY & Segments'!$A:$A,0),MATCH("2H"&RIGHT(H$1,2),'HY & Segments'!$3:$3,0)) | I37: =INDEX('HY & Segments'!$A:$AG,MATCH($A37,'HY & Segments'!$A:$A,0),MATCH("1H"&RIGHT(I$1,2),'HY & Segments'!$3:$3,0))+INDEX('HY & Segments'!$A:$AG,MATCH($A37,'HY & Segments'!$A:$A,0),MATCH("2H"&RIGHT(I$1,2),'HY & Segments'!$3:$3,0)) | J37: =INDEX('HY & Segments'!$A:$AG,MATCH($A37,'HY & Segments'!$A:$A,0),MATCH("1H"&RIGHT(J$1,2),'HY & Segments'!$3:$3,0))+INDEX('HY & Segments'!$A:$AG,MATCH($A37,'HY & Segments'!$A:$A,0),MATCH("2H"&RIGHT(J$1,2),'HY & Segments'!$3:$3,0)) | K37: =INDEX('HY & Segments'!$A:$AG,MATCH($A37,'HY & Segments'!$A:$A,0),MATCH("1H"&RIGHT(K$1,2),'HY & Segments'!$3:$3,0))+INDEX('HY & Segments'!$A:$AG,MATCH($A37,'HY & Segments'!$A:$A,0),MATCH("2H"&RIGHT(K$1,2),'HY & Segments'!$3:$3,0)) | L37: =INDEX('HY & Segments'!$A:$AG,MATCH($A37,'HY & Segments'!$A:$A,0),MATCH("1H"&RIGHT(L$1,2),'HY & Segments'!$3:$3,0))+INDEX('HY & Segments'!$A:$AG,MATCH($A37,'HY & Segments'!$A:$A,0),MATCH("2H"&RIGHT(L$1,2),'HY & Segments'!$3:$3,0)) | M37: =INDEX('HY & Segments'!$A:$AG,MATCH($A37,'HY & Segments'!$A:$A,0),MATCH("1H"&RIGHT(M$1,2),'HY & Segments'!$3:$3,0))+INDEX('HY & Segments'!$A:$AG,MATCH($A37,'HY & Segments'!$A:$A,0),MATCH("2H"&RIGHT(M$1,2),'HY & Segments'!$3:$3,0)) | N37: =INDEX('HY & Segments'!$A:$AG,MATCH($A37,'HY & Segments'!$A:$A,0),MATCH("1H"&RIGHT(N$1,2),'HY & Segments'!$3:$3,0))+INDEX('HY & Segments'!$A:$AG,MATCH($A37,'HY & Segments'!$A:$A,0),MATCH("2H"&RIGHT(N$1,2),'HY & Segments'!$3:$3,0)) | ... P37: =INDEX('HY & Segments'!$A:$AG,MATCH($A37,'HY & Segments'!$A:$A,0),MATCH("1H"&RIGHT(P$1,2),'HY & Segments'!$3:$3,0))+INDEX('HY & Segments'!$A:$AG,MATCH($A37,'HY & Segments'!$A:$A,0),MATCH("2H"&RIGHT(P$1,2),'HY & Segments'!$3:$3,0))
A38: Exp-Other Expenses | B38: Other Expenses | C38: A$m | D38: -13.995 | E38: -17.868 | F38: -29.381 | G38: =INDEX('HY & Segments'!$A:$AG,MATCH($A38,'HY & Segments'!$A:$A,0),MATCH("1H"&RIGHT(G$1,2),'HY & Segments'!$3:$3,0))+INDEX('HY & Segments'!$A:$AG,MATCH($A38,'HY & Segments'!$A:$A,0),MATCH("2H"&RIGHT(G$1,2),'HY & Segments'!$3:$3,0)) | H38: =INDEX('HY & Segments'!$A:$AG,MATCH($A38,'HY & Segments'!$A:$A,0),MATCH("1H"&RIGHT(H$1,2),'HY & Segments'!$3:$3,0))+INDEX('HY & Segments'!$A:$AG,MATCH($A38,'HY & Segments'!$A:$A,0),MATCH("2H"&RIGHT(H$1,2),'HY & Segments'!$3:$3,0)) | I38: =INDEX('HY & Segments'!$A:$AG,MATCH($A38,'HY & Segments'!$A:$A,0),MATCH("1H"&RIGHT(I$1,2),'HY & Segments'!$3:$3,0))+INDEX('HY & Segments'!$A:$AG,MATCH($A38,'HY & Segments'!$A:$A,0),MATCH("2H"&RIGHT(I$1,2),'HY & Segments'!$3:$3,0)) | J38: =INDEX('HY & Segments'!$A:$AG,MATCH($A38,'HY & Segments'!$A:$A,0),MATCH("1H"&RIGHT(J$1,2),'HY & Segments'!$3:$3,0))+INDEX('HY & Segments'!$A:$AG,MATCH($A38,'HY & Segments'!$A:$A,0),MATCH("2H"&RIGHT(J$1,2),'HY & Segments'!$3:$3,0)) | K38: =INDEX('HY & Segments'!$A:$AG,MATCH($A38,'HY & Segments'!$A:$A,0),MATCH("1H"&RIGHT(K$1,2),'HY & Segments'!$3:$3,0))+INDEX('HY & Segments'!$A:$AG,MATCH($A38,'HY & Segments'!$A:$A,0),MATCH("2H"&RIGHT(K$1,2),'HY & Segments'!$3:$3,0)) | L38: =INDEX('HY & Segments'!$A:$AG,MATCH($A38,'HY & Segments'!$A:$A,0),MATCH("1H"&RIGHT(L$1,2),'HY & Segments'!$3:$3,0))+INDEX('HY & Segments'!$A:$AG,MATCH($A38,'HY & Segments'!$A:$A,0),MATCH("2H"&RIGHT(L$1,2),'HY & Segments'!$3:$3,0)) | M38: =INDEX('HY & Segments'!$A:$AG,MATCH($A38,'HY & Segments'!$A:$A,0),MATCH("1H"&RIGHT(M$1,2),'HY & Segments'!$3:$3,0))+INDEX('HY & Segments'!$A:$AG,MATCH($A38,'HY & Segments'!$A:$A,0),MATCH("2H"&RIGHT(M$1,2),'HY & Segments'!$3:$3,0)) | N38: =INDEX('HY & Segments'!$A:$AG,MATCH($A38,'HY & Segments'!$A:$A,0),MATCH("1H"&RIGHT(N$1,2),'HY & Segments'!$3:$3,0))+INDEX('HY & Segments'!$A:$AG,MATCH($A38,'HY & Segments'!$A:$A,0),MATCH("2H"&RIGHT(N$1,2),'HY & Segments'!$3:$3,0)) | ... P38: =INDEX('HY & Segments'!$A:$AG,MATCH($A38,'HY & Segments'!$A:$A,0),MATCH("1H"&RIGHT(P$1,2),'HY & Segments'!$3:$3,0))+INDEX('HY & Segments'!$A:$AG,MATCH($A38,'HY & Segments'!$A:$A,0),MATCH("2H"&RIGHT(P$1,2),'HY & Segments'!$3:$3,0))
A39: Exp-Total Expenses | B39: Total Expenses (excl D&A) | C39: A$m | D39: =SUM(D34:D38) | E39: =SUM(E34:E38) | F39: =SUM(F34:F38) | G39: =SUM(G34:G38) | H39: =SUM(H34:H38) | I39: =SUM(I34:I38) | J39: =SUM(J34:J38) | K39: =SUM(K34:K38) | ... P39: =SUM(P34:P38)
B41: Depreciation & Amortisation
A42: DA-ROU Depreciation | B42: Depreciation - ROU Assets | C42: A$m | D42: -10.332 | E42: -11.247 | F42: -13.874 | G42: =INDEX('HY & Segments'!$A:$AG,MATCH($A42,'HY & Segments'!$A:$A,0),MATCH("1H"&RIGHT(G$1,2),'HY & Segments'!$3:$3,0))+INDEX('HY & Segments'!$A:$AG,MATCH($A42,'HY & Segments'!$A:$A,0),MATCH("2H"&RIGHT(G$1,2),'HY & Segments'!$3:$3,0)) | H42: =INDEX('HY & Segments'!$A:$AG,MATCH($A42,'HY & Segments'!$A:$A,0),MATCH("1H"&RIGHT(H$1,2),'HY & Segments'!$3:$3,0))+INDEX('HY & Segments'!$A:$AG,MATCH($A42,'HY & Segments'!$A:$A,0),MATCH("2H"&RIGHT(H$1,2),'HY & Segments'!$3:$3,0)) | I42: =INDEX('HY & Segments'!$A:$AG,MATCH($A42,'HY & Segments'!$A:$A,0),MATCH("1H"&RIGHT(I$1,2),'HY & Segments'!$3:$3,0))+INDEX('HY & Segments'!$A:$AG,MATCH($A42,'HY & Segments'!$A:$A,0),MATCH("2H"&RIGHT(I$1,2),'HY & Segments'!$3:$3,0)) | J42: =INDEX('HY & Segments'!$A:$AG,MATCH($A42,'HY & Segments'!$A:$A,0),MATCH("1H"&RIGHT(J$1,2),'HY & Segments'!$3:$3,0))+INDEX('HY & Segments'!$A:$AG,MATCH($A42,'HY & Segments'!$A:$A,0),MATCH("2H"&RIGHT(J$1,2),'HY & Segments'!$3:$3,0)) | K42: =INDEX('HY & Segments'!$A:$AG,MATCH($A42,'HY & Segments'!$A:$A,0),MATCH("1H"&RIGHT(K$1,2),'HY & Segments'!$3:$3,0))+INDEX('HY & Segments'!$A:$AG,MATCH($A42,'HY & Segments'!$A:$A,0),MATCH("2H"&RIGHT(K$1,2),'HY & Segments'!$3:$3,0)) | L42: =INDEX('HY & Segments'!$A:$AG,MATCH($A42,'HY & Segments'!$A:$A,0),MATCH("1H"&RIGHT(L$1,2),'HY & Segments'!$3:$3,0))+INDEX('HY & Segments'!$A:$AG,MATCH($A42,'HY & Segments'!$A:$A,0),MATCH("2H"&RIGHT(L$1,2),'HY & Segments'!$3:$3,0)) | M42: =INDEX('HY & Segments'!$A:$AG,MATCH($A42,'HY & Segments'!$A:$A,0),MATCH("1H"&RIGHT(M$1,2),'HY & Segments'!$3:$3,0))+INDEX('HY & Segments'!$A:$AG,MATCH($A42,'HY & Segments'!$A:$A,0),MATCH("2H"&RIGHT(M$1,2),'HY & Segments'!$3:$3,0)) | N42: =INDEX('HY & Segments'!$A:$AG,MATCH($A42,'HY & Segments'!$A:$A,0),MATCH("1H"&RIGHT(N$1,2),'HY & Segments'!$3:$3,0))+INDEX('HY & Segments'!$A:$AG,MATCH($A42,'HY & Segments'!$A:$A,0),MATCH("2H"&RIGHT(N$1,2),'HY & Segments'!$3:$3,0)) | ... P42: =INDEX('HY & Segments'!$A:$AG,MATCH($A42,'HY & Segments'!$A:$A,0),MATCH("1H"&RIGHT(P$1,2),'HY & Segments'!$3:$3,0))+INDEX('HY & Segments'!$A:$AG,MATCH($A42,'HY & Segments'!$A:$A,0),MATCH("2H"&RIGHT(P$1,2),'HY & Segments'!$3:$3,0))
A43: DA-PPE Depreciation | B43: Depreciation - PPE | C43: A$m | D43: -8.39 | E43: -12.96 | F43: -19.296 | G43: =INDEX('HY & Segments'!$A:$AG,MATCH($A43,'HY & Segments'!$A:$A,0),MATCH("1H"&RIGHT(G$1,2),'HY & Segments'!$3:$3,0))+INDEX('HY & Segments'!$A:$AG,MATCH($A43,'HY & Segments'!$A:$A,0),MATCH("2H"&RIGHT(G$1,2),'HY & Segments'!$3:$3,0)) | H43: =INDEX('HY & Segments'!$A:$AG,MATCH($A43,'HY & Segments'!$A:$A,0),MATCH("1H"&RIGHT(H$1,2),'HY & Segments'!$3:$3,0))+INDEX('HY & Segments'!$A:$AG,MATCH($A43,'HY & Segments'!$A:$A,0),MATCH("2H"&RIGHT(H$1,2),'HY & Segments'!$3:$3,0)) | I43: =INDEX('HY & Segments'!$A:$AG,MATCH($A43,'HY & Segments'!$A:$A,0),MATCH("1H"&RIGHT(I$1,2),'HY & Segments'!$3:$3,0))+INDEX('HY & Segments'!$A:$AG,MATCH($A43,'HY & Segments'!$A:$A,0),MATCH("2H"&RIGHT(I$1,2),'HY & Segments'!$3:$3,0)) | J43: =INDEX('HY & Segments'!$A:$AG,MATCH($A43,'HY & Segments'!$A:$A,0),MATCH("1H"&RIGHT(J$1,2),'HY & Segments'!$3:$3,0))+INDEX('HY & Segments'!$A:$AG,MATCH($A43,'HY & Segments'!$A:$A,0),MATCH("2H"&RIGHT(J$1,2),'HY & Segments'!$3:$3,0)) | K43: =INDEX('HY & Segments'!$A:$AG,MATCH($A43,'HY & Segments'!$A:$A,0),MATCH("1H"&RIGHT(K$1,2),'HY & Segments'!$3:$3,0))+INDEX('HY & Segments'!$A:$AG,MATCH($A43,'HY & Segments'!$A:$A,0),MATCH("2H"&RIGHT(K$1,2),'HY & Segments'!$3:$3,0)) | L43: =INDEX('HY & Segments'!$A:$AG,MATCH($A43,'HY & Segments'!$A:$A,0),MATCH("1H"&RIGHT(L$1,2),'HY & Segments'!$3:$3,0))+INDEX('HY & Segments'!$A:$AG,MATCH($A43,'HY & Segments'!$A:$A,0),MATCH("2H"&RIGHT(L$1,2),'HY & Segments'!$3:$3,0)) | M43: =INDEX('HY & Segments'!$A:$AG,MATCH($A43,'HY & Segments'!$A:$A,0),MATCH("1H"&RIGHT(M$1,2),'HY & Segments'!$3:$3,0))+INDEX('HY & Segments'!$A:$AG,MATCH($A43,'HY & Segments'!$A:$A,0),MATCH("2H"&RIGHT(M$1,2),'HY & Segments'!$3:$3,0)) | N43: =INDEX('HY & Segments'!$A:$AG,MATCH($A43,'HY & Segments'!$A:$A,0),MATCH("1H"&RIGHT(N$1,2),'HY & Segments'!$3:$3,0))+INDEX('HY & Segments'!$A:$AG,MATCH($A43,'HY & Segments'!$A:$A,0),MATCH("2H"&RIGHT(N$1,2),'HY & Segments'!$3:$3,0)) | ... P43: =INDEX('HY & Segments'!$A:$AG,MATCH($A43,'HY & Segments'!$A:$A,0),MATCH("1H"&RIGHT(P$1,2),'HY & Segments'!$3:$3,0))+INDEX('HY & Segments'!$A:$AG,MATCH($A43,'HY & Segments'!$A:$A,0),MATCH("2H"&RIGHT(P$1,2),'HY & Segments'!$3:$3,0))
A44: DA-Amortisation Reacquired | B44: Amortisation - Reacquired Rights | C44: A$m | D44: -2.747 | E44: -2.935 | F44: -3.668 | G44: =INDEX('HY & Segments'!$A:$AG,MATCH($A44,'HY & Segments'!$A:$A,0),MATCH("1H"&RIGHT(G$1,2),'HY & Segments'!$3:$3,0))+INDEX('HY & Segments'!$A:$AG,MATCH($A44,'HY & Segments'!$A:$A,0),MATCH("2H"&RIGHT(G$1,2),'HY & Segments'!$3:$3,0)) | H44: =INDEX('HY & Segments'!$A:$AG,MATCH($A44,'HY & Segments'!$A:$A,0),MATCH("1H"&RIGHT(H$1,2),'HY & Segments'!$3:$3,0))+INDEX('HY & Segments'!$A:$AG,MATCH($A44,'HY & Segments'!$A:$A,0),MATCH("2H"&RIGHT(H$1,2),'HY & Segments'!$3:$3,0)) | I44: =INDEX('HY & Segments'!$A:$AG,MATCH($A44,'HY & Segments'!$A:$A,0),MATCH("1H"&RIGHT(I$1,2),'HY & Segments'!$3:$3,0))+INDEX('HY & Segments'!$A:$AG,MATCH($A44,'HY & Segments'!$A:$A,0),MATCH("2H"&RIGHT(I$1,2),'HY & Segments'!$3:$3,0)) | J44: =INDEX('HY & Segments'!$A:$AG,MATCH($A44,'HY & Segments'!$A:$A,0),MATCH("1H"&RIGHT(J$1,2),'HY & Segments'!$3:$3,0))+INDEX('HY & Segments'!$A:$AG,MATCH($A44,'HY & Segments'!$A:$A,0),MATCH("2H"&RIGHT(J$1,2),'HY & Segments'!$3:$3,0)) | K44: =INDEX('HY & Segments'!$A:$AG,MATCH($A44,'HY & Segments'!$A:$A,0),MATCH("1H"&RIGHT(K$1,2),'HY & Segments'!$3:$3,0))+INDEX('HY & Segments'!$A:$AG,MATCH($A44,'HY & Segments'!$A:$A,0),MATCH("2H"&RIGHT(K$1,2),'HY & Segments'!$3:$3,0)) | L44: =INDEX('HY & Segments'!$A:$AG,MATCH($A44,'HY & Segments'!$A:$A,0),MATCH("1H"&RIGHT(L$1,2),'HY & Segments'!$3:$3,0))+INDEX('HY & Segments'!$A:$AG,MATCH($A44,'HY & Segments'!$A:$A,0),MATCH("2H"&RIGHT(L$1,2),'HY & Segments'!$3:$3,0)) | M44: =INDEX('HY & Segments'!$A:$AG,MATCH($A44,'HY & Segments'!$A:$A,0),MATCH("1H"&RIGHT(M$1,2),'HY & Segments'!$3:$3,0))+INDEX('HY & Segments'!$A:$AG,MATCH($A44,'HY & Segments'!$A:$A,0),MATCH("2H"&RIGHT(M$1,2),'HY & Segments'!$3:$3,0)) | N44: =INDEX('HY & Segments'!$A:$AG,MATCH($A44,'HY & Segments'!$A:$A,0),MATCH("1H"&RIGHT(N$1,2),'HY & Segments'!$3:$3,0))+INDEX('HY & Segments'!$A:$AG,MATCH($A44,'HY & Segments'!$A:$A,0),MATCH("2H"&RIGHT(N$1,2),'HY & Segments'!$3:$3,0)) | ... P44: =INDEX('HY & Segments'!$A:$AG,MATCH($A44,'HY & Segments'!$A:$A,0),MATCH("1H"&RIGHT(P$1,2),'HY & Segments'!$3:$3,0))+INDEX('HY & Segments'!$A:$AG,MATCH($A44,'HY & Segments'!$A:$A,0),MATCH("2H"&RIGHT(P$1,2),'HY & Segments'!$3:$3,0))
A45: DA-Amortisation Other | B45: Amortisation - Other | C45: A$m | D45: -4.086 | E45: -3.981 | F45: -2.843 | G45: =INDEX('HY & Segments'!$A:$AG,MATCH($A45,'HY & Segments'!$A:$A,0),MATCH("1H"&RIGHT(G$1,2),'HY & Segments'!$3:$3,0))+INDEX('HY & Segments'!$A:$AG,MATCH($A45,'HY & Segments'!$A:$A,0),MATCH("2H"&RIGHT(G$1,2),'HY & Segments'!$3:$3,0)) | H45: =INDEX('HY & Segments'!$A:$AG,MATCH($A45,'HY & Segments'!$A:$A,0),MATCH("1H"&RIGHT(H$1,2),'HY & Segments'!$3:$3,0))+INDEX('HY & Segments'!$A:$AG,MATCH($A45,'HY & Segments'!$A:$A,0),MATCH("2H"&RIGHT(H$1,2),'HY & Segments'!$3:$3,0)) | I45: =INDEX('HY & Segments'!$A:$AG,MATCH($A45,'HY & Segments'!$A:$A,0),MATCH("1H"&RIGHT(I$1,2),'HY & Segments'!$3:$3,0))+INDEX('HY & Segments'!$A:$AG,MATCH($A45,'HY & Segments'!$A:$A,0),MATCH("2H"&RIGHT(I$1,2),'HY & Segments'!$3:$3,0)) | J45: =INDEX('HY & Segments'!$A:$AG,MATCH($A45,'HY & Segments'!$A:$A,0),MATCH("1H"&RIGHT(J$1,2),'HY & Segments'!$3:$3,0))+INDEX('HY & Segments'!$A:$AG,MATCH($A45,'HY & Segments'!$A:$A,0),MATCH("2H"&RIGHT(J$1,2),'HY & Segments'!$3:$3,0)) | K45: =INDEX('HY & Segments'!$A:$AG,MATCH($A45,'HY & Segments'!$A:$A,0),MATCH("1H"&RIGHT(K$1,2),'HY & Segments'!$3:$3,0))+INDEX('HY & Segments'!$A:$AG,MATCH($A45,'HY & Segments'!$A:$A,0),MATCH("2H"&RIGHT(K$1,2),'HY & Segments'!$3:$3,0)) | L45: =INDEX('HY & Segments'!$A:$AG,MATCH($A45,'HY & Segments'!$A:$A,0),MATCH("1H"&RIGHT(L$1,2),'HY & Segments'!$3:$3,0))+INDEX('HY & Segments'!$A:$AG,MATCH($A45,'HY & Segments'!$A:$A,0),MATCH("2H"&RIGHT(L$1,2),'HY & Segments'!$3:$3,0)) | M45: =INDEX('HY & Segments'!$A:$AG,MATCH($A45,'HY & Segments'!$A:$A,0),MATCH("1H"&RIGHT(M$1,2),'HY & Segments'!$3:$3,0))+INDEX('HY & Segments'!$A:$AG,MATCH($A45,'HY & Segments'!$A:$A,0),MATCH("2H"&RIGHT(M$1,2),'HY & Segments'!$3:$3,0)) | N45: =INDEX('HY & Segments'!$A:$AG,MATCH($A45,'HY & Segments'!$A:$A,0),MATCH("1H"&RIGHT(N$1,2),'HY & Segments'!$3:$3,0))+INDEX('HY & Segments'!$A:$AG,MATCH($A45,'HY & Segments'!$A:$A,0),MATCH("2H"&RIGHT(N$1,2),'HY & Segments'!$3:$3,0)) | ... P45: =INDEX('HY & Segments'!$A:$AG,MATCH($A45,'HY & Segments'!$A:$A,0),MATCH("1H"&RIGHT(P$1,2),'HY & Segments'!$3:$3,0))+INDEX('HY & Segments'!$A:$AG,MATCH($A45,'HY & Segments'!$A:$A,0),MATCH("2H"&RIGHT(P$1,2),'HY & Segments'!$3:$3,0))
A46: DA-Total DA | B46: Total D&A | C46: A$m | D46: =SUM(D42:D45) | E46: =SUM(E42:E45) | F46: =SUM(F42:F45) | G46: =SUM(G42:G45) | H46: =SUM(H42:H45) | I46: =SUM(I42:I45) | J46: =SUM(J42:J45) | K46: =SUM(K42:K45) | ... P46: =SUM(P42:P45)
A48: EBIT-EBIT | B48: EBIT | C48: A$m | D48: =D30+D46 | E48: =E30+E46 | F48: =F30+F46 | G48: =G30+G46 | H48: =H30+H46 | I48: =I30+I46 | J48: =J30+J46 | K48: =K30+K46 | ... P48: =P30+P46
B49: EBIT Margin | C49: % | D49: =IF(D21=0,"",D48/D21) | E49: =IF(E21=0,"",E48/E21) | F49: =IF(F21=0,"",F48/F21) | G49: =IF(G21=0,"",G48/G21) | H49: =IF(H21=0,"",H48/H21) | I49: =IF(I21=0,"",I48/I21) | J49: =IF(J21=0,"",J48/J21) | K49: =IF(K21=0,"",K48/K21) | ... P49: =IF(P21=0,"",P48/P21)
B51: Finance
A52: Int-Term Deposit Income | B52: Interest Income - Term Deposits | C52: A$m | D52: 0 | E52: 1.096 | F52: 12.53 | G52: =INDEX('HY & Segments'!$A:$AG,MATCH($A52,'HY & Segments'!$A:$A,0),MATCH("1H"&RIGHT(G$1,2),'HY & Segments'!$3:$3,0))+INDEX('HY & Segments'!$A:$AG,MATCH($A52,'HY & Segments'!$A:$A,0),MATCH("2H"&RIGHT(G$1,2),'HY & Segments'!$3:$3,0)) | H52: =INDEX('HY & Segments'!$A:$AG,MATCH($A52,'HY & Segments'!$A:$A,0),MATCH("1H"&RIGHT(H$1,2),'HY & Segments'!$3:$3,0))+INDEX('HY & Segments'!$A:$AG,MATCH($A52,'HY & Segments'!$A:$A,0),MATCH("2H"&RIGHT(H$1,2),'HY & Segments'!$3:$3,0)) | I52: =INDEX('HY & Segments'!$A:$AG,MATCH($A52,'HY & Segments'!$A:$A,0),MATCH("1H"&RIGHT(I$1,2),'HY & Segments'!$3:$3,0))+INDEX('HY & Segments'!$A:$AG,MATCH($A52,'HY & Segments'!$A:$A,0),MATCH("2H"&RIGHT(I$1,2),'HY & Segments'!$3:$3,0)) | J52: =INDEX('HY & Segments'!$A:$AG,MATCH($A52,'HY & Segments'!$A:$A,0),MATCH("1H"&RIGHT(J$1,2),'HY & Segments'!$3:$3,0))+INDEX('HY & Segments'!$A:$AG,MATCH($A52,'HY & Segments'!$A:$A,0),MATCH("2H"&RIGHT(J$1,2),'HY & Segments'!$3:$3,0)) | K52: =INDEX('HY & Segments'!$A:$AG,MATCH($A52,'HY & Segments'!$A:$A,0),MATCH("1H"&RIGHT(K$1,2),'HY & Segments'!$3:$3,0))+INDEX('HY & Segments'!$A:$AG,MATCH($A52,'HY & Segments'!$A:$A,0),MATCH("2H"&RIGHT(K$1,2),'HY & Segments'!$3:$3,0)) | L52: =INDEX('HY & Segments'!$A:$AG,MATCH($A52,'HY & Segments'!$A:$A,0),MATCH("1H"&RIGHT(L$1,2),'HY & Segments'!$3:$3,0))+INDEX('HY & Segments'!$A:$AG,MATCH($A52,'HY & Segments'!$A:$A,0),MATCH("2H"&RIGHT(L$1,2),'HY & Segments'!$3:$3,0)) | M52: =INDEX('HY & Segments'!$A:$AG,MATCH($A52,'HY & Segments'!$A:$A,0),MATCH("1H"&RIGHT(M$1,2),'HY & Segments'!$3:$3,0))+INDEX('HY & Segments'!$A:$AG,MATCH($A52,'HY & Segments'!$A:$A,0),MATCH("2H"&RIGHT(M$1,2),'HY & Segments'!$3:$3,0)) | N52: =INDEX('HY & Segments'!$A:$AG,MATCH($A52,'HY & Segments'!$A:$A,0),MATCH("1H"&RIGHT(N$1,2),'HY & Segments'!$3:$3,0))+INDEX('HY & Segments'!$A:$AG,MATCH($A52,'HY & Segments'!$A:$A,0),MATCH("2H"&RIGHT(N$1,2),'HY & Segments'!$3:$3,0)) | ... P52: =INDEX('HY & Segments'!$A:$AG,MATCH($A52,'HY & Segments'!$A:$A,0),MATCH("1H"&RIGHT(P$1,2),'HY & Segments'!$3:$3,0))+INDEX('HY & Segments'!$A:$AG,MATCH($A52,'HY & Segments'!$A:$A,0),MATCH("2H"&RIGHT(P$1,2),'HY & Segments'!$3:$3,0))
A53: Int-Lease Receivable Income | B53: Interest Income - Lease Receivables | C53: A$m | D53: 3.63 | E53: 4.841 | F53: 10.042 | G53: =INDEX('HY & Segments'!$A:$AG,MATCH($A53,'HY & Segments'!$A:$A,0),MATCH("1H"&RIGHT(G$1,2),'HY & Segments'!$3:$3,0))+INDEX('HY & Segments'!$A:$AG,MATCH($A53,'HY & Segments'!$A:$A,0),MATCH("2H"&RIGHT(G$1,2),'HY & Segments'!$3:$3,0)) | H53: =INDEX('HY & Segments'!$A:$AG,MATCH($A53,'HY & Segments'!$A:$A,0),MATCH("1H"&RIGHT(H$1,2),'HY & Segments'!$3:$3,0))+INDEX('HY & Segments'!$A:$AG,MATCH($A53,'HY & Segments'!$A:$A,0),MATCH("2H"&RIGHT(H$1,2),'HY & Segments'!$3:$3,0)) | I53: =INDEX('HY & Segments'!$A:$AG,MATCH($A53,'HY & Segments'!$A:$A,0),MATCH("1H"&RIGHT(I$1,2),'HY & Segments'!$3:$3,0))+INDEX('HY & Segments'!$A:$AG,MATCH($A53,'HY & Segments'!$A:$A,0),MATCH("2H"&RIGHT(I$1,2),'HY & Segments'!$3:$3,0)) | J53: =INDEX('HY & Segments'!$A:$AG,MATCH($A53,'HY & Segments'!$A:$A,0),MATCH("1H"&RIGHT(J$1,2),'HY & Segments'!$3:$3,0))+INDEX('HY & Segments'!$A:$AG,MATCH($A53,'HY & Segments'!$A:$A,0),MATCH("2H"&RIGHT(J$1,2),'HY & Segments'!$3:$3,0)) | K53: =INDEX('HY & Segments'!$A:$AG,MATCH($A53,'HY & Segments'!$A:$A,0),MATCH("1H"&RIGHT(K$1,2),'HY & Segments'!$3:$3,0))+INDEX('HY & Segments'!$A:$AG,MATCH($A53,'HY & Segments'!$A:$A,0),MATCH("2H"&RIGHT(K$1,2),'HY & Segments'!$3:$3,0)) | L53: =INDEX('HY & Segments'!$A:$AG,MATCH($A53,'HY & Segments'!$A:$A,0),MATCH("1H"&RIGHT(L$1,2),'HY & Segments'!$3:$3,0))+INDEX('HY & Segments'!$A:$AG,MATCH($A53,'HY & Segments'!$A:$A,0),MATCH("2H"&RIGHT(L$1,2),'HY & Segments'!$3:$3,0)) | M53: =INDEX('HY & Segments'!$A:$AG,MATCH($A53,'HY & Segments'!$A:$A,0),MATCH("1H"&RIGHT(M$1,2),'HY & Segments'!$3:$3,0))+INDEX('HY & Segments'!$A:$AG,MATCH($A53,'HY & Segments'!$A:$A,0),MATCH("2H"&RIGHT(M$1,2),'HY & Segments'!$3:$3,0)) | N53: =INDEX('HY & Segments'!$A:$AG,MATCH($A53,'HY & Segments'!$A:$A,0),MATCH("1H"&RIGHT(N$1,2),'HY & Segments'!$3:$3,0))+INDEX('HY & Segments'!$A:$AG,MATCH($A53,'HY & Segments'!$A:$A,0),MATCH("2H"&RIGHT(N$1,2),'HY & Segments'!$3:$3,0)) | ... P53: =INDEX('HY & Segments'!$A:$AG,MATCH($A53,'HY & Segments'!$A:$A,0),MATCH("1H"&RIGHT(P$1,2),'HY & Segments'!$3:$3,0))+INDEX('HY & Segments'!$A:$AG,MATCH($A53,'HY & Segments'!$A:$A,0),MATCH("2H"&RIGHT(P$1,2),'HY & Segments'!$3:$3,0))
A54: Int-Other Finance Income | B54: Other Finance Income | C54: A$m | D54: 0.963 | E54: 0.075 | F54: 0.102 | G54: =INDEX('HY & Segments'!$A:$AG,MATCH($A54,'HY & Segments'!$A:$A,0),MATCH("1H"&RIGHT(G$1,2),'HY & Segments'!$3:$3,0))+INDEX('HY & Segments'!$A:$AG,MATCH($A54,'HY & Segments'!$A:$A,0),MATCH("2H"&RIGHT(G$1,2),'HY & Segments'!$3:$3,0)) | H54: =INDEX('HY & Segments'!$A:$AG,MATCH($A54,'HY & Segments'!$A:$A,0),MATCH("1H"&RIGHT(H$1,2),'HY & Segments'!$3:$3,0))+INDEX('HY & Segments'!$A:$AG,MATCH($A54,'HY & Segments'!$A:$A,0),MATCH("2H"&RIGHT(H$1,2),'HY & Segments'!$3:$3,0)) | I54: =INDEX('HY & Segments'!$A:$AG,MATCH($A54,'HY & Segments'!$A:$A,0),MATCH("1H"&RIGHT(I$1,2),'HY & Segments'!$3:$3,0))+INDEX('HY & Segments'!$A:$AG,MATCH($A54,'HY & Segments'!$A:$A,0),MATCH("2H"&RIGHT(I$1,2),'HY & Segments'!$3:$3,0)) | J54: =INDEX('HY & Segments'!$A:$AG,MATCH($A54,'HY & Segments'!$A:$A,0),MATCH("1H"&RIGHT(J$1,2),'HY & Segments'!$3:$3,0))+INDEX('HY & Segments'!$A:$AG,MATCH($A54,'HY & Segments'!$A:$A,0),MATCH("2H"&RIGHT(J$1,2),'HY & Segments'!$3:$3,0)) | K54: =INDEX('HY & Segments'!$A:$AG,MATCH($A54,'HY & Segments'!$A:$A,0),MATCH("1H"&RIGHT(K$1,2),'HY & Segments'!$3:$3,0))+INDEX('HY & Segments'!$A:$AG,MATCH($A54,'HY & Segments'!$A:$A,0),MATCH("2H"&RIGHT(K$1,2),'HY & Segments'!$3:$3,0)) | L54: =INDEX('HY & Segments'!$A:$AG,MATCH($A54,'HY & Segments'!$A:$A,0),MATCH("1H"&RIGHT(L$1,2),'HY & Segments'!$3:$3,0))+INDEX('HY & Segments'!$A:$AG,MATCH($A54,'HY & Segments'!$A:$A,0),MATCH("2H"&RIGHT(L$1,2),'HY & Segments'!$3:$3,0)) | M54: =INDEX('HY & Segments'!$A:$AG,MATCH($A54,'HY & Segments'!$A:$A,0),MATCH("1H"&RIGHT(M$1,2),'HY & Segments'!$3:$3,0))+INDEX('HY & Segments'!$A:$AG,MATCH($A54,'HY & Segments'!$A:$A,0),MATCH("2H"&RIGHT(M$1,2),'HY & Segments'!$3:$3,0)) | N54: =INDEX('HY & Segments'!$A:$AG,MATCH($A54,'HY & Segments'!$A:$A,0),MATCH("1H"&RIGHT(N$1,2),'HY & Segments'!$3:$3,0))+INDEX('HY & Segments'!$A:$AG,MATCH($A54,'HY & Segments'!$A:$A,0),MATCH("2H"&RIGHT(N$1,2),'HY & Segments'!$3:$3,0)) | ... P54: =INDEX('HY & Segments'!$A:$AG,MATCH($A54,'HY & Segments'!$A:$A,0),MATCH("1H"&RIGHT(P$1,2),'HY & Segments'!$3:$3,0))+INDEX('HY & Segments'!$A:$AG,MATCH($A54,'HY & Segments'!$A:$A,0),MATCH("2H"&RIGHT(P$1,2),'HY & Segments'!$3:$3,0))
A55: Int-Total Finance Income | B55: Total Finance Income | C55: A$m | D55: =SUM(D52:D54) | E55: =SUM(E52:E54) | F55: =SUM(F52:F54) | G55: =SUM(G52:G54) | H55: =SUM(H52:H54) | I55: =SUM(I52:I54) | J55: =SUM(J52:J54) | K55: =SUM(K52:K54) | ... P55: =SUM(P52:P54)
A56: Int-Lease Liability Costs | B56: Finance Costs - Lease Liabilities | C56: A$m | D56: -8.199 | E56: -13.394 | F56: -18.771 | G56: =INDEX('HY & Segments'!$A:$AG,MATCH($A56,'HY & Segments'!$A:$A,0),MATCH("1H"&RIGHT(G$1,2),'HY & Segments'!$3:$3,0))+INDEX('HY & Segments'!$A:$AG,MATCH($A56,'HY & Segments'!$A:$A,0),MATCH("2H"&RIGHT(G$1,2),'HY & Segments'!$3:$3,0)) | H56: =INDEX('HY & Segments'!$A:$AG,MATCH($A56,'HY & Segments'!$A:$A,0),MATCH("1H"&RIGHT(H$1,2),'HY & Segments'!$3:$3,0))+INDEX('HY & Segments'!$A:$AG,MATCH($A56,'HY & Segments'!$A:$A,0),MATCH("2H"&RIGHT(H$1,2),'HY & Segments'!$3:$3,0)) | I56: =INDEX('HY & Segments'!$A:$AG,MATCH($A56,'HY & Segments'!$A:$A,0),MATCH("1H"&RIGHT(I$1,2),'HY & Segments'!$3:$3,0))+INDEX('HY & Segments'!$A:$AG,MATCH($A56,'HY & Segments'!$A:$A,0),MATCH("2H"&RIGHT(I$1,2),'HY & Segments'!$3:$3,0)) | J56: =INDEX('HY & Segments'!$A:$AG,MATCH($A56,'HY & Segments'!$A:$A,0),MATCH("1H"&RIGHT(J$1,2),'HY & Segments'!$3:$3,0))+INDEX('HY & Segments'!$A:$AG,MATCH($A56,'HY & Segments'!$A:$A,0),MATCH("2H"&RIGHT(J$1,2),'HY & Segments'!$3:$3,0)) | K56: =INDEX('HY & Segments'!$A:$AG,MATCH($A56,'HY & Segments'!$A:$A,0),MATCH("1H"&RIGHT(K$1,2),'HY & Segments'!$3:$3,0))+INDEX('HY & Segments'!$A:$AG,MATCH($A56,'HY & Segments'!$A:$A,0),MATCH("2H"&RIGHT(K$1,2),'HY & Segments'!$3:$3,0)) | L56: =INDEX('HY & Segments'!$A:$AG,MATCH($A56,'HY & Segments'!$A:$A,0),MATCH("1H"&RIGHT(L$1,2),'HY & Segments'!$3:$3,0))+INDEX('HY & Segments'!$A:$AG,MATCH($A56,'HY & Segments'!$A:$A,0),MATCH("2H"&RIGHT(L$1,2),'HY & Segments'!$3:$3,0)) | M56: =INDEX('HY & Segments'!$A:$AG,MATCH($A56,'HY & Segments'!$A:$A,0),MATCH("1H"&RIGHT(M$1,2),'HY & Segments'!$3:$3,0))+INDEX('HY & Segments'!$A:$AG,MATCH($A56,'HY & Segments'!$A:$A,0),MATCH("2H"&RIGHT(M$1,2),'HY & Segments'!$3:$3,0)) | N56: =INDEX('HY & Segments'!$A:$AG,MATCH($A56,'HY & Segments'!$A:$A,0),MATCH("1H"&RIGHT(N$1,2),'HY & Segments'!$3:$3,0))+INDEX('HY & Segments'!$A:$AG,MATCH($A56,'HY & Segments'!$A:$A,0),MATCH("2H"&RIGHT(N$1,2),'HY & Segments'!$3:$3,0)) | ... P56: =INDEX('HY & Segments'!$A:$AG,MATCH($A56,'HY & Segments'!$A:$A,0),MATCH("1H"&RIGHT(P$1,2),'HY & Segments'!$3:$3,0))+INDEX('HY & Segments'!$A:$AG,MATCH($A56,'HY & Segments'!$A:$A,0),MATCH("2H"&RIGHT(P$1,2),'HY & Segments'!$3:$3,0))
A57: Int-Other Finance Costs | B57: Other Finance Costs | C57: A$m | D57: -0.304 | E57: -0.33 | F57: -0.131 | G57: =INDEX('HY & Segments'!$A:$AG,MATCH($A57,'HY & Segments'!$A:$A,0),MATCH("1H"&RIGHT(G$1,2),'HY & Segments'!$3:$3,0))+INDEX('HY & Segments'!$A:$AG,MATCH($A57,'HY & Segments'!$A:$A,0),MATCH("2H"&RIGHT(G$1,2),'HY & Segments'!$3:$3,0)) | H57: =INDEX('HY & Segments'!$A:$AG,MATCH($A57,'HY & Segments'!$A:$A,0),MATCH("1H"&RIGHT(H$1,2),'HY & Segments'!$3:$3,0))+INDEX('HY & Segments'!$A:$AG,MATCH($A57,'HY & Segments'!$A:$A,0),MATCH("2H"&RIGHT(H$1,2),'HY & Segments'!$3:$3,0)) | I57: =INDEX('HY & Segments'!$A:$AG,MATCH($A57,'HY & Segments'!$A:$A,0),MATCH("1H"&RIGHT(I$1,2),'HY & Segments'!$3:$3,0))+INDEX('HY & Segments'!$A:$AG,MATCH($A57,'HY & Segments'!$A:$A,0),MATCH("2H"&RIGHT(I$1,2),'HY & Segments'!$3:$3,0)) | J57: =INDEX('HY & Segments'!$A:$AG,MATCH($A57,'HY & Segments'!$A:$A,0),MATCH("1H"&RIGHT(J$1,2),'HY & Segments'!$3:$3,0))+INDEX('HY & Segments'!$A:$AG,MATCH($A57,'HY & Segments'!$A:$A,0),MATCH("2H"&RIGHT(J$1,2),'HY & Segments'!$3:$3,0)) | K57: =INDEX('HY & Segments'!$A:$AG,MATCH($A57,'HY & Segments'!$A:$A,0),MATCH("1H"&RIGHT(K$1,2),'HY & Segments'!$3:$3,0))+INDEX('HY & Segments'!$A:$AG,MATCH($A57,'HY & Segments'!$A:$A,0),MATCH("2H"&RIGHT(K$1,2),'HY & Segments'!$3:$3,0)) | L57: =INDEX('HY & Segments'!$A:$AG,MATCH($A57,'HY & Segments'!$A:$A,0),MATCH("1H"&RIGHT(L$1,2),'HY & Segments'!$3:$3,0))+INDEX('HY & Segments'!$A:$AG,MATCH($A57,'HY & Segments'!$A:$A,0),MATCH("2H"&RIGHT(L$1,2),'HY & Segments'!$3:$3,0)) | M57: =INDEX('HY & Segments'!$A:$AG,MATCH($A57,'HY & Segments'!$A:$A,0),MATCH("1H"&RIGHT(M$1,2),'HY & Segments'!$3:$3,0))+INDEX('HY & Segments'!$A:$AG,MATCH($A57,'HY & Segments'!$A:$A,0),MATCH("2H"&RIGHT(M$1,2),'HY & Segments'!$3:$3,0)) | N57: =INDEX('HY & Segments'!$A:$AG,MATCH($A57,'HY & Segments'!$A:$A,0),MATCH("1H"&RIGHT(N$1,2),'HY & Segments'!$3:$3,0))+INDEX('HY & Segments'!$A:$AG,MATCH($A57,'HY & Segments'!$A:$A,0),MATCH("2H"&RIGHT(N$1,2),'HY & Segments'!$3:$3,0)) | ... P57: =INDEX('HY & Segments'!$A:$AG,MATCH($A57,'HY & Segments'!$A:$A,0),MATCH("1H"&RIGHT(P$1,2),'HY & Segments'!$3:$3,0))+INDEX('HY & Segments'!$A:$AG,MATCH($A57,'HY & Segments'!$A:$A,0),MATCH("2H"&RIGHT(P$1,2),'HY & Segments'!$3:$3,0))
A58: Int-Total Finance Costs | B58: Total Finance Costs | C58: A$m | D58: =SUM(D56:D57) | E58: =SUM(E56:E57) | F58: =SUM(F56:F57) | G58: =G56+G57 | H58: =H56+H57 | I58: =I56+I57 | J58: =J56+J57 | K58: =K56+K57 | L58: =L56+L57 | M58: =M56+M57 | N58: =N56+N57 | ... P58: =P56+P57
A59: Int-Net Finance | B59: Net Finance Income/(Costs) | C59: A$m | D59: =D55+D58 | E59: =E55+E58 | F59: =F55+F58 | G59: =G55+G58 | H59: =H55+H58 | I59: =I55+I58 | J59: =J55+J58 | K59: =K55+K58 | ... P59: =P55+P58
A61: PBT-PBT | B61: PBT | C61: A$m | D61: =D48+D59 | E61: =E48+E59 | F61: =F48+F59 | G61: =G48+G59 | H61: =H48+H59 | I61: =I48+I59 | J61: =J48+J59 | K61: =K48+K59 | ... P61: =P48+P59
A62: Tax-Tax Expense | B62: Income Tax Expense | C62: A$m | D62: -2.423 | E62: -2.187 | F62: -14.734 | G62: =INDEX('HY & Segments'!$A:$AG,MATCH($A62,'HY & Segments'!$A:$A,0),MATCH("1H"&RIGHT(G$1,2),'HY & Segments'!$3:$3,0))+INDEX('HY & Segments'!$A:$AG,MATCH($A62,'HY & Segments'!$A:$A,0),MATCH("2H"&RIGHT(G$1,2),'HY & Segments'!$3:$3,0)) | H62: =INDEX('HY & Segments'!$A:$AG,MATCH($A62,'HY & Segments'!$A:$A,0),MATCH("1H"&RIGHT(H$1,2),'HY & Segments'!$3:$3,0))+INDEX('HY & Segments'!$A:$AG,MATCH($A62,'HY & Segments'!$A:$A,0),MATCH("2H"&RIGHT(H$1,2),'HY & Segments'!$3:$3,0)) | I62: =INDEX('HY & Segments'!$A:$AG,MATCH($A62,'HY & Segments'!$A:$A,0),MATCH("1H"&RIGHT(I$1,2),'HY & Segments'!$3:$3,0))+INDEX('HY & Segments'!$A:$AG,MATCH($A62,'HY & Segments'!$A:$A,0),MATCH("2H"&RIGHT(I$1,2),'HY & Segments'!$3:$3,0)) | J62: =INDEX('HY & Segments'!$A:$AG,MATCH($A62,'HY & Segments'!$A:$A,0),MATCH("1H"&RIGHT(J$1,2),'HY & Segments'!$3:$3,0))+INDEX('HY & Segments'!$A:$AG,MATCH($A62,'HY & Segments'!$A:$A,0),MATCH("2H"&RIGHT(J$1,2),'HY & Segments'!$3:$3,0)) | K62: =INDEX('HY & Segments'!$A:$AG,MATCH($A62,'HY & Segments'!$A:$A,0),MATCH("1H"&RIGHT(K$1,2),'HY & Segments'!$3:$3,0))+INDEX('HY & Segments'!$A:$AG,MATCH($A62,'HY & Segments'!$A:$A,0),MATCH("2H"&RIGHT(K$1,2),'HY & Segments'!$3:$3,0)) | L62: =INDEX('HY & Segments'!$A:$AG,MATCH($A62,'HY & Segments'!$A:$A,0),MATCH("1H"&RIGHT(L$1,2),'HY & Segments'!$3:$3,0))+INDEX('HY & Segments'!$A:$AG,MATCH($A62,'HY & Segments'!$A:$A,0),MATCH("2H"&RIGHT(L$1,2),'HY & Segments'!$3:$3,0)) | M62: =INDEX('HY & Segments'!$A:$AG,MATCH($A62,'HY & Segments'!$A:$A,0),MATCH("1H"&RIGHT(M$1,2),'HY & Segments'!$3:$3,0))+INDEX('HY & Segments'!$A:$AG,MATCH($A62,'HY & Segments'!$A:$A,0),MATCH("2H"&RIGHT(M$1,2),'HY & Segments'!$3:$3,0)) | N62: =INDEX('HY & Segments'!$A:$AG,MATCH($A62,'HY & Segments'!$A:$A,0),MATCH("1H"&RIGHT(N$1,2),'HY & Segments'!$3:$3,0))+INDEX('HY & Segments'!$A:$AG,MATCH($A62,'HY & Segments'!$A:$A,0),MATCH("2H"&RIGHT(N$1,2),'HY & Segments'!$3:$3,0)) | ... P62: =INDEX('HY & Segments'!$A:$AG,MATCH($A62,'HY & Segments'!$A:$A,0),MATCH("1H"&RIGHT(P$1,2),'HY & Segments'!$3:$3,0))+INDEX('HY & Segments'!$A:$AG,MATCH($A62,'HY & Segments'!$A:$A,0),MATCH("2H"&RIGHT(P$1,2),'HY & Segments'!$3:$3,0))
B63: Effective Tax Rate | C63: % | D63: =IF(D61=0,"",D62/D61) | E63: =IF(E61=0,"",E62/E61) | F63: =IF(F61=0,"",F62/F61) | G63: =IF(G61=0,"",G62/G61) | H63: =IF(H61=0,"",H62/H61) | I63: =IF(I61=0,"",I62/I61) | J63: =IF(J61=0,"",J62/J61) | K63: =IF(K61=0,"",K62/K61) | ... P63: =IF(P61=0,"",P62/P61)
A64: NPAT-NPAT | B64: NPAT | C64: A$m | D64: =D61+D62 | E64: =E61+E62 | F64: =F61+F62 | G64: =G61+G62 | H64: =H61+H62 | I64: =I61+I62 | J64: =J61+J62 | K64: =K61+K62 | ... P64: =P61+P62
B65: NPAT Margin | C65: % | D65: =IF(D21=0,"",D64/D21) | E65: =IF(E21=0,"",E64/E21) | F65: =IF(F21=0,"",F64/F21) | G65: =IF(G21=0,"",G64/G21) | H65: =IF(H21=0,"",H64/H21) | I65: =IF(I21=0,"",I64/I21) | J65: =IF(J21=0,"",J64/J21) | K65: =IF(K21=0,"",K64/K21) | ... P65: =IF(P21=0,"",P64/P21)
B68: EPS & Dividends
A69: EPS-YE Shares | B69: YE Basic Shares Outstanding | C69: m | D69: 84.916 | E69: 101.353 | F69: 101.655 | G69: =F69 | H69: =G69 | I69: =H69 | J69: =I69 | K69: =J69 | L69: =K69 | M69: =L69 | N69: =M69 | ... P69: =O69
A70: EPS-WASO Basic | B70: WASO Basic | C70: m | D70: 83.992 | E70: 85.568 | F70: 101.51 | G70: =AVERAGE(F69,G69) | H70: =AVERAGE(G69,H69) | I70: =AVERAGE(H69,I69) | J70: =AVERAGE(I69,J69) | K70: =AVERAGE(J69,K69) | L70: =AVERAGE(K69,L69) | M70: =AVERAGE(L69,M69) | N70: =AVERAGE(M69,N69) | ... P70: =AVERAGE(O69,P69)
A71: EPS-Dilution | B71: Dilution | C71: m | D71: 0 | E71: 0 | F71: 4.395 | G71: =F71 | H71: =G71 | I71: =H71 | J71: =I71 | K71: =J71 | L71: =K71 | M71: =L71 | N71: =M71 | ... P71: =O71
A72: EPS-WASO Diluted | B72: WASO Diluted | C72: m | D72: 83.992 | E72: 85.568 | F72: 105.905 | G72: =G70+G71 | H72: =H70+H71 | I72: =I70+I71 | J72: =J70+J71 | K72: =K70+K71 | L72: =L70+L71 | M72: =M70+M71 | N72: =N70+N71 | ... P72: =P70+P71
A74: EPS-Basic EPS | B74: Basic EPS | C74: cps | D74: =IF(D70=0,"",D64/D70*100) | E74: =IF(E70=0,"",E64/E70*100) | F74: =IF(F70=0,"",F64/F70*100) | G74: =IF(G70=0,"",G64/G70*100) | H74: =IF(H70=0,"",H64/H70*100) | I74: =IF(I70=0,"",I64/I70*100) | J74: =IF(J70=0,"",J64/J70*100) | K74: =IF(K70=0,"",K64/K70*100) | ... P74: =IF(P70=0,"",P64/P70*100)
A75: EPS-Diluted EPS | B75: Diluted EPS | C75: cps | D75: =IF(D72=0,"",D64/D72*100) | E75: =IF(E72=0,"",E64/E72*100) | F75: =IF(F72=0,"",F64/F72*100) | G75: =IF(G72=0,"",G64/G72*100) | H75: =IF(H72=0,"",H64/H72*100) | I75: =IF(I72=0,"",I64/I72*100) | J75: =IF(J72=0,"",J64/J72*100) | K75: =IF(K72=0,"",K64/K72*100) | ... P75: =IF(P72=0,"",P64/P72*100)
B76: EPS Growth | C76: % YoY | E76: =IF(D74=0,"",E74/D74-1) | F76: =IF(E74=0,"",F74/E74-1) | G76: =IF(F74=0,"",G74/F74-1) | H76: =IF(G74=0,"",H74/G74-1) | I76: =IF(H74=0,"",I74/H74-1) | J76: =IF(I74=0,"",J74/I74-1) | K76: =IF(J74=0,"",K74/J74-1) | L76: =IF(K74=0,"",L74/K74-1) | ... P76: =IF(O74=0,"",P74/O74-1)
A78: Div-DPS | B78: DPS | C78: cps | D78: 0 | E78: 0 | F78: 12.6 | G78: =IF(G74<=0,0,G80*G74) | H78: =IF(H74<=0,0,H80*H74) | I78: =IF(I74<=0,0,I80*I74) | J78: =IF(J74<=0,0,J80*J74) | K78: =IF(K74<=0,0,K80*K74) | L78: =IF(L74<=0,0,L80*L74) | M78: =IF(M74<=0,0,M80*M74) | N78: =IF(N74<=0,0,N80*N74) | ... P78: =IF(P74<=0,0,P80*P74)
A79: Div-Total Dividends | B79: Total Dividends | C79: A$m | D79: =D78*D70/100 | E79: =E78*E70/100 | F79: =F78*F70/100 | G79: =G78*G70/100 | H79: =H78*H70/100 | I79: =I78*I70/100 | J79: =J78*J70/100 | K79: =K78*K70/100 | ... P79: =P78*P70/100
B80: Payout Ratio | C80: % | D80: =IF(D74=0,"",D78/D74) | E80: =IF(E74=0,"",E78/E74) | F80: =IF(F74=0,"",F78/F74) | G80: =F80 | H80: =G80 | I80: =H80 | J80: =I80 | K80: =J80 | L80: =K80 | M80: =L80 | N80: =M80 | ... P80: =O80
B81: Dividend Yield | C81: % | D81: =IF(Value!$C$4=0,"",D78/Value!$C$4/100) | E81: =IF(Value!$C$4=0,"",E78/Value!$C$4/100) | F81: =IF(Value!$C$4=0,"",F78/Value!$C$4/100) | G81: =IF(Value!$C$4=0,"",G78/Value!$C$4/100) | H81: =IF(Value!$C$4=0,"",H78/Value!$C$4/100) | I81: =IF(Value!$C$4=0,"",I78/Value!$C$4/100) | J81: =IF(Value!$C$4=0,"",J78/Value!$C$4/100) | K81: =IF(Value!$C$4=0,"",K78/Value!$C$4/100) | ... P81: =IF(Value!$C$4=0,"",P78/Value!$C$4/100)
B82: Dividend Growth | C82: % YoY | E82: =IF(D78=0,"",E78/D78-1) | F82: =IF(E78=0,"",F78/E78-1) | G82: =IF(F78=0,"",G78/F78-1) | H82: =IF(G78=0,"",H78/G78-1) | I82: =IF(H78=0,"",I78/H78-1) | J82: =IF(I78=0,"",J78/I78-1) | K82: =IF(J78=0,"",K78/J78-1) | L82: =IF(K78=0,"",L78/K78-1) | ... P82: =IF(O78=0,"",P78/O78-1)
B84: Operating Metrics
A85: KPI-Corp Restaurants Aus | B85: Corporate Restaurants - Australia | C85: # | D85: 55 | E85: 64 | F85: 81
A86: KPI-Franchise Restaurants Aus | B86: Franchise Restaurants - Australia | C86: # | D86: 116 | E86: 130 | F86: 143
A87: KPI-Franchise Restaurants Asia | B87: Franchise Restaurants - Asia | C87: # | D87: 20 | E87: 22 | F87: 26
A88: KPI-US Restaurants | B88: US Restaurants | C88: # | D88: 3 | E88: 4 | F88: 6
A89: KPI-Total Restaurants | B89: Total Global Restaurants | C89: # | D89: 194 | E89: 220 | F89: 256
A90: KPI-Aus Network Sales | B90: Australia Network Sales | C90: A$m | D90: 753 | E90: 948.9 | F90: 1168.5
A91: KPI-Total Network Sales | B91: Global Network Sales | C91: A$m | D91: 759 | E91: 959.7 | F91: 1180.7
A92: KPI-Comp Sales Growth | B92: Comp Sales Growth (Australia) | C92: % | D92: 0.15 | E92: 0.081 | F92: 0.096
A93: KPI-DT AUV | B93: Drive Thru AUV (annualised) | C93: A$m | D93: 5.7 | E93: 6.2 | F93: 6.7
A94: KPI-Strip AUV | B94: Strip AUV (annualised) | C94: A$m | D94: 4.5 | E94: 4.6 | F94: 5
A95: KPI-DT Network Margin | B95: DT Network Restaurant Margin | C95: % | E95: 0.212 | F95: 0.215
A96: KPI-Strip Network Margin | B96: Strip Network Restaurant Margin | C96: % | E96: 0.194 | F96: 0.184
A97: KPI-Breakfast Mix | B97: Breakfast % of Network Sales | C97: % | D97: 0.053 | E97: 0.06 | F97: 0.067
A98: KPI-After 9pm Mix | B98: After 9pm % of Network Sales | C98: % | D98: 0.077 | E98: 0.083 | F98: 0.095
A99: KPI-Delivery Mix | B99: Delivery % of Network Sales | C99: % | E99: 0.243 | F99: 0.266
A100: KPI-Owned Digital Mix | B100: Owned Digital % of Network Sales | C100: % | D100: 0.158 | E100: 0.174 | F100: 0.195
A101: KPI-24/7 Restaurants | B101: 24/7 Trading Restaurants | C101: # | F101: 18
B103: Balance Sheet
B104: Assets
A105: BS-Cash | B105: Cash & Cash Equivalents | C105: A$m | D105: 36.504 | E105: 16.385 | F105: 39.675 | G105: =F105+G174 | H105: =G105+H174 | I105: =H105+I174 | J105: =I105+J174 | K105: =J105+K174 | L105: =K105+L174 | M105: =L105+M174 | N105: =M105+N174 | ... P105: =O105+P174
A106: BS-Trade Receivables | B106: Trade & Other Receivables | C106: A$m | D106: 25.087 | E106: 26.499 | F106: 24.84 | G106: =G12*G115 | H106: =H12*H115 | I106: =I12*I115 | J106: =J12*J115 | K106: =K12*K115 | L106: =L12*L115 | M106: =M12*M115 | N106: =N12*N115 | ... P106: =P12*P115
A107: BS-Inventories | B107: Inventories | C107: A$m | D107: 2.153 | E107: 2.825 | F107: 3.761 | G107: =G12*G116 | H107: =H12*H116 | I107: =I12*I116 | J107: =J12*J116 | K107: =K12*K116 | L107: =L12*L116 | M107: =M12*M116 | N107: =N12*N116 | ... P107: =P12*P116
A108: BS-Term Deposits | B108: Funds in Term Deposits | C108: A$m | D108: 0 | E108: 278.095 | F108: 242.068 | G108: =F108 | H108: =G108 | I108: =H108 | J108: =I108 | K108: =J108 | L108: =K108 | M108: =L108 | N108: =M108 | ... P108: =O108
A109: BS-Finance Lease Recv | B109: Finance Lease Receivables | C109: A$m | D109: 69.333 | E109: 126.403 | F109: 174.844 | G109: =F109*1.05 | H109: =G109*1.05 | I109: =H109*1.05 | J109: =I109*1.05 | K109: =J109*1.05 | L109: =K109*1.05 | M109: =L109*1.05 | N109: =M109*1.05 | ... P109: =O109*1.05
A110: BS-PPE | B110: Property, Plant & Equipment | C110: A$m | D110: 69.486 | E110: 87.63 | F110: 130.056 | G110: =F110-G158+G43 | H110: =G110-H158+H43 | I110: =H110-I158+I43 | J110: =I110-J158+J43 | K110: =J110-K158+K43 | L110: =K110-L158+L43 | M110: =L110-M158+M43 | N110: =M110-N158+N43 | ... P110: =O110-P158+P43
A111: BS-Intangibles | B111: Intangible Assets | C111: A$m | D111: 15.202 | E111: 10.586 | F111: 18.305 | G111: =F111 | H111: =G111 | I111: =H111 | J111: =I111 | K111: =J111 | L111: =K111 | M111: =L111 | N111: =M111 | ... P111: =O111
A112: BS-ROU Assets | B112: Right-of-Use Assets | C112: A$m | D112: 98.939 | E112: 93.796 | F112: 125.43 | G112: =F112+G119+G42 | H112: =G112+H119+H42 | I112: =H112+I119+I42 | J112: =I112+J119+J42 | K112: =J112+K119+K42 | L112: =K112+L119+L42 | M112: =L112+M119+M42 | N112: =M112+N119+N42 | ... P112: =O112+P119+P42
A113: BS-Other Assets | B113: Other Assets (DTA, Prepayments) | C113: A$m | D113: 7.803 | E113: 19.578 | F113: 24.219 | G113: =F113 | H113: =G113 | I113: =H113 | J113: =I113 | K113: =J113 | L113: =K113 | M113: =L113 | N113: =M113 | ... P113: =O113
B114: Total Assets | C114: A$m | D114: =SUM(D105:D113) | E114: =SUM(E105:E113) | F114: =SUM(F105:F113) | G114: =SUM(G105:G113) | H114: =SUM(H105:H113) | I114: =SUM(I105:I113) | J114: =SUM(J105:J113) | K114: =SUM(K105:K113) | ... P114: =SUM(P105:P113)
...

Sheet HY & Segments
D1: 2023 | E1: 2023 | F1: 2024 | G1: 2024 | H1: 2025 | I1: 2025 | J1: 2026 | K1: 2026 | L1: 2027 | M1: 2027 | N1: 2028 | O1: 2028 | P1: 2029 | Q1: 2029 | R1: 2030 | S1: 2030 | T1: 2031 | U1: 2031 | V1: 2032 | W1: 2032 | X1: 2033 | Y1: 2033 | Z1: 2034 | AA1: 2034 | AB1: 2035 | AC1: 2035
B2: GYG Segments (Half-Year) | D2: Actual ----------> | K2: Forecast ----->
B3: Guzman y Gomez (GYG.AX) | C3: Units | D3: 1H23 | E3: 2H23 | F3: 1H24 | G3: 2H24 | H3: 1H25 | I3: 2H25 | J3: 1H26 | K3: 2H26 | L3: 1H27 | M3: 2H27 | N3: 1H28 | O3: 2H28 | P3: 1H29 | Q3: 2H29 | R3: 1H30 | S3: 2H30 | T3: 1H31 | U3: 2H31 | V3: 1H32 | W3: 2H32 | X3: 1H33 | Y3: 2H33 | Z3: 1H34 | AA3: 2H34 | AB3: 1H35 | AC3: 2H35
D4: 44926 | E4: 45107 | F4: 45291 | G4: 45473 | H4: 45657 | I4: 45838 | J4: 46022 | K4: 46203 | L4: 46387 | M4: 46568 | N4: 46752 | O4: 46934 | P4: 47118 | Q4: 47299 | R4: 47483 | S4: 47664 | T4: 47848 | U4: 48029 | V4: 48213 | W4: 48395 | X4: 48579 | Y4: 48760 | Z4: 48944 | AA4: 49125 | AB4: 49309 | AC4: 49490
B5: P&L
B6: Revenue
A7: Rev-Corp Restaurant Sales Aus | B7: Corp Restaurant Sales - Australia | C7: A$m | F7: 136.155 | G7: 142.722 | H7: 176.051 | I7: 183.671 | J7: 215.116 | K7: =K90 | L7: =L90 | M7: =M90 | N7: =N90 | O7: =O90 | P7: =P90 | Q7: =Q90 | R7: =R90 | ... AC7: =AC90
A8: Rev-Corp Restaurant Sales US | B8: Corp Restaurant Sales - US | C8: A$m | F8: 5.618 | G8: 5.216 | H8: 3.232 | I8: 5.637 | J8: 6.46 | K8: =K102 | L8: =L102 | M8: =M102 | N8: =N102 | O8: =O102 | P8: =P102 | Q8: =Q102 | R8: =R102 | ... AC8: =AC102
A9: Rev-Total Corp Restaurant Sales | B9: Total Corp Restaurant Sales | C9: A$m | F9: 141.773 | G9: 147.938 | H9: 179.283 | I9: 189.308 | J9: 221.576 | K9: =K7+K8 | L9: =L7+L8 | M9: =M7+M8 | N9: =N7+N8 | O9: =O7+O8 | P9: =P7+P8 | Q9: =Q7+Q8 | R9: =R7+R8 | ... AC9: =AC7+AC8
A10: Rev-Franchise Royalty Revenue | B10: Franchise Royalty Revenue | C10: A$m | F10: 25.063 | G10: 26.795 | H10: 32.187 | I10: 34.574 | J10: 39.325 | K10: =I10*(1+K91) | L10: =J10*(1+L91) | M10: =K10*(1+M91) | N10: =L10*(1+N91) | O10: =M10*(1+O91) | P10: =N10*(1+P91) | Q10: =O10*(1+Q91) | R10: =P10*(1+R91) | ... AC10: =AA10*(1+AC91)
A11: Rev-Franchise Fee Revenue | B11: Franchise Fee Revenue | C11: A$m | F11: 0.451 | G11: 0.194 | H11: 0.949 | I11: -0.319 | J11: 0.3 | K11: =I11 | L11: =J11 | M11: =K11 | N11: =L11 | O11: =M11 | P11: =N11 | Q11: =O11 | R11: =P11 | ... AC11: =AA11
A12: Rev-Total Revenue | B12: Total Revenue | C12: A$m | F12: 167.287 | G12: 174.927 | H12: 212.419 | I12: 223.563 | J12: 261.201 | K12: =K9+K10+K11 | L12: =L9+L10+L11 | M12: =M9+M10+M11 | N12: =N9+N10+N11 | O12: =O9+O10+O11 | P12: =P9+P10+P11 | Q12: =Q9+Q10+Q11 | R12: =R9+R10+R11 | ... AC12: =AC9+AC10+AC11
B13: Revenue Growth (YoY) | C13: % YoY | H13: =IF(F12=0,"",H12/F12-1) | I13: =IF(G12=0,"",I12/G12-1) | J13: =IF(H12=0,"",J12/H12-1) | K13: =IF(I12=0,"",K12/I12-1) | L13: =IF(J12=0,"",L12/J12-1) | M13: =IF(K12=0,"",M12/K12-1) | N13: =IF(L12=0,"",N12/L12-1) | O13: =IF(M12=0,"",O12/M12-1) | ... AC13: =IF(AA12=0,"",AC12/AA12-1)
B15: Other Revenue
A16: OthRev-Marketing Levy | B16: Marketing Levy Revenue | C16: A$m | F16: 7.658 | G16: 8.724 | H16: 10.976 | I16: 8.712 | J16: 11.893 | K16: =I16*(1+K91) | L16: =J16*(1+L91) | M16: =K16*(1+M91) | N16: =L16*(1+N91) | O16: =M16*(1+O91) | P16: =N16*(1+P91) | Q16: =O16*(1+Q91) | R16: =P16*(1+R91) | ... AC16: =AA16*(1+AC91)
A17: OthRev-Other Franchise Revenue | B17: Other Franchise Revenue | C17: A$m | F17: 2.573 | G17: 3.591 | H17: 3.423 | I17: 5.519 | J17: 3.343 | K17: =I17*(1+K91) | L17: =J17*(1+L91) | M17: =K17*(1+M91) | N17: =L17*(1+N91) | O17: =M17*(1+O91) | P17: =N17*(1+P91) | Q17: =O17*(1+Q91) | R17: =P17*(1+R91) | ... AC17: =AA17*(1+AC91)
A18: OthRev-Other Income | B18: Other Income | C18: A$m | F18: 1.337 | G18: -1.109 | H18: 0.312 | I18: 3.082 | J18: 2.127 | K18: 0 | L18: 0 | M18: 0 | N18: 0 | O18: 0 | P18: 0 | Q18: 0 | R18: 0 | S18: 0 | T18: 0 | U18: 0 | V18: 0 | W18: 0 | X18: 0 | Y18: 0 | Z18: 0 | AA18: 0 | AB18: 0 | AC18: 0
A19: OthRev-Total Other Revenue | B19: Total Other Revenue & Income | C19: A$m | F19: 11.568 | G19: 11.206 | H19: 14.711 | I19: 17.313 | J19: 17.363 | K19: =SUM(K16:K18) | L19: =SUM(L16:L18) | M19: =SUM(M16:M18) | N19: =SUM(N16:N18) | O19: =SUM(O16:O18) | P19: =SUM(P16:P18) | Q19: =SUM(Q16:Q18) | R19: =SUM(R16:R18) | ... AC19: =SUM(AC16:AC18)
B21: Total Revenue & Other Income | C21: A$m | F21: =F12+F19 | G21: =G12+G19 | H21: =H12+H19 | I21: =I12+I19 | J21: =J12+J19 | K21: =K12+K19 | L21: =L12+L19 | M21: =M12+M19 | ... AC21: =AC12+AC19
B23: Segment EBITDA Bridge
A24: SegEBITDA-Australia | B24: Australia Segment EBITDA | C24: A$m | F24: 24.249 | G24: 23.287 | H24: 31.781 | I24: 34.248 | J24: 41.314 | K24: =K97 | L24: =L97 | M24: =M97 | N24: =N97 | O24: =O97 | P24: =P97 | Q24: =Q97 | R24: =R97 | ... AC24: =AC97
A25: SegEBITDA-US | B25: US Segment EBITDA | C25: A$m | F25: -3.095 | G25: -3.449 | H25: -5.014 | I25: -8.209 | J25: -8.308 | K25: =K106 | L25: =L106 | M25: =M106 | N25: =N106 | O25: =O106 | P25: =P106 | Q25: =Q106 | R25: =R106 | ... AC25: =AC106
A26: SegEBITDA-Total Segment EBITDA | B26: Total Segment Underlying EBITDA | C26: A$m | F26: =F24+F25 | G26: =G24+G25 | H26: =H24+H25 | I26: =I24+I25 | J26: =J24+J25 | K26: =K24+K25 | L26: =L24+L25 | M26: =M24+M25 | ... AC26: =AC24+AC25
A27: Bridge-Cash Rent | B27: Cash Rent Addback | C27: A$m | F27: 8.217 | G27: 8.867 | H27: 9.398 | I27: 9.075 | J27: 10.767 | K27: =I27 | L27: =J27 | M27: =K27 | N27: =L27 | O27: =M27 | P27: =N27 | Q27: =O27 | R27: =P27 | ... AC27: =AA27
A28: Bridge-SBP | B28: Share-Based Payments | C28: A$m | F28: -6.02 | G28: -5.122 | H28: -4.587 | I28: -4.431 | J28: -4.72 | K28: =I28 | L28: =J28 | M28: =K28 | N28: =L28 | O28: =M28 | P28: =N28 | Q28: =O28 | R28: =P28 | ... AC28: =AA28
A29: Bridge-Other | B29: Other Income/(Costs) | C29: A$m | F29: -4.447 | G29: -15.214 | H29: 0 | I29: 2.858 | J29: 1.885 | K29: 0 | L29: 0 | M29: 0 | N29: 0 | O29: 0 | P29: 0 | Q29: 0 | R29: 0 | S29: 0 | T29: 0 | U29: 0 | V29: 0 | W29: 0 | X29: 0 | Y29: 0 | Z29: 0 | AA29: 0 | AB29: 0 | AC29: 0
A30: EBITDA-Statutory EBITDA | B30: EBITDA | C30: A$m | F30: =F26+F27+F28+F29 | G30: =G26+G27+G28+G29 | H30: =H26+H27+H28+H29 | I30: =I26+I27+I28+I29 | J30: =J26+J27+J28+J29 | K30: =K26+K27+K28+K29 | L30: =L26+L27+L28+L29 | M30: =M26+M27+M28+M29 | ... AC30: =AC26+AC27+AC28+AC29
B31: EBITDA Margin | C31: % | F31: =IF(F21=0,"",F30/F21) | G31: =IF(G21=0,"",G30/G21) | H31: =IF(H21=0,"",H30/H21) | I31: =IF(I21=0,"",I30/I21) | J31: =IF(J21=0,"",J30/J21) | K31: =IF(K21=0,"",K30/K21) | L31: =IF(L21=0,"",L30/L21) | M31: =IF(M21=0,"",M30/M21) | ... AC31: =IF(AC21=0,"",AC30/AC21)
B33: Expenses (Memo)
A34: Exp-Food & Packaging | B34: Cost of Food & Packaging | C34: A$m | F34: -43.192 | G34: -44.388 | H34: -55.071 | I34: -58.877 | J34: -67.126 | K34: =IF(I39=0,0,K39*I34/I39) | L34: =IF(J39=0,0,L39*J34/J39) | M34: =IF(K39=0,0,M39*K34/K39) | N34: =IF(L39=0,0,N39*L34/L39) | O34: =IF(M39=0,0,O39*M34/M39) | P34: =IF(N39=0,0,P39*N34/N39) | Q34: =IF(O39=0,0,Q39*O34/O39) | R34: =IF(P39=0,0,R39*P34/P39) | ... AC34: =IF(AA39=0,0,AC39*AA34/AA39)
A35: Exp-Employee Benefits | B35: Employee Benefit Expenses | C35: A$m | F35: -73.326 | G35: -80.407 | H35: -89.003 | I35: -95.653 | J35: -110.669 | K35: =IF(I39=0,0,K39*I35/I39) | L35: =IF(J39=0,0,L39*J35/J39) | M35: =IF(K39=0,0,M39*K35/K39) | N35: =IF(L39=0,0,N39*L35/L39) | O35: =IF(M39=0,0,O39*M35/M39) | P35: =IF(N39=0,0,P39*N35/N39) | Q35: =IF(O39=0,0,Q39*O35/O39) | R35: =IF(P39=0,0,R39*P35/P39) | ... AC35: =IF(AA39=0,0,AC39*AA35/AA39)
A36: Exp-Admin | B36: Administrative Expenses | C36: A$m | F36: -25.346 | G36: -35.249 | H36: -25.865 | I36: -27.75 | J36: -28.718 | K36: =IF(I39=0,0,K39*I36/I39) | L36: =IF(J39=0,0,L39*J36/J39) | M36: =IF(K39=0,0,M39*K36/K39) | N36: =IF(L39=0,0,N39*L36/L39) | O36: =IF(M39=0,0,O39*M36/M39) | P36: =IF(N39=0,0,P39*N36/N39) | Q36: =IF(O39=0,0,Q39*O36/O39) | R36: =IF(P39=0,0,R39*P36/P39) | ... AC36: =IF(AA39=0,0,AC39*AA36/AA39)
A37: Exp-Marketing | B37: Marketing Expenses | C37: A$m | F37: -8.537 | G37: -9.401 | H37: -11.302 | I37: -9.985 | J37: -13.706 | K37: =IF(I39=0,0,K39*I37/I39) | L37: =IF(J39=0,0,L39*J37/J39) | M37: =IF(K39=0,0,M39*K37/K39) | N37: =IF(L39=0,0,N39*L37/L39) | O37: =IF(M39=0,0,O39*M37/M39) | P37: =IF(N39=0,0,P39*N37/N39) | Q37: =IF(O39=0,0,Q39*O37/O39) | R37: =IF(P39=0,0,R39*P37/P39) | ... AC37: =IF(AA39=0,0,AC39*AA37/AA39)
A38: Exp-Other Expenses | B38: Other Expenses | C38: A$m | F38: -9.55 | G38: -8.318 | H38: -14.311 | I38: -15.07 | J38: -17.407 | K38: =IF(I39=0,0,K39*I38/I39) | L38: =IF(J39=0,0,L39*J38/J39) | M38: =IF(K39=0,0,M39*K38/K39) | N38: =IF(L39=0,0,N39*L38/L39) | O38: =IF(M39=0,0,O39*M38/M39) | P38: =IF(N39=0,0,P39*N38/N39) | Q38: =IF(O39=0,0,Q39*O38/O39) | R38: =IF(P39=0,0,R39*P38/P39) | ... AC38: =IF(AA39=0,0,AC39*AA38/AA39)
A39: Exp-Total Expenses | B39: Total Expenses (excl D&A) | C39: A$m | F39: =SUM(F34:F38) | G39: =SUM(G34:G38) | H39: =SUM(H34:H38) | I39: =SUM(I34:I38) | J39: =SUM(J34:J38) | K39: =K21-K30 | L39: =L21-L30 | M39: =M21-M30 | N39: =N21-N30 | O39: =O21-O30 | P39: =P21-P30 | Q39: =Q21-Q30 | R39: =R21-R30 | ... AC39: =AC21-AC30
B41: Depreciation & Amortisation
A42: DA-ROU Depreciation | B42: Depreciation - ROU Assets | C42: A$m | F42: -6.324 | G42: -4.923 | H42: -7.743 | I42: -6.131 | J42: -8.071 | K42: =IF(I46=0,0,K46*I42/I46) | L42: =IF(J46=0,0,L46*J42/J46) | M42: =IF(K46=0,0,M46*K42/K46) | N42: =IF(L46=0,0,N46*L42/L46) | O42: =IF(M46=0,0,O46*M42/M46) | P42: =IF(N46=0,0,P46*N42/N46) | Q42: =IF(O46=0,0,Q46*O42/O46) | R42: =IF(P46=0,0,R46*P42/P46) | ... AC42: =IF(AA46=0,0,AC46*AA42/AA46)
A43: DA-PPE Depreciation | B43: Depreciation - PPE | C43: A$m | F43: -6.062 | G43: -6.898 | H43: -7.832 | I43: -11.464 | J43: -10.155 | K43: =IF(I46=0,0,K46*I43/I46) | L43: =IF(J46=0,0,L46*J43/J46) | M43: =IF(K46=0,0,M46*K43/K46) | N43: =IF(L46=0,0,N46*L43/L46) | O43: =IF(M46=0,0,O46*M43/M46) | P43: =IF(N46=0,0,P46*N43/N46) | Q43: =IF(O46=0,0,Q46*O43/O46) | R43: =IF(P46=0,0,R46*P43/P46) | ... AC43: =IF(AA46=0,0,AC46*AA43/AA46)
A44: DA-Amortisation Reacquired | B44: Amortisation - Reacquired Rights | C44: A$m | F44: -1.434 | G44: -1.501 | H44: -1.89 | I44: -1.778 | J44: -1.231 | K44: =IF(I46=0,0,K46*I44/I46) | L44: =IF(J46=0,0,L46*J44/J46) | M44: =IF(K46=0,0,M46*K44/K46) | N44: =IF(L46=0,0,N46*L44/L46) | O44: =IF(M46=0,0,O46*M44/M46) | P44: =IF(N46=0,0,P46*N44/N46) | Q44: =IF(O46=0,0,Q46*O44/O46) | R44: =IF(P46=0,0,R46*P44/P46) | ... AC44: =IF(AA46=0,0,AC46*AA44/AA46)
A45: DA-Amortisation Other | B45: Amortisation - Other | C45: A$m | F45: -2.08 | G45: -1.901 | H45: -1.615 | I45: -1.228 | J45: -1.724 | K45: =IF(I46=0,0,K46*I45/I46) | L45: =IF(J46=0,0,L46*J45/J46) | M45: =IF(K46=0,0,M46*K45/K46) | N45: =IF(L46=0,0,N46*L45/L46) | O45: =IF(M46=0,0,O46*M45/M46) | P45: =IF(N46=0,0,P46*N45/N46) | Q45: =IF(O46=0,0,Q46*O45/O46) | R45: =IF(P46=0,0,R46*P45/P46) | ... AC45: =IF(AA46=0,0,AC46*AA45/AA46)
A46: DA-Total DA | B46: Total D&A | C46: A$m | F46: =SUM(F42:F45) | G46: =SUM(G42:G45) | H46: =SUM(H42:H45) | I46: =SUM(I42:I45) | J46: =SUM(J42:J45) | K46: =K12*K47 | L46: =L12*L47 | M46: =M12*M47 | N46: =N12*N47 | O46: =O12*O47 | P46: =P12*P47 | Q46: =Q12*Q47 | R46: =R12*R47 | ... AC46: =AC12*AC47
B47: D&A / Revenue | C47: % | F47: =IF(F12=0,"",F46/F12) | G47: =IF(G12=0,"",G46/G12) | H47: =IF(H12=0,"",H46/H12) | I47: =IF(I12=0,"",I46/I12) | J47: =IF(J12=0,"",J46/J12) | K47: =I47 | L47: =J47 | M47: =K47 | N47: =L47 | O47: =M47 | P47: =N47 | Q47: =O47 | R47: =P47 | ... AC47: =AA47
A49: EBIT-EBIT | B49: EBIT | C49: A$m | F49: =F30+F46 | G49: =G30+G46 | H49: =H30+H46 | I49: =I30+I46 | J49: =J30+J46 | K49: =K30+K46 | L49: =L30+L46 | M49: =M30+M46 | ... AC49: =AC30+AC46
B50: EBIT Margin | C50: % | F50: =IF(F21=0,"",F49/F21) | G50: =IF(G21=0,"",G49/G21) | H50: =IF(H21=0,"",H49/H21) | I50: =IF(I21=0,"",I49/I21) | J50: =IF(J21=0,"",J49/J21) | K50: =IF(K21=0,"",K49/K21) | L50: =IF(L21=0,"",L49/L21) | M50: =IF(M21=0,"",M49/M21) | ... AC50: =IF(AC21=0,"",AC49/AC21)
B52: Finance
A53: Int-Term Deposit Income | B53: Interest Income - Term Deposits | C53: A$m | F53: 0.459 | G53: 0.637 | H53: 6.632 | I53: 5.898 | J53: 5.051 | K53: =I53 | L53: =J53 | M53: =K53 | N53: =L53 | O53: =M53 | P53: =N53 | Q53: =O53 | R53: =P53 | ... AC53: =AA53
A54: Int-Lease Receivable Income | B54: Interest Income - Lease Receivables | C54: A$m | F54: 1.824 | G54: 3.017 | H54: 4.752 | I54: 5.29 | J54: 6.378 | K54: =I54*1.05 | L54: =J54*1.05 | M54: =K54*1.05 | N54: =L54*1.05 | O54: =M54*1.05 | P54: =N54*1.05 | Q54: =O54*1.05 | R54: =P54*1.05 | ... AC54: =AA54*1.05
A55: Int-Other Finance Income | B55: Other Finance Income | C55: A$m | F55: 0.044 | G55: 0.031 | H55: 0.061 | I55: 0.041 | J55: 0.003 | K55: 0 | L55: 0 | M55: 0 | N55: 0 | O55: 0 | P55: 0 | Q55: 0 | R55: 0 | S55: 0 | T55: 0 | U55: 0 | V55: 0 | W55: 0 | X55: 0 | Y55: 0 | Z55: 0 | AA55: 0 | AB55: 0 | AC55: 0
A56: Int-Total Finance Income | B56: Total Finance Income | C56: A$m | F56: =SUM(F53:F55) | G56: =SUM(G53:G55) | H56: =SUM(H53:H55) | I56: =SUM(I53:I55) | J56: =SUM(J53:J55) | K56: =SUM(K53:K55) | L56: =SUM(L53:L55) | M56: =SUM(M53:M55) | ... AC56: =SUM(AC53:AC55)
A57: Int-Lease Liability Costs | B57: Finance Costs - Lease Liabilities | C57: A$m | F57: -6.261 | G57: -7.133 | H57: -8.686 | I57: -10.085 | J57: -11.946 | K57: =I57*1.08 | L57: =J57*1.08 | M57: =K57*1.08 | N57: =L57*1.08 | O57: =M57*1.08 | P57: =N57*1.08 | Q57: =O57*1.08 | R57: =P57*1.08 | ... AC57: =AA57*1.08
A58: Int-Other Finance Costs | B58: Other Finance Costs | C58: A$m | F58: -0.149 | G58: -0.181 | H58: -0.066 | I58: -0.065 | J58: -0.068 | K58: 0 | L58: 0 | M58: 0 | N58: 0 | O58: 0 | P58: 0 | Q58: 0 | R58: 0 | S58: 0 | T58: 0 | U58: 0 | V58: 0 | W58: 0 | X58: 0 | Y58: 0 | Z58: 0 | AA58: 0 | AB58: 0 | AC58: 0
A59: Int-Total Finance Costs | B59: Total Finance Costs | C59: A$m | F59: =SUM(F57:F58) | G59: =SUM(G57:G58) | H59: =SUM(H57:H58) | I59: =SUM(I57:I58) | J59: =SUM(J57:J58) | K59: =SUM(K57:K58) | L59: =SUM(L57:L58) | M59: =SUM(M57:M58) | ... AC59: =SUM(AC57:AC58)
A60: Int-Net Finance | B60: Net Finance Income/(Costs) | C60: A$m | F60: =F56+F59 | G60: =G56+G59 | H60: =H56+H59 | I60: =I56+I59 | J60: =J56+J59 | K60: =K56+K59 | L60: =L56+L59 | M60: =M56+M59 | ... AC60: =AC56+AC59
A62: PBT-PBT | B62: PBT | C62: A$m | F62: =F49+F60 | G62: =G49+G60 | H62: =H49+H60 | I62: =I49+I60 | J62: =J49+J60 | K62: =K49+K60 | L62: =L49+L60 | M62: =M49+M60 | ... AC62: =AC49+AC60
A63: Tax-Tax Expense | B63: Income Tax Expense | C63: A$m | F63: -2.881 | G63: 0.694 | H63: -7.89 | I63: -6.844 | J63: -8.595 | K63: =-K62*0.3 | L63: =-L62*0.3 | M63: =-M62*0.3 | N63: =-N62*0.3 | O63: =-O62*0.3 | P63: =-P62*0.3 | Q63: =-Q62*0.3 | R63: =-R62*0.3 | ... AC63: =-AC62*0.3
B64: Tax Rate | C64: % | F64: =IF(F62=0,"",F63/F62) | G64: =IF(G62=0,"",G63/G62) | H64: =IF(H62=0,"",H63/H62) | I64: =IF(I62=0,"",I63/I62) | J64: =IF(J62=0,"",J63/J62) | K64: =IF(K62=0,"",K63/K62) | L64: =IF(L62=0,"",L63/L62) | M64: =IF(M62=0,"",M63/M62) | ... AC64: =IF(AC62=0,"",AC63/AC62)
A65: NPAT-NPAT | B65: NPAT | C65: A$m | F65: =F62+F63 | G65: =G62+G63 | H65: =H62+H63 | I65: =I62+I63 | J65: =J62+J63 | K65: =K62+K63 | L65: =L62+L63 | M65: =M62+M63 | ... AC65: =AC62+AC63
B66: NPAT Growth (YoY) | C66: % YoY | H66: =IF(F65=0,"",H65/F65-1) | I66: =IF(G65=0,"",I65/G65-1) | J66: =IF(H65=0,"",J65/H65-1) | K66: =IF(I65=0,"",K65/I65-1) | L66: =IF(J65=0,"",L65/J65-1) | M66: =IF(K65=0,"",M65/K65-1) | N66: =IF(L65=0,"",N65/L65-1) | O66: =IF(M65=0,"",O65/M65-1) | ... AC66: =IF(AA65=0,"",AC65/AA65-1)
B68: Operating Metrics
A69: KPI-Corp Restaurants Aus | B69: Corporate Restaurants - Australia | C69: # | F69: 62 | G69: 64 | H69: 74 | I69: 81 | J69: 87
A70: KPI-Franchise Restaurants Aus | B70: Franchise Restaurants - Australia | C70: # | F70: 121 | G70: 130 | H70: 136 | I70: 143 | J70: 150
A71: KPI-Franchise Restaurants Asia | B71: Franchise Restaurants - Asia | C71: # | F71: 22 | G71: 22 | H71: 25 | I71: 26 | J71: 27
A72: KPI-US Restaurants | B72: US Restaurants | C72: # | F72: 4 | G72: 4 | H72: 4 | I72: 6 | J72: 8
A73: KPI-Total Restaurants | B73: Total Global Restaurants | C73: # | F73: =SUM(F69:F72) | G73: =SUM(G69:G72) | H73: =SUM(H69:H72) | I73: =SUM(I69:I72) | J73: =SUM(J69:J72)
A74: KPI-Aus Network Sales | B74: Australia Network Sales | C74: A$m | F74: 465.1 | G74: 483.8 | H74: 573 | I74: 595.5 | J74: 673.6
A75: KPI-Total Network Sales | B75: Global Network Sales | C75: A$m | F75: 470.7 | G75: 489 | H75: 577.9 | I75: 602.8 | J75: 681.8
A76: KPI-Comp Sales Growth | B76: Comp Sales Growth (Australia) | C76: % | F76: 0.101 | G76: 0.06 | H76: 0.094 | I76: 0.097 | J76: 0.044
A77: KPI-DT AUV | B77: Drive Thru AUV (annualised) | C77: A$m | H77: 6.9 | J77: 6.9
A78: KPI-Strip AUV | B78: Strip AUV (annualised) | C78: A$m | H78: 5 | J78: 5.2
A79: KPI-DT Network Margin | B79: DT Network Restaurant Margin | C79: %
A80: KPI-Strip Network Margin | B80: Strip Network Restaurant Margin | C80: %
A81: KPI-Breakfast Mix | B81: Breakfast % of Network Sales | C81: %
A82: KPI-After 9pm Mix | B82: After 9pm % of Network Sales | C82: %
A83: KPI-Delivery Mix | B83: Delivery % of Network Sales | C83: %
A84: KPI-Owned Digital Mix | B84: Owned Digital % of Network Sales | C84: %
A85: KPI-24/7 Restaurants | B85: 24/7 Trading Restaurants | C85: #
B87: Segment Forecast - Australia
B88: Corp Restaurants | C88: # | F88: 62 | G88: 64 | H88: 74 | I88: 81 | J88: 87 | K88: =J88+K89 | L88: =K88+L89 | M88: =L88+M89 | N88: =M88+N89 | O88: =N88+O89 | P88: =O88+P89 | Q88: =P88+Q89 | R88: =Q88+R89 | ... AC88: =AB88+AC89
B89: New Corp Restaurant Openings | C89: # | F89: 7 | G89: 2 | H89: 10 | I89: 7 | J89: 6 | K89: 6 | L89: =J89 | M89: =K89 | N89: =L89 | O89: =M89 | P89: =N89 | Q89: =O89 | R89: =P89 | S89: =Q89 | ... AC89: =AA89
B90: Corp Restaurant Revenue | C90: A$m | F90: 136.155 | G90: 142.722 | H90: 176.051 | I90: 183.671 | J90: 215.116 | K90: =I90*(1+K91) | L90: =J90*(1+L91) | M90: =K90*(1+M91) | N90: =L90*(1+N91) | O90: =M90*(1+O91) | P90: =N90*(1+P91) | Q90: =O90*(1+Q91) | R90: =P90*(1+R91) | ... AC90: =AA90*(1+AC91)
B91: Corp Restaurant Revenue Growth | C91: % YoY | H91: =IF(F90=0,"",H90/F90-1) | I91: =IF(G90=0,"",I90/G90-1) | J91: =IF(H90=0,"",J90/H90-1) | K91: 0.05 | L91: =J91 | M91: =K91 | N91: =L91 | O91: =M91 | P91: =N91 | Q91: =O91 | R91: =P91 | S91: =Q91 | ... AC91: =AA91
B92: Corp AUV | C92: A$m | F92: 4.654 | G92: 4.531 | H92: 5.103 | I92: 4.74 | J92: 5.122 | K92: =IF((J88+K88)/2=0,"",2*K90/((J88+K88)/2)) | L92: =IF((K88+L88)/2=0,"",2*L90/((K88+L88)/2)) | M92: =IF((L88+M88)/2=0,"",2*M90/((L88+M88)/2)) | N92: =IF((M88+N88)/2=0,"",2*N90/((M88+N88)/2)) | O92: =IF((N88+O88)/2=0,"",2*O90/((N88+O88)/2)) | P92: =IF((O88+P88)/2=0,"",2*P90/((O88+P88)/2)) | Q92: =IF((P88+Q88)/2=0,"",2*Q90/((P88+Q88)/2)) | R92: =IF((Q88+R88)/2=0,"",2*R90/((Q88+R88)/2)) | ... AC92: =IF((AB88+AC88)/2=0,"",2*AC90/((AB88+AC88)/2))
B93: Franchise Restaurants | C93: # | F93: 143 | G93: 152 | H93: 161 | I93: 169 | J93: 177 | K93: =J93+5 | L93: =K93+5 | M93: =L93+5 | N93: =M93+5 | O93: =N93+5 | P93: =O93+5 | Q93: =P93+5 | R93: =Q93+5 | ... AC93: =AB93+5
B94: Franchise Revenue | C94: A$m | F94: 29.477 | G94: 31.268 | H94: 38.197 | I94: 40.463 | J94: 42.829 | K94: =I94*(1+K91) | L94: =J94*(1+L91) | M94: =K94*(1+M91) | N94: =L94*(1+N91) | O94: =M94*(1+O91) | P94: =N94*(1+P91) | Q94: =O94*(1+Q91) | R94: =P94*(1+R91) | ... AC94: =AA94*(1+AC91)
B95: Total Australia Revenue | C95: A$m | F95: =F90+F94 | G95: =G90+G94 | H95: =H90+H94 | I95: =I90+I94 | J95: =J90+J94 | K95: =K90+K94 | L95: =L90+L94 | M95: =M90+M94 | ... AC95: =AC90+AC94
B96: EBITDA / Segment Revenue | C96: % | F96: =IF(F95=0,"",F97/F95) | G96: =IF(G95=0,"",G97/G95) | H96: =IF(H95=0,"",H97/H95) | I96: =IF(I95=0,"",I97/I95) | J96: =IF(J95=0,"",J97/J95) | K96: 0.162 | L96: =J96 | M96: =K96 | N96: =L96 | O96: =M96 | P96: =N96 | Q96: =O96 | R96: =P96 | S96: =Q96 | ... AC96: =AA96
B97: Segment EBITDA | C97: A$m | F97: 24.249 | G97: 23.287 | H97: 31.781 | I97: 34.248 | J97: 41.314 | K97: =K95*K96 | L97: =L95*L96 | M97: =M95*M96 | N97: =N95*N96 | O97: =O95*O96 | P97: =P95*P96 | Q97: =Q95*Q96 | R97: =R95*R96 | ... AC97: =AC95*AC96
B99: Segment Forecast - US
B100: US Corp Restaurants | C100: # | F100: 4 | G100: 4 | H100: 4 | I100: 6 | J100: 8 | K100: =J100+K101 | L100: =K100+L101 | M100: =L100+M101 | N100: =M100+N101 | O100: =N100+O101 | P100: =O100+P101 | Q100: =P100+Q101 | R100: =Q100+R101 | ... AC100: =AB100+AC101
B101: New US Restaurant Openings | C101: # | F101: 0 | G101: 0 | H101: 0 | I101: 2 | J101: 2 | K101: 1 | L101: =J101 | M101: =K101 | N101: =L101 | O101: =M101 | P101: =N101 | Q101: =O101 | R101: =P101 | S101: =Q101 | ... AC101: =AA101
B102: US Revenue | C102: A$m | F102: 5.618 | G102: 5.216 | H102: 3.368 | I102: 5.765 | J102: 6.601 | K102: =I102*(1+K103) | L102: =J102*(1+L103) | M102: =K102*(1+M103) | N102: =L102*(1+N103) | O102: =M102*(1+O103) | P102: =N102*(1+P103) | Q102: =O102*(1+Q103) | R102: =P102*(1+R103) | ... AC102: =AA102*(1+AC103)
B103: US Revenue Growth | C103: % YoY | H103: =IF(F102=0,"",H102/F102-1) | I103: =IF(G102=0,"",I102/G102-1) | J103: =IF(H102=0,"",J102/H102-1) | K103: 0.15 | L103: =J103 | M103: =K103 | N103: =L103 | O103: =M103 | P103: =N103 | Q103: =O103 | R103: =P103 | S103: =Q103 | ... AC103: =AA103
B104: US AUV | C104: A$m | F104: 3.21 | G104: 2.608 | H104: 1.684 | I104: 2.306 | J104: 1.886 | K104: =IF((J100+K100)/2=0,"",2*K102/((J100+K100)/2)) | L104: =IF((K100+L100)/2=0,"",2*L102/((K100+L100)/2)) | M104: =IF((L100+M100)/2=0,"",2*M102/((L100+M100)/2)) | N104: =IF((M100+N100)/2=0,"",2*N102/((M100+N100)/2)) | O104: =IF((N100+O100)/2=0,"",2*O102/((N100+O100)/2)) | P104: =IF((O100+P100)/2=0,"",2*P102/((O100+P100)/2)) | Q104: =IF((P100+Q100)/2=0,"",2*Q102/((P100+Q100)/2)) | R104: =IF((Q100+R100)/2=0,"",2*R102/((Q100+R100)/2)) | ... AC104: =IF((AB100+AC100)/2=0,"",2*AC102/((AB100+AC100)/2))
B105: US EBITDA Margin | C105: % | F105: 0 | G105: 0 | H105: 0 | I105: 0 | J105: 0 | K105: 0 | L105: 0 | M105: 0 | N105: 0 | O105: 0 | P105: 0 | Q105: 0 | R105: 0 | S105: 0 | T105: 0 | U105: 0 | V105: 0 | W105: 0 | X105: 0 | Y105: 0 | Z105: 0 | AA105: 0 | AB105: 0 | AC105: 0
B106: US Segment EBITDA | C106: A$m | F106: -3.095 | G106: -3.449 | H106: -5.014 | I106: -8.209 | J106: -8.308 | K106: =I106 | L106: =J106 | M106: =K106 | N106: =L106 | O106: =M106 | P106: =N106 | Q106: =O106 | R106: =P106 | ... AC106: =AA106
