Workbook

Sheet Value
B2: DCF Valuation
B4: Current Share Price (AUD) | C4: 28
B5: Shares Outstanding (#m) | C5: 101
B6: Market Cap (AUDm) | C6: =C4*C5
B7: Net Cash (AUDm) | C7: =-INDEX(Annual!D:P,MATCH("BS-Cash",Annual!A:A,0),MATCH(2025,Annual!$1:$1,0))
B8: Market EV (AUDm) | C8: =C6-C7
B9: Valuation Date | C9: 46022
B11: WACC Inputs
B12: Risk-free Rate | C12: 0.04
B13: Equity Risk Premium | C13: 0.06
B14: Beta | C14: 1.2
B15: Cost of Equity | C15: =C12+C13*C14
B16: Pre-tax Cost of Debt | C16: 0
B17: Tax Rate | C17: 0.3
B18: After-tax Cost of Debt | C18: =C16*(1-C17)
B19: Debt Weight (D/(D+E)) | C19: 0
B20: WACC | C20: =C15*(1-C19)+C18*C19
B21: Terminal Growth Rate | C21: 0.025
B22: Stub Period | C22: =(DATE(2026,6,30)-C9)/365.25
B24: FCF Projection | D24: FY26E | E24: FY27E | F24: FY28E | G24: FY29E | H24: FY30E | I24: FY31E | J24: FY32E | K24: FY33E | L24: FY34E | M24: FY35E
B25: EBITDA | C25: AUDm | D25: =INDEX(Annual!$D:$P,MATCH("Stat-Statutory EBITDA",Annual!$A:$A,0),MATCH(2026,Annual!$1:$1,0)) | E25: =INDEX(Annual!$D:$P,MATCH("Stat-Statutory EBITDA",Annual!$A:$A,0),MATCH(2027,Annual!$1:$1,0)) | F25: =INDEX(Annual!$D:$P,MATCH("Stat-Statutory EBITDA",Annual!$A:$A,0),MATCH(2028,Annual!$1:$1,0)) | G25: =INDEX(Annual!$D:$P,MATCH("Stat-Statutory EBITDA",Annual!$A:$A,0),MATCH(2029,Annual!$1:$1,0)) | H25: =INDEX(Annual!$D:$P,MATCH("Stat-Statutory EBITDA",Annual!$A:$A,0),MATCH(2030,Annual!$1:$1,0)) | I25: =INDEX(Annual!$D:$P,MATCH("Stat-Statutory EBITDA",Annual!$A:$A,0),MATCH(2031,Annual!$1:$1,0)) | J25: =INDEX(Annual!$D:$P,MATCH("Stat-Statutory EBITDA",Annual!$A:$A,0),MATCH(2032,Annual!$1:$1,0)) | K25: =INDEX(Annual!$D:$P,MATCH("Stat-Statutory EBITDA",Annual!$A:$A,0),MATCH(2033,Annual!$1:$1,0)) | L25: =INDEX(Annual!$D:$P,MATCH("Stat-Statutory EBITDA",Annual!$A:$A,0),MATCH(2034,Annual!$1:$1,0)) | M25: =INDEX(Annual!$D:$P,MATCH("Stat-Statutory EBITDA",Annual!$A:$A,0),MATCH(2035,Annual!$1:$1,0))
B26: less D&A | C26: AUDm | D26: =INDEX(Annual!$D:$P,MATCH("DA-Total DA",Annual!$A:$A,0),MATCH(2026,Annual!$1:$1,0)) | E26: =INDEX(Annual!$D:$P,MATCH("DA-Total DA",Annual!$A:$A,0),MATCH(2027,Annual!$1:$1,0)) | F26: =INDEX(Annual!$D:$P,MATCH("DA-Total DA",Annual!$A:$A,0),MATCH(2028,Annual!$1:$1,0)) | G26: =INDEX(Annual!$D:$P,MATCH("DA-Total DA",Annual!$A:$A,0),MATCH(2029,Annual!$1:$1,0)) | H26: =INDEX(Annual!$D:$P,MATCH("DA-Total DA",Annual!$A:$A,0),MATCH(2030,Annual!$1:$1,0)) | I26: =INDEX(Annual!$D:$P,MATCH("DA-Total DA",Annual!$A:$A,0),MATCH(2031,Annual!$1:$1,0)) | J26: =INDEX(Annual!$D:$P,MATCH("DA-Total DA",Annual!$A:$A,0),MATCH(2032,Annual!$1:$1,0)) | K26: =INDEX(Annual!$D:$P,MATCH("DA-Total DA",Annual!$A:$A,0),MATCH(2033,Annual!$1:$1,0)) | L26: =INDEX(Annual!$D:$P,MATCH("DA-Total DA",Annual!$A:$A,0),MATCH(2034,Annual!$1:$1,0)) | M26: =INDEX(Annual!$D:$P,MATCH("DA-Total DA",Annual!$A:$A,0),MATCH(2035,Annual!$1:$1,0))
B27: EBIT | C27: AUDm | D27: =D25+D26 | E27: =E25+E26 | F27: =F25+F26 | G27: =G25+G26 | H27: =H25+H26 | I27: =I25+I26 | J27: =J25+J26 | K27: =K25+K26 | ... M27: =M25+M26
B28: less Tax on EBIT | C28: AUDm | D28: =IF(D27>0,-D27*$C$17,0) | E28: =IF(E27>0,-E27*$C$17,0) | F28: =IF(F27>0,-F27*$C$17,0) | G28: =IF(G27>0,-G27*$C$17,0) | H28: =IF(H27>0,-H27*$C$17,0) | I28: =IF(I27>0,-I27*$C$17,0) | J28: =IF(J27>0,-J27*$C$17,0) | K28: =IF(K27>0,-K27*$C$17,0) | ... M28: =IF(M27>0,-M27*$C$17,0)
B29: NOPAT | C29: AUDm | D29: =D27+D28 | E29: =E27+E28 | F29: =F27+F28 | G29: =G27+G28 | H29: =H27+H28 | I29: =I27+I28 | J29: =J27+J28 | K29: =K27+K28 | ... M29: =M27+M28
B30: plus D&A | C30: AUDm | D30: =-D26 | E30: =-E26 | F30: =-F26 | G30: =-G26 | H30: =-H26 | I30: =-I26 | J30: =-J26 | K30: =-K26 | ... M30: =-M26
B31: less Capex | C31: AUDm | D31: =INDEX(Annual!$D:$P,MATCH("CF-Capex PPE",Annual!$A:$A,0),MATCH(2026,Annual!$1:$1,0)) | E31: =INDEX(Annual!$D:$P,MATCH("CF-Capex PPE",Annual!$A:$A,0),MATCH(2027,Annual!$1:$1,0)) | F31: =INDEX(Annual!$D:$P,MATCH("CF-Capex PPE",Annual!$A:$A,0),MATCH(2028,Annual!$1:$1,0)) | G31: =INDEX(Annual!$D:$P,MATCH("CF-Capex PPE",Annual!$A:$A,0),MATCH(2029,Annual!$1:$1,0)) | H31: =INDEX(Annual!$D:$P,MATCH("CF-Capex PPE",Annual!$A:$A,0),MATCH(2030,Annual!$1:$1,0)) | I31: =INDEX(Annual!$D:$P,MATCH("CF-Capex PPE",Annual!$A:$A,0),MATCH(2031,Annual!$1:$1,0)) | J31: =INDEX(Annual!$D:$P,MATCH("CF-Capex PPE",Annual!$A:$A,0),MATCH(2032,Annual!$1:$1,0)) | K31: =INDEX(Annual!$D:$P,MATCH("CF-Capex PPE",Annual!$A:$A,0),MATCH(2033,Annual!$1:$1,0)) | L31: =INDEX(Annual!$D:$P,MATCH("CF-Capex PPE",Annual!$A:$A,0),MATCH(2034,Annual!$1:$1,0)) | M31: =INDEX(Annual!$D:$P,MATCH("CF-Capex PPE",Annual!$A:$A,0),MATCH(2035,Annual!$1:$1,0))
B32: less WC Change | C32: AUDm | D32: =INDEX(Annual!$D:$P,MATCH("CF-WC Change",Annual!$A:$A,0),MATCH(2026,Annual!$1:$1,0)) | E32: =INDEX(Annual!$D:$P,MATCH("CF-WC Change",Annual!$A:$A,0),MATCH(2027,Annual!$1:$1,0)) | F32: =INDEX(Annual!$D:$P,MATCH("CF-WC Change",Annual!$A:$A,0),MATCH(2028,Annual!$1:$1,0)) | G32: =INDEX(Annual!$D:$P,MATCH("CF-WC Change",Annual!$A:$A,0),MATCH(2029,Annual!$1:$1,0)) | H32: =INDEX(Annual!$D:$P,MATCH("CF-WC Change",Annual!$A:$A,0),MATCH(2030,Annual!$1:$1,0)) | I32: =INDEX(Annual!$D:$P,MATCH("CF-WC Change",Annual!$A:$A,0),MATCH(2031,Annual!$1:$1,0)) | J32: =INDEX(Annual!$D:$P,MATCH("CF-WC Change",Annual!$A:$A,0),MATCH(2032,Annual!$1:$1,0)) | K32: =INDEX(Annual!$D:$P,MATCH("CF-WC Change",Annual!$A:$A,0),MATCH(2033,Annual!$1:$1,0)) | L32: =INDEX(Annual!$D:$P,MATCH("CF-WC Change",Annual!$A:$A,0),MATCH(2034,Annual!$1:$1,0)) | M32: =INDEX(Annual!$D:$P,MATCH("CF-WC Change",Annual!$A:$A,0),MATCH(2035,Annual!$1:$1,0))
B33: FCFF | C33: AUDm | D33: =D29+D30+D31+D32 | E33: =E29+E30+E31+E32 | F33: =F29+F30+F31+F32 | G33: =G29+G30+G31+G32 | H33: =H29+H30+H31+H32 | I33: =I29+I30+I31+I32 | J33: =J29+J30+J31+J32 | K33: =K29+K30+K31+K32 | ... M33: =M29+M30+M31+M32
B34: Normalised FCFF (capex=D&A) | C34: AUDm | M34: =M29
B35: Terminal Value | M35: =M34*(1+$C$21)/($C$20-$C$21)
B37: Discount Factor | D37: =1/(1+$C$20)^($C$22+0) | E37: =1/(1+$C$20)^($C$22+1) | F37: =1/(1+$C$20)^($C$22+2) | G37: =1/(1+$C$20)^($C$22+3) | H37: =1/(1+$C$20)^($C$22+4) | I37: =1/(1+$C$20)^($C$22+5) | J37: =1/(1+$C$20)^($C$22+6) | K37: =1/(1+$C$20)^($C$22+7) | L37: =1/(1+$C$20)^($C$22+8) | M37: =1/(1+$C$20)^($C$22+9)
B38: PV of FCFF | D38: =D33*D37 | E38: =E33*E37 | F38: =F33*F37 | G38: =G33*G37 | H38: =H33*H37 | I38: =I33*I37 | J38: =J33*J37 | K38: =K33*K37 | ... M38: =M33*M37
B39: PV of Terminal Value | M39: =M35*M37
B41: Sum of PV of FCFs | C41: =SUM(D38:M38)
B42: PV of Terminal Value | C42: =M39
B43: Enterprise Value | C43: =C41+C42
B45: less Net Debt | C45: =C7
B46: less Lease Liabilities | C46: =-INDEX(Annual!D:P,MATCH("BS-Lease Liabilities",Annual!A:A,0),MATCH(2025,Annual!$1:$1,0))
B47: Equity Value | C47: =C43+C45+C46
B48: Per Share Value (AUD) | C48: =C47/C5
B49: Upside / Downside | C49: =C48/C4-1
B52: EV/EBITDA SOTP
B54: Select FY: | C54: FY27E
B56: Segment | C56: FY27E EBITDA | D56: Multiple | E56: Implied EV
B57: Australia | C57: =INDEX(Annual!$D:$P,MATCH("EBITDA-Australia EBITDA",Annual!$A:$A,0),MATCH(2027,Annual!$1:$1,0)) | D57: 25 | E57: =C57*D57
B58: US | C58: =INDEX(Annual!$D:$P,MATCH("EBITDA-US EBITDA",Annual!$A:$A,0),MATCH(2027,Annual!$1:$1,0)) | D58: 0 | E58: =C58*D58
B59: Corporate | C59: 0 | D59: =IF(C57+C58=0,0,(D57*C57+D58*C58)/(C57+C58)) | E59: =C59*D59
B61: Group EV | E61: =SUM(E57:E59)
B62: less Net Debt | E62: =C45
B63: less Lease Liabilities | E63: =C46
B64: Equity Value | E64: =E61+E62+E63
B65: Per Share Value (AUD) | E65: =E64/C5
B66: Upside / Downside | E66: =E65/C4-1
B68: Implied Group EV/EBITDA | E68: =IF(C57+C58=0,"",E61/(C57+C58))

Sheet Annual
D1: 2023 | E1: 2024 | F1: 2025 | G1: 2026 | H1: 2027 | I1: 2028 | J1: 2029 | K1: 2030 | L1: 2031 | M1: 2032 | N1: 2033 | O1: 2034 | P1: 2035
B2: GYG Model Summary | D2: Actual ----------> | G2: Forecast ----->
B3: Guzman y Gomez (GYG.AX) | C3: Units | D3: FY23A | E3: FY24A | F3: FY25A | G3: FY26E | H3: FY27E | I3: FY28E | J3: FY29E | K3: FY30E | L3: FY31E | M3: FY32E | N3: FY33E | O3: FY34E | P3: FY35E
D4: 45107 | E4: 45473 | F4: 45838 | G4: 46203 | H4: 46568 | I4: 46934 | J4: 47299 | K4: 47664 | L4: 48029 | M4: 48395 | N4: 48760 | O4: 49125 | P4: 49490
B5: P&L
B6: Revenue
A7: Rev-Total Revenue | B7: Total Revenue | C7: AUDm | D7: 259.044 | E7: 342.214 | F7: 435.982 | G7: =INDEX('HY & Segments'!$A:$AG,MATCH($A7,'HY & Segments'!$A:$A,0),MATCH("1H"&RIGHT(G$1,2),'HY & Segments'!$3:$3,0))+INDEX('HY & Segments'!$A:$AG,MATCH($A7,'HY & Segments'!$A:$A,0),MATCH("2H"&RIGHT(G$1,2),'HY & Segments'!$3:$3,0)) | H7: =INDEX('HY & Segments'!$A:$AG,MATCH($A7,'HY & Segments'!$A:$A,0),MATCH("1H"&RIGHT(H$1,2),'HY & Segments'!$3:$3,0))+INDEX('HY & Segments'!$A:$AG,MATCH($A7,'HY & Segments'!$A:$A,0),MATCH("2H"&RIGHT(H$1,2),'HY & Segments'!$3:$3,0)) | I7: =INDEX('HY & Segments'!$A:$AG,MATCH($A7,'HY & Segments'!$A:$A,0),MATCH("1H"&RIGHT(I$1,2),'HY & Segments'!$3:$3,0))+INDEX('HY & Segments'!$A:$AG,MATCH($A7,'HY & Segments'!$A:$A,0),MATCH("2H"&RIGHT(I$1,2),'HY & Segments'!$3:$3,0)) | J7: =INDEX('HY & Segments'!$A:$AG,MATCH($A7,'HY & Segments'!$A:$A,0),MATCH("1H"&RIGHT(J$1,2),'HY & Segments'!$3:$3,0))+INDEX('HY & Segments'!$A:$AG,MATCH($A7,'HY & Segments'!$A:$A,0),MATCH("2H"&RIGHT(J$1,2),'HY & Segments'!$3:$3,0)) | K7: =INDEX('HY & Segments'!$A:$AG,MATCH($A7,'HY & Segments'!$A:$A,0),MATCH("1H"&RIGHT(K$1,2),'HY & Segments'!$3:$3,0))+INDEX('HY & Segments'!$A:$AG,MATCH($A7,'HY & Segments'!$A:$A,0),MATCH("2H"&RIGHT(K$1,2),'HY & Segments'!$3:$3,0)) | L7: =INDEX('HY & Segments'!$A:$AG,MATCH($A7,'HY & Segments'!$A:$A,0),MATCH("1H"&RIGHT(L$1,2),'HY & Segments'!$3:$3,0))+INDEX('HY & Segments'!$A:$AG,MATCH($A7,'HY & Segments'!$A:$A,0),MATCH("2H"&RIGHT(L$1,2),'HY & Segments'!$3:$3,0)) | M7: =INDEX('HY & Segments'!$A:$AG,MATCH($A7,'HY & Segments'!$A:$A,0),MATCH("1H"&RIGHT(M$1,2),'HY & Segments'!$3:$3,0))+INDEX('HY & Segments'!$A:$AG,MATCH($A7,'HY & Segments'!$A:$A,0),MATCH("2H"&RIGHT(M$1,2),'HY & Segments'!$3:$3,0)) | N7: =INDEX('HY & Segments'!$A:$AG,MATCH($A7,'HY & Segments'!$A:$A,0),MATCH("1H"&RIGHT(N$1,2),'HY & Segments'!$3:$3,0))+INDEX('HY & Segments'!$A:$AG,MATCH($A7,'HY & Segments'!$A:$A,0),MATCH("2H"&RIGHT(N$1,2),'HY & Segments'!$3:$3,0)) | ... P7: =INDEX('HY & Segments'!$A:$AG,MATCH($A7,'HY & Segments'!$A:$A,0),MATCH("1H"&RIGHT(P$1,2),'HY & Segments'!$3:$3,0))+INDEX('HY & Segments'!$A:$AG,MATCH($A7,'HY & Segments'!$A:$A,0),MATCH("2H"&RIGHT(P$1,2),'HY & Segments'!$3:$3,0))
A8: Rev-Other Revenue | B8: Other Revenue & Income | C8: AUDm | D8: 17.725 | E8: 22.774 | F8: 32.024 | G8: =F8*1.15 | H8: =G8*1.15 | I8: =H8*1.15 | J8: =I8*1.15 | K8: =J8*1.15 | L8: =K8*1.15 | M8: =L8*1.15 | N8: =M8*1.15 | ... P8: =O8*1.15
A9: Rev-Total Rev Incl Other | B9: Total Revenue (incl Other) | C9: AUDm | D9: =D7+D8 | E9: =E7+E8 | F9: =F7+F8 | G9: =G7+G8 | H9: =H7+H8 | I9: =I7+I8 | J9: =J7+J8 | K9: =K7+K8 | ... P9: =P7+P8
B10: Revenue Growth | C10: % YoY | E10: =E7/D7-1 | F10: =F7/E7-1 | G10: =IF(F7=0,"",G7/F7-1) | H10: =IF(G7=0,"",H7/G7-1) | I10: =IF(H7=0,"",I7/H7-1) | J10: =IF(I7=0,"",J7/I7-1) | K10: =IF(J7=0,"",K7/J7-1) | L10: =IF(K7=0,"",L7/K7-1) | M10: =IF(L7=0,"",M7/L7-1) | N10: =IF(M7=0,"",N7/M7-1) | ... P10: =IF(O7=0,"",P7/O7-1)
B12: COGS
A13: COGS-Food & Packaging | B13: Cost of Food & Packaging | C13: AUDm | D13: -70.428 | E13: -87.58 | F13: -113.948 | G13: =G7*-0.261 | H13: =H7*-0.261 | I13: =I7*-0.261 | J13: =J7*-0.261 | K13: =K7*-0.261 | L13: =L7*-0.261 | M13: =M7*-0.261 | N13: =N7*-0.261 | ... P13: =P7*-0.261
A14: COGS-Employee Benefits | B14: Employee Benefits | C14: AUDm | D14: -113.725 | E14: -153.733 | F14: -184.656 | G14: =G7*-0.424 | H14: =H7*-0.424 | I14: =I7*-0.424 | J14: =J7*-0.424 | K14: =K7*-0.424 | L14: =L7*-0.424 | M14: =M7*-0.424 | N14: =N7*-0.424 | ... P14: =P7*-0.424
A15: COGS-Other Costs | B15: Admin, Marketing & Other Expenses | C15: AUDm | D15: -62.995 | E15: -96.401 | F15: -104.283 | G15: =G7*-0.235 | H15: =H7*-0.230 | I15: =I7*-0.225 | J15: =J7*-0.225 | K15: =K7*-0.225 | L15: =L7*-0.225 | M15: =M7*-0.225 | N15: =N7*-0.225 | O15: =O7*-0.225 | P15: =P7*-0.225
A16: COGS-Total Costs | B16: Total Operating Costs (excl D&A) | C16: AUDm | D16: =D13+D14+D15 | E16: =E13+E14+E15 | F16: =F13+F14+F15 | G16: =G13+G14+G15 | H16: =H13+H14+H15 | I16: =I13+I14+I15 | J16: =J13+J14+J15 | K16: =K13+K14+K15 | ... P16: =P13+P14+P15
B18: Statutory EBITDA
A19: GP-Statutory EBITDA | B19: Statutory EBITDA | C19: AUDm | D19: =D9+D16 | E19: =E9+E16 | F19: =F9+F16 | G19: =G9+G16 | H19: =H9+H16 | I19: =I9+I16 | J19: =J9+J16 | K19: =K9+K16 | ... P19: =P9+P16
B20: Statutory EBITDA Margin | C20: % | D20: =IF(D7=0,"",D19/D7) | E20: =IF(E7=0,"",E19/E7) | F20: =IF(F7=0,"",F19/F7) | G20: =IF(G7=0,"",G19/G7) | H20: =IF(H7=0,"",H19/H7) | I20: =IF(I7=0,"",I19/I7) | J20: =IF(J7=0,"",J19/J7) | K20: =IF(K7=0,"",K19/K7) | ... P20: =IF(P7=0,"",P19/P7)
B26: Segment EBITDA
B34: EBITDA
A35: EBITDA-Australia EBITDA | B35: Australia Segment Underlying EBITDA | C35: AUDm | D35: 30.7 | E35: 45.6 | F35: 66 | G35: =INDEX('HY & Segments'!$A:$AG,MATCH($A35,'HY & Segments'!$A:$A,0),MATCH("1H"&RIGHT(G$1,2),'HY & Segments'!$3:$3,0))+INDEX('HY & Segments'!$A:$AG,MATCH($A35,'HY & Segments'!$A:$A,0),MATCH("2H"&RIGHT(G$1,2),'HY & Segments'!$3:$3,0)) | H35: =INDEX('HY & Segments'!$A:$AG,MATCH($A35,'HY & Segments'!$A:$A,0),MATCH("1H"&RIGHT(H$1,2),'HY & Segments'!$3:$3,0))+INDEX('HY & Segments'!$A:$AG,MATCH($A35,'HY & Segments'!$A:$A,0),MATCH("2H"&RIGHT(H$1,2),'HY & Segments'!$3:$3,0)) | I35: =INDEX('HY & Segments'!$A:$AG,MATCH($A35,'HY & Segments'!$A:$A,0),MATCH("1H"&RIGHT(I$1,2),'HY & Segments'!$3:$3,0))+INDEX('HY & Segments'!$A:$AG,MATCH($A35,'HY & Segments'!$A:$A,0),MATCH("2H"&RIGHT(I$1,2),'HY & Segments'!$3:$3,0)) | J35: =INDEX('HY & Segments'!$A:$AG,MATCH($A35,'HY & Segments'!$A:$A,0),MATCH("1H"&RIGHT(J$1,2),'HY & Segments'!$3:$3,0))+INDEX('HY & Segments'!$A:$AG,MATCH($A35,'HY & Segments'!$A:$A,0),MATCH("2H"&RIGHT(J$1,2),'HY & Segments'!$3:$3,0)) | K35: =INDEX('HY & Segments'!$A:$AG,MATCH($A35,'HY & Segments'!$A:$A,0),MATCH("1H"&RIGHT(K$1,2),'HY & Segments'!$3:$3,0))+INDEX('HY & Segments'!$A:$AG,MATCH($A35,'HY & Segments'!$A:$A,0),MATCH("2H"&RIGHT(K$1,2),'HY & Segments'!$3:$3,0)) | L35: =INDEX('HY & Segments'!$A:$AG,MATCH($A35,'HY & Segments'!$A:$A,0),MATCH("1H"&RIGHT(L$1,2),'HY & Segments'!$3:$3,0))+INDEX('HY & Segments'!$A:$AG,MATCH($A35,'HY & Segments'!$A:$A,0),MATCH("2H"&RIGHT(L$1,2),'HY & Segments'!$3:$3,0)) | M35: =INDEX('HY & Segments'!$A:$AG,MATCH($A35,'HY & Segments'!$A:$A,0),MATCH("1H"&RIGHT(M$1,2),'HY & Segments'!$3:$3,0))+INDEX('HY & Segments'!$A:$AG,MATCH($A35,'HY & Segments'!$A:$A,0),MATCH("2H"&RIGHT(M$1,2),'HY & Segments'!$3:$3,0)) | N35: =INDEX('HY & Segments'!$A:$AG,MATCH($A35,'HY & Segments'!$A:$A,0),MATCH("1H"&RIGHT(N$1,2),'HY & Segments'!$3:$3,0))+INDEX('HY & Segments'!$A:$AG,MATCH($A35,'HY & Segments'!$A:$A,0),MATCH("2H"&RIGHT(N$1,2),'HY & Segments'!$3:$3,0)) | ... P35: =INDEX('HY & Segments'!$A:$AG,MATCH($A35,'HY & Segments'!$A:$A,0),MATCH("1H"&RIGHT(P$1,2),'HY & Segments'!$3:$3,0))+INDEX('HY & Segments'!$A:$AG,MATCH($A35,'HY & Segments'!$A:$A,0),MATCH("2H"&RIGHT(P$1,2),'HY & Segments'!$3:$3,0))
A36: EBITDA-US EBITDA | B36: US Segment Underlying EBITDA | C36: AUDm | D36: -4.3 | E36: -6.5 | F36: -13.2 | G36: =INDEX('HY & Segments'!$A:$AG,MATCH($A36,'HY & Segments'!$A:$A,0),MATCH("1H"&RIGHT(G$1,2),'HY & Segments'!$3:$3,0))+INDEX('HY & Segments'!$A:$AG,MATCH($A36,'HY & Segments'!$A:$A,0),MATCH("2H"&RIGHT(G$1,2),'HY & Segments'!$3:$3,0)) | H36: =INDEX('HY & Segments'!$A:$AG,MATCH($A36,'HY & Segments'!$A:$A,0),MATCH("1H"&RIGHT(H$1,2),'HY & Segments'!$3:$3,0))+INDEX('HY & Segments'!$A:$AG,MATCH($A36,'HY & Segments'!$A:$A,0),MATCH("2H"&RIGHT(H$1,2),'HY & Segments'!$3:$3,0)) | I36: =INDEX('HY & Segments'!$A:$AG,MATCH($A36,'HY & Segments'!$A:$A,0),MATCH("1H"&RIGHT(I$1,2),'HY & Segments'!$3:$3,0))+INDEX('HY & Segments'!$A:$AG,MATCH($A36,'HY & Segments'!$A:$A,0),MATCH("2H"&RIGHT(I$1,2),'HY & Segments'!$3:$3,0)) | J36: =INDEX('HY & Segments'!$A:$AG,MATCH($A36,'HY & Segments'!$A:$A,0),MATCH("1H"&RIGHT(J$1,2),'HY & Segments'!$3:$3,0))+INDEX('HY & Segments'!$A:$AG,MATCH($A36,'HY & Segments'!$A:$A,0),MATCH("2H"&RIGHT(J$1,2),'HY & Segments'!$3:$3,0)) | K36: =INDEX('HY & Segments'!$A:$AG,MATCH($A36,'HY & Segments'!$A:$A,0),MATCH("1H"&RIGHT(K$1,2),'HY & Segments'!$3:$3,0))+INDEX('HY & Segments'!$A:$AG,MATCH($A36,'HY & Segments'!$A:$A,0),MATCH("2H"&RIGHT(K$1,2),'HY & Segments'!$3:$3,0)) | L36: =INDEX('HY & Segments'!$A:$AG,MATCH($A36,'HY & Segments'!$A:$A,0),MATCH("1H"&RIGHT(L$1,2),'HY & Segments'!$3:$3,0))+INDEX('HY & Segments'!$A:$AG,MATCH($A36,'HY & Segments'!$A:$A,0),MATCH("2H"&RIGHT(L$1,2),'HY & Segments'!$3:$3,0)) | M36: =INDEX('HY & Segments'!$A:$AG,MATCH($A36,'HY & Segments'!$A:$A,0),MATCH("1H"&RIGHT(M$1,2),'HY & Segments'!$3:$3,0))+INDEX('HY & Segments'!$A:$AG,MATCH($A36,'HY & Segments'!$A:$A,0),MATCH("2H"&RIGHT(M$1,2),'HY & Segments'!$3:$3,0)) | N36: =INDEX('HY & Segments'!$A:$AG,MATCH($A36,'HY & Segments'!$A:$A,0),MATCH("1H"&RIGHT(N$1,2),'HY & Segments'!$3:$3,0))+INDEX('HY & Segments'!$A:$AG,MATCH($A36,'HY & Segments'!$A:$A,0),MATCH("2H"&RIGHT(N$1,2),'HY & Segments'!$3:$3,0)) | ... P36: =INDEX('HY & Segments'!$A:$AG,MATCH($A36,'HY & Segments'!$A:$A,0),MATCH("1H"&RIGHT(P$1,2),'HY & Segments'!$3:$3,0))+INDEX('HY & Segments'!$A:$AG,MATCH($A36,'HY & Segments'!$A:$A,0),MATCH("2H"&RIGHT(P$1,2),'HY & Segments'!$3:$3,0))
A37: EBITDA-Corporate EBITDA | B37: Corporate / Eliminations | C37: AUDm | D37: 0 | E37: 0 | F37: 0 | G37: 0 | H37: 0 | I37: 0 | J37: 0 | K37: 0 | L37: 0 | M37: 0 | N37: 0 | O37: 0 | P37: 0
A38: EBITDA-Underlying EBITDA | B38: Group Segment Underlying EBITDA | C38: AUDm | D38: =SUM(D35:D37) | E38: =SUM(E35:E37) | F38: =SUM(F35:F37) | G38: =SUM(G35:G37) | H38: =SUM(H35:H37) | I38: =SUM(I35:I37) | J38: =SUM(J35:J37) | K38: =SUM(K35:K37) | ... P38: =SUM(P35:P37)
B39: Seg EBITDA Growth | C39: % YoY | E39: =E38/D38-1 | F39: =F38/E38-1 | G39: =IF(F38=0,"",G38/F38-1) | H39: =IF(G38=0,"",H38/G38-1) | I39: =IF(H38=0,"",I38/H38-1) | J39: =IF(I38=0,"",J38/I38-1) | K39: =IF(J38=0,"",K38/J38-1) | L39: =IF(K38=0,"",L38/K38-1) | M39: =IF(L38=0,"",M38/L38-1) | N39: =IF(M38=0,"",N38/M38-1) | ... P39: =IF(O38=0,"",P38/O38-1)
B40: Seg EBITDA Margin (% NS) | C40: % | D40: =IF(D7=0,"",D38/D7) | E40: =IF(E7=0,"",E38/E7) | F40: =IF(F7=0,"",F38/F7) | G40: =IF(G7=0,"",G38/G7) | H40: =IF(H7=0,"",H38/H7) | I40: =IF(I7=0,"",I38/I7) | J40: =IF(J7=0,"",J38/J7) | K40: =IF(K7=0,"",K38/K7) | ... P40: =IF(P7=0,"",P38/P7)
A42: Stat-AASB16 | B42: AASB 16 Lease Impact | C42: AUDm | D42: 3.2 | E42: 12 | F42: 18.5 | G42: =F42*1.12 | H42: =G42*1.12 | I42: =H42*1.12 | J42: =I42*1.12 | K42: =J42*1.12 | L42: =K42*1.12 | M42: =L42*1.12 | N42: =M42*1.12 | ... P42: =O42*1.12
A43: Stat-SBP | B43: Share-Based Payments | C43: AUDm | D43: 0 | E43: -5.5 | F43: -9 | G43: =F43 | H43: =G43 | I43: =H43 | J43: =I43 | K43: =J43 | L43: =K43 | M43: =L43 | N43: =M43 | ... P43: =O43
A44: Stat-Other Adj | B44: Other Adjustments | C44: AUDm | D44: 0 | E44: -18.3 | F44: 2.9 | G44: =F44 | H44: =G44 | I44: =H44 | J44: =I44 | K44: =J44 | L44: =K44 | M44: =L44 | N44: =M44 | ... P44: =O44
A45: Stat-Statutory EBITDA | B45: Statutory EBITDA | C45: AUDm | D45: =D38+D42+D43+D44 | E45: =E38+E42+E43+E44 | F45: =F38+F42+F43+F44 | G45: =G38+G42+G43+G44 | H45: =H38+H42+H43+H44 | I45: =I38+I42+I43+I44 | J45: =J38+J42+J43+J44 | K45: =K38+K42+K43+K44 | ... P45: =P38+P42+P43+P44
B47: D&A
A48: DA-Total DA | B48: Depreciation & Amortisation | C48: AUDm | D48: -25.555 | E48: -31.123 | F48: -39.681 | G48: =F48*1.14 | H48: =G48*1.14 | I48: =H48*1.14 | J48: =I48*1.08 | K48: =J48*1.08 | L48: =K48*1.08 | M48: =L48*1.08 | N48: =M48*1.08 | O48: =N48*1.08 | P48: =O48*1.08
B51: D&A / Revenue | C51: % | D51: =IF(D7=0,"",D48/D7) | E51: =IF(E7=0,"",E48/E7) | F51: =IF(F7=0,"",F48/F7) | G51: =IF(G7=0,"",G48/G7) | H51: =IF(H7=0,"",H48/H7) | I51: =IF(I7=0,"",I48/I7) | J51: =IF(J7=0,"",J48/J7) | K51: =IF(K7=0,"",K48/K7) | ... P51: =IF(P7=0,"",P48/P7)
B53: EBIT
A54: EBIT-EBIT | B54: EBIT (Operating Profit) | C54: AUDm | D54: =D45+D48 | E54: =E45+E48 | F54: =F45+F48 | G54: =G45+G48 | H54: =H45+H48 | I54: =I45+I48 | J54: =J45+J48 | K54: =K45+K48 | ... P54: =P45+P48
B55: EBIT Growth | C55: % YoY | E55: =IF(D54=0,"",E54/D54-1) | F55: =IF(E54=0,"",F54/E54-1) | G55: =IF(F54=0,"",G54/F54-1) | H55: =IF(G54=0,"",H54/G54-1) | I55: =IF(H54=0,"",I54/H54-1) | J55: =IF(I54=0,"",J54/I54-1) | K55: =IF(J54=0,"",K54/J54-1) | L55: =IF(K54=0,"",L54/K54-1) | ... P55: =IF(O54=0,"",P54/O54-1)
B56: EBIT Margin | C56: % | D56: =IF(D7=0,"",D54/D7) | E56: =IF(E7=0,"",E54/E7) | F56: =IF(F7=0,"",F54/F7) | G56: =IF(G7=0,"",G54/G7) | H56: =IF(H7=0,"",H54/H7) | I56: =IF(I7=0,"",I54/I7) | J56: =IF(J7=0,"",J54/J7) | K56: =IF(K7=0,"",K54/K7) | ... P56: =IF(P7=0,"",P54/P7)
B58: Interest
A59: Int-Finance Income | B59: Finance Income | C59: AUDm | D59: 4.593 | E59: 6.012 | F59: 22.674 | G59: =F59*1.0 | H59: =G59*1.0 | I59: =H59*1.0 | J59: =I59*1.0 | K59: =J59*1.0 | L59: =K59*1.0 | M59: =L59*1.0 | N59: =M59*1.0 | ... P59: =O59*1.0
A60: Int-Finance Costs | B60: Finance Costs | C60: AUDm | D60: -8.503 | E60: -13.724 | F60: -18.902 | G60: =F60*1.10 | H60: =G60*1.10 | I60: =H60*1.10 | J60: =I60*1.10 | K60: =J60*1.10 | L60: =K60*1.10 | M60: =L60*1.10 | N60: =M60*1.10 | ... P60: =O60*1.10
A61: Int-Net Finance Costs | B61: Net Finance Costs | C61: AUDm | D61: =D59+D60 | E61: =E59+E60 | F61: =F59+F60 | G61: =G59+G60 | H61: =H59+H60 | I61: =I59+I60 | J61: =J59+J60 | K61: =K59+K60 | ... P61: =P59+P60
B67: PBT, Tax, NPAT
A68: PBT-PBT | B68: PBT | C68: AUDm | D68: =D54+D61 | E68: =E54+E61 | F68: =F54+F61 | G68: =G54+G61 | H68: =H54+H61 | I68: =I54+I61 | J68: =J54+J61 | K68: =K54+K61 | ... P68: =P54+P61
A69: Tax-Tax Expense | B69: Tax Expense | C69: AUDm | D69: -2.423 | E69: -2.187 | F69: -14.734 | G69: =IF(G68>0,-G68*0.35,0) | H69: =IF(H68>0,-H68*0.35,0) | I69: =IF(I68>0,-I68*0.35,0) | J69: =IF(J68>0,-J68*0.35,0) | K69: =IF(K68>0,-K68*0.35,0) | L69: =IF(L68>0,-L68*0.35,0) | M69: =IF(M68>0,-M68*0.35,0) | N69: =IF(N68>0,-N68*0.35,0) | ... P69: =IF(P68>0,-P68*0.35,0)
B70: Effective Tax Rate | C70: % | D70: =IF(D68=0,"",D69/D68) | E70: =IF(E68=0,"",E69/E68) | F70: =IF(F68=0,"",F69/F68) | G70: =IF(G68=0,"",G69/G68) | H70: =IF(H68=0,"",H69/H68) | I70: =IF(I68=0,"",I69/I68) | J70: =IF(J68=0,"",J69/J68) | K70: =IF(K68=0,"",K69/K68) | ... P70: =IF(P68=0,"",P69/P68)
A72: NPAT-Statutory NPAT | B72: NPAT | C72: AUDm | D72: =D68+D69 | E72: =E68+E69 | F72: =F68+F69 | G72: =G68+G69 | H72: =H68+H69 | I72: =I68+I69 | J72: =J68+J69 | K72: =K68+K69 | ... P72: =P68+P69
B75: NPAT Growth | C75: % YoY | E75: =IF(D72=0,"",E72/D72-1) | F75: =IF(E72=0,"",F72/E72-1) | G75: =IF(F72<=0,"",G72/F72-1) | H75: =IF(G72<=0,"",H72/G72-1) | I75: =IF(H72<=0,"",I72/H72-1) | J75: =IF(I72<=0,"",J72/I72-1) | K75: =IF(J72<=0,"",K72/J72-1) | L75: =IF(K72<=0,"",L72/K72-1) | M75: =IF(L72<=0,"",M72/L72-1) | N75: =IF(M72<=0,"",N72/M72-1) | ... P75: =IF(O72<=0,"",P72/O72-1)
B76: NPAT Margin | C76: % | D76: =IF(D7=0,"",D72/D7) | E76: =IF(E7=0,"",E72/E7) | F76: =IF(F7=0,"",F72/F7) | G76: =IF(G7=0,"",G72/G7) | H76: =IF(H7=0,"",H72/H7) | I76: =IF(I7=0,"",I72/I7) | J76: =IF(J7=0,"",J72/J7) | K76: =IF(K7=0,"",K72/K7) | ... P76: =IF(P7=0,"",P72/P7)
B78: EPS & Dividends
A79: EPS-YE Shares | B79: YE Shares Outstanding | C79: #m | D79: 84.8 | E79: 103 | F79: 102.9 | G79: =F79 | H79: =G79 | I79: =H79 | J79: =I79 | K79: =J79 | L79: =K79 | M79: =L79 | N79: =M79 | ... P79: =O79
A80: EPS-WASO Basic | B80: WASO Basic | C80: #m | D80: 84 | E80: 85.4 | F80: 101.2 | G80: =F80 | H80: =G80 | I80: =H80 | J80: =I80 | K80: =J80 | L80: =K80 | M80: =L80 | N80: =M80 | ... P80: =O80
A81: EPS-Dilution | B81: Dilution | C81: #m | D81: 0 | E81: 0 | F81: 4.5 | G81: =F81 | H81: =G81 | I81: =H81 | J81: =I81 | K81: =J81 | L81: =K81 | M81: =L81 | N81: =M81 | ... P81: =O81
A82: EPS-WASO Diluted | B82: WASO Diluted | C82: #m | D82: =D80+D81 | E82: =E80+E81 | F82: =F80+F81 | G82: =G80+G81 | H82: =H80+H81 | I82: =I80+I81 | J82: =J80+J81 | K82: =K80+K81 | ... P82: =P80+P81
A84: EPS-Basic EPS | B84: Basic EPS | C84: AUDps | D84: =IF(D80=0,"",D72/D80) | E84: =IF(E80=0,"",E72/E80) | F84: =IF(F80=0,"",F72/F80) | G84: =IF(G80=0,"",G72/G80) | H84: =IF(H80=0,"",H72/H80) | I84: =IF(I80=0,"",I72/I80) | J84: =IF(J80=0,"",J72/J80) | K84: =IF(K80=0,"",K72/K80) | ... P84: =IF(P80=0,"",P72/P80)
A85: EPS-Diluted EPS | B85: Diluted EPS | C85: AUDps | D85: =IF(D82=0,"",D72/D82) | E85: =IF(E82=0,"",E72/E82) | F85: =IF(F82=0,"",F72/F82) | G85: =IF(G82=0,"",G72/G82) | H85: =IF(H82=0,"",H72/H82) | I85: =IF(I82=0,"",I72/I82) | J85: =IF(J82=0,"",J72/J82) | K85: =IF(K82=0,"",K72/K82) | ... P85: =IF(P82=0,"",P72/P82)
B86: EPS Growth | C86: % YoY | G86: =IF(F85<=0,"",G85/F85-1) | H86: =IF(G85<=0,"",H85/G85-1) | I86: =IF(H85<=0,"",I85/H85-1) | J86: =IF(I85<=0,"",J85/I85-1) | K86: =IF(J85<=0,"",K85/J85-1) | L86: =IF(K85<=0,"",L85/K85-1) | M86: =IF(L85<=0,"",M85/L85-1) | N86: =IF(M85<=0,"",N85/M85-1) | ... P86: =IF(O85<=0,"",P85/O85-1)
A88: Div-DPS | B88: DPS | C88: AUDps | D88: 0 | E88: 0 | F88: 0.126 | G88: =IF(G72>0,G84*0.8,0) | H88: =IF(H72>0,H84*0.8,0) | I88: =IF(I72>0,I84*0.8,0) | J88: =IF(J72>0,J84*0.8,0) | K88: =IF(K72>0,K84*0.8,0) | L88: =IF(L72>0,L84*0.8,0) | M88: =IF(M72>0,M84*0.8,0) | N88: =IF(N72>0,N84*0.8,0) | ... P88: =IF(P72>0,P84*0.8,0)
A89: Div-Total Dividends | B89: Total Dividends | C89: AUDm | D89: 0 | E89: 0 | F89: 13 | G89: =G88*G80 | H89: =H88*H80 | I89: =I88*I80 | J89: =J88*J80 | K89: =K88*K80 | L89: =L88*L80 | M89: =M88*M80 | N89: =N88*N80 | ... P89: =P88*P80
B90: Payout Ratio | C90: % | D90: =IF(D72<=0,"",D89/D72) | E90: =IF(E72<=0,"",E89/E72) | F90: =IF(F72<=0,"",F89/F72) | G90: =IF(G72<=0,"",G89/G72) | H90: =IF(H72<=0,"",H89/H72) | I90: =IF(I72<=0,"",I89/I72) | J90: =IF(J72<=0,"",J89/J72) | K90: =IF(K72<=0,"",K89/K72) | ... P90: =IF(P72<=0,"",P89/P72)
B91: Dividend Yield | C91: %
B92: Dividend Growth | C92: % YoY
B94: Operating Metrics
A95: KPI-Total Restaurants | B95: Total Restaurants | C95: # | D95: 194 | E95: 220 | F95: 256 | G95: =F95+35 | H95: =G95+35 | I95: =H95+35 | J95: =I95+35 | K95: =J95+35 | L95: =K95+35 | M95: =L95+35 | N95: =M95+35 | ... P95: =O95+35
A96: KPI-Aus Corp Restaurants | B96: Australia Corporate Restaurants | C96: # | D96: 55 | E96: 64 | F96: 81 | G96: =F96+10 | H96: =G96+10 | I96: =H96+10 | J96: =I96+10 | K96: =J96+10 | L96: =K96+10 | M96: =L96+10 | N96: =M96+10 | ... P96: =O96+10
A97: KPI-Aus Fran Restaurants | B97: Australia Franchise Restaurants | C97: # | D97: 136 | E97: 152 | F97: 169 | G97: =F97+22 | H97: =G97+22 | I97: =H97+22 | J97: =I97+22 | K97: =J97+22 | L97: =K97+22 | M97: =L97+22 | N97: =M97+22 | ... P97: =O97+22
A98: KPI-US Restaurants | B98: US Restaurants | C98: # | D98: 3 | E98: 4 | F98: 6 | G98: =F98+3 | H98: =G98+3 | I98: =H98+3 | J98: =I98+3 | K98: =J98+3 | L98: =K98+3 | M98: =L98+3 | N98: =M98+3 | ... P98: =O98+3
A99: KPI-Aus Network Sales | B99: Australia Network Sales | C99: AUDm | D99: 753 | E99: 948.9 | F99: 1168.5 | G99: =F99*1.1400000000000001 | H99: =G99*1.1400000000000001 | I99: =H99*1.1400000000000001 | J99: =I99*1.1 | K99: =J99*1.1 | L99: =K99*1.1 | M99: =L99*1.1 | N99: =M99*1.1 | O99: =N99*1.1 | P99: =O99*1.1
A100: KPI-Comp Sales Growth | B100: Comp Sales Growth | C100: % | E100: =E99/D99-1 | F100: =F99/E99-1 | G100: =G99/F99-1 | H100: =H99/G99-1 | I100: =I99/H99-1 | J100: =J99/I99-1 | K100: =K99/J99-1 | L100: =L99/K99-1 | ... P100: =P99/O99-1
A101: KPI-Corp Rest Margin % | B101: Corporate Restaurant Margin % | C101: % | D101: 0.144 | E101: 0.174 | F101: 0.179 | G101: 0.182 | H101: 0.185 | I101: 0.188 | J101: 0.19 | K101: 0.19 | L101: 0.19 | M101: 0.19 | N101: 0.19 | O101: 0.19 | P101: 0.19
A102: KPI-Implied Royalty Rate | B102: Implied Royalty Rate | C102: % | D102: 0.087 | E102: 0.091 | F102: 0.097 | G102: 0.1 | H102: 0.1 | I102: 0.1 | J102: 0.1 | K102: 0.1 | L102: 0.1 | M102: 0.1 | N102: 0.1 | O102: 0.1 | P102: 0.1
A103: KPI-G&A % NS | B103: G&A as % of Network Sales | C103: % | D103: 0.062 | E103: 0.067 | F103: 0.066 | G103: 0.063 | H103: 0.06 | I103: 0.057 | J103: 0.054 | K103: 0.051 | L103: 0.05 | M103: 0.05 | N103: 0.05 | O103: 0.05 | P103: 0.05
A104: KPI-Seg EBITDA % NS | B104: Seg EBITDA as % of Network Sales | C104: % | D104: 0.041 | E104: 0.048 | F104: 0.057 | G104: =IF(G99=0,"",G38/G99) | H104: =IF(H99=0,"",H38/H99) | I104: =IF(I99=0,"",I38/I99) | J104: =IF(J99=0,"",J38/J99) | K104: =IF(K99=0,"",K38/K99) | L104: =IF(L99=0,"",L38/L99) | M104: =IF(M99=0,"",M38/M99) | N104: =IF(N99=0,"",N38/N99) | ... P104: =IF(P99=0,"",P38/P99)
B108: Balance Sheet
B109: Assets
A110: BS-Cash | B110: Cash & Term Deposits | C110: AUDm | D110: 36.504 | E110: 294.48 | F110: 281.743 | G110: =F110+G176 | H110: =G110+H176 | I110: =H110+I176 | J110: =I110+J176 | K110: =J110+K176 | L110: =K110+L176 | M110: =L110+M176 | N110: =M110+N176 | ... P110: =O110+P176
A111: BS-Trade Receivables | B111: Trade Receivables | C111: AUDm | D111: 25.087 | E111: 26.499 | F111: 24.84 | G111: =G7*G118 | H111: =H7*H118 | I111: =I7*I118 | J111: =J7*J118 | K111: =K7*K118 | L111: =L7*L118 | M111: =M7*M118 | N111: =N7*N118 | ... P111: =P7*P118
A112: BS-Inventories | B112: Inventories | C112: AUDm | D112: 2.153 | E112: 2.825 | F112: 3.761 | G112: =G7*G119 | H112: =H7*H119 | I112: =I7*I119 | J112: =J7*J119 | K112: =K7*K119 | L112: =L7*L119 | M112: =M7*M119 | N112: =N7*N119 | ... P112: =P7*P119
A113: BS-PPE | B113: Property, Plant & Equipment | C113: AUDm | D113: 69.486 | E113: 87.63 | F113: 130.056 | G113: =F113-G160-G48*0.4 | H113: =G113-H160-H48*0.4 | I113: =H113-I160-I48*0.4 | J113: =I113-J160-J48*0.4 | K113: =J113-K160-K48*0.4 | L113: =K113-L160-L48*0.4 | M113: =L113-M160-M48*0.4 | N113: =M113-N160-N48*0.4 | ... P113: =O113-P160-P48*0.4
A114: BS-Intangibles | B114: Intangibles | C114: AUDm | D114: 15.202 | E114: 10.586 | F114: 18.305 | G114: =F114 | H114: =G114 | I114: =H114 | J114: =I114 | K114: =J114 | L114: =K114 | M114: =L114 | N114: =M114 | ... P114: =O114
A115: BS-ROU Assets | B115: Right-of-Use Assets | C115: AUDm | D115: 98.939 | E115: 93.796 | F115: 125.43 | G115: =F115*1.12 | H115: =G115*1.12 | I115: =H115*1.12 | J115: =I115*1.12 | K115: =J115*1.12 | L115: =K115*1.12 | M115: =L115*1.12 | N115: =M115*1.12 | ... P115: =O115*1.12
A116: BS-Other Assets | B116: Finance Lease Rec & Other Assets | C116: AUDm | D116: 77.14 | E116: 145.981 | F116: 199.063 | G116: =F116*1.08 | H116: =G116*1.08 | I116: =H116*1.08 | J116: =I116*1.08 | K116: =J116*1.08 | L116: =K116*1.08 | M116: =L116*1.08 | N116: =M116*1.08 | ... P116: =O116*1.08
B117: Total Assets | C117: AUDm | D117: =SUM(D110:D116) | E117: =SUM(E110:E116) | F117: =SUM(F110:F116) | G117: =SUM(G110:G116) | H117: =SUM(H110:H116) | I117: =SUM(I110:I116) | J117: =SUM(J110:J116) | K117: =SUM(K110:K116) | ... P117: =SUM(P110:P116)
B118: Receivables / Revenue | C118: % | D118: =IF(D7=0,"",D111/D7) | E118: =IF(E7=0,"",E111/E7) | F118: =IF(F7=0,"",F111/F7) | G118: =F118 | H118: =G118 | I118: =H118 | J118: =I118 | K118: =J118 | L118: =K118 | M118: =L118 | N118: =M118 | ... P118: =O118
B119: Inventory / Revenue | C119: % | D119: =IF(D7=0,"",D112/D7) | E119: =IF(E7=0,"",E112/E7) | F119: =IF(F7=0,"",F112/F7) | G119: =F119 | H119: =G119 | I119: =H119 | J119: =I119 | K119: =J119 | L119: =K119 | M119: =L119 | N119: =M119 | ... P119: =O119
B121: Payables / Revenue | C121: % | D121: =IF(D7=0,"",D125/D7) | E121: =IF(E7=0,"",E125/E7) | F121: =IF(F7=0,"",F125/F7) | G121: =F121 | H121: =G121 | I121: =H121 | J121: =I121 | K121: =J121 | L121: =K121 | M121: =L121 | N121: =M121 | ... P121: =O121
B124: Liabilities
A125: BS-Trade Payables | B125: Trade & Other Payables | C125: AUDm | D125: 32.635 | E125: 39.387 | F125: 40.439 | G125: =G7*G121 | H125: =H7*H121 | I125: =I7*I121 | J125: =J7*J121 | K125: =K7*K121 | L125: =L7*L121 | M125: =M7*M121 | N125: =N7*N121 | ... P125: =P7*P121
A126: BS-Other Liabilities | B126: Other Liabilities | C126: AUDm | D126: 22.19 | E126: 28.933 | F126: 31.324 | G126: =F126 | H126: =G126 | I126: =H126 | J126: =I126 | K126: =J126 | L126: =K126 | M126: =L126 | N126: =M126 | ... P126: =O126
A127: BS-Lease Liabilities | B127: Lease Liabilities | C127: AUDm | D127: 181.717 | E127: 239.498 | F127: 331.311 | G127: =F127*1.12 | H127: =G127*1.12 | I127: =H127*1.12 | J127: =I127*1.12 | K127: =J127*1.12 | L127: =K127*1.12 | M127: =L127*1.12 | N127: =M127*1.12 | ... P127: =O127*1.12
A128: BS-Total Banking Debt | B128: Total Banking Debt | C128: AUDm | D128: 0 | E128: 0 | F128: 0 | G128: 0 | H128: 0 | I128: 0 | J128: 0 | K128: 0 | L128: 0 | M128: 0 | N128: 0 | O128: 0 | P128: 0
B129: Total Liabilities | C129: AUDm | D129: =SUM(D125:D128) | E129: =SUM(E125:E128) | F129: =SUM(F125:F128) | G129: =SUM(G125:G128) | H129: =SUM(H125:H128) | I129: =SUM(I125:I128) | J129: =SUM(J125:J128) | K129: =SUM(K125:K128) | ... P129: =SUM(P125:P128)
B131: Net Cash (Debt) | C131: AUDm | D131: =D110-D128 | E131: =E110-E128 | F131: =F110-F128 | G131: =G110-G128 | H131: =H110-H128 | I131: =I110-I128 | J131: =J110-J128 | K131: =K110-K128 | ... P131: =P110-P128
B132: Adj Net Debt (incl leases) | C132: AUDm | D132: =D128-D110+D127 | E132: =E128-E110+E127 | F132: =F128-F110+F127 | G132: =G128-G110+G127 | H132: =H128-H110+H127 | I132: =I128-I110+I127 | J132: =J128-J110+J127 | K132: =K128-K110+K127 | ... P132: =P128-P110+P127
B133: Net Cash / Seg EBITDA | C133: x | D133: =IF(D38=0,"",D131/D38) | E133: =IF(E38=0,"",E131/E38) | F133: =IF(F38=0,"",F131/F38) | G133: =IF(G38=0,"",G131/G38) | H133: =IF(H38=0,"",H131/H38) | I133: =IF(I38=0,"",I131/I38) | J133: =IF(J38=0,"",J131/J38) | K133: =IF(K38=0,"",K131/K38) | ... P133: =IF(P38=0,"",P131/P38)
B136: Equity
A137: BS-Issued Capital | B137: Issued Capital | C137: AUDm | D137: 104.046 | E137: 372.708 | F137: 374.988 | G137: =F137 | H137: =G137 | I137: =H137 | J137: =I137 | K137: =J137 | L137: =K137 | M137: =L137 | N137: =M137 | ... P137: =O137
A138: BS-Retained Profits | B138: Accumulated Losses | C138: AUDm | D138: -26.857 | E138: -36.147 | F138: -21.671 | G138: =F138+G72-G89 | H138: =G138+H72-H89 | I138: =H138+I72-I89 | J138: =I138+J72-J89 | K138: =J138+K72-K89 | L138: =K138+L72-L89 | M138: =L138+M72-M89 | N138: =M138+N72-N89 | ... P138: =O138+P72-P89
A139: BS-Reserves | B139: Reserves | C139: AUDm | D139: 10.776 | E139: 17.418 | F139: 26.807 | G139: =F139 | H139: =G139 | I139: =H139 | J139: =I139 | K139: =J139 | L139: =K139 | M139: =L139 | N139: =M139 | ... P139: =O139
A140: BS-Minorities | B140: Minorities | C140: AUDm | D140: 0 | E140: 0 | F140: 0 | G140: 0 | H140: 0 | I140: 0 | J140: 0 | K140: 0 | L140: 0 | M140: 0 | N140: 0 | O140: 0 | P140: 0
B141: Total Equity | C141: AUDm | D141: =SUM(D137:D140) | E141: =SUM(E137:E140) | F141: =SUM(F137:F140) | G141: =SUM(G137:G140) | H141: =SUM(H137:H140) | I141: =SUM(I137:I140) | J141: =SUM(J137:J140) | K141: =SUM(K137:K140) | ... P141: =SUM(P137:P140)
...

Sheet HY & Segments
D1: 2023 | E1: 2023 | F1: 2024 | G1: 2024 | H1: 2025 | I1: 2025 | J1: 2026 | K1: 2026 | L1: 2027 | M1: 2027 | N1: 2028 | O1: 2028 | P1: 2029 | Q1: 2029 | R1: 2030 | S1: 2030 | T1: 2031 | U1: 2031 | V1: 2032 | W1: 2032 | X1: 2033 | Y1: 2033 | Z1: 2034 | AA1: 2034 | AB1: 2035 | AC1: 2035
B2: GYG Segments (Half-Year) | D2: Actual ----------> | K2: Forecast ----->
B3: Guzman y Gomez (GYG.AX) | C3: Units | D3: 1H23 | E3: 2H23 | F3: 1H24 | G3: 2H24 | H3: 1H25 | I3: 2H25 | J3: 1H26 | K3: 2H26 | L3: 1H27 | M3: 2H27 | N3: 1H28 | O3: 2H28 | P3: 1H29 | Q3: 2H29 | R3: 1H30 | S3: 2H30 | T3: 1H31 | U3: 2H31 | V3: 1H32 | W3: 2H32 | X3: 1H33 | Y3: 2H33 | Z3: 1H34 | AA3: 2H34 | AB3: 1H35 | AC3: 2H35
D4: 44926 | E4: 45107 | F4: 45291 | G4: 45473 | H4: 45657 | I4: 45838 | J4: 46022 | K4: 46203 | L4: 46387 | M4: 46568 | N4: 46752 | O4: 46934 | P4: 47118 | Q4: 47299 | R4: 47483 | S4: 47664 | T4: 47848 | U4: 48029 | V4: 48213 | W4: 48395 | X4: 48579 | Y4: 48760 | Z4: 48944 | AA4: 49125 | AB4: 49309 | AC4: 49490
B5: P&L
B6: Revenue
A7: Rev-Total Revenue | B7: Total Revenue | C7: AUDm | D7: 124 | E7: 135.044 | F7: 167.287 | G7: 174.927 | H7: 212.419 | I7: 223.563 | J7: 261.201 | K7: =K104+K109+K118+K121 | L7: =L104+L109+L118+L121 | M7: =M104+M109+M118+M121 | N7: =N104+N109+N118+N121 | O7: =O104+O109+O118+O121 | P7: =P104+P109+P118+P121 | Q7: =Q104+Q109+Q118+Q121 | R7: =R104+R109+R118+R121 | ... AC7: =AC104+AC109+AC118+AC121
A8: Rev-Other Revenue | B8: Other Revenue & Income | C8: AUDm | D8: 8.5 | E8: 9.225 | F8: 11.568 | G8: 11.206 | H8: 14.711 | I8: 17.313 | J8: 17.363 | K8: =I8*1.075 | L8: =J8*1.075 | M8: =K8*1.075 | N8: =L8*1.075 | O8: =M8*1.075 | P8: =N8*1.075 | Q8: =O8*1.075 | R8: =P8*1.075 | ... AC8: =AA8*1.075
A9: Rev-Total Rev Incl Other | B9: Total Revenue (incl Other) | C9: AUDm | D9: =D7+D8 | E9: =E7+E8 | F9: =F7+F8 | G9: =G7+G8 | H9: =H7+H8 | I9: =I7+I8 | J9: =J7+J8 | K9: =K7+K8 | ... AC9: =AC7+AC8
B10: Revenue Growth (YoY) | C10: % YoY | F10: =IF(D7=0,"",F7/D7-1) | G10: =IF(E7=0,"",G7/E7-1) | H10: =IF(F7=0,"",H7/F7-1) | I10: =IF(G7=0,"",I7/G7-1) | J10: =IF(H7=0,"",J7/H7-1) | K10: =IF(I7=0,"",K7/I7-1) | L10: =IF(J7=0,"",L7/J7-1) | M10: =IF(K7=0,"",M7/K7-1) | ... AC10: =IF(AA7=0,"",AC7/AA7-1)
B12: COGS
A13: COGS-Food & Packaging | B13: Cost of Food & Packaging | C13: AUDm | D13: -33.7 | E13: -36.728 | F13: -43.192 | G13: -44.388 | H13: -55.071 | I13: -58.877 | J13: -67.126 | K13: =K7*-0.261 | L13: =L7*-0.261 | M13: =M7*-0.261 | N13: =N7*-0.261 | O13: =O7*-0.261 | P13: =P7*-0.261 | Q13: =Q7*-0.261 | R13: =R7*-0.261 | ... AC13: =AC7*-0.261
A14: COGS-Employee Benefits | B14: Employee Benefits | C14: AUDm | D14: -54.5 | E14: -59.225 | F14: -73.326 | G14: -80.407 | H14: -89.003 | I14: -95.653 | J14: -110.669 | K14: =K7*-0.424 | L14: =L7*-0.424 | M14: =M7*-0.424 | N14: =N7*-0.424 | O14: =O7*-0.424 | P14: =P7*-0.424 | Q14: =Q7*-0.424 | R14: =R7*-0.424 | ... AC14: =AC7*-0.424
A15: COGS-Other Costs | B15: Admin, Marketing & Other | C15: AUDm | D15: -30.2 | E15: -32.795 | F15: -43.433 | G15: -52.968 | H15: -51.478 | I15: -52.805 | J15: -59.831 | K15: =K7*-0.230 | L15: =L7*-0.230 | M15: =M7*-0.230 | N15: =N7*-0.230 | O15: =O7*-0.230 | P15: =P7*-0.230 | Q15: =Q7*-0.230 | R15: =R7*-0.230 | ... AC15: =AC7*-0.230
A16: COGS-Total Costs | B16: Total Operating Costs | C16: AUDm | D16: =D13+D14+D15 | E16: =E13+E14+E15 | F16: =F13+F14+F15 | G16: =G13+G14+G15 | H16: =H13+H14+H15 | I16: =I13+I14+I15 | J16: =J13+J14+J15 | K16: =K13+K14+K15 | ... AC16: =AC13+AC14+AC15
B18: Statutory EBITDA
A19: GP-Statutory EBITDA | B19: Statutory EBITDA | C19: AUDm | D19: =D9+D16 | E19: =E9+E16 | F19: =F9+F16 | G19: =G9+G16 | H19: =H9+H16 | I19: =I9+I16 | J19: =J9+J16 | K19: =K9+K16 | ... AC19: =AC9+AC16
B28: Segment EBITDA
B37: Segment EBITDA
A38: EBITDA-Australia EBITDA | B38: Australia Segment EBITDA | C38: AUDm | D38: 15 | E38: 15.7 | F38: 23.1 | G38: 22.5 | H38: 31.8 | I38: 34.2 | J38: 41.3 | K38: =K112 | L38: =L112 | M38: =M112 | N38: =N112 | O38: =O112 | P38: =P112 | Q38: =Q112 | R38: =R112 | ... AC38: =AC112
A39: EBITDA-US EBITDA | B39: US Segment EBITDA | C39: AUDm | D39: -2 | E39: -2.3 | F39: -3.1 | G39: -3.4 | H39: -5 | I39: -8.2 | J39: -8.3 | K39: =K123 | L39: =L123 | M39: =M123 | N39: =N123 | O39: =O123 | P39: =P123 | Q39: =Q123 | R39: =R123 | ... AC39: =AC123
A40: EBITDA-Corporate EBITDA | B40: Corporate / Eliminations | C40: AUDm | D40: 0 | E40: 0 | F40: 0 | G40: 0 | H40: 0 | I40: 0 | J40: 0 | K40: 0 | L40: 0 | M40: 0 | N40: 0 | O40: 0 | P40: 0 | Q40: 0 | R40: 0 | S40: 0 | T40: 0 | U40: 0 | V40: 0 | W40: 0 | X40: 0 | Y40: 0 | Z40: 0 | AA40: 0 | AB40: 0 | AC40: 0
A42: EBITDA-Underlying EBITDA | B42: Group Segment Underlying EBITDA | C42: AUDm | D42: =SUM(D38:D40) | E42: =SUM(E38:E40) | F42: =SUM(F38:F40) | G42: =SUM(G38:G40) | H42: =SUM(H38:H40) | I42: =SUM(I38:I40) | J42: =SUM(J38:J40) | K42: =SUM(K38:K40) | ... AC42: =SUM(AC38:AC40)
B43: Seg EBITDA Growth (YoY) | C43: % YoY | F43: =IF(D42=0,"",F42/D42-1) | G43: =IF(E42=0,"",G42/E42-1) | H43: =IF(F42=0,"",H42/F42-1) | I43: =IF(G42=0,"",I42/G42-1) | J43: =IF(H42=0,"",J42/H42-1) | K43: =IF(I42=0,"",K42/I42-1) | L43: =IF(J42=0,"",L42/J42-1) | M43: =IF(K42=0,"",M42/K42-1) | ... AC43: =IF(AA42=0,"",AC42/AA42-1)
B44: Seg EBITDA Margin | C44: % | D44: =IF(D7=0,"",D42/D7) | E44: =IF(E7=0,"",E42/E7) | F44: =IF(F7=0,"",F42/F7) | G44: =IF(G7=0,"",G42/G7) | H44: =IF(H7=0,"",H42/H7) | I44: =IF(I7=0,"",I42/I7) | J44: =IF(J7=0,"",J42/J7) | K44: =IF(K7=0,"",K42/K7) | ... AC44: =IF(AC7=0,"",AC42/AC7)
A48: Stat-AASB16 | B48: AASB 16 / SBP / Other Adjustments | C48: AUDm | D48: 1.5 | E48: 1.7 | F48: 2.5 | G48: -9 | H48: 4.8 | I48: 7.5 | J48: 7.9 | K48: =I48*1.05 | L48: =J48*1.05 | M48: =K48*1.05 | N48: =L48*1.05 | O48: =M48*1.05 | P48: =N48*1.05 | Q48: =O48*1.05 | R48: =P48*1.05 | ... AC48: =AA48*1.05
A49: Stat-Statutory EBITDA | B49: Statutory EBITDA | C49: AUDm | D49: =D42+D48 | E49: =E42+E48 | F49: =F42+F48 | G49: =G42+G48 | H49: =H42+H48 | I49: =I42+I48 | J49: =J42+J48 | K49: =K42+K48 | ... AC49: =AC42+AC48
B51: D&A
A52: DA-Total DA | B52: Depreciation & Amortisation | C52: AUDm | D52: -12.2 | E52: -13.355 | F52: -15.9 | G52: -15.223 | H52: -19.08 | I52: -20.601 | J52: -21.181 | K52: =I52*1.06 | L52: =J52*1.06 | M52: =K52*1.06 | N52: =L52*1.06 | O52: =M52*1.06 | P52: =N52*1.06 | Q52: =O52*1.06 | R52: =P52*1.06 | ... AC52: =AA52*1.06
B55: D&A / Revenue | C55: % | D55: =IF(D7=0,"",D52/D7) | E55: =IF(E7=0,"",E52/E7) | F55: =IF(F7=0,"",F52/F7) | G55: =IF(G7=0,"",G52/G7) | H55: =IF(H7=0,"",H52/H7) | I55: =IF(I7=0,"",I52/I7) | J55: =IF(J7=0,"",J52/J7) | K55: =IF(K7=0,"",K52/K7) | ... AC55: =IF(AC7=0,"",AC52/AC7)
B57: EBIT
A58: EBIT-EBIT | B58: EBIT (Operating Profit) | C58: AUDm | D58: =D49+D52 | E58: =E49+E52 | F58: =F49+F52 | G58: =G49+G52 | H58: =H49+H52 | I58: =I49+I52 | J58: =J49+J52 | K58: =K49+K52 | ... AC58: =AC49+AC52
B59: EBIT Growth (YoY) | C59: % YoY | F59: =IF(D58=0,"",F58/D58-1) | G59: =IF(E58=0,"",G58/E58-1) | H59: =IF(F58=0,"",H58/F58-1) | I59: =IF(G58=0,"",I58/G58-1) | J59: =IF(H58=0,"",J58/H58-1) | K59: =IF(I58=0,"",K58/I58-1) | L59: =IF(J58=0,"",L58/J58-1) | M59: =IF(K58=0,"",M58/K58-1) | ... AC59: =IF(AA58=0,"",AC58/AA58-1)
B60: EBIT Margin | C60: % | D60: =IF(D7=0,"",D58/D7) | E60: =IF(E7=0,"",E58/E7) | F60: =IF(F7=0,"",F58/F7) | G60: =IF(G7=0,"",G58/G7) | H60: =IF(H7=0,"",H58/H7) | I60: =IF(I7=0,"",I58/I7) | J60: =IF(J7=0,"",J58/J7) | K60: =IF(K7=0,"",K58/K7) | ... AC60: =IF(AC7=0,"",AC58/AC7)
B62: Interest
A63: Int-Finance Income | B63: Finance Income | C63: AUDm | D63: 2.2 | E63: 2.393 | F63: 2.327 | G63: 3.685 | H63: 11.445 | I63: 11.229 | J63: 11.432 | K63: =I63*1.0 | L63: =J63*1.0 | M63: =K63*1.0 | N63: =L63*1.0 | O63: =M63*1.0 | P63: =N63*1.0 | Q63: =O63*1.0 | R63: =P63*1.0 | ... AC63: =AA63*1.0
A64: Int-Finance Costs | B64: Finance Costs | C64: AUDm | D64: -4.1 | E64: -4.403 | F64: -6.41 | G64: -7.314 | H64: -8.752 | I64: -10.15 | J64: -12.014 | K64: =I64*1.05 | L64: =J64*1.05 | M64: =K64*1.05 | N64: =L64*1.05 | O64: =M64*1.05 | P64: =N64*1.05 | Q64: =O64*1.05 | R64: =P64*1.05 | ... AC64: =AA64*1.05
A66: Int-Net Finance Costs | B66: Net Finance Costs | C66: AUDm | D66: =D63+D64 | E66: =E63+E64 | F66: =F63+F64 | G66: =G63+G64 | H66: =H63+H64 | I66: =I63+I64 | J66: =J63+J64 | K66: =K63+K64 | ... AC66: =AC63+AC64
A71: PBT-PBT | B71: PBT | C71: AUDm | D71: =D58+D66 | E71: =E58+E66 | F71: =F58+F66 | G71: =G58+G66 | H71: =H58+H66 | I71: =I58+I66 | J71: =J58+J66 | K71: =K58+K66 | ... AC71: =AC58+AC66
A72: Tax-Tax Expense | B72: Tax Expense | C72: AUDm | D72: -1.2 | E72: -1.223 | F72: -2.881 | G72: 0.694 | H72: -7.89 | I72: -6.844 | J72: -8.595 | K72: =IF(K71>0,-K71*0.35,0) | L72: =IF(L71>0,-L71*0.35,0) | M72: =IF(M71>0,-M71*0.35,0) | N72: =IF(N71>0,-N71*0.35,0) | O72: =IF(O71>0,-O71*0.35,0) | P72: =IF(P71>0,-P71*0.35,0) | Q72: =IF(Q71>0,-Q71*0.35,0) | R72: =IF(R71>0,-R71*0.35,0) | ... AC72: =IF(AC71>0,-AC71*0.35,0)
B73: Tax Rate | C73: % | D73: =IF(D71=0,"",D72/D71) | E73: =IF(E71=0,"",E72/E71) | F73: =IF(F71=0,"",F72/F71) | G73: =IF(G71=0,"",G72/G71) | H73: =IF(H71=0,"",H72/H71) | I73: =IF(I71=0,"",I72/I71) | J73: =IF(J71=0,"",J72/J71) | K73: =IF(K71=0,"",K72/K71) | ... AC73: =IF(AC71=0,"",AC72/AC71)
A75: NPAT-Statutory NPAT | B75: NPAT | C75: AUDm | D75: =D71+D72 | E75: =E71+E72 | F75: =F71+F72 | G75: =G71+G72 | H75: =H71+H72 | I75: =I71+I72 | J75: =J71+J72 | K75: =K71+K72 | ... AC75: =AC71+AC72
B78: NPAT Growth (YoY) | C78: % YoY | F78: =IF(D75<=0,"",F75/D75-1) | G78: =IF(E75<=0,"",G75/E75-1) | H78: =IF(F75<=0,"",H75/F75-1) | I78: =IF(G75<=0,"",I75/G75-1) | J78: =IF(H75<=0,"",J75/H75-1) | K78: =IF(I75<=0,"",K75/I75-1) | L78: =IF(J75<=0,"",L75/J75-1) | M78: =IF(K75<=0,"",M75/K75-1) | ... AC78: =IF(AA75<=0,"",AC75/AA75-1)
B80: Operating Metrics
A81: KPI-Total Restaurants | B81: Total Restaurants | C81: # | E81: 194 | F81: 209 | G81: 220 | H81: 239 | I81: 256 | J81: 272 | K81: =K82+K83+K84 | L81: =L82+L83+L84 | M81: =M82+M83+M84 | N81: =N82+N83+N84 | O81: =O82+O83+O84 | P81: =P82+P83+P84 | Q81: =Q82+Q83+Q84 | R81: =R82+R83+R84 | ... AC81: =AC82+AC83+AC84
A82: KPI-Aus Corp Restaurants | B82: Aus Corporate Restaurants | C82: # | E82: 55 | F82: 62 | G82: 64 | H82: 74 | I82: 81 | J82: 87 | K82: =J82+5 | L82: =J82+5 | M82: =L82+5 | N82: =L82+5 | O82: =N82+5 | P82: =N82+5 | Q82: =P82+5 | R82: =P82+5 | S82: =R82+5 | T82: =R82+5 | U82: =T82+5 | V82: =T82+5 | W82: =V82+5 | X82: =V82+5 | Y82: =X82+5 | Z82: =X82+5 | AA82: =Z82+5 | AB82: =Z82+5 | AC82: =AB82+5
A83: KPI-Aus Fran Restaurants | B83: Aus Franchise Restaurants | C83: # | E83: 136 | F83: 143 | G83: 152 | H83: 161 | I83: 169 | J83: 177 | K83: =J83+11 | L83: =J83+11 | M83: =L83+11 | N83: =L83+11 | O83: =N83+11 | P83: =N83+11 | Q83: =P83+11 | R83: =P83+11 | S83: =R83+11 | T83: =R83+11 | U83: =T83+11 | V83: =T83+11 | W83: =V83+11 | X83: =V83+11 | Y83: =X83+11 | Z83: =X83+11 | AA83: =Z83+11 | AB83: =Z83+11 | AC83: =AB83+11
A84: KPI-US Restaurants | B84: US Restaurants | C84: # | E84: 3 | F84: 4 | G84: 4 | H84: 4 | I84: 6 | J84: 8 | K84: =K116 | L84: =L116 | M84: =M116 | N84: =N116 | O84: =O116 | P84: =P116 | Q84: =Q116 | R84: =R116 | ... AC84: =AC116
A85: KPI-Aus Network Sales | B85: Australia Network Sales | C85: AUDm | D85: 360 | E85: 393 | F85: 465 | G85: 483.7 | H85: 573 | I85: 595.4 | J85: 673.6 | K85: =K103 | L85: =L103 | M85: =M103 | N85: =N103 | O85: =O103 | P85: =P103 | Q85: =Q103 | R85: =R103 | ... AC85: =AC103
A86: KPI-US Network Sales | B86: US Network Sales | C86: AUDm | D86: 2.8 | E86: 3.2 | F86: 5.6 | G86: 5.2 | H86: 4.9 | I86: 7.3 | J86: 8.2 | K86: =K117 | L86: =L117 | M86: =M117 | N86: =N117 | O86: =O117 | P86: =P117 | Q86: =Q117 | R86: =R117 | ... AC86: =AC117
A87: KPI-Comp Sales Growth | B87: Comp Sales Growth | C87: % | F87: =IF(D85=0,"",(F85+F86)/(D85+D86)-1) | G87: =IF(E85=0,"",(G85+G86)/(E85+E86)-1) | H87: =IF(F85=0,"",(H85+H86)/(F85+F86)-1) | I87: =IF(G85=0,"",(I85+I86)/(G85+G86)-1) | J87: =IF(H85=0,"",(J85+J86)/(H85+H86)-1) | K87: =IF(I85=0,"",(K85+K86)/(I85+I86)-1) | L87: =IF(J85=0,"",(L85+L86)/(J85+J86)-1) | M87: =IF(K85=0,"",(M85+M86)/(K85+K86)-1) | ... AC87: =IF(AA85=0,"",(AC85+AC86)/(AA85+AA86)-1)
B92: Segment Forecast - Australia
B93: Drive Thru Restaurants (#) | C93: # | I93: 117 | J93: 126 | K93: =J93+5 | L93: =K93+5 | M93: =L93+5 | N93: =M93+5 | O93: =N93+5 | P93: =O93+5 | Q93: =P93+5 | R93: =Q93+5 | ... AC93: =AB93+5
B94: Strip Restaurants (#) | C94: # | I94: 68 | J94: 73 | K94: =J94+3 | L94: =K94+3 | M94: =L94+3 | N94: =M94+3 | O94: =N94+3 | P94: =O94+3 | Q94: =P94+3 | R94: =Q94+3 | ... AC94: =AB94+3
B95: Other Restaurants (#) | C95: # | I95: 39 | J95: 38 | K95: =J95 | L95: =K95 | M95: =L95 | N95: =M95 | O95: =N95 | P95: =O95 | Q95: =P95 | R95: =Q95 | ... AC95: =AB95
B96: Total Australia Restaurants (#) | C96: # | I96: =I93+I94+I95 | J96: =J93+J94+J95 | K96: =K93+K94+K95 | L96: =L93+L94+L95 | M96: =M93+M94+M95 | N96: =N93+N94+N95 | O96: =O93+O94+O95 | P96: =P93+P94+P95 | ... AC96: =AC93+AC94+AC95
B97: DT AUV ($m) | C97: AUDm | I97: 6.7 | J97: 6.9 | K97: =J97*1.0125 | L97: =K97*1.0125 | M97: =L97*1.0125 | N97: =M97*1.0125 | O97: =N97*1.0125 | P97: =O97*1.0125 | Q97: =P97*1.0125 | R97: =Q97*1.0125 | ... AC97: =AB97*1.0125
B98: Strip AUV ($m) | C98: AUDm | I98: 5 | J98: 5.2 | K98: =J98*1.0125 | L98: =K98*1.0125 | M98: =L98*1.0125 | N98: =M98*1.0125 | O98: =N98*1.0125 | P98: =O98*1.0125 | Q98: =P98*1.0125 | R98: =Q98*1.0125 | ... AC98: =AB98*1.0125
B99: Other AUV ($m) | C99: AUDm | I99: 4 | J99: 4 | K99: =J99*1.0125 | L99: =K99*1.0125 | M99: =L99*1.0125 | N99: =M99*1.0125 | O99: =N99*1.0125 | P99: =O99*1.0125 | Q99: =P99*1.0125 | R99: =Q99*1.0125 | ... AC99: =AB99*1.0125
B100: Network Sales - Drive Thru | C100: AUDm | I100: =I93*I97*0.5 | J100: =J93*J97*0.5 | K100: =K93*K97*0.5 | L100: =L93*L97*0.5 | M100: =M93*M97*0.5 | N100: =N93*N97*0.5 | O100: =O93*O97*0.5 | P100: =P93*P97*0.5 | ... AC100: =AC93*AC97*0.5
B101: Network Sales - Strip | C101: AUDm | I101: =I94*I98*0.5 | J101: =J94*J98*0.5 | K101: =K94*K98*0.5 | L101: =L94*L98*0.5 | M101: =M94*M98*0.5 | N101: =N94*N98*0.5 | O101: =O94*O98*0.5 | P101: =P94*P98*0.5 | ... AC101: =AC94*AC98*0.5
B102: Network Sales - Other | C102: AUDm | I102: =I95*I99*0.5 | J102: =J95*J99*0.5 | K102: =K95*K99*0.5 | L102: =L95*L99*0.5 | M102: =M95*M99*0.5 | N102: =N95*N99*0.5 | O102: =O95*O99*0.5 | P102: =P95*P99*0.5 | ... AC102: =AC95*AC99*0.5
B103: Total Australia Network Sales | C103: AUDm | D103: 360 | E103: 393 | F103: 465 | G103: 483.7 | H103: 573 | I103: =I100+I101+I102 | J103: =J100+J101+J102 | K103: =K100+K101+K102 | L103: =L100+L101+L102 | M103: =M100+M101+M102 | N103: =N100+N101+N102 | O103: =O100+O101+O102 | P103: =P100+P101+P102 | ... AC103: =AC100+AC101+AC102
B104: Corporate Restaurant Sales | C104: AUDm | D104: 101 | E104: 111 | F104: 136.2 | G104: 142.7 | H104: 176.1 | I104: 183.9 | J104: 215.1 | K104: =J104*1.08 | L104: =J104*1.15 | M104: =L104*1.08 | N104: =L104*1.15 | O104: =N104*1.08 | P104: =N104*1.15 | Q104: =P104*1.08 | R104: =P104*1.15 | S104: =R104*1.08 | T104: =R104*1.15 | U104: =T104*1.08 | V104: =T104*1.15 | W104: =V104*1.08 | X104: =V104*1.15 | Y104: =X104*1.08 | Z104: =X104*1.15 | AA104: =Z104*1.08 | AB104: =Z104*1.15 | AC104: =AB104*1.08
B105: Corporate Restaurant Margin (%) | C105: % | D105: 0.144 | E105: 0.144 | F105: 0.175 | G105: 0.173 | H105: 0.18 | I105: 0.178 | J105: 0.176 | K105: =MIN(0.20,J105+0.002) | L105: =MIN(0.20,K105+0.002) | M105: =MIN(0.20,L105+0.002) | N105: =MIN(0.20,M105+0.002) | O105: =MIN(0.20,N105+0.002) | P105: =MIN(0.20,O105+0.002) | Q105: =MIN(0.20,P105+0.002) | R105: =MIN(0.20,Q105+0.002) | ... AC105: =MIN(0.20,AB105+0.002)
B106: Corporate Restaurant Margin ($) | C106: AUDm | D106: =D104*D105 | E106: =E104*E105 | F106: =F104*F105 | G106: =G104*G105 | H106: =H104*H105 | I106: =I104*I105 | J106: =J104*J105 | K106: =K104*K105 | ... AC106: =AC104*AC105
B107: Franchise Network Sales | C107: AUDm | D107: =D103-D104 | E107: =E103-E104 | F107: =F103-F104 | G107: =G103-G104 | H107: =H103-H104 | I107: =I103-I104 | J107: =J103-J104 | K107: =K103-K104 | ... AC107: =AC103-AC104
B108: Implied Franchise Royalty Rate (%) | C108: % | D108: 0.087 | E108: 0.087 | F108: 0.087 | G108: 0.093 | H108: 0.097 | I108: 0.097 | J108: 0.097 | K108: =MIN(0.10,J108+0.001) | L108: =MIN(0.10,K108+0.001) | M108: =MIN(0.10,L108+0.001) | N108: =MIN(0.10,M108+0.001) | O108: =MIN(0.10,N108+0.001) | P108: =MIN(0.10,O108+0.001) | Q108: =MIN(0.10,P108+0.001) | R108: =MIN(0.10,Q108+0.001) | ... AC108: =MIN(0.10,AB108+0.001)
B109: Franchise & Other Revenue | C109: AUDm | D109: =D107*D108 | E109: =E107*E108 | F109: =F107*F108 | G109: =G107*G108 | H109: 38.2 | I109: 40.5 | J109: 42.8 | K109: =K107*K108 | L109: =L107*L108 | M109: =M107*M108 | N109: =N107*N108 | O109: =O107*O108 | P109: =P107*P108 | Q109: =Q107*Q108 | R109: =R107*R108 | ... AC109: =AC107*AC108
B110: G&A Costs | C110: AUDm | D110: -22 | E110: -24.7 | F110: -30 | G110: -33.7 | H110: -38.1 | I110: -38.9 | J110: -39.4 | K110: =J110*1.04 | L110: =J110*1.04 | M110: =L110*1.04 | N110: =L110*1.04 | O110: =N110*1.04 | P110: =N110*1.04 | Q110: =P110*1.04 | R110: =P110*1.04 | S110: =R110*1.04 | T110: =R110*1.04 | U110: =T110*1.04 | V110: =T110*1.04 | W110: =V110*1.04 | X110: =V110*1.04 | Y110: =X110*1.04 | Z110: =X110*1.04 | AA110: =Z110*1.04 | AB110: =Z110*1.04 | AC110: =AB110*1.04
B111: G&A as % of Network Sales | C111: % | D111: =IF(D103=0,"",ABS(D110)/D103) | E111: =IF(E103=0,"",ABS(E110)/E103) | F111: =IF(F103=0,"",ABS(F110)/F103) | G111: =IF(G103=0,"",ABS(G110)/G103) | H111: =IF(H103=0,"",ABS(H110)/H103) | I111: =IF(I103=0,"",ABS(I110)/I103) | J111: =IF(J103=0,"",ABS(J110)/J103) | K111: =IF(K103=0,"",ABS(K110)/K103) | ... AC111: =IF(AC103=0,"",ABS(AC110)/AC103)
B112: Australia Segment EBITDA | C112: AUDm | D112: =D106+D109+D110 | E112: =E106+E109+E110 | F112: =F106+F109+F110 | G112: =G106+G109+G110 | H112: =H106+H109+H110 | I112: =I106+I109+I110 | J112: =J106+J109+J110 | K112: =K106+K109+K110 | ... AC112: =AC106+AC109+AC110
B113: Seg EBITDA as % of NS | C113: % | D113: =IF(D103=0,"",D112/D103) | E113: =IF(E103=0,"",E112/E103) | F113: =IF(F103=0,"",F112/F103) | G113: =IF(G103=0,"",G112/G103) | H113: =IF(H103=0,"",H112/H103) | I113: =IF(I103=0,"",I112/I103) | J113: =IF(J103=0,"",J112/J103) | K113: =IF(K103=0,"",K112/K103) | ... AC113: =IF(AC103=0,"",AC112/AC103)
B115: Segment Forecast - US | C115: NZD
B116: US Restaurants (#) | C116: # | E116: 3 | F116: 4 | G116: 4 | H116: 4 | I116: 6 | J116: 8 | K116: =J116+1 | L116: =K116+1 | M116: =L116+1 | N116: =M116+1 | O116: =N116+1 | P116: =O116+1 | Q116: =P116+1 | R116: =Q116+1 | ... AC116: =AB116+1
B117: US Network Sales | C117: AUDm | D117: 2.8 | E117: 3.2 | F117: 5.6 | G117: 5.2 | H117: 4.9 | I117: 7.3 | J117: 8.2 | K117: =J117*1.15 | L117: =J117*1.15 | M117: =L117*1.15 | N117: =L117*1.15 | O117: =N117*1.15 | P117: =N117*1.15 | Q117: =P117*1.15 | R117: =P117*1.15 | S117: =R117*1.15 | T117: =R117*1.15 | U117: =T117*1.15 | V117: =T117*1.15 | W117: =V117*1.15 | X117: =V117*1.15 | Y117: =X117*1.15 | Z117: =X117*1.15 | AA117: =Z117*1.15 | AB117: =Z117*1.15 | AC117: =AB117*1.15
B118: Corporate Restaurant Sales | C118: AUDm | F118: 0 | G118: 10.8 | H118: 3.2 | I118: 5.7 | J118: 6.5 | K118: =K117 | L118: =L117 | M118: =M117 | N118: =N117 | O118: =O117 | P118: =P117 | Q118: =Q117 | R118: =R117 | ... AC118: =AC117
B119: Corporate Restaurant Margin (%) | C119: % | H119: -0.406 | I119: -0.667 | J119: -0.692 | K119: =MAX(-0.30,J119+0.03) | L119: =MAX(-0.30,K119+0.03) | M119: =MAX(-0.30,L119+0.03) | N119: =MAX(-0.30,M119+0.03) | O119: =MAX(-0.30,N119+0.03) | P119: =MAX(-0.30,O119+0.03) | Q119: =MAX(-0.30,P119+0.03) | R119: =MAX(-0.30,Q119+0.03) | ... AC119: =MAX(-0.30,AB119+0.03)
B120: Corporate Restaurant Margin ($) | C120: AUDm | G120: -1 | H120: -1.3 | I120: -3.8 | J120: -4.5 | K120: =K118*K119 | L120: =L118*L119 | M120: =M118*M119 | N120: =N118*N119 | O120: =O118*O119 | P120: =P118*P119 | Q120: =Q118*Q119 | R120: =R118*R119 | ... AC120: =AC118*AC119
B121: Franchise & Other Revenue | C121: AUDm | D121: 0 | E121: 0 | F121: 0 | G121: 0 | H121: 0.1 | I121: 0.2 | J121: 0.1 | K121: =J121*1.2 | L121: =K121*1.2 | M121: =L121*1.2 | N121: =M121*1.2 | O121: =N121*1.2 | P121: =O121*1.2 | Q121: =P121*1.2 | R121: =Q121*1.2 | ... AC121: =AB121*1.2
B122: G&A Costs | C122: AUDm | G122: -5.5 | H122: -3.8 | I122: -4.6 | J122: -4 | K122: =J122*1.05 | L122: =J122*1.05 | M122: =L122*1.05 | N122: =L122*1.05 | O122: =N122*1.05 | P122: =N122*1.05 | Q122: =P122*1.05 | R122: =P122*1.05 | S122: =R122*1.05 | T122: =R122*1.05 | U122: =T122*1.05 | V122: =T122*1.05 | W122: =V122*1.05 | X122: =V122*1.05 | Y122: =X122*1.05 | Z122: =X122*1.05 | AA122: =Z122*1.05 | AB122: =Z122*1.05 | AC122: =AB122*1.05
B123: US Segment EBITDA | C123: AUDm | D123: -2 | E123: -2.3 | F123: -3.1 | G123: =G120+G121+G122 | H123: =H120+H121+H122 | I123: =I120+I121+I122 | J123: =J120+J121+J122 | K123: =K120+K121+K122 | L123: =L120+L121+L122 | M123: =M120+M121+M122 | N123: =N120+N121+N122 | ... AC123: =AC120+AC121+AC122
